Workbook

Sheet Formule TDB
A1: Ligne | B1: Intitulé | C1: Réalisé N | E1: Code
A2: 1 | B2: CAM040-Frais d'activation & Sim swap | C2: -701120 -701130 | D2: =VLOOKUP(B2,'Analyse Réel 01-2025'!F:H,1,FALSE) -> CAM040-Frais d'activation & Sim swap | E2: =VLOOKUP(B2,'Analyse Réel 01-2025'!F:H,2,FALSE) -> CA12
A3: 2 | B3: CAM045-Sortant voix on net | C3: -NM(706120,*,A61,*,*,*,*,*,*,*) -NM(706920,*,A58,*,*,*,*,*,*,*) | D3: =VLOOKUP(B3,'Analyse Réel 01-2025'!F:H,1,FALSE) -> CAM045-Sortant voix on net | E3: =VLOOKUP(B3,'Analyse Réel 01-2025'!F:H,2,FALSE) -> CA13
A4: 3 | B4: CAM050-Sortant voix MTN | C4: -NM(706121,*,A48,*,*,*,*,*,*,*) | D4: =VLOOKUP(B4,'Analyse Réel 01-2025'!F:H,1,FALSE) -> CAM050-Sortant voix MTN | E4: =VLOOKUP(B4,'Analyse Réel 01-2025'!F:H,2,FALSE) -> CA14
A5: 4 | B5: CAM055-Sortant voix GLO | C5: -NM(706121,*,*A49,*,*,*,*,*,*,*) | D5: =VLOOKUP(B5,'Analyse Réel 01-2025'!F:H,1,FALSE) -> CAM055-Sortant voix GLO | E5: =VLOOKUP(B5,'Analyse Réel 01-2025'!F:H,2,FALSE) -> CA15
A6: 5 | B6: CAM060-Sortant voix BBCOM | C6: -NM(706121,*,*A50,*,*,*,*,*,*,*) | D6: =VLOOKUP(B6,'Analyse Réel 01-2025'!F:H,1,FALSE) -> CAM060-Sortant voix BBCOM | E6: =VLOOKUP(B6,'Analyse Réel 01-2025'!F:H,2,FALSE) -> CA16
A7: 6 | B7: CAM065-Sortant voix LIBERCOM | C7: -NM(706121,*,*A51,*,*,*,*,*,*,*) | D7: =VLOOKUP(B7,'Analyse Réel 01-2025'!F:H,1,FALSE) -> CAM065-Sortant voix LIBERCOM | E7: =VLOOKUP(B7,'Analyse Réel 01-2025'!F:H,2,FALSE) -> CA17
A8: 7 | B8: CAM070-Sortant voix BTSA | C8: -NM(706123,*,A52,*,*,*,*,*,*,*) | D8: =VLOOKUP(B8,'Analyse Réel 01-2025'!F:H,1,FALSE) -> CAM070-Sortant voix BTSA | E8: =VLOOKUP(B8,'Analyse Réel 01-2025'!F:H,2,FALSE) -> CA18
A9: 8 | B9: CAM075-Sortant voix INTERNATIONAL | C9: -NM(706124,*,A53,*,*,*,*,*,*,*) | D9: =VLOOKUP(B9,'Analyse Réel 01-2025'!F:H,1,FALSE) -> CAM075-Sortant voix INTERNATIONAL | E9: =VLOOKUP(B9,'Analyse Réel 01-2025'!F:H,2,FALSE) -> CA19
A10: 9 | B10: CAM080-Sortant voix roaming | C10: -NM(706140,*,A54,*,*,*,*,*,*,*) | D10: =VLOOKUP(B10,'Analyse Réel 01-2025'!F:H,1,FALSE) -> CAM080-Sortant voix roaming | E10: =VLOOKUP(B10,'Analyse Réel 01-2025'!F:H,2,FALSE) -> CA20
A11: 10 | B11: CAM085-Total VOIX Sortant | C11: $CAMOBILE.#(L2:9) | D11: =VLOOKUP(B11,'Analyse Réel 01-2025'!F:H,1,FALSE) -> CAM085-Total VOIX Sortant | E11: =VLOOKUP(B11,'Analyse Réel 01-2025'!F:H,2,FALSE) -> CA21
A12: 11 | B12: CAM090-Sortant sms on net | C12: -NM(706117,*,T21,*,*,*,*,*,*,*) -NM(706920,*,A59,*,*,*,*,*,*,*) | D12: =VLOOKUP(B12,'Analyse Réel 01-2025'!F:H,1,FALSE) -> CAM090-Sortant sms on net | E12: =VLOOKUP(B12,'Analyse Réel 01-2025'!F:H,2,FALSE) -> CA23
A13: 12 | B13: CAM095-Sortant sms MTN | C13: -NM(706117,*,A48,*,*,*,*,*,*,*) | D13: =VLOOKUP(B13,'Analyse Réel 01-2025'!F:H,1,FALSE) -> CAM095-Sortant sms MTN | E13: =VLOOKUP(B13,'Analyse Réel 01-2025'!F:H,2,FALSE) -> CA24
... A22: 21 | B22: CAM140-Story Box | C22: -0*NM(706151,*,*,*,*,*,*,*,*) | D22: =VLOOKUP(B22,'Analyse Réel 01-2025'!F:H,1,FALSE) -> CAM140-Story Box | E22: =VLOOKUP(B22,'Analyse Réel 01-2025'!F:H,2,FALSE) -> CA35
A23: 22 | B23: CAM145-Phonebook STK | C23: =-"0*NM(706151)" -> #VALUE! | D23: =VLOOKUP(B23,'Analyse Réel 01-2025'!F:H,1,FALSE) -> CAM145-Phonebook STK | E23: =VLOOKUP(B23,'Analyse Réel 01-2025'!F:H,2,FALSE) -> CA36
A24: 23 | B24: CAM150-Gaming | C24: -0*NM(706151,*,*,*,*,*,*,*,*) | D24: =VLOOKUP(B24,'Analyse Réel 01-2025'!F:H,1,FALSE) -> CAM150-Gaming | E24: =VLOOKUP(B24,'Analyse Réel 01-2025'!F:H,2,FALSE) -> CA37
A25: 24 | B25: CAM155-Autres (VOICEALERT,MOOVKDO...) | C25: -0*NM(706151,*,*,*,*,*,*,*,*) | D25: =VLOOKUP(B25,'Analyse Réel 01-2025'!F:H,1,FALSE) -> CAM155-Autres (VOICEALERT,MOOVKDO...) | E25: =VLOOKUP(B25,'Analyse Réel 01-2025'!F:H,2,FALSE) -> CA38
A26: 25 | B26: CAM160-Videos | C26: -0*NM(706151,*,*,*,*,*,*,*,*) | D26: =VLOOKUP(B26,'Analyse Réel 01-2025'!F:H,1,FALSE) -> CAM160-Videos | E26: =VLOOKUP(B26,'Analyse Réel 01-2025'!F:H,2,FALSE) -> CA39
A27: 26 | B27: CAM165-Total Data | C27: $CAMOBILE.#(L19:25) | D27: =VLOOKUP(B27,'Analyse Réel 01-2025'!F:H,1,FALSE) -> CAM165-Total Data | E27: =VLOOKUP(B27,'Analyse Réel 01-2025'!F:H,2,FALSE) -> CA40
A28: 27 | B28: CAM170-Dont CA SVA ( Sce à Val Ajoutéé) | C28: 0 | D28: =VLOOKUP(B28,'Analyse Réel 01-2025'!F:H,1,FALSE) -> CAM170-Dont CA SVA ( Sce à Val Ajoutéé) | E28: =VLOOKUP(B28,'Analyse Réel 01-2025'!F:H,2,FALSE) -> CA44
A29: 28 | B29: CAM185-dont CA Internet 3G | C29: L18 | D29: =VLOOKUP(B29,'Analyse Réel 01-2025'!F:H,1,FALSE) -> CAM185-dont CA Internet 3G | E29: =VLOOKUP(B29,'Analyse Réel 01-2025'!F:H,2,FALSE) -> CA45
A30: 29 | B30: CAM035-Consumer Prepaid | C30: R(L1+L10+L17+L26) | D30: =VLOOKUP(B30,'Analyse Réel 01-2025'!F:H,1,FALSE) -> CAM035-Consumer Prepaid | E30: =VLOOKUP(B30,'Analyse Réel 01-2025'!F:H,2,FALSE) -> CA11
A31: 30 | B31: CAM036-Prépayé (Y compris commissions) | C31: L29 | D31: =VLOOKUP(B31,'Analyse Réel 01-2025'!F:H,1,FALSE) -> CAM036-Prépayé (Y compris commissions) | E31: =VLOOKUP(B31,'Analyse Réel 01-2025'!F:H,2,FALSE) -> 0
A32: 31 | B32: CAM200-Red Consumer Postpaid | C32: -706115 NM(706115,*,A27,*,*,*,*,*,*,*) NM(706115,*,A29,*,*,*,*,*,*,*) NM(706115,*,W99,*,*,*,*,*,*,*) NM(706115,*,V99,*,*,*,*,*,*,*) NM(706115,*,U99,*,*,*,*,*,*,*) NM(706115,*,T15,*,*,*,*,*,*,*) NM(706115,*,S99,*,*,*,*,*,*,*) | D32: =VLOOKUP(B32,'Analyse Réel 01-2025'!F:H,1,FALSE) -> CAM200-Red Consumer Postpaid | E32: =VLOOKUP(B32,'Analyse Réel 01-2025'!F:H,2,FALSE) -> CA48
A33: 32 | B33: CAM205-Red Business Postpaid | C33: -NM(706115,*,T15,*,*,*,*,*,*) | D33: =VLOOKUP(B33,'Analyse Réel 01-2025'!F:H,1,FALSE) -> CAM205-Red Business Postpaid | E33: =VLOOKUP(B33,'Analyse Réel 01-2025'!F:H,2,FALSE) -> CA49
A34: 33 | B34: CAM210-Red Business Prepaid | C34: -NM(706115,*,U99,*,*,*,*,*,*) | D34: =VLOOKUP(B34,'Analyse Réel 01-2025'!F:H,1,FALSE) -> CAM210-Red Business Prepaid | E34: =VLOOKUP(B34,'Analyse Réel 01-2025'!F:H,2,FALSE) -> CA50
A35: 34 | B35: CAM195-Redevance d'abonnement | C35: R(L31+L32+L33) | D35: =VLOOKUP(B35,'Analyse Réel 01-2025'!F:H,1,FALSE) -> CAM195-Redevance d'abonnement | E35: =VLOOKUP(B35,'Analyse Réel 01-2025'!F:H,2,FALSE) -> CA47
A36: 35 | B36: CAM225-Sortant voix on net | C36: -NM(706125,*,A61,*,*,*,*,*,*,*) -NM(706900,*,A58,*,*,*,*,*,*,*) -NM(706900,*,A59,*,*,*,*,*,*,*) | D36: =VLOOKUP(B36,'Analyse Réel 01-2025'!F:H,1,FALSE) -> CAM225-Sortant voix on net | E36: =VLOOKUP(B36,'Analyse Réel 01-2025'!F:H,2,FALSE) -> CA53
A37: 36 | B37: CAM230-Sortant voix MTN | C37: -NM(706126,*,A48,*,*,*,*,*,*) | D37: =VLOOKUP(B37,'Analyse Réel 01-2025'!F:H,1,FALSE) -> CAM230-Sortant voix MTN | E37: =VLOOKUP(B37,'Analyse Réel 01-2025'!F:H,2,FALSE) -> CA54
A38: 37 | B38: CAM235-Sortant voix GLO | C38: -NM(706126,*,A49,*,*,*,*,*,*) | D38: =VLOOKUP(B38,'Analyse Réel 01-2025'!F:H,1,FALSE) -> CAM235-Sortant voix GLO | E38: =VLOOKUP(B38,'Analyse Réel 01-2025'!F:H,2,FALSE) -> CA55
A39: 38 | B39: CAM240-Sortant voix BBCOM | C39: -NM(706126,*,A50,*,*,*,*,*,*) | D39: =VLOOKUP(B39,'Analyse Réel 01-2025'!F:H,1,FALSE) -> CAM240-Sortant voix BBCOM | E39: =VLOOKUP(B39,'Analyse Réel 01-2025'!F:H,2,FALSE) -> CA56
A40: 39 | B40: CAM245-Sortant voix LIBERCOM | C40: -NM(706126,*,A51,*,*,*,*,*,*) | D40: =VLOOKUP(B40,'Analyse Réel 01-2025'!F:H,1,FALSE) -> CAM245-Sortant voix LIBERCOM | E40: =VLOOKUP(B40,'Analyse Réel 01-2025'!F:H,2,FALSE) -> CA57
... A54: 53 | B54: CAM315-Banking | C54: -NM(706115,*,B99,*,*,*,*,*,*) -NM(706115,*,I99,*,*,*,*,*,*,*) | D54: =VLOOKUP(B54,'Analyse Réel 01-2025'!F:H,1,FALSE) -> CAM315-Banking | E54: =VLOOKUP(B54,'Analyse Réel 01-2025'!F:H,2,FALSE) -> CA73
A55: 54 | B55: CAM320-Autres | C55: 0 | D55: =VLOOKUP(B55,'Analyse Réel 01-2025'!F:H,1,FALSE) -> CAM320-Autres | E55: =VLOOKUP(B55,'Analyse Réel 01-2025'!F:H,2,FALSE) -> CA74
A56: 55 | B56: CAM325-Total Data | C56: $CAMOBILE.#(L52:54) | D56: =VLOOKUP(B56,'Analyse Réel 01-2025'!F:H,1,FALSE) -> CAM325-Total Data | E56: =VLOOKUP(B56,'Analyse Réel 01-2025'!F:H,2,FALSE) -> CA75
A57: 56 | B57: CAM326-Consumer Postpaid | C57: R(L43+L50+L55) | D57: =VLOOKUP(B57,'Analyse Réel 01-2025'!F:H,1,FALSE) -> CAM326-Consumer Postpaid | E57: =VLOOKUP(B57,'Analyse Réel 01-2025'!F:H,2,FALSE) -> CA52
A58: 57 | B58: CAM335-Sortant voix on net | C58: -NM(706125,*,A99,*,*,*,*,*,*) -NM(706900,*,A99,*,*,*,*,*,*) | D58: =VLOOKUP(B58,'Analyse Réel 01-2025'!F:H,1,FALSE) -> CAM335-Sortant voix on net | E58: =VLOOKUP(B58,'Analyse Réel 01-2025'!F:H,2,FALSE) -> CA78
A59: 58 | B59: CAM340-Sortant voix MTN | C59: -NM(706126,*,A43,*,*,*,*,*,*) | D59: =VLOOKUP(B59,'Analyse Réel 01-2025'!F:H,1,FALSE) -> CAM340-Sortant voix MTN | E59: =VLOOKUP(B59,'Analyse Réel 01-2025'!F:H,2,FALSE) -> CA79
A60: 59 | B60: CAM345-Sortant voix GLO | D60: =VLOOKUP(B60,'Analyse Réel 01-2025'!F:H,1,FALSE) -> CAM345-Sortant voix GLO | E60: =VLOOKUP(B60,'Analyse Réel 01-2025'!F:H,2,FALSE) -> CA80
A61: 60 | B61: CAM355-Sortant voix BBCOM | D61: =VLOOKUP(B61,'Analyse Réel 01-2025'!F:H,1,FALSE) -> CAM355-Sortant voix BBCOM | E61: =VLOOKUP(B61,'Analyse Réel 01-2025'!F:H,2,FALSE) -> CA81
A62: 61 | B62: CAM360-Sortant voix LIBERCOM | D62: =VLOOKUP(B62,'Analyse Réel 01-2025'!F:H,1,FALSE) -> CAM360-Sortant voix LIBERCOM | E62: =VLOOKUP(B62,'Analyse Réel 01-2025'!F:H,2,FALSE) -> CA82
A63: 62 | B63: CAM365-Sortant voix BTSA | C63: -NM(706128,*,A99,*,*,*,*,*,*) | D63: =VLOOKUP(B63,'Analyse Réel 01-2025'!F:H,1,FALSE) -> CAM365-Sortant voix BTSA | E63: =VLOOKUP(B63,'Analyse Réel 01-2025'!F:H,2,FALSE) -> CA83
A64: 63 | B64: CAM370-Sortant voix INTERNATIONAL | C64: -NM(706129,*,A99,*,*,*,*,*,*,*) | D64: =VLOOKUP(B64,'Analyse Réel 01-2025'!F:H,1,FALSE) -> CAM370-Sortant voix INTERNATIONAL | E64: =VLOOKUP(B64,'Analyse Réel 01-2025'!F:H,2,FALSE) -> CA84
A65: 64 | B65: CAM375-Sortant voix roaming | C65: -NM(706141,*,A99,*,*,*,*,*,*) | D65: =VLOOKUP(B65,'Analyse Réel 01-2025'!F:H,1,FALSE) -> CAM375-Sortant voix roaming | E65: =VLOOKUP(B65,'Analyse Réel 01-2025'!F:H,2,FALSE) -> CA85
A66: 65 | B66: CAM380-Total VOIX Sortant | C66: $CAMOBILE.#(L57:64) | D66: =VLOOKUP(B66,'Analyse Réel 01-2025'!F:H,1,FALSE) -> CAM380-Total VOIX Sortant | E66: =VLOOKUP(B66,'Analyse Réel 01-2025'!F:H,2,FALSE) -> CA86
A67: 66 | B67: CAM385-Sortant sms on net | C67: -NM(706118,*,T20,*,*,*,*,*,*) -706152 | D67: =VLOOKUP(B67,'Analyse Réel 01-2025'!F:H,1,FALSE) -> CAM385-Sortant sms on net | E67: =VLOOKUP(B67,'Analyse Réel 01-2025'!F:H,2,FALSE) -> CA88
A68: 67 | B68: CAM390-Sortant sms MTN | C68: -0*NM(706118,*,*,*,*,*,*,*,*) | D68: =VLOOKUP(B68,'Analyse Réel 01-2025'!F:H,1,FALSE) -> CAM390-Sortant sms MTN | E68: =VLOOKUP(B68,'Analyse Réel 01-2025'!F:H,2,FALSE) -> CA89
A69: 68 | B69: CAM395-Sortant sms GLO | C69: -0*NM(706118,*,*,*,*,*,*,*,*) | D69: =VLOOKUP(B69,'Analyse Réel 01-2025'!F:H,1,FALSE) -> CAM395-Sortant sms GLO | E69: =VLOOKUP(B69,'Analyse Réel 01-2025'!F:H,2,FALSE) -> CA90
A70: 69 | B70: CAM400-Sortant sms BBCOM | C70: -0*NM(706118,*,*,*,*,*,*,*,*) | D70: =VLOOKUP(B70,'Analyse Réel 01-2025'!F:H,1,FALSE) -> CAM400-Sortant sms BBCOM | E70: =VLOOKUP(B70,'Analyse Réel 01-2025'!F:H,2,FALSE) -> CA91
A71: 70 | B71: CAM405-Sortant sms LIBERCOM | C71: -0*NM(706118,*,*,*,*,*,*,*,*) | D71: =VLOOKUP(B71,'Analyse Réel 01-2025'!F:H,1,FALSE) -> CAM405-Sortant sms LIBERCOM | E71: =VLOOKUP(B71,'Analyse Réel 01-2025'!F:H,2,FALSE) -> CA92
A72: 71 | B72: CAM410-Sortant sms INTERNATIONAL | C72: -0*NM(706118,*,*,*,*,*,*,*,*) | D72: =VLOOKUP(B72,'Analyse Réel 01-2025'!F:H,1,FALSE) -> CAM410-Sortant sms INTERNATIONAL | E72: =VLOOKUP(B72,'Analyse Réel 01-2025'!F:H,2,FALSE) -> CA93
A73: 72 | B73: CAM415-Total SMS Sortant | C73: $CAMOBILE.#(L66:71) | D73: =VLOOKUP(B73,'Analyse Réel 01-2025'!F:H,1,FALSE) -> CAM415-Total SMS Sortant | E73: =VLOOKUP(B73,'Analyse Réel 01-2025'!F:H,2,FALSE) -> CA94
A74: 73 | B74: CAM420-Revenu Internet 3G | C74: =-706154 -L3 -> -706154 | D74: =VLOOKUP(B74,'Analyse Réel 01-2025'!F:H,1,FALSE) -> CAM420-Revenu Internet 3G | E74: =VLOOKUP(B74,'Analyse Réel 01-2025'!F:H,2,FALSE) -> CA96
A75: 74 | B75: CAM425-Transport and Automotive | C75: 0 | D75: =VLOOKUP(B75,'Analyse Réel 01-2025'!F:H,1,FALSE) -> CAM425-Transport and Automotive | E75: =VLOOKUP(B75,'Analyse Réel 01-2025'!F:H,2,FALSE) -> CA97
A76: 75 | B76: CAM430-Banking | C76: -NM(706115,*,A27,*,*,*,*,*,*) -NM(706115,*,A29,*,*,*,*,*,*) -NM(706115,*,A28,*,*,*,*,*,*,*) | D76: =VLOOKUP(B76,'Analyse Réel 01-2025'!F:H,1,FALSE) -> CAM430-Banking | E76: =VLOOKUP(B76,'Analyse Réel 01-2025'!F:H,2,FALSE) -> CA98
A77: 76 | B77: CAM435-Autres | C77: 0 | D77: =VLOOKUP(B77,'Analyse Réel 01-2025'!F:H,1,FALSE) -> CAM435-Autres | E77: =VLOOKUP(B77,'Analyse Réel 01-2025'!F:H,2,FALSE) -> CA99
A78: 77 | B78: CAM440-Total Data | C78: $CAMOBILE.#(L74:76) | D78: =VLOOKUP(B78,'Analyse Réel 01-2025'!F:H,1,FALSE) -> CAM440-Total Data | E78: =VLOOKUP(B78,'Analyse Réel 01-2025'!F:H,2,FALSE) -> CA100
A79: 78 | B79: CAM330-Business Postpaid | C79: R(L65+L72+L77) | D79: =VLOOKUP(B79,'Analyse Réel 01-2025'!F:H,1,FALSE) -> CAM330-Business Postpaid | E79: =VLOOKUP(B79,'Analyse Réel 01-2025'!F:H,2,FALSE) -> CA77
A80: 79 | B80: CAM450-Sortant voix on net | C80: -NM(706120,*,A99,*,*,*,*,*,*,*) -NM(706920,*,A17,*,*,*,*,*,*) | D80: =VLOOKUP(B80,'Analyse Réel 01-2025'!F:H,1,FALSE) -> CAM450-Sortant voix on net | E80: =VLOOKUP(B80,'Analyse Réel 01-2025'!F:H,2,FALSE) -> CA103
A81: 80 | B81: CAM455-Sortant voix MTN | C81: -NM(706121,*,A43,*,*,*,*,*,*) | D81: =VLOOKUP(B81,'Analyse Réel 01-2025'!F:H,1,FALSE) -> CAM455-Sortant voix MTN | E81: =VLOOKUP(B81,'Analyse Réel 01-2025'!F:H,2,FALSE) -> CA104
A82: 81 | B82: CAM460-Sortant voix GLO | D82: =VLOOKUP(B82,'Analyse Réel 01-2025'!F:H,1,FALSE) -> CAM460-Sortant voix GLO | E82: =VLOOKUP(B82,'Analyse Réel 01-2025'!F:H,2,FALSE) -> CA105
A83: 82 | B83: CAM465-Sortant voix BBCOM | D83: =VLOOKUP(B83,'Analyse Réel 01-2025'!F:H,1,FALSE) -> CAM465-Sortant voix BBCOM | E83: =VLOOKUP(B83,'Analyse Réel 01-2025'!F:H,2,FALSE) -> CA106
A84: 83 | B84: CAM470-Sortant voix LIBERCOM | D84: =VLOOKUP(B84,'Analyse Réel 01-2025'!F:H,1,FALSE) -> CAM470-Sortant voix LIBERCOM | E84: =VLOOKUP(B84,'Analyse Réel 01-2025'!F:H,2,FALSE) -> CA107
A85: 84 | B85: CAM475-Sortant voix BTSA | C85: -NM(706123,*,A99,*,*,*,*,*,*) | D85: =VLOOKUP(B85,'Analyse Réel 01-2025'!F:H,1,FALSE) -> CAM475-Sortant voix BTSA | E85: =VLOOKUP(B85,'Analyse Réel 01-2025'!F:H,2,FALSE) -> CA108
A86: 85 | B86: CAM480-Sortant voix INTERNATIONAL | C86: -NM(706124,*,A99,*,*,*,*,*,*) | D86: =VLOOKUP(B86,'Analyse Réel 01-2025'!F:H,1,FALSE) -> CAM480-Sortant voix INTERNATIONAL | E86: =VLOOKUP(B86,'Analyse Réel 01-2025'!F:H,2,FALSE) -> CA109
A87: 86 | B87: CAM485-Sortant voix roaming | C87: -NM(706140,*,A99,*,*,*,*,*,*) | D87: =VLOOKUP(B87,'Analyse Réel 01-2025'!F:H,1,FALSE) -> CAM485-Sortant voix roaming | E87: =VLOOKUP(B87,'Analyse Réel 01-2025'!F:H,2,FALSE) -> CA110
A88: 87 | B88: CAM490-Total VOIX Sortant | C88: $CAMOBILE.#(L79:86) | D88: =VLOOKUP(B88,'Analyse Réel 01-2025'!F:H,1,FALSE) -> CAM490-Total VOIX Sortant | E88: =VLOOKUP(B88,'Analyse Réel 01-2025'!F:H,2,FALSE) -> CA111
A89: 88 | B89: CAM495-Sortant sms on net | C89: -NM(706117,*,T16,*,*,*,*,*,*,*) -NM(706920,*,A22,*,*,*,*,*,*,*) | D89: =VLOOKUP(B89,'Analyse Réel 01-2025'!F:H,1,FALSE) -> CAM495-Sortant sms on net | E89: =VLOOKUP(B89,'Analyse Réel 01-2025'!F:H,2,FALSE) -> CA113
A90: 89 | B90: CAM500-Sortant sms MTN | C90: -NM(706117,*,A43,*,*,*,*,*,*) | D90: =VLOOKUP(B90,'Analyse Réel 01-2025'!F:H,1,FALSE) -> CAM500-Sortant sms MTN | E90: =VLOOKUP(B90,'Analyse Réel 01-2025'!F:H,2,FALSE) -> CA114
A91: 90 | B91: CAM505-Sortant sms GLO | C91: -NM(706117,*,A45,*,*,*,*,*,*) | D91: =VLOOKUP(B91,'Analyse Réel 01-2025'!F:H,1,FALSE) -> CAM505-Sortant sms GLO | E91: =VLOOKUP(B91,'Analyse Réel 01-2025'!F:H,2,FALSE) -> CA115
A92: 91 | B92: CAM510-Sortant sms BBCOM | C92: -NM(706117,*,A44,*,*,*,*,*,*) | D92: =VLOOKUP(B92,'Analyse Réel 01-2025'!F:H,1,FALSE) -> CAM510-Sortant sms BBCOM | E92: =VLOOKUP(B92,'Analyse Réel 01-2025'!F:H,2,FALSE) -> CA116
A93: 92 | B93: CAM515-Sortant sms LIBERCOM | C93: -NM(706117,*,A42,*,*,*,*,*,*) | D93: =VLOOKUP(B93,'Analyse Réel 01-2025'!F:H,1,FALSE) -> CAM515-Sortant sms LIBERCOM | E93: =VLOOKUP(B93,'Analyse Réel 01-2025'!F:H,2,FALSE) -> CA117
A94: 93 | B94: CAM520-Sortant sms INTERNATIONAL | C94: -NM(706117,*,T18,*,*,*,*,*,*) | D94: =VLOOKUP(B94,'Analyse Réel 01-2025'!F:H,1,FALSE) -> CAM520-Sortant sms INTERNATIONAL | E94: =VLOOKUP(B94,'Analyse Réel 01-2025'!F:H,2,FALSE) -> CA118
A95: 94 | B95: CAM525-Total SMS Sortant | C95: $CAMOBILE.#(L88:93) | D95: =VLOOKUP(B95,'Analyse Réel 01-2025'!F:H,1,FALSE) -> CAM525-Total SMS Sortant | E95: =VLOOKUP(B95,'Analyse Réel 01-2025'!F:H,2,FALSE) -> CA119
A96: 95 | B96: CAM530-Revenu Internet 3G | C96: -NM(706153,*,A99,*,*,*,*,*,*) -NM(706920,*,A25,*,*,*,*,*,*) | D96: =VLOOKUP(B96,'Analyse Réel 01-2025'!F:H,1,FALSE) -> CAM530-Revenu Internet 3G | E96: =VLOOKUP(B96,'Analyse Réel 01-2025'!F:H,2,FALSE) -> CA121
... A99: 98 | B99: CAM545-Revenu VAS (call histury sim swap, sauvega | C99: -NM(706151,*,A47,*,*,*,*,*,*) -NM(706151,*,S99,*,*,*,*,*,*) -NM(706151,*,SCH,*,*,*,*,*,*) | D99: =VLOOKUP(B99,'Analyse Réel 01-2025'!F:H,1,FALSE) -> CAM545-Revenu VAS (call histury sim swap, sauvega | E99: =VLOOKUP(B99,'Analyse Réel 01-2025'!F:H,2,FALSE) -> CA124
A100: 99 | B100: CAM550-Autres SVA (Sce Foot,M2U, Job etc) | C100: 0 | D100: =VLOOKUP(B100,'Analyse Réel 01-2025'!F:H,1,FALSE) -> CAM550-Autres SVA (Sce Foot,M2U, Job etc) | E100: =VLOOKUP(B100,'Analyse Réel 01-2025'!F:H,2,FALSE) -> CA125
A101: 100 | B101: CAM555-CRBT | C101: -NM(706151,*,A99,*,*,*,*,*,*,*) | D101: =VLOOKUP(B101,'Analyse Réel 01-2025'!F:H,1,FALSE) -> CAM555-CRBT | E101: =VLOOKUP(B101,'Analyse Réel 01-2025'!F:H,2,FALSE) -> CA126
A102: 101 | B102: CAM560-Story Box | C102: -0*NM(706151,*,*,*,*,*,*,*,*) | D102: =VLOOKUP(B102,'Analyse Réel 01-2025'!F:H,1,FALSE) -> CAM560-Story Box | E102: =VLOOKUP(B102,'Analyse Réel 01-2025'!F:H,2,FALSE) -> CA127
A103: 102 | B103: CAM565-Phonebook STK | C103: 0*-NM(706151,*,*,*,*,*,*,*,*) | D103: =VLOOKUP(B103,'Analyse Réel 01-2025'!F:H,1,FALSE) -> CAM565-Phonebook STK | E103: =VLOOKUP(B103,'Analyse Réel 01-2025'!F:H,2,FALSE) -> CA128
A104: 103 | B104: CAM570-Gaming | C104: 0*-NM(706151,*,*,*,*,*,*,*,*) | D104: =VLOOKUP(B104,'Analyse Réel 01-2025'!F:H,1,FALSE) -> CAM570-Gaming | E104: =VLOOKUP(B104,'Analyse Réel 01-2025'!F:H,2,FALSE) -> CA129
A105: 104 | B105: CAM575-Total Data | C105: $CAMOBILE.#(L96:103) | D105: =VLOOKUP(B105,'Analyse Réel 01-2025'!F:H,1,FALSE) -> CAM575-Total Data | E105: =VLOOKUP(B105,'Analyse Réel 01-2025'!F:H,2,FALSE) -> CA130
A106: 105 | B106: CAM580-Dont CA voix | C106: 0 | D106: =VLOOKUP(B106,'Analyse Réel 01-2025'!F:H,1,FALSE) -> CAM580-Dont CA voix | E106: =VLOOKUP(B106,'Analyse Réel 01-2025'!F:H,2,FALSE) -> CA132
A107: 106 | B107: CAM585-Dont CA SMS | C107: 0 | D107: =VLOOKUP(B107,'Analyse Réel 01-2025'!F:H,1,FALSE) -> CAM585-Dont CA SMS | E107: =VLOOKUP(B107,'Analyse Réel 01-2025'!F:H,2,FALSE) -> CA133
A108: 107 | B108: CAM587-dont CA Internet 3G | C108: R(L51+L73+L95) | D108: =VLOOKUP(B108,'Analyse Réel 01-2025'!F:H,1,FALSE) -> CAM587-dont CA Internet 3G | E108: =VLOOKUP(B108,'Analyse Réel 01-2025'!F:H,2,FALSE) -> CA135
A109: 108 | B109: CAM445-Business Prepaid | C109: R(L87+L94+L104) | D109: =VLOOKUP(B109,'Analyse Réel 01-2025'!F:H,1,FALSE) -> CAM445-Business Prepaid | E109: =VLOOKUP(B109,'Analyse Réel 01-2025'!F:H,2,FALSE) -> CA102
A110: 109 | B110: CAM446-Trafic sortant | C110: R(L56+L78+L108) | D110: =VLOOKUP(B110,'Analyse Réel 01-2025'!F:H,1,FALSE) -> CAM446-Trafic sortant | E110: =VLOOKUP(B110,'Analyse Réel 01-2025'!F:H,2,FALSE) -> CA51
A111: 110 | B111: CAM447-Postpayé | C111: R(L34+L109) | D111: =VLOOKUP(B111,'Analyse Réel 01-2025'!F:H,1,FALSE) -> CAM447-Postpayé | E111: =VLOOKUP(B111,'Analyse Réel 01-2025'!F:H,2,FALSE) -> CA46
A112: 111 | B112: CAM600-Mobile money | C112: -NM(706150,*,ZZZ,*,*,*,*,*,*,*) | D112: =VLOOKUP(B112,'Analyse Réel 01-2025'!F:H,1,FALSE) -> CAM600-Mobile money | E112: =VLOOKUP(B112,'Analyse Réel 01-2025'!F:H,2,FALSE) -> CA136
A113: 112 | B113: CAM605-Liaisons Spécialisées | C113: -707300 -706710 | D113: =VLOOKUP(B113,'Analyse Réel 01-2025'!F:H,1,FALSE) -> CAM605-Liaisons Spécialisées | E113: =VLOOKUP(B113,'Analyse Réel 01-2025'!F:H,2,FALSE) -> CA137
A114: 113 | B114: CAM595-Internet Mobile (Prp +Pop) | C114: R(L28+L107) | D114: =VLOOKUP(B114,'Analyse Réel 01-2025'!F:H,1,FALSE) -> CAM595-Internet Mobile (Prp +Pop) | E114: =VLOOKUP(B114,'Analyse Réel 01-2025'!F:H,2,FALSE) -> CA138
A115: 114 | B115: CAM635-Consumer Prepaid | C115: -NM(706130,*,A48,*,*,*,*,*,*) -NM(706133,*,A48,*,*,*,*,*,*) | D115: =VLOOKUP(B115,'Analyse Réel 01-2025'!F:H,1,FALSE) -> CAM635-Consumer Prepaid | E115: =VLOOKUP(B115,'Analyse Réel 01-2025'!F:H,2,FALSE) -> CA144
A116: 115 | B116: CAM640-Consumer Postpaid | C116: -NM(706135,*,A48,*,*,*,*,*,*) -NM(706139,*,A48,*,*,*,*,*,*) | D116: =VLOOKUP(B116,'Analyse Réel 01-2025'!F:H,1,FALSE) -> CAM640-Consumer Postpaid | E116: =VLOOKUP(B116,'Analyse Réel 01-2025'!F:H,2,FALSE) -> CA145
A117: 116 | B117: CAM645-Business Postpaid | C117: -NM(706139,*,A43,*,*,*,*,*,*) -NM(706135,*,A43,*,*,*,*,*,*) | D117: =VLOOKUP(B117,'Analyse Réel 01-2025'!F:H,1,FALSE) -> CAM645-Business Postpaid | E117: =VLOOKUP(B117,'Analyse Réel 01-2025'!F:H,2,FALSE) -> CA146
A118: 117 | B118: CAM650-Business Prepaid | C118: -NM(706130,*,A43,*,*,*,*,*,*) -NM(706133,*,A43,*,*,*,*,*,*) | D118: =VLOOKUP(B118,'Analyse Réel 01-2025'!F:H,1,FALSE) -> CAM650-Business Prepaid | E118: =VLOOKUP(B118,'Analyse Réel 01-2025'!F:H,2,FALSE) -> CA147
A119: 118 | B119: CAM655-Opérateur national MTN | C119: $CAMOBILE.#(L114:117) | D119: =VLOOKUP(B119,'Analyse Réel 01-2025'!F:H,1,FALSE) -> CAM655-Opérateur national MTN | E119: =VLOOKUP(B119,'Analyse Réel 01-2025'!F:H,2,FALSE) -> CA143
... A135: 134 | B135: CAM625-CA Entrant | C135: R(L118+L123+L128+L133) | D135: =VLOOKUP(B135,'Analyse Réel 01-2025'!F:H,1,FALSE) -> CAM625-CA Entrant | E135: =VLOOKUP(B135,'Analyse Réel 01-2025'!F:H,2,FALSE) -> CA142
A136: 135 | B136: CAM760-Roaming in | C136: -706142 | D136: =VLOOKUP(B136,'Analyse Réel 01-2025'!F:H,1,FALSE) -> CAM760-Roaming in | E136: =VLOOKUP(B136,'Analyse Réel 01-2025'!F:H,2,FALSE) -> CA171
A137: 136 | B137: CAM770-vente de téléphones & kits | C137: -701110 | D137: =VLOOKUP(B137,'Analyse Réel 01-2025'!F:H,1,FALSE) -> CAM770-vente de téléphones & kits | E137: =VLOOKUP(B137,'Analyse Réel 01-2025'!F:H,2,FALSE) -> CA173
A138: 137 | B138: CAM775-Vente de clés & modems usb | C138: -701115 | D138: =VLOOKUP(B138,'Analyse Réel 01-2025'!F:H,1,FALSE) -> CAM775-Vente de clés & modems usb | E138: =VLOOKUP(B138,'Analyse Réel 01-2025'!F:H,2,FALSE) -> CA174
...

Sheet PROD_CAMOBILE_2025M1
F1: Correspondance
A2: Intitulé | B2: Réalisé N | C2: Budget N | D2: Budget N Actualisé 3 | E2: ECART | F2: Indicateur X3 | G2: Indicateur MOOV
A3: CAM040-Frais d'activation & Sim swap | B3: -9204763 | C3: -9204763 | D3: 9204763 | E3: 0 | F3: =LEFT(A3,6) -> CAM040 | G3: =VLOOKUP(PROD_CAMOBILE_2025M1!A3,'Analyse Réel 01-2025'!F:G,2,FALSE) -> CA12
A4: CAM045-Sortant voix on net | B4: 1295717222 | C4: 1295717222 | D4: -1355614210 | E4: 0 | F4: =LEFT(A4,6) -> CAM045 | G4: =VLOOKUP(PROD_CAMOBILE_2025M1!A4,'Analyse Réel 01-2025'!F:G,2,FALSE) -> CA13
A5: CAM050-Sortant voix MTN | B5: 1123059001 | C5: 1123059001 | D5: -1123059001 | E5: 0 | F5: =LEFT(A5,6) -> CAM050 | G5: =VLOOKUP(PROD_CAMOBILE_2025M1!A5,'Analyse Réel 01-2025'!F:G,2,FALSE) -> CA14
A6: CAM055-Sortant voix GLO | B6: 0 | C6: 0 | D6: 0 | E6: 0 | F6: =LEFT(A6,6) -> CAM055 | G6: =VLOOKUP(PROD_CAMOBILE_2025M1!A6,'Analyse Réel 01-2025'!F:G,2,FALSE) -> CA15
A7: CAM060-Sortant voix BBCOM | B7: 0 | C7: 0 | D7: 0 | E7: 0 | F7: =LEFT(A7,6) -> CAM060 | G7: =VLOOKUP(PROD_CAMOBILE_2025M1!A7,'Analyse Réel 01-2025'!F:G,2,FALSE) -> CA16
A8: CAM065-Sortant voix LIBERCOM | B8: 0 | C8: 0 | D8: 0 | E8: 0 | F8: =LEFT(A8,6) -> CAM065 | G8: =VLOOKUP(PROD_CAMOBILE_2025M1!A8,'Analyse Réel 01-2025'!F:G,2,FALSE) -> CA17
A9: CAM070-Sortant voix BTSA | B9: 477346316 | C9: 477346316 | D9: 0 | E9: 0 | F9: =LEFT(A9,6) -> CAM070 | G9: =VLOOKUP(PROD_CAMOBILE_2025M1!A9,'Analyse Réel 01-2025'!F:G,2,FALSE) -> CA18
A10: CAM075-Sortant voix INTERNATIONAL | B10: 159932592 | C10: 159932592 | D10: -159932592 | E10: 0 | F10: =LEFT(A10,6) -> CAM075 | G10: =VLOOKUP(PROD_CAMOBILE_2025M1!A10,'Analyse Réel 01-2025'!F:G,2,FALSE) -> CA19
A11: CAM080-Sortant voix roaming | B11: 10567860 | C11: 10567860 | D11: -10567860 | E11: 0 | F11: =LEFT(A11,6) -> CAM080 | G11: =VLOOKUP(PROD_CAMOBILE_2025M1!A11,'Analyse Réel 01-2025'!F:G,2,FALSE) -> CA20
A12: CAM085-Total VOIX Sortant | B12: 3066622991 | C12: 3066622991 | D12: -2649173663 | E12: 0 | F12: =LEFT(A12,6) -> CAM085 | G12: =VLOOKUP(PROD_CAMOBILE_2025M1!A12,'Analyse Réel 01-2025'!F:G,2,FALSE) -> CA21
A13: CAM090-Sortant sms on net | B13: 1236479 | C13: 1236479 | D13: -1296066 | E13: 0 | F13: =LEFT(A13,6) -> CAM090 | G13: =VLOOKUP(PROD_CAMOBILE_2025M1!A13,'Analyse Réel 01-2025'!F:G,2,FALSE) -> CA23
A14: CAM095-Sortant sms MTN | B14: 1231451 | C14: 1231451 | D14: 0 | E14: 0 | F14: =LEFT(A14,6) -> CAM095 | G14: =VLOOKUP(PROD_CAMOBILE_2025M1!A14,'Analyse Réel 01-2025'!F:G,2,FALSE) -> CA24
A15: CAM0100-Sortant sms GLO | B15: 0 | C15: 0 | D15: 0 | E15: 0 | F15: =LEFT(A15,7) -> CAM0100 | G15: =VLOOKUP(PROD_CAMOBILE_2025M1!A15,'Analyse Réel 01-2025'!F:G,2,FALSE) -> CA25
A16: CAM105-Sortant sms BBCOM | B16: 1381 | C16: 1381 | D16: -1381 | E16: 0 | F16: =LEFT(A16,6) -> CAM105 | G16: =VLOOKUP(PROD_CAMOBILE_2025M1!A16,'Analyse Réel 01-2025'!F:G,2,FALSE) -> CA26
A17: CAM110-Sortant sms LIBERCOM | B17: 232047 | C17: 232047 | D17: -232047 | E17: 0 | F17: =LEFT(A17,6) -> CAM110 | G17: =VLOOKUP(PROD_CAMOBILE_2025M1!A17,'Analyse Réel 01-2025'!F:G,2,FALSE) -> CA27
A18: CAM115-Sortant sms INTERNATIONAL | B18: 2620917 | C18: -2620917 | D18: -2620917 | E18: 5241834 | F18: =LEFT(A18,6) -> CAM115 | G18: =VLOOKUP(PROD_CAMOBILE_2025M1!A18,'Analyse Réel 01-2025'!F:G,2,FALSE) -> CA28
A19: CAM120-Total SMS Sortant | B19: 5322275 | C19: 80441 | D19: -4150411 | E19: 5241834 | F19: =LEFT(A19,6) -> CAM120 | G19: =VLOOKUP(PROD_CAMOBILE_2025M1!A19,'Analyse Réel 01-2025'!F:G,2,FALSE) -> CA29
A20: CAM125-Revenu Internet 3G | B20: 3391819301 | C20: 0 | D20: 0 | E20: 3391819301 | F20: =LEFT(A20,6) -> CAM125 | G20: =VLOOKUP(PROD_CAMOBILE_2025M1!A20,'Analyse Réel 01-2025'!F:G,2,FALSE) -> CA31
A21: CAM130-CRBT | B21: 132797 | C21: -132797 | D21: -132797 | E21: 265594 | F21: =LEFT(A21,6) -> CAM130 | G21: =VLOOKUP(PROD_CAMOBILE_2025M1!A21,'Analyse Réel 01-2025'!F:G,2,FALSE) -> CA33
A22: CAM135-Crédit secours | B22: 117373380 | C22: -117373380 | D22: -117373380 | E22: 234746760 | F22: =LEFT(A22,6) -> CAM135 | G22: =VLOOKUP(PROD_CAMOBILE_2025M1!A22,'Analyse Réel 01-2025'!F:G,2,FALSE) -> CA34
A23: CAM140-Story Box | B23: 0 | C23: -129418045 | D23: -129418045 | E23: 129418045 | F23: =LEFT(A23,6) -> CAM140 | G23: =VLOOKUP(PROD_CAMOBILE_2025M1!A23,'Analyse Réel 01-2025'!F:G,2,FALSE) -> CA35
A24: CAM145-Phonebook STK | B24: 0 | C24: -129418045 | D24: -129418045 | E24: 129418045 | F24: =LEFT(A24,6) -> CAM145 | G24: =VLOOKUP(PROD_CAMOBILE_2025M1!A24,'Analyse Réel 01-2025'!F:G,2,FALSE) -> CA36
A25: CAM150-Gaming | B25: 0 | C25: -129418045 | D25: -129418045 | E25: 129418045 | F25: =LEFT(A25,6) -> CAM150 | G25: =VLOOKUP(PROD_CAMOBILE_2025M1!A25,'Analyse Réel 01-2025'!F:G,2,FALSE) -> CA37
A26: CAM155-Autres (VOICEALERT,MOOVKDO...) | B26: 0 | C26: -129418045 | D26: -129418045 | E26: 129418045 | F26: =LEFT(A26,6) -> CAM155 | G26: =VLOOKUP(PROD_CAMOBILE_2025M1!A26,'Analyse Réel 01-2025'!F:G,2,FALSE) -> CA38
A27: CAM160-Videos | B27: 0 | C27: -129418045 | D27: -129418045 | E27: 129418045 | F27: =LEFT(A27,6) -> CAM160 | G27: =VLOOKUP(PROD_CAMOBILE_2025M1!A27,'Analyse Réel 01-2025'!F:G,2,FALSE) -> CA39
... A145: CAM005-CA Global | B145: 7556427339 | C145: -208519772 | D145: -5910137752 | E145: 7764947111 | F145: =LEFT(A145,6) -> CAM005 | G145: =VLOOKUP(PROD_CAMOBILE_2025M1!A145,'Analyse Réel 01-2025'!F:G,2,FALSE) -> CA1

Sheet Données MOOV 01-2025
E1: 0
A2: CA Mobile
D4: 45658
B5: (En Millions ML) | D5: 2025 Réel | E5: 2025 Budget | F5: Ecart / Budget | G5: 2024 Réel | H5: Evol %
A8: CA Global | C8: CA1 | D8: 8324.9028 | E8: 9527.0891 | F8: -1202.1863 | G8: 9480.8077 | H8: -0.12192051
C9: CA2
B10: dont CA Etat | C10: CA3
C11: CA4
A12: CA services Mobile | C12: CA5 | D12: 8118.3484 | E12: 9340.117 | F12: -1221.7686 | G12: 9400.2691 | H12: -0.13637063
C13: CA6 | G13: 0
A14: CA récurrent | C14: CA7 | D14: 7983.1451 | E14: 9190.3209 | F14: -1207.1757 | G14: 9314.5768 | H14: -0.14294065
C15: CA8 | G15: 0
A16: CA sortant | C16: CA9 | D16: 7739.2918 | E16: 8900.1169 | F16: -1160.8251 | G16: 9000.8894 | H16: -0.14016366
B17: Prépayé (yc commissions) | C17: CA10 | D17: 3180.332 | E17: 3844.6975 | F17: -664.36549 | G17: 4134.0606 | H17: -0.23070019
A18: Consumer Prepaid | C18: CA11 | D18: 3180.332 | E18: 3844.6975 | F18: -664.36549 | G18: 4134.0606 | H18: -0.23070019
B19: Frais d'activation & Sim swap | C19: CA12 | D19: -9.204763 | E19: -22.461806 | F19: 13.257043 | G19: -34.062214 | H19: -0.72976616
B20: Sortant voix on net | C20: CA13 | D20: 1325.2425 | E20: 1532.0023 | F20: -206.7598 | G20: 1925.9137 | H20: -0.31188896
B21: Sortant voix MTN | C21: CA14 | D21: 1093.7671 | E21: 1964.2889 | F21: -870.52183 | G21: 1821.5085 | H21: -0.39952676
B22: Sortant voix GLO | C22: CA15 | D22: 0 | E22: 0 | F22: 0 | G22: 0
B23: Sortant voix BBCOM | C23: CA16 | D23: 0 | E23: 0 | G23: 0
B24: Sortant voix LIBERCOM | C24: CA17 | D24: 0 | E24: 134.85752 | F24: -134.85752 | G24: 0
B25: Sortant voix BTSA | C25: CA18 | D25: 477.33819 | E25: 0.26963616 | F25: 477.06855 | G25: 72.348988 | H25: 5.5977176
B26: Sortant voix INTERNATIONAL | C26: CA19 | D26: 159.65992 | E26: 134.97915 | F26: 24.68077 | G26: 206.80959 | H26: -0.22798589
B27: Sortant voix roaming | C27: CA20 | D27: 10.56786 | E27: 16.595851 | F27: -6.0279905 | G27: 12.72778 | H27: -0.16970124
B28: Total VOIX Sortant | C28: CA21 | D28: 3066.5755 | E28: 3782.9934 | F28: -716.41781 | G28: 4039.3085 | H28: -0.24081671
C29: CA22 | E29: 0 | G29: 0
B30: Sortant sms on net | C30: CA23 | D30: 1.236479 | E30: 1.2104351 | F30: 0.026043887 | G30: 1.899627 | H30: -0.3490938
B31: Sortant sms MTN | C31: CA24 | D31: 1.231451 | E31: 1.3495968 | F31: -0.11814585 | G31: 1.765875 | H31: -0.30263977
B32: Sortant sms GLO | C32: CA25 | D32: 0 | E32: 0 | F32: 0 | G32: 0
B33: Sortant sms BBCOM | C33: CA26 | D33: 0.001381 | E33: 0.0020104274 | F33: -0.00062942739 | G33: 0.001729
B34: Sortant sms LIBERCOM | C34: CA27 | D34: 0.232047 | E34: 0.40805876 | F34: -0.17601176 | G34: 0.444316
B35: Sortant sms INTERNATIONAL | C35: CA28 | D35: 2.620917 | E35: 1.7264834 | F35: 0.89443356 | G35: 2.610107 | H35: 0.0041415927
B36: Total SMS Sortant | C36: CA29 | D36: 5.322275 | E36: 4.6965846 | F36: 0.62569041 | G36: 6.721654 | H36: -0.20818968
C37: CA30 | G37: 0
B38: Revenu Internet 3G | C38: CA31 | D38: 3391.8193 | E38: 3972.9579 | F38: -581.13862 | G38: 3929.1116 | H38: -0.13674651
C39: CA32 | G39: 0
B40: CRBT | C40: CA33 | D40: 0.132797 | E40: 0.2890989 | F40: -0.1563019 | G40: 0.565572 | H40: -0.76519877
B41: Crédit secours | C41: CA34 | D41: 7.7828593 | E41: 6.5450633 | F41: 1.237796 | G41: 11.089769 | H41: -0.29819465
B42: Story Box | C42: CA35 | D42: 0 | E42: 0 | F42: 0 | G42: 0
B43: Phonebook STK | C43: CA36 | D43: 0 | E43: 0 | F43: 0 | G43: 0
B44: Gaming | C44: CA37 | D44: 0 | E44: 0 | F44: 0 | G44: 0
B45: Autres dont BAC17 (VOICEALERT,MOOVKDO...) & SAV agences | C45: CA38 | D45: 109.72332 | E45: 72.635227 | F45: 37.088091 | G45: 110.43728
B46: Videos | C46: CA39 | D46: 0 | E46: 0 | F46: 0 | G46: 0
B47: Total Data | C47: CA40 | D47: 117.63897 | E47: 79.469389 | F47: 38.169585 | G47: 122.09263 | H47: -0.036477649
C48: CA41 | G48: 0
B49: dont CA voix | C49: CA42 | G49: 0
B50: dont CA SMS | C50: CA43 | G50: 0
B51: dont SVA (Sce à Val. Ajoutée) | C51: CA44 | G51: 0
B52: dont CA Internet 3G | C52: CA45 | D52: 3391.8193 | E52: 3972.9579 | F52: -581.13862 | G52: 3929.1116 | H52: -0.13674651
B53: Postpayé | C53: CA46 | D53: 283.3024 | E53: 292.50936 | F53: -9.2069629 | G53: 286.37459 | H53: -0.010727893
B54: Redevance d'abonnement | C54: CA47 | D54: 210.72997 | E54: 216.24376 | F54: -5.5137952 | G54: 201.05486 | H54: 0.048121727
A55: Consumer Postpaid | C55: CA48 | D55: 10.744112 | E55: 9.6670395 | F55: 1.0770725 | G55: -10.210921 | H55: -2.0522177
A56: Business Postpaid | C56: CA49 | D56: 14.508871 | E56: 18.503261 | F56: -3.9943899 | G56: 20.653505 | H56: -0.29751047
A57: Business Prepaid | C57: CA50 | D57: 185.47698 | E57: 188.07346 | F57: -2.5964779 | G57: 190.61228 | H57: -0.026941035
B58: Trafic sortant | C58: CA51 | D58: 72.572432 | E58: 76.2656 | F58: -3.6931677 | G58: 85.319735 | H58: -0.14940627
A59: Consumer Postpaid | C59: CA52 | D59: 0.597171 | E59: 1.7686928 | F59: -1.1715218 | G59: 1.55598 | H59: -0.61620908
B60: Sortant voix on net | C60: CA53 | D60: 0.150395 | E60: 0.1204336 | F60: 0.0299614 | G60: 0.293624 | H60: -0.48779732
B61: Sortant voix MTN | C61: CA54 | D61: 0.314893 | E61: 0.26936534 | F61: 0.045527657 | G61: 0.588739 | H61: -0.4651399
B62: Sortant voix GLO | C62: CA55 | D62: 0 | E62: 0 | F62: 0 | G62: 0
B63: Sortant voix BBCOM | C63: CA56 | D63: 0 | E63: 0 | F63: 0 | G63: 0
B64: Sortant voix LIBERCOM | C64: CA57 | D64: 0.044706 | E64: 0.03092746 | F64: 0.01377854 | G64: 0.019446
B65: Sortant voix BTSA | C65: CA58 | D65: -0.001938 | E65: 0.004503074 | F65: -0.006441074 | G65: 0.003216 | H65: -1.6026119
B66: Sortant voix INTERNATIONAL | C66: CA59 | D66: 0.046205 | E66: 0.063212938 | F66: -0.017007938 | G66: 0.271662 | H66: -0.82991732
B67: Sortant voix roaming | C67: CA60 | D67: 0.024176 | E67: 0.38755427 | F67: -0.36337827 | G67: 0.375186
B68: Total VOIX Sortant | C68: CA61 | D68: 0.578437 | E68: 0.87599668 | F68: -0.29755968 | G68: 1.551873 | H68: -0.62726525
C69: CA62 | F69: 0 | G69: 0
B70: Sortant sms on net | C70: CA63 | D70: 0.018734 | E70: 0.0052030414 | F70: 0.013530959 | G70: 0.004107 | H70: 3.5614804
B71: Sortant sms MTN | C71: CA64 | D71: 0 | E71: 0 | F71: 0 | G71: 0 | H71: #DIV/0!
B72: Sortant sms GLO | C72: CA65 | D72: 0 | E72: 0 | F72: 0 | G72: 0
B73: Sortant sms BBCOM | C73: CA66 | D73: 0 | E73: 0 | F73: 0 | G73: 0
B74: Sortant sms LIBERCOM | C74: CA67 | D74: 0 | E74: 0 | F74: 0 | G74: 0
B75: Sortant sms INTERNATIONAL | C75: CA68 | D75: 0 | E75: 0.04025868 | F75: -0.04025868 | G75: 0 | H75: #DIV/0!
B76: Total SMS Sortant | C76: CA69 | D76: 0.018734 | E76: 0.045461721 | F76: -0.026727721 | G76: 0.004107 | H76: 3.5614804
C77: CA70 | G77: 0
B78: Revenu Internet 3G | C78: CA71 | D78: -2.612012 | E78: 1.1029799 | F78: -3.7149919 | G78: 1.63691 | H78: -2.5956968
B79: Transport and Automotive (Traking) | C79: CA72 | E79: 0 | G79: 0
B80: Banking | C80: CA73 | E80: 0.84723435 | F80: -0.84723435 | G80: 0
B81: TPE | C81: CA74 | E81: 0 | F81: 0 | G81: 0
B82: Total Data | C82: CA75 | D82: 0 | E82: 0.84723435 | F82: -0.84723435 | G82: 0
C83: CA76 | G83: 0
A84: Business Postpaid | C84: CA77 | D84: 35.107592 | E84: 31.633661 | F84: 3.4739314 | G84: 30.596928 | H84: 0.14742212
B85: Sortant voix on net | C85: CA78 | D85: 2.479334 | E85: 2.6185885 | F85: -0.13925451 | G85: 3.180434 | H85: -0.22044161
B86: Sortant voix MTN | C86: CA79 | D86: 5.919833 | E86: 4.9611982 | F86: 0.95863476 | G86: 7.071411 | H86: -0.16284982
B87: Sortant voix GLO | C87: CA80 | D87: 0 | E87: 0 | F87: 0 | G87: 0
B88: Sortant voix BBCOM | C88: CA81 | D88: 0 | E88: 0 | F88: 0 | G88: 0
B89: Sortant voix LIBERCOM | C89: CA82 | D89: 0 | E89: 0 | F89: 0 | G89: 0
B90: Sortant voix BTSA | C90: CA83 | D90: 0.022573 | E90: 0.032492996 | F90: -0.009919996 | G90: 0.032085 | H90: -0.29646252
B91: Sortant voix INTERNATIONAL | C91: CA84 | D91: 1.07568 | E91: 1.2571812 | F91: -0.18150118 | G91: 1.401239 | H91: -0.23233653
B92: Sortant voix roaming | C92: CA85 | D92: 1.821352 | E92: 1.218279 | F92: 0.60307299 | G92: -0.236035 | H92: -8.7164488
B93: Total VOIX Sortant | C93: CA86 | D93: 11.318772 | E93: 10.08774 | F93: 1.2310321 | G93: 11.449134 | H93: -0.011386189
C94: CA87 | G94: 0
B95: Sortant sms on net | C95: CA88 | D95: 22.126457 | E95: 20.77031 | F95: 1.3561473 | G95: 18.338001 | H95: 0.20659046
B96: Sortant sms MTN | C96: CA89 | D96: 0 | E96: 0 | F96: 0 | G96: 0 | H96: #DIV/0!
B97: Sortant sms GLO | C97: CA90 | D97: 0 | E97: 0 | F97: 0 | G97: 0
B98: Sortant sms BBCOM | C98: CA91 | D98: 0 | E98: 0 | F98: 0 | G98: 0
B99: Sortant sms LIBERCOM | C99: CA92 | D99: 0 | E99: 0 | F99: 0 | G99: 0
B100: Sortant sms INTERNATIONAL | C100: CA93 | D100: 0 | E100: 0 | F100: 0 | G100: 0 | H100: #DIV/0!
B101: Total SMS Sortant | C101: CA94 | D101: 22.126457 | E101: 20.77031 | F101: 1.3561473 | G101: 18.338001 | H101: 0.20659046
C102: CA95 | F102: 0 | G102: 0
B103: Revenu Internet 3G | C103: CA96 | D103: 43.765311 | E103: 30.940344 | F103: 12.824967 | G103: 9.392304 | H103: 3.6596992
...

Sheet Analyse Réel 01-2025
A1: Réalisé 2025 - Données MOOV | F1: Réalisé 2025 - Données X3 Base PROD | I1: Données X3 - Test | J1: Formule indicateur | K1: Formule indicateur | L1: Ecart | M1: actualisation des RG | N1: Calcul OK | O1: REMARQUES
A2: CA Global | C2: CA1 | D2: =VLOOKUP(C2,'Données MOOV 01-2025'!C:D,2,FALSE) -> 8324.9028 | E2: =D2*1000000 -> 8.3249028e+09 | F2: CAM005-CA Global | G2: CA1 | H2: =VLOOKUP(F2,PROD_CAMOBILE_2025M1!A:B,2,FALSE) -> 7556427339 | I2: 9882621663 | J2: =VLOOKUP(F2,'Formule TDB'!B:C,2,FALSE) -> R(L139+L142) | K2: R(L139+L142) | L2: =E2-H2 -> 7.6847544e+08 | N2: Calcul avec écart
A3: CA services Mobile | C3: CA5 | D3: =VLOOKUP(C3,'Données MOOV 01-2025'!C:D,2,FALSE) -> 8118.3484 | E3: =D3*1000000 -> 8.1183484e+09 | F3: CAM015-CA services Mobile | G3: CA5 | H3: =VLOOKUP(F3,PROD_CAMOBILE_2025M1!A:B,2,FALSE) -> 7349873003 | I3: 9802083009 | J3: =VLOOKUP(F3,'Formule TDB'!B:C,2,FALSE) -> R(L135+L141) | K3: R(L135+L141) | L3: =E3-H3 -> 7.6847544e+08 | N3: Aucun équivalence sur TDB X3
A4: CA récurrent | C4: CA7 | D4: =VLOOKUP(C4,'Données MOOV 01-2025'!C:D,2,FALSE) -> 7983.1451 | E4: =D4*1000000 -> 7.9831451e+09 | F4: CAM020-CA récurrent | G4: CA7 | H4: =VLOOKUP(F4,PROD_CAMOBILE_2025M1!A:B,2,FALSE) -> 7315602945 | I4: 9753598008 | J4: =VLOOKUP(F4,'Formule TDB'!B:C,2,FALSE) -> R(L134+L140) | K4: R(L134+L140) | L4: =E4-H4 -> 6.6754219e+08
A5: CA sortant | C5: CA9 | D5: =VLOOKUP(C5,'Données MOOV 01-2025'!C:D,2,FALSE) -> 7739.2918 | E5: =D5*1000000 -> 7.7392918e+09 | F5: CAM025-CA Sortant | G5: CA9 | H5: =VLOOKUP(F5,PROD_CAMOBILE_2025M1!A:B,2,FALSE) -> 7132612739 | I5: 9511898580 | J5: =VLOOKUP(F5,'Formule TDB'!B:C,2,FALSE) -> R(L30+L110+L111+L112+L113) | K5: R(L30+L110+L111+L112+L113) | L5: =E5-H5 -> 6.0667907e+08
A6: Consumer Prepaid | C6: CA11 | D6: =VLOOKUP(C6,'Données MOOV 01-2025'!C:D,2,FALSE) -> 3180.332 | E6: =D6*1000000 -> 3.180332e+09 | F6: CAM035-Consumer Prepaid | G6: CA11 | H6: =VLOOKUP(F6,PROD_CAMOBILE_2025M1!A:B,2,FALSE) -> 3180246680 | I6: 4671622639 | J6: =VLOOKUP(F6,'Formule TDB'!B:C,2,FALSE) -> R(L1+L10+L17+L26) | K6: R(L1+L10+L17+L26) | L6: =E6-H6 -> 85351 | N6: Action correctives
B7: Frais d'activation & Sim swap | C7: CA12 | D7: =VLOOKUP(C7,'Données MOOV 01-2025'!C:D,2,FALSE) -> -9.204763 | E7: =D7*1000000 -> -9204763 | F7: CAM040-Frais d'activation & Sim swap | G7: CA12 | H7: =VLOOKUP(F7,PROD_CAMOBILE_2025M1!A:B,2,FALSE) -> -9204763 | I7: -34062214 | J7: =VLOOKUP(F7,'Formule TDB'!B:C,2,FALSE) -> -701120 -701130 | K7: -701120 -701130 | L7: =E7-H7 -> 0
B8: Sortant voix on net | C8: CA13 | D8: =VLOOKUP(C8,'Données MOOV 01-2025'!C:D,2,FALSE) -> 1325.2425 | E8: =D8*1000000 -> 1.3252425e+09 | F8: CAM045-Sortant voix on net | G8: CA13 | H8: =VLOOKUP(F8,PROD_CAMOBILE_2025M1!A:B,2,FALSE) -> 1295717222 | I8: 1891504933 | J8: =VLOOKUP(F8,'Formule TDB'!B:C,2,FALSE) -> -NM(706120,*,A61,*,*,*,*,*,*,*) -NM(706920,*,A58,*,*,*,*,*,*,*) | K8: -NM(706120,*,A61,*,*,*,*,*,*,*) -NM(706920,*,A58,*,*,*,*,*,*,*) | L8: =E8-H8 -> 29525256 | M8: NM(706120,*,A61,*,*,*,*,*,*,*) -NM(706920,*,A58,*,*,*,*,*,*,*) + somme( CA consumer D29:D34) | N8: Besoin du ficher CA consumer + RG actualisées | O8: Cet écart provient des retraitements manuels effectués sur les bonus( voir feuille CA Consumer Somme L6 à11) | P8: =SUM('CA Consumer'!D6:D11) -> 29572702
B9: Sortant voix MTN | C9: CA14 | D9: =VLOOKUP(C9,'Données MOOV 01-2025'!C:D,2,FALSE) -> 1093.7671 | E9: =D9*1000000 -> 1.0937671e+09 | F9: CAM050-Sortant voix MTN | G9: CA14 | H9: =VLOOKUP(F9,PROD_CAMOBILE_2025M1!A:B,2,FALSE) -> 1123059001 | I9: 1855699449 | J9: =VLOOKUP(F9,'Formule TDB'!B:C,2,FALSE) -> -NM(706121,*,A48,*,*,*,*,*,*,*) | K9: -NM(706121,*,A48,*,*,*,*,*,*,*) | L9: =E9-H9 -> -29291907 | M9: NM(706121,*,A48,*,*,*,*,*,*,*) - CA consumer D29 | O9: Cet écart provient des retraitements manuels effectués sur les bonus( voir feuille CA Consumer L6) | P9: ='CA Consumer'!D6 -> 29291907
B10: Sortant voix GLO | C10: CA15 | D10: =VLOOKUP(C10,'Données MOOV 01-2025'!C:D,2,FALSE) -> 0 | E10: =D10*1000000 -> 0 | F10: CAM055-Sortant voix GLO | G10: CA15 | H10: =VLOOKUP(F10,PROD_CAMOBILE_2025M1!A:B,2,FALSE) -> 0 | I10: 0 | J10: =VLOOKUP(F10,'Formule TDB'!B:C,2,FALSE) -> -NM(706121,*,*A49,*,*,*,*,*,*,*) | K10: -NM(706121,*,*A49,*,*,*,*,*,*,*) | L10: =E10-H10 -> 0
B11: Sortant voix BBCOM | C11: CA16 | D11: =VLOOKUP(C11,'Données MOOV 01-2025'!C:D,2,FALSE) -> 0 | E11: =D11*1000000 -> 0 | F11: CAM060-Sortant voix BBCOM | G11: CA16 | H11: =VLOOKUP(F11,PROD_CAMOBILE_2025M1!A:B,2,FALSE) -> 0 | I11: 0 | J11: =VLOOKUP(F11,'Formule TDB'!B:C,2,FALSE) -> -NM(706121,*,*A50,*,*,*,*,*,*,*) | K11: -NM(706121,*,*A50,*,*,*,*,*,*,*) | L11: =E11-H11 -> 0
B12: Sortant voix LIBERCOM | C12: CA17 | D12: =VLOOKUP(C12,'Données MOOV 01-2025'!C:D,2,FALSE) -> 0 | E12: =D12*1000000 -> 0 | F12: CAM065-Sortant voix LIBERCOM | G12: CA17 | H12: =VLOOKUP(F12,PROD_CAMOBILE_2025M1!A:B,2,FALSE) -> 0 | I12: 0 | J12: =VLOOKUP(F12,'Formule TDB'!B:C,2,FALSE) -> -NM(706121,*,*A51,*,*,*,*,*,*,*) | K12: -NM(706121,*,*A51,*,*,*,*,*,*,*) | L12: =E12-H12 -> 0
B13: Sortant voix BTSA | C13: CA18 | D13: =VLOOKUP(C13,'Données MOOV 01-2025'!C:D,2,FALSE) -> 477.33819 | E13: =D13*1000000 -> 4.7733819e+08 | F13: CAM070-Sortant voix BTSA | G13: CA18 | H13: =VLOOKUP(F13,PROD_CAMOBILE_2025M1!A:B,2,FALSE) -> 477346316 | I13: 72356625 | J13: =VLOOKUP(F13,'Formule TDB'!B:C,2,FALSE) -> -NM(706123,*,A52,*,*,*,*,*,*,*) | K13: -NM(706123,*,A52,*,*,*,*,*,*,*) | L13: =E13-H13 -> -8124.8475 | M13: NM(706123,*,A52,*,*,*,*,*,*,*) - CA consumer D33 | O13: Cet écart provient des retraitements manuels effectués sur les bonus( voir feuille CA Consumer L10) | P13: ='CA Consumer'!D10 -> 8124.8475
B14: Sortant voix INTERNATIONAL | C14: CA19 | D14: =VLOOKUP(C14,'Données MOOV 01-2025'!C:D,2,FALSE) -> 159.65992 | E14: =D14*1000000 -> 1.5965992e+08 | F14: CAM075-Sortant voix INTERNATIONAL | G14: CA19 | H14: =VLOOKUP(F14,PROD_CAMOBILE_2025M1!A:B,2,FALSE) -> 159932592 | I14: 207019754 | J14: =VLOOKUP(F14,'Formule TDB'!B:C,2,FALSE) -> -NM(706124,*,A53,*,*,*,*,*,*,*) | K14: -NM(706124,*,A53,*,*,*,*,*,*,*) | L14: =E14-H14 -> -272670.34 | M14: NM(706124,*,A53,*,*,*,*,*,*,*) - CA consumer D34 | O14: Cet écart provient des retraitements manuels effectués sur les bonus( voir feuille CA Consumer L11) | P14: ='CA Consumer'!D11 -> 272670.34
B15: Sortant voix roaming | C15: CA20 | D15: =VLOOKUP(C15,'Données MOOV 01-2025'!C:D,2,FALSE) -> 10.56786 | E15: =D15*1000000 -> 10567860 | F15: CAM080-Sortant voix roaming | G15: CA20 | H15: =VLOOKUP(F15,PROD_CAMOBILE_2025M1!A:B,2,FALSE) -> 10567860 | I15: 12727780 | J15: =VLOOKUP(F15,'Formule TDB'!B:C,2,FALSE) -> -NM(706140,*,A54,*,*,*,*,*,*,*) | K15: -NM(706140,*,A54,*,*,*,*,*,*,*) | L15: =E15-H15 -> 0
B16: Total VOIX Sortant | C16: CA21 | D16: =VLOOKUP(C16,'Données MOOV 01-2025'!C:D,2,FALSE) -> 3066.5755 | E16: =D16*1000000 -> 3.0665755e+09 | F16: CAM085-Total VOIX Sortant | G16: CA21 | H16: =VLOOKUP(F16,PROD_CAMOBILE_2025M1!A:B,2,FALSE) -> 3066622991 | I16: 4039308541 | J16: =VLOOKUP(F16,'Formule TDB'!B:C,2,FALSE) -> $CAMOBILE.#(L2:9) | K16: $CAMOBILE.#(L2:9) | L16: =E16-H16 -> -47446 | O16: Somme des écarts L8-9-13-14
B17: Sortant sms on net | C17: CA23 | D17: =VLOOKUP(C17,'Données MOOV 01-2025'!C:D,2,FALSE) -> 1.236479 | E17: =D17*1000000 -> 1236479 | F17: CAM090-Sortant sms on net | G17: CA23 | H17: =VLOOKUP(F17,PROD_CAMOBILE_2025M1!A:B,2,FALSE) -> 1236479 | I17: 1899627 | J17: =VLOOKUP(F17,'Formule TDB'!B:C,2,FALSE) -> -NM(706117,*,T21,*,*,*,*,*,*,*) -NM(706920,*,A59,*,*,*,*,*,*,*) | K17: -NM(706117,*,T21,*,*,*,*,*,*,*) -NM(706920,*,A59,*,*,*,*,*,*,*) | L17: =E17-H17 -> 0
B18: Sortant sms MTN | C18: CA24 | D18: =VLOOKUP(C18,'Données MOOV 01-2025'!C:D,2,FALSE) -> 1.231451 | E18: =D18*1000000 -> 1231451 | F18: CAM095-Sortant sms MTN | G18: CA24 | H18: =VLOOKUP(F18,PROD_CAMOBILE_2025M1!A:B,2,FALSE) -> 1231451 | I18: 1765875 | J18: =VLOOKUP(F18,'Formule TDB'!B:C,2,FALSE) -> -NM(706117,*,A48,*,*,*,*,*,*,*) | K18: -NM(706117,*,A48,*,*,*,*,*,*,*) | L18: =E18-H18 -> 0
B19: Sortant sms GLO | C19: CA25 | D19: =VLOOKUP(C19,'Données MOOV 01-2025'!C:D,2,FALSE) -> 0 | E19: =D19*1000000 -> 0 | F19: CAM0100-Sortant sms GLO | G19: CA25 | H19: =VLOOKUP(F19,PROD_CAMOBILE_2025M1!A:B,2,FALSE) -> 0 | I19: 0 | J19: =VLOOKUP(F19,'Formule TDB'!B:C,2,FALSE) -> -NM(706117,*,A49,*,*,*,*,*,*,*) | K19: -NM(706117,*,A49,*,*,*,*,*,*,*) | L19: =E19-H19 -> 0
B20: Sortant sms BBCOM | C20: CA26 | D20: =VLOOKUP(C20,'Données MOOV 01-2025'!C:D,2,FALSE) -> 0.001381 | E20: =D20*1000000 -> 1381 | F20: CAM105-Sortant sms BBCOM | G20: CA26 | H20: =VLOOKUP(F20,PROD_CAMOBILE_2025M1!A:B,2,FALSE) -> 1381 | I20: 1729 | J20: =VLOOKUP(F20,'Formule TDB'!B:C,2,FALSE) -> -NM(706117,*,A50,*,*,*,*,*,*,*) | K20: -NM(706117,*,A50,*,*,*,*,*,*,*) | L20: =E20-H20 -> 0
B21: Sortant sms LIBERCOM | C21: CA27 | D21: =VLOOKUP(C21,'Données MOOV 01-2025'!C:D,2,FALSE) -> 0.232047 | E21: =D21*1000000 -> 232047 | F21: CAM110-Sortant sms LIBERCOM | G21: CA27 | H21: =VLOOKUP(F21,PROD_CAMOBILE_2025M1!A:B,2,FALSE) -> 232047 | I21: 444316 | J21: =VLOOKUP(F21,'Formule TDB'!B:C,2,FALSE) -> -NM(706117,*,A51,*,*,*,*,*,*,*) | K21: -NM(706117,*,A51,*,*,*,*,*,*,*) | L21: =E21-H21 -> 0
B22: Sortant sms INTERNATIONAL | C22: CA28 | D22: =VLOOKUP(C22,'Données MOOV 01-2025'!C:D,2,FALSE) -> 2.620917 | E22: =D22*1000000 -> 2620917 | F22: CAM115-Sortant sms INTERNATIONAL | G22: CA28 | H22: =VLOOKUP(F22,PROD_CAMOBILE_2025M1!A:B,2,FALSE) -> 2620917 | I22: 2610107 | J22: =VLOOKUP(F22,'Formule TDB'!B:C,2,FALSE) -> -NM(706117,*,A53,*,*,*,*,*,*,*) | K22: -NM(706117,*,A53,*,*,*,*,*,*,*) | L22: =E22-H22 -> 0
B23: Total SMS Sortant | C23: CA29 | D23: =VLOOKUP(C23,'Données MOOV 01-2025'!C:D,2,FALSE) -> 5.322275 | E23: =D23*1000000 -> 5322275 | F23: CAM120-Total SMS Sortant | G23: CA29 | H23: =VLOOKUP(F23,PROD_CAMOBILE_2025M1!A:B,2,FALSE) -> 5322275 | I23: 6721654 | J23: =VLOOKUP(F23,'Formule TDB'!B:C,2,FALSE) -> $CAMOBILE.#(L11:16) | K23: $CAMOBILE.#(L11:16) | L23: =E23-H23 -> 0
B24: Revenu Internet 3G | C24: CA31 | D24: =VLOOKUP(C24,'Données MOOV 01-2025'!C:D,2,FALSE) -> 3391.8193 | E24: =D24*1000000 -> 3391819301 | F24: CAM125-Revenu Internet 3G | G24: CA31 | H24: =VLOOKUP(F24,PROD_CAMOBILE_2025M1!A:B,2,FALSE) -> 3391819301 | I24: 3929111582 | J24: =VLOOKUP(F24,'Formule TDB'!B:C,2,FALSE) -> -NM(706153,*,A55,*,*,*,*,*,*,*) -NM(706920,*,A60,*,*,*,*,*,*,*) | K24: -NM(706153,*,A55,*,*,*,*,*,*,*) -NM(706920,*,A60,*,*,*,*,*,*,*) | L24: =E24-H24 -> 0
B25: CRBT | C25: CA33 | D25: =VLOOKUP(C25,'Données MOOV 01-2025'!C:D,2,FALSE) -> 0.132797 | E25: =D25*1000000 -> 132797 | F25: CAM130-CRBT | G25: CA33 | H25: =VLOOKUP(F25,PROD_CAMOBILE_2025M1!A:B,2,FALSE) -> 132797 | I25: 565572 | J25: =VLOOKUP(F25,'Formule TDB'!B:C,2,FALSE) -> -NM(706151,*,A57,*,*,*,*,*,*,*) | K25: -NM(706151,*,A57,*,*,*,*,*,*,*) | L25: =E25-H25 -> 0
B26: Crédit secours | C26: CA34 | D26: =VLOOKUP(C26,'Données MOOV 01-2025'!C:D,2,FALSE) -> 7.7828593 | E26: =D26*1000000 -> 7782859.3 | F26: CAM135-Crédit secours | G26: CA34 | H26: =VLOOKUP(F26,PROD_CAMOBILE_2025M1!A:B,2,FALSE) -> 117373380 | I26: 121527054 | J26: =VLOOKUP(F26,'Formule TDB'!B:C,2,FALSE) -> -NM(706151,*,A56,*,*,*,*,*,*,*) | K26: -NM(706151,*,A56,*,*,*,*,*,*,*) | L26: =E26-H26 -> -1.0959052e+08 | M26: Fichiers externe, Cellule D4 de la feuille crédits secours | N26: Besoin du fichier crédit Secour + RG actualisées | O26: Le montant des crédits secours est déterminé dans un fichier annexe
B27: Story Box | C27: CA35 | D27: =VLOOKUP(C27,'Données MOOV 01-2025'!C:D,2,FALSE) -> 0 | E27: =D27*1000000 -> 0 | F27: CAM140-Story Box | G27: CA35 | H27: =VLOOKUP(F27,PROD_CAMOBILE_2025M1!A:B,2,FALSE) -> 0 | I27: 134390508 | J27: =VLOOKUP(F27,'Formule TDB'!B:C,2,FALSE) -> -0*NM(706151,*,*,*,*,*,*,*,*) | K27: -0*NM(706151,*,*,*,*,*,*,*,*) | L27: =E27-H27 -> 0
B28: Phonebook STK | C28: CA36 | D28: =VLOOKUP(C28,'Données MOOV 01-2025'!C:D,2,FALSE) -> 0 | E28: =D28*1000000 -> 0 | F28: CAM145-Phonebook STK | G28: CA36 | H28: =VLOOKUP(F28,PROD_CAMOBILE_2025M1!A:B,2,FALSE) -> 0 | I28: 0 | J28: =VLOOKUP(F28,'Formule TDB'!B:C,2,FALSE) -> #VALUE! | K28: #VALUE! | L28: =E28-H28 -> 0
B29: Gaming | C29: CA37 | D29: =VLOOKUP(C29,'Données MOOV 01-2025'!C:D,2,FALSE) -> 0 | E29: =D29*1000000 -> 0 | F29: CAM150-Gaming | G29: CA37 | H29: =VLOOKUP(F29,PROD_CAMOBILE_2025M1!A:B,2,FALSE) -> 0 | I29: 134390508 | J29: =VLOOKUP(F29,'Formule TDB'!B:C,2,FALSE) -> -0*NM(706151,*,*,*,*,*,*,*,*) | K29: -0*NM(706151,*,*,*,*,*,*,*,*) | L29: =E29-H29 -> 0
B30: Autres dont BAC17 (VOICEALERT,MOOVKDO...) & SAV agences | C30: CA38 | D30: =VLOOKUP(C30,'Données MOOV 01-2025'!C:D,2,FALSE) -> 109.72332 | E30: =D30*1000000 -> 1.0972332e+08 | F30: CAM155-Autres (VOICEALERT,MOOVKDO...) | G30: CA38 | H30: =VLOOKUP(F30,PROD_CAMOBILE_2025M1!A:B,2,FALSE) -> 0 | I30: 134390508 | J30: =VLOOKUP(F30,'Formule TDB'!B:C,2,FALSE) -> -0*NM(706151,*,*,*,*,*,*,*,*) | K30: -0*NM(706151,*,*,*,*,*,*,*,*) | L30: =E30-H30 -> 1.0972332e+08 | M30: -NM(706151,*,A56,*,*,*,*,*,*,*) oté du montant des crédits secours, ligne 26 | O30: Cette ligne "autre" comporte le total des lignes précédentes oté du montant des crédits secours
B31: Videos | C31: CA39 | D31: =VLOOKUP(C31,'Données MOOV 01-2025'!C:D,2,FALSE) -> 0 | E31: =D31*1000000 -> 0 | F31: CAM160-Videos | G31: CA39 | H31: =VLOOKUP(F31,PROD_CAMOBILE_2025M1!A:B,2,FALSE) -> 0 | I31: 134390508 | J31: =VLOOKUP(F31,'Formule TDB'!B:C,2,FALSE) -> -0*NM(706151,*,*,*,*,*,*,*,*) | K31: -0*NM(706151,*,*,*,*,*,*,*,*) | L31: =E31-H31 -> 0
B32: Total Data | C32: CA40 | D32: =VLOOKUP(C32,'Données MOOV 01-2025'!C:D,2,FALSE) -> 117.63897 | E32: =D32*1000000 -> 1.1763897e+08 | F32: CAM165-Total Data | G32: CA40 | H32: =VLOOKUP(F32,PROD_CAMOBILE_2025M1!A:B,2,FALSE) -> 117506177 | I32: 659654658 | J32: =VLOOKUP(F32,'Formule TDB'!B:C,2,FALSE) -> $CAMOBILE.#(L19:25) | K32: $CAMOBILE.#(L19:25) | L32: =E32-H32 -> 132797 | O32: Cet ecart doit etre corrigé
B33: dont CA voix | C33: CA42 | E33: =D33*1000000 -> 0 | G33: CA42 | H33: =VLOOKUP(F33,PROD_CAMOBILE_2025M1!A:B,2,FALSE) -> #N/A | J33: =VLOOKUP(F33,'Formule TDB'!B:C,2,FALSE) -> #N/A | K33: #N/A | L33: =E33-H33 -> #N/A
B34: dont CA SMS | C34: CA43 | E34: =D34*1000000 -> 0 | G34: CA43 | H34: =VLOOKUP(F34,PROD_CAMOBILE_2025M1!A:B,2,FALSE) -> #N/A | J34: =VLOOKUP(F34,'Formule TDB'!B:C,2,FALSE) -> #N/A | K34: #N/A | L34: =E34-H34 -> #N/A
B35: dont SVA (Sce à Val. Ajoutée) | C35: CA44 | D35: =VLOOKUP(C35,'Données MOOV 01-2025'!C:D,2,FALSE) -> 0 | E35: =D35*1000000 -> 0 | F35: CAM170-Dont CA SVA ( Sce à Val Ajoutéé) | G35: CA44 | H35: =VLOOKUP(F35,PROD_CAMOBILE_2025M1!A:B,2,FALSE) -> 0 | I35: 0 | J35: =VLOOKUP(F35,'Formule TDB'!B:C,2,FALSE) -> 0 | K35: 0 | L35: =E35-H35 -> 0
B36: dont CA Internet 3G | C36: CA45 | D36: =VLOOKUP(C36,'Données MOOV 01-2025'!C:D,2,FALSE) -> 3391.8193 | E36: =D36*1000000 -> 3391819301 | F36: CAM185-dont CA Internet 3G | G36: CA45 | H36: =VLOOKUP(F36,PROD_CAMOBILE_2025M1!A:B,2,FALSE) -> 3391819301 | I36: 3929111582 | J36: =VLOOKUP(F36,'Formule TDB'!B:C,2,FALSE) -> L18 | K36: L18 | L36: =E36-H36 -> 0
B37: Postpayé | C37: CA46 | D37: =VLOOKUP(C37,'Données MOOV 01-2025'!C:D,2,FALSE) -> 283.3024 | E37: =D37*1000000 -> 283302398 | F37: CAM447-Postpayé | G37: CA46 | H37: =VLOOKUP(F37,PROD_CAMOBILE_2025M1!A:B,2,FALSE) -> 279811823 | I37: 689925758 | J37: =VLOOKUP(F37,'Formule TDB'!B:C,2,FALSE) -> R(L34+L109) | K37: R(L34+L109) | L37: =E37-H37 -> 3490575 | O37: Ligne Total
B38: Redevance d'abonnement | C38: CA47 | D38: =VLOOKUP(C38,'Données MOOV 01-2025'!C:D,2,FALSE) -> 210.72997 | E38: =D38*1000000 -> 210729966 | F38: CAM195-Redevance d'abonnement | G38: CA47 | H38: =VLOOKUP(F38,PROD_CAMOBILE_2025M1!A:B,2,FALSE) -> 210729966 | I38: 201054859 | J38: =VLOOKUP(F38,'Formule TDB'!B:C,2,FALSE) -> R(L31+L32+L33) | K38: R(L31+L32+L33) | L38: =E38-H38 -> 0
A39: Consumer Postpaid | C39: CA48 | D39: =VLOOKUP(C39,'Données MOOV 01-2025'!C:D,2,FALSE) -> 10.744112 | E39: =D39*1000000 -> 10744112 | F39: CAM200-Red Consumer Postpaid | G39: CA48 | H39: =VLOOKUP(F39,PROD_CAMOBILE_2025M1!A:B,2,FALSE) -> 10744112 | I39: -10210921 | J39: =VLOOKUP(F39,'Formule TDB'!B:C,2,FALSE) -> -706115 NM(706115,*,A27,*,*,*,*,*,*,*) NM(706115,*,A29,*,*,*,*,*,*,*) NM(706115,*,W99,*,*,*,*,*,*,*) NM(706115,*,V99,*,*,*,*,*,*,*) NM(706115,*,U99,*,*,*,*,*,*,*) NM(706115,*,T15,*,*,*,*,*,*,*) NM(706115,*,S99,*,*,*,*,*,*,*) | K39: -706115 NM(706115,*,A27,*,*,*,*,*,*,*) NM(706115,*,A29,*,*,*,*,*,*,*) NM(706115,*,W99,*,*,*,*,*,*,*) NM(706115,*,V99,*,*,*,*,*,*,*) NM(706115,*,U99,*,*,*,*,*,*,*) NM(706115,*,T15,*,*,*,*,*,*,*) NM(706115,*,S99,*,*,*,*,*,*,*) | L39: =E39-H39 -> 0
A40: Business Postpaid | C40: CA49 | D40: =VLOOKUP(C40,'Données MOOV 01-2025'!C:D,2,FALSE) -> 14.508871 | E40: =D40*1000000 -> 14508871 | F40: CAM205-Red Business Postpaid | G40: CA49 | H40: =VLOOKUP(F40,PROD_CAMOBILE_2025M1!A:B,2,FALSE) -> 14508871 | I40: 20653505 | J40: =VLOOKUP(F40,'Formule TDB'!B:C,2,FALSE) -> -NM(706115,*,T15,*,*,*,*,*,*) | K40: -NM(706115,*,T15,*,*,*,*,*,*) | L40: =E40-H40 -> 0
A41: Business Prepaid | C41: CA50 | D41: =VLOOKUP(C41,'Données MOOV 01-2025'!C:D,2,FALSE) -> 185.47698 | E41: =D41*1000000 -> 185476983 | F41: CAM210-Red Business Prepaid | G41: CA50 | H41: =VLOOKUP(F41,PROD_CAMOBILE_2025M1!A:B,2,FALSE) -> 185476983 | I41: 190612275 | J41: =VLOOKUP(F41,'Formule TDB'!B:C,2,FALSE) -> -NM(706115,*,U99,*,*,*,*,*,*) | K41: -NM(706115,*,U99,*,*,*,*,*,*) | L41: =E41-H41 -> 0
B42: Trafic sortant | C42: CA51 | D42: =VLOOKUP(C42,'Données MOOV 01-2025'!C:D,2,FALSE) -> 72.572432 | E42: =D42*1000000 -> 72572432 | F42: CAM446-Trafic sortant | G42: CA51 | H42: =VLOOKUP(F42,PROD_CAMOBILE_2025M1!A:B,2,FALSE) -> 69081857 | I42: 488870899 | J42: =VLOOKUP(F42,'Formule TDB'!B:C,2,FALSE) -> R(L56+L78+L108) | K42: R(L56+L78+L108) | L42: =E42-H42 -> 3490575 | O42: Ligne Total
A43: Consumer Postpaid | C43: CA52 | D43: =VLOOKUP(C43,'Données MOOV 01-2025'!C:D,2,FALSE) -> 0.597171 | E43: =D43*1000000 -> 597171 | F43: CAM326-Consumer Postpaid | G43: CA52 | H43: =VLOOKUP(F43,PROD_CAMOBILE_2025M1!A:B,2,FALSE) -> 597171 | I43: 1745800 | J43: =VLOOKUP(F43,'Formule TDB'!B:C,2,FALSE) -> R(L43+L50+L55) | K43: R(L43+L50+L55) | L43: =E43-H43 -> 0
B44: Sortant voix on net | C44: CA53 | D44: =VLOOKUP(C44,'Données MOOV 01-2025'!C:D,2,FALSE) -> 0.150395 | E44: =D44*1000000 -> 150395 | F44: CAM225-Sortant voix on net | G44: CA53 | H44: =VLOOKUP(F44,PROD_CAMOBILE_2025M1!A:B,2,FALSE) -> 150395 | I44: 293624 | J44: =VLOOKUP(F44,'Formule TDB'!B:C,2,FALSE) -> -NM(706125,*,A61,*,*,*,*,*,*,*) -NM(706900,*,A58,*,*,*,*,*,*,*) -NM(706900,*,A59,*,*,*,*,*,*,*) | K44: -NM(706125,*,A61,*,*,*,*,*,*,*) -NM(706900,*,A58,*,*,*,*,*,*,*) -NM(706900,*,A59,*,*,*,*,*,*,*) | L44: =E44-H44 -> 0
B45: Sortant voix MTN | C45: CA54 | D45: =VLOOKUP(C45,'Données MOOV 01-2025'!C:D,2,FALSE) -> 0.314893 | E45: =D45*1000000 -> 314893 | F45: CAM230-Sortant voix MTN | G45: CA54 | H45: =VLOOKUP(F45,PROD_CAMOBILE_2025M1!A:B,2,FALSE) -> 314893 | I45: 588739 | J45: =VLOOKUP(F45,'Formule TDB'!B:C,2,FALSE) -> -NM(706126,*,A48,*,*,*,*,*,*) | K45: -NM(706126,*,A48,*,*,*,*,*,*) | L45: =E45-H45 -> 0
B46: Sortant voix GLO | C46: CA55 | D46: =VLOOKUP(C46,'Données MOOV 01-2025'!C:D,2,FALSE) -> 0 | E46: =D46*1000000 -> 0 | F46: CAM235-Sortant voix GLO | G46: CA55 | H46: =VLOOKUP(F46,PROD_CAMOBILE_2025M1!A:B,2,FALSE) -> 0 | I46: 0 | J46: =VLOOKUP(F46,'Formule TDB'!B:C,2,FALSE) -> -NM(706126,*,A49,*,*,*,*,*,*) | K46: -NM(706126,*,A49,*,*,*,*,*,*) | L46: =E46-H46 -> 0
B47: Sortant voix BBCOM | C47: CA56 | D47: =VLOOKUP(C47,'Données MOOV 01-2025'!C:D,2,FALSE) -> 0 | E47: =D47*1000000 -> 0 | F47: CAM240-Sortant voix BBCOM | G47: CA56 | H47: =VLOOKUP(F47,PROD_CAMOBILE_2025M1!A:B,2,FALSE) -> 0 | I47: 0 | J47: =VLOOKUP(F47,'Formule TDB'!B:C,2,FALSE) -> -NM(706126,*,A50,*,*,*,*,*,*) | K47: -NM(706126,*,A50,*,*,*,*,*,*) | L47: =E47-H47 -> 0
B48: Sortant voix LIBERCOM | C48: CA57 | D48: =VLOOKUP(C48,'Données MOOV 01-2025'!C:D,2,FALSE) -> 0.044706 | E48: =D48*1000000 -> 44706 | F48: CAM245-Sortant voix LIBERCOM | G48: CA57 | H48: =VLOOKUP(F48,PROD_CAMOBILE_2025M1!A:B,2,FALSE) -> 44706 | I48: 19446 | J48: =VLOOKUP(F48,'Formule TDB'!B:C,2,FALSE) -> -NM(706126,*,A51,*,*,*,*,*,*) | K48: -NM(706126,*,A51,*,*,*,*,*,*) | L48: =E48-H48 -> 0
B49: Sortant voix BTSA | C49: CA58 | D49: =VLOOKUP(C49,'Données MOOV 01-2025'!C:D,2,FALSE) -> -0.001938 | E49: =D49*1000000 -> -1938 | F49: CAM250-Sortant voix BTSA | G49: CA58 | H49: =VLOOKUP(F49,PROD_CAMOBILE_2025M1!A:B,2,FALSE) -> -1938 | I49: 3216 | J49: =VLOOKUP(F49,'Formule TDB'!B:C,2,FALSE) -> -NM(706128,*,A52,*,*,*,*,*,*) | K49: -NM(706128,*,A52,*,*,*,*,*,*) | L49: =E49-H49 -> 0
B50: Sortant voix INTERNATIONAL | C50: CA59 | D50: =VLOOKUP(C50,'Données MOOV 01-2025'!C:D,2,FALSE) -> 0.046205 | E50: =D50*1000000 -> 46205 | F50: CAM255-Sortant voix INTERNATIONAL | G50: CA59 | H50: =VLOOKUP(F50,PROD_CAMOBILE_2025M1!A:B,2,FALSE) -> 46205 | I50: 271662 | J50: =VLOOKUP(F50,'Formule TDB'!B:C,2,FALSE) -> -NM(706129,*,A53,*,*,*,*,*,*) | K50: -NM(706129,*,A53,*,*,*,*,*,*) | L50: =E50-H50 -> 0
B51: Sortant voix roaming | C51: CA60 | D51: =VLOOKUP(C51,'Données MOOV 01-2025'!C:D,2,FALSE) -> 0.024176 | E51: =D51*1000000 -> 24176 | F51: CAM260-Sortant voix roaming | G51: CA60 | H51: =VLOOKUP(F51,PROD_CAMOBILE_2025M1!A:B,2,FALSE) -> 24176 | I51: 375186 | J51: =VLOOKUP(F51,'Formule TDB'!B:C,2,FALSE) -> -NM(706141,*,A54,*,*,*,*,*,*) | K51: -NM(706141,*,A54,*,*,*,*,*,*) | L51: =E51-H51 -> 0
B52: Total VOIX Sortant | C52: CA61 | D52: =VLOOKUP(C52,'Données MOOV 01-2025'!C:D,2,FALSE) -> 0.578437 | E52: =D52*1000000 -> 578437 | F52: CAM265-Total VOIX Sortant | G52: CA61 | H52: =VLOOKUP(F52,PROD_CAMOBILE_2025M1!A:B,2,FALSE) -> 578437 | I52: 1551873 | J52: =VLOOKUP(F52,'Formule TDB'!B:C,2,FALSE) -> $CAMOBILE.#(L35:42) | K52: $CAMOBILE.#(L35:42) | L52: =E52-H52 -> 0
B53: Sortant sms on net | C53: CA63 | D53: =VLOOKUP(C53,'Données MOOV 01-2025'!C:D,2,FALSE) -> 0.018734 | E53: =D53*1000000 -> 18734 | F53: CAM270-Sortant sms on net | G53: CA63 | H53: =VLOOKUP(F53,PROD_CAMOBILE_2025M1!A:B,2,FALSE) -> 18734 | I53: 4107 | J53: =VLOOKUP(F53,'Formule TDB'!B:C,2,FALSE) -> -NM(706118,*,T21,*,*,*,*,*,*,*) | K53: -NM(706118,*,T21,*,*,*,*,*,*,*) | L53: =E53-H53 -> 0
B54: Sortant sms MTN | C54: CA64 | D54: =VLOOKUP(C54,'Données MOOV 01-2025'!C:D,2,FALSE) -> 0 | E54: =D54*1000000 -> 0 | F54: CAM275-Sortant sms MTN | G54: CA64 | H54: =VLOOKUP(F54,PROD_CAMOBILE_2025M1!A:B,2,FALSE) -> 0 | I54: 37964 | J54: =VLOOKUP(F54,'Formule TDB'!B:C,2,FALSE) -> -0*NM(706118,*,*,*,*,*,*,*,*) | K54: -0*NM(706118,*,*,*,*,*,*,*,*) | L54: =E54-H54 -> 0
B55: Sortant sms GLO | C55: CA65 | D55: =VLOOKUP(C55,'Données MOOV 01-2025'!C:D,2,FALSE) -> 0 | E55: =D55*1000000 -> 0 | F55: CAM280-Sortant sms GLO | G55: CA65 | H55: =VLOOKUP(F55,PROD_CAMOBILE_2025M1!A:B,2,FALSE) -> 0 | I55: 37964 | J55: =VLOOKUP(F55,'Formule TDB'!B:C,2,FALSE) -> -0*NM(706118,*,*,*,*,*,*,*,*) | K55: -0*NM(706118,*,*,*,*,*,*,*,*) | L55: =E55-H55 -> 0
... B62: Banking | C62: CA73 | D62: =VLOOKUP(C62,'Données MOOV 01-2025'!C:D,2,FALSE) -> 0 | E62: =D62*1000000 -> 0 | F62: CAM315-Banking | G62: CA73 | H62: =VLOOKUP(F62,PROD_CAMOBILE_2025M1!A:B,2,FALSE) -> 0 | I62: 0 | J62: =VLOOKUP(F62,'Formule TDB'!B:C,2,FALSE) -> -NM(706115,*,B99,*,*,*,*,*,*) -NM(706115,*,I99,*,*,*,*,*,*,*) | K62: -NM(706115,*,B99,*,*,*,*,*,*) -NM(706115,*,I99,*,*,*,*,*,*,*) | L62: =E62-H62 -> 0
B63: TPE | C63: CA74 | D63: =VLOOKUP(C63,'Données MOOV 01-2025'!C:D,2,FALSE) -> 0 | E63: =D63*1000000 -> 0 | F63: CAM320-Autres | G63: CA74 | H63: =VLOOKUP(F63,PROD_CAMOBILE_2025M1!A:B,2,FALSE) -> 0 | I63: 0 | J63: =VLOOKUP(F63,'Formule TDB'!B:C,2,FALSE) -> 0 | K63: 0 | L63: =E63-H63 -> 0
B64: Total Data | C64: CA75 | D64: =VLOOKUP(C64,'Données MOOV 01-2025'!C:D,2,FALSE) -> 0 | E64: =D64*1000000 -> 0 | F64: CAM325-Total Data | G64: CA75 | H64: =VLOOKUP(F64,PROD_CAMOBILE_2025M1!A:B,2,FALSE) -> 0 | I64: 0 | J64: =VLOOKUP(F64,'Formule TDB'!B:C,2,FALSE) -> $CAMOBILE.#(L52:54) | K64: $CAMOBILE.#(L52:54) | L64: =E64-H64 -> 0
A65: Business Postpaid | C65: CA77 | D65: =VLOOKUP(C65,'Données MOOV 01-2025'!C:D,2,FALSE) -> 35.107592 | E65: =D65*1000000 -> 35107592 | F65: CAM330-Business Postpaid | G65: CA77 | H65: =VLOOKUP(F65,PROD_CAMOBILE_2025M1!A:B,2,FALSE) -> 31617017 | I65: 30786748 | J65: =VLOOKUP(F65,'Formule TDB'!B:C,2,FALSE) -> R(L65+L72+L77) | K65: R(L65+L72+L77) | L65: =E65-H65 -> 3490575 | O65: Ligne Total
B66: Sortant voix on net | C66: CA78 | D66: =VLOOKUP(C66,'Données MOOV 01-2025'!C:D,2,FALSE) -> 2.479334 | E66: =D66*1000000 -> 2479334 | F66: CAM335-Sortant voix on net | G66: CA78 | H66: =VLOOKUP(F66,PROD_CAMOBILE_2025M1!A:B,2,FALSE) -> 2479334 | I66: 3180434 | J66: =VLOOKUP(F66,'Formule TDB'!B:C,2,FALSE) -> -NM(706125,*,A99,*,*,*,*,*,*) -NM(706900,*,A99,*,*,*,*,*,*) | K66: -NM(706125,*,A99,*,*,*,*,*,*) -NM(706900,*,A99,*,*,*,*,*,*) | L66: =E66-H66 -> 0
B67: Sortant voix MTN | C67: CA79 | D67: =VLOOKUP(C67,'Données MOOV 01-2025'!C:D,2,FALSE) -> 5.919833 | E67: =D67*1000000 -> 5919833 | F67: CAM340-Sortant voix MTN | G67: CA79 | H67: =VLOOKUP(F67,PROD_CAMOBILE_2025M1!A:B,2,FALSE) -> 5122948 | I67: 7071411 | J67: =VLOOKUP(F67,'Formule TDB'!B:C,2,FALSE) -> -NM(706126,*,A43,*,*,*,*,*,*) | K67: -NM(706126,*,A43,*,*,*,*,*,*) | L67: =E67-H67 -> 796885 | M67: Investigations en cours, possible écart résiduel ajusté | N67: Source externe à fournir pour traitement (Fichier de reclassement analytique) + RG actualisée | O67: Ce ecart provient d'écritures passées automatiquement avec code analytique non pris en compte par la règle de gestion. On observe donc cet écart par rapport à la BG
B68: Sortant voix GLO | C68: CA80 | D68: =VLOOKUP(C68,'Données MOOV 01-2025'!C:D,2,FALSE) -> 0 | E68: =D68*1000000 -> 0 | F68: CAM345-Sortant voix GLO | G68: CA80 | H68: =VLOOKUP(F68,PROD_CAMOBILE_2025M1!A:B,2,FALSE) -> 0 | I68: 0 | J68: =VLOOKUP(F68,'Formule TDB'!B:C,2,FALSE) -> 0 | K68: 0 | L68: =E68-H68 -> 0
B69: Sortant voix BBCOM | C69: CA81 | D69: =VLOOKUP(C69,'Données MOOV 01-2025'!C:D,2,FALSE) -> 0 | E69: =D69*1000000 -> 0 | F69: CAM355-Sortant voix BBCOM | G69: CA81 | H69: =VLOOKUP(F69,PROD_CAMOBILE_2025M1!A:B,2,FALSE) -> 0 | I69: 0 | J69: =VLOOKUP(F69,'Formule TDB'!B:C,2,FALSE) -> 0 | K69: 0 | L69: =E69-H69 -> 0
B70: Sortant voix LIBERCOM | C70: CA82 | D70: =VLOOKUP(C70,'Données MOOV 01-2025'!C:D,2,FALSE) -> 0 | E70: =D70*1000000 -> 0 | F70: CAM360-Sortant voix LIBERCOM | G70: CA82 | H70: =VLOOKUP(F70,PROD_CAMOBILE_2025M1!A:B,2,FALSE) -> 0 | I70: 0 | J70: =VLOOKUP(F70,'Formule TDB'!B:C,2,FALSE) -> 0 | K70: 0 | L70: =E70-H70 -> 0
B71: Sortant voix BTSA | C71: CA83 | D71: =VLOOKUP(C71,'Données MOOV 01-2025'!C:D,2,FALSE) -> 0.022573 | E71: =D71*1000000 -> 22573 | F71: CAM365-Sortant voix BTSA | G71: CA83 | H71: =VLOOKUP(F71,PROD_CAMOBILE_2025M1!A:B,2,FALSE) -> 22573 | I71: 32085 | J71: =VLOOKUP(F71,'Formule TDB'!B:C,2,FALSE) -> -NM(706128,*,A99,*,*,*,*,*,*) | K71: -NM(706128,*,A99,*,*,*,*,*,*) | L71: =E71-H71 -> 0
B72: Sortant voix INTERNATIONAL | C72: CA84 | D72: =VLOOKUP(C72,'Données MOOV 01-2025'!C:D,2,FALSE) -> 1.07568 | E72: =D72*1000000 -> 1075680 | F72: CAM370-Sortant voix INTERNATIONAL | G72: CA84 | H72: =VLOOKUP(F72,PROD_CAMOBILE_2025M1!A:B,2,FALSE) -> 1075680 | I72: 1401239 | J72: =VLOOKUP(F72,'Formule TDB'!B:C,2,FALSE) -> -NM(706129,*,A99,*,*,*,*,*,*,*) | K72: -NM(706129,*,A99,*,*,*,*,*,*,*) | L72: =E72-H72 -> 0
B73: Sortant voix roaming | C73: CA85 | D73: =VLOOKUP(C73,'Données MOOV 01-2025'!C:D,2,FALSE) -> 1.821352 | E73: =D73*1000000 -> 1821352 | F73: CAM375-Sortant voix roaming | G73: CA85 | H73: =VLOOKUP(F73,PROD_CAMOBILE_2025M1!A:B,2,FALSE) -> -872338 | I73: -236035 | J73: =VLOOKUP(F73,'Formule TDB'!B:C,2,FALSE) -> -NM(706141,*,A99,*,*,*,*,*,*) | K73: -NM(706141,*,A99,*,*,*,*,*,*) | L73: =E73-H73 -> 2693690 | M73: -NM(706141,*,A99,*,*,*,*,*,*) ajouter le montant en débit du compte 706141 | N73: Source externe à fournir pour traitement (Fichier de reclassement analytique Roaming) + RG actualisée (Custumer update Oracle DB) | O73: Ce ecart provient d'écritures passées automatiquement avec code analytique non pris en compte par la règle de gestion. On observe donc cet écart par rapport à la BG
B74: Total VOIX Sortant | C74: CA86 | D74: =VLOOKUP(C74,'Données MOOV 01-2025'!C:D,2,FALSE) -> 11.318772 | E74: =D74*1000000 -> 11318772 | F74: CAM380-Total VOIX Sortant | G74: CA86 | H74: =VLOOKUP(F74,PROD_CAMOBILE_2025M1!A:B,2,FALSE) -> 7828197 | I74: 11449134 | J74: =VLOOKUP(F74,'Formule TDB'!B:C,2,FALSE) -> $CAMOBILE.#(L57:64) | K74: $CAMOBILE.#(L57:64) | L74: =E74-H74 -> 3490575
B75: Sortant sms on net | C75: CA88 | D75: =VLOOKUP(C75,'Données MOOV 01-2025'!C:D,2,FALSE) -> 22.126457 | E75: =D75*1000000 -> 22126457 | F75: CAM385-Sortant sms on net | G75: CA88 | H75: =VLOOKUP(F75,PROD_CAMOBILE_2025M1!A:B,2,FALSE) -> 22126457 | I75: 18338001 | J75: =VLOOKUP(F75,'Formule TDB'!B:C,2,FALSE) -> -NM(706118,*,T20,*,*,*,*,*,*) -706152 | K75: -NM(706118,*,T20,*,*,*,*,*,*) -706152 | L75: =E75-H75 -> 0
B76: Sortant sms MTN | C76: CA89 | D76: =VLOOKUP(C76,'Données MOOV 01-2025'!C:D,2,FALSE) -> 0 | E76: =D76*1000000 -> 0 | F76: CAM390-Sortant sms MTN | G76: CA89 | H76: =VLOOKUP(F76,PROD_CAMOBILE_2025M1!A:B,2,FALSE) -> 0 | I76: 37964 | J76: =VLOOKUP(F76,'Formule TDB'!B:C,2,FALSE) -> -0*NM(706118,*,*,*,*,*,*,*,*) | K76: -0*NM(706118,*,*,*,*,*,*,*,*) | L76: =E76-H76 -> 0
B77: Sortant sms GLO | C77: CA90 | D77: =VLOOKUP(C77,'Données MOOV 01-2025'!C:D,2,FALSE) -> 0 | E77: =D77*1000000 -> 0 | F77: CAM395-Sortant sms GLO | G77: CA90 | H77: =VLOOKUP(F77,PROD_CAMOBILE_2025M1!A:B,2,FALSE) -> 0 | I77: 37964 | J77: =VLOOKUP(F77,'Formule TDB'!B:C,2,FALSE) -> -0*NM(706118,*,*,*,*,*,*,*,*) | K77: -0*NM(706118,*,*,*,*,*,*,*,*) | L77: =E77-H77 -> 0
B78: Sortant sms BBCOM | C78: CA91 | D78: =VLOOKUP(C78,'Données MOOV 01-2025'!C:D,2,FALSE) -> 0 | E78: =D78*1000000 -> 0 | F78: CAM400-Sortant sms BBCOM | G78: CA91 | H78: =VLOOKUP(F78,PROD_CAMOBILE_2025M1!A:B,2,FALSE) -> 0 | I78: 37964 | J78: =VLOOKUP(F78,'Formule TDB'!B:C,2,FALSE) -> -0*NM(706118,*,*,*,*,*,*,*,*) | K78: -0*NM(706118,*,*,*,*,*,*,*,*) | L78: =E78-H78 -> 0
B79: Sortant sms LIBERCOM | C79: CA92 | D79: =VLOOKUP(C79,'Données MOOV 01-2025'!C:D,2,FALSE) -> 0 | E79: =D79*1000000 -> 0 | F79: CAM405-Sortant sms LIBERCOM | G79: CA92 | H79: =VLOOKUP(F79,PROD_CAMOBILE_2025M1!A:B,2,FALSE) -> 0 | I79: 37964 | J79: =VLOOKUP(F79,'Formule TDB'!B:C,2,FALSE) -> -0*NM(706118,*,*,*,*,*,*,*,*) | K79: -0*NM(706118,*,*,*,*,*,*,*,*) | L79: =E79-H79 -> 0
B80: Sortant sms INTERNATIONAL | C80: CA93 | D80: =VLOOKUP(C80,'Données MOOV 01-2025'!C:D,2,FALSE) -> 0 | E80: =D80*1000000 -> 0 | F80: CAM410-Sortant sms INTERNATIONAL | G80: CA93 | H80: =VLOOKUP(F80,PROD_CAMOBILE_2025M1!A:B,2,FALSE) -> 0 | I80: 37964 | J80: =VLOOKUP(F80,'Formule TDB'!B:C,2,FALSE) -> -0*NM(706118,*,*,*,*,*,*,*,*) | K80: -0*NM(706118,*,*,*,*,*,*,*,*) | L80: =E80-H80 -> 0
B81: Total SMS Sortant | C81: CA94 | D81: =VLOOKUP(C81,'Données MOOV 01-2025'!C:D,2,FALSE) -> 22.126457 | E81: =D81*1000000 -> 22126457 | F81: CAM415-Total SMS Sortant | G81: CA94 | H81: =VLOOKUP(F81,PROD_CAMOBILE_2025M1!A:B,2,FALSE) -> 22126457 | I81: 18527821 | J81: =VLOOKUP(F81,'Formule TDB'!B:C,2,FALSE) -> $CAMOBILE.#(L66:71) | K81: $CAMOBILE.#(L66:71) | L81: =E81-H81 -> 0
B82: Revenu Internet 3G | C82: CA96 | D82: =VLOOKUP(C82,'Données MOOV 01-2025'!C:D,2,FALSE) -> 43.765311 | E82: =D82*1000000 -> 43765311 | F82: CAM420-Revenu Internet 3G | G82: CA96 | H82: =VLOOKUP(F82,PROD_CAMOBILE_2025M1!A:B,2,FALSE) -> 43765311 | I82: 9392304 | J82: =VLOOKUP(F82,'Formule TDB'!B:C,2,FALSE) -> -706154 | K82: -706154 | L82: =E82-H82 -> 0
B83: Transport and Automotive (Traking) | C83: CA97 | D83: =VLOOKUP(C83,'Données MOOV 01-2025'!C:D,2,FALSE) -> 0 | E83: =D83*1000000 -> 0 | F83: CAM425-Transport and Automotive | G83: CA97 | H83: =VLOOKUP(F83,PROD_CAMOBILE_2025M1!A:B,2,FALSE) -> 0 | I83: 0 | J83: =VLOOKUP(F83,'Formule TDB'!B:C,2,FALSE) -> 0 | K83: 0 | L83: =E83-H83 -> 0
B84: Banking | C84: CA98 | D84: =VLOOKUP(C84,'Données MOOV 01-2025'!C:D,2,FALSE) -> 1.662363 | E84: =D84*1000000 -> 1662363 | F84: CAM430-Banking | G84: CA98 | H84: =VLOOKUP(F84,PROD_CAMOBILE_2025M1!A:B,2,FALSE) -> 1662363 | I84: 809793 | J84: =VLOOKUP(F84,'Formule TDB'!B:C,2,FALSE) -> -NM(706115,*,A27,*,*,*,*,*,*) -NM(706115,*,A29,*,*,*,*,*,*) -NM(706115,*,A28,*,*,*,*,*,*,*) | K84: -NM(706115,*,A27,*,*,*,*,*,*) -NM(706115,*,A29,*,*,*,*,*,*) -NM(706115,*,A28,*,*,*,*,*,*,*) | L84: =E84-H84 -> 0
B85: TPE | C85: CA99 | D85: =VLOOKUP(C85,'Données MOOV 01-2025'!C:D,2,FALSE) -> 0 | E85: =D85*1000000 -> 0 | F85: CAM435-Autres | G85: CA99 | H85: =VLOOKUP(F85,PROD_CAMOBILE_2025M1!A:B,2,FALSE) -> 0 | I85: 0 | J85: =VLOOKUP(F85,'Formule TDB'!B:C,2,FALSE) -> 0 | K85: 0 | L85: =E85-H85 -> 0
B86: Total Data | C86: CA100 | D86: =VLOOKUP(C86,'Données MOOV 01-2025'!C:D,2,FALSE) -> 1.662363 | E86: =D86*1000000 -> 1662363 | F86: CAM440-Total Data | G86: CA100 | H86: =VLOOKUP(F86,PROD_CAMOBILE_2025M1!A:B,2,FALSE) -> 1662363 | I86: 809793 | J86: =VLOOKUP(F86,'Formule TDB'!B:C,2,FALSE) -> $CAMOBILE.#(L74:76) | K86: $CAMOBILE.#(L74:76) | L86: =E86-H86 -> 0
A87: Business Prepaid | C87: CA102 | D87: =VLOOKUP(C87,'Données MOOV 01-2025'!C:D,2,FALSE) -> 36.867669 | E87: =D87*1000000 -> 36867669 | F87: CAM445-Business Prepaid | G87: CA102 | H87: =VLOOKUP(F87,PROD_CAMOBILE_2025M1!A:B,2,FALSE) -> 36867669 | I87: 456338351 | J87: =VLOOKUP(F87,'Formule TDB'!B:C,2,FALSE) -> R(L87+L94+L104) | K87: R(L87+L94+L104) | L87: =E87-H87 -> 0
B88: Sortant voix on net | C88: CA103 | D88: =VLOOKUP(C88,'Données MOOV 01-2025'!C:D,2,FALSE) -> 8.2984466 | E88: =D88*1000000 -> 8298446.6 | F88: CAM450-Sortant voix on net | G88: CA103 | H88: =VLOOKUP(F88,PROD_CAMOBILE_2025M1!A:B,2,FALSE) -> -49158729 | I88: -29543050 | J88: =VLOOKUP(F88,'Formule TDB'!B:C,2,FALSE) -> -NM(706120,*,A99,*,*,*,*,*,*,*) -NM(706920,*,A17,*,*,*,*,*,*) | K88: -NM(706120,*,A99,*,*,*,*,*,*,*) -NM(706920,*,A17,*,*,*,*,*,*) | L88: =E88-H88 -> 57457176 | M88: NM(706120,*,A99,*,*,*,*,*,*,*) -NM(706920,*,A17,*,*,*,*,*,*)+ somme( CA Business D29:D34) | N88: Besoin de la source externe CA Business + RG actualisée | O88: Cet écart provient des retraitements manuels effectués sur les bonus( voir feuille CA Business Somme L6 à11) | P88: =SUM('CA Business'!D6:D11) -> 57457176
B89: Sortant voix MTN | C89: CA104 | D89: =VLOOKUP(C89,'Données MOOV 01-2025'!C:D,2,FALSE) -> 10.548947 | E89: =D89*1000000 -> 10548947 | F89: CAM455-Sortant voix MTN | G89: CA104 | H89: =VLOOKUP(F89,PROD_CAMOBILE_2025M1!A:B,2,FALSE) -> 66434200 | I89: 64041147 | J89: =VLOOKUP(F89,'Formule TDB'!B:C,2,FALSE) -> -NM(706121,*,A43,*,*,*,*,*,*) | K89: -NM(706121,*,A43,*,*,*,*,*,*) | L89: =E89-H89 -> -55885253 | M89: NM(706121,*,A43,*,*,*,*,*,*) - CA Business D29 | O89: Cet écart provient des retraitements manuels effectués sur les bonus( voir feuille CA Business L6) | P89: ='CA Business'!D6 -> 55885253
B90: Sortant voix GLO | C90: CA105 | D90: =VLOOKUP(C90,'Données MOOV 01-2025'!C:D,2,FALSE) -> 0 | E90: =D90*1000000 -> 0 | F90: CAM460-Sortant voix GLO | G90: CA105 | H90: =VLOOKUP(F90,PROD_CAMOBILE_2025M1!A:B,2,FALSE) -> 0 | I90: 0 | J90: =VLOOKUP(F90,'Formule TDB'!B:C,2,FALSE) -> 0 | K90: 0 | L90: =E90-H90 -> 0
B91: Sortant voix BBCOM | C91: CA106 | D91: =VLOOKUP(C91,'Données MOOV 01-2025'!C:D,2,FALSE) -> 0 | E91: =D91*1000000 -> 0 | F91: CAM465-Sortant voix BBCOM | G91: CA106 | H91: =VLOOKUP(F91,PROD_CAMOBILE_2025M1!A:B,2,FALSE) -> 0 | I91: 0 | J91: =VLOOKUP(F91,'Formule TDB'!B:C,2,FALSE) -> 0 | K91: 0 | L91: =E91-H91 -> 0
B92: Sortant voix LIBERCOM | C92: CA107 | D92: =VLOOKUP(C92,'Données MOOV 01-2025'!C:D,2,FALSE) -> 0 | E92: =D92*1000000 -> 0 | F92: CAM470-Sortant voix LIBERCOM | G92: CA107 | H92: =VLOOKUP(F92,PROD_CAMOBILE_2025M1!A:B,2,FALSE) -> 0 | I92: 0 | J92: =VLOOKUP(F92,'Formule TDB'!B:C,2,FALSE) -> 0 | K92: 0 | L92: =E92-H92 -> 0
B93: Sortant voix BTSA | C93: CA108 | D93: =VLOOKUP(C93,'Données MOOV 01-2025'!C:D,2,FALSE) -> 2.3791872 | E93: =D93*1000000 -> 2379187.2 | F93: CAM475-Sortant voix BTSA | G93: CA108 | H93: =VLOOKUP(F93,PROD_CAMOBILE_2025M1!A:B,2,FALSE) -> 2476508 | I93: 548142 | J93: =VLOOKUP(F93,'Formule TDB'!B:C,2,FALSE) -> -NM(706123,*,A99,*,*,*,*,*,*) | K93: -NM(706123,*,A99,*,*,*,*,*,*) | L93: =E93-H93 -> -97320.831 | M93: NM(706123,*,A52,*,*,*,*,*,*,*) - CA Business D33 | O93: Cet écart provient des retraitements manuels effectués sur les bonus( voir feuille CA Business L10) | P93: ='CA Business'!D10 -> 97320.831
B94: Sortant voix INTERNATIONAL | C94: CA109 | D94: =VLOOKUP(C94,'Données MOOV 01-2025'!C:D,2,FALSE) -> 1.5992774 | E94: =D94*1000000 -> 1599277.4 | F94: CAM480-Sortant voix INTERNATIONAL | G94: CA109 | H94: =VLOOKUP(F94,PROD_CAMOBILE_2025M1!A:B,2,FALSE) -> 3073879 | I94: 3700075 | J94: =VLOOKUP(F94,'Formule TDB'!B:C,2,FALSE) -> -NM(706124,*,A99,*,*,*,*,*,*) | K94: -NM(706124,*,A99,*,*,*,*,*,*) | L94: =E94-H94 -> -1474601.6 | M94: NM(706124,*,A53,*,*,*,*,*,*,*) - CA Business D34 | O94: Cet écart provient des retraitements manuels effectués sur les bonus( voir feuille CA Business L11) | P94: ='CA Business'!D11 -> 1474601.6
B95: Sortant voix roaming | C95: CA110 | D95: =VLOOKUP(C95,'Données MOOV 01-2025'!C:D,2,FALSE) -> 0.515021 | E95: =D95*1000000 -> 515021 | F95: CAM485-Sortant voix roaming | G95: CA110 | H95: =VLOOKUP(F95,PROD_CAMOBILE_2025M1!A:B,2,FALSE) -> 515021 | I95: 767775 | J95: =VLOOKUP(F95,'Formule TDB'!B:C,2,FALSE) -> -NM(706140,*,A99,*,*,*,*,*,*) | K95: -NM(706140,*,A99,*,*,*,*,*,*) | L95: =E95-H95 -> 0
B96: Total VOIX Sortant | C96: CA111 | D96: =VLOOKUP(C96,'Données MOOV 01-2025'!C:D,2,FALSE) -> 23.340879 | E96: =D96*1000000 -> 23340879 | F96: CAM490-Total VOIX Sortant | G96: CA111 | H96: =VLOOKUP(F96,PROD_CAMOBILE_2025M1!A:B,2,FALSE) -> 23340879 | I96: 39514089 | J96: =VLOOKUP(F96,'Formule TDB'!B:C,2,FALSE) -> $CAMOBILE.#(L79:86) | K96: $CAMOBILE.#(L79:86) | L96: =E96-H96 -> 0
B97: Sortant sms on net | C97: CA113 | D97: =VLOOKUP(C97,'Données MOOV 01-2025'!C:D,2,FALSE) -> -0.169497 | E97: =D97*1000000 -> -169497 | F97: CAM495-Sortant sms on net | G97: CA113 | H97: =VLOOKUP(F97,PROD_CAMOBILE_2025M1!A:B,2,FALSE) -> -169497 | I97: -127571 | J97: =VLOOKUP(F97,'Formule TDB'!B:C,2,FALSE) -> -NM(706117,*,T16,*,*,*,*,*,*,*) -NM(706920,*,A22,*,*,*,*,*,*,*) | K97: -NM(706117,*,T16,*,*,*,*,*,*,*) -NM(706920,*,A22,*,*,*,*,*,*,*) | L97: =E97-H97 -> 0
B98: Sortant sms MTN | C98: CA114 | D98: =VLOOKUP(C98,'Données MOOV 01-2025'!C:D,2,FALSE) -> 0.132518 | E98: =D98*1000000 -> 132518 | F98: CAM500-Sortant sms MTN | G98: CA114 | H98: =VLOOKUP(F98,PROD_CAMOBILE_2025M1!A:B,2,FALSE) -> 132518 | I98: 152766 | J98: =VLOOKUP(F98,'Formule TDB'!B:C,2,FALSE) -> -NM(706117,*,A43,*,*,*,*,*,*) | K98: -NM(706117,*,A43,*,*,*,*,*,*) | L98: =E98-H98 -> 0
B99: Sortant sms GLO | C99: CA115 | D99: =VLOOKUP(C99,'Données MOOV 01-2025'!C:D,2,FALSE) -> 0 | E99: =D99*1000000 -> 0 | F99: CAM505-Sortant sms GLO | G99: CA115 | H99: =VLOOKUP(F99,PROD_CAMOBILE_2025M1!A:B,2,FALSE) -> 0 | I99: 0 | J99: =VLOOKUP(F99,'Formule TDB'!B:C,2,FALSE) -> -NM(706117,*,A45,*,*,*,*,*,*) | K99: -NM(706117,*,A45,*,*,*,*,*,*) | L99: =E99-H99 -> 0
B100: Sortant sms BBCOM | C100: CA116 | D100: =VLOOKUP(C100,'Données MOOV 01-2025'!C:D,2,FALSE) -> 4.5e-05 | E100: =D100*1000000 -> 45 | F100: CAM510-Sortant sms BBCOM | G100: CA116 | H100: =VLOOKUP(F100,PROD_CAMOBILE_2025M1!A:B,2,FALSE) -> 45 | I100: 13 | J100: =VLOOKUP(F100,'Formule TDB'!B:C,2,FALSE) -> -NM(706117,*,A44,*,*,*,*,*,*) | K100: -NM(706117,*,A44,*,*,*,*,*,*) | L100: =E100-H100 -> 0
B101: Sortant sms LIBERCOM | C101: CA117 | D101: =VLOOKUP(C101,'Données MOOV 01-2025'!C:D,2,FALSE) -> 0.026471 | E101: =D101*1000000 -> 26471 | F101: CAM515-Sortant sms LIBERCOM | G101: CA117 | H101: =VLOOKUP(F101,PROD_CAMOBILE_2025M1!A:B,2,FALSE) -> 26471 | I101: 31857 | J101: =VLOOKUP(F101,'Formule TDB'!B:C,2,FALSE) -> -NM(706117,*,A42,*,*,*,*,*,*) | K101: -NM(706117,*,A42,*,*,*,*,*,*) | L101: =E101-H101 -> 0
B102: Sortant sms INTERNATIONAL | C102: CA118 | D102: =VLOOKUP(C102,'Données MOOV 01-2025'!C:D,2,FALSE) -> 0.10589 | E102: =D102*1000000 -> 105890 | F102: CAM520-Sortant sms INTERNATIONAL | G102: CA118 | H102: =VLOOKUP(F102,PROD_CAMOBILE_2025M1!A:B,2,FALSE) -> 105890 | I102: 111347 | J102: =VLOOKUP(F102,'Formule TDB'!B:C,2,FALSE) -> -NM(706117,*,T18,*,*,*,*,*,*) | K102: -NM(706117,*,T18,*,*,*,*,*,*) | L102: =E102-H102 -> 0
B103: Total SMS Sortant | C103: CA119 | D103: =VLOOKUP(C103,'Données MOOV 01-2025'!C:D,2,FALSE) -> 0.095427 | E103: =D103*1000000 -> 95427 | F103: CAM525-Total SMS Sortant | G103: CA119 | H103: =VLOOKUP(F103,PROD_CAMOBILE_2025M1!A:B,2,FALSE) -> 95427 | I103: 168412 | J103: =VLOOKUP(F103,'Formule TDB'!B:C,2,FALSE) -> $CAMOBILE.#(L88:93) | K103: $CAMOBILE.#(L88:93) | L103: =E103-H103 -> 0
B104: Revenu Internet 3G | C104: CA121 | D104: =VLOOKUP(C104,'Données MOOV 01-2025'!C:D,2,FALSE) -> 98.567353 | E104: =D104*1000000 -> 98567353 | F104: CAM530-Revenu Internet 3G | G104: CA121 | H104: =VLOOKUP(F104,PROD_CAMOBILE_2025M1!A:B,2,FALSE) -> 98567353 | I104: 101751932 | J104: =VLOOKUP(F104,'Formule TDB'!B:C,2,FALSE) -> -NM(706153,*,A99,*,*,*,*,*,*) -NM(706920,*,A25,*,*,*,*,*,*) | K104: -NM(706153,*,A99,*,*,*,*,*,*) -NM(706920,*,A25,*,*,*,*,*,*) | L104: =E104-H104 -> 0
B105: Transport and Automotive (Traking) | C105: CA122 | D105: =VLOOKUP(C105,'Données MOOV 01-2025'!C:D,2,FALSE) -> 0 | E105: =D105*1000000 -> 0 | F105: CAM535-Transport and Automotive | G105: CA122 | H105: =VLOOKUP(F105,PROD_CAMOBILE_2025M1!A:B,2,FALSE) -> 0 | I105: 0 | J105: =VLOOKUP(F105,'Formule TDB'!B:C,2,FALSE) -> -NM(706115,*,W99,*,*,*,*,*,*) | K105: -NM(706115,*,W99,*,*,*,*,*,*) | L105: =E105-H105 -> 0
B106: Banking | C106: CA123 | D106: =VLOOKUP(C106,'Données MOOV 01-2025'!C:D,2,FALSE) -> 1.519495 | E106: =D106*1000000 -> 1519495 | F106: CAM540-Banking (TPE) | G106: CA123 | H106: =VLOOKUP(F106,PROD_CAMOBILE_2025M1!A:B,2,FALSE) -> 1519495 | I106: 1186444 | J106: =VLOOKUP(F106,'Formule TDB'!B:C,2,FALSE) -> -NM(706115,*,V99,*,*,*,*,*,*) -NM(706115,*,S99,*,*,*,*,*,*) | K106: -NM(706115,*,V99,*,*,*,*,*,*) -NM(706115,*,S99,*,*,*,*,*,*) | L106: =E106-H106 -> 0
...

Sheet COMPTES
A1: COMPTES MOOV MONEY
A2: 706161 | B2: Revenu Moov Money Cash Out
A3: 706162 | B3: Revenu Moov Money P2P
A4: 706163 | B4: Revenu Moov Money Bank
A5: 706164 | B5: Revenu Moov Money internationa
A6: 706165 | B6: Revenu Moov Money Bill Paiemen
A10: ROAMING NATIONAL
A11: 706143 | B11: ROAMING NATIONAL VOIX
A12: 706144 | B12: ROAMING NATIONAL SMS
A13: 706145 | B13: ROAMING NATIONAL DATA
A17: ROAMING IN
A18: 706142 | B18: ROAMING VISITEURS
A19: 706143 | B19: ROAMING NATIONAL VOIX
A20: 706144 | B20: ROAMING NATIONAL SMS
A21: 706145 | B21: ROAMING NATIONAL DATA

Sheet CA Consumer
C1: CHIFFRE D'AFFAIRES CONSUMER AU 31 JANVIER 2025
C2: LIBELLE | D2: MONTANT EN HT | E2: COMPTES | F2: AXE 2
C3: Gratuités
C4: Consommation Etisalat staff Pré paid (HT) | D4: 0 | E4: 628110
C5: Bonus sur Voix on net | D5: 30324286 | E5: 701920 | F5: A17
C6: Bonus sur Voix off net national mtn | D6: 29291907
C7: Bonus sur Voix off net national glo
C8: Bonus sur Voix off net national bbcom | D8: 0
C9: Bonus sur Voix off net national libercom
C10: Bonus sur Voix off net national opt | D10: 8124.8475
C11: Bonus sur Voix off net international | D11: 272670.34
C12: Bonus sur SMS | D12: 59586.678 | E12: 701920 | F12: A22
C13: Bonus sur Data | D13: 1.491349e+09 | E13: 701920 | F13: A25
C14: Crédits donnés (Hors Cos Etisalat) | E14: 658200
C15: TOTAL CA PRE PAID (Hors Consommation Cos Etisalat et Crédits donnés...)

Sheet CA Business
C1: CHIFFRE D'AFFAIRES BUSINESS AU 31 JANVIER 2025
C2: LIBELLE | D2: MONTANT EN HT | E2: COMPTES | F2: AXE 2
C3: Gratuités
C4: Consommation Etisalat staff Pré paid (HT) | E4: 628110
C5: Bonus sur Voix on net | D5: 22818904 | E5: 701920 | F5: A17
C6: Bonus sur Voix off net national mtn | D6: 55885253
C7: Bonus sur Voix off net national glo
C8: Bonus sur Voix off net national bbcom
C9: Bonus sur Voix off net national libercom
C10: Bonus sur Voix off net national opt | D10: 97320.831
C11: Bonus sur Voix off net international | D11: 1474601.6
C12: Bonus sur SMS | D12: 215991.1 | E12: 701920 | F12: A22
C13: Bonus sur Data | D13: 63833113 | E13: 701920 | F13: A25
C14: Crédits donnés (Hors Cos Etisalat) | E14: 658200
C15: TOTAL CA PRE PAID (Hors Consommation Cos Etisalat et Crédits donnés...)
