Workbook
Name \e: #N/A
Name \M: #REF!
Name \M: #REF!
Name \M: #REF!
Name \M: #REF!
Name \M: #REF!
Name \p: '[1]Cur Q v Plan'!#REF!
Name \p: '[1]Cur Q v Plan'!#REF!
Name \p: '[1]Cur Q v Plan'!#REF!
Name \p: '[1]Cur Q v Plan'!#REF!
Name \p: '[1]Cur Q v Plan'!#REF!
Name \p: '[1]Cur Q v Plan'!#REF!
Name \p: '[1]Cur Q v Plan'!#REF!
Name \p: '[1]Cur Q v Plan'!#REF!
Name \p: '[1]Cur Q v Plan'!#REF!
Name \p: '[2]Cur Q v Plan'!#REF!
Name \p: '[1]Cur Q v Plan'!#REF!
Name \p: '[1]Cur Q v Plan'!#REF!
Name \p: '[1]Cur Q v Plan'!#REF!
Name \r: #N/A
Name \t: #N/A
Name _: #N/A
Name _???: #N/A
Name __???: #N/A
Name ___???: #N/A
Name ____???: #N/A
Name _____???: #N/A
Name ______???: #N/A
Name _______???: #N/A
Name ________???: #N/A
Name __________________________R: #REF!
Name __________________________R: #REF!
Name __________________________R: #REF!
Name __________________________R: #REF!
Name __________________________R: #REF!
Name __________________________R: #REF!
Name __________________________R: #REF!
Name __________________________R: #REF!
Name __________________________R: #REF!
Name __________________________R: #REF!
Name __________________________R: #REF!
Name __________________________R: #REF!
Name __________________________SC16: #REF!
Name __________________________SC16: #REF!
Name __________________________SC16: #REF!
Name __________________________SC16: #REF!
Name __________________________SC16: #REF!
Name __________________________SC16: #REF!
Name __________________________SC16: #REF!
Name __________________________SC16: #REF!
Name __________________________SC16: #REF!
Name __________________________SC16: #REF!
Name __________________________SC16: #REF!
Name __________________________SC16: #REF!
Name _________________________R: #REF!
Name _________________________R: #REF!
Name _________________________R: #REF!
Name _________________________R: #REF!
Name _________________________R: #REF!
Name _________________________R: #REF!

Sheet Cover
X13: Devise : | Y13: En millions de FCFA
E16: Package Stand Alone IFRS Etisalat Bénin | X16: Date d'ouverture : | Y16: 44562
E18: =+Y18 -> 44926 | X18: Date de clôture : | Y18: 44926
X20: Cellule saisissable
X21: Cellule non saisissable
X23: Produits | Y23: (+)
X24: Charges | Y24: (-)
X25: Amortissements des actifs | Y25: (-)
X26: Provisions pour dépréciation des actifs | Y26: (-)

Sheet Sommaire
B3: Sommaire
B5: Comptes sociaux - Normes OHADA | D5: Page | F5: Liens hypertextes
B6: Balance Générale | D6: 4 | F6: Balance Générale
B7: Bilan - Actif | D7: 5 | F7: Bilan - Actif
B8: Bilan - Passif | D8: 6 | F8: Bilan - Passif
B9: Compte de résultat | D9: 7 | F9: Compte de résultat
B11: Matrice de passage OHADA - Normes IFRS
B12: Passage Bilan - Actif | D12: 9 | F12: Passage Bilan - Actif
B13: Passage Bilan - Passif | D13: 10 | F13: Passage Bilan - Passif
B14: Passage Compte de résultat - par nature | D14: 11 | F14: Passage Compte de résultat - par nature
B15: Passage Compte de résultat - par fonction | D15: 12 | F15: Passage Compte de résultat - par fonction
B16: Bilan par flux | D16: 13 | F16: Bilan par flux
B18: Comptes IFRS
B19: Bilan simplifié | D19: 15 | F19: Bilan simplifié
B20: P&L - par nature | D20: 16 | F20: P&L par nature
B21: P&L - par fonction | D21: 17 | F21: P&L par fonction
B23: Notes annexes IFRS
B24: Actifs financiers non courants | D24: 19 | F24: Actifs financiers non courants
B25: Actifs financiers courants | D25: 20 | F25: Actifs financiers courants
B26: Fair value hierarchy | D26: 21 | F26: Fair value hierarchy
B27: Stocks | D27: 22 | F27: Stocks
B28: Cartes SIM | D28: 23 | F28: Cartes SIM
B29: Effectif | D29: 24 | F29: Effectif
A30: NEW | B30: Clients et comptes rattachés-Ageing | D30: 25 | F30: Clients et comptes rattachés - Ageing
A31: NEW | B31: Fournisseurs et comptes rattachés - Ageing | D31: 26 | F31: Fournisseurs et comptes rattachés - Ageing
A32: NEW | B32: Dettes sur acquisition d'immobilisations | D32: 27 | F32: Dettes sur acquisition d'immobilisations
B33: Synthèse FND | D33: 28 | F33: Synthèse FND
B34: Dettes financières à long terme | D34: 29 | F34: Dettes financières à long terme
B35: Dettes financières à court terme | D35: 30 | F35: Dettes financières à court terme
B36: Trésorerie et équivalent de trésorerie | D36: 31 | F36: Trésorerie et équivalent de trésorerie
B37: Risque de change | D37: 32 | F37: Risque de change
B38: Covenants | D38: 33 | F38: Covenants
B39: Nature des provisions-passif | D39: 34 | F39: Provision par nature
B40: Maturité des provisions-passif | D40: 35 | F40: Maturité des provisions - passif
B41: Taux effectif d'impôt | D41: 36 | F41: Taux effectif d'impôt
B42: Nature des impôts différés actifs et passifs | D42: 37 | F42: Nature des impôts différés actifs et passifs
B43: Dividendes | D43: 38 | F43: Dividendes
B44: Dettes SHL | D44: 39 | F44: Dettes SHL
... B51: PIDR | D51: 45 | F51: PIDR
B53: Contrôles de cohérence
B54: Equilibres comptables & Immobilisations | D54: 47 | F54: Contrôle des équilibres comptables et immobilisations
B55: Provisions | D55: 48 | F55: Contrôle des provisions
B56: Autres contrôles | D56: 49 | F56: Autres contrôles

Sheet <<Social>>
F16: Comptes sociaux OHADA

Sheet BG 
A1: Sommaire | F1: 1 | G1: -1 | H1: 1 | I1: -1 | J1: 1 | K1: -1
A2: Balance Générale | F2: Solde au 01/01/2021 | H2: MOUVEMENT2021 | J2: Solde au 31/06/21
A3: Nº Compte | B3: Libellé | C3: IFRS | D3: Classe | E3: A2 | F3: Débit 2021 | G3: Crédit 2021 | H3: Débit 2022 | I3: Crédit 2022 | J3: Débit 2022 | K3: Crédit 2022
A4: 101000 | B4: CAPITAL SOCIAL | C4: SN1131 | D4: =+LEFT(A4,2) -> 10 | F4: =(+IFERROR(VLOOKUP($A4,'[152]BG (2)'!$B$9:$J$570,4,FALSE),0))*1 -> 0 | G4: =(+IFERROR(VLOOKUP($A4,'[152]BG (2)'!$B$9:$J$570,5,FALSE),0))*-1 -> -10408280000 | H4: =(+IFERROR(VLOOKUP($A4,'[152]BG (2)'!$B$9:$J$570,6,FALSE),0))*1 -> 0 | I4: =(+IFERROR(VLOOKUP($A4,'[152]BG (2)'!$B$9:$J$570,7,FALSE),0))*-1 -> 0 | J4: =(+IFERROR(VLOOKUP($A4,'[152]BG (2)'!$B$9:$J$570,8,FALSE),0))*1 -> 0 | K4: =(+IFERROR(VLOOKUP($A4,'[152]BG (2)'!$B$9:$J$570,9,FALSE),0))*-1 -> -10408280000 | P4: =J4+K4 -> -10408280000 | T4: =K4+J4 -> -10408280000 | W4: =+A4-#REF! -> #REF!
A5: 101200 | B5: CAPITAL SOUSCRIT APPELE NON VE | D5: =+LEFT(A5,2) -> 10 | F5: =(+IFERROR(VLOOKUP($A5,'[152]BG (2)'!$B$9:$J$570,4,FALSE),0))*1 -> 0 | G5: =(+IFERROR(VLOOKUP($A5,'[152]BG (2)'!$B$9:$J$570,5,FALSE),0))*-1 -> 0 | H5: =(+IFERROR(VLOOKUP($A5,'[152]BG (2)'!$B$9:$J$570,6,FALSE),0))*1 -> 0 | I5: =(+IFERROR(VLOOKUP($A5,'[152]BG (2)'!$B$9:$J$570,7,FALSE),0))*-1 -> 0 | J5: =(+IFERROR(VLOOKUP($A5,'[152]BG (2)'!$B$9:$J$570,8,FALSE),0))*1 -> 0 | K5: =(+IFERROR(VLOOKUP($A5,'[152]BG (2)'!$B$9:$J$570,9,FALSE),0))*-1 -> 0 | P5: =J5+K5 -> 0 | T5: =K5+J5 -> 0 | W5: =+A5-#REF! -> #REF!
A6: 121000 | B6: REPORT A NOUVEAU CREDITEUR | C6: SN1131 | D6: =+LEFT(A6,2) -> 12 | F6: =(+IFERROR(VLOOKUP($A6,'[152]BG (2)'!$B$9:$J$570,4,FALSE),0))*1 -> 0 | G6: =(+IFERROR(VLOOKUP($A6,'[152]BG (2)'!$B$9:$J$570,5,FALSE),0))*-1 -> -11797647055 | H6: =(+IFERROR(VLOOKUP($A6,'[152]BG (2)'!$B$9:$J$570,6,FALSE),0))*1 -> 0 | I6: =(+IFERROR(VLOOKUP($A6,'[152]BG (2)'!$B$9:$J$570,7,FALSE),0))*-1 -> -4015179140 | J6: =(+IFERROR(VLOOKUP($A6,'[152]BG (2)'!$B$9:$J$570,8,FALSE),0))*1 -> 0 | K6: =(+IFERROR(VLOOKUP($A6,'[152]BG (2)'!$B$9:$J$570,9,FALSE),0))*-1 -> -15812826195 | P6: =J6+K6 -> -15812826195 | T6: =K6+J6 -> -15812826195 | W6: =+A6-#REF! -> #REF!
A7: 129000 | B7: REPORT A NOUVEAU DEBITEUR | C7: SN1131 | D7: =+LEFT(A7,2) -> 12 | F7: =(+IFERROR(VLOOKUP($A7,'[152]BG (2)'!$B$9:$J$570,4,FALSE),0))*1 -> 17260503796 | G7: =(+IFERROR(VLOOKUP($A7,'[152]BG (2)'!$B$9:$J$570,5,FALSE),0))*-1 -> 0 | H7: =(+IFERROR(VLOOKUP($A7,'[152]BG (2)'!$B$9:$J$570,6,FALSE),0))*1 -> 0 | I7: =(+IFERROR(VLOOKUP($A7,'[152]BG (2)'!$B$9:$J$570,7,FALSE),0))*-1 -> 0 | J7: =(+IFERROR(VLOOKUP($A7,'[152]BG (2)'!$B$9:$J$570,8,FALSE),0))*1 -> 17260503796 | K7: =(+IFERROR(VLOOKUP($A7,'[152]BG (2)'!$B$9:$J$570,9,FALSE),0))*-1 -> 0 | P7: =J7+K7 -> 17260503796 | T7: =K7+J7 -> 17260503796 | W7: =+A7-#REF! -> #REF!
A8: 130100 | B8: RESULTAT NET EN INSTANCE D'AFF | D8: =+LEFT(A8,2) -> 13 | F8: =(+IFERROR(VLOOKUP($A8,'[152]BG (2)'!$B$9:$J$570,4,FALSE),0))*1 -> 0 | G8: =(+IFERROR(VLOOKUP($A8,'[152]BG (2)'!$B$9:$J$570,5,FALSE),0))*-1 -> -219020909 | H8: =(+IFERROR(VLOOKUP($A8,'[152]BG (2)'!$B$9:$J$570,6,FALSE),0))*1 -> 0 | I8: =(+IFERROR(VLOOKUP($A8,'[152]BG (2)'!$B$9:$J$570,7,FALSE),0))*-1 -> 0 | J8: =(+IFERROR(VLOOKUP($A8,'[152]BG (2)'!$B$9:$J$570,8,FALSE),0))*1 -> 0 | K8: =(+IFERROR(VLOOKUP($A8,'[152]BG (2)'!$B$9:$J$570,9,FALSE),0))*-1 -> -219020909 | P8: =J8+K8 -> -219020909 | T8: =K8+J8 -> -219020909 | W8: =+A8-#REF! -> #REF!
A9: 130900 | B9: RESULTAT NET EN INSTANCE D'AFF | C9: SN1132 | D9: =+LEFT(A9,2) -> 13 | F9: =(+IFERROR(VLOOKUP($A9,'[152]BG (2)'!$B$9:$J$570,4,FALSE),0))*1 -> 0 | G9: =(+IFERROR(VLOOKUP($A9,'[152]BG (2)'!$B$9:$J$570,5,FALSE),0))*-1 -> 0 | H9: =(+IFERROR(VLOOKUP($A9,'[152]BG (2)'!$B$9:$J$570,6,FALSE),0))*1 -> 0 | I9: =(+IFERROR(VLOOKUP($A9,'[152]BG (2)'!$B$9:$J$570,7,FALSE),0))*-1 -> 0 | J9: =(+IFERROR(VLOOKUP($A9,'[152]BG (2)'!$B$9:$J$570,8,FALSE),0))*1 -> 0 | K9: =(+IFERROR(VLOOKUP($A9,'[152]BG (2)'!$B$9:$J$570,9,FALSE),0))*-1 -> 0 | P9: =J9+K9 -> 0 | T9: =K9+J9 -> 0 | W9: =+A9-#REF! -> #REF!
A10: 131000 | B10: RESULTAT NET : BENEFICE | D10: =+LEFT(A10,2) -> 13 | F10: =(+IFERROR(VLOOKUP($A10,'[152]BG (2)'!$B$9:$J$570,4,FALSE),0))*1 -> 0 | G10: =(+IFERROR(VLOOKUP($A10,'[152]BG (2)'!$B$9:$J$570,5,FALSE),0))*-1 -> -4015179140 | H10: =(+IFERROR(VLOOKUP($A10,'[152]BG (2)'!$B$9:$J$570,6,FALSE),0))*1 -> 4015179140 | I10: =(+IFERROR(VLOOKUP($A10,'[152]BG (2)'!$B$9:$J$570,7,FALSE),0))*-1 -> 0 | J10: =(+IFERROR(VLOOKUP($A10,'[152]BG (2)'!$B$9:$J$570,8,FALSE),0))*1 -> 0 | K10: =(+IFERROR(VLOOKUP($A10,'[152]BG (2)'!$B$9:$J$570,9,FALSE),0))*-1 -> 0 | P10: =J10+K10 -> 0 | T10: =K10+J10 -> 0 | W10: =+A10-#REF! -> #REF!
A11: 139000 | B11: RESULTAT NET : PERTE | D11: =+LEFT(A11,2) -> 13 | F11: =(+IFERROR(VLOOKUP($A11,'[152]BG (2)'!$B$9:$J$570,4,FALSE),0))*1 -> 0 | G11: =(+IFERROR(VLOOKUP($A11,'[152]BG (2)'!$B$9:$J$570,5,FALSE),0))*-1 -> 0 | H11: =(+IFERROR(VLOOKUP($A11,'[152]BG (2)'!$B$9:$J$570,6,FALSE),0))*1 -> 0 | I11: =(+IFERROR(VLOOKUP($A11,'[152]BG (2)'!$B$9:$J$570,7,FALSE),0))*-1 -> 0 | J11: =(+IFERROR(VLOOKUP($A11,'[152]BG (2)'!$B$9:$J$570,8,FALSE),0))*1 -> 0 | K11: =(+IFERROR(VLOOKUP($A11,'[152]BG (2)'!$B$9:$J$570,9,FALSE),0))*-1 -> 0 | P11: =J11+K11 -> 0 | T11: =K11+J11 -> 0 | W11: =+A11-#REF! -> #REF!
A12: 148000 | B12: SUBVENTION D'INVESTISSEMENT | D12: =+LEFT(A12,2) -> 14 | F12: =(+IFERROR(VLOOKUP($A12,'[152]BG (2)'!$B$9:$J$570,4,FALSE),0))*1 -> 0 | G12: =(+IFERROR(VLOOKUP($A12,'[152]BG (2)'!$B$9:$J$570,5,FALSE),0))*-1 -> 0 | H12: =(+IFERROR(VLOOKUP($A12,'[152]BG (2)'!$B$9:$J$570,6,FALSE),0))*1 -> 535112960 | I12: =(+IFERROR(VLOOKUP($A12,'[152]BG (2)'!$B$9:$J$570,7,FALSE),0))*-1 -> -1830627040 | J12: =(+IFERROR(VLOOKUP($A12,'[152]BG (2)'!$B$9:$J$570,8,FALSE),0))*1 -> 0 | K12: =(+IFERROR(VLOOKUP($A12,'[152]BG (2)'!$B$9:$J$570,9,FALSE),0))*-1 -> -1295514080 | P12: =J12+K12 -> -1295514080
A13: 161101 | B13: EMPRUNTS CAA | C13: PNC1606 | D13: =+LEFT(A13,2) -> 16 | F13: =(+IFERROR(VLOOKUP($A13,'[152]BG (2)'!$B$9:$J$570,4,FALSE),0))*1 -> 0 | G13: =(+IFERROR(VLOOKUP($A13,'[152]BG (2)'!$B$9:$J$570,5,FALSE),0))*-1 -> -564773615 | H13: =(+IFERROR(VLOOKUP($A13,'[152]BG (2)'!$B$9:$J$570,6,FALSE),0))*1 -> 188257874 | I13: =(+IFERROR(VLOOKUP($A13,'[152]BG (2)'!$B$9:$J$570,7,FALSE),0))*-1 -> 0 | J13: =(+IFERROR(VLOOKUP($A13,'[152]BG (2)'!$B$9:$J$570,8,FALSE),0))*1 -> 0 | K13: =(+IFERROR(VLOOKUP($A13,'[152]BG (2)'!$B$9:$J$570,9,FALSE),0))*-1 -> -376515741 | P13: =J13+K13 -> -376515741 | T13: =K13+J13 -> -376515741 | W13: =+A13-#REF! -> #REF!
A14: 162000 | B14: EMPRUNTS BANCAIRES | C14: PNC1602 | D14: =+LEFT(A14,2) -> 16 | F14: =(+IFERROR(VLOOKUP($A14,'[152]BG (2)'!$B$9:$J$570,4,FALSE),0))*1 -> 0 | G14: =(+IFERROR(VLOOKUP($A14,'[152]BG (2)'!$B$9:$J$570,5,FALSE),0))*-1 -> 0 | H14: =(+IFERROR(VLOOKUP($A14,'[152]BG (2)'!$B$9:$J$570,6,FALSE),0))*1 -> 0 | I14: =(+IFERROR(VLOOKUP($A14,'[152]BG (2)'!$B$9:$J$570,7,FALSE),0))*-1 -> 0 | J14: =(+IFERROR(VLOOKUP($A14,'[152]BG (2)'!$B$9:$J$570,8,FALSE),0))*1 -> 0 | K14: =(+IFERROR(VLOOKUP($A14,'[152]BG (2)'!$B$9:$J$570,9,FALSE),0))*-1 -> 0 | P14: =J14+K14 -> 0 | T14: =K14+J14 -> 0 | W14: =+A14-#REF! -> #REF!
A15: 162200 | B15: EMPRUNT GOLDEN FALCON INVESTIS | C15: PNC1603 | D15: =+LEFT(A15,2) -> 16 | F15: =(+IFERROR(VLOOKUP($A15,'[152]BG (2)'!$B$9:$J$570,4,FALSE),0))*1 -> 0 | G15: =(+IFERROR(VLOOKUP($A15,'[152]BG (2)'!$B$9:$J$570,5,FALSE),0))*-1 -> 0 | H15: =(+IFERROR(VLOOKUP($A15,'[152]BG (2)'!$B$9:$J$570,6,FALSE),0))*1 -> 0 | I15: =(+IFERROR(VLOOKUP($A15,'[152]BG (2)'!$B$9:$J$570,7,FALSE),0))*-1 -> 0 | J15: =(+IFERROR(VLOOKUP($A15,'[152]BG (2)'!$B$9:$J$570,8,FALSE),0))*1 -> 0 | K15: =(+IFERROR(VLOOKUP($A15,'[152]BG (2)'!$B$9:$J$570,9,FALSE),0))*-1 -> 0 | P15: =J15+K15 -> 0 | T15: =K15+J15 -> 0 | W15: =+A15-#REF! -> #REF!
A16: 162300 | B16: EMPRUNT CORIS BANK | C16: PNC1602 | D16: =+LEFT(A16,2) -> 16 | F16: =(+IFERROR(VLOOKUP($A16,'[152]BG (2)'!$B$9:$J$570,4,FALSE),0))*1 -> 0 | G16: =(+IFERROR(VLOOKUP($A16,'[152]BG (2)'!$B$9:$J$570,5,FALSE),0))*-1 -> -10771050910 | H16: =(+IFERROR(VLOOKUP($A16,'[152]BG (2)'!$B$9:$J$570,6,FALSE),0))*1 -> 3847116856 | I16: =(+IFERROR(VLOOKUP($A16,'[152]BG (2)'!$B$9:$J$570,7,FALSE),0))*-1 -> -921026219 | J16: =(+IFERROR(VLOOKUP($A16,'[152]BG (2)'!$B$9:$J$570,8,FALSE),0))*1 -> 0 | K16: =(+IFERROR(VLOOKUP($A16,'[152]BG (2)'!$B$9:$J$570,9,FALSE),0))*-1 -> -7844960273 | P16: =J16+K16 -> -7844960273 | U16: =K13+K15+K16 -> -8221476014 | V16: =G11+G14+G15 -> 0 | W16: =+A16-#REF! -> #REF!
A17: 162400 | B17: EMPRUNT BANK OF AFRICA (BOA) | C17: PNC1602 | D17: =+LEFT(A17,2) -> 16 | F17: =(+IFERROR(VLOOKUP($A17,'[152]BG (2)'!$B$9:$J$570,4,FALSE),0))*1 -> 0 | G17: =(+IFERROR(VLOOKUP($A17,'[152]BG (2)'!$B$9:$J$570,5,FALSE),0))*-1 -> -14830776943 | H17: =(+IFERROR(VLOOKUP($A17,'[152]BG (2)'!$B$9:$J$570,6,FALSE),0))*1 -> 2073985135 | I17: =(+IFERROR(VLOOKUP($A17,'[152]BG (2)'!$B$9:$J$570,7,FALSE),0))*-1 -> -5000000000 | J17: =(+IFERROR(VLOOKUP($A17,'[152]BG (2)'!$B$9:$J$570,8,FALSE),0))*1 -> 0 | K17: =(+IFERROR(VLOOKUP($A17,'[152]BG (2)'!$B$9:$J$570,9,FALSE),0))*-1 -> -17756791808 | P17: =J17+K17 -> -17756791808 | AC17: =4994500000/1000000 -> 4994.5
A18: 162500 | B18: EMPRUNT CBAO | C18: PNC1602 | D18: =+LEFT(A18,2) -> 16 | F18: =(+IFERROR(VLOOKUP($A18,'[152]BG (2)'!$B$9:$J$570,4,FALSE),0))*1 -> 0 | G18: =(+IFERROR(VLOOKUP($A18,'[152]BG (2)'!$B$9:$J$570,5,FALSE),0))*-1 -> -20000000000 | H18: =(+IFERROR(VLOOKUP($A18,'[152]BG (2)'!$B$9:$J$570,6,FALSE),0))*1 -> 2098417244 | I18: =(+IFERROR(VLOOKUP($A18,'[152]BG (2)'!$B$9:$J$570,7,FALSE),0))*-1 -> 0 | J18: =(+IFERROR(VLOOKUP($A18,'[152]BG (2)'!$B$9:$J$570,8,FALSE),0))*1 -> 0 | K18: =(+IFERROR(VLOOKUP($A18,'[152]BG (2)'!$B$9:$J$570,9,FALSE),0))*-1 -> -17901582756 | P18: =J18+K18 -> -17901582756
A19: 165200 | B19: AUTRES CAUTIONNEMENTS | C19: PC4736 /PNC1608 | D19: =+LEFT(A19,2) -> 16 | F19: =(+IFERROR(VLOOKUP($A19,'[152]BG (2)'!$B$9:$J$570,4,FALSE),0))*1 -> 0 | G19: =(+IFERROR(VLOOKUP($A19,'[152]BG (2)'!$B$9:$J$570,5,FALSE),0))*-1 -> -1297000 | H19: =(+IFERROR(VLOOKUP($A19,'[152]BG (2)'!$B$9:$J$570,6,FALSE),0))*1 -> 0 | I19: =(+IFERROR(VLOOKUP($A19,'[152]BG (2)'!$B$9:$J$570,7,FALSE),0))*-1 -> 0 | J19: =(+IFERROR(VLOOKUP($A19,'[152]BG (2)'!$B$9:$J$570,8,FALSE),0))*1 -> 0 | K19: =(+IFERROR(VLOOKUP($A19,'[152]BG (2)'!$B$9:$J$570,9,FALSE),0))*-1 -> -1297000 | P19: =J19+K19 -> -1297000 | T19: =K19+J19 -> -1297000 | W19: =+A19-#REF! -> #REF!
A20: 165210 | B20: CAUTIONS DISTRIBUTEURS & POSTP | C20: PC4736 /PNC1608 | D20: =+LEFT(A20,2) -> 16 | F20: =(+IFERROR(VLOOKUP($A20,'[152]BG (2)'!$B$9:$J$570,4,FALSE),0))*1 -> 0 | G20: =(+IFERROR(VLOOKUP($A20,'[152]BG (2)'!$B$9:$J$570,5,FALSE),0))*-1 -> -307748479 | H20: =(+IFERROR(VLOOKUP($A20,'[152]BG (2)'!$B$9:$J$570,6,FALSE),0))*1 -> 1260500 | I20: =(+IFERROR(VLOOKUP($A20,'[152]BG (2)'!$B$9:$J$570,7,FALSE),0))*-1 -> -20756200 | J20: =(+IFERROR(VLOOKUP($A20,'[152]BG (2)'!$B$9:$J$570,8,FALSE),0))*1 -> 0 | K20: =(+IFERROR(VLOOKUP($A20,'[152]BG (2)'!$B$9:$J$570,9,FALSE),0))*-1 -> -327244179 | P20: =J20+K20 -> -327244179 | T20: =K20+J20 -> -327244179 | U20: =K22+K21 -> -692693489 | V20: =G21+G20 -> -310493907 | W20: =+A20-#REF! -> #REF!
A21: 166101 | B21: INTERETS COURUS SUR EMPRUNTS S | C21: PC4716 | D21: =+LEFT(A21,2) -> 16 | F21: =(+IFERROR(VLOOKUP($A21,'[152]BG (2)'!$B$9:$J$570,4,FALSE),0))*1 -> 0 | G21: =(+IFERROR(VLOOKUP($A21,'[152]BG (2)'!$B$9:$J$570,5,FALSE),0))*-1 -> -2745428 | H21: =(+IFERROR(VLOOKUP($A21,'[152]BG (2)'!$B$9:$J$570,6,FALSE),0))*1 -> 0 | I21: =(+IFERROR(VLOOKUP($A21,'[152]BG (2)'!$B$9:$J$570,7,FALSE),0))*-1 -> 1961020 | J21: =(+IFERROR(VLOOKUP($A21,'[152]BG (2)'!$B$9:$J$570,8,FALSE),0))*1 -> 0 | K21: =(+IFERROR(VLOOKUP($A21,'[152]BG (2)'!$B$9:$J$570,9,FALSE),0))*-1 -> -784408 | P21: =J21+K21 -> -784408 | T21: =K21+J21 -> -784408 | W21: =+A21-#REF! -> #REF!
A22: 166200 | B22: INTERETS COURUS / EMPRUNTS BAN | C22: PC4722 | D22: =+LEFT(A22,2) -> 16 | F22: =(+IFERROR(VLOOKUP($A22,'[152]BG (2)'!$B$9:$J$570,4,FALSE),0))*1 -> 0 | G22: =(+IFERROR(VLOOKUP($A22,'[152]BG (2)'!$B$9:$J$570,5,FALSE),0))*-1 -> -907777903 | H22: =(+IFERROR(VLOOKUP($A22,'[152]BG (2)'!$B$9:$J$570,6,FALSE),0))*1 -> -265360986 | I22: =(+IFERROR(VLOOKUP($A22,'[152]BG (2)'!$B$9:$J$570,7,FALSE),0))*-1 -> 481229808 | J22: =(+IFERROR(VLOOKUP($A22,'[152]BG (2)'!$B$9:$J$570,8,FALSE),0))*1 -> 0 | K22: =(+IFERROR(VLOOKUP($A22,'[152]BG (2)'!$B$9:$J$570,9,FALSE),0))*-1 -> -691909081 | P22: =J22+K22 -> -691909081 | T22: =K22+J22 -> -691909081 | U22: -13665075378 | V22: -9204504573 | W22: =+A22-#REF! -> #REF!
A23: 166210 | B23: INTERETS COURUS EMPRUNTS AFREX | C23: PC4722 | D23: =+LEFT(A23,2) -> 16 | F23: =(+IFERROR(VLOOKUP($A23,'[152]BG (2)'!$B$9:$J$570,4,FALSE),0))*1 -> 0 | G23: =(+IFERROR(VLOOKUP($A23,'[152]BG (2)'!$B$9:$J$570,5,FALSE),0))*-1 -> -3 | H23: =(+IFERROR(VLOOKUP($A23,'[152]BG (2)'!$B$9:$J$570,6,FALSE),0))*1 -> 0 | I23: =(+IFERROR(VLOOKUP($A23,'[152]BG (2)'!$B$9:$J$570,7,FALSE),0))*-1 -> 0 | J23: =(+IFERROR(VLOOKUP($A23,'[152]BG (2)'!$B$9:$J$570,8,FALSE),0))*1 -> 0 | K23: =(+IFERROR(VLOOKUP($A23,'[152]BG (2)'!$B$9:$J$570,9,FALSE),0))*-1 -> -3 | P23: =J23+K23 -> -3 | T23: =K23+J23 -> -3 | W23: =+A23-#REF! -> #REF!
A24: 166220 | B24: INTERETS COURUS EMPRUNTS GOLDE | C24: PNC1603 | D24: =+LEFT(A24,2) -> 16 | F24: =(+IFERROR(VLOOKUP($A24,'[152]BG (2)'!$B$9:$J$570,4,FALSE),0))*1 -> 0 | G24: =(+IFERROR(VLOOKUP($A24,'[152]BG (2)'!$B$9:$J$570,5,FALSE),0))*-1 -> 0 | H24: =(+IFERROR(VLOOKUP($A24,'[152]BG (2)'!$B$9:$J$570,6,FALSE),0))*1 -> 0 | I24: =(+IFERROR(VLOOKUP($A24,'[152]BG (2)'!$B$9:$J$570,7,FALSE),0))*-1 -> 0 | J24: =(+IFERROR(VLOOKUP($A24,'[152]BG (2)'!$B$9:$J$570,8,FALSE),0))*1 -> 0 | K24: =(+IFERROR(VLOOKUP($A24,'[152]BG (2)'!$B$9:$J$570,9,FALSE),0))*-1 -> 0 | P24: =J24+K24 -> 0 | T24: =K24+J24 -> 0 | U24: =K24 -> 0 | V24: =G23 -> -3 | W24: =+A24-#REF! -> #REF!
A25: 196000 | B25: PROVISIONS POUR PENSIONS ET OB | C25: PNC1504/PC4504 | D25: =+LEFT(A25,2) -> 19 | F25: =(+IFERROR(VLOOKUP($A25,'[152]BG (2)'!$B$9:$J$570,4,FALSE),0))*1 -> 0 | G25: =(+IFERROR(VLOOKUP($A25,'[152]BG (2)'!$B$9:$J$570,5,FALSE),0))*-1 -> -75886080 | H25: =(+IFERROR(VLOOKUP($A25,'[152]BG (2)'!$B$9:$J$570,6,FALSE),0))*1 -> 0 | I25: =(+IFERROR(VLOOKUP($A25,'[152]BG (2)'!$B$9:$J$570,7,FALSE),0))*-1 -> 0 | J25: =(+IFERROR(VLOOKUP($A25,'[152]BG (2)'!$B$9:$J$570,8,FALSE),0))*1 -> 0 | K25: =(+IFERROR(VLOOKUP($A25,'[152]BG (2)'!$B$9:$J$570,9,FALSE),0))*-1 -> -75886080 | P25: =J25+K25 -> -75886080 | T25: =K25+J25 -> -75886080 | U25: =SUM(U16:U24) -> -22579244881 | W25: =+A25-#REF! -> #REF!
A26: 196100 | B26: PROVIS° PR PENSIONS ET OB | D26: =+LEFT(A26,2) -> 19 | F26: =(+IFERROR(VLOOKUP($A26,'[152]BG (2)'!$B$9:$J$570,4,FALSE),0))*1 -> 0 | G26: =(+IFERROR(VLOOKUP($A26,'[152]BG (2)'!$B$9:$J$570,5,FALSE),0))*-1 -> -560543234 | H26: =(+IFERROR(VLOOKUP($A26,'[152]BG (2)'!$B$9:$J$570,6,FALSE),0))*1 -> 69932047 | I26: =(+IFERROR(VLOOKUP($A26,'[152]BG (2)'!$B$9:$J$570,7,FALSE),0))*-1 -> -138375073 | J26: =(+IFERROR(VLOOKUP($A26,'[152]BG (2)'!$B$9:$J$570,8,FALSE),0))*1 -> 0 | K26: =(+IFERROR(VLOOKUP($A26,'[152]BG (2)'!$B$9:$J$570,9,FALSE),0))*-1 -> -628986260 | P26: =J26+K26 -> -628986260 | T26: =K26+J26 -> -628986260 | U26: =SUM(U16:U22) -> -22579244881 | W26: =+A26-#REF! -> #REF!
A27: 198000 | B27: AUTRES PROVISIONS FINANCIERES | C27: PNC1501/PC4501 | D27: =+LEFT(A27,2) -> 19 | F27: =(+IFERROR(VLOOKUP($A27,'[152]BG (2)'!$B$9:$J$570,4,FALSE),0))*1 -> 0 | G27: =(+IFERROR(VLOOKUP($A27,'[152]BG (2)'!$B$9:$J$570,5,FALSE),0))*-1 -> -315691792 | H27: =(+IFERROR(VLOOKUP($A27,'[152]BG (2)'!$B$9:$J$570,6,FALSE),0))*1 -> 60096576 | I27: =(+IFERROR(VLOOKUP($A27,'[152]BG (2)'!$B$9:$J$570,7,FALSE),0))*-1 -> -113600 | J27: =(+IFERROR(VLOOKUP($A27,'[152]BG (2)'!$B$9:$J$570,8,FALSE),0))*1 -> 0 | K27: =(+IFERROR(VLOOKUP($A27,'[152]BG (2)'!$B$9:$J$570,9,FALSE),0))*-1 -> -255708816 | P27: =J27+K27 -> -255708816 | T27: =K27+J27 -> -255708816 | W27: =+A27-#REF! -> #REF!
A28: 198800 | B28: PROVISIONS POUR RISQUES | D28: =+LEFT(A28,2) -> 19 | F28: =(+IFERROR(VLOOKUP($A28,'[152]BG (2)'!$B$9:$J$570,4,FALSE),0))*1 -> 0 | G28: =(+IFERROR(VLOOKUP($A28,'[152]BG (2)'!$B$9:$J$570,5,FALSE),0))*-1 -> -158666718 | H28: =(+IFERROR(VLOOKUP($A28,'[152]BG (2)'!$B$9:$J$570,6,FALSE),0))*1 -> 0 | I28: =(+IFERROR(VLOOKUP($A28,'[152]BG (2)'!$B$9:$J$570,7,FALSE),0))*-1 -> 0 | J28: =(+IFERROR(VLOOKUP($A28,'[152]BG (2)'!$B$9:$J$570,8,FALSE),0))*1 -> 0 | K28: =(+IFERROR(VLOOKUP($A28,'[152]BG (2)'!$B$9:$J$570,9,FALSE),0))*-1 -> -158666718 | P28: =J28+K28 -> -158666718 | T28: =K28+J28 -> -158666718 | W28: =+A28-#REF! -> #REF!
A29: 202800 | B29: CHARGES A ETALER | C29: Annuler en IFRS | D29: =+LEFT(A29,2) -> 20 | F29: =(+IFERROR(VLOOKUP($A29,'[152]BG (2)'!$B$9:$J$570,4,FALSE),0))*1 -> 0 | G29: =(+IFERROR(VLOOKUP($A29,'[152]BG (2)'!$B$9:$J$570,5,FALSE),0))*-1 -> 0 | H29: =(+IFERROR(VLOOKUP($A29,'[152]BG (2)'!$B$9:$J$570,6,FALSE),0))*1 -> 0 | I29: =(+IFERROR(VLOOKUP($A29,'[152]BG (2)'!$B$9:$J$570,7,FALSE),0))*-1 -> 0 | J29: =(+IFERROR(VLOOKUP($A29,'[152]BG (2)'!$B$9:$J$570,8,FALSE),0))*1 -> 0 | K29: =(+IFERROR(VLOOKUP($A29,'[152]BG (2)'!$B$9:$J$570,9,FALSE),0))*-1 -> 0 | P29: =J29+K29 -> 0 | T29: =K29+J29 -> 0 | W29: =+A29-#REF! -> #REF!
A30: 212100 | B30: LICENCES GSM | C30: ANC2240 | D30: =+LEFT(A30,2) -> 21 | F30: =(+IFERROR(VLOOKUP($A30,'[152]BG (2)'!$B$9:$J$570,4,FALSE),0))*1 -> 80000000000 | G30: =(+IFERROR(VLOOKUP($A30,'[152]BG (2)'!$B$9:$J$570,5,FALSE),0))*-1 -> 0 | H30: =(+IFERROR(VLOOKUP($A30,'[152]BG (2)'!$B$9:$J$570,6,FALSE),0))*1 -> 0 | I30: =(+IFERROR(VLOOKUP($A30,'[152]BG (2)'!$B$9:$J$570,7,FALSE),0))*-1 -> 0 | J30: =(+IFERROR(VLOOKUP($A30,'[152]BG (2)'!$B$9:$J$570,8,FALSE),0))*1 -> 80000000000 | K30: =(+IFERROR(VLOOKUP($A30,'[152]BG (2)'!$B$9:$J$570,9,FALSE),0))*-1 -> 0 | P30: =J30+K30 -> 80000000000 | T30: =K30+J30 -> 80000000000 | W30: =+A30-#REF! -> #REF!
A31: 212200 | B31: AUTRES LICENCES ET BREVETS | C31: ANC2221 | D31: =+LEFT(A31,2) -> 21 | F31: =(+IFERROR(VLOOKUP($A31,'[152]BG (2)'!$B$9:$J$570,4,FALSE),0))*1 -> 5886438394 | G31: =(+IFERROR(VLOOKUP($A31,'[152]BG (2)'!$B$9:$J$570,5,FALSE),0))*-1 -> 0 | H31: =(+IFERROR(VLOOKUP($A31,'[152]BG (2)'!$B$9:$J$570,6,FALSE),0))*1 -> 486590555 | I31: =(+IFERROR(VLOOKUP($A31,'[152]BG (2)'!$B$9:$J$570,7,FALSE),0))*-1 -> 0 | J31: =(+IFERROR(VLOOKUP($A31,'[152]BG (2)'!$B$9:$J$570,8,FALSE),0))*1 -> 6373028949 | K31: =(+IFERROR(VLOOKUP($A31,'[152]BG (2)'!$B$9:$J$570,9,FALSE),0))*-1 -> 0 | P31: =J31+K31 -> 6373028949 | T31: =K31+J31 -> 6373028949 | W31: =+A31-#REF! -> #REF!
A32: 213100 | B32: LOGICIELS D'EXPLOITATION TECHN | C32: ANC2222 | D32: =+LEFT(A32,2) -> 21 | F32: =(+IFERROR(VLOOKUP($A32,'[152]BG (2)'!$B$9:$J$570,4,FALSE),0))*1 -> 48010968840 | G32: =(+IFERROR(VLOOKUP($A32,'[152]BG (2)'!$B$9:$J$570,5,FALSE),0))*-1 -> 0 | H32: =(+IFERROR(VLOOKUP($A32,'[152]BG (2)'!$B$9:$J$570,6,FALSE),0))*1 -> 8357348451 | I32: =(+IFERROR(VLOOKUP($A32,'[152]BG (2)'!$B$9:$J$570,7,FALSE),0))*-1 -> 0 | J32: =(+IFERROR(VLOOKUP($A32,'[152]BG (2)'!$B$9:$J$570,8,FALSE),0))*1 -> 56368317291 | K32: =(+IFERROR(VLOOKUP($A32,'[152]BG (2)'!$B$9:$J$570,9,FALSE),0))*-1 -> 0 | P32: =J32+K32 -> 56368317291 | T32: =K32+J32 -> 56368317291 | W32: =+A32-#REF! -> #REF!
A33: 213200 | B33: LOGICIELS AUTRES APPLICATIONS | C33: ANC2222 | D33: =+LEFT(A33,2) -> 21 | F33: =(+IFERROR(VLOOKUP($A33,'[152]BG (2)'!$B$9:$J$570,4,FALSE),0))*1 -> 2155081147 | G33: =(+IFERROR(VLOOKUP($A33,'[152]BG (2)'!$B$9:$J$570,5,FALSE),0))*-1 -> 0 | H33: =(+IFERROR(VLOOKUP($A33,'[152]BG (2)'!$B$9:$J$570,6,FALSE),0))*1 -> 0 | I33: =(+IFERROR(VLOOKUP($A33,'[152]BG (2)'!$B$9:$J$570,7,FALSE),0))*-1 -> 0 | J33: =(+IFERROR(VLOOKUP($A33,'[152]BG (2)'!$B$9:$J$570,8,FALSE),0))*1 -> 2155081147 | K33: =(+IFERROR(VLOOKUP($A33,'[152]BG (2)'!$B$9:$J$570,9,FALSE),0))*-1 -> 0 | P33: =J33+K33 -> 2155081147 | T33: =K33+J33 -> 2155081147 | W33: =+A33-#REF! -> #REF!
A34: 219300 | B34: IMOB INCORP EN COURS / LOGICIE | C34: ANC2222 | D34: =+LEFT(A34,2) -> 21 | F34: =(+IFERROR(VLOOKUP($A34,'[152]BG (2)'!$B$9:$J$570,4,FALSE),0))*1 -> 5581261628 | G34: =(+IFERROR(VLOOKUP($A34,'[152]BG (2)'!$B$9:$J$570,5,FALSE),0))*-1 -> 0 | H34: =(+IFERROR(VLOOKUP($A34,'[152]BG (2)'!$B$9:$J$570,6,FALSE),0))*1 -> -476193229 | I34: =(+IFERROR(VLOOKUP($A34,'[152]BG (2)'!$B$9:$J$570,7,FALSE),0))*-1 -> -3481322210 | J34: =(+IFERROR(VLOOKUP($A34,'[152]BG (2)'!$B$9:$J$570,8,FALSE),0))*1 -> 1623746189 | K34: =(+IFERROR(VLOOKUP($A34,'[152]BG (2)'!$B$9:$J$570,9,FALSE),0))*-1 -> 0 | P34: =J34+K34 -> 1623746189 | T34: =K34+J34 -> 1623746189 | W34: =+A34-#REF! -> #REF!
A35: 223100 | B35: TERRAINS POUR SITES | C35: ANC2310 | D35: =+LEFT(A35,2) -> 22 | F35: =(+IFERROR(VLOOKUP($A35,'[152]BG (2)'!$B$9:$J$570,4,FALSE),0))*1 -> 1197014492 | G35: =(+IFERROR(VLOOKUP($A35,'[152]BG (2)'!$B$9:$J$570,5,FALSE),0))*-1 -> 0 | H35: =(+IFERROR(VLOOKUP($A35,'[152]BG (2)'!$B$9:$J$570,6,FALSE),0))*1 -> 34230581 | I35: =(+IFERROR(VLOOKUP($A35,'[152]BG (2)'!$B$9:$J$570,7,FALSE),0))*-1 -> 0 | J35: =(+IFERROR(VLOOKUP($A35,'[152]BG (2)'!$B$9:$J$570,8,FALSE),0))*1 -> 1231245073 | K35: =(+IFERROR(VLOOKUP($A35,'[152]BG (2)'!$B$9:$J$570,9,FALSE),0))*-1 -> 0 | P35: =J35+K35 -> 1231245073 | T35: =K35+J35 -> 1231245073 | W35: =+A35-#REF! -> #REF!
A36: 223800 | B36: AUTRES TERRAINS BATIS | C36: ANC2310 | D36: =+LEFT(A36,2) -> 22 | F36: =(+IFERROR(VLOOKUP($A36,'[152]BG (2)'!$B$9:$J$570,4,FALSE),0))*1 -> 70000000 | G36: =(+IFERROR(VLOOKUP($A36,'[152]BG (2)'!$B$9:$J$570,5,FALSE),0))*-1 -> 0 | H36: =(+IFERROR(VLOOKUP($A36,'[152]BG (2)'!$B$9:$J$570,6,FALSE),0))*1 -> 0 | I36: =(+IFERROR(VLOOKUP($A36,'[152]BG (2)'!$B$9:$J$570,7,FALSE),0))*-1 -> 0 | J36: =(+IFERROR(VLOOKUP($A36,'[152]BG (2)'!$B$9:$J$570,8,FALSE),0))*1 -> 70000000 | K36: =(+IFERROR(VLOOKUP($A36,'[152]BG (2)'!$B$9:$J$570,9,FALSE),0))*-1 -> 0 | P36: =J36+K36 -> 70000000 | T36: =K36+J36 -> 70000000 | W36: =+A36-#REF! -> #REF!
A37: 229700 | B37: TERRAINS EN COURS D'ACQUISITIO | C37: ANC2310 | D37: =+LEFT(A37,2) -> 22 | F37: =(+IFERROR(VLOOKUP($A37,'[152]BG (2)'!$B$9:$J$570,4,FALSE),0))*1 -> 1724788256 | G37: =(+IFERROR(VLOOKUP($A37,'[152]BG (2)'!$B$9:$J$570,5,FALSE),0))*-1 -> 0 | H37: =(+IFERROR(VLOOKUP($A37,'[152]BG (2)'!$B$9:$J$570,6,FALSE),0))*1 -> 174765000 | I37: =(+IFERROR(VLOOKUP($A37,'[152]BG (2)'!$B$9:$J$570,7,FALSE),0))*-1 -> -30706000 | J37: =(+IFERROR(VLOOKUP($A37,'[152]BG (2)'!$B$9:$J$570,8,FALSE),0))*1 -> 1868847256 | K37: =(+IFERROR(VLOOKUP($A37,'[152]BG (2)'!$B$9:$J$570,9,FALSE),0))*-1 -> 0 | P37: =J37+K37 -> 1868847256 | T37: =K37+J37 -> 1868847256 | W37: =+A37-#REF! -> #REF!
A38: 231100 | B38: BATIMENTS INDUSTRIELS | C38: ANC2320 | D38: =+LEFT(A38,2) -> 23 | F38: =(+IFERROR(VLOOKUP($A38,'[152]BG (2)'!$B$9:$J$570,4,FALSE),0))*1 -> 432753199 | G38: =(+IFERROR(VLOOKUP($A38,'[152]BG (2)'!$B$9:$J$570,5,FALSE),0))*-1 -> 0 | H38: =(+IFERROR(VLOOKUP($A38,'[152]BG (2)'!$B$9:$J$570,6,FALSE),0))*1 -> 0 | I38: =(+IFERROR(VLOOKUP($A38,'[152]BG (2)'!$B$9:$J$570,7,FALSE),0))*-1 -> 0 | J38: =(+IFERROR(VLOOKUP($A38,'[152]BG (2)'!$B$9:$J$570,8,FALSE),0))*1 -> 432753199 | K38: =(+IFERROR(VLOOKUP($A38,'[152]BG (2)'!$B$9:$J$570,9,FALSE),0))*-1 -> 0 | P38: =J38+K38 -> 432753199
A39: 234110 | B39: INFRASTRUCTURES | C39: ANC2330 | D39: =+LEFT(A39,2) -> 23 | F39: =(+IFERROR(VLOOKUP($A39,'[152]BG (2)'!$B$9:$J$570,4,FALSE),0))*1 -> 23553998802 | G39: =(+IFERROR(VLOOKUP($A39,'[152]BG (2)'!$B$9:$J$570,5,FALSE),0))*-1 -> 0 | H39: =(+IFERROR(VLOOKUP($A39,'[152]BG (2)'!$B$9:$J$570,6,FALSE),0))*1 -> 2557864678 | I39: =(+IFERROR(VLOOKUP($A39,'[152]BG (2)'!$B$9:$J$570,7,FALSE),0))*-1 -> 0 | J39: =(+IFERROR(VLOOKUP($A39,'[152]BG (2)'!$B$9:$J$570,8,FALSE),0))*1 -> 26111863480 | K39: =(+IFERROR(VLOOKUP($A39,'[152]BG (2)'!$B$9:$J$570,9,FALSE),0))*-1 -> 0 | P39: =J39+K39 -> 26111863480 | T39: =K39+J39 -> 26111863480 | W39: =+A39-#REF! -> #REF!
A40: 234120 | B40: AMENAGEMENT TECHNIQUE | C40: ANC2330 | D40: =+LEFT(A40,2) -> 23 | F40: =(+IFERROR(VLOOKUP($A40,'[152]BG (2)'!$B$9:$J$570,4,FALSE),0))*1 -> 13060093890 | G40: =(+IFERROR(VLOOKUP($A40,'[152]BG (2)'!$B$9:$J$570,5,FALSE),0))*-1 -> 0 | H40: =(+IFERROR(VLOOKUP($A40,'[152]BG (2)'!$B$9:$J$570,6,FALSE),0))*1 -> 300832814 | I40: =(+IFERROR(VLOOKUP($A40,'[152]BG (2)'!$B$9:$J$570,7,FALSE),0))*-1 -> 0 | J40: =(+IFERROR(VLOOKUP($A40,'[152]BG (2)'!$B$9:$J$570,8,FALSE),0))*1 -> 13360926704 | K40: =(+IFERROR(VLOOKUP($A40,'[152]BG (2)'!$B$9:$J$570,9,FALSE),0))*-1 -> 0 | P40: =J40+K40 -> 13360926704 | T40: =K40+J40 -> 13360926704 | W40: =+A40-#REF! -> #REF!
A41: 234130 | B41: EQUIPEMENTS D'ENERGIE | C41: ANC2330 | D41: =+LEFT(A41,2) -> 23 | F41: =(+IFERROR(VLOOKUP($A41,'[152]BG (2)'!$B$9:$J$570,4,FALSE),0))*1 -> 16742409141 | G41: =(+IFERROR(VLOOKUP($A41,'[152]BG (2)'!$B$9:$J$570,5,FALSE),0))*-1 -> 0 | H41: =(+IFERROR(VLOOKUP($A41,'[152]BG (2)'!$B$9:$J$570,6,FALSE),0))*1 -> 3567989500 | I41: =(+IFERROR(VLOOKUP($A41,'[152]BG (2)'!$B$9:$J$570,7,FALSE),0))*-1 -> 0 | J41: =(+IFERROR(VLOOKUP($A41,'[152]BG (2)'!$B$9:$J$570,8,FALSE),0))*1 -> 20310398641 | K41: =(+IFERROR(VLOOKUP($A41,'[152]BG (2)'!$B$9:$J$570,9,FALSE),0))*-1 -> 0 | P41: =J41+K41 -> 20310398641 | T41: =K41+J41 -> 20310398641 | W41: =+A41-#REF! -> #REF!
A42: 235110 | B42: AMENAGEMENT DE BUREAUX | C42: ANC2380 | D42: =+LEFT(A42,2) -> 23 | F42: =(+IFERROR(VLOOKUP($A42,'[152]BG (2)'!$B$9:$J$570,4,FALSE),0))*1 -> 1040380583 | G42: =(+IFERROR(VLOOKUP($A42,'[152]BG (2)'!$B$9:$J$570,5,FALSE),0))*-1 -> 0 | H42: =(+IFERROR(VLOOKUP($A42,'[152]BG (2)'!$B$9:$J$570,6,FALSE),0))*1 -> 9476008 | I42: =(+IFERROR(VLOOKUP($A42,'[152]BG (2)'!$B$9:$J$570,7,FALSE),0))*-1 -> 0 | J42: =(+IFERROR(VLOOKUP($A42,'[152]BG (2)'!$B$9:$J$570,8,FALSE),0))*1 -> 1049856591 | K42: =(+IFERROR(VLOOKUP($A42,'[152]BG (2)'!$B$9:$J$570,9,FALSE),0))*-1 -> 0 | P42: =J42+K42 -> 1049856591 | T42: =K42+J42 -> 1049856591 | W42: =+A42-#REF! -> #REF!
A43: 235120 | B43: AMENAGEMENT DES AGENCES | C43: ANC2380 | D43: =+LEFT(A43,2) -> 23 | F43: =(+IFERROR(VLOOKUP($A43,'[152]BG (2)'!$B$9:$J$570,4,FALSE),0))*1 -> 765519895 | G43: =(+IFERROR(VLOOKUP($A43,'[152]BG (2)'!$B$9:$J$570,5,FALSE),0))*-1 -> 0 | H43: =(+IFERROR(VLOOKUP($A43,'[152]BG (2)'!$B$9:$J$570,6,FALSE),0))*1 -> 152720787 | I43: =(+IFERROR(VLOOKUP($A43,'[152]BG (2)'!$B$9:$J$570,7,FALSE),0))*-1 -> 0 | J43: =(+IFERROR(VLOOKUP($A43,'[152]BG (2)'!$B$9:$J$570,8,FALSE),0))*1 -> 918240682 | K43: =(+IFERROR(VLOOKUP($A43,'[152]BG (2)'!$B$9:$J$570,9,FALSE),0))*-1 -> 0 | P43: =J43+K43 -> 918240682 | T43: =K43+J43 -> 918240682 | W43: =+A43-#REF! -> #REF!
A44: 235130 | B44: AMENAGEMENT DES RESIDENCES | C44: ANC2380 | D44: =+LEFT(A44,2) -> 23 | F44: =(+IFERROR(VLOOKUP($A44,'[152]BG (2)'!$B$9:$J$570,4,FALSE),0))*1 -> 6738841 | G44: =(+IFERROR(VLOOKUP($A44,'[152]BG (2)'!$B$9:$J$570,5,FALSE),0))*-1 -> 0 | H44: =(+IFERROR(VLOOKUP($A44,'[152]BG (2)'!$B$9:$J$570,6,FALSE),0))*1 -> 0 | I44: =(+IFERROR(VLOOKUP($A44,'[152]BG (2)'!$B$9:$J$570,7,FALSE),0))*-1 -> 0 | J44: =(+IFERROR(VLOOKUP($A44,'[152]BG (2)'!$B$9:$J$570,8,FALSE),0))*1 -> 6738841 | K44: =(+IFERROR(VLOOKUP($A44,'[152]BG (2)'!$B$9:$J$570,9,FALSE),0))*-1 -> 0 | P44: =J44+K44 -> 6738841 | T44: =K44+J44 -> 6738841 | W44: =+A44-#REF! -> #REF!
A45: 235800 | B45: AUTRES AMENAGEMENTS | C45: ANC2380 | D45: =+LEFT(A45,2) -> 23 | F45: =(+IFERROR(VLOOKUP($A45,'[152]BG (2)'!$B$9:$J$570,4,FALSE),0))*1 -> 38309397 | G45: =(+IFERROR(VLOOKUP($A45,'[152]BG (2)'!$B$9:$J$570,5,FALSE),0))*-1 -> 0 | H45: =(+IFERROR(VLOOKUP($A45,'[152]BG (2)'!$B$9:$J$570,6,FALSE),0))*1 -> 0 | I45: =(+IFERROR(VLOOKUP($A45,'[152]BG (2)'!$B$9:$J$570,7,FALSE),0))*-1 -> 0 | J45: =(+IFERROR(VLOOKUP($A45,'[152]BG (2)'!$B$9:$J$570,8,FALSE),0))*1 -> 38309397 | K45: =(+IFERROR(VLOOKUP($A45,'[152]BG (2)'!$B$9:$J$570,9,FALSE),0))*-1 -> 0 | P45: =J45+K45 -> 38309397 | T45: =K45+J45 -> 38309397 | W45: =+A45-#REF! -> #REF!
A46: 238200 | B46: DIVERS INSTALLATIONS ET AGENCE | C46: ANC2380 | D46: =+LEFT(A46,2) -> 23 | F46: =(+IFERROR(VLOOKUP($A46,'[152]BG (2)'!$B$9:$J$570,4,FALSE),0))*1 -> 96397936 | G46: =(+IFERROR(VLOOKUP($A46,'[152]BG (2)'!$B$9:$J$570,5,FALSE),0))*-1 -> 0 | H46: =(+IFERROR(VLOOKUP($A46,'[152]BG (2)'!$B$9:$J$570,6,FALSE),0))*1 -> 0 | I46: =(+IFERROR(VLOOKUP($A46,'[152]BG (2)'!$B$9:$J$570,7,FALSE),0))*-1 -> 0 | J46: =(+IFERROR(VLOOKUP($A46,'[152]BG (2)'!$B$9:$J$570,8,FALSE),0))*1 -> 96397936 | K46: =(+IFERROR(VLOOKUP($A46,'[152]BG (2)'!$B$9:$J$570,9,FALSE),0))*-1 -> 0 | P46: =J46+K46 -> 96397936 | T46: =K46+J46 -> 96397936 | W46: =+A46-#REF! -> #REF!
A47: 239100 | B47: BATIMENTS EN COURS | C47: ANC2320 | D47: =+LEFT(A47,2) -> 23 | F47: =(+IFERROR(VLOOKUP($A47,'[152]BG (2)'!$B$9:$J$570,4,FALSE),0))*1 -> 499188587 | G47: =(+IFERROR(VLOOKUP($A47,'[152]BG (2)'!$B$9:$J$570,5,FALSE),0))*-1 -> 0 | H47: =(+IFERROR(VLOOKUP($A47,'[152]BG (2)'!$B$9:$J$570,6,FALSE),0))*1 -> 847644182 | I47: =(+IFERROR(VLOOKUP($A47,'[152]BG (2)'!$B$9:$J$570,7,FALSE),0))*-1 -> -104126897 | J47: =(+IFERROR(VLOOKUP($A47,'[152]BG (2)'!$B$9:$J$570,8,FALSE),0))*1 -> 1242705872 | K47: =(+IFERROR(VLOOKUP($A47,'[152]BG (2)'!$B$9:$J$570,9,FALSE),0))*-1 -> 0 | P47: =J47+K47 -> 1242705872 | T47: =K47+J47 -> 1242705872 | W47: =+A47-#REF! -> #REF!
A48: 241110 | B48: MATERIEL TRANSMISSION - BSS | C48: ANC2330 | D48: =+LEFT(A48,2) -> 24 | F48: =(+IFERROR(VLOOKUP($A48,'[152]BG (2)'!$B$9:$J$570,4,FALSE),0))*1 -> 39278419567 | G48: =(+IFERROR(VLOOKUP($A48,'[152]BG (2)'!$B$9:$J$570,5,FALSE),0))*-1 -> 0 | H48: =(+IFERROR(VLOOKUP($A48,'[152]BG (2)'!$B$9:$J$570,6,FALSE),0))*1 -> 6756962374 | I48: =(+IFERROR(VLOOKUP($A48,'[152]BG (2)'!$B$9:$J$570,7,FALSE),0))*-1 -> 0 | J48: =(+IFERROR(VLOOKUP($A48,'[152]BG (2)'!$B$9:$J$570,8,FALSE),0))*1 -> 46035381941 | K48: =(+IFERROR(VLOOKUP($A48,'[152]BG (2)'!$B$9:$J$570,9,FALSE),0))*-1 -> 0 | P48: =J48+K48 -> 46035381941 | T48: =K48+J48 -> 46035381941 | W48: =+A48-#REF! -> #REF!
A49: 241120 | B49: MATERIEL DE TRANSMISSION - RAD | C49: ANC2330 | D49: =+LEFT(A49,2) -> 24 | F49: =(+IFERROR(VLOOKUP($A49,'[152]BG (2)'!$B$9:$J$570,4,FALSE),0))*1 -> 24537043449 | G49: =(+IFERROR(VLOOKUP($A49,'[152]BG (2)'!$B$9:$J$570,5,FALSE),0))*-1 -> 0 | H49: =(+IFERROR(VLOOKUP($A49,'[152]BG (2)'!$B$9:$J$570,6,FALSE),0))*1 -> 988771214 | I49: =(+IFERROR(VLOOKUP($A49,'[152]BG (2)'!$B$9:$J$570,7,FALSE),0))*-1 -> 0 | J49: =(+IFERROR(VLOOKUP($A49,'[152]BG (2)'!$B$9:$J$570,8,FALSE),0))*1 -> 25525814663 | K49: =(+IFERROR(VLOOKUP($A49,'[152]BG (2)'!$B$9:$J$570,9,FALSE),0))*-1 -> 0 | P49: =J49+K49 -> 25525814663 | T49: =K49+J49 -> 25525814663 | W49: =+A49-#REF! -> #REF!
A50: 241130 | B50: MATERIEL DE COMMUTATION | C50: ANC2330 | D50: =+LEFT(A50,2) -> 24 | F50: =(+IFERROR(VLOOKUP($A50,'[152]BG (2)'!$B$9:$J$570,4,FALSE),0))*1 -> 15963504217 | G50: =(+IFERROR(VLOOKUP($A50,'[152]BG (2)'!$B$9:$J$570,5,FALSE),0))*-1 -> 0 | H50: =(+IFERROR(VLOOKUP($A50,'[152]BG (2)'!$B$9:$J$570,6,FALSE),0))*1 -> 459823786 | I50: =(+IFERROR(VLOOKUP($A50,'[152]BG (2)'!$B$9:$J$570,7,FALSE),0))*-1 -> 0 | J50: =(+IFERROR(VLOOKUP($A50,'[152]BG (2)'!$B$9:$J$570,8,FALSE),0))*1 -> 16423328003 | K50: =(+IFERROR(VLOOKUP($A50,'[152]BG (2)'!$B$9:$J$570,9,FALSE),0))*-1 -> 0 | P50: =J50+K50 -> 16423328003 | T50: =K50+J50 -> 16423328003 | W50: =+A50-#REF! -> #REF!
... A52: 241150 | B52: EQUIPEMENTS DE MESURE ET DE TE | C52: ANC2330 | D52: =+LEFT(A52,2) -> 24 | F52: =(+IFERROR(VLOOKUP($A52,'[152]BG (2)'!$B$9:$J$570,4,FALSE),0))*1 -> 703102864 | G52: =(+IFERROR(VLOOKUP($A52,'[152]BG (2)'!$B$9:$J$570,5,FALSE),0))*-1 -> 0 | H52: =(+IFERROR(VLOOKUP($A52,'[152]BG (2)'!$B$9:$J$570,6,FALSE),0))*1 -> 0 | I52: =(+IFERROR(VLOOKUP($A52,'[152]BG (2)'!$B$9:$J$570,7,FALSE),0))*-1 -> 0 | J52: =(+IFERROR(VLOOKUP($A52,'[152]BG (2)'!$B$9:$J$570,8,FALSE),0))*1 -> 703102864 | K52: =(+IFERROR(VLOOKUP($A52,'[152]BG (2)'!$B$9:$J$570,9,FALSE),0))*-1 -> 0 | P52: =J52+K52 -> 703102864 | T52: =K52+J52 -> 703102864 | W52: =+A52-#REF! -> #REF!
A53: 241200 | C53: ANC2330 | D53: =+LEFT(A53,2) -> 24 | F53: =(+IFERROR(VLOOKUP($A53,'[152]BG (2)'!$B$9:$J$570,4,FALSE),0))*1 -> 90324192 | G53: =(+IFERROR(VLOOKUP($A53,'[152]BG (2)'!$B$9:$J$570,5,FALSE),0))*-1 -> 0 | H53: =(+IFERROR(VLOOKUP($A53,'[152]BG (2)'!$B$9:$J$570,6,FALSE),0))*1 -> 0 | I53: =(+IFERROR(VLOOKUP($A53,'[152]BG (2)'!$B$9:$J$570,7,FALSE),0))*-1 -> 0 | J53: =(+IFERROR(VLOOKUP($A53,'[152]BG (2)'!$B$9:$J$570,8,FALSE),0))*1 -> 90324192 | K53: =(+IFERROR(VLOOKUP($A53,'[152]BG (2)'!$B$9:$J$570,9,FALSE),0))*-1 -> 0 | P53: =J53+K53 -> 90324192 | T53: =K53+J53 -> 90324192 | W53: =+A53-#REF! -> #REF!
A54: 244100 | B54: MATERIEL DE BUREAU | C54: ANC2350 | D54: =+LEFT(A54,2) -> 24 | F54: =(+IFERROR(VLOOKUP($A54,'[152]BG (2)'!$B$9:$J$570,4,FALSE),0))*1 -> 165186312 | G54: =(+IFERROR(VLOOKUP($A54,'[152]BG (2)'!$B$9:$J$570,5,FALSE),0))*-1 -> 0 | H54: =(+IFERROR(VLOOKUP($A54,'[152]BG (2)'!$B$9:$J$570,6,FALSE),0))*1 -> 5021004 | I54: =(+IFERROR(VLOOKUP($A54,'[152]BG (2)'!$B$9:$J$570,7,FALSE),0))*-1 -> 0 | J54: =(+IFERROR(VLOOKUP($A54,'[152]BG (2)'!$B$9:$J$570,8,FALSE),0))*1 -> 170207316 | K54: =(+IFERROR(VLOOKUP($A54,'[152]BG (2)'!$B$9:$J$570,9,FALSE),0))*-1 -> 0 | P54: =J54+K54 -> 170207316 | T54: =K54+J54 -> 170207316 | W54: =+A54-#REF! -> #REF!
A55: 244200 | B55: MATERIEL INFORMATIQUE | C55: ANC2350 | D55: =+LEFT(A55,2) -> 24 | F55: =(+IFERROR(VLOOKUP($A55,'[152]BG (2)'!$B$9:$J$570,4,FALSE),0))*1 -> 7055533142 | G55: =(+IFERROR(VLOOKUP($A55,'[152]BG (2)'!$B$9:$J$570,5,FALSE),0))*-1 -> 0 | H55: =(+IFERROR(VLOOKUP($A55,'[152]BG (2)'!$B$9:$J$570,6,FALSE),0))*1 -> 2337449953 | I55: =(+IFERROR(VLOOKUP($A55,'[152]BG (2)'!$B$9:$J$570,7,FALSE),0))*-1 -> 0 | J55: =(+IFERROR(VLOOKUP($A55,'[152]BG (2)'!$B$9:$J$570,8,FALSE),0))*1 -> 9392983095 | K55: =(+IFERROR(VLOOKUP($A55,'[152]BG (2)'!$B$9:$J$570,9,FALSE),0))*-1 -> 0 | P55: =J55+K55 -> 9392983095 | T55: =K55+J55 -> 9392983095 | W55: =+A55-#REF! -> #REF!
A56: 244400 | B56: MOBILIER DE BUREAU | C56: ANC2350 | D56: =+LEFT(A56,2) -> 24 | F56: =(+IFERROR(VLOOKUP($A56,'[152]BG (2)'!$B$9:$J$570,4,FALSE),0))*1 -> 484007093 | G56: =(+IFERROR(VLOOKUP($A56,'[152]BG (2)'!$B$9:$J$570,5,FALSE),0))*-1 -> 0 | H56: =(+IFERROR(VLOOKUP($A56,'[152]BG (2)'!$B$9:$J$570,6,FALSE),0))*1 -> 46677076 | I56: =(+IFERROR(VLOOKUP($A56,'[152]BG (2)'!$B$9:$J$570,7,FALSE),0))*-1 -> 0 | J56: =(+IFERROR(VLOOKUP($A56,'[152]BG (2)'!$B$9:$J$570,8,FALSE),0))*1 -> 530684169 | K56: =(+IFERROR(VLOOKUP($A56,'[152]BG (2)'!$B$9:$J$570,9,FALSE),0))*-1 -> 0 | P56: =J56+K56 -> 530684169 | T56: =K56+J56 -> 530684169 | W56: =+A56-#REF! -> #REF!
A57: 244700 | B57: MATERIEL ET MOBILIER DE LOGEME | C57: ANC2380 | D57: =+LEFT(A57,2) -> 24 | F57: =(+IFERROR(VLOOKUP($A57,'[152]BG (2)'!$B$9:$J$570,4,FALSE),0))*1 -> 190364902 | G57: =(+IFERROR(VLOOKUP($A57,'[152]BG (2)'!$B$9:$J$570,5,FALSE),0))*-1 -> 0 | H57: =(+IFERROR(VLOOKUP($A57,'[152]BG (2)'!$B$9:$J$570,6,FALSE),0))*1 -> 6103893 | I57: =(+IFERROR(VLOOKUP($A57,'[152]BG (2)'!$B$9:$J$570,7,FALSE),0))*-1 -> 0 | J57: =(+IFERROR(VLOOKUP($A57,'[152]BG (2)'!$B$9:$J$570,8,FALSE),0))*1 -> 196468795 | K57: =(+IFERROR(VLOOKUP($A57,'[152]BG (2)'!$B$9:$J$570,9,FALSE),0))*-1 -> 0 | P57: =J57+K57 -> 196468795 | T57: =K57+J57 -> 196468795 | W57: =+A57-#REF! -> #REF!
A58: 245100 | B58: MATERIEL DE TRANSPORT | C58: ANC2340 | D58: =+LEFT(A58,2) -> 24 | F58: =(+IFERROR(VLOOKUP($A58,'[152]BG (2)'!$B$9:$J$570,4,FALSE),0))*1 -> 711305198 | G58: =(+IFERROR(VLOOKUP($A58,'[152]BG (2)'!$B$9:$J$570,5,FALSE),0))*-1 -> 0 | H58: =(+IFERROR(VLOOKUP($A58,'[152]BG (2)'!$B$9:$J$570,6,FALSE),0))*1 -> 0 | I58: =(+IFERROR(VLOOKUP($A58,'[152]BG (2)'!$B$9:$J$570,7,FALSE),0))*-1 -> 0 | J58: =(+IFERROR(VLOOKUP($A58,'[152]BG (2)'!$B$9:$J$570,8,FALSE),0))*1 -> 711305198 | K58: =(+IFERROR(VLOOKUP($A58,'[152]BG (2)'!$B$9:$J$570,9,FALSE),0))*-1 -> 0 | P58: =J58+K58 -> 711305198 | T58: =K58+J58 -> 711305198 | W58: =+A58-#REF! -> #REF!
A59: 245800 | B59: AUTRES MATERIELS DE TRANSPORT | C59: ANC2340 | D59: =+LEFT(A59,2) -> 24 | F59: =(+IFERROR(VLOOKUP($A59,'[152]BG (2)'!$B$9:$J$570,4,FALSE),0))*1 -> 3200000 | G59: =(+IFERROR(VLOOKUP($A59,'[152]BG (2)'!$B$9:$J$570,5,FALSE),0))*-1 -> 0 | H59: =(+IFERROR(VLOOKUP($A59,'[152]BG (2)'!$B$9:$J$570,6,FALSE),0))*1 -> 0 | I59: =(+IFERROR(VLOOKUP($A59,'[152]BG (2)'!$B$9:$J$570,7,FALSE),0))*-1 -> 0 | J59: =(+IFERROR(VLOOKUP($A59,'[152]BG (2)'!$B$9:$J$570,8,FALSE),0))*1 -> 3200000 | K59: =(+IFERROR(VLOOKUP($A59,'[152]BG (2)'!$B$9:$J$570,9,FALSE),0))*-1 -> 0 | P59: =J59+K59 -> 3200000 | T59: =K59+J59 -> 3200000 | W59: =+A59-#REF! -> #REF!
A60: 248000 | B60: AUTRES MATERIELS | C60: ANC2380 | D60: =+LEFT(A60,2) -> 24 | F60: =(+IFERROR(VLOOKUP($A60,'[152]BG (2)'!$B$9:$J$570,4,FALSE),0))*1 -> 523939105 | G60: =(+IFERROR(VLOOKUP($A60,'[152]BG (2)'!$B$9:$J$570,5,FALSE),0))*-1 -> 0 | H60: =(+IFERROR(VLOOKUP($A60,'[152]BG (2)'!$B$9:$J$570,6,FALSE),0))*1 -> 12160150 | I60: =(+IFERROR(VLOOKUP($A60,'[152]BG (2)'!$B$9:$J$570,7,FALSE),0))*-1 -> 0 | J60: =(+IFERROR(VLOOKUP($A60,'[152]BG (2)'!$B$9:$J$570,8,FALSE),0))*1 -> 536099255 | K60: =(+IFERROR(VLOOKUP($A60,'[152]BG (2)'!$B$9:$J$570,9,FALSE),0))*-1 -> 0 | P60: =J60+K60 -> 536099255 | T60: =K60+J60 -> 536099255 | W60: =+A60-#REF! -> #REF!
A61: 249100 | B61: MATERIELS TECHNIQUES EN COURS | C61: ANC2330 | D61: =+LEFT(A61,2) -> 24 | F61: =(+IFERROR(VLOOKUP($A61,'[152]BG (2)'!$B$9:$J$570,4,FALSE),0))*1 -> 6616238905 | G61: =(+IFERROR(VLOOKUP($A61,'[152]BG (2)'!$B$9:$J$570,5,FALSE),0))*-1 -> 0 | H61: =(+IFERROR(VLOOKUP($A61,'[152]BG (2)'!$B$9:$J$570,6,FALSE),0))*1 -> 24885659203 | I61: =(+IFERROR(VLOOKUP($A61,'[152]BG (2)'!$B$9:$J$570,7,FALSE),0))*-1 -> -22943218043 | J61: =(+IFERROR(VLOOKUP($A61,'[152]BG (2)'!$B$9:$J$570,8,FALSE),0))*1 -> 8558680065 | K61: =(+IFERROR(VLOOKUP($A61,'[152]BG (2)'!$B$9:$J$570,9,FALSE),0))*-1 -> 0 | P61: =J61+K61 -> 8558680065 | T61: =K61+J61 -> 8558680065 | W61: =+A61-#REF! -> #REF!
A62: 249110 | B62: MATERIEL, MOBILIER LOCAL EN C | C62: ANC2350 | D62: =+LEFT(A62,2) -> 24 | F62: =(+IFERROR(VLOOKUP($A62,'[152]BG (2)'!$B$9:$J$570,4,FALSE),0))*1 -> 1747498260 | G62: =(+IFERROR(VLOOKUP($A62,'[152]BG (2)'!$B$9:$J$570,5,FALSE),0))*-1 -> 0 | H62: =(+IFERROR(VLOOKUP($A62,'[152]BG (2)'!$B$9:$J$570,6,FALSE),0))*1 -> 4906826046 | I62: =(+IFERROR(VLOOKUP($A62,'[152]BG (2)'!$B$9:$J$570,7,FALSE),0))*-1 -> -3082121923 | J62: =(+IFERROR(VLOOKUP($A62,'[152]BG (2)'!$B$9:$J$570,8,FALSE),0))*1 -> 3572202383 | K62: =(+IFERROR(VLOOKUP($A62,'[152]BG (2)'!$B$9:$J$570,9,FALSE),0))*-1 -> 0 | P62: =J62+K62 -> 3572202383 | T62: =K62+J62 -> 3572202383 | W62: =+A62-#REF! -> #REF!
A63: 249510 | B63: MATERIEL DE TRANSPORT EN COURS | C63: ANC2340 | D63: =+LEFT(A63,2) -> 24 | F63: =(+IFERROR(VLOOKUP($A63,'[152]BG (2)'!$B$9:$J$570,4,FALSE),0))*1 -> 1390000 | G63: =(+IFERROR(VLOOKUP($A63,'[152]BG (2)'!$B$9:$J$570,5,FALSE),0))*-1 -> 0 | H63: =(+IFERROR(VLOOKUP($A63,'[152]BG (2)'!$B$9:$J$570,6,FALSE),0))*1 -> 0 | I63: =(+IFERROR(VLOOKUP($A63,'[152]BG (2)'!$B$9:$J$570,7,FALSE),0))*-1 -> 0 | J63: =(+IFERROR(VLOOKUP($A63,'[152]BG (2)'!$B$9:$J$570,8,FALSE),0))*1 -> 1390000 | K63: =(+IFERROR(VLOOKUP($A63,'[152]BG (2)'!$B$9:$J$570,9,FALSE),0))*-1 -> 0 | P63: =J63+K63 -> 1390000 | T63: =K63+J63 -> 1390000 | W63: =+A63-#REF! -> #REF!
A64: 251000 | B64: AVCES ET ACPTES / IMMOBILISATI | C64: ANC2330 | D64: =+LEFT(A64,2) -> 25 | F64: =(+IFERROR(VLOOKUP($A64,'[152]BG (2)'!$B$9:$J$570,4,FALSE),0))*1 -> 283078449 | G64: =(+IFERROR(VLOOKUP($A64,'[152]BG (2)'!$B$9:$J$570,5,FALSE),0))*-1 -> 0 | H64: =(+IFERROR(VLOOKUP($A64,'[152]BG (2)'!$B$9:$J$570,6,FALSE),0))*1 -> 291551321 | I64: =(+IFERROR(VLOOKUP($A64,'[152]BG (2)'!$B$9:$J$570,7,FALSE),0))*-1 -> -424703005 | J64: =(+IFERROR(VLOOKUP($A64,'[152]BG (2)'!$B$9:$J$570,8,FALSE),0))*1 -> 149926765 | K64: =(+IFERROR(VLOOKUP($A64,'[152]BG (2)'!$B$9:$J$570,9,FALSE),0))*-1 -> 0 | P64: =J64+K64 -> 149926765 | T64: =K64+J64 -> 149926765 | W64: =+A64-#REF! -> #REF!
A65: 252000 | B65: AVCES ET ACPTES / IMMOBILISATI | C65: ANC2298 | D65: =+LEFT(A65,2) -> 25 | F65: =(+IFERROR(VLOOKUP($A65,'[152]BG (2)'!$B$9:$J$570,4,FALSE),0))*1 -> 479890198 | G65: =(+IFERROR(VLOOKUP($A65,'[152]BG (2)'!$B$9:$J$570,5,FALSE),0))*-1 -> 0 | H65: =(+IFERROR(VLOOKUP($A65,'[152]BG (2)'!$B$9:$J$570,6,FALSE),0))*1 -> 587469013 | I65: =(+IFERROR(VLOOKUP($A65,'[152]BG (2)'!$B$9:$J$570,7,FALSE),0))*-1 -> -742557183 | J65: =(+IFERROR(VLOOKUP($A65,'[152]BG (2)'!$B$9:$J$570,8,FALSE),0))*1 -> 324802028 | K65: =(+IFERROR(VLOOKUP($A65,'[152]BG (2)'!$B$9:$J$570,9,FALSE),0))*-1 -> 0 | P65: =J65+K65 -> 324802028 | T65: =K65+J65 -> 324802028 | W65: =+A65-#REF! -> #REF!
A66: 261000 | B66: TITRES DE PARTICIPATIONS, CTRL | C66: ANC2511 | D66: =+LEFT(A66,2) -> 26 | F66: =(+IFERROR(VLOOKUP($A66,'[152]BG (2)'!$B$9:$J$570,4,FALSE),0))*1 -> 0 | G66: =(+IFERROR(VLOOKUP($A66,'[152]BG (2)'!$B$9:$J$570,5,FALSE),0))*-1 -> 0 | H66: =(+IFERROR(VLOOKUP($A66,'[152]BG (2)'!$B$9:$J$570,6,FALSE),0))*1 -> 0 | I66: =(+IFERROR(VLOOKUP($A66,'[152]BG (2)'!$B$9:$J$570,7,FALSE),0))*-1 -> 0 | J66: =(+IFERROR(VLOOKUP($A66,'[152]BG (2)'!$B$9:$J$570,8,FALSE),0))*1 -> 0 | K66: =(+IFERROR(VLOOKUP($A66,'[152]BG (2)'!$B$9:$J$570,9,FALSE),0))*-1 -> 0 | P66: =J66+K66 -> 0 | W66: =+A66-#REF! -> #REF!
A67: 275100 | B67: DEPOTS LOYERS | C67: AC3440 | D67: =+LEFT(A67,2) -> 27 | F67: =(+IFERROR(VLOOKUP($A67,'[152]BG (2)'!$B$9:$J$570,4,FALSE),0))*1 -> 393913540 | G67: =(+IFERROR(VLOOKUP($A67,'[152]BG (2)'!$B$9:$J$570,5,FALSE),0))*-1 -> 0 | H67: =(+IFERROR(VLOOKUP($A67,'[152]BG (2)'!$B$9:$J$570,6,FALSE),0))*1 -> 24230000 | I67: =(+IFERROR(VLOOKUP($A67,'[152]BG (2)'!$B$9:$J$570,7,FALSE),0))*-1 -> 0 | J67: =(+IFERROR(VLOOKUP($A67,'[152]BG (2)'!$B$9:$J$570,8,FALSE),0))*1 -> 418143540 | K67: =(+IFERROR(VLOOKUP($A67,'[152]BG (2)'!$B$9:$J$570,9,FALSE),0))*-1 -> 0 | P67: =J67+K67 -> 418143540 | T67: =K67+J67 -> 418143540 | W67: =+A67-#REF! -> #REF!
A68: 275200 | B68: DEPOTS ELECTRICITE | C68: AC3440 | D68: =+LEFT(A68,2) -> 27 | F68: =(+IFERROR(VLOOKUP($A68,'[152]BG (2)'!$B$9:$J$570,4,FALSE),0))*1 -> 101071023 | G68: =(+IFERROR(VLOOKUP($A68,'[152]BG (2)'!$B$9:$J$570,5,FALSE),0))*-1 -> 0 | H68: =(+IFERROR(VLOOKUP($A68,'[152]BG (2)'!$B$9:$J$570,6,FALSE),0))*1 -> 13569900 | I68: =(+IFERROR(VLOOKUP($A68,'[152]BG (2)'!$B$9:$J$570,7,FALSE),0))*-1 -> 0 | J68: =(+IFERROR(VLOOKUP($A68,'[152]BG (2)'!$B$9:$J$570,8,FALSE),0))*1 -> 114640923 | K68: =(+IFERROR(VLOOKUP($A68,'[152]BG (2)'!$B$9:$J$570,9,FALSE),0))*-1 -> 0 | P68: =J68+K68 -> 114640923 | T68: =K68+J68 -> 114640923 | W68: =+A68-#REF! -> #REF!
A69: 275300 | B69: DEPOTS EAU | C69: AC3440 | D69: =+LEFT(A69,2) -> 27 | F69: =(+IFERROR(VLOOKUP($A69,'[152]BG (2)'!$B$9:$J$570,4,FALSE),0))*1 -> 287800 | G69: =(+IFERROR(VLOOKUP($A69,'[152]BG (2)'!$B$9:$J$570,5,FALSE),0))*-1 -> 0 | H69: =(+IFERROR(VLOOKUP($A69,'[152]BG (2)'!$B$9:$J$570,6,FALSE),0))*1 -> 0 | I69: =(+IFERROR(VLOOKUP($A69,'[152]BG (2)'!$B$9:$J$570,7,FALSE),0))*-1 -> 0 | J69: =(+IFERROR(VLOOKUP($A69,'[152]BG (2)'!$B$9:$J$570,8,FALSE),0))*1 -> 287800 | K69: =(+IFERROR(VLOOKUP($A69,'[152]BG (2)'!$B$9:$J$570,9,FALSE),0))*-1 -> 0 | P69: =J69+K69 -> 287800 | T69: =K69+J69 -> 287800 | W69: =+A69-#REF! -> #REF!
A70: 275500 | B70: DEPOTS TELEPHONE / FAX | C70: AC3440 | D70: =+LEFT(A70,2) -> 27 | F70: =(+IFERROR(VLOOKUP($A70,'[152]BG (2)'!$B$9:$J$570,4,FALSE),0))*1 -> 105600 | G70: =(+IFERROR(VLOOKUP($A70,'[152]BG (2)'!$B$9:$J$570,5,FALSE),0))*-1 -> 0 | H70: =(+IFERROR(VLOOKUP($A70,'[152]BG (2)'!$B$9:$J$570,6,FALSE),0))*1 -> 0 | I70: =(+IFERROR(VLOOKUP($A70,'[152]BG (2)'!$B$9:$J$570,7,FALSE),0))*-1 -> 0 | J70: =(+IFERROR(VLOOKUP($A70,'[152]BG (2)'!$B$9:$J$570,8,FALSE),0))*1 -> 105600 | K70: =(+IFERROR(VLOOKUP($A70,'[152]BG (2)'!$B$9:$J$570,9,FALSE),0))*-1 -> 0 | P70: =J70+K70 -> 105600 | T70: =K70+J70 -> 105600 | W70: =+A70-#REF! -> #REF!
A71: 275800 | B71: AUTRES DEPOTS ET CAUTIONNEMENT | C71: ANC2438 | D71: =+LEFT(A71,2) -> 27 | F71: =(+IFERROR(VLOOKUP($A71,'[152]BG (2)'!$B$9:$J$570,4,FALSE),0))*1 -> 179898767 | G71: =(+IFERROR(VLOOKUP($A71,'[152]BG (2)'!$B$9:$J$570,5,FALSE),0))*-1 -> 0 | H71: =(+IFERROR(VLOOKUP($A71,'[152]BG (2)'!$B$9:$J$570,6,FALSE),0))*1 -> 19000000 | I71: =(+IFERROR(VLOOKUP($A71,'[152]BG (2)'!$B$9:$J$570,7,FALSE),0))*-1 -> 0 | J71: =(+IFERROR(VLOOKUP($A71,'[152]BG (2)'!$B$9:$J$570,8,FALSE),0))*1 -> 198898767 | K71: =(+IFERROR(VLOOKUP($A71,'[152]BG (2)'!$B$9:$J$570,9,FALSE),0))*-1 -> 0 | P71: =J71+K71 -> 198898767 | T71: =K71+J71 -> 198898767 | W71: =+A71-#REF! -> #REF!
A72: 281210 | B72: AMORT. LICENCES GSM | C72: ANC2824 | D72: =+LEFT(A72,2) -> 28 | F72: =(+IFERROR(VLOOKUP($A72,'[152]BG (2)'!$B$9:$J$570,4,FALSE),0))*1 -> 0 | G72: =(+IFERROR(VLOOKUP($A72,'[152]BG (2)'!$B$9:$J$570,5,FALSE),0))*-1 -> -53968689892 | H72: =(+IFERROR(VLOOKUP($A72,'[152]BG (2)'!$B$9:$J$570,6,FALSE),0))*1 -> 0 | I72: =(+IFERROR(VLOOKUP($A72,'[152]BG (2)'!$B$9:$J$570,7,FALSE),0))*-1 -> -2555415583 | J72: =(+IFERROR(VLOOKUP($A72,'[152]BG (2)'!$B$9:$J$570,8,FALSE),0))*1 -> 0 | K72: =(+IFERROR(VLOOKUP($A72,'[152]BG (2)'!$B$9:$J$570,9,FALSE),0))*-1 -> -56524105475 | P72: =J72+K72 -> -56524105475 | T72: =K72+J72 -> -56524105475 | W72: =+A72-#REF! -> #REF!
A73: 281220 | B73: AMORT. AUTRES LICENCES ET BREV | C73: ANC28221 | D73: =+LEFT(A73,2) -> 28 | F73: =(+IFERROR(VLOOKUP($A73,'[152]BG (2)'!$B$9:$J$570,4,FALSE),0))*1 -> 0 | G73: =(+IFERROR(VLOOKUP($A73,'[152]BG (2)'!$B$9:$J$570,5,FALSE),0))*-1 -> -5372687333 | H73: =(+IFERROR(VLOOKUP($A73,'[152]BG (2)'!$B$9:$J$570,6,FALSE),0))*1 -> 0 | I73: =(+IFERROR(VLOOKUP($A73,'[152]BG (2)'!$B$9:$J$570,7,FALSE),0))*-1 -> -3558750994 | J73: =(+IFERROR(VLOOKUP($A73,'[152]BG (2)'!$B$9:$J$570,8,FALSE),0))*1 -> 0 | K73: =(+IFERROR(VLOOKUP($A73,'[152]BG (2)'!$B$9:$J$570,9,FALSE),0))*-1 -> -8931438327 | P73: =J73+K73 -> -8931438327 | T73: =K73+J73 -> -8931438327 | W73: =+A73-#REF! -> #REF!
A74: 281310 | B74: AMORT. LOGICIELS D'EXPLOITATIO | C74: ANC28222 | D74: =+LEFT(A74,2) -> 28 | F74: =(+IFERROR(VLOOKUP($A74,'[152]BG (2)'!$B$9:$J$570,4,FALSE),0))*1 -> 0 | G74: =(+IFERROR(VLOOKUP($A74,'[152]BG (2)'!$B$9:$J$570,5,FALSE),0))*-1 -> -38324968221 | H74: =(+IFERROR(VLOOKUP($A74,'[152]BG (2)'!$B$9:$J$570,6,FALSE),0))*1 -> 0 | I74: =(+IFERROR(VLOOKUP($A74,'[152]BG (2)'!$B$9:$J$570,7,FALSE),0))*-1 -> -1170961072 | J74: =(+IFERROR(VLOOKUP($A74,'[152]BG (2)'!$B$9:$J$570,8,FALSE),0))*1 -> 0 | K74: =(+IFERROR(VLOOKUP($A74,'[152]BG (2)'!$B$9:$J$570,9,FALSE),0))*-1 -> -39495929293 | P74: =J74+K74 -> -39495929293 | T74: =K74+J74 -> -39495929293 | W74: =+A74-#REF! -> #REF!
A75: 281320 | B75: AMORT. LOGICIELS AUTRES APPLIC | C75: ANC28222 | D75: =+LEFT(A75,2) -> 28 | F75: =(+IFERROR(VLOOKUP($A75,'[152]BG (2)'!$B$9:$J$570,4,FALSE),0))*1 -> 0 | G75: =(+IFERROR(VLOOKUP($A75,'[152]BG (2)'!$B$9:$J$570,5,FALSE),0))*-1 -> -2428207691 | H75: =(+IFERROR(VLOOKUP($A75,'[152]BG (2)'!$B$9:$J$570,6,FALSE),0))*1 -> 0 | I75: =(+IFERROR(VLOOKUP($A75,'[152]BG (2)'!$B$9:$J$570,7,FALSE),0))*-1 -> -33979024 | J75: =(+IFERROR(VLOOKUP($A75,'[152]BG (2)'!$B$9:$J$570,8,FALSE),0))*1 -> 0 | K75: =(+IFERROR(VLOOKUP($A75,'[152]BG (2)'!$B$9:$J$570,9,FALSE),0))*-1 -> -2462186715 | P75: =J75+K75 -> -2462186715 | T75: =K75+J75 -> -2462186715 | W75: =+A75-#REF! -> #REF!
A76: 283110 | B76: AMORT. BATIMENTS INDUSTRIELS | C76: ANC2320 | D76: =+LEFT(A76,2) -> 28 | F76: =(+IFERROR(VLOOKUP($A76,'[152]BG (2)'!$B$9:$J$570,4,FALSE),0))*1 -> 0 | G76: =(+IFERROR(VLOOKUP($A76,'[152]BG (2)'!$B$9:$J$570,5,FALSE),0))*-1 -> -30653352 | H76: =(+IFERROR(VLOOKUP($A76,'[152]BG (2)'!$B$9:$J$570,6,FALSE),0))*1 -> 0 | I76: =(+IFERROR(VLOOKUP($A76,'[152]BG (2)'!$B$9:$J$570,7,FALSE),0))*-1 -> -22697003 | J76: =(+IFERROR(VLOOKUP($A76,'[152]BG (2)'!$B$9:$J$570,8,FALSE),0))*1 -> 0 | K76: =(+IFERROR(VLOOKUP($A76,'[152]BG (2)'!$B$9:$J$570,9,FALSE),0))*-1 -> -53350355 | P76: =J76+K76 -> -53350355
A77: 283411 | B77: AMORT INFRASTRUCTURES | C77: ANC2833 | D77: =+LEFT(A77,2) -> 28 | F77: =(+IFERROR(VLOOKUP($A77,'[152]BG (2)'!$B$9:$J$570,4,FALSE),0))*1 -> 0 | G77: =(+IFERROR(VLOOKUP($A77,'[152]BG (2)'!$B$9:$J$570,5,FALSE),0))*-1 -> -14633866482 | H77: =(+IFERROR(VLOOKUP($A77,'[152]BG (2)'!$B$9:$J$570,6,FALSE),0))*1 -> 0 | I77: =(+IFERROR(VLOOKUP($A77,'[152]BG (2)'!$B$9:$J$570,7,FALSE),0))*-1 -> -1625319191 | J77: =(+IFERROR(VLOOKUP($A77,'[152]BG (2)'!$B$9:$J$570,8,FALSE),0))*1 -> 0 | K77: =(+IFERROR(VLOOKUP($A77,'[152]BG (2)'!$B$9:$J$570,9,FALSE),0))*-1 -> -16259185673 | P77: =J77+K77 -> -16259185673 | T77: =K77+J77 -> -16259185673 | W77: =+A77-#REF! -> #REF!
A78: 283412 | B78: AMORT AMENAGEMENT TECHNIQUE | C78: ANC2833 | D78: =+LEFT(A78,2) -> 28 | F78: =(+IFERROR(VLOOKUP($A78,'[152]BG (2)'!$B$9:$J$570,4,FALSE),0))*1 -> 0 | G78: =(+IFERROR(VLOOKUP($A78,'[152]BG (2)'!$B$9:$J$570,5,FALSE),0))*-1 -> -7089536600 | H78: =(+IFERROR(VLOOKUP($A78,'[152]BG (2)'!$B$9:$J$570,6,FALSE),0))*1 -> 0 | I78: =(+IFERROR(VLOOKUP($A78,'[152]BG (2)'!$B$9:$J$570,7,FALSE),0))*-1 -> -864305616 | J78: =(+IFERROR(VLOOKUP($A78,'[152]BG (2)'!$B$9:$J$570,8,FALSE),0))*1 -> 0 | K78: =(+IFERROR(VLOOKUP($A78,'[152]BG (2)'!$B$9:$J$570,9,FALSE),0))*-1 -> -7953842216 | P78: =J78+K78 -> -7953842216 | T78: =K78+J78 -> -7953842216 | W78: =+A78-#REF! -> #REF!
A79: 283413 | B79: AMORT EQUIPEMENTS D'ENERGIE | C79: ANC2833 | D79: =+LEFT(A79,2) -> 28 | F79: =(+IFERROR(VLOOKUP($A79,'[152]BG (2)'!$B$9:$J$570,4,FALSE),0))*1 -> 0 | G79: =(+IFERROR(VLOOKUP($A79,'[152]BG (2)'!$B$9:$J$570,5,FALSE),0))*-1 -> -15200284264 | H79: =(+IFERROR(VLOOKUP($A79,'[152]BG (2)'!$B$9:$J$570,6,FALSE),0))*1 -> 0 | I79: =(+IFERROR(VLOOKUP($A79,'[152]BG (2)'!$B$9:$J$570,7,FALSE),0))*-1 -> -1045838779 | J79: =(+IFERROR(VLOOKUP($A79,'[152]BG (2)'!$B$9:$J$570,8,FALSE),0))*1 -> 0 | K79: =(+IFERROR(VLOOKUP($A79,'[152]BG (2)'!$B$9:$J$570,9,FALSE),0))*-1 -> -16246123043 | P79: =J79+K79 -> -16246123043 | T79: =K79+J79 -> -16246123043 | W79: =+A79-#REF! -> #REF!
A80: 283511 | B80: AMORT. AMENAGEMENT DE BUREAUX | C80: ANC2838 | D80: =+LEFT(A80,2) -> 28 | F80: =(+IFERROR(VLOOKUP($A80,'[152]BG (2)'!$B$9:$J$570,4,FALSE),0))*1 -> 0 | G80: =(+IFERROR(VLOOKUP($A80,'[152]BG (2)'!$B$9:$J$570,5,FALSE),0))*-1 -> -753952256 | H80: =(+IFERROR(VLOOKUP($A80,'[152]BG (2)'!$B$9:$J$570,6,FALSE),0))*1 -> 0 | I80: =(+IFERROR(VLOOKUP($A80,'[152]BG (2)'!$B$9:$J$570,7,FALSE),0))*-1 -> -34373497 | J80: =(+IFERROR(VLOOKUP($A80,'[152]BG (2)'!$B$9:$J$570,8,FALSE),0))*1 -> 0 | K80: =(+IFERROR(VLOOKUP($A80,'[152]BG (2)'!$B$9:$J$570,9,FALSE),0))*-1 -> -788325753 | P80: =J80+K80 -> -788325753 | T80: =K80+J80 -> -788325753 | W80: =+A80-#REF! -> #REF!
A81: 283512 | B81: AMORT. AMENAGEMENT AGENCES | C81: ANC2838 | D81: =+LEFT(A81,2) -> 28 | F81: =(+IFERROR(VLOOKUP($A81,'[152]BG (2)'!$B$9:$J$570,4,FALSE),0))*1 -> 0 | G81: =(+IFERROR(VLOOKUP($A81,'[152]BG (2)'!$B$9:$J$570,5,FALSE),0))*-1 -> -419004212 | H81: =(+IFERROR(VLOOKUP($A81,'[152]BG (2)'!$B$9:$J$570,6,FALSE),0))*1 -> 0 | I81: =(+IFERROR(VLOOKUP($A81,'[152]BG (2)'!$B$9:$J$570,7,FALSE),0))*-1 -> -30484960 | J81: =(+IFERROR(VLOOKUP($A81,'[152]BG (2)'!$B$9:$J$570,8,FALSE),0))*1 -> 0 | K81: =(+IFERROR(VLOOKUP($A81,'[152]BG (2)'!$B$9:$J$570,9,FALSE),0))*-1 -> -449489172 | P81: =J81+K81 -> -449489172 | T81: =K81+J81 -> -449489172 | W81: =+A81-#REF! -> #REF!
A82: 283513 | B82: AMORT. AMENAGEMENT RESIDENCE | C82: ANC2838 | D82: =+LEFT(A82,2) -> 28 | F82: =(+IFERROR(VLOOKUP($A82,'[152]BG (2)'!$B$9:$J$570,4,FALSE),0))*1 -> 0 | G82: =(+IFERROR(VLOOKUP($A82,'[152]BG (2)'!$B$9:$J$570,5,FALSE),0))*-1 -> -1016034 | H82: =(+IFERROR(VLOOKUP($A82,'[152]BG (2)'!$B$9:$J$570,6,FALSE),0))*1 -> 0 | I82: =(+IFERROR(VLOOKUP($A82,'[152]BG (2)'!$B$9:$J$570,7,FALSE),0))*-1 -> -92956 | J82: =(+IFERROR(VLOOKUP($A82,'[152]BG (2)'!$B$9:$J$570,8,FALSE),0))*1 -> 0 | K82: =(+IFERROR(VLOOKUP($A82,'[152]BG (2)'!$B$9:$J$570,9,FALSE),0))*-1 -> -1108990 | P82: =J82+K82 -> -1108990 | T82: =K82+J82 -> -1108990 | W82: =+A82-#REF! -> #REF!
A83: 283580 | B83: AMORT. AUTRES AMENAGEMENTS | C83: ANC2838 | D83: =+LEFT(A83,2) -> 28 | F83: =(+IFERROR(VLOOKUP($A83,'[152]BG (2)'!$B$9:$J$570,4,FALSE),0))*1 -> 0 | G83: =(+IFERROR(VLOOKUP($A83,'[152]BG (2)'!$B$9:$J$570,5,FALSE),0))*-1 -> -37590227 | H83: =(+IFERROR(VLOOKUP($A83,'[152]BG (2)'!$B$9:$J$570,6,FALSE),0))*1 -> 0 | I83: =(+IFERROR(VLOOKUP($A83,'[152]BG (2)'!$B$9:$J$570,7,FALSE),0))*-1 -> -272767 | J83: =(+IFERROR(VLOOKUP($A83,'[152]BG (2)'!$B$9:$J$570,8,FALSE),0))*1 -> 0 | K83: =(+IFERROR(VLOOKUP($A83,'[152]BG (2)'!$B$9:$J$570,9,FALSE),0))*-1 -> -37862994 | P83: =J83+K83 -> -37862994 | T83: =K83+J83 -> -37862994 | W83: =+A83-#REF! -> #REF!
A84: 283820 | B84: AMORT. DIVERS INSTALLATIONS ET | C84: ANC2838 | D84: =+LEFT(A84,2) -> 28 | F84: =(+IFERROR(VLOOKUP($A84,'[152]BG (2)'!$B$9:$J$570,4,FALSE),0))*1 -> 0 | G84: =(+IFERROR(VLOOKUP($A84,'[152]BG (2)'!$B$9:$J$570,5,FALSE),0))*-1 -> -102123453 | H84: =(+IFERROR(VLOOKUP($A84,'[152]BG (2)'!$B$9:$J$570,6,FALSE),0))*1 -> 0 | I84: =(+IFERROR(VLOOKUP($A84,'[152]BG (2)'!$B$9:$J$570,7,FALSE),0))*-1 -> 14578002 | J84: =(+IFERROR(VLOOKUP($A84,'[152]BG (2)'!$B$9:$J$570,8,FALSE),0))*1 -> 0 | K84: =(+IFERROR(VLOOKUP($A84,'[152]BG (2)'!$B$9:$J$570,9,FALSE),0))*-1 -> -87545451 | P84: =J84+K84 -> -87545451 | T84: =K84+J84 -> -87545451 | W84: =+A84-#REF! -> #REF!
A85: 284111 | B85: AMORT. MATERIEL DE TRANSMISSIO | C85: ANC2833 | D85: =+LEFT(A85,2) -> 28 | F85: =(+IFERROR(VLOOKUP($A85,'[152]BG (2)'!$B$9:$J$570,4,FALSE),0))*1 -> 0 | G85: =(+IFERROR(VLOOKUP($A85,'[152]BG (2)'!$B$9:$J$570,5,FALSE),0))*-1 -> -26244926120 | H85: =(+IFERROR(VLOOKUP($A85,'[152]BG (2)'!$B$9:$J$570,6,FALSE),0))*1 -> 0 | I85: =(+IFERROR(VLOOKUP($A85,'[152]BG (2)'!$B$9:$J$570,7,FALSE),0))*-1 -> -2876439751 | J85: =(+IFERROR(VLOOKUP($A85,'[152]BG (2)'!$B$9:$J$570,8,FALSE),0))*1 -> 0 | K85: =(+IFERROR(VLOOKUP($A85,'[152]BG (2)'!$B$9:$J$570,9,FALSE),0))*-1 -> -29121365871 | P85: =J85+K85 -> -29121365871 | T85: =K85+J85 -> -29121365871 | W85: =+A85-#REF! -> #REF!
A86: 284112 | B86: AMORT. MATERIEL DE TRANSMISSIO | C86: ANC2833 | D86: =+LEFT(A86,2) -> 28 | F86: =(+IFERROR(VLOOKUP($A86,'[152]BG (2)'!$B$9:$J$570,4,FALSE),0))*1 -> 0 | G86: =(+IFERROR(VLOOKUP($A86,'[152]BG (2)'!$B$9:$J$570,5,FALSE),0))*-1 -> -18133797830 | H86: =(+IFERROR(VLOOKUP($A86,'[152]BG (2)'!$B$9:$J$570,6,FALSE),0))*1 -> 0 | I86: =(+IFERROR(VLOOKUP($A86,'[152]BG (2)'!$B$9:$J$570,7,FALSE),0))*-1 -> -1398159653 | J86: =(+IFERROR(VLOOKUP($A86,'[152]BG (2)'!$B$9:$J$570,8,FALSE),0))*1 -> 0 | K86: =(+IFERROR(VLOOKUP($A86,'[152]BG (2)'!$B$9:$J$570,9,FALSE),0))*-1 -> -19531957483 | P86: =J86+K86 -> -19531957483 | T86: =K86+J86 -> -19531957483 | W86: =+A86-#REF! -> #REF!
A87: 284113 | B87: AMORT. MATERIEL DE COMMUTATION | C87: ANC2833 | D87: =+LEFT(A87,2) -> 28 | F87: =(+IFERROR(VLOOKUP($A87,'[152]BG (2)'!$B$9:$J$570,4,FALSE),0))*1 -> 0 | G87: =(+IFERROR(VLOOKUP($A87,'[152]BG (2)'!$B$9:$J$570,5,FALSE),0))*-1 -> -12076651351 | H87: =(+IFERROR(VLOOKUP($A87,'[152]BG (2)'!$B$9:$J$570,6,FALSE),0))*1 -> 0 | I87: =(+IFERROR(VLOOKUP($A87,'[152]BG (2)'!$B$9:$J$570,7,FALSE),0))*-1 -> -1030078730 | J87: =(+IFERROR(VLOOKUP($A87,'[152]BG (2)'!$B$9:$J$570,8,FALSE),0))*1 -> 0 | K87: =(+IFERROR(VLOOKUP($A87,'[152]BG (2)'!$B$9:$J$570,9,FALSE),0))*-1 -> -13106730081 | P87: =J87+K87 -> -13106730081 | T87: =K87+J87 -> -13106730081 | W87: =+A87-#REF! -> #REF!
A88: 284114 | B88: AMORT. MATERIEL SVA | C88: ANC2833 | D88: =+LEFT(A88,2) -> 28 | F88: =(+IFERROR(VLOOKUP($A88,'[152]BG (2)'!$B$9:$J$570,4,FALSE),0))*1 -> 0 | G88: =(+IFERROR(VLOOKUP($A88,'[152]BG (2)'!$B$9:$J$570,5,FALSE),0))*-1 -> -40716031 | H88: =(+IFERROR(VLOOKUP($A88,'[152]BG (2)'!$B$9:$J$570,6,FALSE),0))*1 -> 0 | I88: =(+IFERROR(VLOOKUP($A88,'[152]BG (2)'!$B$9:$J$570,7,FALSE),0))*-1 -> 19 | J88: =(+IFERROR(VLOOKUP($A88,'[152]BG (2)'!$B$9:$J$570,8,FALSE),0))*1 -> 0 | K88: =(+IFERROR(VLOOKUP($A88,'[152]BG (2)'!$B$9:$J$570,9,FALSE),0))*-1 -> -40716012 | P88: =J88+K88 -> -40716012 | T88: =K88+J88 -> -40716012 | W88: =+A88-#REF! -> #REF!
... A98: 294000 | B98: Provision pour dépréciation du | C98: ANC2833 | D98: =+LEFT(A98,2) -> 29 | F98: =(+IFERROR(VLOOKUP($A98,'[152]BG (2)'!$B$9:$J$570,4,FALSE),0))*1 -> 0 | G98: =(+IFERROR(VLOOKUP($A98,'[152]BG (2)'!$B$9:$J$570,5,FALSE),0))*-1 -> -1472646224 | H98: =(+IFERROR(VLOOKUP($A98,'[152]BG (2)'!$B$9:$J$570,6,FALSE),0))*1 -> 1458883577 | I98: =(+IFERROR(VLOOKUP($A98,'[152]BG (2)'!$B$9:$J$570,7,FALSE),0))*-1 -> -1133004221 | J98: =(+IFERROR(VLOOKUP($A98,'[152]BG (2)'!$B$9:$J$570,8,FALSE),0))*1 -> 0 | K98: =(+IFERROR(VLOOKUP($A98,'[152]BG (2)'!$B$9:$J$570,9,FALSE),0))*-1 -> -1146766868 | P98: =J98+K98 -> -1146766868 | T98: =K98+J98 -> -1146766868 | W98: =+A98-#REF! -> #REF!
A99: 311100 | B99: STOCKS DE TERMINAUX | C99: AC3110 | D99: =+LEFT(A99,2) -> 31 | F99: =(+IFERROR(VLOOKUP($A99,'[152]BG (2)'!$B$9:$J$570,4,FALSE),0))*1 -> 586388365 | G99: =(+IFERROR(VLOOKUP($A99,'[152]BG (2)'!$B$9:$J$570,5,FALSE),0))*-1 -> 0 | H99: =(+IFERROR(VLOOKUP($A99,'[152]BG (2)'!$B$9:$J$570,6,FALSE),0))*1 -> -371325442 | I99: =(+IFERROR(VLOOKUP($A99,'[152]BG (2)'!$B$9:$J$570,7,FALSE),0))*-1 -> 0 | J99: =(+IFERROR(VLOOKUP($A99,'[152]BG (2)'!$B$9:$J$570,8,FALSE),0))*1 -> 215062923 | K99: =(+IFERROR(VLOOKUP($A99,'[152]BG (2)'!$B$9:$J$570,9,FALSE),0))*-1 -> 0 | P99: =J99+K99 -> 215062923 | T99: =K99+J99 -> 215062923 | V99: 342965636 | W99: =+A99-#REF! -> #REF!
A100: 311200 | B100: STOCKS D'ACCESSOIRES | C100: AC3110 | D100: =+LEFT(A100,2) -> 31 | F100: =(+IFERROR(VLOOKUP($A100,'[152]BG (2)'!$B$9:$J$570,4,FALSE),0))*1 -> 571175110 | G100: =(+IFERROR(VLOOKUP($A100,'[152]BG (2)'!$B$9:$J$570,5,FALSE),0))*-1 -> 0 | H100: =(+IFERROR(VLOOKUP($A100,'[152]BG (2)'!$B$9:$J$570,6,FALSE),0))*1 -> -32489474 | I100: =(+IFERROR(VLOOKUP($A100,'[152]BG (2)'!$B$9:$J$570,7,FALSE),0))*-1 -> 0 | J100: =(+IFERROR(VLOOKUP($A100,'[152]BG (2)'!$B$9:$J$570,8,FALSE),0))*1 -> 538685636 | K100: =(+IFERROR(VLOOKUP($A100,'[152]BG (2)'!$B$9:$J$570,9,FALSE),0))*-1 -> 0 | P100: =J100+K100 -> 538685636 | T100: =K100+J100 -> 538685636 | W100: =+A100-#REF! -> #REF!
A101: 312100 | B101: STOCKS DE CARTES SIM | C101: A reclasser en IFRS | D101: =+LEFT(A101,2) -> 31 | F101: =(+IFERROR(VLOOKUP($A101,'[152]BG (2)'!$B$9:$J$570,4,FALSE),0))*1 -> 232661522 | G101: =(+IFERROR(VLOOKUP($A101,'[152]BG (2)'!$B$9:$J$570,5,FALSE),0))*-1 -> 0 | H101: =(+IFERROR(VLOOKUP($A101,'[152]BG (2)'!$B$9:$J$570,6,FALSE),0))*1 -> 193392009 | I101: =(+IFERROR(VLOOKUP($A101,'[152]BG (2)'!$B$9:$J$570,7,FALSE),0))*-1 -> 0 | J101: =(+IFERROR(VLOOKUP($A101,'[152]BG (2)'!$B$9:$J$570,8,FALSE),0))*1 -> 426053531 | K101: =(+IFERROR(VLOOKUP($A101,'[152]BG (2)'!$B$9:$J$570,9,FALSE),0))*-1 -> 0 | P101: =J101+K101 -> 426053531 | T101: =K101+J101 -> 426053531 | W101: =+A101-#REF! -> #REF!
A102: 312110 | B102: STOCKS DE CARTES KIT | C102: A reclasser en IFRS | D102: =+LEFT(A102,2) -> 31 | F102: =(+IFERROR(VLOOKUP($A102,'[152]BG (2)'!$B$9:$J$570,4,FALSE),0))*1 -> 0 | G102: =(+IFERROR(VLOOKUP($A102,'[152]BG (2)'!$B$9:$J$570,5,FALSE),0))*-1 -> 0 | H102: =(+IFERROR(VLOOKUP($A102,'[152]BG (2)'!$B$9:$J$570,6,FALSE),0))*1 -> 40262537 | I102: =(+IFERROR(VLOOKUP($A102,'[152]BG (2)'!$B$9:$J$570,7,FALSE),0))*-1 -> 0 | J102: =(+IFERROR(VLOOKUP($A102,'[152]BG (2)'!$B$9:$J$570,8,FALSE),0))*1 -> 40262537 | K102: =(+IFERROR(VLOOKUP($A102,'[152]BG (2)'!$B$9:$J$570,9,FALSE),0))*-1 -> 0 | P102: =J102+K102 -> 40262537 | T102: =K102+J102 -> 40262537 | W102: =+A102-#REF! -> #REF!
A103: 312200 | B103: STOCKS DE CARTES @SIM | C103: A reclasser en IFRS | D103: =+LEFT(A103,2) -> 31 | F103: =(+IFERROR(VLOOKUP($A103,'[152]BG (2)'!$B$9:$J$570,4,FALSE),0))*1 -> 0 | G103: =(+IFERROR(VLOOKUP($A103,'[152]BG (2)'!$B$9:$J$570,5,FALSE),0))*-1 -> 0 | H103: =(+IFERROR(VLOOKUP($A103,'[152]BG (2)'!$B$9:$J$570,6,FALSE),0))*1 -> 0 | I103: =(+IFERROR(VLOOKUP($A103,'[152]BG (2)'!$B$9:$J$570,7,FALSE),0))*-1 -> 0 | J103: =(+IFERROR(VLOOKUP($A103,'[152]BG (2)'!$B$9:$J$570,8,FALSE),0))*1 -> 0 | K103: =(+IFERROR(VLOOKUP($A103,'[152]BG (2)'!$B$9:$J$570,9,FALSE),0))*-1 -> 0 | P103: =J103+K103 -> 0 | T103: =K103+J103 -> 0 | W103: =+A103-#REF! -> #REF!
A104: 313000 | B104: STOCKS DE CARTES DE RECHARGES | C104: AC3110 | D104: =+LEFT(A104,2) -> 31 | F104: =(+IFERROR(VLOOKUP($A104,'[152]BG (2)'!$B$9:$J$570,4,FALSE),0))*1 -> 6862247 | G104: =(+IFERROR(VLOOKUP($A104,'[152]BG (2)'!$B$9:$J$570,5,FALSE),0))*-1 -> 0 | H104: =(+IFERROR(VLOOKUP($A104,'[152]BG (2)'!$B$9:$J$570,6,FALSE),0))*1 -> -570327 | I104: =(+IFERROR(VLOOKUP($A104,'[152]BG (2)'!$B$9:$J$570,7,FALSE),0))*-1 -> 0 | J104: =(+IFERROR(VLOOKUP($A104,'[152]BG (2)'!$B$9:$J$570,8,FALSE),0))*1 -> 6291920 | K104: =(+IFERROR(VLOOKUP($A104,'[152]BG (2)'!$B$9:$J$570,9,FALSE),0))*-1 -> 0 | P104: =J104+K104 -> 6291920 | T104: =K104+J104 -> 6291920 | W104: =+A104-#REF! -> #REF!
A105: 331100 | B105: STOCKS DE PIECES DETACHEES ETB | C105: AC3110 | D105: =+LEFT(A105,2) -> 33 | F105: =(+IFERROR(VLOOKUP($A105,'[152]BG (2)'!$B$9:$J$570,4,FALSE),0))*1 -> 514817795 | G105: =(+IFERROR(VLOOKUP($A105,'[152]BG (2)'!$B$9:$J$570,5,FALSE),0))*-1 -> 0 | H105: =(+IFERROR(VLOOKUP($A105,'[152]BG (2)'!$B$9:$J$570,6,FALSE),0))*1 -> 119933792 | I105: =(+IFERROR(VLOOKUP($A105,'[152]BG (2)'!$B$9:$J$570,7,FALSE),0))*-1 -> 0 | J105: =(+IFERROR(VLOOKUP($A105,'[152]BG (2)'!$B$9:$J$570,8,FALSE),0))*1 -> 634751587 | K105: =(+IFERROR(VLOOKUP($A105,'[152]BG (2)'!$B$9:$J$570,9,FALSE),0))*-1 -> 0 | P105: =J105+K105 -> 634751587 | T105: =K105+J105 -> 634751587 | W105: =+A105-#REF! -> #REF!
A106: 331110 | B106: STK DE PIECES DETACHEES GNMS | C106: A reclasser en IFRS | D106: =+LEFT(A106,2) -> 33 | F106: =(+IFERROR(VLOOKUP($A106,'[152]BG (2)'!$B$9:$J$570,4,FALSE),0))*1 -> 305492626 | G106: =(+IFERROR(VLOOKUP($A106,'[152]BG (2)'!$B$9:$J$570,5,FALSE),0))*-1 -> 0 | H106: =(+IFERROR(VLOOKUP($A106,'[152]BG (2)'!$B$9:$J$570,6,FALSE),0))*1 -> 36058335 | I106: =(+IFERROR(VLOOKUP($A106,'[152]BG (2)'!$B$9:$J$570,7,FALSE),0))*-1 -> 0 | J106: =(+IFERROR(VLOOKUP($A106,'[152]BG (2)'!$B$9:$J$570,8,FALSE),0))*1 -> 341550961 | K106: =(+IFERROR(VLOOKUP($A106,'[152]BG (2)'!$B$9:$J$570,9,FALSE),0))*-1 -> 0 | P106: =J106+K106 -> 341550961 | T106: =K106+J106 -> 341550961 | W106: =+A106-#REF! -> #REF!
A107: 331200 | B107: STOCKS DE CARBURANTS SITES | C107: AC3110 | D107: =+LEFT(A107,2) -> 33 | F107: =(+IFERROR(VLOOKUP($A107,'[152]BG (2)'!$B$9:$J$570,4,FALSE),0))*1 -> 435820871 | G107: =(+IFERROR(VLOOKUP($A107,'[152]BG (2)'!$B$9:$J$570,5,FALSE),0))*-1 -> 0 | H107: =(+IFERROR(VLOOKUP($A107,'[152]BG (2)'!$B$9:$J$570,6,FALSE),0))*1 -> 20982830 | I107: =(+IFERROR(VLOOKUP($A107,'[152]BG (2)'!$B$9:$J$570,7,FALSE),0))*-1 -> 0 | J107: =(+IFERROR(VLOOKUP($A107,'[152]BG (2)'!$B$9:$J$570,8,FALSE),0))*1 -> 456803701 | K107: =(+IFERROR(VLOOKUP($A107,'[152]BG (2)'!$B$9:$J$570,9,FALSE),0))*-1 -> 0 | P107: =J107+K107 -> 456803701 | T107: =K107+J107 -> 456803701 | W107: =+A107-#REF! -> #REF!
A108: 334000 | B108: STOCK DE FOURNITURES DE BUREAU | C108: AC3110 | D108: =+LEFT(A108,2) -> 33 | F108: =(+IFERROR(VLOOKUP($A108,'[152]BG (2)'!$B$9:$J$570,4,FALSE),0))*1 -> 247711582 | G108: =(+IFERROR(VLOOKUP($A108,'[152]BG (2)'!$B$9:$J$570,5,FALSE),0))*-1 -> 0 | H108: =(+IFERROR(VLOOKUP($A108,'[152]BG (2)'!$B$9:$J$570,6,FALSE),0))*1 -> -203687807 | I108: =(+IFERROR(VLOOKUP($A108,'[152]BG (2)'!$B$9:$J$570,7,FALSE),0))*-1 -> 0 | J108: =(+IFERROR(VLOOKUP($A108,'[152]BG (2)'!$B$9:$J$570,8,FALSE),0))*1 -> 44023775 | K108: =(+IFERROR(VLOOKUP($A108,'[152]BG (2)'!$B$9:$J$570,9,FALSE),0))*-1 -> 0 | P108: =J108+K108 -> 44023775 | T108: =K108+J108 -> 44023775 | W108: =+A108-#REF! -> #REF!
A109: 334100 | B109: STOCK DE FOURNITURE INFORMATIQ | C109: AC3110 | D109: =+LEFT(A109,2) -> 33 | F109: =(+IFERROR(VLOOKUP($A109,'[152]BG (2)'!$B$9:$J$570,4,FALSE),0))*1 -> 144905863 | G109: =(+IFERROR(VLOOKUP($A109,'[152]BG (2)'!$B$9:$J$570,5,FALSE),0))*-1 -> 0 | H109: =(+IFERROR(VLOOKUP($A109,'[152]BG (2)'!$B$9:$J$570,6,FALSE),0))*1 -> -7859827 | I109: =(+IFERROR(VLOOKUP($A109,'[152]BG (2)'!$B$9:$J$570,7,FALSE),0))*-1 -> 0 | J109: =(+IFERROR(VLOOKUP($A109,'[152]BG (2)'!$B$9:$J$570,8,FALSE),0))*1 -> 137046036 | K109: =(+IFERROR(VLOOKUP($A109,'[152]BG (2)'!$B$9:$J$570,9,FALSE),0))*-1 -> 0 | P109: =J109+K109 -> 137046036 | T109: =K109+J109 -> 137046036 | W109: =+A109-#REF! -> #REF!
A110: 338100 | B110: STOCK D'ETRENNE | C110: AC3110 | D110: =+LEFT(A110,2) -> 33 | F110: =(+IFERROR(VLOOKUP($A110,'[152]BG (2)'!$B$9:$J$570,4,FALSE),0))*1 -> 157766375 | G110: =(+IFERROR(VLOOKUP($A110,'[152]BG (2)'!$B$9:$J$570,5,FALSE),0))*-1 -> 0 | H110: =(+IFERROR(VLOOKUP($A110,'[152]BG (2)'!$B$9:$J$570,6,FALSE),0))*1 -> -11404790 | I110: =(+IFERROR(VLOOKUP($A110,'[152]BG (2)'!$B$9:$J$570,7,FALSE),0))*-1 -> 0 | J110: =(+IFERROR(VLOOKUP($A110,'[152]BG (2)'!$B$9:$J$570,8,FALSE),0))*1 -> 146361585 | K110: =(+IFERROR(VLOOKUP($A110,'[152]BG (2)'!$B$9:$J$570,9,FALSE),0))*-1 -> 0 | P110: =J110+K110 -> 146361585 | T110: =K110+J110 -> 146361585 | W110: =+A110-#REF! -> #REF!
...

Sheet Bilan Actif
A1: Sommaire
C2: Bilan - Actif OHADA | M2: =10^6 -> 1000000
C3: En FCFA
A5: Réf. | B5: ACTIF | D5: =+Cover!Y18 -> 44926 | G5: =+Cover!Y16 -> 44562 | J5: Variation
D6: Brut | E6: Amort/Prov | F6: Net | G6: Brut | H6: Amort/Prov | I6: Net | J6: Brut | K6: Amort/Prov | L6: Net
J7: =+D7-G7 -> 0 | K7: =+E7-H7 -> 0 | L7: =+F7-I7 -> 0
A8: AA | B8: Charges immobilisées | D8: =+D9+D10 -> 0 | E8: =+E9+E10 -> 0 | F8: =D8-E8 -> 0 | G8: =+G9+G10 -> 0 | H8: =+H9+H10 -> 0 | I8: =G8-H8 -> 0 | J8: =+D8-G8 -> 0 | K8: =+E8-H8 -> 0 | L8: =+F8-I8 -> 0 | M8: =+G8-J8 -> 0
A9: AB | B9: Frais d'établissement et charges à répartir | D9: 0 | F9: =D9-E9 -> 0 | G9: 0 | I9: =G9-H9 -> 0 | J9: =+D9-G9 -> 0 | K9: =+E9-H9 -> 0 | L9: =+F9-I9 -> 0 | M9: =+G9-J9 -> 0
A10: AC | B10: Primes de remboursement des obligations | F10: =D10-E10 -> 0 | I10: =G10-H10 -> 0 | J10: =+D10-G10 -> 0 | K10: =+E10-H10 -> 0 | L10: =+F10-I10 -> 0 | M10: =+G10-J10 -> 0
A11: AD | B11: Immobilisations incorporelles | D11: =+SUM(D12:D15) -> 146520173576 | E11: =+SUM(E12:E15) -> 107413659810 | F11: =D11-E11 -> 39106513766 | G11: =+SUM(G12:G15) -> 146520173576 | H11: =+SUM(H12:H15) -> 107413659810 | I11: =G11-H11 -> 39106513766 | J11: =+D11-G11 -> 0 | K11: =+E11-H11 -> 0 | L11: =+F11-I11 -> 0 | M11: =+G11-J11 -> 146520173576
A12: AE | B12: Frais de recherche et de développement | F12: =D12-E12 -> 0 | I12: =G12-H12 -> 0 | J12: =+D12-G12 -> 0 | K12: =+E12-H12 -> 0 | L12: =+F12-I12 -> 0 | M12: =+G12-J12 -> 0
A13: AF | B13: Brevets, licences, logiciels | D13: =[152]ACTIF!$D$12 -> 146520173576 | E13: =[152]ACTIF!$E$12 -> 107413659810 | F13: =D13-E13 -> 39106513766 | G13: =[152]ACTIF!$D$12 -> 146520173576 | H13: =[152]ACTIF!$E$12 -> 107413659810 | I13: =G13-H13 -> 39106513766 | J13: =+D13-G13 -> 0 | K13: =+E13-H13 -> 0 | L13: =+F13-I13 -> 0 | M13: =+G13-J13 -> 146520173576
A14: AG | B14: Fonds commercial | F14: =D14-E14 -> 0 | I14: =G14-H14 -> 0 | J14: =+D14-G14 -> 0 | L14: =+F14-I14 -> 0 | M14: =+G14-J14 -> 0
A15: AH | B15: Autres immobilisations incorporelles | F15: =D15-E15 -> 0 | I15: =G15-H15 -> 0 | J15: =+D15-G15 -> 0 | K15: =+E15-H15 -> 0 | L15: =+F15-I15 -> 0 | M15: =+G15-J15 -> 0
A16: AI | B16: Immobilisations corporelles | D16: =SUM(D17:D22) -> 179709685658 | E16: =SUM(E17:E22) -> 113100503569 | F16: =D16-E16 -> 66609182089 | G16: =SUM(G17:G22) -> 179709685658 | H16: =SUM(H17:H22) -> 113100503569 | I16: =G16-H16 -> 66609182089 | J16: =SUM(J17:J22) -> 0 | K16: =SUM(K17:K22) -> 0 | L16: =SUM(L17:L22) -> 0 | M16: =SUM(M17:M22) -> 179709685658
A17: AJ | B17: Terrains | D17: =[152]ACTIF!$D$16 -> 3170092329 | E17: =[152]ACTIF!$E$16 -> 0 | F17: =D17-E17 -> 3170092329 | G17: =[152]ACTIF!$D$16 -> 3170092329 | H17: =[152]ACTIF!$E$16 -> 0 | I17: =G17-H17 -> 3170092329 | J17: =+D17-G17 -> 0 | K17: =+E17-H17 -> 0 | L17: =+F17-I17 -> 0 | M17: =+G17-J17 -> 3170092329
A18: AK | B18: Bâtiments | D18: =[152]ACTIF!$D$18 -> 1675459071 | E18: =[152]ACTIF!$E$18 -> 53350355 | F18: =D18-E18 -> 1622108716 | G18: =[152]ACTIF!$D$18 -> 1675459071 | H18: =[152]ACTIF!$E$18 -> 53350355 | I18: =G18-H18 -> 1622108716 | J18: =+D18-G18 -> 0 | K18: =+E18-H18 -> 0 | L18: =+F18-I18 -> 0 | M18: =+G18-J18 -> 1675459071
A19: AL | B19: Installations et agencements | D19: =[152]ACTIF!$D$20 -> 61892732272 | E19: =[152]ACTIF!$E$20 -> 41823483292 | F19: =D19-E19 -> 20069248980 | G19: =[152]ACTIF!$D$20 -> 61892732272 | H19: =[152]ACTIF!$E$20 -> 41823483292 | I19: =G19-H19 -> 20069248980 | J19: =+D19-G19 -> 0 | K19: =+E19-H19 -> 0 | L19: =+F19-I19 -> 0 | M19: =+G19-J19 -> 61892732272
A20: AM | B20: Matériel | D20: =[152]ACTIF!$D$21 -> 111780777995 | E20: =[152]ACTIF!$E$21 -> 70508337317 | F20: =D20-E20 -> 41272440678 | G20: =[152]ACTIF!$D$21 -> 111780777995 | H20: =[152]ACTIF!$E$21 -> 70508337317 | I20: =G20-H20 -> 41272440678 | J20: =+D20-G20 -> 0 | K20: =+E20-H20 -> 0 | L20: =+F20-I20 -> 0 | M20: =+G20-J20 -> 111780777995
A21: AN | B21: Matériel de transport | D21: =[152]ACTIF!$D$22 -> 715895198 | E21: =[152]ACTIF!$E$22 -> 715332605 | F21: =D21-E21 -> 562593 | G21: =[152]ACTIF!$D$22 -> 715895198 | H21: =[152]ACTIF!$E$22 -> 715332605 | I21: =G21-H21 -> 562593 | J21: =+D21-G21 -> 0 | K21: =+E21-H21 -> 0 | L21: =+F21-I21 -> 0 | M21: =+G21-J21 -> 715895198
A22: AP | B22: Avances et acomptes versés sur immobilisations | D22: =[152]ACTIF!$D$23 -> 474728793 | F22: =D22-E22 -> 474728793 | G22: =[152]ACTIF!$D$23 -> 474728793 | I22: =G22-H22 -> 474728793 | J22: =+D22-G22 -> 0 | K22: =+E22-H22 -> 0 | L22: =+F22-I22 -> 0 | M22: =+G22-J22 -> 474728793
A23: AQ | B23: Immobilisations financières | D23: =SUM(D24:D25) -> 732076630 | E23: =SUM(E24:E25) -> 0 | F23: =D23-E23 -> 732076630 | G23: =SUM(G24:G25) -> 732076630 | H23: =SUM(H24:H25) -> 0 | I23: =G23-H23 -> 732076630 | J23: =SUM(J24:J25) -> 0 | K23: =SUM(K24:K25) -> 0 | L23: =SUM(L24:L25) -> 0 | M23: =SUM(M24:M25) -> 732076630
A24: AR | B24: Titres de participation | D24: =[152]ACTIF!$D$25 -> 0 | F24: =D24-E24 -> 0 | G24: =[152]ACTIF!$D$25 -> 0 | I24: =G24-H24 -> 0 | J24: =+D24-G24 -> 0 | K24: =+E24-H24 -> 0 | L24: =+F24-I24 -> 0 | M24: =+G24-J24 -> 0
A25: AS | B25: Autres immobilisations financières | D25: =[152]ACTIF!$D$26 -> 732076630 | F25: =D25-E25 -> 732076630 | G25: =[152]ACTIF!$D$26 -> 732076630 | I25: =G25-H25 -> 732076630 | J25: =+D25-G25 -> 0 | K25: =+E25-H25 -> 0 | L25: =+F25-I25 -> 0 | M25: =+G25-J25 -> 732076630
A26: AZ | B26: TOTAL ACTIF IMMOBILISE (I) | D26: =+D23+D16+D11+D8 -> 326961935864 | E26: =+E23+E16+E11+E8 -> 220514163379 | F26: =+F23+F16+F11+F8 -> 106447772485 | G26: =+G23+G16+G11+G8 -> 326961935864 | H26: =+H23+H16+H11+H8 -> 220514163379 | I26: =+I23+I16+I11+I8 -> 106447772485 | J26: =+D26-G26 -> 0 | K26: =+E26-H26 -> 0 | L26: =+F26-I26 -> 0 | M26: =+G26-J26 -> 326961935864
B27: ACTIF CIRCULANT | J27: =+D27-G27 -> 0 | K27: =+E27-H27 -> 0 | L27: =+F27-I27 -> 0 | M27: =+G27-J27 -> 0
A28: DH | B28: Actif circulant H. A. O. | D28: =[152]ACTIF!$D$28 -> 1307827431 | F28: =D28-E28 -> 1307827431 | G28: =[152]ACTIF!$D$28 -> 1307827431 | I28: =G28-H28 -> 1307827431 | J28: =+D28-G28 -> 0 | K28: =+E28-H28 -> 0 | L28: =+F28-I28 -> 0 | M28: =+G28-J28 -> 1307827431
A29: BB | B29: Stocks | D29: =[152]ACTIF!$D$29 -> 2986894192 | E29: =[152]ACTIF!$E$29 -> 539720702 | F29: =D29-E29 -> 2447173490 | G29: =[152]ACTIF!$D$29 -> 2986894192 | H29: =[152]ACTIF!$E$29 -> 539720702 | I29: =G29-H29 -> 2447173490 | J29: =+D29-G29 -> 0 | K29: =+E29-H29 -> 0 | L29: =+F29-I29 -> 0 | M29: =+G29-J29 -> 2986894192
A30: BC | B30: Marchandises | F30: =D30-E30 -> 0 | I30: =G30-H30 -> 0 | J30: =+D30-G30 -> 0 | K30: =+E30-H30 -> 0 | L30: =+F30-I30 -> 0 | M30: =+G30-J30 -> 0
A31: BD | B31: Matières premières et autres | F31: =D31-E31 -> 0 | I31: =G31-H31 -> 0 | J31: =+D31-G31 -> 0 | K31: =+E31-H31 -> 0 | L31: =+F31-I31 -> 0 | M31: =+G31-J31 -> 0
B32: Approvisionnements | F32: =D32-E32 -> 0 | I32: =G32-H32 -> 0 | J32: =+D32-G32 -> 0 | K32: =+E32-H32 -> 0 | L32: =+F32-I32 -> 0 | M32: =+G32-J32 -> 0
A33: BE | B33: En-cours | F33: =D33-E33 -> 0 | I33: =G33-H33 -> 0 | J33: =+D33-G33 -> 0 | K33: =+E33-H33 -> 0 | L33: =+F33-I33 -> 0 | M33: =+G33-J33 -> 0
A34: BF | B34: Produits fabriqués | F34: =D34-E34 -> 0 | I34: =G34-H34 -> 0 | J34: =+D34-G34 -> 0 | K34: =+E34-H34 -> 0 | L34: =+F34-I34 -> 0 | M34: =+G34-J34 -> 0
A35: BG | B35: Créances et emplois assimilés | D35: =+SUM(D36:D38) -> 41680074289 | E35: =+SUM(E36:E38) -> 4197508048 | F35: =D35-E35 -> 37482566241 | G35: =+SUM(G36:G38) -> 41680074289 | H35: =+SUM(H36:H38) -> 4197508048 | I35: =G35-H35 -> 37482566241 | J35: =+D35-G35 -> 0 | K35: =+E35-H35 -> 0 | L35: =+F35-I35 -> 0 | M35: =+G35-J35 -> 41680074289
A36: BH | B36: Fournisseurs, avances versées | D36: =+[152]ACTIF!$D$31 -> 1657769200 | F36: =D36-E36 -> 1657769200 | G36: =+[152]ACTIF!$D$31 -> 1657769200 | I36: =G36-H36 -> 1657769200 | J36: =+D36-G36 -> 0 | K36: =+E36-H36 -> 0 | L36: =+F36-I36 -> 0 | M36: =+G36-J36 -> 1657769200
A37: BI | B37: Clients | D37: =+[152]ACTIF!$D$32 -> 24885972671 | E37: =+[152]ACTIF!$E$32 -> 4197508048 | F37: =D37-E37 -> 20688464623 | G37: =+[152]ACTIF!$D$32 -> 24885972671 | H37: =+[152]ACTIF!$E$32 -> 4197508048 | I37: =G37-H37 -> 20688464623 | J37: =+D37-G37 -> 0 | K37: =+E37-H37 -> 0 | L37: =+F37-I37 -> 0 | M37: =+G37-J37 -> 24885972671
A38: BJ | B38: Autres créances | D38: =+[152]ACTIF!$D$33 -> 15136332418 | F38: =D38-E38 -> 15136332418 | G38: =+[152]ACTIF!$D$33 -> 15136332418 | I38: =G38-H38 -> 15136332418 | J38: =+D38-G38 -> 0 | K38: =+E38-H38 -> 0 | L38: =+F38-I38 -> 0 | M38: =+G38-J38 -> 15136332418
A39: BK | B39: TOTAL ACTIF CIRCULANT (II) | D39: =+D28+D29+D35 -> 45974795912 | E39: =+E28+E29+E35 -> 4737228750 | F39: =+F28+F29+F35 -> 41237567162 | G39: =+G28+G29+G35 -> 45974795912 | H39: =+H28+H29+H35 -> 4737228750 | I39: =+I28+I29+I35 -> 41237567162 | J39: =+D39-G39 -> 0 | K39: =+E39-H39 -> 0 | L39: =+F39-I39 -> 0 | M39: =+G39-J39 -> 45974795912
B40: TRESORERIE-ACTIF
A41: BQ | B41: Titres de placement | F41: =+D41-E41 -> 0 | I41: =+G41-H41 -> 0 | J41: =+D41-G41 -> 0 | K41: =+E41-H41 -> 0 | L41: =+F41-I41 -> 0 | M41: =+G41-J41 -> 0
A42: BR | B42: Valeurs à encaisser | D42: =+[152]ACTIF!$D$36 -> 10472865 | F42: =+D42-E42 -> 10472865 | G42: =+[152]ACTIF!$D$36 -> 10472865 | I42: =+G42-H42 -> 10472865 | J42: =+D42-G42 -> 0 | K42: =+E42-H42 -> 0 | L42: =+F42-I42 -> 0 | M42: =+G42-J42 -> 10472865
A43: BS | B43: Banques, chèques postaux, caisse | D43: =+[152]ACTIF!$D$37 -> 33018608137 | F43: =+D43-E43 -> 33018608137 | G43: =+[152]ACTIF!$D$37 -> 33018608137 | I43: =+G43-H43 -> 33018608137 | J43: =+D43-G43 -> 0 | K43: =+E43-H43 -> 0 | L43: =+F43-I43 -> 0 | M43: =+G43-J43 -> 33018608137
A44: BT | B44: TOTAL TRESORERIE-ACTIF (III) | D44: =+SUM(D41:D43) -> 33029081002 | E44: =+SUM(E41:E43) -> 0 | F44: =+SUM(F41:F43) -> 33029081002 | G44: =+SUM(G41:G43) -> 33029081002 | H44: =+SUM(H41:H43) -> 0 | I44: =+SUM(I41:I43) -> 33029081002 | J44: =+D44-G44 -> 0 | K44: =+E44-H44 -> 0 | L44: =+F44-I44 -> 0 | M44: =+G44-J44 -> 33029081002
A45: BU | B45: Ecarts de conversion-Actif (IV) | D45: =SUM(D46) -> 125992774 | F45: =+D45-E45 -> 125992774 | G45: =SUM(G46) -> 125992774 | I45: =G45-H45 -> 125992774 | J45: =+D45-G45 -> 0 | K45: =+E45-H45 -> 0 | L45: =+F45-I45 -> 0 | M45: =+G45-J45 -> 125992774
B46: (perte probable de change) | D46: =+[152]ACTIF!$D$39 -> 125992774 | F46: =+D46-E46 -> 125992774 | G46: =+[152]ACTIF!$D$39 -> 125992774 | I46: =G46-H46 -> 125992774 | J46: =+D46-G46 -> 0 | K46: =+E46-H46 -> 0 | L46: =+F46-I46 -> 0 | M46: =+G46-J46 -> 125992774
A47: BZ | B47: TOTAL GENERAL (I + II + III + IV) | D47: =+D44+D39+D26+D45 -> 406091805552 | E47: =+E44+E39+E26+E45 -> 225251392129 | F47: =+F44+F39+F26+F45 -> 180840413423 | G47: =+G44+G39+G26+G45 -> 406091805552 | H47: =+H44+H39+H26+H45 -> 225251392129 | I47: =+I44+I39+I26+I45 -> 180840413423 | J47: =+D47-G47 -> 0 | K47: =+E47-H47 -> 0 | L47: =+F47-I47 -> 0 | M47: =+G47-J47 -> 406091805552
F48: =F47-[152]ACTIF!$F$40 -> 0 | G48: =+G47-[152]ACTIF!$D$40 -> 0 | I48: =+I47-[152]ACTIF!$F$40 -> 0

Sheet Bilan Passif 
A1: Sommaire
B3: Bilan - Passif OHADA
A6: Réf. | B6: PASSIF | C6: =+Cover!Y18 -> 44926 | D6: =+Cover!Y16 -> 44562 | E6: Variation
A9: CA | B9: Capital | C9: =+[152]PASSIF!$D$10 -> 10408280000 | D9: =+[152]PASSIF!$D$10 -> 10408280000 | E9: =C9-D9 -> 0
A10: CB | B10: Actionnaires capital non appelé - | E10: =C10-D10 -> 0
A11: CC | B11: Primes et réserves | C11: =+SUM(C12:C16) -> -1228656692 | D11: =+SUM(D12:D16) -> -1228656692 | E11: =C11-D11 -> 0
A12: CD | B12: Primes d'apport, d'émission, de fusion | E12: =C12-D12 -> 0
A13: CE | B13: Ecarts de réévaluation | E13: =C13-D13 -> 0
A14: CF | B14: Réserves indisponibles | E14: =C14-D14 -> 0
A15: CG | B15: Réserves libres | E15: =C15-D15 -> 0
A16: CH | B16: Report à nouveau + ou - | C16: =+[152]PASSIF!$D$16 -> -1228656692 | D16: =+[152]PASSIF!$D$16 -> -1228656692 | E16: =C16-D16 -> 0
A17: C I | B17: Résultat net de l'exercice (bénéfice + ou perte -) | C17: =+[152]PASSIF!$D$17 -> 4778363684 | D17: =+[152]PASSIF!$D$17 -> 4778363684 | E17: =C17-D17 -> 0
A18: CK | B18: Autres capitaux propres | C18: =+C19+C20 -> 0 | D18: =+D19+D20 -> 0 | E18: =C18-D18 -> 0
A19: CL | B19: Subventions d'investissement | E19: =C19-D19 -> 0
A20: CM | B20: Provisions réglementées et fonds assimilés | E20: =C20-D20 -> 0
A21: CP | B21: TOTAL CAPITAUX PROPRES (I) | C21: =+C18+C17+C11+C10+C9 -> 13957986992 | D21: =+D18+D17+D11+D10+D9 -> 13957986992 | E21: =+C21-D21 -> 0
B22: DETTES FINANCIERES ET RESSOURCES
B23: ASSIMILEES (1)
A24: DA | B24: Emprunts | C24: =+[152]PASSIF!$D$21 -> 46196599329 | D24: =+[152]PASSIF!$D$21 -> 46196599329 | E24: =C24-D24 -> 0
A25: DB | B25: Dettes de crédit-bail et contrats assimilés | E25: =C25-D25 -> 0
A26: DC | B26: Dettes financières diverses | E26: =C26-D26 -> 0
A27: DD | B27: Provisions financières pour risques et charges | C27: =+[152]PASSIF!$D$23 -> 1119247874 | D27: =+[152]PASSIF!$D$23 -> 1119247874 | E27: =C27-D27 -> 0
A28: DF | B28: TOTAL DETTES FINANCIERES (II) | C28: =+SUM(C24:C27) -> 47315847203 | D28: =+SUM(D24:D27) -> 47315847203 | E28: =+C28-D28 -> 0
A30: DG | B30: TOTAL RESSOURCES STABLES (I + II) | C30: =+C28+C21 -> 61273834195 | D30: =+D28+D21 -> 61273834195 | E30: =+C30-D30 -> 0
B31: PASSIF CIRCULANT
A32: DH | B32: Dettes circulantes et ressources assimilées H.A.O. | C32: =+[152]PASSIF!$D$26 -> 20173765752 | D32: =+[152]PASSIF!$D$26 -> 20173765752 | E32: =+C32-D32 -> 0
A33: DI | B33: Clients, avances reçues | C33: =+[152]PASSIF!$D$27 -> 1266250396 | D33: =+[152]PASSIF!$D$27 -> 1266250396 | E33: =+C33-D33 -> 0
A34: DJ | B34: Fournisseurs d'exploitation | C34: =+[152]PASSIF!$D$28 -> 40919405808 | D34: =+[152]PASSIF!$D$28 -> 40919405808 | E34: =+C34-D34 -> 0
A35: DK | B35: Dettes fiscales | C35: =+[152]PASSIF!$D$29 -> 6711865534 | D35: =+[152]PASSIF!$D$29 -> 6711865534 | E35: =+C35-D35 -> 0
A36: DL | B36: Dettes sociales | E36: =+C36-D36 -> 0
A37: DM | B37: Autres dettes | C37: =+[152]PASSIF!$D$30 -> 34096023296 | D37: =+[152]PASSIF!$D$30 -> 34096023296 | E37: =+C37-D37 -> 0
A38: DN | B38: Risques provisionnés | C38: =+[152]PASSIF!$D$31 -> 212954781 | D38: =+[152]PASSIF!$D$31 -> 212954781 | E38: =+C38-D38 -> 0
A39: DP | B39: TOTAL PASSIF CIRCULANT (III) | C39: =+SUM(C32:C38) -> 103380265567 | D39: =+SUM(D32:D38) -> 103380265567 | E39: =+C39-D39 -> 0
B40: TRESORERIE - PASSIF
A41: DQ | B41: Banques, crédits d'escompte | C41: =+[152]PASSIF!$D$33 -> 52277096 | D41: =+[152]PASSIF!$D$33 -> 52277096 | E41: =+C41-D41 -> 0
A42: DR | B42: Banques, crédits de trésorerie | C42: =+[152]PASSIF!$D$34 -> 16044722077 | D42: =+[152]PASSIF!$D$34 -> 16044722077 | E42: =+C42-D42 -> 0
A43: DS | B43: Banques, découverts | E43: =+C43-D43 -> 0
A44: DT | B44: TOTAL TRESORERIE-PASSIF (IV) | C44: =+SUM(C41:C43) -> 16096999173 | D44: =+SUM(D41:D43) -> 16096999173 | E44: =+C44-D44 -> 0
A45: DU | B45: Ecarts de conversion-Passif (V) | C45: =C46 -> 89314488 | D45: =D46 -> 89314488 | E45: =+C45-D45 -> 0
B46: (gain probable de change) | C46: =+[152]PASSIF!$D$36 -> 89314488 | D46: =+[152]PASSIF!$D$36 -> 89314488
A47: DZ | B47: TOTAL GENERAL (I + II + III + IV + V) | C47: =+C45+C44+C39+C30 -> 180840413423 | D47: =+D45+D44+D39+D30 -> 180840413423 | E47: =+C47-D47 -> 0
A49: Ctrl Actif-Passif | C49: =+C47-'Bilan Actif'!F47 -> 0 | D49: =+D47-'Bilan Actif'!I47 -> 0

Sheet Compte de résultat
A1: Sommaire
C2: Compte de résultat OHADA
B3: En FCFA
A4: Réf. | B4: Compte de résultat | H4: =+Cover!Y18 -> 44926
B5: ACTIVITE D'EXPLOITATION
A6: TA | B6: Ventes de marchandises | H6: =+'[152]Compte de Résultat'!$E$9 -> 1124427867
A7: TC | B7: Ventes de produits fabriqués
A8: TD | B8: Travaux, services vendus | H8: =+'[152]Compte de Résultat'!$E$14 -> 103941367167
A9: TE | B9: Production stockée ou déstockage (+ ou -)
A10: TF | B10: Production immobilisée
A11: TH | B11: Produits accessoires | H11: =+'[152]Compte de Résultat'!$E$15 -> 1193512416
A12: T I | B12: CHIFFRE D'AFFAIRES (1) (TA + TC + TD + TH) | F12: =+H6+H7+H8+H11 -> 106259307450 | H12: =+H6+H7+H8+H11 -> 106259307450
A13: TJ | B13: (1) dont à l'exportation
A14: TK | B14: Subventions d'exploitation
A15: TL | B15: Autres produits | H15: =+'[152]Compte de Résultat'!$E$20 -> 1146703428
A16: TS | B16: Reprises de provisions | H16: =+'[152]Compte de Résultat'!$E$33 -> 1588912200
A17: TT | B17: Transferts de charges | H17: =+'[152]Compte de Résultat'!$E$21 -> 202462584
A18: TW | B18: Total des produits d'exploitation | H18: =+H6+H7+H8+H9+H10+H11+H14+H15+H16+H17 -> 109197385662
A20: RA | B20: Achats de marchandises | H20: =-+'[152]Compte de Résultat'!$E$10 -> 1878495285
A21: RB | B21: - Variation de stocks | F21: (- ou +) | H21: =-+'[152]Compte de Résultat'!$E$11 -> 167058426
A22: RC | B22: Achats de matières premières et fournitures liées | H22: =-'[152]Compte de Résultat'!$E$22 -> 0
A23: RD | B23: - Variation de stocks | F23: (- ou +) | H23: =-'[152]Compte de Résultat'!$E$23 -> -20982830
A24: RE | B24: Autres achats | H24: =-+'[152]Compte de Résultat'!$E$24 -> 13535561694
A25: RH | B25: - Variation de stocks | F25: (- ou +) | H25: =-+'[152]Compte de Résultat'!$E$25 -> 70632568
A26: RI | B26: Transports | H26: =-+'[152]Compte de Résultat'!$E$26 -> 185108708
A27: RJ | B27: Services extérieurs | H27: =-+'[152]Compte de Résultat'!$E$27 -> 55972756449
A28: RK | B28: Impôts et taxes | H28: =-+'[152]Compte de Résultat'!$E$28 -> 2756966914
A29: RL | B29: Autres charges | H29: =-+'[152]Compte de Résultat'!$E$29 -> 2130824161
A30: RP | B30: Charges de personnel | H30: =-+'[152]Compte de Résultat'!$E$31 -> 4859497853
A31: RS | B31: Dotations aux amortissements et aux provisions | H31: =-+'[152]Compte de Résultat'!$E$34 -> 18531485240
A32: RW | B32: Total des charges d'exploitation | H32: =+SUM(H20:H31) -> 100067404468
A34: TX | B34: RESULTAT D'EXPLOITATION | H34: =+H18-H32 -> 9129981194
C35: Bénéfice (+) ; Perte (-)
B36: ACTIVITE FINANCIERE
A37: UA | B37: Revenus financiers | H37: ='[152]Compte de Résultat'!$E$36 -> 870907299
A38: UC | B38: Gains de change | H38: 0
A39: UD | B39: Reprises de provisions | H39: =+'[152]Compte de Résultat'!$E$37 -> 0
A40: UE | B40: Transferts de charges
A41: UF | B41: Total des produits financiers | H41: =+SUM(H37:H40) -> 870907299
A43: SA | B43: Frais financiers | H43: =-'[152]Compte de Résultat'!$E$39 -> 4155056479
A44: SC | B44: Pertes de change | H44: 0
A45: SD | B45: Dotations aux amortissements et aux provisions | H45: =-'[152]Compte de Résultat'!$E$40 -> 0
A46: SF | B46: Total des charges financières | H46: =+SUM(H43:H45) -> 4155056479
A47: UG | B47: RESULTAT FINANCIER | E47: (+ ou -) | H47: =+H41-H46 -> -3284149180
A48: UG | B48: RESULTAT courant | E48: (+ ou -) | H48: =+H47+H34 -> 5845832014
B50: HORS ACTIVITES ORDINAIRES (H.A.O.)
A51: UK | B51: Produits des cessions d'immobilisations | H51: =+'[152]Compte de Résultat'!$E$43 -> 0
A52: UL | B52: Produits H.A.O.
A53: UM | B53: Reprises H.A.O.
A54: UN | B54: Transferts de charges
A55: UO | B55: Total des produits H.A.O. | H55: =+SUM(H51:H54) -> 0
A56: SK | B56: Valeurs comptables des cessions d'immobilisations | H56: =-'[152]Compte de Résultat'!$E$45 -> 0
A57: SL | B57: Charges H.A.O.
A58: SM | B58: Dotations H.A.O.
A59: SO | B59: Total des charges H.A.O. | H59: =+SUM(H56:H58) -> 0
A60: UP | B60: RESULTAT H.A.O. | E60: (+ ou -) | H60: =+H55-H59 -> 0
A61: SR | B61: Impôts sur le résultat | H61: =-'[152]Compte de Résultat'!$E$49 -> 1067468330
A62: SS | B62: Total impôts sur le résultat | H62: =+H61 -> 1067468330
A63: UZ | B63: RESULTAT NET Bénéfice (+) ; Perte (-) | H63: =+H48+H60-H62 -> 4778363684
H64: =+H63-'Bilan Passif '!C17 -> 0
G590: 1068901341 | H590: 336311975

Sheet <<Matrice OHADA-IFRS>>
E16: Matrice de passage OHADA - IFRS

Sheet Passage Actif BC 
A1: Sommaire
G2: Retraitements PPA | Q2: Reclassements | Z2: Retraitements | BC2: Ajustements conso
C3: Passage Bilan - Actif
C4: =Cover!Y13 -> En millions de FCFA | E4: Comptes sociaux OHADA | G4: Marque | I4: Base client (VB) | K4: Base client (AMENTS) | M4: Juste valeur terrain | O4: Juste valeur titres | Q4: Reclass immo. Corp | R4: Reclass immo. Incorp | S4: Reclass immo. Fin | T4: Reclass BFR | U4: Reclass Acomptes IS | V4: Autres Reclassements | W4: CCA/PCA | X4: CCA | Y4: Cash bloqué | Z4: ID social | AB4: IDA/PIDR | AD4: Cartes SIM (VB) | AG4: Cartes SIM (AMORT) | AI4: Subventions (VB) | AK4: Subventions (REPRISES) | AM4: Droit d'actif(VB) | AO4: Droit d'actif(Amort) | AQ4: Frais immobilisés | AS4: Mise en rebut (VB) | AU4: Mise en rebut (AMORT) | AW4: Stocks réseaux (VB) | AY4: Stocks réseaux (AMORT) | BA4: ECA | BC4: Ajust 1 | BD4: Ajust 2 | BE4: Ajust 3 | BF4: Ajust 4 | BH4: IFRS | BJ4: IFRS
G5: Ouverture | H5: Flux | I5: Ouverture | J5: Flux | K5: Ouverture | L5: Flux | M5: Ouverture | N5: Flux | O5: Ouverture | P5: Flux | Z5: Ouverture | AA5: Flux | AB5: Ouverture | AC5: Flux | AD5: Ouverture | AE5: Achats de cartes SIM | AF5: Sorties comptables | AG5: Ouverture | AH5: Flux | AI5: Ouverture | AJ5: Flux | AK5: Ouverture | AL5: Flux | AM5: Ouverture | AN5: Flux | AO5: Ouverture | AP5: Flux | AQ5: Ouverture | AR5: Flux | AS5: Ouverture | AT5: Flux | AU5: Ouverture | AV5: Flux | AW5: Ouverture | AX5: Flux | AY5: Ouverture | AZ5: Flux | BA5: Ouverture | BB5: Flux | BC5: Goodwill | BD5: ID | BE5: SHL & MFees | BF5: Activation charges du personnel
C7: Frais d'établissement et autres charges à répartir | E7: =+'Bilan Actif'!F9/10^6 -> 0 | AQ7: =(-530.12080712+246.787407232001+200.150696+83.075)*0 -> 0 | AR7: =-SUM('BG '!H29:I29)/10^6 -> 0 | BH7: =SUM(E7:BG7) -> 0 | BJ7: 0
C8: Autres charges immobilisées | E8: =+'Bilan Actif'!F10/10^6 -> 0 | BH8: =SUM(E8:BG8) -> 0 | BJ8: 0
B10: ANC2100 | C10: Ecarts d’acquisition | BC10: =19085+7314 -> 26399 | BH10: =SUM(E10:BG10) -> 26399 | BJ10: 26399
B11: ANC2910 | C11: Provisions pour dépréciation des écarts d’acquisition | BH11: =SUM(E11:BG11) -> 0 | BJ11: 0
B12: TANC2000 | C12: Ecarts d'acquisition | F12: =F11+F10 -> 0 | G12: =G11+G10 -> 0 | H12: =H11+H10 -> 0 | I12: =I11+I10 -> 0 | J12: =J11+J10 -> 0 | K12: =K11+K10 -> 0 | L12: =L11+L10 -> 0 | M12: =M11+M10 -> 0 | ... BF12: =BF11+BF10 -> 0 | BH12: =SUM(E12:BG12) -> 26399 | BJ12: 26399
C14: Frais de recherche et de développemt | E14: =+'Bilan Actif'!F12/10^6 -> 0 | R14: =-E14 -> 0 | BH14: =SUM(E14:BG14) -> 0 | BJ14: 0
C15: Brevets, licences, logiciels | E15: =+'Bilan Actif'!F13/10^6 -> 39106.514 | R15: =-E15 -> -39106.514 | BH15: =SUM(E15:BG15) -> 0 | BJ15: 0
C16: Fonds commercial | E16: =+'Bilan Actif'!F14/10^6 -> 0 | R16: =-E16 -> 0 | BH16: =SUM(E16:BG16) -> 0 | BJ16: 0
C17: Autres immobilisations incorporelles | E17: =+'Bilan Actif'!F15/10^6 -> 0 | R17: =-E17 -> 0 | BH17: =SUM(E17:BG17) -> 0 | BJ17: 0
B19: ANC2210 | C19: Frais de développement | R19: 0 | BH19: =SUM(E19:BG19) -> 0 | BJ19: 0
B20: ANC2821 | C20: Amortissements & dépréciation des frais de développement | BH20: =SUM(E20:BG20) -> 0 | BJ20: 0
B21: ANC2221 | C21: Brevets et marques | R21: =+('BG '!J31)/10^6 -> 6373.0289 | BH21: =SUM(E21:BG21) -> 6373.0289 | BJ21: 6254.3029
B22: ANC28221 | C22: Amortissements & dépréciation des brevets et marques | R22: =+('BG '!K73)/10^6 -> -8931.4383 | V22: =-(R22+R21) -> 2558.4094 | BH22: =SUM(E22:BG22) -> -6373.0289 | BJ22: -5372.6873
B23: ANC2222 | C23: Logiciels | R23: =+('BG '!J32+'BG '!J33+'BG '!J34)/10^6 -> 60147.145 | BH23: =SUM(E23:BG23) -> 60147.145 | BJ23: 55522.589
B24: ANC28222 | C24: Amortissements & dépréciation des logiciels | R24: =+('BG '!K74+'BG '!K75)/10^6 -> -41958.116 | V24: =SUM('BG '!R82:S83)/10^6-'[154]RECAP 1'!$K$45-V22 -> -2558.4094 | BH24: =SUM(E24:BG24) -> -44516.525 | BJ24: -40753.176
B25: ANC2240 | C25: Licences telecom | R25: =+('BG '!J30)/10^6 -> 80000 | BH25: =SUM(E25:BG25) -> 80000 | BJ25: 80000
B26: ANC2824 | C26: Amortissements & dépréciation des licences telecom | R26: =+('BG '!K72)/10^6 -> -56524.105 | V26: =SUM('BG '!S80)/10^6-'[154]RECAP 1'!$K$46 -> 0 | BH26: =SUM(E26:BG26) -> -56524.105 | BJ26: -53968.69
B27: ANC2250 | C27: Immobilisations incorporelles acquises par voie de regroupement d'entreprises | BH27: =SUM(E27:BG27) -> 0 | BJ27: 0
B28: ANC2825 | C28: Amortissements & dépréciation des immobilisations incorporelles acquises par voie de regroupement d'entreprises | BH28: =SUM(E28:BG28) -> 0 | BJ28: 0
B29: ANC2260 | C29: Cartes SIM | AD29: =1820.91778991124+330.296429+216.501643+187.185137+514.390844 -> 3069.2918 | AE29: =-AE103 -> 759.49458 | BH29: =SUM(E29:BG29) -> 3828.7864 | BJ29: 3828.7864
B30: ANC2826 | C30: Amortissements & dépréciation cartes SIM | AG30: =-1171.35990694011-346.028541147557-265.028390976732-200.907171654148-177.45912356389 -> -2160.7831 | AH30: =-'Cartes SIM'!D21/1000000 -> -229.49406 | BH30: =SUM(E30:BG30) -> -2390.2772 | BJ30: -2316.3666
B31: ANC2270 | C31: Droit d'utilisation de l'actif | AM31: =4021.665466+2117.71515+33.047333-2.01030600000104+133.291784 -> 6303.7094 | AN31: ='Impacts_IFRS.16-09'!K69 -> 434.41556 | BH31: =SUM(E31:BG31) -> 6738.125 | BJ31: 6729.8771
B32: ANC2827 | C32: Amortissements du droit d'utilisation de l'actif | AO32: =-930.344101-1133.873401-1067.353401-940.196732 -> -4071.7676 | AP32: =+'Impacts_IFRS.16-09'!L82 -> -805.85369 | BH32: =SUM(E32:BG32) -> -4877.6213 | BJ32: -4671.7804
B33: ANC2280 | C33: Autres immobilisations incorporelles | V33: =-(SUM(Activation!H25,Activation!H32:H192)/10^6) -> -2464.3598 | BF33: =SUM(Activation!H25,Activation!H32:H213)/10^6 -> 2745.5723 | BH33: =SUM(E33:BG33) -> 281.21245 | BJ33: 0
B34: ANC2828 | C34: Amortissements & dépréciation des autres immobilisations incorporelles | V34: =-(Activation!CB238/10^6+SUM(Activation!CN239)/10^6) -> 1459.7159 | BF34: =Activation!CB238/10^6+SUM(Activation!CN239)/10^6 -> -1459.7159 | BH34: =SUM(E34:BG34) -> 0 | BJ34: -215.27479
B35: ANC2298 | C35: Immobilisations incorporelles en cours | V35: =+Q56 -> 324.80203 | BH35: =SUM(E35:BG35) -> 324.80203 | BJ35: 579.13573
B36: ANC2929 | C36: Provisions pour dépréciation des immobilisations incorporelles en cours | BH36: =SUM(E36:BG36) -> 0 | BJ36: 0
B37: TANC2100 | C37: Immobilisations incorporelles | E37: =+SUM(E14:E17) -> 39106.514 | G37: =SUM(G19:G36) -> 0 | H37: =SUM(H14:H36) -> 0 | I37: =SUM(I14:I36) -> 0 | J37: =SUM(J14:J36) -> 0 | K37: =SUM(K14:K36) -> 0 | L37: =SUM(L14:L36) -> 0 | M37: =SUM(M14:M36) -> 0 | N37: =SUM(N14:N36) -> 0 | O37: =SUM(O14:O36) -> 0 | ... BF37: =SUM(BF14:BF36) -> 1285.8564 | BH37: =SUM(BH14:BH36) -> 43011.541 | BJ37: 45616.716
C39: Terrains | E39: =+'Bilan Actif'!F17/10^6 -> 3170.0923 | Q39: =-E39 -> -3170.0923 | BH39: =SUM(E39:BG39) -> 0 | BJ39: 0
C40: Bâtiments | E40: =+'Bilan Actif'!F18/10^6 -> 1622.1087 | Q40: =-E40 -> -1622.1087 | BH40: =SUM(E40:BG40) -> 0 | BJ40: 0
C41: Installations et agencements | E41: =+'Bilan Actif'!F19/10^6 -> 20069.249 | Q41: =-E41 -> -20069.249 | BH41: =SUM(E41:BG41) -> 0 | BJ41: 0
C42: Matériel, mobilier et actifs biologiques | E42: =+'Bilan Actif'!F20/10^6 -> 41272.441 | Q42: =-E42 -> -41272.441 | BH42: =SUM(E42:BG42) -> 0 | BJ42: 0
C43: Matériel de transport | E43: =+'Bilan Actif'!F21/10^6 -> 0.562593 | Q43: =-E43 -> -0.562593 | BH43: =SUM(E43:BG43) -> 0 | BJ43: 0
C44: Avances et acomptes versés sur immobilisations | E44: =+'Bilan Actif'!F22/10^6 -> 474.72879 | Q44: =-E44 -> -474.72879 | BH44: =SUM(E44:BG44) -> 0 | BJ44: 0
B46: ANC2310 | C46: Terrains | Q46: =+('BG '!J35+'BG '!J36+'BG '!J37)/10^6 -> 3170.0923 | BH46: =SUM(E46:BG46) -> 3170.0923 | BJ46: 3145.8177
B47: ANC2831 | C47: Amortissements & dépréciation des terrains | BH47: =SUM(E47:BG47) -> 0 | BJ47: 0
B48: ANC2320 | C48: Constructions | Q48: =+SUM('BG '!J47,'BG '!J38)/10^6 -> 1675.4591 | BH48: =SUM(E48:BG48) -> 1675.4591 | BJ48: 1460.8505
B49: ANC2832 | C49: Amortissements & dépréciation des constructions | Q49: =SUM('BG '!K76)/10^6 -> -53.350355 | V49: =SUM('BG '!S91)/10^6-'[154]RECAP 1'!$K$44 -> 0 | BH49: =SUM(E49:BG49) -> -53.350355 | BJ49: -30.653352
B50: ANC2330 | C50: Installations techniques, matériel et outillage | Q50: =+('BG '!J39+'BG '!J40+'BG '!J41+'BG '!J48+'BG '!J49+'BG '!J50+'BG '!J51+'BG '!J52+'BG '!J61+'BG '!J53+'BG '!J64)/10^6 -> 157315.25 | V50: =-V33 -> 2464.3598 | BH50: =SUM(E50:BG50) -> 159779.61 | BJ50: 159498.2
B51: ANC2833 | C51: Amortissements & dépréciation des installations techniques, matériel et outillage | Q51: =SUM('BG '!K77,'BG '!K78,'BG '!K79,'BG '!K85,'BG '!K86,'BG '!K87,'BG '!K88,'BG '!K89,'BG '!K98)/10^6 -> -103969.86 | V51: =-V34 -> -1459.7159 | BH51: =SUM(E51:BG51) -> -105429.58 | BJ51: -109216.92 | BK51: =BJ51-BH51 -> -3787.3423
B52: ANC2340 | C52: Matériel de transport | Q52: =SUM('BG '!J58,'BG '!J59,'BG '!J63)/10^6 -> 715.8952 | BH52: =SUM(E52:BG52) -> 715.8952 | BJ52: 715.8952
B53: ANC2834 | C53: Amortissements & dépréciation du matériel de transport | Q53: =SUM('BG '!K95,'BG '!K96)/10^6 -> -715.3326 | V53: =SUM('BG '!R110,'BG '!R111,'BG '!S111,'BG '!S110)/10^6-'[154]RECAP 1'!$K$49 -> 0 | BH53: =SUM(E53:BG53) -> -715.3326 | BJ53: -714.32512
B54: ANC2350 | C54: Mobilier et matériel de bureau | Q54: =SUM('BG '!J54,'BG '!J55,'BG '!J56,'BG '!J62)/10^6 -> 13666.077 | BH54: =SUM(E54:BG54) -> 13666.077 | BJ54: 11309.622
B55: ANC2835 | C55: Amortissements & dépréciation du mobilier, matériel de bureau | Q55: =SUM('BG '!K91,'BG '!K92,'BG '!K93)/10^6 -> -6417.8604 | V55: =SUM('BG '!R106:S108)/10^6-'[154]RECAP 1'!$K$48 -> 0 | BH55: =SUM(E55:BG55) -> -6417.8604 | BJ55: -5470.6023
B56: ANC2360 | C56: Avances et acomptes versés sur commandes d'immobilisations corporelles | Q56: =+('BG '!J65)/10^6 -> 324.80203 | V56: =-Q56 -> -324.80203 | BH56: =SUM(E56:BG56) -> 0 | BJ56: 0
B57: ANC2936 | C57: Provisions pour dépréciation des avances et acomptes versés sur commandes d'immobilisations corporelles | BH57: =SUM(E57:BG57) -> 0 | BJ57: 0
B58: ANC2380 | C58: Autres immobilisations corporelles | Q58: =SUM('BG '!J42,'BG '!J43,'BG '!J44,'BG '!J45,'BG '!J46,'BG '!J57,'BG '!J60)/10^6 -> 2842.1115 | BH58: =SUM(E58:BG58) -> 2842.1115 | BJ58: 2828.9037
B59: ANC2838 | C59: Amortissements & dépréciation des autres immobilisations corporelles | Q59: =SUM('BG '!K80,'BG '!K81,'BG '!K82,'BG '!K83,'BG '!K84,'BG '!K90,'BG '!K94,'BG '!K97)/10^6 -> -1944.0983 | V59: =SUM('BG '!R95,'BG '!S95,'BG '!R96,'BG '!S96,'BG '!R97,'BG '!S97,'BG '!R98,'BG '!S98,'BG '!R99,'BG '!S99,'BG '!R105,'BG '!S105,'BG '!R109,'BG '!S109,'BG '!R112,'BG '!S112)/10^6-'[154]RECAP 1'!$K$42 -> 0 | BH59: =SUM(E59:BG59) -> -1944.0983 | BJ59: -1846.8334
B60: ANC2390 | C60: Immobilisations corporelles en cours | BH60: =SUM(E60:BG60) -> 0 | BJ60: 0
B61: ANC2939 | C61: Provisions pour dépréciation des immobilisations en cours | BH61: =SUM(E61:BG61) -> 0 | BJ61: 0
B62: TANC2200 | C62: Immobilisations corporelles | E62: =+SUM(E39:E44) -> 66609.182 | G62: =SUM(G39:G61) -> 0 | H62: =SUM(H39:H61) -> 0 | I62: =SUM(I39:I61) -> 0 | J62: =SUM(J39:J61) -> 0 | K62: =SUM(K39:K61) -> 0 | L62: =SUM(L39:L61) -> 0 | M62: =SUM(M39:M61) -> 0 | N62: =SUM(N39:N61) -> 0 | ... BF62: =SUM(BF39:BF61) -> 0 | BG62: =SUM(BG46:BG61) -> 0 | BH62: =SUM(BH46:BH61) -> 67289.024 | BJ62: 61679.951
C64: Titres de participation | E64: =+'Bilan Actif'!F24/10^6 -> 0 | S64: =-E64 -> 0 | BH64: =SUM(E64:BG64) -> 0 | BJ64: 0
C65: Autres immobilisations financières | E65: =+'Bilan Actif'!F25/10^6 -> 732.07663 | S65: =-E65 -> -732.07663 | BH65: =SUM(E65:BG65) -> 0 | BJ65: 0
B67: ANC2410 | C67: Prêts immobilisés (+1 an) | BH67: =SUM(E67:BG67) -> 0 | BJ67: 0
B68: ANC2941 | C68: Provisions pour dépréciation des prêts immobilisés (+1 an) | BH68: =SUM(E68:BG68) -> 0 | BJ68: 0
B69: ANC2420 | C69: Cash bloqué pour emprunts | BH69: =SUM(E69:BG69) -> 0 | BJ69: 0
B70: ANC2942 | C70: Provisions pour dépréciation du cash bloqué pour emprunts | BH70: =SUM(E70:BG70) -> 0 | BJ70: 0
B71: ANC2431 | C71: Actifs financiers non courants détenus jusqu’à l’échéance | BH71: =SUM(E71:BG71) -> 0 | BJ71: 0
B72: ANC29431 | C72: Provisions pour dépréciation des actifs financiers non courants détenus jusqu’à l'échéance | BH72: =SUM(E72:BG72) -> 0 | BJ72: 0
B73: ANC2433 | C73: Créances immobilisées | V73: =-V163 -> 24399.507 | BH73: =SUM(E73:BG73) -> 24399.507 | BJ73: 22761.237
B74: ANC29433 | C74: Provisions pour dépréciation des créances immobilisées | BH74: =SUM(E74:BG74) -> 0 | BJ74: 0
B75: ANC2434 | C75: Créances sur cessions d'immobilisations financières (+1 an) | BH75: =SUM(E75:BG75) -> 0 | BJ75: 0
B76: ANC29434 | C76: Provisions pour dépréciation des créances sur cessions d'immobilisations financières (+1 an) | BH76: =SUM(E76:BG76) -> 0 | BJ76: 0
B77: ANC2435 | C77: Frais et commissions sur facilités de crédit | BH77: =SUM(E77:BG77) -> 0 | BJ77: 0
B78: ANC29435 | C78: Provisions pour dépréciation des frais et commissions sur facilités de crédit | BH78: =SUM(E78:BG78) -> 0 | BJ78: 0
B79: ANC2438 | C79: Créances financières diverses | S79: =SUM('BG '!J71)/1000000 -> 198.89877 | BH79: =SUM(E79:BG79) -> 198.89877 | BJ79: 179.89877
B80: ANC29438 | C80: Provisions pour dépréciation des créances financières diverses | BH80: =SUM(E80:BG80) -> 0 | BJ80: 0
B81: ANC2511 | C81: Titres de participation consolidés | S81: ='BG '!J66/10^6 -> 0 | BH81: =SUM(E81:BG81) -> 0 | BJ81: 0
B82: ANC29511 | C82: Provisions pour dépréciation des titres consolidés | BH82: =SUM(E82:BG82) -> 0 | BJ82: 0
B83: ANC2512 | C83: Titres de participation non consolidés | BH83: =SUM(E83:BG83) -> 0 | BJ83: 0
B84: ANC29512 | C84: Provisions pour dépréciation des titres non consolidés | BH84: =SUM(E84:BG84) -> 0 | BJ84: 0
B85: ANC2520 | C85: Titres mis en équivalence | BH85: =SUM(E85:BG85) -> 0 | BJ85: 0
B86: ANC2952 | C86: Provisions pour dépréciation des titres mis en équivalence | BH86: =SUM(E86:BG86) -> 0 | BJ86: 0
B87: ANC2621 | C87: Instruments dérivés - actifs non courants (variation en situation nette) | BH87: =SUM(E87:BG87) -> 0 | BJ87: 0
B88: ANC2622 | C88: Instruments dérivés - actifs non courants (variation en résultat) | BH88: =SUM(E88:BG88) -> 0 | BJ88: 0
B89: TANC2300 | C89: Actifs financiers non courants | E89: =+E64+E65 -> 732.07663 | G89: =+SUM(G64:G88) -> 0 | H89: =+SUM(H64:H88) -> 0 | I89: =+SUM(I64:I88) -> 0 | J89: =+SUM(J64:J88) -> 0 | K89: =+SUM(K64:K88) -> 0 | L89: =+SUM(L64:L88) -> 0 | M89: =+SUM(M64:M88) -> 0 | N89: =+SUM(N64:N88) -> 0 | ... BF89: =+SUM(BF64:BF88) -> 0 | BH89: =+SUM(BH64:BH88) -> 24598.406 | BJ89: 22941.136
B91: ANC2700 | C91: Impôts différés actifs | V91: =-272.2492342804-12.8035080109648-17.8706515617857+8.88341999999997-65.9909429906782-15.7181490615539 -> -375.74907 | Z91: =1196.5+60.0905809212002 -> 1256.5906 | AB91: =14.5406352-45.9189486081465-0.00410000000008992 -> -31.382413 | AD91: -118.2 | AG91: =22.4371934980207+118.479658813628+103.808562344267+79.5085172930197+60.2721514962443+53.2377370691671 -> 437.74382 | AH91: =-'Passage Actif BC '!AH30*30% -> 68.848217 | AQ91: 158.92854 | BD91: 1231.6 | BF91: -368.4 | BH91: =SUM(E91:BG91) -> 2259.9797 | BJ91: 2237.9183
B92: ANC2970 | C92: Provisions pour dépréciation des impôts différés actifs | BD92: 885.2 | BH92: =SUM(E92:BG92) -> 885.2 | BJ92: 885.2
B93: TANC2400 | C93: Impôts différés actifs | G93: =+G91+G92 -> 0 | H93: =+H91+H92 -> 0 | I93: =+I91+I92 -> 0 | J93: =+J91+J92 -> 0 | K93: =+K91+K92 -> 0 | L93: =+L91+L92 -> 0 | M93: =+M91+M92 -> 0 | N93: =+N91+N92 -> 0 | ... BF93: =+BF91+BF92 -> -368.4 | BH93: =+BH92+BH91 -> 3145.1797 | BJ93: 3123.1183
B95: TANC200 | C95: Actifs non courants | E95: =+E93+E89+E62+E37+E12+E7+E8 -> 106447.77 | G95: =+G93+G89+G62+G37+G12+G7+G8 -> 0 | H95: =+H93+H89+H62+H37+H12+H7+H8 -> 0 | I95: =+I93+I89+I62+I37+I12+I7+I8 -> 0 | J95: =+J93+J89+J62+J37+J12+J7+J8 -> 0 | K95: =+K93+K89+K62+K37+K12+K7+K8 -> 0 | L95: =+L93+L89+L62+L37+L12+L7+L8 -> 0 | M95: =+M93+M89+M62+M37+M12+M7+M8 -> 0 | N95: =+N93+N89+N62+N37+N12+N7+N8 -> 0 | ... BF95: =+BF93+BF89+BF62+BF37+BF12+BF7+BF8 -> 917.45642 | BH95: =+BH93+BH89+BH62+BH37+BH12+BH7+BH8 -> 164443.15 | BJ95: 159759.92
C98: Stocks et encours | E98: =+'Bilan Actif'!F29/10^6 -> 2447.1735 | T98: =-E98 -> -2447.1735 | BH98: =SUM(E98:BG98) -> 0 | BJ98: 0
E99: =+'Bilan Actif'!F31/10^6 -> 0 | T99: =-E99 -> 0 | BH99: =SUM(E99:BG99) -> 0 | BJ99: 0
E100: =+'Bilan Actif'!F33/10^6 -> 0 | T100: =-E100 -> 0 | BH100: =SUM(E100:BG100) -> 0 | BJ100: 0
E101: =+'Bilan Actif'!F34/10^6 -> 0 | T101: =-E101 -> 0 | BH101: =SUM(E101:BG101) -> 0 | BJ101: 0
B103: AC3110 | C103: Stocks | T103: =SUM('BG '!J99,'BG '!J100,'BG '!J104,'BG '!J105,'BG '!J107,'BG '!J108,'BG '!J109,'BG '!J110,'BG '!J101,'BG '!J102,'BG '!J103,'BG '!J106)/10^6 -> 2986.8942 | AD103: =-SUM('BG '!F101,'BG '!F102,'BG '!F103)/1000000 -> -232.66152 | AE103: =-SUM('BG '!H452:I452)/10^6 -> -759.49458 | AF103: =-'Cartes SIM'!E7/1000000 -> 525.84004 | BH103: =SUM(E103:BG103) -> 2520.5781 | BJ103: 2677.4744
B104: AC3910 | C104: Provisions pour dépréciation des stocks | T104: =SUM('BG '!K111,'BG '!K112,'BG '!K113,'BG '!K114,'BG '!K115)/10^6 -> -539.7207 | AD104: 76.7 | BH104: =SUM(E104:BG104) -> -463.0207 | BJ104: -526.73855
B105: TAC3000 | C105: Stocks | E105: =+SUM(E98:E101) -> 2447.1735 | G105: =SUM(G98:G104) -> 0 | H105: =SUM(H98:H104) -> 0 | I105: =SUM(I98:I104) -> 0 | J105: =SUM(J98:J104) -> 0 | K105: =SUM(K98:K104) -> 0 | L105: =SUM(L98:L104) -> 0 | M105: =SUM(M98:M104) -> 0 | N105: =SUM(N98:N104) -> 0 | ... BF105: =SUM(BF98:BF104) -> 0 | BH105: =SUM(BH98:BH104) -> 2057.5574 | BJ105: 2150.7358
B107: AC3453 | C107: Acomptes sur impôts sur le résultat | BH107: =SUM(E107:BG107) -> 0 | BJ107: 0
B108: TAC3100 | C108: Créances sur impôts sur le résultat | G108: =+G107 -> 0 | H108: =+H107 -> 0 | I108: =+I107 -> 0 | J108: =+J107 -> 0 | K108: =+K107 -> 0 | L108: =+L107 -> 0 | M108: =+M107 -> 0 | N108: =+N107 -> 0 | ... BF108: =+BF107 -> 0 | BH108: =+BH107 -> 0 | BJ108: 0
C110: Actif circulant H.A.O. | E110: =+'Bilan Actif'!F28/10^6 -> 1307.8274 | T110: =-E110 -> -1307.8274 | BH110: =SUM(E110:BG110) -> 0 | BJ110: 0
C111: Fournisseurs, avances versées | E111: =+'Bilan Actif'!F36/10^6 -> 1657.7692 | T111: =-E111 -> -1657.7692 | BH111: =SUM(E111:BG111) -> 0 | BJ111: 0
C112: Clients | E112: =+'Bilan Actif'!F37/10^6 -> 20688.465 | T112: =-E112 -> -20688.465 | BH112: =SUM(E112:BG112) -> 0 | BJ112: 0
C113: Autres créances | E113: =+'Bilan Actif'!F38/10^6 -> 15136.332 | T113: =-E113 -> -15136.332 | BH113: =SUM(E113:BG113) -> 0 | BJ113: 0
B115: AC3410 | C115: Fournisseurs débiteurs, avances et acomptes sur commandes en cours | T115: =+SUM('BG '!J165,'BG '!J166,'BG '!J116:J164)/10^6 -> 1657.7692 | BH115: =SUM(E115:BG115) -> 1657.7692 | BJ115: 1481.8341
B116: AC3941 | C116: Provisions pour dépréciation des fournisseurs débiteurs, avances et acomptes sur commandes en cours | BH116: =SUM(E116:BG116) -> 0 | BJ116: 0
...

Sheet Passage Passif BC 
A1: Sommaire
G2: Retraitements PPA | Q2: Reclassements | AK2: Retraitements | BC2: Ajustements conso
C4: Passage Bilan - Passif | E4: Comptes sociaux OHADA | G4: Marque | I4: Base client (VB) | K4: Base client (AMENTS) | M4: Juste valeur terrain | O4: Juste valeur titres | Q4: Reclass SN - Part du Groupe/Minos | R4: Reclass Dettes financières fraction à -1 an | S4: Reclass Dettes financières ICNE | T4: Reclass Dettes financières envers la mère | U4: Conventions financières exploitation (DPA) | V4: Reclass Provisions | W4: Reclass Dette d'IS | X4: Reclass BFR | Y4: Reclass Equivalents de trésorerie | Z4: Autres reclassements | AA4: Autres reclass 2 | AB4: Autres reclass 3 | AC4: Autres reclass 4 | AD4: ID social | AF4: PIDR | AH4: Cartes SIM (VB) | AK4: Cartes SIM (AMORT) | AM4: Subventions (VB) | AO4: Subventions Reprises | AQ4: Droit d'actif(VB) | AS4: Droit d'actif(Amort) | AU4: Frais immobilisés | AW4: ECA | AY4: ECA - Provision pour perte de change | BA4: ECP | BC4: Ajust 1 | BD4: Ajust 2 | BE4: Ajust 3 | BG4: IFRS | BL4: IFRS
C5: =Cover!Y13 -> En millions de FCFA | G5: Ouverture | H5: Flux | I5: Ouverture | J5: Flux | K5: Ouverture | L5: Flux | M5: Ouverture | N5: Flux | O5: Ouverture | P5: Flux | AD5: Ouverture | AE5: Flux | AF5: Ouverture | AG5: Flux | AH5: Ouverture | AI5: Achats de cartes SIM | AJ5: Sorties comptables | AK5: Ouverture | AL5: Flux | AM5: Ouverture | AN5: Flux | AO5: Ouverture | AP5: Flux | AQ5: Ouverture | AR5: Flux | AS5: Ouverture | AT5: Flux | AU5: Ouverture | AV5: Flux | AW5: Ouverture | AX5: Flux | AY5: Ouverture | AZ5: Flux | BA5: Ouverture | BB5: Flux | BC5: Goodwill | BD5: ID | BE5: Activation charges de personnel
C7: Capital | E7: =+('Bilan Passif '!C9+'Bilan Passif '!C10)/10^6 -> 10408.28 | Q7: =-E7 -> -10408.28 | BG7: =+SUM(E7:BE7) -> 0 | BL7: 0
C8: Primes d'apport, d'émission, de fusion | E8: =+'Bilan Passif '!C12/10^6 -> 0 | Q8: =-E8 -> 0 | BG8: =+SUM(E8:BE8) -> 0 | BL8: 0
C9: Ecarts de réévaluation | E9: =+'Bilan Passif '!C13/10^6 -> 0 | Q9: =-E9 -> 0 | BG9: =+SUM(E9:BE9) -> 0 | BL9: 0
C10: Réserves indisponibles | E10: =+'Bilan Passif '!C14/10^6 -> 0 | Q10: =-E10 -> 0 | BG10: =+SUM(E10:BE10) -> 0 | BL10: 0
C11: Réserves libres | E11: =+'Bilan Passif '!C15/10^6 -> 0 | Q11: =-E11 -> 0 | BG11: =+SUM(E11:BE11) -> 0 | BL11: 0
C12: Report à nouveau (+ ou - ) | E12: =+'Bilan Passif '!C16/10^6 -> -1228.6567 | Q12: =-E12 -> 1228.6567 | BG12: =+SUM(E12:BE12) -> 0 | BL12: 0
C13: Résultat net de l'exercice (bénéfice + ou perte -) | E13: =+'Bilan Passif '!C17/10^6 -> 4778.3637 | Q13: =-E13 -> -4778.3637 | BG13: =+SUM(E13:BE13) -> 0 | BL13: 0
C14: Subventions d'investissement | E14: =+'Bilan Passif '!C19/10^6 -> 0 | Q14: =-E14 -> 0 | BG14: =+SUM(E14:BE14) -> 0 | BL14: 0
C15: Provisions réglementées et fonds assimilés | E15: =+'Bilan Passif '!C20/10^6 -> 0 | Q15: =-E15 -> 0 | BG15: =+SUM(E15:BE15) -> 0 | BL15: 0
B17: SN1131 | C17: Capital & réserves - part du groupe | Q17: =-SUM('BG '!J4:K11,'BG '!J688:K688,'BG '!J687)/10^6 -> 9179.6233 | Z17: =-94.2828596846101-Z18 -> 45.27428 | AD17: =1196.5+60.0905809212002 -> 1256.5906 | AF17: 48.608513 | AH17: =275.906817837868+458.955034+527.51748+272.1091863+197.1612356+184.7497827+175.5695235+243.3039189+0.0457790733726142 -> 2335.3188 | AK17: =-52.3534514953817-297.576952826635-404.060113074649-276.452537231798-242.21997880329-185.519873683713-140.635020157903-124.221386494723 -> -1723.0393 | AS17: =-87.0857085-72.2560097-58.0208139-20.72798 -> -238.09051 | AU17: =-371.084564984+246.78740723+200.150696+58.1525 -> 134.00604 | BA17: =222.456446+46.8762550000001-210.424885+12.9370556+41.4813511+75.4173266-111.5003687+2.863455 -> 80.106636 | BC17: =19085+7314 -> 26399 | BD17: =2116.8-1.951335 -> 2114.8487 | BE17: =211.133221692526+178.572330668901+132.956685332176+101.946129422176+70.935573512176+39.925017602176+8.914461692176 -> 744.38342 | BG17: =+SUM(E17:BE17) -> 40376.63 | BL17: 40376.584
B18: SN1132 | C18: Résultat net - part du groupe | Q18: =-SUM('BG '!J448:K687)/1000000 -> 4778.3637 | Z18: ='Passage P&L-par nature'!Y191 -> -139.55714 | AJ18: ='Passage Actif BC '!AF103*70% -> 368.08803 | AL18: =(+'Passage Actif BC '!AH30)*70% -> -160.64584 | AT18: =('Impacts_IFRS.16-09'!L85*70%) -> 40.756979 | AV18: =-SUM('BG '!H29:I29)/10^6*70% -> 0 | BB18: =-SUM('BG '!H271:I272)/1000000*70% -> 0.0858508 | BE18: =(+Activation!CN240)*70%/1000000 -> 31.225326 | BG18: =+SUM(E18:BE18) -> 4918.3169 | BL18: 3337.3214
B19: SN1141 | C19: Titres d’autocontrôle | BG19: =+SUM(E19:BE19) -> 0 | BL19: 0
B20: SN1161 | C20: Ecarts de réévaluation | BG20: =+SUM(E20:BE20) -> 0 | BL20: 0
B21: SN1163 | C21: Impôts différés sur les écarts de réévaluation | BG21: =+SUM(E21:BE21) -> 0 | BL21: 0
B22: SN1171 | C22: Ecarts actuariels sur avantages du personnel | AF22: =-48.468784+153.063162027155+54.2999999999998-64.6156183425448-61.4977152467883+42.6783600365493 -> 75.459404 | AG22: =-PIDR!D13 -> 110.2 | BG22: =+SUM(E22:BE22) -> 185.6594 | BL22: 75.459404
B23: SN1172 | C23: Impôts différés sur les écarts actuariels sur avantages du personnel | AF23: =14.5406352-45.9189486081465-16.29+19.3846855027635+18.4493145740365-12.8035080109648 -> -22.637821 | AG23: =-AG22*30% -> -33.06 | BG23: =+SUM(E23:BE23) -> -55.697821 | BL23: -22.637821
B24: SN1191 | C24: Ecarts de réévaluation des instruments de capitaux propres | BG24: =+SUM(E24:BE24) -> 0 | BL24: 0
B25: SN1192 | C25: Impôts différés sur les écarts de réévaluation des instruments de capitaux propres | BG25: =+SUM(E25:BE25) -> 0 | BL25: 0
B26: TSN 1000 | C26: Situation nette - Part du groupe | E26: =+SUM(E7:E15) -> 13957.987 | G26: =+SUM(G17:G25) -> 0 | H26: =+SUM(H17:H25) -> 0 | I26: =+SUM(I17:I25) -> 0 | J26: =+SUM(J17:J25) -> 0 | K26: =+SUM(K17:K25) -> 0 | L26: =+SUM(L17:L25) -> 0 | M26: =+SUM(M17:M25) -> 0 | N26: =+SUM(N17:N25) -> 0 | ... P26: =+SUM(P17:P25) -> 0 | Q26: =+SUM(Q7:Q25) -> 0 | R26: =+SUM(R7:R25) -> 0 | S26: =+SUM(S7:S25) -> 0 | T26: =+SUM(T7:T25) -> 0 | U26: =+SUM(U7:U25) -> 0 | V26: =+SUM(V7:V25) -> 0 | W26: =+SUM(W7:W25) -> 0 | X26: =+SUM(X7:X25) -> 0 | ... BE26: =+SUM(BE7:BE25) -> 775.60875 | BG26: =+SUM(BG7:BG25) -> 45424.909 | BL26: 43766.727
B28: SN1231 | C28: Capital & réserves - part des minoritaires | BG28: =+SUM(E28:BE28) -> 0 | BL28: 0
B29: SN1232 | C29: Résultat net - part des minoritaires | BG29: =+SUM(E29:BE29) -> 0 | BL29: 0
B30: SN1261 | C30: Ecarts de réévaluation | BG30: =+SUM(E30:BE30) -> 0 | BL30: 0
B31: SN1263 | C31: Impôts différés sur les écarts de réévaluation | BG31: =+SUM(E31:BE31) -> 0 | BL31: 0
B32: SN1271 | C32: Ecarts actuariels sur avantages du personnel | BG32: =+SUM(E32:BE32) -> 0 | BL32: 0
B33: SN1272 | C33: Impôts différés sur les écarts actuariels sur avantages du personnel | BG33: =+SUM(E33:BE33) -> 0 | BL33: 0
B34: SN1291 | C34: Ecarts de réévaluation des instruments de capitaux propres | BG34: =+SUM(E34:BE34) -> 0 | BL34: 0
B35: SN1292 | C35: Impôts différés sur les écarts de réévaluation des instruments de capitaux propres | BG35: =+SUM(E35:BE35) -> 0 | BL35: 0
B36: TSN 1100 | C36: Intérêts minoritaires | E36: =+SUM(E28:E35) -> 0 | G36: =+SUM(G28:G35) -> 0 | H36: =+SUM(H28:H35) -> 0 | I36: =+SUM(I28:I35) -> 0 | J36: =+SUM(J28:J35) -> 0 | K36: =+SUM(K28:K35) -> 0 | L36: =+SUM(L28:L35) -> 0 | M36: =+SUM(M28:M35) -> 0 | N36: =+SUM(N28:N35) -> 0 | ... X36: =+SUM(X28:X35) -> 0 | Z36: =+SUM(Z28:Z35) -> 0 | AA36: =+SUM(AA28:AA35) -> 0 | AB36: =+SUM(AB28:AB35) -> 0 | AC36: =+SUM(AC28:AC35) -> 0 | AD36: =+SUM(AD28:AD35) -> 0 | AE36: =+SUM(AE28:AE35) -> 0 | AF36: =+SUM(AF28:AF35) -> 0 | AG36: =+SUM(AG28:AG35) -> 0 | ... BE36: =+SUM(BE28:BE35) -> 0 | BG36: =+SUM(BG28:BG35) -> 0 | BL36: 0
BG37: =+SUM(E37:BB37) -> 0 | BL37: 0
B38: TSN 100 | C38: TOTAL SITUATION NETTE | E38: =+E36+E26 -> 13957.987 | G38: =+G36+G26+SUM(G7:G15) -> 0 | H38: =+H36+H26+SUM(H7:H15) -> 0 | I38: =+I36+I26+SUM(I7:I15) -> 0 | J38: =+J36+J26+SUM(J7:J15) -> 0 | K38: =+K36+K26+SUM(K7:K15) -> 0 | L38: =+L36+L26+SUM(L7:L15) -> 0 | M38: =+M36+M26+SUM(M7:M15) -> 0 | N38: =+N36+N26+SUM(N7:N15) -> 0 | ... P38: =+P36+P26+SUM(P7:P15) -> 0 | Q38: =+Q36+Q26 -> 0 | R38: =+R36+R26 -> 0 | S38: =+S36+S26 -> 0 | T38: =+T36+T26 -> 0 | U38: =+U36+U26 -> 0 | V38: =+V36+V26 -> 0 | W38: =+W36+W26 -> 0 | X38: =+X36+X26 -> 0 | ... BE38: =+BE36+BE26 -> 775.60875 | BG38: =+BG36+BG26 -> 45424.909 | BL38: 43766.727
B40: Emprunts | E40: =+'Bilan Passif '!C24/10^6 -> 46196.599 | R40: =SUM('BG '!K13:K14,'BG '!K16:K20)/1000000 -> -44208.392 | S40: =(SUM('BG '!K22,'BG '!K24,'BG '!K21)+'BG '!J15)/1000000 -> -692.69349 | T40: =('BG '!K15)/10^6 -> 0 | Z40: ='BG '!K12/1000000 -> -1295.5141 | BG40: =+SUM(E40:BE40) -> 2.9999994e-06 | BL40: 3.0000003e-06
B41: Dettes de crédit-bail et contrats assimilés | E41: =+'Bilan Passif '!C25/10^6 -> 0 | BG41: =+SUM(E41:BE41) -> 0 | BL41: 0
B42: Dettes financières diverses | E42: =+'Bilan Passif '!C26/10^6 -> 0 | Z42: =-E42 -> 0 | BG42: =+SUM(E42:BE42) -> 0 | BL42: 0
B43: Provisions financières pour risques et charges | E43: =+'Bilan Passif '!C27/10^6 -> 1119.2479 | V43: =-E43 -> -1119.2479 | BG43: =+SUM(E43:BE43) -> 0 | BL43: 0
B45: PNC1602 | C45: Emprunts auprès des établissements de crédit (+1 an) | R45: =(-'BG '!K16/1000000)*0+('Amortissment Coris'!C25+'SYNTHESE BOA'!D58+'TABLEAU CBAO'!E53)/1000000 -> 29003.313 | Z45: =-'BG '!K12/1000000 -> 1295.5141 | BG45: =+SUM(E45:BE45) -> 30298.827 | BL45: 33000.791
B46: PNC1603 | C46: Dettes envers la société mère (+1 an) | S46: =(-('BG '!K24)-'BG '!J15)/10^6 -> 0 | T46: =-'BG '!K15/10^6 -> 0 | Z46: =6918.1479695*0+7079.14449*0 -> 0 | BG46: =+SUM(E46:BE46) -> 0 | BL46: 0
B47: PNC1604 | C47: Avances reçues et comptes courants bloqués (+1 an) | BG47: =+SUM(E47:BE47) -> 0 | BL47: 0
B48: PNC1605 | C48: Obligation locative (+1 an) | Z48: =-Z119 -> 0 | AQ48: =3207.250837+1191.490619-951.196397-771.206006 -> 2676.3391 | AR48: =SUM('Impacts_IFRS.16-09'!$F$75:$K$76) -> -427.4799 | BG48: =+SUM(E48:BE48) -> 2248.8592 | BL48: 2443.4391
B49: PNC1606 | C49: Conventions financières (+1 an) | BG49: =+SUM(E49:BE49) -> 0 | BL49: 0
B50: PNC1608 | C50: Autres dettes financières non courantes (+1 an) | R50: =(-'BG '!K13/1000000)*0+'Emprunt ACE'!I44/1000000 -> 188.25787 | BG50: =+SUM(E50:BE50) -> 188.25787 | BL50: 282.38681
B51: TPNC1300 | C51: Dettes financières à long terme (+1 an) | G51: =+SUM(G45:G50) -> 0 | H51: =+SUM(H45:H50) -> 0 | I51: =+SUM(I45:I50) -> 0 | J51: =+SUM(J45:J50) -> 0 | K51: =+SUM(K45:K50) -> 0 | L51: =+SUM(L45:L50) -> 0 | M51: =+SUM(M45:M50) -> 0 | N51: =+SUM(N45:N50) -> 0 | ... BE51: =+SUM(BE45:BE50) -> 0 | BG51: =+SUM(BG45:BG50) -> 32735.944 | BL51: 35726.617
BG52: =+SUM(E52:BB52) -> 0 | BL52: 0
B53: PNC1501 | C53: Provisions non courantes d'exploitation (+1an) | BG53: =+SUM(E53:BE53) -> 0 | BL53: 0
B54: PNC1502 | C54: Provisions non courantes - hors exploitation (+1an) | V54: =-('BG '!K27+'BG '!K28)/10^6 -> 414.37553 | BG54: =+SUM(E54:BE54) -> 414.37553 | BL54: 448.01931
B55: PNC1503 | C55: Provisions non courantes pour impôt (+1an) | BG55: =+SUM(E55:BE55) -> 0 | BL55: 0
B56: PNC1504 | C56: Provisions non courantes pour indemnités de départ à la retraite (+1an) | V56: =-('BG '!K25+'BG '!K26)/10^6 -> 704.87234 | Z56: =94.2828596846101 -> 94.28286 | AF56: =((36.787694+11.68109-153.063162027155-54.3040999999999+64.6156183425448)+61.4977152467883-42.6783600365493) -> -75.463504 | AG56: =PIDR!D13 -> -110.2 | BG56: =+SUM(E56:BE56) -> 613.4917 | BL56: 666.96602 | BM56: 2.95773 | BO56: =BG56-V56 -> -91.380645
B57: PNC1505 | C57: Provisions non courantes pour rentes viagères (+1an) | BG57: =+SUM(E57:BE57) -> 0 | BL57: 0
B58: TPNC1200 | C58: Provisions non courantes | G58: =+SUM(G53:G57) -> 0 | H58: =+SUM(H53:H57) -> 0 | I58: =+SUM(I53:I57) -> 0 | J58: =+SUM(J53:J57) -> 0 | K58: =+SUM(K53:K57) -> 0 | L58: =+SUM(L53:L57) -> 0 | M58: =+SUM(M53:M57) -> 0 | N58: =+SUM(N53:N57) -> 0 | ... X58: =+SUM(X53:X57) -> 0 | Z58: =+SUM(Z53:Z57) -> 94.28286 | AA58: =+SUM(AA53:AA57) -> 0 | AB58: =+SUM(AB53:AB57) -> 0 | AC58: =+SUM(AC53:AC57) -> 0 | AD58: =+SUM(AD53:AD57) -> 0 | AE58: =+SUM(AE53:AE57) -> 0 | AF58: =+SUM(AF53:AF57) -> -75.463504 | AG58: =+SUM(AG53:AG57) -> -110.2 | ... BE58: =+SUM(BE53:BE57) -> 0 | BG58: =+SUM(BG53:BG57) -> 1027.8672 | BL58: 1114.9853
B60: PNC1618 | C60: Autres passifs financiers non courants (+1 an) | BG60: =+SUM(E60:BE60) -> 0 | BL60: 0
B61: TPNC 1400 | C61: Autres passifs financiers non courants (+1 an) | G61: =+G60 -> 0 | H61: =+H60 -> 0 | I61: =+I60 -> 0 | J61: =+J60 -> 0 | K61: =+K60 -> 0 | L61: =+L60 -> 0 | M61: =+M60 -> 0 | N61: =+N60 -> 0 | ... BE61: =+BE60 -> 0 | BG61: =+BG60 -> 0 | BL61: 0
B63: PNC1700 | C63: Impôts différés passifs | Z63: =-272.2492342804-12.8035080109648-17.8706515617857+8.88341999999997-65.9909429906782-15.7181490615539 -> -375.74907 | AF63: =-48.6085135+16.29-19.3846855027635-18.4493145740365+12.8035080109648 -> -57.349006 | AG63: =-AG23 -> 33.06 | AH63: =116.6182227+84.4976724+79.1784783+75.2440815+104.2731081 -> 459.81156 | AJ63: ='Passage Actif BC '!AF103*30% -> 157.75201 | AS63: =-37.3224465-30.9668613-24.8660631-8.88342 -> -102.03879 | AT63: =('Impacts_IFRS.16-09'!$L$85*30%) -> 17.467277 | AU63: 24.9225 | AV63: =-SUM('BG '!H29:I29)/10^6*30% -> 0 | BA63: =5.5444524+17.7777219+32.3217114-47.7858723+1.227195 -> 9.0852084 | BB63: =-SUM('BG '!H271:I272)/1000000*30% -> 0.0367932 | BE63: =-70.3099380546651+17.110721829504+3.82048358236114+(+Activation!CN240)*30%/1000000 -> -35.99645 | BG63: =+SUM(E63:BE63) -> 131.00204 | BK63: 65.990943 | BL63: 0
B64: TPNC 1500 | C64: Impôts différés passifs | G64: =+G63 -> 0 | H64: =+H63 -> 0 | I64: =+I63 -> 0 | J64: =+J63 -> 0 | K64: =+K63 -> 0 | L64: =+L63 -> 0 | M64: =+M63 -> 0 | N64: =+N63 -> 0 | ... BE64: =+BE63 -> -35.99645 | BG64: =+BG63 -> 131.00204 | BL64: 0
B66: PNC1812 | C66: Autres produits constatés d’avance non courants (+1 an) | BG66: =+SUM(E66:BE66) -> 0 | BL66: 0
B67: TPNC1600 | C67: Autres passifs non courants (+1 an) | G67: =+G66 -> 0 | H67: =+H66 -> 0 | I67: =+I66 -> 0 | J67: =+J66 -> 0 | K67: =+K66 -> 0 | L67: =+L66 -> 0 | M67: =+M66 -> 0 | N67: =+N66 -> 0 | ... BG67: =+BG66 -> 0 | BL67: 0
B69: TPNC100 | C69: TOTAL PASSIF NON COURANT | E69: =+E67+E64+E61+E58+E51+SUM(E40:E43) -> 47315.847 | G69: =+G67+G64+G61+G58+G51+SUM(G40:G43) -> 0 | H69: =+H67+H64+H61+H58+H51+SUM(H40:H43) -> 0 | I69: =+I67+I64+I61+I58+I51+SUM(I40:I43) -> 0 | J69: =+J67+J64+J61+J58+J51+SUM(J40:J43) -> 0 | K69: =+K67+K64+K61+K58+K51+SUM(K40:K43) -> 0 | L69: =+L67+L64+L61+L58+L51+SUM(L40:L43) -> 0 | M69: =+M67+M64+M61+M58+M51+SUM(M40:M43) -> 0 | N69: =+N67+N64+N61+N58+N51+SUM(N40:N43) -> 0 | ... BE69: =+BE67+BE64+BE61+BE58+BE51+SUM(BE40:BE43) -> -35.99645 | BG69: =+BG67+BG64+BG61+BG58+BG51+SUM(BG40:BG43) -> 33894.814 | BL69: 36841.602
C71: Dettes circulantes et ressources assimilées H.A.O. | E71: =+'Bilan Passif '!C32/10^6 -> 20173.766 | X71: =-E71 -> -20173.766 | BG71: =+SUM(E71:BE71) -> 0 | BL71: 0
C72: Clients, avances reçues | E72: =+'Bilan Passif '!C33/10^6 -> 1266.2504 | X72: =-E72 -> -1266.2504 | BG72: =+SUM(E72:BE72) -> 0 | BL72: 0
C73: Fournisseurs d'exploitation | E73: =+'Bilan Passif '!C34/10^6 -> 40919.406 | X73: =-E73 -> -40919.406 | BG73: =+SUM(E73:BE73) -> 0 | BL73: 0
C74: Dettes fiscales | E74: =+'Bilan Passif '!C35/10^6 -> 6711.8655 | X74: =-E74 -> -6711.8655 | BG74: =+SUM(E74:BE74) -> 0 | BL74: 0
C75: Dettes sociales | E75: =+'Bilan Passif '!C36/10^6 -> 0 | X75: =-E75 -> 0 | BG75: =+SUM(E75:BE75) -> 0 | BL75: 0
C76: Autres dettes | E76: =+'Bilan Passif '!C37/10^6 -> 34096.023 | X76: =-E76 -> -34096.023 | BG76: =+SUM(E76:BE76) -> 0 | BL76: 0
C77: Risques provisionnés | E77: =+'Bilan Passif '!C38/10^6 -> 212.95478 | X77: =-E77 -> -212.95478 | BG77: =+SUM(E77:BE77) -> 0 | BL77: 0
C78: Banques, crédits d'escompte | E78: =+'Bilan Passif '!C41/10^6 -> 52.277096 | X78: =-E78 -> -52.277096 | BG78: =+SUM(E78:BE78) -> 0 | BL78: 0
C79: Banques, crédits de trésorerie | E79: =+'Bilan Passif '!C42/10^6 -> 16044.722 | X79: =-E79 -> -16044.722 | BG79: =+SUM(E79:BE79) -> 0 | BL79: 0
C80: Banques, découverts | E80: =+'Bilan Passif '!C43/10^6 -> 0 | X80: =-E80 -> 0 | BG80: =+SUM(E80:BE80) -> 0 | BL80: 0
B82: PC4410 | C82: Clients créditeurs, avances et acomptes | X82: =-SUM('BG '!K176,'BG '!K197,'BG '!K202)/1000000 -> 1266.2504 | Z82: =(127.682725-(33.749288+127.682725)+19.533101+5.71425100000001)*0 -> 0 | BG82: =+SUM(E82:BE82) -> 1266.2504 | BL82: 8.501936
B83: PC4420 | C83: Fournisseurs et comptes rattachés | X83: =-SUM('BG '!K116:K164)/1000000 -> 40919.406 | Z83: =(-5404)*0 -> 0 | BB83: =-SUM('BG '!H270:I270)/10^6*0 -> 0 | BG83: =+SUM(E83:BE83) -> 40919.406 | BH83: 82256.765 | BL83: 46331.339
B84: PC4430 | C84: Personnel - créditeur | X84: =-SUM('BG '!K203,'BG '!K204,'BG '!K205,'BG '!K206,'BG '!K207)/1000000 -> 1063.9224 | Z84: =39.1309990000008*0 -> 0 | BG84: =+SUM(E84:BE84) -> 1063.9224 | BL84: 1298.5605
B85: PC4440 | C85: Organismes sociaux | X85: =-SUM('BG '!K210,'BG '!K208,'BG '!K209)/1000000 -> 342.62656 | BG85: =+SUM(E85:BE85) -> 342.62656 | BL85: 391.04953
B86: PC4455 | C86: Etat –TVA facturée | X86: =-SUM('BG '!K214:K217)/1000000 -> 2307.4653 | BG86: =+SUM(E86:BE86) -> 2307.4653 | BL86: 1115.8719
B87: PC4458 | C87: Etat - autres comptes créditeurs (hors impôt sur le résultat) | X87: =-SUM('BG '!$K$212,'BG '!$K$211,'BG '!$K$222,'BG '!$K$223,'BG '!$K$225,'BG '!$K$227,'BG '!$K$228,'BG '!$K$229,'BG '!$K$230,'BG '!$K$231)/1000000 -> 2997.8512 | BG87: =+SUM(E87:BE87) -> 2997.8512 | BH87: 1858.8314 | BL87: 1718.7474
B88: PC44611 | C88: Comptes d'actionnaires créditeurs-groupe | Z88: =(-6918.1479695*0-7079.14449*0-7256.088082*0-9618.229671*0-10868.3*0-9654.789301*0-8626.871441)*0 -> 0 | BG88: =+SUM(E88:BE88) -> 0 | BH88: 7256.0881 | BI88: 1356.4647 | BL88: 0
B89: PC44612 | C89: Comptes d'actionnaires créditeurs-minoritaires | BG89: =+SUM(E89:BE89) -> 0 | BL89: 0
B90: PC4471 | C90: Dividendes à payer (société mère) | BG90: =+SUM(E90:BE90) -> 0 | BL90: 0
B91: PC4473 | C91: Dividendes à payer (autres actionnaires) | BG91: =+SUM(E91:BE91) -> 0 | BL91: 0
B92: PC44741 | C92: Retenue à la source part du groupe | BG92: =+SUM(E92:BE92) -> 0 | BL92: 0
B93: PC44742 | C93: Retenue à la source part des minoritaires | BG93: =+SUM(E93:BE93) -> 0 | BL93: 0
B94: PC4481 | C94: Dettes sur acquisitions d'immobilisations corporelles et incorporelles (-1 an) | X94: =-SUM('BG '!K274,'BG '!K273,'BG '!K275,'BG '!K276,'BG '!K277,'BG '!K279,'BG '!K280,'BG '!K281,'BG '!K282,'BG '!K283)/1000000 -> 20173.766 | BG94: =+SUM(E94:BE94) -> 20173.766 | BL94: 19908.609
B95: PC4482 | C95: Dettes liées aux restructurations | BG95: =+SUM(E95:BE95) -> 0 | BL95: 0
B96: PC4488 | C96: Dettes rattachées aux autres créanciers | X96: =-SUM('BG '!$K$237,'BG '!$I$238,'BG '!$K$239,'BG '!$K$240,'BG '!$K$243,'BG '!$K$247,'BG '!$K$248,'BG '!$K$252,'BG '!$K$253,'BG '!$K$254,'BG '!$K$259,'BG '!$K$267,'BG '!$K$268,'BG '!K256,'BG '!K266,'BG '!K265,'BG '!K257)/10^6 -> 9705.8965 | Z96: =(7256.088082*0+9618.229671*0+10868.3*0+9654.789301*0+8626.871441)*0 -> 0 | BG96: =+SUM(E96:BE96) -> 9705.8965 | BI96: 3103.0648 | BL96: 9810.2605
B97: PC4490 | C97: Comptes de régularisation - passif | AQ97: =-[155]Feuil1!$G$17-104.425999-8.32064199999999 -> -104.26796 | AR97: =-AQ97-'Impacts_IFRS.16-09'!$L$71 -> -2.182481 | BG97: =+SUM(E97:BE97) -> -106.45044 | BL97: -92.771727
B98: PC4734 | C98: Dettes sur acquisition des titres et actifs financiers | BG98: =+SUM(E98:BE98) -> 0 | BL98: 0
B99: PC4735 | C99: Dettes sur acquisition des titres consolidés | BG99: =+SUM(E99:BE99) -> 0 | BL99: 0
B100: PC4736 | C100: Dépôts et cautionnements d'exploitation reçus | R100: =-SUM('BG '!K19:K20)/10^6 -> 328.54118 | X100: =-SUM('BG '!K255)/1000000 -> 24390.127 | Z100: =-Z42 -> 0 | BG100: =+SUM(E100:BE100) -> 24718.668 | BL100: 23802.05
B101: TP4000 | C101: Dettes d'exploitation | G101: =+SUM(G82:G100) -> 0 | H101: =+SUM(H82:H100) -> 0 | I101: =+SUM(I82:I100) -> 0 | J101: =+SUM(J82:J100) -> 0 | K101: =+SUM(K82:K100) -> 0 | L101: =+SUM(L82:L100) -> 0 | M101: =+SUM(M82:M100) -> 0 | N101: =+SUM(N82:N100) -> 0 | ... BE101: =+SUM(BE82:BE100) -> 0 | BG101: =+SUM(BG82:BG100) -> 103389.4 | BL101: 104292.22
B103: PC4453 | C103: Etat, impôt sur le résultat | BG103: =+SUM(E103:BE103) -> 0 | BL103: 0
B104: TP4100 | C104: Passif d'impôts exigibles | E104: =E103 -> 0 | G104: =G103 -> 0 | H104: =H103 -> 0 | I104: =I103 -> 0 | J104: =J103 -> 0 | K104: =K103 -> 0 | L104: =L103 -> 0 | M104: =M103 -> 0 | N104: =N103 -> 0 | ... BE104: =BE103 -> 0 | BG104: =BG103 -> 0 | BL104: 0
B106: PC4501 | C106: Provisions courantes d'exploitation (-1 an) | X106: =-SUM('BG '!K288,'BG '!K447)/10^6 -> 212.95478 | AW106: =-228.073865-160.682246-208.372387+205.183512-145.669848-201.865698-89.011717+291.024975+126.740934 -> -410.72634 | AX106: =-SUM('BG '!H269:I270)/10^6 -> 284.73357 | BG106: =+SUM(E106:BE106) -> 86.962007 | BL106: 86.962007
B107: PC4502 | C107: Provisions courantes - hors exploitation (-1 an) | BG107: =+SUM(E107:BE107) -> 0 | BL107: 0
B108: PC4503 | C108: Provisions courantes pour impôts (-1 an) | BG108: =+SUM(E108:BE108) -> 0 | BL108: 0
B109: PC4504 | C109: Provisions courantes pour indemnités de départ à la retraite (-1 an) | BG109: =+SUM(E109:BE109) -> 0 | BL109: 0
B110: PC4505 | C110: Provision courantes pour restructuration (-1 an) | BG110: =+SUM(E110:BE110) -> 0 | BL110: 0
B111: TP4200 | C111: Provisions courantes | E111: =+SUM(E106:E110) -> 0 | G111: =+SUM(G106:G110) -> 0 | H111: =+SUM(H106:H110) -> 0 | I111: =+SUM(I106:I110) -> 0 | J111: =+SUM(J106:J110) -> 0 | K111: =+SUM(K106:K110) -> 0 | L111: =+SUM(L106:L110) -> 0 | M111: =+SUM(M106:M110) -> 0 | N111: =+SUM(N106:N110) -> 0 | ... BE111: =+SUM(BE106:BE110) -> 0 | BG111: =+SUM(BG106:BG110) -> 86.962007 | BL111: 86.962007
B113: PC4712 | C113: Emprunts auprès des établissements de crédit (- 1an) | R113: =('Amortissment Coris'!C24+'TABLEAU CBAO'!E52+'SYNTHESE BOA'!D57)/1000000 -> 14500.022 | BG113: =+SUM(E113:BE113) -> 14500.022 | BL113: 13236.858
B114: PC4722 | C114: ICNE sur emprunts auprès des établissements de crédit | S114: =-SUM('BG '!K22,'BG '!K21)/10^6 -> 692.69349 | BG114: =+SUM(E114:BE114) -> 692.69349 | BL114: 0
B115: PC4713 | C115: Dettes envers la société mère (- 1an) | T115: =-T40*0 -> 0 | BG115: =+SUM(E115:BE115) -> 0 | BL115: 0
...

Sheet Passage P&L-par nature
A1: Sommaire | Z1: ² | AA1: yu
C2: Passage Compte de résultat - par nature | F2: Exploitation | S2: Financier | U2: Autres | Z2: 0
C4: =Cover!Y13 -> En millions de FCFA | E4: Comptes sociaux OHADA | F4: Reclass produits d'exploitation | G4: Reclass charges d'exploitation | H4: Commisions distributeurs | I4: Résiliation | J4: Achats Cartes SIM | K4: Var. de stock Cartes SIM | L4: Amortissements Cartes SIM | M4: SVA | N4: Frais immobilisés | O4: ECA | P4: Provision pour perte de change | Q4: ECP | R4: Complément PIDR | S4: Impact Désactualisation PIDR | T4: Escomptes | U4: Autres Reclassements | V4: ID social | W4: Activation Charges du personnel | X4: Droit d'actif | Y4: Delta | Z4: Ajust 1 | AA4: Ajust 2 | AB4: Ajust 3 | AD4: IFRS | AF4: IFRS
C6: Ventes de marchandises | E6: =+'Compte de résultat'!H6/10^6 -> 1124.4279 | F6: =-E6 -> -1124.4279 | AD6: =+SUM(E6:AB6) -> 0 | AF6: 0 | AG6: =+AD6-AF6 -> 0
C7: Ventes de produits fabriqués | E7: =+'Compte de résultat'!H7/10^6 -> 0 | F7: =-E7 -> 0 | AD7: =+SUM(E7:AB7) -> 0 | AF7: 0 | AG7: =+AD7-AF7 -> 0
C8: Travaux, services vendus | E8: =+'Compte de résultat'!H8/10^6 -> 103941.37 | F8: =-E8 -> -103941.37 | AD8: =+SUM(E8:AB8) -> 0 | AF8: 0 | AG8: =+AD8-AF8 -> 0
C9: Production stockée (ou déstockage) | E9: =+'Compte de résultat'!H9/10^6 -> 0 | F9: =-E9 -> 0 | AD9: =+SUM(E9:AB9) -> 0 | AF9: 0 | AG9: =+AD9-AF9 -> 0
C10: Production immobilisée | E10: =+'Compte de résultat'!H10/10^6 -> 0 | F10: =-E10 -> 0 | AD10: =+SUM(E10:AB10) -> 0 | AF10: 0 | AG10: =+AD10-AF10 -> 0
C11: Produits accessoires | E11: =+'Compte de résultat'!H11/10^6 -> 1193.5124 | F11: =-E11 -> -1193.5124 | AD11: =+SUM(E11:AB11) -> 0 | AF11: 0 | AG11: =+AD11-AF11 -> 0
C12: Subventions d'exploitation | E12: =+'Compte de résultat'!H14/10^6 -> 0 | F12: =-E12 -> 0 | AD12: =+SUM(E12:AB12) -> 0 | AF12: 0 | AG12: =+AD12-AF12 -> 0
C13: Autres produits | E13: =+'Compte de résultat'!H15/10^6 -> 1146.7034 | F13: =-E13 -> -1146.7034 | AD13: =+SUM(E13:AB13) -> 0 | AF13: 0 | AG13: =+AD13-AF13 -> 0
C14: Reprises de provisions | E14: =+'Compte de résultat'!H16/10^6 -> 1588.9122 | F14: =-E14 -> -1588.9122 | AD14: =+SUM(E14:AB14) -> 0 | AF14: 0 | AG14: =+AD14-AF14 -> 0
C15: Transferts de charges | E15: =+'Compte de résultat'!H17/10^6 -> 202.46258 | F15: =-E15 -> -202.46258 | AD15: =+SUM(E15:AB15) -> 0 | AF15: 0 | AG15: =+AD15-AF15 -> 0
AG16: =+AD16-AF16 -> 0
B17: RP7111 | C17: Ventes de biens | F17: =-SUM('BG '!K616,'BG '!J616,'BG '!J617,'BG '!K617,'BG '!J618,'BG '!K618,'BG '!J619,'BG '!K620,'BG '!J620,'BG '!K619,'BG '!K622,'BG '!K621)/10^6 -> 1124.4279 | AD17: =+SUM(E17:AB17) -> 1124.4279 | AF17: 1124.4279 | AG17: =+AD17-AF17 -> 0
B18: RP7112 | C18: Ventes de services | F18: =-SUM('BG '!J627,'BG '!K627,'BG '!J628,'BG '!K628,'BG '!J629,'BG '!K629,'BG '!J630,'BG '!K630,'BG '!J631,'BG '!K631,'BG '!J632,'BG '!K632,'BG '!J633,'BG '!K633,'BG '!J634,'BG '!K634,'BG '!J635,'BG '!K635,'BG '!J636,'BG '!K636,'BG '!J637,'BG '!K637,'BG '!J638,'BG '!K638,'BG '!J639,'BG '!K639,'BG '!J640,'BG '!K640,'BG '!J641,'BG '!K641,'BG '!J642,'BG '!K642,'BG '!J643,'BG '!K643,'BG '!J644,'BG '!K644,'BG '!J645,'BG '!K645,'BG '!J646,'BG '!K646,'BG '!J647,'BG '!K647,'BG '!J648,'BG '!K648,'BG '!J649,'BG '!K649,'BG '!J650,'BG '!K650,'BG '!J651,'BG '!K651,'BG '!J656,'BG '!K656,'BG '!J658,'BG '!K658,'BG '!J659,'BG '!K659,'BG '!J660,'BG '!K660,'BG '!J661,'BG '!K661,'BG '!J663,'BG '!K663,'BG '!J624,'BG '!J625,'BG '!J626,'BG '!K655,'BG '!J664,'BG '!J665,'BG '!J666,'BG '!J657:K657,'BG '!K664,'BG '!K652,'BG '!K653,'BG '!K654)/10^6 -> 103573.11 | H18: =SUM('BG '!J664,'BG '!J666)/1000000 -> 0 | U18: =-'Taxe 5%'!G36/1000000 -> -768.31055 | Y18: =[157]Feuil9!$G$205/1000000 -> 51.994344 | AD18: =+SUM(E18:AB18) -> 102856.79 | AF18: 102856.79 | AG18: =+AD18-AF18 -> 0
B19: RP7113 | C19: Autres revenus | F19: =-SUM('BG '!K667:K668,'BG '!K662)/10^6 -> 1561.7742 | AD19: =+SUM(E19:AB19) -> 1561.7742 | AF19: 1561.7742 | AG19: =+AD19-AF19 -> 0
B20: RP711 C | C20: Chiffre d'affaires | E20: =+SUM(E6:E15) -> 109197.39 | F20: =+F19+F18+F17 -> 106259.31 | G20: =+G19+G18+G17 -> 0 | H20: =+H19+H18+H17 -> 0 | I20: =+I19+I18+I17 -> 0 | J20: =+J19+J18+J17 -> 0 | K20: =+K19+K18+K17 -> 0 | L20: =+L19+L18+L17 -> 0 | M20: =+M19+M18+M17 -> 0 | ... AB20: =+AB19+AB18+AB17 -> 0 | AD20: =SUM(AD17:AD19) -> 105542.99 | AF20: 105542.99 | AG20: =+AD20-AF20 -> 0
AG21: =+AD21-AF21 -> 0
B22: RP7141 | C22: Immobilisations produites par l’entreprise pour elle-même | AD22: =+SUM(E22:AB22) -> 0 | AF22: 0 | AG22: =+AD22-AF22 -> 0
B23: RP7142 | C23: Subventions d’exploitation et d’investissement | AD23: =+SUM(E23:AB23) -> 0 | AF23: 0 | AG23: =+AD23-AF23 -> 0
B24: RP7143 | C24: Transferts de charges d’exploitation | F24: =-'BG '!K679/10^6 -> 143.76481 | U24: ='BG '!K679/10^6 -> -143.76481 | AD24: =+SUM(E24:AB24) -> 0 | AF24: 0 | AG24: =+AD24-AF24 -> 0
B25: RP7147 | C25: Gains de change d’exploitation | U25: =-((-'BG '!J587/10^6)*0+(SUM('BG '!H271:I272)/1000000)) -> 0.122644 | AD25: =+SUM(E25:AB25) -> 0.122644 | AF25: 0.122644 | AG25: =+AD25-AF25 -> 0
B26: RP7148 | C26: Produits de cession des immobilisations corporelles et incorporelles | U26: =(-'BG '!K684)/1000000 -> 0 | AD26: =+SUM(E26:AB26) -> 0 | AF26: 0 | AG26: =+AD26-AF26 -> 0
B27: RP7149 | C27: Produits opérationnels divers | F27: =-SUM('BG '!K670,'BG '!K671,'BG '!K669)/10^6 -> 110.90948 | U27: =SUM('BG '!K670,'BG '!K671)/1000000 -> -110.90948 | AD27: =+SUM(E27:AB27) -> 0 | AF27: 0 | AG27: =+AD27-AF27 -> 0
B28: RP714 | C28: Autres produits opérationnels | F28: =+SUM(F22:F27) -> 254.67429 | G28: =+SUM(G22:G27) -> 0 | H28: =+SUM(H22:H27) -> 0 | I28: =+SUM(I22:I27) -> 0 | J28: =+SUM(J22:J27) -> 0 | K28: =+SUM(K22:K27) -> 0 | L28: =+SUM(L22:L27) -> 0 | M28: =+SUM(M22:M27) -> 0 | ... AB28: =+SUM(AB22:AB27) -> 0 | AD28: =+SUM(AD22:AD27) -> 0.122644 | AF28: 0.122644 | AG28: =+AD28-AF28 -> 0
AG29: =+AD29-AF29 -> 0
B30: RP7152 | C30: Reprise sur amortissement et dépréciation des immobilisations incorporelles | AD30: =+SUM(E30:AB30) -> 0 | AF30: 0 | AG30: =+AD30-AF30 -> 0
B31: RP7153 | C31: Reprise sur amortissement et dépréciation des immobilisations corporelles | F31: =-'BG '!K682/10^6 -> 1458.8836 | U31: ='BG '!K682/10^6 -> -1458.8836 | AD31: =+SUM(E31:AB31) -> 0 | AF31: 0 | AG31: =+AD31-AF31 -> 0
B32: RP71551 | C32: Reprise de l'exploitation aux provisions du passif courant (hors provisions sur IS) | AD32: =+SUM(E32:AB32) -> 0 | AF32: 0 | AG32: =+AD32-AF32 -> 0
B33: RP71552 | C33: Reprise de l'exploitation aux provisions du passif non courant (hors provisions sur IS) | F33: =-SUM('BG '!K674,'BG '!K681)/10^6 -> 130.02862 | U33: =-F33 -> -130.02862 | AD33: =+SUM(E33:AB33) -> 0 | AF33: 0 | AG33: =+AD33-AF33 -> 0
B34: RP71560 | C34: Reprise sur provisions pour dépréciation des stocks | F34: =-SUM('BG '!K672)/10^6 -> 0 | U34: ='BG '!K672/1000000 -> 0 | AD34: =+SUM(E34:AB34) -> 0 | AF34: 0 | AG34: =+AD34-AF34 -> 0
B35: RP71561 | C35: Reprise sur provisions pour dépréciation des clients et comptes rattachés | F35: =-SUM('BG '!K673)/10^6 -> 1035.7939 | U35: =SUM('BG '!K673)/10^6 -> -1035.7939 | AD35: =+SUM(E35:AB35)+1035.79394778353 -> 1035.7939 | AF35: 1035.7939 | AG35: =+AD35-AF35 -> 0
B36: RP71562 | C36: Reprise sur provisions pour dépréciation des fournisseurs débiteurs, avances et acomptes | AD36: =+SUM(E36:AB36) -> 0 | AF36: 0 | AG36: =+AD36-AF36 -> 0
B37: RP71563 | C37: Reprise sur provisions pour dépréciation du personnel – débiteur | AD37: =+SUM(E37:AB37) -> 0 | AF37: 0 | AG37: =+AD37-AF37 -> 0
B38: RC71564 | C38: Reprise sur provisions pour dépréciation des dépôts et cautionnements versés | AD38: =+SUM(E38:AB38) -> 0 | AF38: 0 | AG38: =+AD38-AF38 -> 0
B39: RP71565 | C39: Reprise sur provisions pour dépréciation des créances fiscales | AD39: =+SUM(E39:AB39) -> 0 | AF39: 0 | AG39: =+AD39-AF39 -> 0
B40: RP71566 | C40: Reprise sur provisions pour dépréciation des autres débiteurs | AD40: =+SUM(E40:AB40) -> 0 | AF40: 0 | AG40: =+AD40-AF40 -> 0
B41: RC71567 | C41: Reprise sur provisions pour dépréciation des comptes d'actionnaires débiteurs | AD41: =+SUM(E41:AB41) -> 0 | AF41: 0 | AG41: =+AD41-AF41 -> 0
B42: RP715 | C42: Reprise sur amortissement et provisions | F42: =+SUM(F30:F41) -> 2624.7061 | G42: =+SUM(G30:G41) -> 0 | H42: =+SUM(H30:H41) -> 0 | I42: =+SUM(I30:I41) -> 0 | J42: =+SUM(J30:J41) -> 0 | K42: =+SUM(K30:K41) -> 0 | L42: =+SUM(L30:L41) -> 0 | M42: =+SUM(M30:M41) -> 0 | ... AB42: =+SUM(AB30:AB41) -> 0 | AD42: =+SUM(AD30:AD41) -> 1035.7939 | AF42: 1035.7939 | AG42: =+AD42-AF42 -> 0
AG43: =+AD43-AF43 -> 0
C44: Achats de marchandises | E44: =-'Compte de résultat'!H20/10^6 -> -1878.4953 | G44: =-E44 -> 1878.4953 | AD44: =+SUM(E44:AB44) -> 0 | AF44: 0 | AG44: =+AD44-AF44 -> 0
C45: Variation de stocks | E45: =-'Compte de résultat'!H21/10^6 -> -167.05843 | G45: =-E45 -> 167.05843 | AD45: =+SUM(E45:AB45) -> 0 | AF45: 0 | AG45: =+AD45-AF45 -> 0
C46: Achats de matières premières et fournitures liées | E46: =-'Compte de résultat'!H22/10^6 -> 0 | G46: =-E46 -> 0 | AD46: =+SUM(E46:AB46) -> 0 | AF46: 0 | AG46: =+AD46-AF46 -> 0
C47: Variation de stocks | E47: =-'Compte de résultat'!H23/10^6 -> 20.98283 | G47: =-E47 -> -20.98283 | AD47: =+SUM(E47:AB47) -> 0 | AF47: 0 | AG47: =+AD47-AF47 -> 0
C48: Autres achats | E48: =-'Compte de résultat'!H24/10^6 -> -13535.562 | G48: =-E48 -> 13535.562 | AD48: =+SUM(E48:AB48) -> 0 | AF48: 0 | AG48: =+AD48-AF48 -> 0
C49: Variation de stocks | E49: =-'Compte de résultat'!H25/10^6 -> -70.632568 | G49: =-E49 -> 70.632568 | AD49: =+SUM(E49:AB49) -> 0 | AF49: 0 | AG49: =+AD49-AF49 -> 0
C50: Transports | E50: =-'Compte de résultat'!H26/10^6 -> -185.10871 | G50: =-E50 -> 185.10871 | AD50: =+SUM(E50:AB50) -> 0 | AF50: 0 | AG50: =+AD50-AF50 -> 0
C51: Services extérieurs | E51: =-'Compte de résultat'!H27/10^6 -> -55972.756 | G51: =-E51 -> 55972.756 | AD51: =+SUM(E51:AB51) -> 0 | AF51: 0 | AG51: =+AD51-AF51 -> 0
C52: Impôts et taxes | E52: =-'Compte de résultat'!H28/10^6 -> -2756.9669 | G52: =-E52 -> 2756.9669 | AD52: =+SUM(E52:AB52) -> 0 | AF52: 0 | AG52: =+AD52-AF52 -> 0
C53: Autres charges | E53: =-'Compte de résultat'!H29/10^6 -> -2130.8242 | G53: =-E53 -> 2130.8242 | AD53: =+SUM(E53:AB53) -> 0 | AF53: 0 | AG53: =+AD53-AF53 -> 0
C54: Charges de personnel | E54: =-'Compte de résultat'!H30/10^6 -> -4859.4979 | G54: =-E54 -> 4859.4979 | AD54: =+SUM(E54:AB54) -> 0 | AF54: 0 | AG54: =+AD54-AF54 -> 0
C55: Dotations aux amortissements et aux provisions | E55: =-'Compte de résultat'!H31/10^6 -> -18531.485 | G55: =-E55 -> 18531.485 | AD55: =+SUM(E55:AB55) -> 0 | AF55: 0 | AG55: =+AD55-AF55 -> 0
AG56: =+AD56-AF56 -> 0
B57: RC6111 | C57: Coûts des terminaux | G57: =-SUM('BG '!J449:K451,'BG '!J454:K455,'BG '!J448:K448)/10^6 -> -1519.1529 | U57: =(-U88-U34-U83)*0 -> 0 | AD57: =+SUM(E57:AB57) -> -1519.1529 | AF57: -1519.1529 | AG57: =+AD57-AF57 -> 0
B58: RC6112 | C58: Charges d'interconnexion nationale et internationale | G58: =-SUM('BG '!J476:J483,'BG '!J485:K486,'BG '!K476:K483)/10^6 -> -7257.5141 | U58: ='COMMISSION MM'!G50/1000000 -> 4417.7264 | Y58: =[157]Feuil9!$G$33/1000000 -> 4.785804 | AD58: =+SUM(E58:AB58) -> -2835.0019 | AF58: -2835.0019 | AG58: =+AD58-AF58 -> 0
B59: RC6113 | C59: Autres achats consommés | G59: =-SUM('BG '!J452,'BG '!K452,'BG '!J453,'BG '!K453,'BG '!J456,'BG '!K456,'BG '!J457,'BG '!K457,'BG '!J458:K458,'BG '!J484:K484)/10^6 -> -748.8796 | J59: =SUM('BG '!J452,'BG '!K452)/1000000 -> 759.49458 | K59: =SUM('BG '!K456,'BG '!K457)/1000000+SUM('BG '!J456,'BG '!J457)/1000000 -> -233.65455 | U59: =-'Détails des Charges ope'!AH11/1000000 -> -4444.93 | AD59: =+SUM(E59:AB59) -> -4667.9696 | AF59: -4667.9696 | AG59: =+AD59-AF59 -> 0
B60: RC611 | C60: Achats consommés | F60: =+SUM(F57:F59) -> 0 | G60: =+SUM(G57:G59) -> -9525.5465 | H60: =+SUM(H57:H59) -> 0 | I60: =+SUM(I57:I59) -> 0 | J60: =+SUM(J57:J59) -> 759.49458 | K60: =+SUM(K57:K59) -> -233.65455 | L60: =+SUM(L57:L59) -> 0 | M60: =+SUM(M57:M59) -> 0 | ... AB60: =+SUM(AB57:AB59) -> 0 | AD60: =+SUM(AD57:AD59) -> -9022.1243 | AF60: -9022.1243 | AG60: =+AD60-AF60 -> 0
AG61: =+AD61-AF61 -> 0
B62: RC6121 | C62: Traitements et salaires | G62: =-SUM('BG '!J549,'BG '!J573,'BG '!J574,'BG '!J575,'BG '!J576,'BG '!J583,'BG '!J579,'BG '!J578,'BG '!J582,'BG '!J577)/10^6 -> -5175.2678 | U62: ='BG '!J549/1000000 -> 1074.25 | W62: =SUM(Activation!H176:H213)/1000000 -> 513.79162 | AD62: =+SUM(E62:AB62) -> -3587.2262 | AF62: -3790.9122 | AG62: =+AD62-AF62 -> 203.68606
B63: RC6122 | C63: Charges sociales | G63: =-SUM('BG '!J513,'BG '!J580,'BG '!K513)/10^6 -> -970.41569 | AD63: =+SUM(E63:AB63) -> -970.41569 | AF63: -970.41569 | AG63: =+AD63-AF63 -> 0
B64: RC6123 | C64: Rémunérations payées en action | AD64: =+SUM(E64:AB64) -> 0 | AF64: 0 | AG64: =+AD64-AF64 -> 0
B65: RC612 | C65: Charges de personnel | F65: =+SUM(F62:F64) -> 0 | G65: =+SUM(G62:G64) -> -6145.6835 | H65: =+SUM(H62:H64) -> 0 | I65: =+SUM(I62:I64) -> 0 | J65: =+SUM(J62:J64) -> 0 | K65: =+SUM(K62:K64) -> 0 | L65: =+SUM(L62:L64) -> 0 | M65: =+SUM(M62:M64) -> 0 | ... AB65: =+SUM(AB62:AB64) -> 0 | AD65: =+SUM(AD62:AD64) -> -4557.6418 | AF65: -4761.3279 | AG65: =+AD65-AF65 -> 203.68606
AG66: =+AD66-AF66 -> 0
B67: RC6131 | C67: Impôts et taxes directs et indirects | G67: =-SUM('BG '!J557,'BG '!J558,'BG '!J559,'BG '!J560,'BG '!J561,'BG '!J562,'BG '!J563,'BG '!J564,'BG '!K557,'BG '!K558,'BG '!K559,'BG '!K560,'BG '!K561,'BG '!K562,'BG '!K563,'BG '!K564,'BG '!J568,'BG '!J565)/10^6 -> -2763.3224 | U67: =(-SUM('BG '!K670)/1000000)*0+'Taxe 5%'!G36/1000000-U27 -> 879.22003 | Y67: =[157]Feuil9!$G$110/1000000 -> 17.770399 | AD67: =+SUM(E67:AB67) -> -1866.3319 | AF67: -1866.3319 | AG67: =+AD67-AF67 -> 3.0000001e-06
B68: RC6132 | C68: Redevances - régulateur | G68: =-SUM('BG '!J545)/10^6 -> -30095.551 | Y68: =[157]Feuil9!$G$95/1000000 -> -44.602617 | AD68: =+SUM(E68:AB68) -> -30140.154 | AF68: -30140.154 | AG68: =+AD68-AF68 -> 0
B69: RC613 | C69: Impôts et taxes | F69: =+F67+F68 -> 0 | G69: =+G67+G68 -> -32858.873 | H69: =+H67+H68 -> 0 | I69: =+I67+I68 -> 0 | J69: =+J67+J68 -> 0 | K69: =+K67+K68 -> 0 | L69: =+L67+L68 -> 0 | M69: =+M67+M68 -> 0 | ... AB69: =+AB67+AB68 -> 0 | AD69: =+AD67+AD68 -> -32006.486 | AF69: -32006.486 | AG69: =+AD69-AF69 -> 3.000001e-06
AG70: =+AD70-AF70 -> 0
B71: RC6140 | C71: Communication | G71: =-SUM('BG '!J516,'BG '!J517,'BG '!J518,'BG '!J519,'BG '!J521,'BG '!J522,'BG '!J523,'BG '!J524,'BG '!J525,'BG '!K516,'BG '!K517,'BG '!K518,'BG '!K519,'BG '!K521,'BG '!K522,'BG '!K523,'BG '!K524,'BG '!K525,'BG '!J520,'BG '!K461,'BG '!J461)/10^6 -> -3395.1467 | U71: =29.033395+28.89609 -> 57.929485 | AD71: =+SUM(E71:AB71) -> -3337.2172 | AF71: -3337.2172 | AG71: =+AD71-AF71 -> 0
B72: RC6141 | C72: Commissions | G72: =-SUM('BG '!J534)/1000000 -> -6841.6295 | H72: =-SUM('BG '!J664,'BG '!J666)/1000000 -> 0 | U72: =-'COMMISSION MM'!G50/1000000 -> -4417.7264 | Y72: =[157]Feuil9!$G$34/1000000+[157]Feuil9!$G$84/1000000 -> -89.556292 | AD72: =+SUM(E72:AB72) -> -11348.912 | AF72: -11348.912 | AG72: =+AD72-AF72 -> 0
B73: RC6142 | C73: Locations et charges locatives | G73: =-SUM('BG '!J492:K492,'BG '!J493:K493,'BG '!J494:K494,'BG '!J495:K495,'BG '!J496:K496,'BG '!J497:K497,'BG '!J498:K498,'BG '!J499:K499,'BG '!J500:K500,'BG '!J501:K501)/10^6 -> -4963.1088 | X73: ='Impacts_IFRS.16-09'!L81 -> 980.56182 | AD73: =+SUM(E73:AB73) -> -3982.547 | AF73: -3982.547 | AG73: =+AD73-AF73 -> 0
B74: RC6143 | C74: Entretiens, réparations et maintenances courantes | G74: =-SUM('BG '!J502,'BG '!J503,'BG '!J504,'BG '!J505,'BG '!J506,'BG '!J507,'BG '!J508,'BG '!J509,'BG '!J510,'BG '!K502,'BG '!K503,'BG '!K504,'BG '!K505,'BG '!K506,'BG '!K507,'BG '!K508,'BG '!K509,'BG '!J462:K463)/10^6 -> -4255.7388 | AD74: =+SUM(E74:AB74) -> -4255.7388 | AF74: -4255.7388 | AG74: =+AD74-AF74 -> 0
B75: RC6144 | C75: Rémunérations des intermédiaires et honoraires | G75: =-SUM('BG '!J535,'BG '!J536,'BG '!J537,'BG '!J538,'BG '!J539,'BG '!J541,'BG '!J542,'BG '!J546,'BG '!K538,'BG '!K542)/10^6 -> -3218.1219 | U75: =-'BG '!J549/1000000 -> -1074.25 | AD75: =+SUM(E75:AB75) -> -4292.372 | AF75: -4292.372 | AG75: =+AD75-AF75 -> 0
B76: RC6145 | C76: Frais postaux et services bancaires | G76: =-SUM('BG '!J531,'BG '!J532,'BG '!J533)/10^6 -> -211.06719 | U76: =-'BG '!J511/1000000 -> -60.386751 | Y76: =[157]Feuil9!$G$81/1000000 -> -17.803553 | AD76: =+SUM(E76:AB76) -> -289.25749 | AF76: -289.25749 | AG76: =+AD76-AF76 -> 0
B77: RC6146 | C77: Charges de départ volontaire | AD77: =+SUM(E77:AB77) -> 0 | AF77: 0 | AG77: =+AD77-AF77 -> 0
B78: RC6147 | C78: Pertes de change d'exploitation | G78: =-'BG '!J587/10^6*0 -> 0 | Q78: =-SUM('BG '!H271:I272)/1000000 -> 0.122644 | U78: =(SUM('BG '!H271:I272)/1000000) -> -0.122644 | AD78: =+SUM(E78:AB78) -> 0 | AF78: 0 | AG78: =+AD78-AF78 -> 0
B79: RC6148 | C79: Valeur nette comptable des immobilisations corporelles et incorporelles | U79: =-'BG '!J682/1000000 -> 0 | AD79: =+SUM(E79:AB79) -> 0 | AF79: 0 | AG79: =+AD79-AF79 -> 0
B80: RC6149 | C80: Charges opérationnelles diverses | G80: =-SUM('BG '!J459,'BG '!K459,'BG '!J460,'BG '!K460,'BG '!J465,'BG '!K465,'BG '!J466,'BG '!K466,'BG '!J467,'BG '!K467,'BG '!J468,'BG '!K468,'BG '!J469,'BG '!K469,'BG '!J470,'BG '!K470,'BG '!J471,'BG '!K471,'BG '!J473,'BG '!K473,'BG '!J474,'BG '!K474,'BG '!J475,'BG '!K475,'BG '!J487,'BG '!K487,'BG '!J488,'BG '!K488,'BG '!J489,'BG '!K489,'BG '!J490,'BG '!K490,'BG '!J491,'BG '!K491,'BG '!J511,'BG '!K511,'BG '!J512,'BG '!K512,'BG '!J514,'BG '!K514,'BG '!J515,'BG '!K515,'BG '!J526,'BG '!K526,'BG '!J527,'BG '!K527,'BG '!J528,'BG '!K528,'BG '!J529,'BG '!K529,'BG '!J530,'BG '!K530,'BG '!J540,'BG '!K540,'BG '!J543,'BG '!K543,'BG '!J544,'BG '!K544,'BG '!J547,'BG '!K547,'BG '!J548,'BG '!K548,'BG '!J552,'BG '!K552,'BG '!J553,'BG '!K553,'BG '!J554,'BG '!K554,'BG '!J555,'BG '!K555,'BG '!J566,'BG '!K566,'BG '!J567,'BG '!K567,'BG '!J569,'BG '!K569,'BG '!J550,'BG '!J551:K551,'BG '!J464)/1000000 -> -9774.2624 | U80: ='Détails des Charges ope'!AH11/1000000+'BG '!J511/1000000-U71-'BG '!K679/10^6-U35-U89 -> 4591.1521 | Y80: =[157]Feuil9!$G$93/1000000 -> -8.3e-05 | AD80: =+SUM(E80:AB80) -> -5183.1104 | AF80: -5183.1104 | AG80: =+AD80-AF80 -> 0
B81: RC614 | C81: Autres charges opérationnelles | F81: =+SUM(F71:F80) -> 0 | G81: =+SUM(G71:G80) -> -32659.075 | H81: =+SUM(H71:H80) -> 0 | I81: =+SUM(I71:I80) -> 0 | J81: =+SUM(J71:J80) -> 0 | K81: =+SUM(K71:K80) -> 0 | L81: =+SUM(L71:L80) -> 0 | M81: =+SUM(M71:M80) -> 0 | ... AB81: =+SUM(AB71:AB80) -> 0 | AD81: =+SUM(AD71:AD80) -> -32689.155 | AF81: -32689.155 | AG81: =+AD81-AF81 -> 0
AG82: =+AD82-AF82 -> 0
B83: RC6152 | C83: Dotations aux amortissements et aux dépréciations des immobilisations incorporelles | G83: =-SUM('BG '!J590:J594)/10^6 -> -7319.1067 | L83: =-+'Cartes SIM'!D21/1000000 -> -229.49406 | N83: =-SUM('BG '!H29:I29)/1000000 -> 0 | W83: =Activation!CN239/10^6 -> -291.34008 | AD83: =+SUM(E83:AB83) -> -7839.9408 | AF83: -7845.4797 | AG83: =+AD83-AF83 -> 5.5388825
B84: RC6151 | C84: Dotations aux amortissements du droit d'utilisati | X84: ='Impacts_IFRS.16-09'!L82 -> -805.85369 | AD84: =+SUM(E84:AB84) -> -805.85369 | AF84: -805.85369 | AG84: =+AD84-AF84 -> 0
B85: RC6153 | C85: Dotations aux amortissements et aux dépréciations des immobilisations corporelles | G85: =-SUM('BG '!J595:J612,'BG '!J614:J615)/10^6 -> -11073.89 | U85: =-'BG '!K682/10^6 -> 1458.8836 | AD85: =+SUM(E85:AB85) -> -9615.0063 | AF85: -9613.9246 | AG85: =+AD85-AF85 -> -1.081736 | AL85: -1.081736
B86: RC61551 | C86: Dotations de l'exploitation aux provisions du passif courant (hors provision sur IS) | G86: =-SUM('BG '!J572)/10^6 -> 0 | AD86: =+SUM(E86:AB86) -> 0 | AF86: 0 | AG86: =+AD86-AF86 -> 0
B87: RC61552 | C87: Dotations de l'exploitation aux provisions du passif non courant (hors provision sur IS) | G87: =-SUM('BG '!J613:K613)/1000000 -> -138.48867 | S87: =PIDR!D11 -> 38.6 | U87: =-U33 -> 130.02862 | Y87: =[157]Feuil9!$G$163/1000000 -> -61.497715 | AD87: =+SUM(E87:AB87) -> -31.357765 | AF87: -31.357765 | AG87: =+AD87-AF87 -> 0
B88: RC61560 | C88: Dotations aux provisions pour dépréciation des stocks | G88: =-SUM('BG '!J570:K570)/10^6 -> 30.528745 | U88: =-'BG '!K672/1000000 -> 0 | AD88: =+SUM(E88:AB88) -> 30.528745 | AF88: 30.528745 | AG88: =+AD88-AF88 -> 0
B89: RC61561 | C89: Dotations aux provisions pour dépréciation des clients et comptes rattachés | G89: =-SUM('BG '!J571)/10^6 -> -318.5715 | U89: =(-'BG '!K673/1000000) -> 1035.7939 | AD89: =+SUM(E89:AB89)-1035.793949 -> -318.5715 | AF89: -318.5715 | AG89: =+AD89-AF89 -> 0
B90: RC61562 | C90: Dotations aux provisions pour dépréciation des fournisseurs débiteurs, avances et acomptes | AD90: =+SUM(E90:AB90) -> 0 | AF90: 0 | AG90: =+AD90-AF90 -> 0
B91: RC61563 | C91: Dotations aux provisions pour dépréciation du personnel – débiteur | AD91: =+SUM(E91:AB91) -> 0 | AF91: 0 | AG91: =+AD91-AF91 -> 0
B92: RC61564 | C92: Dotations aux provisions pour dépréciation des dépôts et cautionnements versés | AD92: =+SUM(E92:AB92) -> 0 | AF92: 0 | AG92: =+AD92-AF92 -> 0
B93: RC61565 | C93: Dotations aux provisions pour dépréciation des créances fiscales | AD93: =+SUM(E93:AB93) -> 0 | AF93: 0 | AG93: =+AD93-AF93 -> 0
B94: RC61566 | C94: Dotations aux provisions pour dépréciation des autres débiteurs | AD94: =+SUM(E94:AB94) -> 0 | AF94: 0 | AG94: =+AD94-AF94 -> 0
B95: RC61567 | C95: Dotations aux provisions pour dépréciation des comptes d'actionnaires débiteurs | AD95: =+SUM(E95:AB95) -> 0 | AF95: 0 | AG95: =+AD95-AF95 -> 0
B96: RC615 | C96: Dotations aux amortissements et aux provisions | F96: =+SUM(F83:F95) -> 0 | G96: =+SUM(G83:G95) -> -18819.528 | H96: =+SUM(H83:H95) -> 0 | I96: =+SUM(I83:I95) -> 0 | J96: =+SUM(J83:J95) -> 0 | K96: =+SUM(K83:K95) -> 0 | L96: =+SUM(L83:L95) -> -229.49406 | M96: =+SUM(M83:M95) -> 0 | ... AB96: =+SUM(AB83:AB95) -> 0 | AD96: =+SUM(AD83:AD95) -> -18580.201 | AF96: -18584.658 | AG96: =+AD96-AF96 -> 4.4571465
AG97: =+AD97-AF97 -> 0
B98: R.100 | C98: Résultat d'exploitation "EBITA" | E98: =+SUM(E6:E15)+SUM(E44:E55) -> 9129.9812 | F98: =+SUM(F6:F15)+F20+F28+F42+SUM(F44:F55)+F60+F65+F69+F81+F96 -> -58.697776 | G98: =+SUM(G6:G15)+G20+G28+G42+SUM(G44:G55)+G60+G65+G69+G81+G96 -> 58.697776 | H98: =+SUM(H6:H15)+H20+H28+H42+SUM(H44:H55)+H60+H65+H69+H81+H96 -> 0 | I98: =+SUM(I6:I15)+I20+I28+I42+SUM(I44:I55)+I60+I65+I69+I81+I96 -> 0 | J98: =+SUM(J6:J15)+J20+J28+J42+SUM(J44:J55)+J60+J65+J69+J81+J96 -> 759.49458 | K98: =+SUM(K6:K15)+K20+K28+K42+SUM(K44:K55)+K60+K65+K69+K81+K96 -> -233.65455 | L98: =+SUM(L6:L15)+L20+L28+L42+SUM(L44:L55)+L60+L65+L69+L81+L96 -> -229.49406 | M98: =+SUM(M6:M15)+M20+M28+M42+SUM(M44:M55)+M60+M65+M69+M81+M96 -> 0 | ... AB98: =+SUM(AB6:AB15)+AB20+AB28+AB42+SUM(AB44:AB55)+AB60+AB65+AB69+AB81+AB96 -> 0 | AD98: =+SUM(AD6:AD15)+AD20+AD28+AD42+SUM(AD44:AD55)+AD60+AD65+AD69+AD81+AD96 -> 9723.2998 | AF98: 9515.1566 | AG98: =+AD98-AF98 -> 208.14321
AG99: =+AD99-AF99 -> 0
B100: RC6211 | C100: Dotations aux amortissements des immobilisations acquises par voie de regroupement d’entreprises | AD100: =+SUM(E100:AB100) -> 0 | AF100: 0 | AG100: =+AD100-AF100 -> 0
B101: RC6212 | C101: Dotations aux provisions pour dépréciation des immobilisations acquises par voie de regroupement d’entreprises | AD101: =+SUM(E101:AB101) -> 0 | AF101: 0 | AG101: =+AD101-AF101 -> 0
B102: RC6220 | C102: Juste valeur des actifs et passifs (Perte) | AD102: =+SUM(E102:AB102) -> 0 | AF102: 0 | AG102: =+AD102-AF102 -> 0
...

Sheet Feuil3

Sheet Passage P&L-par fonction
A1: Sommaire
C2: Passage Compte de résultat - par fonction | F2: Exploitation | S2: Financier | U2: Autres | Z2: Ajustements - consolidation
C4: =Cover!Y13 -> En millions de FCFA | E4: Comptes sociaux OHADA | F4: Reclass produits d'exploitation | G4: Reclass charges d'exploitation | H4: Commisions distributeurs | I4: Résiliation | J4: Achats Cartes SIM | K4: Var. de stock Cartes SIM | L4: Amortissements Cartes SIM | M4: SVA | N4: Frais immobilisés | O4: ECA | P4: Provision pour perte de change | Q4: ECP | R4: Complément PIDR | S4: Impact Désactualisation PIDR | T4: Escomptes | U4: Autres Reclassements | V4: ID social | W4: Activation Charges du personnel | X4: Droit d'actif | Y4: Delta | Z4: Ajust 1 | AA4: Ajust 2 | AB4: Ajust 3 | AD4: IFRS | AH4: IFRS | AM4: IFRS
C6: Ventes de marchandises | E6: =+'Passage P&L-par nature'!E6 -> 1124.4279 | F6: =-E6 -> -1124.4279 | AD6: =+SUM(E6:AB6) -> 0 | AH6: 0 | AI6: =AD6-AH6 -> 0 | AM6: 0 | AN6: =+AD6-AM6 -> 0
C7: Ventes de produits fabriqués | E7: =+'Passage P&L-par nature'!E7 -> 0 | F7: =-E7 -> 0 | AD7: =+SUM(E7:AB7) -> 0 | AH7: 0 | AI7: =AD7-AH7 -> 0 | AM7: 0 | AN7: =+AD7-AM7 -> 0
C8: Travaux, services vendus | E8: =+'Passage P&L-par nature'!E8 -> 103941.37 | F8: =-E8 -> -103941.37 | AD8: =+SUM(E8:AB8) -> 0 | AH8: 0 | AI8: =AD8-AH8 -> 0 | AM8: 0 | AN8: =+AD8-AM8 -> 0
C9: Production stockée (ou déstockage) | E9: =+'Passage P&L-par nature'!E9 -> 0 | F9: =-E9 -> 0 | AD9: =+SUM(E9:AB9) -> 0 | AH9: 0 | AI9: =AD9-AH9 -> 0 | AM9: 0 | AN9: =+AD9-AM9 -> 0
C10: Production immobilisée | E10: =+'Passage P&L-par nature'!E10 -> 0 | F10: =-E10 -> 0 | AD10: =+SUM(E10:AB10) -> 0 | AH10: 0 | AI10: =AD10-AH10 -> 0 | AM10: 0 | AN10: =+AD10-AM10 -> 0
C11: Produits accessoires | E11: =+'Passage P&L-par nature'!E11 -> 1193.5124 | F11: =-E11 -> -1193.5124 | AD11: =+SUM(E11:AB11) -> 0 | AH11: 0 | AI11: =AD11-AH11 -> 0 | AM11: 0 | AN11: =+AD11-AM11 -> 0
C12: Subventions d'exploitation | E12: =+'Passage P&L-par nature'!E12 -> 0 | F12: =-E12 -> 0 | AD12: =+SUM(E12:AB12) -> 0 | AH12: 0 | AI12: =AD12-AH12 -> 0 | AM12: 0 | AN12: =+AD12-AM12 -> 0
C13: Autres produits | E13: =+'Passage P&L-par nature'!E13 -> 1146.7034 | F13: =-E13 -> -1146.7034 | AD13: =+SUM(E13:AB13) -> 0 | AH13: 0 | AI13: =AD13-AH13 -> 0 | AM13: 0 | AN13: =+AD13-AM13 -> 0
C14: Reprises de provisions | E14: =+'Passage P&L-par nature'!E14 -> 1588.9122 | F14: =-E14 -> -1588.9122 | AD14: =+SUM(E14:AB14) -> 0 | AH14: 0 | AI14: =AD14-AH14 -> 0 | AM14: 0 | AN14: =+AD14-AM14 -> 0
C15: Transferts de charges | E15: =+'Passage P&L-par nature'!E15 -> 202.46258 | F15: =-E15 -> -202.46258 | AD15: =+SUM(E15:AB15) -> 0 | AH15: 0 | AI15: =AD15-AH15 -> 0 | AM15: 0 | AN15: =+AD15-AM15 -> 0
AI16: =AD16-AH16 -> 0 | AN16: =+AD16-AM16 -> 0
C17: Achats de marchandises | E17: =+'Passage P&L-par nature'!E44 -> -1878.4953 | G17: =-E17 -> 1878.4953 | AD17: =+SUM(E17:AB17) -> 0 | AH17: 0 | AI17: =AD17-AH17 -> 0 | AM17: 0 | AN17: =+AD17-AM17 -> 0
C18: Variation de stocks | E18: =+'Passage P&L-par nature'!E45 -> -167.05843 | G18: =-E18 -> 167.05843 | AD18: =+SUM(E18:AB18) -> 0 | AH18: 0 | AI18: =AD18-AH18 -> 0 | AM18: 0 | AN18: =+AD18-AM18 -> 0
C19: Achats de matières premières et fournitures liées | E19: =+'Passage P&L-par nature'!E46 -> 0 | G19: =-E19 -> 0 | AD19: =+SUM(E19:AB19) -> 0 | AH19: 0 | AI19: =AD19-AH19 -> 0 | AM19: 0 | AN19: =+AD19-AM19 -> 0
C20: Variation de stocks | E20: =+'Passage P&L-par nature'!E47 -> 20.98283 | G20: =-E20 -> -20.98283 | AD20: =+SUM(E20:AB20) -> 0 | AH20: 0 | AI20: =AD20-AH20 -> 0 | AM20: 0 | AN20: =+AD20-AM20 -> 0
C21: Autres achats | E21: =+'Passage P&L-par nature'!E48 -> -13535.562 | G21: =-E21 -> 13535.562 | AD21: =+SUM(E21:AB21) -> 0 | AH21: 0 | AI21: =AD21-AH21 -> 0 | AM21: 0 | AN21: =+AD21-AM21 -> 0
C22: Variation de stocks | E22: =+'Passage P&L-par nature'!E49 -> -70.632568 | G22: =-E22 -> 70.632568 | AD22: =+SUM(E22:AB22) -> 0 | AH22: 0 | AI22: =AD22-AH22 -> 0 | AM22: 0 | AN22: =+AD22-AM22 -> 0
C23: Transports | E23: =+'Passage P&L-par nature'!E50 -> -185.10871 | G23: =-E23 -> 185.10871 | AD23: =+SUM(E23:AB23) -> 0 | AH23: 0 | AI23: =AD23-AH23 -> 0 | AM23: 0 | AN23: =+AD23-AM23 -> 0
C24: Services extérieurs | E24: =+'Passage P&L-par nature'!E51 -> -55972.756 | G24: =-E24 -> 55972.756 | AD24: =+SUM(E24:AB24) -> 0 | AH24: 0 | AI24: =AD24-AH24 -> 0 | AM24: 0 | AN24: =+AD24-AM24 -> 0
C25: Impôts et taxes | E25: =+'Passage P&L-par nature'!E52 -> -2756.9669 | G25: =-E25 -> 2756.9669 | AD25: =+SUM(E25:AB25) -> 0 | AH25: 0 | AI25: =AD25-AH25 -> 0 | AM25: 0 | AN25: =+AD25-AM25 -> 0
C26: Autres charges | E26: =+'Passage P&L-par nature'!E53 -> -2130.8242 | G26: =-E26 -> 2130.8242 | AD26: =+SUM(E26:AB26) -> 0 | AH26: 0 | AI26: =AD26-AH26 -> 0 | AM26: 0 | AN26: =+AD26-AM26 -> 0
C27: Charges de personnel | E27: =+'Passage P&L-par nature'!E54 -> -4859.4979 | G27: =-E27 -> 4859.4979 | AD27: =+SUM(E27:AB27) -> 0 | AH27: 0 | AI27: =AD27-AH27 -> 0 | AM27: 0 | AN27: =+AD27-AM27 -> 0
C28: Dotations aux amortissements et aux provisions | E28: =+'Passage P&L-par nature'!E55 -> -18531.485 | G28: =-E28 -> 18531.485 | AD28: =+SUM(E28:AB28) -> 0 | AH28: 0 | AI28: =AD28-AH28 -> 0 | AM28: 0 | AN28: =+AD28-AM28 -> 0
AI29: =AD29-AH29 -> 0 | AN29: =+AD29-AM29 -> 0
B30: RP7111 | C30: Ventes de biens | F30: =+'Passage P&L-par nature'!F17 -> 1124.4279 | AD30: =+SUM(E30:AB30) -> 1124.4279 | AH30: 318.14612 | AI30: =AD30-AH30 -> 806.28174 | AM30: 1124.4279 | AN30: =+AD30-AM30 -> 0
B31: RP7112 | C31: Ventes de services | F31: =+'Passage P&L-par nature'!F18 -> 103573.11 | H31: =+'Passage P&L-par nature'!H18 -> 0 | I31: =+'Passage P&L-par nature'!I18 -> 0 | J31: =+'Passage P&L-par nature'!J18 -> 0 | K31: =+'Passage P&L-par nature'!K18 -> 0 | L31: =+'Passage P&L-par nature'!L18 -> 0 | M31: =+'Passage P&L-par nature'!M18 -> 0 | N31: =+'Passage P&L-par nature'!N18 -> 0 | O31: =+'Passage P&L-par nature'!O18 -> 0 | ... AB31: =+'Passage P&L-par nature'!AB18 -> 0 | AD31: =+SUM(E31:AB31) -> 102856.79 | AH31: 26105.742 | AI31: =AD31-AH31 -> 76751.048 | AM31: 102856.79 | AN31: =+AD31-AM31 -> 0
B32: RP7113 | C32: Autres revenus | F32: =+'Passage P&L-par nature'!F19 -> 1561.7742 | AD32: =+SUM(E32:AB32) -> 1561.7742 | AH32: 211.63947 | AI32: =AD32-AH32 -> 1350.1347 | AM32: 1561.7742 | AN32: =+AD32-AM32 -> 0
B33: RP711 C | C33: Chiffre d'affaires | F33: =+SUM(F30:F32) -> 106259.31 | G33: =+SUM(G30:G32) -> 0 | H33: =+SUM(H30:H32) -> 0 | I33: =+SUM(I30:I32) -> 0 | J33: =+SUM(J30:J32) -> 0 | K33: =+SUM(K30:K32) -> 0 | L33: =+SUM(L30:L32) -> 0 | M33: =+SUM(M30:M32) -> 0 | ... AB33: =+SUM(AB30:AB32) -> 0 | AD33: =+SUM(AD30:AD32) -> 105542.99 | AH33: 26635.527 | AI33: =AD33-AH33 -> 78907.464 | AM33: 105542.99 | AN33: =+AD33-AM33 -> 0
AI34: =AD34-AH34 -> 0 | AN34: =+AD34-AM34 -> 0
B35: RC6410 | C35: Coûts des ventes de biens | G35: ='Passage P&L-par nature'!G57+'Passage P&L-par nature'!G88+'Passage P&L-par nature'!F34+'Passage P&L-par nature'!G59 -> -2237.5037 | H35: ='Passage P&L-par nature'!H57+'Passage P&L-par nature'!H88+'Passage P&L-par nature'!G34+'Passage P&L-par nature'!H59 -> 0 | I35: ='Passage P&L-par nature'!I57+'Passage P&L-par nature'!I88+'Passage P&L-par nature'!H34+'Passage P&L-par nature'!I59 -> 0 | J35: ='Passage P&L-par nature'!J57+'Passage P&L-par nature'!J88+'Passage P&L-par nature'!I34+'Passage P&L-par nature'!J59 -> 759.49458 | K35: ='Passage P&L-par nature'!K57+'Passage P&L-par nature'!K88+'Passage P&L-par nature'!J34+'Passage P&L-par nature'!K59 -> -233.65455 | L35: ='Passage P&L-par nature'!L57+'Passage P&L-par nature'!L88+'Passage P&L-par nature'!K34+'Passage P&L-par nature'!L59 -> 0 | M35: ='Passage P&L-par nature'!M57+'Passage P&L-par nature'!M88+'Passage P&L-par nature'!L34+'Passage P&L-par nature'!M59 -> 0 | N35: ='Passage P&L-par nature'!N57+'Passage P&L-par nature'!N88+'Passage P&L-par nature'!M34+'Passage P&L-par nature'!N59 -> 0 | ... T35: ='Passage P&L-par nature'!T57+'Passage P&L-par nature'!T88+'Passage P&L-par nature'!S34+'Passage P&L-par nature'!T59 -> 0 | U35: ='Passage P&L-par nature'!U57+'Passage P&L-par nature'!U88+'Passage P&L-par nature'!T34+'Passage P&L-par nature'!U59-'Passage P&L-par nature'!U59 -> 0 | V35: ='Passage P&L-par nature'!V57+'Passage P&L-par nature'!V88+'Passage P&L-par nature'!U34+'Passage P&L-par nature'!V59 -> 0 | W35: ='Passage P&L-par nature'!W57+'Passage P&L-par nature'!W88+'Passage P&L-par nature'!V34+'Passage P&L-par nature'!W59 -> 0 | X35: ='Passage P&L-par nature'!X57+'Passage P&L-par nature'!X88+'Passage P&L-par nature'!W34+'Passage P&L-par nature'!X59 -> 0 | Y35: ='Passage P&L-par nature'!Y57+'Passage P&L-par nature'!Y88+'Passage P&L-par nature'!X34+'Passage P&L-par nature'!Y59 -> 0 | Z35: ='Passage P&L-par nature'!Z57+'Passage P&L-par nature'!Z88+'Passage P&L-par nature'!Y34+'Passage P&L-par nature'!Z59 -> 0 | AA35: ='Passage P&L-par nature'!AA57+'Passage P&L-par nature'!AA88+'Passage P&L-par nature'!Z34+'Passage P&L-par nature'!AA59 -> 0 | AB35: ='Passage P&L-par nature'!AB57+'Passage P&L-par nature'!AB88+'Passage P&L-par nature'!AA34+'Passage P&L-par nature'!AB59 -> 0 | AD35: =+SUM(E35:AB35) -> -1711.6637 | AH35: -414.08583 | AI35: =AD35-AH35 -> -1297.5779 | AM35: -1711.6637 | AN35: =+AD35-AM35 -> 0
B36: RC6420 | C36: Coûts des ventes de services | G36: ='Passage P&L-par nature'!G58+'Passage P&L-par nature'!G72 -> -14099.144 | H36: ='Passage P&L-par nature'!H58+'Passage P&L-par nature'!H72 -> 0 | I36: ='Passage P&L-par nature'!I58+'Passage P&L-par nature'!I72 -> 0 | J36: ='Passage P&L-par nature'!J58+'Passage P&L-par nature'!J72 -> 0 | K36: ='Passage P&L-par nature'!K58+'Passage P&L-par nature'!K72 -> 0 | L36: ='Passage P&L-par nature'!L58+'Passage P&L-par nature'!L72 -> 0 | M36: ='Passage P&L-par nature'!M58+'Passage P&L-par nature'!M72 -> 0 | N36: ='Passage P&L-par nature'!N58+'Passage P&L-par nature'!N72 -> 0 | ... AB36: ='Passage P&L-par nature'!AB58+'Passage P&L-par nature'!AB72 -> 0 | AD36: =+SUM(E36:AB36) -> -14183.914 | AH36: -3906.8126 | AI36: =AD36-AH36 -> -10277.101 | AM36: -14183.914 | AN36: =+AD36-AM36 -> 0
B37: RC640 | C37: Coûts des ventes | F37: =+SUM(F35:F36) -> 0 | G37: =+SUM(G35:G36) -> -16336.647 | H37: =+SUM(H35:H36) -> 0 | I37: =+SUM(I35:I36) -> 0 | J37: =+SUM(J35:J36) -> 759.49458 | K37: =+SUM(K35:K36) -> -233.65455 | L37: =+SUM(L35:L36) -> 0 | M37: =+SUM(M35:M36) -> 0 | ... AB37: =+SUM(AB35:AB36) -> 0 | AD37: =+SUM(AD35:AD36) -> -15895.578 | AH37: -4320.8984 | AI37: =AD37-AH37 -> -11574.679 | AM37: -15895.578 | AN37: =+AD37-AM37 -> 0
AI38: =AD38-AH38 -> 0 | AN38: =+AD38-AM38 -> 0
B39: R.80 | C39: Marge brute | F39: =+F37+F33 -> 106259.31 | G39: =+G37+G33 -> -16336.647 | H39: =+H37+H33 -> 0 | I39: =+I37+I33 -> 0 | J39: =+J37+J33 -> 759.49458 | K39: =+K37+K33 -> -233.65455 | L39: =+L37+L33 -> 0 | M39: =+M37+M33 -> 0 | ... R39: =+R37+R33 -> 0 | Z39: =+Z37+Z33 -> 0 | AA39: =+AA37+AA33 -> 0 | AB39: =+AB37+AB33 -> 0 | AD39: =+AD37+AD33 -> 89647.413 | AH39: 22314.629 | AI39: =AD39-AH39 -> 67332.785 | AM39: 89647.413 | AN39: =+AD39-AM39 -> 0
AI40: =AD40-AH40 -> 0 | AN40: =+AD40-AM40 -> 0
B41: RC6430 | C41: Coûts opérationnels | F41: ='Passage P&L-par nature'!AD28+'Passage P&L-par nature'!AD42-'Passage P&L-par nature'!AD34-'Passage P&L-par nature'!AD26 -> 1035.9166 | G41: =SUM('Passage P&L-par nature'!G65,'Passage P&L-par nature'!G69,'Passage P&L-par nature'!G81,'Passage P&L-par nature'!G89,'Passage P&L-par nature'!G86,'Passage P&L-par nature'!AD87)-'Passage P&L-par nature'!G72 -> -65171.932 | H41: =SUM('Passage P&L-par nature'!H65,'Passage P&L-par nature'!H69,'Passage P&L-par nature'!H81,'Passage P&L-par nature'!H89,'Passage P&L-par nature'!H86)-'Passage P&L-par nature'!H72 -> 0 | I41: =SUM('Passage P&L-par nature'!I65,'Passage P&L-par nature'!I69,'Passage P&L-par nature'!I81,'Passage P&L-par nature'!I89,'Passage P&L-par nature'!I86)-'Passage P&L-par nature'!I72 -> 0 | J41: =SUM('Passage P&L-par nature'!J65,'Passage P&L-par nature'!J69,'Passage P&L-par nature'!J81,'Passage P&L-par nature'!J89,'Passage P&L-par nature'!J86)-'Passage P&L-par nature'!J72 -> 0 | K41: =SUM('Passage P&L-par nature'!K65,'Passage P&L-par nature'!K69,'Passage P&L-par nature'!K81,'Passage P&L-par nature'!K89,'Passage P&L-par nature'!K86)-'Passage P&L-par nature'!K72 -> 0 | L41: =SUM('Passage P&L-par nature'!L65,'Passage P&L-par nature'!L69,'Passage P&L-par nature'!L81,'Passage P&L-par nature'!L89,'Passage P&L-par nature'!L86)-'Passage P&L-par nature'!L72 -> 0 | M41: =SUM('Passage P&L-par nature'!M65,'Passage P&L-par nature'!M69,'Passage P&L-par nature'!M81,'Passage P&L-par nature'!M89,'Passage P&L-par nature'!M86)-'Passage P&L-par nature'!M72 -> 0 | N41: =SUM('Passage P&L-par nature'!N65,'Passage P&L-par nature'!N69,'Passage P&L-par nature'!N81,'Passage P&L-par nature'!N89,'Passage P&L-par nature'!N86)-'Passage P&L-par nature'!N72 -> 0 | O41: =SUM('Passage P&L-par nature'!O65,'Passage P&L-par nature'!O69,'Passage P&L-par nature'!O81,'Passage P&L-par nature'!O89,'Passage P&L-par nature'!O86)-'Passage P&L-par nature'!O72 -> 0 | ... T41: =SUM('Passage P&L-par nature'!T65,'Passage P&L-par nature'!T69,'Passage P&L-par nature'!T81,'Passage P&L-par nature'!T89,'Passage P&L-par nature'!T86)-'Passage P&L-par nature'!T72 -> 0 | U41: =SUM('Passage P&L-par nature'!U65,'Passage P&L-par nature'!U69,'Passage P&L-par nature'!U81,'Passage P&L-par nature'!U89,'Passage P&L-par nature'!U86)-'Passage P&L-par nature'!U72-AD49+'Passage P&L-par nature'!U59 -> 2058.6561 | V41: =SUM('Passage P&L-par nature'!V65,'Passage P&L-par nature'!V69,'Passage P&L-par nature'!V81,'Passage P&L-par nature'!V89,'Passage P&L-par nature'!V86)-'Passage P&L-par nature'!V72 -> 0 | W41: =SUM('Passage P&L-par nature'!W65,'Passage P&L-par nature'!W69,'Passage P&L-par nature'!W81,'Passage P&L-par nature'!W89,'Passage P&L-par nature'!W86)-'Passage P&L-par nature'!W72 -> 513.79162 | X41: =SUM('Passage P&L-par nature'!X65,'Passage P&L-par nature'!X69,'Passage P&L-par nature'!X81,'Passage P&L-par nature'!X89,'Passage P&L-par nature'!X86)-'Passage P&L-par nature'!X72 -> 980.56182 | Y41: =SUM('Passage P&L-par nature'!Y65,'Passage P&L-par nature'!Y69,'Passage P&L-par nature'!Y81,'Passage P&L-par nature'!Y89,'Passage P&L-par nature'!Y86)-'Passage P&L-par nature'!Y72 -> -44.635854 | Z41: =SUM('Passage P&L-par nature'!Z65,'Passage P&L-par nature'!Z69,'Passage P&L-par nature'!Z81,'Passage P&L-par nature'!Z89,'Passage P&L-par nature'!Z86)-'Passage P&L-par nature'!Z72 -> 0 | AA41: =SUM('Passage P&L-par nature'!AA65,'Passage P&L-par nature'!AA69,'Passage P&L-par nature'!AA81,'Passage P&L-par nature'!AA89,'Passage P&L-par nature'!AA86)-'Passage P&L-par nature'!AA72 -> 0 | AB41: =SUM('Passage P&L-par nature'!AB65,'Passage P&L-par nature'!AB69,'Passage P&L-par nature'!AB81,'Passage P&L-par nature'!AB89,'Passage P&L-par nature'!AB86)-'Passage P&L-par nature'!AB72 -> 0 | AD41: =+SUM(E41:AB41) -> -60627.519 | AH41: -15376.649 | AI41: =AD41-AH41 -> -45250.87 | AM41: -60831.205 | AN41: =+AD41-AM41 -> 203.68606 | AO41: 58.363346
AI42: =AD42-AH42 -> 0 | AN42: =+AD42-AM42 -> 0
B43: R.90 | C43: EBITDA | F43: =+F41+F39 -> 107295.22 | G43: =+G41+G39 -> -81508.579 | H43: =+H41+H39 -> 0 | I43: =+I41+I39 -> 0 | J43: =+J41+J39 -> 759.49458 | K43: =+K41+K39 -> -233.65455 | L43: =+L41+L39 -> 0 | M43: =+M41+M39 -> 0 | ... AB43: =+AB41+AB39 -> 0 | AD43: =+AD41+AD39 -> 29019.895 | AH43: 6937.9799 | AI43: =AD43-AH43 -> 22081.915 | AM43: 28816.208 | AN43: =+AD43-AM43 -> 203.68606
AI44: =AD44-AH44 -> 0 | AN44: =+AD44-AM44 -> 0
B45: RP7148 | C45: Produits des cessions des immobilisations corporelles et Incorporelles | F45: ='Passage P&L-par nature'!F26 -> 0 | G45: ='Passage P&L-par nature'!G26 -> 0 | H45: ='Passage P&L-par nature'!H26 -> 0 | I45: ='Passage P&L-par nature'!I26 -> 0 | J45: ='Passage P&L-par nature'!J26 -> 0 | K45: ='Passage P&L-par nature'!K26 -> 0 | L45: ='Passage P&L-par nature'!L26 -> 0 | M45: ='Passage P&L-par nature'!M26 -> 0 | ... AB45: ='Passage P&L-par nature'!AB26 -> 0 | AD45: =+SUM(E45:AB45) -> 0 | AH45: 0 | AI45: =AD45-AH45 -> 0 | AM45: 0 | AN45: =+AD45-AM45 -> 0
B46: RP7149 | C46: Produits opérationnels divers | AD46: =+SUM(E46:AB46) -> 0 | AH46: 0 | AI46: =AD46-AH46 -> 0 | AM46: 0 | AN46: =+AD46-AM46 -> 0
B47: RP714 | C47: Autres produits opérationnels | F47: =+SUM(F45:F46) -> 0 | G47: =+SUM(G45:G46) -> 0 | H47: =+SUM(H45:H46) -> 0 | I47: =+SUM(I45:I46) -> 0 | J47: =+SUM(J45:J46) -> 0 | K47: =+SUM(K45:K46) -> 0 | L47: =+SUM(L45:L46) -> 0 | M47: =+SUM(M45:M46) -> 0 | ... AB47: =+SUM(AB45:AB46) -> 0 | AD47: =+SUM(AD45:AD46) -> 0 | AH47: 0 | AI47: =AD47-AH47 -> 0 | AM47: 0 | AN47: =+AD47-AM47 -> 0
AI48: =AD48-AH48 -> 0 | AN48: =+AD48-AM48 -> 0
B49: RC6148 | C49: Valeur nette comptable des immobilisations corporelles et incorporelles | G49: ='Passage P&L-par nature'!G79 -> 0 | H49: ='Passage P&L-par nature'!H79 -> 0 | I49: ='Passage P&L-par nature'!I79 -> 0 | J49: ='Passage P&L-par nature'!J79 -> 0 | K49: ='Passage P&L-par nature'!K79 -> 0 | L49: ='Passage P&L-par nature'!L79 -> 0 | M49: ='Passage P&L-par nature'!M79 -> 0 | N49: ='Passage P&L-par nature'!N79 -> 0 | ... AB49: ='Passage P&L-par nature'!AB79 -> 0 | AD49: =+SUM(E49:AB49) -> 0 | AH49: 0 | AI49: =AD49-AH49 -> 0 | AM49: 0 | AN49: =+AD49-AM49 -> 0
B50: RC6149 | C50: Charges opérationnelles diverses | AD50: =+SUM(E50:AB50) -> 0 | AH50: 0 | AI50: =AD50-AH50 -> 0 | AM50: 0 | AN50: =+AD50-AM50 -> 0
B51: RC614 | C51: Autres charges opérationnelles | F51: =+SUM(F49:F50) -> 0 | G51: =+SUM(G49:G50) -> 0 | H51: =+SUM(H49:H50) -> 0 | I51: =+SUM(I49:I50) -> 0 | J51: =+SUM(J49:J50) -> 0 | K51: =+SUM(K49:K50) -> 0 | L51: =+SUM(L49:L50) -> 0 | M51: =+SUM(M49:M50) -> 0 | ... AB51: =+SUM(AB49:AB50) -> 0 | AD51: =+SUM(AD49:AD50) -> 0 | AH51: 0 | AI51: =AD51-AH51 -> 0 | AM51: 0 | AN51: =+AD51-AM51 -> 0
AI52: =AD52-AH52 -> 0 | AN52: =+AD52-AM52 -> 0
B53: RP7152 | C53: Reprises sur amortissements des immobilisations incorporelles | AD53: =+SUM(E53:AB53) -> 0 | AH53: 0 | AI53: =AD53-AH53 -> 0 | AM53: 0 | AN53: =+AD53-AM53 -> 0
B54: RP7153 | C54: Reprises sur amortissements des immobilisations corporelles | F54: ='Passage P&L-par nature'!F31*0 -> 0 | G54: ='Passage P&L-par nature'!G31*0 -> 0 | H54: ='Passage P&L-par nature'!H31*0 -> 0 | I54: ='Passage P&L-par nature'!I31*0 -> 0 | J54: ='Passage P&L-par nature'!J31*0 -> 0 | K54: ='Passage P&L-par nature'!K31*0 -> 0 | L54: ='Passage P&L-par nature'!L31*0 -> 0 | M54: ='Passage P&L-par nature'!M31*0 -> 0 | ... AB54: ='Passage P&L-par nature'!AB31*0 -> 0 | AD54: =+SUM(E54:AB54) -> 0 | AH54: 0 | AI54: =AD54-AH54 -> 0 | AM54: 0 | AN54: =+AD54-AM54 -> 0
B55: RP71541 | C55: Reprise sur provisions pour dépréciation des immobilisations incorporelles (hors IFRS3) | AD55: =+SUM(E55:AB55) -> 0 | AH55: 0 | AI55: =AD55-AH55 -> 0 | AM55: 0 | AN55: =+AD55-AM55 -> 0
B56: RP71542 | C56: Reprise sur provisions pour dépréciation des immobilisations corporelles | AD56: =+SUM(E56:AB56) -> 0 | AH56: 0 | AI56: =AD56-AH56 -> 0 | AM56: 0 | AN56: =+AD56-AM56 -> 0
B57: YRP71551 | C57: Reprises de l'exploitation aux provisions du passif courant (hors provisions sur IS) "HORS EBITDA" | AD57: =+SUM(E57:AB57) -> 0 | AH57: 0 | AI57: =AD57-AH57 -> 0 | AM57: 0 | AN57: =+AD57-AM57 -> 0
B58: YRP71552 | C58: Reprises de l'exploitation aux provisions du passif non courant (hors provisions sur IS) "HORS EBITDA" | AD58: =+SUM(E58:AB58) -> 0 | AH58: 0 | AI58: =AD58-AH58 -> 0 | AM58: 0 | AN58: =+AD58-AM58 -> 0
B59: RP715 | C59: Reprise sur amortissemnts et provisions | F59: =+SUM(F53:F58) -> 0 | G59: =+SUM(G53:G58) -> 0 | H59: =+SUM(H53:H58) -> 0 | I59: =+SUM(I53:I58) -> 0 | J59: =+SUM(J53:J58) -> 0 | K59: =+SUM(K53:K58) -> 0 | L59: =+SUM(L53:L58) -> 0 | M59: =+SUM(M53:M58) -> 0 | ... W59: =+SUM(W53:W58) -> 0 | Y59: =+SUM(Y53:Y58) -> 0 | Z59: =+SUM(Z53:Z58) -> 0 | AA59: =+SUM(AA53:AA58) -> 0 | AB59: =+SUM(AB53:AB58) -> 0 | AD59: =+SUM(AD53:AD58) -> 0 | AH59: 0 | AI59: =AD59-AH59 -> 0 | AM59: 0 | AN59: =+AD59-AM59 -> 0
AI60: =AD60-AH60 -> 0 | AN60: =+AD60-AM60 -> 0
B61: RC6152 | C61: Dotations aux amortissements des immobilisations incorporelles | G61: ='Passage P&L-par nature'!G83 -> -7319.1067 | J61: ='Passage P&L-par nature'!J83 -> 0 | K61: ='Passage P&L-par nature'!K83 -> 0 | L61: ='Passage P&L-par nature'!L83 -> -229.49406 | M61: ='Passage P&L-par nature'!M83 -> 0 | N61: ='Passage P&L-par nature'!N83 -> 0 | O61: ='Passage P&L-par nature'!O83 -> 0 | P61: ='Passage P&L-par nature'!P83 -> 0 | Q61: ='Passage P&L-par nature'!Q83 -> 0 | ... AB61: ='Passage P&L-par nature'!AB83 -> 0 | AD61: =+SUM(E61:AB61) -> -7839.9408 | AH61: -116.06242 | AI61: =AD61-AH61 -> -7723.8784 | AM61: -7845.4797 | AN61: =+AD61-AM61 -> 5.5388825
B62: RC6151 | C62: Dotations aux amortissements du droit d'utilisati | X62: ='Passage P&L-par nature'!X84 -> -805.85369 | Y62: ='Passage P&L-par nature'!Y84 -> 0 | AD62: =+SUM(E62:AB62) -> -805.85369 | AH62: -192.96474 | AI62: =AD62-AH62 -> -612.88894 | AM62: -805.85369 | AN62: =+AD62-AM62 -> 0
B63: RC6153 | C63: Dotations aux amortissements des immobilisations corporelles | G63: ='Passage P&L-par nature'!G85 -> -11073.89 | H63: ='Passage P&L-par nature'!H85 -> 0 | I63: ='Passage P&L-par nature'!I85 -> 0 | J63: ='Passage P&L-par nature'!J85 -> 0 | K63: ='Passage P&L-par nature'!K85 -> 0 | L63: ='Passage P&L-par nature'!L85 -> 0 | M63: ='Passage P&L-par nature'!M85 -> 0 | N63: ='Passage P&L-par nature'!N85 -> 0 | ... Y63: ='Passage P&L-par nature'!Y85 -> 0 | AD63: =+SUM(E63:AB63) -> -9615.0063 | AH63: -4301.1442 | AI63: =AD63-AH63 -> -5313.8621 | AM63: -9613.9246 | AN63: =+AD63-AM63 -> -1.081736 | AO63: -1.081736
B64: YRC61551 | C64: Dotations de l'exploitation aux provisions du passif courant (hors provision sur IS) "HORS EBITDA" | AD64: =+SUM(E64:AB64) -> 0 | AH64: 0 | AI64: =AD64-AH64 -> 0 | AM64: 0 | AN64: =+AD64-AM64 -> 0
B65: YRC61552 | C65: Dotations de l'exploitation aux provisions du passif non courant (hors provision sur IS) "HORS EBITDA" | AD65: =+SUM(E65:AB65) -> 0 | AH65: 0 | AI65: =AD65-AH65 -> 0 | AM65: 0 | AN65: =+AD65-AM65 -> 0
B66: RC615 | C66: Dotations aux amortissements et aux provisions | F66: =+SUM(F61:F65) -> 0 | G66: =+SUM(G61:G65) -> -18392.997 | H66: =+SUM(H61:H65) -> 0 | I66: =+SUM(I61:I65) -> 0 | J66: =+SUM(J61:J65) -> 0 | K66: =+SUM(K61:K65) -> 0 | L66: =+SUM(L61:L65) -> -229.49406 | M66: =+SUM(M61:M65) -> 0 | ... AB66: =+SUM(AB61:AB65) -> 0 | AD66: =+SUM(AD61:AD65) -> -18260.801 | AH66: -4610.1714 | AI66: =AD66-AH66 -> -13650.629 | AM66: -18265.258 | AN66: =+AD66-AM66 -> 4.4571465
AI67: =AD67-AH67 -> 0 | AN67: =+AD67-AM67 -> 0
B68: R.100 | C68: Résultat d'exploitation "EBITA" | E68: =+SUM(E6:E15)+SUM(E17:E28) -> 9129.9812 | F68: =+F66+F59+F51+F47+F43+SUM(F19:F28)+SUM(F6:F15) -> -1902.1616 | G68: =+G66+G59+G51+G47+G43+SUM(G19:G28)+SUM(G6:G15) -> -1879.725 | H68: =+H66+H59+H51+H47+H43+SUM(H19:H28)+SUM(H6:H15) -> 0 | I68: =+I66+I59+I51+I47+I43+SUM(I19:I28)+SUM(I6:I15) -> 0 | J68: =+J66+J59+J51+J47+J43+SUM(J19:J28)+SUM(J6:J15) -> 759.49458 | K68: =+K66+K59+K51+K47+K43+SUM(K19:K28)+SUM(K6:K15) -> -233.65455 | L68: =+L66+L59+L51+L47+L43+SUM(L19:L28)+SUM(L6:L15) -> -229.49406 | M68: =+M66+M59+M51+M47+M43+SUM(M19:M28)+SUM(M6:M15) -> 0 | ... AB68: =+AB66+AB59+AB51+AB47+AB43+SUM(AB19:AB28)+SUM(AB6:AB15) -> 0 | AD68: =+AD66+AD59+AD51+AD47+AD43+SUM(AD17:AD28)+SUM(AD6:AD15) -> 10759.094 | AH68: 2327.8085 | AI68: =AD68-AH68 -> 8431.2852 | AM68: 10550.951 | AN68: =+AD68-AM68 -> 208.14321
AI69: =AD69-AH69 -> 0 | AN69: =+AD69-AM69 -> 0
C70: Contrôle visuel (vs EBITA P&L par nature) | AD70: =AD68-'Passage P&L-par nature'!AD98 -> 1035.7939 | AH70: 0 | AI70: =AD70-AH70 -> 1035.7939 | AM70: 1035.7939

Sheet Bilan-par flux
A1: Sommaire
C3: Bilan par flux
C4: =Cover!Y13 -> En millions de FCFA | E4: F00 Ouverture | G4: F10 Résultat | H4: F12 Affectation | I4: F13 Dividendes | J4: F17 Opérations avec les actionnaires | K4: F20 Augmentation | L4: F25 Dotation | M4: F40 Diminution | N4: F45 Reprise | O4: F60 BFR | P4: F88 Reclassement | Q4: F98 Désactualisation | R4: F82 JV par P&L | S4: F87 Changement de Méthode | U4: F99 Clôture | W4: F99 Clôture | AD4: F99 Clôture
B7: ANC2100 | C7: Ecarts d’acquisition | E7: 26399 | P7: =U7-SUM(Q7:S7)-SUM(E7:O7) -> 0 | U7: =+'Passage Actif BC '!BH10 -> 26399 | W7: 26399 | X7: =W7-U7 -> 0 | AD7: 26399 | AE7: =U7-AD7 -> 0
B8: ANC2910 | C8: Provisions pour dépréciation des écarts d’acquisition | E8: 0 | P8: =U8-SUM(Q8:S8)-SUM(E8:O8) -> 0 | U8: =+'Passage Actif BC '!BH11 -> 0 | W8: 0 | X8: =W8-U8 -> 0 | AD8: 0 | AE8: =U8-AD8 -> 0
B9: TANC2000 | C9: Ecarts d'acquisition | E9: 26399 | F9: =F8+F7 -> 0 | K9: =K8+K7 -> 0 | L9: =L8+L7 -> 0 | M9: =M8+M7 -> 0 | N9: =N8+N7 -> 0 | O9: =O8+O7 -> 0 | P9: =+SUM(P7:P8) -> 0 | Q9: =Q8+Q7 -> 0 | R9: =R8+R7 -> 0 | S9: =S8+S7 -> 0 | U9: =SUM(E9:T9) -> 26399 | W9: 26399 | X9: =W9-U9 -> 0 | AD9: 26399 | AE9: =U9-AD9 -> 0
X10: =W10-U10 -> 0 | AE10: =U10-AD10 -> 0
B11: ANC2210 | C11: Frais de développement | E11: 0 | P11: =U11-SUM(Q11:S11)-SUM(E11:O11) -> 0 | U11: =+'Passage Actif BC '!BH19 -> 0 | W11: 0 | X11: =W11-U11 -> 0 | AD11: 0 | AE11: =U11-AD11 -> 0
B12: ANC2821 | C12: Amortissements & dépréciation des frais de développement | E12: 0 | P12: =U12-SUM(Q12:S12)-SUM(E12:O12) -> 0 | U12: =+'Passage Actif BC '!BH20 -> 0 | W12: 0 | X12: =W12-U12 -> 0 | AD12: 0 | AE12: =U12-AD12 -> 0
B13: ANC2221 | C13: Brevets et marques | E13: 5886.4 | K13: =+SUMIFS('BG '!$H$29:$H$71,'BG '!$C$29:$C$71,'Bilan-par flux'!B13)/1000000 -> 486.59055 | P13: =U13-SUM(Q13:S13)-SUM(E13:O13) -> 0.038394 | U13: =+'Passage Actif BC '!BH21 -> 6373.0289 | W13: 5904.0054 | X13: =W13-U13 -> -469.02355 | AD13: 6373.0289 | AE13: =U13-AD13 -> 0
B14: ANC28221 | C14: Amortissements & dépréciation des brevets et marques | E14: -5372.7 | L14: ='BG '!I73/10^6 -> -3558.751 | P14: =U14-SUM(Q14:S14)-SUM(E14:O14) -> 2558.422 | U14: =+'Passage Actif BC '!BH22 -> -6373.0289 | W14: -5372.6873 | X14: =W14-U14 -> 1000.3416 | AD14: -6373.0289 | AE14: =U14-AD14 -> 0
B15: ANC2222 | C15: Logiciels | E15: 55747.3 | K15: =(+SUMIFS('BG '!$H$29:$H$71,'BG '!$C$29:$C$71,'Bilan-par flux'!B15)+'BG '!I34)/1000000 -> 4399.833 | P15: =U15-SUM(Q15:S15)-SUM(E15:O15) -> 0.011615 | U15: =+'Passage Actif BC '!BH23 -> 60147.145 | W15: 55830.691 | X15: =W15-U15 -> -4316.454 | AD15: 60147.145 | AE15: =U15-AD15 -> 0
B16: ANC28222 | C16: Amortissements & dépréciation des logiciels | E16: -40753.2 | L16: =SUM('BG '!H74:I75)/10^6 -> -1204.9401 | P16: =U16-SUM(Q16:S16)-SUM(E16:O16) -> -2558.3853 | U16: =+'Passage Actif BC '!BH24 -> -44516.525 | W16: -40753.176 | X16: =W16-U16 -> 3763.3495 | AD16: -44516.525 | AE16: =U16-AD16 -> 0
B17: ANC2240 | C17: Licences télécom | E17: 80000 | K17: =+SUMIFS('BG '!$H$29:$H$71,'BG '!$C$29:$C$71,'Bilan-par flux'!B17)/1000000 -> 0 | P17: =U17-SUM(Q17:S17)-SUM(E17:O17) -> 0 | U17: =+'Passage Actif BC '!BH25 -> 80000 | W17: 80000 | X17: =W17-U17 -> 0 | AD17: 80000 | AE17: =U17-AD17 -> 0
B18: ANC2824 | C18: Amortissements & dépréciation des licences télécom | E18: -53968.7 | L18: =SUM('BG '!I72)/10^6 -> -2555.4156 | P18: =U18-SUM(Q18:S18)-SUM(E18:O18) -> 0.010108 | U18: =+'Passage Actif BC '!BH26 -> -56524.105 | W18: -53968.69 | X18: =W18-U18 -> 2555.4156 | AD18: -56524.105 | AE18: =U18-AD18 -> 0
B19: ANC2250 | C19: Immobilisations incorporelles acquises par voie de regroupement d'entreprises | E19: 0 | K19: =+SUMIFS('BG '!$H$29:$H$71,'BG '!$C$29:$C$71,'Bilan-par flux'!B19)/1000000 -> 0 | P19: =U19-SUM(Q19:S19)-SUM(E19:O19) -> 0 | U19: =+'Passage Actif BC '!BH27 -> 0 | W19: 0 | X19: =W19-U19 -> 0 | AD19: 0 | AE19: =U19-AD19 -> 0
B20: ANC2825 | C20: Amortissements & dépréciation des immobilisations incorporelles acquises par voie de regroupement d'entreprises | E20: 0 | P20: =U20-SUM(Q20:S20)-SUM(E20:O20) -> 0 | U20: =+'Passage Actif BC '!BH28 -> 0 | W20: 0 | X20: =W20-U20 -> 0 | AD20: 0 | AE20: =U20-AD20 -> 0
B21: ANC2260 | C21: Cartes SIM | E21: 3069.3 | K21: =+SUMIFS('BG '!$H$29:$H$71,'BG '!$C$29:$C$71,'Bilan-par flux'!B21)/1000000*0+'BG '!J452/10^6 -> 759.49458 | P21: =U21-SUM(Q21:S21)-SUM(E21:O21) -> -0.0081570888 | U21: =+'Passage Actif BC '!BH29 -> 3828.7864 | W21: 3017.9303 | X21: =W21-U21 -> -810.85611 | AD21: 3828.7864 | AE21: =U21-AD21 -> 0
B22: ANC2826 | C22: Amortissements & dépréciation cartes SIM | E22: -2160.8 | L22: =-'Cartes SIM'!D21/10^6 -> -229.49406 | P22: =U22-SUM(Q22:S22)-SUM(E22:O22) -> 0.016865718 | U22: =+'Passage Actif BC '!BH30 -> -2390.2772 | W22: -2207.8561 | X22: =W22-U22 -> 182.4211 | AD22: -2395.8161 | AE22: =U22-AD22 -> 5.5388825
B23: ANC2270 | C23: Droit d'utilisation de l'actif | E23: 6303.7 | P23: =U23-SUM(Q23:S23)-SUM(E23:O23) -> 434.42499 | U23: =+'Passage Actif BC '!BH31 -> 6738.125 | W23: 6303.8794 | X23: =W23-U23 -> -434.24562 | AD23: 6738.125 | AE23: =U23-AD23 -> 0
B24: ANC2827 | C24: Amortissements du droit d'utilisation de l'actif | E24: -4071.8 | L24: ='Impacts_IFRS.16-09'!G70 -> -805.85369 | P24: =U24-SUM(Q24:S24)-SUM(E24:O24) -> 0.032365 | U24: =+'Passage Actif BC '!BH32 -> -4877.6213 | W24: -4264.7324 | X24: =W24-U24 -> 612.88894 | AD24: -4877.6213 | AE24: =U24-AD24 -> 0
B25: ANC2280 | C25: Autres immobilisations incorporelles | E25: 0 | K25: =+SUMIFS('BG '!$H$29:$H$71,'BG '!$C$29:$C$71,'Bilan-par flux'!B25)/1000000+SUM(Activation!$H$176:$H$213)/1000000 -> 513.79162 | P25: =U25-SUM(Q25:S25)-SUM(E25:O25) -> -232.57917 | U25: =+'Passage Actif BC '!BH33 -> 281.21245 | W25: 0 | X25: =W25-U25 -> -281.21245 | AD25: 77.52639 | AE25: =U25-AD25 -> 203.68606
B26: ANC2828 | C26: Amortissements & dépréciation des autres immobilisations incorporelles | E26: 0 | L26: =+Activation!$CN$239/1000000 -> -291.34008 | P26: =U26-SUM(Q26:S26)-SUM(E26:O26) -> 291.34008 | U26: =+'Passage Actif BC '!BH34 -> 0 | W26: 0 | X26: =W26-U26 -> 0 | AD26: 0 | AE26: =U26-AD26 -> 0
B27: ANC2298 | C27: Immobilisations incorporelles en cours | E27: 538.8 | K27: =+(SUMIFS('BG '!$H$29:$H$71,'BG '!$C$29:$C$71,'Bilan-par flux'!B27)+SUM('BG '!I65))/1000000-58.9098019999999 -> -213.99797 | P27: =U27-SUM(Q27:S27)-SUM(E27:O27) -> 0 | U27: =+'Passage Actif BC '!BH35 -> 324.80203 | W27: 601.40583 | X27: =W27-U27 -> 276.6038 | AD27: 324.80203 | AE27: =U27-AD27 -> 0
B28: ANC2929 | C28: Provisions pour dépréciation des immobilisations incorporelles en cours | E28: 0 | P28: =U28-SUM(Q28:S28)-SUM(E28:O28) -> 0 | U28: =+'Passage Actif BC '!BH36 -> 0 | W28: 0 | X28: =W28-U28 -> 0 | AD28: 0 | AE28: =U28-AD28 -> 0
B29: TANC2100 | C29: Immobilisations incorporelles | E29: =SUM(E11:E28) -> 45218.3 | K29: =+SUM(K11:K28) -> 5945.7118 | L29: =+SUM(L11:L28) -> -8645.7945 | M29: =+SUM(M11:M28) -> 0 | N29: =+SUM(N11:N28) -> 0 | O29: =+SUM(O11:O28) -> 0 | P29: =+SUM(P11:P28) -> 493.32385 | Q29: =+SUM(Q11:Q28) -> 0 | R29: =+SUM(R11:R28) -> 0 | S29: =+SUM(S11:S28) -> 0 | U29: =SUM(U11:U28) -> 43011.541 | W29: 45090.77 | X29: =W29-U29 -> 2079.2287 | AD29: 42802.316 | AE29: =U29-AD29 -> 209.22494
X30: =W30-U30 -> 0 | AE30: =U30-AD30 -> 0
B31: ANC2310 | C31: Terrains | E31: 2991.8 | K31: =+(SUMIFS('BG '!$H$29:$H$71,'BG '!$C$29:$C$71,'Bilan-par flux'!B31)+SUM('BG '!I35:I37))/1000000 -> 178.28958 | P31: =U31-SUM(Q31:S31)-SUM(E31:O31) -> 0.002748 | U31: =+'Passage Actif BC '!BH46 -> 3170.0923 | W31: 2994.4277 | X31: =W31-U31 -> -175.66458 | AD31: 3170.0923 | AE31: =U31-AD31 -> 0
B32: ANC2831 | C32: Amortissement & dépréciation des terrains | P32: =U32-SUM(Q32:S32)-SUM(E32:O32) -> 0 | U32: =+'Passage Actif BC '!BH47 -> 0 | W32: 0 | X32: =W32-U32 -> 0 | AD32: 0 | AE32: =U32-AD32 -> 0
B33: ANC2320 | C33: Constructions | E33: 931.9 | K33: =+SUMIFS('BG '!$H$29:$H$71,'BG '!$C$29:$C$71,'Bilan-par flux'!B33)/1000000+'BG '!I47/1000000 -> 743.51729 | P33: =U33-SUM(Q33:S33)-SUM(E33:O33) -> 0.041786 | U33: =+'Passage Actif BC '!BH48 -> 1675.4591 | W33: 1059.4316 | X33: =W33-U33 -> -616.02743 | AD33: 1603.398 | AE33: =U33-AD33 -> 72.061121 | AF33: 72.061121
B34: ANC2832 | C34: Amortissement & dépréciation des constructions | E34: -30.7 | L34: =SUM('BG '!I76)/10^6 -> -22.697003 | P34: =U34-SUM(Q34:S34)-SUM(E34:O34) -> 0.046648 | U34: =+'Passage Actif BC '!BH49 -> -53.350355 | W34: -30.653352 | X34: =W34-U34 -> 22.697003 | AD34: -53.350355 | AE34: =U34-AD34 -> 0 | AF34: 0
B35: ANC2330 | C35: Installations techniques, matériel et outillage | E35: 143185.2 | K35: =+SUM('BG '!H39,'BG '!H40,'BG '!H41,'BG '!H48,'BG '!H49,'BG '!H50,'BG '!H51,'BG '!H52,'BG '!H53,'BG '!H61,'BG '!H64,'BG '!I61,'BG '!I64)/1000000-79.7 -> 16361.834 | P35: =U35-SUM(Q35:S35)-SUM(E35:O35) -> 232.57456 | U35: =+'Passage Actif BC '!BH50 -> 159779.61 | W35: 144233.88 | X35: =W35-U35 -> -15545.725 | AD35: 159089.48 | AE35: =U35-AD35 -> 690.13267 | AF35: 690.13267
B36: ANC2833 | C36: Amortissement & dépréciation des installations techniques, matériel et outillage | E36: -96591.5 | L36: =SUM('BG '!H77,'BG '!I77,'BG '!H78,'BG '!I78,'BG '!H79,'BG '!I79,'BG '!H85,'BG '!I85,'BG '!H86,'BG '!I86,'BG '!H87,'BG '!I87,'BG '!H88,'BG '!I88,'BG '!H89,'BG '!I89,'BG '!H98,'BG '!I98,'BG '!K682)/10^6-'BG '!$K$682/1000000 -> -8546.7789 | P36: =U36-SUM(Q36:S36)-SUM(E36:O36) -> -291.2989 | U36: =+'Passage Actif BC '!BH51 -> -105429.58 | W36: -100961.59 | X36: =W36-U36 -> 4467.9853 | AD36: -105428.5 | AE36: =U36-AD36 -> -1.081736 | AF36: -1.081736
B37: ANC2340 | C37: Matériel de transport | E37: 715.9 | K37: =+SUMIFS('BG '!$H$29:$H$71,'BG '!$C$29:$C$71,'Bilan-par flux'!B37)/1000000 -> 0 | M37: =SUM('BG '!I58,'BG '!I59)/10^6 -> 0 | P37: =U37-SUM(Q37:S37)-SUM(E37:O37) -> -0.004802 | U37: =+'Passage Actif BC '!BH52 -> 715.8952 | W37: 715.8952 | X37: =W37-U37 -> 0 | AD37: 715.8952 | AE37: =U37-AD37 -> 0 | AF37: 0
B38: ANC2834 | C38: Amortissements & dépréciation du matériel de transport | E38: -714.3 | L38: =SUM('BG '!H95,'BG '!H96,'BG '!I96,'BG '!I95)/10^6-'[154]RECAP 1'!$K$49 -> -1.007486 | P38: =U38-SUM(Q38:S38)-SUM(E38:O38) -> -0.025119 | U38: =+'Passage Actif BC '!BH53 -> -715.3326 | W38: -714.32512 | X38: =W38-U38 -> 1.007486 | AD38: -715.3326 | AE38: =U38-AD38 -> 0 | AF38: 0
B39: ANC2350 | C39: Mobilier et matériel de bureau | E39: 9452.2 | K39: =+(SUMIFS('BG '!$H$29:$H$71,'BG '!$C$29:$C$71,'Bilan-par flux'!$B$39)+SUM('BG '!I62))/1000000 -> 4213.8522 | M39: =SUM('BG '!I55:I56)/10^6*0 -> 0 | P39: =U39-SUM(Q39:S39)-SUM(E39:O39) -> 0.024807 | U39: =+'Passage Actif BC '!BH54 -> 13666.077 | W39: 9838.7955 | X39: =W39-U39 -> -3827.2814 | AD39: 13261.46 | AE39: =U39-AD39 -> 404.61685 | AF39: 404.61685
B40: ANC2835 | C40: Amortissements & dépréciation du mobilier, matériel de bureau | E40: -5470.6 | L40: =SUM('BG '!H91:I93)/10^6-'[154]RECAP 1'!$K$48 -> -947.25802 | M40: =-SUM('BG '!I55:I56)/10^6*0 -> 0 | P40: =U40-SUM(Q40:S40)-SUM(E40:O40) -> -0.002347 | U40: =+'Passage Actif BC '!BH55 -> -6417.8604 | W40: -5470.6023 | X40: =W40-U40 -> 947.25803 | AD40: -6417.8604 | AE40: =U40-AD40 -> 0 | AF40: 0
B41: ANC2360 | C41: Avances et acomptes versés sur commandes d'immobilisations corporelles | E41: 0 | M41: =(SUM('BG '!H65,'BG '!I65)/1000000+110.707727099991)*0 -> 0 | P41: =U41-SUM(Q41:S41)-SUM(E41:O41) -> 0 | U41: =+'Passage Actif BC '!BH56 -> 0 | W41: 0 | X41: =W41-U41 -> 0 | AD41: 0 | AE41: =U41-AD41 -> 0
B42: ANC2936 | C42: Provisions pour dépréciation des avances et acomptes versés sur commandes d'immobilisations corporelles | E42: 0 | P42: =U42-SUM(Q42:S42)-SUM(E42:O42) -> 0 | U42: =+'Passage Actif BC '!BH57 -> 0 | W42: 0 | X42: =W42-U42 -> 0 | AD42: 0 | AE42: =U42-AD42 -> 0
B43: ANC2380 | C43: Autres immobilisations corporelles | E43: 2661.7 | K43: =+SUMIFS('BG '!$H$29:$H$71,'BG '!$C$29:$C$71,'Bilan-par flux'!B43)/1000000 -> 180.46084 | M43: ='BG '!I57/10^6*0 -> 0 | P43: =U43-SUM(Q43:S43)-SUM(E43:O43) -> -0.049341 | U43: =+'Passage Actif BC '!BH58 -> 2842.1115 | W43: 2673.1112 | X43: =W43-U43 -> -169.00029 | AD43: 2842.1115 | AE43: =U43-AD43 -> 0
B44: ANC2838 | C44: Amortissement & dépréciation des autres immobilisations corporelles | E44: -1846.8 | L44: =SUM('BG '!H80,'BG '!I80,'BG '!H81,'BG '!I81,'BG '!H82,'BG '!I82,'BG '!H83,'BG '!I83,'BG '!H84,'BG '!I84,'BG '!H90,'BG '!I90,'BG '!H94,'BG '!I94,'BG '!H97,'BG '!I97)/10^6-'[154]RECAP 1'!$K$42 -> -97.264885 | M44: =-'BG '!I57/10^6*0 -> 0 | P44: =U44-SUM(Q44:S44)-SUM(E44:O44) -> -0.033387 | U44: =+'Passage Actif BC '!BH59 -> -1944.0983 | W44: -1846.8334 | X44: =W44-U44 -> 97.264885 | AD44: -1944.0983 | AE44: =U44-AD44 -> 0
B45: ANC2390 | C45: Immobilisations corporelles en cours | E45: 0 | K45: =+SUMIFS('BG '!$H$29:$H$71,'BG '!$C$29:$C$71,'Bilan-par flux'!B45)/1000000 -> 0 | P45: =U45-SUM(Q45:S45)-SUM(E45:O45) -> 0 | U45: =+'Passage Actif BC '!BH60 -> 0 | W45: 0 | X45: =W45-U45 -> 0 | AD45: 0 | AE45: =U45-AD45 -> 0
B46: ANC2939 | C46: Provisions pour dépréciation des immobilisations en cours | E46: 0 | P46: =U46-SUM(Q46:S46)-SUM(E46:O46) -> 0 | U46: =+'Passage Actif BC '!BH61 -> 0 | W46: 0 | X46: =W46-U46 -> 0 | AD46: 0 | AE46: =U46-AD46 -> 0
B47: TANC2200 | C47: Immobilisations corporelles | E47: =SUM(E31:E46) -> 55284.8 | K47: =SUM(K31:K46) -> 21677.954 | L47: =SUM(L31:L46) -> -9615.0063 | M47: =SUM(M31:M46) -> 0 | N47: =SUM(N31:N46) -> 0 | O47: =SUM(O31:O46) -> 0 | P47: =SUM(P31:P46) -> -58.72335 | Q47: =SUM(Q31:Q46) -> 0 | R47: =SUM(R31:R46) -> 0 | ... U47: =SUM(U31:U46) -> 67289.024 | W47: 52491.538 | X47: =W47-U47 -> -14797.486 | AD47: 66123.295 | AE47: =U47-AD47 -> 1165.7289
X48: =W48-U48 -> 0 | AE48: =U48-AD48 -> 0
B49: ANC2410 | C49: Prêts immobilisés (+1 an) | E49: 0 | K49: =+SUMIFS('BG '!$H$29:$H$71,'BG '!$C$29:$C$71,'Bilan-par flux'!B49)/1000000 -> 0 | P49: =U49-SUM(Q49:S49)-SUM(E49:O49) -> 0 | U49: =+'Passage Actif BC '!BH67 -> 0 | W49: 0 | X49: =W49-U49 -> 0 | AD49: 0 | AE49: =U49-AD49 -> 0
B50: ANC2941 | C50: Provisions pour dépréciation des prêts immobilisés (+1 an) | E50: 0 | P50: =U50-SUM(Q50:S50)-SUM(E50:O50) -> 0 | U50: =+'Passage Actif BC '!BH68 -> 0 | W50: 0 | X50: =W50-U50 -> 0 | AD50: 0 | AE50: =U50-AD50 -> 0
B51: ANC2420 | C51: Cash bloqué pour emprunts | E51: 0 | K51: =+SUMIFS('BG '!$H$29:$H$71,'BG '!$C$29:$C$71,'Bilan-par flux'!B51)/1000000 -> 0 | P51: =U51-SUM(Q51:S51)-SUM(E51:O51) -> 0 | U51: =+'Passage Actif BC '!BH69 -> 0 | W51: 0 | X51: =W51-U51 -> 0 | AD51: 0 | AE51: =U51-AD51 -> 0
B52: ANC2942 | C52: Provisions pour dépréciation du cash bloqué pour emprunts | E52: 0 | P52: =U52-SUM(Q52:S52)-SUM(E52:O52) -> 0 | U52: =+'Passage Actif BC '!BH70 -> 0 | W52: 0 | X52: =W52-U52 -> 0 | AD52: 0 | AE52: =U52-AD52 -> 0
B53: ANC2431 | C53: Actifs financiers non courants détenus jusqu’à l’échéance | E53: 0 | K53: =+SUMIFS('BG '!$H$29:$H$71,'BG '!$C$29:$C$71,'Bilan-par flux'!B53)/1000000 -> 0 | P53: =U53-SUM(Q53:S53)-SUM(E53:O53) -> 0 | U53: =+'Passage Actif BC '!BH71 -> 0 | W53: 0 | X53: =W53-U53 -> 0 | AD53: 0 | AE53: =U53-AD53 -> 0
B54: ANC29431 | C54: Provisions pour dépréciation des actifs financiers non courants détenus jusqu’à l'échéance | E54: 0 | P54: =U54-SUM(Q54:S54)-SUM(E54:O54) -> 0 | U54: =+'Passage Actif BC '!BH72 -> 0 | W54: 0 | X54: =W54-U54 -> 0 | AD54: 0 | AE54: =U54-AD54 -> 0
B55: ANC2433 | C55: Créances immobilisées | E55: 22100.3 | K55: 2299.2074 | P55: =U55-SUM(Q55:S55)-SUM(E55:O55) -> 0 | U55: =+'Passage Actif BC '!BH73 -> 24399.507 | W55: 22761.237 | X55: =W55-U55 -> -1638.2701 | AD55: 24399.507 | AE55: =U55-AD55 -> 0
B56: ANC29433 | C56: Provisions pour dépréciation des créances immobilisées | E56: 0 | P56: =U56-SUM(Q56:S56)-SUM(E56:O56) -> 0 | U56: =+'Passage Actif BC '!BH74 -> 0 | W56: 0 | X56: =W56-U56 -> 0 | AD56: 0 | AE56: =U56-AD56 -> 0
B57: ANC2434 | C57: Créances sur cessions d'immobilisations financières (+1 an) | E57: 0 | P57: =U57-SUM(Q57:S57)-SUM(E57:O57) -> 0 | U57: =+'Passage Actif BC '!BH75 -> 0 | W57: 0 | X57: =W57-U57 -> 0 | AD57: 0 | AE57: =U57-AD57 -> 0
B58: ANC29434 | C58: Provisions pour dépréciation des créances sur cession d'immobilisations financières (+1 an) | E58: 0 | P58: =U58-SUM(Q58:S58)-SUM(E58:O58) -> 0 | U58: =+'Passage Actif BC '!BH76 -> 0 | W58: 0 | X58: =W58-U58 -> 0 | AD58: 0 | AE58: =U58-AD58 -> 0
B59: ANC2435 | C59: Frais et commissions sur facilités de crédit | E59: 0 | P59: =U59-SUM(Q59:S59)-SUM(E59:O59) -> 0 | U59: =+'Passage Actif BC '!BH77 -> 0 | W59: 0 | X59: =W59-U59 -> 0 | AD59: 0 | AE59: =U59-AD59 -> 0
B60: ANC29435 | C60: Provisions pour dépréciation des frais et commissions sur facilités de crédit | E60: 0 | P60: =U60-SUM(Q60:S60)-SUM(E60:O60) -> 0 | U60: =+'Passage Actif BC '!BH78 -> 0 | W60: 0 | X60: =W60-U60 -> 0 | AD60: 0 | AE60: =U60-AD60 -> 0
B61: ANC2438 | C61: Créances financières diverses | E61: 179.9 | K61: =+SUMIFS('BG '!$H$29:$H$71,'BG '!$C$29:$C$71,'Bilan-par flux'!B61)/1000000 -> 19 | M61: ='BG '!I71/10^6 -> 0 | P61: =U61-SUM(Q61:S61)-SUM(E61:O61) -> -0.001233 | U61: =+'Passage Actif BC '!BH79 -> 198.89877 | W61: 179.89877 | X61: =W61-U61 -> -19 | AD61: 198.89877 | AE61: =U61-AD61 -> 0
B62: ANC29438 | C62: Provisions pour dépréciation des créances financières diverses | E62: 0 | P62: =U62-SUM(Q62:S62)-SUM(E62:O62) -> 0 | U62: =+'Passage Actif BC '!BH80 -> 0 | W62: 0 | X62: =W62-U62 -> 0 | AD62: 0 | AE62: =U62-AD62 -> 0
B63: ANC2511 | C63: Titres de participation consolidés | E63: 0 | K63: =+SUMIFS('BG '!$H$29:$H$71,'BG '!$C$29:$C$71,'Bilan-par flux'!B63)/1000000 -> 0 | P63: =U63-SUM(Q63:S63)-SUM(E63:O63) -> 0 | U63: =+'Passage Actif BC '!BH81 -> 0 | W63: 0 | X63: =W63-U63 -> 0 | AD63: 0 | AE63: =U63-AD63 -> 0
B64: ANC29511 | C64: Provisions pour dépréciation des titres consolidés | E64: 0 | P64: =U64-SUM(Q64:S64)-SUM(E64:O64) -> 0 | U64: =+'Passage Actif BC '!BH82 -> 0 | W64: 0 | X64: =W64-U64 -> 0 | AD64: 0 | AE64: =U64-AD64 -> 0
B65: ANC2512 | C65: Titres de participation non consolidés | E65: 0 | K65: =+SUMIFS('BG '!$H$29:$H$71,'BG '!$C$29:$C$71,'Bilan-par flux'!B65)/1000000 -> 0 | P65: =U65-SUM(Q65:S65)-SUM(E65:O65) -> 0 | U65: =+'Passage Actif BC '!BH83 -> 0 | W65: 0 | X65: =W65-U65 -> 0 | AD65: 0 | AE65: =U65-AD65 -> 0
B66: ANC29512 | C66: Provisions pour dépréciation des titres non consolidés | E66: 0 | P66: =U66-SUM(Q66:S66)-SUM(E66:O66) -> 0 | U66: =+'Passage Actif BC '!BH84 -> 0 | W66: 0 | X66: =W66-U66 -> 0 | AD66: 0 | AE66: =U66-AD66 -> 0
B67: ANC2520 | C67: Titres mis en équivalence | E67: 0 | P67: =U67-SUM(Q67:S67)-SUM(E67:O67) -> 0 | U67: =+'Passage Actif BC '!BH85 -> 0 | W67: 0 | X67: =W67-U67 -> 0 | AD67: 0 | AE67: =U67-AD67 -> 0
B68: ANC2952 | C68: Provisions pour dépréciation des titres mis en équivalence | E68: 0 | P68: =U68-SUM(Q68:S68)-SUM(E68:O68) -> 0 | U68: =+'Passage Actif BC '!BH86 -> 0 | W68: 0 | X68: =W68-U68 -> 0 | AD68: 0 | AE68: =U68-AD68 -> 0
B69: ANC2621 | C69: Instruments dérivés - actifs non courants (variation en situation nette) | E69: 0 | P69: =U69-SUM(Q69:S69)-SUM(E69:O69) -> 0 | U69: =+'Passage Actif BC '!BH87 -> 0 | W69: 0 | X69: =W69-U69 -> 0 | AD69: 0 | AE69: =U69-AD69 -> 0
B70: ANC2622 | C70: Instruments dérivés - actifs non courants (variation en résultat) | E70: 0 | P70: =U70-SUM(Q70:S70)-SUM(E70:O70) -> 0 | U70: =+'Passage Actif BC '!BH88 -> 0 | W70: 0 | X70: =W70-U70 -> 0 | AD70: 0 | AE70: =U70-AD70 -> 0
B71: TANC2300 | C71: Actifs financiers non courants | E71: =+SUM(E49:E70) -> 22280.2 | K71: =+SUM(K49:K70) -> 2318.2074 | L71: =+SUM(L49:L70) -> 0 | M71: =+SUM(M49:M70) -> 0 | N71: =+SUM(N49:N70) -> 0 | O71: =+SUM(O49:O70) -> 0 | P71: =+SUM(P49:P70) -> -0.001233 | Q71: =+SUM(Q49:Q70) -> 0 | R71: =+SUM(R49:R70) -> 0 | S71: =+SUM(S49:S70) -> 0 | U71: =+SUM(U49:U70) -> 24598.406 | W71: 22941.136 | X71: =W71-U71 -> -1657.2701 | AD71: 24598.406 | AE71: =U71-AD71 -> 0
X72: =W72-U72 -> 0 | AE72: =U72-AD72 -> 0
B73: ANC2700 | C73: Impôts différés actifs | E73: 2281.9 | M73: -20.258658 | P73: =U73-SUM(Q73:S73)-SUM(E73:O73) -> -1.6616647 | U73: =+'Passage Actif BC '!BH91 -> 2259.9797 | W73: 2287.0742 | X73: =W73-U73 -> 27.094566 | AD73: 2261.6413 | AE73: =U73-AD73 -> -1.6616647
B74: ANC2970 | C74: Provisions pour dépréciation des impôts différés actifs | E74: 885.2 | P74: =U74-SUM(Q74:S74)-SUM(E74:O74) -> 0 | U74: =+'Passage Actif BC '!BH92 -> 885.2 | W74: 885.2 | X74: =W74-U74 -> 0 | AD74: 885.2 | AE74: =U74-AD74 -> 0
B75: TANC2400 | C75: Impôts différés actifs | E75: =SUM(E73:E74) -> 3167.1 | K75: =+K73+K74 -> 0 | L75: =+L73+L74 -> 0 | M75: =+M73+M74 -> -20.258658 | N75: =+N73+N74 -> 0 | O75: =+O73+O74 -> 0 | P75: =+P73+P74 -> -1.6616647 | Q75: =+Q73+Q74 -> 0 | R75: =+R73+R74 -> 0 | S75: =+S73+S74 -> 0 | U75: =SUM(E75:T75) -> 3145.1797 | W75: 3172.2742 | X75: =W75-U75 -> 27.094566 | AD75: 3146.8413 | AE75: =U75-AD75 -> -1.6616647
X76: =W76-U76 -> 0 | AE76: =U76-AD76 -> 0
B77: TANC200 | C77: Actifs non courants | E77: =+E75+E71+E47+E29+E9 -> 152349.4 | K77: =+K75+K71+K47+K29+K9 -> 29941.873 | L77: =+L75+L71+L47+L29+L9 -> -18260.801 | M77: =+M75+M71+M47+M29+M9 -> -20.258658 | N77: =+N75+N71+N47+N29+N9 -> 0 | O77: =+O75+O71+O47+O29+O9 -> 0 | P77: =+P75+P71+P47+P29+P9 -> 432.9376 | Q77: =+Q75+Q71+Q47+Q29+Q9 -> 0 | R77: =+R75+R71+R47+R29+R9 -> 0 | S77: =+S75+S71+S47+S29+S9 -> 0 | U77: =+U75+U71+U47+U29+U9 -> 164443.15 | W77: 150094.72 | X77: =W77-U77 -> -14348.432 | AD77: 163069.86 | AE77: =U77-AD77 -> 1373.2922
X78: =W78-U78 -> 0 | AE78: =U78-AD78 -> 0
X79: =W79-U79 -> 0 | AE79: =U79-AD79 -> 0
B80: AC3110 | C80: Stocks | E80: 2970.9 | O80: =U80-SUM(P80:S80)-SUM(E80:N80) -> -450.32188 | U80: =+'Passage Actif BC '!BH103 -> 2520.5781 | W80: 2669.3928 | X80: =W80-U80 -> 148.81464 | AD80: 2520.5781 | AE80: =U80-AD80 -> 0
B81: AC3910 | C81: Provisions pour dépréciation des stocks | E81: -493.5 | L81: =-'BG '!J570/1000000 -> 0 | N81: =-'BG '!K672/1000000 -> 0 | O81: =U81-SUM(P81:S81)-SUM(E81:N81) -> 30.479298 | U81: =+'Passage Actif BC '!BH104 -> -463.0207 | W81: -559.34972 | X81: =W81-U81 -> -96.329021 | AD81: -463.0207 | AE81: =U81-AD81 -> 0
B82: TAC3000 | C82: Stocks | E82: =SUM(E80:E81) -> 2477.4 | K82: =SUM(K80:K81) -> 0 | L82: =SUM(L80:L81) -> 0 | M82: =SUM(M80:M81) -> 0 | N82: =SUM(N80:N81) -> 0 | O82: =SUM(O80:O81) -> -419.84258 | P82: =SUM(P80:P81) -> 0 | Q82: =SUM(Q80:Q81) -> 0 | R82: =SUM(R80:R81) -> 0 | S82: =SUM(S80:S81) -> 0 | U82: =SUM(E82:T82) -> 2057.5574 | W82: 2110.043 | X82: =W82-U82 -> 52.485617 | AD82: 2057.5574 | AE82: =U82-AD82 -> 0
X83: =W83-U83 -> 0 | AE83: =U83-AD83 -> 0
B84: AC3453 | C84: Acomptes sur impôts sur le résultat | E84: 0 | O84: =U84-SUM(P84:S84)-SUM(E84:N84) -> 0 | U84: =+'Passage Actif BC '!BH107 -> 0 | W84: 0 | X84: =W84-U84 -> 0 | AD84: 0 | AE84: =U84-AD84 -> 0
