Workbook

Sheet RECAP 
A2: RUBRIQUES | B2: REVENU INTERCO | C2: CHARGES INTERCO
A3: INTERCO NATIONAL VOIX HT | B3: ='[1]NAT+INT DETAIL '!D14 -> 0 | C3: ='[1]NAT+INT DETAIL '!G14 -> 0
A4: INTERCO NATIONAL SMS HT | B4: ='[1]NAT+INT DETAIL '!D16 -> 0 | C4: ='[1]NAT+INT DETAIL '!G16 -> 0
A5: RN NATIONAL SBIN | B5: =+'TRAFIC&REVENU DETAILS'!G27 -> 3.4869206e+08 | C5: =+'TRAFIC&REVENU DETAILS'!D27 -> 3998053.1
A6: RN NATIONAL MTN | B6: =+'TRAFIC&REVENU DETAILS'!G32 -> 0 | C6: =+'TRAFIC&REVENU DETAILS'!D32 -> 618597.8
A7: TOTAL (1) HT | B7: =+B3+B4+B5+B6 -> 3.4869206e+08 | C7: =+C3+C4+C5+C6 -> 4616650.9
A8: INTERNATIONAL VOIX HT | B8: =+'TRAFIC&REVENU DETAILS'!D70 -> 1.1237062e+08 | C8: =+'TRAFIC&REVENU DETAILS'!G70 -> 1.5512832e+08
A9: INTERNATIONAL SMS HT | B9: =+'TRAFIC&REVENU DETAILS'!D80 -> 1.1068393e+08 | C9: =+'TRAFIC&REVENU DETAILS'!G80 -> 2451652.4
A10: TOTAL (2) HT | B10: =+B8+B9 -> 2.2305455e+08 | C10: =+C8+C9 -> 1.5757997e+08
A11: ROAMING (3) HT | B11: =+'TRAFIC&REVENU DETAILS'!D89 -> 64485749 | C11: =+'TRAFIC&REVENU DETAILS'!G89 -> 14744419
A12: Provisions DIOT (Avril.25) (6) | B12: =+'Current Month-Summary'!I37*655.957 -> -1913326.1 | D12: Provisions DIOT (Mar.25)(5) | E12: ='Current Month-Summary (2)'!I35*655.957 -> -1227602.6
A13: TOTAL 4 (1+2+3) HT | B13: =B7+B10+B11 -> 6.3623236e+08 | C13: =C7+C10+C11 -> 1.7694104e+08
A14: GRAND TOTAL (4+5+6) HT | B14: =E12+B13+B12 -> 6.3309143e+08 | C14: =C7+C10+C11 -> 1.7694104e+08
B24: =B10/1000000 -> 223.05455
B25: ='TRAFIC&REVENU DETAILS'!C70/1000000 -> 1.0351576
B26: =B24/B25 -> 215.47883

Sheet TRAFIC&REVENU DETAILS
B1: ENREGISTREMENT | F1: Référence: ENG.OPT.04
F2: Indice de révision: 00
F3: Créé le: 13/07/2012
F4: Dernière modif le:
A5: POINT DES CREANCES ET DETTES DES CARRIERS SUR LE TRAFIC | F5: Pagination: page 1 sur 1
A7: 45778
A8: NATIONAL
B9: INCOMING | E9: OUTGOING
B10: TRAFIC VOIX NATIONAL | E10: TRAFIC VOIX NATIONAL
B11: TA | C11: TRAFIC | D11: REVENU | E11: TA | F11: TRAFIC | G11: CHARGES | H11: BALANCE
A12: MTN (en minutes ) | B12: 0 | C12: =ICT!D26 -> 29853237 | D12: 0 | E12: 0 | F12: =+ICT!D126 -> 34730006 | G12: 0 | H12: =+D12-G12 -> 0
A13: SBIN MOBILE (en minutes ) | B13: 0 | C13: =ICT!D27 -> 1.0080555e+08 | D13: 0 | E13: 0 | F13: =+ICT!D127 -> 25869595 | G13: 0 | H13: =+D13-G13 -> 0
A14: SBIN FIXE (en minutes ) | B14: 0 | C14: =ICT!D8 -> 27746.433 | D14: 0 | E14: 0 | F14: =+ICT!D110 -> 46704.1 | G14: 0 | H14: =+D14-G14 -> 0
A15: SOUS TOTAL | C15: =SUM(C12:C14) -> 1.3068653e+08 | D15: =SUM(D12:D14) -> 0 | F15: =SUM(F12:F14) -> 60646305 | G15: =SUM(G12:G14) -> 0 | H15: =SUM(H12:H14) -> 0
B16: TRAFIC SMS NATIONAL | E16: TRAFIC SMS NATIONAL
B17: TA | C17: TRAFIC | D17: REVENU | E17: TA | F17: TRAFIC | G17: CHARGES
A18: MTN SMS (Unités) | B18: 0 | C18: =ICT!C48 -> 2724684 | D18: =+B18*C18 -> 0 | E18: =B18 -> 0 | F18: =+ICT!C150 -> 2676573 | G18: =+E18*F18 -> 0 | H18: =D18-G18 -> 0
A19: SBIN SMS (Unités) | B19: 0 | C19: =ICT!C49 -> 3476412 | D19: =+B19*C19 -> 0 | F19: =+ICT!C151 -> 2890730 | G19: =+E19*F19 -> 0
A20: SOUS TOTAL | C20: =+C18+C19 -> 6201096 | D20: =D18 -> 0 | F20: =+F18 -> 2676573 | G20: =G18 -> 0 | H20: =H18 -> 0
B21: TRAFIC ROAMING NATIONAL VOIX | E21: TRAFIC ROAMING NATIONAL
A22: SBIN
B23: TA | C23: TRAFIC | D23: CHARGES | E23: TA | F23: TRAFIC | G23: REVENU
A24: SBIN VOIX (en minutes ) | B24: =6/1.18 -> 5.0847458 | C24: =REVENU!C68 -> 475353.78 | D24: =+B24*C24 -> 2417053.1 | E24: =6/1.18 -> 5.0847458 | F24: =+REVENU!C34 -> 45038969 | G24: =+E24*F24 -> 2.2901171e+08 | H24: =G24-D24 -> 2.2659465e+08
A25: SBIN SMS (Unités) | B25: =0.6/1.18 -> 0.50847458 | C25: =REVENU!D68 -> 9300 | D25: =+B25*C25 -> 4728.8136 | E25: =0.6/1.18 -> 0.50847458 | F25: =+REVENU!D34 -> 374553 | G25: =+E25*F25 -> 190450.68 | H25: =G25-D25 -> 185721.86
A26: SBIN DATA (en Go) | B26: =400/1.18 -> 338.98305 | C26: =REVENU!E68 -> 4650 | D26: =+B26*C26 -> 1576271.2 | E26: =400/1.18 -> 338.98305 | F26: =+REVENU!E34 -> 352495.21 | G26: =+E26*F26 -> 1.194899e+08 | H26: =G26-D26 -> 1.1791363e+08
D27: =SUM(D24:D26) -> 3998053.1 | G27: =SUM(G24:G26) -> 3.4869206e+08 | H27: =G27-D27 -> 3.4469401e+08
A28: MTN
A29: MTN VOIX (en minutes ) | B29: =6/1.18 -> 5.0847458 | C29: =+ICT!D33 -> 53968.4 | D29: =+B29*C29 -> 274415.59 | E29: =8.5/1.18 -> 7.2033898 | G29: =+E29*F29 -> 0
A30: MTN SMS (Unités) | B30: =0.6/1.18 -> 0.50847458 | C30: =+ICT!C36 -> 10225 | D30: =+B30*C30 -> 5199.1525 | E30: =1/1.18 -> 0.84745763 | G30: =+E30*F30 -> 0
A31: MTN DATA (en Go) | B31: =400/1.18 -> 338.98305 | C31: 1000 | D31: =+B31*C31 -> 338983.05 | E31: =500/1.18 -> 423.72881 | G31: =+E31*F31 -> 0
D32: =+D29+D30+D31 -> 618597.8 | G32: =SUM(G29:G31) -> 0
A38: INTERNATIONAL VOIX
B39: INCOMING | E39: OUTGOING | K39: TRAFIC FREE ROAMING
B40: TA | C40: TRAFIC | D40: REVENU | E40: TA | F40: TRAFIC | G40: CHARGES | H40: BALANCE | K40: ENTRANT | L40: SORTANT
A41: ORANGE BF (en minutes ) | B41: 180 | C41: 0 | D41: =C41*B41 -> 0 | E41: =0.2995*655.957 -> 196.45912 | H41: =+D41-G41 -> 0 | N41: =B41*C41 -> 0 | O41: =N41/1000000 -> 0 | AF41: =C42+C44+C50 -> 353834.03
A42: BELGA VOIX(en minutes ) | B42: =0.3*655.957 -> 196.7871 | C42: =+ICT!D10-C68 -> 55460.75 | D42: =(C42*B42)+(B65*C65)+(1600*655.957) -> 11963491 | F42: =+ICT!D114+ICT!D91 -> 226828.8 | G42: =(ICT!B156+ICT!B114+ICT!B91)*655.957 -> 28500835 | H42: =+D42-G42 -> -16537343 | N42: =B42*C42 -> 10913960 | O42: =N42/1000000 -> 10.91396 | AF42: =AF41/C70 -> 0.34181658
A43: BTI(en minutes ) | B43: =0.3*655.957 -> 196.7871 | C43: =0 -> 0 | D43: =(C43*B43)+(B66*C66) -> 0 | H43: =+D43-G43 -> 0 | N43: =B43*C43 -> 0 | O43: =N43/1000000 -> 0 | T43: =C43/'[2]NAT+INT'!$C$25-1 -> -1
A44: ORANGE (en minutes ) | B44: =0.3*655.957 -> 196.7871 | C44: =+ICT!D12 -> 29838.8 | D44: =C44*B44 -> 5871890.9 | H44: =+D44-G44 -> 5871890.9 | N44: =B44*C44 -> 5871890.9 | O44: =N44/1000000 -> 5.8718909
A45: PCCW(en minutes ) | B45: =0.3*655.957 -> 196.7871 | C45: 0 | D45: =C45*B45 -> 0 | H45: =+D45-G45 -> 0 | N45: =B45*C45 -> 0 | O45: =N45/1000000 -> 0
A46: ORANGE CI | B46: 125 | C46: 0 | D46: =C46*B46 -> 0 | E46: 125 | H46: =+D46-G46 -> 0
A47: TOGO TELECOM (en minutes ) | B47: 45.76 | C47: =+ICT!D19-K47 -> 185860.17 | D47: =(C47*B47)+(J47*K47) -> 8813798.2 | E47: 45.76 | G47: 0 | H47: =+D47-G47 -> 8813798.2 | J47: 11 | K47: =+MTC!Y33 -> 28076.083 | L47: =+MTC!Y34 -> 28564.4 | N47: =B47*C47 -> 8504961.2 | O47: =N47/1000000 -> 8.5049612
A48: ZAMANI TELECOMS | B48: 130 | C48: =ICT!D20 -> 4864.2 | D48: =C48*B48 -> 632346 | E48: 130 | F48: =+ICT!D98+ICT!D123 -> 14482.167 | G48: =E48*F48 -> 1882681.7 | H48: =+D48-G48 -> -1250335.7 | N48: =B48*C48 -> 632346 | O48: =N48/1000000 -> 0.632346
A49: FREE SENEGAL | B49: 50 | C49: =ICT!D11 -> 1168.7833 | D49: 326800 | E49: 50 | F49: =+ICT!D115+ICT!G94 -> 1361.0833 | G49: 326800 | H49: =+D49-G49 -> 0 | J49: 15 | K49: =+MTC!Y30 -> 33.683 | L49: =+MTC!Y31 -> 1065.433 | N49: =B49*C49 -> 58439.167 | O49: =N49/1000000 -> 0.058439167
A50: MT (en minutes ) | B50: =0.3*655.957 -> 196.7871 | C50: =ICT!D14+ICT!D57 -> 268534.48 | D50: =(C50*B50)+(B56*C56)+(B57*C57)+(B58*C58)+(B59*C59)+(B60*C60)+(B61*C61)+(B62*C62)+(B63*C63)+(B64*C64) -> 57143393 | F50: =+ICT!D92+ICT!D117+ICT!D92 -> 838114.42 | G50: =+(ICT!B117+ICT!B92+ICT!B158)*655.957 -> 99134928 | H50: =+D50-G50 -> -41991535 | N50: =B50*C50 -> 52844122 | O50: =D50/1000000 -> 57.143393
A51: MOOV TGO (en minutes ) | B51: 45.76 | C51: =ICT!D17-K51 -> 236134.42 | D51: =(B51*C51)+(K51*J51) -> 15751871 | E51: 45.76 | F51: =+ICT!D95+ICT!D120-L51 -> 247248.6 | G51: =(E51*F51)+(L51*J51) -> 15556249 | H51: =+D51-G51 -> 195622.32 | J51: 10 | K51: =+MTC!Y36 -> 494636 | L51: =+MTC!Y37 -> 424215.27 | N51: =B51*C51 -> 10805511 | O51: =N51/1000000 -> 10.805511 | T51: =C51/'[2]NAT+INT'!$C$29-1 -> -0.62806448
A52: MOOV NIGER (en minutes ) | B52: 75 | C52: 0 | D52: =C52*B52 -> 0 | E52: 150 | H52: =+D52-G52 -> 0 | N52: =B52*C52 -> 0 | O52: =N52/1000000 -> 0
A53: MOOV CI (en minutes ) | B53: 50.85 | C53: =+ICT!D16 -> 85807.05 | D53: =(C53*B53)+(J53*K53) -> 4393552.2 | E53: 50.85 | F53: =+ICT!D119+ICT!D102 -> 57744.617 | G53: =(E53*F53)+(L53*J53) -> 3344086.8 | H53: =+D53-G53 -> 1049465.5 | J53: 15 | K53: =+MTC!Y24 -> 2017.583 | L53: =+MTC!Y25 -> 27184.867 | N53: =B53*C53 -> 4363288.5 | O53: =N53/1000000 -> 4.3632885
A54: ONATEL(en minutes ) | B54: 88.95 | C54: =+ICT!D18 -> 63043.05 | D54: =6000000+(K54*J54) -> 6006549.8 | F54: =+ICT!D121+ICT!D96 -> 27364.45 | G54: =5250000+(L54*J54) -> 5374193.5 | H54: =+D54-G54 -> 632356.25 | J54: 15 | K54: =+MTC!Y21 -> 436.65 | L54: =+MTC!Y22 -> 8279.567 | N54: =B54*C54 -> 5607679.3 | O54: =N54/1000000 -> 5.6076793 | U54: =C54-K54 -> 62606.4 | V54: 70000 | W54: =U54-V54 -> -7393.6 | Y54: =F54-L54 -> 19084.883
A55: MOOV GABON T | B55: 126 | C55: =+ICT!D13 -> 11950.95 | D55: =C55*B55 -> 1505819.7 | E55: 159 | F55: =+ICT!D116 -> 2067.55 | G55: =E55*F55 -> 328740.45 | H55: =+D55-G55 -> 1177079.3 | N55: =B55*C55 -> 1505819.7 | O55: =N55/1000000 -> 1.5058197
A56: TRANSIT MV CI (en minutes ) | B56: 50.85 | C56: =+ICT!D58 -> 59809.85 | F56: =+ICT!K156 -> 0 | H56: =+D56-G56 -> 0 | N56: =B56*C56 -> 3041330.9 | P56: =(C56+#REF!)*B56/1000000 -> #REF! | Q56: =#REF!*B56/1000000 -> #REF! | R56: =P56-Q56 -> #REF!
A57: TRANSIT GT (en minutes ) | B57: 128.96114 | C57: =+ICT!D53 -> 3.6666667 | F57: 0 | H57: =+D57-G57 -> 0 | N57: =B57*C57 -> 472.85753 | V57: =+D54/C54 -> 95.276954
A58: TRANSIT SOTELMA (en minutes ) | B58: 76.287802 | C58: =+ICT!D62 -> 7086.45 | F58: =+ICT!D161 -> 17642.65 | H58: 0 | N58: =B58*C58 -> 540609.7
A59: TRANSIT MV NIGER (en minutes ) | B59: 75 | C59: 0 | F59: =+ICT!D160 -> 85431.783 | H59: 0 | N59: =B59*C59 -> 0 | AC59: =F59*176 -> 15035994 | AD59: =F59*100 -> 8543178.3
A60: TRANSIT MOOV CAF (en minutes ) | B60: 73.99195 | C60: =+ICT!D56 -> 145.28333 | F60: =+ICT!D159 -> 32.7 | H60: =+D60-G60 -> 0 | O60: =N60/1000000 -> 0
A61: TRANSIT MAURITEL (en minutes ) | B61: 144.31054 | C61: =+ICT!D55 -> 129.05 | F61: =+ICT!F157 -> 0 | H61: =+D61-G61 -> 0
A62: TRANSIT ONATEL (en minutes ) | B62: 88.947769 | C62: =+ICT!D61 -> 29.883333 | F62: =+ICT!F160 -> 0 | H62: =+D62-G62 -> 0
A63: TRANSIT MOOV TGO (en minutes ) | B63: 45.76 | C63: =+ICT!D59 -> 14449.85 | F63: =+ICT!G158 -> 0 | H63: =+D63-G63 -> 0
A64: TRANSIT TIGO TCHAD (en minutes ) | B64: 76.287805 | C64: =+ICT!D63 -> 309.36667 | F64: =+ICT!D162 -> 195.8 | H64: =+D64-G64 -> 0
A65: TRANSIT TOGO TELECOM (en minutes ) | B65: 50 | F65: =+ICT!D163 -> 101910.35 | H65: =+D65-G65 -> 0
A66: TRANSIT ORANGE SENEGAL (en minutes ) | B66: 95 | H66: =+D66-G66 -> 0
A67: TRANSIT ORANGE CI (en minutes) | B67: 122.38 | H67: =+D67-G67 -> 0
A68: TRANSIT LIBON (en minutes | B68: =0.08*655.957 -> 52.47656 | C68: 9900 | H68: =+D68-G68 -> 0
A69: AVOIR MA MALITEL | B69: -61.58 | C69: =+K69 -> 631.55 | D69: =+B69*C69 -> -38890.849 | E69: 61.58 | F69: =L69 -> 11039.333 | G69: =+E69*F69 -> 679802.13 | H69: =+D69-G69 -> -718692.98 | K69: =+MTC!Y27 -> 631.55 | L69: =+MTC!Y28 -> 11039.333
A70: TOTAL | C70: =SUM(C41:C69) -> 1035157.6 | D70: =SUM(D41:D69) -> 1.1237062e+08 | F70: =SUM(F41:F68) -> 1620425 | G70: =SUM(G41:G69) -> 1.5512832e+08 | H70: =SUM(H41:H66) -> -42039001 | K70: =SUM(K41:K68) -> 525200 | L70: =SUM(L41:L68) -> 489309.53 | O70: =SUM(O41:O60) -> 105.40729
C71: =+D70/C70 -> 108.55412 | F71: =+G70/F70 -> 95.733106
A73: INTERNATIONAL SMS
B74: INCOMING | E74: OUTGOING
B75: TA | C75: TRAFIC | D75: REVENU | E75: TA | F75: TRAFIC | G75: CHARGES | H75: BALANCE
A76: BELGA A2P (Unités) | B76: =0.08*655.957 -> 52.47656 | C76: =+'SMS A2P'!B33 -> 446367 | D76: =+'SMS A2P'!D33 -> 26322872 | G76: 0 | H76: =+D76-G76 -> 26322872
A77: BELGA SMSI (Unités) | B77: =0.08*655.957 -> 52.47656 | C77: =ICT!C41 -> 329 | D77: =+B77*C77 -> 17264.788 | E77: =0.06*655.957 -> 39.35742 | F77: =+ICT!C146 -> 26829 | G77: =+E77*F77 -> 1055920.2 | H77: =+D77-G77 -> -1038655.4
A78: SAP (Unités) | B78: =0.08*655.957 -> 52.47656 | C78: ='SMS A2P'!F33 -> 83778 | D78: =84343790.68496-D79 -> 73018791 | E78: =0.06*655.957 -> 39.35742 | F78: =+ICT!C147 -> 35463 | G78: =+E78*F78 -> 1395732.2 | H78: =+D78-G78 -> 71623058
A79: SBIN A2P | B79: 1.51 | C79: 7500000 | D79: =+B79*C79 -> 11325000
A80: TOTAL | C80: =C76+C77+C78 -> 530474 | D80: =SUM(D76:D79) -> 1.1068393e+08 | F80: =SUM(F77:F78) -> 62292 | G80: =SUM(G76:G78) -> 2451652.4 | H80: =SUM(H76:H78) -> 96907275
D81: =+D80/1000000 -> 110.68393
E82: =C80+F80 -> 592766
B83: ROAMING VISITEUR REVENU | E83: ROAMING VOYAGEUR CHARGES
B84: USAGE | C84: TRAFIC | D84: REVENU | E84: USAGE | F84: TRAFIC | G84: CHARGES | AF84: =170000 -> 170000 | AG84: 30 | AH84: =AF84*AG84 -> 5100000
A85: Roaming | B85: VOIX MO | C85: ='ROAMING IN '!BA202 -> 88479.432 | D85: ='ROAMING IN '!BL202 -> 14436531 | E85: VOIX MO | F85: =+'ROAMING OUT'!AM146 -> 66860.301 | G85: =+'ROAMING OUT'!AX146 -> 6167112
B86: VOIX MT | C86: ='ROAMING IN '!CC202 -> 612151.61 | D86: ='ROAMING IN '!CN202 -> 746.157 | E86: VOIX MT | F86: =+'ROAMING OUT'!BO146 -> 671839.79 | G86: =+'ROAMING OUT'!BZ146 -> 12018.176
B87: SMS | C87: ='ROAMING IN '!AL202 -> 28013 | D87: ='ROAMING IN '!AX202 -> 559908.52 | E87: SMS | F87: =+'ROAMING OUT'!X146 -> 2360 | G87: =+'ROAMING OUT'!AJ146 -> 189961.49
B88: DATA | C88: =('ROAMING IN '!O202+'ROAMING IN '!AC202)/1024 -> 4177043.4 | D88: =+'ROAMING IN '!V202+'ROAMING IN '!AJ202 -> 49488564 | E88: DATA | F88: =+'ROAMING OUT'!O146/1024 -> 643850.68 | G88: =+'ROAMING OUT'!V146 -> 8375327.5
B89: TOTAL | D89: =+D85+D86+D87+D88 -> 64485749 | E89: TOTAL | G89: =+G85+G86+G87+G88 -> 14744419
E91: =+C88+F88 -> 4820894
D92: =+D70+D80+D89+G27 -> 6.3623236e+08 | G92: =+G70+G80+G89 -> 1.7232439e+08
D96: =D70+D80 -> 2.2305455e+08

Sheet RECAP
B1: ENREGISTREMENT | F1: Référence: ENG.OPT.04
F2: Indice de révision: 00
F3: Créé le: 13/07/2012
F4: Dernière modif le:
A5: POINT DES CREANCES ET DETTES DES CARRIERS SUR LE TRAFIC | F5: Pagination: page 1 sur 1
A7: 45778
A8: NATIONAL
B9: INCOMING | E9: OUTGOING
B10: TRAFIC VOIX NATIONAL | E10: TRAFIC VOIX NATIONAL
B11: TA | C11: TRAFIC | D11: REVENU | E11: TA | F11: TRAFIC | G11: CHARGES | H11: BALANCE
A12: MTN (en minutes ) | B12: 0 | C12: =ICT!D26 -> 29853237 | D12: 0 | E12: 0 | F12: =+ICT!D126 -> 34730006 | G12: 0 | H12: =+D12-G12 -> 0
A13: SBIN MOBILE (en minutes ) | B13: 0 | C13: =ICT!D27 -> 1.0080555e+08 | D13: 0 | E13: 0 | F13: =+ICT!D127 -> 25869595 | G13: 0 | H13: =+D13-G13 -> 0
A14: SBIN FIXE (en minutes ) | B14: 0 | C14: =ICT!D8 -> 27746.433 | D14: 0 | E14: 0 | F14: =+ICT!D110 -> 46704.1 | G14: 0 | H14: =+D14-G14 -> 0
A15: SOUS TOTAL | C15: =SUM(C12:C14) -> 1.3068653e+08 | D15: =SUM(D12:D14) -> 0 | F15: =SUM(F12:F14) -> 60646305 | G15: =SUM(G12:G14) -> 0 | H15: =SUM(H12:H14) -> 0
B16: TRAFIC SMS NATIONAL | E16: TRAFIC SMS NATIONAL
B17: TA | C17: TRAFIC | D17: REVENU | E17: TA | F17: TRAFIC | G17: CHARGES
A18: MTN SMS (Unités) | B18: 0 | C18: =ICT!C48 -> 2724684 | D18: =+B18*C18 -> 0 | E18: =B18 -> 0 | F18: =+ICT!C150 -> 2676573 | G18: =+E18*F18 -> 0 | H18: =D18-G18 -> 0
A19: SBIN SMS (Unités) | B19: 0 | C19: =ICT!C49 -> 3476412 | D19: =+B19*C19 -> 0 | F19: =+ICT!C151 -> 2890730 | G19: =+E19*F19 -> 0
A20: SOUS TOTAL | C20: =+C18+C19 -> 6201096 | D20: =D18 -> 0 | F20: =+F18 -> 2676573 | G20: =G18 -> 0 | H20: =H18 -> 0
B21: TRAFIC ROAMING NATIONAL VOIX | E21: TRAFIC ROAMING NATIONAL
A22: SBIN
B23: TA | C23: TRAFIC | D23: CHARGES | E23: TA | F23: TRAFIC | G23: REVENU
A24: SBIN VOIX (en minutes ) | B24: =6/1.18 -> 5.0847458 | C24: =REVENU!C68 -> 475353.78 | D24: =+B24*C24 -> 2417053.1 | E24: =6/1.18 -> 5.0847458 | F24: =+REVENU!C34 -> 45038969 | G24: =+E24*F24 -> 2.2901171e+08 | H24: =G24-D24 -> 2.2659465e+08
A25: SBIN SMS (Unités) | B25: =0.6/1.18 -> 0.50847458 | C25: =REVENU!D68 -> 9300 | D25: =+B25*C25 -> 4728.8136 | E25: =0.6/1.18 -> 0.50847458 | F25: =+REVENU!D34 -> 374553 | G25: =+E25*F25 -> 190450.68 | H25: =G25-D25 -> 185721.86
A26: SBIN DATA (en Go) | B26: =400/1.18 -> 338.98305 | C26: =REVENU!E68 -> 4650 | D26: =+B26*C26 -> 1576271.2 | E26: =400/1.18 -> 338.98305 | F26: =+REVENU!E34 -> 352495.21 | G26: =+E26*F26 -> 1.194899e+08 | H26: =G26-D26 -> 1.1791363e+08
D27: =SUM(D24:D26) -> 3998053.1 | G27: =SUM(G24:G26) -> 3.4869206e+08 | H27: =G27-D27 -> 3.4469401e+08
A28: MTN
A29: MTN VOIX (en minutes ) | B29: =6/1.18 -> 5.0847458 | C29: =+ICT!D33 -> 53968.4 | D29: =+B29*C29 -> 274415.59 | E29: =8.5/1.18 -> 7.2033898 | G29: =+E29*F29 -> 0
A30: MTN SMS (Unités) | B30: =0.6/1.18 -> 0.50847458 | C30: =+ICT!C36 -> 10225 | D30: =+B30*C30 -> 5199.1525 | E30: =1/1.18 -> 0.84745763 | G30: =+E30*F30 -> 0
A31: MTN DATA (en Go) | B31: =400/1.18 -> 338.98305 | C31: 1000 | D31: =+B31*C31 -> 338983.05 | E31: =500/1.18 -> 423.72881 | G31: =+E31*F31 -> 0
D32: =+D29+D30+D31 -> 618597.8 | G32: =SUM(G29:G31) -> 0
A38: INTERNATIONAL VOIX
B39: INCOMING | E39: OUTGOING | K39: TRAFIC FREE ROAMING
B40: TA | C40: TRAFIC | D40: REVENU | E40: TA | F40: TRAFIC | G40: CHARGES | H40: BALANCE | K40: ENTRANT | L40: SORTANT
A41: ORANGE BF (en minutes ) | B41: 180 | C41: 0 | D41: =C41*B41 -> 0 | E41: =0.2995*655.957 -> 196.45912 | H41: =+D41-G41 -> 0 | N41: =B41*C41 -> 0 | O41: =N41/1000000 -> 0 | AF41: =C42+C44+C50 -> 353834.03
A42: BELGA VOIX(en minutes ) | B42: =0.3*655.957 -> 196.7871 | C42: =+ICT!D10-C68 -> 55460.75 | D42: =(C42*B42)+(B65*C65)+(1600*655.957) -> 11963491 | F42: =+ICT!D114+ICT!D91 -> 226828.8 | G42: =(ICT!B156+ICT!B114+ICT!B91)*655.957 -> 28500835 | H42: =+D42-G42 -> -16537343 | N42: =B42*C42 -> 10913960 | O42: =N42/1000000 -> 10.91396 | AF42: =AF41/C70 -> 0.34181658
A43: BTI(en minutes ) | B43: =0.3*655.957 -> 196.7871 | C43: =0 -> 0 | D43: =(C43*B43)+(B66*C66) -> 0 | H43: =+D43-G43 -> 0 | N43: =B43*C43 -> 0 | O43: =N43/1000000 -> 0 | T43: =C43/'[2]NAT+INT'!$C$25-1 -> -1
A44: ORANGE (en minutes ) | B44: =0.3*655.957 -> 196.7871 | C44: =+ICT!D12 -> 29838.8 | D44: =C44*B44 -> 5871890.9 | H44: =+D44-G44 -> 5871890.9 | N44: =B44*C44 -> 5871890.9 | O44: =N44/1000000 -> 5.8718909
A45: PCCW(en minutes ) | B45: =0.3*655.957 -> 196.7871 | C45: 0 | D45: =C45*B45 -> 0 | H45: =+D45-G45 -> 0 | N45: =B45*C45 -> 0 | O45: =N45/1000000 -> 0
A46: ORANGE CI | B46: 125 | C46: 0 | D46: =C46*B46 -> 0 | E46: 125 | H46: =+D46-G46 -> 0
A47: TOGO TELECOM (en minutes ) | B47: 45.76 | C47: =+ICT!D19-K47 -> 185860.17 | D47: =(C47*B47)+(J47*K47) -> 8813798.2 | E47: 45.76 | G47: 0 | H47: =+D47-G47 -> 8813798.2 | J47: 11 | K47: =+MTC!Y33 -> 28076.083 | L47: =+MTC!Y34 -> 28564.4 | N47: =B47*C47 -> 8504961.2 | O47: =N47/1000000 -> 8.5049612
A48: ZAMANI TELECOMS | B48: 130 | C48: =ICT!D20 -> 4864.2 | D48: =C48*B48 -> 632346 | E48: 130 | F48: =+ICT!D98+ICT!D123 -> 14482.167 | G48: =E48*F48 -> 1882681.7 | H48: =+D48-G48 -> -1250335.7 | N48: =B48*C48 -> 632346 | O48: =N48/1000000 -> 0.632346
A49: FREE SENEGAL | B49: 50 | C49: =ICT!D11 -> 1168.7833 | D49: 326800 | E49: 50 | F49: =+ICT!D115+ICT!G94 -> 1361.0833 | G49: 326800 | H49: =+D49-G49 -> 0 | J49: 15 | K49: =+MTC!Y30 -> 33.683 | L49: =+MTC!Y31 -> 1065.433 | N49: =B49*C49 -> 58439.167 | O49: =N49/1000000 -> 0.058439167
A50: MT (en minutes ) | B50: =0.3*655.957 -> 196.7871 | C50: =ICT!D14+ICT!D57 -> 268534.48 | D50: =(C50*B50)+(B56*C56)+(B57*C57)+(B58*C58)+(B59*C59)+(B60*C60)+(B61*C61)+(B62*C62)+(B63*C63)+(B64*C64) -> 57143393 | F50: =+ICT!D92+ICT!D117+ICT!D92 -> 838114.42 | G50: =+(ICT!B117+ICT!B92+ICT!B158)*655.957 -> 99134928 | H50: =+D50-G50 -> -41991535 | N50: =B50*C50 -> 52844122 | O50: =D50/1000000 -> 57.143393
A51: MOOV TGO (en minutes ) | B51: 45.76 | C51: =ICT!D17-K51 -> 236134.42 | D51: =(B51*C51)+(K51*J51) -> 15751871 | E51: 45.76 | F51: =+ICT!D95+ICT!D120-L51 -> 247248.6 | G51: =(E51*F51)+(L51*J51) -> 15556249 | H51: =+D51-G51 -> 195622.32 | J51: 10 | K51: =+MTC!Y36 -> 494636 | L51: =+MTC!Y37 -> 424215.27 | N51: =B51*C51 -> 10805511 | O51: =N51/1000000 -> 10.805511 | T51: =C51/'[2]NAT+INT'!$C$29-1 -> -0.62806448
A52: MOOV NIGER (en minutes ) | B52: 75 | C52: 0 | D52: =C52*B52 -> 0 | E52: 150 | H52: =+D52-G52 -> 0 | N52: =B52*C52 -> 0 | O52: =N52/1000000 -> 0
A53: MOOV CI (en minutes ) | B53: 50.85 | C53: =+ICT!D16 -> 85807.05 | D53: =(C53*B53)+(J53*K53) -> 4393552.2 | E53: 50.85 | F53: =+ICT!D119+ICT!D102 -> 57744.617 | G53: =(E53*F53)+(L53*J53) -> 3344086.8 | H53: =+D53-G53 -> 1049465.5 | J53: 15 | K53: =+MTC!Y24 -> 2017.583 | L53: =+MTC!Y25 -> 27184.867 | N53: =B53*C53 -> 4363288.5 | O53: =N53/1000000 -> 4.3632885
A54: ONATEL(en minutes ) | B54: 88.95 | C54: =+ICT!D18 -> 63043.05 | D54: =6000000+(K54*J54) -> 6006549.8 | F54: =+ICT!D121+ICT!D96 -> 27364.45 | G54: =5250000+(L54*J54) -> 5374193.5 | H54: =+D54-G54 -> 632356.25 | J54: 15 | K54: =+MTC!Y21 -> 436.65 | L54: =+MTC!Y22 -> 8279.567 | N54: =B54*C54 -> 5607679.3 | O54: =N54/1000000 -> 5.6076793 | U54: =C54-K54 -> 62606.4 | V54: 70000 | W54: =U54-V54 -> -7393.6 | Y54: =F54-L54 -> 19084.883
A55: MOOV GABON T | B55: 126 | C55: =+ICT!D13 -> 11950.95 | D55: =C55*B55 -> 1505819.7 | E55: 159 | F55: =+ICT!D116 -> 2067.55 | G55: =E55*F55 -> 328740.45 | H55: =+D55-G55 -> 1177079.3 | N55: =B55*C55 -> 1505819.7 | O55: =N55/1000000 -> 1.5058197
A56: TRANSIT MV CI (en minutes ) | B56: 50.85 | C56: =+ICT!D58 -> 59809.85 | F56: =+ICT!K156 -> 0 | H56: =+D56-G56 -> 0 | N56: =B56*C56 -> 3041330.9 | P56: =(C56+#REF!)*B56/1000000 -> #REF! | Q56: =#REF!*B56/1000000 -> #REF! | R56: =P56-Q56 -> #REF!
A57: TRANSIT GT (en minutes ) | B57: 128.96114 | C57: =+ICT!D53 -> 3.6666667 | F57: 0 | H57: =+D57-G57 -> 0 | N57: =B57*C57 -> 472.85753 | V57: =+D54/C54 -> 95.276954
A58: TRANSIT SOTELMA (en minutes ) | B58: 76.287802 | C58: =+ICT!D62 -> 7086.45 | F58: =+ICT!D161 -> 17642.65 | H58: 0 | N58: =B58*C58 -> 540609.7
A59: TRANSIT MV NIGER (en minutes ) | B59: 75 | C59: 0 | F59: =+ICT!D160 -> 85431.783 | H59: 0 | N59: =B59*C59 -> 0 | AC59: =F59*176 -> 15035994 | AD59: =F59*100 -> 8543178.3
A60: TRANSIT MOOV CAF (en minutes ) | B60: 73.99195 | C60: =+ICT!D56 -> 145.28333 | F60: =+ICT!D159 -> 32.7 | H60: =+D60-G60 -> 0 | O60: =N60/1000000 -> 0
A61: TRANSIT MAURITEL (en minutes ) | B61: 144.31054 | C61: =+ICT!D55 -> 129.05 | F61: =+ICT!F157 -> 0 | H61: =+D61-G61 -> 0
A62: TRANSIT ONATEL (en minutes ) | B62: 88.947769 | C62: =+ICT!D61 -> 29.883333 | F62: =+ICT!F160 -> 0 | H62: =+D62-G62 -> 0
A63: TRANSIT MOOV TGO (en minutes ) | B63: 45.76 | C63: =+ICT!D59 -> 14449.85 | F63: =+ICT!G158 -> 0 | H63: =+D63-G63 -> 0
A64: TRANSIT TIGO TCHAD (en minutes ) | B64: 76.287805 | C64: =+ICT!D63 -> 309.36667 | F64: =+ICT!D162 -> 195.8 | H64: =+D64-G64 -> 0
A65: TRANSIT TOGO TELECOM (en minutes ) | B65: 50 | F65: =+ICT!D163 -> 101910.35 | H65: =+D65-G65 -> 0
A66: TRANSIT ORANGE SENEGAL (en minutes ) | B66: 95 | H66: =+D66-G66 -> 0
A67: TRANSIT ORANGE CI (en minutes) | B67: 122.38 | H67: =+D67-G67 -> 0
A68: TRANSIT LIBON (en minutes | B68: =0.08*655.957 -> 52.47656 | C68: 9900 | H68: =+D68-G68 -> 0
A69: AVOIR MA MALITEL | B69: -61.58 | C69: =+K69 -> 631.55 | D69: =+B69*C69 -> -38890.849 | E69: 61.58 | F69: =L69 -> 11039.333 | G69: =+E69*F69 -> 679802.13 | H69: =+D69-G69 -> -718692.98 | K69: =+MTC!Y27 -> 631.55 | L69: =+MTC!Y28 -> 11039.333
A70: TOTAL | C70: =SUM(C41:C69) -> 1035157.6 | D70: =SUM(D41:D69) -> 1.1237062e+08 | F70: =SUM(F41:F68) -> 1620425 | G70: =SUM(G41:G69) -> 1.5512832e+08 | H70: =SUM(H41:H66) -> -42039001 | K70: =SUM(K41:K68) -> 525200 | L70: =SUM(L41:L68) -> 489309.53 | O70: =SUM(O41:O60) -> 105.40729
C71: =+D70/C70 -> 108.55412 | F71: =+G70/F70 -> 95.733106
A73: INTERNATIONAL SMS
B74: INCOMING | E74: OUTGOING
B75: TA | C75: TRAFIC | D75: REVENU | E75: TA | F75: TRAFIC | G75: CHARGES | H75: BALANCE
A76: BELGA A2P (Unités) | B76: =0.08*655.957 -> 52.47656 | C76: =+'SMS A2P'!B33 -> 446367 | D76: =+'SMS A2P'!D33 -> 26322872 | G76: 0 | H76: =+D76-G76 -> 26322872
A77: BELGA SMSI (Unités) | B77: =0.08*655.957 -> 52.47656 | C77: =ICT!C41 -> 329 | D77: =+B77*C77 -> 17264.788 | E77: =0.06*655.957 -> 39.35742 | F77: =+ICT!C146 -> 26829 | G77: =+E77*F77 -> 1055920.2 | H77: =+D77-G77 -> -1038655.4
A78: SAP (Unités) | B78: =0.08*655.957 -> 52.47656 | C78: ='SMS A2P'!F33 -> 83778 | D78: =84343790.68496-D79 -> 73018791 | E78: =0.06*655.957 -> 39.35742 | F78: =+ICT!C147 -> 35463 | G78: =+E78*F78 -> 1395732.2 | H78: =+D78-G78 -> 71623058
A79: SBIN A2P | B79: 1.51 | C79: 7500000 | D79: =+B79*C79 -> 11325000
A80: TOTAL | C80: =C76+C77+C78 -> 530474 | D80: =SUM(D76:D79) -> 1.1068393e+08 | F80: =SUM(F77:F78) -> 62292 | G80: =SUM(G76:G78) -> 2451652.4 | H80: =SUM(H76:H78) -> 96907275
D81: =+D80/1000000 -> 110.68393
E82: =C80+F80 -> 592766
B83: ROAMING VISITEUR REVENU | E83: ROAMING VOYAGEUR CHARGES
B84: USAGE | C84: TRAFIC | D84: REVENU | E84: USAGE | F84: TRAFIC | G84: CHARGES | AF84: =170000 -> 170000 | AG84: 30 | AH84: =AF84*AG84 -> 5100000
A85: Roaming | B85: VOIX MO | C85: ='ROAMING IN '!BA202 -> 88479.432 | D85: ='ROAMING IN '!BL202 -> 14436531 | E85: VOIX MO | F85: =+'ROAMING OUT'!AM146 -> 66860.301 | G85: =+'ROAMING OUT'!AX146 -> 6167112
B86: VOIX MT | C86: ='ROAMING IN '!CC202 -> 612151.61 | D86: ='ROAMING IN '!CN202 -> 746.157 | E86: VOIX MT | F86: =+'ROAMING OUT'!BO146 -> 671839.79 | G86: =+'ROAMING OUT'!BZ146 -> 12018.176
B87: SMS | C87: ='ROAMING IN '!AL202 -> 28013 | D87: ='ROAMING IN '!AX202 -> 559908.52 | E87: SMS | F87: =+'ROAMING OUT'!X146 -> 2360 | G87: =+'ROAMING OUT'!AJ146 -> 189961.49
B88: DATA | C88: =('ROAMING IN '!O202+'ROAMING IN '!AC202)/1024 -> 4177043.4 | D88: =+'ROAMING IN '!V202+'ROAMING IN '!AJ202 -> 49488564 | E88: DATA | F88: =+'ROAMING OUT'!O146/1024 -> 643850.68 | G88: =+'ROAMING OUT'!V146 -> 8375327.5
B89: TOTAL | D89: =+D85+D86+D87+D88 -> 64485749 | E89: TOTAL | G89: =+G85+G86+G87+G88 -> 14744419
E91: =+C88+F88 -> 4820894
D92: =+D70+D80+D89+G27 -> 6.3623236e+08 | G92: =+G70+G80+G89 -> 1.7232439e+08
D96: =D70+D80 -> 2.2305455e+08

Sheet ICT
A1: Aggregated Data | B1: 1.102099e+08 | C1: 17220504359
A3: Rating Scenario:EN-RTRAN | B3: 0 | C3: 117257 | D3: =+C3/60 -> 1954.2833
A4: Billing Operator:MT-BEN | B4: 0 | C4: 117257 | D4: =+C4/60 -> 1954.2833
A5: Rating Scenario:ENT-COUR | B5: 174975 | C5: 132069 | D5: =+C5/60 -> 2201.15
D6: =+C6/60 -> 0
A7: Rating Scenario:ENT-FIX | B7: 0 | C7: 1664786 | D7: =+C7/60 -> 27746.433
A8: Billing Operator:SBIN | B8: 0 | C8: 1664786 | D8: =+C8/60 -> 27746.433
A9: Rating Scenario:ENT-INT | B9: 55089592 | C9: 87794132 | D9: =+C9/60 -> 1463235.5
A10: Billing Operator:BELGA | B10: 19510.045 | C10: 3921645 | D10: =+C10/60 -> 65360.75
A11: Billing Operator:FRSN | B11: 58439.167 | C11: 70127 | D11: =+C11/60 -> 1168.7833
A12: Billing Operator:FT | B12: 8893.21 | C12: 1790328 | D12: =+C12/60 -> 29838.8
A13: Billing Operator:GA-TEL | B13: 1552536.5 | C13: 717057 | D13: =+C13/60 -> 11950.95
A14: Billing Operator:MATEL | B14: 76598.885 | C14: 15386533 | D14: =+C14/60 -> 256442.22
A15: Billing Operator:MV-NE | B15: 2408.1653 | C15: 3184 | D15: =+C15/60 -> 53.066667
A16: Billing Operator:MV-RCI | B16: 4351404.7 | C16: 5148423 | D16: =+C16/60 -> 85807.05
A17: Billing Operator:MV-TOG | B17: 33195942 | C17: 43846225 | D17: =+C17/60 -> 730770.42
A18: Billing Operator:ONATEL | B18: 5580758.3 | C18: 3782583 | D18: =+C18/60 -> 63043.05
... A23: Billing Operator:SBIN | B23: 0 | C23: 26856650 | D23: =+C23/60 -> 447610.83
D24: =+C24/60 -> 0
A25: Rating Scenario:ENT-NAT | B25: 0 | C25: 7839526958 | D25: =+C25/60 -> 1.3065878e+08
A26: Billing Operator:MT-BEN | B26: 0 | C26: 1791194193 | D26: =+C26/60 -> 29853237
A27: Billing Operator:SBIN | B27: 0 | C27: 6048332765 | D27: =+C27/60 -> 1.0080555e+08
A28: Rating Scenario:ENT-RFIX | B28: 0 | C28: 1037 | D28: =+C28/60 -> 17.283333
A29: Billing Operator:SBIN | B29: 0 | C29: 1037 | D29: =+C29/60 -> 17.283333
A30: Rating Scenario:ENT-RNAT | B30: 0 | C30: 161788610 | D30: =+C30/60 -> 2696476.8
A31: Billing Operator:SBIN | B31: 0 | C31: 161788610 | D31: =+C31/60 -> 2696476.8
A32: Rating Scenario:ENT-RNMT | B32: 0 | C32: 3238104 | D32: =+C32/60 -> 53968.4
A33: Billing Operator:MT-BEN | B33: 0 | C33: 3238104 | D33: =+C33/60 -> 53968.4
A35: Rating Scenario:ENT-RSMS | B35: 0 | C35: 8518336
A36: Billing Operator:MT-BEN | B36: 0 | C36: 10225
A37: Billing Operator:SBIN | B37: 0 | C37: 8508111
A38: Rating Scenario:ENT-SA2P | B38: 28596.89 | C38: 408527
A39: Billing Operator:BELGA | B39: 28596.89 | C39: 408527
A40: Rating Scenario:ENT-SMSI | B40: 5488.3528 | C40: 1866623
A41: Billing Operator:BELGA | B41: 23.04 | C41: 329
A42: Billing Operator:MV-NE | B42: 0 | C42: 565952
A43: Billing Operator:MV-TOG | B43: 274.56 | C43: 1220644
A44: Billing Operator:SBIN | B44: 0 | C44: 1
A45: Billing Operator:SYB | B45: 5190.7528 | C45: 79697
A47: Rating Scenario:ENT-SMSN | B47: 0 | C47: 6201096
... A49: Billing Operator:SBIN | B49: 0 | C49: 3476412
A51: Rating Scenario:ENT-TRAN | B51: 6272.1316 | C51: 11288453 | D51: =+C51/60 -> 188140.88
A52: Billing Operator:BELGA | B52: 1.267858 | C52: 894 | D52: =+C52/60 -> 14.9
A53: Billing Operator:GA-TEL | B53: 0 | C53: 220 | D53: =+C53/60 -> 3.6666667
A54: Billing Operator:MATEL | B54: 6089.3334 | C54: 5643251 | D54: =+C54/60 -> 94054.183
A55: Billing Operator:MAURIT | B55: 0 | C55: 7743 | D55: =+C55/60 -> 129.05
A56: Billing Operator:MV-CAF | B56: 0 | C56: 8717 | D56: =+C56/60 -> 145.28333
A57: Billing Operator:MV-NE | B57: 0 | C57: 725536 | D57: =+C57/60 -> 12092.267
A58: Billing Operator:MV-RCI | B58: 0 | C58: 3588591 | D58: =+C58/60 -> 59809.85
A59: Billing Operator:MV-TOG | B59: 0 | C59: 866991 | D59: =+C59/60 -> 14449.85
A60: Billing Operator:OCI | B60: 0 | C60: 89 | D60: =+C60/60 -> 1.4833333
A61: Billing Operator:ONATEL | B61: 181.53033 | C61: 1793 | D61: =+C61/60 -> 29.883333
A62: Billing Operator:SOTLMA | B62: 0 | C62: 425187 | D62: =+C62/60 -> 7086.45
... A64: Billing Operator:TOGOTL | B64: 0 | C64: 879 | D64: =+C64/60 -> 14.65
A66: Rating Scenario:ENTIRSMS | B66: 0.10664 | C66: 148
A67: Billing Operator:MT-BEN | B67: 0 | C67: 9
A68: Billing Operator:SBIN | B68: 0 | C68: 59
A69: Billing Operator:SYB | B69: 0.10664 | C69: 80
A70: Rating Scenario:SMS-VAS | B70: 707177.08 | C70: 504243
A71: Billing Operator:ADK | B71: 22980.8 | C71: 5420
A72: Billing Operator:AROLIT | B72: 144617.92 | C72: 34108
A73: Billing Operator:ASIN | B73: 468380.84 | C73: 68329
A74: Billing Operator:ETAPES | B74: 40547.12 | C74: 9563
A75: Billing Operator:VAS | B75: 0 | C75: 376503
A76: Billing Operator:WIREPK | B76: 30650.4 | C76: 10320
A77: Rating Scenario:SMSVASIN | B77: 593.3 | C77: 619
... A88: Billing Operator:WIREPK | B88: 2577077.9 | C88: 867703
A90: Rating Scenario:SO-RTRAN | B90: 296664.9 | C90: 2543516919 | D90: =+C90/60 -> 42391949
A91: Billing Operator:BELGA | B91: 473.67039 | C91: 195505 | D91: =+C91/60 -> 3258.4167
A92: Billing Operator:MATEL | B92: 4597.284 | C92: 1274494 | D92: =+C92/60 -> 21241.567
A93: Billing Operator:MT-BEN | B93: 0 | C93: 584026 | D93: =+C93/60 -> 9733.7667
A94: Billing Operator:MV-RCI | B94: 17400.87 | C94: 20532 | D94: =+C94/60 -> 342.2
A95: Billing Operator:MV-TOG | B95: 109861.37 | C95: 144049 | D95: =+C95/60 -> 2400.8167
A96: Billing Operator:ONATEL | B96: 118409.2 | C96: 68313 | D96: =+C96/60 -> 1138.55
A97: Billing Operator:SBIN | B97: 0 | C97: 2541208805 | D97: =+C97/60 -> 42353480
A98: Billing Operator:ZAMANI | B98: 45922.5 | C98: 21195 | D98: =+C98/60 -> 353.25
A100: Rating Scenario:SOR-COUR | B100: 326775 | C100: 320520 | D100: =+C100/60 -> 5342
A101: Billing Operator:AFRICA | B101: 21000 | C101: 9609 | D101: =+C101/60 -> 160.15
A102: Billing Operator:CORIS | B102: 4700 | C102: 4422 | D102: =+C102/60 -> 73.7
... A107: Billing Operator:SOFRCO | B107: 1500 | C107: 757 | D107: =+C107/60 -> 12.616667
D108: =+C108/60 -> 0
A109: Rating Scenario:SOR-FIX | B109: 15705.608 | C109: 2802246 | D109: =+C109/60 -> 46704.1
A110: Billing Operator:SBIN | B110: 15705.608 | C110: 2802246 | D110: =+C110/60 -> 46704.1
D111: =+C111/60 -> 0
A112: Rating Scenario:SOR-INT | B112: 48607244 | C112: 107398148 | D112: =+C112/60 -> 1789969.1
A113: Billing Operator:AFRICA | B113: 0 | C113: 9570 | D113: =+C113/60 -> 159.5
A114: Billing Operator:BELGA | B114: 34192.182 | C114: 13414223 | D114: =+C114/60 -> 223570.38
A115: Billing Operator:FRSN | B115: 108886.67 | C115: 81665 | D115: =+C115/60 -> 1361.0833
A116: Billing Operator:GA-TEL | B116: 322537.8 | C116: 124053 | D116: =+C116/60 -> 2067.55
A117: Billing Operator:MATEL | B117: 122245.31 | C117: 47737877 | D117: =+C117/60 -> 795631.28
A118: Billing Operator:MV-NE | B118: 7887.5 | C118: 3155 | D118: =+C118/60 -> 52.583333
A119: Billing Operator:MV-RCI | B119: 2897727.9 | C119: 3460255 | D119: =+C119/60 -> 57670.917
A120: Billing Operator:MV-TOG | B120: 40731801 | C120: 40143783 | D120: =+C120/60 -> 669063.05
A121: Billing Operator:ONATEL | B121: 2686037.8 | C121: 1573554 | D121: =+C121/60 -> 26225.9
A122: Billing Operator:TOGOTL | B122: 2221.1667 | C122: 2278 | D122: =+C122/60 -> 37.966667
A123: Billing Operator:ZAMANI | B123: 1693706.7 | C123: 847735 | D123: =+C123/60 -> 14128.917
D124: =+C124/60 -> 0
A125: Rating Scenario:SOR-MOB | B125: 0 | C125: 3635976077 | D125: =+C125/60 -> 60599601
A126: Billing Operator:MT-BEN | B126: 0 | C126: 2083800358 | D126: =+C126/60 -> 34730006
A127: Billing Operator:SBIN | B127: 0 | C127: 1552175719 | D127: =+C127/60 -> 25869595
...

Sheet ROAMING IN 
D2: CALL ANALYSIS REPORT
D4: Client: BEN02
D6: Roaming Parnters: ALL
D7: Direction: TAP OUT
D8: Record Type: ALL
D10: Currency: XOF
D11: Report Type: Monthly
D12: Month and Year From: May-2025
D13: Month and Year To: May-2025
I18: GPRS | AL18: MOC | BN18: MTC
I19: MMS | X19: Others | AL19: SMS | AZ19: Voice | BN19: SMS | CB19: Voice
A20: Client | B20: RP Code | E20: Roaming Partner Name | F20: Direction | G20: Year | H20: Month | I20: Total Calls | K20: Duration in min. | L20: Ceil Duration in Min. | M20: Duration in Sec. | N20: Chargeable Units | O20: Charged Units | P20: Data Volume Incoming (KB) | Q20: Data Volume Outgoing (KB) | R20: Charges (SDR) | S20: Tax (SDR) | T20: Charges (XOF) | U20: Tax (XOF) | V20: Total Amount(XOF) | W20: Total Amount(SDR) | X20: Total Calls | Y20: Duration in min. | Z20: Ceil Duration in Min. | AA20: Duration in Sec. | AB20: Chargeable Units | AC20: Charged Units | AD20: Data Volume Incoming (KB) | AE20: Data Volume Outgoing (KB) | AF20: Charges (SDR) | AG20: Tax (SDR) | AH20: Charges (XOF) | AI20: Tax (XOF) | AJ20: Total Amount(XOF) | AK20: Total Amount(SDR) | AL20: Total Calls | AM20: Duration in min. | AN20: Ceil Duration in Min. | AO20: Duration in Sec. | AP20: Chargeable Units | AQ20: Charged Units | AR20: Data Volume Incoming (KB) | AS20: Data Volume Outgoing (KB) | AT20: Charges (SDR) | AU20: Tax (SDR) | AV20: Charges (XOF) | AW20: Tax (XOF) | AX20: Total Amount(XOF) | AY20: Total Amount(SDR) | AZ20: Total Calls | BA20: Duration in min. | BB20: Ceil Duration in Min. | BC20: Duration in Sec. | BD20: Chargeable Units | BE20: Charged Units | BF20: Data Volume Incoming (KB) | BG20: Data Volume Outgoing (KB) | BH20: Charges (SDR) | BI20: Tax (SDR) | BJ20: Charges (XOF) | BK20: Tax (XOF) | BL20: Total Amount(XOF) | BM20: Total Amount(SDR) | BN20: Total Calls | BO20: Duration in min. | BP20: Ceil Duration in Min. | BQ20: Duration in Sec. | BR20: Chargeable Units | BS20: Charged Units | BT20: Data Volume Incoming (KB) | BU20: Data Volume Outgoing (KB) | BV20: Charges (SDR) | BW20: Tax (SDR) | BX20: Charges (XOF) | BY20: Tax (XOF) | BZ20: Total Amount(XOF) | CA20: Total Amount(SDR) | CB20: Total Calls | CC20: Duration in min. | CD20: Ceil Duration in Min. | CE20: Duration in Sec. | CF20: Chargeable Units | CG20: Charged Units | CH20: Data Volume Incoming (KB) | CI20: Data Volume Outgoing (KB) | CJ20: Charges (SDR) | CK20: Tax (SDR) | CL20: Charges (XOF) | CM20: Tax (XOF) | CN20: Total Amount(XOF) | CO20: Total Amount(SDR)
A21: BEN02 | B21: AAZOR | E21: Orange France (M2m Traffic) | F21: INBOUND | G21: 2025 | H21: May | AL21: 1 | AM21: 0 | AN21: 0 | AO21: 0 | AP21: 0 | AQ21: 0 | AR21: 0 | AS21: 0 | AT21: 0.006 | AU21: 0.001 | AV21: 4.448 | AW21: 0.8 | AX21: 5.248 | AY21: 0.007 | BN21: 1 | BO21: 0 | BP21: 0 | BQ21: 0 | BR21: 0 | BS21: 0 | BT21: 0 | BU21: 0 | BV21: 0 | BW21: 0 | BX21: 0 | BY21: 0 | BZ21: 0 | CA21: 0 | CB21: 1 | CC21: 1 | CD21: 1 | CE21: 60 | CF21: 60 | CG21: 60 | CH21: 0 | CI21: 0 | CJ21: 0 | CK21: 0 | CL21: 0 | CM21: 0 | CN21: 0 | CO21: 0
B22: AAZTD | E22: Telekom Deutschland Gmbh | F22: INBOUND | G22: 2025 | H22: May | AL22: 70 | AM22: 0 | AN22: 0 | AO22: 0 | AP22: 0 | AQ22: 0 | AR22: 0 | AS22: 0 | AT22: 1.177 | AU22: 0.212 | AV22: 918.363 | AW22: 165.327 | AX22: 1083.69 | AY22: 1.389 | BN22: 68 | BO22: 0 | BP22: 0 | BQ22: 0 | BR22: 0 | BS22: 0 | BT22: 0 | BU22: 0 | BV22: 0 | BW22: 0 | BX22: 0 | BY22: 0 | BZ22: 0 | CA22: 0
B23: AAZVF | E23: Vodafone Malta | F23: INBOUND | G23: 2025 | H23: May | X23: 2681 | Y23: 94962.283 | Z23: 0 | AA23: 5697737 | AB23: 38343 | AC23: 39085 | AD23: 9807 | AE23: 28536 | AF23: 0.257 | AG23: 0.046 | AH23: 200.385 | AI23: 36.044 | AJ23: 236.429 | AK23: 0.303
B24: ALBVF | E24: Vodafone Albani | F24: INBOUND | G24: 2025 | H24: May | X24: 6 | Y24: 112.833 | Z24: 0 | AA24: 6770 | AB24: 0 | AC24: 0 | AD24: 0 | AE24: 0 | AF24: 0 | AG24: 0 | AH24: 0 | AI24: 0 | AJ24: 0 | AK24: 0
B25: ARETC | E25: Etisalat, Uae | F25: INBOUND | G25: 2025 | H25: May | X25: 18442 | Y25: 354468.02 | Z25: 0 | AA25: 21268081 | AB25: 21364519 | AC25: 23156736 | AD25: 14907897 | AE25: 6456622 | AF25: 6446.763 | AG25: 1160.417 | AH25: 5028423.9 | AI25: 905116.19 | AJ25: 5933540.1 | AK25: 7607.181 | AL25: 7 | AM25: 0 | AN25: 0 | AO25: 0 | AP25: 0 | AQ25: 0 | AR25: 0 | AS25: 0 | AT25: 0.609 | AU25: 0.11 | AV25: 474.737 | AW25: 85.454 | AX25: 560.19 | AY25: 0.718 | AZ25: 8 | BA25: 12.567 | BB25: 17 | BC25: 754 | BD25: 754 | BE25: 801 | BF25: 0 | BG25: 0 | BH25: 4.186 | BI25: 0.753 | BJ25: 3264.745 | BK25: 587.654 | BL25: 3852.399 | BM25: 4.939 | BN25: 18745 | BO25: 0 | BP25: 0 | BQ25: 0 | BR25: 0 | BS25: 0 | BT25: 0 | BU25: 0 | BV25: 0 | BW25: 0 | BX25: 0 | BY25: 0 | BZ25: 0 | CA25: 0 | CB25: 57 | CC25: 52.35 | CD25: 85 | CE25: 3141 | CF25: 3141 | CG25: 5100 | CH25: 0 | CI25: 0 | CJ25: 0 | CK25: 0 | CL25: 0 | CM25: 0 | CN25: 0 | CO25: 0
B26: BELKO | E26: Telnet Group Bvba/Sprl | F26: INBOUND | G26: 2025 | H26: May | X26: 328 | Y26: 7550.033 | Z26: 0 | AA26: 453002 | AB26: 2701 | AC26: 2803 | AD26: 260 | AE26: 2441 | AF26: 0.012 | AG26: 0.002 | AH26: 8.971 | AI26: 1.624 | AJ26: 10.595 | AK26: 0.014 | AL26: 3 | AM26: 0 | AN26: 0 | AO26: 0 | AP26: 0 | AQ26: 0 | AR26: 0 | AS26: 0 | AT26: 0.025 | AU26: 0.005 | AV26: 19.679 | AW26: 3.543 | AX26: 23.222 | AY26: 0.03 | BN26: 148 | BO26: 0 | BP26: 0 | BQ26: 0 | BR26: 0 | BS26: 0 | BT26: 0 | BU26: 0 | BV26: 0 | BW26: 0 | BX26: 0 | BY26: 0 | BZ26: 0 | CA26: 0
B27: BELMO | E27: Mobistar Gsm | F27: INBOUND | G27: 2025 | H27: May | I27: 1 | K27: 1.733 | L27: 0 | M27: 104 | N27: 46 | O27: 46 | P27: 37 | Q27: 9 | R27: 0 | S27: 0 | T27: 0.2 | U27: 0.036 | V27: 0.236 | W27: 0 | X27: 366326 | Y27: 12151146 | Z27: 0 | AA27: 729068764 | AB27: 4094781 | AC27: 4170016 | AD27: 1916178 | AE27: 2178603 | AF27: 23.241 | AG27: 4.176 | AH27: 18128.118 | AI27: 3257.527 | AJ27: 21385.644 | AK27: 27.418 | AL27: 249 | AM27: 0 | AN27: 0 | AO27: 0 | AP27: 0 | AQ27: 0 | AR27: 0 | AS27: 0 | AT27: 1.42 | AU27: 0.255 | AV27: 1107.431 | AW27: 199.268 | AX27: 1306.699 | AY27: 1.675 | AZ27: 48 | BA27: 74.2 | BB27: 104 | BC27: 4452 | BD27: 4452 | BE27: 4425 | BF27: 0 | BG27: 0 | BH27: 9.595 | BI27: 1.727 | BJ27: 7483.894 | BK27: 1347.102 | BL27: 8830.996 | BM27: 11.322 | BN27: 2862 | BO27: 0 | BP27: 0 | BQ27: 0 | BR27: 0 | BS27: 0 | BT27: 0 | BU27: 0 | BV27: 0 | BW27: 0 | BX27: 0 | BY27: 0 | BZ27: 0 | CA27: 0 | CB27: 52 | CC27: 60.8 | CD27: 94 | CE27: 3648 | CF27: 3648 | CG27: 3648 | CH27: 0 | CI27: 0 | CJ27: 0 | CK27: 0 | CL27: 0 | CM27: 0 | CN27: 0 | CO27: 0
B28: BELTB | E28: Belgacom(Nv/Sa) | F28: INBOUND | G28: 2025 | H28: May | X28: 73618 | Y28: 1593542 | Z28: 0 | AA28: 95612518 | AB28: 7799242 | AC28: 7802392 | AD28: 4954033 | AE28: 2845210 | AF28: 54.304 | AG28: 9.775 | AH28: 42357.016 | AI28: 7624.452 | AJ28: 49981.469 | AK28: 64.079 | AL28: 44 | AM28: 0 | AN28: 0 | AO28: 0 | AP28: 0 | AQ28: 0 | AR28: 0 | AS28: 0 | AT28: 0.627 | AU28: 0.113 | AV28: 489.227 | AW28: 88.064 | AX28: 577.291 | AY28: 0.74 | AZ28: 17 | BA28: 31.883 | BB28: 44 | BC28: 1913 | BD28: 1913 | BE28: 1913 | BF28: 0 | BG28: 0 | BH28: 6.86 | BI28: 1.235 | BJ28: 5350.555 | BK28: 963.099 | BL28: 6313.654 | BM28: 8.095 | BN28: 2861 | BO28: 0 | BP28: 0 | BQ28: 0 | BR28: 0 | BS28: 0 | BT28: 0 | BU28: 0 | BV28: 0 | BW28: 0 | BX28: 0 | BY28: 0 | BZ28: 0 | CA28: 0 | CB28: 16 | CC28: 14.2 | CD28: 24 | CE28: 852 | CF28: 852 | CG28: 852 | CH28: 0 | CI28: 0 | CJ28: 0 | CK28: 0 | CL28: 0 | CM28: 0 | CN28: 0 | CO28: 0
B29: BELTN | E29: Telnet Group Bvba/Sprl | F29: INBOUND | G29: 2025 | H29: May | X29: 2 | Y29: 0.05 | Z29: 0 | AA29: 3 | AB29: 0 | AC29: 1 | AD29: 0 | AE29: 0 | AF29: 0 | AG29: 0 | AH29: 0.003 | AI29: 0.001 | AJ29: 0.004 | AK29: 0 | BN29: 2 | BO29: 0 | BP29: 0 | BQ29: 0 | BR29: 0 | BS29: 0 | BT29: 0 | BU29: 0 | BV29: 0 | BW29: 0 | BX29: 0 | BY29: 0 | BZ29: 0 | CA29: 0
B30: BFACT | E30: Orange (Airtel) - Bfaso | F30: INBOUND | G30: 2025 | H30: May | X30: 588682 | Y30: 1213892 | Z30: 0 | AA30: 72833520 | AB30: 66888 | AC30: 70244 | AD30: 20561 | AE30: 46328 | AF30: 0.576 | AG30: 0.102 | AH30: 449.191 | AI30: 79.404 | AJ30: 528.595 | AK30: 0.678 | BN30: 3 | BO30: 0 | BP30: 0 | BQ30: 0 | BR30: 0 | BS30: 0 | BT30: 0 | BU30: 0 | BV30: 0 | BW30: 0 | BX30: 0 | BY30: 0 | BZ30: 0 | CA30: 0
B31: BFAON | E31: Telmob | F31: INBOUND | G31: 2025 | H31: May | X31: 921130 | Y31: 15580195 | Z31: 0 | AA31: 934811680 | AB31: 10425585 | AC31: 10450223 | AD31: 6857304 | AE31: 3568282 | AF31: 51.5 | AG31: 9.271 | AH31: 40169.202 | AI31: 7231.335 | AJ31: 47400.537 | AK31: 60.771 | AL31: 744 | AM31: 0 | AN31: 0 | AO31: 0 | AP31: 0 | AQ31: 0 | AR31: 0 | AS31: 0 | AT31: 5.631 | AU31: 1.013 | AV31: 4392.397 | AW31: 790.388 | AX31: 5182.785 | AY31: 6.645 | AZ31: 287 | BA31: 269.733 | BB31: 445 | BC31: 16184 | BD31: 16184 | BE31: 16184 | BF31: 0 | BG31: 0 | BH31: 30.565 | BI31: 5.502 | BJ31: 23840.537 | BK31: 4291.301 | BL31: 28131.837 | BM31: 36.067 | BN31: 208281 | BO31: 0 | BP31: 0 | BQ31: 0 | BR31: 0 | BS31: 0 | BT31: 0 | BU31: 0 | BV31: 0 | BW31: 0 | BX31: 0 | BY31: 0 | BZ31: 0 | CA31: 0 | CB31: 503 | CC31: 436.65 | CD31: 728 | CE31: 26199 | CF31: 26199 | CG31: 26199 | CH31: 0 | CI31: 0 | CJ31: 0 | CK31: 0 | CL31: 0 | CM31: 0 | CN31: 0 | CO31: 0
B32: BFATL | E32: Telecel - Bfaso | F32: INBOUND | G32: 2025 | H32: May | AZ32: 1 | BA32: 0.25 | BB32: 1 | BC32: 15 | BD32: 15 | BE32: 60 | BF32: 0 | BG32: 0 | BH32: 0.239 | BI32: 0.043 | BJ32: 186.292 | BK32: 33.533 | BL32: 219.824 | BM32: 0.282 | BN32: 73585 | BO32: 0 | BP32: 0 | BQ32: 0 | BR32: 0 | BS32: 0 | BT32: 0 | BU32: 0 | BV32: 0 | BW32: 0 | BX32: 0 | BY32: 0 | BZ32: 0 | CA32: 0 | CB32: 534 | CC32: 552.25 | CD32: 853 | CE32: 33135 | CF32: 33135 | CG32: 41100 | CH32: 0 | CI32: 0 | CJ32: 0 | CK32: 0 | CL32: 0 | CM32: 0 | CN32: 0 | CO32: 0
B33: BRARN | E33: Tim - Brarn | F33: INBOUND | G33: 2025 | H33: May | BN33: 61 | BO33: 0 | BP33: 0 | BQ33: 0 | BR33: 0 | BS33: 0 | BT33: 0 | BU33: 0 | BV33: 0 | BW33: 0 | BX33: 0 | BY33: 0 | BZ33: 0 | CA33: 0
B34: BRASP | E34: Tim - Brasp | F34: INBOUND | G34: 2025 | H34: May | AL34: 7 | AM34: 0 | AN34: 0 | AO34: 0 | AP34: 0 | AQ34: 0 | AR34: 0 | AS34: 0 | AT34: 0.758 | AU34: 0.136 | AV34: 591.459 | AW34: 106.463 | AX34: 697.923 | AY34: 0.895 | AZ34: 7 | BA34: 6.983 | BB34: 11 | BC34: 419 | BD34: 419 | BE34: 660 | BF34: 0 | BG34: 0 | BH34: 12.12 | BI34: 2.182 | BJ34: 9453.654 | BK34: 1701.659 | BL34: 11155.312 | BM34: 14.302 | BN34: 30 | BO34: 0 | BP34: 0 | BQ34: 0 | BR34: 0 | BS34: 0 | BT34: 0 | BU34: 0 | BV34: 0 | BW34: 0 | BX34: 0 | BY34: 0 | BZ34: 0 | CA34: 0
B35: CAFAT | E35: Acell-Rca | F35: INBOUND | G35: 2025 | H35: May | AL35: 38 | AM35: 0 | AN35: 0 | AO35: 0 | AP35: 0 | AQ35: 0 | AR35: 0 | AS35: 0 | AT35: 0.288 | AU35: 0.052 | AV35: 224.343 | AW35: 40.369 | AX35: 264.712 | AY35: 0.339 | BN35: 1580 | BO35: 0 | BP35: 0 | BQ35: 0 | BR35: 0 | BS35: 0 | BT35: 0 | BU35: 0 | BV35: 0 | BW35: 0 | BX35: 0 | BY35: 0 | BZ35: 0 | CA35: 0 | CB35: 3 | CC35: 2.667 | CD35: 4 | CE35: 160 | CF35: 160 | CG35: 160 | CH35: 0 | CI35: 0 | CJ35: 0 | CK35: 0 | CL35: 0 | CM35: 0 | CN35: 0 | CO35: 0
B36: CANBM | E36: Bell Mobility | F36: INBOUND | G36: 2025 | H36: May | X36: 5484 | Y36: 103865.17 | Z36: 0 | AA36: 6231910 | AB36: 608455 | AC36: 609280 | AD36: 305182 | AE36: 303273 | AF36: 7.506 | AG36: 1.351 | AH36: 5854.412 | AI36: 1053.756 | AJ36: 6908.168 | AK36: 8.857 | AL36: 43 | AM36: 0 | AN36: 0 | AO36: 0 | AP36: 0 | AQ36: 0 | AR36: 0 | AS36: 0 | AT36: 0.181 | AU36: 0.033 | AV36: 141.034 | AW36: 25.39 | AX36: 166.424 | AY36: 0.213 | AZ36: 21 | BA36: 20.35 | BB36: 32 | BC36: 1221 | BD36: 1221 | BE36: 1221 | BF36: 0 | BG36: 0 | BH36: 1.392 | BI36: 0.251 | BJ36: 1085.609 | BK36: 195.411 | BL36: 1281.021 | BM36: 1.642 | BN36: 523 | BO36: 0 | BP36: 0 | BQ36: 0 | BR36: 0 | BS36: 0 | BT36: 0 | BU36: 0 | BV36: 0 | BW36: 0 | BX36: 0 | BY36: 0 | BZ36: 0 | CA36: 0 | CB36: 16 | CC36: 27.767 | CD36: 38 | CE36: 1666 | CF36: 1666 | CG36: 1666 | CH36: 0 | CI36: 0 | CJ36: 0 | CK36: 0 | CL36: 0 | CM36: 0 | CN36: 0 | CO36: 0
B37: CANMC | E37: Fido-Canada | F37: INBOUND | G37: 2025 | H37: May | X37: 38 | Y37: 55.033 | Z37: 0 | AA37: 3302 | AB37: 14648 | AC37: 14970 | AD37: 10859 | AE37: 3789 | AF37: 111.144 | AG37: 20.006 | AH37: 86691.241 | AI37: 15604.427 | AJ37: 102295.67 | AK37: 131.15 | AL37: 2 | AM37: 0 | AN37: 0 | AO37: 0 | AP37: 0 | AQ37: 0 | AR37: 0 | AS37: 0 | AT37: 0.217 | AU37: 0.039 | AV37: 168.988 | AW37: 30.418 | AX37: 199.407 | AY37: 0.256 | AZ37: 4 | BA37: 3.333 | BB37: 6 | BC37: 200 | BD37: 200 | BE37: 360 | BF37: 0 | BG37: 0 | BH37: 1.433 | BI37: 0.258 | BJ37: 1117.75 | BK37: 201.196 | BL37: 1318.946 | BM37: 1.691 | BN37: 35 | BO37: 0 | BP37: 0 | BQ37: 0 | BR37: 0 | BS37: 0 | BT37: 0 | BU37: 0 | BV37: 0 | BW37: 0 | BX37: 0 | BY37: 0 | BZ37: 0 | CA37: 0
B38: CANOB | E38: Sasktel Canada (Bics) | F38: INBOUND | G38: 2025 | H38: May | X38: 1 | Y38: 0.417 | Z38: 0 | AA38: 25 | AB38: 684 | AC38: 690 | AD38: 664 | AE38: 21 | AF38: 5.161 | AG38: 0.929 | AH38: 4025.887 | AI38: 724.659 | AJ38: 4750.546 | AK38: 6.091
B39: CANRW | E39: Rogers - Canada | F39: INBOUND | G39: 2025 | H39: May | X39: 12 | Y39: 17.017 | Z39: 0 | AA39: 1021 | AB39: 5891 | AC39: 5895 | AD39: 3820 | AE39: 2071 | AF39: 0.042 | AG39: 0.007 | AH39: 32.47 | AI39: 5.845 | AJ39: 38.316 | AK39: 0.049 | BN39: 9 | BO39: 0 | BP39: 0 | BQ39: 0 | BR39: 0 | BS39: 0 | BT39: 0 | BU39: 0 | BV39: 0 | BW39: 0 | BX39: 0 | BY39: 0 | BZ39: 0 | CA39: 0
B40: CANTS | E40: Telus | F40: INBOUND | G40: 2025 | H40: May | X40: 76331 | Y40: 453750.58 | Z40: 0 | AA40: 27225035 | AB40: 44606893 | AC40: 44613600 | AD40: 30967722 | AE40: 13639171 | AF40: 549.596 | AG40: 98.927 | AH40: 428680.81 | AI40: 77162.389 | AJ40: 505843.2 | AK40: 648.524 | AL40: 694 | AM40: 0 | AN40: 0 | AO40: 0 | AP40: 0 | AQ40: 0 | AR40: 0 | AS40: 0 | AT40: 2.918 | AU40: 0.525 | AV40: 2276.227 | AW40: 409.775 | AX40: 2686.002 | AY40: 3.444 | AZ40: 118 | BA40: 479.467 | BB40: 552 | BC40: 28768 | BD40: 28768 | BE40: 28768 | BF40: 0 | BG40: 0 | BH40: 29.279 | BI40: 5.27 | BJ40: 22837.147 | BK40: 4110.687 | BL40: 26947.834 | BM40: 34.549 | BN40: 4562 | BO40: 0 | BP40: 0 | BQ40: 0 | BR40: 0 | BS40: 0 | BT40: 0 | BU40: 0 | BV40: 0 | BW40: 0 | BX40: 0 | BY40: 0 | BZ40: 0 | CA40: 0 | CB40: 36 | CC40: 174.133 | CD40: 197 | CE40: 10448 | CF40: 10448 | CG40: 10448 | CH40: 0 | CI40: 0 | CJ40: 0 | CK40: 0 | CL40: 0 | CM40: 0 | CN40: 0 | CO40: 0
B41: CANVT | E41: Videotron | F41: INBOUND | G41: 2025 | H41: May | X41: 14128 | Y41: 241620.72 | Z41: 0 | AA41: 14497243 | AB41: 5050911 | AC41: 5051490 | AD41: 3224103 | AE41: 1826808 | AF41: 41.486 | AG41: 7.467 | AH41: 32358.989 | AI41: 5824.559 | AJ41: 38183.548 | AK41: 48.954 | AL41: 14 | AM41: 0 | AN41: 0 | AO41: 0 | AP41: 0 | AQ41: 0 | AR41: 0 | AS41: 0 | AT41: 0.118 | AU41: 0.021 | AV41: 91.836 | AW41: 16.533 | AX41: 108.369 | AY41: 0.139 | AZ41: 16 | BA41: 41.767 | BB41: 54 | BC41: 2506 | BD41: 2506 | BE41: 2506 | BF41: 0 | BG41: 0 | BH41: 2.981 | BI41: 0.537 | BJ41: 2325.368 | BK41: 418.565 | BL41: 2743.933 | BM41: 3.518 | BN41: 593 | BO41: 0 | BP41: 0 | BQ41: 0 | BR41: 0 | BS41: 0 | BT41: 0 | BU41: 0 | BV41: 0 | BW41: 0 | BX41: 0 | BY41: 0 | BZ41: 0 | CA41: 0 | CB41: 5 | CC41: 5.867 | CD41: 9 | CE41: 352 | CF41: 352 | CG41: 352 | CH41: 0 | CI41: 0 | CJ41: 0 | CK41: 0 | CL41: 0 | CM41: 0 | CN41: 0 | CO41: 0
B42: CHEC1 | E42: Swisscom(Switzerland)Ltd | F42: INBOUND | G42: 2025 | H42: May | X42: 365 | Y42: 13228.283 | Z42: 0 | AA42: 793697 | AB42: 23887 | AC42: 24030 | AD42: 15357 | AE42: 8530 | AF42: 0.178 | AG42: 0.032 | AH42: 138.549 | AI42: 24.952 | AJ42: 163.501 | AK42: 0.21 | AL42: 37 | AM42: 0 | AN42: 0 | AO42: 0 | AP42: 0 | AQ42: 0 | AR42: 0 | AS42: 0 | AT42: 0.311 | AU42: 0.056 | AV42: 242.71 | AW42: 43.694 | AX42: 286.404 | AY42: 0.367 | BN42: 484 | BO42: 0 | BP42: 0 | BQ42: 0 | BR42: 0 | BS42: 0 | BT42: 0 | BU42: 0 | BV42: 0 | BW42: 0 | BX42: 0 | BY42: 0 | BZ42: 0 | CA42: 0 | CB42: 5 | CC42: 13.833 | CD42: 17 | CE42: 830 | CF42: 830 | CG42: 830 | CH42: 0 | CI42: 0 | CJ42: 0 | CK42: 0 | CL42: 0 | CM42: 0 | CN42: 0 | CO42: 0
B43: CHEDX | E43: Sunrise Communications Ag | F43: INBOUND | G43: 2025 | H43: May | X43: 61862 | Y43: 1208470.9 | Z43: 0 | AA43: 72508254 | AB43: 17216991 | AC43: 17218752 | AD43: 13074736 | AE43: 4142255 | AF43: 70.706 | AG43: 12.727 | AH43: 55150.096 | AI43: 9927.051 | AJ43: 65077.147 | AK43: 83.433 | AL43: 421 | AM43: 0 | AN43: 0 | AO43: 0 | AP43: 0 | AQ43: 0 | AR43: 0 | AS43: 0 | AT43: 3.541 | AU43: 0.637 | AV43: 2761.647 | AW43: 497.162 | AX43: 3258.81 | AY43: 4.178 | AZ43: 46 | BA43: 138.933 | BB43: 164 | BC43: 8336 | BD43: 8336 | BE43: 8336 | BF43: 0 | BG43: 0 | BH43: 35.052 | BI43: 6.309 | BJ43: 27340.29 | BK43: 4921.253 | BL43: 32261.542 | BM43: 41.361 | BN43: 2958 | BO43: 0 | BP43: 0 | BQ43: 0 | BR43: 0 | BS43: 0 | BT43: 0 | BU43: 0 | BV43: 0 | BW43: 0 | BX43: 0 | BY43: 0 | BZ43: 0 | CA43: 0 | CB43: 16 | CC43: 16.967 | CD43: 27 | CE43: 1018 | CF43: 1018 | CG43: 1018 | CH43: 0 | CI43: 0 | CJ43: 0 | CK43: 0 | CL43: 0 | CM43: 0 | CN43: 0 | CO43: 0
B44: CHNCU | E44: China Unicom | F44: INBOUND | G44: 2025 | H44: May | AL44: 185 | AM44: 0 | AN44: 0 | AO44: 0 | AP44: 0 | AQ44: 0 | AR44: 0 | AS44: 0 | AT44: 7.779 | AU44: 1.4 | AV44: 6067.608 | AW44: 1092.195 | AX44: 7159.804 | AY44: 9.179 | AZ44: 65 | BA44: 74.3 | BB44: 110 | BC44: 4458 | BD44: 4458 | BE44: 6600 | BF44: 0 | BG44: 0 | BH44: 15.222 | BI44: 2.74 | BJ44: 11872.831 | BK44: 2137.115 | BL44: 14009.946 | BM44: 17.962 | BN44: 8903 | BO44: 0 | BP44: 0 | BQ44: 0 | BR44: 0 | BS44: 0 | BT44: 0 | BU44: 0 | BV44: 0 | BW44: 0 | BX44: 0 | BY44: 0 | BZ44: 0 | CA44: 0 | CB44: 41 | CC44: 30.733 | CD44: 59 | CE44: 1844 | CF44: 1844 | CG44: 3540 | CH44: 0 | CI44: 0 | CJ44: 0.05 | CK44: 0.009 | CL44: 38.702 | CM44: 6.958 | CN44: 45.66 | CO44: 0.059
B45: CHNDX | E45: China Telecom | F45: INBOUND | G45: 2025 | H45: May | X45: 107898 | Y45: 1996668.6 | Z45: 0 | AA45: 119800116 | AB45: 29113714 | AC45: 29114765 | AD45: 25511863 | AE45: 3601851 | AF45: 358.666 | AG45: 64.56 | AH45: 279756.43 | AI45: 50356.136 | AJ45: 330112.57 | AK45: 423.226 | AL45: 198 | AM45: 0 | AN45: 0 | AO45: 0 | AP45: 0 | AQ45: 0 | AR45: 0 | AS45: 0 | AT45: 3.33 | AU45: 0.6 | AV45: 2597.654 | AW45: 467.64 | AX45: 3065.294 | AY45: 3.93 | AZ45: 25 | BA45: 9.817 | BB45: 26 | BC45: 589 | BD45: 589 | BE45: 1560 | BF45: 0 | BG45: 0 | BH45: 1.598 | BI45: 0.288 | BJ45: 1246.32 | BK45: 224.341 | BL45: 1470.66 | BM45: 1.885 | BN45: 91 | BO45: 0 | BP45: 0 | BQ45: 0 | BR45: 0 | BS45: 0 | BT45: 0 | BU45: 0 | BV45: 0 | BW45: 0 | BX45: 0 | BY45: 0 | BZ45: 0 | CA45: 0
B46: CIV02 | E46: Moov(A-Cell) | F46: INBOUND | G46: 2025 | H46: May | X46: 989092 | Y46: 17109900 | Z46: 0 | AA46: 1026594002 | AB46: 9238158 | AC46: 9321945 | AD46: 3139222 | AE46: 6098937 | AF46: 45.944 | AG46: 8.281 | AH46: 35836.275 | AI46: 6459.153 | AJ46: 42295.427 | AK46: 54.225 | AL46: 32 | AM46: 0 | AN46: 0 | AO46: 0 | AP46: 0 | AQ46: 0 | AR46: 0 | AS46: 0 | AT46: 0.242 | AU46: 0.044 | AV46: 188.92 | AW46: 33.995 | AX46: 222.915 | AY46: 0.286 | AZ46: 1123 | BA46: 1466.8 | BB46: 2016 | BC46: 88008 | BD46: 88008 | BE46: 88008 | BF46: 0 | BG46: 0 | BH46: 128.871 | BI46: 23.197 | BJ46: 100518.14 | BK46: 18093.253 | BL46: 118611.4 | BM46: 152.067 | BN46: 709857 | BO46: 0 | BP46: 0 | BQ46: 0 | BR46: 0 | BS46: 0 | BT46: 0 | BU46: 0 | BV46: 0 | BW46: 0 | BX46: 0 | BY46: 0 | BZ46: 0 | CA46: 0 | CB46: 1308 | CC46: 2017.583 | CD46: 2723 | CE46: 121055 | CF46: 121055 | CG46: 121055 | CH46: 0 | CI46: 0 | CJ46: 0 | CK46: 0 | CL46: 0 | CM46: 0 | CN46: 0 | CO46: 0
B47: CIV03 | E47: Orange-Ivory C | F47: INBOUND | G47: 2025 | H47: May | X47: 2687750 | Y47: 41866942 | Z47: 0 | AA47: 2512016527 | AB47: 231158076 | AC47: 231472949 | AD47: 175918731 | AE47: 55239346 | AF47: 1900.938 | AG47: 342.023 | AH47: 1482716.4 | AI47: 266775.02 | AJ47: 1749491.5 | AK47: 2242.961 | AL47: 3158 | AM47: 0 | AN47: 0 | AO47: 0 | AP47: 0 | AQ47: 0 | AR47: 0 | AS47: 0 | AT47: 26.559 | AU47: 4.781 | AV47: 20715.636 | AW47: 3729.307 | AX47: 24444.943 | AY47: 31.34 | AZ47: 4287 | BA47: 5798.1 | BB47: 8116 | BC47: 347886 | BD47: 347886 | BE47: 347886 | BF47: 0 | BG47: 0 | BH47: 1601.693 | BI47: 288.305 | BJ47: 1249308 | BK47: 224875.51 | BL47: 1474183.5 | BM47: 1889.998 | BN47: 321123 | BO47: 0 | BP47: 0 | BQ47: 0 | BR47: 0 | BS47: 0 | BT47: 0 | BU47: 0 | BV47: 0 | BW47: 0 | BX47: 0 | BY47: 0 | BZ47: 0 | CA47: 0 | CB47: 12724 | CC47: 25353.233 | CD47: 31997 | CE47: 1521194 | CF47: 1521194 | CG47: 1521194 | CH47: 0 | CI47: 0 | CJ47: 0 | CK47: 0 | CL47: 0 | CM47: 0 | CN47: 0 | CO47: 0
B48: CMR02 | E48: Orange Cameroun | F48: INBOUND | G48: 2025 | H48: May | X48: 249109 | Y48: 4880654 | Z48: 0 | AA48: 292839239 | AB48: 6323 | AC48: 6765 | AD48: 4524 | AE48: 1799 | AF48: 0.055 | AG48: 0.01 | AH48: 43.239 | AI48: 7.617 | AJ48: 50.855 | AK48: 0.065 | AL48: 87 | AM48: 0 | AN48: 0 | AO48: 0 | AP48: 0 | AQ48: 0 | AR48: 0 | AS48: 0 | AT48: 0.732 | AU48: 0.132 | AV48: 570.697 | AW48: 102.739 | AX48: 673.436 | AY48: 0.863 | AZ48: 127 | BA48: 176.483 | BB48: 255 | BC48: 10589 | BD48: 10589 | BE48: 10589 | BF48: 0 | BG48: 0 | BH48: 60.729 | BI48: 10.931 | BJ48: 47368.298 | BK48: 8526.294 | BL48: 55894.592 | BM48: 71.66 | BN48: 95767 | BO48: 0 | BP48: 0 | BQ48: 0 | BR48: 0 | BS48: 0 | BT48: 0 | BU48: 0 | BV48: 0 | BW48: 0 | BX48: 0 | BY48: 0 | BZ48: 0 | CA48: 0 | CB48: 169 | CC48: 155 | CD48: 258 | CE48: 9300 | CF48: 9300 | CG48: 9300 | CH48: 0 | CI48: 0 | CJ48: 0 | CK48: 0 | CL48: 0 | CM48: 0 | CN48: 0 | CO48: 0
B49: CMRMT | E49: Mtn - Cameroon | F49: INBOUND | G49: 2025 | H49: May | X49: 250 | Y49: 5880.217 | Z49: 0 | AA49: 352813 | AB49: 74322 | AC49: 74435 | AD49: 36942 | AE49: 37379 | AF49: 0.306 | AG49: 0.055 | AH49: 238.394 | AI49: 42.897 | AJ49: 281.291 | AK49: 0.361 | AL49: 11 | AM49: 0 | AN49: 0 | AO49: 0 | AP49: 0 | AQ49: 0 | AR49: 0 | AS49: 0 | AT49: 0.435 | AU49: 0.078 | AV49: 339.13 | AW49: 61.046 | AX49: 400.176 | AY49: 0.513 | AZ49: 8 | BA49: 4.033 | BB49: 8 | BC49: 242 | BD49: 242 | BE49: 242 | BF49: 0 | BG49: 0 | BH49: 0.607 | BI49: 0.109 | BJ49: 473.491 | BK49: 85.227 | BL49: 558.718 | BM49: 0.716 | BN49: 17072 | BO49: 0 | BP49: 0 | BQ49: 0 | BR49: 0 | BS49: 0 | BT49: 0 | BU49: 0 | BV49: 0 | BW49: 0 | BX49: 0 | BY49: 0 | BZ49: 0 | CA49: 0 | CB49: 27 | CC49: 45.65 | CD49: 60 | CE49: 2739 | CF49: 2739 | CG49: 2739 | CH49: 0 | CI49: 0 | CJ49: 0 | CK49: 0 | CL49: 0 | CM49: 0 | CN49: 0 | CO49: 0
B50: CODFT | E50: Congo China | F50: INBOUND | G50: 2025 | H50: May | X50: 15854 | Y50: 236070.43 | Z50: 0 | AA50: 14164226 | AB50: 54720 | AC50: 56182 | AD50: 41723 | AE50: 12997 | AF50: 0.461 | AG50: 0.082 | AH50: 359.434 | AI50: 63.767 | AJ50: 423.202 | AK50: 0.543 | AL50: 10 | AM50: 0 | AN50: 0 | AO50: 0 | AP50: 0 | AQ50: 0 | AR50: 0 | AS50: 0 | AT50: 0.084 | AU50: 0.015 | AV50: 65.597 | AW50: 11.809 | AX50: 77.406 | AY50: 0.099 | AZ50: 6 | BA50: 3.65 | BB50: 8 | BC50: 219 | BD50: 219 | BE50: 219 | BF50: 0 | BG50: 0 | BH50: 1.06 | BI50: 0.191 | BJ50: 826.505 | BK50: 148.77 | BL50: 975.275 | BM50: 1.25 | BN50: 16906 | BO50: 0 | BP50: 0 | BQ50: 0 | BR50: 0 | BS50: 0 | BT50: 0 | BU50: 0 | BV50: 0 | BW50: 0 | BX50: 0 | BY50: 0 | BZ50: 0 | CA50: 0 | CB50: 21 | CC50: 21.35 | CD50: 34 | CE50: 1281 | CF50: 1281 | CG50: 1281 | CH50: 0 | CI50: 0 | CJ50: 0 | CK50: 0 | CL50: 0 | CM50: 0 | CN50: 0 | CO50: 0
B51: CODSA | E51: Oasis Sprl | F51: INBOUND | G51: 2025 | H51: May | BN51: 23 | BO51: 0 | BP51: 0 | BQ51: 0 | BR51: 0 | BS51: 0 | BT51: 0 | BU51: 0 | BV51: 0 | BW51: 0 | BX51: 0 | BY51: 0 | BZ51: 0 | CA51: 0
B52: CODVC | E52: Vodacom - Congo | F52: INBOUND | G52: 2025 | H52: May | X52: 42 | Y52: 331 | Z52: 0 | AA52: 19860 | AB52: 566 | AC52: 567 | AD52: 411 | AE52: 154 | AF52: 0.004 | AG52: 0.001 | AH52: 2.906 | AI52: 0.523 | AJ52: 3.429 | AK52: 0.004
B53: COGCT | E53: Airtel - Congo | F53: INBOUND | G53: 2025 | H53: May | BN53: 788 | BO53: 0 | BP53: 0 | BQ53: 0 | BR53: 0 | BS53: 0 | BT53: 0 | BU53: 0 | BV53: 0 | BW53: 0 | BX53: 0 | BY53: 0 | BZ53: 0 | CA53: 0
B54: CZECM | E54: Vodafone , Czech Republic | F54: INBOUND | G54: 2025 | H54: May | X54: 1744 | Y54: 34036.217 | Z54: 0 | AA54: 2042173 | AB54: 133832 | AC54: 133974 | AD54: 114609 | AE54: 19223 | AF54: 0.88 | AG54: 0.158 | AH54: 686.57 | AI54: 123.583 | AJ54: 810.153 | AK54: 1.039 | AL54: 5 | AM54: 0 | AN54: 0 | AO54: 0 | AP54: 0 | AQ54: 0 | AR54: 0 | AS54: 0 | AT54: 0.168 | AU54: 0.03 | AV54: 131.191 | AW54: 23.614 | AX54: 154.805 | AY54: 0.198 | BN54: 163 | BO54: 0 | BP54: 0 | BQ54: 0 | BR54: 0 | BS54: 0 | BT54: 0 | BU54: 0 | BV54: 0 | BW54: 0 | BX54: 0 | BY54: 0 | BZ54: 0 | CA54: 0
B55: DEUD1 | E55: T-Mobile,German | F55: INBOUND | G55: 2025 | H55: May | X55: 33703 | Y55: 448798.7 | Z55: 0 | AA55: 26927922 | AB55: 35195172 | AC55: 35201193 | AD55: 30480236 | AE55: 4714936 | AF55: 231.278 | AG55: 41.63 | AH55: 180394.75 | AI55: 32470.79 | AJ55: 212865.54 | AK55: 272.907 | AL55: 7 | AM55: 0 | AN55: 0 | AO55: 0 | AP55: 0 | AQ55: 0 | AR55: 0 | AS55: 0 | AT55: 0.118 | AU55: 0.021 | AV55: 91.836 | AW55: 16.533 | AX55: 108.369 | AY55: 0.139 | AZ55: 16 | BA55: 43.8 | BB55: 54 | BC55: 2628 | BD55: 2628 | BE55: 2628 | BF55: 0 | BG55: 0 | BH55: 5.043 | BI55: 0.908 | BJ55: 3933.777 | BK55: 708.08 | BL55: 4641.856 | BM55: 5.951 | BN55: 1099 | BO55: 0 | BP55: 0 | BQ55: 0 | BR55: 0 | BS55: 0 | BT55: 0 | BU55: 0 | BV55: 0 | BW55: 0 | BX55: 0 | BY55: 0 | BZ55: 0 | CA55: 0
B56: DEUD2 | E56: Vodafone German | F56: INBOUND | G56: 2025 | H56: May | X56: 42870 | Y56: 793176.3 | Z56: 0 | AA56: 47590578 | AB56: 18196797 | AC56: 18199948 | AD56: 13101016 | AE56: 5095781 | AF56: 119.577 | AG56: 21.524 | AH56: 93268.804 | AI56: 16788.198 | AJ56: 110057 | AK56: 141.1 | AL56: 35 | AM56: 0 | AN56: 0 | AO56: 0 | AP56: 0 | AQ56: 0 | AR56: 0 | AS56: 0 | AT56: 1.177 | AU56: 0.212 | AV56: 918.335 | AW56: 165.3 | AX56: 1083.635 | AY56: 1.389 | AZ56: 44 | BA56: 51.267 | BB56: 82 | BC56: 3076 | BD56: 3076 | BE56: 3076 | BF56: 0 | BG56: 0 | BH56: 4.858 | BI56: 0.874 | BJ56: 3789.247 | BK56: 682.065 | BL56: 4471.312 | BM56: 5.733 | BN56: 1380 | BO56: 0 | BP56: 0 | BQ56: 0 | BR56: 0 | BS56: 0 | BT56: 0 | BU56: 0 | BV56: 0 | BW56: 0 | BX56: 0 | BY56: 0 | BZ56: 0 | CA56: 0 | CB56: 34 | CC56: 49.533 | CD56: 70 | CE56: 2972 | CF56: 2972 | CG56: 2972 | CH56: 0 | CI56: 0 | CJ56: 0 | CK56: 0 | CL56: 0 | CM56: 0 | CN56: 0 | CO56: 0
B57: DEUE1 | E57: E-Plus, Germany | F57: INBOUND | G57: 2025 | H57: May | X57: 363 | Y57: 6802.867 | Z57: 0 | AA57: 408172 | AB57: 54866 | AC57: 54973 | AD57: 47068 | AE57: 7798 | AF57: 9.03 | AG57: 1.625 | AH57: 7042.965 | AI57: 1267.751 | AJ57: 8310.716 | AK57: 10.655 | AL57: 97 | AM57: 0 | AN57: 0 | AO57: 0 | AP57: 0 | AQ57: 0 | AR57: 0 | AS57: 0 | AT57: 4.079 | AU57: 0.734 | AV57: 3181.395 | AW57: 572.665 | AX57: 3754.059 | AY57: 4.813 | AZ57: 54 | BA57: 21.233 | BB57: 59 | BC57: 1274 | BD57: 1274 | BE57: 1274 | BF57: 0 | BG57: 0 | BH57: 4.464 | BI57: 0.804 | BJ57: 3482.04 | BK57: 626.763 | BL57: 4108.803 | BM57: 5.268 | BN57: 2370 | BO57: 0 | BP57: 0 | BQ57: 0 | BR57: 0 | BS57: 0 | BT57: 0 | BU57: 0 | BV57: 0 | BW57: 0 | BX57: 0 | BY57: 0 | BZ57: 0 | CA57: 0 | CB57: 83 | CC57: 27.15 | CD57: 85 | CE57: 1629 | CF57: 1629 | CG57: 1629 | CH57: 0 | CI57: 0 | CJ57: 0 | CK57: 0 | CL57: 0 | CM57: 0 | CN57: 0 | CO57: 0
B58: DEUE2 | E58: O2 (Germany) Gm | F58: INBOUND | G58: 2025 | H58: May | X58: 1226 | Y58: 21972.717 | Z58: 0 | AA58: 1318363 | AB58: 67562 | AC58: 67979 | AD58: 38015 | AE58: 29547 | AF58: 11.166 | AG58: 2.01 | AH58: 8709.186 | AI58: 1567.81 | AJ58: 10276.996 | AK58: 13.176 | AL58: 27 | AM58: 0 | AN58: 0 | AO58: 0 | AP58: 0 | AQ58: 0 | AR58: 0 | AS58: 0 | AT58: 1.135 | AU58: 0.204 | AV58: 885.543 | AW58: 159.402 | AX58: 1044.944 | AY58: 1.34 | AZ58: 64 | BA58: 150.133 | BB58: 186 | BC58: 9008 | BD58: 9008 | BE58: 9008 | BF58: 0 | BG58: 0 | BH58: 31.565 | BI58: 5.682 | BJ58: 24620.256 | BK58: 4431.645 | BL58: 29051.901 | BM58: 37.246 | BN58: 1218 | BO58: 0 | BP58: 0 | BQ58: 0 | BR58: 0 | BS58: 0 | BT58: 0 | BU58: 0 | BV58: 0 | BW58: 0 | BX58: 0 | BY58: 0 | BZ58: 0 | CA58: 0 | CB58: 47 | CC58: 31.533 | CD58: 63 | CE58: 1892 | CF58: 1892 | CG58: 1892 | CH58: 0 | CI58: 0 | CJ58: 0 | CK58: 0 | CL58: 0 | CM58: 0 | CN58: 0 | CO58: 0
B59: DNKDM | E59: Telenor A/S | F59: INBOUND | G59: 2025 | H59: May | AL59: 11 | AM59: 0 | AN59: 0 | AO59: 0 | AP59: 0 | AQ59: 0 | AR59: 0 | AS59: 0 | AT59: 1.192 | AU59: 0.214 | AV59: 929.436 | AW59: 167.3 | AX59: 1096.736 | AY59: 1.406 | AZ59: 3 | BA59: 2.417 | BB59: 4 | BC59: 145 | BD59: 145 | BE59: 240 | BF59: 0 | BG59: 0 | BH59: 2.142 | BI59: 0.386 | BJ59: 1670.723 | BK59: 300.731 | BL59: 1971.453 | BM59: 2.528 | BN59: 41 | BO59: 0 | BP59: 0 | BQ59: 0 | BR59: 0 | BS59: 0 | BT59: 0 | BU59: 0 | BV59: 0 | BW59: 0 | BX59: 0 | BY59: 0 | BZ59: 0 | CA59: 0 | CB59: 2 | CC59: 5.3 | CD59: 6 | CE59: 318 | CF59: 318 | CG59: 330 | CH59: 0 | CI59: 0 | CJ59: 0 | CK59: 0 | CL59: 0 | CM59: 0 | CN59: 0 | CO59: 0
B60: EGYAR | E60: Orange Egypt | F60: INBOUND | G60: 2025 | H60: May | X60: 51 | Y60: 570.433 | Z60: 0 | AA60: 34226 | AB60: 672 | AC60: 674 | AD60: 17 | AE60: 655 | AF60: 0.006 | AG60: 0.001 | AH60: 4.317 | AI60: 0.778 | AJ60: 5.095 | AK60: 0.007
B61: EGYEM | E61: Etisalat Misr | F61: INBOUND | G61: 2025 | H61: May | AL61: 8 | AM61: 0 | AN61: 0 | AO61: 0 | AP61: 0 | AQ61: 0 | AR61: 0 | AS61: 0 | AT61: 0.867 | AU61: 0.156 | AV61: 675.954 | AW61: 121.673 | AX61: 797.626 | AY61: 1.023 | BN61: 4063 | BO61: 0 | BP61: 0 | BQ61: 0 | BR61: 0 | BS61: 0 | BT61: 0 | BU61: 0 | BV61: 0 | BW61: 0 | BX61: 0 | BY61: 0 | BZ61: 0 | CA61: 0 | CB61: 5 | CC61: 23.767 | CD61: 27 | CE61: 1426 | CF61: 1426 | CG61: 1500 | CH61: 0 | CI61: 0 | CJ61: 0 | CK61: 0 | CL61: 0 | CM61: 0 | CN61: 0 | CO61: 0
B62: EGYMS | E62: Vodafone Egypt | F62: INBOUND | G62: 2025 | H62: May | X62: 24506 | Y62: 361665.72 | Z62: 0 | AA62: 21699943 | AB62: 3242595 | AC62: 3242878 | AD62: 2739978 | AE62: 502617 | AF62: 26.633 | AG62: 4.794 | AH62: 20773.337 | AI62: 3739.176 | AJ62: 24512.512 | AK62: 31.427 | AL62: 20 | AM62: 0 | AN62: 0 | AO62: 0 | AP62: 0 | AQ62: 0 | AR62: 0 | AS62: 0 | AT62: 0.673 | AU62: 0.121 | AV62: 524.763 | AW62: 94.457 | AX62: 619.22 | AY62: 0.794 | BN62: 2527 | BO62: 0 | BP62: 0 | BQ62: 0 | BR62: 0 | BS62: 0 | BT62: 0 | BU62: 0 | BV62: 0 | BW62: 0 | BX62: 0 | BY62: 0 | BZ62: 0 | CA62: 0
B63: EMNDE | E63: Emnify Gmbh | F63: INBOUND | G63: 2025 | H63: May | X63: 70 | Y63: 1162.05 | Z63: 0 | AA63: 69723 | AB63: 65469 | AC63: 65489 | AD63: 13933 | AE63: 51537 | AF63: 0.684 | AG63: 0.123 | AH63: 533.277 | AI63: 95.993 | AJ63: 629.269 | AK63: 0.807
B64: ESPAT | E64: Vodafone Espana | F64: INBOUND | G64: 2025 | H64: May | X64: 1423251 | Y64: 10678834 | Z64: 0 | AA64: 640730065 | AB64: 171624209 | AC64: 172113394 | AD64: 157025318 | AE64: 14598890 | AF64: 1131.163 | AG64: 203.389 | AH64: 882298.2 | AI64: 158641.83 | AJ64: 1040940 | AK64: 1334.552 | AL64: 174 | AM64: 0 | AN64: 0 | AO64: 0 | AP64: 0 | AQ64: 0 | AR64: 0 | AS64: 0 | AT64: 5.853 | AU64: 1.054 | AV64: 4565.438 | AW64: 821.776 | AX64: 5387.214 | AY64: 6.907 | AZ64: 141 | BA64: 725.283 | BB64: 796 | BC64: 43517 | BD64: 43517 | BE64: 43517 | BF64: 0 | BG64: 0 | BH64: 78.692 | BI64: 14.165 | BJ64: 61378.992 | BK64: 11048.22 | BL64: 72427.212 | BM64: 92.856 | BN64: 33261 | BO64: 0 | BP64: 0 | BQ64: 0 | BR64: 0 | BS64: 0 | BT64: 0 | BU64: 0 | BV64: 0 | BW64: 0 | BX64: 0 | BY64: 0 | BZ64: 0 | CA64: 0 | CB64: 154 | CC64: 123.983 | CD64: 227 | CE64: 7439 | CF64: 7439 | CG64: 7439 | CH64: 0 | CI64: 0 | CJ64: 0 | CK64: 0 | CL64: 0 | CM64: 0 | CN64: 0 | CO64: 0
B65: ESPRT | E65: Orange Spain | F65: INBOUND | G65: 2025 | H65: May | AL65: 76 | AM65: 0 | AN65: 0 | AO65: 0 | AP65: 0 | AQ65: 0 | AR65: 0 | AS65: 0 | AT65: 0.433 | AU65: 0.078 | AV65: 338.011 | AW65: 60.821 | AX65: 398.832 | AY65: 0.511 | AZ65: 2 | BA65: 5.75 | BB65: 7 | BC65: 345 | BD65: 345 | BE65: 345 | BF65: 0 | BG65: 0 | BH65: 0.41 | BI65: 0.074 | BJ65: 319.656 | BK65: 57.538 | BL65: 377.195 | BM65: 0.484 | BN65: 9145 | BO65: 0 | BP65: 0 | BQ65: 0 | BR65: 0 | BS65: 0 | BT65: 0 | BU65: 0 | BV65: 0 | BW65: 0 | BX65: 0 | BY65: 0 | BZ65: 0 | CA65: 0 | CB65: 134 | CC65: 78.7 | CD65: 158 | CE65: 4722 | CF65: 4722 | CG65: 4722 | CH65: 0 | CI65: 0 | CJ65: 0 | CK65: 0 | CL65: 0 | CM65: 0 | CN65: 0 | CO65: 0
B66: ESPTE | E66: Telefonica, Spn | F66: INBOUND | G66: 2025 | H66: May | X66: 310585 | Y66: 140057.43 | Z66: 0 | AA66: 8403446 | AB66: 4527 | AC66: 4703 | AD66: 3068 | AE66: 1459 | AF66: 0.772 | AG66: 0.139 | AH66: 602.495 | AI66: 108.52 | AJ66: 711.015 | AK66: 0.912
B67: ESPVV | E67: Vadafone Spain | F67: INBOUND | G67: 2025 | H67: May | X67: 2214 | Y67: 43914.3 | Z67: 0 | AA67: 2634858 | AB67: 3242 | AC67: 3311 | AD67: 1559 | AE67: 1684 | AF67: 0.022 | AG67: 0.004 | AH67: 16.994 | AI67: 3.045 | AJ67: 20.04 | AK67: 0.026 | BN67: 116 | BO67: 0 | BP67: 0 | BQ67: 0 | BR67: 0 | BS67: 0 | BT67: 0 | BU67: 0 | BV67: 0 | BW67: 0 | BX67: 0 | BY67: 0 | BZ67: 0 | CA67: 0 | CB67: 5 | CC67: 6.083 | CD67: 10 | CE67: 365 | CF67: 365 | CG67: 365 | CH67: 0 | CI67: 0 | CJ67: 0 | CK67: 0 | CL67: 0 | CM67: 0 | CN67: 0 | CO67: 0
B68: ESTRE | E68: Elisa Mobiilsid | F68: INBOUND | G68: 2025 | H68: May | BN68: 1 | BO68: 0 | BP68: 0 | BQ68: 0 | BR68: 0 | BS68: 0 | BT68: 0 | BU68: 0 | BV68: 0 | BW68: 0 | BX68: 0 | BY68: 0 | BZ68: 0 | CA68: 0
B69: ETH01 | E69: Ethio Telecom | F69: INBOUND | G69: 2025 | H69: May | X69: 24 | Y69: 24.283 | Z69: 0 | AA69: 1457 | AB69: 123 | AC69: 240 | AD69: 8 | AE69: 115 | AF69: 2.803 | AG69: 0.505 | AH69: 2186.318 | AI69: 393.539 | AJ69: 2579.856 | AK69: 3.308
B70: FRA09 | E70: Sfr | F70: INBOUND | G70: 2025 | H70: May | I70: 8 | K70: 37.417 | L70: 0 | M70: 2245 | N70: 466 | O70: 471 | P70: 447 | Q70: 20 | R70: 0.001 | S70: 0 | T70: 0.767 | U70: 0.14 | V70: 0.906 | W70: 0.001 | X70: 116771 | Y70: 2931665.4 | Z70: 0 | AA70: 175899924 | AB70: 225461001 | AC70: 225481832 | AD70: 191038371 | AE70: 34422631 | AF70: 470.799 | AG70: 84.745 | AH70: 367219.16 | AI70: 66100.647 | AJ70: 433319.8 | AK70: 555.544 | AL70: 238 | AM70: 0 | AN70: 0 | AO70: 0 | AP70: 0 | AQ70: 0 | AR70: 0 | AS70: 0 | AT70: 1.696 | AU70: 0.305 | AV70: 1323.043 | AW70: 238.174 | AX70: 1561.216 | AY70: 2.002 | AZ70: 58 | BA70: 81.083 | BB70: 121 | BC70: 4865 | BD70: 4865 | BE70: 4865 | BF70: 0 | BG70: 0 | BH70: 11.205 | BI70: 2.017 | BJ70: 8739.611 | BK70: 1573.129 | BL70: 10312.74 | BM70: 13.222 | BN70: 1320 | BO70: 0 | BP70: 0 | BQ70: 0 | BR70: 0 | BS70: 0 | BT70: 0 | BU70: 0 | BV70: 0 | BW70: 0 | BX70: 0 | BY70: 0 | BZ70: 0 | CA70: 0 | CB70: 70 | CC70: 81.333 | CD70: 126 | CE70: 4880 | CF70: 4880 | CG70: 4880 | CH70: 0 | CI70: 0 | CJ70: 0 | CK70: 0 | CL70: 0 | CM70: 0 | CN70: 0 | CO70: 0
B71: FRAF1 | E71: France Telecom | F71: INBOUND | G71: 2025 | H71: May | X71: 332078 | Y71: 4287739.7 | Z71: 0 | AA71: 257264383 | AB71: 1860236384 | AC71: 1860295090 | AD71: 1548133717 | AE71: 312102667 | AF71: 10358.499 | AG71: 1864.525 | AH71: 8079546.1 | AI71: 1454314.3 | AJ71: 9533860.4 | AK71: 12223.023 | AL71: 1348 | AM71: 0 | AN71: 0 | AO71: 0 | AP71: 0 | AQ71: 0 | AR71: 0 | AS71: 0 | AT71: 7.686 | AU71: 1.383 | AV71: 5995.249 | AW71: 1078.766 | AX71: 7074.016 | AY71: 9.069 | AZ71: 455 | BA71: 852.633 | BB71: 1140 | BC71: 51158 | BD71: 51158 | BE71: 51158 | BF71: 0 | BG71: 0 | BH71: 103.503 | BI71: 18.631 | BJ71: 80731.449 | BK71: 14531.67 | BL71: 95263.119 | BM71: 122.133 | BN71: 8614 | BO71: 0 | BP71: 0 | BQ71: 0 | BR71: 0 | BS71: 0 | BT71: 0 | BU71: 0 | BV71: 0 | BW71: 0 | BX71: 0 | BY71: 0 | BZ71: 0 | CA71: 0 | CB71: 270 | CC71: 528.083 | CD71: 701 | CE71: 31685 | CF71: 31685 | CG71: 31685 | CH71: 0 | CI71: 0 | CJ71: 0 | CK71: 0 | CL71: 0 | CM71: 0 | CN71: 0 | CO71: 0
B72: FRAF2 | E72: Sfr - Cegetel | F72: INBOUND | G72: 2025 | H72: May | X72: 391725 | Y72: 6552493.5 | Z72: 0 | AA72: 393149607 | AB72: 36298661 | AC72: 36307904 | AD72: 28221532 | AE72: 8077129 | AF72: 75.809 | AG72: 13.644 | AH72: 59130.475 | AI72: 10641.928 | AJ72: 69772.404 | AK72: 89.453 | AL72: 2807 | AM72: 0 | AN72: 0 | AO72: 0 | AP72: 0 | AQ72: 0 | AR72: 0 | AS72: 0 | AT72: 20.005 | AU72: 3.601 | AV72: 15604.121 | AW72: 2809.048 | AX72: 18413.17 | AY72: 23.607 | AZ72: 404 | BA72: 817.417 | BB72: 1089 | BC72: 49045 | BD72: 49045 | BE72: 49045 | BF72: 0 | BG72: 0 | BH72: 76.403 | BI72: 13.753 | BJ72: 59593.702 | BK72: 10726.862 | BL72: 70320.564 | BM72: 90.155 | BN72: 24758 | BO72: 0 | BP72: 0 | BQ72: 0 | BR72: 0 | BS72: 0 | BT72: 0 | BU72: 0 | BV72: 0 | BW72: 0 | BX72: 0 | BY72: 0 | BZ72: 0 | CA72: 0 | CB72: 519 | CC72: 678.017 | CD72: 1013 | CE72: 40681 | CF72: 40681 | CG72: 40681 | CH72: 0 | CI72: 0 | CJ72: 0 | CK72: 0 | CL72: 0 | CM72: 0 | CN72: 0 | CO72: 0
B73: FRAF3 | E73: Bouygues Telecom | F73: INBOUND | G73: 2025 | H73: May | I73: 378 | K73: 13564.717 | L73: 0 | M73: 813883 | N73: 279505 | O73: 279678 | P73: 232659 | Q73: 46846 | R73: 1.838 | S73: 0.331 | T73: 1433.277 | U73: 257.978 | V73: 1691.255 | W73: 2.168 | X73: 1197 | Y73: 2299.9 | Z73: 0 | AA73: 137994 | AB73: 4693 | AC73: 5386 | AD73: 1705 | AE73: 2988 | AF73: 0.035 | AG73: 0.006 | AH73: 27.598 | AI73: 5.004 | AJ73: 32.603 | AK73: 0.042 | AL73: 64 | AM73: 0 | AN73: 0 | AO73: 0 | AP73: 0 | AQ73: 0 | AR73: 0 | AS73: 0 | AT73: 1.076 | AU73: 0.194 | AV73: 839.646 | AW73: 151.156 | AX73: 990.802 | AY73: 1.27 | AZ73: 93 | BA73: 128.283 | BB73: 183 | BC73: 7697 | BD73: 7697 | BE73: 7697 | BF73: 0 | BG73: 0 | BH73: 28.66 | BI73: 5.159 | BJ73: 22354.473 | BK73: 4023.809 | BL73: 26378.283 | BM73: 33.819 | BN73: 6148 | BO73: 0 | BP73: 0 | BQ73: 0 | BR73: 0 | BS73: 0 | BT73: 0 | BU73: 0 | BV73: 0 | BW73: 0 | BX73: 0 | BY73: 0 | BZ73: 0 | CA73: 0 | CB73: 127 | CC73: 120.9 | CD73: 208 | CE73: 7254 | CF73: 7254 | CG73: 7254 | CH73: 0 | CI73: 0 | CJ73: 0 | CK73: 0 | CL73: 0 | CM73: 0 | CN73: 0 | CO73: 0
B74: FRAFM | E74: Free Mobile | F74: INBOUND | G74: 2025 | H74: May | I74: 13 | K74: 4.283 | L74: 0 | M74: 257 | N74: 14 | O74: 23 | P74: 5 | Q74: 10 | R74: 0 | S74: 0 | T74: 0.118 | U74: 0.018 | V74: 0.136 | W74: 0 | X74: 4813 | Y74: 205144.72 | Z74: 0 | AA74: 12308683 | AB74: 141412 | AC74: 143393 | AD74: 97035 | AE74: 44377 | AF74: 0.942 | AG74: 0.169 | AH74: 735.015 | AI74: 131.879 | AJ74: 866.893 | AK74: 1.111 | AL74: 3758 | AM74: 0 | AN74: 0 | AO74: 0 | AP74: 0 | AQ74: 0 | AR74: 0 | AS74: 0 | AT74: 94.811 | AU74: 17.065 | AV74: 73951.495 | AW74: 13310.624 | AX74: 87262.12 | AY74: 111.876 | AZ74: 743 | BA74: 1277.5 | BB74: 1753 | BC74: 76650 | BD74: 76650 | BE74: 76650 | BF74: 0 | BG74: 0 | BH74: 295.083 | BI74: 53.115 | BJ74: 230162.22 | BK74: 41429.199 | BL74: 271591.42 | BM74: 348.198 | BN74: 27331 | BO74: 0 | BP74: 0 | BQ74: 0 | BR74: 0 | BS74: 0 | BT74: 0 | BU74: 0 | BV74: 0 | BW74: 0 | BX74: 0 | BY74: 0 | BZ74: 0 | CA74: 0 | CB74: 678 | CC74: 885.617 | CD74: 1332 | CE74: 53137 | CF74: 53137 | CG74: 53137 | CH74: 0 | CI74: 0 | CJ74: 0 | CK74: 0 | CL74: 0 | CM74: 0 | CN74: 0 | CO74: 0
B75: FRARE | E75: Sfr Reunionaise | F75: INBOUND | G75: 2025 | H75: May | AL75: 37 | AM75: 0 | AN75: 0 | AO75: 0 | AP75: 0 | AQ75: 0 | AR75: 0 | AS75: 0 | AT75: 0.264 | AU75: 0.047 | AV75: 205.683 | AW75: 37.027 | AX75: 242.71 | AY75: 0.311 | AZ75: 34 | BA75: 129.667 | BB75: 150 | BC75: 7780 | BD75: 7780 | BE75: 7780 | BF75: 0 | BG75: 0 | BH75: 29.786 | BI75: 5.361 | BJ75: 23232.748 | BK75: 4181.893 | BL75: 27414.641 | BM75: 35.147 | CB75: 9 | CC75: 84.417 | CD75: 90 | CE75: 5065 | CF75: 5065 | CG75: 5065 | CH75: 0 | CI75: 0 | CJ75: 0 | CK75: 0 | CL75: 0 | CM75: 0 | CN75: 0 | CO75: 0
B76: GAB01 | E76: Libertis-Gabon | F76: INBOUND | G76: 2025 | H76: May | X76: 417992 | Y76: 8134838.7 | Z76: 0 | AA76: 488090322 | AB76: 628384 | AC76: 630325 | AD76: 312587 | AE76: 315797 | AF76: 3.106 | AG76: 0.559 | AH76: 2422.774 | AI76: 436.254 | AJ76: 2859.029 | AK76: 3.665 | AL76: 2 | AM76: 0 | AN76: 0 | AO76: 0 | AP76: 0 | AQ76: 0 | AR76: 0 | AS76: 0 | AT76: 0.015 | AU76: 0.003 | AV76: 11.808 | AW76: 2.125 | AX76: 13.932 | AY76: 0.018 | AZ76: 90 | BA76: 96.2 | BB76: 136 | BC76: 5772 | BD76: 5772 | BE76: 5772 | BF76: 0 | BG76: 0 | BH76: 19.643 | BI76: 3.536 | BJ76: 15321.514 | BK76: 2757.873 | BL76: 18079.387 | BM76: 23.179 | BN76: 31214 | BO76: 0 | BP76: 0 | BQ76: 0 | BR76: 0 | BS76: 0 | BT76: 0 | BU76: 0 | BV76: 0 | BW76: 0 | BX76: 0 | BY76: 0 | BZ76: 0 | CA76: 0 | CB76: 232 | CC76: 222.417 | CD76: 342 | CE76: 13345 | CF76: 13345 | CG76: 13345 | CH76: 0 | CI76: 0 | CJ76: 0 | CK76: 0 | CL76: 0 | CM76: 0 | CN76: 0 | CO76: 0
B77: GABCT | E77: Airtel - Gabon | F77: INBOUND | G77: 2025 | H77: May | X77: 7 | Y77: 36.017 | Z77: 0 | AA77: 2161 | AB77: 5554 | AC77: 5558 | AD77: 4129 | AE77: 1425 | AF77: 0.057 | AG77: 0.01 | AH77: 44.364 | AI77: 7.986 | AJ77: 52.349 | AK77: 0.067 | BN77: 20 | BO77: 0 | BP77: 0 | BQ77: 0 | BR77: 0 | BS77: 0 | BT77: 0 | BU77: 0 | BV77: 0 | BW77: 0 | BX77: 0 | BY77: 0 | BZ77: 0 | CA77: 0
B78: GBRJT | E78: Jt (Jersey) | F78: INBOUND | G78: 2025 | H78: May | X78: 1863395 | Y78: 27518522 | Z78: 0 | AA78: 1651111333 | AB78: 5293365 | AC78: 5822639 | AD78: 1662762 | AE78: 3630603 | AF78: 478.059 | AG78: 86.243 | AH78: 372882.16 | AI78: 67268.749 | AJ78: 440150.91 | AK78: 564.302 | AL78: 7 | AM78: 0 | AN78: 0 | AO78: 0 | AP78: 0 | AQ78: 0 | AR78: 0 | AS78: 0 | AT78: 0.294 | AU78: 0.053 | AV78: 229.585 | AW78: 41.326 | AX78: 270.912 | AY78: 0.347 | BN78: 3993 | BO78: 0 | BP78: 0 | BQ78: 0 | BR78: 0 | BS78: 0 | BT78: 0 | BU78: 0 | BV78: 0 | BW78: 0 | BX78: 0 | BY78: 0 | BZ78: 0 | CA78: 0
B79: GBRME | E79: E & E (T-Mble) | F79: INBOUND | G79: 2025 | H79: May | X79: 992 | Y79: 23822.133 | Z79: 0 | AA79: 1429328 | AB79: 19365 | AC79: 19654 | AD79: 7167 | AE79: 12198 | AF79: 0.161 | AG79: 0.029 | AH79: 125.846 | AI79: 22.58 | AJ79: 148.426 | AK79: 0.19 | AL79: 22 | AM79: 0 | AN79: 0 | AO79: 0 | AP79: 0 | AQ79: 0 | AR79: 0 | AS79: 0 | AT79: 0.185 | AU79: 0.033 | AV79: 144.314 | AW79: 25.98 | AX79: 170.294 | AY79: 0.218 | AZ79: 6 | BA79: 12.7 | BB79: 17 | BC79: 762 | BD79: 762 | BE79: 762 | BF79: 0 | BG79: 0 | BH79: 0.33 | BI79: 0.059 | BJ79: 257.135 | BK79: 46.284 | BL79: 303.418 | BM79: 0.389 | BN79: 1215 | BO79: 0 | BP79: 0 | BQ79: 0 | BR79: 0 | BS79: 0 | BT79: 0 | BU79: 0 | BV79: 0 | BW79: 0 | BX79: 0 | BY79: 0 | BZ79: 0 | CA79: 0 | CB79: 22 | CC79: 37.783 | CD79: 47 | CE79: 2267 | CF79: 2267 | CG79: 2267 | CH79: 0 | CI79: 0 | CJ79: 0 | CK79: 0 | CL79: 0 | CM79: 0 | CN79: 0 | CO79: 0
B80: GBROR | E80: Orange, Uk | F80: INBOUND | G80: 2025 | H80: May | BN80: 3 | BO80: 0 | BP80: 0 | BQ80: 0 | BR80: 0 | BS80: 0 | BT80: 0 | BU80: 0 | BV80: 0 | BW80: 0 | BX80: 0 | BY80: 0 | BZ80: 0 | CA80: 0
B81: GBRVF | E81: Vodafone, U.K. | F81: INBOUND | G81: 2025 | H81: May | X81: 49614 | Y81: 488075.67 | Z81: 0 | AA81: 29284540 | AB81: 686640 | AC81: 690677 | AD81: 310416 | AE81: 376224 | AF81: 4.537 | AG81: 0.817 | AH81: 3539.2 | AI81: 637.012 | AJ81: 4176.211 | AK81: 5.354
B82: GEOMA | E82: Magticom,Geo | F82: INBOUND | G82: 2025 | H82: May | BN82: 111 | BO82: 0 | BP82: 0 | BQ82: 0 | BR82: 0 | BS82: 0 | BT82: 0 | BU82: 0 | BV82: 0 | BW82: 0 | BX82: 0 | BY82: 0 | BZ82: 0 | CA82: 0
B83: GHAGT | E83: Vodafone , Ghana | F83: INBOUND | G83: 2025 | H83: May | X83: 74987 | Y83: 115358.1 | Z83: 0 | AA83: 6921486 | AB83: 836453 | AC83: 875824 | AD83: 711730 | AE83: 124723 | AF83: 1.063 | AG83: 0.179 | AH83: 829.383 | AI83: 139.816 | AJ83: 969.199 | AK83: 1.243 | AL83: 16 | AM83: 0 | AN83: 0 | AO83: 0 | AP83: 0 | AQ83: 0 | AR83: 0 | AS83: 0 | AT83: 0.782 | AU83: 0.141 | AV83: 609.779 | AW83: 109.76 | AX83: 719.54 | AY83: 0.922 | AZ83: 34 | BA83: 19.067 | BB83: 37 | BC83: 1144 | BD83: 1144 | BE83: 1144 | BF83: 0 | BG83: 0 | BH83: 2.016 | BI83: 0.363 | BJ83: 1572.324 | BK83: 283.017 | BL83: 1855.341 | BM83: 2.379 | BN83: 17492 | BO83: 0 | BP83: 0 | BQ83: 0 | BR83: 0 | BS83: 0 | BT83: 0 | BU83: 0 | BV83: 0 | BW83: 0 | BX83: 0 | BY83: 0 | BZ83: 0 | CA83: 0 | CB83: 876 | CC83: 3584.9 | CD83: 4053 | CE83: 215094 | CF83: 215094 | CG83: 215094 | CH83: 0 | CI83: 0 | CJ83: 0 | CK83: 0 | CL83: 0 | CM83: 0 | CN83: 0 | CO83: 0
B84: GHAMT | E84: Millicom | F84: INBOUND | G84: 2025 | H84: May | X84: 11354 | Y84: 100378.95 | Z84: 0 | AA84: 6022737 | AB84: 468055 | AC84: 473413 | AD84: 178607 | AE84: 289448 | AF84: 0.56 | AG84: 0.1 | AH84: 436.66 | AI84: 78.089 | AJ84: 514.749 | AK84: 0.66 | AL84: 13 | AM84: 0 | AN84: 0 | AO84: 0 | AP84: 0 | AQ84: 0 | AR84: 0 | AS84: 0 | AT84: 0.636 | AU84: 0.114 | AV84: 495.75 | AW84: 89.231 | AX84: 584.981 | AY84: 0.75 | AZ84: 281 | BA84: 92.283 | BB84: 302 | BC84: 5537 | BD84: 5537 | BE84: 5537 | BF84: 0 | BG84: 0 | BH84: 11.187 | BI84: 2.014 | BJ84: 8725.853 | BK84: 1570.657 | BL84: 10296.511 | BM84: 13.201 | BN84: 7424 | BO84: 0 | BP84: 0 | BQ84: 0 | BR84: 0 | BS84: 0 | BT84: 0 | BU84: 0 | BV84: 0 | BW84: 0 | BX84: 0 | BY84: 0 | BZ84: 0 | CA84: 0 | CB84: 1117 | CC84: 3083.95 | CD84: 3752 | CE84: 185037 | CF84: 185037 | CG84: 185037 | CH84: 0 | CI84: 0 | CJ84: 0 | CK84: 0 | CL84: 0 | CM84: 0 | CN84: 0 | CO84: 0
B85: GHASC | E85: Mtn (Scancom) | F85: INBOUND | G85: 2025 | H85: May | X85: 6194 | Y85: 75253.683 | Z85: 0 | AA85: 4515221 | AB85: 5245814 | AC85: 5247782 | AD85: 4365336 | AE85: 880478 | AF85: 21.549 | AG85: 3.879 | AH85: 16807.839 | AI85: 3025.766 | AJ85: 19833.605 | AK85: 25.428 | AL85: 1243 | AM85: 0 | AN85: 0 | AO85: 0 | AP85: 0 | AQ85: 0 | AR85: 0 | AS85: 0 | AT85: 49.131 | AU85: 8.844 | AV85: 38321.645 | AW85: 6898.206 | AX85: 45219.851 | AY85: 57.975 | AZ85: 462 | BA85: 273.767 | BB85: 572 | BC85: 16426 | BD85: 16426 | BE85: 16426 | BF85: 0 | BG85: 0 | BH85: 33.706 | BI85: 6.067 | BJ85: 26290.418 | BK85: 4732.269 | BL85: 31022.687 | BM85: 39.773 | BN85: 16859 | BO85: 0 | BP85: 0 | BQ85: 0 | BR85: 0 | BS85: 0 | BT85: 0 | BU85: 0 | BV85: 0 | BW85: 0 | BX85: 0 | BY85: 0 | BZ85: 0 | CA85: 0 | CB85: 7730 | CC85: 36378.517 | CD85: 40358 | CE85: 2182711 | CF85: 2182711 | CG85: 2182711 | CH85: 0 | CI85: 0 | CJ85: 0 | CK85: 0 | CL85: 0 | CM85: 0 | CN85: 0 | CO85: 0
B86: GHAZN | E86: Airtel - Ghana | F86: INBOUND | G86: 2025 | H86: May | X86: 462 | Y86: 9700.933 | Z86: 0 | AA86: 582056 | AB86: 7123 | AC86: 7338 | AD86: 1729 | AE86: 5394 | AF86: 0.009 | AG86: 0.002 | AH86: 6.75 | AI86: 1.191 | AJ86: 7.941 | AK86: 0.01 | AZ86: 2 | BA86: 0.233 | BB86: 2 | BC86: 14 | BD86: 14 | BE86: 14 | BF86: 0 | BG86: 0 | BH86: 0.046 | BI86: 0.008 | BJ86: 35.593 | BK86: 6.407 | BL86: 41.999 | BM86: 0.054 | BN86: 48 | BO86: 0 | BP86: 0 | BQ86: 0 | BR86: 0 | BS86: 0 | BT86: 0 | BU86: 0 | BV86: 0 | BW86: 0 | BX86: 0 | BY86: 0 | BZ86: 0 | CA86: 0 | CB86: 18 | CC86: 16 | CD86: 27 | CE86: 960 | CF86: 960 | CG86: 960 | CH86: 0 | CI86: 0 | CJ86: 0 | CK86: 0 | CL86: 0 | CM86: 0 | CN86: 0 | CO86: 0
B87: GINFT | E87: Orange | F87: INBOUND | G87: 2025 | H87: May | X87: 22 | Y87: 661.117 | Z87: 0 | AA87: 39667 | AB87: 4 | AC87: 10 | AD87: 1 | AE87: 2 | AF87: 0 | AG87: 0 | AH87: 0.062 | AI87: 0.009 | AJ87: 0.071 | AK87: 0 | AL87: 71 | AM87: 0 | AN87: 0 | AO87: 0 | AP87: 0 | AQ87: 0 | AR87: 0 | AS87: 0 | AT87: 0.597 | AU87: 0.107 | AV87: 465.741 | AW87: 83.844 | AX87: 549.585 | AY87: 0.705 | AZ87: 103 | BA87: 95.3 | BB87: 148 | BC87: 5718 | BD87: 5718 | BE87: 5718 | BF87: 0 | BG87: 0 | BH87: 26.567 | BI87: 4.782 | BJ87: 20721.681 | BK87: 3729.905 | BL87: 24451.585 | BM87: 31.349 | BN87: 7761 | BO87: 0 | BP87: 0 | BQ87: 0 | BR87: 0 | BS87: 0 | BT87: 0 | BU87: 0 | BV87: 0 | BW87: 0 | BX87: 0 | BY87: 0 | BZ87: 0 | CA87: 0 | CB87: 114 | CC87: 83.8 | CD87: 150 | CE87: 5028 | CF87: 5028 | CG87: 5028 | CH87: 0 | CI87: 0 | CJ87: 0 | CK87: 0 | CL87: 0 | CM87: 0 | CN87: 0 | CO87: 0
B88: GLPFT | E88: Orange Caraibe | F88: INBOUND | G88: 2025 | H88: May | AL88: 7 | AM88: 0 | AN88: 0 | AO88: 0 | AP88: 0 | AQ88: 0 | AR88: 0 | AS88: 0 | AT88: 0.758 | AU88: 0.136 | AV88: 591.459 | AW88: 106.463 | AX88: 697.923 | AY88: 0.895 | AZ88: 10 | BA88: 19.767 | BB88: 26 | BC88: 1186 | BD88: 1186 | BE88: 1560 | BF88: 0 | BG88: 0 | BH88: 35.875 | BI88: 6.458 | BJ88: 27982.474 | BK88: 5036.847 | BL88: 33019.321 | BM88: 42.333 | BN88: 1 | BO88: 0 | BP88: 0 | BQ88: 0 | BR88: 0 | BS88: 0 | BT88: 0 | BU88: 0 | BV88: 0 | BW88: 0 | BX88: 0 | BY88: 0 | BZ88: 0 | CA88: 0 | CB88: 8 | CC88: 12.783 | CD88: 17 | CE88: 767 | CF88: 767 | CG88: 900 | CH88: 0 | CI88: 0 | CJ88: 0 | CK88: 0 | CL88: 0 | CM88: 0 | CN88: 0 | CO88: 0
B89: GMBCM | E89: Comium Gambia | F89: INBOUND | G89: 2025 | H89: May | BN89: 6 | BO89: 0 | BP89: 0 | BQ89: 0 | BR89: 0 | BS89: 0 | BT89: 0 | BU89: 0 | BV89: 0 | BW89: 0 | BX89: 0 | BY89: 0 | BZ89: 0 | CA89: 0
B90: GNBFT | E90: Orange | F90: INBOUND | G90: 2025 | H90: May | BN90: 874 | BO90: 0 | BP90: 0 | BQ90: 0 | BR90: 0 | BS90: 0 | BT90: 0 | BU90: 0 | BV90: 0 | BW90: 0 | BX90: 0 | BY90: 0 | BZ90: 0 | CA90: 0
B91: GNBOC | E91: Mtn Guinea Bissau | F91: INBOUND | G91: 2025 | H91: May | BN91: 123 | BO91: 0 | BP91: 0 | BQ91: 0 | BR91: 0 | BS91: 0 | BT91: 0 | BU91: 0 | BV91: 0 | BW91: 0 | BX91: 0 | BY91: 0 | BZ91: 0 | CA91: 0 | CB91: 3 | CC91: 3.033 | CD91: 5 | CE91: 182 | CF91: 182 | CG91: 182 | CH91: 0 | CI91: 0 | CJ91: 0 | CK91: 0 | CL91: 0 | CM91: 0 | CN91: 0 | CO91: 0
B92: GNQHT | E92: Green Com S.A.(Hits Ge Sa) | F92: INBOUND | G92: 2025 | H92: May | AL92: 24 | AM92: 0 | AN92: 0 | AO92: 0 | AP92: 0 | AQ92: 0 | AR92: 0 | AS92: 0 | AT92: 2.6 | AU92: 0.468 | AV92: 2027.861 | AW92: 365.018 | AX92: 2392.878 | AY92: 3.068 | AZ92: 13 | BA92: 31.2 | BB92: 36 | BC92: 1872 | BD92: 1872 | BE92: 2160 | BF92: 0 | BG92: 0 | BH92: 20.453 | BI92: 3.681 | BJ92: 15952.874 | BK92: 2871.519 | BL92: 18824.392 | BM92: 24.134 | BN92: 2567 | BO92: 0 | BP92: 0 | BQ92: 0 | BR92: 0 | BS92: 0 | BT92: 0 | BU92: 0 | BV92: 0 | BW92: 0 | BX92: 0 | BY92: 0 | BZ92: 0 | CA92: 0 | CB92: 49 | CC92: 50.7 | CD92: 74 | CE92: 3042 | CF92: 3042 | CG92: 3720 | CH92: 0 | CI92: 0 | CJ92: 0 | CK92: 0 | CL92: 0 | CM92: 0 | CN92: 0 | CO92: 0
B93: GRCCO | E93: Cosmote Gsm | F93: INBOUND | G93: 2025 | H93: May | X93: 7278 | Y93: 101871.6 | Z93: 0 | AA93: 6112296 | AB93: 325103 | AC93: 325388 | AD93: 220117 | AE93: 104986 | AF93: 2.138 | AG93: 0.385 | AH93: 1667.583 | AI93: 300.118 | AJ93: 1967.701 | AK93: 2.523 | AZ93: 7 | BA93: 41.65 | BB93: 46 | BC93: 2499 | BD93: 2499 | BE93: 2499 | BF93: 0 | BG93: 0 | BH93: 8.084 | BI93: 1.455 | BJ93: 6305.278 | BK93: 1134.95 | BL93: 7440.228 | BM93: 9.539 | BN93: 348 | BO93: 0 | BP93: 0 | BQ93: 0 | BR93: 0 | BS93: 0 | BT93: 0 | BU93: 0 | BV93: 0 | BW93: 0 | BX93: 0 | BY93: 0 | BZ93: 0 | CA93: 0 | CB93: 9 | CC93: 27.267 | CD93: 32 | CE93: 1636 | CF93: 1636 | CG93: 1636 | CH93: 0 | CI93: 0 | CJ93: 0 | CK93: 0 | CL93: 0 | CM93: 0 | CN93: 0 | CO93: 0
B94: GRCPF | E94: Vodafone Panafo | F94: INBOUND | G94: 2025 | H94: May | X94: 3606 | Y94: 63527.65 | Z94: 0 | AA94: 3811659 | AB94: 102422 | AC94: 102867 | AD94: 55951 | AE94: 46471 | AF94: 0.676 | AG94: 0.122 | AH94: 527.277 | AI94: 94.84 | AJ94: 622.117 | AK94: 0.798 | AL94: 11 | AM94: 0 | AN94: 0 | AO94: 0 | AP94: 0 | AQ94: 0 | AR94: 0 | AS94: 0 | AT94: 0.37 | AU94: 0.067 | AV94: 288.62 | AW94: 51.951 | AX94: 340.571 | AY94: 0.437 | AZ94: 18 | BA94: 48.383 | BB94: 60 | BC94: 2903 | BD94: 2903 | BE94: 2903 | BF94: 0 | BG94: 0 | BH94: 4.122 | BI94: 0.742 | BJ94: 3215.281 | BK94: 578.752 | BL94: 3794.033 | BM94: 4.864 | BN94: 223 | BO94: 0 | BP94: 0 | BQ94: 0 | BR94: 0 | BS94: 0 | BT94: 0 | BU94: 0 | BV94: 0 | BW94: 0 | BX94: 0 | BY94: 0 | BZ94: 0 | CA94: 0 | CB94: 12 | CC94: 52.55 | CD94: 57 | CE94: 3153 | CF94: 3153 | CG94: 3153 | CH94: 0 | CI94: 0 | CJ94: 0 | CK94: 0 | CL94: 0 | CM94: 0 | CN94: 0 | CO94: 0
B95: HKGSM | E95: Smartone | F95: INBOUND | G95: 2025 | H95: May | X95: 2 | Y95: 0.483 | Z95: 0 | AA95: 29 | AB95: 121 | AC95: 150 | AD95: 114 | AE95: 7 | AF95: 1.44 | AG95: 0.259 | AH95: 1123.088 | AI95: 202.156 | AJ95: 1325.244 | AK95: 1.699 | BN95: 1 | BO95: 0 | BP95: 0 | BQ95: 0 | BR95: 0 | BS95: 0 | BT95: 0 | BU95: 0 | BV95: 0 | BW95: 0 | BX95: 0 | BY95: 0 | BZ95: 0 | CA95: 0
B96: HUNH2 | E96: Magyar Telekom | F96: INBOUND | G96: 2025 | H96: May | BN96: 6 | BO96: 0 | BP96: 0 | BQ96: 0 | BR96: 0 | BS96: 0 | BT96: 0 | BU96: 0 | BV96: 0 | BW96: 0 | BX96: 0 | BY96: 0 | BZ96: 0 | CA96: 0
B97: HUNVR | E97: Vodafone Hungary Ltd | F97: INBOUND | G97: 2025 | H97: May | X97: 3965 | Y97: 78221.083 | Z97: 0 | AA97: 4693265 | AB97: 6886 | AC97: 6887 | AD97: 5118 | AE97: 1768 | AF97: 0.045 | AG97: 0.008 | AH97: 35.294 | AI97: 6.352 | AJ97: 41.646 | AK97: 0.053 | AL97: 7 | AM97: 0 | AN97: 0 | AO97: 0 | AP97: 0 | AQ97: 0 | AR97: 0 | AS97: 0 | AT97: 0.235 | AU97: 0.042 | AV97: 183.667 | AW97: 33.06 | AX97: 216.727 | AY97: 0.278 | AZ97: 4 | BA97: 1.05 | BB97: 4 | BC97: 63 | BD97: 63 | BE97: 63 | BF97: 0 | BG97: 0 | BH97: 0.182 | BI97: 0.033 | BJ97: 142.124 | BK97: 25.582 | BL97: 167.706 | BM97: 0.215 | BN97: 106 | BO97: 0 | BP97: 0 | BQ97: 0 | BR97: 0 | BS97: 0 | BT97: 0 | BU97: 0 | BV97: 0 | BW97: 0 | BX97: 0 | BY97: 0 | BZ97: 0 | CA97: 0 | CB97: 8 | CC97: 24.2 | CD97: 28 | CE97: 1452 | CF97: 1452 | CG97: 1452 | CH97: 0 | CI97: 0 | CJ97: 0 | CK97: 0 | CL97: 0 | CM97: 0 | CN97: 0 | CO97: 0
B98: IND10 | E98: Bharti Airtel - Up East | F98: INBOUND | G98: 2025 | H98: May | AL98: 6 | AM98: 0 | AN98: 0 | AO98: 0 | AP98: 0 | AQ98: 0 | AR98: 0 | AS98: 0 | AT98: 0.048 | AU98: 0.009 | AV98: 37.388 | AW98: 6.73 | AX98: 44.118 | AY98: 0.057 | BN98: 1549 | BO98: 0 | BP98: 0 | BQ98: 0 | BR98: 0 | BS98: 0 | BT98: 0 | BU98: 0 | BV98: 0 | BW98: 0 | BX98: 0 | BY98: 0 | BZ98: 0 | CA98: 0 | CB98: 10 | CC98: 1.85 | CD98: 10 | CE98: 111 | CF98: 111 | CG98: 111 | CH98: 0 | CI98: 0 | CJ98: 0 | CK98: 0 | CL98: 0 | CM98: 0 | CN98: 0 | CO98: 0
B99: IND11 | E99: Bharti Airtel - Orissa | F99: INBOUND | G99: 2025 | H99: May | X99: 10755 | Y99: 193056.17 | Z99: 0 | AA99: 11583370 | AB99: 1123373 | AC99: 1123743 | AD99: 1072016 | AE99: 51358 | AF99: 4.43 | AG99: 0.798 | AH99: 3455.308 | AI99: 622.063 | AJ99: 4077.371 | AK99: 5.227 | AL99: 8 | AM99: 0 | AN99: 0 | AO99: 0 | AP99: 0 | AQ99: 0 | AR99: 0 | AS99: 0 | AT99: 0.064 | AU99: 0.012 | AV99: 49.851 | AW99: 8.973 | AX99: 58.824 | AY99: 0.075 | AZ99: 3 | BA99: 2.55 | BB99: 5 | BC99: 153 | BD99: 153 | BE99: 153 | BF99: 0 | BG99: 0 | BH99: 0.041 | BI99: 0.007 | BJ99: 31.782 | BK99: 5.721 | BL99: 37.504 | BM99: 0.048 | BN99: 946 | BO99: 0 | BP99: 0 | BQ99: 0 | BR99: 0 | BS99: 0 | BT99: 0 | BU99: 0 | BV99: 0 | BW99: 0 | BX99: 0 | BY99: 0 | BZ99: 0 | CA99: 0 | CB99: 3 | CC99: 7.917 | CD99: 10 | CE99: 475 | CF99: 475 | CG99: 475 | CH99: 0 | CI99: 0 | CJ99: 0 | CK99: 0 | CL99: 0 | CM99: 0 | CN99: 0 | CO99: 0
B100: IND12 | E100: Bharti Airtel - Bihar | F100: INBOUND | G100: 2025 | H100: May | X100: 42334 | Y100: 763360.55 | Z100: 0 | AA100: 45801633 | AB100: 53981 | AC100: 54766 | AD100: 14979 | AE100: 39002 | AF100: 0.216 | AG100: 0.039 | AH100: 168.501 | AI100: 30.377 | AJ100: 198.878 | AK100: 0.255 | AL100: 29 | AM100: 0 | AN100: 0 | AO100: 0 | AP100: 0 | AQ100: 0 | AR100: 0 | AS100: 0 | AT100: 0.232 | AU100: 0.042 | AV100: 180.709 | AW100: 32.527 | AX100: 213.237 | AY100: 0.273 | AZ100: 6 | BA100: 3.267 | BB100: 6 | BC100: 196 | BD100: 196 | BE100: 196 | BF100: 0 | BG100: 0 | BH100: 0.436 | BI100: 0.078 | BJ100: 339.765 | BK100: 61.158 | BL100: 400.922 | BM100: 0.514 | BN100: 3367 | BO100: 0 | BP100: 0 | BQ100: 0 | BR100: 0 | BS100: 0 | BT100: 0 | BU100: 0 | BV100: 0 | BW100: 0 | BX100: 0 | BY100: 0 | BZ100: 0 | CA100: 0 | CB100: 10 | CC100: 9.267 | CD100: 14 | CE100: 556 | CF100: 556 | CG100: 556 | CH100: 0 | CI100: 0 | CJ100: 0 | CK100: 0 | CL100: 0 | CM100: 0 | CN100: 0 | CO100: 0
B101: IND14 | E101: Bharti Airtel - West Bengal | F101: INBOUND | G101: 2025 | H101: May | AL101: 20 | AM101: 0 | AN101: 0 | AO101: 0 | AP101: 0 | AQ101: 0 | AR101: 0 | AS101: 0 | AT101: 0.16 | AU101: 0.029 | AV101: 124.627 | AW101: 22.433 | AX101: 147.06 | AY101: 0.189 | AZ101: 16 | BA101: 137.483 | BB101: 147 | BC101: 8249 | BD101: 8249 | BE101: 8249 | BF101: 0 | BG101: 0 | BH101: 5.899 | BI101: 1.062 | BJ101: 4601.408 | BK101: 828.253 | BL101: 5429.662 | BM101: 6.961 | BN101: 506 | BO101: 0 | BP101: 0 | BQ101: 0 | BR101: 0 | BS101: 0 | BT101: 0 | BU101: 0 | BV101: 0 | BW101: 0 | BX101: 0 | BY101: 0 | BZ101: 0 | CA101: 0 | CB101: 3 | CC101: 3.05 | CD101: 5 | CE101: 183 | CF101: 183 | CG101: 183 | CH101: 0 | CI101: 0 | CJ101: 0 | CK101: 0 | CL101: 0 | CM101: 0 | CN101: 0 | CO101: 0
B102: INDA1 | E102: Bharti Airtel - Mumbai | F102: INBOUND | G102: 2025 | H102: May | X102: 38285 | Y102: 584386.02 | Z102: 0 | AA102: 35063161 | AB102: 8793665 | AC102: 8795709 | AD102: 7527839 | AE102: 1265827 | AF102: 34.674 | AG102: 6.242 | AH102: 27045.18 | AI102: 4868.644 | AJ102: 31913.824 | AK102: 40.916 | AL102: 23 | AM102: 0 | AN102: 0 | AO102: 0 | AP102: 0 | AQ102: 0 | AR102: 0 | AS102: 0 | AT102: 0.184 | AU102: 0.033 | AV102: 143.321 | AW102: 25.797 | AX102: 169.119 | AY102: 0.217 | AZ102: 30 | BA102: 144.75 | BB102: 162 | BC102: 8685 | BD102: 8685 | BE102: 8685 | BF102: 0 | BG102: 0 | BH102: 5.831 | BI102: 1.05 | BJ102: 4547.825 | BK102: 818.609 | BL102: 5366.434 | BM102: 6.88 | BN102: 2140 | BO102: 0 | BP102: 0 | BQ102: 0 | BR102: 0 | BS102: 0 | BT102: 0 | BU102: 0 | BV102: 0 | BW102: 0 | BX102: 0 | BY102: 0 | BZ102: 0 | CA102: 0 | CB102: 47 | CC102: 85.317 | CD102: 115 | CE102: 5119 | CF102: 5119 | CG102: 5119 | CH102: 0 | CI102: 0 | CJ102: 0 | CK102: 0 | CL102: 0 | CM102: 0 | CN102: 0 | CO102: 0
B103: INDA2 | E103: Bharti Airtel - Mumbai | F103: INBOUND | G103: 2025 | H103: May | X103: 31098 | Y103: 513239.8 | Z103: 0 | AA103: 30794388 | AB103: 7077727 | AC103: 7079533 | AD103: 4982702 | AE103: 2095025 | AF103: 27.908 | AG103: 5.024 | AH103: 21768.254 | AI103: 3918.472 | AJ103: 25686.726 | AK103: 32.932 | AL103: 25 | AM103: 0 | AN103: 0 | AO103: 0 | AP103: 0 | AQ103: 0 | AR103: 0 | AS103: 0 | AT103: 0.2 | AU103: 0.036 | AV103: 155.784 | AW103: 28.041 | AX103: 183.825 | AY103: 0.236 | AZ103: 57 | BA103: 151.95 | BB103: 182 | BC103: 9117 | BD103: 9117 | BE103: 9117 | BF103: 0 | BG103: 0 | BH103: 3.907 | BI103: 0.703 | BJ103: 3047.74 | BK103: 548.593 | BL103: 3596.333 | BM103: 4.611 | BN103: 1634 | BO103: 0 | BP103: 0 | BQ103: 0 | BR103: 0 | BS103: 0 | BT103: 0 | BU103: 0 | BV103: 0 | BW103: 0 | BX103: 0 | BY103: 0 | BZ103: 0 | CA103: 0 | CB103: 82 | CC103: 140.683 | CD103: 186 | CE103: 8441 | CF103: 8441 | CG103: 8441 | CH103: 0 | CI103: 0 | CJ103: 0 | CK103: 0 | CL103: 0 | CM103: 0 | CN103: 0 | CO103: 0
B104: INDA3 | E104: Bharti Airtel - Gujarat | F104: INBOUND | G104: 2025 | H104: May | X104: 34623 | Y104: 622295.4 | Z104: 0 | AA104: 37337724 | AB104: 959108 | AC104: 959763 | AD104: 721305 | AE104: 237802 | AF104: 3.784 | AG104: 0.681 | AH104: 2951.118 | AI104: 531.342 | AJ104: 3482.461 | AK104: 4.465 | AL104: 18 | AM104: 0 | AN104: 0 | AO104: 0 | AP104: 0 | AQ104: 0 | AR104: 0 | AS104: 0 | AT104: 0.144 | AU104: 0.026 | AV104: 112.164 | AW104: 20.189 | AX104: 132.354 | AY104: 0.17 | AZ104: 17 | BA104: 18.433 | BB104: 28 | BC104: 1106 | BD104: 1106 | BE104: 1106 | BF104: 0 | BG104: 0 | BH104: 0.382 | BI104: 0.069 | BJ104: 298.309 | BK104: 53.694 | BL104: 352.003 | BM104: 0.451 | BN104: 2997 | BO104: 0 | BP104: 0 | BQ104: 0 | BR104: 0 | BS104: 0 | BT104: 0 | BU104: 0 | BV104: 0 | BW104: 0 | BX104: 0 | BY104: 0 | BZ104: 0 | CA104: 0 | CB104: 27 | CC104: 20.883 | CD104: 38 | CE104: 1253 | CF104: 1253 | CG104: 1253 | CH104: 0 | CI104: 0 | CJ104: 0 | CK104: 0 | CL104: 0 | CM104: 0 | CN104: 0 | CO104: 0
B105: INDA4 | E105: Bharti Airtel - Tamil Nadu | F105: INBOUND | G105: 2025 | H105: May | X105: 28789 | Y105: 490392.78 | Z105: 0 | AA105: 29423567 | AB105: 17913364 | AC105: 17914293 | AD105: 16581765 | AE105: 1331598 | AF105: 70.62 | AG105: 12.712 | AH105: 55082.883 | AI105: 9914.97 | AJ105: 64997.853 | AK105: 83.331 | AL105: 5 | AM105: 0 | AN105: 0 | AO105: 0 | AP105: 0 | AQ105: 0 | AR105: 0 | AS105: 0 | AT105: 0.04 | AU105: 0.007 | AV105: 31.157 | AW105: 5.608 | AX105: 36.765 | AY105: 0.047 | AZ105: 4 | BA105: 12.933 | BB105: 14 | BC105: 776 | BD105: 776 | BE105: 776 | BF105: 0 | BG105: 0 | BH105: 0.253 | BI105: 0.045 | BJ105: 197.006 | BK105: 35.461 | BL105: 232.466 | BM105: 0.298 | BN105: 1688 | BO105: 0 | BP105: 0 | BQ105: 0 | BR105: 0 | BS105: 0 | BT105: 0 | BU105: 0 | BV105: 0 | BW105: 0 | BX105: 0 | BY105: 0 | BZ105: 0 | CA105: 0 | CB105: 1 | CC105: 1.717 | CD105: 2 | CE105: 103 | CF105: 103 | CG105: 103 | CH105: 0 | CI105: 0 | CJ105: 0 | CK105: 0 | CL105: 0 | CM105: 0 | CN105: 0 | CO105: 0
B106: INDA5 | E106: Bharti Airtel - Haryana | F106: INBOUND | G106: 2025 | H106: May | X106: 7030 | Y106: 102116.35 | Z106: 0 | AA106: 6126981 | AB106: 334064 | AC106: 334339 | AD106: 259943 | AE106: 74122 | AF106: 1.318 | AG106: 0.237 | AH106: 1028.04 | AI106: 185.091 | AJ106: 1213.131 | AK106: 1.555 | AL106: 5 | AM106: 0 | AN106: 0 | AO106: 0 | AP106: 0 | AQ106: 0 | AR106: 0 | AS106: 0 | AT106: 0.04 | AU106: 0.007 | AV106: 31.157 | AW106: 5.608 | AX106: 36.765 | AY106: 0.047 | AZ106: 5 | BA106: 46.55 | BB106: 50 | BC106: 2793 | BD106: 2793 | BE106: 2793 | BF106: 0 | BG106: 0 | BH106: 1.261 | BI106: 0.227 | BJ106: 983.313 | BK106: 176.996 | BL106: 1160.308 | BM106: 1.488 | BN106: 423 | BO106: 0 | BP106: 0 | BQ106: 0 | BR106: 0 | BS106: 0 | BT106: 0 | BU106: 0 | BV106: 0 | BW106: 0 | BX106: 0 | BY106: 0 | BZ106: 0 | CA106: 0 | CB106: 4 | CC106: 4.5 | CD106: 7 | CE106: 270 | CF106: 270 | CG106: 270 | CH106: 0 | CI106: 0 | CJ106: 0 | CK106: 0 | CL106: 0 | CM106: 0 | CN106: 0 | CO106: 0
B107: INDA6 | E107: Bharti Airtel - Up | F107: INBOUND | G107: 2025 | H107: May | X107: 11613 | Y107: 145449.38 | Z107: 0 | AA107: 8726963 | AB107: 7265206 | AC107: 7265468 | AD107: 6438344 | AE107: 826862 | AF107: 28.641 | AG107: 5.155 | AH107: 22339.851 | AI107: 4021.192 | AJ107: 26361.043 | AK107: 33.797 | AL107: 3 | AM107: 0 | AN107: 0 | AO107: 0 | AP107: 0 | AQ107: 0 | AR107: 0 | AS107: 0 | AT107: 0.024 | AU107: 0.004 | AV107: 18.694 | AW107: 3.365 | AX107: 22.059 | AY107: 0.028 | AZ107: 42 | BA107: 83.383 | BB107: 106 | BC107: 5003 | BD107: 5003 | BE107: 5003 | BF107: 0 | BG107: 0 | BH107: 1.959 | BI107: 0.353 | BJ107: 1528.041 | BK107: 275.046 | BL107: 1803.087 | BM107: 2.312 | BN107: 823 | BO107: 0 | BP107: 0 | BQ107: 0 | BR107: 0 | BS107: 0 | BT107: 0 | BU107: 0 | BV107: 0 | BW107: 0 | BX107: 0 | BY107: 0 | BZ107: 0 | CA107: 0 | CB107: 15 | CC107: 59.05 | CD107: 68 | CE107: 3543 | CF107: 3543 | CG107: 3543 | CH107: 0 | CI107: 0 | CJ107: 0 | CK107: 0 | CL107: 0 | CM107: 0 | CN107: 0 | CO107: 0
B108: INDA7 | E108: Bharti Airtel - Kerala | F108: INBOUND | G108: 2025 | H108: May | X108: 26758 | Y108: 447615.55 | Z108: 0 | AA108: 26856933 | AB108: 10130743 | AC108: 10132432 | AD108: 9062450 | AE108: 1068292 | AF108: 39.943 | AG108: 7.19 | AH108: 31155.312 | AI108: 5608.327 | AJ108: 36763.639 | AK108: 47.133 | AL108: 8 | AM108: 0 | AN108: 0 | AO108: 0 | AP108: 0 | AQ108: 0 | AR108: 0 | AS108: 0 | AT108: 0.064 | AU108: 0.012 | AV108: 49.851 | AW108: 8.973 | AX108: 58.824 | AY108: 0.075 | AZ108: 6 | BA108: 24.367 | BB108: 28 | BC108: 1462 | BD108: 1462 | BE108: 1462 | BF108: 0 | BG108: 0 | BH108: 0.854 | BI108: 0.154 | BJ108: 665.818 | BK108: 119.848 | BL108: 785.666 | BM108: 1.007 | BN108: 1246 | BO108: 0 | BP108: 0 | BQ108: 0 | BR108: 0 | BS108: 0 | BT108: 0 | BU108: 0 | BV108: 0 | BW108: 0 | BX108: 0 | BY108: 0 | BZ108: 0 | CA108: 0 | CB108: 1 | CC108: 0.083 | CD108: 1 | CE108: 5 | CF108: 5 | CG108: 5 | CH108: 0 | CI108: 0 | CJ108: 0 | CK108: 0 | CL108: 0 | CM108: 0 | CN108: 0 | CO108: 0
...

Sheet ROAMING OUT
D2: CALL ANALYSIS REPORT
D4: Client: BEN02
D6: Roaming Parnters: ALL
D7: Direction: TAP IN
D8: Record Type: ALL
D10: Currency: XOF
D11: Report Type: Monthly
D12: Month and Year From: May-2025
D13: Month and Year To: May-2025
I18: GPRS | X18: MOC | AZ18: MTC
I19: Others | X19: SMS | AL19: Voice | AZ19: SMS | BN19: Voice
A20: Client | B20: RP Code | E20: Roaming Partner Name | F20: Direction | G20: Year | H20: Month | I20: Total Calls | K20: Duration in min. | L20: Ceil Duration in Min. | M20: Duration in Sec. | N20: Chargeable Units | O20: Charged Units | P20: Data Volume Incoming (KB) | Q20: Data Volume Outgoing (KB) | R20: Charges (SDR) | S20: Tax (SDR) | T20: Charges (XOF) | U20: Tax (XOF) | V20: Total Amount(XOF) | W20: Total Amount(SDR) | X20: Total Calls | Y20: Duration in min. | Z20: Ceil Duration in Min. | AA20: Duration in Sec. | AB20: Chargeable Units | AC20: Charged Units | AD20: Data Volume Incoming (KB) | AE20: Data Volume Outgoing (KB) | AF20: Charges (SDR) | AG20: Tax (SDR) | AH20: Charges (XOF) | AI20: Tax (XOF) | AJ20: Total Amount(XOF) | AK20: Total Amount(SDR) | AL20: Total Calls | AM20: Duration in min. | AN20: Ceil Duration in Min. | AO20: Duration in Sec. | AP20: Chargeable Units | AQ20: Charged Units | AR20: Data Volume Incoming (KB) | AS20: Data Volume Outgoing (KB) | AT20: Charges (SDR) | AU20: Tax (SDR) | AV20: Charges (XOF) | AW20: Tax (XOF) | AX20: Total Amount(XOF) | AY20: Total Amount(SDR) | AZ20: Total Calls | BA20: Duration in min. | BB20: Ceil Duration in Min. | BC20: Duration in Sec. | BD20: Chargeable Units | BE20: Charged Units | BF20: Data Volume Incoming (KB) | BG20: Data Volume Outgoing (KB) | BH20: Charges (SDR) | BI20: Tax (SDR) | BJ20: Charges (XOF) | BK20: Tax (XOF) | BL20: Total Amount(XOF) | BM20: Total Amount(SDR) | BN20: Total Calls | BO20: Duration in min. | BP20: Ceil Duration in Min. | BQ20: Duration in Sec. | BR20: Chargeable Units | BS20: Charged Units | BT20: Data Volume Incoming (KB) | BU20: Data Volume Outgoing (KB) | BV20: Charges (SDR) | BW20: Tax (SDR) | BX20: Charges (XOF) | BY20: Tax (XOF) | BZ20: Total Amount(XOF) | CA20: Total Amount(SDR)
A21: BEN02 | B21: ALBVF | E21: Vodafone Albani | F21: OUTBOUND | G21: 2025 | H21: May | I21: 442 | K21: 1067.9 | L21: 0 | M21: 64074 | N21: 0 | O21: 1 | P21: 0 | Q21: 0 | R21: 0 | S21: 0 | T21: 0 | U21: 0 | V21: 0 | W21: 0
B22: ARETC | E22: Etisalat, Uae | F22: OUTBOUND | G22: 2025 | H22: May | I22: 52548 | K22: 1434520.4 | L22: 0 | M22: 86071223 | N22: 626173 | O22: 1893376 | P22: 368378 | Q22: 257795 | R22: 741.826 | S22: 0 | T22: 578618.58 | U22: 0 | V22: 578618.58 | W22: 741.826 | X22: 400 | Y22: 0 | Z22: 0 | AA22: 0 | AB22: 0 | AC22: 0 | AD22: 0 | AE22: 0 | AF22: 50.56 | AG22: 0 | AH22: 39436.396 | AI22: 0 | AJ22: 39436.396 | AK22: 50.56 | AL22: 17 | AM22: 40.75 | AN22: 49 | AO22: 2445 | AP22: 2445 | AQ22: 3043 | AR22: 0 | AS22: 0 | AT22: 78.878 | AU22: 0 | AV22: 61523.819 | AW22: 0 | AX22: 61523.819 | AY22: 78.878 | AZ22: 5213 | BA22: 0 | BB22: 0 | BC22: 0 | BD22: 0 | BE22: 0 | BF22: 0 | BG22: 0 | BH22: 0 | BI22: 0 | BJ22: 0 | BK22: 0 | BL22: 0 | BM22: 0 | BN22: 59 | BO22: 65.267 | BP22: 101 | BQ22: 3916 | BR22: 3916 | BS22: 6001 | BT22: 0 | BU22: 0 | BV22: 0 | BW22: 0 | BX22: 0 | BY22: 0 | BZ22: 0 | CA22: 0
B23: BELKO | E23: Telnet Group Bvba/Sprl | F23: OUTBOUND | G23: 2025 | H23: May | I23: 565 | K23: 11338.933 | L23: 0 | M23: 680336 | N23: 40214 | O23: 40543 | P23: 19348 | Q23: 20867 | R23: 0.166 | S23: 0 | T23: 129.245 | U23: 0 | V23: 129.245 | W23: 0.166 | BN23: 2 | BO23: 1.55 | BP23: 2 | BQ23: 93 | BR23: 93 | BS23: 120 | BT23: 0 | BU23: 0 | BV23: 0 | BW23: 0 | BX23: 0 | BY23: 0 | BZ23: 0 | CA23: 0
B24: BELMO | E24: Mobistar Gsm | F24: OUTBOUND | G24: 2025 | H24: May | I24: 313 | K24: 3236.217 | L24: 0 | M24: 194173 | N24: 11815 | O24: 11991 | P24: 5885 | Q24: 5930 | R24: 0.079 | S24: 0 | T24: 61.627 | U24: 0 | V24: 61.627 | W24: 0.079 | AZ24: 3 | BA24: 0 | BB24: 0 | BC24: 0 | BD24: 0 | BE24: 0 | BF24: 0 | BG24: 0 | BH24: 0 | BI24: 0 | BJ24: 0 | BK24: 0 | BL24: 0 | BM24: 0 | BN24: 1 | BO24: 0.467 | BP24: 1 | BQ24: 28 | BR24: 28 | BS24: 28 | BT24: 0 | BU24: 0 | BV24: 0 | BW24: 0 | BX24: 0 | BY24: 0 | BZ24: 0 | CA24: 0
B25: BFACT | E25: Orange (Airtel) - Bfaso | F25: OUTBOUND | G25: 2025 | H25: May | I25: 191576 | K25: 6090891.8 | L25: 0 | M25: 365453510 | N25: 172833 | O25: 174058 | P25: 107747 | Q25: 65086 | R25: 1.445 | S25: 0.258 | T25: 1126.917 | U25: 200.981 | V25: 1327.897 | W25: 1.702 | AL25: 35 | AM25: 25.333 | AN25: 52 | AO25: 1520 | AP25: 1520 | AQ25: 3120 | AR25: 0 | AS25: 0 | AT25: 0 | AU25: 0 | AV25: 0 | AW25: 0 | AX25: 0 | AY25: 0 | AZ25: 9 | BA25: 0 | BB25: 0 | BC25: 0 | BD25: 0 | BE25: 0 | BF25: 0 | BG25: 0 | BH25: 0 | BI25: 0 | BJ25: 0 | BK25: 0 | BL25: 0 | BM25: 0
B26: BFAON | E26: Telmob | F26: OUTBOUND | G26: 2025 | H26: May | AL26: 397 | AM26: 300.083 | AN26: 557 | AO26: 18005 | AP26: 18005 | AQ26: 14946 | AR26: 0 | AS26: 0 | AT26: 39.437 | AU26: 7.098 | AV26: 30760.545 | AW26: 5536.383 | AX26: 36296.928 | AY26: 46.535 | AZ26: 324 | BA26: 0 | BB26: 0 | BC26: 0 | BD26: 0 | BE26: 0 | BF26: 0 | BG26: 0 | BH26: 0 | BI26: 0 | BJ26: 0 | BK26: 0 | BL26: 0 | BM26: 0 | BN26: 5134 | BO26: 8279.567 | BP26: 11083 | BQ26: 496774 | BR26: 496774 | BS26: 0 | BT26: 0 | BU26: 0 | BV26: 0 | BW26: 0 | BX26: 0 | BY26: 0 | BZ26: 0 | CA26: 0
B27: BFATL | E27: Telecel - Bfaso | F27: OUTBOUND | G27: 2025 | H27: May | AL27: 24 | AM27: 6.4 | AN27: 26 | AO27: 384 | AP27: 384 | AQ27: 186 | AR27: 0 | AS27: 0 | AT27: 1.04 | AU27: 0.188 | AV27: 811.192 | AW27: 146.638 | AX27: 957.83 | AY27: 1.228 | AZ27: 435 | BA27: 0 | BB27: 0 | BC27: 0 | BD27: 0 | BE27: 0 | BF27: 0 | BG27: 0 | BH27: 0 | BI27: 0 | BJ27: 0 | BK27: 0 | BL27: 0 | BM27: 0 | BN27: 1 | BO27: 0.333 | BP27: 1 | BQ27: 20 | BR27: 20 | BS27: 0 | BT27: 0 | BU27: 0 | BV27: 0 | BW27: 0 | BX27: 0 | BY27: 0 | BZ27: 0 | CA27: 0
B28: CAFAT | E28: Acell-Rca | F28: OUTBOUND | G28: 2025 | H28: May | AL28: 2 | AM28: 2.683 | AN28: 4 | AO28: 161 | AP28: 161 | AQ28: 161 | AR28: 0 | AS28: 0 | AT28: 0.79 | AU28: 0.15 | AV28: 616.067 | AW28: 117.053 | AX28: 733.119 | AY28: 0.94 | AZ28: 688 | BA28: 0 | BB28: 0 | BC28: 0 | BD28: 0 | BE28: 0 | BF28: 0 | BG28: 0 | BH28: 0 | BI28: 0 | BJ28: 0 | BK28: 0 | BL28: 0 | BM28: 0 | BN28: 1 | BO28: 0.2 | BP28: 1 | BQ28: 12 | BR28: 12 | BS28: 12 | BT28: 0 | BU28: 0 | BV28: 0 | BW28: 0 | BX28: 0 | BY28: 0 | BZ28: 0 | CA28: 0
B29: CAFFT | E29: Orange-Hub | F29: OUTBOUND | G29: 2025 | H29: May | AL29: 19 | AM29: 21.2 | AN29: 32 | AO29: 1272 | AP29: 1272 | AQ29: 1272 | AR29: 0 | AS29: 0 | AT29: 5.349 | AU29: 1.016 | AV29: 4171.889 | AW29: 792.667 | AX29: 4964.555 | AY29: 6.365 | AZ29: 798 | BA29: 0 | BB29: 0 | BC29: 0 | BD29: 0 | BE29: 0 | BF29: 0 | BG29: 0 | BH29: 0 | BI29: 0 | BJ29: 0 | BK29: 0 | BL29: 0 | BM29: 0 | BN29: 13 | BO29: 7.817 | BP29: 16 | BQ29: 469 | BR29: 469 | BS29: 469 | BT29: 0 | BU29: 0 | BV29: 0 | BW29: 0 | BX29: 0 | BY29: 0 | BZ29: 0 | CA29: 0
B30: CANBM | E30: Bell Mobility | F30: OUTBOUND | G30: 2025 | H30: May | I30: 2858 | K30: 95445.067 | L30: 0 | M30: 5726704 | N30: 117589 | O30: 118985 | P30: 24187 | Q30: 93403 | R30: 1.456 | S30: 0 | T30: 1135.519 | U30: 0 | V30: 1135.519 | W30: 1.456 | AL30: 71 | AM30: 115.95 | AN30: 149 | AO30: 6957 | AP30: 6957 | AQ30: 6957 | AR30: 0 | AS30: 0 | AT30: 9.747 | AU30: 1.459 | AV30: 7602.548 | AW30: 1138.247 | AX30: 8740.795 | AY30: 11.206 | BN30: 23 | BO30: 29.117 | BP30: 40 | BQ30: 1747 | BR30: 1747 | BS30: 1747 | BT30: 0 | BU30: 0 | BV30: 0 | BW30: 0 | BX30: 0 | BY30: 0 | BZ30: 0 | CA30: 0
B31: CANRW | E31: Rogers - Canada | F31: OUTBOUND | G31: 2025 | H31: May | I31: 1943 | K31: 185859.1 | L31: 0 | M31: 11151546 | N31: 181551 | O31: 182592 | P31: 19675 | Q31: 161876 | R31: 1.316 | S31: 0 | T31: 1026.415 | U31: 0 | V31: 1026.415 | W31: 1.316 | AL31: 93 | AM31: 219.717 | AN31: 267 | AO31: 13183 | AP31: 13183 | AQ31: 16020 | AR31: 0 | AS31: 0 | AT31: 62.696 | AU31: 0.114 | AV31: 48902.534 | AW31: 88.732 | AX31: 48991.266 | AY31: 62.81 | AZ31: 7539 | BA31: 0 | BB31: 0 | BC31: 0 | BD31: 0 | BE31: 0 | BF31: 0 | BG31: 0 | BH31: 0 | BI31: 0 | BJ31: 0 | BK31: 0 | BL31: 0 | BM31: 0 | BN31: 31 | BO31: 49.467 | BP31: 65 | BQ31: 2968 | BR31: 2968 | BS31: 3900 | BT31: 0 | BU31: 0 | BV31: 0.144 | BW31: 0 | BX31: 112.046 | BY31: 0 | BZ31: 112.046 | CA31: 0.144
B32: CANTS | E32: Telus | F32: OUTBOUND | G32: 2025 | H32: May | I32: 2084 | K32: 6088.25 | L32: 0 | M32: 365295 | N32: 19094 | O32: 20176 | P32: 5838 | Q32: 13256 | R32: 0.226 | S32: 0 | T32: 176.185 | U32: 0 | V32: 176.185 | W32: 0.226
B33: CHEDX | E33: Sunrise Communications Ag | F33: OUTBOUND | G33: 2025 | H33: May | I33: 12575 | K33: 742123.42 | L33: 0 | M33: 44527405 | N33: 41431 | O33: 41708 | P33: 8480 | Q33: 32950 | R33: 0.179 | S33: 0 | T33: 139.307 | U33: 0 | V33: 139.307 | W33: 0.179 | AL33: 53 | AM33: 84.533 | AN33: 113 | AO33: 5072 | AP33: 5072 | AQ33: 5072 | AR33: 0 | AS33: 0 | AT33: 22.637 | AU33: 0 | AV33: 17656.913 | AW33: 0 | AX33: 17656.913 | AY33: 22.637 | BN33: 22 | BO33: 23.467 | BP33: 35 | BQ33: 1408 | BR33: 1408 | BS33: 1408 | BT33: 0 | BU33: 0 | BV33: 0 | BW33: 0 | BX33: 0 | BY33: 0 | BZ33: 0 | CA33: 0
B34: CHNCU | E34: China Unicom | F34: OUTBOUND | G34: 2025 | H34: May | AL34: 34 | AM34: 57.367 | AN34: 77 | AO34: 3442 | AP34: 3442 | AQ34: 0 | AR34: 0 | AS34: 0 | AT34: 11.254 | AU34: 0 | AV34: 8777.875 | AW34: 0 | AX34: 8777.875 | AY34: 11.254 | BN34: 59 | BO34: 80.483 | BP34: 115 | BQ34: 4829 | BR34: 4829 | BS34: 0 | BT34: 0 | BU34: 0 | BV34: 0.088 | BW34: 0 | BX34: 68.682 | BY34: 0 | BZ34: 68.682 | CA34: 0.088
B35: CIV02 | E35: Moov(A-Cell) | F35: OUTBOUND | G35: 2025 | H35: May | I35: 856482 | K35: 24354752 | L35: 0 | M35: 1461285099 | N35: 13721464 | O35: 13747162 | P35: 11108396 | Q35: 2613068 | R35: 67.816 | S35: 0 | T35: 52896.286 | U35: 0 | V35: 52896.286 | W35: 67.816 | AL35: 1304 | AM35: 1490.567 | AN35: 2195 | AO35: 89434 | AP35: 89434 | AQ35: 89489 | AR35: 0 | AS35: 0 | AT35: 206.17 | AU35: 0 | AV35: 160810.62 | AW35: 0 | AX35: 160810.62 | AY35: 206.17 | AZ35: 102178 | BA35: 0 | BB35: 0 | BC35: 0 | BD35: 0 | BE35: 0 | BF35: 0 | BG35: 0 | BH35: 0 | BI35: 0 | BJ35: 0 | BK35: 0 | BL35: 0 | BM35: 0 | BN35: 14811 | BO35: 27184.867 | BP35: 35169 | BQ35: 1631092 | BR35: 1631092 | BS35: 1631092 | BT35: 0 | BU35: 0 | BV35: 0 | BW35: 0 | BX35: 0 | BY35: 0 | BZ35: 0 | CA35: 0
B36: CIV03 | E36: Orange-Ivory C | F36: OUTBOUND | G36: 2025 | H36: May | I36: 21618 | K36: 526098.17 | L36: 0 | M36: 31565890 | N36: 180400 | O36: 180988 | P36: 112801 | Q36: 67599 | R36: 1.5 | S36: 0.271 | T36: 1170.136 | U36: 211.035 | V36: 1381.171 | W36: 1.771 | AL36: 18 | AM36: 1.8 | AN36: 19 | AO36: 108 | AP36: 108 | AQ36: 1111 | AR36: 0 | AS36: 0 | AT36: 0.386 | AU36: 0.07 | AV36: 301.256 | AW36: 54.225 | AX36: 355.481 | AY36: 0.456 | AZ36: 339 | BA36: 0 | BB36: 0 | BC36: 0 | BD36: 0 | BE36: 0 | BF36: 0 | BG36: 0 | BH36: 0 | BI36: 0 | BJ36: 0 | BK36: 0 | BL36: 0 | BM36: 0 | BN36: 49 | BO36: 113.217 | BP36: 140 | BQ36: 6793 | BR36: 6793 | BS36: 6793 | BT36: 0 | BU36: 0 | BV36: 0 | BW36: 0 | BX36: 0 | BY36: 0 | BZ36: 0 | CA36: 0
B37: CIVTL | E37: Loteny Telecom | F37: OUTBOUND | G37: 2025 | H37: May | I37: 33823 | K37: 493113.18 | L37: 0 | M37: 29586791 | N37: 9080720 | O37: 9097276 | P37: 4284509 | Q37: 4796211 | R37: 37.354 | S37: 0 | T37: 29135.586 | U37: 0 | V37: 29135.586 | W37: 37.354 | AL37: 1627 | AM37: 1762.75 | AN37: 2675 | AO37: 105765 | AP37: 105765 | AQ37: 105940 | AR37: 0 | AS37: 0 | AT37: 480.957 | AU37: 0 | AV37: 375142.25 | AW37: 0 | AX37: 375142.25 | AY37: 480.957 | BN37: 16824 | BO37: 29017 | BP37: 38235 | BQ37: 1741020 | BR37: 1741020 | BS37: 2294100 | BT37: 0 | BU37: 0 | BV37: 0 | BW37: 0 | BX37: 0 | BY37: 0 | BZ37: 0 | CA37: 0
B38: CMR02 | E38: Orange Cameroun | F38: OUTBOUND | G38: 2025 | H38: May | I38: 70000 | K38: 2287541.8 | L38: 0 | M38: 137252510 | N38: 142638 | O38: 145792 | P38: 25379 | Q38: 117259 | R38: 1.201 | S38: 0 | T38: 937.067 | U38: 0 | V38: 937.067 | W38: 1.201 | X38: 11 | Y38: 0 | Z38: 0 | AA38: 0 | AB38: 0 | AC38: 0 | AD38: 0 | AE38: 0 | AF38: 0.093 | AG38: 0 | AH38: 72.157 | AI38: 0 | AJ38: 72.157 | AK38: 0.093 | AL38: 52 | AM38: 48.383 | AN38: 80 | AO38: 2903 | AP38: 2903 | AQ38: 2903 | AR38: 0 | AS38: 0 | AT38: 15.613 | AU38: 0 | AV38: 12177.836 | AW38: 0 | AX38: 12177.836 | AY38: 15.613 | AZ38: 5680 | BA38: 0 | BB38: 0 | BC38: 0 | BD38: 0 | BE38: 0 | BF38: 0 | BG38: 0 | BH38: 0 | BI38: 0 | BJ38: 0 | BK38: 0 | BL38: 0 | BM38: 0 | BN38: 65 | BO38: 43.917 | BP38: 84 | BQ38: 2635 | BR38: 2635 | BS38: 2635 | BT38: 0 | BU38: 0 | BV38: 0 | BW38: 0 | BX38: 0 | BY38: 0 | BZ38: 0 | CA38: 0
B39: CMRMT | E39: Mtn - Cameroon | F39: OUTBOUND | G39: 2025 | H39: May | I39: 1575 | K39: 40781.567 | L39: 0 | M39: 2446894 | N39: 256408 | O39: 256830 | P39: 11041 | Q39: 245368 | R39: 1.055 | S39: 0 | T39: 822.596 | U39: 0 | V39: 822.596 | W39: 1.055 | AL39: 32 | AM39: 32.2 | AN39: 49 | AO39: 1932 | AP39: 1932 | AQ39: 1995 | AR39: 0 | AS39: 0 | AT39: 8.312 | AU39: 0 | AV39: 6483.602 | AW39: 0 | AX39: 6483.602 | AY39: 8.312 | BN39: 47 | BO39: 38.05 | BP39: 70 | BQ39: 2283 | BR39: 2283 | BS39: 4200 | BT39: 0 | BU39: 0 | BV39: 0 | BW39: 0 | BX39: 0 | BY39: 0 | BZ39: 0 | CA39: 0
B40: CODAC | E40: Africell Rdc Sa. | F40: OUTBOUND | G40: 2025 | H40: May | AZ40: 6 | BA40: 0 | BB40: 0 | BC40: 0 | BD40: 0 | BE40: 0 | BF40: 0 | BG40: 0 | BH40: 0 | BI40: 0 | BJ40: 0 | BK40: 0 | BL40: 0 | BM40: 0
B41: CODFT | E41: Congo China | F41: OUTBOUND | G41: 2025 | H41: May | I41: 14071 | K41: 132921.55 | L41: 0 | M41: 7975293 | N41: 4317 | O41: 4393 | P41: 2563 | Q41: 1754 | R41: 0.032 | S41: 0.008 | T41: 24.773 | U41: 6.248 | V41: 31.02 | W41: 0.04 | AL41: 6 | AM41: 9.867 | AN41: 12 | AO41: 592 | AP41: 592 | AQ41: 592 | AR41: 0 | AS41: 0 | AT41: 2.594 | AU41: 0.674 | AV41: 2023.237 | AW41: 526.042 | AX41: 2549.279 | AY41: 3.268 | AZ41: 4 | BA41: 0 | BB41: 0 | BC41: 0 | BD41: 0 | BE41: 0 | BF41: 0 | BG41: 0 | BH41: 0 | BI41: 0 | BJ41: 0 | BK41: 0 | BL41: 0 | BM41: 0 | BN41: 5 | BO41: 3.583 | BP41: 7 | BQ41: 215 | BR41: 215 | BS41: 215 | BT41: 0 | BU41: 0 | BV41: 0 | BW41: 0 | BX41: 0 | BY41: 0 | BZ41: 0 | CA41: 0
B42: CODVC | E42: Vodacom - Congo | F42: OUTBOUND | G42: 2025 | H42: May | I42: 61693 | K42: 890943.52 | L42: 0 | M42: 53456611 | N42: 65711 | O42: 67162 | P42: 28874 | Q42: 36838 | R42: 0.411 | S42: 0.107 | T42: 320.239 | U42: 83.489 | V42: 403.728 | W42: 0.518
B43: COGCT | E43: Airtel - Congo | F43: OUTBOUND | G43: 2025 | H43: May | I43: 2893 | K43: 120465.45 | L43: 0 | M43: 7227927 | N43: 565248 | O43: 567397 | P43: 277770 | Q43: 287479 | R43: 6.27 | S43: 0 | T43: 4890.719 | U43: 0 | V43: 4890.719 | W43: 6.27 | AL43: 43 | AM43: 42.55 | AN43: 66 | AO43: 2553 | AP43: 2553 | AQ43: 2553 | AR43: 0 | AS43: 0 | AT43: 7.133 | AU43: 0 | AV43: 5563.548 | AW43: 0 | AX43: 5563.548 | AY43: 7.133 | BN43: 51 | BO43: 38.133 | BP43: 72 | BQ43: 2288 | BR43: 2288 | BS43: 2288 | BT43: 0 | BU43: 0 | BV43: 0 | BW43: 0 | BX43: 0 | BY43: 0 | BZ43: 0 | CA43: 0
B44: CPVTM | E44: T Telecomunic | F44: OUTBOUND | G44: 2025 | H44: May | AZ44: 31 | BA44: 0 | BB44: 0 | BC44: 0 | BD44: 0 | BE44: 0 | BF44: 0 | BG44: 0 | BH44: 0 | BI44: 0 | BJ44: 0 | BK44: 0 | BL44: 0 | BM44: 0
B45: CZECM | E45: Vodafone , Czech Republic | F45: OUTBOUND | G45: 2025 | H45: May | AZ45: 2 | BA45: 0 | BB45: 0 | BC45: 0 | BD45: 0 | BE45: 0 | BF45: 0 | BG45: 0 | BH45: 0 | BI45: 0 | BJ45: 0 | BK45: 0 | BL45: 0 | BM45: 0
B46: DEUD1 | E46: T-Mobile,German | F46: OUTBOUND | G46: 2025 | H46: May | I46: 13 | K46: 978.817 | L46: 0 | M46: 58729 | N46: 365 | O46: 371 | P46: 271 | Q46: 94 | R46: 0.002 | S46: 0 | T46: 1.895 | U46: 0 | V46: 1.895 | W46: 0.002 | AL46: 1 | AM46: 0.083 | AN46: 1 | AO46: 5 | AP46: 5 | AQ46: 5 | AR46: 0 | AS46: 0 | AT46: 0.035 | AU46: 0 | AV46: 27.331 | AW46: 0 | AX46: 27.331 | AY46: 0.035 | BN46: 1 | BO46: 1.15 | BP46: 2 | BQ46: 69 | BR46: 69 | BS46: 69 | BT46: 0 | BU46: 0 | BV46: 0 | BW46: 0 | BX46: 0 | BY46: 0 | BZ46: 0 | CA46: 0
B47: DEUD2 | E47: Vodafone German | F47: OUTBOUND | G47: 2025 | H47: May | I47: 287 | K47: 39390.9 | L47: 0 | M47: 2363454 | N47: 21932 | O47: 22101 | P47: 4958 | Q47: 16975 | R47: 0.145 | S47: 0 | T47: 113.304 | U47: 0 | V47: 113.304 | W47: 0.145 | AL47: 13 | AM47: 10.1 | AN47: 17 | AO47: 606 | AP47: 606 | AQ47: 606 | AR47: 0 | AS47: 0 | AT47: 2.489 | AU47: 0 | AV47: 1941.635 | AW47: 0 | AX47: 1941.635 | AY47: 2.489 | BN47: 30 | BO47: 29.917 | BP47: 47 | BQ47: 1795 | BR47: 1795 | BS47: 1795 | BT47: 0 | BU47: 0 | BV47: 0 | BW47: 0 | BX47: 0 | BY47: 0 | BZ47: 0 | CA47: 0
B48: DEUE2 | E48: O2 (Germany) Gm | F48: OUTBOUND | G48: 2025 | H48: May | AL48: 5 | AM48: 9.4 | AN48: 12 | AO48: 564 | AP48: 564 | AQ48: 720 | AR48: 0 | AS48: 0 | AT48: 19.242 | AU48: 0 | AV48: 15008.298 | AW48: 0 | AX48: 15008.298 | AY48: 19.242 | BN48: 4 | BO48: 0.4 | BP48: 4 | BQ48: 24 | BR48: 24 | BS48: 240 | BT48: 0 | BU48: 0 | BV48: 0 | BW48: 0 | BX48: 0 | BY48: 0 | BZ48: 0 | CA48: 0
B49: EGYAR | E49: Orange Egypt | F49: OUTBOUND | G49: 2025 | H49: May | I49: 20 | K49: 681.283 | L49: 0 | M49: 40877 | N49: 524 | O49: 537 | P49: 44 | Q49: 481 | R49: 0.004 | S49: 0 | T49: 3.455 | U49: 0 | V49: 3.455 | W49: 0.004 | AZ49: 19 | BA49: 0 | BB49: 0 | BC49: 0 | BD49: 0 | BE49: 0 | BF49: 0 | BG49: 0 | BH49: 0 | BI49: 0 | BJ49: 0 | BK49: 0 | BL49: 0 | BM49: 0
B50: EGYMS | E50: Vodafone Egypt | F50: OUTBOUND | G50: 2025 | H50: May | I50: 338 | K50: 7037.4 | L50: 0 | M50: 422244 | N50: 38695 | O50: 38784 | P50: 2290 | Q50: 36405 | R50: 0.318 | S50: 0 | T50: 248.123 | U50: 0 | V50: 248.123 | W50: 0.318 | AL50: 5 | AM50: 2.1 | AN50: 5 | AO50: 126 | AP50: 126 | AQ50: 126 | AR50: 0 | AS50: 0 | AT50: 0.177 | AU50: 0 | AV50: 137.739 | AW50: 0 | AX50: 137.739 | AY50: 0.177 | BN50: 2 | BO50: 3.783 | BP50: 4 | BQ50: 227 | BR50: 227 | BS50: 227 | BT50: 0 | BU50: 0 | BV50: 0 | BW50: 0 | BX50: 0 | BY50: 0 | BZ50: 0 | CA50: 0
B51: ESPAT | E51: Vodafone Espana | F51: OUTBOUND | G51: 2025 | H51: May | I51: 315 | K51: 15881.867 | L51: 0 | M51: 952912 | N51: 17747 | O51: 17919 | P51: 2409 | Q51: 15338 | R51: 0.115 | S51: 0 | T51: 89.777 | U51: 0 | V51: 89.777 | W51: 0.115 | AL51: 13 | AM51: 18.9 | AN51: 26 | AO51: 1134 | AP51: 1134 | AQ51: 1134 | AR51: 0 | AS51: 0 | AT51: 4.841 | AU51: 0 | AV51: 3776.097 | AW51: 0 | AX51: 3776.097 | AY51: 4.841 | AZ51: 1440 | BA51: 0 | BB51: 0 | BC51: 0 | BD51: 0 | BE51: 0 | BF51: 0 | BG51: 0 | BH51: 0 | BI51: 0 | BJ51: 0 | BK51: 0 | BL51: 0 | BM51: 0 | BN51: 20 | BO51: 14.733 | BP51: 26 | BQ51: 884 | BR51: 884 | BS51: 884 | BT51: 0 | BU51: 0 | BV51: 0 | BW51: 0 | BX51: 0 | BY51: 0 | BZ51: 0 | CA51: 0
B52: ESPOC | E52: Xfera Moviles | F52: OUTBOUND | G52: 2025 | H52: May | I52: 2 | K52: 30.567 | L52: 0 | M52: 1834 | N52: 17 | O52: 20 | P52: 6 | Q52: 11 | R52: 0.131 | S52: 0 | T52: 102.491 | U52: 0 | V52: 102.491 | W52: 0.131
B53: ESPRT | E53: Orange Spain | F53: OUTBOUND | G53: 2025 | H53: May | AZ53: 40 | BA53: 0 | BB53: 0 | BC53: 0 | BD53: 0 | BE53: 0 | BF53: 0 | BG53: 0 | BH53: 0 | BI53: 0 | BJ53: 0 | BK53: 0 | BL53: 0 | BM53: 0 | BN53: 3 | BO53: 2.65 | BP53: 5 | BQ53: 159 | BR53: 159 | BS53: 202 | BT53: 0 | BU53: 0 | BV53: 0 | BW53: 0 | BX53: 0 | BY53: 0 | BZ53: 0 | CA53: 0
B54: ETH01 | E54: Ethio Telecom | F54: OUTBOUND | G54: 2025 | H54: May | I54: 311 | K54: 5842.767 | L54: 0 | M54: 350566 | N54: 51333 | O54: 51473 | P54: 5080 | Q54: 46252 | R54: 303.376 | S54: 15.169 | T54: 236630.56 | U54: 11831.418 | V54: 248461.98 | W54: 318.544 | AL54: 9 | AM54: 6.167 | AN54: 10 | AO54: 370 | AP54: 370 | AQ54: 600 | AR54: 0 | AS54: 0 | AT54: 17.387 | AU54: 0.869 | AV54: 13561.651 | AW54: 678.055 | AX54: 14239.706 | AY54: 18.256 | AZ54: 378 | BA54: 0 | BB54: 0 | BC54: 0 | BD54: 0 | BE54: 0 | BF54: 0 | BG54: 0 | BH54: 0 | BI54: 0 | BJ54: 0 | BK54: 0 | BL54: 0 | BM54: 0 | BN54: 17 | BO54: 13.217 | BP54: 24 | BQ54: 793 | BR54: 793 | BS54: 1440 | BT54: 0 | BU54: 0 | BV54: 7.795 | BW54: 0.39 | BX54: 6079.796 | BY54: 303.971 | BZ54: 6383.767 | CA54: 8.184
B55: FRAF1 | E55: France Telecom | F55: OUTBOUND | G55: 2025 | H55: May | I55: 11364 | K55: 754968.58 | L55: 0 | M55: 45298115 | N55: 2211515 | O55: 2217664 | P55: 976026 | Q55: 1235488 | R55: 14.58 | S55: 0 | T55: 11372.268 | U55: 0 | V55: 11372.268 | W55: 14.58 | X55: 111 | Y55: 0 | Z55: 0 | AA55: 0 | AB55: 0 | AC55: 0 | AD55: 0 | AE55: 0 | AF55: 0.747 | AG55: 0 | AH55: 582.677 | AI55: 0 | AJ55: 582.677 | AK55: 0.747 | AL55: 724 | AM55: 1152.55 | AN55: 1572 | AO55: 69153 | AP55: 69153 | AQ55: 69603 | AR55: 0 | AS55: 0 | AT55: 295.202 | AU55: 0 | AV55: 230255.14 | AW55: 0 | AX55: 230255.14 | AY55: 295.202 | AZ55: 40965 | BA55: 0 | BB55: 0 | BC55: 0 | BD55: 0 | BE55: 0 | BF55: 0 | BG55: 0 | BH55: 0 | BI55: 0 | BJ55: 0 | BK55: 0 | BL55: 0 | BM55: 0 | BN55: 814 | BO55: 1150.833 | BP55: 1595 | BQ55: 69050 | BR55: 69050 | BS55: 69050 | BT55: 0 | BU55: 0 | BV55: 0 | BW55: 0 | BX55: 0 | BY55: 0 | BZ55: 0 | CA55: 0
B56: FRAF2 | E56: Sfr - Cegetel | F56: OUTBOUND | G56: 2025 | H56: May | I56: 635 | K56: 33390.767 | L56: 0 | M56: 2003446 | N56: 59458 | O56: 59795 | P56: 36606 | Q56: 22852 | R56: 0.136 | S56: 0 | T56: 106.079 | U56: 0 | V56: 106.079 | W56: 0.136 | AL56: 30 | AM56: 66.833 | AN56: 83 | AO56: 4010 | AP56: 4010 | AQ56: 4069 | AR56: 0 | AS56: 0 | AT56: 18.924 | AU56: 0 | AV56: 14760.569 | AW56: 0 | AX56: 14760.569 | AY56: 18.924 | AZ56: 2224 | BA56: 0 | BB56: 0 | BC56: 0 | BD56: 0 | BE56: 0 | BF56: 0 | BG56: 0 | BH56: 0 | BI56: 0 | BJ56: 0 | BK56: 0 | BL56: 0 | BM56: 0 | BN56: 14 | BO56: 20.817 | BP56: 28 | BQ56: 1249 | BR56: 1249 | BS56: 1680 | BT56: 0 | BU56: 0 | BV56: 0 | BW56: 0 | BX56: 0 | BY56: 0 | BZ56: 0 | CA56: 0
B57: FRAF3 | E57: Bouygues Telecom | F57: OUTBOUND | G57: 2025 | H57: May | I57: 7801 | K57: 648557.37 | L57: 0 | M57: 38913442 | N57: 993323 | O57: 996295 | P57: 234212 | Q57: 759111 | R57: 6.543 | S57: 0 | T57: 5103.573 | U57: 0 | V57: 5103.573 | W57: 6.543 | X57: 16 | Y57: 0 | Z57: 0 | AA57: 0 | AB57: 0 | AC57: 0 | AD57: 0 | AE57: 0 | AF57: 0.269 | AG57: 0 | AH57: 209.911 | AI57: 0 | AJ57: 209.911 | AK57: 0.269 | AL57: 589 | AM57: 796.15 | AN57: 1141 | AO57: 47769 | AP57: 47769 | AQ57: 47769 | AR57: 0 | AS57: 0 | AT57: 247.008 | AU57: 0 | AV57: 192664.63 | AW57: 0 | AX57: 192664.63 | AY57: 247.008 | AZ57: 35628 | BA57: 0 | BB57: 0 | BC57: 0 | BD57: 0 | BE57: 0 | BF57: 0 | BG57: 0 | BH57: 0 | BI57: 0 | BJ57: 0 | BK57: 0 | BL57: 0 | BM57: 0 | BN57: 595 | BO57: 617.3 | BP57: 958 | BQ57: 37038 | BR57: 37038 | BS57: 57480 | BT57: 0 | BU57: 0 | BV57: 0 | BW57: 0 | BX57: 0 | BY57: 0 | BZ57: 0 | CA57: 0
B58: FRAFM | E58: Free Mobile | F58: OUTBOUND | G58: 2025 | H58: May | I58: 4041 | K58: 149230.15 | L58: 0 | M58: 8953809 | N58: 723409 | O58: 725572 | P58: 319398 | Q58: 404011 | R58: 4.768 | S58: 0 | T58: 3718.675 | U58: 0 | V58: 3718.675 | W58: 4.768 | AL58: 218 | AM58: 322.05 | AN58: 456 | AO58: 19323 | AP58: 19323 | AQ58: 19362 | AR58: 0 | AS58: 0 | AT58: 106.231 | AU58: 0 | AV58: 82858.94 | AW58: 0 | AX58: 82858.94 | AY58: 106.231 | AZ58: 11154 | BA58: 0 | BB58: 0 | BC58: 0 | BD58: 0 | BE58: 0 | BF58: 0 | BG58: 0 | BH58: 0 | BI58: 0 | BJ58: 0 | BK58: 0 | BL58: 0 | BM58: 0 | BN58: 255 | BO58: 297.15 | BP58: 441 | BQ58: 17829 | BR58: 17829 | BS58: 17829 | BT58: 0 | BU58: 0 | BV58: 0 | BW58: 0 | BX58: 0 | BY58: 0 | BZ58: 0 | CA58: 0
B59: GAB01 | E59: Libertis-Gabon | F59: OUTBOUND | G59: 2025 | H59: May | I59: 244653 | K59: 13364285 | L59: 0 | M59: 801857103 | N59: 359357 | O59: 364035 | P59: 90531 | Q59: 268826 | R59: 1.806 | S59: 0.318 | T59: 1408.463 | U59: 247.959 | V59: 1656.422 | W59: 2.124 | AL59: 242 | AM59: 237.15 | AN59: 373 | AO59: 14229 | AP59: 14229 | AQ59: 14153 | AR59: 0 | AS59: 0 | AT59: 58.459 | AU59: 10.523 | AV59: 45597.81 | AW59: 8207.614 | AX59: 53805.424 | AY59: 68.982 | AZ59: 29613 | BA59: 0 | BB59: 0 | BC59: 0 | BD59: 0 | BE59: 0 | BF59: 0 | BG59: 0 | BH59: 0 | BI59: 0 | BJ59: 0 | BK59: 0 | BL59: 0 | BM59: 0 | BN59: 213 | BO59: 214.467 | BP59: 346 | BQ59: 12868 | BR59: 12868 | BS59: 0 | BT59: 0 | BU59: 0 | BV59: 0 | BW59: 0 | BX59: 0 | BY59: 0 | BZ59: 0 | CA59: 0
B60: GBRVF | E60: Vodafone, U.K. | F60: OUTBOUND | G60: 2025 | H60: May | I60: 73 | K60: 5253.617 | L60: 0 | M60: 315217 | N60: 5781 | O60: 5822 | P60: 3019 | Q60: 2761 | R60: 0.038 | S60: 0 | T60: 29.99 | U60: 0 | V60: 29.99 | W60: 0.038
B61: GHAGT | E61: Vodafone , Ghana | F61: OUTBOUND | G61: 2025 | H61: May | I61: 96270 | K61: 3681530.1 | L61: 0 | M61: 220891808 | N61: 10305303 | O61: 10312683 | P61: 8495005 | Q61: 1810298 | R61: 9.06 | S61: 2.022 | T61: 7066.728 | U61: 1577.144 | V61: 8643.871 | W61: 11.082 | AL61: 954 | AM61: 727.717 | AN61: 1346 | AO61: 43663 | AP61: 43663 | AQ61: 43601 | AR61: 0 | AS61: 0 | AT61: 50.783 | AU61: 12.05 | AV61: 39610.334 | AW61: 9398.904 | AX61: 49009.237 | AY61: 62.833 | AZ61: 15297 | BA61: 0 | BB61: 0 | BC61: 0 | BD61: 0 | BE61: 0 | BF61: 0 | BG61: 0 | BH61: 0 | BI61: 0 | BJ61: 0 | BK61: 0 | BL61: 0 | BM61: 0 | BN61: 6795 | BO61: 12185.35 | BP61: 15845 | BQ61: 731121 | BR61: 731121 | BS61: 731121 | BT61: 0 | BU61: 0 | BV61: 0 | BW61: 0 | BX61: 0 | BY61: 0 | BZ61: 0 | CA61: 0
B62: GHAMT | E62: Millicom | F62: OUTBOUND | G62: 2025 | H62: May | I62: 25140 | K62: 375407.77 | L62: 0 | M62: 22524466 | N62: 20624238 | O62: 20637873 | P62: 14498064 | Q62: 6126174 | R62: 17.581 | S62: 4.857 | T62: 13713.039 | U62: 3788.421 | V62: 17501.46 | W62: 22.438 | AL62: 1546 | AM62: 965.6 | AN62: 2052 | AO62: 57936 | AP62: 57936 | AQ62: 59363 | AR62: 0 | AS62: 0 | AT62: 65.972 | AU62: 18.615 | AV62: 51457.632 | AW62: 14519.551 | AX62: 65977.183 | AY62: 84.587 | AZ62: 50235 | BA62: 0 | BB62: 0 | BC62: 0 | BD62: 0 | BE62: 0 | BF62: 0 | BG62: 0 | BH62: 0 | BI62: 0 | BJ62: 0 | BK62: 0 | BL62: 0 | BM62: 0 | BN62: 13889 | BO62: 24456.95 | BP62: 31910 | BQ62: 1467417 | BR62: 1467417 | BS62: 1914600 | BT62: 0 | BU62: 0 | BV62: 0 | BW62: 0 | BX62: 0 | BY62: 0 | BZ62: 0 | CA62: 0
B63: GHASC | E63: Mtn (Scancom) | F63: OUTBOUND | G63: 2025 | H63: May | I63: 118665 | K63: 1399824.1 | L63: 0 | M63: 83989444 | N63: 79548184 | O63: 79576537 | P63: 61517711 | Q63: 18030473 | R63: 308.025 | S63: 85.163 | T63: 240257.38 | U63: 66426.786 | V63: 306684.16 | W63: 393.189 | X63: 1 | Y63: 0 | Z63: 0 | AA63: 0 | AB63: 0 | AC63: 0 | AD63: 0 | AE63: 0 | AF63: 0.037 | AG63: 0.01 | AH63: 29.077 | AI63: 8.04 | AJ63: 37.117 | AK63: 0.048 | AL63: 3175 | AM63: 2218.783 | AN63: 4331 | AO63: 133127 | AP63: 133127 | AQ63: 133215 | AR63: 0 | AS63: 0 | AT63: 489.086 | AU63: 135.232 | AV63: 381483.25 | AW63: 105480.15 | AX63: 486963.39 | AY63: 624.318 | BN63: 28194 | BO63: 50658.133 | BP63: 65859 | BQ63: 3039488 | BR63: 3039488 | BS63: 3039488 | BT63: 0 | BU63: 0 | BV63: 0 | BW63: 0 | BX63: 0 | BY63: 0 | BZ63: 0 | CA63: 0
B64: GINAG | E64: Areeba | F64: OUTBOUND | G64: 2025 | H64: May | I64: 470 | K64: 20606.433 | L64: 0 | M64: 1236386 | N64: 2086 | O64: 2220 | P64: 162 | Q64: 1924 | R64: 0.923 | S64: 0.166 | T64: 720.118 | U64: 129.65 | V64: 849.769 | W64: 1.089 | X64: 924 | Y64: 0 | Z64: 0 | AA64: 0 | AB64: 0 | AC64: 0 | AD64: 0 | AE64: 0 | AF64: 122.533 | AG64: 22.056 | AH64: 95575.14 | AI64: 17203.41 | AJ64: 112778.55 | AK64: 144.589 | AL64: 24 | AM64: 18.033 | AN64: 33 | AO64: 1082 | AP64: 1082 | AQ64: 1082 | AR64: 0 | AS64: 0 | AT64: 10.523 | AU64: 1.894 | AV64: 8207.942 | AW64: 1477.43 | AX64: 9685.372 | AY64: 12.417 | BN64: 63 | BO64: 66.333 | BP64: 103 | BQ64: 3980 | BR64: 3980 | BS64: 6180 | BT64: 0 | BU64: 0 | BV64: 0 | BW64: 0 | BX64: 0 | BY64: 0 | BZ64: 0 | CA64: 0
B65: GINFT | E65: Orange | F65: OUTBOUND | G65: 2025 | H65: May | I65: 3157 | K65: 60132.15 | L65: 0 | M65: 3607929 | N65: 121313 | O65: 121996 | P65: 97720 | Q65: 23593 | R65: 1.002 | S65: 0.179 | T65: 781.856 | U65: 139.954 | V65: 921.81 | W65: 1.182 | AL65: 5 | AM65: 1.983 | AN65: 5 | AO65: 119 | AP65: 119 | AQ65: 119 | AR65: 0 | AS65: 0 | AT65: 0.05 | AU65: 0.009 | AV65: 39.023 | AW65: 7.028 | AX65: 46.051 | AY65: 0.059 | AZ65: 5 | BA65: 0 | BB65: 0 | BC65: 0 | BD65: 0 | BE65: 0 | BF65: 0 | BG65: 0 | BH65: 0 | BI65: 0 | BJ65: 0 | BK65: 0 | BL65: 0 | BM65: 0 | BN65: 5 | BO65: 15.15 | BP65: 18 | BQ65: 909 | BR65: 909 | BS65: 909 | BT65: 0 | BU65: 0 | BV65: 0 | BW65: 0 | BX65: 0 | BY65: 0 | BZ65: 0 | CA65: 0
B66: GLPFT | E66: Orange Caraibe | F66: OUTBOUND | G66: 2025 | H66: May | I66: 1 | K66: 1.117 | L66: 0 | M66: 67 | N66: 47 | O66: 50 | P66: 1 | Q66: 46 | R66: 0.411 | S66: 0 | T66: 320.288 | U66: 0 | V66: 320.288 | W66: 0.411
B67: GMBQC | E67: Qcell Gambia | F67: OUTBOUND | G67: 2025 | H67: May | I67: 426 | K67: 10741.95 | L67: 0 | M67: 644517 | N67: 57290 | O67: 57511 | P67: 35074 | Q67: 22216 | R67: 0.234 | S67: 0 | T67: 182.612 | U67: 0 | V67: 182.612 | W67: 0.234 | AL67: 9 | AM67: 6.75 | AN67: 12 | AO67: 405 | AP67: 405 | AQ67: 405 | AR67: 0 | AS67: 0 | AT67: 2.451 | AU67: 0 | AV67: 1912.088 | AW67: 0 | AX67: 1912.088 | AY67: 2.451 | BN67: 5 | BO67: 3.5 | BP67: 6 | BQ67: 210 | BR67: 210 | BS67: 360 | BT67: 0 | BU67: 0 | BV67: 0 | BW67: 0 | BX67: 0 | BY67: 0 | BZ67: 0 | CA67: 0
B68: GNBOC | E68: Mtn Guinea Bissau | F68: OUTBOUND | G68: 2025 | H68: May | I68: 29 | K68: 156 | L68: 0 | M68: 9360 | N68: 33954 | O68: 34001 | P68: 27121 | Q68: 6833 | R68: 186.384 | S68: 35.413 | T68: 145378.03 | U68: 27622.169 | V68: 173000.2 | W68: 221.797 | X68: 1 | Y68: 0 | Z68: 0 | AA68: 0 | AB68: 0 | AC68: 0 | AD68: 0 | AE68: 0 | AF68: 0.161 | AG68: 0.031 | AH68: 125.501 | AI68: 23.868 | AJ68: 149.368 | AK68: 0.192 | AZ68: 6 | BA68: 0 | BB68: 0 | BC68: 0 | BD68: 0 | BE68: 0 | BF68: 0 | BG68: 0 | BH68: 0 | BI68: 0 | BJ68: 0 | BK68: 0 | BL68: 0 | BM68: 0 | BN68: 8 | BO68: 7.133 | BP68: 11 | BQ68: 428 | BR68: 428 | BS68: 660 | BT68: 0 | BU68: 0 | BV68: 0 | BW68: 0 | BX68: 0 | BY68: 0 | BZ68: 0 | CA68: 0
B69: GNQHT | E69: Green Com S.A.(Hits Ge Sa) | F69: OUTBOUND | G69: 2025 | H69: May | I69: 734 | K69: 7411.267 | L69: 0 | M69: 444676 | N69: 18669 | O69: 21850 | P69: 232 | Q69: 18437 | R69: 18.041 | S69: 2.703 | T69: 14071.563 | U69: 2108.279 | V69: 16179.842 | W69: 20.744 | AL69: 6 | AM69: 3.95 | AN69: 6 | AO69: 237 | AP69: 237 | AQ69: 360 | AR69: 0 | AS69: 0 | AT69: 4.619 | AU69: 0.693 | AV69: 3603.001 | AW69: 540.441 | AX69: 4143.442 | AY69: 5.312 | AZ69: 4288 | BA69: 0 | BB69: 0 | BC69: 0 | BD69: 0 | BE69: 0 | BF69: 0 | BG69: 0 | BH69: 0 | BI69: 0 | BJ69: 0 | BK69: 0 | BL69: 0 | BM69: 0 | BN69: 5 | BO69: 2.817 | BP69: 5 | BQ69: 169 | BR69: 169 | BS69: 300 | BT69: 0 | BU69: 0 | BV69: 0 | BW69: 0 | BX69: 0 | BY69: 0 | BZ69: 0 | CA69: 0
B70: GRCCO | E70: Cosmote Gsm | F70: OUTBOUND | G70: 2025 | H70: May | I70: 2 | K70: 82.383 | L70: 0 | M70: 4943 | N70: 10 | O70: 0 | P70: 0 | Q70: 10 | R70: 0 | S70: 0 | T70: 0.055 | U70: 0 | V70: 0.055 | W70: 0 | AL70: 1 | AM70: 0.667 | AN70: 1 | AO70: 40 | AP70: 40 | AQ70: 0 | AR70: 0 | AS70: 0 | AT70: 0.241 | AU70: 0 | AV70: 188.04 | AW70: 0 | AX70: 188.04 | AY70: 0.241 | AZ70: 171 | BA70: 0 | BB70: 0 | BC70: 0 | BD70: 0 | BE70: 0 | BF70: 0 | BG70: 0 | BH70: 0 | BI70: 0 | BJ70: 0 | BK70: 0 | BL70: 0 | BM70: 0 | BN70: 5 | BO70: 11.067 | BP70: 14 | BQ70: 664 | BR70: 664 | BS70: 0 | BT70: 0 | BU70: 0 | BV70: 0 | BW70: 0 | BX70: 0 | BY70: 0 | BZ70: 0 | CA70: 0
B71: GRCPF | E71: Vodafone Panafo | F71: OUTBOUND | G71: 2025 | H71: May | I71: 26 | K71: 340.05 | L71: 0 | M71: 20403 | N71: 0 | O71: 0 | P71: 0 | Q71: 0 | R71: 0 | S71: 0 | T71: 0 | U71: 0 | V71: 0 | W71: 0
B72: HUNVR | E72: Vodafone Hungary Ltd | F72: OUTBOUND | G72: 2025 | H72: May | I72: 89 | K72: 5254.4 | L72: 0 | M72: 315264 | N72: 1203 | O72: 1259 | P72: 243 | Q72: 961 | R72: 0.008 | S72: 0 | T72: 5.881 | U72: 0 | V72: 5.881 | W72: 0.008 | AZ72: 6 | BA72: 0 | BB72: 0 | BC72: 0 | BD72: 0 | BE72: 0 | BF72: 0 | BG72: 0 | BH72: 0 | BI72: 0 | BJ72: 0 | BK72: 0 | BL72: 0 | BM72: 0
B73: INDA1 | E73: Bharti Airtel - Mumbai | F73: OUTBOUND | G73: 2025 | H73: May | I73: 2 | K73: 77.317 | L73: 0 | M73: 4639 | N73: 589 | O73: 590 | P73: 1 | Q73: 588 | R73: 0.002 | S73: 0 | T73: 1.685 | U73: 0 | V73: 1.685 | W73: 0.002 | AL73: 1 | AM73: 0.45 | AN73: 1 | AO73: 27 | AP73: 27 | AQ73: 27 | AR73: 0 | AS73: 0 | AT73: 0.09 | AU73: 0 | AV73: 70.215 | AW73: 0 | AX73: 70.215 | AY73: 0.09 | BN73: 11 | BO73: 15 | BP73: 23 | BQ73: 900 | BR73: 900 | BS73: 900 | BT73: 0 | BU73: 0 | BV73: 0 | BW73: 0 | BX73: 0 | BY73: 0 | BZ73: 0 | CA73: 0
B74: INDA3 | E74: Bharti Airtel - Gujarat | F74: OUTBOUND | G74: 2025 | H74: May | X74: 1 | Y74: 0 | Z74: 0 | AA74: 0 | AB74: 0 | AC74: 0 | AD74: 0 | AE74: 0 | AF74: 0.007 | AG74: 0 | AH74: 5.585 | AI74: 0 | AJ74: 5.585 | AK74: 0.007 | BN74: 2 | BO74: 0.283 | BP74: 2 | BQ74: 17 | BR74: 17 | BS74: 17 | BT74: 0 | BU74: 0 | BV74: 0 | BW74: 0 | BX74: 0 | BY74: 0 | BZ74: 0 | CA74: 0
B75: INDA7 | E75: Bharti Airtel - Kerala | F75: OUTBOUND | G75: 2025 | H75: May | AL75: 2 | AM75: 2.167 | AN75: 3 | AO75: 130 | AP75: 130 | AQ75: 130 | AR75: 0 | AS75: 0 | AT75: 0.031 | AU75: 0 | AV75: 24.149 | AW75: 0 | AX75: 24.149 | AY75: 0.031 | BN75: 1 | BO75: 0.05 | BP75: 1 | BQ75: 3 | BR75: 3 | BS75: 3 | BT75: 0 | BU75: 0 | BV75: 0 | BW75: 0 | BX75: 0 | BY75: 0 | BZ75: 0 | CA75: 0
B76: INDA9 | E76: Bharti Airtel - Punjab | F76: OUTBOUND | G76: 2025 | H76: May | AL76: 3 | AM76: 0.15 | AN76: 3 | AO76: 9 | AP76: 9 | AQ76: 9 | AR76: 0 | AS76: 0 | AT76: 0.048 | AU76: 0 | AV76: 37.596 | AW76: 0 | AX76: 37.596 | AY76: 0.048 | BN76: 6 | BO76: 3.067 | BP76: 7 | BQ76: 184 | BR76: 184 | BS76: 184 | BT76: 0 | BU76: 0 | BV76: 0 | BW76: 0 | BX76: 0 | BY76: 0 | BZ76: 0 | CA76: 0
B77: INDAT | E77: Bharti Airtel - Delhi | F77: OUTBOUND | G77: 2025 | H77: May | I77: 26 | K77: 1424.75 | L77: 0 | M77: 85485 | N77: 58254 | O77: 58273 | P77: 34574 | Q77: 23681 | R77: 0.206 | S77: 0 | T77: 160.6 | U77: 0 | V77: 160.6 | W77: 0.206 | AL77: 23 | AM77: 22.067 | AN77: 34 | AO77: 1324 | AP77: 1324 | AQ77: 1324 | AR77: 0 | AS77: 0 | AT77: 3.586 | AU77: 0 | AV77: 2796.716 | AW77: 0 | AX77: 2796.716 | AY77: 3.586 | BN77: 15 | BO77: 8.45 | BP77: 17 | BQ77: 507 | BR77: 507 | BS77: 507 | BT77: 0 | BU77: 0 | BV77: 0 | BW77: 0 | BX77: 0 | BY77: 0 | BZ77: 0 | CA77: 0
B78: INDJB | E78: Bharti Airtel - Karnataka | F78: OUTBOUND | G78: 2025 | H78: May | I78: 1 | K78: 62.5 | L78: 0 | M78: 3750 | N78: 179 | O78: 179 | P78: 1 | Q78: 177 | R78: 0.001 | S78: 0 | T78: 0.468 | U78: 0 | V78: 0.468 | W78: 0.001 | BN78: 2 | BO78: 0.283 | BP78: 2 | BQ78: 17 | BR78: 17 | BS78: 17 | BT78: 0 | BU78: 0 | BV78: 0 | BW78: 0 | BX78: 0 | BY78: 0 | BZ78: 0 | CA78: 0
B79: INDJH | E79: Bharti Airtel - Ap | F79: OUTBOUND | G79: 2025 | H79: May | X79: 1 | Y79: 0 | Z79: 0 | AA79: 0 | AB79: 0 | AC79: 0 | AD79: 0 | AE79: 0 | AF79: 0.007 | AG79: 0 | AH79: 5.585 | AI79: 0 | AJ79: 5.585 | AK79: 0.007
B80: INDMT | E80: Bharti Airtel - Kolkata | F80: OUTBOUND | G80: 2025 | H80: May | I80: 1 | K80: 0.1 | L80: 0 | M80: 6 | N80: 1 | O80: 1 | P80: 0 | Q80: 1 | R80: 0 | S80: 0 | T80: 0 | U80: 0 | V80: 0 | W80: 0 | AL80: 1 | AM80: 3 | AN80: 3 | AO80: 180 | AP80: 180 | AQ80: 180 | AR80: 0 | AS80: 0 | AT80: 0.043 | AU80: 0 | AV80: 33.493 | AW80: 0 | AX80: 33.493 | AY80: 0.043 | BN80: 1 | BO80: 0.35 | BP80: 1 | BQ80: 21 | BR80: 21 | BS80: 21 | BT80: 0 | BU80: 0 | BV80: 0 | BW80: 0 | BX80: 0 | BY80: 0 | BZ80: 0 | CA80: 0
B81: INDSC | E81: Bharti Airtel - Chennai | F81: OUTBOUND | G81: 2025 | H81: May | BN81: 6 | BO81: 1.8 | BP81: 6 | BQ81: 108 | BR81: 108 | BS81: 108 | BT81: 0 | BU81: 0 | BV81: 0 | BW81: 0 | BX81: 0 | BY81: 0 | BZ81: 0 | CA81: 0
B82: IRLEC | E82: Vodafone-Irelnd | F82: OUTBOUND | G82: 2025 | H82: May | I82: 545 | K82: 29820.5 | L82: 0 | M82: 1789230 | N82: 283 | O82: 302 | P82: 135 | Q82: 148 | R82: 0.002 | S82: 0 | T82: 1.568 | U82: 0 | V82: 1.568 | W82: 0.002 | AZ82: 1 | BA82: 0 | BB82: 0 | BC82: 0 | BD82: 0 | BE82: 0 | BF82: 0 | BG82: 0 | BH82: 0 | BI82: 0 | BJ82: 0 | BK82: 0 | BL82: 0 | BM82: 0
B83: ISLFT | E83: Nova | F83: OUTBOUND | G83: 2025 | H83: May | I83: 1 | K83: 0 | L83: 0 | M83: 0 | N83: 0 | O83: 0 | P83: 0 | Q83: 0 | R83: 0 | S83: 0 | T83: 0 | U83: 0 | V83: 0 | W83: 0
B84: ISRPL | E84: Pelephone | F84: OUTBOUND | G84: 2025 | H84: May | I84: 1001 | K84: 7156.567 | L84: 0 | M84: 429394 | N84: 26096 | O84: 26622 | P84: 15652 | Q84: 10444 | R84: 0.106 | S84: 0.019 | T84: 82.788 | U84: 15.069 | V84: 97.858 | W84: 0.125
B85: ITAFM | E85: Iliad Italia | F85: OUTBOUND | G85: 2025 | H85: May | I85: 341 | K85: 6969.65 | L85: 0 | M85: 418179 | N85: 23822 | O85: 23999 | P85: 1890 | Q85: 21932 | R85: 0.158 | S85: 0 | T85: 123.169 | U85: 0 | V85: 123.169 | W85: 0.158 | AL85: 5 | AM85: 6.5 | AN85: 10 | AO85: 390 | AP85: 390 | AQ85: 390 | AR85: 0 | AS85: 0 | AT85: 2.409 | AU85: 0 | AV85: 1879.328 | AW85: 0 | AX85: 1879.328 | AY85: 2.409 | AZ85: 6089 | BA85: 0 | BB85: 0 | BC85: 0 | BD85: 0 | BE85: 0 | BF85: 0 | BG85: 0 | BH85: 0 | BI85: 0 | BJ85: 0 | BK85: 0 | BL85: 0 | BM85: 0 | BN85: 12 | BO85: 10.933 | BP85: 17 | BQ85: 656 | BR85: 656 | BS85: 656 | BT85: 0 | BU85: 0 | BV85: 0 | BW85: 0 | BX85: 0 | BY85: 0 | BZ85: 0 | CA85: 0
B86: ITAOM | E86: Vodafon-Omnitel | F86: OUTBOUND | G86: 2025 | H86: May | I86: 732 | K86: 81322.967 | L86: 0 | M86: 4879378 | N86: 38287 | O86: 38636 | P86: 759 | Q86: 37528 | R86: 0.181 | S86: 0 | T86: 141.179 | U86: 0 | V86: 141.179 | W86: 0.181 | AL86: 25 | AM86: 167.183 | AN86: 181 | AO86: 10031 | AP86: 10031 | AQ86: 10031 | AR86: 0 | AS86: 0 | AT86: 42.298 | AU86: 0 | AV86: 32992.102 | AW86: 0 | AX86: 32992.102 | AY86: 42.298 | AZ86: 3485 | BA86: 0 | BB86: 0 | BC86: 0 | BD86: 0 | BE86: 0 | BF86: 0 | BG86: 0 | BH86: 0 | BI86: 0 | BJ86: 0 | BK86: 0 | BL86: 0 | BM86: 0 | BN86: 23 | BO86: 20.767 | BP86: 33 | BQ86: 1246 | BR86: 1246 | BS86: 1246 | BT86: 0 | BU86: 0 | BV86: 0 | BW86: 0 | BX86: 0 | BY86: 0 | BZ86: 0 | CA86: 0
B87: ITASI | E87: Tim S.P.A | F87: OUTBOUND | G87: 2025 | H87: May | I87: 52 | K87: 1232.15 | L87: 0 | M87: 73929 | N87: 2830 | O87: 2880 | P87: 2683 | Q87: 147 | R87: 0.019 | S87: 0 | T87: 14.43 | U87: 0 | V87: 14.43 | W87: 0.019
B88: ITAWI | E88: Wind - Italy | F88: OUTBOUND | G88: 2025 | H88: May | I88: 639 | K88: 48818.333 | L88: 0 | M88: 2929100 | N88: 39048 | O88: 56740 | P88: 3715 | Q88: 35333 | R88: 913.101 | S88: 0 | T88: 712211.74 | U88: 0 | V88: 712211.74 | W88: 913.101 | AL88: 4 | AM88: 4.75 | AN88: 7 | AO88: 285 | AP88: 285 | AQ88: 420 | AR88: 0 | AS88: 0 | AT88: 13.674 | AU88: 0 | AV88: 10665.863 | AW88: 0 | AX88: 10665.863 | AY88: 13.674 | BN88: 7 | BO88: 4.367 | BP88: 8 | BQ88: 262 | BR88: 262 | BS88: 262 | BT88: 0 | BU88: 0 | BV88: 0 | BW88: 0 | BX88: 0 | BY88: 0 | BZ88: 0 | CA88: 0
B89: JORMC | E89: Petra Jordanian Mobile | F89: OUTBOUND | G89: 2025 | H89: May | AZ89: 107 | BA89: 0 | BB89: 0 | BC89: 0 | BD89: 0 | BE89: 0 | BF89: 0 | BG89: 0 | BH89: 0 | BI89: 0 | BJ89: 0 | BK89: 0 | BL89: 0 | BM89: 0
B90: KENSA | E90: Safaricom | F90: OUTBOUND | G90: 2025 | H90: May | I90: 30926 | K90: 548568.8 | L90: 0 | M90: 32914128 | N90: 29322 | O90: 82200 | P90: 887 | Q90: 28435 | R90: 1117.754 | S90: 0 | T90: 871839.16 | U90: 0 | V90: 871839.16 | W90: 1117.754 | AL90: 1 | AM90: 0.017 | AN90: 1 | AO90: 1 | AP90: 1 | AQ90: 60 | AR90: 0 | AS90: 0 | AT90: 0 | AU90: 0 | AV90: 0 | AW90: 0 | AX90: 0 | AY90: 0 | AZ90: 108 | BA90: 0 | BB90: 0 | BC90: 0 | BD90: 0 | BE90: 0 | BF90: 0 | BG90: 0 | BH90: 0 | BI90: 0 | BJ90: 0 | BK90: 0 | BL90: 0 | BM90: 0
B91: KORSK | E91: Sk Telecom | F91: OUTBOUND | G91: 2025 | H91: May | I91: 6 | K91: 67.317 | L91: 0 | M91: 4039 | N91: 72 | O91: 75 | P91: 1 | Q91: 71 | R91: 0.001 | S91: 0 | T91: 0.686 | U91: 0 | V91: 0.686 | W91: 0.001
B92: KWTKT | E92: Viva Kuwait | F92: OUTBOUND | G92: 2025 | H92: May | AL92: 9 | AM92: 1.4 | AN92: 9 | AO92: 84 | AP92: 84 | AQ92: 540 | AR92: 0 | AS92: 0 | AT92: 0 | AU92: 0 | AV92: 0 | AW92: 0 | AX92: 0 | AY92: 0
B93: LBNFL | E93: Mic 1 S.A.L. | F93: OUTBOUND | G93: 2025 | H93: May | I93: 6718 | K93: 271616.75 | L93: 0 | M93: 16297005 | N93: 228364 | O93: 268250 | P93: 8185 | Q93: 220178 | R93: 3083.002 | S93: 339.118 | T93: 2404717 | U93: 264508.98 | V93: 2669225.9 | W93: 3422.12 | AL93: 9 | AM93: 4.85 | AN93: 9 | AO93: 291 | AP93: 291 | AQ93: 540 | AR93: 0 | AS93: 0 | AT93: 10.488 | AU93: 1.154 | AV93: 8180.525 | AW93: 899.853 | AX93: 9080.378 | AY93: 11.642 | BN93: 8 | BO93: 6.25 | BP93: 11 | BQ93: 375 | BR93: 375 | BS93: 660 | BT93: 0 | BU93: 0 | BV93: 0 | BW93: 0 | BX93: 0 | BY93: 0 | BZ93: 0 | CA93: 0
B94: LBNLC | E94: Touch Lebanon | F94: OUTBOUND | G94: 2025 | H94: May | I94: 632 | K94: 2589.117 | L94: 0 | M94: 155347 | N94: 5870 | O94: 9950 | P94: 381 | Q94: 5489 | R94: 5.369 | S94: 0.591 | T94: 4187.793 | U94: 460.814 | V94: 4648.606 | W94: 5.96
B95: LBRLC | E95: Lonestar Com.Co | F95: OUTBOUND | G95: 2025 | H95: May | BN95: 1 | BO95: 1.7 | BP95: 2 | BQ95: 102 | BR95: 102 | BS95: 0 | BT95: 0 | BU95: 0 | BV95: 0 | BW95: 0 | BX95: 0 | BY95: 0 | BZ95: 0 | CA95: 0
B96: LUXTG | E96: Tango-Luxemburg | F96: OUTBOUND | G96: 2025 | H96: May | I96: 3 | K96: 0.033 | L96: 0 | M96: 2 | N96: 0 | O96: 3 | P96: 0 | Q96: 0 | R96: 0 | S96: 0 | T96: 0.019 | U96: 0 | V96: 0.019 | W96: 0 | AL96: 3 | AM96: 2.683 | AN96: 5 | AO96: 161 | AP96: 161 | AQ96: 161 | AR96: 0 | AS96: 0 | AT96: 0.677 | AU96: 0 | AV96: 528.045 | AW96: 0 | AX96: 528.045 | AY96: 0.677 | AZ96: 512 | BA96: 0 | BB96: 0 | BC96: 0 | BD96: 0 | BE96: 0 | BF96: 0 | BG96: 0 | BH96: 0 | BI96: 0 | BJ96: 0 | BK96: 0 | BL96: 0 | BM96: 0 | BN96: 4 | BO96: 1.15 | BP96: 4 | BQ96: 69 | BR96: 69 | BS96: 69 | BT96: 0 | BU96: 0 | BV96: 0 | BW96: 0 | BX96: 0 | BY96: 0 | BZ96: 0 | CA96: 0
B97: LUXVM | E97: Orange(Vox.Mbl) | F97: OUTBOUND | G97: 2025 | H97: May | I97: 2 | K97: 69.883 | L97: 0 | M97: 4193 | N97: 15 | O97: 16 | P97: 0 | Q97: 15 | R97: 0 | S97: 0 | T97: 0.086 | U97: 0 | V97: 0.086 | W97: 0 | BN97: 1 | BO97: 2.083 | BP97: 3 | BQ97: 125 | BR97: 125 | BS97: 125 | BT97: 0 | BU97: 0 | BV97: 0 | BW97: 0 | BX97: 0 | BY97: 0 | BZ97: 0 | CA97: 0
B98: MARM1 | E98: Maroc Telecom Iam | F98: OUTBOUND | G98: 2025 | H98: May | I98: 58385 | K98: 2699527.3 | L98: 0 | M98: 161971636 | N98: 3214675 | O98: 3217219 | P98: 2598576 | Q98: 616100 | R98: 15.856 | S98: 0 | T98: 12367.631 | U98: 0 | V98: 12367.631 | W98: 15.856 | X98: 5 | Y98: 0 | Z98: 0 | AA98: 0 | AB98: 0 | AC98: 0 | AD98: 0 | AE98: 0 | AF98: 0.038 | AG98: 0 | AH98: 29.523 | AI98: 0 | AJ98: 29.523 | AK98: 0.038 | AL98: 163 | AM98: 210.217 | AN98: 299 | AO98: 12613 | AP98: 12613 | AQ98: 12613 | AR98: 0 | AS98: 0 | AT98: 50.08 | AU98: 0 | AV98: 39061.742 | AW98: 0 | AX98: 39061.742 | AY98: 50.08 | AZ98: 6873 | BA98: 0 | BB98: 0 | BC98: 0 | BD98: 0 | BE98: 0 | BF98: 0 | BG98: 0 | BH98: 0 | BI98: 0 | BJ98: 0 | BK98: 0 | BL98: 0 | BM98: 0 | BN98: 144 | BO98: 140.383 | BP98: 223 | BQ98: 8423 | BR98: 8423 | BS98: 8423 | BT98: 0 | BU98: 0 | BV98: 0 | BW98: 0 | BX98: 0 | BY98: 0 | BZ98: 0 | CA98: 0
B99: MARM3 | E99: Wana Corporate | F99: OUTBOUND | G99: 2025 | H99: May | AL99: 40 | AM99: 58.167 | AN99: 81 | AO99: 3490 | AP99: 3490 | AQ99: 3490 | AR99: 0 | AS99: 0 | AT99: 23.814 | AU99: 0 | AV99: 18574.503 | AW99: 0 | AX99: 18574.503 | AY99: 23.814 | BN99: 3 | BO99: 3.3 | BP99: 4 | BQ99: 198 | BR99: 198 | BS99: 198 | BT99: 0 | BU99: 0 | BV99: 0 | BW99: 0 | BX99: 0 | BY99: 0 | BZ99: 0 | CA99: 0
B100: MDAFT | E100: Orange | F100: OUTBOUND | G100: 2025 | H100: May | AZ100: 1 | BA100: 0 | BB100: 0 | BC100: 0 | BD100: 0 | BE100: 0 | BF100: 0 | BG100: 0 | BH100: 0 | BI100: 0 | BJ100: 0 | BK100: 0 | BL100: 0 | BM100: 0
B101: MDGTM | E101: Telecom Malagasy S.A | F101: OUTBOUND | G101: 2025 | H101: May | AL101: 1 | AM101: 0.417 | AN101: 1 | AO101: 25 | AP101: 25 | AQ101: 60 | AR101: 0 | AS101: 0 | AT101: 1.805 | AU101: 0 | AV101: 1407.893 | AW101: 0 | AX101: 1407.893 | AY101: 1.805 | BN101: 2 | BO101: 2.117 | BP101: 3 | BQ101: 127 | BR101: 127 | BS101: 180 | BT101: 0 | BU101: 0 | BV101: 1.105 | BW101: 0 | BX101: 861.977 | BY101: 0 | BZ101: 861.977 | CA101: 1.105
B102: MLI01 | E102: Malitel Gsm-900 | F102: OUTBOUND | G102: 2025 | H102: May | I102: 36876 | K102: 145550.38 | L102: 0 | M102: 8733023 | N102: 16664595 | O102: 16685268 | P102: 13036288 | Q102: 3628307 | R102: 21.015 | S102: 3.762 | T102: 16391.452 | U102: 2934.542 | V102: 19325.994 | W102: 24.777 | AL102: 1242 | AM102: 735.717 | AN102: 1566 | AO102: 44143 | AP102: 44143 | AQ102: 44143 | AR102: 0 | AS102: 0 | AT102: 0.143 | AU102: 0.026 | AV102: 111.749 | AW102: 20.109 | AX102: 131.858 | AY102: 0.169 | AZ102: 21147 | BA102: 0 | BB102: 0 | BC102: 0 | BD102: 0 | BE102: 0 | BF102: 0 | BG102: 0 | BH102: 0 | BI102: 0 | BJ102: 0 | BK102: 0 | BL102: 0 | BM102: 0 | BN102: 6260 | BO102: 11039.333 | BP102: 14454 | BQ102: 662360 | BR102: 662360 | BS102: 797680 | BT102: 0 | BU102: 0 | BV102: 0 | BW102: 0 | BX102: 0 | BY102: 0 | BZ102: 0 | CA102: 0
B103: MLI02 | E103: Orange Mali Sa | F103: OUTBOUND | G103: 2025 | H103: May | I103: 281671 | K103: 13366341 | L103: 0 | M103: 801980462 | N103: 18275313 | O103: 18281777 | P103: 14825626 | Q103: 3449687 | R103: 1272.409 | S103: 229.028 | T103: 992468.47 | U103: 178639.91 | V103: 1171108.4 | W103: 1501.436 | X103: 32 | Y103: 0 | Z103: 0 | AA103: 0 | AB103: 0 | AC103: 0 | AD103: 0 | AE103: 0 | AF103: 0.684 | AG103: 0.123 | AH103: 533.639 | AI103: 96.095 | AJ103: 629.734 | AK103: 0.807 | AL103: 2647 | AM103: 1499.15 | AN103: 3347 | AO103: 89949 | AP103: 89949 | AQ103: 89991 | AR103: 0 | AS103: 0 | AT103: 275.125 | AU103: 49.522 | AV103: 214595.03 | AW103: 38626.982 | AX103: 253222.02 | AY103: 324.647 | AZ103: 74392 | BA103: 0 | BB103: 0 | BC103: 0 | BD103: 0 | BE103: 0 | BF103: 0 | BG103: 0 | BH103: 0 | BI103: 0 | BJ103: 0 | BK103: 0 | BL103: 0 | BM103: 0 | BN103: 16313 | BO103: 28627.617 | BP103: 37522 | BQ103: 1717657 | BR103: 1717657 | BS103: 1717657 | BT103: 0 | BU103: 0 | BV103: 0 | BW103: 0 | BX103: 0 | BY103: 0 | BZ103: 0 | CA103: 0
B104: MOZVC | E104: Vodacom | F104: OUTBOUND | G104: 2025 | H104: May | I104: 2706 | K104: 5006.783 | L104: 0 | M104: 300407 | N104: 1716 | O104: 1739 | P104: 529 | Q104: 1187 | R104: 0.011 | S104: 0 | T104: 8.294 | U104: 0 | V104: 8.294 | W104: 0.011
B105: MRTMM | E105: Mauritel Mobile | F105: OUTBOUND | G105: 2025 | H105: May | I105: 255 | K105: 8050.967 | L105: 0 | M105: 483058 | N105: 9 | O105: 9 | P105: 2 | Q105: 6 | R105: 0 | S105: 0 | T105: 0.034 | U105: 0 | V105: 0.034 | W105: 0
B106: MRTOC | E106: Chinguitel - Mauritania (Bics) | F106: OUTBOUND | G106: 2025 | H106: May | I106: 24 | K106: 647.417 | L106: 0 | M106: 38845 | N106: 2418 | O106: 2560 | P106: 15 | Q106: 2403 | R106: 27.988 | S106: 4.478 | T106: 21830.251 | U106: 3492.838 | V106: 25323.088 | W106: 32.466 | AL106: 2 | AM106: 1.267 | AN106: 2 | AO106: 76 | AP106: 76 | AQ106: 120 | AR106: 0 | AS106: 0 | AT106: 1.085 | AU106: 0.174 | AV106: 846.185 | AW106: 135.39 | AX106: 981.575 | AY106: 1.258 | AZ106: 3593 | BA106: 0 | BB106: 0 | BC106: 0 | BD106: 0 | BE106: 0 | BF106: 0 | BG106: 0 | BH106: 0 | BI106: 0 | BJ106: 0 | BK106: 0 | BL106: 0 | BM106: 0
B107: NERCT | E107: Airtel - Niger | F107: OUTBOUND | G107: 2025 | H107: May | I107: 17102 | K107: 260683.25 | L107: 0 | M107: 15640995 | N107: 502198 | O107: 511551 | P107: 47689 | Q107: 454508 | R107: 5.652 | S107: 1.271 | T107: 4408.548 | U107: 991.674 | V107: 5400.222 | W107: 6.923 | AL107: 906 | AM107: 142.75 | AN107: 944 | AO107: 8565 | AP107: 8565 | AQ107: 8565 | AR107: 0 | AS107: 0 | AT107: 29.222 | AU107: 6.596 | AV107: 22792.936 | AW107: 5144.593 | AX107: 27937.529 | AY107: 35.818 | BN107: 452 | BO107: 377.017 | BP107: 659 | BQ107: 22621 | BR107: 22621 | BS107: 22621 | BT107: 0 | BU107: 0 | BV107: 0 | BW107: 0 | BX107: 0 | BY107: 0 | BZ107: 0 | CA107: 0
B108: NERFT | E108: Orange Niger | F108: OUTBOUND | G108: 2025 | H108: May | I108: 12768 | K108: 83493.033 | L108: 0 | M108: 5009582 | N108: 286491 | O108: 291922 | P108: 109044 | Q108: 177446 | R108: 24.081 | S108: 4.268 | T108: 18782.987 | U108: 3329.006 | V108: 22111.993 | W108: 28.349 | AL108: 191 | AM108: 116.433 | AN108: 230 | AO108: 6986 | AP108: 6986 | AQ108: 6936 | AR108: 0 | AS108: 0 | AT108: 12.913 | AU108: 2.45 | AV108: 10072.037 | AW108: 1910.98 | AX108: 11983.017 | AY108: 15.363 | AZ108: 63056 | BA108: 0 | BB108: 0 | BC108: 0 | BD108: 0 | BE108: 0 | BF108: 0 | BG108: 0 | BH108: 0 | BI108: 0 | BJ108: 0 | BK108: 0 | BL108: 0 | BM108: 0 | BN108: 385 | BO108: 356.317 | BP108: 595 | BQ108: 21379 | BR108: 21379 | BS108: 0 | BT108: 0 | BU108: 0 | BV108: 0 | BW108: 0 | BX108: 0 | BY108: 0 | BZ108: 0 | CA108: 0
...

Sheet MTC
D2: CALL ANALYSIS REPORT
D4: Client: BEN02
D6: Roaming Parnters: BFAON;CIV02;TGOTC;TGOTL;MLI01;SENSG
D7: Direction: Both
D8: Record Type: Voice
D10: Currency: XOF
D11: Report Type: Monthly
D12: Month and Year From: May-2025
D13: Month and Year To: May-2025
I18: MOC | X18: MTC
I19: Voice | X19: Voice
A20: Client | B20: RP Code | E20: Roaming Partner Name | F20: Direction | G20: Year | H20: Month | I20: Total Calls | K20: Duration in min. | L20: Ceil Duration in Min. | M20: Duration in Sec. | N20: Chargeable Units | O20: Charged Units | P20: Data Volume Incoming (KB) | Q20: Data Volume Outgoing (KB) | R20: Charges (SDR) | S20: Tax (SDR) | T20: Charges (XOF) | U20: Tax (XOF) | V20: Total Amount(XOF) | W20: Total Amount(SDR) | X20: Total Calls | Y20: Duration in min. | Z20: Ceil Duration in Min. | AA20: Duration in Sec. | AB20: Chargeable Units | AC20: Charged Units | AD20: Data Volume Incoming (KB) | AE20: Data Volume Outgoing (KB) | AF20: Charges (SDR) | AG20: Tax (SDR) | AH20: Charges (XOF) | AI20: Tax (XOF) | AJ20: Total Amount(XOF) | AK20: Total Amount(SDR)
A21: BEN02 | B21: BFAON | E21: Telmob | F21: INBOUND | G21: 2025 | H21: May | I21: 287 | K21: 269.733 | L21: 445 | M21: 16184 | N21: 16184 | O21: 16184 | P21: 0 | Q21: 0 | R21: 30.565 | S21: 5.502 | T21: 23840.537 | U21: 4291.301 | V21: 28131.837 | W21: 36.067 | X21: 503 | Y21: 436.65 | Z21: 728 | AA21: 26199 | AB21: 26199 | AC21: 26199 | AD21: 0 | AE21: 0 | AF21: 0 | AG21: 0 | AH21: 0 | AI21: 0 | AJ21: 0 | AK21: 0
F22: OUTBOUND | G22: 2025 | H22: May | I22: 397 | K22: 300.083 | L22: 557 | M22: 18005 | N22: 18005 | O22: 14946 | P22: 0 | Q22: 0 | R22: 39.437 | S22: 7.098 | T22: 30760.545 | U22: 5536.383 | V22: 36296.928 | W22: 46.535 | X22: 5134 | Y22: 8279.567 | Z22: 11083 | AA22: 496774 | AB22: 496774 | AC22: 0 | AD22: 0 | AE22: 0 | AF22: 0 | AG22: 0 | AH22: 0 | AI22: 0 | AJ22: 0 | AK22: 0
E23: Telmob Total | I23: 684 | K23: 569.816 | L23: 1002 | M23: 34189 | N23: 34189 | O23: 31130 | P23: 0 | Q23: 0 | R23: 70.002 | S23: 12.6 | T23: 54601.082 | U23: 9827.684 | V23: 64428.765 | W23: 82.602 | X23: 5637 | Y23: 8716.217 | Z23: 11811 | AA23: 522973 | AB23: 522973 | AC23: 26199 | AD23: 0 | AE23: 0 | AF23: 0 | AG23: 0 | AH23: 0 | AI23: 0 | AJ23: 0 | AK23: 0
B24: CIV02 | E24: Moov(A-Cell) | F24: INBOUND | G24: 2025 | H24: May | I24: 1123 | K24: 1466.8 | L24: 2016 | M24: 88008 | N24: 88008 | O24: 88008 | P24: 0 | Q24: 0 | R24: 128.871 | S24: 23.197 | T24: 100518.14 | U24: 18093.253 | V24: 118611.4 | W24: 152.067 | X24: 1308 | Y24: 2017.583 | Z24: 2723 | AA24: 121055 | AB24: 121055 | AC24: 121055 | AD24: 0 | AE24: 0 | AF24: 0 | AG24: 0 | AH24: 0 | AI24: 0 | AJ24: 0 | AK24: 0
F25: OUTBOUND | G25: 2025 | H25: May | I25: 1304 | K25: 1490.567 | L25: 2195 | M25: 89434 | N25: 89434 | O25: 89489 | P25: 0 | Q25: 0 | R25: 206.17 | S25: 0 | T25: 160810.62 | U25: 0 | V25: 160810.62 | W25: 206.17 | X25: 14811 | Y25: 27184.867 | Z25: 35169 | AA25: 1631092 | AB25: 1631092 | AC25: 1631092 | AD25: 0 | AE25: 0 | AF25: 0 | AG25: 0 | AH25: 0 | AI25: 0 | AJ25: 0 | AK25: 0
E26: Moov(A-Cell) Total | I26: 2427 | K26: 2957.367 | L26: 4211 | M26: 177442 | N26: 177442 | O26: 177497 | P26: 0 | Q26: 0 | R26: 335.041 | S26: 23.197 | T26: 261328.77 | U26: 18093.253 | V26: 279422.02 | W26: 358.237 | X26: 16119 | Y26: 29202.45 | Z26: 37892 | AA26: 1752147 | AB26: 1752147 | AC26: 1752147 | AD26: 0 | AE26: 0 | AF26: 0 | AG26: 0 | AH26: 0 | AI26: 0 | AJ26: 0 | AK26: 0
B27: MLI01 | E27: Malitel Gsm-900 | F27: INBOUND | G27: 2025 | H27: May | I27: 936 | K27: 654.133 | L27: 1333 | M27: 39248 | N27: 39248 | O27: 39248 | P27: 0 | Q27: 0 | R27: 57.306 | S27: 10.315 | T27: 44698.271 | U27: 8045.7 | V27: 52743.971 | W27: 67.621 | X27: 660 | Y27: 631.55 | Z27: 1041 | AA27: 37893 | AB27: 37893 | AC27: 37893 | AD27: 0 | AE27: 0 | AF27: 0 | AG27: 0 | AH27: 0 | AI27: 0 | AJ27: 0 | AK27: 0
F28: OUTBOUND | G28: 2025 | H28: May | I28: 1242 | K28: 735.717 | L28: 1566 | M28: 44143 | N28: 44143 | O28: 44143 | P28: 0 | Q28: 0 | R28: 0.143 | S28: 0.026 | T28: 111.749 | U28: 20.109 | V28: 131.858 | W28: 0.169 | X28: 6260 | Y28: 11039.333 | Z28: 14454 | AA28: 662360 | AB28: 662360 | AC28: 797680 | AD28: 0 | AE28: 0 | AF28: 0 | AG28: 0 | AH28: 0 | AI28: 0 | AJ28: 0 | AK28: 0
E29: Malitel Gsm-900 Total | I29: 2178 | K29: 1389.85 | L29: 2899 | M29: 83391 | N29: 83391 | O29: 83391 | P29: 0 | Q29: 0 | R29: 57.449 | S29: 10.341 | T29: 44810.02 | U29: 8065.809 | V29: 52875.829 | W29: 67.79 | X29: 6920 | Y29: 11670.883 | Z29: 15495 | AA29: 700253 | AB29: 700253 | AC29: 835573 | AD29: 0 | AE29: 0 | AF29: 0 | AG29: 0 | AH29: 0 | AI29: 0 | AJ29: 0 | AK29: 0
B30: SENSG | E30: Yas Senegal | F30: INBOUND | G30: 2025 | H30: May | I30: 34 | K30: 72.3 | L30: 89 | M30: 4338 | N30: 4338 | O30: 4338 | P30: 0 | Q30: 0 | R30: 9.356 | S30: 1.684 | T30: 7297.983 | U30: 1313.639 | V30: 8611.623 | W30: 11.041 | X30: 28 | Y30: 33.683 | Z30: 48 | AA30: 2021 | AB30: 2021 | AC30: 2021 | AD30: 0 | AE30: 0 | AF30: 0 | AG30: 0 | AH30: 0 | AI30: 0 | AJ30: 0 | AK30: 0
F31: OUTBOUND | G31: 2025 | H31: May | I31: 137 | K31: 209.7 | L31: 283 | M31: 12582 | N31: 12582 | O31: 12582 | P31: 0 | Q31: 0 | R31: 52.381 | S31: 0 | T31: 40856.597 | U31: 0 | V31: 40856.597 | W31: 52.381 | X31: 579 | Y31: 1065.433 | Z31: 1376 | AA31: 63926 | AB31: 63926 | AC31: 82560 | AD31: 0 | AE31: 0 | AF31: 0 | AG31: 0 | AH31: 0 | AI31: 0 | AJ31: 0 | AK31: 0
E32: Yas Senegal Total | I32: 171 | K32: 282 | L32: 372 | M32: 16920 | N32: 16920 | O32: 16920 | P32: 0 | Q32: 0 | R32: 61.737 | S32: 1.684 | T32: 48154.58 | U32: 1313.639 | V32: 49468.22 | W32: 63.422 | X32: 607 | Y32: 1099.116 | Z32: 1424 | AA32: 65947 | AB32: 65947 | AC32: 84581 | AD32: 0 | AE32: 0 | AF32: 0 | AG32: 0 | AH32: 0 | AI32: 0 | AJ32: 0 | AK32: 0
B33: TGOTC | E33: Togo Cellulaire | F33: INBOUND | G33: 2025 | H33: May | I33: 671 | K33: 740.217 | L33: 1054 | M33: 44413 | N33: 44413 | O33: 44413 | P33: 0 | Q33: 0 | R33: 46.843 | S33: 8.432 | T33: 36537.497 | U33: 6576.737 | V33: 43114.233 | W33: 55.275 | X33: 14607 | Y33: 28076.083 | Z33: 35346 | AA33: 1684565 | AB33: 1684565 | AC33: 1684565 | AD33: 0 | AE33: 0 | AF33: 0 | AG33: 0 | AH33: 0 | AI33: 0 | AJ33: 0 | AK33: 0
F34: OUTBOUND | G34: 2025 | H34: May | I34: 19136 | K34: 16608.217 | L34: 28091 | M34: 996493 | N34: 996493 | O34: 996493 | P34: 0 | Q34: 0 | R34: 995.286 | S34: 179.152 | T34: 776315.46 | U34: 139737.25 | V34: 916052.71 | W34: 1174.439 | X34: 17338 | Y34: 28564.4 | Z34: 37756 | AA34: 1713864 | AB34: 1713864 | AC34: 1713864 | AD34: 0 | AE34: 0 | AF34: 0 | AG34: 0 | AH34: 0 | AI34: 0 | AJ34: 0 | AK34: 0
E35: Togo Cellulaire Total | I35: 19807 | K35: 17348.434 | L35: 29145 | M35: 1040906 | N35: 1040906 | O35: 1040906 | P35: 0 | Q35: 0 | R35: 1042.129 | S35: 187.584 | T35: 812852.96 | U35: 146313.99 | V35: 959166.94 | W35: 1229.714 | X35: 31945 | Y35: 56640.483 | Z35: 73102 | AA35: 3398429 | AB35: 3398429 | AC35: 3398429 | AD35: 0 | AE35: 0 | AF35: 0 | AG35: 0 | AH35: 0 | AI35: 0 | AJ35: 0 | AK35: 0
B36: TGOTL | E36: Moov Africa Togo | F36: INBOUND | G36: 2025 | H36: May | I36: 15118 | K36: 15519.283 | L36: 23031 | M36: 931157 | N36: 931157 | O36: 931157 | P36: 0 | Q36: 0 | R36: 1010.132 | S36: 181.824 | T36: 787895.23 | U36: 141821.36 | V36: 929716.58 | W36: 1191.957 | X36: 201518 | Y36: 494636 | Z36: 591157 | AA36: 29678160 | AB36: 29678160 | AC36: 29678160 | AD36: 0 | AE36: 0 | AF36: 0 | AG36: 0 | AH36: 0 | AI36: 0 | AJ36: 0 | AK36: 0
F37: OUTBOUND | G37: 2025 | H37: May | I37: 30846 | K37: 28229.3 | L37: 46610 | M37: 1693758 | N37: 1693758 | O37: 1693758 | P37: 0 | Q37: 0 | R37: 1670.7 | S37: 300.727 | T37: 1303132.5 | U37: 234564.57 | V37: 1537697.1 | W37: 1971.427 | X37: 257034 | Y37: 424215.27 | Z37: 559617 | AA37: 25452916 | AB37: 25452916 | AC37: 25452916 | AD37: 0 | AE37: 0 | AF37: 0 | AG37: 0 | AH37: 0 | AI37: 0 | AJ37: 0 | AK37: 0
E38: Moov Africa Togo Total | I38: 45964 | K38: 43748.583 | L38: 69641 | M38: 2624915 | N38: 2624915 | O38: 2624915 | P38: 0 | Q38: 0 | R38: 2680.832 | S38: 482.551 | T38: 2091027.8 | U38: 376385.92 | V38: 2467413.7 | W38: 3163.384 | X38: 458552 | Y38: 918851.27 | Z38: 1150774 | AA38: 55131076 | AB38: 55131076 | AC38: 55131076 | AD38: 0 | AE38: 0 | AF38: 0 | AG38: 0 | AH38: 0 | AI38: 0 | AJ38: 0 | AK38: 0
A39: BEN02 Total | I39: 71231 | K39: 66296.05 | L39: 107270 | M39: 3977763 | N39: 3977763 | O39: 3974759 | P39: 0 | Q39: 0 | R39: 4247.19 | S39: 717.957 | T39: 3312775.2 | U39: 560000.3 | V39: 3872775.5 | W39: 4965.149 | X39: 519780 | Y39: 1026180.4 | Z39: 1290498 | AA39: 61570825 | AB39: 61570825 | AC39: 61228005 | AD39: 0 | AE39: 0 | AF39: 0 | AG39: 0 | AH39: 0 | AI39: 0 | AJ39: 0 | AK39: 0

Sheet Current Month-Summary
B3: Summary of Discount Recievable / (Payable) for the Period from April - 2025
B5: Sl No. | C5: Discount Groups | D5: Outbound Roaming (TAPIN) | G5: Inbound Roaming (TAPOUT) | J5: Net Discount Recievable / (Payable)-EUR
D6: Standrad Charges in EUR | E6: PRA Charges in EUR | F6: Discount Receivable (Tap In) - EUR | G6: Standrad Charges in EUR | H6: PRA Charges in EUR | I6: Discount Payable (Tap Out) - EUR
B7: 1 | C7: Telefonica EUROPE | D7: ='[3]Outbound-Group'!BB10 -> 0 | E7: ='[3]Outbound-Group'!BC10 -> 0 | F7: =D7-E7 -> 0 | G7: ='[3]Inbound-Group'!AY10 -> 211.95128 | H7: ='[3]Inbound-Group'!AZ10 -> 140.05938 | I7: =G7-H7 -> 71.891899 | J7: =F7-I7 -> -71.891899 | K7: ='[3]Inbound-Group'!AY10 -> 211.95128 | L7: ='[3]Inbound-Group'!AZ10 -> 140.05938 | M7: =K7-L7 -> 71.891899 | N7: =I7-M7 -> 0
B8: =B7+1 -> 2 | C8: Telefonica LATAM | D8: ='[3]Outbound-Group'!BB30 -> 0 | E8: ='[3]Outbound-Group'!BC30 -> 0 | F8: =D8-E8 -> 0 | G8: ='[3]Inbound-Group'!AY30 -> 0 | H8: ='[3]Inbound-Group'!AZ30 -> 0 | I8: =G8-H8 -> 0 | J8: =F8-I8 -> 0
B9: =B8+1 -> 3 | C9: Telefonica CZSK Affiliates | D9: ='[3]Outbound-Group'!BB33 -> 0 | E9: ='[3]Outbound-Group'!BC33 -> 0 | F9: =D9-E9 -> 0 | G9: ='[3]Inbound-Group'!AY33 -> 0 | H9: ='[3]Inbound-Group'!AZ33 -> 0 | I9: =G9-H9 -> 0 | J9: =F9-I9 -> 0
B10: =B9+1 -> 4 | C10: FT Telecom (Orange Group) | D10: ='[3]Outbound-Group'!BB57+'[3]Outbound-Group'!BB46 -> 253.90192 | E10: ='[3]Outbound-Group'!BC57+'[3]Outbound-Group'!BC46 -> 253.9948 | F10: =D10-E10 -> -0.092878798 | G10: ='[3]Inbound-Group'!AY57+'[3]Inbound-Group'!AY46 -> 13556.424 | H10: ='[3]Inbound-Group'!AZ57+'[3]Inbound-Group'!AZ46 -> 13556.091 | I10: =G10-H10 -> 0.33351495 | J10: =F10-I10 -> -0.42639375 | K10: ='[3]Inbound-Group'!AY57+'[3]Inbound-Group'!AY46 -> 13556.424 | L10: ='[3]Inbound-Group'!AZ57+'[3]Inbound-Group'!AZ46 -> 13556.091 | M10: =K10-L10 -> 0.33351495 | N10: =I10-M10 -> 0
B11: =B10+1 -> 5 | C11: Altice Group | D11: ='[3]Outbound-Group'!BB53 -> 146.22728 | E11: ='[3]Outbound-Group'!BC53 -> 333.33333 | F11: =D11-E11 -> -187.10606 | G11: ='[3]Inbound-Group'!AY53 -> 146.1232 | H11: ='[3]Inbound-Group'!AZ53 -> 333.33333 | I11: =G11-H11 -> -187.21014 | J11: =F11-I11 -> 0.10408135
B12: =B11+1 -> 6 | C12: Belgacom Group | D12: ='[3]Outbound-Group'!BB60 -> 0.039999247 | E12: ='[3]Outbound-Group'!BC60 -> 0.04 | F12: =D12-E12 -> -7.5344e-07 | G12: ='[3]Inbound-Group'!AY60 -> 94.737648 | H12: ='[3]Inbound-Group'!AZ60 -> 94.738301 | I12: =G12-H12 -> -0.00065300025 | J12: =F12-I12 -> 0.00065224681 | K12: ='[3]Inbound-Group'!AY60 -> 94.737648 | L12: ='[3]Inbound-Group'!AZ60 -> 94.738301 | M12: =K12-L12 -> -0.00065300025 | N12: =I12-M12 -> 0
B13: =B12+1 -> 7 | C13: Deutsche Telekom AG (DTAG) Europe | D13: ='[3]Outbound-Group'!BB95 -> 291.16297 | E13: ='[3]Outbound-Group'!BC95 -> 287.31064 | F13: =D13-E13 -> 3.8523252 | G13: ='[3]Inbound-Group'!AY95 -> 590.96817 | H13: ='[3]Inbound-Group'!AZ95 -> 500.85553 | I13: =G13-H13 -> 90.112649 | J13: =F13-I13 -> -86.260324
B14: =B13+1 -> 8 | C14: Deutsche Telekom AG (DTAG)USA | D14: ='[3]Outbound-Group'!BB107 -> 50.261648 | E14: ='[3]Outbound-Group'!BC107 -> 49.66934 | F14: =D14-E14 -> 0.5923086 | G14: ='[3]Inbound-Group'!AY107 -> 2793.3308 | H14: ='[3]Inbound-Group'!AZ107 -> 2809.9065 | I14: =G14-H14 -> -16.575647 | J14: =F14-I14 -> 17.167956 | K14: ='[3]Inbound-Group'!AY107 -> 2793.3308 | L14: ='[3]Inbound-Group'!AZ107 -> 2809.9065 | M14: =K14-L14 -> -16.575647 | N14: =I14-M14 -> 0
B15: =B14+1 -> 9 | C15: Salt Group | D15: ='[3]Outbound-Group'!BB113 -> 0 | E15: ='[3]Outbound-Group'!BC113 -> 0 | F15: =D15-E15 -> 0 | G15: ='[3]Inbound-Group'!AY113 -> 0 | H15: ='[3]Inbound-Group'!AZ113 -> 0 | I15: =G15-H15 -> 0 | J15: =F15-I15 -> 0
B16: =B15+1 -> 10 | C16: Orange Africa | D16: ='[3]Outbound-Group'!BB129 -> 2265.9275 | E16: ='[3]Outbound-Group'!BC129 -> 1199.975 | F16: =D16-E16 -> 1065.9525 | G16: ='[3]Inbound-Group'!AY129 -> 7466.1645 | H16: ='[3]Inbound-Group'!AZ129 -> 2818.8022 | I16: =G16-H16 -> 4647.3623 | J16: =F16-I16 -> -3581.4098 | K16: ='[3]Inbound-Group'!AY129 -> 7466.1645 | L16: ='[3]Inbound-Group'!AZ129 -> 2818.8022 | M16: =K16-L16 -> 4647.3623 | N16: =I16-M16 -> 0
B17: =B16+1 -> 11 | C17: Vodafone | D17: ='[3]Outbound-Group'!BB156 -> 179.72944 | E17: ='[3]Outbound-Group'!BC156 -> 396.06226 | F17: =D17-E17 -> -216.33282 | G17: ='[3]Inbound-Group'!AY155 -> 3717.6593 | H17: ='[3]Inbound-Group'!AZ155 -> 5533.3721 | I17: =G17-H17 -> -1815.7128 | J17: =F17-I17 -> 1599.38 | K17: ='[3]Inbound-Group'!#REF!+'[3]Inbound-Group'!#REF! -> #REF! | L17: ='[3]Inbound-Group'!#REF!+'[3]Inbound-Group'!#REF! -> #REF! | M17: =K17-L17 -> #REF! | N17: =I17-M17 -> #REF!
B18: =B17+1 -> 12 | C18: Maroco Telecom (IAM) | D18: ='[3]Outbound-Group'!BB157 -> 139.62644 | E18: ='[3]Outbound-Group'!BC157 -> 1939.7119 | F18: =D18-E18 -> -1800.0855 | G18: ='[3]Inbound-Group'!AY156 -> 246.73197 | H18: ='[3]Inbound-Group'!AZ156 -> 5242.7585 | I18: =G18-H18 -> -4996.0265 | J18: =F18-I18 -> 3195.941 | K18: ='[3]Inbound-Group'!AY156 -> 246.73197 | L18: ='[3]Inbound-Group'!AZ156 -> 5242.7585 | M18: =K18-L18 -> -4996.0265 | N18: =I18-M18 -> 0
B19: =B18+1 -> 13 | C19: Hutchison Telephone (HTCL) | D19: ='[3]Outbound-Group'!BB161 -> 0 | E19: ='[3]Outbound-Group'!BC160 -> 0 | F19: =D19-E19 -> 0 | G19: ='[3]Inbound-Group'!AY160 -> 0 | H19: ='[3]Inbound-Group'!AZ160 -> 0 | I19: =G19-H19 -> 0 | J19: =F19-I19 -> 0 | K19: ='[3]Inbound-Group'!AY160 -> 0 | L19: ='[3]Inbound-Group'!AZ160 -> 0 | M19: =K19-L19 -> 0 | N19: =I19-M19 -> 0
B20: =B19+1 -> 14 | C20: KDDI Japan | D20: ='[3]Outbound-Group'!BB164 -> 0 | E20: ='[3]Outbound-Group'!BC164 -> 0 | F20: =D20-E20 -> 0 | G20: ='[3]Inbound-Group'!AY163 -> 2.0100002 | H20: ='[3]Inbound-Group'!AZ163 -> 2.01 | I20: =G20-H20 -> 2.3182e-07 | J20: =F20-I20 -> -2.3182e-07
B21: =B20+1 -> 15 | C21: KPN Group | D21: ='[3]Outbound-Group'!BB167 -> 1.5566431 | E21: ='[3]Outbound-Group'!BC167 -> 1.5591406 | F21: =D21-E21 -> -0.0024975454 | G21: ='[3]Inbound-Group'!AY166 -> 14.887895 | H21: ='[3]Inbound-Group'!AZ166 -> 14.883344 | I21: =G21-H21 -> 0.0045510437 | J21: =F21-I21 -> -0.0070485891
B22: =B21+1 -> 16 | C22: Etisalat UAE | D22: ='[3]Outbound-Group'!BB168 -> 1091.2349 | E22: ='[3]Outbound-Group'!BC168 -> 59.688628 | F22: =D22-E22 -> 1031.5463 | G22: ='[3]Inbound-Group'!AY167 -> 19858.752 | H22: ='[3]Inbound-Group'!AZ167 -> 216.68831 | I22: =G22-H22 -> 19642.063 | J22: =F22-I22 -> -18610.517 | K22: ='[3]Inbound-Group'!AY167 -> 19858.752 | L22: ='[3]Inbound-Group'!AZ167 -> 216.68831 | M22: =K22-L22 -> 19642.063 | N22: =I22-M22 -> 0
B23: =B22+1 -> 17 | C23: Swisscom | D23: ='[3]Outbound-Group'!BB169 -> 0.54980532 | E23: ='[3]Outbound-Group'!BC169 -> 1.4035 | F23: =D23-E23 -> -0.85369468 | G23: ='[3]Inbound-Group'!AY169 -> 0.88228001 | H23: ='[3]Inbound-Group'!AZ169 -> 0.88228516 | I23: =G23-H23 -> -5.14211e-06 | J23: =F23-I23 -> -0.85368953 | K23: ='[3]Inbound-Group'!AY169 -> 0.88228001 | L23: ='[3]Inbound-Group'!AZ169 -> 0.88228516 | M23: =K23-L23 -> -5.14211e-06 | N23: =I23-M23 -> 0
B24: =B23+1 -> 18 | C24: MTN Group | D24: ='[3]Outbound-Group'!BB188 -> 3124.6609 | E24: ='[3]Outbound-Group'!BC188 -> 2754.1251 | F24: =D24-E24 -> 370.53574 | G24: ='[3]Inbound-Group'!AY188 -> 224.03866 | H24: ='[3]Inbound-Group'!AZ188 -> 224.03766 | I24: =G24-H24 -> 0.0010029348 | J24: =F24-I24 -> 370.53473
B25: =B24+1 -> 19 | C25: Airtel Africa | D25: ='[3]Outbound-Group'!BB205 -> 714.57455 | E25: ='[3]Outbound-Group'!BC205 -> 1026.5521 | F25: =D25-E25 -> -311.97751 | G25: ='[3]Inbound-Group'!AY205 -> 879.27193 | H25: ='[3]Inbound-Group'!AZ205 -> 1695.1533 | I25: =G25-H25 -> -815.88133 | J25: =F25-I25 -> 503.90381
B26: =B25+1 -> 20 | C26: KT Corporation | D26: ='[3]Outbound-Group'!BB206 -> 0 | E26: ='[3]Outbound-Group'!BC206 -> 0 | F26: =D26-E26 -> 0 | G26: ='[3]Inbound-Group'!AY206 -> 0 | H26: ='[3]Inbound-Group'!AZ206 -> 0 | I26: =G26-H26 -> 0 | J26: =F26-I26 -> 0
B27: =B26+1 -> 21 | C27: 9 Mobile Nigeria | D27: ='[3]Outbound-Group'!BB207 -> 0.85766509 | E27: ='[3]Outbound-Group'!BC207 -> 0.85766602 | F27: =D27-E27 -> -9.22445e-07 | G27: ='[3]Inbound-Group'!AY207 -> 146.82876 | H27: ='[3]Inbound-Group'!AZ207 -> 146.82806 | I27: =G27-H27 -> 0.00069889913 | J27: =F27-I27 -> -0.00069982158
B28: =B27+1 -> 22 | C28: Airtel Tigo Ghana | D28: ='[3]Outbound-Group'!BB208+'[3]Outbound-Group'!BB209 -> 140.78378 | E28: ='[3]Outbound-Group'!BC208+'[3]Outbound-Group'!BC209 -> 2523.2906 | F28: =D28-E28 -> -2382.5068 | G28: ='[3]Inbound-Group'!AY208+'[3]Inbound-Group'!AY209 -> 1.5411469 | H28: ='[3]Inbound-Group'!AZ208+'[3]Inbound-Group'!AZ209 -> 10.730313 | I28: =G28-H28 -> -9.1891656 | J28: =F28-I28 -> -2373.3177
B29: =B28+1 -> 23 | C29: Orange Guinee | D29: ='[3]Outbound-Group'!BB210 -> 0 | E29: ='[3]Outbound-Group'!BC210 -> 0 | F29: =D29-E29 -> 0 | G29: ='[3]Inbound-Group'!AY210 -> 0 | H29: ='[3]Inbound-Group'!AZ210 -> 0 | I29: =G29-H29 -> 0 | J29: =F29-I29 -> 0
B30: 24 | C30: VIETTEL GROUP(MOBILE) | D30: ='[3]Outbound-Group'!BB210+'[3]Outbound-Group'!BB211 -> 0 | E30: ='[3]Outbound-Group'!BC210+'[3]Outbound-Group'!BC211 -> 0 | F30: =D30-E30 -> 0 | G30: ='[3]Inbound-Group'!AY210+'[3]Inbound-Group'!AY211 -> 0 | H30: ='[3]Inbound-Group'!AZ210+'[3]Inbound-Group'!AZ211 -> 0 | I30: =G30-H30 -> 0 | J30: =F30-I30 -> 0
B31: 25 | C31: Tunisie Telecom | D31: ='[3]Outbound-Group'!BB211+'[3]Outbound-Group'!BB212 -> 13.400767 | E31: ='[3]Outbound-Group'!BC211+'[3]Outbound-Group'!BC212 -> 13.400965 | F31: =D31-E31 -> -0.00019735875 | G31: ='[3]Inbound-Group'!AY211+'[3]Inbound-Group'!AY212 -> 2.9669213 | H31: ='[3]Inbound-Group'!AZ211+'[3]Inbound-Group'!AZ212 -> 3.500124 | I31: =G31-H31 -> -0.53320277 | J31: =F31-I31 -> 0.53300541
B32: 25 | C32: Verizon Wireless | D32: ='[3]Outbound-Group'!BB213+'[3]Outbound-Group'!BB214+'[3]Outbound-Group'!BB215+'[3]Outbound-Group'!BB216+'[3]Outbound-Group'!BB217 -> 0 | E32: ='[3]Outbound-Group'!BC213+'[3]Outbound-Group'!BC214+'[3]Outbound-Group'!BC215+'[3]Outbound-Group'!BC216+'[3]Outbound-Group'!BC217 -> 0 | F32: =D32-E32 -> 0 | G32: ='[3]Inbound-Group'!AY213+'[3]Inbound-Group'!AY214+'[3]Inbound-Group'!AY215+'[3]Inbound-Group'!AY216+'[3]Inbound-Group'!AY217 -> 17970.802 | H32: ='[3]Inbound-Group'!AZ213+'[3]Inbound-Group'!AZ214+'[3]Inbound-Group'!AZ215+'[3]Inbound-Group'!AZ216+'[3]Inbound-Group'!AZ217 -> 18042.546 | I32: =G32-H32 -> -71.744498 | J32: =F32-I32 -> 71.744498
B33: 26 | C33: STC BAHRAIN | D33: ='[3]Outbound-Group'!BB218 -> 0 | E33: ='[3]Outbound-Group'!BC218 -> 0 | F33: =D33-E33 -> 0 | G33: ='[3]Inbound-Group'!AY218 -> 0 | H33: ='[3]Inbound-Group'!AZ218 -> 0 | I33: =G33-H33 -> 0 | J33: =F33-I33 -> 0
B35: Total Discount Recievable / (Payable) | D35: =SUM(D7:D32) -> 8414.4962 | E35: =SUM(E7:E32) -> 10840.975 | F35: =SUM(F7:F33) -> -2426.4788 | G35: =SUM(G7:G32) -> 67926.072 | H35: =SUM(H7:H32) -> 51387.176 | I35: =SUM(I7:I32) -> 16538.896 | J35: =SUM(J7:J34) -> -18965.375 | K35: =SUM(K7:K23) -> #REF! | L35: =SUM(L7:L23) -> #REF! | M35: =SUM(M7:M23) -> #REF!
D37: =D11+D14+D17+D25+D28+D31+D32 -> 1244.9775 | E37: =E11+E14+E17+E25+E28+E31+E32 -> 4342.3086 | F37: =F11+F14+F17+F25+F28+F31+F32 -> -3097.3311 | G37: =G11+G14+G17+G25+G28+G31+G32 -> 25511.695 | H37: =H11+H14+H17+H25+H28+H31+H32 -> 28428.542 | I37: =I11+I14+I17+I25+I28+I31+I32 -> -2916.8468

Sheet Current Month-Summary (2)
B3: Summary of Discount Recievable / (Payable) for the Period from March - 2025
B5: Sl No. | C5: Discount Groups | D5: Outbound Roaming (TAPIN) | G5: Inbound Roaming (TAPOUT) | J5: Net Discount Recievable / (Payable)-EUR
D6: Standrad Charges in EUR | E6: PRA Charges in EUR | F6: Discount Receivable (Tap In) - EUR | G6: Standrad Charges in EUR | H6: PRA Charges in EUR | I6: Discount Payable (Tap Out) - EUR
B7: 1 | C7: Telefonica EUROPE | D7: ='[4]Outbound-Group'!BB10 -> 0 | E7: ='[4]Outbound-Group'!BC10 -> 0 | F7: =D7-E7 -> 0 | G7: ='[4]Inbound-Group'!AY10 -> 2.3985918 | H7: ='[4]Inbound-Group'!AZ10 -> 1.5244629 | I7: =G7-H7 -> 0.87412891 | J7: =F7-I7 -> -0.87412891 | K7: ='[4]Inbound-Group'!AY10 -> 2.3985918 | L7: ='[4]Inbound-Group'!AZ10 -> 1.5244629 | M7: =K7-L7 -> 0.87412891 | N7: =I7-M7 -> 0
B8: =B7+1 -> 2 | C8: Telefonica LATAM | D8: ='[4]Outbound-Group'!BB30 -> 0 | E8: ='[4]Outbound-Group'!BC30 -> 0 | F8: =D8-E8 -> 0 | G8: ='[4]Inbound-Group'!AY30 -> 0 | H8: ='[4]Inbound-Group'!AZ30 -> 0 | I8: =G8-H8 -> 0 | J8: =F8-I8 -> 0
B9: =B8+1 -> 3 | C9: Telefonica CZSK Affiliates | D9: ='[4]Outbound-Group'!BB33 -> 0 | E9: ='[4]Outbound-Group'!BC33 -> 0 | F9: =D9-E9 -> 0 | G9: ='[4]Inbound-Group'!AY33 -> 0 | H9: ='[4]Inbound-Group'!AZ33 -> 0 | I9: =G9-H9 -> 0 | J9: =F9-I9 -> 0
B10: =B9+1 -> 4 | C10: FT Telecom (Orange Group) | D10: ='[4]Outbound-Group'!BB57+'[4]Outbound-Group'!BB46 -> 200.71108 | E10: ='[4]Outbound-Group'!BC57+'[4]Outbound-Group'!BC46 -> 200.8888 | F10: =D10-E10 -> -0.17772311 | G10: ='[4]Inbound-Group'!AY57+'[4]Inbound-Group'!AY46 -> 10497.469 | H10: ='[4]Inbound-Group'!AZ57+'[4]Inbound-Group'!AZ46 -> 10496.85 | I10: =G10-H10 -> 0.61861964 | J10: =F10-I10 -> -0.79634276 | K10: ='[4]Inbound-Group'!AY57+'[4]Inbound-Group'!AY46 -> 10497.469 | L10: ='[4]Inbound-Group'!AZ57+'[4]Inbound-Group'!AZ46 -> 10496.85 | M10: =K10-L10 -> 0.61861964 | N10: =I10-M10 -> 0
B11: =B10+1 -> 5 | C11: Altice Group | D11: ='[4]Outbound-Group'!BB53 -> 454.4004 | E11: ='[4]Outbound-Group'!BC53 -> 333.33333 | F11: =D11-E11 -> 121.06706 | G11: ='[4]Inbound-Group'!AY53 -> 33.027776 | H11: ='[4]Inbound-Group'!AZ53 -> 333.33333 | I11: =G11-H11 -> -300.30556 | J11: =F11-I11 -> 421.37262
B12: =B11+1 -> 6 | C12: Belgacom Group | D12: ='[4]Outbound-Group'!BB60 -> 0.16005908 | E12: ='[4]Outbound-Group'!BC60 -> 0.16005859 | F12: =D12-E12 -> 4.8802e-07 | G12: ='[4]Inbound-Group'!AY60 -> 23.540564 | H12: ='[4]Inbound-Group'!AZ60 -> 23.543049 | I12: =G12-H12 -> -0.0024852315 | J12: =F12-I12 -> 0.0024857195 | K12: ='[4]Inbound-Group'!AY60 -> 23.540564 | L12: ='[4]Inbound-Group'!AZ60 -> 23.543049 | M12: =K12-L12 -> -0.0024852315 | N12: =I12-M12 -> 0
B13: =B12+1 -> 7 | C13: Deutsche Telekom AG (DTAG) Europe | D13: ='[4]Outbound-Group'!BB95 -> 252.57865 | E13: ='[4]Outbound-Group'!BC95 -> 252.67684 | F13: =D13-E13 -> -0.098182398 | G13: ='[4]Inbound-Group'!AY95 -> 398.44402 | H13: ='[4]Inbound-Group'!AZ95 -> 337.70755 | I13: =G13-H13 -> 60.736472 | J13: =F13-I13 -> -60.834655
B14: =B13+1 -> 8 | C14: Deutsche Telekom AG (DTAG)USA | D14: ='[4]Outbound-Group'!BB107 -> 35.917734 | E14: ='[4]Outbound-Group'!BC107 -> 35.62645 | F14: =D14-E14 -> 0.29128406 | G14: ='[4]Inbound-Group'!AY107 -> 4987.4753 | H14: ='[4]Inbound-Group'!AZ107 -> 5162.042 | I14: =G14-H14 -> -174.56666 | J14: =F14-I14 -> 174.85794 | K14: ='[4]Inbound-Group'!AY107 -> 4987.4753 | L14: ='[4]Inbound-Group'!AZ107 -> 5162.042 | M14: =K14-L14 -> -174.56666 | N14: =I14-M14 -> 0
B15: =B14+1 -> 9 | C15: Salt Group | D15: ='[4]Outbound-Group'!BB113 -> 0 | E15: ='[4]Outbound-Group'!BC113 -> 0 | F15: =D15-E15 -> 0 | G15: ='[4]Inbound-Group'!AY113 -> 0 | H15: ='[4]Inbound-Group'!AZ113 -> 0 | I15: =G15-H15 -> 0 | J15: =F15-I15 -> 0
B16: =B15+1 -> 10 | C16: Orange Africa | D16: ='[4]Outbound-Group'!BB129 -> 2471.2848 | E16: ='[4]Outbound-Group'!BC129 -> 1411.8539 | F16: =D16-E16 -> 1059.4309 | G16: ='[4]Inbound-Group'!AY129 -> 7093.3225 | H16: ='[4]Inbound-Group'!AZ129 -> 2839.5347 | I16: =G16-H16 -> 4253.7878 | J16: =F16-I16 -> -3194.3569 | K16: ='[4]Inbound-Group'!AY129 -> 7093.3225 | L16: ='[4]Inbound-Group'!AZ129 -> 2839.5347 | M16: =K16-L16 -> 4253.7878 | N16: =I16-M16 -> 0
B17: =B16+1 -> 11 | C17: Vodafone | D17: ='[4]Outbound-Group'!BB156 -> 178.47823 | E17: ='[4]Outbound-Group'!BC156 -> 451.78404 | F17: =D17-E17 -> -273.30581 | G17: ='[4]Inbound-Group'!AY155 -> 5844.4459 | H17: ='[4]Inbound-Group'!AZ155 -> 7925.9792 | I17: =G17-H17 -> -2081.5332 | J17: =F17-I17 -> 1808.2274 | K17: ='[4]Inbound-Group'!#REF!+'[4]Inbound-Group'!#REF! -> #REF! | L17: ='[4]Inbound-Group'!#REF!+'[4]Inbound-Group'!#REF! -> #REF! | M17: =K17-L17 -> #REF! | N17: =I17-M17 -> #REF!
B18: =B17+1 -> 12 | C18: Maroco Telecom (IAM) | D18: ='[4]Outbound-Group'!BB157 -> 55.917825 | E18: ='[4]Outbound-Group'!BC157 -> 1572.5243 | F18: =D18-E18 -> -1516.6064 | G18: ='[4]Inbound-Group'!AY156 -> 164.10244 | H18: ='[4]Inbound-Group'!AZ156 -> 4014.2179 | I18: =G18-H18 -> -3850.1155 | J18: =F18-I18 -> 2333.509 | K18: ='[4]Inbound-Group'!AY156 -> 164.10244 | L18: ='[4]Inbound-Group'!AZ156 -> 4014.2179 | M18: =K18-L18 -> -3850.1155 | N18: =I18-M18 -> 0
B19: =B18+1 -> 13 | C19: Hutchison Telephone (HTCL) | D19: ='[4]Outbound-Group'!BB161 -> 0 | E19: ='[4]Outbound-Group'!BC160 -> 0 | F19: =D19-E19 -> 0 | G19: ='[4]Inbound-Group'!AY160 -> 0 | H19: ='[4]Inbound-Group'!AZ160 -> 0 | I19: =G19-H19 -> 0 | J19: =F19-I19 -> 0 | K19: ='[4]Inbound-Group'!AY160 -> 0 | L19: ='[4]Inbound-Group'!AZ160 -> 0 | M19: =K19-L19 -> 0 | N19: =I19-M19 -> 0
B20: =B19+1 -> 14 | C20: KDDI Japan | D20: ='[4]Outbound-Group'!BB164 -> 0 | E20: ='[4]Outbound-Group'!BC164 -> 0 | F20: =D20-E20 -> 0 | G20: ='[4]Inbound-Group'!AY163 -> 0.16406084 | H20: ='[4]Inbound-Group'!AZ163 -> 0.16406055 | I20: =G20-H20 -> 2.94195e-07 | J20: =F20-I20 -> -2.94195e-07
B21: =B20+1 -> 15 | C21: KPN Group | D21: ='[4]Outbound-Group'!BB167 -> 1.5340286 | E21: ='[4]Outbound-Group'!BC167 -> 1.5342578 | F21: =D21-E21 -> -0.000229173 | G21: ='[4]Inbound-Group'!AY166 -> 11.702113 | H21: ='[4]Inbound-Group'!AZ166 -> 11.714141 | I21: =G21-H21 -> -0.012027981 | J21: =F21-I21 -> 0.011798808
B22: =B21+1 -> 16 | C22: Etisalat UAE | D22: ='[4]Outbound-Group'!BB168 -> 1410.476 | E22: ='[4]Outbound-Group'!BC168 -> 438.76111 | F22: =D22-E22 -> 971.71491 | G22: ='[4]Inbound-Group'!AY167 -> 8170.1314 | H22: ='[4]Inbound-Group'!AZ167 -> 7043.9878 | I22: =G22-H22 -> 1126.1436 | J22: =F22-I22 -> -154.42866 | K22: ='[4]Inbound-Group'!AY167 -> 8170.1314 | L22: ='[4]Inbound-Group'!AZ167 -> 7043.9878 | M22: =K22-L22 -> 1126.1436 | N22: =I22-M22 -> 0
B23: =B22+1 -> 17 | C23: Swisscom | D23: ='[4]Outbound-Group'!BB169 -> 15.213334 | E23: ='[4]Outbound-Group'!BC169 -> 15.128828 | F23: =D23-E23 -> 0.084505906 | G23: ='[4]Inbound-Group'!AY169 -> 0.3400818 | H23: ='[4]Inbound-Group'!AZ169 -> 0.34005957 | I23: =G23-H23 -> 2.2228807e-05 | J23: =F23-I23 -> 0.084483677 | K23: ='[4]Inbound-Group'!AY169 -> 0.3400818 | L23: ='[4]Inbound-Group'!AZ169 -> 0.34005957 | M23: =K23-L23 -> 2.2228807e-05 | N23: =I23-M23 -> 0
B24: =B23+1 -> 18 | C24: MTN Group | D24: ='[4]Outbound-Group'!BB188 -> 5808.6566 | E24: ='[4]Outbound-Group'!BC188 -> 5413.6713 | F24: =D24-E24 -> 394.98529 | G24: ='[4]Inbound-Group'!AY188 -> 91.528375 | H24: ='[4]Inbound-Group'!AZ188 -> 90.719519 | I24: =G24-H24 -> 0.80885631 | J24: =F24-I24 -> 394.17643
B25: =B24+1 -> 19 | C25: Airtel Africa | D25: ='[4]Outbound-Group'!BB205 -> 696.15699 | E25: ='[4]Outbound-Group'!BC205 -> 1040.2275 | F25: =D25-E25 -> -344.07049 | G25: ='[4]Inbound-Group'!AY205 -> 43.863314 | H25: ='[4]Inbound-Group'!AZ205 -> 80.488627 | I25: =G25-H25 -> -36.625313 | J25: =F25-I25 -> -307.44517
B26: =B25+1 -> 20 | C26: KT Corporation | D26: ='[4]Outbound-Group'!BB206 -> 0 | E26: ='[4]Outbound-Group'!BC206 -> 0 | F26: =D26-E26 -> 0 | G26: ='[4]Inbound-Group'!AY206 -> 0 | H26: ='[4]Inbound-Group'!AZ206 -> 0 | I26: =G26-H26 -> 0 | J26: =F26-I26 -> 0
B27: =B26+1 -> 21 | C27: 9 Mobile Nigeria | D27: ='[4]Outbound-Group'!BB207 -> 0.010108519 | E27: ='[4]Outbound-Group'!BC207 -> 0.010107422 | F27: =D27-E27 -> 1.097385e-06 | G27: ='[4]Inbound-Group'!AY207 -> 168.66859 | H27: ='[4]Inbound-Group'!AZ207 -> 168.66611 | I27: =G27-H27 -> 0.0024751304 | J27: =F27-I27 -> -0.002474033
B28: =B27+1 -> 22 | C28: Airtel Tigo Ghana | D28: ='[4]Outbound-Group'!BB208+'[4]Outbound-Group'!BB209 -> 109.03602 | E28: ='[4]Outbound-Group'!BC208+'[4]Outbound-Group'!BC209 -> 2219.4767 | F28: =D28-E28 -> -2110.4407 | G28: ='[4]Inbound-Group'!AY208+'[4]Inbound-Group'!AY209 -> 2.3446145 | H28: ='[4]Inbound-Group'!AZ208+'[4]Inbound-Group'!AZ209 -> 31.664062 | I28: =G28-H28 -> -29.319448 | J28: =F28-I28 -> -2081.1212
B29: =B28+1 -> 23 | C29: Orange Guinee | D29: ='[4]Outbound-Group'!BB210 -> 0 | E29: ='[4]Outbound-Group'!BC210 -> 0 | F29: =D29-E29 -> 0 | G29: ='[4]Inbound-Group'!AY210 -> 0 | H29: ='[4]Inbound-Group'!AZ210 -> 0 | I29: =G29-H29 -> 0 | J29: =F29-I29 -> 0
B30: 24 | C30: VIETTEL GROUP(MOBILE) | D30: ='[4]Outbound-Group'!BB210+'[4]Outbound-Group'!BB211 -> 0 | E30: ='[4]Outbound-Group'!BC210+'[4]Outbound-Group'!BC211 -> 0 | F30: =D30-E30 -> 0 | G30: ='[4]Inbound-Group'!AY210+'[4]Inbound-Group'!AY211 -> 0 | H30: ='[4]Inbound-Group'!AZ210+'[4]Inbound-Group'!AZ211 -> 0 | I30: =G30-H30 -> 0 | J30: =F30-I30 -> 0
B31: 25 | C31: Tunisie Telecom | D31: ='[4]Outbound-Group'!BB211+'[4]Outbound-Group'!BB212 -> 4.0076428 | E31: ='[4]Outbound-Group'!BC211+'[4]Outbound-Group'!BC212 -> 4.0079521 | F31: =D31-E31 -> -0.00030938414 | G31: ='[4]Inbound-Group'!AY211+'[4]Inbound-Group'!AY212 -> 0.00013548276 | H31: ='[4]Inbound-Group'!AZ211+'[4]Inbound-Group'!AZ212 -> 0.00016113281 | I31: =G31-H31 -> -2.5650053e-05 | J31: =F31-I31 -> -0.00028373409
B32: 25 | C32: Verizon Wireless | D32: ='[4]Outbound-Group'!BB213+'[4]Outbound-Group'!BB214+'[4]Outbound-Group'!BB215+'[4]Outbound-Group'!BB216+'[4]Outbound-Group'!BB217 -> 0 | E32: ='[4]Outbound-Group'!BC213+'[4]Outbound-Group'!BC214+'[4]Outbound-Group'!BC215+'[4]Outbound-Group'!BC216+'[4]Outbound-Group'!BC217 -> 0 | F32: =D32-E32 -> 0 | G32: ='[4]Inbound-Group'!AY213+'[4]Inbound-Group'!AY214+'[4]Inbound-Group'!AY215+'[4]Inbound-Group'!AY216+'[4]Inbound-Group'!AY217 -> 21780.308 | H32: ='[4]Inbound-Group'!AZ213+'[4]Inbound-Group'!AZ214+'[4]Inbound-Group'!AZ215+'[4]Inbound-Group'!AZ216+'[4]Inbound-Group'!AZ217 -> 22622.268 | I32: =G32-H32 -> -841.95982 | J32: =F32-I32 -> 841.95982
B33: 26 | C33: STC BAHRAIN | D33: ='[4]Outbound-Group'!BB218 -> 0 | E33: ='[4]Outbound-Group'!BC218 -> 0 | F33: =D33-E33 -> 0 | G33: ='[4]Inbound-Group'!AY218 -> 0 | H33: ='[4]Inbound-Group'!AZ218 -> 0 | I33: =G33-H33 -> 0 | J33: =F33-I33 -> 0
B35: Total Discount Recievable / (Payable) | D35: =SUM(D7:D32) -> 11694.54 | E35: =SUM(E7:E32) -> 13391.665 | F35: =SUM(F7:F33) -> -1697.1259 | G35: =SUM(G7:G32) -> 59313.277 | H35: =SUM(H7:H32) -> 61184.745 | I35: =SUM(I7:I32) -> -1871.4681 | J35: =SUM(J7:J34) -> 174.34223 | K35: =SUM(K7:K23) -> #REF! | L35: =SUM(L7:L23) -> #REF! | M35: =SUM(M7:M23) -> #REF!

Sheet REVENU
C1: TRAFIC | G1: Prix Unitaires | K1: Revenu HT | N1: TOTAL
A2: DATE | B2: PARC Abonnés | C2: VOIX | D2: SMS | E2: DATA | G2: VOIX | H2: SMS | I2: DATA | K2: VOIX | L2: SMS | M2: DATA
A3: 45778 | C3: 846210 | D3: 3175 | E3: 11370.813 | G3: =6/1.18 -> 5.0847458 | H3: =0.6/1.18 -> 0.50847458 | I3: =400/1.18 -> 338.98305 | K3: =C3*G3 -> 4302762.7 | L3: =D3*H3 -> 1614.4068 | M3: =E3*I3 -> 3854512.9 | N3: =SUM(K3:M3) -> 8158890.1
A4: 45779 | C4: 1261645 | D4: 4864 | E4: 11370.813 | G4: =6/1.18 -> 5.0847458 | H4: =0.6/1.18 -> 0.50847458 | I4: =400/1.18 -> 338.98305 | K4: =C4*G4 -> 6415144.1 | L4: =D4*H4 -> 2473.2203 | M4: =E4*I4 -> 3854512.9 | N4: =SUM(K4:M4) -> 10272130
A5: 45780 | C5: 1302502 | D5: 4678 | E5: 11370.813 | G5: =6/1.18 -> 5.0847458 | H5: =0.6/1.18 -> 0.50847458 | I5: =400/1.18 -> 338.98305 | K5: =C5*G5 -> 6622891.5 | L5: =D5*H5 -> 2378.6441 | M5: =E5*I5 -> 3854512.9 | N5: =SUM(K5:M5) -> 10479783
A6: 45781 | C6: 1415064 | D6: 5008 | E6: 11370.813 | G6: =6/1.18 -> 5.0847458 | H6: =0.6/1.18 -> 0.50847458 | I6: =400/1.18 -> 338.98305 | K6: =C6*G6 -> 7195240.7 | L6: =D6*H6 -> 2546.4407 | M6: =E6*I6 -> 3854512.9 | N6: =SUM(K6:M6) -> 11052300
A7: 45782 | C7: 1397044 | D7: 4847 | E7: 11370.813 | G7: =6/1.18 -> 5.0847458 | H7: =0.6/1.18 -> 0.50847458 | I7: =400/1.18 -> 338.98305 | K7: =C7*G7 -> 7103613.6 | L7: =D7*H7 -> 2464.5763 | M7: =E7*I7 -> 3854512.9 | N7: =SUM(K7:M7) -> 10960591
A8: 45783 | C8: 1411053 | D8: 4460 | E8: 11370.813 | G8: =6/1.18 -> 5.0847458 | H8: =0.6/1.18 -> 0.50847458 | I8: =400/1.18 -> 338.98305 | K8: =C8*G8 -> 7174845.8 | L8: =D8*H8 -> 2267.7966 | M8: =E8*I8 -> 3854512.9 | N8: =SUM(K8:M8) -> 11031626
A9: 45784 | C9: 1390820 | D9: 4660 | E9: 11370.813 | G9: =6/1.18 -> 5.0847458 | H9: =0.6/1.18 -> 0.50847458 | I9: =400/1.18 -> 338.98305 | K9: =C9*G9 -> 7071966.1 | L9: =D9*H9 -> 2369.4915 | M9: =E9*I9 -> 3854512.9 | N9: =SUM(K9:M9) -> 10928849
A10: 45785 | C10: 1393772 | D10: 4407 | E10: 11370.813 | G10: =6/1.18 -> 5.0847458 | H10: =0.6/1.18 -> 0.50847458 | I10: =400/1.18 -> 338.98305 | K10: =C10*G10 -> 7086976.3 | L10: =D10*H10 -> 2240.8475 | M10: =E10*I10 -> 3854512.9 | N10: =SUM(K10:M10) -> 10943730
A11: 45786 | C11: 1430400 | D11: 4387 | E11: 11370.813 | G11: =6/1.18 -> 5.0847458 | H11: =0.6/1.18 -> 0.50847458 | I11: =400/1.18 -> 338.98305 | K11: =C11*G11 -> 7273220.3 | L11: =D11*H11 -> 2230.678 | M11: =E11*I11 -> 3854512.9 | N11: =SUM(K11:M11) -> 11129964
A12: 45787 | C12: 1451830 | D12: 4988 | E12: 11370.813 | G12: =6/1.18 -> 5.0847458 | H12: =0.6/1.18 -> 0.50847458 | I12: =400/1.18 -> 338.98305 | K12: =C12*G12 -> 7382186.4 | L12: =D12*H12 -> 2536.2712 | M12: =E12*I12 -> 3854512.9 | N12: =SUM(K12:M12) -> 11239236
A13: 45788 | C13: 1460083 | D13: 4520 | E13: 11370.813 | G13: =6/1.18 -> 5.0847458 | H13: =0.6/1.18 -> 0.50847458 | I13: =400/1.18 -> 338.98305 | K13: =C13*G13 -> 7424150.8 | L13: =D13*H13 -> 2298.3051 | M13: =E13*I13 -> 3854512.9 | N13: =SUM(K13:M13) -> 11280962
A14: 45789 | C14: 1464270 | D14: 4222 | E14: 11370.813 | G14: =6/1.18 -> 5.0847458 | H14: =0.6/1.18 -> 0.50847458 | I14: =400/1.18 -> 338.98305 | K14: =C14*G14 -> 7445440.7 | L14: =D14*H14 -> 2146.7797 | M14: =E14*I14 -> 3854512.9 | N14: =SUM(K14:M14) -> 11302100
... A23: 45798 | C23: 1512708 | D23: 17614 | E23: 11370.813 | G23: =6/1.18 -> 5.0847458 | H23: =0.6/1.18 -> 0.50847458 | I23: =400/1.18 -> 338.98305 | K23: =C23*G23 -> 7691735.6 | L23: =D23*H23 -> 8956.2712 | M23: =E23*I23 -> 3854512.9 | N23: =SUM(K23:M23) -> 11555205
A24: 45799 | C24: 1578606 | D24: 19280 | E24: 11370.813 | G24: =6/1.18 -> 5.0847458 | H24: =0.6/1.18 -> 0.50847458 | I24: =400/1.18 -> 338.98305 | K24: =AVERAGE(K3:K23) -> 7174666.6 | L24: =AVERAGE(L3:L23) -> 3216.8039 | M24: =AVERAGE(M3:M23) -> 3854512.9 | N24: =SUM(K24:M24) -> 11032396
A25: 45800 | C25: 1529013 | D25: 19250 | E25: 11370.813 | G25: =6/1.18 -> 5.0847458 | H25: =0.6/1.18 -> 0.50847458 | I25: =400/1.18 -> 338.98305 | K25: =AVERAGE(K4:K24) -> 7311423.9 | L25: =AVERAGE(L4:L24) -> 3293.1085 | M25: =AVERAGE(M4:M24) -> 3854512.9 | N25: =SUM(K25:M25) -> 11169230
A26: 45801 | C26: 1523245 | D26: 20510 | E26: 11370.813 | G26: =6/1.18 -> 5.0847458 | H26: =0.6/1.18 -> 0.50847458 | I26: =400/1.18 -> 338.98305 | K26: =AVERAGE(K5:K25) -> 7354103.9 | L26: =AVERAGE(L5:L25) -> 3332.1508 | M26: =AVERAGE(M5:M25) -> 3854512.9 | N26: =SUM(K26:M26) -> 11211949
A27: 45802 | C27: 1642290 | D27: 22451 | E27: 11370.813 | G27: =6/1.18 -> 5.0847458 | H27: =0.6/1.18 -> 0.50847458 | I27: =400/1.18 -> 338.98305 | K27: =AVERAGE(K6:K26) -> 7388923.5 | L27: =AVERAGE(L6:L26) -> 3377.5559 | M27: =AVERAGE(M6:M26) -> 3854512.9 | N27: =SUM(K27:M27) -> 11246814
A28: 45803 | C28: 1580789 | D28: 21680 | E28: 11370.813 | G28: =6/1.18 -> 5.0847458 | H28: =0.6/1.18 -> 0.50847458 | I28: =400/1.18 -> 338.98305 | K28: =AVERAGE(K7:K27) -> 7398146.5 | L28: =AVERAGE(L7:L27) -> 3417.1328 | M28: =AVERAGE(M7:M27) -> 3854512.9 | N28: =SUM(K28:M28) -> 11256077
A29: 45804 | C29: 1516548 | D29: 25756 | E29: 11370.813 | G29: =6/1.18 -> 5.0847458 | H29: =0.6/1.18 -> 0.50847458 | I29: =400/1.18 -> 338.98305 | K29: =AVERAGE(K8:K28) -> 7412171.9 | L29: =AVERAGE(L8:L28) -> 3462.4926 | M29: =AVERAGE(M8:M28) -> 3854512.9 | N29: =SUM(K29:M29) -> 11270147
A30: 45805 | C30: 1523308 | D30: 28193 | E30: 11370.813 | G30: =6/1.18 -> 5.0847458 | H30: =0.6/1.18 -> 0.50847458 | I30: =400/1.18 -> 338.98305 | K30: =AVERAGE(K9:K29) -> 7423473.2 | L30: =AVERAGE(L9:L29) -> 3519.3829 | M30: =AVERAGE(M9:M29) -> 3854512.9 | N30: =SUM(K30:M30) -> 11281505
A31: 45806 | C31: =AVERAGE(C10:C30) -> 1500039.7 | D31: 28193 | E31: 11370.813 | G31: =6/1.18 -> 5.0847458 | H31: =0.6/1.18 -> 0.50847458 | I31: =400/1.18 -> 338.98305 | K31: =AVERAGE(K10:K30) -> 7440211.6 | L31: =AVERAGE(L10:L30) -> 3574.1396 | M31: =AVERAGE(M10:M30) -> 3854512.9 | N31: =SUM(K31:M31) -> 11298299
A32: 45807 | C32: =AVERAGE(C11:C31) -> 1505100.1 | D32: 28193 | E32: 11370.813 | G32: =6/1.18 -> 5.0847458 | H32: =0.6/1.18 -> 0.50847458 | I32: =400/1.18 -> 338.98305 | K32: =AVERAGE(K11:K31) -> 7457032.3 | L32: =AVERAGE(L11:L31) -> 3637.6297 | M32: =AVERAGE(M11:M31) -> 3854512.9 | N32: =SUM(K32:M32) -> 11315183
A33: 45808 | C33: =AVERAGE(C12:C32) -> 1508657.2 | D33: 28193 | E33: 11370.813 | G33: =6/1.18 -> 5.0847458 | H33: =0.6/1.18 -> 0.50847458 | I33: =400/1.18 -> 338.98305 | K33: =AVERAGE(K12:K32) -> 7465785.3 | L33: =AVERAGE(L12:L32) -> 3704.6274 | M33: =AVERAGE(M12:M32) -> 3854512.9 | N33: =SUM(K33:M33) -> 11324003
C34: =SUM(C3:C33) -> 45038969 | D34: =SUM(D3:D33) -> 374553 | E34: =SUM(E3:E33) -> 352495.21 | K34: =SUM(K3:K33) -> 2.2449394e+08 | L34: =SUM(L3:L33) -> 102087.91 | M34: =SUM(M3:M33) -> 1.194899e+08 | N34: =SUM(N3:N33) -> 3.4408593e+08
A37: 45778 | C37: 13767 | D37: 300 | E37: 150 | G37: =6/1.18 -> 5.0847458 | H37: =0.6/1.18 -> 0.50847458 | I37: =400/1.18 -> 338.98305 | K37: =C37*G37 -> 70001.695 | L37: =D37*H37 -> 152.54237 | M37: =E37*I37 -> 50847.458 | N37: =SUM(K37:M37) -> 121001.69
A38: 45779 | C38: 14468.7 | D38: 300 | E38: 150 | G38: =6/1.18 -> 5.0847458 | H38: =0.6/1.18 -> 0.50847458 | I38: =400/1.18 -> 338.98305 | K38: =C38*G38 -> 73569.661 | L38: =D38*H38 -> 152.54237 | M38: =E38*I38 -> 50847.458 | N38: =SUM(K38:M38) -> 124569.66
A39: 45780 | C39: 14690.117 | D39: 300 | E39: 150 | G39: =6/1.18 -> 5.0847458 | H39: =0.6/1.18 -> 0.50847458 | I39: =400/1.18 -> 338.98305 | K39: =C39*G39 -> 74695.508 | L39: =D39*H39 -> 152.54237 | M39: =E39*I39 -> 50847.458 | N39: =SUM(K39:M39) -> 125695.51
A40: 45781 | C40: 14481.183 | D40: 300 | E40: 150 | G40: =6/1.18 -> 5.0847458 | H40: =0.6/1.18 -> 0.50847458 | I40: =400/1.18 -> 338.98305 | K40: =C40*G40 -> 73633.136 | L40: =D40*H40 -> 152.54237 | M40: =E40*I40 -> 50847.458 | N40: =SUM(K40:M40) -> 124633.14
A41: 45782 | C41: 15105.933 | D41: 300 | E41: 150 | G41: =6/1.18 -> 5.0847458 | H41: =0.6/1.18 -> 0.50847458 | I41: =400/1.18 -> 338.98305 | K41: =C41*G41 -> 76809.831 | L41: =D41*H41 -> 152.54237 | M41: =E41*I41 -> 50847.458 | N41: =SUM(K41:M41) -> 127809.83
A42: 45783 | C42: 14878.45 | D42: 300 | E42: 150 | G42: =6/1.18 -> 5.0847458 | H42: =0.6/1.18 -> 0.50847458 | I42: =400/1.18 -> 338.98305 | K42: =C42*G42 -> 75653.136 | L42: =D42*H42 -> 152.54237 | M42: =E42*I42 -> 50847.458 | N42: =SUM(K42:M42) -> 126653.14
A43: 45784 | C43: 17370.9 | D43: 300 | E43: 150 | G43: =6/1.18 -> 5.0847458 | H43: =0.6/1.18 -> 0.50847458 | I43: =400/1.18 -> 338.98305 | K43: =C43*G43 -> 88326.61 | L43: =D43*H43 -> 152.54237 | M43: =E43*I43 -> 50847.458 | N43: =SUM(K43:M43) -> 139326.61
A44: 45785 | C44: 16387.967 | D44: 300 | E44: 150 | G44: =6/1.18 -> 5.0847458 | H44: =0.6/1.18 -> 0.50847458 | I44: =400/1.18 -> 338.98305 | K44: =C44*G44 -> 83328.644 | L44: =D44*H44 -> 152.54237 | M44: =E44*I44 -> 50847.458 | N44: =SUM(K44:M44) -> 134328.64
A45: 45786 | C45: 15760.983 | D45: 300 | E45: 150 | G45: =6/1.18 -> 5.0847458 | H45: =0.6/1.18 -> 0.50847458 | I45: =400/1.18 -> 338.98305 | K45: =C45*G45 -> 80140.593 | L45: =D45*H45 -> 152.54237 | M45: =E45*I45 -> 50847.458 | N45: =SUM(K45:M45) -> 131140.59
A46: 45787 | C46: 17052.583 | D46: 300 | E46: 150 | G46: =6/1.18 -> 5.0847458 | H46: =0.6/1.18 -> 0.50847458 | I46: =400/1.18 -> 338.98305 | K46: =C46*G46 -> 86708.051 | L46: =D46*H46 -> 152.54237 | M46: =E46*I46 -> 50847.458 | N46: =SUM(K46:M46) -> 137708.05
A47: 45788 | C47: 15771.217 | D47: 300 | E47: 150 | G47: =6/1.18 -> 5.0847458 | H47: =0.6/1.18 -> 0.50847458 | I47: =400/1.18 -> 338.98305 | K47: =C47*G47 -> 80192.627 | L47: =D47*H47 -> 152.54237 | M47: =E47*I47 -> 50847.458 | N47: =SUM(K47:M47) -> 131192.63
A48: 45789 | C48: 15204.267 | D48: 300 | E48: 150 | G48: =6/1.18 -> 5.0847458 | H48: =0.6/1.18 -> 0.50847458 | I48: =400/1.18 -> 338.98305 | K48: =C48*G48 -> 77309.831 | L48: =D48*H48 -> 152.54237 | M48: =E48*I48 -> 50847.458 | N48: =SUM(K48:M48) -> 128309.83
... A57: 45798 | C57: 15175.133 | D57: 300 | E57: 150 | G57: =6/1.18 -> 5.0847458 | H57: =0.6/1.18 -> 0.50847458 | I57: =400/1.18 -> 338.98305 | K57: =C57*G57 -> 77161.695 | L57: =D57*H57 -> 152.54237 | M57: =E57*I57 -> 50847.458 | N57: =SUM(K57:M57) -> 128161.69
A58: 45799 | C58: 15686.7 | D58: 300 | E58: 150 | G58: =6/1.18 -> 5.0847458 | H58: =0.6/1.18 -> 0.50847458 | I58: =400/1.18 -> 338.98305 | K58: =AVERAGE(K37:K57) -> 77472.127 | L58: =AVERAGE(L37:L57) -> 152.54237 | M58: =AVERAGE(M37:M57) -> 50847.458 | N58: =SUM(K58:M58) -> 128472.13
A59: 45800 | C59: 14724.767 | D59: 300 | E59: 150 | G59: =6/1.18 -> 5.0847458 | H59: =0.6/1.18 -> 0.50847458 | I59: =400/1.18 -> 338.98305 | K59: =AVERAGE(K38:K58) -> 77827.862 | L59: =AVERAGE(L38:L58) -> 152.54237 | M59: =AVERAGE(M38:M58) -> 50847.458 | N59: =SUM(K59:M59) -> 128827.86
A60: 45801 | C60: 16260.933 | D60: 300 | E60: 150 | G60: =6/1.18 -> 5.0847458 | H60: =0.6/1.18 -> 0.50847458 | I60: =400/1.18 -> 338.98305 | K60: =AVERAGE(K39:K59) -> 78030.633 | L60: =AVERAGE(L39:L59) -> 152.54237 | M60: =AVERAGE(M39:M59) -> 50847.458 | N60: =SUM(K60:M60) -> 129030.63
A61: 45802 | C61: 15197.8 | D61: 300 | E61: 150 | G61: =6/1.18 -> 5.0847458 | H61: =0.6/1.18 -> 0.50847458 | I61: =400/1.18 -> 338.98305 | K61: =AVERAGE(K40:K60) -> 78189.448 | L61: =AVERAGE(L40:L60) -> 152.54237 | M61: =AVERAGE(M40:M60) -> 50847.458 | N61: =SUM(K61:M61) -> 129189.45
A62: 45803 | C62: 15976.017 | D62: 300 | E62: 150 | G62: =6/1.18 -> 5.0847458 | H62: =0.6/1.18 -> 0.50847458 | I62: =400/1.18 -> 338.98305 | K62: =AVERAGE(K41:K61) -> 78406.416 | L62: =AVERAGE(L41:L61) -> 152.54237 | M62: =AVERAGE(M41:M61) -> 50847.458 | N62: =SUM(K62:M62) -> 129406.42
A63: 45804 | C63: 15370.433 | D63: 300 | E63: 150 | G63: =6/1.18 -> 5.0847458 | H63: =0.6/1.18 -> 0.50847458 | I63: =400/1.18 -> 338.98305 | K63: =AVERAGE(K42:K62) -> 78482.444 | L63: =AVERAGE(L42:L62) -> 152.54237 | M63: =AVERAGE(M42:M62) -> 50847.458 | N63: =SUM(K63:M63) -> 129482.44
A64: 45805 | C64: 15054.133 | D64: 300 | E64: 150 | G64: =6/1.18 -> 5.0847458 | H64: =0.6/1.18 -> 0.50847458 | I64: =400/1.18 -> 338.98305 | K64: =AVERAGE(K43:K63) -> 78617.173 | L64: =AVERAGE(L43:L63) -> 152.54237 | M64: =AVERAGE(M43:M63) -> 50847.458 | N64: =SUM(K64:M64) -> 129617.17
A65: 45806 | C65: 15533.383 | D65: 300 | E65: 150 | G65: =6/1.18 -> 5.0847458 | H65: =0.6/1.18 -> 0.50847458 | I65: =400/1.18 -> 338.98305 | K65: =AVERAGE(K44:K64) -> 78154.818 | L65: =AVERAGE(L44:L64) -> 152.54237 | M65: =AVERAGE(M44:M64) -> 50847.458 | N65: =SUM(K65:M65) -> 129154.82
A66: 45807 | C66: 15794.867 | D66: 300 | E66: 150 | G66: =6/1.18 -> 5.0847458 | H66: =0.6/1.18 -> 0.50847458 | I66: =400/1.18 -> 338.98305 | K66: =AVERAGE(K45:K65) -> 77908.446 | L66: =AVERAGE(L45:L65) -> 152.54237 | M66: =AVERAGE(M45:M65) -> 50847.458 | N66: =SUM(K66:M66) -> 128908.45
A67: 45808 | C67: 15794.867 | D67: 300 | E67: 150 | G67: =6/1.18 -> 5.0847458 | H67: =0.6/1.18 -> 0.50847458 | I67: =400/1.18 -> 338.98305 | K67: =AVERAGE(K46:K66) -> 77802.153 | L67: =AVERAGE(L46:L66) -> 152.54237 | M67: =AVERAGE(M46:M66) -> 50847.458 | N67: =SUM(K67:M67) -> 128802.15
C68: =SUM(C37:C67) -> 475353.78 | D68: =SUM(D37:D67) -> 9300 | E68: =SUM(E37:E67) -> 4650 | K68: =SUM(K37:K67) -> 2407806.2 | L68: =SUM(L37:L67) -> 4728.8136 | M68: =SUM(M37:M67) -> 1576271.2 | N68: =SUM(N37:N67) -> 3988806.2
Q311: =+N311+N276+N240+N205+N171+N136+N102+N66+N33 -> 11452911
P380: =N380*1.18 -> 0

Sheet SMS A2P
A2: 45778 | B2: 18805 | C2: =0.08*655.957 -> 52.47656 | D2: =+B2*C2 -> 986821.71 | F2: 156 | G2: =0.08*655.957 -> 52.47656 | H2: =+F2*G2 -> 8186.3434 | L2: =+B2*0.16*655.957 -> 1973643.4 | M2: =(200000*655.957)/31 -> 4231980.6 | N2: =+M2-L2 -> 2258337.2
A3: 45779 | B3: 18745 | C3: =0.08*655.957 -> 52.47656 | D3: =+B3*C3 -> 983673.12 | F3: 123 | G3: =0.08*655.957 -> 52.47656 | H3: =+F3*G3 -> 6454.6169 | L3: =+B3*0.16*655.957 -> 1967346.2 | M3: =(200000*655.957)/31 -> 4231980.6 | N3: =+M3-L3 -> 2264634.4
A4: 45780 | B4: 16576 | C4: =0.08*655.957 -> 52.47656 | D4: =+B4*C4 -> 869851.46 | F4: 135 | G4: =0.08*655.957 -> 52.47656 | H4: =+F4*G4 -> 7084.3356 | L4: =+B4*0.16*655.957 -> 1739702.9 | M4: =(200000*655.957)/31 -> 4231980.6 | N4: =+M4-L4 -> 2492277.7
A5: 45781 | B5: 16181 | C5: =0.08*655.957 -> 52.47656 | D5: =+B5*C5 -> 849123.22 | F5: 134 | G5: =0.08*655.957 -> 52.47656 | H5: =+F5*G5 -> 7031.859 | L5: =+B5*0.16*655.957 -> 1698246.4 | M5: =(200000*655.957)/31 -> 4231980.6 | N5: =+M5-L5 -> 2533734.2
A6: 45782 | B6: 18011 | C6: =0.08*655.957 -> 52.47656 | D6: =+B6*C6 -> 945155.32 | F6: 883 | G6: =0.08*655.957 -> 52.47656 | H6: =+F6*G6 -> 46336.802 | L6: =+B6*0.16*655.957 -> 1890310.6 | M6: =(200000*655.957)/31 -> 4231980.6 | N6: =+M6-L6 -> 2341670
A7: 45783 | B7: 16174 | C7: =0.08*655.957 -> 52.47656 | D7: =+B7*C7 -> 848755.88 | F7: 1203 | G7: =0.08*655.957 -> 52.47656 | H7: =+F7*G7 -> 63129.302 | L7: =+B7*0.16*655.957 -> 1697511.8 | M7: =(200000*655.957)/31 -> 4231980.6 | N7: =+M7-L7 -> 2534468.9
A8: 45784 | B8: 16835 | C8: =0.08*655.957 -> 52.47656 | D8: =+B8*C8 -> 883442.89 | F8: 959 | G8: =0.08*655.957 -> 52.47656 | H8: =+F8*G8 -> 50325.021 | L8: =+B8*0.16*655.957 -> 1766885.8 | M8: =(200000*655.957)/31 -> 4231980.6 | N8: =+M8-L8 -> 2465094.9
A9: 45785 | B9: 17209 | C9: =0.08*655.957 -> 52.47656 | D9: =+B9*C9 -> 903069.12 | F9: 1038 | G9: =0.08*655.957 -> 52.47656 | H9: =+F9*G9 -> 54470.669 | L9: =+B9*0.16*655.957 -> 1806138.2 | M9: =(200000*655.957)/31 -> 4231980.6 | N9: =+M9-L9 -> 2425842.4
A10: 45786 | B10: 19050 | C10: =0.08*655.957 -> 52.47656 | D10: =+B10*C10 -> 999678.47 | F10: 1077 | G10: =0.08*655.957 -> 52.47656 | H10: =+F10*G10 -> 56517.255 | L10: =+B10*0.16*655.957 -> 1999356.9 | M10: =(200000*655.957)/31 -> 4231980.6 | N10: =+M10-L10 -> 2232623.7
A11: 45787 | B11: 18569 | C11: =0.08*655.957 -> 52.47656 | D11: =+B11*C11 -> 974437.24 | F11: 943 | G11: =0.08*655.957 -> 52.47656 | H11: =+F11*G11 -> 49485.396 | L11: =+B11*0.16*655.957 -> 1948874.5 | M11: =(200000*655.957)/31 -> 4231980.6 | N11: =+M11-L11 -> 2283106.2
A12: 45788 | B12: 18334 | C12: =0.08*655.957 -> 52.47656 | D12: =+B12*C12 -> 962105.25 | F12: 899 | G12: =0.08*655.957 -> 52.47656 | H12: =+F12*G12 -> 47176.427 | L12: =+B12*0.16*655.957 -> 1924210.5 | M12: =(200000*655.957)/31 -> 4231980.6 | N12: =+M12-L12 -> 2307770.1
A13: 45789 | B13: 17824 | C13: =0.08*655.957 -> 52.47656 | D13: =+B13*C13 -> 935342.21 | F13: 1024 | G13: =0.08*655.957 -> 52.47656 | H13: =+F13*G13 -> 53735.997 | L13: =+B13*0.16*655.957 -> 1870684.4 | M13: =(200000*655.957)/31 -> 4231980.6 | N13: =+M13-L13 -> 2361296.2
... A24: 45800 | B24: 7539 | C24: =0.08*655.957 -> 52.47656 | D24: =+B24*C24 -> 395620.79 | F24: 4238 | G24: =0.08*655.957 -> 52.47656 | H24: =+F24*G24 -> 222395.66 | L24: =+B24*0.16*655.957 -> 791241.57 | M24: =(200000*655.957)/31 -> 4231980.6 | N24: =+M24-L24 -> 3440739.1
A25: 45801 | B25: 7527 | C25: =0.16*655.957 -> 104.95312 | D25: =+B25*C25 -> 789982.13 | F25: 2934 | G25: =0.08*655.957 -> 52.47656 | H25: =+F25*G25 -> 153966.23 | L25: =+B25*0.16*655.957 -> 789982.13 | M25: =(200000*655.957)/31 -> 4231980.6 | N25: =+M25-L25 -> 3441998.5
A26: 45802 | B26: 6461 | C26: =0.16*655.957 -> 104.95312 | D26: =+B26*C26 -> 678102.11 | F26: 4514 | G26: =0.08*655.957 -> 52.47656 | H26: =+F26*G26 -> 236879.19 | L26: =+B26*0.16*655.957 -> 678102.11 | M26: =(200000*655.957)/31 -> 4231980.6 | N26: =+M26-L26 -> 3553878.5
A27: 45803 | B27: 7813 | C27: =0.16*655.957 -> 104.95312 | D27: =+B27*C27 -> 819998.73 | F27: 4146 | G27: =0.08*655.957 -> 52.47656 | H27: =+F27*G27 -> 217567.82 | L27: =+B27*0.16*655.957 -> 819998.73 | M27: =(200000*655.957)/31 -> 4231980.6 | N27: =+M27-L27 -> 3411981.9
A28: 45804 | B28: 7332 | C28: =0.16*655.957 -> 104.95312 | D28: =+B28*C28 -> 769516.28 | F28: 5029 | G28: =0.08*655.957 -> 52.47656 | H28: =+F28*G28 -> 263904.62 | L28: =+B28*0.16*655.957 -> 769516.28 | M28: =(200000*655.957)/31 -> 4231980.6 | N28: =+M28-L28 -> 3462464.4
A29: 45805 | B29: 7709 | C29: =0.16*655.957 -> 104.95312 | D29: =+B29*C29 -> 809083.6 | F29: 5765 | G29: =0.08*655.957 -> 52.47656 | H29: =+F29*G29 -> 302527.37 | L29: =+B29*0.16*655.957 -> 809083.6 | M29: =(200000*655.957)/31 -> 4231980.6 | N29: =+M29-L29 -> 3422897
A30: 45806 | B30: 7109 | C30: =0.16*655.957 -> 104.95312 | D30: =+B30*C30 -> 746111.73 | F30: 7254 | G30: =0.08*655.957 -> 52.47656 | H30: =+F30*G30 -> 380664.97 | L30: =+B30*0.16*655.957 -> 746111.73 | M30: =(200000*655.957)/31 -> 4231980.6 | N30: =+M30-L30 -> 3485868.9
A31: 45807 | B31: 6206 | C31: =0.16*655.957 -> 104.95312 | D31: =+B31*C31 -> 651339.06 | F31: 10071 | G31: =0.08*655.957 -> 52.47656 | H31: =+F31*G31 -> 528491.44 | L31: =+B31*0.16*655.957 -> 651339.06 | M31: =(200000*655.957)/31 -> 4231980.6 | N31: =+M31-L31 -> 3580641.6
A32: 45808 | B32: 5088 | C32: =0.16*655.957 -> 104.95312 | D32: =+B32*C32 -> 534001.47 | F32: 15105 | G32: =0.08*655.957 -> 52.47656 | H32: =+F32*G32 -> 792658.44 | L32: =+B32*0.16*655.957 -> 534001.47 | M32: =(200000*655.957)/31 -> 4231980.6 | N32: =+M32-L32 -> 3697979.2
B33: =SUM(B2:B32) -> 446367 | D33: =SUM(D2:D32) -> 26322872 | F33: =SUM(F2:F32) -> 83778 | H33: =SUM(H2:H32) -> 4396381.2 | N33: =SUM(N2:N32) -> 84343791
