Workbook

Sheet P&L conso
B1: P&L consolidé | BD1: u
D2: JANVIER | E2: FEVRIER | F2: MARS | G2: AVRIL | H2: MAI | I2: JUIN | J2: JUILLET | K2: AOÛT | L2: SEPTEMBRE | M2: OCTOBRE | N2: NOVEMBRE | O2: DÉCEMBRE | P2: JANVIER | Q2: FEVRIER | R2: MARS | S2: AVR | T2: MAI | U2: JUIN | V2: JUILLET | W2: AOUT | X2: SEPT | Y2: OCT | Z2: NOV | AA2: DEC | AB2: JANV | AC2: FEV | AD2: MARS | AE2: AVRIL | AF2: MAI | AG2: JUIN | AH2: JUILLET | AI2: AOUT | AJ2: SEPT | AK2: OCT | AL2: NOV | AM2: DEC | AN2: JANV | AO2: FEV | AP2: MARS | AQ2: AVRIL | AR2: MAI | AS2: JUIN | AT2: JUIL | AU2: AOÛT | AV2: SEPTEMBRE | AW2: OCTOBRE | AX2: NOVEMBRE | AY2: DÉCEMBRE
B3: (En Millions ML) | D3: 2018 Réel | E3: 2018 Réel | F3: 2018 Réel | G3: 2018 Réel | H3: 2018 Réel | I3: 2018 Réel | J3: 2018 Réel | K3: 2018 Réel | L3: 2018 Réel | M3: 2018 Réel | N3: 2018 Réel | O3: 2018 Réel | P3: 2019 Réel | Q3: 2019 Réel | R3: 2019 Réel | S3: 2019 Réel | T3: 2019 Réel | U3: 2019 Réel | V3: 2019 Réel | W3: 2019 Réel | X3: 2019 Réel | Y3: 2019 Réel | Z3: 2019 Réel | AA3: 2019 Réel | AB3: 2020 Réel | AC3: 2020 Réel | AD3: 2020 Réel | AE3: 2020 Réel | AF3: 2020 Réel | AG3: 2020 Réel | AH3: 2020 Réel | AI3: 2020 Réel | AJ3: 2020 Réel | AK3: 2020 Réel | AL3: 2020 Réel | AM3: 2022 Réel | AN3: 2024 Réel | AO3: 2024 Réel | AP3: 2024 Réel | AQ3: 2024 Réel | AR3: 2024 Réel | AS3: 2024 Réel | AT3: 2024 Réel | AU3: 2024 Réel | AV3: 2024 Réel | AW3: 2024 Réel | AX3: 2024 Réel | AY3: 2024 Réel | AZ3: 2023
B5: Chiffre d'affaires | D5: ='CA Mobile'!D8 -> 0 | E5: ='CA Mobile'!E8 -> 0 | F5: ='CA Mobile'!F8 -> 0 | G5: ='CA Mobile'!G8 -> 0 | H5: ='CA Mobile'!H8 -> 0 | I5: ='CA Mobile'!I8 -> 0 | J5: ='CA Mobile'!J8 -> 0 | K5: ='CA Mobile'!K8 -> 0 | ... O5: ='CA Mobile'!O8 -> 0 | P5: 0 | Q5: 0 | R5: ='CA Mobile'!R8 -> 0 | S5: 0 | T5: 0 | U5: ='CA Mobile'!U8 -> 0 | V5: ='CA Mobile'!V8 -> 0 | W5: 0 | X5: 0 | Y5: 0 | Z5: 0 | AA5: ='CA Mobile'!AA8 -> 0 | AB5: ='CA Mobile'!AB8 -> 0 | AC5: 0 | AD5: 0 | AE5: 0 | AF5: 0 | AG5: 0 | AH5: 0 | AI5: 0 | AJ5: 0 | AK5: 0 | AL5: 0 | AM5: 0 | AN5: ='CA Mobile'!AY8 -> 0 | AO5: ='CA Mobile'!AZ8 -> 0 | AP5: ='CA Mobile'!BA8 -> 0 | AQ5: ='CA Mobile'!BB8 -> 0 | AR5: ='CA Mobile'!BC8 -> 0 | AS5: ='CA Mobile'!BD8 -> 0 | AT5: ='CA Mobile'!BE8 -> 0 | AU5: ='CA Mobile'!BF8 -> 0 | ... AY5: ='CA Mobile'!BJ8 -> 0 | AZ5: =SUM(AN5:AY5) -> 0
B6: Fixe & Internet | AZ6: =SUM(AN6:AR6) -> 0
B7: Intercompagnie Fixe & Internet | AZ7: =SUM(AN7:AR7) -> 0
B8: Mobile | AZ8: =SUM(AN8:AR8) -> 0
B9: Intercompagnie Mobile | AZ9: =SUM(AN9:AR9) -> 0
AZ10: =SUM(AN10:AR10) -> 0
B11: Intercompagnie | AZ11: =SUM(AN11:AR11) -> 0
B12: dont Intercompagnie hors trafic | AZ12: =SUM(AN12:AR12) -> 0
B14: Coût des ventes | D14: ='Marge Mobile'!D42 -> 55200422 | E14: ='Marge Mobile'!E42 -> 42367549 | F14: ='Marge Mobile'!F42 -> 28904193 | G14: ='Marge Mobile'!G42 -> 42458421 | H14: ='Marge Mobile'!H42 -> 32149914 | I14: ='Marge Mobile'!I42 -> 25253867 | J14: ='Marge Mobile'!J42 -> 80516153 | K14: ='Marge Mobile'!K42 -> 80516153 | ... O14: ='Marge Mobile'!O42 -> 80516153 | P14: 25425492 | Q14: 25276578 | R14: ='Marge Mobile'!R42 -> 80516153 | S14: 9071599 | T14: 25827199 | U14: 40104587 | V14: 13834613 | W14: 22267526 | X14: 15859187 | Y14: 26808812 | Z14: 17107746 | AA14: ='Marge Mobile'!AA42 -> 80516153 | AB14: ='Marge Mobile'!AB42 -> 80516153 | AC14: 24355861 | AD14: 18085844 | AE14: 30823902 | AF14: 19840831 | AG14: 17693198 | AH14: 28827141 | AI14: 22601249 | AJ14: 17308736 | AK14: 31536601 | AL14: 690912 | AN14: ='Marge Mobile'!AN42 -> 34618808 | AO14: ='Marge Mobile'!AO42 -> 37772426 | AP14: ='Marge Mobile'!AP42 -> 47698819 | AQ14: ='Marge Mobile'!AQ42 -> 0 | AR14: ='Marge Mobile'!AR42 -> 0 | AS14: ='Marge Mobile'!AS42 -> 0 | AT14: ='Marge Mobile'!AT42 -> 0 | AU14: ='Marge Mobile'!AU42 -> 0 | ... AY14: ='Marge Mobile'!AY42 -> 0 | AZ14: =SUM(AN14:AY14) -> 120090053
B15: Fixe & Internet | AZ15: =SUM(AN15:AR15) -> 0
B16: Intercompagnie Fixe & Internet | AZ16: =SUM(AN16:AR16) -> 0
B17: Mobile | AZ17: =SUM(AN17:AR17) -> 0
B18: Intercompagnie Mobile | AZ18: =SUM(AN18:AR18) -> 0
AZ19: =SUM(AN19:AR19) -> 0
B20: Marge Brute | D20: =D5+D14 -> 55200422 | E20: =E5+E14 -> 42367549 | F20: =F5+F14 -> 28904193 | G20: =G5+G14 -> 42458421 | H20: =H5+H14 -> 32149914 | I20: =I5+I14 -> 25253867 | J20: =J5+J14 -> 80516153 | K20: =K5+K14 -> 80516153 | ... O20: =O5+O14 -> 80516153 | P20: 25425492 | Q20: 25276578 | R20: =R5+R14 -> 80516153 | S20: 9071599 | T20: 25827199 | U20: 40104587 | V20: 13834613 | W20: 22267526 | X20: 15859187 | Y20: 26808812 | Z20: 17107746 | AA20: =AA5+AA14 -> 80516153 | AB20: =AB5+AB14 -> 80516153 | AC20: 24355861 | AD20: 18085844 | AE20: 30823902 | AF20: 19840831 | AG20: 17693198 | AH20: 28827141 | AI20: 22601249 | AJ20: 17308736 | AK20: 31536601 | AL20: 690912 | AN20: =AN5-AN14 -> -34618808 | AO20: =AO5-AO14 -> -37772426 | AP20: =AP5-AP14 -> -47698819 | AQ20: =AQ5-AQ14 -> 0 | AR20: =AR5-AR14 -> 0 | AS20: =AS5-AS14 -> 0 | AT20: =AT5-AT14 -> 0 | AU20: =AU5-AU14 -> 0 | ... AY20: =AY5-AY14 -> 0 | AZ20: =SUM(AN20:AY21) -> -120090053
B21: % CA | AZ21: =SUM(AN21:AR21) -> 0
B22: Fixe & Internet | AZ22: =SUM(AN22:AR22) -> 0
B23: Mobile | AZ23: =SUM(AN23:AR23) -> 0
AZ24: =SUM(AN24:AR24) -> 0
B25: Coûts opérationnels | D25: =-'Opex Consolidés'!D7 -> 25842130 | E25: =-'Opex Consolidés'!E7 -> 25842130 | F25: =-'Opex Consolidés'!F7 -> 2.5004213e+08 | G25: =-'Opex Consolidés'!G7 -> 1.210623e+08 | H25: =-'Opex Consolidés'!H7 -> 31115136 | I25: =-'Opex Consolidés'!I7 -> 1.8247527e+08 | J25: =-'Opex Consolidés'!J7 -> 1.0890133e+08 | K25: =-'Opex Consolidés'!K7 -> 1.0958182e+08 | ... O25: =-'Opex Consolidés'!O7 -> 1.611964e+08 | P25: 25842130 | Q25: 25842130 | R25: =-'Opex Consolidés'!F7 -> 2.5004213e+08 | S25: 1.210623e+08 | T25: 31115136 | U25: 1.8247527e+08 | V25: 1.0890133e+08 | W25: 1.0958182e+08 | X25: 1.0973137e+08 | Y25: 1.0985062e+08 | Z25: 1.0985062e+08 | AA25: =-'Opex Consolidés'!O7 -> 1.611964e+08 | AB25: =-'Opex Consolidés'!P7 -> 1.5590212e+08 | AC25: 2.2119604e+08 | AD25: 19916280 | AE25: 1.3019037e+08 | AF25: 1.3019037e+08 | AG25: 2.683311e+08 | AH25: 1.3583707e+08 | AI25: 1.2849657e+08 | AJ25: 1.292504e+08 | AK25: 1.3137707e+08 | AL25: 1.321329e+08 | AN25: ='Opex Consolidés'!AB7 -> 91880957 | AO25: ='Opex Consolidés'!AC7 -> 92284289 | AP25: ='Opex Consolidés'!AD7 -> 88853041 | AQ25: ='Opex Consolidés'!AE7 -> 0 | AR25: ='Opex Consolidés'!AF7 -> 0 | AS25: ='Opex Consolidés'!AG7 -> 0 | AT25: ='Opex Consolidés'!AH7 -> 0 | AU25: ='Opex Consolidés'!AI7 -> 0 | ... AY25: ='Opex Consolidés'!AM7 -> 0 | AZ25: =SUM(AN25:AY25) -> 2.7301829e+08
B26: Fixe & Internet | AZ26: =SUM(AN26:AR26) -> 0
B27: Intercompagnie Fixe & Internet | AZ27: =SUM(AN27:AR27) -> 0
B28: Mobile | AZ28: =SUM(AN28:AR28) -> 0
B29: Intercompagnie Mobile | AZ29: =SUM(AN29:AR29) -> 0
AZ30: =SUM(AN30:AR30) -> 0
B31: EBITDA | D31: =D20+D25 -> 81042552 | E31: =E20+E25 -> 68209679 | F31: =F20+F25 -> 2.7894632e+08 | G31: =G20+G25 -> 1.6352072e+08 | H31: =H20+H25 -> 63265050 | I31: =I20+I25 -> 2.0772914e+08 | J31: =J20+J25 -> 1.8941749e+08 | K31: =K20+K25 -> 1.9009797e+08 | ... O31: =O20+O25 -> 2.4171255e+08 | P31: 51267622 | Q31: 51118708 | R31: =R20+R25 -> 3.3055828e+08 | S31: 1.301339e+08 | T31: 56942335 | U31: 2.2257986e+08 | V31: 1.2273595e+08 | W31: 1.3184934e+08 | X31: 1.2559056e+08 | Y31: 1.3665943e+08 | Z31: 1.2695836e+08 | AA31: =AA20+AA25 -> 2.4171255e+08 | AB31: =AB20+AB25 -> 2.3641827e+08 | AC31: 2.455519e+08 | AD31: 38002124 | AE31: 1.6101427e+08 | AF31: 1.500312e+08 | AG31: 2.860243e+08 | AH31: 1.6466421e+08 | AI31: 1.5109782e+08 | AJ31: 1.4655914e+08 | AK31: 1.6291367e+08 | AL31: 1.3282382e+08 | AN31: =AN20+AN25 -> 57262149 | AO31: =AO20+AO25 -> 54511863 | AP31: =AP20+AP25 -> 41154222 | AQ31: =AQ20+AQ25 -> 0 | AR31: =AR20+AR25 -> 0 | AS31: =AS20+AS25 -> 0 | AT31: =AT20+AT25 -> 0 | AU31: =AU20+AU25 -> 0 | ... AY31: =AY20+AY25 -> 0 | AZ31: =SUM(AN31:AY31) -> 1.5292823e+08
B32: % CA | AZ32: =SUM(AN32:AR32) -> 0
B33: Fixe & Internet | AZ33: =SUM(AN33:AR33) -> 0
B34: Mobile | AZ34: =SUM(AN34:AR34) -> 0
AZ35: =SUM(AN35:AR35) -> 0
B36: Amortissements et déprec. Courant | D36: =+D61+D60+D62 -> -21521647 | E36: =+E61+E60+E62 -> -20023028 | F36: =+F61+F60+F62 -> -18512540 | G36: =+G61+G60+G62 -> -20145472 | H36: =+H61+H60+H62 -> -33658083 | I36: =+I61+I60+I62 -> -33841265 | J36: =SUM('[10]BG Mois'!$J$544,'[10]BG Mois'!$J$546:$J$547)*1000000 -> 26837168 | K36: =SUM('[11]BG Mois'!$J$545,'[11]BG Mois'!$J$546,'[11]BG Mois'!$J$543)*1000000 -> 23374081 | L36: =SUM('[12]BG Mois'!$J$537,'[12]BG Mois'!$J$539)*1000000 -> -42845986 | M36: =SUM('[13]BG Mois'!$J$541,'[13]BG Mois'!$J$543)*1000000 -> -44417085 | N36: =SUM('[14]BG Mois'!$J$540,'[14]BG Mois'!$J$542)*1000000 -> -44417085 | O36: =+O61+O60 -> -12336796 | P36: -35688043 | Q36: -42680804 | R36: =+R61+R60+R62+R63 -> -2.5426551e+08 | S36: -1.2464723e+08 | T36: -47483806 | U36: -1.8909234e+08 | V36: -1.2142454e+08 | W36: -1.2209631e+08 | X36: -1.1941504e+08 | Y36: -1.1937415e+08 | Z36: -1.1921431e+08 | AA36: =+AA61+AA60+AA62+AA63 -> -1.4123682e+08 | AB36: =+AB61+AB60+AB62+AB63 -> -1.7306909e+08 | AC36: -2.0020656e+08 | AD36: 1974960.7 | AE36: -1.2681254e+08 | AF36: -1.2675104e+08 | AG36: -1.9255121e+08 | AH36: -1.3650713e+08 | AI36: -1.3711062e+08 | AJ36: -1.3445568e+08 | AK36: -1.3349311e+08 | AL36: -1.3161498e+08 | AN36: =+AN61+AN60+AN62+AN63 -> -1.345405e+08 | AO36: =+AO61+AO60+AO62+AO63 -> -1.3094169e+08 | AP36: =+AP61+AP60+AP62+AP63 -> -1.3249288e+08 | AQ36: =+AQ61+AQ60+AQ62+AQ63 -> 0 | AR36: =+AR61+AR60+AR62+AR63 -> 0 | AS36: =+AS61+AS60+AS62+AS63 -> 0 | AT36: =+AT61+AT60+AT62+AT63 -> 0 | AU36: =+AU61+AU60+AU62+AU63 -> 0 | ... AY36: =+AY61+AY60+AY62+AY63 -> 0 | AZ36: =SUM(AN36:AY36) -> -3.9797506e+08
B37: Dotations (Amo. et Pv NC) | AZ37: =SUM(AN37:AR37) -> 0
B38: Autres non courant | AZ38: =SUM(AN38:AR38) -> 0
B39: +/- value de cession d'immob. | AZ39: =SUM(AN39:AR39) -> 0
AZ40: =SUM(AN40:AR40) -> 0
B41: EBIT | D41: =D31+D36+D37+D38+D39 -> 59520905 | E41: =E31+E36+E37+E38+E39 -> 48186651 | F41: =F31+F36+F37+F38+F39 -> 2.6043378e+08 | G41: =G31+G36+G37+G38+G39 -> 1.4337525e+08 | H41: =H31+H36+H37+H38+H39 -> 29606967 | I41: =I31+I36+I37+I38+I39 -> 1.7388787e+08 | J41: =J31+J36+J37+J38+J39 -> 2.1625466e+08 | K41: =K31+K36+K37+K38+K39 -> 2.1347205e+08 | ... O41: =O31+O36+O37+O38+O39 -> 2.2937576e+08 | P41: 15579579 | Q41: 8437903.7 | R41: =R31+R36+R37+R38+R39 -> 76292774 | S41: 5486672.3 | T41: 9458529.4 | U41: 33487512 | V41: 1311408.5 | W41: 9753032.8 | X41: 6175520.8 | Y41: 17285276 | Z41: 7744050.6 | AA41: =AA31+AA36+AA37+AA38+AA39 -> 1.0047573e+08 | AB41: =AB31+AB36+AB37+AB38+AB39 -> 63349177 | AC41: 45345340 | AD41: 39977085 | AE41: 34201727 | AF41: 23280162 | AG41: 93473091 | AH41: 28157083 | AI41: 13987200 | AJ41: 12103465 | AK41: 29420565 | AL41: 1208836.2 | AN41: =AN31+AN36+AN37+AN38+AN39 -> -77278346 | AO41: =AO31+AO36+AO37+AO38+AO39 -> -76429828 | AP41: =AP31+AP36+AP37+AP38+AP39 -> -91338655 | AQ41: =AQ31+AQ36+AQ37+AQ38+AQ39 -> 0 | AR41: =AR31+AR36+AR37+AR38+AR39 -> 0 | AS41: =AS31+AS36+AS37+AS38+AS39 -> 0 | AT41: =AT31+AT36+AT37+AT38+AT39 -> 0 | AU41: =AU31+AU36+AU37+AU38+AU39 -> 0 | ... AY41: =AY31+AY36+AY37+AY38+AY39 -> 0 | AZ41: =SUM(AN41:AY42) -> -2.4504683e+08
B42: % CA | AZ42: =SUM(AN42:AR42) -> 0
B43: Fixe & Internet | AZ43: =SUM(AN43:AR43) -> 0
B44: Mobile | AZ44: =SUM(AN44:AR44) -> 0
AZ45: =SUM(AN45:AR45) -> 0
AZ46: =SUM(AN46:AT46) -> 0
B47: Résultat financier | D47: =-'Opex Consolidés'!D47 -> 0 | E47: =-'Opex Consolidés'!E47 -> 0 | F47: =-'Opex Consolidés'!F47 -> -51379512 | G47: =-'Opex Consolidés'!G47 -> -2028681 | H47: =-'Opex Consolidés'!H47 -> -882940 | I47: =-'Opex Consolidés'!I47 -> -52684470 | J47: =-'Opex Consolidés'!J47 -> -20358747 | K47: =-'Opex Consolidés'!K47 -> -16817672 | ... O47: =-'Opex Consolidés'!O47 -> -39383678 | P47: 0 | Q47: 0 | R47: =-'Opex Consolidés'!F47 -> -51379512 | S47: -2028681 | T47: -882940 | U47: -52684470 | V47: -20358747 | W47: -16817672 | X47: -13820921 | Y47: -16046566 | Z47: -16046566 | AA47: =-'Opex Consolidés'!O47 -> -39383678 | AB47: =-'Opex Consolidés'!P47 -> -28872361 | AC47: -33468953 | AD47: 4270680 | AE47: -18847232 | AF47: -48734075 | AG47: -123679295 | AH47: -32993319 | AI47: -21365147 | AJ47: -13158859 | AK47: -32896245 | AL47: -21041536 | AN47: ='Opex Consolidés'!AB47 -> -5589000 | AO47: ='Opex Consolidés'!AC47 -> -6645038 | AP47: ='Opex Consolidés'!AD47 -> -6321756 | AQ47: ='Opex Consolidés'!AE47 -> 0 | AR47: ='Opex Consolidés'!AF47 -> 0 | AS47: ='Opex Consolidés'!AG47 -> 0 | AT47: ='Opex Consolidés'!AH47 -> 0 | AU47: ='Opex Consolidés'!AI47 -> 0 | ... AY47: ='Opex Consolidés'!AM47 -> 0 | AZ47: =SUM(AN47:AY47) -> -18555794
B48: dont intérêt sur SHL | AZ48: =SUM(AN48:AR48) -> 0
AZ49: =SUM(AN49:AR49) -> 0
B50: RESULTAT avant IS | D50: =D41+D47 -> 59520905 | E50: =E41+E47 -> 48186651 | F50: =F41+F47 -> 2.0905427e+08 | G50: =G41+G47 -> 1.4134657e+08 | H50: =H41+H47 -> 28724027 | I50: =I41+I47 -> 1.212034e+08 | J50: =J41+J47 -> 1.9589591e+08 | K50: =K41+K47 -> 1.9665438e+08 | ... O50: =O41+O47 -> 1.8999208e+08 | P50: 15579579 | Q50: 8437903.7 | R50: =R41+R47 -> 24913262 | S50: 3457991.3 | T50: 8575589.4 | U50: -19196958 | V50: -19047338 | W50: -7064639.2 | X50: -7645400.2 | Y50: 1238710 | Z50: -8302515.4 | AA50: =AA41+AA47 -> 61092052 | AB50: =AB41+AB47 -> 34476816 | AC50: 11876387 | AD50: 44247765 | AE50: 15354495 | AF50: -25453913 | AG50: -30206204 | AH50: -4836236 | AI50: -7377947.1 | AJ50: -1055393.7 | AK50: -3475680.1 | AL50: -19832700 | AN50: =AN41+AN47 -> -82867346 | AO50: =AO41+AO47 -> -83074866 | AP50: =AP41+AP47 -> -97660411 | AQ50: =AQ41+AQ47 -> 0 | AR50: =AR41+AR47 -> 0 | AS50: =AS41+AS47 -> 0 | AT50: =AT41+AT47 -> 0 | AU50: =AU41+AU47 -> 0 | ... AY50: =AY41+AY47 -> 0 | AZ50: =SUM(AN50:AY50) -> -2.6360262e+08
B51: IS | AZ51: =SUM(AN51:AX51) -> 0
B52: ID | D52: =-D50*0.3 -> -17856271 | E52: =-E50*0.3 -> -14455995 | F52: =-F50*0.3 -> -62716281 | G52: =-G50*0.3 -> -42403972 | H52: =-H50*0.3 -> -8617208 | I52: =-I50*0.3 -> -36361020 | J52: =-J50*0.3 -> -58768773 | K52: =-K50*0.3 -> -58996314 | ... O52: =-O50*0.3 -> -56997623 | P52: -4673873.7 | Q52: -2531371.1 | R52: =-R50*0.3+(-12.4) -> -7473990.9 | S52: -1037397.4 | T52: -2572676.8 | U52: 5759087.5 | V52: 5714201.5 | W52: 2119391.8 | X52: 2293620 | Y52: -371613.01 | Z52: 2490754.6 | AA52: =-AA50*0.3 -> -18327616 | AB52: =-AB50*0.3 -> -10343045 | AC52: -3562916 | AD52: -13274329 | AE52: -4606348.4 | AF52: 7636173.8 | AG52: 9061861.1 | AH52: 1450870.8 | AI52: 2213384.1 | AJ52: 316618.11 | AK52: 1042704 | AL52: 5949809.9 | AN52: =-AN50*0.3 -> 24860204 | AO52: =-AO50*0.3 -> 24922460 | AP52: =-AP50*0.3 -> 29298123 | AQ52: =-AQ50*0.3 -> 0 | AR52: =-AR50*0.3 -> 0 | AS52: =-AS50*0.3 -> 0 | AT52: =-AT50*0.3 -> 0 | AU52: =-AU50*0.3 -> 0 | ... AY52: =-AY50*0.3 -> 0 | AZ52: =SUM(AN52:AY52) -> 79080787
B54: RESULTAT NET | D54: =D50+D52+D51 -> 41664633 | E54: =E50+E52+E51 -> 33730656 | F54: =F50+F52+F51 -> 1.4633799e+08 | G54: =G50+G52+G51 -> 98942600 | H54: =H50+H52+H51 -> 20106819 | I54: =I50+I52+I51 -> 84842381 | J54: =J50+J52+J51 -> 1.3712714e+08 | K54: =K50+K52+K51 -> 1.3765807e+08 | ... O54: =O50+O52+O51 -> 1.3299445e+08 | P54: 10905705 | Q54: 5906532.6 | R54: =R50+R52+R51 -> 17439271 | S54: 2420593.9 | T54: 6002912.6 | U54: -13437871 | V54: -13333137 | W54: -4945247.4 | X54: -5351780.1 | Y54: 867097.03 | Z54: -5811760.8 | AA54: =AA50+AA52+AA51 -> 42764436 | AB54: =AB50+AB52+AB51 -> 24133771 | AC54: 8313470.7 | AD54: 30973435 | AE54: 10748146 | AF54: -17817739 | AG54: -21144343 | AH54: -3385365.2 | AI54: -5164563 | AJ54: -738775.58 | AK54: -2432976.1 | AL54: -13882890 | AN54: =AN50+AN52+AN51 -> -58007142 | AO54: =AO50+AO52+AO51 -> -58152406 | AP54: =AP50+AP52+AP51 -> -68362288 | AQ54: =AQ50+AQ52+AQ51 -> 0 | AR54: =AR50+AR52+AR51 -> 0 | AS54: =AS50+AS52+AS51 -> 0 | AT54: =AT50+AT52+AT51 -> 0 | AU54: =AU50+AU52+AU51 -> 0 | ... AY54: =AY50+AY52+AY51 -> 0 | AZ54: =SUM(AN54:AY54) -> -1.8452184e+08
AZ56: =SUM(AB56:AJ56) -> 0
AZ57: =SUM(AB57:AJ57) -> 0
B60: AMORT SIM | D60: -31955749 | E60: -30457130 | F60: -28946642 | G60: -30579574 | H60: -35822185 | I60: =+'[15]YTD Juin'!$J$555*1000000 -> -36005367 | J60: ='[10]BG Mois'!$J$546*1000000 -> 0 | K60: =+'[11]BG Mois'!$J$545*1000000 -> -6168398.1 | L60: -6168398.1 | M60: -38248687 | N60: -38248687 | O60: =+'[16]BG Mois'!$J$546*1000000 -> -6168398.1 | P60: -29519645 | Q60: -30359518 | R60: -30027234 | S60: -29509339 | T60: -29380215 | U60: -29474973 | V60: -29001301 | W60: -28833039 | X60: -28395624 | Y60: -28047097 | Z60: -27579612 | AA60: -27524231 | AB60: -26411560 | AC60: -25968199 | AD60: -25617817 | AE60: -26691891 | AF60: -25153144 | AG60: -25037227 | AH60: -24720179 | AI60: -25570788 | AJ60: -26388546 | AK60: -20553676 | AL60: -20094292 | AN60: -43854740 | AO60: -43943624 | AP60: -43955810 | AZ60: =SUM(AN60:AY60) -> -1.3175417e+08
B61: AMORT PERSONNEL | D61: -6168398.1 | E61: -6168398.1 | F61: -6168398.1 | G61: -6168398.1 | H61: -6168398.1 | I61: =+'[15]YTD Juin'!$J$553*1000000 -> -6168398.1 | J61: ='[10]BG Mois'!$J$544*1000000 -> 31253086 | K61: =+'[11]BG Mois'!$J$543*1000000 -> 0 | L61: 0 | M61: -6168398.1 | N61: -6168398.1 | O61: -6168398.1 | P61: -6168398.1 | Q61: -12321286 | R61: -12628931 | S61: -12936575 | T61: -13244219 | U61: -13551864 | V61: -13859508 | W61: -14167153 | X61: -14474797 | Y61: -14782441 | Z61: -15090086 | AA61: -15397730 | AB61: -15705375 | AC61: -16013019 | AD61: -16320663 | AE61: -16628308 | AF61: -16935952 | AG61: -17243597 | AH61: -17551241 | AI61: -17858885 | AJ61: -18166530 | AK61: -18474174 | AL61: -18781819 | AN61: -26113453 | AO61: -26113453 | AP61: -26113453 | AZ61: =SUM(AN61:AY61) -> -78340359
B62: AMORT CHARGES IMMOB | D62: 16602500 | E62: 16602500 | F62: 16602500 | G62: 16602500 | H62: 8332500 | I62: =+'[15]YTD Mai'!$J$556*1000000 -> 8332500 | J62: ='[10]BG Mois'!$J$548 -> -261.53903 | K62: =+'[11]BG Mois'!$J$546*1000000 -> 29542479 | L62: 29542479 | M62: 0 | N62: 0 | O62: =+'[14]BG Mois'!$J$543*1000000 -> 0 | P62: 0 | Q62: 0 | R62: 0 | S62: 0 | T62: 0 | U62: 0 | V62: 0 | W62: 0 | X62: 0 | Y62: 0 | Z62: 0 | AA62: 0 | AB62: 0 | AC62: 0 | AD62: 0 | AE62: 0 | AF62: 0 | AG62: 0 | AH62: 0 | AI62: 0 | AJ62: 0 | AK62: 0 | AL62: 0 | AZ62: =SUM(AN62:AY62) -> 0
B63: AMORT LOYERS/ IAS16 | P63: 0 | Q63: 0 | R63: -211609345 | S63: -82201317 | T63: -4859371 | U63: -146065508 | V63: -78563730 | W63: -79096121 | X63: -76544616 | Y63: -76544616 | Z63: -76544616 | AA63: -98314861 | AB63: -130952160 | AC63: -158225345 | AD63: 43913441 | AE63: -83492346 | AF63: -84661941 | AG63: -150270388 | AH63: -94235710 | AI63: -93680948 | AJ63: -89900600 | AK63: -94465258 | AL63: -92738870 | AN63: =+'[17]Impacts IFRS 16'!$C$3 -> -64572302 | AO63: =+'[18]Impacts IFRS 16'!$D$3 -> -60884614 | AP63: ='[19]Impacts IFRS 16'!$E$3 -> -62423614 | AZ63: =SUM(AN63:AY63) -> -187880530 | BA63: AD3
B64: Check | D64: 0 | E64: 0 | F64: 0 | G64: =G54-SUM('[20]YTD Avril'!$J$551:$J$556)*1000000 -> 65234045 | H64: 0 | I64: =I54-SUM('[15]YTD Juin'!$J$552:$J$557)*1000000 -> 72764068 | L64: 0 | M64: 0 | N64: 3.0267984e-09 | P64: 0 | Q64: =Q54-SUM('[21]BG Mois'!$J$553:$J$558)*1000000 -> 0 | R64: 1.1175871e-08 | S64: -1.6298145e-08 | T64: -9.3132257e-09 | U64: -2.6077032e-08 | V64: 0 | W64: 1.1546319e-14 | X64: 0 | Y64: 0.0408832 | Z64: 0 | AA64: 0 | AB64: =AB54/1000000-SUM('[22]BG Mois'!$J$404:$J$412) -> 39.052089 | AC64: 1.7763568e-14 | AD64: 0 | AE64: 0 | AF64: 0 | AG64: 1.2079227e-13 | AH64: -9.4591002e-14 | AI64: 3.7303494e-14 | AJ64: 6.6724404e-14 | AK64: 5.7287508e-14 | AL64: -1.4743762e-13 | AM64: 8.1712415e-14
B88: intercompagnie intern fixe vers telmob | D88: 538819050 | E88: 538819050
B89: interco Telmob après supression inter entrant | D89: -109581559 | E89: -109581559
B92: Interco CA Transit Telmob vers International | D92: 385261401 | E92: 385261401
B94: interco Onatel après supression CA Transit Telmob vers International | D94: -490152329 | E94: -490152329

Sheet Opex Consolidés
A2: Opex Consolidés
D3: 2018/001 | E3: 2018/002 | F3: 2018/003 | G3: 2018/004 | H3: 2018/005 | I3: 2018/006 | J3: 2018/007 | K3: 2018/008 | L3: 2018/009 | M3: 2018/009 | N3: 2018/011 | O3: 2018/012 | P3: 2018/012 | Q3: 2018/012 | R3: 2018/012 | S3: 2018/012 | T3: 2018/012 | U3: 2018/012 | V3: 2018/012 | W3: 2018/012
D4: JANVIER | E4: FEVRIER | F4: MARS | G4: AVRIL | H4: MAI | I4: JUIN | J4: JUILLET | K4: AOÛT | L4: SEPT. | M4: OCT | N4: NOV. | O4: DEC | P4: JANV | Q4: FEV | R4: MARS | S4: AVR | T4: MAI | U4: JUIN | V4: JUILLET | W4: AOUT | X4: SEPT | Y4: OCT | Z4: NOV | AA4: DEC | AB4: JANV | AC4: FÉVR | AD4: MARS | AE4: AVR | AF4: MAI | AG4: JUIN | AH4: JUIL | AI4: AOÛT | AJ4: SEPT | AK4: OCT | AL4: NOV | AM4: DÉC
B5: (En Millions ML) | D5: 2019 Réel | E5: 2019 Réel | F5: 2019 Réel | G5: 2019 Réel | H5: 2019 Réel | I5: 2019 Réel | J5: 2019 Réel | K5: 2019 Réel | L5: 2019 Réel | M5: 2019 Réel | N5: 2019 Réel | O5: 2019 Réel | P5: 2020 Réel | Q5: 2020 Réel | R5: 2020 Réel | S5: 2020 Réel | T5: 2020 Réel | U5: 2020 Réel | V5: 2020 Réel | W5: 2020 Réel | X5: 2020 Réel | Y5: 2020 Réel | Z5: 2020 Réel | AA5: 2020 Réel | AB5: 2024 Réel | AC5: 2024 Réel | AD5: 2024 Réel | AE5: 2024 Réel | AF5: 2024 Réel | AG5: 2024 Réel | AH5: 2024 Réel | AI5: 2024 Réel | AJ5: 2024 Réel | AK5: 2024 Réel | AL5: 2024 Réel | AM5: 2024 Réel | AN5: =+'P&L conso'!AZ3 -> 2023
B7: Total Opex | D7: =D9+D11+D13+D21+D28+D33+D39 -> -25842130 | E7: =E9+E11+E13+E21+E28+E33+E39 -> -25842130 | F7: =F9+F11+F13+F21+F28+F33+F39 -> -2.5004213e+08 | G7: =G9+G11+G13+G21+G28+G33+G39 -> -1.210623e+08 | H7: =H9+H11+H13+H21+H28+H33+H39 -> -31115136 | I7: =I9+I11+I13+I21+I28+I33+I39 -> -1.8247527e+08 | J7: =J9+J11+J13+J21+J28+J33+J39 -> -1.0890133e+08 | K7: =K9+K11+K13+K21+K28+K33+K39 -> -1.0958182e+08 | L7: -1.0973137e+08 | M7: =M9+M11+M13+M21+M28+M33+M39 -> -1.0985062e+08 | N7: =N9+N11+N13+N21+N28+N33+N39 -> -1.0985062e+08 | O7: =O9+O11+O13+O21+O28+O33+O39 -> -1.611964e+08 | P7: =P9+P11+P13+P21+P28+P33+P39 -> -1.5590212e+08 | Q7: =Q9+Q11+Q13+Q21+Q28+Q33+Q39 -> -2.2119604e+08 | R7: =R9+R11+R13+R21+R28+R33+R39 -> -19916280 | S7: -1.3019037e+08 | T7: -1.3019037e+08 | U7: -2.683311e+08 | V7: -1.3583707e+08 | W7: -1.2849657e+08 | X7: -1.292504e+08 | Y7: -1.3137707e+08 | Z7: -1.321329e+08 | AA7: -1.4223874e+08 | AB7: =AB9+AB11+AB13+AB21+AB28+AB33+AB39 -> 91880957 | AC7: =AC9+AC11+AC13+AC21+AC28+AC33+AC39 -> 92284289 | AD7: =AD9+AD11+AD13+AD21+AD28+AD33+AD39 -> 88853041 | AE7: =AE9+AE11+AE13+AE21+AE28+AE33+AE39 -> 0 | AF7: =AF9+AF11+AF13+AF21+AF28+AF33+AF39 -> 0 | AG7: =AG9+AG11+AG13+AG21+AG28+AG33+AG39 -> 0 | AH7: =AH9+AH11+AH13+AH21+AH28+AH33+AH39 -> 0 | AI7: =AI9+AI11+AI13+AI21+AI28+AI33+AI39 -> 0 | ... AM7: =AM9+AM11+AM13+AM21+AM28+AM33+AM39 -> 0 | AN7: =SUM(AB7:AM7) -> 2.7301829e+08
B9: Personnel | D9: =-+'[23]YTD Janv'!$J$538*1000000 -> -25842130 | E9: =-'[24]YTD Fév'!$J$529*1000000 -> -25842130 | F9: =E9 -> -25842130 | G9: =+F9 -> -25842130 | H9: =+G9 -> -25842130 | I9: =+H9 -> -25842130 | J9: =I9 -> -25842130 | K9: =J9 -> -25842130 | L9: -25842130 | M9: =+L9 -> -25842130 | N9: =+M9 -> -25842130 | O9: =+N9 -> -25842130 | P9: =+O9 -> -25842130 | Q9: =+P9 -> -25842130 | R9: =+Q9 -> -25842130 | S9: -25842130 | T9: -25842130 | U9: -25842130 | V9: -25842130 | W9: -25842130 | X9: -25842130 | Y9: -25842130 | Z9: -25842130 | AA9: -25842130 | AB9: =25842129.925 -> 25842130 | AC9: =25842129.925 -> 25842130 | AD9: =25842129.925 -> 25842130 | AN9: =SUM(AB9:AM9) -> 77526390
B11: Communication | AN11: =SUM(AB11:AG11) -> 0
B13: Exploitation & maintenance | D13: =+SUM(D14:D19) -> 0 | E13: =+SUM(E14:E19) -> 0 | F13: =+SUM(F14:F19) -> -224200000 | G13: =+SUM(G14:G19) -> -95220174 | H13: =+SUM(H14:H19) -> -5273006 | I13: =+SUM(I14:I19) -> -156633139 | J13: =+SUM(J14:J19) -> -83059205 | K13: =+SUM(K14:K19) -> -83739689 | L13: -83889241 | M13: =+SUM(M14:M19) -> -84008488 | N13: =+SUM(N14:N19) -> -84008488 | O13: =+SUM(O14:O19) -> -135354269 | P13: =+SUM(P14:P19) -> -130059989 | Q13: =+SUM(Q14:Q19) -> -195353912 | R13: =+SUM(R14:R19) -> 5925850 | S13: -104348239 | T13: -104348239 | U13: -242488975 | V13: -109994942 | W13: -102654442 | X13: -103408275 | Y13: -105534942 | Z13: -106290775 | AA13: -116396609 | AB13: =+SUM(AB14:AB19) -> 66038827 | AC13: =+SUM(AC14:AC19) -> 66442159 | AD13: =+SUM(AD14:AD19) -> 63010911 | AE13: =+SUM(AE14:AE19) -> 0 | AF13: =+SUM(AF14:AF19) -> 0 | AG13: =+SUM(AG14:AG19) -> 0 | AH13: =+SUM(AH14:AH19) -> 0 | AI13: =+SUM(AI14:AI19) -> 0 | ... AM13: =+SUM(AM14:AM19) -> 0 | AN13: =SUM(AB13:AM13) -> 195491897
B14: Achat d'énergie - Bâtiment - Gardiennage | F14: -224200000 | G14: -95220174 | H14: -5273006 | I14: -156633139 | J14: -83059205 | K14: -83739689 | L14: -83889241 | M14: -84008488 | N14: -84008488 | O14: -135354269 | P14: -130059989 | Q14: -195353912 | R14: 5925850 | S14: -104348239 | T14: -104348239 | U14: -242488975 | V14: -109994942 | W14: -102654442 | X14: -103408275 | Y14: -105534942 | Z14: -106290775 | AA14: -116396609 | AB14: =+'[17]Impacts IFRS 16'!$C$2 -> 66038827 | AC14: =+'[18]Impacts IFRS 16'!$D$2 -> 66442159 | AD14: ='[19]Impacts IFRS 16'!$E$2 -> 63010911 | AN14: =SUM(AB14:AM14) -> 195491897 | AO14: ='[25]Impacts IFRS 16'!$F$2 -> 238144877
B15: Lignes et réseaux (entretien & achats) | AN15: =SUM(AC15:AG15) -> 0
B16: Fees du contrat GMNS | AN16: =SUM(AC16:AG16) -> 0
B17: Fees du contrat IHS (spécifique à CDI) | AN17: =SUM(AC17:AG17) -> 0
B18: Matériel de transport (Entretien et locat°) | AN18: =SUM(AC18:AG18) -> 0
B19: Maintenance informatique | AN19: =SUM(AC19:AG19) -> 0
AN20: =SUM(AC20:AG20) -> 0
B21: Frais généraux | D21: =SUM(D22:D26) -> 0 | E21: =SUM(E22:E26) -> 0 | F21: =SUM(F22:F26) -> 0 | G21: =SUM(G22:G26) -> 0 | H21: =SUM(H22:H26) -> 0 | I21: =SUM(I22:I26) -> 0 | J21: =SUM(J22:J26) -> 0 | K21: =SUM(K22:K26) -> 0 | L21: 0 | M21: =SUM(M22:M26) -> 0 | N21: =SUM(N22:N26) -> 0 | O21: =SUM(O22:O26) -> 0 | P21: =SUM(P22:P26) -> 0 | Q21: =SUM(Q22:Q26) -> 0 | R21: =SUM(R22:R26) -> 0 | S21: 0 | T21: 0 | U21: 0 | V21: 0 | W21: 0 | X21: 0 | Y21: 0 | Z21: 0 | AA21: 0 | AB21: =SUM(AB22:AB26) -> 0 | AC21: =SUM(AC22:AC26) -> 0 | AD21: =SUM(AD22:AD26) -> 0 | AE21: =SUM(AE22:AE26) -> 0 | AF21: =SUM(AF22:AF26) -> 0 | AG21: =SUM(AG22:AG26) -> 0 | AH21: =SUM(AH22:AH26) -> 0 | AI21: =SUM(AI22:AI26) -> 0 | ... AM21: =SUM(AM22:AM26) -> 0 | AN21: =SUM(AC21:AG21) -> 0
B22: Frais d'achats d'études, honoraires | AN22: =SUM(AC22:AG22) -> 0
B23: Management Fees | AN23: =SUM(AC23:AG23) -> 0
B24: Transport, déplacement, mission | AN24: =SUM(AC24:AG24) -> 0
B25: Frais postaux, bancaires et assurances | AN25: =SUM(AC25:AG25) -> 0
B26: Achats de mat. et fournitures consom. | AN26: =SUM(AC26:AG26) -> 0
AN27: =SUM(AC27:AG27) -> 0
B28: Impôts, taxes et redevances | D28: =SUM(D29:D31) -> 0 | E28: =SUM(E29:E31) -> 0 | F28: =SUM(F29:F31) -> 0 | G28: =SUM(G29:G31) -> 0 | H28: =SUM(H29:H31) -> 0 | I28: =SUM(I29:I31) -> 0 | J28: =SUM(J29:J31) -> 0 | K28: =SUM(K29:K31) -> 0 | L28: 0 | M28: =SUM(M29:M31) -> 0 | N28: =SUM(N29:N31) -> 0 | O28: =SUM(O29:O31) -> 0 | P28: =SUM(P29:P31) -> 0 | Q28: =SUM(Q29:Q31) -> 0 | R28: =SUM(R29:R31) -> 0 | S28: 0 | T28: 0 | U28: 0 | V28: 0 | W28: 0 | X28: 0 | Y28: 0 | Z28: 0 | AA28: 0 | AB28: =SUM(AB29:AB31) -> 0 | AC28: =SUM(AC29:AC31) -> 0 | AD28: =SUM(AD29:AD31) -> 0 | AE28: =SUM(AE29:AE31) -> 0 | AF28: =SUM(AF29:AF31) -> 0 | AG28: =SUM(AG29:AG31) -> 0 | AH28: =SUM(AH29:AH31) -> 0 | AI28: =SUM(AI29:AI31) -> 0 | ... AM28: =SUM(AM29:AM31) -> 0 | AN28: =SUM(AC28:AG28) -> 0
B29: Redevances régulateur | AN29: =SUM(AC29:AG29) -> 0
B30: Droits sur le trafic International Entrant | AN30: =SUM(AC30:AG30) -> 0
B31: Autres impôts et taxes | AN31: =SUM(AC31:AG31) -> 0
AN32: =SUM(AC32:AG32) -> 0
B33: Provision clients, R&C & NC | D33: =SUM(D34:D37) -> 0 | E33: =SUM(E34:E37) -> 0 | F33: =SUM(F34:F37) -> 0 | G33: =SUM(G34:G37) -> 0 | H33: =SUM(H34:H37) -> 0 | I33: =SUM(I34:I37) -> 0 | J33: =SUM(J34:J37) -> 0 | K33: =SUM(K34:K37) -> 0 | L33: 0 | M33: =SUM(M34:M37) -> 0 | N33: =SUM(N34:N37) -> 0 | O33: =SUM(O34:O37) -> 0 | P33: =SUM(P34:P37) -> 0 | Q33: =SUM(Q34:Q37) -> 0 | R33: =SUM(R34:R37) -> 0 | S33: 0 | T33: 0 | U33: 0 | V33: 0 | W33: 0 | X33: 0 | Y33: 0 | Z33: 0 | AA33: 0 | AB33: =SUM(AB34:AB37) -> 0 | AC33: =SUM(AC34:AC37) -> 0 | AD33: =SUM(AD34:AD37) -> 0 | AE33: =SUM(AE34:AE37) -> 0 | AF33: =SUM(AF34:AF37) -> 0 | AG33: =SUM(AG34:AG37) -> 0 | AH33: =SUM(AH34:AH37) -> 0 | AI33: =SUM(AI34:AI37) -> 0 | ... AM33: =SUM(AM34:AM37) -> 0 | AN33: =SUM(AB33:AM33) -> 0
B34: Prov. Créances clients | AN34: =SUM(AC34:AG34) -> 0
B35: Prov. R&C | AN35: =SUM(AC35:AG35) -> 0
B36: PIDR | D36: =(D42+D43+D45)*0 -> 0 | E36: =E42+E43+E45 -> 0 | F36: =F42+F43+F45 -> 0 | G36: =G42+G43+G45 -> 0 | H36: =H42+H43+H45 -> 0 | I36: =I42+I43+I45 -> 0 | J36: =J42+J43+J45 -> 0 | K36: =K42+K43+K45 -> 0 | L36: 0 | M36: =M42+M43+M45 -> 0 | N36: =N42+N43+N45 -> 0 | O36: =O42+O43+O45 -> 0 | P36: =P42+P43+P45 -> 0 | Q36: =Q42+Q43+Q45 -> 0 | R36: =R42+R43+R45 -> 0 | S36: 0 | T36: 0 | U36: 0 | V36: 0 | W36: 0 | X36: 0 | Y36: 0 | Z36: 0 | AA36: 0 | AB36: =AB42+AB43+AB45 -> 0 | AC36: =AC42+AC43+AC45 -> 0 | AD36: =AD42+AD43+AD45 -> 0 | AE36: =AE42+AE43+AE45 -> 0 | AF36: =AF42+AF43+AF45 -> 0 | AG36: =AG42+AG43+AG45 -> 0 | AH36: =AH42+AH43+AH45 -> 0 | AI36: =AI42+AI43+AI45 -> 0 | ... AM36: =AM42+AM43+AM45 -> 0 | AN36: =SUM(AC36:AG36) -> 0
B37: Autres provisions | AN37: =SUM(AC37:AG37) -> 0
AN38: =SUM(AC38:AG38) -> 0
B39: Ecart de change sur exploitation | AN39: =SUM(AB39:AM39) -> 0
AN40: =SUM(AC40:AG40) -> 0
AN41: =SUM(AC41:AG41) -> 0
B42: Annualtion PIDR IFRS Fin Avril 2015 | AN42: =SUM(AC42:AG42) -> 0
B43: PIDR MERCER 2017 | D43: =258038248/12*0 -> 0 | E43: =+D43 -> 0 | F43: =+E43 -> 0 | G43: =+F43 -> 0 | H43: =+G43 -> 0 | I43: =+H43 -> 0 | J43: =+I43 -> 0 | K43: =+J43 -> 0 | L43: 0 | M43: =+L43 -> 0 | N43: =+M43 -> 0 | O43: =+N43 -> 0 | P43: =+O43 -> 0 | Q43: =+P43 -> 0 | R43: =+Q43 -> 0 | S43: 0 | T43: 0 | U43: 0 | V43: 0 | W43: 0 | X43: 0 | Y43: 0 | Z43: 0 | AA43: 0 | AB43: =+AM43 -> 0 | AN43: =SUM(AC43:AG43) -> 0
B44: PIDR Cptes Sociaux | AN44: =SUM(AC44:AG44) -> 0 | AW44: AT CDI 2017.12 | AY44: Flux BFC
B45: Annulation PIDR Cptes Sociaux | D45: =-D44 -> 0 | E45: =-E44 -> 0 | F45: =-F44 -> 0 | G45: =-G44 -> 0 | H45: =-H44 -> 0 | I45: =-I44 -> 0 | J45: =-J44 -> 0 | K45: =-K44 -> 0 | L45: 0 | M45: =-M44 -> 0 | N45: =-N44 -> 0 | O45: =-O44 -> 0 | P45: =-P44 -> 0 | Q45: =-Q44 -> 0 | R45: =-R44 -> 0 | S45: 0 | T45: 0 | U45: 0 | V45: 0 | W45: 0 | X45: 0 | Y45: 0 | Z45: 0 | AA45: 0 | AB45: =-AB44 -> 0 | AN45: =SUM(AC45:AG45) -> 0
B46: TOTAL PIDR | D46: =SUM(D42:D45) -> 0 | E46: =SUM(E42:E45) -> 0 | F46: =SUM(F42:F45) -> 0 | G46: =SUM(G42:G45) -> 0 | H46: =SUM(H42:H45) -> 0 | I46: =SUM(I42:I45) -> 0 | J46: =SUM(J42:J45) -> 0 | K46: =SUM(K42:K45) -> 0 | L46: 0 | M46: =SUM(M42:M45) -> 0 | N46: =SUM(N42:N45) -> 0 | O46: =SUM(O42:O45) -> 0 | P46: =SUM(P42:P45) -> 0 | Q46: =SUM(Q42:Q45) -> 0 | R46: =SUM(R42:R45) -> 0 | S46: 0 | T46: 0 | U46: 0 | V46: 0 | W46: 0 | X46: 0 | Y46: 0 | Z46: 0 | AA46: 0 | AB46: =SUM(AB42:AB45) -> 0 | AN46: =SUM(AB46:AM46) -> 0 | AV46: Solde d'ouverture | AW46: =+'[26]Disclosure Results'!$AL$21/10^6 -> 2022.8479 | AY46: F00
B47: Charges financières | D47: =77380698/12*0 -> 0 | E47: =+D47 -> 0 | F47: 51379512 | G47: 2028681 | H47: 882940 | I47: 52684470 | J47: 20358747 | K47: 16817672 | L47: 13820921 | M47: 16046566 | N47: 16046566 | O47: 39383678 | P47: 28872361 | Q47: 33468953 | R47: -4270680 | S47: 18847232 | T47: 48734075 | U47: 123679295 | V47: 32993319 | W47: 21365147 | X47: 13158859 | Y47: 32896245 | Z47: 21041536 | AA47: 13516617 | AB47: =+'[17]Impacts IFRS 16'!$C$4 -> -5589000 | AC47: =+'[18]Impacts IFRS 16'!$D$4 -> -6645038 | AD47: ='[19]Impacts IFRS 16'!$E$4 -> -6321756 | AN47: =SUM(AB47:AM47) -> -18555794 | AV47: Coût des services rendus | AW47: 241.00399 | AY47: F25
B48: Pertes et gains actuariels comptabilisés en autres éléments du résultat global Charges et produits comptabilisés en capitaux propres | AN48: =SUM(AC48:AG48) -> 0 | AV48: Prestations versées aux bénéficiaires (cash) | AY48: F45
AN49: =SUM(AC49:AG49) -> 0 | AV49: Impact EBITA | AW49: =+AW47+AW48 -> 241.00399
B50: Annulation ID | AN50: =SUM(AC50:AM50) -> 0 | AV50: Effets de la désactualisation des passifs actuariels (a) | AW50: 68.776828 | AY50: F98
B51: ID MERCER 2017 | D51: =(D43+D47+D45)*-30% -> 0 | E51: =(E43+E47+E45)*-30% -> 0 | F51: =(F43+F47+F45)*-30% -> -15413854 | G51: =(G43+G47+G45)*-30% -> -608604.3 | H51: =(H43+H47+H45)*-30% -> -264882 | I51: =(I43+I47+I45)*-30% -> -15805341 | J51: =(J43+J47+J45)*-30% -> -6107624.1 | K51: =(K43+K47+K45)*-30% -> -5045301.6 | L51: -4146276.3 | M51: =(M43+M47+M45)*-30% -> -4813969.8 | N51: =(N43+N47+N45)*-30% -> -4813969.8 | O51: =(O43+O47+O45)*-30% -> -11815103 | P51: =(P43+P47+P45)*-30% -> -8661708.3 | Q51: =(Q43+Q47+Q45)*-30% -> -10040686 | R51: =(R43+R47+R45)*-30% -> 1281204 | S51: -5654169.6 | T51: -14620222 | U51: -37103788 | V51: -9897995.7 | W51: -6409544.1 | X51: -3947657.7 | Y51: -9868873.5 | Z51: -6312460.8 | AA51: -4054985.1 | AN51: =SUM(AC51:AM51) -> 0 | AV51: Charge de la période | AW51: =+AW49+AW50 -> 309.78082
B52: TOTAL ID | D52: =SUM(D50:D51) -> 0 | E52: =SUM(E50:E51) -> 0 | F52: =SUM(F50:F51) -> -15413854 | G52: =SUM(G50:G51) -> -608604.3 | H52: =SUM(H50:H51) -> -264882 | I52: =SUM(I50:I51) -> -15805341 | J52: =SUM(J50:J51) -> -6107624.1 | K52: =SUM(K50:K51) -> -5045301.6 | L52: -4146276.3 | M52: =SUM(M50:M51) -> -4813969.8 | N52: =SUM(N50:N51) -> -4813969.8 | O52: =SUM(O50:O51) -> -11815103 | P52: =SUM(P50:P51) -> -8661708.3 | Q52: =SUM(Q50:Q51) -> -10040686 | R52: =SUM(R50:R51) -> 1281204 | S52: -5654169.6 | T52: -14620222 | U52: -37103788 | V52: -9897995.7 | W52: -6409544.1 | X52: -3947657.7 | Y52: -9868873.5 | Z52: -6312460.8 | AA52: -4054985.1 | AB52: =SUM(AB50:AB51) -> 0 | AC52: =SUM(AC50:AC51) -> 0 | AD52: =SUM(AD50:AD51) -> 0 | AE52: =SUM(AE50:AE51) -> 0 | AF52: =SUM(AF50:AF51) -> 0 | AG52: =SUM(AG50:AG51) -> 0 | AH52: =SUM(AH50:AH51) -> 0 | AI52: =SUM(AI50:AI51) -> 0 | ... AM52: =SUM(AM50:AM51) -> 0 | AN52: =SUM(AC52:AM52) -> 0 | AV52: Pertes et gains actuariels comptabilisés en autres éléments du résultat global | AW52: 85.518091 | AY52: F87
AV53: Charges et produits comptabilisés directement en capitaux propres | AW53: =+AW52 -> 85.518091
AV54: Solde de clôture | AW54: =+AW46+AW51+AW53 -> 2418.1468

Sheet Marge Mobile
A2: Marge brute Mobile
D5: JANVIER | E5: FEVRIER | F5: MARS | G5: AVRIL | H5: MAI | I5: JUIN | J5: JUILLET | K5: AOÛT | L5: SEPTEMBRE | M5: OCTOBRE | N5: NOVEMBRE | O5: DÉCEMBRE | P5: JANV | Q5: FEV | R5: MARS | S5: AVRIL | T5: MAI | U5: JUIN | V5: JUILLET | W5: AOUT | X5: SEPT | Y5: OCT | Z5: NOV | AA5: DEC | AB5: JANV | AC5: FEV | AD5: MARS | AE5: AVRIL | AF5: MAI | AG5: JUIN | AH5: JUILLET | AI5: AOUT | AJ5: SEPT | AK5: OCT | AL5: NOV | AM5: DEC | AN5: JANV | AO5: FÉVR | AP5: MARS | AQ5: AVR | AR5: MAI | AS5: JUIN | AT5: JUIL | AU5: AOÛT | AV5: SEPT | AW5: OCT | AX5: NOV | AY5: DÉC
B6: (En Millions ML) | D6: 2018 Réel | E6: 2018 Réel | F6: 2018 Réel | G6: 2018 Réel | H6: 2018 Réel | I6: 2018 Réel | J6: 2018 Réel | K6: 2018 Réel | L6: 2018 Réel | M6: 2018 Réel | N6: 2018 Réel | O6: 2018 Réel | P6: 2019 Réel | Q6: 2019 Réel | R6: 2019 Réel | S6: 2019 Réel | T6: 2019 Réel | U6: 2019 Réel | V6: 2019 Réel | W6: 2019 Réel | X6: 2019 Réel | Y6: 2019 Réel | Z6: 2019 Réel | AA6: 2019 Réel | AB6: 2020 Réel | AC6: 2020 Réel | AD6: 2020 Réel | AE6: 2020 Réel | AF6: 2020 Réel | AG6: 2020 Réel | AH6: 2020 Réel | AI6: 2020 Réel | AJ6: 2020 Réel | AK6: 2020 Réel | AL6: 2020 Réel | AM6: 2021 Réel | AN6: 2024 Réel | AO6: 2024 Réel | AP6: 2024 Réel | AQ6: 2024 Réel | AR6: 2024 Réel | AS6: 2024 Réel | AT6: 2024 Réel | AU6: 2024 Réel | AV6: 2024 Réel | AW6: 2024 Réel | AX6: 2024 Réel | AY6: 2024 Réel | AZ6: 2024
A8: Total Revenu | D8: ='CA Mobile'!D8 -> 0 | E8: ='CA Mobile'!E8 -> 0 | F8: ='CA Mobile'!F8 -> 0 | G8: ='CA Mobile'!G8 -> 0 | H8: ='CA Mobile'!H8 -> 0 | I8: ='CA Mobile'!I8 -> 0 | J8: ='CA Mobile'!J8 -> 0 | K8: ='CA Mobile'!K8 -> 0 | ... T8: ='CA Mobile'!T8 -> 0 | U8: 0 | V8: ='CA Mobile'!V8 -> 0 | W8: ='CA Mobile'!W8 -> 0 | X8: 0 | Y8: ='CA Mobile'!Y8 -> 0 | Z8: ='CA Mobile'!Z8 -> 0 | AA8: ='CA Mobile'!AA8 -> 0 | AB8: ='CA Mobile'!AB8 -> 0 | AC8: ='CA Mobile'!AC8 -> 0 | AD8: ='CA Mobile'!AD8 -> 0 | AE8: 0 | AF8: 0 | AG8: 0 | AH8: 0 | AI8: 0 | AJ8: 0 | AK8: 0 | AL8: 0 | AM8: 0 | AN8: ='CA Mobile'!AY8 -> 0 | AO8: ='CA Mobile'!AZ8 -> 0 | AP8: ='CA Mobile'!BA8 -> 0 | AQ8: ='CA Mobile'!BB8 -> 0 | AR8: ='CA Mobile'!BC8 -> 0 | AS8: ='CA Mobile'!BD8 -> 0 | AT8: ='CA Mobile'!BE8 -> 0 | AU8: ='CA Mobile'!BF8 -> 0 | ... AX8: ='CA Mobile'!BI8 -> 0 | AZ8: =SUM(AN8:AY8) -> 0
B9: Trafic (mn)
B10: Coût unitaire
B11: International
B12: Trafic (mn)
B13: Coût unitaire
B14: Opérateur national MTN
B15: Trafic (mn)
B16: Coût unitaire
B17: Opérateur national ORANGE
B18: Trafic (mn) | BC18: =+'[27]BG Momo'!$I$23 -> 0
B19: Coût unitaire
B20: Opérateur national AUTRES MOBILES
B21: Trafic Local (mn)
B22: Coût unitaire
B23: Trafic Interurbain (mn)
B24: Coût unitaire
B25: Interconnexion Fixe | BC25: ='[28]BG Momo'!$L$11 -> -431010580
B26: Nbre SMS
B27: Coût unitaire
B28: Interconnexion SMS | AX28: =+AT20 -> 0
B29: Roaming out
B31: Coûts des terminaux et cartes | D31: =SUM(D32:D35) -> 55200422 | E31: =SUM(E32:E35) -> 42367549 | F31: =SUM(F32:F35) -> 28904193 | G31: =SUM(G32:G35) -> 42458421 | H31: =SUM(H32:H35) -> 32149914 | I31: =SUM(I32:I35) -> 25253867 | J31: =SUM(J32:J35) -> 80516153 | K31: =SUM(K32:K35) -> 80516153 | ... T31: =SUM(T32:T35) -> 80516153 | U31: 40104587 | V31: =SUM(V32:V35) -> 80516153 | W31: =SUM(W32:W35) -> 80516153 | X31: -28395624 | Y31: =SUM(Y32:Y35) -> 80516153 | Z31: =SUM(Z32:Z35) -> 80516153 | AA31: =SUM(AA32:AA35) -> 80516153 | AB31: =SUM(AB32:AB35) -> 80516153 | AC31: =SUM(AC32:AC35) -> 80516153 | AD31: =SUM(AD32:AD35) -> 80516153 | AE31: 30823902 | AF31: 19840831 | AG31: 17693198 | AH31: 28827141 | AI31: 22601249 | AJ31: 17308736 | AK31: 31536601 | AL31: 690912 | AM31: 27436532 | AN31: =SUM(AN32:AN35) -> 34618808 | AO31: =SUM(AO32:AO35) -> 37772426 | AP31: =SUM(AP32:AP35) -> 47698819 | AQ31: =SUM(AQ32:AQ35) -> 0 | AR31: =SUM(AR32:AR35) -> 0 | AS31: =SUM(AS32:AS35) -> 0 | AT31: =SUM(AT32:AT35) -> 0 | AU31: =SUM(AU32:AU35) -> 0 | ... AZ31: =SUM(AZ32:AZ35) -> 120090053
B32: Dont coût des cartes SIM | D32: 55200422 | E32: 42367549 | F32: 28904193 | G32: 42458421 | H32: 32149914 | I32: =+'[15]YTD Juin'!$J$554*1000000 -> 25253867 | J32: =+'[29]BG ETI'!$L$340+'[29]BG ETI'!$L$344 -> 80516153 | K32: =+'[29]BG ETI'!$L$340+'[29]BG ETI'!$L$344 -> 80516153 | L32: =+'[29]BG ETI'!$L$340+'[29]BG ETI'!$L$344 -> 80516153 | M32: =+'[29]BG ETI'!$L$340+'[29]BG ETI'!$L$344 -> 80516153 | N32: =+'[29]BG ETI'!$L$340+'[29]BG ETI'!$L$344 -> 80516153 | O32: =+'[29]BG ETI'!$L$340+'[29]BG ETI'!$L$344 -> 80516153 | P32: =+'[29]BG ETI'!$L$340+'[29]BG ETI'!$L$344 -> 80516153 | Q32: =+'[29]BG ETI'!$L$340+'[29]BG ETI'!$L$344 -> 80516153 | ... AM32: =+'[29]BG ETI'!$L$340+'[29]BG ETI'!$L$344 -> 80516153 | AN32: =SUMIFS('[27]BG ETI'!$L$1:$L$1048576,'[27]BG ETI'!$A$1:$A$1048576,"601230")+SUMIFS('[27]BG ETI'!$L$1:$L$1048576,'[27]BG ETI'!$A$1:$A$1048576,"603130") -> 34618808 | AO32: 37772426 | AP32: =SUMIFS('[28]BG ETI'!$L$1:$L$1048576,'[28]BG ETI'!$A$1:$A$1048576,"601230")+SUMIFS('[28]BG ETI'!$L$1:$L$1048576,'[28]BG ETI'!$A$1:$A$1048576,"603130") -> 47698819 | AZ32: =SUM(AN32:AY32) -> 120090053 | BA32: SIM
B33: Dont coût des cartes de recharge vendues
B34: Dont coût des terminaux | BA34: 1000000
B35: Dont provisions sur stocks
B36: Reversement SVA
B37: Blackberry
B38: Commissions | D38: =SUM(D39:D40) -> 0 | E38: =SUM(E39:E40) -> 0 | F38: =SUM(F39:F40) -> 0 | G38: =SUM(G39:G40) -> 0 | H38: =SUM(H39:H40) -> 0 | I38: =SUM(I39:I40) -> 0 | J38: =SUM(J39:J40) -> 0 | K38: =SUM(K39:K40) -> 0 | ... T38: =SUM(T39:T40) -> 0 | U38: 0 | V38: =SUM(V39:V40) -> 0 | W38: =SUM(W39:W40) -> 0 | X38: 0 | Y38: =SUM(Y39:Y40) -> 0 | Z38: =SUM(Z39:Z40) -> 0 | AA38: =SUM(AA39:AA40) -> 0 | AB38: =SUM(AB39:AB40) -> 0 | AC38: =SUM(AC39:AC40) -> 0 | AD38: =SUM(AD39:AD40) -> 0 | AE38: 0 | AF38: 0 | AG38: 0 | AH38: 0 | AI38: 0 | AJ38: 0 | AK38: 0 | AL38: 0 | AM38: 0 | AN38: =SUM(AN39:AN40) -> 0 | AZ38: =SUM(AZ39:AZ40) -> 0
B39: Dont commissions up-front
B40: Dont avoirs de performance
A42: Coûts des ventes | D42: =D11+D14+D17+D20+D25+D28+D29+D31+D36+D37+D38 -> 55200422 | E42: =E11+E14+E17+E20+E25+E28+E29+E31+E36+E37+E38 -> 42367549 | F42: =F11+F14+F17+F20+F25+F28+F29+F31+F36+F37+F38 -> 28904193 | G42: =G11+G14+G17+G20+G25+G28+G29+G31+G36+G37+G38 -> 42458421 | H42: =H11+H14+H17+H20+H25+H28+H29+H31+H36+H37+H38 -> 32149914 | I42: =I11+I14+I17+I20+I25+I28+I29+I31+I36+I37+I38 -> 25253867 | J42: =J11+J14+J17+J20+J25+J28+J29+J31+J36+J37+J38 -> 80516153 | K42: =K11+K14+K17+K20+K25+K28+K29+K31+K36+K37+K38 -> 80516153 | ... T42: =T11+T14+T17+T20+T25+T28+T29+T31+T36+T37+T38 -> 80516153 | U42: 40104587 | V42: =V11+V14+V17+V20+V25+V28+V29+V31+V36+V37+V38 -> 80516153 | W42: =W11+W14+W17+W20+W25+W28+W29+W31+W36+W37+W38 -> 80516153 | X42: -28395624 | Y42: =Y11+Y14+Y17+Y20+Y25+Y28+Y29+Y31+Y36+Y37+Y38 -> 80516153 | Z42: =Z11+Z14+Z17+Z20+Z25+Z28+Z29+Z31+Z36+Z37+Z38 -> 80516153 | AA42: =AA11+AA14+AA17+AA20+AA25+AA28+AA29+AA31+AA36+AA37+AA38 -> 80516153 | AB42: =AB11+AB14+AB17+AB20+AB25+AB28+AB29+AB31+AB36+AB37+AB38 -> 80516153 | AC42: =AC11+AC14+AC17+AC20+AC25+AC28+AC29+AC31+AC36+AC37+AC38 -> 80516153 | AD42: =AD11+AD14+AD17+AD20+AD25+AD28+AD29+AD31+AD36+AD37+AD38 -> 80516153 | AE42: 30823902 | AF42: 19840831 | AG42: 17693198 | AH42: 28827141 | AI42: 22601249 | AJ42: 17308736 | AK42: 31536601 | AL42: 690912 | AM42: 27436532 | AN42: =AN11+AN14+AN17+AN20+AN25+AN28+AN29+AN31+AN36+AN37+AN38 -> 34618808 | AO42: =AO11+AO14+AO17+AO20+AO25+AO28+AO29+AO31+AO36+AO37+AO38 -> 37772426 | AP42: =AP11+AP14+AP17+AP20+AP25+AP28+AP29+AP31+AP36+AP37+AP38 -> 47698819 | AQ42: =AQ11+AQ14+AQ17+AQ20+AQ25+AQ28+AQ29+AQ31+AQ36+AQ37+AQ38 -> 0 | AR42: =AR11+AR14+AR17+AR20+AR25+AR28+AR29+AR31+AR36+AR37+AR38 -> 0 | AS42: =AS11+AS14+AS17+AS20+AS25+AS28+AS29+AS31+AS36+AS37+AS38 -> 0 | AT42: =AT11+AT14+AT17+AT20+AT25+AT28+AT29+AT31+AT36+AT37+AT38 -> 0 | AU42: =AU11+AU14+AU17+AU20+AU25+AU28+AU29+AU31+AU36+AU37+AU38 -> 0 | ... AZ42: =AZ11+AZ14+AZ17+AZ20+AZ25+AZ28+AZ29+AZ31+AZ36+AZ37+AZ38 -> 120090053
A44: Marge Brute | D44: =+D8-D42 -> -55200422 | E44: =+E8-E42 -> -42367549 | F44: =+F8-F42 -> -28904193 | G44: =+G8-G42 -> -42458421 | H44: =+H8-H42 -> -32149914 | I44: =+I8-I42 -> -25253867 | J44: =+J8-J42 -> -80516153 | K44: =+K8-K42 -> -80516153 | ... T44: =+T8-T42 -> -80516153 | U44: -40104587 | V44: =+V8-V42 -> -80516153 | W44: =+W8-W42 -> -80516153 | X44: 28395624 | Y44: =+Y8-Y42 -> -80516153 | Z44: =+Z8-Z42 -> -80516153 | AA44: =+AA8-AA42 -> -80516153 | AB44: =+AB8-AB42 -> -80516153 | AC44: =+AC8-AC42 -> -80516153 | AD44: =+AD8-AD42 -> -80516153 | AE44: -30823902 | AF44: -19840831 | AG44: -17693198 | AH44: -28827141 | AI44: -22601249 | AJ44: -17308736 | AK44: -31536601 | AL44: -690912 | AM44: -27436532 | AN44: =+AN8-AN42 -> -34618808 | AO44: =+AO8-AO42 -> -37772426 | AP44: =+AP8-AP42 -> -47698819 | AQ44: =+AQ8-AQ42 -> 0 | AR44: =+AR8-AR42 -> 0 | AS44: =+AS8-AS42 -> 0 | AT44: =+AT8-AT42 -> 0 | AU44: =+AU8-AU42 -> 0 | ... AZ44: =+AZ8-AZ42 -> -120090053
A45: En % du CA | D45: =D44/D8 -> #DIV/0! | E45: =E44/E8 -> #DIV/0! | F45: =F44/F8 -> #DIV/0! | G45: =G44/G8 -> #DIV/0! | H45: =H44/H8 -> #DIV/0! | I45: =I44/I8 -> #DIV/0! | J45: =J44/J8 -> #DIV/0! | K45: =K44/K8 -> #DIV/0! | ... P45: =P44/P8 -> #DIV/0! | AZ45: =AZ44/AZ8 -> #DIV/0!

Sheet CA Mobile
A2: CA Mobile | D2: =D16/31/10^6 -> 0 | E2: =E16/28/10^6 -> 0 | F2: =F16/31/10^6 -> 0 | G2: =G16/30/10^6 -> 0 | H2: =H16/31/10^6 -> 0 | I2: =I16/30/10^6 -> 0 | J2: =J16/31/10^6 -> 0 | K2: =K16/31/10^6 -> 0 | L2: =L16/30/10^6 -> 0 | M2: =M16/31/10^6 -> 0 | N2: =N16/30/10^6 -> 0 | O2: =O16/31/10^6 -> 0
D4: JANVIER | E4: FEVRIER | F4: MARS | G4: AVRIL | H4: MAI | I4: JUIN | J4: JUILLET | K4: AOÛT | L4: SEPTEMBRE | M4: OCTOBRE | N4: NOVEMBRE | O4: DÉCEMBRE
B5: (En Millions ML) | D5: 2018 Réel | E5: 2018 Réel | F5: 2018 Réel | G5: 2018 Réel | H5: 2018 Réel | I5: 2018 Réel | J5: 2018 Réel | K5: 2018 Réel | L5: 2018 Réel | M5: 2018 Réel | N5: 2018 Réel | O5: 2018 Réel | P5: 2018
A8: CA Global | D8: =D12+D39 -> 0 | E8: =E12+E39 -> 0 | F8: =F12+F39+F45 -> 0 | G8: =G12+G39+G45 -> 0 | H8: =H12+H39+H45 -> 0 | I8: =I12+I39+I45 -> 0 | J8: =J12+J39+J45 -> 0 | K8: =K12+K39+K45 -> 0 | L8: =L12+L39+L45 -> 0 | M8: =M12+M39+M45 -> 0 | ... P8: =P12+P39+P45 -> 0
A10: dont CA Etat
A12: CA services Mobile | D12: =D14+D37 -> 0 | E12: =E14+E37 -> 0 | F12: =F14+F37 -> 0 | G12: =G14+G37 -> 0 | H12: =H14+H37 -> 0 | I12: =I14+I37 -> 0 | J12: =J14+J37 -> 0 | K12: =K14+K37 -> 0 | ... P12: =P14+P37 -> 0
A14: CA récurrent | D14: =D16+D24+D31 -> 0 | E14: =E16+E24+E31 -> 0 | F14: =F16+F24+F31 -> 0 | G14: =G16+G24+G31 -> 0 | H14: =H16+H24+H31 -> 0 | I14: =I16+I24+I31 -> 0 | J14: =J16+J24+J31 -> 0 | K14: =K16+K24+K31 -> 0 | ... P14: =P16+P24+P31 -> 0
A16: CA sortant | D16: =D17+D19 -> 0 | E16: =E17+E19 -> 0 | F16: =F17+F19 -> 0 | G16: =G17+G19 -> 0 | H16: =H17+H19 -> 0 | I16: =I17+I19 -> 0 | J16: =J17+J19 -> 0 | K16: =K17+K19 -> 0 | ... P16: =P17+P19 -> 0
B17: Prépayé (yc commissions)
B18: dont CA Internet 3G
B19: Postpayé | D19: =D20+D21 -> 0 | E19: =E20+E21 -> 0 | F19: =F20+F21 -> 0 | G19: =G20+G21 -> 0 | H19: =H20+H21 -> 0 | I19: =I20+I21 -> 0 | J19: =J20+J21 -> 0 | K19: =K20+K21 -> 0 | ... P19: =P20+P21 -> 0
B20: Redevance d'abonnement
B21: Trafic sortant
B22: dont CA Internet 3G
A24: CA entrant | D24: =SUM(D25:D28) -> 0 | E24: =SUM(E25:E28) -> 0 | F24: =SUM(F25:F28) -> 0 | G24: =SUM(G25:G28) -> 0 | H24: =SUM(H25:H28) -> 0 | I24: =SUM(I25:I28) -> 0 | J24: =SUM(J25:J28) -> 0 | K24: =SUM(K25:K28) -> 0 | ... P24: =SUM(P25:P28) -> 0
B25: Opérateur national MTN
B26: Opérateur national ORANGE
B27: Opérateur national AUTRES MOBILES
B28: International
A31: Colocalisation | D31: =SUM(D33:D35) -> 0 | E31: =SUM(E33:E35) -> 0 | F31: =SUM(F33:F35) -> 0 | G31: =SUM(G33:G35) -> 0 | H31: =SUM(H33:H35) -> 0 | I31: =SUM(I33:I35) -> 0 | J31: =SUM(J33:J35) -> 0 | K31: =SUM(K33:K35) -> 0 | ... P31: =SUM(P33:P35) -> 0
B33: Opérateur national 1 | D33: 0 | E33: 0 | F33: 0 | G33: 0 | H33: 0 | I33: 0 | J33: 0 | K33: 0 | L33: 0 | M33: 0 | N33: 0 | O33: 0 | P33: 0
B34: Opérateur national 2 | D34: 0 | E34: 0 | F34: 0 | G34: 0 | H34: 0 | I34: 0 | J34: 0 | K34: 0 | L34: 0 | M34: 0 | N34: 0 | O34: 0 | P34: 0
B35: Opérateur national 3 | D35: 0 | E35: 0 | F35: 0 | G35: 0 | H35: 0 | I35: 0 | J35: 0 | K35: 0 | L35: 0 | M35: 0 | N35: 0 | O35: 0 | P35: 0
A37: Roaming in | P37: =SUM(D37:O37) -> 0
A39: CA équipement | D39: =SUM(D40:D42) -> 0 | E39: =SUM(E40:E42) -> 0 | F39: =SUM(F40:F42) -> 0 | G39: =SUM(G40:G42) -> 0 | H39: =SUM(H40:H42) -> 0 | I39: =SUM(I40:I42) -> 0 | J39: =SUM(J40:J42) -> 0 | K39: =SUM(K40:K42) -> 0 | ... P39: =SUM(P40:P42) -> 0
B40: Ventes de Terminaux
B41: Ventes de Kits
B42: Autres
A45: CA Flooz | P45: =SUM(D45:O45) -> 0
F47: 0 | G47: 0 | H47: 0 | I47: 0 | J47: 0 | K47: 0 | L47: 0 | M47: 0 | N47: 0 | O47: 0

Sheet Reclassement P&L conso
B1: P&L consolidé
D2: JANVIER | E2: FEVRIER | F2: MARS | G2: AVRIL | H2: MAI | I2: JUIN | J2: JUILLET | K2: AOÛT | L2: SEPTEMBRE | M2: OCTOBRE | N2: NOVEMBRE | O2: DÉCEMBRE
B3: (En Millions ML) | D3: 2018 Réel | E3: 2018 Réel | F3: 2018 Réel | G3: 2018 Réel | H3: 2018 Réel | I3: 2018 Réel | J3: 2018 Réel | K3: 2018 Réel | L3: 2018 Réel | M3: 2018 Réel | N3: 2018 Réel | O3: 2018 Réel | P3: 2018
B5: Chiffre d'affaires | D5: ='CA Mobile'!D8 -> 0 | E5: ='CA Mobile'!E8 -> 0 | F5: ='CA Mobile'!F8 -> 0 | G5: ='CA Mobile'!G8 -> 0 | H5: ='CA Mobile'!H8 -> 0 | I5: ='CA Mobile'!I8 -> 0 | J5: ='CA Mobile'!J8 -> 0 | K5: ='CA Mobile'!K8 -> 0 | ... O5: ='CA Mobile'!O8 -> 0 | P5: =SUM(D5:O5) -> 0
B6: Fixe & Internet
B7: Intercompagnie Fixe & Internet
B8: Mobile
B9: Intercompagnie Mobile
B11: Intercompagnie
B12: dont Intercompagnie hors trafic
B14: Coût des ventes | D14: =-'Reclassement Marge Mobile'!D42 -> 0 | E14: =-'Reclassement Marge Mobile'!E42 -> 0 | F14: =-'Reclassement Marge Mobile'!F42 -> 0 | G14: =-'Reclassement Marge Mobile'!G42 -> 0 | H14: =-'Reclassement Marge Mobile'!H42 -> 0 | I14: =-'Reclassement Marge Mobile'!I42 -> 0 | J14: =-'Reclassement Marge Mobile'!J42 -> 0 | K14: =-'Reclassement Marge Mobile'!K42 -> 0 | ... O14: =-'Reclassement Marge Mobile'!O42 -> 0 | P14: =SUM(D14:O14) -> 0
B15: Fixe & Internet
B16: Intercompagnie Fixe & Internet
B17: Mobile
B18: Intercompagnie Mobile
B20: Marge Brute | D20: =D5+D14 -> 0 | E20: =E5+E14 -> 0 | F20: =F5+F14 -> 0 | G20: =G5+G14 -> 0 | H20: =H5+H14 -> 0 | I20: =I5+I14 -> 0 | J20: =J5+J14 -> 0 | K20: =K5+K14 -> 0 | ... O20: =O5+O14 -> 0 | P20: =SUM(D20:O20) -> 0
B21: % CA
B22: Fixe & Internet
B23: Mobile
B25: Coûts opérationnels | D25: =-'Reclassement Opex Consolidés'!D7 -> 0 | E25: =-'Reclassement Opex Consolidés'!E7 -> 0 | F25: =-'Reclassement Opex Consolidés'!F7 -> 0 | G25: =-'Reclassement Opex Consolidés'!G7 -> 0 | H25: =-'Reclassement Opex Consolidés'!H7 -> 0 | I25: =-'Reclassement Opex Consolidés'!I7 -> 0 | J25: =-'Reclassement Opex Consolidés'!J7 -> 0 | K25: =-'Reclassement Opex Consolidés'!K7 -> 0 | ... O25: =-'Reclassement Opex Consolidés'!O7 -> 0 | P25: =SUM(D25:O25) -> 0
B26: Fixe & Internet
B27: Intercompagnie Fixe & Internet
B28: Mobile
B29: Intercompagnie Mobile
B31: EBITDA | D31: =D20+D25 -> 0 | E31: =E20+E25 -> 0 | F31: =F20+F25 -> 0 | G31: =G20+G25 -> 0 | H31: =H20+H25 -> 0 | I31: =I20+I25 -> 0 | J31: =J20+J25 -> 0 | K31: =K20+K25 -> 0 | ... O31: =O20+O25 -> 0 | P31: =SUM(D31:O31) -> 0
B32: % CA
B33: Fixe & Internet
B34: Mobile
B36: Amortissements et déprec. Courant | P36: =SUM(D36:O36) -> 0
B37: Dotations (Amo. et Pv NC)
B38: Autres non courant | D38: =-Source!D19 -> 0 | O38: ='Reclassement Opex Consolidés'!O26 -> 0 | P38: =SUM(D38:O38) -> 0
B39: +/- value de cession d'immob.
B41: EBIT | D41: =D31+D36+D37+D38+D39 -> 0 | E41: =E31+E36+E37+E38+E39 -> 0 | F41: =F31+F36+F37+F38+F39 -> 0 | G41: =G31+G36+G37+G38+G39 -> 0 | H41: =H31+H36+H37+H38+H39 -> 0 | I41: =I31+I36+I37+I38+I39 -> 0 | J41: =J31+J36+J37+J38+J39 -> 0 | K41: =K31+K36+K37+K38+K39 -> 0 | ... O41: =O31+O36+O37+O38+O39 -> 0 | P41: =SUM(D41:O41) -> 0
B42: % CA
B43: Fixe & Internet
B44: Mobile
B47: Résultat financier | D47: =-Source!D16 -> 0 | P47: =SUM(D47:O47) -> 0
B48: dont intérêt sur SHL
B50: RESULTAT avant IS | D50: =D41+D47 -> 0 | E50: =E41+E47 -> 0 | F50: =F41+F47 -> 0 | G50: =G41+G47 -> 0 | H50: =H41+H47 -> 0 | I50: =I41+I47 -> 0 | J50: =J41+J47 -> 0 | K50: =K41+K47 -> 0 | ... P50: =P41+P47 -> 0
B51: IS | D51: =-D50*0.3 -> 0 | E51: =-E50*0.3 -> 0 | F51: =-F50*0.3 -> 0 | G51: =-G50*0.3 -> 0 | H51: =-H50*0.3 -> 0 | I51: =-I50*0.3 -> 0 | J51: =-J50*0.3 -> 0 | K51: =-K50*0.3 -> 0 | ... O51: =-O50*0.3 -> 0 | P51: =SUM(D51:O51) -> 0
B52: ID | P52: =SUM(D52:O52) -> 0
B54: RESULTAT NET | D54: =D50+D52+D51 -> 0 | E54: =E50+E52+E51 -> 0 | F54: =F50+F52+F51 -> 0 | G54: =G50+G52+G51 -> 0 | H54: =H50+H52+H51 -> 0 | I54: =I50+I52+I51 -> 0 | J54: =J50+J52+J51 -> 0 | K54: =K50+K52+K51 -> 0 | ... P54: =P50+P52+P51 -> 0
B86: intercompagnie intern fixe vers telmob | D86: 538819050 | E86: 538819050
B87: interco Telmob après supression inter entrant | D87: -109581559 | E87: -109581559
B90: Interco CA Transit Telmob vers International | D90: 385261401 | E90: 385261401
B92: interco Onatel après supression CA Transit Telmob vers International | D92: -490152329 | E92: -490152329

Sheet Reclassement Opex Consolidés
A2: Opex Consolidés
D3: 2018/001 | E3: 2018/002 | F3: 2018/003 | G3: 2018/004 | H3: 2018/005 | I3: 2018/006 | J3: 2018/007 | K3: 2018/008 | L3: 2018/009 | M3: 2018/010 | N3: 2018/011 | O3: 2018/012
D4: JANVIER | E4: FEVRIER | F4: MARS | G4: AVRIL | H4: MAI | I4: JUIN | J4: JUILLET | K4: AOÛT | L4: SEPT. | M4: OCT. | N4: NOV. | O4: DEC
B5: (En Millions ML) | D5: 2018 Réel | E5: 2018 Réel | F5: 2018 Réel | G5: 2018 Réel | H5: 2018 Réel | I5: 2018 Réel | J5: 2018 Réel | K5: 2018 Réel | L5: 2018 Réel | M5: 2018 Réel | N5: 2018 Réel | O5: 2018 Réel | P5: 2018
B7: Total Opex | D7: =D9+D11+D13+D21+D28+D33+D39 -> 0 | E7: =E9+E11+E13+E21+E28+E33+E39 -> 0 | F7: =F9+F11+F13+F21+F28+F33+F39 -> 0 | G7: =G9+G11+G13+G21+G28+G33+G39 -> 0 | H7: =H9+H11+H13+H21+H28+H33+H39 -> 0 | I7: =I9+I11+I13+I21+I28+I33+I39 -> 0 | J7: =J9+J11+J13+J21+J28+J33+J39 -> 0 | K7: =K9+K11+K13+K21+K28+K33+K39 -> 0 | ... P7: =P9+P11+P13+P21+P28+P33+P39 -> 0
B9: Personnel | D9: =-D11 -> 0 | O9: =-O14-O22 -> 0 | P9: =SUM(D9:O9) -> 0
B11: Communication | D11: =-Source!D8 -> 0 | P11: =SUM(D11:O11) -> 0
B13: Exploitation & maintenance | D13: =+SUM(D14:D19) -> 0 | E13: =+SUM(E14:E19) -> 0 | F13: =+SUM(F14:F19) -> 0 | G13: =+SUM(G14:G19) -> 0 | H13: =+SUM(H14:H19) -> 0 | I13: =+SUM(I14:I19) -> 0 | J13: =+SUM(J14:J19) -> 0 | K13: =+SUM(K14:K19) -> 0 | ... P13: =+SUM(P14:P19) -> 0
B14: Achat d'énergie - Bâtiment - Gardiennage | P14: =SUM(D14:O14) -> 0
B15: Lignes et réseaux (entretien & achats) | P15: =SUM(D15:O15) -> 0
B16: Fees du contrat GMNS | P16: =SUM(D16:O16) -> 0
B17: Fees du contrat IHS (spécifique à CDI) | P17: =SUM(D17:O17) -> 0
B18: Matériel de transport (Entretien et locat°) | P18: =SUM(D18:O18) -> 0
B19: Maintenance informatique | P19: =SUM(D19:O19) -> 0
B21: Frais généraux | D21: =SUM(D22:D26) -> 0 | E21: =SUM(E22:E26) -> 0 | F21: =SUM(F22:F26) -> 0 | G21: =SUM(G22:G26) -> 0 | H21: =SUM(H22:H26) -> 0 | I21: =SUM(I22:I26) -> 0 | J21: =SUM(J22:J26) -> 0 | K21: =SUM(K22:K26) -> 0 | ... P21: =SUM(P22:P26) -> 0
B22: Frais d'achats d'études, honoraires | P22: =SUM(D22:O22) -> 0
B23: Management Fees | P23: =SUM(D23:O23) -> 0
B24: Transport, déplacement, mission | P24: =SUM(D24:O24) -> 0
B25: Frais postaux, bancaires et assurances | P25: =SUM(D25:O25) -> 0
B26: Achats de mat. et fournitures consom. | D26: =-Source!D19-Source!D16 -> 0 | P26: =SUM(D26:O26) -> 0
B28: Impôts, taxes et redevances | D28: =SUM(D29:D31) -> 0 | E28: =SUM(E29:E31) -> 0 | F28: =SUM(F29:F31) -> 0 | G28: =SUM(G29:G31) -> 0 | H28: =SUM(H29:H31) -> 0 | I28: =SUM(I29:I31) -> 0 | J28: =SUM(J29:J31) -> 0 | K28: =SUM(K29:K31) -> 0 | ... P28: =SUM(P29:P31) -> 0
B29: Redevances régulateur | P29: =SUM(D29:O29) -> 0
B30: Droits sur le trafic International Entrant | P30: =SUM(D30:O30) -> 0
B31: Autres impôts et taxes | P31: =SUM(D31:O31) -> 0
B33: Provision clients, R&C & NC | D33: =SUM(D34:D37) -> 0 | E33: =SUM(E34:E37) -> 0 | F33: =SUM(F34:F37) -> 0 | G33: =SUM(G34:G37) -> 0 | H33: =SUM(H34:H37) -> 0 | I33: =SUM(I34:I37) -> 0 | J33: =SUM(J34:J37) -> 0 | K33: =SUM(K34:K37) -> 0 | ... P33: =SUM(P34:P37) -> 0
B34: Prov. Créances clients | P34: =SUM(D34:O34) -> 0
B35: Prov. R&C | P35: =SUM(D35:O35) -> 0
B36: PIDR | P36: =SUM(D36:O36) -> 0
B37: Autres provisions | P37: =SUM(D37:O37) -> 0
B39: Ecart de change sur exploitation | P39: =SUM(D39:O39) -> 0 | R39: =+Q39-P39 -> 0

Sheet Reclassement Marge Mobile
A2: Marge brute Mobile
D5: JANVIER | E5: FEVRIER | F5: MARS | G5: AVRIL | H5: MAI | I5: JUIN | J5: JUILLET | K5: AOÛT | L5: SEPTEMBRE | M5: OCTOBRE | N5: NOVEMBRE | O5: DÉCEMBRE
B6: (En Millions ML) | D6: 2018 Réel | E6: 2018 Réel | F6: 2018 Réel | G6: 2018 Réel | H6: 2018 Réel | I6: 2018 Réel | J6: 2018 Réel | K6: 2018 Réel | L6: 2018 Réel | M6: 2018 Réel | N6: 2018 Réel | O6: 2018 Réel | P6: 2018
A8: Total Revenu | D8: ='CA Mobile'!D8 -> 0 | E8: ='CA Mobile'!E8 -> 0 | F8: ='CA Mobile'!F8 -> 0 | G8: ='CA Mobile'!G8 -> 0 | H8: ='CA Mobile'!H8 -> 0 | I8: ='CA Mobile'!I8 -> 0 | J8: ='CA Mobile'!J8 -> 0 | K8: ='CA Mobile'!K8 -> 0 | ... P8: ='CA Mobile'!P8 -> 0
B9: Trafic (mn)
B10: Coût unitaire
B11: International
B12: Trafic (mn)
B13: Coût unitaire
B14: Opérateur national MTN
B15: Trafic (mn)
B16: Coût unitaire
B17: Opérateur national ORANGE
B18: Trafic (mn)
B19: Coût unitaire
B20: Opérateur national AUTRES MOBILES
... B29: Roaming out
B31: Coûts des terminaux et cartes | D31: =SUM(D32:D35) -> 0 | E31: =SUM(E32:E35) -> 0 | F31: =SUM(F32:F35) -> 0 | G31: =SUM(G32:G35) -> 0 | H31: =SUM(H32:H35) -> 0 | I31: =SUM(I32:I35) -> 0 | J31: =SUM(J32:J35) -> 0 | K31: =SUM(K32:K35) -> 0 | ... P31: =SUM(P32:P35) -> 0
B32: Dont coût des cartes SIM | P32: =SUM(D32:O32) -> 0 | Q32: SIM
B33: Dont coût des cartes de recharge vendues | P33: =SUM(D33:O33) -> 0
B34: Dont coût des terminaux | P34: =SUM(D34:O34) -> 0
B35: Dont provisions sur stocks | P35: =SUM(D35:O35) -> 0
B36: Reversement SVA | P36: =SUM(D36:O36) -> 0
B37: Blackberry | P37: =SUM(D37:O37) -> 0
B38: Commissions | D38: =SUM(D39:D40) -> 0 | E38: =SUM(E39:E40) -> 0 | F38: =SUM(F39:F40) -> 0 | G38: =SUM(G39:G40) -> 0 | H38: =SUM(H39:H40) -> 0 | I38: =SUM(I39:I40) -> 0 | J38: =SUM(J39:J40) -> 0 | K38: =SUM(K39:K40) -> 0 | ... P38: =SUM(P39:P40) -> 0
B39: Dont commissions up-front | P39: =SUM(D39:O39) -> 0
B40: Dont avoirs de performance | P40: =SUM(D40:O40) -> 0
A42: Coûts des ventes | D42: =D11+D14+D17+D20+D25+D28+D29+D31+D36+D37+D38 -> 0 | E42: =E11+E14+E17+E20+E25+E28+E29+E31+E36+E37+E38 -> 0 | F42: =F11+F14+F17+F20+F25+F28+F29+F31+F36+F37+F38 -> 0 | G42: =G11+G14+G17+G20+G25+G28+G29+G31+G36+G37+G38 -> 0 | H42: =H11+H14+H17+H20+H25+H28+H29+H31+H36+H37+H38 -> 0 | I42: =I11+I14+I17+I20+I25+I28+I29+I31+I36+I37+I38 -> 0 | J42: =J11+J14+J17+J20+J25+J28+J29+J31+J36+J37+J38 -> 0 | K42: =K11+K14+K17+K20+K25+K28+K29+K31+K36+K37+K38 -> 0 | ... P42: =P11+P14+P17+P20+P25+P28+P29+P31+P36+P37+P38 -> 0
A44: Marge Brute | D44: =+D8-D42 -> 0 | E44: =+E8-E42 -> 0 | F44: =+F8-F42 -> 0 | G44: =+G8-G42 -> 0 | H44: =+H8-H42 -> 0 | I44: =+I8-I42 -> 0 | J44: =+J8-J42 -> 0 | K44: =+K8-K42 -> 0 | ... P44: =+P8-P42 -> 0
A45: En % du CA | D45: =D44/D8 -> #DIV/0! | E45: =E44/E8 -> #DIV/0! | F45: =F44/F8 -> #DIV/0! | G45: =G44/G8 -> #DIV/0! | H45: =H44/H8 -> #DIV/0! | I45: =I44/I8 -> #DIV/0! | J45: =J44/J8 -> #DIV/0! | K45: =K44/K8 -> #DIV/0! | ... P45: =P44/P8 -> #DIV/0!
B48: Coût des cartes SIM Social (Fév-Déc 15)

Sheet tmpscrapsheet

Sheet Source
A1: 627700000 | B1: FRAIS DE COLLOQ, SEMIN, CONFCE
A2: 2018001
A3: 2018001
A5: =[34]!AG_SMRT("0,Etat récapitulatif 1,1",A$1,A$1,A$2,A$3) -> #NAME? | B5: Numéro compte | C5: Description | D5: Montant base | E5: Origine journal | F5: Description | G5: Référence transaction
A6: 2018/001 | B6: 627700000 | C6: FRAIS DE COLLOQ, SEMIN, CONFCE | E6: RKD | F6: RADISSON BLU ABJ-SEMINAIRE STRATEGIQUE MOOV CI 18 | G6: 5473559
A7: 2018/001 | B7: 627700000 | C7: FRAIS DE COLLOQ, SEMIN, CONFCE | E7: RKD | F7: VILLA BLANCA-SEMINAIRE FORMAT° & BILAN DEPART LOG | G7: 5473548
A8: Totaux | D8: =SUBTOTAL(9,D6:D7) -> 0
A11: 758400000 | B11: AUTRES PRODUITS
A12: 2018001
A13: 2018001
A15: =[34]!AG_SMRT("0,Etat récapitulatif 1,1",A11,A11,A12,A13) -> #NAME? | B15: Numéro compte | C15: Description | D15: Montant base | E15: Origine journal | F15: Description | G15: Référence transaction
A16: 2018/001 | B16: 758400000 | C16: AUTRES PRODUITS | E16: CAM | F16: AUTRE PRODUIT DAT | G16: 3600
A17: 2018/001 | B17: 758400000 | C17: AUTRES PRODUITS | E17: CAM | F17: AUTRES PRODUITS/REVERSMT/PC 0023180 FRAIS MISSION | G17: 0023268
A18: 2018/001 | B18: 758400000 | C18: AUTRES PRODUITS | E18: KOM | F18: REMBOURSEMENT DOTATION TELEPHONIQUE CEDRIC BOUEDY | G18: 0023251
A19: 2018/001 | B19: 758400000 | C19: AUTRES PRODUITS | E19: MBA | F19: ERICSSON-BC005053/VOUCHER | G19: 0004512
A20: 2018/001 | B20: 758400000 | C20: AUTRES PRODUITS | E20: NID | F20: ANNULATION VIREMENT-PAIEMENT DIVIDENDES MT | G20: MOOV/DF/DT/SF-TD 25 01 18
A21: Totaux | D21: =SUBTOTAL(9,D16:D20) -> 0

Sheet Ls_XLB_WorkbookFile

Sheet Ls_AgXLB_WorkbookFile
A1: >>Etat récapitulatif 1 | B1: >'adb | C1: >'[LASATA SETUP FILE] Date=2018-02-06 10:57:31 FileType=Agora XLB Data Fill Version=0 Buffer= @systemProduct:Str=SS6 @systemTable:Str=LA @filterFrom_DbC:Str=MCI @filterFrom_/LA/Ldg:Str=A @filterFrom_/LA/AccCde:Str='Source'!$A$11{P}1 @filterTo_/LA/AccCde:Str='Source'!$A$11{P}2 @filterFrom_/LA/Prd:Str='Source'!$A$12{P}3 @filterTo_/LA/Prd:Str='Source'!$A$13{P}4 @outputField_/LA/Prd:Str= @outputField_/LA/AccCde:Str= @outputField_/LA/CA/Nme:Str= @outputField_/LA/BseAmt{ExtractType}1:Str= @outputField_/LA/JnlSrc:Str= @outputField_/LA/Desc:Str= @outputField_/LA/TrnRef:Str= @formatType:Lng=-4154 @formatNumber:Int=1 @formatPattern:Int=1 @formatFont:Int=1 @formatWidth:Int=1 @formatAlignment:Int=1 @formatBorder:Int=1 @filenmSetupfile:Str= @filenmWorkbookSetupFile:Str=Etat récapitulatif 1 @settngShowMessages:Str=Y @settngDirection:Str=D @settngApplyFormula:Str=Y @settngLock:Str=N @settngOutputHeaders:Int=0 @settngOutputCaptions:Int=1 @settngOutputTotals:Int=1 @settngOutputFiltering:Int=0 @settngPivotTable:Int=0 @settngTopPercent:Str= @settngReportStyle:Lng=1
