Workbook
Name _: #REF!
Name _: #REF!
Name _: #REF!
Name _: #REF!
Name __: #REF!
Name __: #REF!
Name __: #REF!
Name ___________B1: #N/A
Name ___________eng2: #N/A
Name ___________eng3: 'Data Mobile'!___________eng3
Name ___________eng3: #N/A
Name ___________eng3: 'Data Mobile'!___________eng3
Name ___________eng4: #N/A
Name __________B1: #N/A
Name __________eng2: #N/A
Name __________eng3: 'Data Mobile'!__________eng3
Name __________eng3: #N/A
Name __________eng3: 'Data Mobile'!__________eng3
Name __________eng4: #N/A
Name _________eng3: 'Data Mobile'!_________eng3
Name _________eng3: #N/A
Name _________eng3: 'Data Mobile'!_________eng3
Name ________eng3: 'Data Mobile'!________eng3
Name ________eng3: #N/A
Name ________eng3: 'Data Mobile'!________eng3
Name _______eng3: 'Data Mobile'!_______eng3
Name _______eng3: #N/A
Name _______eng3: 'Data Mobile'!_______eng3
Name ______eng3: 'Data Mobile'!______eng3
Name ______eng3: #N/A
Name ______eng3: 'Data Mobile'!______eng3
Name ______FRF4: '[2]FX Rates'!$G$10
Name ______GBP4: '[2]FX Rates'!$G$9
Name _____0: #REF!
Name _____0: #REF!
Name _____0: #REF!
Name _____0: #REF!
Name _____12: #REF!
Name _____12: #REF!
Name _____12: #REF!
Name _____12: #REF!
Name _____14: #REF!
Name _____14: #REF!
Name _____14: #REF!
Name _____14: #REF!
Name _____16: #REF!
Name _____16: #REF!
Name _____16: #REF!
Name _____2: #REF!
Name _____2: #REF!
Name _____2: #REF!
Name _____25: #REF!
Name _____25: #REF!
Name _____25: #REF!
Name _____26: #REF!
Name _____26: #REF!
Name _____26: #REF!
Name _____27: #REF!
Name _____27: #REF!
Name _____27: #REF!

Sheet Cover
E15: MOOV AFRICA BENIN TBG
E17: 45809
A5603: 41743
A5604: 41743
A5605: 41744
A5606: 41744
A5607: 41744
A5608: 41744
A5609: 41744
A5610: 41744
A5611: 41744
A5612: 41744
A5613: 41744
A5614: 41744
A5615: 41744

Sheet P&L conso
A1: P&L consolidé | V1: =+V25+'Opex Consolidés'!V7 | AD1: =+AD25+'Opex Consolidés'!AD7 | AL1: =+AL25+'Opex Consolidés'!AL7 | AU1: #REF! | BC1: 577.07409 | BK1: =+BK25+'Opex Consolidés'!BD7 | BT1: -68804439 | BW1: =BV4 | CB1: =+CB25+'Opex Consolidés'!BU7 | CJ1: =+CJ25+'Opex Consolidés'!CC7 | CR1: =+CR25+'Opex Consolidés'!CR7 | CS1: 17000.499 | CT1: =CT25+'Opex Consolidés'!CT7 | CW1: 16458.089 | CZ1: 26225.79 | DC1: 8378.9625
E3: 0 | G3: 0 | AD3: 0 | CZ3: 0 | DD3: 0
D4: 45658 | J4: 45689 | P4: 45717 | V4: 45748 | AD4: 45778 | AL4: 45809 | AU4: 45839 | BC4: 45870 | BK4: 45901 | BT4: 45931 | CB4: 45962 | CJ4: 45992 | CR4: CUMUL | CZ4: ANNUEL
A5: (En Millions ML) | D5: 2025 Réel | E5: 2025 Budget | F5: Ecart / Budget | G5: 2024 Réel | H5: Evol % | J5: 2025 Réel | K5: 2025 Budget | L5: Ecart / Budget | M5: 2024 Réel | N5: Evol % | P5: 2025 Réel | Q5: 2025 Budget | R5: Ecart / Budget | S5: 2024 Réel | T5: Evol % | V5: 2025 Réel | W5: 2025 Budget | X5: 2025 Actu1 | Y5: Ecart / Budget | Z5: Ecart / Actu1 | AA5: 2024 Réel | AB5: Evol % | AD5: 2025 Réel | AE5: 2025 Budget | AF5: 2025 Actu1 | AG5: Ecart / Budget | AH5: Ecart / Actu1 | AI5: 2024 Réel | AJ5: Evol % | AL5: 2025 Réel | AM5: 2025 Budget | AN5: 2025 Actu1 | AO5: 2025 Actu2 | AP5: Ecart / Budget | AQ5: Ecart / Actu1 | AR5: 2024 Réel | AS5: Evol % | AU5: 2025 Réel | AV5: 2025 Budget | AW5: 2025 Actu2 | AX5: Ecart / Budget | AY5: Ecart / Actu2 | AZ5: 2024 Réel | BA5: Evol % | BC5: 2025 Réel | BD5: 2025 Budget | BE5: 2025 Actu2 | BF5: Ecart / Budget | BG5: Ecart / Actu2 | BH5: 2024 Réel | BI5: Evol % | BK5: 2025 Réel | BL5: 2025 Budget | BM5: 2025 Actu2 | BN5: 2025 Actu3 | BO5: Ecart / Budget | BP5: Ecart / Actu2 | BQ5: 2024 Réel | BR5: Evol % | BT5: 2025 Réel | BU5: 2025 Budget | BV5: 2025 Actu3 | BW5: Ecart / Budget | BX5: Ecart / Actu3 | BY5: 2024 Réel | BZ5: Evol % | CB5: 2025 Réel | CC5: 2025 Budget | CD5: 2025 Actu3 | CE5: Ecart / Budget | CF5: Ecart / Actu3 | CG5: 2024 Réel | CH5: Evol % | CJ5: 2025 Réel | CK5: 2025 Budget | CL5: 2025 Actu3 | CM5: Ecart / Budget | CN5: Ecart / Actu3 | CO5: 2024 Réel | CP5: Evol % | CR5: 2025 Réel | CS5: 2025 Budget | CT5: 2025 Actu3 | CU5: Ecart / Budget | CV5: Ecart / Actu3 | CW5: 2024 Réel | CX5: Evol % | CZ5: 2025 Budget | DA5: 2025 Actu1 | DB5: 2025 Actu2 | DC5: 2025 Actu3 | DD5: 2024 Réel | DE5: Bud / 2024 (%) | DF5: Actu 1 / 2024 (%) | DG5: Actu 2 / 2024 (%) | DH5: Actu3 / 2024 (%)
A7: Chiffre d'affaires | C7: PL1 | D7: 8324.9028 | E7: 9527.0891 | F7: -1202.1863 | G7: 9480.8077 | H7: -0.12192051 | J7: 7599.911 | K7: 8782.1227 | L7: -1182.2117 | M7: 9059.8608 | N7: -0.16114484 | P7: 7943.4924 | Q7: 9473.1389 | R7: -1529.6465 | S7: 9959.7273 | T7: -0.20243877 | V7: 8080.2292 | W7: 9362.5379 | X7: 7876.1248 | Y7: -1282.3087 | Z7: 204.10442 | AA7: 9279.8977 | AB7: -0.12927605 | AD7: 7954.7423 | AE7: 9772.4636 | AF7: 8199.6147 | AG7: -1817.7213 | AH7: -244.87237 | AI7: 9134.1999 | AJ7: -0.12912544 | AL7: 6462.0625 | AM7: 9466.6859 | AN7: 0 | AO7: 0 | AP7: -3004.6234 | AQ7: 6462.0625 | AR7: 8946.7558 | AS7: -0.27772004 | CR7: =+SUMIF($D$5:$CQ$5,CR$5,$D7:$CQ7) | CS7: =+SUMIF($D$5:$CQ$5,CS$5,$D7:$CQ7) | CT7: ='CA Mobile'!CT8 | CU7: =+CR7-CS7 | CV7: =+CR7-CT7 | CW7: =+SUMIF($D$5:$CQ$5,CW$5,$D7:$CQ7) | CX7: =IFERROR(CR7/CW7-1, "-") | CZ7: 114333.76 | DD7: 106192.13 | DE7: =CZ7/DD7-1 | DF7: =DA7/DD7-1 | DG7: =DB7/DD7-1 | DH7: =DC7/DD7-1
A8: Fixe & Internet | C8: PL2 | CR8: =+SUMIF($D$5:$CQ$5,CR$5,$D8:$CQ8) | CS8: =+SUMIF($D$5:$CQ$5,CS$5,$D8:$CQ8) | CU8: =+CR8-CS8 | CV8: =+CR8-CT8 | CW8: =+SUMIF($D$5:$CQ$5,CW$5,$D8:$CQ8) | CX8: =IFERROR(CR8/CW8-1, "-")
A9: Mobile | C9: PL3 | D9: 8324.9028 | E9: 9527.0891 | F9: -1202.1863 | G9: 9480.8077 | H9: -0.12192051 | J9: 7599.911 | K9: 8782.1227 | L9: -1182.2117 | M9: 9059.8608 | N9: -0.16114484 | P9: 7943.4924 | Q9: 9473.1389 | R9: -1529.6465 | S9: 9959.7273 | T9: -0.20243877 | V9: 8080.2292 | W9: 9362.5379 | X9: 7876.1248 | Y9: -1282.3087 | Z9: 204.10442 | AA9: 9279.8977 | AB9: -0.12927605 | AD9: 7954.7423 | AE9: 9772.4636 | AF9: 8199.6147 | AG9: -1817.7213 | AH9: -244.87237 | AI9: 9134.1999 | AJ9: -0.12912544 | AL9: 6462.0625 | AM9: 9466.6859 | AN9: 8095.1472 | AO9: 0 | AP9: -3004.6234 | AQ9: -1633.0847 | AR9: 8946.7558 | AS9: -0.27772004 | CR9: =+SUMIF($D$5:$CQ$5,CR$5,$D9:$CQ9) | CS9: =+SUMIF($D$5:$CQ$5,CS$5,$D9:$CQ9) | CT9: =CT10 | CU9: =+CR9-CS9 | CV9: =+CR9-CT9 | CW9: =+SUMIF($D$5:$CQ$5,CW$5,$D9:$CQ9) | CX9: =IFERROR(CR9/CW9-1, "-") | CZ9: 114333.76 | DA9: 100883.84 | DD9: 106192.13 | DE9: =CZ9/DD9-1 | DG9: =DB9/DD9-1 | DH9: =DC9/DD9-1
A10: Intercompagnie Mobile | C10: PL4 | D10: 8324.9028 | E10: 9527.0891 | F10: -1202.1863 | G10: 9480.8077 | H10: -0.12192051 | J10: 7599.911 | K10: 8782.1227 | L10: -1182.2117 | M10: 9059.8608 | N10: -0.16114484 | P10: 7943.4924 | Q10: 9473.1389 | R10: -1529.6465 | S10: 9959.7273 | T10: -0.20243877 | V10: 8080.2292 | W10: 9362.5379 | X10: 7876.1248 | Y10: -1282.3087 | Z10: 204.10442 | AA10: 9279.8977 | AB10: -0.12927605 | AD10: 7954.7423 | AE10: 9772.4636 | AF10: 8199.6147 | AG10: -1817.7213 | AH10: -244.87237 | AI10: 9134.1999 | AJ10: -0.12912544 | AL10: 6462.0625 | AM10: 9466.6859 | AN10: 8095.1472 | AO10: 0 | AP10: -3004.6234 | AQ10: -1633.0847 | AR10: 8946.7558 | AS10: -0.27772004 | CR10: =+SUMIF($D$5:$CQ$5,CR$5,$D10:$CQ10) | CS10: =+SUMIF($D$5:$CQ$5,CS$5,$D10:$CQ10) | CT10: ='CA Mobile'!CT8 | CU10: =+CR10-CS10 | CV10: =+CR10-CT10 | CW10: =+SUMIF($D$5:$CQ$5,CW$5,$D10:$CQ10) | CX10: =IFERROR(CR10/CW10-1, "-") | CZ10: 114333.76 | DA10: 100883.84 | DD10: 106192.13 | DE10: =CZ10/DD10-1 | DF10: =DA10/DD10-1 | DG10: =DB10/DD10-1 | DH10: =DC10/DD10-1
C11: PL5 | CR11: =+SUMIF($D$5:$CQ$5,CR$5,$D11:$CQ11) | CS11: =+SUMIF($D$5:$CQ$5,CS$5,$D11:$CQ11) | CT11: =+SUMIF($D$5:$CP$5,CT$5,$D11:$CP11)+SUMIF($D$5:$BI$5,CR$5,$D11:$BI11) | CU11: =+CR11-CS11 | CV11: =+CR11-CT11 | CW11: =+SUMIF($D$5:$CQ$5,CW$5,$D11:$CQ11) | CX11: =IFERROR(CR11/CW11-1, "-")
A12: Intercompagnie | C12: PL6 | CR12: =+SUMIF($D$5:$CQ$5,CR$5,$D12:$CQ12) | CS12: =+SUMIF($D$5:$CQ$5,CS$5,$D12:$CQ12) | CT12: =+SUMIF($D$5:$CP$5,CT$5,$D12:$CP12)+SUMIF($D$5:$BI$5,CR$5,$D12:$BI12) | CU12: =+CR12-CS12 | CV12: =+CR12-CT12 | CW12: =+SUMIF($D$5:$CQ$5,CW$5,$D12:$CQ12) | CX12: =IFERROR(CR12/CW12-1, "-") | DE12: =CZ12/DD12-1
A13: dont Intercompagnie hors trafic | C13: PL7 | CR13: =+SUMIF($D$5:$CQ$5,CR$5,$D13:$CQ13) | CS13: =+SUMIF($D$5:$CQ$5,CS$5,$D13:$CQ13) | CT13: =+SUMIF($D$5:$CP$5,CT$5,$D13:$CP13)+SUMIF($D$5:$BI$5,CR$5,$D13:$BI13) | CU13: =+CR13-CS13 | CV13: =+CR13-CT13 | CW13: =+SUMIF($D$5:$CQ$5,CW$5,$D13:$CQ13) | CX13: =IFERROR(CR13/CW13-1, "-") | DE13: =CZ13/DD13-1
C14: PL8 | CR14: =+SUMIF($D$5:$CQ$5,CR$5,$D14:$CQ14) | CS14: =+SUMIF($D$5:$CQ$5,CS$5,$D14:$CQ14) | CT14: =+SUMIF($D$5:$CP$5,CT$5,$D14:$CP14)+SUMIF($D$5:$BI$5,CR$5,$D14:$BI14) | CU14: =+CR14-CS14 | CV14: =+CR14-CT14 | CW14: =+SUMIF($D$5:$CQ$5,CW$5,$D14:$CQ14) | CX14: =IFERROR(CR14/CW14-1, "-") | DE14: =CZ14/DD14-1
A15: Coût des ventes | C15: PL9 | D15: -1407.8713 | E15: -1517.7256 | F15: 109.85439 | G15: -1387.0909 | H15: 0.014981231 | J15: -1367.514 | K15: -1459.5803 | L15: 92.066302 | M15: -1472.3759 | N15: -0.071219506 | P15: -1517.8719 | Q15: -1580.7997 | R15: 62.927761 | S15: -1642.8287 | T15: -0.076061964 | V15: -1545.0213 | W15: -1545.981 | X15: -1371.157 | Y15: 0.95971407 | Z15: -173.86429 | AA15: -1449.7183 | AB15: 0.065738969 | AD15: -1332.1608 | AE15: -1578.2509 | AF15: -1420.3445 | AG15: 246.09008 | AH15: 88.18369 | AI15: -1621.855 | AJ15: -0.17861903 | AL15: -1275.3912 | AM15: -1551.4919 | AN15: -1413.2652 | AO15: 0 | AP15: 276.10074 | AQ15: 137.87398 | AR15: -1587.1442 | AS15: -0.19642385 | CR15: =+SUMIF($D$5:$CQ$5,CR$5,$D15:$CQ15) | CS15: =+SUMIF($D$5:$CQ$5,CS$5,$D15:$CQ15) | CT15: =+CT16+CT17 | CU15: =+CR15-CS15 | CV15: =+CR15-CT15 | CW15: =+SUMIF($D$5:$CQ$5,CW$5,$D15:$CQ15) | CX15: =IFERROR(CR15/CW15-1, "-") | CZ15: -18651.46 | DA15: -17158.455 | DD15: -17784.539 | DE15: =(CZ15/DD15-1) | DF15: =DA15/DD15-1 | DG15: =DB15/DD15-1 | DH15: =DC15/DD15-1
A16: Fixe & Internet | C16: PL10 | CR16: =+SUMIF($D$5:$CQ$5,CR$5,$D16:$CQ16) | CS16: =+SUMIF($D$5:$CQ$5,CS$5,$D16:$CQ16) | CT16: =+SUMIF($D$5:$CP$5,CT$5,$D16:$CP16)+SUMIF($D$5:$BI$5,CR$5,$D16:$BI16) | CU16: =+CR16-CS16 | CV16: =+CR16-CT16 | CW16: =+SUMIF($D$5:$CQ$5,CW$5,$D16:$CQ16) | CX16: =IFERROR(CR16/CW16-1, "-") | DE16: =CZ16/DD16-1
A17: Mobile | C17: PL11 | D17: -1407.8713 | E17: -1517.7256 | F17: 109.85439 | G17: -1387.0909 | H17: 0.014981231 | J17: -1367.514 | K17: -1459.5803 | L17: 92.066302 | M17: -1472.3759 | N17: -0.071219506 | P17: -1517.8719 | Q17: -1580.7997 | R17: 62.927761 | S17: -1642.8287 | T17: -0.076061964 | V17: -1545.0213 | W17: -1545.981 | X17: -1371.157 | Y17: 0.95971407 | Z17: -173.86429 | AA17: -1449.7183 | AB17: 0.065738969 | AD17: -1332.1608 | AE17: -1578.2509 | AF17: -1420.3445 | AG17: 246.09008 | AH17: 88.18369 | AI17: -1621.855 | AJ17: -0.17861903 | AL17: -1275.3912 | AM17: -1551.4919 | AN17: -1413.2652 | AO17: 0 | AP17: 276.10074 | AQ17: 137.87398 | AR17: -1587.1442 | AS17: -0.19642385 | CR17: =+SUMIF($D$5:$CQ$5,CR$5,$D17:$CQ17) | CS17: =+SUMIF($D$5:$CQ$5,CS$5,$D17:$CQ17) | CT17: =+CT18 | CU17: =+CR17-CS17 | CV17: =+CR17-CT17 | CW17: =+SUMIF($D$5:$CQ$5,CW$5,$D17:$CQ17) | CX17: =IFERROR(CR17/CW17-1, "-") | CZ17: -18651.46 | DA17: -17158.455 | DD17: -17784.539 | DE17: =(CZ17/DD17-1) | DF17: =DA17/DD17-1 | DG17: =DB17/DD17-1 | DH17: =DC17/DD17-1
A18: Intercompagnie Mobile | C18: PL12 | D18: -1407.8713 | E18: -1517.7256 | F18: 109.85439 | G18: -1387.0909 | H18: 0.014981231 | J18: -1367.514 | K18: -1459.5803 | L18: 92.066302 | M18: -1472.3759 | N18: -0.071219506 | P18: -1517.8719 | Q18: -1580.7997 | R18: 62.927761 | S18: -1642.8287 | T18: -0.076061964 | V18: -1545.0213 | W18: -1545.981 | X18: -1371.157 | Y18: 0.95971407 | Z18: -173.86429 | AA18: -1449.7183 | AB18: 0.065738969 | AD18: -1332.1608 | AE18: -1578.2509 | AF18: -1420.3445 | AG18: 246.09008 | AH18: 88.18369 | AI18: -1621.855 | AJ18: -0.17861903 | AL18: -1275.3912 | AM18: -1551.4919 | AN18: -1413.2652 | AO18: 0 | AP18: 276.10074 | AQ18: 137.87398 | AR18: -1587.1442 | AS18: -0.19642385 | CR18: =+SUMIF($D$5:$CQ$5,CR$5,$D18:$CQ18) | CS18: =+SUMIF($D$5:$CQ$5,CS$5,$D18:$CQ18) | CT18: ='Marge Mobile'!CT58 | CU18: =+CR18-CS18 | CV18: =+CR18-CT18 | CW18: =+SUMIF($D$5:$CQ$5,CW$5,$D18:$CQ18) | CX18: =IFERROR(CR18/CW18-1, "-") | CZ18: -18651.46 | DA18: -17158.455 | DD18: -17784.539 | DE18: =(CZ18/DD18-1) | DF18: =DA18/DD18-1 | DG18: =DB18/DD18-1 | DH18: =DC18/DD18-1
C19: PL13 | CS19: =+SUMIF($D$5:$CQ$5,CS$5,$D19:$CQ19) | CT19: =+SUMIF($D$5:$CP$5,CT$5,$D19:$CX19)+SUMIF($D$5:$AJ$5,CR$5,$D19:$AJ19) | CU19: =+CR19-CS19 | CV19: =+CR19-CT19 | CW19: =+SUMIF($D$5:$CQ$5,CW$5,$D19:$CQ19) | CX19: =IFERROR(CR19/CW19-1, "-")
A20: Marge Brute | C20: PL14 | D20: 6917.0315 | E20: 8009.3634 | F20: -1092.3319 | G20: 8093.7168 | H20: -0.14538256 | J20: 6232.397 | K20: 7322.5424 | L20: -1090.1454 | M20: 7587.485 | N20: -0.17859514 | P20: 6425.6205 | Q20: 7892.3393 | R20: -1466.7188 | S20: 8316.8986 | T20: -0.22740185 | V20: 6535.2079 | W20: 7816.5569 | X20: 6504.9678 | Y20: -1281.349 | Z20: 30.240132 | AA20: 7830.1794 | AB20: -0.1653821 | AD20: 6622.5815 | AE20: 8194.2127 | AF20: 6779.2702 | AG20: -1571.6312 | AH20: -156.68868 | AI20: 7512.345 | AJ20: -0.11844018 | AL20: 5186.6713 | AM20: 7915.194 | AN20: 6681.882 | AO20: 0 | AP20: -2728.5227 | AQ20: -1495.2107 | AR20: 7359.6117 | AS20: -0.29525204 | CR20: =+SUMIF($D$5:$CQ$5,CR$5,$D20:$CQ20) | CS20: =+SUMIF($D$5:$CQ$5,CS$5,$D20:$CQ20) | CT20: =+CT7+CT15 | CU20: =+CR20-CS20 | CV20: =+CR20-CT20 | CW20: =+SUMIF($D$5:$CQ$5,CW$5,$D20:$CQ20) | CX20: =IFERROR(CR20/CW20-1, "-") | CZ20: 95682.303 | DA20: 83725.385 | DD20: 88407.592 | DE20: =CZ20/DD20-1 | DF20: =DA20/DD20-1 | DG20: =DB20/DD20-1 | DH20: =DC20/DD20-1
A21: % CA | C21: PL15 | D21: 0.83088436 | E21: 0.84069366 | F21: -0.0098093041 | G21: 0.85369486 | H21: -0.00026719731 | J21: 0.82006184 | K21: 0.83380097 | L21: -0.013739126 | M21: 0.83748361 | N21: -0.00020802519 | P21: 0.8089163 | Q21: 0.83312821 | R21: -0.024211907 | S21: 0.83505285 | T21: -0.00031299269 | V21: 0.80878992 | W21: 0.83487586 | X21: 0.82590969 | Y21: -0.026085944 | Z21: -0.017119772 | AA21: 0.84377863 | AB21: -0.00041466701 | AD21: 0.8325325 | AE21: 0.8385002 | AF21: 0.82677911 | AG21: -0.0059677032 | AH21: 0.0057533832 | AI21: 0.82244148 | AJ21: 0.00012269582 | AL21: 0.80263404 | AM21: 0.83611034 | AN21: 0.0082541822 | AO21: 0 | AP21: -0.033476304 | AQ21: 0.79437985 | AR21: 0.82260115 | AS21: -0.00024273147 | CR21: =+CR20/CR7 | CS21: =+CS20/CS7 | CT21: =+CT20/CT7 | CU21: =+(CR21-CS21) | CV21: =+(CR21-CT21) | CW21: =+CW20/CW7 | CX21: =IFERROR(CR21/CW21-1, "-") | CZ21: 0.83686831 | DA21: 0.008299187 | DD21: 9.9825998 | DE21: =+(CZ21-DD21) | DF21: =DA21/DD21-1 | DG21: =DB21/DD21-1 | DH21: =DC21/DD21-1
A22: Fixe & Internet | C22: PL16 | CR22: =+CJ22 | CS22: =+#REF! | CT22: =IF(CS$4<=Cover!$E$17,INDEX(#REF!,MATCH($C22,#REF!,0),7),0) | CU22: =+CR22-CS22 | CV22: =+CR22-CT22 | CW22: =+#REF! | CX22: =IFERROR(CR22/CW22-1, "-") | DE22: =CZ22/DD22-1
A23: Mobile | C23: PL17 | D23: 6917.0315 | E23: 8009.3634 | F23: -1092.3319 | G23: 8093.7168 | H23: -0.14538256 | J23: 6232.397 | K23: 7322.5424 | L23: -1090.1454 | M23: 7587.485 | N23: -0.17859514 | P23: 6425.6205 | Q23: 7892.3393 | R23: -1466.7188 | S23: 8316.8986 | T23: -0.22740185 | V23: 6535.2079 | W23: 7816.5569 | X23: 6504.9678 | Y23: -1281.349 | Z23: 30.240132 | AA23: 7830.1794 | AB23: -0.1653821 | AD23: 6622.5815 | AE23: 8194.2127 | AF23: 6779.2702 | AG23: -1571.6312 | AH23: -156.68868 | AI23: 7512.345 | AJ23: -0.11844018 | AL23: 5186.6713 | AM23: 7915.194 | AN23: 6681.882 | AO23: 0 | AP23: -2728.5227 | AQ23: -1495.2107 | AR23: 7359.6117 | AS23: -0.29525204 | CR23: =+SUMIF($D$5:$CQ$5,CR$5,$D23:$CQ23) | CS23: =+SUMIF($D$5:$CQ$5,CS$5,$D23:$CQ23) | CT23: =+CT9+CT17 | CU23: =+CR23-CS23 | CV23: =+CR23-CT23 | CW23: =+SUMIF($D$5:$CQ$5,CW$5,$D23:$CQ23) | CX23: =IFERROR(CR23/CW23-1, "-") | CZ23: 95682.303 | DA23: 83725.385 | DD23: 88407.592 | DE23: =(CZ23/DD23-1) | DF23: =DA23/DD23-1 | DG23: =DB23/DD23-1 | DH23: =DC23/DD23-1
C24: PL18 | CR24: =+SUMIF($D$5:$CQ$5,CR$5,$D24:$CQ24) | CS24: =+SUMIF($D$5:$CQ$5,CS$5,$D24:$CQ24) | CT24: =+SUMIF($D$5:$CP$5,CT$5,$D24:$CX24)+SUMIF($D$5:$AJ$5,CR$5,$D24:$AJ24) | CU24: =+CR24-CS24 | CV24: =+CR24-CT24 | CW24: =+SUMIF($D$5:$CQ$5,CW$5,$D24:$CQ24) | CX24: =IFERROR(CR24/CW24-1, "-")
A25: Coûts opérationnels | C25: PL19 | D25: -5023.3945 | E25: -5752.8634 | F25: 729.46896 | G25: -5774.0655 | H25: -0.13000736 | J25: -5233.5165 | K25: -5412.0079 | L25: 178.49134 | M25: -5467.9109 | N25: -0.042867268 | P25: -5306.2354 | Q25: -5658.8042 | R25: 352.56882 | S25: -5318.9236 | T25: -0.0023854885 | V25: -5421.9008 | W25: -5772.0206 | X25: -5383.448 | Y25: 350.11983 | Z25: -38.452731 | AA25: -5458.7716 | AB25: -0.0067544161 | AD25: -5302.1763 | AE25: -5682.373 | AF25: -5325.1097 | AG25: 380.19665 | AH25: 22.93341 | AI25: -5565.8537 | AJ25: -0.047374108 | AL25: -5739.4271 | AM25: -5580.6859 | AN25: -5222.0484 | AO25: 0 | AP25: -158.74112 | AQ25: -517.37863 | AR25: -5075.041 | AS25: 0.13091246 | CR25: =+SUMIF($D$5:$CQ$5,CR$5,$D25:$CQ25) | CS25: =+SUMIF($D$5:$CQ$5,CS$5,$D25:$CQ25) | CT25: =+SUMIF($D$5:$CP$5,CT$5,$D25:$CP25)+SUMIF($D$5:$BI$5,CR$5,$D25:$BI25) | CU25: =+CR25-CS25 | CV25: =+CR25-CT25 | CW25: =+SUMIF($D$5:$CQ$5,CW$5,$D25:$CQ25) | CX25: =IFERROR(CR25/CW25-1, "-") | CZ25: -67535.531 | DA25: -63800.274 | DD25: -66696.264 | DE25: =CZ25/DD25-1 | DF25: =DA25/DD25-1 | DG25: =DB25/DD25-1 | DH25: =DC25/DD25-1
A26: Fixe & Internet | C26: PL20 | CR26: =+SUMIF($D$5:$CQ$5,CR$5,$D26:$CQ26) | CS26: =+SUMIF($D$5:$CQ$5,CS$5,$D26:$CQ26) | CT26: =+SUMIF($D$5:$CP$5,CT$5,$D26:$CP26)+SUMIF($D$5:$BI$5,CR$5,$D26:$BI26) | CU26: =+CR26-CS26 | CV26: =+CR26-CT26 | CW26: =+SUMIF($D$5:$CQ$5,CW$5,$D26:$CQ26) | CX26: =IFERROR(CR26/CW26-1, "-") | DE26: =CZ26/DD26-1
A27: Intercompagnie Fixe & Internet | C27: PL21 | CR27: =+SUMIF($D$5:$CQ$5,CR$5,$D27:$CQ27) | CS27: =+SUMIF($D$5:$CQ$5,CS$5,$D27:$CQ27) | CT27: =+SUMIF($D$5:$CP$5,CT$5,$D27:$CP27)+SUMIF($D$5:$BI$5,CR$5,$D27:$BI27) | CU27: =+CR27-CS27 | CV27: =+CR27-CT27 | CW27: =+SUMIF($D$5:$CQ$5,CW$5,$D27:$CQ27) | CX27: =IFERROR(CR27/CW27-1, "-") | DE27: =CZ27/DD27-1
A28: Mobile | C28: PL22 | D28: -5023.3945 | E28: -5752.8634 | F28: 729.46896 | G28: -5774.0655 | H28: -0.13000736 | J28: -5233.5165 | K28: -5412.0079 | L28: 178.49134 | M28: -5467.9109 | N28: -0.042867268 | P28: -5306.2354 | Q28: -5658.8042 | R28: 352.56882 | S28: -5318.9236 | T28: -0.0023854885 | V28: -5421.9008 | W28: -5772.0206 | X28: -5383.448 | Y28: 350.11983 | Z28: -38.452731 | AA28: -5458.7716 | AB28: -0.0067544161 | AD28: -5302.1763 | AE28: -5682.373 | AF28: -5325.1097 | AG28: 380.19665 | AH28: 22.93341 | AI28: -5565.8537 | AJ28: -0.047374108 | AL28: -5739.4271 | AM28: -5580.6859 | AN28: -5222.0484 | AO28: 0 | AP28: -158.74112 | AQ28: -517.37863 | AR28: -5075.041 | AS28: 0.13091246 | CR28: =+SUMIF($D$5:$CQ$5,CR$5,$D28:$CQ28) | CS28: =+SUMIF($D$5:$CQ$5,CS$5,$D28:$CQ28) | CT28: =+CT29 | CU28: =+CR28-CS28 | CV28: =+CR28-CT28 | CW28: =+SUMIF($D$5:$CQ$5,CW$5,$D28:$CQ28) | CX28: =IFERROR(CR28/CW28-1, "-") | CZ28: -67535.531 | DA28: -63800.274 | DD28: -66696.264 | DE28: =CZ28/DD28-1 | DF28: =DA28/DD28-1 | DG28: =DB28/DD28-1 | DH28: =DC28/DD28-1
A29: Intercompagnie Mobile | C29: PL23 | D29: -5023.3945 | E29: -5752.8634 | F29: 729.46896 | G29: -5774.0655 | H29: -0.13000736 | J29: -5233.5165 | K29: -5412.0079 | L29: 178.49134 | M29: -5467.9109 | N29: -0.042867268 | P29: -5306.2354 | Q29: -5658.8042 | R29: 352.56882 | S29: -5318.9236 | T29: -0.0023854885 | V29: -5421.9008 | W29: -5772.0206 | X29: -5383.448 | Y29: 350.11983 | Z29: -38.452731 | AA29: -5458.7716 | AB29: -0.0067544161 | AD29: -5302.1763 | AE29: -5682.373 | AF29: -5325.1097 | AG29: 380.19665 | AH29: 22.93341 | AI29: -5565.8537 | AJ29: -0.047374108 | AL29: -5739.4271 | AM29: -5580.6859 | AN29: -5222.0484 | AO29: 0 | AP29: -158.74112 | AQ29: -517.37863 | AR29: -5075.041 | AS29: 0.13091246 | CR29: =+SUMIF($D$5:$CQ$5,CR$5,$D29:$CQ29) | CS29: =+SUMIF($D$5:$CQ$5,CS$5,$D29:$CQ29) | CT29: =-'Opex Consolidés'!CT7 | CU29: =+CR29-CS29 | CV29: =+CR29-CT29 | CW29: =+SUMIF($D$5:$CQ$5,CW$5,$D29:$CQ29) | CX29: =IFERROR(CR29/CW29-1, "-") | CZ29: -67535.531 | DA29: -63800.274 | DD29: -66696.264 | DE29: =CZ29/DD29-1 | DF29: =DA29/DD29-1 | DH29: =DC29/DD29-1
C30: PL24 | CX30: =IFERROR(CR30/CW30-1, "-")
A31: EBITDA | C31: PL25 | D31: 1893.637 | E31: 2256.5 | F31: -362.86294 | G31: 2319.6513 | H31: -0.18365444 | J31: 998.88051 | K31: 1910.5345 | L31: -911.65403 | M31: 2119.574 | N31: -0.52873526 | P31: 1119.3851 | Q31: 2233.5351 | R31: -1114.15 | S31: 2997.975 | T31: -0.62661959 | V31: 1113.3071 | W31: 2044.5363 | X31: 1121.5197 | Y31: -931.22918 | Z31: -8.2125987 | AA31: 2371.4079 | AB31: -0.53052903 | AD31: 1320.4052 | AE31: 2511.8397 | AF31: 1454.1604 | AG31: -1191.4346 | AH31: -133.75527 | AI31: 1946.4913 | AJ31: -0.32164856 | AL31: -552.75577 | AM31: 2334.508 | AN31: 1459.8336 | AO31: 0 | AP31: -2887.2638 | AQ31: -2012.5894 | AR31: 2284.5707 | AS31: -1.2419517 | CR31: =+SUMIF($D$5:$CQ$5,CR$5,$D31:$CQ31) | CS31: =+SUMIF($D$5:$CQ$5,CS$5,$D31:$CQ31) | CT31: =+CT20+CT25 | CU31: =+CR31-CS31 | CV31: =+CR31-CT31 | CW31: =+SUMIF($D$5:$CQ$5,CW$5,$D31:$CQ31) | CX31: =IFERROR(CR31/CW31-1, "-") | CZ31: 28146.773 | DA31: 19925.11 | DD31: 21711.328 | DE31: =CZ31/DD31-1 | DF31: =DA31/DD31-1 | DG31: =DB31/DD31-1 | DH31: =DC31/DD31-1
A32: % CA | C32: PL26 | D32: 0.22746656 | E32: 0.23685094 | F32: -0.0093843725 | G32: 0.24466811 | H32: -0.00070305628 | J32: 0.13143318 | K32: 0.21754815 | L32: -0.086114965 | M32: 0.23395216 | N32: -0.0043820488 | P32: 0.14091851 | Q32: 0.23577561 | R32: -0.094857097 | S32: 0.30100975 | T32: -0.0053184735 | V32: 0.13778163 | W32: 0.21837416 | X32: 0.14239487 | Y32: -0.080592528 | Z32: -0.004613238 | AA32: 0.25554246 | AB32: -0.0046082685 | AD32: 0.16598968 | AE32: 0.25703239 | AF32: 0.17734497 | AG32: -0.091042711 | AH32: -0.011355288 | AI32: 0.21309926 | AJ32: -0.0022106871 | AL32: -0.085538598 | AM32: 0.24660246 | AN32: 0.0018033441 | AO32: 0 | AP32: -0.33214106 | AQ32: -0.087341943 | AR32: 0.25535186 | AS32: -0.013349833 | CR32: =+CR31/CR7 | CS32: =+CS31/CS7 | CT32: =+CT31/CT7 | CU32: =+(CR32-CS32) | CV32: =+(CR32-CT32) | CW32: =+CW31/CW7 | CX32: =IFERROR(CR32/CW32-1, "-") | CZ32: 0.24618076 | DA32: 0.0019750547 | DD32: 2.4332127 | DE32: =(CZ32-DD32) | DF32: =DA32/DD32-1 | DG32: =DB32/DD32-1 | DH32: =DC32/DD32-1
A33: Fixe & Internet | C33: PL27 | CR33: =+CJ33 | CS33: =+#REF! | CU33: =+CR33-CS33 | CV33: =+CR33-CT33 | CW33: =+#REF! | CX33: =IFERROR(CR33/CW33-1, "-") | DE33: =CZ33/DD33-1
A34: Mobile | C34: PL28 | D34: 1893.637 | E34: 2256.5 | F34: -362.86294 | G34: 2319.6513 | H34: -0.18365444 | J34: 998.88051 | K34: 1910.5345 | L34: -911.65403 | M34: 2119.574 | N34: -0.52873526 | P34: 1119.3851 | Q34: 2233.5351 | R34: -1114.15 | S34: 2997.975 | T34: -0.62661959 | V34: 1113.3071 | W34: 2044.5363 | X34: 1121.5197 | Y34: -931.22918 | Z34: -8.2125987 | AA34: 2371.4079 | AB34: -0.53052903 | AD34: 1320.4052 | AE34: 2511.8397 | AF34: 1454.1604 | AG34: -1191.4346 | AH34: -133.75527 | AI34: 1946.4913 | AJ34: -0.32164856 | AL34: -552.75577 | AM34: 2334.508 | AN34: 1459.8336 | AO34: 0 | AP34: -2887.2638 | AQ34: -2012.5894 | AR34: 2284.5707 | AS34: -1.2419517 | CR34: =+SUMIF($D$5:$CQ$5,CR$5,$D34:$CQ34) | CS34: =+SUMIF($D$5:$CQ$5,CS$5,$D34:$CQ34) | CT34: =+CT23+CT28 | CU34: =+CR34-CS34 | CV34: =+CR34-CT34 | CW34: =+SUMIF($D$5:$CQ$5,CW$5,$D34:$CQ34) | CX34: =IFERROR(CR34/CW34-1, "-") | CZ34: 28146.773 | DA34: 19925.11 | DD34: 21711.328 | DE34: =CZ34/DD34-1 | DF34: =DA34/DD34-1 | DG34: =DB34/DD34-1 | DH34: =DC34/DD34-1
C35: PL29 | CR35: =+SUMIF($D$5:$CQ$5,CR$5,$D35:$CQ35) | CS35: =+SUMIF($D$5:$CQ$5,CS$5,$D35:$CQ35) | CT35: =+SUMIF($D$5:$CP$5,CT$5,$D35:$CX35)+SUMIF($D$5:$AJ$5,CR$5,$D35:$AJ35) | CU35: =+CR35-CS35 | CV35: =+CR35-CT35 | CW35: =+SUMIF($D$5:$CQ$5,CW$5,$D35:$CQ35) | CX35: =IFERROR(CR35/CW35-1, "-")
A36: Amortissements et déprec. Courant | C36: PL30 | D36: -1741.8583 | E36: -1755 | F36: 13.141733 | G36: -1626.288 | H36: 0.071063857 | J36: -1754.9732 | K36: -1774.631 | L36: 19.657768 | M36: -1623.0309 | N36: 0.081293773 | P36: -1779.8004 | Q36: -1774.631 | R36: -5.1694124 | S36: -1961.7764 | T36: -0.092760822 | V36: -1775.0229 | W36: -1732.131 | X36: -1732.131 | Y36: -42.891929 | Z36: -42.891929 | AA36: -1803.3618 | AB36: -0.015714472 | AD36: -1806.0059 | AE36: -1754.9927 | AF36: -1754.9927 | AG36: -51.013161 | AH36: -51.013161 | AI36: -1809.4697 | AJ36: -0.0019142878 | AL36: -1817.6639 | AM36: -1752.6683 | AN36: -1752.6683 | AO36: 0 | AP36: -64.995655 | AQ36: -64.995655 | AR36: -1801.8079 | AS36: 0.0088000375 | CR36: =+SUMIF($D$5:$CQ$5,CR$5,$D36:$CQ36) | CS36: =+SUMIF($D$5:$CQ$5,CS$5,$D36:$CQ36) | CT36: =+SUMIF($D$5:$CP$5,CT$5,$D36:$CP36)+SUMIF($D$5:$BI$5,CR$5,$D36:$BI36) | CU36: =+CR36-CS36 | CV36: =+CR36-CT36 | CW36: =+SUMIF($D$5:$CQ$5,CW$5,$D36:$CQ36) | CX36: =IFERROR(CR36/CW36-1, "-") | CZ36: -21086.659 | DA36: -21305.834 | DD36: -20598.107 | DE36: =CZ36/DD36-1 | DF36: =DA36/DD36-1 | DG36: =DB36/DD36-1 | DH36: =DC36/DD36-1
A37: Dotations (Amo. et Pv NC) | C37: PL31 | CR37: =+SUMIF($D$5:$CQ$5,CR$5,$D37:$CQ37) | CS37: =+SUMIF($D$5:$CQ$5,CS$5,$D37:$CQ37) | CT37: =+SUMIF($D$5:$CP$5,CT$5,$D37:$CP37)+SUMIF($D$5:$BI$5,CR$5,$D37:$BI37) | CU37: =+CR37-CS37 | CV37: =+CR37-CT37 | CW37: =+SUMIF($D$5:$CQ$5,CW$5,$D37:$CQ37) | CX37: =IFERROR(CR37/CW37-1, "-")
A38: Autres non courant | C38: PL32 | CR38: =+SUMIF($D$5:$CQ$5,CR$5,$D38:$CQ38) | CS38: =+SUMIF($D$5:$CQ$5,CS$5,$D38:$CQ38) | CT38: =+SUMIF($D$5:$CP$5,CT$5,$D38:$CP38)+SUMIF($D$5:$BI$5,CR$5,$D38:$BI38) | CU38: =+CR38-CS38 | CV38: =+CR38-CT38 | CW38: =+SUMIF($D$5:$CQ$5,CW$5,$D38:$CQ38) | CX38: =IFERROR(CR38/CW38-1, "-")
A39: +/- value de cession d'immob. | C39: PL33 | CR39: =+SUMIF($D$5:$CQ$5,CR$5,$D39:$CQ39) | CS39: =+SUMIF($D$5:$CQ$5,CS$5,$D39:$CQ39) | CT39: =+SUMIF($D$5:$CP$5,CT$5,$D39:$CP39)+SUMIF($D$5:$BI$5,CR$5,$D39:$BI39) | CU39: =+CR39-CS39 | CV39: =+CR39-CT39 | CW39: =+SUMIF($D$5:$CQ$5,CW$5,$D39:$CQ39) | CX39: =IFERROR(CR39/CW39-1, "-")
C40: PL34 | CR40: =+SUMIF($D$5:$CQ$5,CR$5,$D40:$CQ40) | CS40: =+SUMIF($D$5:$CQ$5,CS$5,$D40:$CQ40) | CT40: =+SUMIF($D$5:$CP$5,CT$5,$D40:$CP40)+SUMIF($D$5:$BI$5,CR$5,$D40:$BI40) | CU40: =+CR40-CS40 | CV40: =+CR40-CT40 | CW40: =+SUMIF($D$5:$CQ$5,CW$5,$D40:$CQ40) | CX40: =IFERROR(CR40/CW40-1, "-")
A41: EBITA | C41: PL35 | D41: 151.77877 | E41: 501.49997 | F41: -349.72121 | G41: 693.36333 | H41: -0.78109779 | J41: -756.09269 | K41: 135.90357 | L41: -891.99626 | M41: 496.54315 | N41: -2.522713 | P41: -660.41525 | Q41: 458.90413 | R41: -1119.3194 | S41: 1036.1987 | T41: -1.6373442 | V41: -661.71575 | W41: 312.40536 | X41: -610.61122 | Y41: -974.12111 | Z41: -51.104527 | AA41: 568.04608 | AB41: -2.164898 | AD41: -485.6007 | AE41: 756.84703 | AF41: -300.83227 | AG41: -1242.4477 | AH41: -184.76843 | AI41: 137.02157 | AJ41: -4.5439727 | AL41: -2370.4197 | AM41: 581.83976 | AN41: -292.83466 | AO41: 0 | AP41: -2952.2595 | AQ41: -2077.585 | AR41: 482.76276 | AS41: -5.9101129 | CR41: =+SUMIF($D$5:$CQ$5,CR$5,$D41:$CQ41) | CS41: =+SUMIF($D$5:$CQ$5,CS$5,$D41:$CQ41) | CT41: =+CT31+CT36+CT37+CT38+CT39 | CU41: =+CR41-CS41 | CV41: =+CR41-CT41 | CW41: =+SUMIF($D$5:$CQ$5,CW$5,$D41:$CQ41) | CX41: =IFERROR(CR41/CW41-1, "-") | CZ41: 7060.1132 | DA41: -1380.7232 | DD41: 1113.2213 | DE41: =CZ41/DD41-1 | DF41: =DA41/DD41-1 | DG41: =DB41/DD41-1 | DH41: =DC41/DD41-1
A42: % CA | C42: PL36 | D42: 0.018231897 | E42: 0.052639371 | F42: -0.034407474 | G42: 0.07313336 | H42: -0.0075070342 | J42: -0.099487046 | K42: 0.015475025 | L42: -0.11496207 | M42: 0.054806929 | N42: -0.028152275 | P42: -0.083139156 | Q42: 0.048442669 | R42: -0.13158182 | S42: 0.10403886 | T42: -0.017991164 | V42: -0.081893191 | W42: 0.033367594 | X42: -0.067623512 | Y42: -0.11526078 | Z42: -0.014269678 | AA42: 0.061212537 | AB42: -0.0233785 | AD42: -0.061045434 | AE42: 0.077446901 | AF42: -0.036688586 | AG42: -0.13849234 | AH42: -0.024356849 | AI42: 0.015000938 | AJ42: -0.050694411 | AL42: -0.36682092 | AM42: 0.061461822 | AN42: -0.00036174099 | AO42: 0 | AP42: -0.42828274 | AQ42: -0.36645918 | AR42: 0.053959533 | AS42: -0.077980744 | CR42: =+CR41/CR7 | CS42: =+CS41/CS7 | CT42: =+CT41/CT7 | CU42: =+(CR42-CS42)*100 | CV42: =+(CR42-CT42)*100 | CW42: =+CW41/CW7 | CX42: =IFERROR(CR42/CW42-1, "-") | CZ42: 0.061750029 | DA42: -0.00013686267 | DD42: 0.10165576 | DE42: =+(CZ42-DD42)*100 | DF42: =DA42/DD42-1 | DG42: =DB42/DD42-1 | DH42: =DC42/DD42-1
A43: Fixe & Internet | C43: PL37 | CR43: =+CJ43 | CS43: =+#REF! | CT43: =+SUMIF($D$5:$CP$5,CT$5,$D43:$CX43)+SUMIF($D$5:$AJ$5,CR$5,$D43:$AJ43) | CU43: =+CR43-CS43 | CV43: =+CR43-CT43 | CW43: =+#REF! | CX43: =IFERROR(CR43/CW43-1, "-") | DE43: =CZ43/DD43-1
A44: Mobile | C44: PL38 | CR44: =+CJ44 | CS44: =+#REF! | CT44: =+SUMIF($D$5:$CP$5,CT$5,$D44:$CX44)+SUMIF($D$5:$AJ$5,CR$5,$D44:$AJ44) | CU44: =+CR44-CS44 | CV44: =+CR44-CT44 | CW44: =+#REF! | CX44: =IFERROR(CR44/CW44-1, "-") | DE44: =CZ44/DD44-1
C45: PL39 | CR45: =+CJ45 | CS45: =+#REF! | CT45: =+SUMIF($D$5:$CP$5,CT$5,$D45:$CX45)+SUMIF($D$5:$AJ$5,CR$5,$D45:$AJ45) | CU45: =+CR45-CS45 | CV45: =+CR45-CT45 | CW45: =+#REF! | CX45: =IFERROR(CR45/CW45-1, "-") | DE45: =CZ45/DD45-1
C46: PL40 | CR46: =+SUMIF($D$5:$CQ$5,CR$5,$D46:$CQ46) | CS46: =+SUMIF($D$5:$CQ$5,CS$5,$D46:$CQ46) | CT46: =+SUMIF($D$5:$CP$5,CT$5,$D46:$CX46)+SUMIF($D$5:$AJ$5,CR$5,$D46:$AJ46) | CU46: =+CR46-CS46 | CV46: =+CR46-CT46 | CW46: =+SUMIF($D$5:$CQ$5,CW$5,$D46:$CQ46) | CX46: =IFERROR(CR46/CW46-1, "-")
A47: Résultat financier | C47: PL41 | D47: -374.40374 | E47: -333.5 | F47: -40.903737 | G47: -221.8682 | H47: 0.6875052 | J47: -312.15107 | K47: -333.5 | L47: 21.348931 | M47: -267.02722 | N47: 0.16898595 | P47: -434.83104 | Q47: -328.5 | R47: -106.33104 | S47: -278.50458 | T47: 0.56130661 | V47: -362.40579 | W47: -332.5 | X47: -331.97056 | Y47: -29.905793 | Z47: -30.435229 | AA47: -211.43119 | AB47: 0.71406022 | AD47: -334.05661 | AE47: -333.5 | AF47: -340.8832 | AG47: -0.556614 | AH47: 6.8265838 | AI47: -384.87278 | AJ47: -0.13203367 | AL47: -983.25458 | AM47: -328.5 | AN47: -324.24689 | AO47: 0 | AP47: -654.75458 | AQ47: -659.00769 | AR47: -324.60168 | AS47: 2.0291112 | CR47: =+SUMIF($D$5:$CQ$5,CR$5,$D47:$CQ47) | CS47: =+SUMIF($D$5:$CQ$5,CS$5,$D47:$CQ47) | CT47: =+SUMIF($D$5:$CP$5,CT$5,$D47:$CP47)+SUMIF($D$5:$BI$5,CR$5,$D47:$BI47) | CU47: =+CR47-CS47 | CV47: =+CR47-CT47 | CW47: =+SUMIF($D$5:$CQ$5,CW$5,$D47:$CQ47) | CX47: =IFERROR(CR47/CW47-1, "-") | CZ47: -3986 | DA47: -4220.0844 | DD47: -4045.6537 | DE47: =CZ47/DD47-1 | DF47: =DA47/DD47-1 | DG47: =DB47/DD47-1 | DH47: =DC47/DD47-1
A48: dont intérêt sur SHL | C48: PL42 | CR48: =+SUMIF($D$5:$CQ$5,CR$5,$D48:$CQ48) | CS48: =+SUMIF($D$5:$CQ$5,CS$5,$D48:$CQ48) | CT48: =+SUMIF($D$5:$CP$5,CT$5,$D48:$CX48)+SUMIF($D$5:$AJ$5,CR$5,$D48:$AJ48) | CU48: =+CR48-CS48 | CV48: =+CR48-CT48 | CW48: =+SUMIF($D$5:$CQ$5,CW$5,$D48:$CQ48) | CX48: =IFERROR(CR48/CW48-1, "-") | DF48: =DA48/DD48-1 | DG48: =DB48/DD48-1
C49: PL43 | CR49: =+SUMIF($D$5:$CQ$5,CR$5,$D49:$CQ49) | CS49: =+SUMIF($D$5:$CQ$5,CS$5,$D49:$CQ49) | CT49: =+SUMIF($D$5:$CP$5,CT$5,$D49:$CX49)+SUMIF($D$5:$AJ$5,CR$5,$D49:$AJ49) | CU49: =+CR49-CS49 | CV49: =+CR49-CT49 | CW49: =+SUMIF($D$5:$CQ$5,CW$5,$D49:$CQ49) | CX49: =IFERROR(CR49/CW49-1, "-")
A50: RESULTAT avant IS | C50: PL44 | D50: -222.62497 | E50: 167.99997 | F50: -390.62494 | G50: 471.49513 | H50: -1.4721681 | J50: -1068.2438 | K50: -197.59643 | L50: -870.64733 | M50: 229.51592 | N50: -5.654334 | P50: -1095.2463 | Q50: 130.40413 | R50: -1225.6504 | S50: 757.69407 | T50: -2.4454994 | V50: -1024.1215 | W50: -20.094637 | X50: -942.58179 | Y50: -1004.0269 | Z50: -81.539757 | AA50: 356.61489 | AB50: -3.8717857 | AD50: -819.65731 | AE50: 423.34703 | AF50: -641.71546 | AG50: -1243.0043 | AH50: -177.94185 | AI50: -247.85121 | AJ50: 2.3070539 | AL50: -3353.6743 | AM50: 253.33976 | AN50: -617.08155 | AO50: 0 | AP50: -3607.014 | AQ50: -2736.5927 | AR50: 158.16108 | AS50: -22.204168 | CR50: =+SUMIF($D$5:$CQ$5,CR$5,$D50:$CQ50) | CS50: =+SUMIF($D$5:$CQ$5,CS$5,$D50:$CQ50) | CT50: =+SUMIF($D$5:$CP$5,CT$5,$D50:$CP50)+SUMIF($D$5:$BI$5,CR$5,$D50:$BI50) | CU50: =+CR50-CS50 | CV50: =+CR50-CT50 | CW50: =+SUMIF($D$5:$CQ$5,CW$5,$D50:$CQ50) | CX50: =IFERROR(CR50/CW50-1, "-") | CZ50: 3074.1132 | DA50: -5600.8075 | DD50: -2932.4324 | DE50: =CZ50/DD50-1 | DF50: =DA50/DD50-1 | DG50: =DB50/DD50-1 | DH50: =DC50/DD50-1
A51: IS | C51: PL45 | D51: -83.249028 | E51: -95.270891 | F51: 12.021863 | G51: -94.808077 | H51: -0.12192051 | J51: -75.99911 | K51: -87.821227 | L51: 11.822117 | M51: -90.598608 | N51: -0.16114484 | P51: -84.955645 | Q51: -94.731389 | R51: 9.7757446 | S51: -103.07188 | T51: -0.17576314 | V51: -80.802292 | W51: -93.625379 | X51: -78.761248 | Y51: 12.823087 | Z51: -2.0410442 | AA51: -96.273588 | AB51: -0.16070135 | AD51: -79.547423 | AE51: -97.724636 | AF51: -81.996147 | AG51: 18.177213 | AH51: 2.4487237 | AI51: -84.392778 | AJ51: -0.057414336 | AL51: -64.620625 | AM51: -94.666859 | AN51: -80.951472 | AO51: 0 | AP51: 30.046234 | AQ51: 16.330847 | AR51: -89.467558 | AS51: -0.27772004 | CR51: =+SUMIF($D$5:$CQ$5,CR$5,$D51:$CQ51) | CS51: =+SUMIF($D$5:$CQ$5,CS$5,$D51:$CQ51) | CT51: =+SUMIF($D$5:$CP$5,CT$5,$D51:$CP51)+SUMIF($D$5:$BI$5,CR$5,$D51:$BI51) | CU51: =+CR51-CS51 | CV51: =+CR51-CT51 | CW51: =+SUMIF($D$5:$CQ$5,CW$5,$D51:$CQ51) | CX51: =IFERROR(CR51/CW51-1, "-") | CZ51: -1143.3376 | DA51: -1014.3591 | DD51: -1211.9148 | DE51: =CZ51/DD51-1 | DF51: =DA51/DD51-1 | DG51: =DB51/DD51-1 | DH51: =DC51/DF51-1
A52: ID | C52: PL46 | D52: -24.860204 | E52: -4.5 | F52: -20.360204 | G52: -4.4652194 | H52: 4.5675213 | J52: -24.92246 | K52: -4.5 | L52: -20.42246 | M52: -10.123319 | N52: 1.4618863 | P52: 70.764638 | Q52: -4.5 | R52: 75.264638 | S52: -47.009368 | T52: -2.5053306 | V52: -37.312239 | W52: -4.5 | X52: 7 | Y52: -32.812239 | Z52: -44.312239 | AA52: -21.416474 | AB52: 0.7422214 | AD52: -37.365549 | AE52: -4.5 | AF52: 7 | AG52: -32.865549 | AH52: -44.365549 | AI52: -24.705404 | AJ52: 0.51244435 | AL52: 72.255039 | AM52: -4.5 | AN52: 7 | AO52: 0 | AP52: 76.755039 | AQ52: 65.255039 | AR52: 14.826724 | AS52: 3.8732975 | CR52: =+SUMIF($D$5:$CQ$5,CR$5,$D52:$CQ52) | CS52: =+SUMIF($D$5:$CQ$5,CS$5,$D52:$CQ52) | CT52: =+SUMIF($D$5:$CP$5,CT$5,$D52:$CP52)+SUMIF($D$5:$BI$5,CR$5,$D52:$BI52) | CU52: =+CR52-CS52 | CV52: =+CR52-CT52 | CW52: =+SUMIF($D$5:$CQ$5,CW$5,$D52:$CQ52) | CX52: =IFERROR(CR52/CW52-1, "-") | CZ52: -54 | DA52: 83.981974 | DD52: -112.08471 | DE52: =CZ52/DD52-1 | DF52: =DA52/DD52-1 | DG52: =DB52/DD52-1 | DH52: =DC52/DF52-1
C53: PL47 | CT53: =+SUMIF($D$5:$CP$5,CT$5,$D53:$CX53)+SUMIF($D$5:$AJ$5,CR$5,$D53:$AJ53) | CX53: =IFERROR(CR53/CW53-1, "-")
A54: RESULTAT NET | C54: PL48 | D54: -330.7342 | E54: 68.229082 | F54: -398.96328 | G54: 372.22183 | H54: -1.8885406 | J54: -1169.1653 | K54: -289.91766 | L54: -879.24767 | M54: 128.794 | N54: -10.077794 | P54: -1109.4373 | Q54: 31.172745 | R54: -1140.61 | S54: 607.61282 | T54: -2.8258951 | V54: -1142.2361 | W54: -118.22002 | X54: -1014.343 | Y54: -1024.0161 | Z54: -127.89304 | AA54: 238.92483 | AB54: -5.7807341 | AD54: -936.57029 | AE54: 321.12239 | AF54: -716.71161 | AG54: -1257.6927 | AH54: -219.85867 | AI54: -356.94939 | AJ54: 1.6238181 | AL54: -3346.0399 | AM54: 154.1729 | AN54: -691.03302 | AO54: 0 | AP54: -3500.2128 | AQ54: -2655.0068 | AR54: 83.520251 | AS54: -41.062617 | CR54: =+SUMIF($D$5:$CQ$5,CR$5,$D54:$CQ54) | CS54: =+SUMIF($D$5:$CQ$5,CS$5,$D54:$CQ54) | CT54: =+SUMIF($D$5:$CP$5,CT$5,$D54:$CP54)+SUMIF($D$5:$BI$5,CR$5,$D54:$BI54) | CU54: =+CR54-CS54 | CV54: =+CR54-CT54 | CW54: =+SUMIF($D$5:$CQ$5,CW$5,$D54:$CQ54) | CX54: =IFERROR(CR54/CW54-1, "-") | CZ54: 1876.7756 | DA54: -6531.1847 | DD54: -4256.4319 | DE54: =(CZ54/DD54-1) | DF54: =-(DA54/DD54-1) | DG54: =-(DB54/DD54-1) | DH54: =-(DC54/DD54-1)
C55: PL49 | CT55: =+SUMIF($D$5:$CP$5,CT$5,$D55:$CX55)+SUMIF($D$5:$AJ$5,CR$5,$D55:$AJ55) | CX55: =IFERROR(CR55/CW55-1, "-")
A56: % CA | C56: PL50 | D56: -0.039728296 | E56: 0.0071615875 | F56: -0.046889884 | G56: 0.039260561 | H56: -0.020119136 | J56: -0.15383934 | K56: -0.033012253 | L56: -0.12082709 | M56: 0.014215891 | N56: -0.11821646 | P56: -0.13966619 | Q56: 0.0032906458 | R56: -0.14295683 | S56: 0.061006974 | T56: -0.032893479 | V56: -0.14136184 | W56: -0.01262692 | X56: -0.12878707 | Y56: -0.12873492 | Z56: -0.012574771 | AA56: 0.025746494 | AB56: -0.064905278 | AD56: -0.11773735 | AE56: 0.032859922 | AF56: -0.087407962 | AG56: -0.15059727 | AH56: -0.030329388 | AI56: -0.039078342 | AJ56: 0.020128543 | AL56: -0.51779751 | AM56: 0.0093352554 | AN56: -0.00085363861 | AO56: 0 | AP56: -0.52713276 | AQ56: -0.51694387 | AR56: 0.0093352554 | AS56: -0.56466882 | CR56: =+CR54/CR7 | CS56: =+CS54/CS7 | CT56: =+CT54/CT7 | CU56: =+(CR56-CS56)*100 | CV56: =+(CR56-CT56)*100 | CW56: =+CW54/CW7 | CX56: =IFERROR(CR56/CW56-1, "-") | CZ56: 0.016414885 | DA56: -0.00064739652 | DD56: -0.51253766 | DE56: =+(CZ56-DD56)*100 | DF56: =+(DA56-DD56)*100 | DG56: =+(DB56-DD56)*100 | DH56: =+(DC56-DD56)*100
CR58: =CR54-SUM(CJ54,CB54,BT54,BK54,BC54,AU54,AL54,AD54,V54,P54,J54,D54)
A61: CA PNL | D61: =D7 | E61: =E7 | G61: =G7 | M61: =M7 | P61: =P7 | Q61: =Q7 | S61: =S7 | V61: =V7 | W61: =W7 | AA61: =AA7 | AD61: =AD7 | AE61: =AE7 | AI61: =AI7 | AL61: =AL7 | AM61: =AM7 | AR61: =AR7 | AU61: 8581.7161 | AV61: 9776.3005 | AZ61: 8753.0121 | BC61: 8351.3134 | BD61: 9829.75 | BH61: 8653.6552 | BK61: =BK7 | BL61: =BL7 | BQ61: =BQ7 | BT61: =BT7 | BU61: =BU7 | BY61: =BY7 | CB61: =CB7 | CC61: =CC7 | CG61: =CG7 | CJ61: =CJ7 | CK61: =CK7 | CL61: =CL7 | CO61: =CO7 | CR61: =CR7 | CS61: =CS7 | CT61: =CT7 | CW61: =CW7
A62: CA | D62: ='CA Mobile'!D8 | E62: ='CA Mobile'!E8 | G62: ='CA Mobile'!G8 | M62: ='CA Mobile'!M8 | P62: ='CA Mobile'!P8 | Q62: ='CA Mobile'!Q8 | S62: ='CA Mobile'!S8 | V62: ='CA Mobile'!V8 | W62: ='CA Mobile'!W8 | AA62: ='CA Mobile'!AA8 | AD62: ='CA Mobile'!AD8 | AE62: ='CA Mobile'!AE8 | AI62: ='CA Mobile'!AI8 | AL62: ='CA Mobile'!AL8 | AM62: ='CA Mobile'!AM8 | AR62: ='CA Mobile'!AR8 | AU62: 8581.7161 | AV62: 9776.3005 | AZ62: 8753.0121 | BC62: 8351.3134 | BD62: 9829.75 | BH62: 8653.6552 | BK62: ='CA Mobile'!BK8 | BL62: ='CA Mobile'!BL8 | BQ62: ='CA Mobile'!BQ8 | BT62: ='CA Mobile'!BT8 | BU62: ='CA Mobile'!BU8 | BY62: ='CA Mobile'!BY8 | CB62: ='CA Mobile'!CB8 | CC62: ='CA Mobile'!CC8 | CG62: ='CA Mobile'!CG8 | CJ62: ='CA Mobile'!CJ8 | CK62: ='CA Mobile'!CK8 | CL62: =+'CA Mobile'!CL8 | CO62: ='CA Mobile'!CO8 | CR62: ='CA Mobile'!CR8 | CS62: ='CA Mobile'!CS8 | CT62: ='CA Mobile'!CT8 | CW62: ='CA Mobile'!CW8
A63: CHECK | D63: =D61-D62 | E63: =E61-E62 | G63: =G61-G62 | M63: =M61-M62 | P63: =P61-P62 | Q63: =Q61-Q62 | S63: =S61-S62 | V63: =V61-V62 | W63: =W61-W62 | AA63: =AA61-AA62 | AD63: =AD61-AD62 | AE63: =AE61-AE62 | AI63: =AI61-AI62 | AL63: =AL61-AL62 | AM63: =AM61-AM62 | AR63: =AR61-AR62 | AU63: 0 | AV63: 0 | AZ63: 0 | BC63: 0 | BD63: 0 | BH63: 0 | BK63: =BK61-BK62 | BL63: =BL61-BL62 | BQ63: =BQ61-BQ62 | BT63: =BT61-BT62 | BU63: =BU61-BU62 | BY63: =BY61-BY62 | CB63: =CB61-CB62 | CC63: =CC61-CC62 | CG63: =CG61-CG62 | CJ63: =CJ61-CJ62 | CK63: =CK61-CK62 | CL63: =+CL61-CL62 | CO63: =CO61-CO62 | CR63: =CR61-CR62 | CS63: =CS61-CS62 | CT63: =CT61-CT62 | CU63: =CU61-CU62 | CV63: =CV61-CV62 | CW63: =CW61-CW62
A64: CA MARGES | D64: ='Marge Mobile'!D7 | E64: ='Marge Mobile'!E7 | G64: ='Marge Mobile'!G7 | M64: ='Marge Mobile'!M7 | P64: ='Marge Mobile'!P7 | Q64: ='Marge Mobile'!Q7 | S64: ='Marge Mobile'!S7 | V64: ='Marge Mobile'!V7 | W64: ='Marge Mobile'!W7 | AA64: ='Marge Mobile'!AA7 | AD64: ='Marge Mobile'!AD7 | AE64: ='Marge Mobile'!AE7 | AI64: ='Marge Mobile'!AI7 | AL64: ='Marge Mobile'!AL7 | AM64: ='Marge Mobile'!AM7 | AR64: ='Marge Mobile'!AR7 | AU64: 8581.7161 | AV64: 9776.3005 | AZ64: 8753.0121 | BC64: 8351.3134 | BD64: 9829.75 | BH64: 8653.6552 | BK64: ='Marge Mobile'!BK7 | BL64: ='Marge Mobile'!BL7 | BQ64: ='Marge Mobile'!BQ7 | BT64: ='Marge Mobile'!BT7 | BU64: ='Marge Mobile'!BU7 | BY64: ='Marge Mobile'!BY7 | CB64: ='Marge Mobile'!CB7 | CC64: ='Marge Mobile'!CC7 | CG64: ='Marge Mobile'!CG7 | CJ64: ='Marge Mobile'!CJ7 | CK64: ='Marge Mobile'!CK7 | CL64: ='Marge Mobile'!CL7 | CO64: ='Marge Mobile'!CO7 | CR64: ='Marge Mobile'!CR7 | CS64: ='Marge Mobile'!CS7 | CT64: ='Marge Mobile'!CT7 | CW64: ='Marge Mobile'!CW7
A65: CHECK | D65: =D61-D64 | E65: =E61-E64 | G65: =G61-G64 | M65: =M61-M64 | P65: =P61-P64 | Q65: =Q61-Q64 | S65: =S61-S64 | V65: =V61-V64 | W65: =W61-W64 | AA65: =AA61-AA64 | AD65: =AD61-AD64 | AE65: =AE61-AE64 | AI65: =AI61-AI64 | AL65: =AL61-AL64 | AM65: =AM61-AM64 | AR65: =AR61-AR64 | AU65: 0 | AV65: 0 | AZ65: 0 | BC65: 0 | BD65: 0 | BH65: 0 | BK65: =BK61-BK64 | BL65: =BL61-BL64 | BQ65: =BQ61-BQ64 | BT65: =BT61-BT64 | BU65: =BU61-BU64 | BY65: =BY61-BY64 | CB65: =CB61-CB64 | CC65: =CC61-CC64 | CG65: =CG61-CG64 | CJ65: =CJ61-CJ64 | CK65: =CK61-CK64 | CL65: =CL61-CL64 | CM65: =CM61-CM64 | CN65: =CN61-CN64 | CO65: =CO61-CO64 | CR65: =CR61-CR64 | CS65: =CS61-CS64 | CT65: =CT61-CT64 | CU65: =CU61-CU64 | CV65: =CV61-CV64 | CW65: =CW61-CW64
A66: OPEX PNL | D66: =D25 | E66: =E25 | G66: =G25 | M66: =M25 | P66: =P25 | Q66: =Q25 | S66: =S25 | V66: =V25 | W66: =W25 | AA66: =AA25 | AD66: =AD25 | AE66: =AE25 | AI66: =AI25 | AL66: =AL25 | AM66: =AM25 | AR66: =AR25 | AU66: -5235.8027 | AV66: -5853.3972 | AZ66: -5748.7478 | BC66: -5276.3231 | BD66: -5736.1233 | BH66: -5142.3972 | BK66: =BK25 | BL66: =BL25 | BQ66: =BQ25 | BT66: =BT25 | BU66: =BU25 | BY66: =BY25 | CB66: =CB25 | CC66: =CC25 | CG66: =CG25 | CJ66: =CJ25 | CK66: =CK25 | CL66: =CL25 | CO66: =CO25 | CR66: =CR25 | CS66: =CS25 | CT66: =CT25 | CW66: =CW25
A67: OPEX | D67: ='Opex Consolidés'!D7 | E67: ='Opex Consolidés'!E7 | G67: ='Opex Consolidés'!G7 | M67: ='Opex Consolidés'!M7 | P67: ='Opex Consolidés'!P7 | Q67: ='Opex Consolidés'!Q7 | S67: ='Opex Consolidés'!S7 | V67: ='Opex Consolidés'!V7 | W67: ='Opex Consolidés'!W7 | AA67: ='Opex Consolidés'!AA7 | AD67: ='Opex Consolidés'!AD7 | AE67: ='Opex Consolidés'!AE7 | AI67: ='Opex Consolidés'!AI7 | AL67: ='Opex Consolidés'!AL7 | AM67: ='Opex Consolidés'!AM7 | AR67: ='Opex Consolidés'!AR7 | AU67: 5235.8027 | AV67: 5853.3972 | AZ67: 5748.7478 | BC67: 5276.3231 | BD67: 5736.1233 | BH67: 5142.3972 | BK67: ='Opex Consolidés'!BK7 | BL67: ='Opex Consolidés'!BL7 | BQ67: ='Opex Consolidés'!BQ7 | BT67: ='Opex Consolidés'!BT7 | BU67: ='Opex Consolidés'!BU7 | BY67: ='Opex Consolidés'!BY7 | CB67: ='Opex Consolidés'!CB7 | CC67: ='Opex Consolidés'!CC7 | CG67: ='Opex Consolidés'!CG7 | CJ67: ='Opex Consolidés'!CJ7 | CK67: ='Opex Consolidés'!CK7 | CL67: ='Opex Consolidés'!#REF! | CO67: ='Opex Consolidés'!CO7 | CR67: ='Opex Consolidés'!CR7 | CS67: ='Opex Consolidés'!CS7 | CT67: ='Opex Consolidés'!CT7 | CW67: ='Opex Consolidés'!CW7
A68: CHECK | D68: =D66+D67 | E68: =E66+E67 | G68: =G66+G67 | M68: =M66+M67 | P68: =P66+P67 | Q68: =Q66+Q67 | S68: =S66+S67 | V68: =V66+V67 | W68: =W66+W67 | AA68: =AA66+AA67 | AD68: =AD66+AD67 | AE68: =AE66+AE67 | AI68: =AI66+AI67 | AL68: =AL66+AL67 | AM68: =AM66+AM67 | AR68: =AR66+AR67 | AU68: 0 | AV68: 0 | AZ68: 0 | BC68: 0 | BD68: 0 | BH68: 0 | BK68: =BK66+BK67 | BL68: =BL66+BL67 | BQ68: =BQ66+BQ67 | BT68: =BT66+BT67 | BU68: =BU66+BU67 | BY68: =BY66+BY67 | CB68: =CB66+CB67 | CC68: =CC66+CC67 | CG68: =CG66+CG67 | CJ68: =CJ66+CJ67 | CK68: =CK66+CK67 | CL68: =CL66+CL67 | CM68: =CM66+CM67 | CN68: =CN66+CN67 | CO68: =CO66+CO67 | CR68: =CR66+CR67 | CS68: =CS66+CS67 | CT68: =CT66+CT67 | CW68: =CW66+CW67
D72: =D7-'CA Mobile'!D8 | E72: =E7-'CA Mobile'!E8 | F72: =F7-'CA Mobile'!F8 | G72: =G7-'CA Mobile'!G8 | H72: =H7-'CA Mobile'!H8 | I72: =I7-'CA Mobile'!I8 | L72: =L7-'CA Mobile'!L8 | M72: =M7-'CA Mobile'!M8 | N72: =N7-'CA Mobile'!N8 | O72: =O7-'CA Mobile'!O8 | P72: =P7-'CA Mobile'!P8 | Q72: =Q7-'CA Mobile'!Q8 | R72: =R7-'CA Mobile'!R8 | S72: =S7-'CA Mobile'!S8 | ... AT72: =AT7-'CA Mobile'!AT8 | AU72: 0 | AV72: 0 | AW72: 0 | AX72: 0 | AY72: 0 | AZ72: 0 | BA72: 0 | BB72: =BB7-'CA Mobile'!BB8 | BC72: 0 | BD72: 0 | BE72: 0 | BF72: 0 | BG72: 1.8189894e-12 | BH72: 0 | BI72: 0 | BJ72: =BJ7-'CA Mobile'!BJ8 | BK72: =BK7-'CA Mobile'!BK8 | BL72: =BL7-'CA Mobile'!BL8 | BM72: =BM7-'CA Mobile'!BM8 | BN72: =BN7-'CA Mobile'!BN8 | BO72: =BO7-'CA Mobile'!BO8 | BP72: =BP7-'CA Mobile'!BP8 | BQ72: =BQ7-'CA Mobile'!BQ8 | ... DH72: =DH7-'CA Mobile'!DH8
D73: =D15-'Marge Mobile'!D58 | E73: =E15-'Marge Mobile'!E58 | F73: =F15-'Marge Mobile'!F58 | G73: =G15-'Marge Mobile'!G58 | H73: =H15-'Marge Mobile'!H58 | I73: =I15-'Marge Mobile'!I58 | L73: =L15-'Marge Mobile'!L58 | M73: =M15-'Marge Mobile'!M58 | N73: =N15-'Marge Mobile'!N58 | O73: =O15-'Marge Mobile'!O58 | P73: =P15-'Marge Mobile'!P58 | Q73: =Q15-'Marge Mobile'!Q58 | R73: =R15-'Marge Mobile'!R58 | S73: =S15-'Marge Mobile'!S58 | ... AT73: =AT15-'Marge Mobile'!AT58 | AU73: 0 | AV73: 0 | AW73: 0 | AX73: 0 | AY73: 0 | AZ73: 0 | BA73: 0 | BB73: =BB15-'Marge Mobile'!BB58 | BC73: 0 | BD73: 0 | BE73: 0 | BF73: 0 | BG73: 0 | BH73: 0 | BI73: 0 | BJ73: =BJ15-'Marge Mobile'!BJ58 | BK73: =BK15-'Marge Mobile'!BK58 | BL73: =BL15-'Marge Mobile'!BL58 | BM73: =BM15-'Marge Mobile'!BM58 | BN73: =BN15-'Marge Mobile'!BN58 | BO73: =BO15-'Marge Mobile'!BO58 | BP73: =BP15-'Marge Mobile'!BP58 | BQ73: =BQ15-'Marge Mobile'!BQ58 | ... DH73: =DH15-'Marge Mobile'!DH58
D74: =D20-'Marge Mobile'!D60 | E74: =E20-'Marge Mobile'!E60 | F74: =F20-'Marge Mobile'!F60 | G74: =G20-'Marge Mobile'!G60 | H74: =H20-'Marge Mobile'!H60 | I74: =I20-'Marge Mobile'!I60 | L74: =L20-'Marge Mobile'!L60 | M74: =M20-'Marge Mobile'!M60 | N74: =N20-'Marge Mobile'!N60 | O74: =O20-'Marge Mobile'!O60 | P74: =P20-'Marge Mobile'!P60 | Q74: =Q20-'Marge Mobile'!Q60 | R74: =R20-'Marge Mobile'!R60 | S74: =S20-'Marge Mobile'!S60 | ... AT74: =AT20-'Marge Mobile'!AT60 | AU74: 0 | AV74: 0 | AW74: 0 | AX74: 0 | AY74: 0 | AZ74: 0 | BA74: 0 | BB74: =BB20-'Marge Mobile'!BB60 | BC74: 0 | BD74: 0 | BE74: 0 | BF74: 0 | BG74: 0 | BH74: 0 | BI74: 0 | BJ74: =BJ20-'Marge Mobile'!BJ60 | BK74: =BK20-'Marge Mobile'!BK60 | BL74: =BL20-'Marge Mobile'!BL60 | BM74: =BM20-'Marge Mobile'!BM60 | BN74: =BN20-'Marge Mobile'!BN60 | BO74: =BO20-'Marge Mobile'!BO60 | BP74: =BP20-'Marge Mobile'!BP60 | BQ74: =BQ20-'Marge Mobile'!BQ60 | ... DH74: =DH20-'Marge Mobile'!DH60
D75: =D25+'Opex Consolidés'!D7 | E75: =E25+'Opex Consolidés'!E7 | F75: =F25+'Opex Consolidés'!F7 | G75: =G25+'Opex Consolidés'!G7 | H75: =H25+'Opex Consolidés'!H7 | I75: =I25+'Opex Consolidés'!I7 | L75: =L25+'Opex Consolidés'!L7 | M75: =M25+'Opex Consolidés'!M7 | N75: =N25+'Opex Consolidés'!N7 | O75: =O25+'Opex Consolidés'!O7 | P75: =P25+'Opex Consolidés'!P7 | Q75: =Q25+'Opex Consolidés'!Q7 | R75: =R25+'Opex Consolidés'!R7 | S75: =S25+'Opex Consolidés'!S7 | ... AA75: =AA25+'Opex Consolidés'!AA7 | AB75: #REF! | AC75: =AC25+'Opex Consolidés'!AC7 | AD75: =AD25+'Opex Consolidés'!AD7 | AE75: =AE25+'Opex Consolidés'!AE7 | AF75: =AF25+'Opex Consolidés'!AF7 | AG75: =AG25+'Opex Consolidés'!AG7 | AH75: =AH25+'Opex Consolidés'!AH7 | AI75: =AI25+'Opex Consolidés'!AI7 | AJ75: =AJ25+'Opex Consolidés'!AJ7 | ... AT75: =AT25+'Opex Consolidés'!AT7 | AU75: 0 | AV75: 0 | AW75: 0 | AX75: 0 | AY75: 0 | AZ75: 0 | BA75: -0.17845454 | BB75: =BB25+'Opex Consolidés'!BB7 | BC75: 0 | BD75: 0 | BE75: 0 | BF75: 0 | BG75: 0 | BH75: 0 | BI75: 0.052086955 | BJ75: =BJ25+'Opex Consolidés'!BJ7 | BK75: =BK25+'Opex Consolidés'!BK7 | BL75: =BL25+'Opex Consolidés'!BL7 | BM75: =BM25+'Opex Consolidés'!BM7 | BN75: =BN25+'Opex Consolidés'!BN7 | BO75: =BO25+'Opex Consolidés'!BO7 | BP75: =BP25+'Opex Consolidés'!BP7 | BQ75: =BQ25+'Opex Consolidés'!BQ7 | ... DH75: =DH25+'Opex Consolidés'!DH7

Sheet Opex Consolidés
J1: 6444110418 | Y1: =Y7/W7 | Z1: =Z7/X7 | AU1: -20648636 | AW1: 12.127701 | CR1: =65151.9-CR7 | DP1: 0
A2: Opex Consolidés | J2: 419560633 | K2: 0 | P2: 21468044 | W2: 839.68735 | X2: 0 | AD2: 0 | AE2: 0 | AF2: 2024 Réel | AO2: 0 | AU2: 0 | BN2: 0 | BP2: 0 | CR2: =CS7+'P&L conso'!CS25 | CT2: =CT7+'P&L conso'!CT25 | DP2: 10167534 | DQ2: 0 | DR2: 0 | DU2: 0
E3: 0 | G3: 0 | CZ3: 0 | DQ3: 295188041
D4: 45658 | J4: 45689 | P4: 45717 | V4: 45748 | AD4: 45778 | AL4: 45809 | AU4: 45839 | BC4: 45870 | BK4: 45901 | BT4: 45931 | CB4: 45962 | CJ4: 45992 | CR4: CUMUL | CZ4: ANNUEL
B5: (En Millions ML) | D5: 2025 Réel | E5: 2025 Budget | F5: Ecart / Budget | G5: 2024 Réel | H5: Evol % | J5: 2025 Réel | K5: 2025 Budget | L5: Ecart / Budget | M5: 2024 Réel | N5: Evol % | P5: 2025 Réel | Q5: 2025 Budget | R5: Ecart / Budget | S5: 2024 Réel | T5: Evol % | V5: 2025 Réel | W5: 2025 Budget | X5: 2025 Actu1 | Y5: Ecart / Budget | Z5: Ecart / Actu1 | AA5: 2024 Réel | AB5: Evol % | AD5: 2025 Réel | AE5: 2025 Budget | AF5: 2025 Actu1 | AG5: Ecart / Budget | AH5: Ecart / Actu1 | AI5: 2024 Réel | AJ5: Evol % | AL5: 2025 Réel | AM5: 2025 Budget | AN5: 2025 Actu1 | AO5: 2025 Actu2 | AP5: Ecart / Budget | AQ5: Ecart / Actu1 | AR5: 2024 Réel | AS5: Evol % | AU5: 2025 Réel | AV5: 2025 Budget | AW5: 2025 Actu2 | AX5: Ecart / Budget | AY5: Ecart / Actu2 | AZ5: 2024 Réel | BA5: Evol % | BC5: 2025 Réel | BD5: 2025 Budget | BE5: 2025 Actu2 | BF5: Ecart / Budget | BG5: Ecart / Actu2 | BH5: 2024 Réel | BI5: Evol % | BK5: 2025 Réel | BL5: 2025 Budget | BM5: 2025 Actu2 | BN5: 2025 Actu3 | BO5: Ecart / Budget | BP5: Ecart / Actu2 | BQ5: 2024 Réel | BR5: Evol % | BT5: 2025 Réel | BU5: 2025 Budget | BV5: 2025 Actu3 | BW5: Ecart / Budget | BX5: Ecart / Actu3 | BY5: 2024 Réel | BZ5: Evol % | CB5: 2025 Réel | CC5: 2025 Budget | CD5: 2025 Actu3 | CE5: Ecart / Budget | CF5: Ecart / Actu3 | CG5: 2024 Réel | CH5: Evol % | CJ5: 2025 Réel | CK5: 2025 Budget | CL5: 2025 Actu3 | CM5: Ecart / Budget | CN5: Ecart / Actu3 | CO5: 2024 Réel | CP5: Evol % | CR5: 2025 Réel | CS5: 2025 Budget | CT5: 2025 Actu3 | CU5: Ecart / Budget | CV5: Ecart / Actu3 | CW5: 2024 Réel | CX5: Evol % | CZ5: 2025 Budget | DA5: 2025 Actu1 | DB5: 2025 Actu2 | DC5: 2025 Actu3 | DD5: 2024 Réel | DE5: Bud / 2024 (%) | DF5: Actu 1 / 2024 (%) | DG5: Actu 2 / 2024 (%) | DH5: Actu3 / 2024 (%) | DJ5: 2025 Réel | DK5: 2025 Budget | DL5: 2024 Réel | DM5: Actu | DP5: 2025 Réel
DJ6: =SUM(D6,J6,P6,V6,AD6,AL6,AU6,BC6,BK6,BT6,CB6,CJ6)-CR6 | DK6: =SUM(E6,K6,Q6,W6,AE6,AM6,AV6,BD6,BL6,BU6,CC6,CK6)-CS6 | DL6: =SUM(G6,M6,S6,AA6,AI6,AR6,AZ6,BH6,BQ6,BY6,CG6,CO6)-CW6 | DM6: =SUM(D6,J6,P6,V6,AD6,AL6,AU6,BC6,,BN6,BV6,CD6,CL6)-CT6
B7: Total Opex | C7: Opex1 | D7: 5023.3945 | E7: 5752.8634 | F7: -729.46896 | G7: 5774.0655 | H7: -0.13000736 | J7: 5233.5165 | K7: 5412.0079 | L7: -178.49134 | M7: 5467.9109 | N7: -0.042867268 | P7: 5306.2354 | Q7: 5658.8042 | R7: -352.56882 | S7: 5318.9236 | T7: -0.0023854885 | V7: 5421.9008 | W7: 5772.0206 | X7: 5383.448 | Y7: -350.11983 | Z7: 38.452731 | AA7: 5458.7716 | AB7: -0.0067544161 | AD7: 5302.1763 | AE7: 5682.373 | AF7: 5325.1097 | AG7: -380.19665 | AH7: -22.93341 | AI7: 5565.8537 | AJ7: -0.047374108 | AL7: 5739.4271 | AM7: 5580.6859 | AN7: 0 | AO7: 0 | AP7: 158.74112 | AQ7: 5739.4271 | AR7: 5075.041 | AS7: 0.13091246 | CR7: =SUMIF($D$5:$CQ$5,CR$5,$D7:$CQ7) | CS7: =SUMIF($D$5:$CQ$5,CS$5,$D7:$CQ7) | CT7: =SUMIF($D$5:$CQ$5,CT$5,$D7:$CQ7)+SUMIF($D$5:$BI$5,CR$5,$D7:$BI7) | CU7: =+CR7-CS7 | CV7: =+CR7-CT7 | CW7: =SUMIF($D$5:$CQ$5,CW$5,$D7:$CQ7) | CX7: =IFERROR(CR7/CW7-1, "-") | CZ7: 67535.531 | DD7: 66696.264 | DE7: =+CZ7/DD7-1 | DF7: =+DA7/DD7-1 | DG7: =+DB7/DD7-1 | DH7: =+DC7/DD7-1 | DJ7: =SUM(D7,J7,P7,V7,AD7,AL7,AU7,BC7,BK7,BT7,CB7,CJ7)-CR7 | DK7: =SUM(E7,K7,Q7,W7,AE7,AM7,AV7,BD7,BL7,BU7,CC7,CK7)-CS7 | DL7: =SUM(G7,M7,S7,AA7,AI7,AR7,AZ7,BH7,BQ7,BY7,CG7,CO7)-CW7 | DM7: =SUM(D7,J7,P7,V7,AD7,AL7,AU7,BC7,,BN7,BV7,CD7,CL7)-CT7 | DP7: =SUM(DP9,DP40,DP57,DP113,DP167,DP184,DP201) | DQ7: =-CR7+DP7/10^6 | DR7: =SUM(E7,K7,Q7,W7,AE7,AM7,AV7,BD7,BL7,BU7,CC7,CK7)-CS7 | DS7: =SUM(D7,J7,P7,V7,AD7,AL7,AU7,BC7,,BN7,BV7,CD7,CL7)-CT7 | DU7: 6509.7557 | DV7: =DU7-CJ7
C8: Opex2 | CT8: =SUMIF($D$5:$CQ$5,CT$5,$D8:$CQ8)+SUMIF($D$5:$BI$5,CR$5,$D8:$BI8) | CX8: =IFERROR(CR8/CW8-1, "-") | DJ8: =SUM(D8,J8,P8,V8,AD8,AL8,AU8,BC8,BK8,BT8,CB8,CJ8)-CR8 | DK8: =SUM(E8,K8,Q8,W8,AE8,AM8,AV8,BD8,BL8,BU8,CC8,CK8)-CS8 | DL8: =SUM(G8,M8,S8,AA8,AI8,AR8,AZ8,BH8,BQ8,BY8,CG8,CO8)-CW8 | DM8: =SUM(D8,J8,P8,V8,AD8,AL8,AU8,BC8,,BN8,BV8,CD8,CL8)-CT8 | DQ8: =-CR8+DP8/10^6 | DR8: =SUM(E8,K8,Q8,W8,AE8,AM8,AV8,BD8,BL8,BU8,CC8,CK8)-CS8 | DS8: =SUM(D8,J8,P8,V8,AD8,AL8,AU8,BC8,,BN8,BV8,CD8,CL8)-CT8 | DV8: =DU8-CJ8 | DX8: =CS8-CZ8 | DY8: =CT8-DC8 | DZ8: =CW8-DD8
B9: Personnel | C9: Opex3 | D9: 418.50116 | E9: 437.22587 | F9: -18.724713 | G9: 463.14343 | H9: -0.096389728 | J9: 427.18334 | K9: 437.22587 | L9: -10.04253 | M9: 414.54924 | N9: 0.03047673 | P9: 451.70827 | Q9: 437.22587 | R9: 14.482397 | S9: 412.27444 | T9: 0.095649461 | V9: 425.00465 | W9: 452.22587 | X9: 452.22587 | Y9: -27.221217 | Z9: -27.221217 | AA9: 409.95078 | AB9: 0.036721172 | AD9: 403.8914 | AE9: 437.22587 | AF9: 437.22587 | AG9: -33.33447 | AH9: -33.33447 | AI9: 422.14686 | AJ9: -0.043244332 | AL9: 559.2972 | AM9: 437.22587 | AN9: 0 | AO9: 0 | AP9: 122.07133 | AQ9: 559.2972 | AR9: 439.56219 | AS9: 0.27239605 | CR9: =SUMIF($D$5:$CQ$5,CR$5,$D9:$CQ9) | CS9: =SUMIF($D$5:$CQ$5,CS$5,$D9:$CQ9) | CT9: =SUMIF($D$5:$CQ$5,CT$5,$D9:$CQ9)+SUMIF($D$5:$BI$5,CR$5,$D9:$BI9) | CU9: =+CR9-CS9 | CV9: =+CR9-CT9 | CW9: =SUMIF($D$5:$CQ$5,CW$5,$D9:$CQ9) | CX9: =IFERROR(CR9/CW9-1, "-") | CZ9: 5306.5205 | DD9: 5023.8916 | DE9: =+CZ9/DD9-1 | DF9: =+DA9/DD9-1 | DG9: =+DB9/DD9-1 | DH9: =+DC9/DD9-1 | DJ9: =SUM(D9,J9,P9,V9,AD9,AL9,AU9,BC9,BK9,BT9,CB9,CJ9)-CR9 | DK9: =SUM(E9,K9,Q9,W9,AE9,AM9,AV9,BD9,BL9,BU9,CC9,CK9)-CS9 | DL9: =SUM(G9,M9,S9,AA9,AI9,AR9,AZ9,BH9,BQ9,BY9,CG9,CO9)-CW9 | DM9: =SUM(D9,J9,P9,V9,AD9,AL9,AU9,BC9,,BN9,BV9,CD9,CL9)-CT9 | DP9: =SUM(DP10:DP38) | DQ9: =-CR9+DP9/10^6 | DR9: =SUM(E9,K9,Q9,W9,AE9,AM9,AV9,BD9,BL9,BU9,CC9,CK9)-CS9 | DS9: =SUM(D9,J9,P9,V9,AD9,AL9,AU9,BC9,,BN9,BV9,CD9,CL9)-CT9 | DU9: 438.17153 | DV9: =DU9-CJ9 | DX9: =(CS9-CZ9)*10^6 | DY9: =(CT9-DC9)*10^6 | DZ9: =(CW9-DD9)*10^6
B10: TAXES SUR APPOINTEMENTS ET SAL | C10: Opex4 | G10: 0 | M10: 0 | S10: 0 | AA10: 0 | AI10: 0 | CR10: =SUMIF($D$5:$CQ$5,CR$5,$D10:$CQ10) | CS10: =SUMIF($D$5:$CQ$5,CS$5,$D10:$CQ10) | CT10: =SUMIF($D$5:$CQ$5,CT$5,$D10:$CQ10)+SUMIF($D$5:$BI$5,CR$5,$D10:$BI10) | CU10: =+CR10-CS10 | CV10: =+CR10-CT10 | CW10: =SUMIF($D$5:$CQ$5,CW$5,$D10:$CQ10) | CX10: =IFERROR(CR10/CW10-1, "-") | CZ10: 0 | DA10: 0 | DD10: 0 | DJ10: =SUM(D10,J10,P10,V10,AD10,AL10,AU10,BC10,BK10,BT10,CB10,CJ10)-CR10 | DK10: =SUM(E10,K10,Q10,W10,AE10,AM10,AV10,BD10,BL10,BU10,CC10,CK10)-CS10 | DL10: =SUM(G10,M10,S10,AA10,AI10,AR10,AZ10,BH10,BQ10,BY10,CG10,CO10)-CW10 | DM10: =SUM(D10,J10,P10,V10,AD10,AL10,AU10,BC10,,BN10,BV10,CD10,CL10)-CT10 | DQ10: =-CR10+DP10/10^6 | DR10: =SUM(E10,K10,Q10,W10,AE10,AM10,AV10,BD10,BL10,BU10,CC10,CK10)-CS10 | DS10: =SUM(D10,J10,P10,V10,AD10,AL10,AU10,BC10,,BN10,BV10,CD10,CL10)-CT10 | DV10: =DU10-CJ10 | DX10: =(CS10-CZ10)*10^6 | DY10: =(CT10-DC10)*10^6 | DZ10: =(CW10-DD10)*10^6
B11: APPOINTEMENTS, SALAIRES PERSON | C11: Opex5 | D11: 226.87083 | E11: 271.843 | G11: 243.82677 | J11: 276.09957 | K11: 271.843 | M11: 250.52701 | P11: 256.55706 | Q11: 271.843 | S11: 251.32896 | V11: 254.56437 | W11: 271.843 | X11: 271.843 | AA11: 255.07508 | AD11: 256.07346 | AE11: 271.843 | AF11: 271.843 | AI11: 254.42255 | AL11: 230.9815 | AM11: 271.843 | CR11: =SUMIF($D$5:$CQ$5,CR$5,$D11:$CQ11) | CS11: =SUMIF($D$5:$CQ$5,CS$5,$D11:$CQ11) | CT11: =SUMIF($D$5:$CQ$5,CT$5,$D11:$CQ11)+SUMIF($D$5:$BI$5,CR$5,$D11:$BI11) | CU11: =+CR11-CS11 | CV11: =+CR11-CT11 | CW11: =SUMIF($D$5:$CQ$5,CW$5,$D11:$CQ11) | CX11: =IFERROR(CR11/CW11-1, "-") | CZ11: 3262.1161 | DA11: 3206.1145 | DD11: 3047.1451 | DE11: =+CZ11/DD11-1 | DF11: =+DA11/DD11-1 | DG11: =+DB11/DD11-1 | DH11: =+DC11/DD11-1 | DJ11: =SUM(D11,J11,P11,V11,AD11,AL11,AU11,BC11,BK11,BT11,CB11,CJ11)-CR11 | DK11: =SUM(E11,K11,Q11,W11,AE11,AM11,AV11,BD11,BL11,BU11,CC11,CK11)-CS11 | DL11: =SUM(G11,M11,S11,AA11,AI11,AR11,AZ11,BH11,BQ11,BY11,CG11,CO11)-CW11 | DM11: =SUM(D11,J11,P11,V11,AD11,AL11,AU11,BC11,,BN11,BV11,CD11,CL11)-CT11 | DP11: #VALUE! | DQ11: =-CR11+DP11/10^6 | DR11: =SUM(E11,K11,Q11,W11,AE11,AM11,AV11,BD11,BL11,BU11,CC11,CK11)-CS11 | DS11: =SUM(D11,J11,P11,V11,AD11,AL11,AU11,BC11,,BN11,BV11,CD11,CL11)-CT11 | DT11: =DQ11/11 | DU11: 262.72376 | DV11: =DU11-CJ11 | DX11: =(CS11-CZ11)*10^6 | DY11: =(CT11-DC11)*10^6 | DZ11: =(CW11-DD11)*10^6
B12: CONGES PAYES PERSONNEL NATIONA | C12: Opex6 | D12: 49.304441 | G12: 52.490243 | J12: 13.921259 | M12: 19.639126 | P12: 6.139638 | S12: 27.372416 | V12: 17.04329 | AA12: 12.074878 | AD12: 14.646434 | AI12: 16.600311 | AL12: 13.385284 | CR12: =SUMIF($D$5:$CQ$5,CR$5,$D12:$CQ12) | CS12: =SUMIF($D$5:$CQ$5,CS$5,$D12:$CQ12) | CT12: =SUMIF($D$5:$CQ$5,CT$5,$D12:$CQ12)+SUMIF($D$5:$BI$5,CR$5,$D12:$BI12) | CU12: =+CR12-CS12 | CV12: =+CR12-CT12 | CW12: =SUMIF($D$5:$CQ$5,CW$5,$D12:$CQ12) | CX12: =IFERROR(CR12/CW12-1, "-") | CZ12: 0 | DA12: 69.365338 | DD12: 110.74184 | DE12: =+CZ12/DD12-1 | DF12: =+DA12/DD12-1 | DG12: =+DB12/DD12-1 | DH12: =+DC12/DD12-1 | DJ12: =SUM(D12,J12,P12,V12,AD12,AL12,AU12,BC12,BK12,BT12,CB12,CJ12)-CR12 | DK12: =SUM(E12,K12,Q12,W12,AE12,AM12,AV12,BD12,BL12,BU12,CC12,CK12)-CS12 | DL12: =SUM(G12,M12,S12,AA12,AI12,AR12,AZ12,BH12,BQ12,BY12,CG12,CO12)-CW12 | DM12: =SUM(D12,J12,P12,V12,AD12,AL12,AU12,BC12,,BN12,BV12,CD12,CL12)-CT12 | DP12: #VALUE! | DQ12: =-CR12+DP12/10^6 | DR12: =SUM(E12,K12,Q12,W12,AE12,AM12,AV12,BD12,BL12,BU12,CC12,CK12)-CS12 | DS12: =SUM(D12,J12,P12,V12,AD12,AL12,AU12,BC12,,BN12,BV12,CD12,CL12)-CT12 | DU12: -31.251393 | DV12: =DU12-CJ12 | DX12: =(CS12-CZ12)*10^6 | DY12: =(CT12-DC12)*10^6 | DZ12: =(CW12-DD12)*10^6
B13: CHARGES SOCIALES S/ REMUNERATI | C13: Opex7 | D13: 67.453394 | E13: 70.154336 | G13: 76.944862 | J13: 70.409587 | K13: 70.154336 | M13: 70.194999 | P13: 68.244258 | Q13: 70.154336 | S13: 62.751017 | V13: 66.503683 | W13: 70.154336 | X13: 70.154336 | AA13: 63.971797 | AD13: 67.135866 | AE13: 70.154336 | AF13: 70.154336 | AI13: 67.709261 | AL13: 66.425273 | AM13: 70.154336 | CR13: =SUMIF($D$5:$CQ$5,CR$5,$D13:$CQ13) | CS13: =SUMIF($D$5:$CQ$5,CS$5,$D13:$CQ13) | CT13: =SUMIF($D$5:$CQ$5,CT$5,$D13:$CQ13)+SUMIF($D$5:$BI$5,CR$5,$D13:$BI13) | CU13: =+CR13-CS13 | CV13: =+CR13-CT13 | CW13: =SUMIF($D$5:$CQ$5,CW$5,$D13:$CQ13) | CX13: =IFERROR(CR13/CW13-1, "-") | CZ13: 841.85203 | DA13: 837.49626 | DD13: 797.67097 | DE13: =+CZ13/DD13-1 | DF13: =+DA13/DD13-1 | DG13: =+DB13/DD13-1 | DH13: =+DC13/DD13-1 | DJ13: =SUM(D13,J13,P13,V13,AD13,AL13,AU13,BC13,BK13,BT13,CB13,CJ13)-CR13 | DK13: =SUM(E13,K13,Q13,W13,AE13,AM13,AV13,BD13,BL13,BU13,CC13,CK13)-CS13 | DL13: =SUM(G13,M13,S13,AA13,AI13,AR13,AZ13,BH13,BQ13,BY13,CG13,CO13)-CW13 | DM13: =SUM(D13,J13,P13,V13,AD13,AL13,AU13,BC13,,BN13,BV13,CD13,CL13)-CT13 | DP13: #VALUE! | DQ13: =-CR13+DP13/10^6 | DR13: =SUM(E13,K13,Q13,W13,AE13,AM13,AV13,BD13,BL13,BU13,CC13,CK13)-CS13 | DS13: =SUM(D13,J13,P13,V13,AD13,AL13,AU13,BC13,,BN13,BV13,CD13,CL13)-CT13 | DU13: 68.494617 | DV13: =DU13-CJ13 | DX13: =(CS13-CZ13)*10^6 | DY13: =(CT13-DC13)*10^6 | DZ13: =(CW13-DD13)*10^6
B14: AUTRES CHARGES SOCIALES | C14: Opex8 | D14: 16.100452 | E14: 23.470584 | G14: 17.821406 | J14: 20.932853 | K14: 23.470584 | M14: 18.223743 | P14: 18.214341 | Q14: 23.470584 | S14: 18.138523 | V14: 18.372789 | W14: 23.470584 | X14: 23.470584 | AA14: 20.539258 | AD14: 18.097547 | AE14: 23.470584 | AF14: 23.470584 | AI14: 18.286525 | AL14: 16.915452 | AM14: 23.470584 | CR14: =SUMIF($D$5:$CQ$5,CR$5,$D14:$CQ14) | CS14: =SUMIF($D$5:$CQ$5,CS$5,$D14:$CQ14) | CT14: =SUMIF($D$5:$CQ$5,CT$5,$D14:$CQ14)+SUMIF($D$5:$BI$5,CR$5,$D14:$BI14) | CU14: =+CR14-CS14 | CV14: =+CR14-CT14 | CW14: =SUMIF($D$5:$CQ$5,CW$5,$D14:$CQ14) | CX14: =IFERROR(CR14/CW14-1, "-") | CZ14: 281.64701 | DA14: 266.48291 | DD14: 216.52125 | DE14: =+CZ14/DD14-1 | DF14: =+DA14/DD14-1 | DG14: =+DB14/DD14-1 | DH14: =+DC14/DD14-1 | DJ14: =SUM(D14,J14,P14,V14,AD14,AL14,AU14,BC14,BK14,BT14,CB14,CJ14)-CR14 | DK14: =SUM(E14,K14,Q14,W14,AE14,AM14,AV14,BD14,BL14,BU14,CC14,CK14)-CS14 | DL14: =SUM(G14,M14,S14,AA14,AI14,AR14,AZ14,BH14,BQ14,BY14,CG14,CO14)-CW14 | DM14: =SUM(D14,J14,P14,V14,AD14,AL14,AU14,BC14,,BN14,BV14,CD14,CL14)-CT14 | DP14: #VALUE! | DQ14: =-CR14+DP14/10^6 | DR14: =SUM(E14,K14,Q14,W14,AE14,AM14,AV14,BD14,BL14,BU14,CC14,CK14)-CS14 | DS14: =SUM(D14,J14,P14,V14,AD14,AL14,AU14,BC14,,BN14,BV14,CD14,CL14)-CT14 | DU14: 14.369378 | DV14: =DU14-CJ14 | DX14: =(CS14-CZ14)*10^6 | DY14: =(CT14-DC14)*10^6 | DZ14: =(CW14-DD14)*10^6
B15: PERSONNEL INTERIMAIRE & STAGIA | C15: Opex9 | E15: 0 | G15: 0 | K15: 0 | M15: 0 | Q15: 0 | S15: 0 | W15: 0 | X15: 0 | AA15: 0 | AE15: 0 | AF15: 0 | AI15: 0 | AL15: 0 | AM15: 0 | CT15: =SUMIF($D$5:$CQ$5,CT$5,$D15:$CQ15)+SUMIF($D$5:$BI$5,CR$5,$D15:$BI15) | CX15: =IFERROR(CR15/CW15-1, "-") | CZ15: 0 | DA15: 0 | DD15: 0 | DG15: =+DB15/DD15-1 | DH15: =+DC15/DD15-1 | DJ15: =SUM(D15,J15,P15,V15,AD15,AL15,AU15,BC15,BK15,BT15,CB15,CJ15)-CR15 | DK15: =SUM(E15,K15,Q15,W15,AE15,AM15,AV15,BD15,BL15,BU15,CC15,CK15)-CS15 | DL15: =SUM(G15,M15,S15,AA15,AI15,AR15,AZ15,BH15,BQ15,BY15,CG15,CO15)-CW15 | DM15: =SUM(D15,J15,P15,V15,AD15,AL15,AU15,BC15,,BN15,BV15,CD15,CL15)-CT15 | DQ15: =-CR15+DP15/10^6 | DR15: =SUM(E15,K15,Q15,W15,AE15,AM15,AV15,BD15,BL15,BU15,CC15,CK15)-CS15 | DS15: =SUM(D15,J15,P15,V15,AD15,AL15,AU15,BC15,,BN15,BV15,CD15,CL15)-CT15 | DV15: =DU15-CJ15 | DX15: =(CS15-CZ15)*10^6 | DY15: =(CT15-DC15)*10^6 | DZ15: =(CW15-DD15)*10^6
B16: PRIMES ET GRATIFICATIONS PERSO | C16: Opex10 | D16: 33.39541 | E16: 38.379319 | G16: 26.709627 | J16: 4.563872 | K16: 38.379319 | M16: 15.861169 | P16: 87.867673 | Q16: 38.379319 | S16: 28.380923 | V16: 37.495894 | W16: 38.379319 | X16: 38.379319 | AA16: 26.218939 | AD16: 19.917355 | AE16: 38.379319 | AF16: 38.379319 | AI16: 36.479091 | AL16: 39.543724 | AM16: 38.379319 | CR16: =SUMIF($D$5:$CQ$5,CR$5,$D16:$CQ16) | CS16: =SUMIF($D$5:$CQ$5,CS$5,$D16:$CQ16) | CT16: =SUMIF($D$5:$CQ$5,CT$5,$D16:$CQ16)+SUMIF($D$5:$BI$5,CR$5,$D16:$BI16) | CU16: =+CR16-CS16 | CV16: =+CR16-CT16 | CW16: =SUMIF($D$5:$CQ$5,CW$5,$D16:$CQ16) | CX16: =IFERROR(CR16/CW16-1, "-") | CZ16: 460.55183 | DA16: 471.24082 | DD16: 459.16007 | DE16: =+CZ16/DD16-1 | DF16: =+DA16/DD16-1 | DG16: =+DB16/DD16-1 | DH16: =+DC16/DD16-1 | DJ16: =SUM(D16,J16,P16,V16,AD16,AL16,AU16,BC16,BK16,BT16,CB16,CJ16)-CR16 | DK16: =SUM(E16,K16,Q16,W16,AE16,AM16,AV16,BD16,BL16,BU16,CC16,CK16)-CS16 | DL16: =SUM(G16,M16,S16,AA16,AI16,AR16,AZ16,BH16,BQ16,BY16,CG16,CO16)-CW16 | DM16: =SUM(D16,J16,P16,V16,AD16,AL16,AU16,BC16,,BN16,BV16,CD16,CL16)-CT16 | DP16: #VALUE! | DQ16: =-CR16+DP16/10^6 | DR16: =SUM(E16,K16,Q16,W16,AE16,AM16,AV16,BD16,BL16,BU16,CC16,CK16)-CS16 | DS16: =SUM(D16,J16,P16,V16,AD16,AL16,AU16,BC16,,BN16,BV16,CD16,CL16)-CT16 | DT16: 22.791149 | DU16: 89.601339 | DV16: =DU16-CJ16 | DX16: =(CS16-CZ16)*10^6 | DY16: =(CT16-DC16)*10^6 | DZ16: =(CW16-DD16)*10^6
B17: INDEMNITES DE LICENCIEMENT PER | C17: Opex11 | G17: 0 | J17: 12.842046 | M17: 0 | P17: -12.842046 | S17: 0 | V17: 0 | AA17: 0 | AD17: 0 | AI17: 0 | AL17: 0 | CR17: =SUMIF($D$5:$CQ$5,CR$5,$D17:$CQ17) | CS17: =SUMIF($D$5:$CQ$5,CS$5,$D17:$CQ17) | CT17: =SUMIF($D$5:$CQ$5,CT$5,$D17:$CQ17)+SUMIF($D$5:$BI$5,CR$5,$D17:$BI17) | CU17: =+CR17-CS17 | CV17: =+CR17-CT17 | CW17: =SUMIF($D$5:$CQ$5,CW$5,$D17:$CQ17) | CX17: =IFERROR(CR17/CW17-1, "-") | CZ17: 0 | DA17: 0 | DD17: 0 | DJ17: =SUM(D17,J17,P17,V17,AD17,AL17,AU17,BC17,BK17,BT17,CB17,CJ17)-CR17 | DK17: =SUM(E17,K17,Q17,W17,AE17,AM17,AV17,BD17,BL17,BU17,CC17,CK17)-CS17 | DL17: =SUM(G17,M17,S17,AA17,AI17,AR17,AZ17,BH17,BQ17,BY17,CG17,CO17)-CW17 | DM17: =SUM(D17,J17,P17,V17,AD17,AL17,AU17,BC17,,BN17,BV17,CD17,CL17)-CT17 | DQ17: =-CR17+DP17/10^6 | DR17: =SUM(E17,K17,Q17,W17,AE17,AM17,AV17,BD17,BL17,BU17,CC17,CK17)-CS17 | DS17: =SUM(D17,J17,P17,V17,AD17,AL17,AU17,BC17,,BN17,BV17,CD17,CL17)-CT17 | DV17: =DU17-CJ17 | DX17: =(CS17-CZ17)*10^6 | DY17: =(CT17-DC17)*10^6 | DZ17: =(CW17-DD17)*10^6
B18: EAU RESIDENCES | C18: Opex12 | G18: 0 | M18: 0 | S18: 0 | AA18: 0 | AI18: 0 | CR18: =SUMIF($D$5:$CQ$5,CR$5,$D18:$CQ18) | CS18: =SUMIF($D$5:$CQ$5,CS$5,$D18:$CQ18) | CT18: =SUMIF($D$5:$CQ$5,CT$5,$D18:$CQ18)+SUMIF($D$5:$BI$5,CR$5,$D18:$BI18) | CU18: =+CR18-CS18 | CV18: =+CR18-CT18 | CW18: =SUMIF($D$5:$CQ$5,CW$5,$D18:$CQ18) | CX18: =IFERROR(CR18/CW18-1, "-") | CZ18: 0 | DA18: 0 | DD18: 0 | DJ18: =SUM(D18,J18,P18,V18,AD18,AL18,AU18,BC18,BK18,BT18,CB18,CJ18)-CR18 | DK18: =SUM(E18,K18,Q18,W18,AE18,AM18,AV18,BD18,BL18,BU18,CC18,CK18)-CS18 | DL18: =SUM(G18,M18,S18,AA18,AI18,AR18,AZ18,BH18,BQ18,BY18,CG18,CO18)-CW18 | DM18: =SUM(D18,J18,P18,V18,AD18,AL18,AU18,BC18,,BN18,BV18,CD18,CL18)-CT18 | DQ18: =-CR18+DP18/10^6 | DR18: =SUM(E18,K18,Q18,W18,AE18,AM18,AV18,BD18,BL18,BU18,CC18,CK18)-CS18 | DS18: =SUM(D18,J18,P18,V18,AD18,AL18,AU18,BC18,,BN18,BV18,CD18,CL18)-CT18 | DV18: =DU18-CJ18 | DX18: =(CS18-CZ18)*10^6 | DY18: =(CT18-DC18)*10^6 | DZ18: =(CW18-DD18)*10^6
B19: ELECTRICITE RESIDENCES | C19: Opex13 | G19: 0 | M19: 0 | S19: 0 | AA19: 0 | AI19: 0 | CR19: =SUMIF($D$5:$CQ$5,CR$5,$D19:$CQ19) | CS19: =SUMIF($D$5:$CQ$5,CS$5,$D19:$CQ19) | CT19: =SUMIF($D$5:$CQ$5,CT$5,$D19:$CQ19)+SUMIF($D$5:$BI$5,CR$5,$D19:$BI19) | CU19: =+CR19-CS19 | CV19: =+CR19-CT19 | CW19: =SUMIF($D$5:$CQ$5,CW$5,$D19:$CQ19) | CX19: =IFERROR(CR19/CW19-1, "-") | CZ19: 0 | DA19: 0 | DD19: 0 | DJ19: =SUM(D19,J19,P19,V19,AD19,AL19,AU19,BC19,BK19,BT19,CB19,CJ19)-CR19 | DK19: =SUM(E19,K19,Q19,W19,AE19,AM19,AV19,BD19,BL19,BU19,CC19,CK19)-CS19 | DL19: =SUM(G19,M19,S19,AA19,AI19,AR19,AZ19,BH19,BQ19,BY19,CG19,CO19)-CW19 | DM19: =SUM(D19,J19,P19,V19,AD19,AL19,AU19,BC19,,BN19,BV19,CD19,CL19)-CT19 | DQ19: =-CR19+DP19/10^6 | DR19: =SUM(E19,K19,Q19,W19,AE19,AM19,AV19,BD19,BL19,BU19,CC19,CK19)-CS19 | DS19: =SUM(D19,J19,P19,V19,AD19,AL19,AU19,BC19,,BN19,BV19,CD19,CL19)-CT19 | DV19: =DU19-CJ19 | DX19: =(CS19-CZ19)*10^6 | DY19: =(CT19-DC19)*10^6 | DZ19: =(CW19-DD19)*10^6
B20: LOYERS RESIDENCES | C20: Opex14 | G20: 0 | M20: 0 | S20: 0 | AA20: 0 | AI20: 0 | CR20: =SUMIF($D$5:$CQ$5,CR$5,$D20:$CQ20) | CS20: =SUMIF($D$5:$CQ$5,CS$5,$D20:$CQ20) | CT20: =SUMIF($D$5:$CQ$5,CT$5,$D20:$CQ20)+SUMIF($D$5:$BI$5,CR$5,$D20:$BI20) | CU20: =+CR20-CS20 | CV20: =+CR20-CT20 | CW20: =SUMIF($D$5:$CQ$5,CW$5,$D20:$CQ20) | CX20: =IFERROR(CR20/CW20-1, "-") | CZ20: 0 | DA20: 0 | DD20: 0 | DJ20: =SUM(D20,J20,P20,V20,AD20,AL20,AU20,BC20,BK20,BT20,CB20,CJ20)-CR20 | DK20: =SUM(E20,K20,Q20,W20,AE20,AM20,AV20,BD20,BL20,BU20,CC20,CK20)-CS20 | DL20: =SUM(G20,M20,S20,AA20,AI20,AR20,AZ20,BH20,BQ20,BY20,CG20,CO20)-CW20 | DM20: =SUM(D20,J20,P20,V20,AD20,AL20,AU20,BC20,,BN20,BV20,CD20,CL20)-CT20 | DQ20: =-CR20+DP20/10^6 | DR20: =SUM(E20,K20,Q20,W20,AE20,AM20,AV20,BD20,BL20,BU20,CC20,CK20)-CS20 | DS20: =SUM(D20,J20,P20,V20,AD20,AL20,AU20,BC20,,BN20,BV20,CD20,CL20)-CT20 | DV20: =DU20-CJ20 | DX20: =(CS20-CZ20)*10^6 | DY20: =(CT20-DC20)*10^6 | DZ20: =(CW20-DD20)*10^6
B21: ENTRETIEN ET REPARATIONS RESID | C21: Opex15 | G21: 0 | M21: 0 | S21: 0 | AA21: 0 | AI21: 0 | CR21: =SUMIF($D$5:$CQ$5,CR$5,$D21:$CQ21) | CS21: =SUMIF($D$5:$CQ$5,CS$5,$D21:$CQ21) | CT21: =SUMIF($D$5:$CQ$5,CT$5,$D21:$CQ21)+SUMIF($D$5:$BI$5,CR$5,$D21:$BI21) | CU21: =+CR21-CS21 | CV21: =+CR21-CT21 | CW21: =SUMIF($D$5:$CQ$5,CW$5,$D21:$CQ21) | CX21: =IFERROR(CR21/CW21-1, "-") | CZ21: 0 | DA21: 0 | DD21: 0 | DJ21: =SUM(D21,J21,P21,V21,AD21,AL21,AU21,BC21,BK21,BT21,CB21,CJ21)-CR21 | DK21: =SUM(E21,K21,Q21,W21,AE21,AM21,AV21,BD21,BL21,BU21,CC21,CK21)-CS21 | DL21: =SUM(G21,M21,S21,AA21,AI21,AR21,AZ21,BH21,BQ21,BY21,CG21,CO21)-CW21 | DM21: =SUM(D21,J21,P21,V21,AD21,AL21,AU21,BC21,,BN21,BV21,CD21,CL21)-CT21 | DQ21: =-CR21+DP21/10^6 | DR21: =SUM(E21,K21,Q21,W21,AE21,AM21,AV21,BD21,BL21,BU21,CC21,CK21)-CS21 | DS21: =SUM(D21,J21,P21,V21,AD21,AL21,AU21,BC21,,BN21,BV21,CD21,CL21)-CT21 | DV21: =DU21-CJ21 | DX21: =(CS21-CZ21)*10^6 | DY21: =(CT21-DC21)*10^6 | DZ21: =(CW21-DD21)*10^6
B22: FRAIS MEDICAUX PERSONNEL NATIO | C22: Opex16 | G22: 0 | M22: 0 | S22: 0 | AA22: 0 | AI22: 0 | AL22: 0 | CR22: =SUMIF($D$5:$CQ$5,CR$5,$D22:$CQ22) | CS22: =SUMIF($D$5:$CQ$5,CS$5,$D22:$CQ22) | CT22: =SUMIF($D$5:$CQ$5,CT$5,$D22:$CQ22)+SUMIF($D$5:$BI$5,CR$5,$D22:$BI22) | CU22: =+CR22-CS22 | CV22: =+CR22-CT22 | CW22: =SUMIF($D$5:$CQ$5,CW$5,$D22:$CQ22) | CX22: =IFERROR(CR22/CW22-1, "-") | CZ22: 0 | DA22: 0 | DD22: 0 | DJ22: =SUM(D22,J22,P22,V22,AD22,AL22,AU22,BC22,BK22,BT22,CB22,CJ22)-CR22 | DK22: =SUM(E22,K22,Q22,W22,AE22,AM22,AV22,BD22,BL22,BU22,CC22,CK22)-CS22 | DL22: =SUM(G22,M22,S22,AA22,AI22,AR22,AZ22,BH22,BQ22,BY22,CG22,CO22)-CW22 | DM22: =SUM(D22,J22,P22,V22,AD22,AL22,AU22,BC22,,BN22,BV22,CD22,CL22)-CT22 | DQ22: =-CR22+DP22/10^6 | DR22: =SUM(E22,K22,Q22,W22,AE22,AM22,AV22,BD22,BL22,BU22,CC22,CK22)-CS22 | DS22: =SUM(D22,J22,P22,V22,AD22,AL22,AU22,BC22,,BN22,BV22,CD22,CL22)-CT22 | DV22: =DU22-CJ22 | DX22: =(CS22-CZ22)*10^6 | DY22: =(CT22-DC22)*10^6 | DZ22: =(CW22-DD22)*10^6
B23: AVANTAGES EN NATURE PERSONNEL | C23: Opex17 | D23: 14.098579 | E23: 15.315587 | G23: 32.254248 | J23: 13.386099 | K23: 15.315587 | M23: 27.960439 | P23: 12.477019 | Q23: 15.315587 | S23: 11.743268 | V23: 16.032823 | W23: 30.315587 | X23: 30.315587 | AA23: 19.511494 | AD23: 12.985269 | AE23: 15.315587 | AF23: 15.315587 | AI23: 15.867698 | AL23: 7.47608 | AM23: 15.315587 | CR23: =SUMIF($D$5:$CQ$5,CR$5,$D23:$CQ23) | CS23: =SUMIF($D$5:$CQ$5,CS$5,$D23:$CQ23) | CT23: =SUMIF($D$5:$CQ$5,CT$5,$D23:$CQ23)+SUMIF($D$5:$BI$5,CR$5,$D23:$BI23) | CU23: =+CR23-CS23 | CV23: =+CR23-CT23 | CW23: =SUMIF($D$5:$CQ$5,CW$5,$D23:$CQ23) | CX23: =IFERROR(CR23/CW23-1, "-") | CZ23: 243.59705 | DA23: 237.61198 | DD23: 195.41184 | DE23: =+CZ23/DD23-1 | DF23: =+DA23/DD23-1 | DG23: =+DB23/DD23-1 | DH23: =+DC23/DD23-1 | DJ23: =SUM(D23,J23,P23,V23,AD23,AL23,AU23,BC23,BK23,BT23,CB23,CJ23)-CR23 | DK23: =SUM(E23,K23,Q23,W23,AE23,AM23,AV23,BD23,BL23,BU23,CC23,CK23)-CS23 | DL23: =SUM(G23,M23,S23,AA23,AI23,AR23,AZ23,BH23,BQ23,BY23,CG23,CO23)-CW23 | DM23: =SUM(D23,J23,P23,V23,AD23,AL23,AU23,BC23,,BN23,BV23,CD23,CL23)-CT23 | DP23: #VALUE! | DQ23: =-CR23+DP23/10^6 | DR23: =SUM(E23,K23,Q23,W23,AE23,AM23,AV23,BD23,BL23,BU23,CC23,CK23)-CS23 | DS23: =SUM(D23,J23,P23,V23,AD23,AL23,AU23,BC23,,BN23,BV23,CD23,CL23)-CT23 | DU23: 13.826821 | DV23: =DU23-CJ23 | DX23: =(CS23-CZ23)*10^6 | DY23: =(CT23-DC23)*10^6 | DZ23: =(CW23-DD23)*10^6
B24: TRANSFERT DE CHARGES D'EXPLOITATION | C24: Opex18 | G24: 0 | M24: 0 | S24: 0 | AA24: 0 | AI24: 0 | CR24: =SUMIF($D$5:$CQ$5,CR$5,$D24:$CQ24) | CS24: =SUMIF($D$5:$CQ$5,CS$5,$D24:$CQ24) | CT24: =SUMIF($D$5:$CQ$5,CT$5,$D24:$CQ24)+SUMIF($D$5:$BI$5,CR$5,$D24:$BI24) | CU24: =+CR24-CS24 | CV24: =+CR24-CT24 | CW24: =SUMIF($D$5:$CQ$5,CW$5,$D24:$CQ24) | CX24: =IFERROR(CR24/CW24-1, "-") | CZ24: 0 | DA24: 0 | DD24: 0 | DJ24: =SUM(D24,J24,P24,V24,AD24,AL24,AU24,BC24,BK24,BT24,CB24,CJ24)-CR24 | DK24: =SUM(E24,K24,Q24,W24,AE24,AM24,AV24,BD24,BL24,BU24,CC24,CK24)-CS24 | DL24: =SUM(G24,M24,S24,AA24,AI24,AR24,AZ24,BH24,BQ24,BY24,CG24,CO24)-CW24 | DM24: =SUM(D24,J24,P24,V24,AD24,AL24,AU24,BC24,,BN24,BV24,CD24,CL24)-CT24 | DQ24: =-CR24+DP24/10^6 | DR24: =SUM(E24,K24,Q24,W24,AE24,AM24,AV24,BD24,BL24,BU24,CC24,CK24)-CS24 | DS24: =SUM(D24,J24,P24,V24,AD24,AL24,AU24,BC24,,BN24,BV24,CD24,CL24)-CT24 | DV24: =DU24-CJ24 | DX24: =(CS24-CZ24)*10^6 | DY24: =(CT24-DC24)*10^6 | DZ24: =(CW24-DD24)*10^6
B25: EAU RESIDENCES | C25: Opex19 | G25: 0 | M25: 0 | S25: 0 | AA25: 0 | AI25: 0 | CR25: =SUMIF($D$5:$CQ$5,CR$5,$D25:$CQ25) | CS25: =SUMIF($D$5:$CQ$5,CS$5,$D25:$CQ25) | CT25: =SUMIF($D$5:$CQ$5,CT$5,$D25:$CQ25)+SUMIF($D$5:$BI$5,CR$5,$D25:$BI25) | CU25: =+CR25-CS25 | CV25: =+CR25-CT25 | CW25: =SUMIF($D$5:$CQ$5,CW$5,$D25:$CQ25) | CX25: =IFERROR(CR25/CW25-1, "-") | CZ25: 0 | DA25: 0 | DD25: 0 | DJ25: =SUM(D25,J25,P25,V25,AD25,AL25,AU25,BC25,BK25,BT25,CB25,CJ25)-CR25 | DK25: =SUM(E25,K25,Q25,W25,AE25,AM25,AV25,BD25,BL25,BU25,CC25,CK25)-CS25 | DL25: =SUM(G25,M25,S25,AA25,AI25,AR25,AZ25,BH25,BQ25,BY25,CG25,CO25)-CW25 | DM25: =SUM(D25,J25,P25,V25,AD25,AL25,AU25,BC25,,BN25,BV25,CD25,CL25)-CT25 | DQ25: =-CR25+DP25/10^6 | DR25: =SUM(E25,K25,Q25,W25,AE25,AM25,AV25,BD25,BL25,BU25,CC25,CK25)-CS25 | DS25: =SUM(D25,J25,P25,V25,AD25,AL25,AU25,BC25,,BN25,BV25,CD25,CL25)-CT25 | DV25: =DU25-CJ25 | DX25: =(CS25-CZ25)*10^6 | DY25: =(CT25-DC25)*10^6 | DZ25: =(CW25-DD25)*10^6
B26: ELECTRICITE RESIDENCES | C26: Opex20 | G26: 0 | M26: 0 | S26: 0 | AA26: 0 | AI26: 0 | CR26: =SUMIF($D$5:$CQ$5,CR$5,$D26:$CQ26) | CS26: =SUMIF($D$5:$CQ$5,CS$5,$D26:$CQ26) | CT26: =SUMIF($D$5:$CQ$5,CT$5,$D26:$CQ26)+SUMIF($D$5:$BI$5,CR$5,$D26:$BI26) | CU26: =+CR26-CS26 | CV26: =+CR26-CT26 | CW26: =SUMIF($D$5:$CQ$5,CW$5,$D26:$CQ26) | CX26: =IFERROR(CR26/CW26-1, "-") | CZ26: 0 | DA26: 0 | DD26: 0 | DJ26: =SUM(D26,J26,P26,V26,AD26,AL26,AU26,BC26,BK26,BT26,CB26,CJ26)-CR26 | DK26: =SUM(E26,K26,Q26,W26,AE26,AM26,AV26,BD26,BL26,BU26,CC26,CK26)-CS26 | DL26: =SUM(G26,M26,S26,AA26,AI26,AR26,AZ26,BH26,BQ26,BY26,CG26,CO26)-CW26 | DM26: =SUM(D26,J26,P26,V26,AD26,AL26,AU26,BC26,,BN26,BV26,CD26,CL26)-CT26 | DQ26: =-CR26+DP26/10^6 | DR26: =SUM(E26,K26,Q26,W26,AE26,AM26,AV26,BD26,BL26,BU26,CC26,CK26)-CS26 | DS26: =SUM(D26,J26,P26,V26,AD26,AL26,AU26,BC26,,BN26,BV26,CD26,CL26)-CT26 | DV26: =DU26-CJ26 | DX26: =(CS26-CZ26)*10^6 | DY26: =(CT26-DC26)*10^6 | DZ26: =(CW26-DD26)*10^6
B27: LOYERS RESIDENCES | C27: Opex21 | G27: 0 | M27: 0 | S27: 0 | AA27: 0 | AI27: 0 | CR27: =SUMIF($D$5:$CQ$5,CR$5,$D27:$CQ27) | CS27: =SUMIF($D$5:$CQ$5,CS$5,$D27:$CQ27) | CT27: =SUMIF($D$5:$CQ$5,CT$5,$D27:$CQ27)+SUMIF($D$5:$BI$5,CR$5,$D27:$BI27) | CU27: =+CR27-CS27 | CV27: =+CR27-CT27 | CW27: =SUMIF($D$5:$CQ$5,CW$5,$D27:$CQ27) | CX27: =IFERROR(CR27/CW27-1, "-") | CZ27: 0 | DA27: 0 | DD27: 0 | DJ27: =SUM(D27,J27,P27,V27,AD27,AL27,AU27,BC27,BK27,BT27,CB27,CJ27)-CR27 | DK27: =SUM(E27,K27,Q27,W27,AE27,AM27,AV27,BD27,BL27,BU27,CC27,CK27)-CS27 | DL27: =SUM(G27,M27,S27,AA27,AI27,AR27,AZ27,BH27,BQ27,BY27,CG27,CO27)-CW27 | DM27: =SUM(D27,J27,P27,V27,AD27,AL27,AU27,BC27,,BN27,BV27,CD27,CL27)-CT27 | DQ27: =-CR27+DP27/10^6 | DR27: =SUM(E27,K27,Q27,W27,AE27,AM27,AV27,BD27,BL27,BU27,CC27,CK27)-CS27 | DS27: =SUM(D27,J27,P27,V27,AD27,AL27,AU27,BC27,,BN27,BV27,CD27,CL27)-CT27 | DV27: =DU27-CJ27 | DX27: =(CS27-CZ27)*10^6 | DY27: =(CT27-DC27)*10^6 | DZ27: =(CW27-DD27)*10^6
B28: ENTRETIEN ET REPARATIONS RESID | C28: Opex22 | G28: 0 | M28: 0 | S28: 0 | AA28: 0 | AI28: 0 | CR28: =SUMIF($D$5:$CQ$5,CR$5,$D28:$CQ28) | CS28: =SUMIF($D$5:$CQ$5,CS$5,$D28:$CQ28) | CT28: =SUMIF($D$5:$CQ$5,CT$5,$D28:$CQ28)+SUMIF($D$5:$BI$5,CR$5,$D28:$BI28) | CU28: =+CR28-CS28 | CV28: =+CR28-CT28 | CW28: =SUMIF($D$5:$CQ$5,CW$5,$D28:$CQ28) | CX28: =IFERROR(CR28/CW28-1, "-") | CZ28: 0 | DA28: 0 | DD28: 0 | DJ28: =SUM(D28,J28,P28,V28,AD28,AL28,AU28,BC28,BK28,BT28,CB28,CJ28)-CR28 | DK28: =SUM(E28,K28,Q28,W28,AE28,AM28,AV28,BD28,BL28,BU28,CC28,CK28)-CS28 | DL28: =SUM(G28,M28,S28,AA28,AI28,AR28,AZ28,BH28,BQ28,BY28,CG28,CO28)-CW28 | DM28: =SUM(D28,J28,P28,V28,AD28,AL28,AU28,BC28,,BN28,BV28,CD28,CL28)-CT28 | DQ28: =-CR28+DP28/10^6 | DR28: =SUM(E28,K28,Q28,W28,AE28,AM28,AV28,BD28,BL28,BU28,CC28,CK28)-CS28 | DS28: =SUM(D28,J28,P28,V28,AD28,AL28,AU28,BC28,,BN28,BV28,CD28,CL28)-CT28 | DV28: =DU28-CJ28 | DX28: =(CS28-CZ28)*10^6 | DY28: =(CT28-DC28)*10^6 | DZ28: =(CW28-DD28)*10^6
B29: FRAIS DE TELEPHONE RESIDENCES | C29: Opex23 | G29: 0 | M29: 0 | S29: 0 | AA29: 0 | AI29: 0 | CR29: =SUMIF($D$5:$CQ$5,CR$5,$D29:$CQ29) | CS29: =SUMIF($D$5:$CQ$5,CS$5,$D29:$CQ29) | CT29: =SUMIF($D$5:$CQ$5,CT$5,$D29:$CQ29)+SUMIF($D$5:$BI$5,CR$5,$D29:$BI29) | CU29: =+CR29-CS29 | CV29: =+CR29-CT29 | CW29: =SUMIF($D$5:$CQ$5,CW$5,$D29:$CQ29) | CX29: =IFERROR(CR29/CW29-1, "-") | CZ29: 0 | DA29: 0 | DD29: 0 | DJ29: =SUM(D29,J29,P29,V29,AD29,AL29,AU29,BC29,BK29,BT29,CB29,CJ29)-CR29 | DK29: =SUM(E29,K29,Q29,W29,AE29,AM29,AV29,BD29,BL29,BU29,CC29,CK29)-CS29 | DL29: =SUM(G29,M29,S29,AA29,AI29,AR29,AZ29,BH29,BQ29,BY29,CG29,CO29)-CW29 | DM29: =SUM(D29,J29,P29,V29,AD29,AL29,AU29,BC29,,BN29,BV29,CD29,CL29)-CT29 | DQ29: =-CR29+DP29/10^6 | DR29: =SUM(E29,K29,Q29,W29,AE29,AM29,AV29,BD29,BL29,BU29,CC29,CK29)-CS29 | DS29: =SUM(D29,J29,P29,V29,AD29,AL29,AU29,BC29,,BN29,BV29,CD29,CL29)-CT29 | DV29: =DU29-CJ29 | DX29: =(CS29-CZ29)*10^6 | DY29: =(CT29-DC29)*10^6 | DZ29: =(CW29-DD29)*10^6
B30: PRIMES ET GRATIFICATIONS PERSO | C30: Opex24 | G30: 0 | M30: 0 | S30: 0 | AA30: 0 | AI30: 0 | CR30: =SUMIF($D$5:$CQ$5,CR$5,$D30:$CQ30) | CS30: =SUMIF($D$5:$CQ$5,CS$5,$D30:$CQ30) | CT30: =SUMIF($D$5:$CQ$5,CT$5,$D30:$CQ30)+SUMIF($D$5:$BI$5,CR$5,$D30:$BI30) | CU30: =+CR30-CS30 | CV30: =+CR30-CT30 | CW30: =SUMIF($D$5:$CQ$5,CW$5,$D30:$CQ30) | CX30: =IFERROR(CR30/CW30-1, "-") | CZ30: 0 | DA30: 0 | DD30: 0 | DJ30: =SUM(D30,J30,P30,V30,AD30,AL30,AU30,BC30,BK30,BT30,CB30,CJ30)-CR30 | DK30: =SUM(E30,K30,Q30,W30,AE30,AM30,AV30,BD30,BL30,BU30,CC30,CK30)-CS30 | DL30: =SUM(G30,M30,S30,AA30,AI30,AR30,AZ30,BH30,BQ30,BY30,CG30,CO30)-CW30 | DM30: =SUM(D30,J30,P30,V30,AD30,AL30,AU30,BC30,,BN30,BV30,CD30,CL30)-CT30 | DP30: 0 | DQ30: =-CR30+DP30/10^6 | DR30: =SUM(E30,K30,Q30,W30,AE30,AM30,AV30,BD30,BL30,BU30,CC30,CK30)-CS30 | DS30: =SUM(D30,J30,P30,V30,AD30,AL30,AU30,BC30,,BN30,BV30,CD30,CL30)-CT30 | DV30: =DU30-CJ30 | DX30: =(CS30-CZ30)*10^6 | DY30: =(CT30-DC30)*10^6 | DZ30: =(CW30-DD30)*10^6
B31: INDEMNITES DE LICENCIEMENT PER | C31: Opex25 | G31: 0 | M31: 0 | S31: 0 | AA31: 0 | AI31: 0 | CR31: =SUMIF($D$5:$CQ$5,CR$5,$D31:$CQ31) | CS31: =SUMIF($D$5:$CQ$5,CS$5,$D31:$CQ31) | CT31: =SUMIF($D$5:$CQ$5,CT$5,$D31:$CQ31)+SUMIF($D$5:$BI$5,CR$5,$D31:$BI31) | CU31: =+CR31-CS31 | CV31: =+CR31-CT31 | CW31: =SUMIF($D$5:$CQ$5,CW$5,$D31:$CQ31) | CX31: =IFERROR(CR31/CW31-1, "-") | CZ31: 0 | DA31: 0 | DD31: 0 | DJ31: =SUM(D31,J31,P31,V31,AD31,AL31,AU31,BC31,BK31,BT31,CB31,CJ31)-CR31 | DK31: =SUM(E31,K31,Q31,W31,AE31,AM31,AV31,BD31,BL31,BU31,CC31,CK31)-CS31 | DL31: =SUM(G31,M31,S31,AA31,AI31,AR31,AZ31,BH31,BQ31,BY31,CG31,CO31)-CW31 | DM31: =SUM(D31,J31,P31,V31,AD31,AL31,AU31,BC31,,BN31,BV31,CD31,CL31)-CT31 | DQ31: =-CR31+DP31/10^6 | DR31: =SUM(E31,K31,Q31,W31,AE31,AM31,AV31,BD31,BL31,BU31,CC31,CK31)-CS31 | DS31: =SUM(D31,J31,P31,V31,AD31,AL31,AU31,BC31,,BN31,BV31,CD31,CL31)-CT31 | DV31: =DU31-CJ31 | DX31: =(CS31-CZ31)*10^6 | DY31: =(CT31-DC31)*10^6 | DZ31: =(CW31-DD31)*10^6
B32: AVANTAGES EN NATURE PERSONNEL | C32: Opex26 | G32: 0 | M32: 0 | S32: 0 | AA32: 0 | AI32: 0 | CR32: =SUMIF($D$5:$CQ$5,CR$5,$D32:$CQ32) | CS32: =SUMIF($D$5:$CQ$5,CS$5,$D32:$CQ32) | CT32: =SUMIF($D$5:$CQ$5,CT$5,$D32:$CQ32)+SUMIF($D$5:$BI$5,CR$5,$D32:$BI32) | CU32: =+CR32-CS32 | CV32: =+CR32-CT32 | CW32: =SUMIF($D$5:$CQ$5,CW$5,$D32:$CQ32) | CX32: =IFERROR(CR32/CW32-1, "-") | CZ32: 0 | DA32: 0 | DD32: 0 | DJ32: =SUM(D32,J32,P32,V32,AD32,AL32,AU32,BC32,BK32,BT32,CB32,CJ32)-CR32 | DK32: =SUM(E32,K32,Q32,W32,AE32,AM32,AV32,BD32,BL32,BU32,CC32,CK32)-CS32 | DL32: =SUM(G32,M32,S32,AA32,AI32,AR32,AZ32,BH32,BQ32,BY32,CG32,CO32)-CW32 | DM32: =SUM(D32,J32,P32,V32,AD32,AL32,AU32,BC32,,BN32,BV32,CD32,CL32)-CT32 | DQ32: =-CR32+DP32/10^6 | DR32: =SUM(E32,K32,Q32,W32,AE32,AM32,AV32,BD32,BL32,BU32,CC32,CK32)-CS32 | DS32: =SUM(D32,J32,P32,V32,AD32,AL32,AU32,BC32,,BN32,BV32,CD32,CL32)-CT32 | DV32: =DU32-CJ32 | DX32: =(CS32-CZ32)*10^6 | DY32: =(CT32-DC32)*10^6 | DZ32: =(CW32-DD32)*10^6
B33: AUTRES INDEMNITES ET AVANTAGES | C33: Opex27 | G33: 0 | M33: 0 | S33: 0 | AA33: 0 | AI33: 0 | AL33: 0 | CR33: =SUMIF($D$5:$CQ$5,CR$5,$D33:$CQ33) | CS33: =SUMIF($D$5:$CQ$5,CS$5,$D33:$CQ33) | CT33: =SUMIF($D$5:$CQ$5,CT$5,$D33:$CQ33)+SUMIF($D$5:$BI$5,CR$5,$D33:$BI33) | CU33: =+CR33-CS33 | CV33: =+CR33-CT33 | CW33: =SUMIF($D$5:$CQ$5,CW$5,$D33:$CQ33) | CX33: =IFERROR(CR33/CW33-1, "-") | CZ33: 0 | DA33: 0 | DD33: 0 | DJ33: =SUM(D33,J33,P33,V33,AD33,AL33,AU33,BC33,BK33,BT33,CB33,CJ33)-CR33 | DK33: =SUM(E33,K33,Q33,W33,AE33,AM33,AV33,BD33,BL33,BU33,CC33,CK33)-CS33 | DL33: =SUM(G33,M33,S33,AA33,AI33,AR33,AZ33,BH33,BQ33,BY33,CG33,CO33)-CW33 | DM33: =SUM(D33,J33,P33,V33,AD33,AL33,AU33,BC33,,BN33,BV33,CD33,CL33)-CT33 | DQ33: =-CR33+DP33/10^6 | DR33: =SUM(E33,K33,Q33,W33,AE33,AM33,AV33,BD33,BL33,BU33,CC33,CK33)-CS33 | DS33: =SUM(D33,J33,P33,V33,AD33,AL33,AU33,BC33,,BN33,BV33,CD33,CL33)-CT33 | DV33: =DU33-CJ33 | DX33: =(CS33-CZ33)*10^6 | DY33: =(CT33-DC33)*10^6 | DZ33: =(CW33-DD33)*10^6
B34: FRAIS DE FORMATION DU PERSONNE | C34: Opex28 | G34: 0 | M34: 0 | S34: 0 | AA34: 0 | AI34: 0 | CR34: =SUMIF($D$5:$CQ$5,CR$5,$D34:$CQ34) | CS34: =SUMIF($D$5:$CQ$5,CS$5,$D34:$CQ34) | CT34: =SUMIF($D$5:$CQ$5,CT$5,$D34:$CQ34)+SUMIF($D$5:$BI$5,CR$5,$D34:$BI34) | CU34: =+CR34-CS34 | CV34: =+CR34-CT34 | CW34: =SUMIF($D$5:$CQ$5,CW$5,$D34:$CQ34) | CX34: =IFERROR(CR34/CW34-1, "-") | CZ34: 0 | DA34: 0 | DD34: 0 | DJ34: =SUM(D34,J34,P34,V34,AD34,AL34,AU34,BC34,BK34,BT34,CB34,CJ34)-CR34 | DK34: =SUM(E34,K34,Q34,W34,AE34,AM34,AV34,BD34,BL34,BU34,CC34,CK34)-CS34 | DL34: =SUM(G34,M34,S34,AA34,AI34,AR34,AZ34,BH34,BQ34,BY34,CG34,CO34)-CW34 | DM34: =SUM(D34,J34,P34,V34,AD34,AL34,AU34,BC34,,BN34,BV34,CD34,CL34)-CT34 | DQ34: =-CR34+DP34/10^6 | DR34: =SUM(E34,K34,Q34,W34,AE34,AM34,AV34,BD34,BL34,BU34,CC34,CK34)-CS34 | DS34: =SUM(D34,J34,P34,V34,AD34,AL34,AU34,BC34,,BN34,BV34,CD34,CL34)-CT34 | DV34: =DU34-CJ34 | DX34: =(CS34-CZ34)*10^6 | DY34: =(CT34-DC34)*10^6 | DZ34: =(CW34-DD34)*10^6
B35: TRANSPORT PERSONNEL | C35: Opex29 | G35: 0 | M35: 0 | S35: 0 | AA35: 0 | AI35: 0 | CR35: =SUMIF($D$5:$CQ$5,CR$5,$D35:$CQ35) | CS35: =SUMIF($D$5:$CQ$5,CS$5,$D35:$CQ35) | CT35: =SUMIF($D$5:$CQ$5,CT$5,$D35:$CQ35)+SUMIF($D$5:$BI$5,CR$5,$D35:$BI35) | CU35: =+CR35-CS35 | CV35: =+CR35-CT35 | CW35: =SUMIF($D$5:$CQ$5,CW$5,$D35:$CQ35) | CX35: =IFERROR(CR35/CW35-1, "-") | CZ35: 0 | DA35: 0 | DD35: 0 | DJ35: =SUM(D35,J35,P35,V35,AD35,AL35,AU35,BC35,BK35,BT35,CB35,CJ35)-CR35 | DK35: =SUM(E35,K35,Q35,W35,AE35,AM35,AV35,BD35,BL35,BU35,CC35,CK35)-CS35 | DL35: =SUM(G35,M35,S35,AA35,AI35,AR35,AZ35,BH35,BQ35,BY35,CG35,CO35)-CW35 | DM35: =SUM(D35,J35,P35,V35,AD35,AL35,AU35,BC35,,BN35,BV35,CD35,CL35)-CT35 | DQ35: =-CR35+DP35/10^6 | DR35: =SUM(E35,K35,Q35,W35,AE35,AM35,AV35,BD35,BL35,BU35,CC35,CK35)-CS35 | DS35: =SUM(D35,J35,P35,V35,AD35,AL35,AU35,BC35,,BN35,BV35,CD35,CL35)-CT35 | DV35: =DU35-CJ35 | DX35: =(CS35-CZ35)*10^6 | DY35: =(CT35-DC35)*10^6 | DZ35: =(CW35-DD35)*10^6
B36: RECEPTIONS PERSONNEL | C36: Opex30 | G36: 0 | M36: 0 | S36: 0 | AA36: 0 | AI36: 0 | CR36: =SUMIF($D$5:$CQ$5,CR$5,$D36:$CQ36) | CS36: =SUMIF($D$5:$CQ$5,CS$5,$D36:$CQ36) | CT36: =SUMIF($D$5:$CQ$5,CT$5,$D36:$CQ36)+SUMIF($D$5:$BI$5,CR$5,$D36:$BI36) | CU36: =+CR36-CS36 | CV36: =+CR36-CT36 | CW36: =SUMIF($D$5:$CQ$5,CW$5,$D36:$CQ36) | CX36: =IFERROR(CR36/CW36-1, "-") | CZ36: 0 | DA36: 0 | DD36: 0 | DJ36: =SUM(D36,J36,P36,V36,AD36,AL36,AU36,BC36,BK36,BT36,CB36,CJ36)-CR36 | DK36: =SUM(E36,K36,Q36,W36,AE36,AM36,AV36,BD36,BL36,BU36,CC36,CK36)-CS36 | DL36: =SUM(G36,M36,S36,AA36,AI36,AR36,AZ36,BH36,BQ36,BY36,CG36,CO36)-CW36 | DM36: =SUM(D36,J36,P36,V36,AD36,AL36,AU36,BC36,,BN36,BV36,CD36,CL36)-CT36 | DQ36: =-CR36+DP36/10^6 | DR36: =SUM(E36,K36,Q36,W36,AE36,AM36,AV36,BD36,BL36,BU36,CC36,CK36)-CS36 | DS36: =SUM(D36,J36,P36,V36,AD36,AL36,AU36,BC36,,BN36,BV36,CD36,CL36)-CT36 | DV36: =DU36-CJ36 | DX36: =(CS36-CZ36)*10^6 | DY36: =(CT36-DC36)*10^6 | DZ36: =(CW36-DD36)*10^6
B37: ASSURANCE DU PERSONNEL | C37: Opex31 | D37: 11.278049 | E37: 18.06304 | G37: 13.096269 | J37: 15.028051 | K37: 18.06304 | M37: 12.142748 | P37: 15.050325 | Q37: 18.06304 | S37: 12.559337 | V37: 14.991809 | W37: 18.06304 | X37: 18.06304 | AA37: 12.559339 | AD37: 15.035475 | AE37: 18.06304 | AF37: 18.06304 | AI37: 12.781421 | AL37: 15.035474 | AM37: 18.06304 | CR37: =SUMIF($D$5:$CQ$5,CR$5,$D37:$CQ37) | CS37: =SUMIF($D$5:$CQ$5,CS$5,$D37:$CQ37) | CT37: =SUMIF($D$5:$CQ$5,CT$5,$D37:$CQ37)+SUMIF($D$5:$BI$5,CR$5,$D37:$BI37) | CU37: =+CR37-CS37 | CV37: =+CR37-CT37 | CW37: =SUMIF($D$5:$CQ$5,CW$5,$D37:$CQ37) | CX37: =IFERROR(CR37/CW37-1, "-") | CZ37: 216.75648 | DA37: 203.92379 | DD37: 197.24053 | DE37: =+CZ37/DD37-1 | DF37: =+DA37/DD37-1 | DG37: =+DB37/DD37-1 | DH37: =+DC37/DD37-1 | DJ37: =SUM(D37,J37,P37,V37,AD37,AL37,AU37,BC37,BK37,BT37,CB37,CJ37)-CR37 | DK37: =SUM(E37,K37,Q37,W37,AE37,AM37,AV37,BD37,BL37,BU37,CC37,CK37)-CS37 | DL37: =SUM(G37,M37,S37,AA37,AI37,AR37,AZ37,BH37,BQ37,BY37,CG37,CO37)-CW37 | DM37: =SUM(D37,J37,P37,V37,AD37,AL37,AU37,BC37,,BN37,BV37,CD37,CL37)-CT37 | DP37: #VALUE! | DQ37: =-CR37+DP37/10^6 | DR37: =SUM(E37,K37,Q37,W37,AE37,AM37,AV37,BD37,BL37,BU37,CC37,CK37)-CS37 | DS37: =SUM(D37,J37,P37,V37,AD37,AL37,AU37,BC37,,BN37,BV37,CD37,CL37)-CT37 | DU37: 20.407007 | DV37: =DU37-CJ37 | DX37: =(CS37-CZ37)*10^6 | DY37: =(CT37-DC37)*10^6 | DZ37: =(CW37-DD37)*10^6
B38: Réduction budget | C38: Opex32 | G38: 0 | M38: 0 | S38: 0 | AA38: 0 | AI38: 0 | CR38: =SUMIF($D$5:$CQ$5,CR$5,$D38:$CQ38) | CS38: =SUMIF($D$5:$CQ$5,CS$5,$D38:$CQ38) | CT38: =SUMIF($D$5:$CQ$5,CT$5,$D38:$CQ38)+SUMIF($D$5:$BI$5,CR$5,$D38:$BI38) | CU38: =+CR38-CS38 | CV38: =+CR38-CT38 | CW38: =SUMIF($D$5:$CQ$5,CW$5,$D38:$CQ38) | CX38: =IFERROR(CR38/CW38-1, "-") | CZ38: 0 | DA38: 0 | DD38: 0 | DJ38: =SUM(D38,J38,P38,V38,AD38,AL38,AU38,BC38,BK38,BT38,CB38,CJ38)-CR38 | DK38: =SUM(E38,K38,Q38,W38,AE38,AM38,AV38,BD38,BL38,BU38,CC38,CK38)-CS38 | DL38: =SUM(G38,M38,S38,AA38,AI38,AR38,AZ38,BH38,BQ38,BY38,CG38,CO38)-CW38 | DM38: =SUM(D38,J38,P38,V38,AD38,AL38,AU38,BC38,,BN38,BV38,CD38,CL38)-CT38 | DQ38: =-CR38+DP38/10^6 | DR38: =SUM(E38,K38,Q38,W38,AE38,AM38,AV38,BD38,BL38,BU38,CC38,CK38)-CS38 | DS38: =SUM(D38,J38,P38,V38,AD38,AL38,AU38,BC38,,BN38,BV38,CD38,CL38)-CT38 | DV38: =DU38-CJ38 | DX38: =(CS38-CZ38)*10^6 | DY38: =(CT38-DC38)*10^6 | DZ38: =(CW38-DD38)*10^6
C39: Opex33 | CT39: =SUMIF($D$5:$CQ$5,CT$5,$D39:$CQ39)+SUMIF($D$5:$BI$5,CR$5,$D39:$BI39) | CX39: =IFERROR(CR39/CW39-1, "-") | DJ39: =SUM(D39,J39,P39,V39,AD39,AL39,AU39,BC39,BK39,BT39,CB39,CJ39)-CR39 | DK39: =SUM(E39,K39,Q39,W39,AE39,AM39,AV39,BD39,BL39,BU39,CC39,CK39)-CS39 | DL39: =SUM(G39,M39,S39,AA39,AI39,AR39,AZ39,BH39,BQ39,BY39,CG39,CO39)-CW39 | DM39: =SUM(D39,J39,P39,V39,AD39,AL39,AU39,BC39,,BN39,BV39,CD39,CL39)-CT39 | DQ39: =-CR39+DP39/10^6 | DR39: =SUM(E39,K39,Q39,W39,AE39,AM39,AV39,BD39,BL39,BU39,CC39,CK39)-CS39 | DS39: =SUM(D39,J39,P39,V39,AD39,AL39,AU39,BC39,,BN39,BV39,CD39,CL39)-CT39 | DV39: =DU39-CJ39 | DX39: =(CS39-CZ39)*10^6 | DY39: =(CT39-DC39)*10^6 | DZ39: =(CW39-DD39)*10^6
B40: Communication | C40: Opex34 | D40: 207.44366 | E40: 284.29255 | F40: -76.848886 | G40: 298.65881 | H40: -0.30541588 | J40: 156.33087 | K40: 281.99255 | L40: -125.66168 | M40: 261.89455 | N40: -0.40307706 | P40: 171.04848 | Q40: 281.99255 | R40: -110.94407 | S40: 205.24888 | T40: -0.16662893 | V40: 262.74882 | W40: 289.29255 | X40: 289.43404 | Y40: -26.543733 | Z40: -26.685223 | AA40: 340.74725 | AB40: -0.22890407 | AD40: 311.27311 | AE40: 281.99255 | AF40: 225.59404 | AG40: 29.280558 | AH40: 85.679068 | AI40: 286.62081 | AJ40: 0.086010143 | AL40: 325.53625 | AM40: 281.99255 | AN40: 0 | AO40: 0 | AP40: 43.5437 | AQ40: 325.53625 | AR40: 489.18241 | AS40: -0.33452994 | CR40: =SUMIF($D$5:$CQ$5,CR$5,$D40:$CQ40) | CS40: =SUMIF($D$5:$CQ$5,CS$5,$D40:$CQ40) | CT40: =SUMIF($D$5:$CQ$5,CT$5,$D40:$CQ40)+SUMIF($D$5:$BI$5,CR$5,$D40:$BI40) | CU40: =+CR40-CS40 | CV40: =+CR40-CT40 | CW40: =SUMIF($D$5:$CQ$5,CW$5,$D40:$CQ40) | CX40: =IFERROR(CR40/CW40-1, "-") | CZ40: 3445.1106 | DD40: 3399.8252 | DE40: =+CZ40/DD40-1 | DF40: =+DA40/DD40-1 | DG40: =+DB40/DD40-1 | DH40: =+DC40/DD40-1 | DJ40: =SUM(D40,J40,P40,V40,AD40,AL40,AU40,BC40,BK40,BT40,CB40,CJ40)-CR40 | DK40: =SUM(E40,K40,Q40,W40,AE40,AM40,AV40,BD40,BL40,BU40,CC40,CK40)-CS40 | DL40: =SUM(G40,M40,S40,AA40,AI40,AR40,AZ40,BH40,BQ40,BY40,CG40,CO40)-CW40 | DM40: =SUM(D40,J40,P40,V40,AD40,AL40,AU40,BC40,,BN40,BV40,CD40,CL40)-CT40 | DP40: =SUM(DP41:DP55) | DQ40: =-CR40+DP40/10^6 | DR40: =SUM(E40,K40,Q40,W40,AE40,AM40,AV40,BD40,BL40,BU40,CC40,CK40)-CS40 | DS40: =SUM(D40,J40,P40,V40,AD40,AL40,AU40,BC40,,BN40,BV40,CD40,CL40)-CT40 | DU40: 338.23657 | DV40: =DU40-CJ40 | DX40: =(CS40-CZ40)*10^6 | DY40: =(CT40-DC40)*10^6 | DZ40: =(CW40-DD40)*10^6
B41: VARIATION DE STOCKS AUTRES APPRO | C41: Opex35 | D41: -21.606391 | G41: 13.705822 | J41: 3.432117 | M41: 14.594004 | P41: 10.346972 | S41: 24.290029 | V41: -276.29809 | AA41: -23.393705 | AD41: 29.814507 | AI41: 3.447318 | AL41: 11.67075 | CR41: =SUMIF($D$5:$CQ$5,CR$5,$D41:$CQ41) | CS41: =SUMIF($D$5:$CQ$5,CS$5,$D41:$CQ41) | CT41: =SUMIF($D$5:$CQ$5,CT$5,$D41:$CQ41)+SUMIF($D$5:$BI$5,CR$5,$D41:$BI41) | CU41: =+CR41-CS41 | CV41: =+CR41-CT41 | CW41: =SUMIF($D$5:$CQ$5,CW$5,$D41:$CQ41) | CX41: =IFERROR(CR41/CW41-1, "-") | CZ41: 0 | DA41: -7.827302 | DD41: -67.770805 | DJ41: =SUM(D41,J41,P41,V41,AD41,AL41,AU41,BC41,BK41,BT41,CB41,CJ41)-CR41 | DK41: =SUM(E41,K41,Q41,W41,AE41,AM41,AV41,BD41,BL41,BU41,CC41,CK41)-CS41 | DL41: =SUM(G41,M41,S41,AA41,AI41,AR41,AZ41,BH41,BQ41,BY41,CG41,CO41)-CW41 | DM41: =SUM(D41,J41,P41,V41,AD41,AL41,AU41,BC41,,BN41,BV41,CD41,CL41)-CT41 | DP41: -82699732 | DQ41: =-CR41+DP41/10^6 | DR41: =SUM(E41,K41,Q41,W41,AE41,AM41,AV41,BD41,BL41,BU41,CC41,CK41)-CS41 | DS41: =SUM(D41,J41,P41,V41,AD41,AL41,AU41,BC41,,BN41,BV41,CD41,CL41)-CT41 | DU41: 14.928927 | DV41: =DU41-CJ41 | DX41: =(CS41-CZ41)*10^6 | DY41: =(CT41-DC41)*10^6 | DZ41: =(CW41-DD41)*10^6
B42: ANNONCES, INSERTIONS TELE | C42: Opex36 | D42: 2.064386 | G42: -3.526452 | J42: 2.064387 | M42: 3.265321 | P42: 2.064387 | S42: 2.635321 | V42: 2.064387 | AA42: 2.955321 | AD42: 2.064386 | AI42: 2.990321 | AL42: 7.780505 | CR42: =SUMIF($D$5:$CQ$5,CR$5,$D42:$CQ42) | CS42: =SUMIF($D$5:$CQ$5,CS$5,$D42:$CQ42) | CT42: =SUMIF($D$5:$CQ$5,CT$5,$D42:$CQ42)+SUMIF($D$5:$BI$5,CR$5,$D42:$BI42) | CU42: =+CR42-CS42 | CV42: =+CR42-CT42 | CW42: =SUMIF($D$5:$CQ$5,CW$5,$D42:$CQ42) | CX42: =IFERROR(CR42/CW42-1, "-") | CZ42: 0 | DA42: 6.19316 | DD42: 33.480539 | DJ42: =SUM(D42,J42,P42,V42,AD42,AL42,AU42,BC42,BK42,BT42,CB42,CJ42)-CR42 | DK42: =SUM(E42,K42,Q42,W42,AE42,AM42,AV42,BD42,BL42,BU42,CC42,CK42)-CS42 | DL42: =SUM(G42,M42,S42,AA42,AI42,AR42,AZ42,BH42,BQ42,BY42,CG42,CO42)-CW42 | DM42: =SUM(D42,J42,P42,V42,AD42,AL42,AU42,BC42,,BN42,BV42,CD42,CL42)-CT42 | DP42: 21416152 | DQ42: =-CR42+DP42/10^6 | DR42: =SUM(E42,K42,Q42,W42,AE42,AM42,AV42,BD42,BL42,BU42,CC42,CK42)-CS42 | DS42: =SUM(D42,J42,P42,V42,AD42,AL42,AU42,BC42,,BN42,BV42,CD42,CL42)-CT42 | DU42: 12.064387 | DV42: =DU42-CJ42 | DX42: =(CS42-CZ42)*10^6 | DY42: =(CT42-DC42)*10^6 | DZ42: =(CW42-DD42)*10^6
B43: ANNONCES, INSERTIONS RADIO | C43: Opex37 | D43: 2.638442 | G43: 7.317301 | J43: 2.638441 | M43: 4.693368 | P43: 2.638442 | S43: 4.693368 | V43: 2.638442 | AA43: 4.693367 | AD43: 2.638442 | AI43: 4.693368 | AL43: 6.534988 | CR43: =SUMIF($D$5:$CQ$5,CR$5,$D43:$CQ43) | CS43: =SUMIF($D$5:$CQ$5,CS$5,$D43:$CQ43) | CT43: =SUMIF($D$5:$CQ$5,CT$5,$D43:$CQ43)+SUMIF($D$5:$BI$5,CR$5,$D43:$BI43) | CU43: =+CR43-CS43 | CV43: =+CR43-CT43 | CW43: =SUMIF($D$5:$CQ$5,CW$5,$D43:$CQ43) | CX43: =IFERROR(CR43/CW43-1, "-") | CZ43: 0 | DA43: 7.915325 | DD43: 44.714864 | DJ43: =SUM(D43,J43,P43,V43,AD43,AL43,AU43,BC43,BK43,BT43,CB43,CJ43)-CR43 | DK43: =SUM(E43,K43,Q43,W43,AE43,AM43,AV43,BD43,BL43,BU43,CC43,CK43)-CS43 | DL43: =SUM(G43,M43,S43,AA43,AI43,AR43,AZ43,BH43,BQ43,BY43,CG43,CO43)-CW43 | DM43: =SUM(D43,J43,P43,V43,AD43,AL43,AU43,BC43,,BN43,BV43,CD43,CL43)-CT43 | DP43: 42076422 | DQ43: =-CR43+DP43/10^6 | DR43: =SUM(E43,K43,Q43,W43,AE43,AM43,AV43,BD43,BL43,BU43,CC43,CK43)-CS43 | DS43: =SUM(D43,J43,P43,V43,AD43,AL43,AU43,BC43,,BN43,BV43,CD43,CL43)-CT43 | DU43: 2.638442 | DV43: =DU43-CJ43 | DX43: =(CS43-CZ43)*10^6 | DY43: =(CT43-DC43)*10^6 | DZ43: =(CW43-DD43)*10^6
B44: ANNONCES, INSERTIONS PRESSE | C44: Opex38 | D44: 1.785759 | G44: 14.269218 | J44: 1.785758 | M44: 5.13969 | P44: 1.785759 | S44: -26.29031 | V44: 1.785758 | AA44: 4.57469 | AD44: 1.785759 | AI44: 14.32969 | AL44: 5.018994 | CR44: =SUMIF($D$5:$CQ$5,CR$5,$D44:$CQ44) | CS44: =SUMIF($D$5:$CQ$5,CS$5,$D44:$CQ44) | CT44: =SUMIF($D$5:$CQ$5,CT$5,$D44:$CQ44)+SUMIF($D$5:$BI$5,CR$5,$D44:$BI44) | CU44: =+CR44-CS44 | CV44: =+CR44-CT44 | CW44: =SUMIF($D$5:$CQ$5,CW$5,$D44:$CQ44) | CX44: =IFERROR(CR44/CW44-1, "-") | CZ44: 0 | DA44: 5.357276 | DD44: 34.733286 | DJ44: =SUM(D44,J44,P44,V44,AD44,AL44,AU44,BC44,BK44,BT44,CB44,CJ44)-CR44 | DK44: =SUM(E44,K44,Q44,W44,AE44,AM44,AV44,BD44,BL44,BU44,CC44,CK44)-CS44 | DL44: =SUM(G44,M44,S44,AA44,AI44,AR44,AZ44,BH44,BQ44,BY44,CG44,CO44)-CW44 | DM44: =SUM(D44,J44,P44,V44,AD44,AL44,AU44,BC44,,BN44,BV44,CD44,CL44)-CT44 | DP44: 27947528 | DQ44: =-CR44+DP44/10^6 | DR44: =SUM(E44,K44,Q44,W44,AE44,AM44,AV44,BD44,BL44,BU44,CC44,CK44)-CS44 | DS44: =SUM(D44,J44,P44,V44,AD44,AL44,AU44,BC44,,BN44,BV44,CD44,CL44)-CT44 | DU44: 6.785758 | DV44: =DU44-CJ44 | DX44: =(CS44-CZ44)*10^6 | DY44: =(CT44-DC44)*10^6 | DZ44: =(CW44-DD44)*10^6
B45: FRAIS D'AGENCES PUBLICITAIRES | C45: Opex39 | D45: 132.52911 | G45: 122.27814 | J45: 64.794418 | M45: 103.37866 | P45: 75.126544 | S45: 110.04067 | V45: 132.97799 | AA45: 150.90159 | AD45: 176.64114 | AI45: 84.020526 | AL45: 188.40204 | CR45: =SUMIF($D$5:$CQ$5,CR$5,$D45:$CQ45) | CS45: =SUMIF($D$5:$CQ$5,CS$5,$D45:$CQ45) | CT45: =SUMIF($D$5:$CQ$5,CT$5,$D45:$CQ45)+SUMIF($D$5:$BI$5,CR$5,$D45:$BI45) | CU45: =+CR45-CS45 | CV45: =+CR45-CT45 | CW45: =SUMIF($D$5:$CQ$5,CW$5,$D45:$CQ45) | CX45: =IFERROR(CR45/CW45-1, "-") | CZ45: 0 | DA45: 272.45007 | DD45: 1759.8838 | DJ45: =SUM(D45,J45,P45,V45,AD45,AL45,AU45,BC45,BK45,BT45,CB45,CJ45)-CR45 | DK45: =SUM(E45,K45,Q45,W45,AE45,AM45,AV45,BD45,BL45,BU45,CC45,CK45)-CS45 | DL45: =SUM(G45,M45,S45,AA45,AI45,AR45,AZ45,BH45,BQ45,BY45,CG45,CO45)-CW45 | DM45: =SUM(D45,J45,P45,V45,AD45,AL45,AU45,BC45,,BN45,BV45,CD45,CL45)-CT45 | DP45: #VALUE! | DQ45: =-CR45+DP45/10^6 | DR45: =SUM(E45,K45,Q45,W45,AE45,AM45,AV45,BD45,BL45,BU45,CC45,CK45)-CS45 | DS45: =SUM(D45,J45,P45,V45,AD45,AL45,AU45,BC45,,BN45,BV45,CD45,CL45)-CT45 | DU45: 188.133 | DV45: =DU45-CJ45 | DX45: =(CS45-CZ45)*10^6 | DY45: =(CT45-DC45)*10^6 | DZ45: =(CW45-DD45)*10^6
B46: CONCEPTIONS, PRODUCTION PUBLIC | C46: Opex40 | D46: 0 | G46: 0 | J46: 0 | M46: 0 | P46: 0 | S46: 0 | V46: 0 | AA46: 0 | AD46: 0 | AI46: 0 | AL46: 0 | CR46: =SUMIF($D$5:$CQ$5,CR$5,$D46:$CQ46) | CS46: =SUMIF($D$5:$CQ$5,CS$5,$D46:$CQ46) | CT46: =SUMIF($D$5:$CQ$5,CT$5,$D46:$CQ46)+SUMIF($D$5:$BI$5,CR$5,$D46:$BI46) | CU46: =+CR46-CS46 | CV46: =+CR46-CT46 | CW46: =SUMIF($D$5:$CQ$5,CW$5,$D46:$CQ46) | CX46: =IFERROR(CR46/CW46-1, "-") | CZ46: 0 | DA46: 0 | DD46: 0 | DJ46: =SUM(D46,J46,P46,V46,AD46,AL46,AU46,BC46,BK46,BT46,CB46,CJ46)-CR46 | DK46: =SUM(E46,K46,Q46,W46,AE46,AM46,AV46,BD46,BL46,BU46,CC46,CK46)-CS46 | DL46: =SUM(G46,M46,S46,AA46,AI46,AR46,AZ46,BH46,BQ46,BY46,CG46,CO46)-CW46 | DM46: =SUM(D46,J46,P46,V46,AD46,AL46,AU46,BC46,,BN46,BV46,CD46,CL46)-CT46 | DP46: 0 | DQ46: =-CR46+DP46/10^6 | DR46: =SUM(E46,K46,Q46,W46,AE46,AM46,AV46,BD46,BL46,BU46,CC46,CK46)-CS46 | DS46: =SUM(D46,J46,P46,V46,AD46,AL46,AU46,BC46,,BN46,BV46,CD46,CL46)-CT46 | DU46: 0 | DV46: =DU46-CJ46 | DX46: =(CS46-CZ46)*10^6 | DY46: =(CT46-DC46)*10^6 | DZ46: =(CW46-DD46)*10^6
B47: CATALOGUES, IMPRIMES PUBLICITA | C47: Opex41 | D47: 31.144505 | G47: 26.068321 | J47: 0.674072 | M47: 10.659468 | P47: 4.844413 | S47: -32.632042 | V47: 297.1029 | AA47: 86.694565 | AD47: 4.239739 | AI47: 8.230623 | AL47: 12.837625 | CR47: =SUMIF($D$5:$CQ$5,CR$5,$D47:$CQ47) | CS47: =SUMIF($D$5:$CQ$5,CS$5,$D47:$CQ47) | CT47: =SUMIF($D$5:$CQ$5,CT$5,$D47:$CQ47)+SUMIF($D$5:$BI$5,CR$5,$D47:$BI47) | CU47: =+CR47-CS47 | CV47: =+CR47-CT47 | CW47: =SUMIF($D$5:$CQ$5,CW$5,$D47:$CQ47) | CX47: =IFERROR(CR47/CW47-1, "-") | CZ47: 0 | DA47: 36.66299 | DD47: 290.24024 | DJ47: =SUM(D47,J47,P47,V47,AD47,AL47,AU47,BC47,BK47,BT47,CB47,CJ47)-CR47 | DK47: =SUM(E47,K47,Q47,W47,AE47,AM47,AV47,BD47,BL47,BU47,CC47,CK47)-CS47 | DL47: =SUM(G47,M47,S47,AA47,AI47,AR47,AZ47,BH47,BQ47,BY47,CG47,CO47)-CW47 | DM47: =SUM(D47,J47,P47,V47,AD47,AL47,AU47,BC47,,BN47,BV47,CD47,CL47)-CT47 | DP47: 277712779 | DQ47: =-CR47+DP47/10^6 | DR47: =SUM(E47,K47,Q47,W47,AE47,AM47,AV47,BD47,BL47,BU47,CC47,CK47)-CS47 | DS47: =SUM(D47,J47,P47,V47,AD47,AL47,AU47,BC47,,BN47,BV47,CD47,CL47)-CT47 | DU47: 12.527459 | DV47: =DU47-CJ47 | DX47: =(CS47-CZ47)*10^6 | DY47: =(CT47-DC47)*10^6 | DZ47: =(CW47-DD47)*10^6
B48: ENSEIGNES PUBLICITAIRES - AFFI | C48: Opex42 | D48: 7.40375 | G48: -4.213157 | J48: 6.00875 | M48: 43.492772 | P48: 6.00875 | S48: 43.492773 | V48: 18.190375 | AA48: 43.492772 | AD48: 4.145833 | AI48: 43.492772 | AL48: 22.252308 | CR48: =SUMIF($D$5:$CQ$5,CR$5,$D48:$CQ48) | CS48: =SUMIF($D$5:$CQ$5,CS$5,$D48:$CQ48) | CT48: =SUMIF($D$5:$CQ$5,CT$5,$D48:$CQ48)+SUMIF($D$5:$BI$5,CR$5,$D48:$BI48) | CU48: =+CR48-CS48 | CV48: =+CR48-CT48 | CW48: =SUMIF($D$5:$CQ$5,CW$5,$D48:$CQ48) | CX48: =IFERROR(CR48/CW48-1, "-") | CZ48: 0 | DA48: 19.42125 | DD48: 423.24548 | DJ48: =SUM(D48,J48,P48,V48,AD48,AL48,AU48,BC48,BK48,BT48,CB48,CJ48)-CR48 | DK48: =SUM(E48,K48,Q48,W48,AE48,AM48,AV48,BD48,BL48,BU48,CC48,CK48)-CS48 | DL48: =SUM(G48,M48,S48,AA48,AI48,AR48,AZ48,BH48,BQ48,BY48,CG48,CO48)-CW48 | DM48: =SUM(D48,J48,P48,V48,AD48,AL48,AU48,BC48,,BN48,BV48,CD48,CL48)-CT48 | DP48: 398425246 | DQ48: =-CR48+DP48/10^6 | DR48: =SUM(E48,K48,Q48,W48,AE48,AM48,AV48,BD48,BL48,BU48,CC48,CK48)-CS48 | DS48: =SUM(D48,J48,P48,V48,AD48,AL48,AU48,BC48,,BN48,BV48,CD48,CL48)-CT48 | DU48: 24.820232 | DV48: =DU48-CJ48 | DX48: =(CS48-CZ48)*10^6 | DY48: =(CT48-DC48)*10^6 | DZ48: =(CW48-DD48)*10^6
B49: FOIRES ET EXPOSITIONS | C49: Opex43 | D49: 0 | G49: 0 | J49: 0 | M49: 0 | P49: 0 | S49: 0 | V49: 0 | AA49: 0 | AD49: 0 | AI49: 0 | AL49: 0 | CR49: =SUMIF($D$5:$CQ$5,CR$5,$D49:$CQ49) | CS49: =SUMIF($D$5:$CQ$5,CS$5,$D49:$CQ49) | CT49: =SUMIF($D$5:$CQ$5,CT$5,$D49:$CQ49)+SUMIF($D$5:$BI$5,CR$5,$D49:$BI49) | CU49: =+CR49-CS49 | CV49: =+CR49-CT49 | CW49: =SUMIF($D$5:$CQ$5,CW$5,$D49:$CQ49) | CX49: =IFERROR(CR49/CW49-1, "-") | CZ49: 0 | DA49: 0 | DD49: 0 | DJ49: =SUM(D49,J49,P49,V49,AD49,AL49,AU49,BC49,BK49,BT49,CB49,CJ49)-CR49 | DK49: =SUM(E49,K49,Q49,W49,AE49,AM49,AV49,BD49,BL49,BU49,CC49,CK49)-CS49 | DL49: =SUM(G49,M49,S49,AA49,AI49,AR49,AZ49,BH49,BQ49,BY49,CG49,CO49)-CW49 | DM49: =SUM(D49,J49,P49,V49,AD49,AL49,AU49,BC49,,BN49,BV49,CD49,CL49)-CT49 | DP49: 0 | DQ49: =-CR49+DP49/10^6 | DR49: =SUM(E49,K49,Q49,W49,AE49,AM49,AV49,BD49,BL49,BU49,CC49,CK49)-CS49 | DS49: =SUM(D49,J49,P49,V49,AD49,AL49,AU49,BC49,,BN49,BV49,CD49,CL49)-CT49 | DU49: 0 | DV49: =DU49-CJ49 | DX49: =(CS49-CZ49)*10^6 | DY49: =(CT49-DC49)*10^6 | DZ49: =(CW49-DD49)*10^6
B50: CADEAUX A LA CLIENTELE | C50: Opex44 | D50: 0 | G50: 42.841 | J50: 0 | M50: 35.17345 | P50: 0 | S50: 39.336394 | V50: 2.475 | AA50: 7.240882 | AD50: 6.547 | AI50: 2.4195 | AL50: 0.0826 | CR50: =SUMIF($D$5:$CQ$5,CR$5,$D50:$CQ50) | CS50: =SUMIF($D$5:$CQ$5,CS$5,$D50:$CQ50) | CT50: =SUMIF($D$5:$CQ$5,CT$5,$D50:$CQ50)+SUMIF($D$5:$BI$5,CR$5,$D50:$BI50) | CU50: =+CR50-CS50 | CV50: =+CR50-CT50 | CW50: =SUMIF($D$5:$CQ$5,CW$5,$D50:$CQ50) | CX50: =IFERROR(CR50/CW50-1, "-") | CZ50: 0 | DA50: 0 | DD50: 141.35509 | DJ50: =SUM(D50,J50,P50,V50,AD50,AL50,AU50,BC50,BK50,BT50,CB50,CJ50)-CR50 | DK50: =SUM(E50,K50,Q50,W50,AE50,AM50,AV50,BD50,BL50,BU50,CC50,CK50)-CS50 | DL50: =SUM(G50,M50,S50,AA50,AI50,AR50,AZ50,BH50,BQ50,BY50,CG50,CO50)-CW50 | DM50: =SUM(D50,J50,P50,V50,AD50,AL50,AU50,BC50,,BN50,BV50,CD50,CL50)-CT50 | DP50: #VALUE! | DQ50: =-CR50+DP50/10^6 | DR50: =SUM(E50,K50,Q50,W50,AE50,AM50,AV50,BD50,BL50,BU50,CC50,CK50)-CS50 | DS50: =SUM(D50,J50,P50,V50,AD50,AL50,AU50,BC50,,BN50,BV50,CD50,CL50)-CT50 | DU50: 0 | DV50: =DU50-CJ50 | DX50: =(CS50-CZ50)*10^6 | DY50: =(CT50-DC50)*10^6 | DZ50: =(CW50-DD50)*10^6
B51: FRAIS DE COLLOQUES, SEMINAIRES | C51: Opex45 | D51: 0 | G51: 0 | J51: 0 | M51: 0 | P51: 0 | S51: 0 | V51: 0 | AA51: 0 | AD51: 0 | AI51: 0 | AL51: 0 | CR51: =SUMIF($D$5:$CQ$5,CR$5,$D51:$CQ51) | CS51: =SUMIF($D$5:$CQ$5,CS$5,$D51:$CQ51) | CT51: =SUMIF($D$5:$CQ$5,CT$5,$D51:$CQ51)+SUMIF($D$5:$BI$5,CR$5,$D51:$BI51) | CU51: =+CR51-CS51 | CV51: =+CR51-CT51 | CW51: =SUMIF($D$5:$CQ$5,CW$5,$D51:$CQ51) | CX51: =IFERROR(CR51/CW51-1, "-") | CZ51: 0 | DA51: 0 | DD51: 0 | DJ51: =SUM(D51,J51,P51,V51,AD51,AL51,AU51,BC51,BK51,BT51,CB51,CJ51)-CR51 | DK51: =SUM(E51,K51,Q51,W51,AE51,AM51,AV51,BD51,BL51,BU51,CC51,CK51)-CS51 | DL51: =SUM(G51,M51,S51,AA51,AI51,AR51,AZ51,BH51,BQ51,BY51,CG51,CO51)-CW51 | DM51: =SUM(D51,J51,P51,V51,AD51,AL51,AU51,BC51,,BN51,BV51,CD51,CL51)-CT51 | DP51: 0 | DQ51: =-CR51+DP51/10^6 | DR51: =SUM(E51,K51,Q51,W51,AE51,AM51,AV51,BD51,BL51,BU51,CC51,CK51)-CS51 | DS51: =SUM(D51,J51,P51,V51,AD51,AL51,AU51,BC51,,BN51,BV51,CD51,CL51)-CT51 | DU51: 0 | DV51: =DU51-CJ51 | DX51: =(CS51-CZ51)*10^6 | DY51: =(CT51-DC51)*10^6 | DZ51: =(CW51-DD51)*10^6
B52: RELATIONS PUBLIQUES | C52: Opex46 | D52: 51.484103 | G52: 78.218618 | J52: 74.932923 | M52: 39.797815 | P52: 68.233216 | S52: 64.982685 | V52: 81.812057 | AA52: 61.891552 | AD52: 76.524453 | AI52: 121.29669 | AL52: 70.956445 | CR52: =SUMIF($D$5:$CQ$5,CR$5,$D52:$CQ52) | CS52: =SUMIF($D$5:$CQ$5,CS$5,$D52:$CQ52) | CT52: =SUMIF($D$5:$CQ$5,CT$5,$D52:$CQ52)+SUMIF($D$5:$BI$5,CR$5,$D52:$BI52) | CU52: =+CR52-CS52 | CV52: =+CR52-CT52 | CW52: =SUMIF($D$5:$CQ$5,CW$5,$D52:$CQ52) | CX52: =IFERROR(CR52/CW52-1, "-") | CZ52: 0 | DA52: 194.65024 | DD52: 754.15542 | DJ52: =SUM(D52,J52,P52,V52,AD52,AL52,AU52,BC52,BK52,BT52,CB52,CJ52)-CR52 | DK52: =SUM(E52,K52,Q52,W52,AE52,AM52,AV52,BD52,BL52,BU52,CC52,CK52)-CS52 | DL52: =SUM(G52,M52,S52,AA52,AI52,AR52,AZ52,BH52,BQ52,BY52,CG52,CO52)-CW52 | DM52: =SUM(D52,J52,P52,V52,AD52,AL52,AU52,BC52,,BN52,BV52,CD52,CL52)-CT52 | DP52: #VALUE! | DQ52: =-CR52+DP52/10^6 | DR52: =SUM(E52,K52,Q52,W52,AE52,AM52,AV52,BD52,BL52,BU52,CC52,CK52)-CS52 | DS52: =SUM(D52,J52,P52,V52,AD52,AL52,AU52,BC52,,BN52,BV52,CD52,CL52)-CT52 | DU52: 76.338363 | DV52: =DU52-CJ52 | DX52: =(CS52-CZ52)*10^6 | DY52: =(CT52-DC52)*10^6 | DZ52: =(CW52-DD52)*10^6
B53: DEVELOPPEMENT DE LA MARQUE | C53: Opex47 | D53: 0 | G53: 0 | J53: 0 | M53: 0 | P53: 0 | S53: 0 | V53: 0 | AA53: 0 | AD53: 0 | AI53: 0 | AL53: 0 | CR53: =SUMIF($D$5:$CQ$5,CR$5,$D53:$CQ53) | CS53: =SUMIF($D$5:$CQ$5,CS$5,$D53:$CQ53) | CT53: =SUMIF($D$5:$CQ$5,CT$5,$D53:$CQ53)+SUMIF($D$5:$BI$5,CR$5,$D53:$BI53) | CU53: =+CR53-CS53 | CV53: =+CR53-CT53 | CW53: =SUMIF($D$5:$CQ$5,CW$5,$D53:$CQ53) | CX53: =IFERROR(CR53/CW53-1, "-") | CZ53: 0 | DA53: 0 | DD53: 0 | DJ53: =SUM(D53,J53,P53,V53,AD53,AL53,AU53,BC53,BK53,BT53,CB53,CJ53)-CR53 | DK53: =SUM(E53,K53,Q53,W53,AE53,AM53,AV53,BD53,BL53,BU53,CC53,CK53)-CS53 | DL53: =SUM(G53,M53,S53,AA53,AI53,AR53,AZ53,BH53,BQ53,BY53,CG53,CO53)-CW53 | DM53: =SUM(D53,J53,P53,V53,AD53,AL53,AU53,BC53,,BN53,BV53,CD53,CL53)-CT53 | DP53: 0 | DQ53: =-CR53+DP53/10^6 | DR53: =SUM(E53,K53,Q53,W53,AE53,AM53,AV53,BD53,BL53,BU53,CC53,CK53)-CS53 | DS53: =SUM(D53,J53,P53,V53,AD53,AL53,AU53,BC53,,BN53,BV53,CD53,CL53)-CT53 | DU53: 0 | DV53: =DU53-CJ53 | DX53: =(CS53-CZ53)*10^6 | DY53: =(CT53-DC53)*10^6 | DZ53: =(CW53-DD53)*10^6
B54: AUTRES IMPOTS ET TAXES DIRECTS | C54: Opex48 | G54: 0 | M54: 0 | S54: 0 | AA54: 0 | AI54: 0 | AL54: 0 | CR54: =SUMIF($D$5:$CQ$5,CR$5,$D54:$CQ54) | CS54: =SUMIF($D$5:$CQ$5,CS$5,$D54:$CQ54) | CT54: =SUMIF($D$5:$CQ$5,CT$5,$D54:$CQ54)+SUMIF($D$5:$BI$5,CR$5,$D54:$BI54) | CU54: =+CR54-CS54 | CV54: =+CR54-CT54 | CW54: =SUMIF($D$5:$CQ$5,CW$5,$D54:$CQ54) | CX54: =IFERROR(CR54/CW54-1, "-") | CZ54: 0 | DA54: 0 | DD54: 0 | DJ54: =SUM(D54,J54,P54,V54,AD54,AL54,AU54,BC54,BK54,BT54,CB54,CJ54)-CR54 | DK54: =SUM(E54,K54,Q54,W54,AE54,AM54,AV54,BD54,BL54,BU54,CC54,CK54)-CS54 | DL54: =SUM(G54,M54,S54,AA54,AI54,AR54,AZ54,BH54,BQ54,BY54,CG54,CO54)-CW54 | DM54: =SUM(D54,J54,P54,V54,AD54,AL54,AU54,BC54,,BN54,BV54,CD54,CL54)-CT54 | DQ54: =-CR54+DP54/10^6 | DR54: =SUM(E54,K54,Q54,W54,AE54,AM54,AV54,BD54,BL54,BU54,CC54,CK54)-CS54 | DS54: =SUM(D54,J54,P54,V54,AD54,AL54,AU54,BC54,,BN54,BV54,CD54,CL54)-CT54 | DV54: =DU54-CJ54 | DX54: =(CS54-CZ54)*10^6 | DY54: =(CT54-DC54)*10^6 | DZ54: =(CW54-DD54)*10^6
B55: ENQUETES ET ETUDES DE MARCHES | C55: Opex49 | D55: 0 | G55: 1.7 | J55: 0 | M55: 1.7 | P55: 0 | S55: -25.3 | V55: 0 | AA55: 1.696211 | AD55: 6.871851 | AI55: 1.7 | AL55: 0 | CR55: =SUMIF($D$5:$CQ$5,CR$5,$D55:$CQ55) | CS55: =SUMIF($D$5:$CQ$5,CS$5,$D55:$CQ55) | CT55: =SUMIF($D$5:$CQ$5,CT$5,$D55:$CQ55)+SUMIF($D$5:$BI$5,CR$5,$D55:$BI55) | CU55: =+CR55-CS55 | CV55: =+CR55-CT55 | CW55: =SUMIF($D$5:$CQ$5,CW$5,$D55:$CQ55) | CX55: =IFERROR(CR55/CW55-1, "-") | CZ55: 0 | DA55: 0 | DD55: -14.21263 | DJ55: =SUM(D55,J55,P55,V55,AD55,AL55,AU55,BC55,BK55,BT55,CB55,CJ55)-CR55 | DK55: =SUM(E55,K55,Q55,W55,AE55,AM55,AV55,BD55,BL55,BU55,CC55,CK55)-CS55 | DL55: =SUM(G55,M55,S55,AA55,AI55,AR55,AZ55,BH55,BQ55,BY55,CG55,CO55)-CW55 | DM55: =SUM(D55,J55,P55,V55,AD55,AL55,AU55,BC55,,BN55,BV55,CD55,CL55)-CT55 | DP55: -14212630 | DQ55: =-CR55+DP55/10^6 | DR55: =SUM(E55,K55,Q55,W55,AE55,AM55,AV55,BD55,BL55,BU55,CC55,CK55)-CS55 | DS55: =SUM(D55,J55,P55,V55,AD55,AL55,AU55,BC55,,BN55,BV55,CD55,CL55)-CT55 | DU55: 0 | DV55: =DU55-CJ55 | DX55: =(CS55-CZ55)*10^6 | DY55: =(CT55-DC55)*10^6 | DZ55: =(CW55-DD55)*10^6
C56: Opex50 | CT56: =SUMIF($D$5:$CQ$5,CT$5,$D56:$CQ56)+SUMIF($D$5:$BI$5,CR$5,$D56:$BI56) | CX56: =IFERROR(CR56/CW56-1, "-") | DJ56: =SUM(D56,J56,P56,V56,AD56,AL56,AU56,BC56,BK56,BT56,CB56,CJ56)-CR56 | DK56: =SUM(E56,K56,Q56,W56,AE56,AM56,AV56,BD56,BL56,BU56,CC56,CK56)-CS56 | DL56: =SUM(G56,M56,S56,AA56,AI56,AR56,AZ56,BH56,BQ56,BY56,CG56,CO56)-CW56 | DM56: =SUM(D56,J56,P56,V56,AD56,AL56,AU56,BC56,,BN56,BV56,CD56,CL56)-CT56 | DQ56: =-CR56+DP56/10^6 | DR56: =SUM(E56,K56,Q56,W56,AE56,AM56,AV56,BD56,BL56,BU56,CC56,CK56)-CS56 | DS56: =SUM(D56,J56,P56,V56,AD56,AL56,AU56,BC56,,BN56,BV56,CD56,CL56)-CT56 | DV56: =DU56-CJ56 | DX56: =(CS56-CZ56)*10^6 | DY56: =(CT56-DC56)*10^6 | DZ56: =(CW56-DD56)*10^6
B57: Exploitation & maintenance | C57: Opex51 | D57: 1604.2984 | E57: 1768.4753 | F57: -164.17692 | G57: 1754.5013 | H57: -0.085610038 | J57: 1520.4476 | K57: 1737.3645 | L57: -216.91691 | M57: 1646.6434 | N57: -0.076638212 | P57: 1564.1925 | Q57: 1726.6695 | R57: -162.47699 | S57: 1520.9238 | T57: 0.028448916 | V57: 1658.2498 | W57: 1714.1927 | X57: 1649.5647 | Y57: -55.942899 | Z57: 8.6851004 | AA57: 1720.2834 | AB57: -0.036060092 | AD57: 1612.5591 | AE57: 1713.7202 | AF57: 1650.237 | AG57: -101.16113 | AH57: -37.677901 | AI57: 1705.3317 | AJ57: -0.054401533 | AL57: 1584.1792 | AM57: 1732.334 | AN57: 0 | AO57: 0 | AP57: -148.15472 | AQ57: 1584.1792 | AR57: 1161.8344 | AS57: 0.36351553 | CR57: =SUMIF($D$5:$CQ$5,CR$5,$D57:$CQ57) | CS57: =+CS58+CS79+CS97+CS100+CS106 | CT57: =SUMIF($D$5:$CQ$5,CT$5,$D57:$CQ57)+SUMIF($D$5:$BI$5,CR$5,$D57:$BI57) | CU57: =+CR57-CS57 | CV57: =+CR57-CT57 | CW57: =SUMIF($D$5:$CQ$5,CW$5,$D57:$CQ57) | CX57: =IFERROR(CR57/CW57-1, "-") | CZ57: 20292.074 | DD57: 19423.997 | DE57: =+CZ57/DD57-1 | DF57: =+DA57/DD57-1 | DG57: =+DB57/DD57-1 | DH57: =+DC57/DD57-1 | DJ57: =SUM(D57,J57,P57,V57,AD57,AL57,AU57,BC57,BK57,BT57,CB57,CJ57)-CR57 | DL57: =SUM(G57,M57,S57,AA57,AI57,AR57,AZ57,BH57,BQ57,BY57,CG57,CO57)-CW57 | DM57: =SUM(D57,J57,P57,V57,AD57,AL57,AU57,BC57,,BN57,BV57,CD57,CL57)-CT57 | DP57: =+DP58+DP79+DP97+DP100+DP106 | DQ57: =-CR57+DP57/10^6 | DR57: =SUM(E57,K57,Q57,W57,AE57,AM57,AV57,BD57,BL57,BU57,CC57,CK57)-CS57 | DS57: =SUM(D57,J57,P57,V57,AD57,AL57,AU57,BC57,,BN57,BV57,CD57,CL57)-CT57 | DU57: 1613.6547 | DV57: =DU57-CJ57 | DX57: =(CS57-CZ57)*10^6 | DY57: =(CT57-DC57)*10^6 | DZ57: =(CW57-DD57)*10^6
B58: Achat d'énergie - Bâtiment - Gardiennage | C58: Opex52 | D58: 740.84422 | E58: 864.64316 | F58: -123.79895 | G58: 775.79213 | H58: -0.045048045 | J58: 662.3155 | K58: 833.26986 | L58: -170.95435 | M58: 728.80167 | N58: -0.091226699 | P58: 701.91208 | Q58: 821.96986 | R58: -120.05777 | S58: 732.36998 | T58: -0.041588137 | V58: 738.96105 | W58: 806.11361 | X58: 745.50224 | Y58: -67.152559 | Z58: -6.5411986 | AA58: 700.29478 | AB58: 0.055214276 | AD58: 704.46723 | AE58: 804.61361 | AF58: 744.15224 | AG58: -100.14637 | AH58: -39.685013 | AI58: 752.35416 | AJ58: -0.063649443 | AL58: 673.17023 | AM58: 821.85736 | AN58: 0 | AO58: 0 | AP58: -148.68713 | AQ58: 673.17023 | AR58: 689.08012 | AS58: -0.023088594 | CR58: =SUMIF($D$5:$CQ$5,CR$5,$D58:$CQ58) | CS58: =SUMIF($D$5:$CQ$5,CS$5,$D58:$CQ58) | CT58: =SUMIF($D$5:$CQ$5,CT$5,$D58:$CQ58)+SUMIF($D$5:$BI$5,CR$5,$D58:$BI58) | CU58: =+CR58-CS58 | CV58: =+CR58-CT58 | CW58: =SUMIF($D$5:$CQ$5,CW$5,$D58:$CQ58) | CX58: =IFERROR(CR58/CW58-1, "-") | CZ58: 9467 | DD58: 8825.8967 | DE58: =+CZ58/DD58-1 | DF58: =+DA58/DD58-1 | DG58: =+DB58/DD58-1 | DH58: =+DC58/DD58-1 | DJ58: =SUM(D58,J58,P58,V58,AD58,AL58,AU58,BC58,BK58,BT58,CB58,CJ58)-CR58 | DK58: =SUM(E58,K58,Q58,W58,AE58,AM58,AV58,BD58,BL58,BU58,CC58,CK58)-CS58 | DL58: =SUM(G58,M58,S58,AA58,AI58,AR58,AZ58,BH58,BQ58,BY58,CG58,CO58)-CW58 | DM58: =SUM(D58,J58,P58,V58,AD58,AL58,AU58,BC58,,BN58,BV58,CD58,CL58)-CT58 | DP58: =SUM(DP59:DP78) | DQ58: =-CR58+DP58/10^6 | DR58: =SUM(E58,K58,Q58,W58,AE58,AM58,AV58,BD58,BL58,BU58,CC58,CK58)-CS58 | DS58: =SUM(D58,J58,P58,V58,AD58,AL58,AU58,BC58,,BN58,BV58,CD58,CL58)-CT58 | DU58: 722.66259 | DV58: =DU58-CJ58 | DX58: =(CS58-CZ58)*10^6 | DY58: =(CT58-DC58)*10^6 | DZ58: =(CW58-DD58)*10^6
B59: LOYERS ENTREPOTS | C59: Opex53 | D59: 11.586364 | E59: 12.375 | G59: 12.806 | J59: 10.186364 | K59: 12.375 | M59: 14.806 | P59: 10.886364 | Q59: 12.375 | S59: 13.306 | V59: 10.886364 | W59: 12.375 | X59: 11.375 | AA59: 13.306 | AD59: 10.886364 | AE59: 12.375 | AF59: 11.375 | AI59: 45.651684 | AL59: 10.886364 | AM59: 12.375 | CR59: =SUMIF($D$5:$CQ$5,CR$5,$D59:$CQ59) | CS59: =SUMIF($D$5:$CQ$5,CS$5,$D59:$CQ59) | CT59: =SUMIF($D$5:$CQ$5,CT$5,$D59:$CQ59)+SUMIF($D$5:$BI$5,CR$5,$D59:$BI59) | CU59: =+CR59-CS59 | CV59: =+CR59-CT59 | CW59: =SUMIF($D$5:$CQ$5,CW$5,$D59:$CQ59) | CX59: =IFERROR(CR59/CW59-1, "-") | CZ59: 148.03453 | DA59: 135.03409 | DD59: 148.82273 | DE59: =+CZ59/DD59-1 | DF59: =+DA59/DD59-1 | DG59: =+DB59/DD59-1 | DH59: =+DC59/DD59-1 | DJ59: =SUM(D59,J59,P59,V59,AD59,AL59,AU59,BC59,BK59,BT59,CB59,CJ59)-CR59 | DK59: =SUM(E59,K59,Q59,W59,AE59,AM59,AV59,BD59,BL59,BU59,CC59,CK59)-CS59 | DL59: =SUM(G59,M59,S59,AA59,AI59,AR59,AZ59,BH59,BQ59,BY59,CG59,CO59)-CW59 | DM59: =SUM(D59,J59,P59,V59,AD59,AL59,AU59,BC59,,BN59,BV59,CD59,CL59)-CT59 | DP59: 137236368 | DQ59: =-CR59+DP59/10^6 | DR59: =SUM(E59,K59,Q59,W59,AE59,AM59,AV59,BD59,BL59,BU59,CC59,CK59)-CS59 | DS59: =SUM(D59,J59,P59,V59,AD59,AL59,AU59,BC59,,BN59,BV59,CD59,CL59)-CT59 | DU59: 11.586364 | DV59: =DU59-CJ59 | DX59: =(CS59-CZ59)*10^6 | DY59: =(CT59-DC59)*10^6 | DZ59: =(CW59-DD59)*10^6
B60: ELECTRICITE CT AKASSATO | C60: Opex54 | D60: 0 | E60: 0 | G60: 0 | J60: 0 | K60: 0 | M60: 0 | P60: 0 | Q60: 0 | S60: 0 | V60: 0 | W60: 0 | X60: 0 | AA60: 0 | AD60: 0 | AE60: 0 | AF60: 0 | AI60: 0 | AM60: 0 | CR60: =SUMIF($D$5:$CQ$5,CR$5,$D60:$CQ60) | CS60: =SUMIF($D$5:$CQ$5,CS$5,$D60:$CQ60) | CT60: =SUMIF($D$5:$CQ$5,CT$5,$D60:$CQ60)+SUMIF($D$5:$BI$5,CR$5,$D60:$BI60) | CU60: =+CR60-CS60 | CV60: =+CR60-CT60 | CW60: =SUMIF($D$5:$CQ$5,CW$5,$D60:$CQ60) | CX60: =IFERROR(CR60/CW60-1, "-") | CZ60: 0 | DA60: 0 | DD60: 0 | DJ60: =SUM(D60,J60,P60,V60,AD60,AL60,AU60,BC60,BK60,BT60,CB60,CJ60)-CR60 | DK60: =SUM(E60,K60,Q60,W60,AE60,AM60,AV60,BD60,BL60,BU60,CC60,CK60)-CS60 | DL60: =SUM(G60,M60,S60,AA60,AI60,AR60,AZ60,BH60,BQ60,BY60,CG60,CO60)-CW60 | DM60: =SUM(D60,J60,P60,V60,AD60,AL60,AU60,BC60,,BN60,BV60,CD60,CL60)-CT60 | DP60: 0 | DQ60: =-CR60+DP60/10^6 | DR60: =SUM(E60,K60,Q60,W60,AE60,AM60,AV60,BD60,BL60,BU60,CC60,CK60)-CS60 | DS60: =SUM(D60,J60,P60,V60,AD60,AL60,AU60,BC60,,BN60,BV60,CD60,CL60)-CT60 | DU60: 0 | DV60: =DU60-CJ60 | DX60: =(CS60-CZ60)*10^6 | DY60: =(CT60-DC60)*10^6 | DZ60: =(CW60-DD60)*10^6
B61: EAU CT | C61: Opex55 | D61: 0 | E61: 2.550607 | G61: 0 | J61: 0 | K61: 2.550607 | M61: 0 | P61: 0 | Q61: 2.550607 | S61: 0 | V61: 0 | W61: 2.550607 | X61: 2.550607 | AA61: 0 | AD61: 0 | AE61: 2.550607 | AF61: 2.550607 | AI61: 0 | AM61: 2.550607 | CR61: =SUMIF($D$5:$CQ$5,CR$5,$D61:$CQ61) | CS61: =SUMIF($D$5:$CQ$5,CS$5,$D61:$CQ61) | CT61: =SUMIF($D$5:$CQ$5,CT$5,$D61:$CQ61)+SUMIF($D$5:$BI$5,CR$5,$D61:$BI61) | CU61: =+CR61-CS61 | CV61: =+CR61-CT61 | CW61: =SUMIF($D$5:$CQ$5,CW$5,$D61:$CQ61) | CX61: =IFERROR(CR61/CW61-1, "-") | CZ61: 30.607284 | DA61: 22.955463 | DD61: 0 | DJ61: =SUM(D61,J61,P61,V61,AD61,AL61,AU61,BC61,BK61,BT61,CB61,CJ61)-CR61 | DK61: =SUM(E61,K61,Q61,W61,AE61,AM61,AV61,BD61,BL61,BU61,CC61,CK61)-CS61 | DL61: =SUM(G61,M61,S61,AA61,AI61,AR61,AZ61,BH61,BQ61,BY61,CG61,CO61)-CW61 | DM61: =SUM(D61,J61,P61,V61,AD61,AL61,AU61,BC61,,BN61,BV61,CD61,CL61)-CT61 | DP61: 0 | DQ61: =-CR61+DP61/10^6 | DR61: =SUM(E61,K61,Q61,W61,AE61,AM61,AV61,BD61,BL61,BU61,CC61,CK61)-CS61 | DS61: =SUM(D61,J61,P61,V61,AD61,AL61,AU61,BC61,,BN61,BV61,CD61,CL61)-CT61 | DU61: 0 | DV61: =DU61-CJ61 | DX61: =(CS61-CZ61)*10^6 | DY61: =(CT61-DC61)*10^6 | DZ61: =(CW61-DD61)*10^6
B62: ELECTRICITE SITES TECHNIQUES | C62: Opex56 | D62: 265.72855 | E62: 275.42985 | G62: 275.42985 | J62: 240.53754 | K62: 255.81875 | M62: 255.61663 | P62: 238.96459 | Q62: 259.81875 | S62: 256.99249 | V62: 268.44266 | W62: 257.5625 | X62: 252.5625 | AA62: 255.00058 | AD62: 266.90464 | AE62: 261.5625 | AF62: 256.5625 | AI62: 265.79151 | AL62: 262.78549 | AM62: 267.30625 | CR62: =SUMIF($D$5:$CQ$5,CR$5,$D62:$CQ62) | CS62: =SUMIF($D$5:$CQ$5,CS$5,$D62:$CQ62) | CT62: =SUMIF($D$5:$CQ$5,CT$5,$D62:$CQ62)+SUMIF($D$5:$BI$5,CR$5,$D62:$BI62) | CU62: =+CR62-CS62 | CV62: =+CR62-CT62 | CW62: =SUMIF($D$5:$CQ$5,CW$5,$D62:$CQ62) | CX62: =IFERROR(CR62/CW62-1, "-") | CZ62: 3180.6 | DA62: 3089.7633 | DD62: 3020.2246 | DE62: =+CZ62/DD62-1 | DF62: =+DA62/DD62-1 | DG62: =+DB62/DD62-1 | DH62: =+DC62/DD62-1 | DJ62: =SUM(D62,J62,P62,V62,AD62,AL62,AU62,BC62,BK62,BT62,CB62,CJ62)-CR62 | DK62: =SUM(E62,K62,Q62,W62,AE62,AM62,AV62,BD62,BL62,BU62,CC62,CK62)-CS62 | DL62: =SUM(G62,M62,S62,AA62,AI62,AR62,AZ62,BH62,BQ62,BY62,CG62,CO62)-CW62 | DM62: =SUM(D62,J62,P62,V62,AD62,AL62,AU62,BC62,,BN62,BV62,CD62,CL62)-CT62 | DP62: 2770925511 | DQ62: =-CR62+DP62/10^6 | DR62: =SUM(E62,K62,Q62,W62,AE62,AM62,AV62,BD62,BL62,BU62,CC62,CK62)-CS62 | DS62: =SUM(D62,J62,P62,V62,AD62,AL62,AU62,BC62,,BN62,BV62,CD62,CL62)-CT62 | DU62: 249.29905 | DV62: =DU62-CJ62 | DX62: =(CS62-CZ62)*10^6 | DY62: =(CT62-DC62)*10^6 | DZ62: =(CW62-DD62)*10^6
B63: ELECTRICITE SITES TECHNIQUES C | C63: Opex57 | G63: 0 | M63: 0 | S63: 0 | AA63: 0 | AI63: 0 | CR63: =SUMIF($D$5:$CQ$5,CR$5,$D63:$CQ63) | CS63: =SUMIF($D$5:$CQ$5,CS$5,$D63:$CQ63) | CT63: =SUMIF($D$5:$CQ$5,CT$5,$D63:$CQ63)+SUMIF($D$5:$BI$5,CR$5,$D63:$BI63) | CU63: =+CR63-CS63 | CV63: =+CR63-CT63 | CW63: =SUMIF($D$5:$CQ$5,CW$5,$D63:$CQ63) | CX63: =IFERROR(CR63/CW63-1, "-") | CZ63: 0 | DA63: 0 | DD63: 0 | DJ63: =SUM(D63,J63,P63,V63,AD63,AL63,AU63,BC63,BK63,BT63,CB63,CJ63)-CR63 | DK63: =SUM(E63,K63,Q63,W63,AE63,AM63,AV63,BD63,BL63,BU63,CC63,CK63)-CS63 | DL63: =SUM(G63,M63,S63,AA63,AI63,AR63,AZ63,BH63,BQ63,BY63,CG63,CO63)-CW63 | DM63: =SUM(D63,J63,P63,V63,AD63,AL63,AU63,BC63,,BN63,BV63,CD63,CL63)-CT63 | DQ63: =-CR63+DP63/10^6 | DR63: =SUM(E63,K63,Q63,W63,AE63,AM63,AV63,BD63,BL63,BU63,CC63,CK63)-CS63 | DS63: =SUM(D63,J63,P63,V63,AD63,AL63,AU63,BC63,,BN63,BV63,CD63,CL63)-CT63 | DV63: =DU63-CJ63 | DX63: =(CS63-CZ63)*10^6 | DY63: =(CT63-DC63)*10^6 | DZ63: =(CW63-DD63)*10^6
B64: VARIATION DE STOCKS, CARBURANT | C64: Opex58 | D64: 37.10636 | G64: 0.985911 | J64: 95.178221 | M64: -1.817916 | P64: 55.786802 | S64: 33.705978 | V64: 124.38708 | AA64: -10.328164 | AD64: 14.436606 | AI64: -54.525939 | AL64: 35.00957 | CR64: =SUMIF($D$5:$CQ$5,CR$5,$D64:$CQ64) | CS64: =SUMIF($D$5:$CQ$5,CS$5,$D64:$CQ64) | CT64: =SUMIF($D$5:$CQ$5,CT$5,$D64:$CQ64)+SUMIF($D$5:$BI$5,CR$5,$D64:$BI64) | CU64: =+CR64-CS64 | CV64: =+CR64-CT64 | CW64: =SUMIF($D$5:$CQ$5,CW$5,$D64:$CQ64) | CX64: =IFERROR(CR64/CW64-1, "-") | CZ64: 0 | DA64: 188.07138 | DD64: -188.38026 | DE64: =+CZ64/DD64-1 | DF64: =+DA64/DD64-1 | DG64: =+DB64/DD64-1 | DH64: =+DC64/DD64-1 | DJ64: =SUM(D64,J64,P64,V64,AD64,AL64,AU64,BC64,BK64,BT64,CB64,CJ64)-CR64 | DK64: =SUM(E64,K64,Q64,W64,AE64,AM64,AV64,BD64,BL64,BU64,CC64,CK64)-CS64 | DL64: =SUM(G64,M64,S64,AA64,AI64,AR64,AZ64,BH64,BQ64,BY64,CG64,CO64)-CW64 | DM64: =SUM(D64,J64,P64,V64,AD64,AL64,AU64,BC64,,BN64,BV64,CD64,CL64)-CT64 | DP64: -147538860 | DQ64: =-CR64+DP64/10^6 | DR64: =SUM(E64,K64,Q64,W64,AE64,AM64,AV64,BD64,BL64,BU64,CC64,CK64)-CS64 | DS64: =SUM(D64,J64,P64,V64,AD64,AL64,AU64,BC64,,BN64,BV64,CD64,CL64)-CT64 | DU64: -40.841398 | DV64: =DU64-CJ64 | DX64: =(CS64-CZ64)*10^6 | DY64: =(CT64-DC64)*10^6 | DZ64: =(CW64-DD64)*10^6
B65: FRAIS DE CARBURANT ET LUBRIFIA | C65: Opex59 | D65: 159.11576 | E65: 340.04583 | G65: 225.70638 | J65: 60.984793 | K65: 331.94583 | M65: 239.75936 | P65: 140.38552 | Q65: 315.74583 | S65: 182.15849 | V65: 87.920579 | W65: 299.54583 | X65: 194.98024 | AA65: 208.33075 | AD65: 145.13845 | AE65: 291.44583 | AF65: 187.03024 | AI65: 248.04704 | AL65: 170.9218 | AM65: 299.54583 | CR65: =SUMIF($D$5:$CQ$5,CR$5,$D65:$CQ65) | CS65: =SUMIF($D$5:$CQ$5,CS$5,$D65:$CQ65) | CT65: =SUMIF($D$5:$CQ$5,CT$5,$D65:$CQ65)+SUMIF($D$5:$BI$5,CR$5,$D65:$BI65) | CU65: =+CR65-CS65 | CV65: =+CR65-CT65 | CW65: =SUMIF($D$5:$CQ$5,CW$5,$D65:$CQ65) | CX65: =IFERROR(CR65/CW65-1, "-") | CZ65: 3237.34 | DA65: 1735.5076 | DD65: 3003.1996 | DE65: =+CZ65/DD65-1 | DF65: =+DA65/DD65-1 | DG65: =+DB65/DD65-1 | DH65: =+DC65/DD65-1 | DJ65: =SUM(D65,J65,P65,V65,AD65,AL65,AU65,BC65,BK65,BT65,CB65,CJ65)-CR65 | DK65: =SUM(E65,K65,Q65,W65,AE65,AM65,AV65,BD65,BL65,BU65,CC65,CK65)-CS65 | DL65: =SUM(G65,M65,S65,AA65,AI65,AR65,AZ65,BH65,BQ65,BY65,CG65,CO65)-CW65 | DM65: =SUM(D65,J65,P65,V65,AD65,AL65,AU65,BC65,,BN65,BV65,CD65,CL65)-CT65 | DP65: 2742772775 | DQ65: =-CR65+DP65/10^6 | DR65: =SUM(E65,K65,Q65,W65,AE65,AM65,AV65,BD65,BL65,BU65,CC65,CK65)-CS65 | DS65: =SUM(D65,J65,P65,V65,AD65,AL65,AU65,BC65,,BN65,BV65,CD65,CL65)-CT65 | DU65: 260.42687 | DV65: =DU65-CJ65 | DX65: =(CS65-CZ65)*10^6 | DY65: =(CT65-DC65)*10^6 | DZ65: =(CW65-DD65)*10^6
B66: LOYERS SITES TECHNIQUES | C66: Opex60 | D66: 72.470275 | E66: 79.168561 | G66: 69.682115 | J66: 76.451632 | K66: 79.168561 | M66: 68.865734 | P66: 64.339265 | Q66: 79.648561 | S66: 73.20455 | V66: 73.026761 | W66: 80.848561 | X66: 80.848561 | AA66: 91.777789 | AD66: 75.613519 | AE66: 82.048561 | AF66: 82.048561 | AI66: 71.804294 | AL66: 79.000823 | AM66: 84.448561 | CR66: =SUMIF($D$5:$CQ$5,CR$5,$D66:$CQ66) | CS66: =SUMIF($D$5:$CQ$5,CS$5,$D66:$CQ66) | CT66: =SUMIF($D$5:$CQ$5,CT$5,$D66:$CQ66)+SUMIF($D$5:$BI$5,CR$5,$D66:$BI66) | CU66: =+CR66-CS66 | CV66: =+CR66-CT66 | CW66: =SUMIF($D$5:$CQ$5,CW$5,$D66:$CQ66) | CX66: =IFERROR(CR66/CW66-1, "-") | CZ66: 1006.4227 | DA66: 981.69822 | DD66: 872.2101 | DE66: =+CZ66/DD66-1 | DF66: =+DA66/DD66-1 | DG66: =+DB66/DD66-1 | DH66: =+DC66/DD66-1 | DJ66: =SUM(D66,J66,P66,V66,AD66,AL66,AU66,BC66,BK66,BT66,CB66,CJ66)-CR66 | DK66: =SUM(E66,K66,Q66,W66,AE66,AM66,AV66,BD66,BL66,BU66,CC66,CK66)-CS66 | DL66: =SUM(G66,M66,S66,AA66,AI66,AR66,AZ66,BH66,BQ66,BY66,CG66,CO66)-CW66 | DM66: =SUM(D66,J66,P66,V66,AD66,AL66,AU66,BC66,,BN66,BV66,CD66,CL66)-CT66 | DP66: 800076571 | DQ66: =-CR66+DP66/10^6 | DR66: =SUM(E66,K66,Q66,W66,AE66,AM66,AV66,BD66,BL66,BU66,CC66,CK66)-CS66 | DS66: =SUM(D66,J66,P66,V66,AD66,AL66,AU66,BC66,,BN66,BV66,CD66,CL66)-CT66 | DU66: 72.133524 | DV66: =DU66-CJ66 | DX66: =(CS66-CZ66)*10^6 | DY66: =(CT66-DC66)*10^6 | DZ66: =(CW66-DD66)*10^6
B67: FRAIS DE GARDIENNAGE | C67: Opex61 | D67: 84.493612 | E67: 74.2 | G67: 94.739544 | J67: 89.814838 | K67: 74.2 | M67: 92.252022 | P67: 77.427874 | Q67: 74.62 | S67: 95.013424 | V67: 70.0774 | W67: 76.02 | X67: 76.02 | AA67: 93.671288 | AD67: 82.3894 | AE67: 77.42 | AF67: 77.42 | AI67: 93.652 | AL67: 52.597014 | AM67: 78.82 | CR67: =SUMIF($D$5:$CQ$5,CR$5,$D67:$CQ67) | CS67: =SUMIF($D$5:$CQ$5,CS$5,$D67:$CQ67) | CT67: =SUMIF($D$5:$CQ$5,CT$5,$D67:$CQ67)+SUMIF($D$5:$BI$5,CR$5,$D67:$BI67) | CU67: =+CR67-CS67 | CV67: =+CR67-CT67 | CW67: =SUMIF($D$5:$CQ$5,CW$5,$D67:$CQ67) | CX67: =IFERROR(CR67/CW67-1, "-") | CZ67: 936.6 | DA67: 965.31632 | DD67: 1066.3568 | DE67: =+CZ67/DD67-1 | DF67: =+DA67/DD67-1 | DG67: =+DB67/DD67-1 | DH67: =+DC67/DD67-1 | DJ67: =SUM(D67,J67,P67,V67,AD67,AL67,AU67,BC67,BK67,BT67,CB67,CJ67)-CR67 | DK67: =SUM(E67,K67,Q67,W67,AE67,AM67,AV67,BD67,BL67,BU67,CC67,CK67)-CS67 | DL67: =SUM(G67,M67,S67,AA67,AI67,AR67,AZ67,BH67,BQ67,BY67,CG67,CO67)-CW67 | DM67: =SUM(D67,J67,P67,V67,AD67,AL67,AU67,BC67,,BN67,BV67,CD67,CL67)-CT67 | DP67: 983202562 | DQ67: =-CR67+DP67/10^6 | DR67: =SUM(E67,K67,Q67,W67,AE67,AM67,AV67,BD67,BL67,BU67,CC67,CK67)-CS67 | DS67: =SUM(D67,J67,P67,V67,AD67,AL67,AU67,BC67,,BN67,BV67,CD67,CL67)-CT67 | DU67: 83.154258 | DV67: =DU67-CJ67 | DX67: =(CS67-CZ67)*10^6 | DY67: =(CT67-DC67)*10^6 | DZ67: =(CW67-DD67)*10^6
B68: LOYERS SIEGE ET AGENCES | C68: Opex62 | D68: -2.01427 | E68: -4.6323172 | G68: -18.007882 | J68: -2.46103 | K68: -8.2945232 | M68: -15.413937 | P68: 6.92923 | Q68: -8.2945232 | S68: -14.715083 | V68: 2.491497 | W68: -8.2945232 | X68: 5.6597113 | AA68: -19.155726 | AD68: 2.778901 | AE68: -8.2945232 | AF68: 5.6597113 | AI68: -17.169845 | AL68: 1.876925 | AM68: -8.2945233 | CR68: =SUMIF($D$5:$CQ$5,CR$5,$D68:$CQ68) | CS68: =SUMIF($D$5:$CQ$5,CS$5,$D68:$CQ68) | CT68: =SUMIF($D$5:$CQ$5,CT$5,$D68:$CQ68)+SUMIF($D$5:$BI$5,CR$5,$D68:$BI68) | CU68: =+CR68-CS68 | CV68: =+CR68-CT68 | CW68: =SUMIF($D$5:$CQ$5,CW$5,$D68:$CQ68) | CX68: =IFERROR(CR68/CW68-1, "-") | CZ68: -95.872073 | DA68: 53.391332 | DD68: -166.70763 | DE68: =+CZ68/DD68-1 | DF68: =+DA68/DD68-1 | DG68: =+DB68/DD68-1 | DH68: =+DC68/DD68-1 | DJ68: =SUM(D68,J68,P68,V68,AD68,AL68,AU68,BC68,BK68,BT68,CB68,CJ68)-CR68 | DK68: =SUM(E68,K68,Q68,W68,AE68,AM68,AV68,BD68,BL68,BU68,CC68,CK68)-CS68 | DL68: =SUM(G68,M68,S68,AA68,AI68,AR68,AZ68,BH68,BQ68,BY68,CG68,CO68)-CW68 | DM68: =SUM(D68,J68,P68,V68,AD68,AL68,AU68,BC68,,BN68,BV68,CD68,CL68)-CT68 | DP68: -231139194 | DQ68: =-CR68+DP68/10^6 | DR68: =SUM(E68,K68,Q68,W68,AE68,AM68,AV68,BD68,BL68,BU68,CC68,CK68)-CS68 | DS68: =SUM(D68,J68,P68,V68,AD68,AL68,AU68,BC68,,BN68,BV68,CD68,CL68)-CT68 | DU68: -5.670593 | DV68: =DU68-CJ68 | DX68: =(CS68-CZ68)*10^6 | DY68: =(CT68-DC68)*10^6 | DZ68: =(CW68-DD68)*10^6
B69: FOURNITURES D'ENTRETIEN NON ST | C69: Opex63 | D69: 0 | G69: 0 | J69: 0 | M69: 0 | P69: 0 | S69: 0 | V69: 0 | AA69: 0 | AD69: 0 | AI69: 0 | AL69: 0 | CR69: =SUMIF($D$5:$CQ$5,CR$5,$D69:$CQ69) | CS69: =SUMIF($D$5:$CQ$5,CS$5,$D69:$CQ69) | CT69: =SUMIF($D$5:$CQ$5,CT$5,$D69:$CQ69)+SUMIF($D$5:$BI$5,CR$5,$D69:$BI69) | CU69: =+CR69-CS69 | CV69: =+CR69-CT69 | CW69: =SUMIF($D$5:$CQ$5,CW$5,$D69:$CQ69) | CX69: =IFERROR(CR69/CW69-1, "-") | CZ69: 0 | DA69: 0 | DD69: 0 | DJ69: =SUM(D69,J69,P69,V69,AD69,AL69,AU69,BC69,BK69,BT69,CB69,CJ69)-CR69 | DK69: =SUM(E69,K69,Q69,W69,AE69,AM69,AV69,BD69,BL69,BU69,CC69,CK69)-CS69 | DL69: =SUM(G69,M69,S69,AA69,AI69,AR69,AZ69,BH69,BQ69,BY69,CG69,CO69)-CW69 | DM69: =SUM(D69,J69,P69,V69,AD69,AL69,AU69,BC69,,BN69,BV69,CD69,CL69)-CT69 | DP69: 0 | DQ69: =-CR69+DP69/10^6 | DR69: =SUM(E69,K69,Q69,W69,AE69,AM69,AV69,BD69,BL69,BU69,CC69,CK69)-CS69 | DS69: =SUM(D69,J69,P69,V69,AD69,AL69,AU69,BC69,,BN69,BV69,CD69,CL69)-CT69 | DU69: 0 | DV69: =DU69-CJ69 | DX69: =(CS69-CZ69)*10^6 | DY69: =(CT69-DC69)*10^6 | DZ69: =(CW69-DD69)*10^6
B70: ENTRETIEN ET REPARATIONS BATS | C70: Opex64 | D70: 20.673182 | E70: 22.311777 | G70: 28.460013 | J70: 12.954899 | K70: 22.311777 | M70: 8.920074 | P70: 18.532175 | Q70: 22.311777 | S70: 15.360303 | V70: 20.848394 | W70: 22.311777 | X70: 22.311777 | AA70: 4.329474 | AD70: 28.906341 | AE70: 22.311777 | AF70: 22.311777 | AI70: 15.238785 | AL70: -7.173875 | AM70: 22.311777 | CR70: =SUMIF($D$5:$CQ$5,CR$5,$D70:$CQ70) | CS70: =SUMIF($D$5:$CQ$5,CS$5,$D70:$CQ70) | CT70: =SUMIF($D$5:$CQ$5,CT$5,$D70:$CQ70)+SUMIF($D$5:$BI$5,CR$5,$D70:$BI70) | CU70: =+CR70-CS70 | CV70: =+CR70-CT70 | CW70: =SUMIF($D$5:$CQ$5,CW$5,$D70:$CQ70) | CX70: =IFERROR(CR70/CW70-1, "-") | CZ70: 267.74132 | DA70: 252.96625 | DD70: 161.26271 | DE70: =+CZ70/DD70-1 | DF70: =+DA70/DD70-1 | DG70: =+DB70/DD70-1 | DH70: =+DC70/DD70-1 | DJ70: =SUM(D70,J70,P70,V70,AD70,AL70,AU70,BC70,BK70,BT70,CB70,CJ70)-CR70 | DK70: =SUM(E70,K70,Q70,W70,AE70,AM70,AV70,BD70,BL70,BU70,CC70,CK70)-CS70 | DL70: =SUM(G70,M70,S70,AA70,AI70,AR70,AZ70,BH70,BQ70,BY70,CG70,CO70)-CW70 | DM70: =SUM(D70,J70,P70,V70,AD70,AL70,AU70,BC70,,BN70,BV70,CD70,CL70)-CT70 | DP70: 142576762 | DQ70: =-CR70+DP70/10^6 | DR70: =SUM(E70,K70,Q70,W70,AE70,AM70,AV70,BD70,BL70,BU70,CC70,CK70)-CS70 | DS70: =SUM(D70,J70,P70,V70,AD70,AL70,AU70,BC70,,BN70,BV70,CD70,CL70)-CT70 | DU70: 18.685949 | DV70: =DU70-CJ70 | DX70: =(CS70-CZ70)*10^6 | DY70: =(CT70-DC70)*10^6 | DZ70: =(CW70-DD70)*10^6
B71: FRAIS DE GARDIENNAGE | C71: Opex65 | D71: 0 | E71: 10 | G71: 0 | J71: 0 | K71: 10 | M71: 0 | P71: 0 | Q71: 10 | S71: 0 | V71: 0 | W71: 10 | X71: 10 | AA71: 0 | AD71: 0 | AE71: 10 | AF71: 10 | AI71: 0 | AM71: 10 | CR71: =SUMIF($D$5:$CQ$5,CR$5,$D71:$CQ71) | CS71: =SUMIF($D$5:$CQ$5,CS$5,$D71:$CQ71) | CT71: =SUMIF($D$5:$CQ$5,CT$5,$D71:$CQ71)+SUMIF($D$5:$BI$5,CR$5,$D71:$BI71) | CU71: =+CR71-CS71 | CV71: =+CR71-CT71 | CW71: =SUMIF($D$5:$CQ$5,CW$5,$D71:$CQ71) | CX71: =IFERROR(CR71/CW71-1, "-") | CZ71: 120 | DA71: 90 | DD71: 0 | DJ71: =SUM(D71,J71,P71,V71,AD71,AL71,AU71,BC71,BK71,BT71,CB71,CJ71)-CR71 | DK71: =SUM(E71,K71,Q71,W71,AE71,AM71,AV71,BD71,BL71,BU71,CC71,CK71)-CS71 | DL71: =SUM(G71,M71,S71,AA71,AI71,AR71,AZ71,BH71,BQ71,BY71,CG71,CO71)-CW71 | DM71: =SUM(D71,J71,P71,V71,AD71,AL71,AU71,BC71,,BN71,BV71,CD71,CL71)-CT71 | DP71: 0 | DQ71: =-CR71+DP71/10^6 | DR71: =SUM(E71,K71,Q71,W71,AE71,AM71,AV71,BD71,BL71,BU71,CC71,CK71)-CS71 | DS71: =SUM(D71,J71,P71,V71,AD71,AL71,AU71,BC71,,BN71,BV71,CD71,CL71)-CT71 | DU71: 0 | DV71: =DU71-CJ71 | DX71: =(CS71-CZ71)*10^6 | DY71: =(CT71-DC71)*10^6 | DZ71: =(CW71-DD71)*10^6
B72: EAU BUREAUX, ADMINISTRATION, C | C72: Opex66 | D72: 1.640838 | E72: 2.05 | G72: -0.092885 | J72: 1.630458 | K72: 2.05 | M72: 1.384714 | P72: 1.737326 | Q72: 2.05 | S72: 1.854955 | V72: 1.417275 | W72: 2.05 | X72: 2.05 | AA72: 1.315059 | AD72: 0.893116 | AE72: 2.05 | AF72: 2.05 | AI72: 1.487874 | AL72: 1.477807 | AM72: 1.65 | CR72: =SUMIF($D$5:$CQ$5,CR$5,$D72:$CQ72) | CS72: =SUMIF($D$5:$CQ$5,CS$5,$D72:$CQ72) | CT72: =SUMIF($D$5:$CQ$5,CT$5,$D72:$CQ72)+SUMIF($D$5:$BI$5,CR$5,$D72:$BI72) | CU72: =+CR72-CS72 | CV72: =+CR72-CT72 | CW72: =SUMIF($D$5:$CQ$5,CW$5,$D72:$CQ72) | CX72: =IFERROR(CR72/CW72-1, "-") | CZ72: 21.8 | DA72: 20.658622 | DD72: 17.513253 | DE72: =+CZ72/DD72-1 | DF72: =+DA72/DD72-1 | DG72: =+DB72/DD72-1 | DH72: =+DC72/DD72-1 | DJ72: =SUM(D72,J72,P72,V72,AD72,AL72,AU72,BC72,BK72,BT72,CB72,CJ72)-CR72 | DK72: =SUM(E72,K72,Q72,W72,AE72,AM72,AV72,BD72,BL72,BU72,CC72,CK72)-CS72 | DL72: =SUM(G72,M72,S72,AA72,AI72,AR72,AZ72,BH72,BQ72,BY72,CG72,CO72)-CW72 | DM72: =SUM(D72,J72,P72,V72,AD72,AL72,AU72,BC72,,BN72,BV72,CD72,CL72)-CT72 | DP72: 16502302 | DQ72: =-CR72+DP72/10^6 | DR72: =SUM(E72,K72,Q72,W72,AE72,AM72,AV72,BD72,BL72,BU72,CC72,CK72)-CS72 | DS72: =SUM(D72,J72,P72,V72,AD72,AL72,AU72,BC72,,BN72,BV72,CD72,CL72)-CT72 | DU72: 1.010951 | DV72: =DU72-CJ72 | DX72: =(CS72-CZ72)*10^6 | DY72: =(CT72-DC72)*10^6 | DZ72: =(CW72-DD72)*10^6
B73: ELECTRICITE BUREAUX, ADMINISTR | C73: Opex67 | D73: 69.826478 | E73: 46.925 | G73: 59.786947 | J73: 63.652094 | K73: 46.925 | M73: 58.15263 | P73: 70.758358 | Q73: 46.925 | S73: 66.813214 | V73: 69.815537 | W73: 46.925 | X73: 70.925 | AA73: 57.477276 | AD73: 72.364943 | AE73: 46.925 | AF73: 70.925 | AI73: 69.314982 | AL73: 65.707808 | AM73: 46.925 | CR73: =SUMIF($D$5:$CQ$5,CR$5,$D73:$CQ73) | CS73: =SUMIF($D$5:$CQ$5,CS$5,$D73:$CQ73) | CT73: =SUMIF($D$5:$CQ$5,CT$5,$D73:$CQ73)+SUMIF($D$5:$BI$5,CR$5,$D73:$BI73) | CU73: =+CR73-CS73 | CV73: =+CR73-CT73 | CW73: =SUMIF($D$5:$CQ$5,CW$5,$D73:$CQ73) | CX73: =IFERROR(CR73/CW73-1, "-") | CZ73: 563.1 | DA73: 842.56193 | DD73: 762.11087 | DE73: =+CZ73/DD73-1 | DF73: =+DA73/DD73-1 | DG73: =+DB73/DD73-1 | DH73: =+DC73/DD73-1 | DJ73: =SUM(D73,J73,P73,V73,AD73,AL73,AU73,BC73,BK73,BT73,CB73,CJ73)-CR73 | DK73: =SUM(E73,K73,Q73,W73,AE73,AM73,AV73,BD73,BL73,BU73,CC73,CK73)-CS73 | DL73: =SUM(G73,M73,S73,AA73,AI73,AR73,AZ73,BH73,BQ73,BY73,CG73,CO73)-CW73 | DM73: =SUM(D73,J73,P73,V73,AD73,AL73,AU73,BC73,,BN73,BV73,CD73,CL73)-CT73 | DP73: 683676551 | DQ73: =-CR73+DP73/10^6 | DR73: =SUM(E73,K73,Q73,W73,AE73,AM73,AV73,BD73,BL73,BU73,CC73,CK73)-CS73 | DS73: =SUM(D73,J73,P73,V73,AD73,AL73,AU73,BC73,,BN73,BV73,CD73,CL73)-CT73 | DT73: -8.781966 | DU73: 69.652354 | DV73: =DU73-CJ73 | DX73: =(CS73-CZ73)*10^6 | DY73: =(CT73-DC73)*10^6 | DZ73: =(CW73-DD73)*10^6
B74: FRAIS DE TELEPHONE BUREAUX | C74: Opex68 | D74: 20.024066 | E74: 4.21885 | G74: 26.251136 | J74: 13.385696 | K74: 4.21885 | M74: 6.188356 | P74: 16.164576 | Q74: 4.21885 | S74: 8.585164 | V74: 8.892499 | W74: 4.21885 | X74: 16.21885 | AA74: 4.479949 | AD74: 3.983952 | AE74: 4.21885 | AF74: 16.21885 | AI74: 12.971274 | AL74: 0.080509 | AM74: 4.21885 | CR74: =SUMIF($D$5:$CQ$5,CR$5,$D74:$CQ74) | CS74: =SUMIF($D$5:$CQ$5,CS$5,$D74:$CQ74) | CT74: =SUMIF($D$5:$CQ$5,CT$5,$D74:$CQ74)+SUMIF($D$5:$BI$5,CR$5,$D74:$BI74) | CU74: =+CR74-CS74 | CV74: =+CR74-CT74 | CW74: =SUMIF($D$5:$CQ$5,CW$5,$D74:$CQ74) | CX74: =IFERROR(CR74/CW74-1, "-") | CZ74: 50.6262 | DA74: 195.54399 | DD74: 128.36688 | DE74: =+CZ74/DD74-1 | DF74: =+DA74/DD74-1 | DG74: =+DB74/DD74-1 | DH74: =+DC74/DD74-1 | DJ74: =SUM(D74,J74,P74,V74,AD74,AL74,AU74,BC74,BK74,BT74,CB74,CJ74)-CR74 | DK74: =SUM(E74,K74,Q74,W74,AE74,AM74,AV74,BD74,BL74,BU74,CC74,CK74)-CS74 | DL74: =SUM(G74,M74,S74,AA74,AI74,AR74,AZ74,BH74,BQ74,BY74,CG74,CO74)-CW74 | DM74: =SUM(D74,J74,P74,V74,AD74,AL74,AU74,BC74,,BN74,BV74,CD74,CL74)-CT74 | DP74: 125141612 | DQ74: =-CR74+DP74/10^6 | DR74: =SUM(E74,K74,Q74,W74,AE74,AM74,AV74,BD74,BL74,BU74,CC74,CK74)-CS74 | DS74: =SUM(D74,J74,P74,V74,AD74,AL74,AU74,BC74,,BN74,BV74,CD74,CL74)-CT74 | DU74: 3.225267 | DV74: =DU74-CJ74 | DX74: =(CS74-CZ74)*10^6 | DY74: =(CT74-DC74)*10^6 | DZ74: =(CW74-DD74)*10^6
B75: FRAIS DE TELECOPIE | C75: Opex69 | D75: 0 | G75: 0 | J75: 0 | M75: 0 | P75: 0 | S75: 0 | V75: 0 | AA75: 0 | AD75: 0 | AI75: 0 | AL75: 0 | CR75: =SUMIF($D$5:$CQ$5,CR$5,$D75:$CQ75) | CS75: =SUMIF($D$5:$CQ$5,CS$5,$D75:$CQ75) | CT75: =SUMIF($D$5:$CQ$5,CT$5,$D75:$CQ75)+SUMIF($D$5:$BI$5,CR$5,$D75:$BI75) | CU75: =+CR75-CS75 | CV75: =+CR75-CT75 | CW75: =SUMIF($D$5:$CQ$5,CW$5,$D75:$CQ75) | CX75: =IFERROR(CR75/CW75-1, "-") | CZ75: 0 | DA75: 0 | DD75: 0 | DE75: =+CZ75/DD75-1 | DF75: =+DA75/DD75-1 | DG75: =+DB75/DD75-1 | DH75: =+DC75/DD75-1 | DJ75: =SUM(D75,J75,P75,V75,AD75,AL75,AU75,BC75,BK75,BT75,CB75,CJ75)-CR75 | DK75: =SUM(E75,K75,Q75,W75,AE75,AM75,AV75,BD75,BL75,BU75,CC75,CK75)-CS75 | DL75: =SUM(G75,M75,S75,AA75,AI75,AR75,AZ75,BH75,BQ75,BY75,CG75,CO75)-CW75 | DM75: =SUM(D75,J75,P75,V75,AD75,AL75,AU75,BC75,,BN75,BV75,CD75,CL75)-CT75 | DP75: 0 | DQ75: =-CR75+DP75/10^6 | DR75: =SUM(E75,K75,Q75,W75,AE75,AM75,AV75,BD75,BL75,BU75,CC75,CK75)-CS75 | DS75: =SUM(D75,J75,P75,V75,AD75,AL75,AU75,BC75,,BN75,BV75,CD75,CL75)-CT75 | DU75: 0 | DV75: =DU75-CJ75 | DX75: =(CS75-CZ75)*10^6 | DY75: =(CT75-DC75)*10^6 | DZ75: =(CW75-DD75)*10^6
B76: AUTRES FRAIS DE COMMUNICATIONS | C76: Opex70 | D76: 0.193 | G76: 0.045 | J76: 0 | M76: 0.088 | P76: 0 | S76: 0.0905 | V76: 0.755 | AA76: 0.0905 | AD76: 0.171 | AI76: 0.0905 | AL76: 0 | CR76: =SUMIF($D$5:$CQ$5,CR$5,$D76:$CQ76) | CS76: =SUMIF($D$5:$CQ$5,CS$5,$D76:$CQ76) | CT76: =SUMIF($D$5:$CQ$5,CT$5,$D76:$CQ76)+SUMIF($D$5:$BI$5,CR$5,$D76:$BI76) | CU76: =+CR76-CS76 | CV76: =+CR76-CT76 | CW76: =SUMIF($D$5:$CQ$5,CW$5,$D76:$CQ76) | CX76: =IFERROR(CR76/CW76-1, "-") | CZ76: 0 | DA76: 0.193 | DD76: 0.917 | DE76: =+CZ76/DD76-1 | DF76: =+DA76/DD76-1 | DG76: =+DB76/DD76-1 | DH76: =+DC76/DD76-1 | DJ76: =SUM(D76,J76,P76,V76,AD76,AL76,AU76,BC76,BK76,BT76,CB76,CJ76)-CR76 | DK76: =SUM(E76,K76,Q76,W76,AE76,AM76,AV76,BD76,BL76,BU76,CC76,CK76)-CS76 | DL76: =SUM(G76,M76,S76,AA76,AI76,AR76,AZ76,BH76,BQ76,BY76,CG76,CO76)-CW76 | DM76: =SUM(D76,J76,P76,V76,AD76,AL76,AU76,BC76,,BN76,BV76,CD76,CL76)-CT76 | DP76: 917000 | DQ76: =-CR76+DP76/10^6 | DR76: =SUM(E76,K76,Q76,W76,AE76,AM76,AV76,BD76,BL76,BU76,CC76,CK76)-CS76 | DS76: =SUM(D76,J76,P76,V76,AD76,AL76,AU76,BC76,,BN76,BV76,CD76,CL76)-CT76 | DU76: 0 | DV76: =DU76-CJ76 | DX76: =(CS76-CZ76)*10^6 | DY76: =(CT76-DC76)*10^6 | DZ76: =(CW76-DD76)*10^6
B77: FRAIS CONNEXION INTERNET | C77: Opex71 | D77: 0 | G77: 0 | J77: 0 | M77: 0 | P77: 0 | S77: 0 | V77: 0 | AA77: 0 | AD77: 0 | AI77: 0 | AL77: 0 | CR77: =SUMIF($D$5:$CQ$5,CR$5,$D77:$CQ77) | CS77: =SUMIF($D$5:$CQ$5,CS$5,$D77:$CQ77) | CT77: =SUMIF($D$5:$CQ$5,CT$5,$D77:$CQ77)+SUMIF($D$5:$BI$5,CR$5,$D77:$BI77) | CU77: =+CR77-CS77 | CV77: =+CR77-CT77 | CW77: =SUMIF($D$5:$CQ$5,CW$5,$D77:$CQ77) | CX77: =IFERROR(CR77/CW77-1, "-") | CZ77: 0 | DA77: 0 | DD77: 0 | DE77: =+CZ77/DD77-1 | DF77: =+DA77/DD77-1 | DG77: =+DB77/DD77-1 | DH77: =+DC77/DD77-1 | DJ77: =SUM(D77,J77,P77,V77,AD77,AL77,AU77,BC77,BK77,BT77,CB77,CJ77)-CR77 | DK77: =SUM(E77,K77,Q77,W77,AE77,AM77,AV77,BD77,BL77,BU77,CC77,CK77)-CS77 | DL77: =SUM(G77,M77,S77,AA77,AI77,AR77,AZ77,BH77,BQ77,BY77,CG77,CO77)-CW77 | DM77: =SUM(D77,J77,P77,V77,AD77,AL77,AU77,BC77,,BN77,BV77,CD77,CL77)-CT77 | DP77: 0 | DQ77: =-CR77+DP77/10^6 | DR77: =SUM(E77,K77,Q77,W77,AE77,AM77,AV77,BD77,BL77,BU77,CC77,CK77)-CS77 | DS77: =SUM(D77,J77,P77,V77,AD77,AL77,AU77,BC77,,BN77,BV77,CD77,CL77)-CT77 | DU77: 0 | DV77: =DU77-CJ77 | DX77: =(CS77-CZ77)*10^6 | DY77: =(CT77-DC77)*10^6 | DZ77: =(CW77-DD77)*10^6
B78: Contrainte :SBEE | C78: Opex72 | G78: 0 | M78: 0 | S78: 0 | AA78: 0 | AI78: 0 | CR78: =SUMIF($D$5:$CQ$5,CR$5,$D78:$CQ78) | CS78: =SUMIF($D$5:$CQ$5,CS$5,$D78:$CQ78) | CT78: =SUMIF($D$5:$CQ$5,CT$5,$D78:$CQ78)+SUMIF($D$5:$BI$5,CR$5,$D78:$BI78) | CU78: =+CR78-CS78 | CV78: =+CR78-CT78 | CW78: =SUMIF($D$5:$CQ$5,CW$5,$D78:$CQ78) | CX78: =IFERROR(CR78/CW78-1, "-") | CZ78: 0 | DA78: 0 | DD78: 0 | DE78: =+CZ78/DD78-1 | DF78: =+DA78/DD78-1 | DG78: =+DB78/DD78-1 | DH78: =+DC78/DD78-1 | DJ78: =SUM(D78,J78,P78,V78,AD78,AL78,AU78,BC78,BK78,BT78,CB78,CJ78)-CR78 | DK78: =SUM(E78,K78,Q78,W78,AE78,AM78,AV78,BD78,BL78,BU78,CC78,CK78)-CS78 | DL78: =SUM(G78,M78,S78,AA78,AI78,AR78,AZ78,BH78,BQ78,BY78,CG78,CO78)-CW78 | DM78: =SUM(D78,J78,P78,V78,AD78,AL78,AU78,BC78,,BN78,BV78,CD78,CL78)-CT78 | DQ78: =-CR78+DP78/10^6 | DR78: =SUM(E78,K78,Q78,W78,AE78,AM78,AV78,BD78,BL78,BU78,CC78,CK78)-CS78 | DS78: =SUM(D78,J78,P78,V78,AD78,AL78,AU78,BC78,,BN78,BV78,CD78,CL78)-CT78 | DV78: =DU78-CJ78 | DX78: =(CS78-CZ78)*10^6 | DY78: =(CT78-DC78)*10^6 | DZ78: =(CW78-DD78)*10^6
B79: Lignes et réseaux (entretien & achats) | C79: Opex73 | D79: 554.6743 | E79: 591.38042 | F79: -36.706117 | G79: 604.1125 | H79: -0.081836084 | J79: 631.83886 | K79: 591.64292 | L79: 40.195943 | M79: 618.12528 | N79: 0.022185763 | P79: 584.94128 | Q79: 592.24792 | R79: -7.3066381 | S79: 460.62758 | T79: 0.26987899 | V79: 611.81364 | W79: 595.62742 | X79: 595.62742 | Y79: 16.186223 | Z79: 16.186223 | AA79: 591.90812 | AB79: 0.033629412 | AD79: 638.11546 | AE79: 596.65492 | AF79: 596.65492 | AG79: 41.460536 | AH79: 41.460536 | AI79: 579.33252 | AJ79: 0.10146667 | AL79: 627.51322 | AM79: 598.02492 | AN79: 0 | AO79: 0 | AP79: 29.488301 | AQ79: 627.51322 | AR79: 184.91582 | AS79: 2.3935075 | CR79: =SUMIF($D$5:$CQ$5,CR$5,$D79:$CQ79) | CS79: =SUMIF($D$5:$CQ$5,CS$5,$D79:$CQ79) | CT79: =SUMIF($D$5:$CQ$5,CT$5,$D79:$CQ79)+SUMIF($D$5:$BI$5,CR$5,$D79:$BI79) | CU79: =+CR79-CS79 | CV79: =+CR79-CT79 | CW79: =SUMIF($D$5:$CQ$5,CW$5,$D79:$CQ79) | CX79: =IFERROR(CR79/CW79-1, "-") | CZ79: 7005.7328 | DD79: 6476.2447 | DE79: =+CZ79/DD79-1 | DF79: =+DA79/DD79-1 | DG79: =+DB79/DD79-1 | DH79: =+DC79/DD79-1 | DJ79: =SUM(D79,J79,P79,V79,AD79,AL79,AU79,BC79,BK79,BT79,CB79,CJ79)-CR79 | DK79: =SUM(E79,K79,Q79,W79,AE79,AM79,AV79,BD79,BL79,BU79,CC79,CK79)-CS79 | DL79: =SUM(G79,M79,S79,AA79,AI79,AR79,AZ79,BH79,BQ79,BY79,CG79,CO79)-CW79 | DM79: =SUM(D79,J79,P79,V79,AD79,AL79,AU79,BC79,,BN79,BV79,CD79,CL79)-CT79 | DP79: =SUM(DP80:DP96) | DQ79: =-CR79+DP79/10^6 | DR79: =SUM(E79,K79,Q79,W79,AE79,AM79,AV79,BD79,BL79,BU79,CC79,CK79)-CS79 | DS79: =SUM(D79,J79,P79,V79,AD79,AL79,AU79,BC79,,BN79,BV79,CD79,CL79)-CT79 | DU79: 535.11528 | DV79: =DU79-CJ79 | DX79: =(CS79-CZ79)*10^6 | DY79: =(CT79-DC79)*10^6 | DZ79: =(CW79-DD79)*10^6
B80: ACHATS PETIT MATERIEL ET OUTIL | C80: Opex74 | D80: 0 | E80: 0.5 | G80: 0 | J80: 0 | K80: 0.5 | M80: 0 | P80: 0 | Q80: 0.5 | S80: 0 | V80: 0 | W80: 0.5 | X80: 0.5 | AA80: 0 | AD80: 0 | AE80: 0.5 | AF80: 0.5 | AI80: 0 | AM80: 0.5 | CR80: =SUMIF($D$5:$CQ$5,CR$5,$D80:$CQ80) | CS80: =SUMIF($D$5:$CQ$5,CS$5,$D80:$CQ80) | CT80: =SUMIF($D$5:$CQ$5,CT$5,$D80:$CQ80)+SUMIF($D$5:$BI$5,CR$5,$D80:$BI80) | CU80: =+CR80-CS80 | CV80: =+CR80-CT80 | CW80: =SUMIF($D$5:$CQ$5,CW$5,$D80:$CQ80) | CX80: =IFERROR(CR80/CW80-1, "-") | CZ80: 6 | DA80: 4.5 | DD80: 0 | DG80: =+DB80/DD80-1 | DH80: =+DC80/DD80-1 | DJ80: =SUM(D80,J80,P80,V80,AD80,AL80,AU80,BC80,BK80,BT80,CB80,CJ80)-CR80 | DK80: =SUM(E80,K80,Q80,W80,AE80,AM80,AV80,BD80,BL80,BU80,CC80,CK80)-CS80 | DL80: =SUM(G80,M80,S80,AA80,AI80,AR80,AZ80,BH80,BQ80,BY80,CG80,CO80)-CW80 | DM80: =SUM(D80,J80,P80,V80,AD80,AL80,AU80,BC80,,BN80,BV80,CD80,CL80)-CT80 | DP80: 0 | DQ80: =-CR80+DP80/10^6 | DR80: =SUM(E80,K80,Q80,W80,AE80,AM80,AV80,BD80,BL80,BU80,CC80,CK80)-CS80 | DS80: =SUM(D80,J80,P80,V80,AD80,AL80,AU80,BC80,,BN80,BV80,CD80,CL80)-CT80 | DU80: 0 | DV80: =DU80-CJ80 | DX80: =(CS80-CZ80)*10^6 | DY80: =(CT80-DC80)*10^6 | DZ80: =(CW80-DD80)*10^6
B81: ENTRETIEN ET REPARATIONS BATS | C81: Opex75 | E81: 0 | G81: 0 | K81: 0 | M81: 0 | Q81: 0 | S81: 0 | W81: 0 | X81: 0 | AA81: 0 | AE81: 0 | AF81: 0 | AI81: 0 | AM81: 0 | CR81: =SUMIF($D$5:$CQ$5,CR$5,$D81:$CQ81) | CS81: =SUMIF($D$5:$CQ$5,CS$5,$D81:$CQ81) | CT81: =SUMIF($D$5:$CQ$5,CT$5,$D81:$CQ81)+SUMIF($D$5:$BI$5,CR$5,$D81:$BI81) | CU81: =+CR81-CS81 | CV81: =+CR81-CT81 | CW81: =SUMIF($D$5:$CQ$5,CW$5,$D81:$CQ81) | CX81: =IFERROR(CR81/CW81-1, "-") | CZ81: 0 | DA81: 0 | DD81: 0 | DG81: =+DB81/DD81-1 | DH81: =+DC81/DD81-1 | DJ81: =SUM(D81,J81,P81,V81,AD81,AL81,AU81,BC81,BK81,BT81,CB81,CJ81)-CR81 | DK81: =SUM(E81,K81,Q81,W81,AE81,AM81,AV81,BD81,BL81,BU81,CC81,CK81)-CS81 | DL81: =SUM(G81,M81,S81,AA81,AI81,AR81,AZ81,BH81,BQ81,BY81,CG81,CO81)-CW81 | DM81: =SUM(D81,J81,P81,V81,AD81,AL81,AU81,BC81,,BN81,BV81,CD81,CL81)-CT81 | DQ81: =-CR81+DP81/10^6 | DR81: =SUM(E81,K81,Q81,W81,AE81,AM81,AV81,BD81,BL81,BU81,CC81,CK81)-CS81 | DS81: =SUM(D81,J81,P81,V81,AD81,AL81,AU81,BC81,,BN81,BV81,CD81,CL81)-CT81 | DV81: =DU81-CJ81 | DX81: =(CS81-CZ81)*10^6 | DY81: =(CT81-DC81)*10^6 | DZ81: =(CW81-DD81)*10^6
B82: ENTRETIEN ET REPARATIONS SITES | C82: Opex76 | D82: 165.1342 | E82: 163.89385 | G82: 246.44724 | J82: 134.56994 | K82: 163.89385 | M82: 204.02882 | P82: 144.93521 | Q82: 164.14885 | S82: 71.74289 | V82: 145.28608 | W82: 167.26585 | X82: 142.76741 | AA82: 242.65236 | AD82: 198.91681 | AE82: 168.03085 | AF82: 143.86039 | AI82: 145.88186 | AL82: 143.07643 | AM82: 169.05085 | CR82: =SUMIF($D$5:$CQ$5,CR$5,$D82:$CQ82) | CS82: =SUMIF($D$5:$CQ$5,CS$5,$D82:$CQ82) | CT82: =SUMIF($D$5:$CQ$5,CT$5,$D82:$CQ82)+SUMIF($D$5:$BI$5,CR$5,$D82:$BI82) | CU82: =+CR82-CS82 | CV82: =+CR82-CT82 | CW82: =SUMIF($D$5:$CQ$5,CW$5,$D82:$CQ82) | CX82: =IFERROR(CR82/CW82-1, "-") | CZ82: 2027.1559 | DA82: 1597.9966 | DD82: 1533.2233 | DE82: =+CZ82/DD82-1 | DF82: =+DA82/DD82-1 | DG82: =+DB82/DD82-1 | DH82: =+DC82/DD82-1 | DJ82: =SUM(D82,J82,P82,V82,AD82,AL82,AU82,BC82,BK82,BT82,CB82,CJ82)-CR82 | DK82: =SUM(E82,K82,Q82,W82,AE82,AM82,AV82,BD82,BL82,BU82,CC82,CK82)-CS82 | DL82: =SUM(G82,M82,S82,AA82,AI82,AR82,AZ82,BH82,BQ82,BY82,CG82,CO82)-CW82 | DM82: =SUM(D82,J82,P82,V82,AD82,AL82,AU82,BC82,,BN82,BV82,CD82,CL82)-CT82 | DP82: 1375989178 | DQ82: =-CR82+DP82/10^6 | DR82: =SUM(E82,K82,Q82,W82,AE82,AM82,AV82,BD82,BL82,BU82,CC82,CK82)-CS82 | DS82: =SUM(D82,J82,P82,V82,AD82,AL82,AU82,BC82,,BN82,BV82,CD82,CL82)-CT82 | DU82: 188.74287 | DV82: =DU82-CJ82 | DX82: =(CS82-CZ82)*10^6 | DY82: =(CT82-DC82)*10^6 | DZ82: =(CW82-DD82)*10^6
B83: VARIATION DE STOCKS AUTRES APPRO DT | C83: Opex77 | D83: -21.624101 | G83: -29.169905 | J83: 11.139503 | M83: 27.015399 | P83: 2.745293 | S83: -6.720023 | V83: -18.024155 | AA83: -75.215926 | AD83: -62.79578 | AI83: 50.794752 | AL83: 8.510022 | CR83: =SUMIF($D$5:$CQ$5,CR$5,$D83:$CQ83) | CS83: =SUMIF($D$5:$CQ$5,CS$5,$D83:$CQ83) | CT83: =SUMIF($D$5:$CQ$5,CT$5,$D83:$CQ83)+SUMIF($D$5:$BI$5,CR$5,$D83:$BI83) | CU83: =+CR83-CS83 | CV83: =+CR83-CT83 | CW83: =SUMIF($D$5:$CQ$5,CW$5,$D83:$CQ83) | CX83: =IFERROR(CR83/CW83-1, "-") | CZ83: 0 | DA83: -7.739305 | DD83: -39.419054 | DE83: =+CZ83/DD83-1 | DF83: =+DA83/DD83-1 | DG83: =+DB83/DD83-1 | DH83: =+DC83/DD83-1 | DJ83: =SUM(D83,J83,P83,V83,AD83,AL83,AU83,BC83,BK83,BT83,CB83,CJ83)-CR83 | DK83: =SUM(E83,K83,Q83,W83,AE83,AM83,AV83,BD83,BL83,BU83,CC83,CK83)-CS83 | DL83: =SUM(G83,M83,S83,AA83,AI83,AR83,AZ83,BH83,BQ83,BY83,CG83,CO83)-CW83 | DM83: =SUM(D83,J83,P83,V83,AD83,AL83,AU83,BC83,,BN83,BV83,CD83,CL83)-CT83 | DP83: 24074962 | DQ83: =-CR83+DP83/10^6 | DR83: =SUM(E83,K83,Q83,W83,AE83,AM83,AV83,BD83,BL83,BU83,CC83,CK83)-CS83 | DS83: =SUM(D83,J83,P83,V83,AD83,AL83,AU83,BC83,,BN83,BV83,CD83,CL83)-CT83 | DU83: -63.494016 | DV83: =DU83-CJ83 | DX83: =(CS83-CZ83)*10^6 | DY83: =(CT83-DC83)*10^6 | DZ83: =(CW83-DD83)*10^6
B84: ENTRETIEN ET REPARATIONS EQUIP | C84: Opex78 | D84: 14.993301 | E84: 0 | G84: 15.353437 | J84: 8.407418 | K84: 0 | M84: 18.432561 | P84: 7.242861 | Q84: 0 | S84: 3.458419 | V84: 24.720291 | W84: 0 | X84: 10 | AA84: 23.253474 | AD84: 44.650006 | AE84: 0 | AF84: 10 | AI84: 36.973682 | AL84: 18.31692 | AM84: 0 | CR84: =SUMIF($D$5:$CQ$5,CR$5,$D84:$CQ84) | CS84: =SUMIF($D$5:$CQ$5,CS$5,$D84:$CQ84) | CT84: =SUMIF($D$5:$CQ$5,CT$5,$D84:$CQ84)+SUMIF($D$5:$BI$5,CR$5,$D84:$BI84) | CU84: =+CR84-CS84 | CV84: =+CR84-CT84 | CW84: =SUMIF($D$5:$CQ$5,CW$5,$D84:$CQ84) | CX84: =IFERROR(CR84/CW84-1, "-") | CZ84: 0 | DA84: 120.64358 | DD84: 189.61944 | DE84: =+CZ84/DD84-1 | DF84: =+DA84/DD84-1 | DG84: =+DB84/DD84-1 | DH84: =+DC84/DD84-1 | DJ84: =SUM(D84,J84,P84,V84,AD84,AL84,AU84,BC84,BK84,BT84,CB84,CJ84)-CR84 | DK84: =SUM(E84,K84,Q84,W84,AE84,AM84,AV84,BD84,BL84,BU84,CC84,CK84)-CS84 | DL84: =SUM(G84,M84,S84,AA84,AI84,AR84,AZ84,BH84,BQ84,BY84,CG84,CO84)-CW84 | DM84: =SUM(D84,J84,P84,V84,AD84,AL84,AU84,BC84,,BN84,BV84,CD84,CL84)-CT84 | DP84: 190417513 | DQ84: =-CR84+DP84/10^6 | DR84: =SUM(E84,K84,Q84,W84,AE84,AM84,AV84,BD84,BL84,BU84,CC84,CK84)-CS84 | DS84: =SUM(D84,J84,P84,V84,AD84,AL84,AU84,BC84,,BN84,BV84,CD84,CL84)-CT84 | DU84: -0.798076 | DV84: =DU84-CJ84 | DX84: =(CS84-CZ84)*10^6 | DY84: =(CT84-DC84)*10^6 | DZ84: =(CW84-DD84)*10^6
B85: MAINTENANCE EQUIPEMENTS TECHNI | C85: Opex79 | D85: 138.96136 | E85: 173.01668 | G85: 51.584482 | J85: 118.15767 | K85: 173.01668 | M85: 59.386811 | P85: 114.46626 | Q85: 173.01668 | S85: 55.096484 | V85: 130.62966 | W85: 173.01668 | X85: 126.76668 | AA85: 55.277644 | AD85: 129.69623 | AE85: 173.01668 | AF85: 126.76668 | AI85: 35.557831 | AL85: 130.62966 | AM85: 173.01668 | CR85: =SUMIF($D$5:$CQ$5,CR$5,$D85:$CQ85) | CS85: =SUMIF($D$5:$CQ$5,CS$5,$D85:$CQ85) | CT85: =SUMIF($D$5:$CQ$5,CT$5,$D85:$CQ85)+SUMIF($D$5:$BI$5,CR$5,$D85:$BI85) | CU85: =+CR85-CS85 | CV85: =+CR85-CT85 | CW85: =SUMIF($D$5:$CQ$5,CW$5,$D85:$CQ85) | CX85: =IFERROR(CR85/CW85-1, "-") | CZ85: 2076.2002 | DA85: 1512.4854 | DD85: 1185.5214 | DE85: =+CZ85/DD85-1 | DF85: =+DA85/DD85-1 | DG85: =+DB85/DD85-1 | DH85: =+DC85/DD85-1 | DJ85: =SUM(D85,J85,P85,V85,AD85,AL85,AU85,BC85,BK85,BT85,CB85,CJ85)-CR85 | DK85: =SUM(E85,K85,Q85,W85,AE85,AM85,AV85,BD85,BL85,BU85,CC85,CK85)-CS85 | DL85: =SUM(G85,M85,S85,AA85,AI85,AR85,AZ85,BH85,BQ85,BY85,CG85,CO85)-CW85 | DM85: =SUM(D85,J85,P85,V85,AD85,AL85,AU85,BC85,,BN85,BV85,CD85,CL85)-CT85 | DP85: 1056881347 | DQ85: =-CR85+DP85/10^6 | DR85: =SUM(E85,K85,Q85,W85,AE85,AM85,AV85,BD85,BL85,BU85,CC85,CK85)-CS85 | DS85: =SUM(D85,J85,P85,V85,AD85,AL85,AU85,BC85,,BN85,BV85,CD85,CL85)-CT85 | DU85: 128.64007 | DV85: =DU85-CJ85 | DX85: =(CS85-CZ85)*10^6 | DY85: =(CT85-DC85)*10^6 | DZ85: =(CW85-DD85)*10^6
B86: LOYERS D'ESPACES EN CO-LOCATIO | C86: Opex80 | D86: 18.701503 | E86: 5.5 | G86: 48.940736 | J86: 18.701503 | K86: 5.5 | M86: 48.940738 | P86: 18.701503 | Q86: 5.5 | S86: 49.202804 | V86: 34.33604 | W86: 5.5 | X86: 18.701503 | AA86: 41.040046 | AD86: 34.336039 | AE86: 5.5 | AF86: 18.701503 | AI86: 37.5538 | AL86: 34.33604 | AM86: 5.5 | CR86: =SUMIF($D$5:$CQ$5,CR$5,$D86:$CQ86) | CS86: =SUMIF($D$5:$CQ$5,CS$5,$D86:$CQ86) | CT86: =SUMIF($D$5:$CQ$5,CT$5,$D86:$CQ86)+SUMIF($D$5:$BI$5,CR$5,$D86:$BI86) | CU86: =+CR86-CS86 | CV86: =+CR86-CT86 | CW86: =SUMIF($D$5:$CQ$5,CW$5,$D86:$CQ86) | CX86: =IFERROR(CR86/CW86-1, "-") | CZ86: 66 | DA86: 224.41804 | DD86: 308.44898 | DE86: =+CZ86/DD86-1 | DF86: =+DA86/DD86-1 | DG86: =+DB86/DD86-1 | DH86: =+DC86/DD86-1 | DJ86: =SUM(D86,J86,P86,V86,AD86,AL86,AU86,BC86,BK86,BT86,CB86,CJ86)-CR86 | DK86: =SUM(E86,K86,Q86,W86,AE86,AM86,AV86,BD86,BL86,BU86,CC86,CK86)-CS86 | DL86: =SUM(G86,M86,S86,AA86,AI86,AR86,AZ86,BH86,BQ86,BY86,CG86,CO86)-CW86 | DM86: =SUM(D86,J86,P86,V86,AD86,AL86,AU86,BC86,,BN86,BV86,CD86,CL86)-CT86 | DP86: 300348843 | DQ86: =-CR86+DP86/10^6 | DR86: =SUM(E86,K86,Q86,W86,AE86,AM86,AV86,BD86,BL86,BU86,CC86,CK86)-CS86 | DS86: =SUM(D86,J86,P86,V86,AD86,AL86,AU86,BC86,,BN86,BV86,CD86,CL86)-CT86 | DU86: 8.100141 | DV86: =DU86-CJ86 | DX86: =(CS86-CZ86)*10^6 | DY86: =(CT86-DC86)*10^6 | DZ86: =(CW86-DD86)*10^6
B87: LOYERS LIAISONS SIGNALISATIONS | C87: Opex81 | D87: 1.311914 | E87: 1.9839355 | G87: 1.311914 | J87: 1.311914 | K87: 1.9839355 | M87: 1.311914 | P87: 1.967872 | Q87: 1.9839355 | S87: 1.476389 | V87: 1.639893 | W87: 1.9839355 | X87: 1.967872 | AA87: 1.476389 | AD87: 1.311914 | AE87: 1.9839355 | AF87: 1.639893 | AI87: 1.476389 | AL87: 1.311914 | AM87: 1.9839355 | CR87: =SUMIF($D$5:$CQ$5,CR$5,$D87:$CQ87) | CS87: =SUMIF($D$5:$CQ$5,CS$5,$D87:$CQ87) | CT87: =SUMIF($D$5:$CQ$5,CT$5,$D87:$CQ87)+SUMIF($D$5:$BI$5,CR$5,$D87:$BI87) | CU87: =+CR87-CS87 | CV87: =+CR87-CT87 | CW87: =SUMIF($D$5:$CQ$5,CW$5,$D87:$CQ87) | CX87: =IFERROR(CR87/CW87-1, "-") | CZ87: 23.807226 | DA87: 19.678716 | DD87: 15.907443 | DE87: =+CZ87/DD87-1 | DF87: =+DA87/DD87-1 | DG87: =+DB87/DD87-1 | DH87: =+DC87/DD87-1 | DJ87: =SUM(D87,J87,P87,V87,AD87,AL87,AU87,BC87,BK87,BT87,CB87,CJ87)-CR87 | DK87: =SUM(E87,K87,Q87,W87,AE87,AM87,AV87,BD87,BL87,BU87,CC87,CK87)-CS87 | DL87: =SUM(G87,M87,S87,AA87,AI87,AR87,AZ87,BH87,BQ87,BY87,CG87,CO87)-CW87 | DM87: =SUM(D87,J87,P87,V87,AD87,AL87,AU87,BC87,,BN87,BV87,CD87,CL87)-CT87 | DP87: 14595529 | DQ87: =-CR87+DP87/10^6 | DR87: =SUM(E87,K87,Q87,W87,AE87,AM87,AV87,BD87,BL87,BU87,CC87,CK87)-CS87 | DS87: =SUM(D87,J87,P87,V87,AD87,AL87,AU87,BC87,,BN87,BV87,CD87,CL87)-CT87 | DU87: 1.311914 | DV87: =DU87-CJ87 | DX87: =(CS87-CZ87)*10^6 | DY87: =(CT87-DC87)*10^6 | DZ87: =(CW87-DD87)*10^6
B88: LOYERS LIAISONS SEGMENT SPACIA | C88: Opex82 | D88: 0 | E88: 0 | G88: 0 | J88: 0 | K88: 0 | M88: 0 | P88: 0 | Q88: 0 | S88: 0 | V88: 0 | W88: 0 | X88: 0 | AA88: 0 | AD88: 0 | AE88: 0 | AF88: 0 | AI88: 0 | AL88: 0 | AM88: 0 | CR88: =SUMIF($D$5:$CQ$5,CR$5,$D88:$CQ88) | CS88: =SUMIF($D$5:$CQ$5,CS$5,$D88:$CQ88) | CT88: =SUMIF($D$5:$CQ$5,CT$5,$D88:$CQ88)+SUMIF($D$5:$BI$5,CR$5,$D88:$BI88) | CU88: =+CR88-CS88 | CV88: =+CR88-CT88 | CW88: =SUMIF($D$5:$CQ$5,CW$5,$D88:$CQ88) | CX88: =IFERROR(CR88/CW88-1, "-") | CZ88: 0 | DA88: 0 | DD88: 0 | DJ88: =SUM(D88,J88,P88,V88,AD88,AL88,AU88,BC88,BK88,BT88,CB88,CJ88)-CR88 | DK88: =SUM(E88,K88,Q88,W88,AE88,AM88,AV88,BD88,BL88,BU88,CC88,CK88)-CS88 | DL88: =SUM(G88,M88,S88,AA88,AI88,AR88,AZ88,BH88,BQ88,BY88,CG88,CO88)-CW88 | DM88: =SUM(D88,J88,P88,V88,AD88,AL88,AU88,BC88,,BN88,BV88,CD88,CL88)-CT88 | DP88: 0 | DQ88: =-CR88+DP88/10^6 | DR88: =SUM(E88,K88,Q88,W88,AE88,AM88,AV88,BD88,BL88,BU88,CC88,CK88)-CS88 | DS88: =SUM(D88,J88,P88,V88,AD88,AL88,AU88,BC88,,BN88,BV88,CD88,CL88)-CT88 | DU88: 0 | DV88: =DU88-CJ88 | DX88: =(CS88-CZ88)*10^6 | DY88: =(CT88-DC88)*10^6 | DZ88: =(CW88-DD88)*10^6
B89: LOYERS LIAISONS MIC | C89: Opex83 | D89: 0 | E89: 0 | G89: 0 | J89: 0 | K89: 0 | M89: 0 | P89: 0 | Q89: 0 | S89: 0 | V89: 0 | W89: 0 | X89: 0 | AA89: 0 | AD89: 0 | AE89: 0 | AF89: 0 | AI89: 0 | AL89: 0 | AM89: 0 | CR89: =SUMIF($D$5:$CQ$5,CR$5,$D89:$CQ89) | CS89: =SUMIF($D$5:$CQ$5,CS$5,$D89:$CQ89) | CT89: =SUMIF($D$5:$CQ$5,CT$5,$D89:$CQ89)+SUMIF($D$5:$BI$5,CR$5,$D89:$BI89) | CU89: =+CR89-CS89 | CV89: =+CR89-CT89 | CW89: =SUMIF($D$5:$CQ$5,CW$5,$D89:$CQ89) | CX89: =IFERROR(CR89/CW89-1, "-") | CZ89: 0 | DA89: 0 | DD89: 0 | DJ89: =SUM(D89,J89,P89,V89,AD89,AL89,AU89,BC89,BK89,BT89,CB89,CJ89)-CR89 | DK89: =SUM(E89,K89,Q89,W89,AE89,AM89,AV89,BD89,BL89,BU89,CC89,CK89)-CS89 | DL89: =SUM(G89,M89,S89,AA89,AI89,AR89,AZ89,BH89,BQ89,BY89,CG89,CO89)-CW89 | DM89: =SUM(D89,J89,P89,V89,AD89,AL89,AU89,BC89,,BN89,BV89,CD89,CL89)-CT89 | DP89: 0 | DQ89: =-CR89+DP89/10^6 | DR89: =SUM(E89,K89,Q89,W89,AE89,AM89,AV89,BD89,BL89,BU89,CC89,CK89)-CS89 | DS89: =SUM(D89,J89,P89,V89,AD89,AL89,AU89,BC89,,BN89,BV89,CD89,CL89)-CT89 | DU89: 0 | DV89: =DU89-CJ89 | DX89: =(CS89-CZ89)*10^6 | DY89: =(CT89-DC89)*10^6 | DZ89: =(CW89-DD89)*10^6
B90: LOYERS LIAISONS FIBRES OPTIQUE | C90: Opex84 | D90: 189.24312 | E90: 19.365467 | G90: 228.28941 | J90: 292.00391 | K90: 19.365467 | M90: 203.59853 | P90: 247.81928 | Q90: 19.365467 | S90: 238.92761 | V90: 245.97815 | W90: 19.365467 | X90: 247.61096 | AA90: 256.16613 | AD90: 244.93723 | AE90: 19.365467 | AF90: 247.87346 | AI90: 223.6812 | AL90: 244.26923 | AM90: 19.365467 | CR90: =SUMIF($D$5:$CQ$5,CR$5,$D90:$CQ90) | CS90: =SUMIF($D$5:$CQ$5,CS$5,$D90:$CQ90) | CT90: =SUMIF($D$5:$CQ$5,CT$5,$D90:$CQ90)+SUMIF($D$5:$BI$5,CR$5,$D90:$BI90) | CU90: =+CR90-CS90 | CV90: =+CR90-CT90 | CW90: =SUMIF($D$5:$CQ$5,CW$5,$D90:$CQ90) | CX90: =IFERROR(CR90/CW90-1, "-") | CZ90: 232.3856 | DA90: 2961.5529 | DD90: 2710.5095 | DE90: =+CZ90/DD90-1 | DF90: =+DA90/DD90-1 | DG90: =+DB90/DD90-1 | DH90: =+DC90/DD90-1 | DJ90: =SUM(D90,J90,P90,V90,AD90,AL90,AU90,BC90,BK90,BT90,CB90,CJ90)-CR90 | DK90: =SUM(E90,K90,Q90,W90,AE90,AM90,AV90,BD90,BL90,BU90,CC90,CK90)-CS90 | DL90: =SUM(G90,M90,S90,AA90,AI90,AR90,AZ90,BH90,BQ90,BY90,CG90,CO90)-CW90 | DM90: =SUM(D90,J90,P90,V90,AD90,AL90,AU90,BC90,,BN90,BV90,CD90,CL90)-CT90 | DP90: 2486243611 | DQ90: =-CR90+DP90/10^6 | DR90: =SUM(E90,K90,Q90,W90,AE90,AM90,AV90,BD90,BL90,BU90,CC90,CK90)-CS90 | DS90: =SUM(D90,J90,P90,V90,AD90,AL90,AU90,BC90,,BN90,BV90,CD90,CL90)-CT90 | DU90: 224.26593 | DV90: =DU90-CJ90 | DX90: =(CS90-CZ90)*10^6 | DY90: =(CT90-DC90)*10^6 | DZ90: =(CW90-DD90)*10^6
B91: LOYERS AUTRES LIAISONS | C91: Opex85 | D91: 47.063002 | E91: 226.87049 | G91: 40.853002 | J91: 47.063002 | K91: 227.13299 | M91: 55.410502 | P91: 47.063002 | Q91: 227.48299 | S91: 47.063002 | V91: 47.063002 | W91: 227.74549 | X91: 47.063002 | AA91: 47.063002 | AD91: 47.063002 | AE91: 228.00799 | AF91: 47.063002 | AI91: 47.063002 | AL91: 47.063002 | AM91: 228.35799 | CR91: =SUMIF($D$5:$CQ$5,CR$5,$D91:$CQ91) | CS91: =SUMIF($D$5:$CQ$5,CS$5,$D91:$CQ91) | CT91: =SUMIF($D$5:$CQ$5,CT$5,$D91:$CQ91)+SUMIF($D$5:$BI$5,CR$5,$D91:$BI91) | CU91: =+CR91-CS91 | CV91: =+CR91-CT91 | CW91: =SUMIF($D$5:$CQ$5,CW$5,$D91:$CQ91) | CX91: =IFERROR(CR91/CW91-1, "-") | CZ91: 2571.1839 | DA91: 564.75602 | DD91: 566.89352 | DE91: =+CZ91/DD91-1 | DF91: =+DA91/DD91-1 | DG91: =+DB91/DD91-1 | DH91: =+DC91/DD91-1 | DJ91: =SUM(D91,J91,P91,V91,AD91,AL91,AU91,BC91,BK91,BT91,CB91,CJ91)-CR91 | DK91: =SUM(E91,K91,Q91,W91,AE91,AM91,AV91,BD91,BL91,BU91,CC91,CK91)-CS91 | DL91: =SUM(G91,M91,S91,AA91,AI91,AR91,AZ91,BH91,BQ91,BY91,CG91,CO91)-CW91 | DM91: =SUM(D91,J91,P91,V91,AD91,AL91,AU91,BC91,,BN91,BV91,CD91,CL91)-CT91 | DP91: 519830522 | DQ91: =-CR91+DP91/10^6 | DR91: =SUM(E91,K91,Q91,W91,AE91,AM91,AV91,BD91,BL91,BU91,CC91,CK91)-CS91 | DS91: =SUM(D91,J91,P91,V91,AD91,AL91,AU91,BC91,,BN91,BV91,CD91,CL91)-CT91 | DU91: 47.063002 | DV91: =DU91-CJ91 | DX91: =(CS91-CZ91)*10^6 | DY91: =(CT91-DC91)*10^6 | DZ91: =(CW91-DD91)*10^6
B92: LOCATION D'INFRASTRUCTURES TEL | C92: Opex86 | D92: 0 | E92: 0 | G92: 0 | J92: 0 | K92: 0 | M92: 0 | P92: 0 | Q92: 0 | S92: 0 | V92: 0 | W92: 0 | X92: 0 | AA92: 0 | AD92: 0 | AE92: 0 | AF92: 0 | AI92: 0 | AL92: 0 | AM92: 0 | CR92: =SUMIF($D$5:$CQ$5,CR$5,$D92:$CQ92) | CS92: =SUMIF($D$5:$CQ$5,CS$5,$D92:$CQ92) | CT92: =SUMIF($D$5:$CQ$5,CT$5,$D92:$CQ92)+SUMIF($D$5:$BI$5,CR$5,$D92:$BI92) | CU92: =+CR92-CS92 | CV92: =+CR92-CT92 | CW92: =SUMIF($D$5:$CQ$5,CW$5,$D92:$CQ92) | CX92: =IFERROR(CR92/CW92-1, "-") | CZ92: 0 | DA92: 0 | DD92: 0 | DJ92: =SUM(D92,J92,P92,V92,AD92,AL92,AU92,BC92,BK92,BT92,CB92,CJ92)-CR92 | DK92: =SUM(E92,K92,Q92,W92,AE92,AM92,AV92,BD92,BL92,BU92,CC92,CK92)-CS92 | DL92: =SUM(G92,M92,S92,AA92,AI92,AR92,AZ92,BH92,BQ92,BY92,CG92,CO92)-CW92 | DM92: =SUM(D92,J92,P92,V92,AD92,AL92,AU92,BC92,,BN92,BV92,CD92,CL92)-CT92 | DP92: 0 | DQ92: =-CR92+DP92/10^6 | DR92: =SUM(E92,K92,Q92,W92,AE92,AM92,AV92,BD92,BL92,BU92,CC92,CK92)-CS92 | DS92: =SUM(D92,J92,P92,V92,AD92,AL92,AU92,BC92,,BN92,BV92,CD92,CL92)-CT92 | DU92: 0 | DV92: =DU92-CJ92 | DX92: =(CS92-CZ92)*10^6 | DY92: =(CT92-DC92)*10^6 | DZ92: =(CW92-DD92)*10^6
B93: LOCATION D'EQUIPEMENTS TELECO | C93: Opex87 | D93: 0 | G93: 0 | J93: 0 | M93: 0 | P93: 0 | S93: 0 | V93: 0 | AA93: 0 | AD93: 0 | AI93: 0 | CR93: =SUMIF($D$5:$CQ$5,CR$5,$D93:$CQ93) | CS93: =SUMIF($D$5:$CQ$5,CS$5,$D93:$CQ93) | CT93: =SUMIF($D$5:$CQ$5,CT$5,$D93:$CQ93)+SUMIF($D$5:$BI$5,CR$5,$D93:$BI93) | CU93: =+CR93-CS93 | CV93: =+CR93-CT93 | CW93: =SUMIF($D$5:$CQ$5,CW$5,$D93:$CQ93) | CX93: =IFERROR(CR93/CW93-1, "-") | CZ93: 0 | DA93: 0 | DD93: 0 | DJ93: =SUM(D93,J93,P93,V93,AD93,AL93,AU93,BC93,BK93,BT93,CB93,CJ93)-CR93 | DK93: =SUM(E93,K93,Q93,W93,AE93,AM93,AV93,BD93,BL93,BU93,CC93,CK93)-CS93 | DL93: =SUM(G93,M93,S93,AA93,AI93,AR93,AZ93,BH93,BQ93,BY93,CG93,CO93)-CW93 | DM93: =SUM(D93,J93,P93,V93,AD93,AL93,AU93,BC93,,BN93,BV93,CD93,CL93)-CT93 | DP93: 0 | DQ93: =-CR93+DP93/10^6 | DR93: =SUM(E93,K93,Q93,W93,AE93,AM93,AV93,BD93,BL93,BU93,CC93,CK93)-CS93 | DS93: =SUM(D93,J93,P93,V93,AD93,AL93,AU93,BC93,,BN93,BV93,CD93,CL93)-CT93 | DU93: 0 | DV93: =DU93-CJ93 | DX93: =(CS93-CZ93)*10^6 | DY93: =(CT93-DC93)*10^6 | DZ93: =(CW93-DD93)*10^6
B94: AUTRES LOCATIONS ET CHARGES LO | C94: Opex88 | D94: 0.89 | E94: 0 | G94: 0.502188 | J94: 0.484 | K94: 0 | M94: 0 | P94: 0 | Q94: 0 | S94: 0.38 | V94: 0.184684 | W94: 0 | X94: 0 | AA94: 0.195 | AD94: 0 | AE94: 0 | AF94: 0 | AI94: 0.35 | AM94: 0 | CR94: =SUMIF($D$5:$CQ$5,CR$5,$D94:$CQ94) | CS94: =SUMIF($D$5:$CQ$5,CS$5,$D94:$CQ94) | CT94: =SUMIF($D$5:$CQ$5,CT$5,$D94:$CQ94)+SUMIF($D$5:$BI$5,CR$5,$D94:$BI94) | CU94: =+CR94-CS94 | CV94: =+CR94-CT94 | CW94: =SUMIF($D$5:$CQ$5,CW$5,$D94:$CQ94) | CX94: =IFERROR(CR94/CW94-1, "-") | CZ94: 0 | DA94: 1.374 | DD94: 5.540138 | DG94: =+DB94/DD94-1 | DH94: =+DC94/DD94-1 | DJ94: =SUM(D94,J94,P94,V94,AD94,AL94,AU94,BC94,BK94,BT94,CB94,CJ94)-CR94 | DK94: =SUM(E94,K94,Q94,W94,AE94,AM94,AV94,BD94,BL94,BU94,CC94,CK94)-CS94 | DL94: =SUM(G94,M94,S94,AA94,AI94,AR94,AZ94,BH94,BQ94,BY94,CG94,CO94)-CW94 | DM94: =SUM(D94,J94,P94,V94,AD94,AL94,AU94,BC94,,BN94,BV94,CD94,CL94)-CT94 | DP94: 2491688 | DQ94: =-CR94+DP94/10^6 | DR94: =SUM(E94,K94,Q94,W94,AE94,AM94,AV94,BD94,BL94,BU94,CC94,CK94)-CS94 | DS94: =SUM(D94,J94,P94,V94,AD94,AL94,AU94,BC94,,BN94,BV94,CD94,CL94)-CT94 | DU94: 1.28345 | DV94: =DU94-CJ94 | DX94: =(CS94-CZ94)*10^6 | DY94: =(CT94-DC94)*10^6 | DZ94: =(CW94-DD94)*10^6
B95: REMUNERATIONS TRANSITAIRES | C95: Opex89 | D95: 0 | G95: 0 | J95: 0 | M95: 0 | P95: 0 | S95: 0 | V95: 0 | AA95: 0 | AD95: 0 | AI95: 0 | CR95: =SUMIF($D$5:$CQ$5,CR$5,$D95:$CQ95) | CS95: =SUMIF($D$5:$CQ$5,CS$5,$D95:$CQ95) | CT95: =SUMIF($D$5:$CQ$5,CT$5,$D95:$CQ95)+SUMIF($D$5:$BI$5,CR$5,$D95:$BI95) | CU95: =+CR95-CS95 | CV95: =+CR95-CT95 | CW95: =SUMIF($D$5:$CQ$5,CW$5,$D95:$CQ95) | CX95: =IFERROR(CR95/CW95-1, "-") | CZ95: 0 | DA95: 0 | DD95: 0 | DJ95: =SUM(D95,J95,P95,V95,AD95,AL95,AU95,BC95,BK95,BT95,CB95,CJ95)-CR95 | DK95: =SUM(E95,K95,Q95,W95,AE95,AM95,AV95,BD95,BL95,BU95,CC95,CK95)-CS95 | DL95: =SUM(G95,M95,S95,AA95,AI95,AR95,AZ95,BH95,BQ95,BY95,CG95,CO95)-CW95 | DM95: =SUM(D95,J95,P95,V95,AD95,AL95,AU95,BC95,,BN95,BV95,CD95,CL95)-CT95 | DP95: 0 | DQ95: =-CR95+DP95/10^6 | DR95: =SUM(E95,K95,Q95,W95,AE95,AM95,AV95,BD95,BL95,BU95,CC95,CK95)-CS95 | DS95: =SUM(D95,J95,P95,V95,AD95,AL95,AU95,BC95,,BN95,BV95,CD95,CL95)-CT95 | DU95: 0 | DV95: =DU95-CJ95 | DX95: =(CS95-CZ95)*10^6 | DY95: =(CT95-DC95)*10^6 | DZ95: =(CW95-DD95)*10^6
B96: FRAIS DE DEBOURS ENLEVEMENT | C96: Opex90 | D96: 0 | E96: 0.25 | G96: 0 | J96: 0 | K96: 0.25 | M96: 0 | P96: 0 | Q96: 0.25 | S96: 0 | V96: 0 | W96: 0.25 | X96: 0.25 | AA96: 0 | AD96: 0 | AE96: 0.25 | AF96: 0.25 | AI96: 0 | AM96: 0.25 | CR96: =SUMIF($D$5:$CQ$5,CR$5,$D96:$CQ96) | CS96: =SUMIF($D$5:$CQ$5,CS$5,$D96:$CQ96) | CT96: =SUMIF($D$5:$CQ$5,CT$5,$D96:$CQ96)+SUMIF($D$5:$BI$5,CR$5,$D96:$BI96) | CU96: =+CR96-CS96 | CV96: =+CR96-CT96 | CW96: =SUMIF($D$5:$CQ$5,CW$5,$D96:$CQ96) | CX96: =IFERROR(CR96/CW96-1, "-") | CZ96: 3 | DA96: 2.25 | DD96: 0 | DJ96: =SUM(D96,J96,P96,V96,AD96,AL96,AU96,BC96,BK96,BT96,CB96,CJ96)-CR96 | DK96: =SUM(E96,K96,Q96,W96,AE96,AM96,AV96,BD96,BL96,BU96,CC96,CK96)-CS96 | DL96: =SUM(G96,M96,S96,AA96,AI96,AR96,AZ96,BH96,BQ96,BY96,CG96,CO96)-CW96 | DM96: =SUM(D96,J96,P96,V96,AD96,AL96,AU96,BC96,,BN96,BV96,CD96,CL96)-CT96 | DP96: 0 | DQ96: =-CR96+DP96/10^6 | DR96: =SUM(E96,K96,Q96,W96,AE96,AM96,AV96,BD96,BL96,BU96,CC96,CK96)-CS96 | DS96: =SUM(D96,J96,P96,V96,AD96,AL96,AU96,BC96,,BN96,BV96,CD96,CL96)-CT96 | DU96: 0 | DV96: =DU96-CJ96 | DX96: =(CS96-CZ96)*10^6 | DY96: =(CT96-DC96)*10^6 | DZ96: =(CW96-DD96)*10^6
B97: Fees du contrat GMNS | C97: Opex91 | D97: 129.42982 | E97: 129.42982 | F97: -2.77038e-07 | G97: 226.18464 | H97: -0.4277692 | J97: 129.42982 | K97: 129.42982 | L97: -2.77038e-07 | M97: 215.95959 | N97: -0.40067574 | P97: 129.42982 | Q97: 129.42982 | R97: -2.77038e-07 | S97: 215.95959 | T97: -0.40067574 | V97: 129.42982 | W97: 129.42982 | X97: 129.42982 | Y97: -2.77038e-07 | Z97: -2.77038e-07 | AA97: 215.95959 | AB97: -0.40067574 | AD97: 129.42982 | AE97: 129.42982 | AF97: 129.42982 | AG97: -2.77038e-07 | AH97: -2.77038e-07 | AI97: 215.95959 | AJ97: -0.40067574 | AL97: 129.42982 | AM97: 129.42982 | AN97: 0 | AO97: 0 | AP97: -2.7703749e-07 | AQ97: 129.42982 | AR97: 215.95959 | AS97: -0.40067574 | CR97: =SUMIF($D$5:$CQ$5,CR$5,$D97:$CQ97) | CS97: =SUMIF($D$5:$CQ$5,CS$5,$D97:$CQ97) | CT97: =SUMIF($D$5:$CQ$5,CT$5,$D97:$CQ97)+SUMIF($D$5:$BI$5,CR$5,$D97:$BI97) | CU97: =+CR97-CS97 | CV97: =+CR97-CT97 | CW97: =SUMIF($D$5:$CQ$5,CW$5,$D97:$CQ97) | CX97: =IFERROR(CR97/CW97-1, "-") | CZ97: 1623.1412 | DD97: 2250.0507 | DE97: =+CZ97/DD97-1 | DF97: =+DA97/DD97-1 | DG97: =+DB97/DD97-1 | DH97: =+DC97/DD97-1 | DJ97: =SUM(D97,J97,P97,V97,AD97,AL97,AU97,BC97,BK97,BT97,CB97,CJ97)-CR97 | DK97: =SUM(E97,K97,Q97,W97,AE97,AM97,AV97,BD97,BL97,BU97,CC97,CK97)-CS97 | DL97: =SUM(G97,M97,S97,AA97,AI97,AR97,AZ97,BH97,BQ97,BY97,CG97,CO97)-CW97 | DM97: =SUM(D97,J97,P97,V97,AD97,AL97,AU97,BC97,,BN97,BV97,CD97,CL97)-CT97 | DP97: =+DP98 | DQ97: =-CR97+DP97/10^6 | DR97: =SUM(E97,K97,Q97,W97,AE97,AM97,AV97,BD97,BL97,BU97,CC97,CK97)-CS97 | DS97: =SUM(D97,J97,P97,V97,AD97,AL97,AU97,BC97,,BN97,BV97,CD97,CL97)-CT97 | DU97: 157.63914 | DV97: =DU97-CJ97 | DX97: =(CS97-CZ97)*10^6 | DY97: =(CT97-DC97)*10^6 | DZ97: =(CW97-DD97)*10^6
B98: HONORAIRES CONSULTANTS (ERICSSON-GNMS) | C98: Opex92 | D98: 129.42982 | E98: 129.42982 | G98: 226.18464 | J98: 129.42982 | K98: 129.42982 | M98: 215.95959 | P98: 129.42982 | Q98: 129.42982 | S98: 215.95959 | V98: 129.42982 | W98: 129.42982 | X98: 129.42982 | AA98: 215.95959 | AD98: 129.42982 | AE98: 129.42982 | AF98: 129.42982 | AI98: 215.95959 | AL98: 129.42982 | AM98: 129.42982 | CR98: =SUMIF($D$5:$CQ$5,CR$5,$D98:$CQ98) | CS98: =SUMIF($D$5:$CQ$5,CS$5,$D98:$CQ98) | CT98: =SUMIF($D$5:$CQ$5,CT$5,$D98:$CQ98)+SUMIF($D$5:$BI$5,CR$5,$D98:$BI98) | CU98: =+CR98-CS98 | CV98: =+CR98-CT98 | CW98: =SUMIF($D$5:$CQ$5,CW$5,$D98:$CQ98) | CX98: =IFERROR(CR98/CW98-1, "-") | CZ98: 1623.1412 | DA98: 1623.1412 | DD98: 2250.0507 | DE98: =+CZ98/DD98-1 | DF98: =+DA98/DD98-1 | DG98: =+DB98/DD98-1 | DH98: =+DC98/DD98-1 | DJ98: =SUM(D98,J98,P98,V98,AD98,AL98,AU98,BC98,BK98,BT98,CB98,CJ98)-CR98 | DK98: =SUM(E98,K98,Q98,W98,AE98,AM98,AV98,BD98,BL98,BU98,CC98,CK98)-CS98 | DL98: =SUM(G98,M98,S98,AA98,AI98,AR98,AZ98,BH98,BQ98,BY98,CG98,CO98)-CW98 | DM98: =SUM(D98,J98,P98,V98,AD98,AL98,AU98,BC98,,BN98,BV98,CD98,CL98)-CT98 | DP98: 2092411608 | DQ98: =-CR98+DP98/10^6 | DR98: =SUM(E98,K98,Q98,W98,AE98,AM98,AV98,BD98,BL98,BU98,CC98,CK98)-CS98 | DS98: =SUM(D98,J98,P98,V98,AD98,AL98,AU98,BC98,,BN98,BV98,CD98,CL98)-CT98 | DU98: 157.63914 | DV98: =DU98-CJ98 | DX98: =(CS98-CZ98)*10^6 | DY98: =(CT98-DC98)*10^6 | DZ98: =(CW98-DD98)*10^6
B99: Fees du contrat IHS (spécifique à CDI) | C99: Opex93 | CR99: =SUMIF($D$5:$CQ$5,CR$5,$D99:$CQ99) | CS99: =SUMIF($D$5:$CQ$5,CS$5,$D99:$CQ99) | CT99: =SUMIF($D$5:$CQ$5,CT$5,$D99:$CQ99)+SUMIF($D$5:$BI$5,CR$5,$D99:$BI99) | CU99: =+CR99-CS99 | CV99: =+CR99-CT99 | CW99: =SUMIF($D$5:$CQ$5,CW$5,$D99:$CQ99) | CX99: =IFERROR(CR99/CW99-1, "-") | DF99: =+DA99/DD99-1 | DG99: =+DB99/DD99-1 | DJ99: =SUM(D99,J99,P99,V99,AD99,AL99,AU99,BC99,BK99,BT99,CB99,CJ99)-CR99 | DK99: =SUM(E99,K99,Q99,W99,AE99,AM99,AV99,BD99,BL99,BU99,CC99,CK99)-CS99 | DL99: =SUM(G99,M99,S99,AA99,AI99,AR99,AZ99,BH99,BQ99,BY99,CG99,CO99)-CW99 | DM99: =SUM(D99,J99,P99,V99,AD99,AL99,AU99,BC99,,BN99,BV99,CD99,CL99)-CT99 | DQ99: =-CR99+DP99/10^6 | DR99: =SUM(E99,K99,Q99,W99,AE99,AM99,AV99,BD99,BL99,BU99,CC99,CK99)-CS99 | DS99: =SUM(D99,J99,P99,V99,AD99,AL99,AU99,BC99,,BN99,BV99,CD99,CL99)-CT99 | DV99: =DU99-CJ99 | DX99: =(CS99-CZ99)*10^6 | DY99: =(CT99-DC99)*10^6 | DZ99: =(CW99-DD99)*10^6
B100: Matériel de transport (Entretien et locat°) | C100: Opex94 | D100: 5.794694 | E100: 9.0052297 | F100: -3.2105357 | G100: 6.796928 | H100: -0.14745397 | J100: 7.748399 | K100: 9.0052297 | L100: -1.2568307 | M100: 6.846612 | N100: 0.13171288 | P100: 5.68556 | Q100: 9.0052297 | R100: -3.3196697 | S100: 9.713052 | T100: -0.41464742 | V100: 8.077004 | W100: 9.0052297 | X100: 9.0052297 | Y100: -0.92822567 | Z100: -0.92822567 | AA100: 8.365007 | AB100: -0.034429499 | AD100: 10.43012 | AE100: 9.0052297 | AF100: 10 | AG100: 1.4248903 | AH100: 0.43012 | AI100: 12.603312 | AJ100: -0.17243023 | AL100: 6.690343 | AM100: 9.0052297 | AN100: 0 | AO100: 0 | AP100: -2.3148867 | AQ100: 6.690343 | AR100: 3.994372 | AS100: 0.67494239 | CR100: =SUMIF($D$5:$CQ$5,CR$5,$D100:$CQ100) | CS100: =SUMIF($D$5:$CQ$5,CS$5,$D100:$CQ100) | CT100: =SUMIF($D$5:$CQ$5,CT$5,$D100:$CQ100)+SUMIF($D$5:$BI$5,CR$5,$D100:$BI100) | CU100: =+CR100-CS100 | CV100: =+CR100-CT100 | CW100: =SUMIF($D$5:$CQ$5,CW$5,$D100:$CQ100) | CX100: =IFERROR(CR100/CW100-1, "-") | CZ100: 108 | DD100: 94.586567 | DE100: =+CZ100/DD100-1 | DF100: =+DA100/DD100-1 | DG100: =+DB100/DD100-1 | DH100: =+DC100/DD100-1 | DJ100: =SUM(D100,J100,P100,V100,AD100,AL100,AU100,BC100,BK100,BT100,CB100,CJ100)-CR100 | DK100: =SUM(E100,K100,Q100,W100,AE100,AM100,AV100,BD100,BL100,BU100,CC100,CK100)-CS100 | DL100: =SUM(G100,M100,S100,AA100,AI100,AR100,AZ100,BH100,BQ100,BY100,CG100,CO100)-CW100 | DM100: =SUM(D100,J100,P100,V100,AD100,AL100,AU100,BC100,,BN100,BV100,CD100,CL100)-CT100 | DP100: =SUM(DP101:DP105) | DQ100: =-CR100+DP100/10^6 | DR100: =SUM(E100,K100,Q100,W100,AE100,AM100,AV100,BD100,BL100,BU100,CC100,CK100)-CS100 | DS100: =SUM(D100,J100,P100,V100,AD100,AL100,AU100,BC100,,BN100,BV100,CD100,CL100)-CT100 | DU100: 25.859749 | DV100: =DU100-CJ100 | DX100: =(CS100-CZ100)*10^6 | DY100: =(CT100-DC100)*10^6 | DZ100: =(CW100-DD100)*10^6
...

Sheet CA Mobile
P1: =#REF! | Y1: =Y8/W8 | Z1: =Z8/X8 | AU1: 0 | AV1: 0 | DJ1: 0
A2: CA Mobile | J2: 0 | P2: 8366.7791 | Q2: =P2+P179+P177+P171+P149+P144+P143+P53-P118-P126 | R2: =+P8-Q2 | W2: 0 | AD2: 0 | AG2: =AD8/AF8-1 | BC2: 0 | CK2: 0 | DC2: 0
E3: 0 | CZ3: 0 | DD3: 0
D4: 45658 | J4: 45689 | P4: 45717 | V4: 45748 | AD4: 45778 | AL4: 45809 | AU4: 45839 | BC4: 45870 | BK4: 45901 | BT4: 45931 | CB4: 45962 | CJ4: 45992 | CR4: CUMUL | DB4: ANNUEL
B5: (En Millions ML) | D5: 2025 Réel | E5: 2025 Budget | F5: Ecart / Budget | G5: 2024 Réel | H5: Evol % | J5: 2025 Réel | K5: 2025 Budget | L5: Ecart / Budget | M5: 2024 Réel | N5: Evol % | P5: 2025 Réel | Q5: 2025 Budget | R5: Ecart / Budget | S5: 2024 Réel | T5: Evol % | V5: 2025 Réel | W5: 2025 Budget | X5: 2025 Actu1 | Y5: Ecart / Budget | Z5: Ecart / Actu1 | AA5: 2024 Réel | AB5: Evol % | AD5: 2025 Réel | AE5: 2025 Budget | AF5: 2025 Actu1 | AG5: Ecart / Budget | AH5: Ecart / Actu1 | AI5: 2024 Réel | AJ5: Evol % | AL5: 2025 Réel | AM5: 2025 Budget | AN5: 2025 Actu1 | AO5: 2025 Actu2 | AP5: Ecart / Budget | AQ5: Ecart / Actu1 | AR5: 2024 Réel | AS5: Evol % | AU5: 2025 Réel | AV5: 2025 Budget | AW5: 2025 Actu2 | AX5: Ecart / Budget | AY5: Ecart / Actu2 | AZ5: 2024 Réel | BA5: Evol % | BC5: 2025 Réel | BD5: 2025 Budget | BE5: 2025 Actu2 | BF5: Ecart / Budget | BG5: Ecart / Actu2 | BH5: 2024 Réel | BI5: Evol % | BK5: 2025 Réel | BL5: 2025 Budget | BM5: 2025 Actu2 | BN5: 2025 Actu3 | BO5: Ecart / Budget | BP5: Ecart / Actu2 | BQ5: 2024 Réel | BR5: Evol % | BT5: 2025 Réel | BU5: 2025 Budget | BV5: 2025 Actu3 | BW5: Ecart / Budget | BX5: Ecart / Actu3 | BY5: 2024 Réel | BZ5: Evol % | CB5: 2025 Réel | CC5: 2025 Budget | CD5: 2025 Actu3 | CE5: Ecart / Budget | CF5: Ecart / Actu3 | CG5: 2024 Réel | CH5: Evol % | CJ5: 2025 Réel | CK5: 2025 Budget | CL5: 2025 Actu3 | CM5: Ecart / Budget | CN5: Ecart / Actu3 | CO5: 2024 Réel | CP5: Evol % | CR5: 2025 Réel | CS5: 2025 Budget | CT5: 2025 Actu3 | CU5: Ecart / Budget | CV5: Ecart / Actu3 | CW5: 2024 Réel | CX5: Evol % | CZ5: 2025 Budget | DA5: 2025 Actu1 | DB5: 2025 Actu2 | DC5: 2025 Actu3 | DD5: 2024 Réel | DE5: Bud / 2024 (%) | DF5: Actu 1 / 2024 (%) | DG5: Actu 2 / 2024 (%) | DH5: Actu3 / 2024 (%)
A8: CA Global | C8: CA1 | D8: 8324.9028 | E8: 9527.0891 | F8: -1202.1863 | G8: 9480.8077 | H8: -0.12192051 | J8: 7599.911 | K8: 8782.1227 | L8: -1182.2117 | M8: 9059.8608 | N8: -0.16114484 | P8: 7943.4924 | Q8: 9473.1389 | R8: -1529.6465 | S8: 9959.7273 | T8: -0.20243877 | V8: 8080.2292 | W8: 9362.5379 | X8: 7876.1248 | Y8: -1282.3087 | Z8: 204.10442 | AA8: 9279.8977 | AB8: -0.12927605 | AD8: 7954.7423 | AE8: 9772.4636 | AF8: 8199.6147 | AG8: -1817.7213 | AH8: -244.87237 | AI8: 9134.1999 | AJ8: -0.12912544 | AL8: 6462.0625 | AM8: 9466.6859 | AN8: 8095.1472 | AO8: 0 | AP8: -3004.6234 | AQ8: -1633.0847 | AR8: 8946.7558 | AS8: -0.27772004 | CR8: 46365.34 | CS8: 56384.038 | CU8: -10018.698 | CV8: =+CR8-CT8 | CW8: 46914.494 | CX8: =IFERROR(CR8/CW8-1, "-") | CZ8: 114333.76 | DA8: 100883.84 | DD8: 106192.13 | DE8: =(CZ8-DD8)/DD8 | DF8: =(DA8-DD8)/DD8 | DG8: =(DB8-DD8)/DD8 | DH8: =(DC8-DD8)/DD8 | DM8: =CS8-CZ8 | DN8: =CT8-DC8 | DO8: =CW8-DD8
C9: CA2 | CV9: =+CR9-CT9 | CX9: =IFERROR(CR9/CW9-1, "-") | DM9: =(CS9-CZ9)*10^6 | DN9: =(CT9-DC9)*10^6 | DO9: =(CW9-DD9)*10^6
B10: dont CA Etat | C10: CA3 | CV10: =+CR10-CT10 | CX10: =IFERROR(CR10/CW10-1, "-") | DM10: =(CS10-CZ10)*10^6 | DN10: =(CT10-DC10)*10^6 | DO10: =(CW10-DD10)*10^6
C11: CA4 | CV11: =+CR11-CT11 | CX11: =IFERROR(CR11/CW11-1, "-") | DM11: =(CS11-CZ11)*10^6 | DN11: =(CT11-DC11)*10^6 | DO11: =(CW11-DD11)*10^6
A12: CA services Mobile | C12: CA5 | D12: 8118.3484 | E12: 9340.117 | F12: -1221.7686 | G12: 9400.2691 | H12: -0.13637063 | J12: 7438.6636 | K12: 8595.1506 | L12: -1156.487 | M12: 8867.9127 | N12: -0.16117085 | P12: 7825.4018 | Q12: 9286.1669 | R12: -1460.7651 | S12: 9820.3346 | T12: -0.20314306 | V12: 7896.8451 | W12: 9175.5659 | X12: 7690.1527 | Y12: -1278.7208 | Z12: 206.69236 | AA12: 9164.5804 | AB12: -0.13832988 | AD12: 7818.4162 | AE12: 9585.4915 | AF12: 8013.6426 | AG12: -1767.0753 | AH12: -195.22638 | AI12: 9068.304 | AJ12: -0.13783038 | AL12: 6387.4823 | AM12: 9278.7138 | AN12: 7909.1751 | AO12: 0 | AP12: -2891.2316 | AQ12: -1521.6929 | AR12: 8721.8972 | AS12: -0.2676499 | CR12: 45485.157 | CS12: 55261.206 | CU12: -9776.0483 | CV12: =+CR12-CT12 | CW12: 46321.401 | CX12: =IFERROR(CR12/CW12-1, "-") | CZ12: 112087.1 | DA12: 98724.199 | DD12: 104134.76 | DE12: =(CZ12-DD12)/DD12 | DF12: =(DA12-DD12)/DD12 | DG12: =(DB12-DD12)/DD12 | DH12: =(DC12-DD12)/DD12 | DM12: =(CS12-CZ12)*10^6 | DN12: =(CT12-DC12)*10^6 | DO12: =(CW12-DD12)*10^6
C13: CA6 | CV13: =+CR13-CT13 | CX13: =IFERROR(CR13/CW13-1, "-") | DM13: =(CS13-CZ13)*10^6 | DN13: =(CT13-DC13)*10^6 | DO13: =(CW13-DD13)*10^6
A14: CA récurrent | C14: CA7 | D14: 7983.1451 | E14: 9190.3209 | F14: -1207.1757 | G14: 9314.5768 | H14: -0.14294065 | J14: 7200.8417 | K14: 8457.9278 | L14: -1257.0861 | M14: 8778.6239 | N14: -0.17973002 | P14: 7648.4886 | Q14: 9131.6851 | R14: -1483.1965 | S14: 9712.3829 | T14: -0.21250133 | V14: 7537.1699 | W14: 9023.3403 | X14: 7518.8968 | Y14: -1486.1704 | Z14: 18.273027 | AA14: 9074.5251 | AB14: -0.1694144 | AD14: 7326.8856 | AE14: 9425.3998 | AF14: 7842.3867 | AG14: -2098.5142 | AH14: -515.50111 | AI14: 8971.4869 | AJ14: -0.18331424 | AL14: 5632.0669 | AM14: 9120.928 | AN14: 7737.9193 | AO14: 0 | AP14: -3488.8611 | AQ14: -2105.8524 | AR14: 8557.2947 | AS14: -0.34184026 | CR14: 43328.598 | CS14: 54349.602 | CU14: -11021.004 | CV14: =+CR14-CT14 | CW14: 45851.596 | CX14: =IFERROR(CR14/CW14-1, "-") | CZ14: 110140.98 | DA14: 96632.957 | DD14: 102631.64 | DE14: =(CZ14-DD14)/DD14 | DF14: =(DA14-DD14)/DD14 | DG14: =(DB14-DD14)/DD14 | DH14: =(DC14-DD14)/DD14 | DM14: =(CS14-CZ14)*10^6 | DN14: =(CT14-DC14)*10^6 | DO14: =(CW14-DD14)*10^6
C15: CA8 | CV15: =+CR15-CT15 | CX15: =IFERROR(CR15/CW15-1, "-") | DM15: =(CS15-CZ15)*10^6 | DN15: =(CT15-DC15)*10^6 | DO15: =(CW15-DD15)*10^6
A16: CA sortant | C16: CA9 | D16: 7739.2918 | E16: 8900.1169 | F16: -1160.8251 | G16: 9000.8894 | H16: -0.14016366 | J16: 6969.1497 | K16: 8185.5921 | L16: -1216.4424 | M16: 8473.1298 | N16: -0.17749994 | P16: 7409.3042 | Q16: 8857.764 | R16: -1448.4599 | S16: 9387.3301 | T16: -0.2107123 | V16: 7303.1048 | W16: 8752.973 | X16: 7274.1549 | Y16: -1449.8682 | Z16: 28.949903 | AA16: 8777.6654 | AB16: -0.16799007 | AD16: 7054.7165 | AE16: 9168.8618 | AF16: 7596.4969 | AG16: -2114.1453 | AH16: -541.78048 | AI16: 8690.3808 | AJ16: -0.18821549 | AL16: 5377.5664 | AM16: 8852.6956 | AN16: 7495.2257 | AO16: 0 | AP16: -3475.1292 | AQ16: -2117.6593 | AR16: 8254.7094 | AS16: -0.34854564 | CR16: 41853.133 | CS16: 52718.003 | CU16: -10864.87 | CV16: =+CR16-CT16 | CW16: 44329.395 | CX16: =IFERROR(CR16/CW16-1, "-") | CZ16: 106924.27 | DA16: 93694.611 | DD16: 99048.001 | DE16: =(CZ16-DD16)/DD16 | DF16: =(DA16-DD16)/DD16 | DG16: =(DB16-DD16)/DD16 | DH16: =(DC16-DD16)/DD16 | DM16: =(CS16-CZ16)*10^6 | DN16: =(CT16-DC16)*10^6 | DO16: =(CW16-DD16)*10^6
B17: Prépayé (yc commissions) | C17: CA10 | D17: 3180.332 | E17: 3844.6975 | F17: -664.36549 | G17: 4134.0606 | H17: -0.23070019 | J17: 2693.6338 | K17: 3485.7674 | L17: -792.13362 | M17: 3898.7071 | N17: -0.30909563 | P17: 2822.2165 | Q17: 3661.4635 | R17: -839.24697 | S17: 4254.9464 | T17: -0.33672103 | V17: 2814.4171 | W17: 3589.6058 | X17: 2755.4518 | Y17: -775.18872 | Z17: 58.965308 | AA17: 3646.6263 | AB17: -0.22821346 | AD17: 2543.8055 | AE17: 3709.6789 | AF17: 2900.5635 | AG17: -1165.8734 | AH17: -356.75798 | AI17: 3632.2773 | AJ17: -0.29966647 | AL17: 2328.3631 | AM17: 3487.2954 | AN17: 2876.8076 | AO17: 0 | AP17: -1158.9323 | AQ17: -548.44449 | AR17: 3512.5074 | AS17: -0.33712223 | CR17: 16382.768 | CS17: 21778.509 | CU17: -5395.7405 | CV17: =+CR17-CT17 | CW17: 19566.618 | CX17: =IFERROR(CR17/CW17-1, "-") | CZ17: 41713.594 | DA17: 36911.416 | DD17: 40845.142 | DE17: =(CZ17-DD17)/DD17 | DF17: =(DA17-DD17)/DD17 | DG17: =(DB17-DD17)/DD17 | DH17: =(DC17-DD17)/DD17 | DM17: =(CS17-CZ17)*10^6 | DN17: =(CT17-DC17)*10^6 | DO17: =(CW17-DD17)*10^6
A18: Consumer Prepaid | C18: CA11 | D18: 3180.332 | E18: 3844.6975 | G18: 4134.0606 | J18: 2693.6338 | K18: 3485.7674 | M18: 3898.7071 | P18: 2822.2165 | Q18: 3661.4635 | S18: 4254.9464 | V18: 2814.4171 | W18: 3589.6058 | X18: 2755.4518 | AA18: 3646.6263 | AD18: 2543.8055 | AE18: 3709.6789 | AF18: 2900.5635 | AI18: 3632.2773 | AL18: 2328.3631 | CR18: =+SUMIF($D$5:$CQ$5,CR$5,$D18:$CQ18) | CS18: =+SUMIF($D$5:$CQ$5,CS$5,$D18:$CQ18) | CT18: =SUMIF($D$5:$CQ$5,CT$5,$D18:$CQ18)+SUMIF($D$5:$BI$5,CR$5,$D18:$BI18) | CU18: =+CR18-CS18 | CV18: =+CR18-CT18 | CW18: =+SUMIF($D$5:$CQ$5,CW$5,$D18:$CQ18) | CX18: =+CR18/CW18-1 | CZ18: 41713.594 | DA18: 36911.416 | DD18: 40845.142 | DE18: =(CZ18-DD18)/DD18 | DF18: =(DA18-DD18)/DD18 | DG18: =(DB18-DD18)/DD18 | DH18: =(DC18-DD18)/DD18 | DM18: =(CS18-CZ18)*10^6 | DN18: =(CT18-DC18)*10^6 | DO18: =(CW18-DD18)*10^6
B19: Frais d'activation & Sim swap | C19: CA12 | D19: -9.204763 | E19: -22.461806 | G19: -34.062214 | J19: -10.193765 | K19: -22.461806 | M19: -16.284725 | P19: -19.075374 | Q19: -22.461806 | S19: 23.0374 | V19: -7.311322 | W19: -22.461806 | X19: -14.634569 | AA19: 49.439702 | AD19: -9.738512 | AE19: -22.461806 | AF19: -14.634569 | AI19: -29.696997 | AL19: -15.659001 | AM19: -22.461806 | AN19: -14.634569 | CR19: =+SUMIF($D$5:$CQ$5,CR$5,$D19:$CQ19) | CS19: =+SUMIF($D$5:$CQ$5,CS$5,$D19:$CQ19) | CT19: =SUMIF($D$5:$CQ$5,CT$5,$D19:$CQ19)+SUMIF($D$5:$BI$5,CR$5,$D19:$BI19) | CU19: =+CR19-CS19 | CV19: =+CR19-CT19 | CW19: =+SUMIF($D$5:$CQ$5,CW$5,$D19:$CQ19) | CX19: =+CR19/CW19-1 | CZ19: -269.54168 | DA19: -170.18503 | DD19: -102.58321 | DE19: =(CZ19-DD19)/DD19 | DF19: =(DA19-DD19)/DD19 | DG19: =(DB19-DD19)/DD19 | DH19: =(DC19-DD19)/DD19 | DM19: =(CS19-CZ19)*10^6 | DN19: =(CT19-DC19)*10^6 | DO19: =(CW19-DD19)*10^6
B20: Sortant voix on net | C20: CA13 | D20: 1325.2425 | E20: 1532.0023 | G20: 1925.9137 | J20: 1129.2483 | K20: 1445.4383 | M20: 1831.4185 | P20: 1071.5605 | Q20: 1509.9634 | S20: 1922.7645 | V20: 1194.1612 | W20: 1477.3446 | X20: 1054.0572 | AA20: 1650.8071 | AD20: 966.00702 | AE20: 1510.8206 | AF20: 1101.4406 | AI20: 1664.9536 | AL20: 817.71835 | AM20: 1404.6592 | AN20: 1052.9247 | CR20: =+SUMIF($D$5:$CQ$5,CR$5,$D20:$CQ20) | CS20: =+SUMIF($D$5:$CQ$5,CS$5,$D20:$CQ20) | CT20: =SUMIF($D$5:$CQ$5,CT$5,$D20:$CQ20)+SUMIF($D$5:$BI$5,CR$5,$D20:$BI20) | CU20: =+CR20-CS20 | CV20: =+CR20-CT20 | CW20: =+SUMIF($D$5:$CQ$5,CW$5,$D20:$CQ20) | CX20: =+CR20/CW20-1 | CZ20: 16414.425 | DA20: 14049.539 | DD20: 18153.923 | DE20: =(CZ20-DD20)/DD20 | DF20: =(DA20-DD20)/DD20 | DG20: =(DB20-DD20)/DD20 | DH20: =(DC20-DD20)/DD20 | DM20: =(CS20-CZ20)*10^6 | DN20: =(CT20-DC20)*10^6 | DO20: =(CW20-DD20)*10^6
B21: Sortant voix MTN | C21: CA14 | D21: 1093.7671 | E21: 1964.2889 | G21: 1821.5085 | J21: 891.33484 | K21: 1734.4496 | M21: 1675.7918 | P21: 946.80505 | Q21: 1811.1466 | S21: 1893.3833 | V21: 991.00515 | W21: 1795.8073 | X21: 1024.3719 | AA21: 1473.71 | AD21: 904.7114 | AE21: 1879.0664 | AF21: 1094.9453 | AI21: 1604.8697 | AL21: 745.07268 | AM21: 1773.9869 | AN21: 1112.2691 | CR21: =+SUMIF($D$5:$CQ$5,CR$5,$D21:$CQ21) | CS21: =+SUMIF($D$5:$CQ$5,CS$5,$D21:$CQ21) | CT21: =SUMIF($D$5:$CQ$5,CT$5,$D21:$CQ21)+SUMIF($D$5:$BI$5,CR$5,$D21:$BI21) | CU21: =+CR21-CS21 | CV21: =+CR21-CT21 | CW21: =+SUMIF($D$5:$CQ$5,CW$5,$D21:$CQ21) | CX21: =+CR21/CW21-1 | CZ21: 21498.145 | DA21: 13781.095 | DD21: 18164.669 | DE21: =(CZ21-DD21)/DD21 | DF21: =(DA21-DD21)/DD21 | DG21: =(DB21-DD21)/DD21 | DH21: =(DC21-DD21)/DD21 | DM21: =(CS21-CZ21)*10^6 | DN21: =(CT21-DC21)*10^6 | DO21: =(CW21-DD21)*10^6
B22: Sortant voix GLO | C22: CA15 | D22: 0 | E22: 0 | G22: 0 | J22: 0 | K22: 0 | M22: 0 | P22: 0 | Q22: 0 | S22: 0 | V22: 0 | W22: 0 | X22: 0 | AA22: 0 | AD22: 0.021132 | AE22: 0 | AF22: 0 | AI22: 0 | AL22: 0 | CR22: =+SUMIF($D$5:$CQ$5,CR$5,$D22:$CQ22) | CS22: =+SUMIF($D$5:$CQ$5,CS$5,$D22:$CQ22) | CT22: =SUMIF($D$5:$CQ$5,CT$5,$D22:$CQ22)+SUMIF($D$5:$BI$5,CR$5,$D22:$BI22) | CU22: =+CR22-CS22 | CV22: =+CR22-CT22 | CW22: =+SUMIF($D$5:$CQ$5,CW$5,$D22:$CQ22) | CZ22: 0 | DA22: 0 | DD22: 0 | DM22: =(CS22-CZ22)*10^6 | DN22: =(CT22-DC22)*10^6 | DO22: =(CW22-DD22)*10^6
B23: Sortant voix BBCOM | C23: CA16 | D23: 0 | E23: 0 | G23: 0 | J23: 0 | K23: 0 | M23: 0 | P23: 0 | Q23: 0 | S23: 0 | V23: 0 | W23: 0 | X23: 0 | AA23: 0 | AD23: 0 | AE23: 0 | AF23: 0 | AI23: 0 | AL23: 0 | CR23: =+SUMIF($D$5:$CQ$5,CR$5,$D23:$CQ23) | CS23: =+SUMIF($D$5:$CQ$5,CS$5,$D23:$CQ23) | CT23: =SUMIF($D$5:$CQ$5,CT$5,$D23:$CQ23)+SUMIF($D$5:$BI$5,CR$5,$D23:$BI23) | CU23: =+CR23-CS23 | CV23: =+CR23-CT23 | CW23: =+SUMIF($D$5:$CQ$5,CW$5,$D23:$CQ23) | CZ23: 0 | DA23: 0 | DD23: 0 | DM23: =(CS23-CZ23)*10^6 | DN23: =(CT23-DC23)*10^6 | DO23: =(CW23-DD23)*10^6
B24: Sortant voix LIBERCOM | C24: CA17 | D24: 0 | E24: 134.85752 | G24: 0 | J24: 0 | K24: 119.07238 | M24: 0 | P24: 0 | Q24: 124.38783 | S24: 0 | V24: 0 | W24: 123.28637 | X24: 76.46994 | AA24: 0 | AD24: 0 | AE24: 129.00452 | AF24: 81.738279 | AI24: 0 | AL24: 0 | AM24: 121.83573 | AN24: 83.031514 | CR24: =+SUMIF($D$5:$CQ$5,CR$5,$D24:$CQ24) | CS24: =+SUMIF($D$5:$CQ$5,CS$5,$D24:$CQ24) | CT24: =SUMIF($D$5:$CQ$5,CT$5,$D24:$CQ24)+SUMIF($D$5:$BI$5,CR$5,$D24:$BI24) | CU24: =+CR24-CS24 | CV24: =+CR24-CT24 | CW24: =+SUMIF($D$5:$CQ$5,CW$5,$D24:$CQ24) | CZ24: 1476.2803 | DA24: 809.89796 | DD24: 113.55521 | DM24: =(CS24-CZ24)*10^6 | DN24: =(CT24-DC24)*10^6 | DO24: =(CW24-DD24)*10^6
B25: Sortant voix BTSA | C25: CA18 | D25: 477.33819 | E25: 0.26963616 | G25: 72.348988 | J25: 443.00542 | K25: 0.23807511 | M25: 74.761174 | P25: 542.00244 | Q25: 0.2487029 | S25: 85.784432 | V25: 414.46736 | W25: 0.24650062 | X25: 364.99333 | AA25: 95.492603 | AD25: 455.74639 | AE25: 0.25793359 | AF25: 390.13927 | AI25: 98.01419 | AL25: 577.81528 | AM25: 0.2436002 | AN25: 396.31192 | CR25: =+SUMIF($D$5:$CQ$5,CR$5,$D25:$CQ25) | CS25: =+SUMIF($D$5:$CQ$5,CS$5,$D25:$CQ25) | CT25: =SUMIF($D$5:$CQ$5,CT$5,$D25:$CQ25)+SUMIF($D$5:$BI$5,CR$5,$D25:$BI25) | CU25: =+CR25-CS25 | CV25: =+CR25-CT25 | CW25: =+SUMIF($D$5:$CQ$5,CW$5,$D25:$CQ25) | CX25: =+CR25/CW25-1 | CZ25: 2.951697 | DA25: 5328.0134 | DD25: 1167.615 | DE25: =(CZ25-DD25)/DD25 | DF25: =(DA25-DD25)/DD25 | DG25: =(DB25-DD25)/DD25 | DH25: =(DC25-DD25)/DD25 | DM25: =(CS25-CZ25)*10^6 | DN25: =(CT25-DC25)*10^6 | DO25: =(CW25-DD25)*10^6
B26: Sortant voix INTERNATIONAL | C26: CA19 | D26: 159.65992 | E26: 134.97915 | G26: 206.80959 | J26: 139.88452 | K26: 111.99366 | M26: 191.51705 | P26: 181.13024 | Q26: 130.13844 | S26: 185.64906 | V26: 113.36488 | W26: 106.77848 | X26: 148.89 | AA26: 203.71291 | AD26: 124.37249 | AE26: 97.116671 | AF26: 142.56192 | AI26: 175.29465 | AL26: 116.14583 | AM26: 92.696709 | AN26: 143.5862 | CR26: =+SUMIF($D$5:$CQ$5,CR$5,$D26:$CQ26) | CS26: =+SUMIF($D$5:$CQ$5,CS$5,$D26:$CQ26) | CT26: =SUMIF($D$5:$CQ$5,CT$5,$D26:$CQ26)+SUMIF($D$5:$BI$5,CR$5,$D26:$BI26) | CU26: =+CR26-CS26 | CV26: =+CR26-CT26 | CW26: =+SUMIF($D$5:$CQ$5,CW$5,$D26:$CQ26) | CX26: =+CR26/CW26-1 | CZ26: 1148.1447 | DA26: 1814.7776 | DD26: 1908.7331 | DE26: =(CZ26-DD26)/DD26 | DF26: =(DA26-DD26)/DD26 | DG26: =(DB26-DD26)/DD26 | DH26: =(DC26-DD26)/DD26 | DM26: =(CS26-CZ26)*10^6 | DN26: =(CT26-DC26)*10^6 | DO26: =(CW26-DD26)*10^6
B27: Sortant voix roaming | C27: CA20 | D27: 10.56786 | E27: 16.595851 | G27: 12.72778 | J27: 10.085312 | K27: 14.877293 | M27: 13.135162 | P27: 13.910103 | Q27: 16.190098 | S27: 15.075004 | V27: 7.596249 | W27: 15.999767 | X27: 13.929471 | AA27: 6.984574 | AD27: 12.878297 | AE27: 16.570214 | AF27: 14.109394 | AI27: 10.504886 | AL27: 14.234937 | AM27: 16.040831 | AN27: 13.66839 | CR27: =+SUMIF($D$5:$CQ$5,CR$5,$D27:$CQ27) | CS27: =+SUMIF($D$5:$CQ$5,CS$5,$D27:$CQ27) | CT27: =SUMIF($D$5:$CQ$5,CT$5,$D27:$CQ27)+SUMIF($D$5:$BI$5,CR$5,$D27:$BI27) | CU27: =+CR27-CS27 | CV27: =+CR27-CT27 | CW27: =+SUMIF($D$5:$CQ$5,CW$5,$D27:$CQ27) | CX27: =+CR27/CW27-1 | CZ27: 196.53325 | DA27: 163.23462 | DD27: 136.8012 | DE27: =(CZ27-DD27)/DD27 | DF27: =(DA27-DD27)/DD27 | DG27: =(DB27-DD27)/DD27 | DH27: =(DC27-DD27)/DD27 | DM27: =(CS27-CZ27)*10^6 | DN27: =(CT27-DC27)*10^6 | DO27: =(CW27-DD27)*10^6
B28: Total VOIX Sortant | C28: CA21 | D28: 3066.5755 | E28: 3782.9934 | G28: 4039.3085 | J28: 2613.5584 | K28: 3426.0693 | M28: 3786.6237 | P28: 2755.4084 | Q28: 3592.075 | S28: 4102.6563 | V28: 2720.5948 | W28: 3519.4631 | X28: 2682.7119 | AA28: 3430.7072 | AD28: 2463.7367 | AE28: 3632.8363 | AF28: 2824.9348 | AI28: 3553.6371 | AL28: 2270.9871 | AM28: 3409.4629 | AN28: 2801.7918 | CR28: =+SUMIF($D$5:$CQ$5,CR$5,$D28:$CQ28) | CS28: =+SUMIF($D$5:$CQ$5,CS$5,$D28:$CQ28) | CT28: =SUMIF($D$5:$CQ$5,CT$5,$D28:$CQ28)+SUMIF($D$5:$BI$5,CR$5,$D28:$BI28) | CU28: =+CR28-CS28 | CV28: =+CR28-CT28 | CW28: =+SUMIF($D$5:$CQ$5,CW$5,$D28:$CQ28) | CX28: =+CR28/CW28-1 | CZ28: 40736.48 | DA28: 35946.558 | DD28: 39645.297 | DE28: =(CZ28-DD28)/DD28 | DF28: =(DA28-DD28)/DD28 | DG28: =(DB28-DD28)/DD28 | DH28: =(DC28-DD28)/DD28 | DM28: =(CS28-CZ28)*10^6 | DN28: =(CT28-DC28)*10^6 | DO28: =(CW28-DD28)*10^6
C29: CA22 | CR29: =+SUMIF($D$5:$CQ$5,CR$5,$D29:$CQ29) | CS29: =+SUMIF($D$5:$CQ$5,CS$5,$D29:$CQ29) | CT29: =SUMIF($D$5:$CQ$5,CT$5,$D29:$CQ29)+SUMIF($D$5:$BI$5,CR$5,$D29:$BI29) | CU29: =+CR29-CS29 | CV29: =+CR29-CT29 | CW29: =+SUMIF($D$5:$CQ$5,CW$5,$D29:$CQ29) | DM29: =(CS29-CZ29)*10^6 | DN29: =(CT29-DC29)*10^6 | DO29: =(CW29-DD29)*10^6
B30: Sortant sms on net | C30: CA23 | D30: 1.236479 | E30: 1.2104351 | G30: 1.899627 | J30: 1.069845 | K30: 1.0398187 | M30: 1.969119 | P30: 1.14373 | Q30: 1.1670257 | S30: 1.791167 | V30: 6.743099 | W30: 1.0669521 | X30: 1.1278842 | AA30: 2.082762 | AD30: 0.975179 | AE30: 1.0504499 | AF30: 1.1173901 | AI30: 1.77121 | AL30: 0.905922 | AM30: 1.0113768 | AN30: 1.0752968 | CR30: =+SUMIF($D$5:$CQ$5,CR$5,$D30:$CQ30) | CS30: =+SUMIF($D$5:$CQ$5,CS$5,$D30:$CQ30) | CT30: =SUMIF($D$5:$CQ$5,CT$5,$D30:$CQ30)+SUMIF($D$5:$BI$5,CR$5,$D30:$BI30) | CU30: =+CR30-CS30 | CV30: =+CR30-CT30 | CW30: =+SUMIF($D$5:$CQ$5,CW$5,$D30:$CQ30) | CX30: =+CR30/CW30-1 | CZ30: 11.855596 | DA30: 12.37972 | DD30: 31.01325 | DE30: =(CZ30-DD30)/DD30 | DF30: =(DA30-DD30)/DD30 | DG30: =(DB30-DD30)/DD30 | DH30: =(DC30-DD30)/DD30 | DM30: =(CS30-CZ30)*10^6 | DN30: =(CT30-DC30)*10^6 | DO30: =(CW30-DD30)*10^6
B31: Sortant sms MTN | C31: CA24 | D31: 1.231451 | E31: 1.3495968 | G31: 1.765875 | J31: 1.131735 | K31: 1.1374519 | M31: 1.712154 | P31: 1.980375 | Q31: 1.3023064 | S31: 1.648988 | V31: 0.393717 | W31: 1.1885618 | X31: 0.17232822 | AA31: 1.774768 | AD31: 1.14641 | AE31: 1.1962148 | AF31: 0.18238891 | AI31: 1.705125 | AL31: 0.953639 | AM31: 1.2040726 | AN31: 0.17970464 | CR31: =+SUMIF($D$5:$CQ$5,CR$5,$D31:$CQ31) | CS31: =+SUMIF($D$5:$CQ$5,CS$5,$D31:$CQ31) | CT31: =SUMIF($D$5:$CQ$5,CT$5,$D31:$CQ31)+SUMIF($D$5:$BI$5,CR$5,$D31:$BI31) | CU31: =+CR31-CS31 | CV31: =+CR31-CT31 | CW31: =+SUMIF($D$5:$CQ$5,CW$5,$D31:$CQ31) | CX31: =+CR31/CW31-1 | CZ31: 13.739963 | DA31: 5.8286992 | DD31: 20.29824 | DE31: =(CZ31-DD31)/DD31 | DF31: =(DA31-DD31)/DD31 | DG31: =(DB31-DD31)/DD31 | DH31: =(DC31-DD31)/DD31 | DM31: =(CS31-CZ31)*10^6 | DN31: =(CT31-DC31)*10^6 | DO31: =(CW31-DD31)*10^6
B32: Sortant sms GLO | C32: CA25 | D32: 0 | E32: 0 | G32: 0 | J32: 0 | K32: 0 | M32: 0 | P32: 0 | Q32: 0 | S32: 0 | V32: 0 | W32: 0 | X32: 0 | AA32: 0 | AD32: 0 | AE32: 0 | AF32: 0 | AI32: 0 | AL32: 0 | CR32: =+SUMIF($D$5:$CQ$5,CR$5,$D32:$CQ32) | CS32: =+SUMIF($D$5:$CQ$5,CS$5,$D32:$CQ32) | CT32: =SUMIF($D$5:$CQ$5,CT$5,$D32:$CQ32)+SUMIF($D$5:$BI$5,CR$5,$D32:$BI32) | CU32: =+CR32-CS32 | CV32: =+CR32-CT32 | CW32: =+SUMIF($D$5:$CQ$5,CW$5,$D32:$CQ32) | CZ32: 0 | DA32: 0 | DD32: 0 | DM32: =(CS32-CZ32)*10^6 | DN32: =(CT32-DC32)*10^6 | DO32: =(CW32-DD32)*10^6
B33: Sortant sms BBCOM | C33: CA26 | D33: 0.001381 | E33: 0.0020104274 | G33: 0.001729 | J33: 0.001449 | K33: 0.0016762382 | M33: 0.001983 | P33: 0 | Q33: 0.0019295857 | S33: 0 | V33: 0.002344 | W33: 0.0017563069 | X33: 8.0236106e-05 | AA33: 0.004004 | AD33: 0.001852 | AE33: 0.0017700046 | AF33: 3.7365582e-05 | AI33: 0.001928 | AL33: 0 | AM33: 0.0017804293 | AN33: 5.8747942e-05 | CR33: =+SUMIF($D$5:$CQ$5,CR$5,$D33:$CQ33) | CS33: =+SUMIF($D$5:$CQ$5,CS$5,$D33:$CQ33) | CT33: =SUMIF($D$5:$CQ$5,CT$5,$D33:$CQ33)+SUMIF($D$5:$BI$5,CR$5,$D33:$BI33) | CU33: =+CR33-CS33 | CV33: =+CR33-CT33 | CW33: =+SUMIF($D$5:$CQ$5,CW$5,$D33:$CQ33) | CX33: =+CR33/CW33-1 | CZ33: 0.020332203 | DA33: 0.0032743833 | DD33: 0.020196 | DE33: =(CZ33-DD33)/DD33 | DF33: =(DA33-DD33)/DD33 | DG33: =(DB33-DD33)/DD33 | DH33: =(DC33-DD33)/DD33 | DM33: =(CS33-CZ33)*10^6 | DN33: =(CT33-DC33)*10^6 | DO33: =(CW33-DD33)*10^6
B34: Sortant sms LIBERCOM | C34: CA27 | D34: 0.232047 | E34: 0.40805876 | G34: 0.444316 | J34: 0.256878 | K34: 0.34140512 | M34: 0.483856 | P34: 0 | Q34: 0.39232378 | S34: 0.120348 | V34: 0.474559 | W34: 0.35740193 | X34: 0.014224217 | AA34: 0.720278 | AD34: 0.059786 | AE34: 0.36003331 | AF34: 0.0066241519 | AI34: 0.461819 | AL34: 0.837927 | AM34: 0.36223221 | AN34: 0.010414806 | CR34: =+SUMIF($D$5:$CQ$5,CR$5,$D34:$CQ34) | CS34: =+SUMIF($D$5:$CQ$5,CS$5,$D34:$CQ34) | CT34: =SUMIF($D$5:$CQ$5,CT$5,$D34:$CQ34)+SUMIF($D$5:$BI$5,CR$5,$D34:$BI34) | CU34: =+CR34-CS34 | CV34: =+CR34-CT34 | CW34: =+SUMIF($D$5:$CQ$5,CW$5,$D34:$CQ34) | CX34: =+CR34/CW34-1 | CZ34: 4.1356326 | DA34: 0.56770504 | DD34: 4.869894 | DE34: =(CZ34-DD34)/DD34 | DF34: =(DA34-DD34)/DD34 | DG34: =(DB34-DD34)/DD34 | DH34: =(DC34-DD34)/DD34 | DM34: =(CS34-CZ34)*10^6 | DN34: =(CT34-DC34)*10^6 | DO34: =(CW34-DD34)*10^6
B35: Sortant sms INTERNATIONAL | C35: CA28 | D35: 2.620917 | E35: 1.7264834 | G35: 2.610107 | J35: 2.365969 | K35: 1.4070221 | M35: 2.446585 | P35: 2.169288 | Q35: 1.6645672 | S35: 2.156481 | V35: 1.859409 | W35: 1.4475044 | X35: 7.156174 | AA35: 3.351597 | AD35: 1.419257 | AE35: 1.4659039 | AF35: 7.2924992 | AI35: 2.819749 | AL35: 1.293527 | AM35: 1.440472 | AN35: 7.1624499 | CR35: =+SUMIF($D$5:$CQ$5,CR$5,$D35:$CQ35) | CS35: =+SUMIF($D$5:$CQ$5,CS$5,$D35:$CQ35) | CT35: =SUMIF($D$5:$CQ$5,CT$5,$D35:$CQ35)+SUMIF($D$5:$BI$5,CR$5,$D35:$BI35) | CU35: =+CR35-CS35 | CV35: =+CR35-CT35 | CW35: =+SUMIF($D$5:$CQ$5,CW$5,$D35:$CQ35) | CX35: =+CR35/CW35-1 | CZ35: 16.937702 | DA35: 67.234984 | DD35: 28.821699 | DE35: =(CZ35-DD35)/DD35 | DF35: =(DA35-DD35)/DD35 | DG35: =(DB35-DD35)/DD35 | DH35: =(DC35-DD35)/DD35 | DM35: =(CS35-CZ35)*10^6 | DN35: =(CT35-DC35)*10^6 | DO35: =(CW35-DD35)*10^6
B36: Total SMS Sortant | C36: CA29 | D36: 5.322275 | E36: 4.6965846 | G36: 6.721654 | J36: 4.825876 | K36: 3.9273741 | M36: 6.613697 | P36: 5.293393 | Q36: 4.5281527 | S36: 5.716984 | V36: 9.473128 | W36: 4.0621766 | X36: 8.4706909 | AA36: 7.933409 | AD36: 3.602484 | AE36: 4.0743719 | AF36: 8.5989398 | AI36: 6.759831 | AL36: 3.991015 | AM36: 4.0199341 | AN36: 8.4279249 | CR36: =+SUMIF($D$5:$CQ$5,CR$5,$D36:$CQ36) | CS36: =+SUMIF($D$5:$CQ$5,CS$5,$D36:$CQ36) | CT36: =SUMIF($D$5:$CQ$5,CT$5,$D36:$CQ36)+SUMIF($D$5:$BI$5,CR$5,$D36:$BI36) | CU36: =+CR36-CS36 | CV36: =+CR36-CT36 | CW36: =+SUMIF($D$5:$CQ$5,CW$5,$D36:$CQ36) | CX36: =+CR36/CW36-1 | CZ36: 46.689227 | DA36: 86.014382 | DD36: 85.023279 | DE36: =(CZ36-DD36)/DD36 | DF36: =(DA36-DD36)/DD36 | DG36: =(DB36-DD36)/DD36 | DH36: =(DC36-DD36)/DD36 | DM36: =(CS36-CZ36)*10^6 | DN36: =(CT36-DC36)*10^6 | DO36: =(CW36-DD36)*10^6
C37: CA30 | CR37: =+SUMIF($D$5:$CQ$5,CR$5,$D37:$CQ37) | CS37: =+SUMIF($D$5:$CQ$5,CS$5,$D37:$CQ37) | CT37: =SUMIF($D$5:$CQ$5,CT$5,$D37:$CQ37)+SUMIF($D$5:$BI$5,CR$5,$D37:$BI37) | CU37: =+CR37-CS37 | CV37: =+CR37-CT37 | CW37: =+SUMIF($D$5:$CQ$5,CW$5,$D37:$CQ37) | DM37: =(CS37-CZ37)*10^6 | DN37: =(CT37-DC37)*10^6 | DO37: =(CW37-DD37)*10^6
B38: Revenu Internet 3G | C38: CA31 | D38: 3391.8193 | E38: 3972.9579 | G38: 3929.1116 | J38: 3154.7127 | K38: 3623.2346 | M38: 3651.9212 | P38: 3350.5914 | Q38: 4066.6491 | S38: 4052.4318 | V38: 3323.0163 | W38: 3997.4935 | X38: 3306.4819 | AA38: 3953.1544 | AD38: 3293.8297 | AE38: 4278.6044 | AF38: 3474.9081 | AI38: 3847.0446 | AL38: 3165.7604 | AM38: 4176.7512 | AN38: 3402.2755 | CR38: =+SUMIF($D$5:$CQ$5,CR$5,$D38:$CQ38) | CS38: =+SUMIF($D$5:$CQ$5,CS$5,$D38:$CQ38) | CT38: =SUMIF($D$5:$CQ$5,CT$5,$D38:$CQ38)+SUMIF($D$5:$BI$5,CR$5,$D38:$BI38) | CU38: =+CR38-CS38 | CV38: =+CR38-CT38 | CW38: =+SUMIF($D$5:$CQ$5,CW$5,$D38:$CQ38) | CX38: =+CR38/CW38-1 | CZ38: 50816.773 | DA38: 41836.031 | DD38: 44049.578 | DE38: =(CZ38-DD38)/DD38 | DF38: =(DA38-DD38)/DD38 | DG38: =(DB38-DD38)/DD38 | DH38: =(DC38-DD38)/DD38 | DM38: =(CS38-CZ38)*10^6 | DN38: =(CT38-DC38)*10^6 | DO38: =(CW38-DD38)*10^6
C39: CA32 | CR39: =+SUMIF($D$5:$CQ$5,CR$5,$D39:$CQ39) | CS39: =+SUMIF($D$5:$CQ$5,CS$5,$D39:$CQ39) | CT39: =SUMIF($D$5:$CQ$5,CT$5,$D39:$CQ39)+SUMIF($D$5:$BI$5,CR$5,$D39:$BI39) | CU39: =+CR39-CS39 | CV39: =+CR39-CT39 | CW39: =+SUMIF($D$5:$CQ$5,CW$5,$D39:$CQ39) | DM39: =(CS39-CZ39)*10^6 | DN39: =(CT39-DC39)*10^6 | DO39: =(CW39-DD39)*10^6
B40: CRBT | C40: CA33 | D40: 0.132797 | E40: 0.2890989 | G40: 0.565572 | J40: 0.134873 | K40: 0.2624272 | M40: 0.583941 | P40: 0 | Q40: 0.29199712 | S40: 0.608177 | V40: 0.378517 | W40: 0.28399075 | X40: 0.31015384 | AA40: 0.446823 | AD40: 0 | AE40: 0.29492439 | AF40: 0.32209476 | AI40: 0.479301 | AL40: 0.013051 | AM40: 0.28683776 | AN40: 0.31326313 | CR40: =+SUMIF($D$5:$CQ$5,CR$5,$D40:$CQ40) | CS40: =+SUMIF($D$5:$CQ$5,CS$5,$D40:$CQ40) | CT40: =SUMIF($D$5:$CQ$5,CT$5,$D40:$CQ40)+SUMIF($D$5:$BI$5,CR$5,$D40:$BI40) | CU40: =+CR40-CS40 | CV40: =+CR40-CT40 | CW40: =+SUMIF($D$5:$CQ$5,CW$5,$D40:$CQ40) | CX40: =+CR40/CW40-1 | CZ40: 3.4995447 | DA40: 3.1683816 | DD40: 82.64214 | DE40: =(CZ40-DD40)/DD40 | DF40: =(DA40-DD40)/DD40 | DG40: =(DB40-DD40)/DD40 | DH40: =(DC40-DD40)/DD40 | DM40: =(CS40-CZ40)*10^6 | DN40: =(CT40-DC40)*10^6 | DO40: =(CW40-DD40)*10^6
B41: Crédit secours | C41: CA34 | D41: 7.7828593 | E41: 6.5450633 | G41: 11.089769 | J41: 6.1609763 | K41: 6.0299035 | M41: 8.2821593 | P41: 6.3825358 | Q41: 6.8094839 | S41: 9.0645038 | V41: 6.0734941 | W41: 6.7216195 | X41: 6.235343 | AA41: 8.1910127 | AD41: 5.5051847 | AE41: 7.084587 | AF41: 6.5720515 | AI41: 7.6101144 | AL41: 5.0739201 | AM41: 6.993173 | AN41: 6.5508514 | CR41: =+SUMIF($D$5:$CQ$5,CR$5,$D41:$CQ41) | CS41: =+SUMIF($D$5:$CQ$5,CS$5,$D41:$CQ41) | CT41: =SUMIF($D$5:$CQ$5,CT$5,$D41:$CQ41)+SUMIF($D$5:$BI$5,CR$5,$D41:$BI41) | CU41: =+CR41-CS41 | CV41: =+CR41-CT41 | CW41: =+SUMIF($D$5:$CQ$5,CW$5,$D41:$CQ41) | CX41: =+CR41/CW41-1 | CZ41: 86.175014 | DA41: 84.292493 | DD41: 86.4991 | DE41: =(CZ41-DD41)/DD41 | DF41: =(DA41-DD41)/DD41 | DG41: =(DB41-DD41)/DD41 | DH41: =(DC41-DD41)/DD41 | DM41: =(CS41-CZ41)*10^6 | DN41: =(CT41-DC41)*10^6 | DO41: =(CW41-DD41)*10^6
B42: Story Box | C42: CA35 | D42: 0 | E42: 0 | G42: 0 | J42: 0 | K42: 0 | M42: 0 | P42: 0 | Q42: 0 | S42: 0 | V42: 0 | W42: 0 | X42: 0 | AA42: 0 | AD42: 0 | AE42: 0 | AF42: 0 | AI42: 0 | AL42: 0 | CR42: =+SUMIF($D$5:$CQ$5,CR$5,$D42:$CQ42) | CS42: =+SUMIF($D$5:$CQ$5,CS$5,$D42:$CQ42) | CT42: =SUMIF($D$5:$CQ$5,CT$5,$D42:$CQ42)+SUMIF($D$5:$BI$5,CR$5,$D42:$BI42) | CU42: =+CR42-CS42 | CV42: =+CR42-CT42 | CW42: =+SUMIF($D$5:$CQ$5,CW$5,$D42:$CQ42) | CZ42: 0 | DA42: 0 | DD42: 0 | DM42: =(CS42-CZ42)*10^6 | DN42: =(CT42-DC42)*10^6 | DO42: =(CW42-DD42)*10^6
B43: Phonebook STK | C43: CA36 | D43: 0 | E43: 0 | G43: 0 | J43: 0 | K43: 0 | M43: 0 | P43: 0 | Q43: 0 | S43: 0 | V43: 0 | W43: 0 | X43: 0 | AA43: 0 | AD43: 0 | AE43: 0 | AF43: 0 | AI43: 0 | AL43: 0 | CR43: =+SUMIF($D$5:$CQ$5,CR$5,$D43:$CQ43) | CS43: =+SUMIF($D$5:$CQ$5,CS$5,$D43:$CQ43) | CT43: =SUMIF($D$5:$CQ$5,CT$5,$D43:$CQ43)+SUMIF($D$5:$BI$5,CR$5,$D43:$BI43) | CU43: =+CR43-CS43 | CV43: =+CR43-CT43 | CW43: =+SUMIF($D$5:$CQ$5,CW$5,$D43:$CQ43) | CZ43: 0 | DA43: 0 | DD43: 0 | DM43: =(CS43-CZ43)*10^6 | DN43: =(CT43-DC43)*10^6 | DO43: =(CW43-DD43)*10^6
B44: Gaming | C44: CA37 | D44: 0 | E44: 0 | G44: 0 | J44: 0 | K44: 0 | M44: 0 | P44: 0 | Q44: 0 | S44: 0 | V44: 0 | W44: 0 | X44: 0 | AA44: 0 | AD44: 0 | AE44: 0 | AF44: 0 | AI44: 0 | AL44: 0 | AM44: 0 | AN44: 0 | CR44: =+SUMIF($D$5:$CQ$5,CR$5,$D44:$CQ44) | CS44: =+SUMIF($D$5:$CQ$5,CS$5,$D44:$CQ44) | CT44: =SUMIF($D$5:$CQ$5,CT$5,$D44:$CQ44)+SUMIF($D$5:$BI$5,CR$5,$D44:$BI44) | CU44: =+CR44-CS44 | CV44: =+CR44-CT44 | CW44: =+SUMIF($D$5:$CQ$5,CW$5,$D44:$CQ44) | CZ44: 0 | DA44: 0 | DD44: 0 | DM44: =(CS44-CZ44)*10^6 | DN44: =(CT44-DC44)*10^6 | DO44: =(CW44-DD44)*10^6
B45: Autres dont BAC17 (VOICEALERT,MOOVKDO...) & SAV agences | C45: CA38 | D45: 109.72332 | E45: 72.635227 | G45: 110.43728 | J45: 79.147399 | K45: 71.940203 | M45: 112.88836 | P45: 74.207574 | Q45: 80.220615 | S45: 113.86312 | V45: 85.208473 | W45: 81.536753 | X45: 72.35829 | AA45: 149.90812 | AD45: 80.699652 | AE45: 87.850508 | AF45: 74.770233 | AI45: 93.487894 | AL45: 63.957038 | AM45: 88.994361 | CR45: =+SUMIF($D$5:$CQ$5,CR$5,$D45:$CQ45) | CS45: =+SUMIF($D$5:$CQ$5,CS$5,$D45:$CQ45) | CT45: =SUMIF($D$5:$CQ$5,CT$5,$D45:$CQ45)+SUMIF($D$5:$BI$5,CR$5,$D45:$BI45) | CU45: =+CR45-CS45 | CV45: =+CR45-CT45 | CW45: =+SUMIF($D$5:$CQ$5,CW$5,$D45:$CQ45) | CX45: =+CR45/CW45-1 | CZ45: 1110.2921 | DA45: 961.56799 | DD45: 1048.2637 | DE45: =(CZ45-DD45)/DD45 | DF45: =(DA45-DD45)/DD45 | DG45: =(DB45-DD45)/DD45 | DH45: =(DC45-DD45)/DD45 | DM45: =(CS45-CZ45)*10^6 | DN45: =(CT45-DC45)*10^6 | DO45: =(CW45-DD45)*10^6
B46: Videos | C46: CA39 | D46: 0 | E46: 0 | G46: 0 | J46: 0 | K46: 0 | M46: 0 | P46: 0 | Q46: 0 | S46: 0 | V46: 0 | W46: 0 | X46: 0 | AA46: 0 | AD46: 0 | AE46: 0 | AF46: 0 | AI46: 0 | AL46: 0 | CR46: =+SUMIF($D$5:$CQ$5,CR$5,$D46:$CQ46) | CS46: =+SUMIF($D$5:$CQ$5,CS$5,$D46:$CQ46) | CT46: =SUMIF($D$5:$CQ$5,CT$5,$D46:$CQ46)+SUMIF($D$5:$BI$5,CR$5,$D46:$BI46) | CU46: =+CR46-CS46 | CV46: =+CR46-CT46 | CW46: =+SUMIF($D$5:$CQ$5,CW$5,$D46:$CQ46) | CZ46: 0 | DA46: 0 | DD46: 0 | DG46: =(DB46-DD46)/DD46 | DM46: =(CS46-CZ46)*10^6 | DN46: =(CT46-DC46)*10^6 | DO46: =(CW46-DD46)*10^6
B47: Total Data | C47: CA40 | D47: 117.63897 | E47: 79.469389 | G47: 122.09263 | J47: 85.443248 | K47: 78.232534 | M47: 121.75446 | P47: 80.59011 | Q47: 87.322096 | S47: 123.5358 | V47: 91.660484 | W47: 88.542364 | X47: 78.903787 | AA47: 158.54595 | AD47: 86.204837 | AE47: 95.23002 | AF47: 81.664379 | AI47: 101.57731 | AL47: 69.044009 | AM47: 96.274371 | AN47: 81.222404 | CR47: =+SUMIF($D$5:$CQ$5,CR$5,$D47:$CQ47) | CS47: =+SUMIF($D$5:$CQ$5,CS$5,$D47:$CQ47) | CT47: =SUMIF($D$5:$CQ$5,CT$5,$D47:$CQ47)+SUMIF($D$5:$BI$5,CR$5,$D47:$BI47) | CU47: =+CR47-CS47 | CV47: =+CR47-CT47 | CW47: =+SUMIF($D$5:$CQ$5,CW$5,$D47:$CQ47) | CX47: =+CR47/CW47-1 | CZ47: 1199.9667 | DA47: 1049.0289 | DD47: 1217.4049 | DE47: =(CZ47-DD47)/DD47 | DF47: =(DA47-DD47)/DD47 | DG47: =(DB47-DD47)/DD47 | DH47: =(DC47-DD47)/DD47 | DM47: =(CS47-CZ47)*10^6 | DN47: =(CT47-DC47)*10^6 | DO47: =(CW47-DD47)*10^6
C48: CA41 | CR48: =+SUMIF($D$5:$CQ$5,CR$5,$D48:$CQ48) | CS48: =+SUMIF($D$5:$CQ$5,CS$5,$D48:$CQ48) | CT48: =SUMIF($D$5:$CQ$5,CT$5,$D48:$CQ48)+SUMIF($D$5:$BI$5,CR$5,$D48:$BI48) | CU48: =+CR48-CS48 | CV48: =+CR48-CT48 | CW48: =+SUMIF($D$5:$CQ$5,CW$5,$D48:$CQ48) | DM48: =(CS48-CZ48)*10^6 | DN48: =(CT48-DC48)*10^6 | DO48: =(CW48-DD48)*10^6
B49: dont CA voix | C49: CA42 | CR49: =+SUMIF($D$5:$CQ$5,CR$5,$D49:$CQ49) | CS49: =+SUMIF($D$5:$CQ$5,CS$5,$D49:$CQ49) | CT49: =SUMIF($D$5:$CQ$5,CT$5,$D49:$CQ49)+SUMIF($D$5:$BI$5,CR$5,$D49:$BI49) | CU49: =+CR49-CS49 | CV49: =+CR49-CT49 | CW49: =+SUMIF($D$5:$CQ$5,CW$5,$D49:$CQ49) | DM49: =(CS49-CZ49)*10^6 | DN49: =(CT49-DC49)*10^6 | DO49: =(CW49-DD49)*10^6
B50: dont CA SMS | C50: CA43 | CR50: =+SUMIF($D$5:$CQ$5,CR$5,$D50:$CQ50) | CS50: =+SUMIF($D$5:$CQ$5,CS$5,$D50:$CQ50) | CT50: =SUMIF($D$5:$CQ$5,CT$5,$D50:$CQ50)+SUMIF($D$5:$BI$5,CR$5,$D50:$BI50) | CU50: =+CR50-CS50 | CV50: =+CR50-CT50 | CW50: =+SUMIF($D$5:$CQ$5,CW$5,$D50:$CQ50) | DM50: =(CS50-CZ50)*10^6 | DN50: =(CT50-DC50)*10^6 | DO50: =(CW50-DD50)*10^6
B51: dont SVA (Sce à Val. Ajoutée) | C51: CA44 | CR51: =+SUMIF($D$5:$CQ$5,CR$5,$D51:$CQ51) | CS51: =+SUMIF($D$5:$CQ$5,CS$5,$D51:$CQ51) | CT51: =SUMIF($D$5:$CQ$5,CT$5,$D51:$CQ51)+SUMIF($D$5:$BI$5,CR$5,$D51:$BI51) | CU51: =+CR51-CS51 | CV51: =+CR51-CT51 | CW51: =+SUMIF($D$5:$CQ$5,CW$5,$D51:$CQ51) | DM51: =(CS51-CZ51)*10^6 | DN51: =(CT51-DC51)*10^6 | DO51: =(CW51-DD51)*10^6
B52: dont CA Internet 3G | C52: CA45 | AL52: 3165.7604 | AN52: 3402.2755 | CR52: =+SUMIF($D$5:$CQ$5,CR$5,$D52:$CQ52) | CS52: =+SUMIF($D$5:$CQ$5,CS$5,$D52:$CQ52) | CT52: =SUMIF($D$5:$CQ$5,CT$5,$D52:$CQ52)+SUMIF($D$5:$BI$5,CR$5,$D52:$BI52) | CU52: =+CR52-CS52 | CV52: =+CR52-CT52 | CW52: =+SUMIF($D$5:$CQ$5,CW$5,$D52:$CQ52) | CX52: =+CR52/CW52-1 | DA52: 41836.031 | DE52: =(CZ52-DD52)/DD52 | DF52: =(DA52-DD52)/DD52 | DG52: =(DB52-DD52)/DD52 | DH52: =(DC52-DD52)/DD52 | DM52: =(CS52-CZ52)*10^6 | DN52: =(CT52-DC52)*10^6 | DO52: =(CW52-DD52)*10^6
B53: Postpayé | C53: CA46 | D53: 283.3024 | E53: 292.50936 | F53: -9.2069629 | G53: 286.37459 | H53: -0.010727893 | J53: 275.73228 | K53: 288.83262 | L53: -13.100341 | M53: 276.5361 | N53: -0.0029067597 | P53: 266.05768 | Q53: 295.31681 | R53: -29.259127 | S53: 316.32176 | T53: -0.15890175 | V53: 279.46655 | W53: 298.46963 | X53: 280.04777 | Y53: -19.003074 | Z53: -0.58121527 | AA53: 284.53132 | AB53: -0.017800368 | AD53: 277.32106 | AE53: 281.4221 | AF53: 281.43339 | AG53: -4.1010428 | AH53: -4.1123353 | AI53: 277.01215 | AJ53: 0.0011151327 | AL53: 265.90205 | AM53: 294.65284 | AN53: 281.32092 | AO53: 0 | AP53: -28.750791 | AQ53: -15.418878 | AR53: 264.13788 | AS53: 0.0066789702 | CR53: 1647.782 | CS53: 1751.2034 | CU53: -103.42134 | CV53: =+CR53-CT53 | CW53: 1440.7759 | CX53: =IFERROR(CR53/CW53-1, "-") | CZ53: 3522.7874 | DA53: 3355.2001 | DD53: 3393.7467 | DE53: =(CZ53-DD53)/DD53 | DF53: =(DA53-DD53)/DD53 | DG53: =(DB53-DD53)/DD53 | DH53: =(DC53-DD53)/DD53 | DM53: =(CS53-CZ53)*10^6 | DN53: =(CT53-DC53)*10^6 | DO53: =(CW53-DD53)*10^6
B54: Redevance d'abonnement | C54: CA47 | D54: 210.72997 | E54: 216.24376 | F54: -5.5137952 | G54: 201.05486 | H54: 0.048121727 | J54: 204.27607 | K54: 216.8997 | L54: -12.623628 | M54: 213.38037 | N54: -0.042667008 | P54: 202.28072 | Q54: 217.55563 | R54: -15.274912 | S54: 233.12156 | T54: -0.13229507 | V54: 205.38513 | W54: 218.26623 | X54: 218.94093 | Y54: -12.881106 | Z54: -13.555806 | AA54: 209.66649 | AB54: -0.020419891 | AD54: 209.40001 | AE54: 219.14081 | AF54: 219.44401 | AG54: -9.7408018 | AH54: -10.044001 | AI54: 210.90654 | AJ54: -0.0071430977 | AL54: 214.01683 | AM54: 220.12472 | AN54: 220.00998 | AO54: 0 | AP54: -6.1078885 | AQ54: -5.9931493 | AR54: 211.4481 | AS54: 0.012148281 | CR54: 1246.0887 | CS54: 1308.2309 | CU54: -62.142131 | CV54: =+CR54-CT54 | CW54: 1068.1298 | CX54: =IFERROR(CR54/CW54-1, "-") | CZ54: 2654.834 | DA54: 2610.6139 | DD54: 2541.4332 | DE54: =(CZ54-DD54)/DD54 | DF54: =(DA54-DD54)/DD54 | DG54: =(DB54-DD54)/DD54 | DH54: =(DC54-DD54)/DD54 | DM54: =(CS54-CZ54)*10^6 | DN54: =(CT54-DC54)*10^6 | DO54: =(CW54-DD54)*10^6
A55: Consumer Postpaid | C55: CA48 | D55: 10.744112 | E55: 9.6670395 | G55: -10.210921 | J55: 8.377123 | K55: 9.6913966 | M55: 12.944075 | P55: 11.147391 | Q55: 9.7157537 | S55: 32.80881 | V55: 7.867374 | W55: 9.7421406 | X55: 8.8937641 | AA55: 10.199999 | AD55: 12.190486 | AE55: 9.7746168 | AF55: 8.9262403 | AI55: 12.206783 | AL55: 10.219515 | AM55: 9.8111525 | AN55: 8.962776 | CR55: =+SUMIF($D$5:$CQ$5,CR$5,$D55:$CQ55) | CS55: =+SUMIF($D$5:$CQ$5,CS$5,$D55:$CQ55) | CT55: =SUMIF($D$5:$CQ$5,CT$5,$D55:$CQ55)+SUMIF($D$5:$BI$5,CR$5,$D55:$BI55) | CU55: =+CR55-CS55 | CV55: =+CR55-CT55 | CW55: =+SUMIF($D$5:$CQ$5,CW$5,$D55:$CQ55) | CX55: =+CR55/CW55-1 | CZ55: 118.22909 | DA55: 111.78814 | DD55: 125.38987 | DE55: =(CZ55-DD55)/DD55 | DF55: =(DA55-DD55)/DD55 | DG55: =(DB55-DD55)/DD55 | DH55: =(DC55-DD55)/DD55 | DM55: =(CS55-CZ55)*10^6 | DN55: =(CT55-DC55)*10^6 | DO55: =(CW55-DD55)*10^6
A56: Business Postpaid | C56: CA49 | D56: 14.508871 | E56: 18.503261 | G56: 20.653505 | J56: 14.707985 | K56: 18.53334 | M56: 20.636356 | P56: 14.380717 | Q56: 18.56342 | S56: 20.542765 | V56: 15.03903 | W56: 18.596006 | X56: 7.5581062 | AA56: 20.468296 | AD56: 14.192589 | AE56: 18.636112 | AF56: 7.5982122 | AI56: 19.646177 | AL56: 14.139861 | AM56: 18.681231 | AN56: 7.6433314 | CR56: =+SUMIF($D$5:$CQ$5,CR$5,$D56:$CQ56) | CS56: =+SUMIF($D$5:$CQ$5,CS$5,$D56:$CQ56) | CT56: =SUMIF($D$5:$CQ$5,CT$5,$D56:$CQ56)+SUMIF($D$5:$BI$5,CR$5,$D56:$BI56) | CU56: =+CR56-CS56 | CV56: =+CR56-CT56 | CW56: =+SUMIF($D$5:$CQ$5,CW$5,$D56:$CQ56) | CX56: =+CR56/CW56-1 | CZ56: 224.78639 | DA56: 113.44285 | DD56: 210.46011 | DE56: =(CZ56-DD56)/DD56 | DF56: =(DA56-DD56)/DD56 | DG56: =(DB56-DD56)/DD56 | DH56: =(DC56-DD56)/DD56 | DM56: =(CS56-CZ56)*10^6 | DN56: =(CT56-DC56)*10^6 | DO56: =(CW56-DD56)*10^6
A57: Business Prepaid | C57: CA50 | D57: 185.47698 | E57: 188.07346 | G57: 190.61228 | J57: 181.19096 | K57: 188.67496 | M57: 179.79994 | P57: 176.75261 | Q57: 189.27646 | S57: 179.76998 | V57: 182.47872 | W57: 189.92809 | X57: 202.48906 | AA57: 178.9982 | AD57: 183.01694 | AE57: 190.73009 | AF57: 202.91956 | AI57: 179.05358 | AL57: 189.65745 | AM57: 191.63233 | AN57: 203.40387 | CR57: =+SUMIF($D$5:$CQ$5,CR$5,$D57:$CQ57) | CS57: =+SUMIF($D$5:$CQ$5,CS$5,$D57:$CQ57) | CT57: =SUMIF($D$5:$CQ$5,CT$5,$D57:$CQ57)+SUMIF($D$5:$BI$5,CR$5,$D57:$BI57) | CU57: =+CR57-CS57 | CV57: =+CR57-CT57 | CW57: =+SUMIF($D$5:$CQ$5,CW$5,$D57:$CQ57) | CX57: =+CR57/CW57-1 | CZ57: 2311.8185 | DA57: 2385.3829 | DD57: 2205.5832 | DE57: =(CZ57-DD57)/DD57 | DF57: =(DA57-DD57)/DD57 | DG57: =(DB57-DD57)/DD57 | DH57: =(DC57-DD57)/DD57 | DM57: =(CS57-CZ57)*10^6 | DN57: =(CT57-DC57)*10^6 | DO57: =(CW57-DD57)*10^6
