Workbook
Name \e: #N/A
Name \M: #REF!
Name \M: #REF!
Name \M: #REF!
Name \M: #REF!
Name \p: '[1]cur q v plan'!#REF!
Name \p: '[1]cur q v plan'!#REF!
Name \p: '[1]cur q v plan'!#REF!
Name \p: '[1]cur q v plan'!#REF!
Name \r: #N/A
Name \t: #N/A
Name _: #REF!
Name _: #REF!
Name _: #REF!
Name _: #REF!
Name __: #REF!
Name __: #REF!
Name __: {"subs",#N/A,FALSE,"database ";"proportional",#N/A,FALSE,"database "}
Name __: #REF!
Name ___________B1: #N/A
Name ___________eng2: #N/A
Name ___________eng3: [0]!___________eng3
Name ___________eng3: #N/A
Name ___________eng3: [0]!___________eng3
Name ___________eng4: #N/A
Name __________B1: #N/A
Name __________eng2: #N/A
Name __________eng3: [0]!__________eng3
Name __________eng3: #N/A
Name __________eng3: [0]!__________eng3
Name __________eng4: #N/A
Name _________eng3: [0]!_________eng3
Name _________eng3: #N/A
Name _________eng3: [0]!_________eng3
Name ________eng3: [0]!________eng3
Name ________eng3: #N/A
Name ________eng3: [0]!________eng3
Name _______eng3: [0]!_______eng3
Name _______eng3: #N/A
Name _______eng3: [0]!_______eng3
Name ______eng3: [0]!______eng3
Name ______eng3: #N/A
Name ______eng3: [0]!______eng3
Name ______FRF4: '[6]FX Rates'!$G$10
Name ______GBP4: '[6]FX Rates'!$G$9
Name _____0: #REF!
Name _____0: #REF!
Name _____0: #REF!
Name _____0: #REF!
Name _____12: #REF!
Name _____12: #REF!
Name _____12: #REF!
Name _____12: #REF!
Name _____14: #REF!
Name _____14: #REF!
Name _____14: #REF!
Name _____14: #REF!
Name _____16: #REF!
Name _____16: #REF!
Name _____16: #REF!

Sheet Cover
E15: MOOV AFRICA BENIN TBG
E17: 45627
A5603: 41743
A5604: 41743
A5605: 41744
A5606: 41744
A5607: 41744
A5608: 41744
A5609: 41744
A5610: 41744
A5611: 41744
A5612: 41744
A5613: 41744
A5614: 41744
A5615: 41744

Sheet P&L conso
A1: P&L consolidé | V1: =+V25+'Opex Consolidés'!V7 -> 0 | AD1: =+AD25+'Opex Consolidés'!AD7 -> 0 | AL1: =+AL25+'Opex Consolidés'!AL7 -> 0 | AU1: =#REF! -> #REF! | BC1: 577.07409 | BK1: =+BK25+'Opex Consolidés'!BD7 -> 0 | BT1: -68804439 | BW1: =BV4 -> 0 | CB1: =+CB25+'Opex Consolidés'!BU7 -> 0 | CJ1: =+CJ25+'Opex Consolidés'!CC7 -> 0 | CR1: =+CR25+'Opex Consolidés'!CR7 -> 0 | CS1: 17000.499 | CT1: =CT25+'Opex Consolidés'!CT7 -> 0 | CW1: 16458.089 | CZ1: 26225.79 | DC1: 8378.9625
E3: 0 | G3: 0 | AD3: 0 | CZ3: 0 | DD3: 0
D4: 45292 | J4: 45323 | P4: 45352 | V4: 45383 | AD4: 45413 | AL4: 45444 | AU4: 45474 | BC4: 45505 | BK4: 45536 | BT4: 45566 | CB4: 45597 | CJ4: 45627 | CR4: CUMUL | CZ4: ANNUEL
A5: (En Millions ML) | D5: 2024 Réel | E5: 2024 Budget | F5: Ecart / Budget | G5: 2023 Réel | H5: Evol % | J5: 2024 Réel | K5: 2024 Budget | L5: Ecart / Budget | M5: 2023 Réel | N5: Evol % | P5: 2024 Réel | Q5: 2024 Budget | R5: Ecart / Budget | S5: 2023 Réel | T5: Evol % | V5: 2024 Réel | W5: 2024 Budget | X5: 2024 Actu1 | Y5: Ecart / Budget | Z5: Ecart / Actu1 | AA5: 2023 Réel | AB5: Evol % | AD5: 2024 Réel | AE5: 2024 Budget | AF5: 2024 Actu1 | AG5: Ecart / Budget | AH5: Ecart / Actu1 | AI5: 2023 Réel | AJ5: Evol % | AL5: 2024 Réel | AM5: 2024 Budget | AN5: 2024 Actu1 | AO5: 2024 Actu2 | AP5: Ecart / Budget | AQ5: Ecart / Actu1 | AR5: 2023 Réel | AS5: Evol % | AU5: 2024 Réel | AV5: 2024 Budget | AW5: 2024 Actu2 | AX5: Ecart / Budget | AY5: Ecart / Actu2 | AZ5: 2023 Réel | BA5: Evol % | BC5: 2024 Réel | BD5: 2024 Budget | BE5: 2024 Actu2 | BF5: Ecart / Budget | BG5: Ecart / Actu2 | BH5: 2023 Réel | BI5: Evol % | BK5: 2024 Réel | BL5: 2024 Budget | BM5: 2024 Actu2 | BN5: 2024 Actu3 | BO5: Ecart / Budget | BP5: Ecart / Actu2 | BQ5: 2023 Réel | BR5: Evol % | BT5: 2024 Réel | BU5: 2024 Budget | BV5: 2024 Actu3 | BW5: Ecart / Budget | BX5: Ecart / Actu3 | BY5: 2023 Réel | BZ5: Evol % | CB5: 2024 Réel | CC5: 2024 Budget | CD5: 2024 Actu3 | CE5: Ecart / Budget | CF5: Ecart / Actu3 | CG5: 2023 Réel | CH5: Evol % | CJ5: 2024 Réel | CK5: 2024 Budget | CL5: 2024 Actu3 | CM5: Ecart / Budget | CN5: Ecart / Actu3 | CO5: 2023 Réel | CP5: Evol % | CR5: 2024 Réel | CS5: 2024 Budget | CT5: 2024 Actu3 | CU5: Ecart / Budget | CV5: Ecart / Actu3 | CW5: 2023 Réel | CX5: Evol % | CZ5: 2024 Budget | DA5: 2024 Actu1 | DB5: 2024 Actu2 | DC5: 2024 Actu3 | DD5: 2023 Réel | DE5: Bud / 2023 (%) | DF5: Actu 1 / 2023 (%) | DG5: Actu 2 / 2023 (%) | DH5: Actu3 / 2023 (%)
A7: Chiffre d'affaires | C7: PL1 | CU7: =+CR7-CS7 -> 0 | CV7: =+CR7-CT7 -> 0 | CX7: =IFERROR(CR7/CW7-1, "-") -> - | DE7: =CZ7/DD7-1 -> #DIV/0! | DF7: =DA7/DD7-1 -> #DIV/0! | DG7: =DB7/DD7-1 -> #DIV/0! | DH7: =DC7/DD7-1 -> #DIV/0!
A8: Fixe & Internet | C8: PL2 | CU8: =+CR8-CS8 -> 0 | CV8: =+CR8-CT8 -> 0 | CX8: =IFERROR(CR8/CW8-1, "-") -> -
A9: Mobile | C9: PL3 | CU9: =+CR9-CS9 -> 0 | CV9: =+CR9-CT9 -> 0 | CX9: =IFERROR(CR9/CW9-1, "-") -> - | DE9: =CZ9/DD9-1 -> #DIV/0! | DG9: =DB9/DD9-1 -> #DIV/0! | DH9: =DC9/DD9-1 -> #DIV/0!
A10: Intercompagnie Mobile | C10: PL4 | CU10: =+CR10-CS10 -> 0 | CV10: =+CR10-CT10 -> 0 | CX10: =IFERROR(CR10/CW10-1, "-") -> - | DE10: =CZ10/DD10-1 -> #DIV/0! | DF10: =DA10/DD10-1 -> #DIV/0! | DG10: =DB10/DD10-1 -> #DIV/0! | DH10: =DC10/DD10-1 -> #DIV/0!
C11: PL5 | CU11: =+CR11-CS11 -> 0 | CV11: =+CR11-CT11 -> 0 | CX11: =IFERROR(CR11/CW11-1, "-") -> -
A12: Intercompagnie | C12: PL6 | CU12: =+CR12-CS12 -> 0 | CV12: =+CR12-CT12 -> 0 | CX12: =IFERROR(CR12/CW12-1, "-") -> - | DE12: =CZ12/DD12-1 -> #DIV/0!
A13: dont Intercompagnie hors trafic | C13: PL7 | CU13: =+CR13-CS13 -> 0 | CV13: =+CR13-CT13 -> 0 | CX13: =IFERROR(CR13/CW13-1, "-") -> - | DE13: =CZ13/DD13-1 -> #DIV/0!
C14: PL8 | CU14: =+CR14-CS14 -> 0 | CV14: =+CR14-CT14 -> 0 | CX14: =IFERROR(CR14/CW14-1, "-") -> - | DE14: =CZ14/DD14-1 -> #DIV/0!
A15: Coût des ventes | C15: PL9 | CU15: =+CR15-CS15 -> 0 | CV15: =+CR15-CT15 -> 0 | CX15: =IFERROR(CR15/CW15-1, "-") -> - | DE15: =(CZ15/DD15-1) -> #DIV/0! | DF15: =DA15/DD15-1 -> #DIV/0! | DG15: =DB15/DD15-1 -> #DIV/0! | DH15: =DC15/DD15-1 -> #DIV/0!
A16: Fixe & Internet | C16: PL10 | CU16: =+CR16-CS16 -> 0 | CV16: =+CR16-CT16 -> 0 | CX16: =IFERROR(CR16/CW16-1, "-") -> - | DE16: =CZ16/DD16-1 -> #DIV/0!
A17: Mobile | C17: PL11 | CU17: =+CR17-CS17 -> 0 | CV17: =+CR17-CT17 -> 0 | CX17: =IFERROR(CR17/CW17-1, "-") -> - | DE17: =(CZ17/DD17-1) -> #DIV/0! | DF17: =DA17/DD17-1 -> #DIV/0! | DG17: =DB17/DD17-1 -> #DIV/0! | DH17: =DC17/DD17-1 -> #DIV/0!
A18: Intercompagnie Mobile | C18: PL12 | CU18: =+CR18-CS18 -> 0 | CV18: =+CR18-CT18 -> 0 | CX18: =IFERROR(CR18/CW18-1, "-") -> - | DE18: =(CZ18/DD18-1) -> #DIV/0! | DF18: =DA18/DD18-1 -> #DIV/0! | DG18: =DB18/DD18-1 -> #DIV/0! | DH18: =DC18/DD18-1 -> #DIV/0!
C19: PL13 | CU19: =+CR19-CS19 -> 0 | CV19: =+CR19-CT19 -> 0 | CX19: =IFERROR(CR19/CW19-1, "-") -> -
A20: Marge Brute | C20: PL14 | CU20: =+CR20-CS20 -> 0 | CV20: =+CR20-CT20 -> 0 | CX20: =IFERROR(CR20/CW20-1, "-") -> - | DE20: =CZ20/DD20-1 -> #DIV/0! | DF20: =DA20/DD20-1 -> #DIV/0! | DG20: =DB20/DD20-1 -> #DIV/0! | DH20: =DC20/DD20-1 -> #DIV/0!
A21: % CA | C21: PL15 | CU21: =+(CR21-CS21) -> 0 | CV21: =+(CR21-CT21) -> 0 | CX21: =IFERROR(CR21/CW21-1, "-") -> - | DE21: =+(CZ21-DD21) -> 0 | DF21: =DA21/DD21-1 -> #DIV/0! | DG21: =DB21/DD21-1 -> #DIV/0! | DH21: =DC21/DD21-1 -> #DIV/0!
A22: Fixe & Internet | C22: PL16 | CU22: =+CR22-CS22 -> 0 | CV22: =+CR22-CT22 -> 0 | CX22: =IFERROR(CR22/CW22-1, "-") -> - | DE22: =CZ22/DD22-1 -> #DIV/0!
A23: Mobile | C23: PL17 | CU23: =+CR23-CS23 -> 0 | CV23: =+CR23-CT23 -> 0 | CX23: =IFERROR(CR23/CW23-1, "-") -> - | DE23: =(CZ23/DD23-1) -> #DIV/0! | DF23: =DA23/DD23-1 -> #DIV/0! | DG23: =DB23/DD23-1 -> #DIV/0! | DH23: =DC23/DD23-1 -> #DIV/0!
C24: PL18 | CU24: =+CR24-CS24 -> 0 | CV24: =+CR24-CT24 -> 0 | CX24: =IFERROR(CR24/CW24-1, "-") -> -
A25: Coûts opérationnels | C25: PL19 | CU25: =+CR25-CS25 -> 0 | CV25: =+CR25-CT25 -> 0 | CX25: =IFERROR(CR25/CW25-1, "-") -> - | DE25: =CZ25/DD25-1 -> #DIV/0! | DF25: =DA25/DD25-1 -> #DIV/0! | DG25: =DB25/DD25-1 -> #DIV/0! | DH25: =DC25/DD25-1 -> #DIV/0!
A26: Fixe & Internet | C26: PL20 | CU26: =+CR26-CS26 -> 0 | CV26: =+CR26-CT26 -> 0 | CX26: =IFERROR(CR26/CW26-1, "-") -> - | DE26: =CZ26/DD26-1 -> #DIV/0!
A27: Intercompagnie Fixe & Internet | C27: PL21 | CU27: =+CR27-CS27 -> 0 | CV27: =+CR27-CT27 -> 0 | CX27: =IFERROR(CR27/CW27-1, "-") -> - | DE27: =CZ27/DD27-1 -> #DIV/0!
A28: Mobile | C28: PL22 | CU28: =+CR28-CS28 -> 0 | CV28: =+CR28-CT28 -> 0 | CX28: =IFERROR(CR28/CW28-1, "-") -> - | DE28: =CZ28/DD28-1 -> #DIV/0! | DF28: =DA28/DD28-1 -> #DIV/0! | DG28: =DB28/DD28-1 -> #DIV/0! | DH28: =DC28/DD28-1 -> #DIV/0!
A29: Intercompagnie Mobile | C29: PL23 | CU29: =+CR29-CS29 -> 0 | CV29: =+CR29-CT29 -> 0 | CX29: =IFERROR(CR29/CW29-1, "-") -> - | DE29: =CZ29/DD29-1 -> #DIV/0! | DF29: =DA29/DD29-1 -> #DIV/0! | DH29: =DC29/DD29-1 -> #DIV/0!
C30: PL24 | CX30: =IFERROR(CR30/CW30-1, "-") -> -
A31: EBITDA | C31: PL25 | CU31: =+CR31-CS31 -> 0 | CV31: =+CR31-CT31 -> 0 | CX31: =IFERROR(CR31/CW31-1, "-") -> - | DE31: =CZ31/DD31-1 -> #DIV/0! | DF31: =DA31/DD31-1 -> #DIV/0! | DG31: =DB31/DD31-1 -> #DIV/0! | DH31: =DC31/DD31-1 -> #DIV/0!
A32: % CA | C32: PL26 | CU32: =+(CR32-CS32) -> 0 | CV32: =+(CR32-CT32) -> 0 | CX32: =IFERROR(CR32/CW32-1, "-") -> - | DE32: =(CZ32-DD32) -> 0 | DF32: =DA32/DD32-1 -> #DIV/0! | DG32: =DB32/DD32-1 -> #DIV/0! | DH32: =DC32/DD32-1 -> #DIV/0!
A33: Fixe & Internet | C33: PL27 | CU33: =+CR33-CS33 -> 0 | CV33: =+CR33-CT33 -> 0 | CX33: =IFERROR(CR33/CW33-1, "-") -> - | DE33: =CZ33/DD33-1 -> #DIV/0!
A34: Mobile | C34: PL28 | CU34: =+CR34-CS34 -> 0 | CV34: =+CR34-CT34 -> 0 | CX34: =IFERROR(CR34/CW34-1, "-") -> - | DE34: =CZ34/DD34-1 -> #DIV/0! | DF34: =DA34/DD34-1 -> #DIV/0! | DG34: =DB34/DD34-1 -> #DIV/0! | DH34: =DC34/DD34-1 -> #DIV/0!
C35: PL29 | CU35: =+CR35-CS35 -> 0 | CV35: =+CR35-CT35 -> 0 | CX35: =IFERROR(CR35/CW35-1, "-") -> -
A36: Amortissements et déprec. Courant | C36: PL30 | CU36: =+CR36-CS36 -> 0 | CV36: =+CR36-CT36 -> 0 | CX36: =IFERROR(CR36/CW36-1, "-") -> - | DE36: =CZ36/DD36-1 -> #DIV/0! | DF36: =DA36/DD36-1 -> #DIV/0! | DG36: =DB36/DD36-1 -> #DIV/0! | DH36: =DC36/DD36-1 -> #DIV/0!
A37: Dotations (Amo. et Pv NC) | C37: PL31 | CU37: =+CR37-CS37 -> 0 | CV37: =+CR37-CT37 -> 0 | CX37: =IFERROR(CR37/CW37-1, "-") -> -
A38: Autres non courant | C38: PL32 | CU38: =+CR38-CS38 -> 0 | CV38: =+CR38-CT38 -> 0 | CX38: =IFERROR(CR38/CW38-1, "-") -> -
A39: +/- value de cession d'immob. | C39: PL33 | CU39: =+CR39-CS39 -> 0 | CV39: =+CR39-CT39 -> 0 | CX39: =IFERROR(CR39/CW39-1, "-") -> -
C40: PL34 | CU40: =+CR40-CS40 -> 0 | CV40: =+CR40-CT40 -> 0 | CX40: =IFERROR(CR40/CW40-1, "-") -> -
A41: EBITA | C41: PL35 | CU41: =+CR41-CS41 -> 0 | CV41: =+CR41-CT41 -> 0 | CX41: =IFERROR(CR41/CW41-1, "-") -> - | DE41: =CZ41/DD41-1 -> #DIV/0! | DF41: =DA41/DD41-1 -> #DIV/0! | DG41: =DB41/DD41-1 -> #DIV/0! | DH41: =DC41/DD41-1 -> #DIV/0!
A42: % CA | C42: PL36 | CU42: =+(CR42-CS42)*100 -> 0 | CV42: =+(CR42-CT42)*100 -> 0 | CX42: =IFERROR(CR42/CW42-1, "-") -> - | DE42: =+(CZ42-DD42)*100 -> 0 | DF42: =DA42/DD42-1 -> #DIV/0! | DG42: =DB42/DD42-1 -> #DIV/0! | DH42: =DC42/DD42-1 -> #DIV/0!
A43: Fixe & Internet | C43: PL37 | CU43: =+CR43-CS43 -> 0 | CV43: =+CR43-CT43 -> 0 | CX43: =IFERROR(CR43/CW43-1, "-") -> - | DE43: =CZ43/DD43-1 -> #DIV/0!
A44: Mobile | C44: PL38 | CU44: =+CR44-CS44 -> 0 | CV44: =+CR44-CT44 -> 0 | CX44: =IFERROR(CR44/CW44-1, "-") -> - | DE44: =CZ44/DD44-1 -> #DIV/0!
C45: PL39 | CU45: =+CR45-CS45 -> 0 | CV45: =+CR45-CT45 -> 0 | CX45: =IFERROR(CR45/CW45-1, "-") -> - | DE45: =CZ45/DD45-1 -> #DIV/0!
C46: PL40 | CU46: =+CR46-CS46 -> 0 | CV46: =+CR46-CT46 -> 0 | CX46: =IFERROR(CR46/CW46-1, "-") -> -
A47: Résultat financier | C47: PL41 | CU47: =+CR47-CS47 -> 0 | CV47: =+CR47-CT47 -> 0 | CX47: =IFERROR(CR47/CW47-1, "-") -> - | DE47: =CZ47/DD47-1 -> #DIV/0! | DF47: =DA47/DD47-1 -> #DIV/0! | DG47: =DB47/DD47-1 -> #DIV/0! | DH47: =DC47/DD47-1 -> #DIV/0!
A48: dont intérêt sur SHL | C48: PL42 | CU48: =+CR48-CS48 -> 0 | CV48: =+CR48-CT48 -> 0 | CX48: =IFERROR(CR48/CW48-1, "-") -> - | DF48: =DA48/DD48-1 -> #DIV/0! | DG48: =DB48/DD48-1 -> #DIV/0!
C49: PL43 | CU49: =+CR49-CS49 -> 0 | CV49: =+CR49-CT49 -> 0 | CX49: =IFERROR(CR49/CW49-1, "-") -> -
A50: RESULTAT avant IS | C50: PL44 | CU50: =+CR50-CS50 -> 0 | CV50: =+CR50-CT50 -> 0 | CX50: =IFERROR(CR50/CW50-1, "-") -> - | DE50: =CZ50/DD50-1 -> #DIV/0! | DF50: =DA50/DD50-1 -> #DIV/0! | DG50: =DB50/DD50-1 -> #DIV/0! | DH50: =DC50/DD50-1 -> #DIV/0!
A51: IS | C51: PL45 | CU51: =+CR51-CS51 -> 0 | CV51: =+CR51-CT51 -> 0 | CX51: =IFERROR(CR51/CW51-1, "-") -> - | DE51: =CZ51/DD51-1 -> #DIV/0! | DF51: =DA51/DD51-1 -> #DIV/0! | DG51: =DB51/DD51-1 -> #DIV/0! | DH51: =DC51/DF51-1 -> #DIV/0!
A52: ID | C52: PL46 | CU52: =+CR52-CS52 -> 0 | CV52: =+CR52-CT52 -> 0 | CX52: =IFERROR(CR52/CW52-1, "-") -> - | DE52: =CZ52/DD52-1 -> #DIV/0! | DF52: =DA52/DD52-1 -> #DIV/0! | DG52: =DB52/DD52-1 -> #DIV/0! | DH52: =DC52/DF52-1 -> #DIV/0!
C53: PL47 | CX53: =IFERROR(CR53/CW53-1, "-") -> -
A54: RESULTAT NET | C54: PL48 | CU54: =+CR54-CS54 -> 0 | CV54: =+CR54-CT54 -> 0 | CX54: =IFERROR(CR54/CW54-1, "-") -> - | DE54: =(CZ54/DD54-1) -> #DIV/0! | DF54: =-(DA54/DD54-1) -> #DIV/0! | DG54: =-(DB54/DD54-1) -> #DIV/0! | DH54: =-(DC54/DD54-1) -> #DIV/0!
C55: PL49 | CX55: =IFERROR(CR55/CW55-1, "-") -> -
A56: % CA | C56: PL50 | CU56: =+(CR56-CS56)*100 -> 0 | CV56: =+(CR56-CT56)*100 -> 0 | CX56: =IFERROR(CR56/CW56-1, "-") -> - | DE56: =+(CZ56-DD56)*100 -> 0 | DF56: =+(DA56-DD56)*100 -> 0 | DG56: =+(DB56-DD56)*100 -> 0 | DH56: =+(DC56-DD56)*100 -> 0
CR58: =CR54-SUM(CJ54,CB54,BT54,BK54,BC54,AU54,AL54,AD54,V54,P54,J54,D54) -> 0
A61: CA PNL | D61: =D7 -> 0 | E61: =E7 -> 0 | G61: =G7 -> 0 | M61: =M7 -> 0 | P61: =P7 -> 0 | Q61: =Q7 -> 0 | S61: =S7 -> 0 | V61: =V7 -> 0 | W61: =W7 -> 0 | AA61: =AA7 -> 0 | AD61: =AD7 -> 0 | AE61: =AE7 -> 0 | AI61: =AI7 -> 0 | AL61: =AL7 -> 0 | AM61: =AM7 -> 0 | AR61: =AR7 -> 0 | AU61: 8581.7161 | AV61: 9776.3005 | AZ61: 8753.0121 | BC61: 8351.3134 | BD61: 9829.75 | BH61: 8653.6552 | BK61: =BK7 -> 0 | BL61: =BL7 -> 0 | BQ61: =BQ7 -> 0 | BT61: =BT7 -> 0 | BU61: =BU7 -> 0 | BY61: =BY7 -> 0 | CB61: =CB7 -> 0 | CC61: =CC7 -> 0 | CG61: =CG7 -> 0 | CJ61: =CJ7 -> 0 | CK61: =CK7 -> 0 | CL61: =CL7 -> 0 | CO61: =CO7 -> 0 | CR61: =CR7 -> 0 | CS61: =CS7 -> 0 | CT61: =CT7 -> 0 | CW61: =CW7 -> 0
A62: CA | D62: ='CA Mobile'!D8 -> 0 | E62: ='CA Mobile'!E8 -> 0 | G62: ='CA Mobile'!G8 -> 0 | M62: ='CA Mobile'!M8 -> 0 | P62: ='CA Mobile'!P8 -> 0 | Q62: ='CA Mobile'!Q8 -> 0 | S62: ='CA Mobile'!S8 -> 0 | V62: ='CA Mobile'!V8 -> 0 | W62: ='CA Mobile'!W8 -> 0 | AA62: ='CA Mobile'!AA8 -> 0 | AD62: ='CA Mobile'!AD8 -> 0 | AE62: ='CA Mobile'!AE8 -> 0 | AI62: ='CA Mobile'!AI8 -> 0 | AL62: ='CA Mobile'!AL8 -> 0 | AM62: ='CA Mobile'!AM8 -> 0 | AR62: ='CA Mobile'!AR8 -> 0 | AU62: 8581.7161 | AV62: 9776.3005 | AZ62: 8753.0121 | BC62: 8351.3134 | BD62: 9829.75 | BH62: 8653.6552 | BK62: ='CA Mobile'!BK8 -> 0 | BL62: ='CA Mobile'!BL8 -> 0 | BQ62: ='CA Mobile'!BQ8 -> 0 | BT62: ='CA Mobile'!BT8 -> 0 | BU62: ='CA Mobile'!BU8 -> 0 | BY62: ='CA Mobile'!BY8 -> 0 | CB62: ='CA Mobile'!CB8 -> 0 | CC62: ='CA Mobile'!CC8 -> 0 | CG62: ='CA Mobile'!CG8 -> 0 | CJ62: ='CA Mobile'!CJ8 -> 0 | CK62: ='CA Mobile'!CK8 -> 0 | CL62: =+'CA Mobile'!CL8 -> 0 | CO62: ='CA Mobile'!CO8 -> 0 | CR62: ='CA Mobile'!CR8 -> 0 | CS62: ='CA Mobile'!CS8 -> 0 | CT62: ='CA Mobile'!CT8 -> 0 | CW62: ='CA Mobile'!CW8 -> 0
A63: CHECK | D63: =D61-D62 -> 0 | E63: =E61-E62 -> 0 | G63: =G61-G62 -> 0 | M63: =M61-M62 -> 0 | P63: =P61-P62 -> 0 | Q63: =Q61-Q62 -> 0 | S63: =S61-S62 -> 0 | V63: =V61-V62 -> 0 | W63: =W61-W62 -> 0 | AA63: =AA61-AA62 -> 0 | AD63: =AD61-AD62 -> 0 | AE63: =AE61-AE62 -> 0 | AI63: =AI61-AI62 -> 0 | AL63: =AL61-AL62 -> 0 | AM63: =AM61-AM62 -> 0 | AR63: =AR61-AR62 -> 0 | AU63: 0 | AV63: 0 | AZ63: 0 | BC63: 0 | BD63: 0 | BH63: 0 | BK63: =BK61-BK62 -> 0 | BL63: =BL61-BL62 -> 0 | BQ63: =BQ61-BQ62 -> 0 | BT63: =BT61-BT62 -> 0 | BU63: =BU61-BU62 -> 0 | BY63: =BY61-BY62 -> 0 | CB63: =CB61-CB62 -> 0 | CC63: =CC61-CC62 -> 0 | CG63: =CG61-CG62 -> 0 | CJ63: =CJ61-CJ62 -> 0 | CK63: =CK61-CK62 -> 0 | CL63: =+CL61-CL62 -> 0 | CO63: =CO61-CO62 -> 0 | CR63: =CR61-CR62 -> 0 | CS63: =CS61-CS62 -> 0 | CT63: =CT61-CT62 -> 0 | CU63: =CU61-CU62 -> 0 | CV63: =CV61-CV62 -> 0 | CW63: =CW61-CW62 -> 0
A64: CA MARGES | D64: ='Marge Mobile'!D7 -> 0 | E64: ='Marge Mobile'!E7 -> 0 | G64: ='Marge Mobile'!G7 -> 0 | M64: ='Marge Mobile'!M7 -> 0 | P64: ='Marge Mobile'!P7 -> 0 | Q64: ='Marge Mobile'!Q7 -> 0 | S64: ='Marge Mobile'!S7 -> 0 | V64: ='Marge Mobile'!V7 -> 0 | W64: ='Marge Mobile'!W7 -> 0 | AA64: ='Marge Mobile'!AA7 -> 0 | AD64: ='Marge Mobile'!AD7 -> 0 | AE64: ='Marge Mobile'!AE7 -> 0 | AI64: ='Marge Mobile'!AI7 -> 0 | AL64: ='Marge Mobile'!AL7 -> 0 | AM64: ='Marge Mobile'!AM7 -> 0 | AR64: ='Marge Mobile'!AR7 -> 0 | AU64: 8581.7161 | AV64: 9776.3005 | AZ64: 8753.0121 | BC64: 8351.3134 | BD64: 9829.75 | BH64: 8653.6552 | BK64: ='Marge Mobile'!BK7 -> 0 | BL64: ='Marge Mobile'!BL7 -> 0 | BQ64: ='Marge Mobile'!BQ7 -> 0 | BT64: ='Marge Mobile'!BT7 -> 0 | BU64: ='Marge Mobile'!BU7 -> 0 | BY64: ='Marge Mobile'!BY7 -> 0 | CB64: ='Marge Mobile'!CB7 -> 0 | CC64: ='Marge Mobile'!CC7 -> 0 | CG64: ='Marge Mobile'!CG7 -> 0 | CJ64: ='Marge Mobile'!CJ7 -> 0 | CK64: ='Marge Mobile'!CK7 -> 0 | CL64: ='Marge Mobile'!CL7 -> 0 | CO64: ='Marge Mobile'!CO7 -> 0 | CR64: ='Marge Mobile'!CR7 -> 0 | CS64: ='Marge Mobile'!CS7 -> 0 | CT64: ='Marge Mobile'!CT7 -> 0 | CW64: ='Marge Mobile'!CW7 -> 0
A65: CHECK | D65: =D61-D64 -> 0 | E65: =E61-E64 -> 0 | G65: =G61-G64 -> 0 | M65: =M61-M64 -> 0 | P65: =P61-P64 -> 0 | Q65: =Q61-Q64 -> 0 | S65: =S61-S64 -> 0 | V65: =V61-V64 -> 0 | W65: =W61-W64 -> 0 | AA65: =AA61-AA64 -> 0 | AD65: =AD61-AD64 -> 0 | AE65: =AE61-AE64 -> 0 | AI65: =AI61-AI64 -> 0 | AL65: =AL61-AL64 -> 0 | AM65: =AM61-AM64 -> 0 | AR65: =AR61-AR64 -> 0 | AU65: 0 | AV65: 0 | AZ65: 0 | BC65: 0 | BD65: 0 | BH65: 0 | BK65: =BK61-BK64 -> 0 | BL65: =BL61-BL64 -> 0 | BQ65: =BQ61-BQ64 -> 0 | BT65: =BT61-BT64 -> 0 | BU65: =BU61-BU64 -> 0 | BY65: =BY61-BY64 -> 0 | CB65: =CB61-CB64 -> 0 | CC65: =CC61-CC64 -> 0 | CG65: =CG61-CG64 -> 0 | CJ65: =CJ61-CJ64 -> 0 | CK65: =CK61-CK64 -> 0 | CL65: =CL61-CL64 -> 0 | CM65: =CM61-CM64 -> 0 | CN65: =CN61-CN64 -> 0 | CO65: =CO61-CO64 -> 0 | CR65: =CR61-CR64 -> 0 | CS65: =CS61-CS64 -> 0 | CT65: =CT61-CT64 -> 0 | CU65: =CU61-CU64 -> 0 | CV65: =CV61-CV64 -> 0 | CW65: =CW61-CW64 -> 0
A66: OPEX PNL | D66: =D25 -> 0 | E66: =E25 -> 0 | G66: =G25 -> 0 | M66: =M25 -> 0 | P66: =P25 -> 0 | Q66: =Q25 -> 0 | S66: =S25 -> 0 | V66: =V25 -> 0 | W66: =W25 -> 0 | AA66: =AA25 -> 0 | AD66: =AD25 -> 0 | AE66: =AE25 -> 0 | AI66: =AI25 -> 0 | AL66: =AL25 -> 0 | AM66: =AM25 -> 0 | AR66: =AR25 -> 0 | AU66: -5235.8027 | AV66: -5853.3972 | AZ66: -5748.7478 | BC66: -5276.3231 | BD66: -5736.1233 | BH66: -5142.3972 | BK66: =BK25 -> 0 | BL66: =BL25 -> 0 | BQ66: =BQ25 -> 0 | BT66: =BT25 -> 0 | BU66: =BU25 -> 0 | BY66: =BY25 -> 0 | CB66: =CB25 -> 0 | CC66: =CC25 -> 0 | CG66: =CG25 -> 0 | CJ66: =CJ25 -> 0 | CK66: =CK25 -> 0 | CL66: =CL25 -> 0 | CO66: =CO25 -> 0 | CR66: =CR25 -> 0 | CS66: =CS25 -> 0 | CT66: =CT25 -> 0 | CW66: =CW25 -> 0
A67: OPEX | D67: ='Opex Consolidés'!D7 -> 0 | E67: ='Opex Consolidés'!E7 -> 0 | G67: ='Opex Consolidés'!G7 -> 0 | M67: ='Opex Consolidés'!M7 -> 0 | P67: ='Opex Consolidés'!P7 -> 0 | Q67: ='Opex Consolidés'!Q7 -> 0 | S67: ='Opex Consolidés'!S7 -> 0 | V67: ='Opex Consolidés'!V7 -> 0 | W67: ='Opex Consolidés'!W7 -> 0 | AA67: ='Opex Consolidés'!AA7 -> 0 | AD67: ='Opex Consolidés'!AD7 -> 0 | AE67: ='Opex Consolidés'!AE7 -> 0 | AI67: ='Opex Consolidés'!AI7 -> 0 | AL67: ='Opex Consolidés'!AL7 -> 0 | AM67: ='Opex Consolidés'!AM7 -> 0 | AR67: ='Opex Consolidés'!AR7 -> 0 | AU67: 5235.8027 | AV67: 5853.3972 | AZ67: 5748.7478 | BC67: 5276.3231 | BD67: 5736.1233 | BH67: 5142.3972 | BK67: ='Opex Consolidés'!BK7 -> 0 | BL67: ='Opex Consolidés'!BL7 -> 0 | BQ67: ='Opex Consolidés'!BQ7 -> 0 | BT67: ='Opex Consolidés'!BT7 -> 0 | BU67: ='Opex Consolidés'!BU7 -> 0 | BY67: ='Opex Consolidés'!BY7 -> 0 | CB67: ='Opex Consolidés'!CB7 -> 0 | CC67: ='Opex Consolidés'!CC7 -> 0 | CG67: ='Opex Consolidés'!CG7 -> 0 | CJ67: ='Opex Consolidés'!CJ7 -> 0 | CK67: ='Opex Consolidés'!CK7 -> 0 | CL67: ='Opex Consolidés'!#REF! -> #REF! | CO67: ='Opex Consolidés'!CO7 -> 0 | CR67: ='Opex Consolidés'!CR7 -> 0 | CS67: ='Opex Consolidés'!CS7 -> 0 | CT67: ='Opex Consolidés'!CT7 -> 0 | CW67: ='Opex Consolidés'!CW7 -> 0
A68: CHECK | D68: =D66+D67 -> 0 | E68: =E66+E67 -> 0 | G68: =G66+G67 -> 0 | M68: =M66+M67 -> 0 | P68: =P66+P67 -> 0 | Q68: =Q66+Q67 -> 0 | S68: =S66+S67 -> 0 | V68: =V66+V67 -> 0 | W68: =W66+W67 -> 0 | AA68: =AA66+AA67 -> 0 | AD68: =AD66+AD67 -> 0 | AE68: =AE66+AE67 -> 0 | AI68: =AI66+AI67 -> 0 | AL68: =AL66+AL67 -> 0 | AM68: =AM66+AM67 -> 0 | AR68: =AR66+AR67 -> 0 | AU68: 0 | AV68: 0 | AZ68: 0 | BC68: 0 | BD68: 0 | BH68: 0 | BK68: =BK66+BK67 -> 0 | BL68: =BL66+BL67 -> 0 | BQ68: =BQ66+BQ67 -> 0 | BT68: =BT66+BT67 -> 0 | BU68: =BU66+BU67 -> 0 | BY68: =BY66+BY67 -> 0 | CB68: =CB66+CB67 -> 0 | CC68: =CC66+CC67 -> 0 | CG68: =CG66+CG67 -> 0 | CJ68: =CJ66+CJ67 -> 0 | CK68: =CK66+CK67 -> 0 | CL68: =CL66+CL67 -> #REF! | CM68: =CM66+CM67 -> 0 | CN68: =CN66+CN67 -> 0 | CO68: =CO66+CO67 -> 0 | CR68: =CR66+CR67 -> 0 | CS68: =CS66+CS67 -> 0 | CT68: =CT66+CT67 -> 0 | CW68: =CW66+CW67 -> 0
D72: =D7-'CA Mobile'!D8 -> 0 | E72: =E7-'CA Mobile'!E8 -> 0 | F72: =F7-'CA Mobile'!F8 -> 0 | G72: =G7-'CA Mobile'!G8 -> 0 | H72: =H7-'CA Mobile'!H8 -> 0 | I72: =I7-'CA Mobile'!I8 -> 0 | L72: =L7-'CA Mobile'!L8 -> 0 | M72: =M7-'CA Mobile'!M8 -> 0 | N72: =N7-'CA Mobile'!N8 -> 0 | O72: =O7-'CA Mobile'!O8 -> 0 | P72: =P7-'CA Mobile'!P8 -> 0 | Q72: =Q7-'CA Mobile'!Q8 -> 0 | R72: =R7-'CA Mobile'!R8 -> 0 | S72: =S7-'CA Mobile'!S8 -> 0 | ... AT72: =AT7-'CA Mobile'!AT8 -> 0 | AU72: 0 | AV72: 0 | AW72: 0 | AX72: 0 | AY72: 0 | AZ72: 0 | BA72: 0 | BB72: =BB7-'CA Mobile'!BB8 -> 0 | BC72: 0 | BD72: 0 | BE72: 0 | BF72: 0 | BG72: 1.8189894e-12 | BH72: 0 | BI72: 0 | BJ72: =BJ7-'CA Mobile'!BJ8 -> 0 | BK72: =BK7-'CA Mobile'!BK8 -> 0 | BL72: =BL7-'CA Mobile'!BL8 -> 0 | BM72: =BM7-'CA Mobile'!BM8 -> 0 | BN72: =BN7-'CA Mobile'!BN8 -> 0 | BO72: =BO7-'CA Mobile'!BO8 -> 0 | BP72: =BP7-'CA Mobile'!BP8 -> 0 | BQ72: =BQ7-'CA Mobile'!BQ8 -> 0 | ... DH72: =DH7-'CA Mobile'!DH8 -> #DIV/0!
D73: =D15-'Marge Mobile'!D58 -> 0 | E73: =E15-'Marge Mobile'!E58 -> 0 | F73: =F15-'Marge Mobile'!F58 -> 0 | G73: =G15-'Marge Mobile'!G58 -> 0 | H73: =H15-'Marge Mobile'!H58 -> 0 | I73: =I15-'Marge Mobile'!I58 -> 0 | L73: =L15-'Marge Mobile'!L58 -> 0 | M73: =M15-'Marge Mobile'!M58 -> 0 | N73: =N15-'Marge Mobile'!N58 -> 0 | O73: =O15-'Marge Mobile'!O58 -> 0 | P73: =P15-'Marge Mobile'!P58 -> 0 | Q73: =Q15-'Marge Mobile'!Q58 -> 0 | R73: =R15-'Marge Mobile'!R58 -> 0 | S73: =S15-'Marge Mobile'!S58 -> 0 | ... AT73: =AT15-'Marge Mobile'!AT58 -> 0 | AU73: 0 | AV73: 0 | AW73: 0 | AX73: 0 | AY73: 0 | AZ73: 0 | BA73: 0 | BB73: =BB15-'Marge Mobile'!BB58 -> 0 | BC73: 0 | BD73: 0 | BE73: 0 | BF73: 0 | BG73: 0 | BH73: 0 | BI73: 0 | BJ73: =BJ15-'Marge Mobile'!BJ58 -> 0 | BK73: =BK15-'Marge Mobile'!BK58 -> 0 | BL73: =BL15-'Marge Mobile'!BL58 -> 0 | BM73: =BM15-'Marge Mobile'!BM58 -> 0 | BN73: =BN15-'Marge Mobile'!BN58 -> 0 | BO73: =BO15-'Marge Mobile'!BO58 -> 0 | BP73: =BP15-'Marge Mobile'!BP58 -> 0 | BQ73: =BQ15-'Marge Mobile'!BQ58 -> 0 | ... DH73: =DH15-'Marge Mobile'!DH58 -> #DIV/0!
D74: =D20-'Marge Mobile'!D60 -> 0 | E74: =E20-'Marge Mobile'!E60 -> 0 | F74: =F20-'Marge Mobile'!F60 -> 0 | G74: =G20-'Marge Mobile'!G60 -> 0 | H74: =H20-'Marge Mobile'!H60 -> 0 | I74: =I20-'Marge Mobile'!I60 -> 0 | L74: =L20-'Marge Mobile'!L60 -> 0 | M74: =M20-'Marge Mobile'!M60 -> 0 | N74: =N20-'Marge Mobile'!N60 -> 0 | O74: =O20-'Marge Mobile'!O60 -> 0 | P74: =P20-'Marge Mobile'!P60 -> 0 | Q74: =Q20-'Marge Mobile'!Q60 -> 0 | R74: =R20-'Marge Mobile'!R60 -> 0 | S74: =S20-'Marge Mobile'!S60 -> 0 | ... AT74: =AT20-'Marge Mobile'!AT60 -> 0 | AU74: 0 | AV74: 0 | AW74: 0 | AX74: 0 | AY74: 0 | AZ74: 0 | BA74: 0 | BB74: =BB20-'Marge Mobile'!BB60 -> 0 | BC74: 0 | BD74: 0 | BE74: 0 | BF74: 0 | BG74: 0 | BH74: 0 | BI74: 0 | BJ74: =BJ20-'Marge Mobile'!BJ60 -> 0 | BK74: =BK20-'Marge Mobile'!BK60 -> 0 | BL74: =BL20-'Marge Mobile'!BL60 -> 0 | BM74: =BM20-'Marge Mobile'!BM60 -> 0 | BN74: =BN20-'Marge Mobile'!BN60 -> 0 | BO74: =BO20-'Marge Mobile'!BO60 -> 0 | BP74: =BP20-'Marge Mobile'!BP60 -> 0 | BQ74: =BQ20-'Marge Mobile'!BQ60 -> 0 | ... DH74: =DH20-'Marge Mobile'!DH60 -> #DIV/0!
D75: =D25+'Opex Consolidés'!D7 -> 0 | E75: =E25+'Opex Consolidés'!E7 -> 0 | F75: =F25+'Opex Consolidés'!F7 -> 0 | G75: =G25+'Opex Consolidés'!G7 -> 0 | H75: =H25+'Opex Consolidés'!H7 -> 0 | I75: =I25+'Opex Consolidés'!I7 -> 0 | L75: =L25+'Opex Consolidés'!L7 -> 0 | M75: =M25+'Opex Consolidés'!M7 -> 0 | N75: =N25+'Opex Consolidés'!N7 -> 0 | O75: =O25+'Opex Consolidés'!O7 -> 0 | P75: =P25+'Opex Consolidés'!P7 -> 0 | Q75: =Q25+'Opex Consolidés'!Q7 -> 0 | R75: =R25+'Opex Consolidés'!R7 -> 0 | S75: =S25+'Opex Consolidés'!S7 -> 0 | ... AA75: =AA25+'Opex Consolidés'!AA7 -> 0 | AB75: =#REF! -> #REF! | AC75: =AC25+'Opex Consolidés'!AC7 -> 0 | AD75: =AD25+'Opex Consolidés'!AD7 -> 0 | AE75: =AE25+'Opex Consolidés'!AE7 -> 0 | AF75: =AF25+'Opex Consolidés'!AF7 -> 0 | AG75: =AG25+'Opex Consolidés'!AG7 -> 0 | AH75: =AH25+'Opex Consolidés'!AH7 -> 0 | AI75: =AI25+'Opex Consolidés'!AI7 -> 0 | AJ75: =AJ25+'Opex Consolidés'!AJ7 -> 0 | ... AT75: =AT25+'Opex Consolidés'!AT7 -> 0 | AU75: 0 | AV75: 0 | AW75: 0 | AX75: 0 | AY75: 0 | AZ75: 0 | BA75: -0.17845454 | BB75: =BB25+'Opex Consolidés'!BB7 -> 0 | BC75: 0 | BD75: 0 | BE75: 0 | BF75: 0 | BG75: 0 | BH75: 0 | BI75: 0.052086955 | BJ75: =BJ25+'Opex Consolidés'!BJ7 -> 0 | BK75: =BK25+'Opex Consolidés'!BK7 -> 0 | BL75: =BL25+'Opex Consolidés'!BL7 -> 0 | BM75: =BM25+'Opex Consolidés'!BM7 -> 0 | BN75: =BN25+'Opex Consolidés'!BN7 -> 0 | BO75: =BO25+'Opex Consolidés'!BO7 -> 0 | BP75: =BP25+'Opex Consolidés'!BP7 -> 0 | BQ75: =BQ25+'Opex Consolidés'!BQ7 -> 0 | ... DH75: =DH25+'Opex Consolidés'!DH7 -> #DIV/0!

Sheet Opex Consolidés
J1: 6444110418 | Y1: =Y7/W7 -> #DIV/0! | Z1: =Z7/X7 -> #DIV/0! | AU1: -20648636 | AW1: 12.127701 | CR1: =65151.9-CR7 -> 65151.9 | DP1: 0
A2: Opex Consolidés | J2: 419560633 | K2: 0 | P2: 21468044 | W2: 839.68735 | X2: 0 | AD2: 0 | AE2: 0 | AF2: 2024 Réel | AO2: 0 | AU2: 0 | BN2: 0 | BP2: 0 | CR2: =CS7+'P&L conso'!CS25 -> 0 | CT2: =CT7+'P&L conso'!CT25 -> 0 | DP2: 10167534 | DQ2: 0 | DR2: 0 | DU2: 0
E3: 0 | G3: 0 | CZ3: 0 | DQ3: 295188041
D4: 45292 | J4: 45323 | P4: 45352 | V4: 45383 | AD4: 45413 | AL4: 45444 | AU4: 45474 | BC4: 45505 | BK4: 45536 | BT4: 45566 | CB4: 45597 | CJ4: 45627 | CR4: CUMUL | CZ4: ANNUEL
B5: (En Millions ML) | D5: 2024 Réel | E5: 2024 Budget | F5: Ecart / Budget | G5: 2023 Réel | H5: Evol % | J5: 2024 Réel | K5: 2024 Budget | L5: Ecart / Budget | M5: 2023 Réel | N5: Evol % | P5: 2024 Réel | Q5: 2024 Budget | R5: Ecart / Budget | S5: 2023 Réel | T5: Evol % | V5: 2024 Réel | W5: 2024 Budget | X5: 2024 Actu1 | Y5: Ecart / Budget | Z5: Ecart / Actu1 | AA5: 2023 Réel | AB5: Evol % | AD5: 2024 Réel | AE5: 2024 Budget | AF5: 2024 Actu1 | AG5: Ecart / Budget | AH5: Ecart / Actu1 | AI5: 2023 Réel | AJ5: Evol % | AL5: 2024 Réel | AM5: 2024 Budget | AN5: 2024 Actu1 | AO5: 2024 Actu2 | AP5: Ecart / Budget | AQ5: Ecart / Actu1 | AR5: 2023 Réel | AS5: Evol % | AU5: 2024 Réel | AV5: 2024 Budget | AW5: 2024 Actu2 | AX5: Ecart / Budget | AY5: Ecart / Actu2 | AZ5: 2023 Réel | BA5: Evol % | BC5: 2024 Réel | BD5: 2024 Budget | BE5: 2024 Actu2 | BF5: Ecart / Budget | BG5: Ecart / Actu2 | BH5: 2023 Réel | BI5: Evol % | BK5: 2024 Réel | BL5: 2024 Budget | BM5: 2024 Actu2 | BN5: 2024 Actu3 | BO5: Ecart / Budget | BP5: Ecart / Actu2 | BQ5: 2023 Réel | BR5: Evol % | BT5: 2024 Réel | BU5: 2024 Budget | BV5: 2024 Actu3 | BW5: Ecart / Budget | BX5: Ecart / Actu3 | BY5: 2023 Réel | BZ5: Evol % | CB5: 2024 Réel | CC5: 2024 Budget | CD5: 2024 Actu3 | CE5: Ecart / Budget | CF5: Ecart / Actu3 | CG5: 2023 Réel | CH5: Evol % | CJ5: 2024 Réel | CK5: 2024 Budget | CL5: 2024 Actu3 | CM5: Ecart / Budget | CN5: Ecart / Actu3 | CO5: 2023 Réel | CP5: Evol % | CR5: 2024 Réel | CS5: 2024 Budget | CT5: 2024 Actu3 | CU5: Ecart / Budget | CV5: Ecart / Actu3 | CW5: 2023 Réel | CX5: Evol % | CZ5: 2024 Budget | DA5: 2024 Actu1 | DB5: 2024 Actu2 | DC5: 2024 Actu3 | DD5: 2023 Réel | DE5: Bud / 2023 (%) | DF5: Actu 1 / 2023 (%) | DG5: Actu 2 / 2023 (%) | DH5: Actu3 / 2023 (%) | DJ5: 2024 Réel | DK5: 2024 Budget | DL5: 2023 Réel | DM5: Actu | DP5: 2024 Réel
DJ6: =SUM(D6,J6,P6,V6,AD6,AL6,AU6,BC6,BK6,BT6,CB6,CJ6)-CR6 -> 0 | DK6: =SUM(E6,K6,Q6,W6,AE6,AM6,AV6,BD6,BL6,BU6,CC6,CK6)-CS6 -> 0 | DL6: =SUM(G6,M6,S6,AA6,AI6,AR6,AZ6,BH6,BQ6,BY6,CG6,CO6)-CW6 -> 0 | DM6: =SUM(D6,J6,P6,V6,AD6,AL6,AU6,BC6,,BN6,BV6,CD6,CL6)-CT6 -> 0
B7: Total Opex | C7: Opex1 | CU7: =+CR7-CS7 -> 0 | CV7: =+CR7-CT7 -> 0 | CX7: =IFERROR(CR7/CW7-1, "-") -> - | DE7: =+CZ7/DD7-1 -> #DIV/0! | DF7: =+DA7/DD7-1 -> #DIV/0! | DG7: =+DB7/DD7-1 -> #DIV/0! | DH7: =+DC7/DD7-1 -> #DIV/0! | DJ7: =SUM(D7,J7,P7,V7,AD7,AL7,AU7,BC7,BK7,BT7,CB7,CJ7)-CR7 -> 0 | DK7: =SUM(E7,K7,Q7,W7,AE7,AM7,AV7,BD7,BL7,BU7,CC7,CK7)-CS7 -> 0 | DL7: =SUM(G7,M7,S7,AA7,AI7,AR7,AZ7,BH7,BQ7,BY7,CG7,CO7)-CW7 -> 0 | DM7: =SUM(D7,J7,P7,V7,AD7,AL7,AU7,BC7,,BN7,BV7,CD7,CL7)-CT7 -> 0 | DP7: =SUM(DP9,DP40,DP57,DP113,DP167,DP184,DP201) -> #VALUE! | DQ7: =-CR7+DP7/10^6 -> #VALUE! | DR7: =SUM(E7,K7,Q7,W7,AE7,AM7,AV7,BD7,BL7,BU7,CC7,CK7)-CS7 -> 0 | DS7: =SUM(D7,J7,P7,V7,AD7,AL7,AU7,BC7,,BN7,BV7,CD7,CL7)-CT7 -> 0 | DU7: 6509.7557 | DV7: =DU7-CJ7 -> 6509.7557
C8: Opex2 | CX8: =IFERROR(CR8/CW8-1, "-") -> - | DJ8: =SUM(D8,J8,P8,V8,AD8,AL8,AU8,BC8,BK8,BT8,CB8,CJ8)-CR8 -> 0 | DK8: =SUM(E8,K8,Q8,W8,AE8,AM8,AV8,BD8,BL8,BU8,CC8,CK8)-CS8 -> 0 | DL8: =SUM(G8,M8,S8,AA8,AI8,AR8,AZ8,BH8,BQ8,BY8,CG8,CO8)-CW8 -> 0 | DM8: =SUM(D8,J8,P8,V8,AD8,AL8,AU8,BC8,,BN8,BV8,CD8,CL8)-CT8 -> 0 | DQ8: =-CR8+DP8/10^6 -> 0 | DR8: =SUM(E8,K8,Q8,W8,AE8,AM8,AV8,BD8,BL8,BU8,CC8,CK8)-CS8 -> 0 | DS8: =SUM(D8,J8,P8,V8,AD8,AL8,AU8,BC8,,BN8,BV8,CD8,CL8)-CT8 -> 0 | DV8: =DU8-CJ8 -> 0 | DX8: =CS8-CZ8 -> 0 | DY8: =CT8-DC8 -> 0 | DZ8: =CW8-DD8 -> 0
B9: Personnel | C9: Opex3 | CU9: =+CR9-CS9 -> 0 | CV9: =+CR9-CT9 -> 0 | CX9: =IFERROR(CR9/CW9-1, "-") -> - | DE9: =+CZ9/DD9-1 -> #DIV/0! | DF9: =+DA9/DD9-1 -> #DIV/0! | DG9: =+DB9/DD9-1 -> #DIV/0! | DH9: =+DC9/DD9-1 -> #DIV/0! | DJ9: =SUM(D9,J9,P9,V9,AD9,AL9,AU9,BC9,BK9,BT9,CB9,CJ9)-CR9 -> 0 | DK9: =SUM(E9,K9,Q9,W9,AE9,AM9,AV9,BD9,BL9,BU9,CC9,CK9)-CS9 -> 0 | DL9: =SUM(G9,M9,S9,AA9,AI9,AR9,AZ9,BH9,BQ9,BY9,CG9,CO9)-CW9 -> 0 | DM9: =SUM(D9,J9,P9,V9,AD9,AL9,AU9,BC9,,BN9,BV9,CD9,CL9)-CT9 -> 0 | DP9: =SUM(DP10:DP38) -> #VALUE! | DQ9: =-CR9+DP9/10^6 -> #VALUE! | DR9: =SUM(E9,K9,Q9,W9,AE9,AM9,AV9,BD9,BL9,BU9,CC9,CK9)-CS9 -> 0 | DS9: =SUM(D9,J9,P9,V9,AD9,AL9,AU9,BC9,,BN9,BV9,CD9,CL9)-CT9 -> 0 | DU9: 438.17153 | DV9: =DU9-CJ9 -> 438.17153 | DX9: =(CS9-CZ9)*10^6 -> 0 | DY9: =(CT9-DC9)*10^6 -> 0 | DZ9: =(CW9-DD9)*10^6 -> 0
B10: TAXES SUR APPOINTEMENTS ET SAL | C10: Opex4 | CU10: =+CR10-CS10 -> 0 | CV10: =+CR10-CT10 -> 0 | CX10: =IFERROR(CR10/CW10-1, "-") -> - | DJ10: =SUM(D10,J10,P10,V10,AD10,AL10,AU10,BC10,BK10,BT10,CB10,CJ10)-CR10 -> 0 | DK10: =SUM(E10,K10,Q10,W10,AE10,AM10,AV10,BD10,BL10,BU10,CC10,CK10)-CS10 -> 0 | DL10: =SUM(G10,M10,S10,AA10,AI10,AR10,AZ10,BH10,BQ10,BY10,CG10,CO10)-CW10 -> 0 | DM10: =SUM(D10,J10,P10,V10,AD10,AL10,AU10,BC10,,BN10,BV10,CD10,CL10)-CT10 -> 0 | DQ10: =-CR10+DP10/10^6 -> 0 | DR10: =SUM(E10,K10,Q10,W10,AE10,AM10,AV10,BD10,BL10,BU10,CC10,CK10)-CS10 -> 0 | DS10: =SUM(D10,J10,P10,V10,AD10,AL10,AU10,BC10,,BN10,BV10,CD10,CL10)-CT10 -> 0 | DV10: =DU10-CJ10 -> 0 | DX10: =(CS10-CZ10)*10^6 -> 0 | DY10: =(CT10-DC10)*10^6 -> 0 | DZ10: =(CW10-DD10)*10^6 -> 0
B11: APPOINTEMENTS, SALAIRES PERSON | C11: Opex5 | CU11: =+CR11-CS11 -> 0 | CV11: =+CR11-CT11 -> 0 | CX11: =IFERROR(CR11/CW11-1, "-") -> - | DE11: =+CZ11/DD11-1 -> #DIV/0! | DF11: =+DA11/DD11-1 -> #DIV/0! | DG11: =+DB11/DD11-1 -> #DIV/0! | DH11: =+DC11/DD11-1 -> #DIV/0! | DJ11: =SUM(D11,J11,P11,V11,AD11,AL11,AU11,BC11,BK11,BT11,CB11,CJ11)-CR11 -> 0 | DK11: =SUM(E11,K11,Q11,W11,AE11,AM11,AV11,BD11,BL11,BU11,CC11,CK11)-CS11 -> 0 | DL11: =SUM(G11,M11,S11,AA11,AI11,AR11,AZ11,BH11,BQ11,BY11,CG11,CO11)-CW11 -> 0 | DM11: =SUM(D11,J11,P11,V11,AD11,AL11,AU11,BC11,,BN11,BV11,CD11,CL11)-CT11 -> 0 | DP11: =#VALUE! -> #VALUE! | DQ11: =-CR11+DP11/10^6 -> #VALUE! | DR11: =SUM(E11,K11,Q11,W11,AE11,AM11,AV11,BD11,BL11,BU11,CC11,CK11)-CS11 -> 0 | DS11: =SUM(D11,J11,P11,V11,AD11,AL11,AU11,BC11,,BN11,BV11,CD11,CL11)-CT11 -> 0 | DT11: =DQ11/11 -> #VALUE! | DU11: 262.72376 | DV11: =DU11-CJ11 -> 262.72376 | DX11: =(CS11-CZ11)*10^6 -> 0 | DY11: =(CT11-DC11)*10^6 -> 0 | DZ11: =(CW11-DD11)*10^6 -> 0
B12: CONGES PAYES PERSONNEL NATIONA | C12: Opex6 | CU12: =+CR12-CS12 -> 0 | CV12: =+CR12-CT12 -> 0 | CX12: =IFERROR(CR12/CW12-1, "-") -> - | DE12: =+CZ12/DD12-1 -> #DIV/0! | DF12: =+DA12/DD12-1 -> #DIV/0! | DG12: =+DB12/DD12-1 -> #DIV/0! | DH12: =+DC12/DD12-1 -> #DIV/0! | DJ12: =SUM(D12,J12,P12,V12,AD12,AL12,AU12,BC12,BK12,BT12,CB12,CJ12)-CR12 -> 0 | DK12: =SUM(E12,K12,Q12,W12,AE12,AM12,AV12,BD12,BL12,BU12,CC12,CK12)-CS12 -> 0 | DL12: =SUM(G12,M12,S12,AA12,AI12,AR12,AZ12,BH12,BQ12,BY12,CG12,CO12)-CW12 -> 0 | DM12: =SUM(D12,J12,P12,V12,AD12,AL12,AU12,BC12,,BN12,BV12,CD12,CL12)-CT12 -> 0 | DP12: =#VALUE! -> #VALUE! | DQ12: =-CR12+DP12/10^6 -> #VALUE! | DR12: =SUM(E12,K12,Q12,W12,AE12,AM12,AV12,BD12,BL12,BU12,CC12,CK12)-CS12 -> 0 | DS12: =SUM(D12,J12,P12,V12,AD12,AL12,AU12,BC12,,BN12,BV12,CD12,CL12)-CT12 -> 0 | DU12: -31.251393 | DV12: =DU12-CJ12 -> -31.251393 | DX12: =(CS12-CZ12)*10^6 -> 0 | DY12: =(CT12-DC12)*10^6 -> 0 | DZ12: =(CW12-DD12)*10^6 -> 0
B13: CHARGES SOCIALES S/ REMUNERATI | C13: Opex7 | CU13: =+CR13-CS13 -> 0 | CV13: =+CR13-CT13 -> 0 | CX13: =IFERROR(CR13/CW13-1, "-") -> - | DE13: =+CZ13/DD13-1 -> #DIV/0! | DF13: =+DA13/DD13-1 -> #DIV/0! | DG13: =+DB13/DD13-1 -> #DIV/0! | DH13: =+DC13/DD13-1 -> #DIV/0! | DJ13: =SUM(D13,J13,P13,V13,AD13,AL13,AU13,BC13,BK13,BT13,CB13,CJ13)-CR13 -> 0 | DK13: =SUM(E13,K13,Q13,W13,AE13,AM13,AV13,BD13,BL13,BU13,CC13,CK13)-CS13 -> 0 | DL13: =SUM(G13,M13,S13,AA13,AI13,AR13,AZ13,BH13,BQ13,BY13,CG13,CO13)-CW13 -> 0 | DM13: =SUM(D13,J13,P13,V13,AD13,AL13,AU13,BC13,,BN13,BV13,CD13,CL13)-CT13 -> 0 | DP13: =#VALUE! -> #VALUE! | DQ13: =-CR13+DP13/10^6 -> #VALUE! | DR13: =SUM(E13,K13,Q13,W13,AE13,AM13,AV13,BD13,BL13,BU13,CC13,CK13)-CS13 -> 0 | DS13: =SUM(D13,J13,P13,V13,AD13,AL13,AU13,BC13,,BN13,BV13,CD13,CL13)-CT13 -> 0 | DU13: 68.494617 | DV13: =DU13-CJ13 -> 68.494617 | DX13: =(CS13-CZ13)*10^6 -> 0 | DY13: =(CT13-DC13)*10^6 -> 0 | DZ13: =(CW13-DD13)*10^6 -> 0
B14: AUTRES CHARGES SOCIALES | C14: Opex8 | CU14: =+CR14-CS14 -> 0 | CV14: =+CR14-CT14 -> 0 | CX14: =IFERROR(CR14/CW14-1, "-") -> - | DE14: =+CZ14/DD14-1 -> #DIV/0! | DF14: =+DA14/DD14-1 -> #DIV/0! | DG14: =+DB14/DD14-1 -> #DIV/0! | DH14: =+DC14/DD14-1 -> #DIV/0! | DJ14: =SUM(D14,J14,P14,V14,AD14,AL14,AU14,BC14,BK14,BT14,CB14,CJ14)-CR14 -> 0 | DK14: =SUM(E14,K14,Q14,W14,AE14,AM14,AV14,BD14,BL14,BU14,CC14,CK14)-CS14 -> 0 | DL14: =SUM(G14,M14,S14,AA14,AI14,AR14,AZ14,BH14,BQ14,BY14,CG14,CO14)-CW14 -> 0 | DM14: =SUM(D14,J14,P14,V14,AD14,AL14,AU14,BC14,,BN14,BV14,CD14,CL14)-CT14 -> 0 | DP14: =#VALUE! -> #VALUE! | DQ14: =-CR14+DP14/10^6 -> #VALUE! | DR14: =SUM(E14,K14,Q14,W14,AE14,AM14,AV14,BD14,BL14,BU14,CC14,CK14)-CS14 -> 0 | DS14: =SUM(D14,J14,P14,V14,AD14,AL14,AU14,BC14,,BN14,BV14,CD14,CL14)-CT14 -> 0 | DU14: 14.369378 | DV14: =DU14-CJ14 -> 14.369378 | DX14: =(CS14-CZ14)*10^6 -> 0 | DY14: =(CT14-DC14)*10^6 -> 0 | DZ14: =(CW14-DD14)*10^6 -> 0
B15: PERSONNEL INTERIMAIRE & STAGIA | C15: Opex9 | CX15: =IFERROR(CR15/CW15-1, "-") -> - | DG15: =+DB15/DD15-1 -> #DIV/0! | DH15: =+DC15/DD15-1 -> #DIV/0! | DJ15: =SUM(D15,J15,P15,V15,AD15,AL15,AU15,BC15,BK15,BT15,CB15,CJ15)-CR15 -> 0 | DK15: =SUM(E15,K15,Q15,W15,AE15,AM15,AV15,BD15,BL15,BU15,CC15,CK15)-CS15 -> 0 | DL15: =SUM(G15,M15,S15,AA15,AI15,AR15,AZ15,BH15,BQ15,BY15,CG15,CO15)-CW15 -> 0 | DM15: =SUM(D15,J15,P15,V15,AD15,AL15,AU15,BC15,,BN15,BV15,CD15,CL15)-CT15 -> 0 | DQ15: =-CR15+DP15/10^6 -> 0 | DR15: =SUM(E15,K15,Q15,W15,AE15,AM15,AV15,BD15,BL15,BU15,CC15,CK15)-CS15 -> 0 | DS15: =SUM(D15,J15,P15,V15,AD15,AL15,AU15,BC15,,BN15,BV15,CD15,CL15)-CT15 -> 0 | DV15: =DU15-CJ15 -> 0 | DX15: =(CS15-CZ15)*10^6 -> 0 | DY15: =(CT15-DC15)*10^6 -> 0 | DZ15: =(CW15-DD15)*10^6 -> 0
B16: PRIMES ET GRATIFICATIONS PERSO | C16: Opex10 | CU16: =+CR16-CS16 -> 0 | CV16: =+CR16-CT16 -> 0 | CX16: =IFERROR(CR16/CW16-1, "-") -> - | DE16: =+CZ16/DD16-1 -> #DIV/0! | DF16: =+DA16/DD16-1 -> #DIV/0! | DG16: =+DB16/DD16-1 -> #DIV/0! | DH16: =+DC16/DD16-1 -> #DIV/0! | DJ16: =SUM(D16,J16,P16,V16,AD16,AL16,AU16,BC16,BK16,BT16,CB16,CJ16)-CR16 -> 0 | DK16: =SUM(E16,K16,Q16,W16,AE16,AM16,AV16,BD16,BL16,BU16,CC16,CK16)-CS16 -> 0 | DL16: =SUM(G16,M16,S16,AA16,AI16,AR16,AZ16,BH16,BQ16,BY16,CG16,CO16)-CW16 -> 0 | DM16: =SUM(D16,J16,P16,V16,AD16,AL16,AU16,BC16,,BN16,BV16,CD16,CL16)-CT16 -> 0 | DP16: =#VALUE! -> #VALUE! | DQ16: =-CR16+DP16/10^6 -> #VALUE! | DR16: =SUM(E16,K16,Q16,W16,AE16,AM16,AV16,BD16,BL16,BU16,CC16,CK16)-CS16 -> 0 | DS16: =SUM(D16,J16,P16,V16,AD16,AL16,AU16,BC16,,BN16,BV16,CD16,CL16)-CT16 -> 0 | DT16: 22.791149 | DU16: 89.601339 | DV16: =DU16-CJ16 -> 89.601339 | DX16: =(CS16-CZ16)*10^6 -> 0 | DY16: =(CT16-DC16)*10^6 -> 0 | DZ16: =(CW16-DD16)*10^6 -> 0
B17: INDEMNITES DE LICENCIEMENT PER | C17: Opex11 | CU17: =+CR17-CS17 -> 0 | CV17: =+CR17-CT17 -> 0 | CX17: =IFERROR(CR17/CW17-1, "-") -> - | DJ17: =SUM(D17,J17,P17,V17,AD17,AL17,AU17,BC17,BK17,BT17,CB17,CJ17)-CR17 -> 0 | DK17: =SUM(E17,K17,Q17,W17,AE17,AM17,AV17,BD17,BL17,BU17,CC17,CK17)-CS17 -> 0 | DL17: =SUM(G17,M17,S17,AA17,AI17,AR17,AZ17,BH17,BQ17,BY17,CG17,CO17)-CW17 -> 0 | DM17: =SUM(D17,J17,P17,V17,AD17,AL17,AU17,BC17,,BN17,BV17,CD17,CL17)-CT17 -> 0 | DQ17: =-CR17+DP17/10^6 -> 0 | DR17: =SUM(E17,K17,Q17,W17,AE17,AM17,AV17,BD17,BL17,BU17,CC17,CK17)-CS17 -> 0 | DS17: =SUM(D17,J17,P17,V17,AD17,AL17,AU17,BC17,,BN17,BV17,CD17,CL17)-CT17 -> 0 | DV17: =DU17-CJ17 -> 0 | DX17: =(CS17-CZ17)*10^6 -> 0 | DY17: =(CT17-DC17)*10^6 -> 0 | DZ17: =(CW17-DD17)*10^6 -> 0
B18: EAU RESIDENCES | C18: Opex12 | CU18: =+CR18-CS18 -> 0 | CV18: =+CR18-CT18 -> 0 | CX18: =IFERROR(CR18/CW18-1, "-") -> - | DJ18: =SUM(D18,J18,P18,V18,AD18,AL18,AU18,BC18,BK18,BT18,CB18,CJ18)-CR18 -> 0 | DK18: =SUM(E18,K18,Q18,W18,AE18,AM18,AV18,BD18,BL18,BU18,CC18,CK18)-CS18 -> 0 | DL18: =SUM(G18,M18,S18,AA18,AI18,AR18,AZ18,BH18,BQ18,BY18,CG18,CO18)-CW18 -> 0 | DM18: =SUM(D18,J18,P18,V18,AD18,AL18,AU18,BC18,,BN18,BV18,CD18,CL18)-CT18 -> 0 | DQ18: =-CR18+DP18/10^6 -> 0 | DR18: =SUM(E18,K18,Q18,W18,AE18,AM18,AV18,BD18,BL18,BU18,CC18,CK18)-CS18 -> 0 | DS18: =SUM(D18,J18,P18,V18,AD18,AL18,AU18,BC18,,BN18,BV18,CD18,CL18)-CT18 -> 0 | DV18: =DU18-CJ18 -> 0 | DX18: =(CS18-CZ18)*10^6 -> 0 | DY18: =(CT18-DC18)*10^6 -> 0 | DZ18: =(CW18-DD18)*10^6 -> 0
B19: ELECTRICITE RESIDENCES | C19: Opex13 | CU19: =+CR19-CS19 -> 0 | CV19: =+CR19-CT19 -> 0 | CX19: =IFERROR(CR19/CW19-1, "-") -> - | DJ19: =SUM(D19,J19,P19,V19,AD19,AL19,AU19,BC19,BK19,BT19,CB19,CJ19)-CR19 -> 0 | DK19: =SUM(E19,K19,Q19,W19,AE19,AM19,AV19,BD19,BL19,BU19,CC19,CK19)-CS19 -> 0 | DL19: =SUM(G19,M19,S19,AA19,AI19,AR19,AZ19,BH19,BQ19,BY19,CG19,CO19)-CW19 -> 0 | DM19: =SUM(D19,J19,P19,V19,AD19,AL19,AU19,BC19,,BN19,BV19,CD19,CL19)-CT19 -> 0 | DQ19: =-CR19+DP19/10^6 -> 0 | DR19: =SUM(E19,K19,Q19,W19,AE19,AM19,AV19,BD19,BL19,BU19,CC19,CK19)-CS19 -> 0 | DS19: =SUM(D19,J19,P19,V19,AD19,AL19,AU19,BC19,,BN19,BV19,CD19,CL19)-CT19 -> 0 | DV19: =DU19-CJ19 -> 0 | DX19: =(CS19-CZ19)*10^6 -> 0 | DY19: =(CT19-DC19)*10^6 -> 0 | DZ19: =(CW19-DD19)*10^6 -> 0
B20: LOYERS RESIDENCES | C20: Opex14 | CU20: =+CR20-CS20 -> 0 | CV20: =+CR20-CT20 -> 0 | CX20: =IFERROR(CR20/CW20-1, "-") -> - | DJ20: =SUM(D20,J20,P20,V20,AD20,AL20,AU20,BC20,BK20,BT20,CB20,CJ20)-CR20 -> 0 | DK20: =SUM(E20,K20,Q20,W20,AE20,AM20,AV20,BD20,BL20,BU20,CC20,CK20)-CS20 -> 0 | DL20: =SUM(G20,M20,S20,AA20,AI20,AR20,AZ20,BH20,BQ20,BY20,CG20,CO20)-CW20 -> 0 | DM20: =SUM(D20,J20,P20,V20,AD20,AL20,AU20,BC20,,BN20,BV20,CD20,CL20)-CT20 -> 0 | DQ20: =-CR20+DP20/10^6 -> 0 | DR20: =SUM(E20,K20,Q20,W20,AE20,AM20,AV20,BD20,BL20,BU20,CC20,CK20)-CS20 -> 0 | DS20: =SUM(D20,J20,P20,V20,AD20,AL20,AU20,BC20,,BN20,BV20,CD20,CL20)-CT20 -> 0 | DV20: =DU20-CJ20 -> 0 | DX20: =(CS20-CZ20)*10^6 -> 0 | DY20: =(CT20-DC20)*10^6 -> 0 | DZ20: =(CW20-DD20)*10^6 -> 0
B21: ENTRETIEN ET REPARATIONS RESID | C21: Opex15 | CU21: =+CR21-CS21 -> 0 | CV21: =+CR21-CT21 -> 0 | CX21: =IFERROR(CR21/CW21-1, "-") -> - | DJ21: =SUM(D21,J21,P21,V21,AD21,AL21,AU21,BC21,BK21,BT21,CB21,CJ21)-CR21 -> 0 | DK21: =SUM(E21,K21,Q21,W21,AE21,AM21,AV21,BD21,BL21,BU21,CC21,CK21)-CS21 -> 0 | DL21: =SUM(G21,M21,S21,AA21,AI21,AR21,AZ21,BH21,BQ21,BY21,CG21,CO21)-CW21 -> 0 | DM21: =SUM(D21,J21,P21,V21,AD21,AL21,AU21,BC21,,BN21,BV21,CD21,CL21)-CT21 -> 0 | DQ21: =-CR21+DP21/10^6 -> 0 | DR21: =SUM(E21,K21,Q21,W21,AE21,AM21,AV21,BD21,BL21,BU21,CC21,CK21)-CS21 -> 0 | DS21: =SUM(D21,J21,P21,V21,AD21,AL21,AU21,BC21,,BN21,BV21,CD21,CL21)-CT21 -> 0 | DV21: =DU21-CJ21 -> 0 | DX21: =(CS21-CZ21)*10^6 -> 0 | DY21: =(CT21-DC21)*10^6 -> 0 | DZ21: =(CW21-DD21)*10^6 -> 0
B22: FRAIS MEDICAUX PERSONNEL NATIO | C22: Opex16 | CU22: =+CR22-CS22 -> 0 | CV22: =+CR22-CT22 -> 0 | CX22: =IFERROR(CR22/CW22-1, "-") -> - | DJ22: =SUM(D22,J22,P22,V22,AD22,AL22,AU22,BC22,BK22,BT22,CB22,CJ22)-CR22 -> 0 | DK22: =SUM(E22,K22,Q22,W22,AE22,AM22,AV22,BD22,BL22,BU22,CC22,CK22)-CS22 -> 0 | DL22: =SUM(G22,M22,S22,AA22,AI22,AR22,AZ22,BH22,BQ22,BY22,CG22,CO22)-CW22 -> 0 | DM22: =SUM(D22,J22,P22,V22,AD22,AL22,AU22,BC22,,BN22,BV22,CD22,CL22)-CT22 -> 0 | DQ22: =-CR22+DP22/10^6 -> 0 | DR22: =SUM(E22,K22,Q22,W22,AE22,AM22,AV22,BD22,BL22,BU22,CC22,CK22)-CS22 -> 0 | DS22: =SUM(D22,J22,P22,V22,AD22,AL22,AU22,BC22,,BN22,BV22,CD22,CL22)-CT22 -> 0 | DV22: =DU22-CJ22 -> 0 | DX22: =(CS22-CZ22)*10^6 -> 0 | DY22: =(CT22-DC22)*10^6 -> 0 | DZ22: =(CW22-DD22)*10^6 -> 0
B23: AVANTAGES EN NATURE PERSONNEL | C23: Opex17 | CU23: =+CR23-CS23 -> 0 | CV23: =+CR23-CT23 -> 0 | CX23: =IFERROR(CR23/CW23-1, "-") -> - | DE23: =+CZ23/DD23-1 -> #DIV/0! | DF23: =+DA23/DD23-1 -> #DIV/0! | DG23: =+DB23/DD23-1 -> #DIV/0! | DH23: =+DC23/DD23-1 -> #DIV/0! | DJ23: =SUM(D23,J23,P23,V23,AD23,AL23,AU23,BC23,BK23,BT23,CB23,CJ23)-CR23 -> 0 | DK23: =SUM(E23,K23,Q23,W23,AE23,AM23,AV23,BD23,BL23,BU23,CC23,CK23)-CS23 -> 0 | DL23: =SUM(G23,M23,S23,AA23,AI23,AR23,AZ23,BH23,BQ23,BY23,CG23,CO23)-CW23 -> 0 | DM23: =SUM(D23,J23,P23,V23,AD23,AL23,AU23,BC23,,BN23,BV23,CD23,CL23)-CT23 -> 0 | DP23: =#VALUE! -> #VALUE! | DQ23: =-CR23+DP23/10^6 -> #VALUE! | DR23: =SUM(E23,K23,Q23,W23,AE23,AM23,AV23,BD23,BL23,BU23,CC23,CK23)-CS23 -> 0 | DS23: =SUM(D23,J23,P23,V23,AD23,AL23,AU23,BC23,,BN23,BV23,CD23,CL23)-CT23 -> 0 | DU23: 13.826821 | DV23: =DU23-CJ23 -> 13.826821 | DX23: =(CS23-CZ23)*10^6 -> 0 | DY23: =(CT23-DC23)*10^6 -> 0 | DZ23: =(CW23-DD23)*10^6 -> 0
B24: TRANSFERT DE CHARGES D'EXPLOITATION | C24: Opex18 | CU24: =+CR24-CS24 -> 0 | CV24: =+CR24-CT24 -> 0 | CX24: =IFERROR(CR24/CW24-1, "-") -> - | DJ24: =SUM(D24,J24,P24,V24,AD24,AL24,AU24,BC24,BK24,BT24,CB24,CJ24)-CR24 -> 0 | DK24: =SUM(E24,K24,Q24,W24,AE24,AM24,AV24,BD24,BL24,BU24,CC24,CK24)-CS24 -> 0 | DL24: =SUM(G24,M24,S24,AA24,AI24,AR24,AZ24,BH24,BQ24,BY24,CG24,CO24)-CW24 -> 0 | DM24: =SUM(D24,J24,P24,V24,AD24,AL24,AU24,BC24,,BN24,BV24,CD24,CL24)-CT24 -> 0 | DQ24: =-CR24+DP24/10^6 -> 0 | DR24: =SUM(E24,K24,Q24,W24,AE24,AM24,AV24,BD24,BL24,BU24,CC24,CK24)-CS24 -> 0 | DS24: =SUM(D24,J24,P24,V24,AD24,AL24,AU24,BC24,,BN24,BV24,CD24,CL24)-CT24 -> 0 | DV24: =DU24-CJ24 -> 0 | DX24: =(CS24-CZ24)*10^6 -> 0 | DY24: =(CT24-DC24)*10^6 -> 0 | DZ24: =(CW24-DD24)*10^6 -> 0
B25: EAU RESIDENCES | C25: Opex19 | CU25: =+CR25-CS25 -> 0 | CV25: =+CR25-CT25 -> 0 | CX25: =IFERROR(CR25/CW25-1, "-") -> - | DJ25: =SUM(D25,J25,P25,V25,AD25,AL25,AU25,BC25,BK25,BT25,CB25,CJ25)-CR25 -> 0 | DK25: =SUM(E25,K25,Q25,W25,AE25,AM25,AV25,BD25,BL25,BU25,CC25,CK25)-CS25 -> 0 | DL25: =SUM(G25,M25,S25,AA25,AI25,AR25,AZ25,BH25,BQ25,BY25,CG25,CO25)-CW25 -> 0 | DM25: =SUM(D25,J25,P25,V25,AD25,AL25,AU25,BC25,,BN25,BV25,CD25,CL25)-CT25 -> 0 | DQ25: =-CR25+DP25/10^6 -> 0 | DR25: =SUM(E25,K25,Q25,W25,AE25,AM25,AV25,BD25,BL25,BU25,CC25,CK25)-CS25 -> 0 | DS25: =SUM(D25,J25,P25,V25,AD25,AL25,AU25,BC25,,BN25,BV25,CD25,CL25)-CT25 -> 0 | DV25: =DU25-CJ25 -> 0 | DX25: =(CS25-CZ25)*10^6 -> 0 | DY25: =(CT25-DC25)*10^6 -> 0 | DZ25: =(CW25-DD25)*10^6 -> 0
B26: ELECTRICITE RESIDENCES | C26: Opex20 | CU26: =+CR26-CS26 -> 0 | CV26: =+CR26-CT26 -> 0 | CX26: =IFERROR(CR26/CW26-1, "-") -> - | DJ26: =SUM(D26,J26,P26,V26,AD26,AL26,AU26,BC26,BK26,BT26,CB26,CJ26)-CR26 -> 0 | DK26: =SUM(E26,K26,Q26,W26,AE26,AM26,AV26,BD26,BL26,BU26,CC26,CK26)-CS26 -> 0 | DL26: =SUM(G26,M26,S26,AA26,AI26,AR26,AZ26,BH26,BQ26,BY26,CG26,CO26)-CW26 -> 0 | DM26: =SUM(D26,J26,P26,V26,AD26,AL26,AU26,BC26,,BN26,BV26,CD26,CL26)-CT26 -> 0 | DQ26: =-CR26+DP26/10^6 -> 0 | DR26: =SUM(E26,K26,Q26,W26,AE26,AM26,AV26,BD26,BL26,BU26,CC26,CK26)-CS26 -> 0 | DS26: =SUM(D26,J26,P26,V26,AD26,AL26,AU26,BC26,,BN26,BV26,CD26,CL26)-CT26 -> 0 | DV26: =DU26-CJ26 -> 0 | DX26: =(CS26-CZ26)*10^6 -> 0 | DY26: =(CT26-DC26)*10^6 -> 0 | DZ26: =(CW26-DD26)*10^6 -> 0
B27: LOYERS RESIDENCES | C27: Opex21 | CU27: =+CR27-CS27 -> 0 | CV27: =+CR27-CT27 -> 0 | CX27: =IFERROR(CR27/CW27-1, "-") -> - | DJ27: =SUM(D27,J27,P27,V27,AD27,AL27,AU27,BC27,BK27,BT27,CB27,CJ27)-CR27 -> 0 | DK27: =SUM(E27,K27,Q27,W27,AE27,AM27,AV27,BD27,BL27,BU27,CC27,CK27)-CS27 -> 0 | DL27: =SUM(G27,M27,S27,AA27,AI27,AR27,AZ27,BH27,BQ27,BY27,CG27,CO27)-CW27 -> 0 | DM27: =SUM(D27,J27,P27,V27,AD27,AL27,AU27,BC27,,BN27,BV27,CD27,CL27)-CT27 -> 0 | DQ27: =-CR27+DP27/10^6 -> 0 | DR27: =SUM(E27,K27,Q27,W27,AE27,AM27,AV27,BD27,BL27,BU27,CC27,CK27)-CS27 -> 0 | DS27: =SUM(D27,J27,P27,V27,AD27,AL27,AU27,BC27,,BN27,BV27,CD27,CL27)-CT27 -> 0 | DV27: =DU27-CJ27 -> 0 | DX27: =(CS27-CZ27)*10^6 -> 0 | DY27: =(CT27-DC27)*10^6 -> 0 | DZ27: =(CW27-DD27)*10^6 -> 0
B28: ENTRETIEN ET REPARATIONS RESID | C28: Opex22 | CU28: =+CR28-CS28 -> 0 | CV28: =+CR28-CT28 -> 0 | CX28: =IFERROR(CR28/CW28-1, "-") -> - | DJ28: =SUM(D28,J28,P28,V28,AD28,AL28,AU28,BC28,BK28,BT28,CB28,CJ28)-CR28 -> 0 | DK28: =SUM(E28,K28,Q28,W28,AE28,AM28,AV28,BD28,BL28,BU28,CC28,CK28)-CS28 -> 0 | DL28: =SUM(G28,M28,S28,AA28,AI28,AR28,AZ28,BH28,BQ28,BY28,CG28,CO28)-CW28 -> 0 | DM28: =SUM(D28,J28,P28,V28,AD28,AL28,AU28,BC28,,BN28,BV28,CD28,CL28)-CT28 -> 0 | DQ28: =-CR28+DP28/10^6 -> 0 | DR28: =SUM(E28,K28,Q28,W28,AE28,AM28,AV28,BD28,BL28,BU28,CC28,CK28)-CS28 -> 0 | DS28: =SUM(D28,J28,P28,V28,AD28,AL28,AU28,BC28,,BN28,BV28,CD28,CL28)-CT28 -> 0 | DV28: =DU28-CJ28 -> 0 | DX28: =(CS28-CZ28)*10^6 -> 0 | DY28: =(CT28-DC28)*10^6 -> 0 | DZ28: =(CW28-DD28)*10^6 -> 0
B29: FRAIS DE TELEPHONE RESIDENCES | C29: Opex23 | CU29: =+CR29-CS29 -> 0 | CV29: =+CR29-CT29 -> 0 | CX29: =IFERROR(CR29/CW29-1, "-") -> - | DJ29: =SUM(D29,J29,P29,V29,AD29,AL29,AU29,BC29,BK29,BT29,CB29,CJ29)-CR29 -> 0 | DK29: =SUM(E29,K29,Q29,W29,AE29,AM29,AV29,BD29,BL29,BU29,CC29,CK29)-CS29 -> 0 | DL29: =SUM(G29,M29,S29,AA29,AI29,AR29,AZ29,BH29,BQ29,BY29,CG29,CO29)-CW29 -> 0 | DM29: =SUM(D29,J29,P29,V29,AD29,AL29,AU29,BC29,,BN29,BV29,CD29,CL29)-CT29 -> 0 | DQ29: =-CR29+DP29/10^6 -> 0 | DR29: =SUM(E29,K29,Q29,W29,AE29,AM29,AV29,BD29,BL29,BU29,CC29,CK29)-CS29 -> 0 | DS29: =SUM(D29,J29,P29,V29,AD29,AL29,AU29,BC29,,BN29,BV29,CD29,CL29)-CT29 -> 0 | DV29: =DU29-CJ29 -> 0 | DX29: =(CS29-CZ29)*10^6 -> 0 | DY29: =(CT29-DC29)*10^6 -> 0 | DZ29: =(CW29-DD29)*10^6 -> 0
B30: PRIMES ET GRATIFICATIONS PERSO | C30: Opex24 | CU30: =+CR30-CS30 -> 0 | CV30: =+CR30-CT30 -> 0 | CX30: =IFERROR(CR30/CW30-1, "-") -> - | DJ30: =SUM(D30,J30,P30,V30,AD30,AL30,AU30,BC30,BK30,BT30,CB30,CJ30)-CR30 -> 0 | DK30: =SUM(E30,K30,Q30,W30,AE30,AM30,AV30,BD30,BL30,BU30,CC30,CK30)-CS30 -> 0 | DL30: =SUM(G30,M30,S30,AA30,AI30,AR30,AZ30,BH30,BQ30,BY30,CG30,CO30)-CW30 -> 0 | DM30: =SUM(D30,J30,P30,V30,AD30,AL30,AU30,BC30,,BN30,BV30,CD30,CL30)-CT30 -> 0 | DP30: 0 | DQ30: =-CR30+DP30/10^6 -> 0 | DR30: =SUM(E30,K30,Q30,W30,AE30,AM30,AV30,BD30,BL30,BU30,CC30,CK30)-CS30 -> 0 | DS30: =SUM(D30,J30,P30,V30,AD30,AL30,AU30,BC30,,BN30,BV30,CD30,CL30)-CT30 -> 0 | DV30: =DU30-CJ30 -> 0 | DX30: =(CS30-CZ30)*10^6 -> 0 | DY30: =(CT30-DC30)*10^6 -> 0 | DZ30: =(CW30-DD30)*10^6 -> 0
B31: INDEMNITES DE LICENCIEMENT PER | C31: Opex25 | CU31: =+CR31-CS31 -> 0 | CV31: =+CR31-CT31 -> 0 | CX31: =IFERROR(CR31/CW31-1, "-") -> - | DJ31: =SUM(D31,J31,P31,V31,AD31,AL31,AU31,BC31,BK31,BT31,CB31,CJ31)-CR31 -> 0 | DK31: =SUM(E31,K31,Q31,W31,AE31,AM31,AV31,BD31,BL31,BU31,CC31,CK31)-CS31 -> 0 | DL31: =SUM(G31,M31,S31,AA31,AI31,AR31,AZ31,BH31,BQ31,BY31,CG31,CO31)-CW31 -> 0 | DM31: =SUM(D31,J31,P31,V31,AD31,AL31,AU31,BC31,,BN31,BV31,CD31,CL31)-CT31 -> 0 | DQ31: =-CR31+DP31/10^6 -> 0 | DR31: =SUM(E31,K31,Q31,W31,AE31,AM31,AV31,BD31,BL31,BU31,CC31,CK31)-CS31 -> 0 | DS31: =SUM(D31,J31,P31,V31,AD31,AL31,AU31,BC31,,BN31,BV31,CD31,CL31)-CT31 -> 0 | DV31: =DU31-CJ31 -> 0 | DX31: =(CS31-CZ31)*10^6 -> 0 | DY31: =(CT31-DC31)*10^6 -> 0 | DZ31: =(CW31-DD31)*10^6 -> 0
B32: AVANTAGES EN NATURE PERSONNEL | C32: Opex26 | CU32: =+CR32-CS32 -> 0 | CV32: =+CR32-CT32 -> 0 | CX32: =IFERROR(CR32/CW32-1, "-") -> - | DJ32: =SUM(D32,J32,P32,V32,AD32,AL32,AU32,BC32,BK32,BT32,CB32,CJ32)-CR32 -> 0 | DK32: =SUM(E32,K32,Q32,W32,AE32,AM32,AV32,BD32,BL32,BU32,CC32,CK32)-CS32 -> 0 | DL32: =SUM(G32,M32,S32,AA32,AI32,AR32,AZ32,BH32,BQ32,BY32,CG32,CO32)-CW32 -> 0 | DM32: =SUM(D32,J32,P32,V32,AD32,AL32,AU32,BC32,,BN32,BV32,CD32,CL32)-CT32 -> 0 | DQ32: =-CR32+DP32/10^6 -> 0 | DR32: =SUM(E32,K32,Q32,W32,AE32,AM32,AV32,BD32,BL32,BU32,CC32,CK32)-CS32 -> 0 | DS32: =SUM(D32,J32,P32,V32,AD32,AL32,AU32,BC32,,BN32,BV32,CD32,CL32)-CT32 -> 0 | DV32: =DU32-CJ32 -> 0 | DX32: =(CS32-CZ32)*10^6 -> 0 | DY32: =(CT32-DC32)*10^6 -> 0 | DZ32: =(CW32-DD32)*10^6 -> 0
B33: AUTRES INDEMNITES ET AVANTAGES | C33: Opex27 | CU33: =+CR33-CS33 -> 0 | CV33: =+CR33-CT33 -> 0 | CX33: =IFERROR(CR33/CW33-1, "-") -> - | DJ33: =SUM(D33,J33,P33,V33,AD33,AL33,AU33,BC33,BK33,BT33,CB33,CJ33)-CR33 -> 0 | DK33: =SUM(E33,K33,Q33,W33,AE33,AM33,AV33,BD33,BL33,BU33,CC33,CK33)-CS33 -> 0 | DL33: =SUM(G33,M33,S33,AA33,AI33,AR33,AZ33,BH33,BQ33,BY33,CG33,CO33)-CW33 -> 0 | DM33: =SUM(D33,J33,P33,V33,AD33,AL33,AU33,BC33,,BN33,BV33,CD33,CL33)-CT33 -> 0 | DQ33: =-CR33+DP33/10^6 -> 0 | DR33: =SUM(E33,K33,Q33,W33,AE33,AM33,AV33,BD33,BL33,BU33,CC33,CK33)-CS33 -> 0 | DS33: =SUM(D33,J33,P33,V33,AD33,AL33,AU33,BC33,,BN33,BV33,CD33,CL33)-CT33 -> 0 | DV33: =DU33-CJ33 -> 0 | DX33: =(CS33-CZ33)*10^6 -> 0 | DY33: =(CT33-DC33)*10^6 -> 0 | DZ33: =(CW33-DD33)*10^6 -> 0
B34: FRAIS DE FORMATION DU PERSONNE | C34: Opex28 | CU34: =+CR34-CS34 -> 0 | CV34: =+CR34-CT34 -> 0 | CX34: =IFERROR(CR34/CW34-1, "-") -> - | DJ34: =SUM(D34,J34,P34,V34,AD34,AL34,AU34,BC34,BK34,BT34,CB34,CJ34)-CR34 -> 0 | DK34: =SUM(E34,K34,Q34,W34,AE34,AM34,AV34,BD34,BL34,BU34,CC34,CK34)-CS34 -> 0 | DL34: =SUM(G34,M34,S34,AA34,AI34,AR34,AZ34,BH34,BQ34,BY34,CG34,CO34)-CW34 -> 0 | DM34: =SUM(D34,J34,P34,V34,AD34,AL34,AU34,BC34,,BN34,BV34,CD34,CL34)-CT34 -> 0 | DQ34: =-CR34+DP34/10^6 -> 0 | DR34: =SUM(E34,K34,Q34,W34,AE34,AM34,AV34,BD34,BL34,BU34,CC34,CK34)-CS34 -> 0 | DS34: =SUM(D34,J34,P34,V34,AD34,AL34,AU34,BC34,,BN34,BV34,CD34,CL34)-CT34 -> 0 | DV34: =DU34-CJ34 -> 0 | DX34: =(CS34-CZ34)*10^6 -> 0 | DY34: =(CT34-DC34)*10^6 -> 0 | DZ34: =(CW34-DD34)*10^6 -> 0
B35: TRANSPORT PERSONNEL | C35: Opex29 | CU35: =+CR35-CS35 -> 0 | CV35: =+CR35-CT35 -> 0 | CX35: =IFERROR(CR35/CW35-1, "-") -> - | DJ35: =SUM(D35,J35,P35,V35,AD35,AL35,AU35,BC35,BK35,BT35,CB35,CJ35)-CR35 -> 0 | DK35: =SUM(E35,K35,Q35,W35,AE35,AM35,AV35,BD35,BL35,BU35,CC35,CK35)-CS35 -> 0 | DL35: =SUM(G35,M35,S35,AA35,AI35,AR35,AZ35,BH35,BQ35,BY35,CG35,CO35)-CW35 -> 0 | DM35: =SUM(D35,J35,P35,V35,AD35,AL35,AU35,BC35,,BN35,BV35,CD35,CL35)-CT35 -> 0 | DQ35: =-CR35+DP35/10^6 -> 0 | DR35: =SUM(E35,K35,Q35,W35,AE35,AM35,AV35,BD35,BL35,BU35,CC35,CK35)-CS35 -> 0 | DS35: =SUM(D35,J35,P35,V35,AD35,AL35,AU35,BC35,,BN35,BV35,CD35,CL35)-CT35 -> 0 | DV35: =DU35-CJ35 -> 0 | DX35: =(CS35-CZ35)*10^6 -> 0 | DY35: =(CT35-DC35)*10^6 -> 0 | DZ35: =(CW35-DD35)*10^6 -> 0
B36: RECEPTIONS PERSONNEL | C36: Opex30 | CU36: =+CR36-CS36 -> 0 | CV36: =+CR36-CT36 -> 0 | CX36: =IFERROR(CR36/CW36-1, "-") -> - | DJ36: =SUM(D36,J36,P36,V36,AD36,AL36,AU36,BC36,BK36,BT36,CB36,CJ36)-CR36 -> 0 | DK36: =SUM(E36,K36,Q36,W36,AE36,AM36,AV36,BD36,BL36,BU36,CC36,CK36)-CS36 -> 0 | DL36: =SUM(G36,M36,S36,AA36,AI36,AR36,AZ36,BH36,BQ36,BY36,CG36,CO36)-CW36 -> 0 | DM36: =SUM(D36,J36,P36,V36,AD36,AL36,AU36,BC36,,BN36,BV36,CD36,CL36)-CT36 -> 0 | DQ36: =-CR36+DP36/10^6 -> 0 | DR36: =SUM(E36,K36,Q36,W36,AE36,AM36,AV36,BD36,BL36,BU36,CC36,CK36)-CS36 -> 0 | DS36: =SUM(D36,J36,P36,V36,AD36,AL36,AU36,BC36,,BN36,BV36,CD36,CL36)-CT36 -> 0 | DV36: =DU36-CJ36 -> 0 | DX36: =(CS36-CZ36)*10^6 -> 0 | DY36: =(CT36-DC36)*10^6 -> 0 | DZ36: =(CW36-DD36)*10^6 -> 0
B37: ASSURANCE DU PERSONNEL | C37: Opex31 | CU37: =+CR37-CS37 -> 0 | CV37: =+CR37-CT37 -> 0 | CX37: =IFERROR(CR37/CW37-1, "-") -> - | DE37: =+CZ37/DD37-1 -> #DIV/0! | DF37: =+DA37/DD37-1 -> #DIV/0! | DG37: =+DB37/DD37-1 -> #DIV/0! | DH37: =+DC37/DD37-1 -> #DIV/0! | DJ37: =SUM(D37,J37,P37,V37,AD37,AL37,AU37,BC37,BK37,BT37,CB37,CJ37)-CR37 -> 0 | DK37: =SUM(E37,K37,Q37,W37,AE37,AM37,AV37,BD37,BL37,BU37,CC37,CK37)-CS37 -> 0 | DL37: =SUM(G37,M37,S37,AA37,AI37,AR37,AZ37,BH37,BQ37,BY37,CG37,CO37)-CW37 -> 0 | DM37: =SUM(D37,J37,P37,V37,AD37,AL37,AU37,BC37,,BN37,BV37,CD37,CL37)-CT37 -> 0 | DP37: =#VALUE! -> #VALUE! | DQ37: =-CR37+DP37/10^6 -> #VALUE! | DR37: =SUM(E37,K37,Q37,W37,AE37,AM37,AV37,BD37,BL37,BU37,CC37,CK37)-CS37 -> 0 | DS37: =SUM(D37,J37,P37,V37,AD37,AL37,AU37,BC37,,BN37,BV37,CD37,CL37)-CT37 -> 0 | DU37: 20.407007 | DV37: =DU37-CJ37 -> 20.407007 | DX37: =(CS37-CZ37)*10^6 -> 0 | DY37: =(CT37-DC37)*10^6 -> 0 | DZ37: =(CW37-DD37)*10^6 -> 0
B38: Réduction budget | C38: Opex32 | CU38: =+CR38-CS38 -> 0 | CV38: =+CR38-CT38 -> 0 | CX38: =IFERROR(CR38/CW38-1, "-") -> - | DJ38: =SUM(D38,J38,P38,V38,AD38,AL38,AU38,BC38,BK38,BT38,CB38,CJ38)-CR38 -> 0 | DK38: =SUM(E38,K38,Q38,W38,AE38,AM38,AV38,BD38,BL38,BU38,CC38,CK38)-CS38 -> 0 | DL38: =SUM(G38,M38,S38,AA38,AI38,AR38,AZ38,BH38,BQ38,BY38,CG38,CO38)-CW38 -> 0 | DM38: =SUM(D38,J38,P38,V38,AD38,AL38,AU38,BC38,,BN38,BV38,CD38,CL38)-CT38 -> 0 | DQ38: =-CR38+DP38/10^6 -> 0 | DR38: =SUM(E38,K38,Q38,W38,AE38,AM38,AV38,BD38,BL38,BU38,CC38,CK38)-CS38 -> 0 | DS38: =SUM(D38,J38,P38,V38,AD38,AL38,AU38,BC38,,BN38,BV38,CD38,CL38)-CT38 -> 0 | DV38: =DU38-CJ38 -> 0 | DX38: =(CS38-CZ38)*10^6 -> 0 | DY38: =(CT38-DC38)*10^6 -> 0 | DZ38: =(CW38-DD38)*10^6 -> 0
C39: Opex33 | CX39: =IFERROR(CR39/CW39-1, "-") -> - | DJ39: =SUM(D39,J39,P39,V39,AD39,AL39,AU39,BC39,BK39,BT39,CB39,CJ39)-CR39 -> 0 | DK39: =SUM(E39,K39,Q39,W39,AE39,AM39,AV39,BD39,BL39,BU39,CC39,CK39)-CS39 -> 0 | DL39: =SUM(G39,M39,S39,AA39,AI39,AR39,AZ39,BH39,BQ39,BY39,CG39,CO39)-CW39 -> 0 | DM39: =SUM(D39,J39,P39,V39,AD39,AL39,AU39,BC39,,BN39,BV39,CD39,CL39)-CT39 -> 0 | DQ39: =-CR39+DP39/10^6 -> 0 | DR39: =SUM(E39,K39,Q39,W39,AE39,AM39,AV39,BD39,BL39,BU39,CC39,CK39)-CS39 -> 0 | DS39: =SUM(D39,J39,P39,V39,AD39,AL39,AU39,BC39,,BN39,BV39,CD39,CL39)-CT39 -> 0 | DV39: =DU39-CJ39 -> 0 | DX39: =(CS39-CZ39)*10^6 -> 0 | DY39: =(CT39-DC39)*10^6 -> 0 | DZ39: =(CW39-DD39)*10^6 -> 0
B40: Communication | C40: Opex34 | CU40: =+CR40-CS40 -> 0 | CV40: =+CR40-CT40 -> 0 | CX40: =IFERROR(CR40/CW40-1, "-") -> - | DE40: =+CZ40/DD40-1 -> #DIV/0! | DF40: =+DA40/DD40-1 -> #DIV/0! | DG40: =+DB40/DD40-1 -> #DIV/0! | DH40: =+DC40/DD40-1 -> #DIV/0! | DJ40: =SUM(D40,J40,P40,V40,AD40,AL40,AU40,BC40,BK40,BT40,CB40,CJ40)-CR40 -> 0 | DK40: =SUM(E40,K40,Q40,W40,AE40,AM40,AV40,BD40,BL40,BU40,CC40,CK40)-CS40 -> 0 | DL40: =SUM(G40,M40,S40,AA40,AI40,AR40,AZ40,BH40,BQ40,BY40,CG40,CO40)-CW40 -> 0 | DM40: =SUM(D40,J40,P40,V40,AD40,AL40,AU40,BC40,,BN40,BV40,CD40,CL40)-CT40 -> 0 | DP40: =SUM(DP41:DP55) -> #VALUE! | DQ40: =-CR40+DP40/10^6 -> #VALUE! | DR40: =SUM(E40,K40,Q40,W40,AE40,AM40,AV40,BD40,BL40,BU40,CC40,CK40)-CS40 -> 0 | DS40: =SUM(D40,J40,P40,V40,AD40,AL40,AU40,BC40,,BN40,BV40,CD40,CL40)-CT40 -> 0 | DU40: 338.23657 | DV40: =DU40-CJ40 -> 338.23657 | DX40: =(CS40-CZ40)*10^6 -> 0 | DY40: =(CT40-DC40)*10^6 -> 0 | DZ40: =(CW40-DD40)*10^6 -> 0
B41: VARIATION DE STOCKS AUTRES APPRO | C41: Opex35 | CU41: =+CR41-CS41 -> 0 | CV41: =+CR41-CT41 -> 0 | CX41: =IFERROR(CR41/CW41-1, "-") -> - | DJ41: =SUM(D41,J41,P41,V41,AD41,AL41,AU41,BC41,BK41,BT41,CB41,CJ41)-CR41 -> 0 | DK41: =SUM(E41,K41,Q41,W41,AE41,AM41,AV41,BD41,BL41,BU41,CC41,CK41)-CS41 -> 0 | DL41: =SUM(G41,M41,S41,AA41,AI41,AR41,AZ41,BH41,BQ41,BY41,CG41,CO41)-CW41 -> 0 | DM41: =SUM(D41,J41,P41,V41,AD41,AL41,AU41,BC41,,BN41,BV41,CD41,CL41)-CT41 -> 0 | DP41: -82699732 | DQ41: =-CR41+DP41/10^6 -> -82.699732 | DR41: =SUM(E41,K41,Q41,W41,AE41,AM41,AV41,BD41,BL41,BU41,CC41,CK41)-CS41 -> 0 | DS41: =SUM(D41,J41,P41,V41,AD41,AL41,AU41,BC41,,BN41,BV41,CD41,CL41)-CT41 -> 0 | DU41: 14.928927 | DV41: =DU41-CJ41 -> 14.928927 | DX41: =(CS41-CZ41)*10^6 -> 0 | DY41: =(CT41-DC41)*10^6 -> 0 | DZ41: =(CW41-DD41)*10^6 -> 0
B42: ANNONCES, INSERTIONS TELE | C42: Opex36 | CU42: =+CR42-CS42 -> 0 | CV42: =+CR42-CT42 -> 0 | CX42: =IFERROR(CR42/CW42-1, "-") -> - | DJ42: =SUM(D42,J42,P42,V42,AD42,AL42,AU42,BC42,BK42,BT42,CB42,CJ42)-CR42 -> 0 | DK42: =SUM(E42,K42,Q42,W42,AE42,AM42,AV42,BD42,BL42,BU42,CC42,CK42)-CS42 -> 0 | DL42: =SUM(G42,M42,S42,AA42,AI42,AR42,AZ42,BH42,BQ42,BY42,CG42,CO42)-CW42 -> 0 | DM42: =SUM(D42,J42,P42,V42,AD42,AL42,AU42,BC42,,BN42,BV42,CD42,CL42)-CT42 -> 0 | DP42: 21416152 | DQ42: =-CR42+DP42/10^6 -> 21.416152 | DR42: =SUM(E42,K42,Q42,W42,AE42,AM42,AV42,BD42,BL42,BU42,CC42,CK42)-CS42 -> 0 | DS42: =SUM(D42,J42,P42,V42,AD42,AL42,AU42,BC42,,BN42,BV42,CD42,CL42)-CT42 -> 0 | DU42: 12.064387 | DV42: =DU42-CJ42 -> 12.064387 | DX42: =(CS42-CZ42)*10^6 -> 0 | DY42: =(CT42-DC42)*10^6 -> 0 | DZ42: =(CW42-DD42)*10^6 -> 0
B43: ANNONCES, INSERTIONS RADIO | C43: Opex37 | CU43: =+CR43-CS43 -> 0 | CV43: =+CR43-CT43 -> 0 | CX43: =IFERROR(CR43/CW43-1, "-") -> - | DJ43: =SUM(D43,J43,P43,V43,AD43,AL43,AU43,BC43,BK43,BT43,CB43,CJ43)-CR43 -> 0 | DK43: =SUM(E43,K43,Q43,W43,AE43,AM43,AV43,BD43,BL43,BU43,CC43,CK43)-CS43 -> 0 | DL43: =SUM(G43,M43,S43,AA43,AI43,AR43,AZ43,BH43,BQ43,BY43,CG43,CO43)-CW43 -> 0 | DM43: =SUM(D43,J43,P43,V43,AD43,AL43,AU43,BC43,,BN43,BV43,CD43,CL43)-CT43 -> 0 | DP43: 42076422 | DQ43: =-CR43+DP43/10^6 -> 42.076422 | DR43: =SUM(E43,K43,Q43,W43,AE43,AM43,AV43,BD43,BL43,BU43,CC43,CK43)-CS43 -> 0 | DS43: =SUM(D43,J43,P43,V43,AD43,AL43,AU43,BC43,,BN43,BV43,CD43,CL43)-CT43 -> 0 | DU43: 2.638442 | DV43: =DU43-CJ43 -> 2.638442 | DX43: =(CS43-CZ43)*10^6 -> 0 | DY43: =(CT43-DC43)*10^6 -> 0 | DZ43: =(CW43-DD43)*10^6 -> 0
B44: ANNONCES, INSERTIONS PRESSE | C44: Opex38 | CU44: =+CR44-CS44 -> 0 | CV44: =+CR44-CT44 -> 0 | CX44: =IFERROR(CR44/CW44-1, "-") -> - | DJ44: =SUM(D44,J44,P44,V44,AD44,AL44,AU44,BC44,BK44,BT44,CB44,CJ44)-CR44 -> 0 | DK44: =SUM(E44,K44,Q44,W44,AE44,AM44,AV44,BD44,BL44,BU44,CC44,CK44)-CS44 -> 0 | DL44: =SUM(G44,M44,S44,AA44,AI44,AR44,AZ44,BH44,BQ44,BY44,CG44,CO44)-CW44 -> 0 | DM44: =SUM(D44,J44,P44,V44,AD44,AL44,AU44,BC44,,BN44,BV44,CD44,CL44)-CT44 -> 0 | DP44: 27947528 | DQ44: =-CR44+DP44/10^6 -> 27.947528 | DR44: =SUM(E44,K44,Q44,W44,AE44,AM44,AV44,BD44,BL44,BU44,CC44,CK44)-CS44 -> 0 | DS44: =SUM(D44,J44,P44,V44,AD44,AL44,AU44,BC44,,BN44,BV44,CD44,CL44)-CT44 -> 0 | DU44: 6.785758 | DV44: =DU44-CJ44 -> 6.785758 | DX44: =(CS44-CZ44)*10^6 -> 0 | DY44: =(CT44-DC44)*10^6 -> 0 | DZ44: =(CW44-DD44)*10^6 -> 0
B45: FRAIS D'AGENCES PUBLICITAIRES | C45: Opex39 | CU45: =+CR45-CS45 -> 0 | CV45: =+CR45-CT45 -> 0 | CX45: =IFERROR(CR45/CW45-1, "-") -> - | DJ45: =SUM(D45,J45,P45,V45,AD45,AL45,AU45,BC45,BK45,BT45,CB45,CJ45)-CR45 -> 0 | DK45: =SUM(E45,K45,Q45,W45,AE45,AM45,AV45,BD45,BL45,BU45,CC45,CK45)-CS45 -> 0 | DL45: =SUM(G45,M45,S45,AA45,AI45,AR45,AZ45,BH45,BQ45,BY45,CG45,CO45)-CW45 -> 0 | DM45: =SUM(D45,J45,P45,V45,AD45,AL45,AU45,BC45,,BN45,BV45,CD45,CL45)-CT45 -> 0 | DP45: =#VALUE! -> #VALUE! | DQ45: =-CR45+DP45/10^6 -> #VALUE! | DR45: =SUM(E45,K45,Q45,W45,AE45,AM45,AV45,BD45,BL45,BU45,CC45,CK45)-CS45 -> 0 | DS45: =SUM(D45,J45,P45,V45,AD45,AL45,AU45,BC45,,BN45,BV45,CD45,CL45)-CT45 -> 0 | DU45: 188.133 | DV45: =DU45-CJ45 -> 188.133 | DX45: =(CS45-CZ45)*10^6 -> 0 | DY45: =(CT45-DC45)*10^6 -> 0 | DZ45: =(CW45-DD45)*10^6 -> 0
B46: CONCEPTIONS, PRODUCTION PUBLIC | C46: Opex40 | CU46: =+CR46-CS46 -> 0 | CV46: =+CR46-CT46 -> 0 | CX46: =IFERROR(CR46/CW46-1, "-") -> - | DJ46: =SUM(D46,J46,P46,V46,AD46,AL46,AU46,BC46,BK46,BT46,CB46,CJ46)-CR46 -> 0 | DK46: =SUM(E46,K46,Q46,W46,AE46,AM46,AV46,BD46,BL46,BU46,CC46,CK46)-CS46 -> 0 | DL46: =SUM(G46,M46,S46,AA46,AI46,AR46,AZ46,BH46,BQ46,BY46,CG46,CO46)-CW46 -> 0 | DM46: =SUM(D46,J46,P46,V46,AD46,AL46,AU46,BC46,,BN46,BV46,CD46,CL46)-CT46 -> 0 | DP46: 0 | DQ46: =-CR46+DP46/10^6 -> 0 | DR46: =SUM(E46,K46,Q46,W46,AE46,AM46,AV46,BD46,BL46,BU46,CC46,CK46)-CS46 -> 0 | DS46: =SUM(D46,J46,P46,V46,AD46,AL46,AU46,BC46,,BN46,BV46,CD46,CL46)-CT46 -> 0 | DU46: 0 | DV46: =DU46-CJ46 -> 0 | DX46: =(CS46-CZ46)*10^6 -> 0 | DY46: =(CT46-DC46)*10^6 -> 0 | DZ46: =(CW46-DD46)*10^6 -> 0
B47: CATALOGUES, IMPRIMES PUBLICITA | C47: Opex41 | CU47: =+CR47-CS47 -> 0 | CV47: =+CR47-CT47 -> 0 | CX47: =IFERROR(CR47/CW47-1, "-") -> - | DJ47: =SUM(D47,J47,P47,V47,AD47,AL47,AU47,BC47,BK47,BT47,CB47,CJ47)-CR47 -> 0 | DK47: =SUM(E47,K47,Q47,W47,AE47,AM47,AV47,BD47,BL47,BU47,CC47,CK47)-CS47 -> 0 | DL47: =SUM(G47,M47,S47,AA47,AI47,AR47,AZ47,BH47,BQ47,BY47,CG47,CO47)-CW47 -> 0 | DM47: =SUM(D47,J47,P47,V47,AD47,AL47,AU47,BC47,,BN47,BV47,CD47,CL47)-CT47 -> 0 | DP47: 277712779 | DQ47: =-CR47+DP47/10^6 -> 277.71278 | DR47: =SUM(E47,K47,Q47,W47,AE47,AM47,AV47,BD47,BL47,BU47,CC47,CK47)-CS47 -> 0 | DS47: =SUM(D47,J47,P47,V47,AD47,AL47,AU47,BC47,,BN47,BV47,CD47,CL47)-CT47 -> 0 | DU47: 12.527459 | DV47: =DU47-CJ47 -> 12.527459 | DX47: =(CS47-CZ47)*10^6 -> 0 | DY47: =(CT47-DC47)*10^6 -> 0 | DZ47: =(CW47-DD47)*10^6 -> 0
B48: ENSEIGNES PUBLICITAIRES - AFFI | C48: Opex42 | CU48: =+CR48-CS48 -> 0 | CV48: =+CR48-CT48 -> 0 | CX48: =IFERROR(CR48/CW48-1, "-") -> - | DJ48: =SUM(D48,J48,P48,V48,AD48,AL48,AU48,BC48,BK48,BT48,CB48,CJ48)-CR48 -> 0 | DK48: =SUM(E48,K48,Q48,W48,AE48,AM48,AV48,BD48,BL48,BU48,CC48,CK48)-CS48 -> 0 | DL48: =SUM(G48,M48,S48,AA48,AI48,AR48,AZ48,BH48,BQ48,BY48,CG48,CO48)-CW48 -> 0 | DM48: =SUM(D48,J48,P48,V48,AD48,AL48,AU48,BC48,,BN48,BV48,CD48,CL48)-CT48 -> 0 | DP48: 398425246 | DQ48: =-CR48+DP48/10^6 -> 398.42525 | DR48: =SUM(E48,K48,Q48,W48,AE48,AM48,AV48,BD48,BL48,BU48,CC48,CK48)-CS48 -> 0 | DS48: =SUM(D48,J48,P48,V48,AD48,AL48,AU48,BC48,,BN48,BV48,CD48,CL48)-CT48 -> 0 | DU48: 24.820232 | DV48: =DU48-CJ48 -> 24.820232 | DX48: =(CS48-CZ48)*10^6 -> 0 | DY48: =(CT48-DC48)*10^6 -> 0 | DZ48: =(CW48-DD48)*10^6 -> 0
B49: FOIRES ET EXPOSITIONS | C49: Opex43 | CU49: =+CR49-CS49 -> 0 | CV49: =+CR49-CT49 -> 0 | CX49: =IFERROR(CR49/CW49-1, "-") -> - | DJ49: =SUM(D49,J49,P49,V49,AD49,AL49,AU49,BC49,BK49,BT49,CB49,CJ49)-CR49 -> 0 | DK49: =SUM(E49,K49,Q49,W49,AE49,AM49,AV49,BD49,BL49,BU49,CC49,CK49)-CS49 -> 0 | DL49: =SUM(G49,M49,S49,AA49,AI49,AR49,AZ49,BH49,BQ49,BY49,CG49,CO49)-CW49 -> 0 | DM49: =SUM(D49,J49,P49,V49,AD49,AL49,AU49,BC49,,BN49,BV49,CD49,CL49)-CT49 -> 0 | DP49: 0 | DQ49: =-CR49+DP49/10^6 -> 0 | DR49: =SUM(E49,K49,Q49,W49,AE49,AM49,AV49,BD49,BL49,BU49,CC49,CK49)-CS49 -> 0 | DS49: =SUM(D49,J49,P49,V49,AD49,AL49,AU49,BC49,,BN49,BV49,CD49,CL49)-CT49 -> 0 | DU49: 0 | DV49: =DU49-CJ49 -> 0 | DX49: =(CS49-CZ49)*10^6 -> 0 | DY49: =(CT49-DC49)*10^6 -> 0 | DZ49: =(CW49-DD49)*10^6 -> 0
B50: CADEAUX A LA CLIENTELE | C50: Opex44 | CU50: =+CR50-CS50 -> 0 | CV50: =+CR50-CT50 -> 0 | CX50: =IFERROR(CR50/CW50-1, "-") -> - | DJ50: =SUM(D50,J50,P50,V50,AD50,AL50,AU50,BC50,BK50,BT50,CB50,CJ50)-CR50 -> 0 | DK50: =SUM(E50,K50,Q50,W50,AE50,AM50,AV50,BD50,BL50,BU50,CC50,CK50)-CS50 -> 0 | DL50: =SUM(G50,M50,S50,AA50,AI50,AR50,AZ50,BH50,BQ50,BY50,CG50,CO50)-CW50 -> 0 | DM50: =SUM(D50,J50,P50,V50,AD50,AL50,AU50,BC50,,BN50,BV50,CD50,CL50)-CT50 -> 0 | DP50: =#VALUE! -> #VALUE! | DQ50: =-CR50+DP50/10^6 -> #VALUE! | DR50: =SUM(E50,K50,Q50,W50,AE50,AM50,AV50,BD50,BL50,BU50,CC50,CK50)-CS50 -> 0 | DS50: =SUM(D50,J50,P50,V50,AD50,AL50,AU50,BC50,,BN50,BV50,CD50,CL50)-CT50 -> 0 | DU50: 0 | DV50: =DU50-CJ50 -> 0 | DX50: =(CS50-CZ50)*10^6 -> 0 | DY50: =(CT50-DC50)*10^6 -> 0 | DZ50: =(CW50-DD50)*10^6 -> 0
B51: FRAIS DE COLLOQUES, SEMINAIRES | C51: Opex45 | CU51: =+CR51-CS51 -> 0 | CV51: =+CR51-CT51 -> 0 | CX51: =IFERROR(CR51/CW51-1, "-") -> - | DJ51: =SUM(D51,J51,P51,V51,AD51,AL51,AU51,BC51,BK51,BT51,CB51,CJ51)-CR51 -> 0 | DK51: =SUM(E51,K51,Q51,W51,AE51,AM51,AV51,BD51,BL51,BU51,CC51,CK51)-CS51 -> 0 | DL51: =SUM(G51,M51,S51,AA51,AI51,AR51,AZ51,BH51,BQ51,BY51,CG51,CO51)-CW51 -> 0 | DM51: =SUM(D51,J51,P51,V51,AD51,AL51,AU51,BC51,,BN51,BV51,CD51,CL51)-CT51 -> 0 | DP51: 0 | DQ51: =-CR51+DP51/10^6 -> 0 | DR51: =SUM(E51,K51,Q51,W51,AE51,AM51,AV51,BD51,BL51,BU51,CC51,CK51)-CS51 -> 0 | DS51: =SUM(D51,J51,P51,V51,AD51,AL51,AU51,BC51,,BN51,BV51,CD51,CL51)-CT51 -> 0 | DU51: 0 | DV51: =DU51-CJ51 -> 0 | DX51: =(CS51-CZ51)*10^6 -> 0 | DY51: =(CT51-DC51)*10^6 -> 0 | DZ51: =(CW51-DD51)*10^6 -> 0
B52: RELATIONS PUBLIQUES | C52: Opex46 | CU52: =+CR52-CS52 -> 0 | CV52: =+CR52-CT52 -> 0 | CX52: =IFERROR(CR52/CW52-1, "-") -> - | DJ52: =SUM(D52,J52,P52,V52,AD52,AL52,AU52,BC52,BK52,BT52,CB52,CJ52)-CR52 -> 0 | DK52: =SUM(E52,K52,Q52,W52,AE52,AM52,AV52,BD52,BL52,BU52,CC52,CK52)-CS52 -> 0 | DL52: =SUM(G52,M52,S52,AA52,AI52,AR52,AZ52,BH52,BQ52,BY52,CG52,CO52)-CW52 -> 0 | DM52: =SUM(D52,J52,P52,V52,AD52,AL52,AU52,BC52,,BN52,BV52,CD52,CL52)-CT52 -> 0 | DP52: =#VALUE! -> #VALUE! | DQ52: =-CR52+DP52/10^6 -> #VALUE! | DR52: =SUM(E52,K52,Q52,W52,AE52,AM52,AV52,BD52,BL52,BU52,CC52,CK52)-CS52 -> 0 | DS52: =SUM(D52,J52,P52,V52,AD52,AL52,AU52,BC52,,BN52,BV52,CD52,CL52)-CT52 -> 0 | DU52: 76.338363 | DV52: =DU52-CJ52 -> 76.338363 | DX52: =(CS52-CZ52)*10^6 -> 0 | DY52: =(CT52-DC52)*10^6 -> 0 | DZ52: =(CW52-DD52)*10^6 -> 0
B53: DEVELOPPEMENT DE LA MARQUE | C53: Opex47 | CU53: =+CR53-CS53 -> 0 | CV53: =+CR53-CT53 -> 0 | CX53: =IFERROR(CR53/CW53-1, "-") -> - | DJ53: =SUM(D53,J53,P53,V53,AD53,AL53,AU53,BC53,BK53,BT53,CB53,CJ53)-CR53 -> 0 | DK53: =SUM(E53,K53,Q53,W53,AE53,AM53,AV53,BD53,BL53,BU53,CC53,CK53)-CS53 -> 0 | DL53: =SUM(G53,M53,S53,AA53,AI53,AR53,AZ53,BH53,BQ53,BY53,CG53,CO53)-CW53 -> 0 | DM53: =SUM(D53,J53,P53,V53,AD53,AL53,AU53,BC53,,BN53,BV53,CD53,CL53)-CT53 -> 0 | DP53: 0 | DQ53: =-CR53+DP53/10^6 -> 0 | DR53: =SUM(E53,K53,Q53,W53,AE53,AM53,AV53,BD53,BL53,BU53,CC53,CK53)-CS53 -> 0 | DS53: =SUM(D53,J53,P53,V53,AD53,AL53,AU53,BC53,,BN53,BV53,CD53,CL53)-CT53 -> 0 | DU53: 0 | DV53: =DU53-CJ53 -> 0 | DX53: =(CS53-CZ53)*10^6 -> 0 | DY53: =(CT53-DC53)*10^6 -> 0 | DZ53: =(CW53-DD53)*10^6 -> 0
B54: AUTRES IMPOTS ET TAXES DIRECTS | C54: Opex48 | CU54: =+CR54-CS54 -> 0 | CV54: =+CR54-CT54 -> 0 | CX54: =IFERROR(CR54/CW54-1, "-") -> - | DJ54: =SUM(D54,J54,P54,V54,AD54,AL54,AU54,BC54,BK54,BT54,CB54,CJ54)-CR54 -> 0 | DK54: =SUM(E54,K54,Q54,W54,AE54,AM54,AV54,BD54,BL54,BU54,CC54,CK54)-CS54 -> 0 | DL54: =SUM(G54,M54,S54,AA54,AI54,AR54,AZ54,BH54,BQ54,BY54,CG54,CO54)-CW54 -> 0 | DM54: =SUM(D54,J54,P54,V54,AD54,AL54,AU54,BC54,,BN54,BV54,CD54,CL54)-CT54 -> 0 | DQ54: =-CR54+DP54/10^6 -> 0 | DR54: =SUM(E54,K54,Q54,W54,AE54,AM54,AV54,BD54,BL54,BU54,CC54,CK54)-CS54 -> 0 | DS54: =SUM(D54,J54,P54,V54,AD54,AL54,AU54,BC54,,BN54,BV54,CD54,CL54)-CT54 -> 0 | DV54: =DU54-CJ54 -> 0 | DX54: =(CS54-CZ54)*10^6 -> 0 | DY54: =(CT54-DC54)*10^6 -> 0 | DZ54: =(CW54-DD54)*10^6 -> 0
B55: ENQUETES ET ETUDES DE MARCHES | C55: Opex49 | CU55: =+CR55-CS55 -> 0 | CV55: =+CR55-CT55 -> 0 | CX55: =IFERROR(CR55/CW55-1, "-") -> - | DJ55: =SUM(D55,J55,P55,V55,AD55,AL55,AU55,BC55,BK55,BT55,CB55,CJ55)-CR55 -> 0 | DK55: =SUM(E55,K55,Q55,W55,AE55,AM55,AV55,BD55,BL55,BU55,CC55,CK55)-CS55 -> 0 | DL55: =SUM(G55,M55,S55,AA55,AI55,AR55,AZ55,BH55,BQ55,BY55,CG55,CO55)-CW55 -> 0 | DM55: =SUM(D55,J55,P55,V55,AD55,AL55,AU55,BC55,,BN55,BV55,CD55,CL55)-CT55 -> 0 | DP55: -14212630 | DQ55: =-CR55+DP55/10^6 -> -14.21263 | DR55: =SUM(E55,K55,Q55,W55,AE55,AM55,AV55,BD55,BL55,BU55,CC55,CK55)-CS55 -> 0 | DS55: =SUM(D55,J55,P55,V55,AD55,AL55,AU55,BC55,,BN55,BV55,CD55,CL55)-CT55 -> 0 | DU55: 0 | DV55: =DU55-CJ55 -> 0 | DX55: =(CS55-CZ55)*10^6 -> 0 | DY55: =(CT55-DC55)*10^6 -> 0 | DZ55: =(CW55-DD55)*10^6 -> 0
C56: Opex50 | CX56: =IFERROR(CR56/CW56-1, "-") -> - | DJ56: =SUM(D56,J56,P56,V56,AD56,AL56,AU56,BC56,BK56,BT56,CB56,CJ56)-CR56 -> 0 | DK56: =SUM(E56,K56,Q56,W56,AE56,AM56,AV56,BD56,BL56,BU56,CC56,CK56)-CS56 -> 0 | DL56: =SUM(G56,M56,S56,AA56,AI56,AR56,AZ56,BH56,BQ56,BY56,CG56,CO56)-CW56 -> 0 | DM56: =SUM(D56,J56,P56,V56,AD56,AL56,AU56,BC56,,BN56,BV56,CD56,CL56)-CT56 -> 0 | DQ56: =-CR56+DP56/10^6 -> 0 | DR56: =SUM(E56,K56,Q56,W56,AE56,AM56,AV56,BD56,BL56,BU56,CC56,CK56)-CS56 -> 0 | DS56: =SUM(D56,J56,P56,V56,AD56,AL56,AU56,BC56,,BN56,BV56,CD56,CL56)-CT56 -> 0 | DV56: =DU56-CJ56 -> 0 | DX56: =(CS56-CZ56)*10^6 -> 0 | DY56: =(CT56-DC56)*10^6 -> 0 | DZ56: =(CW56-DD56)*10^6 -> 0
B57: Exploitation & maintenance | C57: Opex51 | CU57: =+CR57-CS57 -> 0 | CV57: =+CR57-CT57 -> 0 | CX57: =IFERROR(CR57/CW57-1, "-") -> - | DE57: =+CZ57/DD57-1 -> #DIV/0! | DF57: =+DA57/DD57-1 -> #DIV/0! | DG57: =+DB57/DD57-1 -> #DIV/0! | DH57: =+DC57/DD57-1 -> #DIV/0! | DJ57: =SUM(D57,J57,P57,V57,AD57,AL57,AU57,BC57,BK57,BT57,CB57,CJ57)-CR57 -> 0 | DL57: =SUM(G57,M57,S57,AA57,AI57,AR57,AZ57,BH57,BQ57,BY57,CG57,CO57)-CW57 -> 0 | DM57: =SUM(D57,J57,P57,V57,AD57,AL57,AU57,BC57,,BN57,BV57,CD57,CL57)-CT57 -> 0 | DP57: =+DP58+DP79+DP97+DP100+DP106 -> 17775202009 | DQ57: =-CR57+DP57/10^6 -> 17775.202 | DR57: =SUM(E57,K57,Q57,W57,AE57,AM57,AV57,BD57,BL57,BU57,CC57,CK57)-CS57 -> 0 | DS57: =SUM(D57,J57,P57,V57,AD57,AL57,AU57,BC57,,BN57,BV57,CD57,CL57)-CT57 -> 0 | DU57: 1613.6547 | DV57: =DU57-CJ57 -> 1613.6547 | DX57: =(CS57-CZ57)*10^6 -> 0 | DY57: =(CT57-DC57)*10^6 -> 0 | DZ57: =(CW57-DD57)*10^6 -> 0
B58: Achat d'énergie - Bâtiment - Gardiennage | C58: Opex52 | CU58: =+CR58-CS58 -> 0 | CV58: =+CR58-CT58 -> 0 | CX58: =IFERROR(CR58/CW58-1, "-") -> - | DE58: =+CZ58/DD58-1 -> #DIV/0! | DF58: =+DA58/DD58-1 -> #DIV/0! | DG58: =+DB58/DD58-1 -> #DIV/0! | DH58: =+DC58/DD58-1 -> #DIV/0! | DJ58: =SUM(D58,J58,P58,V58,AD58,AL58,AU58,BC58,BK58,BT58,CB58,CJ58)-CR58 -> 0 | DK58: =SUM(E58,K58,Q58,W58,AE58,AM58,AV58,BD58,BL58,BU58,CC58,CK58)-CS58 -> 0 | DL58: =SUM(G58,M58,S58,AA58,AI58,AR58,AZ58,BH58,BQ58,BY58,CG58,CO58)-CW58 -> 0 | DM58: =SUM(D58,J58,P58,V58,AD58,AL58,AU58,BC58,,BN58,BV58,CD58,CL58)-CT58 -> 0 | DP58: =SUM(DP59:DP78) -> 8024349960 | DQ58: =-CR58+DP58/10^6 -> 8024.35 | DR58: =SUM(E58,K58,Q58,W58,AE58,AM58,AV58,BD58,BL58,BU58,CC58,CK58)-CS58 -> 0 | DS58: =SUM(D58,J58,P58,V58,AD58,AL58,AU58,BC58,,BN58,BV58,CD58,CL58)-CT58 -> 0 | DU58: 722.66259 | DV58: =DU58-CJ58 -> 722.66259 | DX58: =(CS58-CZ58)*10^6 -> 0 | DY58: =(CT58-DC58)*10^6 -> 0 | DZ58: =(CW58-DD58)*10^6 -> 0
B59: LOYERS ENTREPOTS | C59: Opex53 | CU59: =+CR59-CS59 -> 0 | CV59: =+CR59-CT59 -> 0 | CX59: =IFERROR(CR59/CW59-1, "-") -> - | DE59: =+CZ59/DD59-1 -> #DIV/0! | DF59: =+DA59/DD59-1 -> #DIV/0! | DG59: =+DB59/DD59-1 -> #DIV/0! | DH59: =+DC59/DD59-1 -> #DIV/0! | DJ59: =SUM(D59,J59,P59,V59,AD59,AL59,AU59,BC59,BK59,BT59,CB59,CJ59)-CR59 -> 0 | DK59: =SUM(E59,K59,Q59,W59,AE59,AM59,AV59,BD59,BL59,BU59,CC59,CK59)-CS59 -> 0 | DL59: =SUM(G59,M59,S59,AA59,AI59,AR59,AZ59,BH59,BQ59,BY59,CG59,CO59)-CW59 -> 0 | DM59: =SUM(D59,J59,P59,V59,AD59,AL59,AU59,BC59,,BN59,BV59,CD59,CL59)-CT59 -> 0 | DP59: 137236368 | DQ59: =-CR59+DP59/10^6 -> 137.23637 | DR59: =SUM(E59,K59,Q59,W59,AE59,AM59,AV59,BD59,BL59,BU59,CC59,CK59)-CS59 -> 0 | DS59: =SUM(D59,J59,P59,V59,AD59,AL59,AU59,BC59,,BN59,BV59,CD59,CL59)-CT59 -> 0 | DU59: 11.586364 | DV59: =DU59-CJ59 -> 11.586364 | DX59: =(CS59-CZ59)*10^6 -> 0 | DY59: =(CT59-DC59)*10^6 -> 0 | DZ59: =(CW59-DD59)*10^6 -> 0
B60: ELECTRICITE CT AKASSATO | C60: Opex54 | CU60: =+CR60-CS60 -> 0 | CV60: =+CR60-CT60 -> 0 | CX60: =IFERROR(CR60/CW60-1, "-") -> - | DJ60: =SUM(D60,J60,P60,V60,AD60,AL60,AU60,BC60,BK60,BT60,CB60,CJ60)-CR60 -> 0 | DK60: =SUM(E60,K60,Q60,W60,AE60,AM60,AV60,BD60,BL60,BU60,CC60,CK60)-CS60 -> 0 | DL60: =SUM(G60,M60,S60,AA60,AI60,AR60,AZ60,BH60,BQ60,BY60,CG60,CO60)-CW60 -> 0 | DM60: =SUM(D60,J60,P60,V60,AD60,AL60,AU60,BC60,,BN60,BV60,CD60,CL60)-CT60 -> 0 | DP60: 0 | DQ60: =-CR60+DP60/10^6 -> 0 | DR60: =SUM(E60,K60,Q60,W60,AE60,AM60,AV60,BD60,BL60,BU60,CC60,CK60)-CS60 -> 0 | DS60: =SUM(D60,J60,P60,V60,AD60,AL60,AU60,BC60,,BN60,BV60,CD60,CL60)-CT60 -> 0 | DU60: 0 | DV60: =DU60-CJ60 -> 0 | DX60: =(CS60-CZ60)*10^6 -> 0 | DY60: =(CT60-DC60)*10^6 -> 0 | DZ60: =(CW60-DD60)*10^6 -> 0
B61: EAU CT | C61: Opex55 | CU61: =+CR61-CS61 -> 0 | CV61: =+CR61-CT61 -> 0 | CX61: =IFERROR(CR61/CW61-1, "-") -> - | DJ61: =SUM(D61,J61,P61,V61,AD61,AL61,AU61,BC61,BK61,BT61,CB61,CJ61)-CR61 -> 0 | DK61: =SUM(E61,K61,Q61,W61,AE61,AM61,AV61,BD61,BL61,BU61,CC61,CK61)-CS61 -> 0 | DL61: =SUM(G61,M61,S61,AA61,AI61,AR61,AZ61,BH61,BQ61,BY61,CG61,CO61)-CW61 -> 0 | DM61: =SUM(D61,J61,P61,V61,AD61,AL61,AU61,BC61,,BN61,BV61,CD61,CL61)-CT61 -> 0 | DP61: 0 | DQ61: =-CR61+DP61/10^6 -> 0 | DR61: =SUM(E61,K61,Q61,W61,AE61,AM61,AV61,BD61,BL61,BU61,CC61,CK61)-CS61 -> 0 | DS61: =SUM(D61,J61,P61,V61,AD61,AL61,AU61,BC61,,BN61,BV61,CD61,CL61)-CT61 -> 0 | DU61: 0 | DV61: =DU61-CJ61 -> 0 | DX61: =(CS61-CZ61)*10^6 -> 0 | DY61: =(CT61-DC61)*10^6 -> 0 | DZ61: =(CW61-DD61)*10^6 -> 0
B62: ELECTRICITE SITES TECHNIQUES | C62: Opex56 | CU62: =+CR62-CS62 -> 0 | CV62: =+CR62-CT62 -> 0 | CX62: =IFERROR(CR62/CW62-1, "-") -> - | DE62: =+CZ62/DD62-1 -> #DIV/0! | DF62: =+DA62/DD62-1 -> #DIV/0! | DG62: =+DB62/DD62-1 -> #DIV/0! | DH62: =+DC62/DD62-1 -> #DIV/0! | DJ62: =SUM(D62,J62,P62,V62,AD62,AL62,AU62,BC62,BK62,BT62,CB62,CJ62)-CR62 -> 0 | DK62: =SUM(E62,K62,Q62,W62,AE62,AM62,AV62,BD62,BL62,BU62,CC62,CK62)-CS62 -> 0 | DL62: =SUM(G62,M62,S62,AA62,AI62,AR62,AZ62,BH62,BQ62,BY62,CG62,CO62)-CW62 -> 0 | DM62: =SUM(D62,J62,P62,V62,AD62,AL62,AU62,BC62,,BN62,BV62,CD62,CL62)-CT62 -> 0 | DP62: 2770925511 | DQ62: =-CR62+DP62/10^6 -> 2770.9255 | DR62: =SUM(E62,K62,Q62,W62,AE62,AM62,AV62,BD62,BL62,BU62,CC62,CK62)-CS62 -> 0 | DS62: =SUM(D62,J62,P62,V62,AD62,AL62,AU62,BC62,,BN62,BV62,CD62,CL62)-CT62 -> 0 | DU62: 249.29905 | DV62: =DU62-CJ62 -> 249.29905 | DX62: =(CS62-CZ62)*10^6 -> 0 | DY62: =(CT62-DC62)*10^6 -> 0 | DZ62: =(CW62-DD62)*10^6 -> 0
B63: ELECTRICITE SITES TECHNIQUES C | C63: Opex57 | CU63: =+CR63-CS63 -> 0 | CV63: =+CR63-CT63 -> 0 | CX63: =IFERROR(CR63/CW63-1, "-") -> - | DJ63: =SUM(D63,J63,P63,V63,AD63,AL63,AU63,BC63,BK63,BT63,CB63,CJ63)-CR63 -> 0 | DK63: =SUM(E63,K63,Q63,W63,AE63,AM63,AV63,BD63,BL63,BU63,CC63,CK63)-CS63 -> 0 | DL63: =SUM(G63,M63,S63,AA63,AI63,AR63,AZ63,BH63,BQ63,BY63,CG63,CO63)-CW63 -> 0 | DM63: =SUM(D63,J63,P63,V63,AD63,AL63,AU63,BC63,,BN63,BV63,CD63,CL63)-CT63 -> 0 | DQ63: =-CR63+DP63/10^6 -> 0 | DR63: =SUM(E63,K63,Q63,W63,AE63,AM63,AV63,BD63,BL63,BU63,CC63,CK63)-CS63 -> 0 | DS63: =SUM(D63,J63,P63,V63,AD63,AL63,AU63,BC63,,BN63,BV63,CD63,CL63)-CT63 -> 0 | DV63: =DU63-CJ63 -> 0 | DX63: =(CS63-CZ63)*10^6 -> 0 | DY63: =(CT63-DC63)*10^6 -> 0 | DZ63: =(CW63-DD63)*10^6 -> 0
B64: VARIATION DE STOCKS, CARBURANT | C64: Opex58 | CU64: =+CR64-CS64 -> 0 | CV64: =+CR64-CT64 -> 0 | CX64: =IFERROR(CR64/CW64-1, "-") -> - | DE64: =+CZ64/DD64-1 -> #DIV/0! | DF64: =+DA64/DD64-1 -> #DIV/0! | DG64: =+DB64/DD64-1 -> #DIV/0! | DH64: =+DC64/DD64-1 -> #DIV/0! | DJ64: =SUM(D64,J64,P64,V64,AD64,AL64,AU64,BC64,BK64,BT64,CB64,CJ64)-CR64 -> 0 | DK64: =SUM(E64,K64,Q64,W64,AE64,AM64,AV64,BD64,BL64,BU64,CC64,CK64)-CS64 -> 0 | DL64: =SUM(G64,M64,S64,AA64,AI64,AR64,AZ64,BH64,BQ64,BY64,CG64,CO64)-CW64 -> 0 | DM64: =SUM(D64,J64,P64,V64,AD64,AL64,AU64,BC64,,BN64,BV64,CD64,CL64)-CT64 -> 0 | DP64: -147538860 | DQ64: =-CR64+DP64/10^6 -> -147.53886 | DR64: =SUM(E64,K64,Q64,W64,AE64,AM64,AV64,BD64,BL64,BU64,CC64,CK64)-CS64 -> 0 | DS64: =SUM(D64,J64,P64,V64,AD64,AL64,AU64,BC64,,BN64,BV64,CD64,CL64)-CT64 -> 0 | DU64: -40.841398 | DV64: =DU64-CJ64 -> -40.841398 | DX64: =(CS64-CZ64)*10^6 -> 0 | DY64: =(CT64-DC64)*10^6 -> 0 | DZ64: =(CW64-DD64)*10^6 -> 0
B65: FRAIS DE CARBURANT ET LUBRIFIA | C65: Opex59 | CU65: =+CR65-CS65 -> 0 | CV65: =+CR65-CT65 -> 0 | CX65: =IFERROR(CR65/CW65-1, "-") -> - | DE65: =+CZ65/DD65-1 -> #DIV/0! | DF65: =+DA65/DD65-1 -> #DIV/0! | DG65: =+DB65/DD65-1 -> #DIV/0! | DH65: =+DC65/DD65-1 -> #DIV/0! | DJ65: =SUM(D65,J65,P65,V65,AD65,AL65,AU65,BC65,BK65,BT65,CB65,CJ65)-CR65 -> 0 | DK65: =SUM(E65,K65,Q65,W65,AE65,AM65,AV65,BD65,BL65,BU65,CC65,CK65)-CS65 -> 0 | DL65: =SUM(G65,M65,S65,AA65,AI65,AR65,AZ65,BH65,BQ65,BY65,CG65,CO65)-CW65 -> 0 | DM65: =SUM(D65,J65,P65,V65,AD65,AL65,AU65,BC65,,BN65,BV65,CD65,CL65)-CT65 -> 0 | DP65: 2742772775 | DQ65: =-CR65+DP65/10^6 -> 2742.7728 | DR65: =SUM(E65,K65,Q65,W65,AE65,AM65,AV65,BD65,BL65,BU65,CC65,CK65)-CS65 -> 0 | DS65: =SUM(D65,J65,P65,V65,AD65,AL65,AU65,BC65,,BN65,BV65,CD65,CL65)-CT65 -> 0 | DU65: 260.42687 | DV65: =DU65-CJ65 -> 260.42687 | DX65: =(CS65-CZ65)*10^6 -> 0 | DY65: =(CT65-DC65)*10^6 -> 0 | DZ65: =(CW65-DD65)*10^6 -> 0
B66: LOYERS SITES TECHNIQUES | C66: Opex60 | CU66: =+CR66-CS66 -> 0 | CV66: =+CR66-CT66 -> 0 | CX66: =IFERROR(CR66/CW66-1, "-") -> - | DE66: =+CZ66/DD66-1 -> #DIV/0! | DF66: =+DA66/DD66-1 -> #DIV/0! | DG66: =+DB66/DD66-1 -> #DIV/0! | DH66: =+DC66/DD66-1 -> #DIV/0! | DJ66: =SUM(D66,J66,P66,V66,AD66,AL66,AU66,BC66,BK66,BT66,CB66,CJ66)-CR66 -> 0 | DK66: =SUM(E66,K66,Q66,W66,AE66,AM66,AV66,BD66,BL66,BU66,CC66,CK66)-CS66 -> 0 | DL66: =SUM(G66,M66,S66,AA66,AI66,AR66,AZ66,BH66,BQ66,BY66,CG66,CO66)-CW66 -> 0 | DM66: =SUM(D66,J66,P66,V66,AD66,AL66,AU66,BC66,,BN66,BV66,CD66,CL66)-CT66 -> 0 | DP66: 800076571 | DQ66: =-CR66+DP66/10^6 -> 800.07657 | DR66: =SUM(E66,K66,Q66,W66,AE66,AM66,AV66,BD66,BL66,BU66,CC66,CK66)-CS66 -> 0 | DS66: =SUM(D66,J66,P66,V66,AD66,AL66,AU66,BC66,,BN66,BV66,CD66,CL66)-CT66 -> 0 | DU66: 72.133524 | DV66: =DU66-CJ66 -> 72.133524 | DX66: =(CS66-CZ66)*10^6 -> 0 | DY66: =(CT66-DC66)*10^6 -> 0 | DZ66: =(CW66-DD66)*10^6 -> 0
B67: FRAIS DE GARDIENNAGE | C67: Opex61 | CU67: =+CR67-CS67 -> 0 | CV67: =+CR67-CT67 -> 0 | CX67: =IFERROR(CR67/CW67-1, "-") -> - | DE67: =+CZ67/DD67-1 -> #DIV/0! | DF67: =+DA67/DD67-1 -> #DIV/0! | DG67: =+DB67/DD67-1 -> #DIV/0! | DH67: =+DC67/DD67-1 -> #DIV/0! | DJ67: =SUM(D67,J67,P67,V67,AD67,AL67,AU67,BC67,BK67,BT67,CB67,CJ67)-CR67 -> 0 | DK67: =SUM(E67,K67,Q67,W67,AE67,AM67,AV67,BD67,BL67,BU67,CC67,CK67)-CS67 -> 0 | DL67: =SUM(G67,M67,S67,AA67,AI67,AR67,AZ67,BH67,BQ67,BY67,CG67,CO67)-CW67 -> 0 | DM67: =SUM(D67,J67,P67,V67,AD67,AL67,AU67,BC67,,BN67,BV67,CD67,CL67)-CT67 -> 0 | DP67: 983202562 | DQ67: =-CR67+DP67/10^6 -> 983.20256 | DR67: =SUM(E67,K67,Q67,W67,AE67,AM67,AV67,BD67,BL67,BU67,CC67,CK67)-CS67 -> 0 | DS67: =SUM(D67,J67,P67,V67,AD67,AL67,AU67,BC67,,BN67,BV67,CD67,CL67)-CT67 -> 0 | DU67: 83.154258 | DV67: =DU67-CJ67 -> 83.154258 | DX67: =(CS67-CZ67)*10^6 -> 0 | DY67: =(CT67-DC67)*10^6 -> 0 | DZ67: =(CW67-DD67)*10^6 -> 0
B68: LOYERS SIEGE ET AGENCES | C68: Opex62 | CU68: =+CR68-CS68 -> 0 | CV68: =+CR68-CT68 -> 0 | CX68: =IFERROR(CR68/CW68-1, "-") -> - | DE68: =+CZ68/DD68-1 -> #DIV/0! | DF68: =+DA68/DD68-1 -> #DIV/0! | DG68: =+DB68/DD68-1 -> #DIV/0! | DH68: =+DC68/DD68-1 -> #DIV/0! | DJ68: =SUM(D68,J68,P68,V68,AD68,AL68,AU68,BC68,BK68,BT68,CB68,CJ68)-CR68 -> 0 | DK68: =SUM(E68,K68,Q68,W68,AE68,AM68,AV68,BD68,BL68,BU68,CC68,CK68)-CS68 -> 0 | DL68: =SUM(G68,M68,S68,AA68,AI68,AR68,AZ68,BH68,BQ68,BY68,CG68,CO68)-CW68 -> 0 | DM68: =SUM(D68,J68,P68,V68,AD68,AL68,AU68,BC68,,BN68,BV68,CD68,CL68)-CT68 -> 0 | DP68: -231139194 | DQ68: =-CR68+DP68/10^6 -> -231.13919 | DR68: =SUM(E68,K68,Q68,W68,AE68,AM68,AV68,BD68,BL68,BU68,CC68,CK68)-CS68 -> 0 | DS68: =SUM(D68,J68,P68,V68,AD68,AL68,AU68,BC68,,BN68,BV68,CD68,CL68)-CT68 -> 0 | DU68: -5.670593 | DV68: =DU68-CJ68 -> -5.670593 | DX68: =(CS68-CZ68)*10^6 -> 0 | DY68: =(CT68-DC68)*10^6 -> 0 | DZ68: =(CW68-DD68)*10^6 -> 0
B69: FOURNITURES D'ENTRETIEN NON ST | C69: Opex63 | CU69: =+CR69-CS69 -> 0 | CV69: =+CR69-CT69 -> 0 | CX69: =IFERROR(CR69/CW69-1, "-") -> - | DJ69: =SUM(D69,J69,P69,V69,AD69,AL69,AU69,BC69,BK69,BT69,CB69,CJ69)-CR69 -> 0 | DK69: =SUM(E69,K69,Q69,W69,AE69,AM69,AV69,BD69,BL69,BU69,CC69,CK69)-CS69 -> 0 | DL69: =SUM(G69,M69,S69,AA69,AI69,AR69,AZ69,BH69,BQ69,BY69,CG69,CO69)-CW69 -> 0 | DM69: =SUM(D69,J69,P69,V69,AD69,AL69,AU69,BC69,,BN69,BV69,CD69,CL69)-CT69 -> 0 | DP69: 0 | DQ69: =-CR69+DP69/10^6 -> 0 | DR69: =SUM(E69,K69,Q69,W69,AE69,AM69,AV69,BD69,BL69,BU69,CC69,CK69)-CS69 -> 0 | DS69: =SUM(D69,J69,P69,V69,AD69,AL69,AU69,BC69,,BN69,BV69,CD69,CL69)-CT69 -> 0 | DU69: 0 | DV69: =DU69-CJ69 -> 0 | DX69: =(CS69-CZ69)*10^6 -> 0 | DY69: =(CT69-DC69)*10^6 -> 0 | DZ69: =(CW69-DD69)*10^6 -> 0
B70: ENTRETIEN ET REPARATIONS BATS | C70: Opex64 | CU70: =+CR70-CS70 -> 0 | CV70: =+CR70-CT70 -> 0 | CX70: =IFERROR(CR70/CW70-1, "-") -> - | DE70: =+CZ70/DD70-1 -> #DIV/0! | DF70: =+DA70/DD70-1 -> #DIV/0! | DG70: =+DB70/DD70-1 -> #DIV/0! | DH70: =+DC70/DD70-1 -> #DIV/0! | DJ70: =SUM(D70,J70,P70,V70,AD70,AL70,AU70,BC70,BK70,BT70,CB70,CJ70)-CR70 -> 0 | DK70: =SUM(E70,K70,Q70,W70,AE70,AM70,AV70,BD70,BL70,BU70,CC70,CK70)-CS70 -> 0 | DL70: =SUM(G70,M70,S70,AA70,AI70,AR70,AZ70,BH70,BQ70,BY70,CG70,CO70)-CW70 -> 0 | DM70: =SUM(D70,J70,P70,V70,AD70,AL70,AU70,BC70,,BN70,BV70,CD70,CL70)-CT70 -> 0 | DP70: 142576762 | DQ70: =-CR70+DP70/10^6 -> 142.57676 | DR70: =SUM(E70,K70,Q70,W70,AE70,AM70,AV70,BD70,BL70,BU70,CC70,CK70)-CS70 -> 0 | DS70: =SUM(D70,J70,P70,V70,AD70,AL70,AU70,BC70,,BN70,BV70,CD70,CL70)-CT70 -> 0 | DU70: 18.685949 | DV70: =DU70-CJ70 -> 18.685949 | DX70: =(CS70-CZ70)*10^6 -> 0 | DY70: =(CT70-DC70)*10^6 -> 0 | DZ70: =(CW70-DD70)*10^6 -> 0
B71: FRAIS DE GARDIENNAGE | C71: Opex65 | CU71: =+CR71-CS71 -> 0 | CV71: =+CR71-CT71 -> 0 | CX71: =IFERROR(CR71/CW71-1, "-") -> - | DJ71: =SUM(D71,J71,P71,V71,AD71,AL71,AU71,BC71,BK71,BT71,CB71,CJ71)-CR71 -> 0 | DK71: =SUM(E71,K71,Q71,W71,AE71,AM71,AV71,BD71,BL71,BU71,CC71,CK71)-CS71 -> 0 | DL71: =SUM(G71,M71,S71,AA71,AI71,AR71,AZ71,BH71,BQ71,BY71,CG71,CO71)-CW71 -> 0 | DM71: =SUM(D71,J71,P71,V71,AD71,AL71,AU71,BC71,,BN71,BV71,CD71,CL71)-CT71 -> 0 | DP71: 0 | DQ71: =-CR71+DP71/10^6 -> 0 | DR71: =SUM(E71,K71,Q71,W71,AE71,AM71,AV71,BD71,BL71,BU71,CC71,CK71)-CS71 -> 0 | DS71: =SUM(D71,J71,P71,V71,AD71,AL71,AU71,BC71,,BN71,BV71,CD71,CL71)-CT71 -> 0 | DU71: 0 | DV71: =DU71-CJ71 -> 0 | DX71: =(CS71-CZ71)*10^6 -> 0 | DY71: =(CT71-DC71)*10^6 -> 0 | DZ71: =(CW71-DD71)*10^6 -> 0
B72: EAU BUREAUX, ADMINISTRATION, C | C72: Opex66 | CU72: =+CR72-CS72 -> 0 | CV72: =+CR72-CT72 -> 0 | CX72: =IFERROR(CR72/CW72-1, "-") -> - | DE72: =+CZ72/DD72-1 -> #DIV/0! | DF72: =+DA72/DD72-1 -> #DIV/0! | DG72: =+DB72/DD72-1 -> #DIV/0! | DH72: =+DC72/DD72-1 -> #DIV/0! | DJ72: =SUM(D72,J72,P72,V72,AD72,AL72,AU72,BC72,BK72,BT72,CB72,CJ72)-CR72 -> 0 | DK72: =SUM(E72,K72,Q72,W72,AE72,AM72,AV72,BD72,BL72,BU72,CC72,CK72)-CS72 -> 0 | DL72: =SUM(G72,M72,S72,AA72,AI72,AR72,AZ72,BH72,BQ72,BY72,CG72,CO72)-CW72 -> 0 | DM72: =SUM(D72,J72,P72,V72,AD72,AL72,AU72,BC72,,BN72,BV72,CD72,CL72)-CT72 -> 0 | DP72: 16502302 | DQ72: =-CR72+DP72/10^6 -> 16.502302 | DR72: =SUM(E72,K72,Q72,W72,AE72,AM72,AV72,BD72,BL72,BU72,CC72,CK72)-CS72 -> 0 | DS72: =SUM(D72,J72,P72,V72,AD72,AL72,AU72,BC72,,BN72,BV72,CD72,CL72)-CT72 -> 0 | DU72: 1.010951 | DV72: =DU72-CJ72 -> 1.010951 | DX72: =(CS72-CZ72)*10^6 -> 0 | DY72: =(CT72-DC72)*10^6 -> 0 | DZ72: =(CW72-DD72)*10^6 -> 0
B73: ELECTRICITE BUREAUX, ADMINISTR | C73: Opex67 | CU73: =+CR73-CS73 -> 0 | CV73: =+CR73-CT73 -> 0 | CX73: =IFERROR(CR73/CW73-1, "-") -> - | DE73: =+CZ73/DD73-1 -> #DIV/0! | DF73: =+DA73/DD73-1 -> #DIV/0! | DG73: =+DB73/DD73-1 -> #DIV/0! | DH73: =+DC73/DD73-1 -> #DIV/0! | DJ73: =SUM(D73,J73,P73,V73,AD73,AL73,AU73,BC73,BK73,BT73,CB73,CJ73)-CR73 -> 0 | DK73: =SUM(E73,K73,Q73,W73,AE73,AM73,AV73,BD73,BL73,BU73,CC73,CK73)-CS73 -> 0 | DL73: =SUM(G73,M73,S73,AA73,AI73,AR73,AZ73,BH73,BQ73,BY73,CG73,CO73)-CW73 -> 0 | DM73: =SUM(D73,J73,P73,V73,AD73,AL73,AU73,BC73,,BN73,BV73,CD73,CL73)-CT73 -> 0 | DP73: 683676551 | DQ73: =-CR73+DP73/10^6 -> 683.67655 | DR73: =SUM(E73,K73,Q73,W73,AE73,AM73,AV73,BD73,BL73,BU73,CC73,CK73)-CS73 -> 0 | DS73: =SUM(D73,J73,P73,V73,AD73,AL73,AU73,BC73,,BN73,BV73,CD73,CL73)-CT73 -> 0 | DT73: -8.781966 | DU73: 69.652354 | DV73: =DU73-CJ73 -> 69.652354 | DX73: =(CS73-CZ73)*10^6 -> 0 | DY73: =(CT73-DC73)*10^6 -> 0 | DZ73: =(CW73-DD73)*10^6 -> 0
B74: FRAIS DE TELEPHONE BUREAUX | C74: Opex68 | CU74: =+CR74-CS74 -> 0 | CV74: =+CR74-CT74 -> 0 | CX74: =IFERROR(CR74/CW74-1, "-") -> - | DE74: =+CZ74/DD74-1 -> #DIV/0! | DF74: =+DA74/DD74-1 -> #DIV/0! | DG74: =+DB74/DD74-1 -> #DIV/0! | DH74: =+DC74/DD74-1 -> #DIV/0! | DJ74: =SUM(D74,J74,P74,V74,AD74,AL74,AU74,BC74,BK74,BT74,CB74,CJ74)-CR74 -> 0 | DK74: =SUM(E74,K74,Q74,W74,AE74,AM74,AV74,BD74,BL74,BU74,CC74,CK74)-CS74 -> 0 | DL74: =SUM(G74,M74,S74,AA74,AI74,AR74,AZ74,BH74,BQ74,BY74,CG74,CO74)-CW74 -> 0 | DM74: =SUM(D74,J74,P74,V74,AD74,AL74,AU74,BC74,,BN74,BV74,CD74,CL74)-CT74 -> 0 | DP74: 125141612 | DQ74: =-CR74+DP74/10^6 -> 125.14161 | DR74: =SUM(E74,K74,Q74,W74,AE74,AM74,AV74,BD74,BL74,BU74,CC74,CK74)-CS74 -> 0 | DS74: =SUM(D74,J74,P74,V74,AD74,AL74,AU74,BC74,,BN74,BV74,CD74,CL74)-CT74 -> 0 | DU74: 3.225267 | DV74: =DU74-CJ74 -> 3.225267 | DX74: =(CS74-CZ74)*10^6 -> 0 | DY74: =(CT74-DC74)*10^6 -> 0 | DZ74: =(CW74-DD74)*10^6 -> 0
B75: FRAIS DE TELECOPIE | C75: Opex69 | CU75: =+CR75-CS75 -> 0 | CV75: =+CR75-CT75 -> 0 | CX75: =IFERROR(CR75/CW75-1, "-") -> - | DE75: =+CZ75/DD75-1 -> #DIV/0! | DF75: =+DA75/DD75-1 -> #DIV/0! | DG75: =+DB75/DD75-1 -> #DIV/0! | DH75: =+DC75/DD75-1 -> #DIV/0! | DJ75: =SUM(D75,J75,P75,V75,AD75,AL75,AU75,BC75,BK75,BT75,CB75,CJ75)-CR75 -> 0 | DK75: =SUM(E75,K75,Q75,W75,AE75,AM75,AV75,BD75,BL75,BU75,CC75,CK75)-CS75 -> 0 | DL75: =SUM(G75,M75,S75,AA75,AI75,AR75,AZ75,BH75,BQ75,BY75,CG75,CO75)-CW75 -> 0 | DM75: =SUM(D75,J75,P75,V75,AD75,AL75,AU75,BC75,,BN75,BV75,CD75,CL75)-CT75 -> 0 | DP75: 0 | DQ75: =-CR75+DP75/10^6 -> 0 | DR75: =SUM(E75,K75,Q75,W75,AE75,AM75,AV75,BD75,BL75,BU75,CC75,CK75)-CS75 -> 0 | DS75: =SUM(D75,J75,P75,V75,AD75,AL75,AU75,BC75,,BN75,BV75,CD75,CL75)-CT75 -> 0 | DU75: 0 | DV75: =DU75-CJ75 -> 0 | DX75: =(CS75-CZ75)*10^6 -> 0 | DY75: =(CT75-DC75)*10^6 -> 0 | DZ75: =(CW75-DD75)*10^6 -> 0
B76: AUTRES FRAIS DE COMMUNICATIONS | C76: Opex70 | CU76: =+CR76-CS76 -> 0 | CV76: =+CR76-CT76 -> 0 | CX76: =IFERROR(CR76/CW76-1, "-") -> - | DE76: =+CZ76/DD76-1 -> #DIV/0! | DF76: =+DA76/DD76-1 -> #DIV/0! | DG76: =+DB76/DD76-1 -> #DIV/0! | DH76: =+DC76/DD76-1 -> #DIV/0! | DJ76: =SUM(D76,J76,P76,V76,AD76,AL76,AU76,BC76,BK76,BT76,CB76,CJ76)-CR76 -> 0 | DK76: =SUM(E76,K76,Q76,W76,AE76,AM76,AV76,BD76,BL76,BU76,CC76,CK76)-CS76 -> 0 | DL76: =SUM(G76,M76,S76,AA76,AI76,AR76,AZ76,BH76,BQ76,BY76,CG76,CO76)-CW76 -> 0 | DM76: =SUM(D76,J76,P76,V76,AD76,AL76,AU76,BC76,,BN76,BV76,CD76,CL76)-CT76 -> 0 | DP76: 917000 | DQ76: =-CR76+DP76/10^6 -> 0.917 | DR76: =SUM(E76,K76,Q76,W76,AE76,AM76,AV76,BD76,BL76,BU76,CC76,CK76)-CS76 -> 0 | DS76: =SUM(D76,J76,P76,V76,AD76,AL76,AU76,BC76,,BN76,BV76,CD76,CL76)-CT76 -> 0 | DU76: 0 | DV76: =DU76-CJ76 -> 0 | DX76: =(CS76-CZ76)*10^6 -> 0 | DY76: =(CT76-DC76)*10^6 -> 0 | DZ76: =(CW76-DD76)*10^6 -> 0
B77: FRAIS CONNEXION INTERNET | C77: Opex71 | CU77: =+CR77-CS77 -> 0 | CV77: =+CR77-CT77 -> 0 | CX77: =IFERROR(CR77/CW77-1, "-") -> - | DE77: =+CZ77/DD77-1 -> #DIV/0! | DF77: =+DA77/DD77-1 -> #DIV/0! | DG77: =+DB77/DD77-1 -> #DIV/0! | DH77: =+DC77/DD77-1 -> #DIV/0! | DJ77: =SUM(D77,J77,P77,V77,AD77,AL77,AU77,BC77,BK77,BT77,CB77,CJ77)-CR77 -> 0 | DK77: =SUM(E77,K77,Q77,W77,AE77,AM77,AV77,BD77,BL77,BU77,CC77,CK77)-CS77 -> 0 | DL77: =SUM(G77,M77,S77,AA77,AI77,AR77,AZ77,BH77,BQ77,BY77,CG77,CO77)-CW77 -> 0 | DM77: =SUM(D77,J77,P77,V77,AD77,AL77,AU77,BC77,,BN77,BV77,CD77,CL77)-CT77 -> 0 | DP77: 0 | DQ77: =-CR77+DP77/10^6 -> 0 | DR77: =SUM(E77,K77,Q77,W77,AE77,AM77,AV77,BD77,BL77,BU77,CC77,CK77)-CS77 -> 0 | DS77: =SUM(D77,J77,P77,V77,AD77,AL77,AU77,BC77,,BN77,BV77,CD77,CL77)-CT77 -> 0 | DU77: 0 | DV77: =DU77-CJ77 -> 0 | DX77: =(CS77-CZ77)*10^6 -> 0 | DY77: =(CT77-DC77)*10^6 -> 0 | DZ77: =(CW77-DD77)*10^6 -> 0
B78: Contrainte :SBEE | C78: Opex72 | CU78: =+CR78-CS78 -> 0 | CV78: =+CR78-CT78 -> 0 | CX78: =IFERROR(CR78/CW78-1, "-") -> - | DE78: =+CZ78/DD78-1 -> #DIV/0! | DF78: =+DA78/DD78-1 -> #DIV/0! | DG78: =+DB78/DD78-1 -> #DIV/0! | DH78: =+DC78/DD78-1 -> #DIV/0! | DJ78: =SUM(D78,J78,P78,V78,AD78,AL78,AU78,BC78,BK78,BT78,CB78,CJ78)-CR78 -> 0 | DK78: =SUM(E78,K78,Q78,W78,AE78,AM78,AV78,BD78,BL78,BU78,CC78,CK78)-CS78 -> 0 | DL78: =SUM(G78,M78,S78,AA78,AI78,AR78,AZ78,BH78,BQ78,BY78,CG78,CO78)-CW78 -> 0 | DM78: =SUM(D78,J78,P78,V78,AD78,AL78,AU78,BC78,,BN78,BV78,CD78,CL78)-CT78 -> 0 | DQ78: =-CR78+DP78/10^6 -> 0 | DR78: =SUM(E78,K78,Q78,W78,AE78,AM78,AV78,BD78,BL78,BU78,CC78,CK78)-CS78 -> 0 | DS78: =SUM(D78,J78,P78,V78,AD78,AL78,AU78,BC78,,BN78,BV78,CD78,CL78)-CT78 -> 0 | DV78: =DU78-CJ78 -> 0 | DX78: =(CS78-CZ78)*10^6 -> 0 | DY78: =(CT78-DC78)*10^6 -> 0 | DZ78: =(CW78-DD78)*10^6 -> 0
B79: Lignes et réseaux (entretien & achats) | C79: Opex73 | CU79: =+CR79-CS79 -> 0 | CV79: =+CR79-CT79 -> 0 | CX79: =IFERROR(CR79/CW79-1, "-") -> - | DE79: =+CZ79/DD79-1 -> #DIV/0! | DF79: =+DA79/DD79-1 -> #DIV/0! | DG79: =+DB79/DD79-1 -> #DIV/0! | DH79: =+DC79/DD79-1 -> #DIV/0! | DJ79: =SUM(D79,J79,P79,V79,AD79,AL79,AU79,BC79,BK79,BT79,CB79,CJ79)-CR79 -> 0 | DK79: =SUM(E79,K79,Q79,W79,AE79,AM79,AV79,BD79,BL79,BU79,CC79,CK79)-CS79 -> 0 | DL79: =SUM(G79,M79,S79,AA79,AI79,AR79,AZ79,BH79,BQ79,BY79,CG79,CO79)-CW79 -> 0 | DM79: =SUM(D79,J79,P79,V79,AD79,AL79,AU79,BC79,,BN79,BV79,CD79,CL79)-CT79 -> 0 | DP79: =SUM(DP80:DP96) -> 5970873193 | DQ79: =-CR79+DP79/10^6 -> 5970.8732 | DR79: =SUM(E79,K79,Q79,W79,AE79,AM79,AV79,BD79,BL79,BU79,CC79,CK79)-CS79 -> 0 | DS79: =SUM(D79,J79,P79,V79,AD79,AL79,AU79,BC79,,BN79,BV79,CD79,CL79)-CT79 -> 0 | DU79: 535.11528 | DV79: =DU79-CJ79 -> 535.11528 | DX79: =(CS79-CZ79)*10^6 -> 0 | DY79: =(CT79-DC79)*10^6 -> 0 | DZ79: =(CW79-DD79)*10^6 -> 0
B80: ACHATS PETIT MATERIEL ET OUTIL | C80: Opex74 | CU80: =+CR80-CS80 -> 0 | CV80: =+CR80-CT80 -> 0 | CX80: =IFERROR(CR80/CW80-1, "-") -> - | DG80: =+DB80/DD80-1 -> #DIV/0! | DH80: =+DC80/DD80-1 -> #DIV/0! | DJ80: =SUM(D80,J80,P80,V80,AD80,AL80,AU80,BC80,BK80,BT80,CB80,CJ80)-CR80 -> 0 | DK80: =SUM(E80,K80,Q80,W80,AE80,AM80,AV80,BD80,BL80,BU80,CC80,CK80)-CS80 -> 0 | DL80: =SUM(G80,M80,S80,AA80,AI80,AR80,AZ80,BH80,BQ80,BY80,CG80,CO80)-CW80 -> 0 | DM80: =SUM(D80,J80,P80,V80,AD80,AL80,AU80,BC80,,BN80,BV80,CD80,CL80)-CT80 -> 0 | DP80: 0 | DQ80: =-CR80+DP80/10^6 -> 0 | DR80: =SUM(E80,K80,Q80,W80,AE80,AM80,AV80,BD80,BL80,BU80,CC80,CK80)-CS80 -> 0 | DS80: =SUM(D80,J80,P80,V80,AD80,AL80,AU80,BC80,,BN80,BV80,CD80,CL80)-CT80 -> 0 | DU80: 0 | DV80: =DU80-CJ80 -> 0 | DX80: =(CS80-CZ80)*10^6 -> 0 | DY80: =(CT80-DC80)*10^6 -> 0 | DZ80: =(CW80-DD80)*10^6 -> 0
B81: ENTRETIEN ET REPARATIONS BATS | C81: Opex75 | CU81: =+CR81-CS81 -> 0 | CV81: =+CR81-CT81 -> 0 | CX81: =IFERROR(CR81/CW81-1, "-") -> - | DG81: =+DB81/DD81-1 -> #DIV/0! | DH81: =+DC81/DD81-1 -> #DIV/0! | DJ81: =SUM(D81,J81,P81,V81,AD81,AL81,AU81,BC81,BK81,BT81,CB81,CJ81)-CR81 -> 0 | DK81: =SUM(E81,K81,Q81,W81,AE81,AM81,AV81,BD81,BL81,BU81,CC81,CK81)-CS81 -> 0 | DL81: =SUM(G81,M81,S81,AA81,AI81,AR81,AZ81,BH81,BQ81,BY81,CG81,CO81)-CW81 -> 0 | DM81: =SUM(D81,J81,P81,V81,AD81,AL81,AU81,BC81,,BN81,BV81,CD81,CL81)-CT81 -> 0 | DQ81: =-CR81+DP81/10^6 -> 0 | DR81: =SUM(E81,K81,Q81,W81,AE81,AM81,AV81,BD81,BL81,BU81,CC81,CK81)-CS81 -> 0 | DS81: =SUM(D81,J81,P81,V81,AD81,AL81,AU81,BC81,,BN81,BV81,CD81,CL81)-CT81 -> 0 | DV81: =DU81-CJ81 -> 0 | DX81: =(CS81-CZ81)*10^6 -> 0 | DY81: =(CT81-DC81)*10^6 -> 0 | DZ81: =(CW81-DD81)*10^6 -> 0
B82: ENTRETIEN ET REPARATIONS SITES | C82: Opex76 | CU82: =+CR82-CS82 -> 0 | CV82: =+CR82-CT82 -> 0 | CX82: =IFERROR(CR82/CW82-1, "-") -> - | DE82: =+CZ82/DD82-1 -> #DIV/0! | DF82: =+DA82/DD82-1 -> #DIV/0! | DG82: =+DB82/DD82-1 -> #DIV/0! | DH82: =+DC82/DD82-1 -> #DIV/0! | DJ82: =SUM(D82,J82,P82,V82,AD82,AL82,AU82,BC82,BK82,BT82,CB82,CJ82)-CR82 -> 0 | DK82: =SUM(E82,K82,Q82,W82,AE82,AM82,AV82,BD82,BL82,BU82,CC82,CK82)-CS82 -> 0 | DL82: =SUM(G82,M82,S82,AA82,AI82,AR82,AZ82,BH82,BQ82,BY82,CG82,CO82)-CW82 -> 0 | DM82: =SUM(D82,J82,P82,V82,AD82,AL82,AU82,BC82,,BN82,BV82,CD82,CL82)-CT82 -> 0 | DP82: 1375989178 | DQ82: =-CR82+DP82/10^6 -> 1375.9892 | DR82: =SUM(E82,K82,Q82,W82,AE82,AM82,AV82,BD82,BL82,BU82,CC82,CK82)-CS82 -> 0 | DS82: =SUM(D82,J82,P82,V82,AD82,AL82,AU82,BC82,,BN82,BV82,CD82,CL82)-CT82 -> 0 | DU82: 188.74287 | DV82: =DU82-CJ82 -> 188.74287 | DX82: =(CS82-CZ82)*10^6 -> 0 | DY82: =(CT82-DC82)*10^6 -> 0 | DZ82: =(CW82-DD82)*10^6 -> 0
B83: VARIATION DE STOCKS AUTRES APPRO DT | C83: Opex77 | CU83: =+CR83-CS83 -> 0 | CV83: =+CR83-CT83 -> 0 | CX83: =IFERROR(CR83/CW83-1, "-") -> - | DE83: =+CZ83/DD83-1 -> #DIV/0! | DF83: =+DA83/DD83-1 -> #DIV/0! | DG83: =+DB83/DD83-1 -> #DIV/0! | DH83: =+DC83/DD83-1 -> #DIV/0! | DJ83: =SUM(D83,J83,P83,V83,AD83,AL83,AU83,BC83,BK83,BT83,CB83,CJ83)-CR83 -> 0 | DK83: =SUM(E83,K83,Q83,W83,AE83,AM83,AV83,BD83,BL83,BU83,CC83,CK83)-CS83 -> 0 | DL83: =SUM(G83,M83,S83,AA83,AI83,AR83,AZ83,BH83,BQ83,BY83,CG83,CO83)-CW83 -> 0 | DM83: =SUM(D83,J83,P83,V83,AD83,AL83,AU83,BC83,,BN83,BV83,CD83,CL83)-CT83 -> 0 | DP83: 24074962 | DQ83: =-CR83+DP83/10^6 -> 24.074962 | DR83: =SUM(E83,K83,Q83,W83,AE83,AM83,AV83,BD83,BL83,BU83,CC83,CK83)-CS83 -> 0 | DS83: =SUM(D83,J83,P83,V83,AD83,AL83,AU83,BC83,,BN83,BV83,CD83,CL83)-CT83 -> 0 | DU83: -63.494016 | DV83: =DU83-CJ83 -> -63.494016 | DX83: =(CS83-CZ83)*10^6 -> 0 | DY83: =(CT83-DC83)*10^6 -> 0 | DZ83: =(CW83-DD83)*10^6 -> 0
B84: ENTRETIEN ET REPARATIONS EQUIP | C84: Opex78 | CU84: =+CR84-CS84 -> 0 | CV84: =+CR84-CT84 -> 0 | CX84: =IFERROR(CR84/CW84-1, "-") -> - | DE84: =+CZ84/DD84-1 -> #DIV/0! | DF84: =+DA84/DD84-1 -> #DIV/0! | DG84: =+DB84/DD84-1 -> #DIV/0! | DH84: =+DC84/DD84-1 -> #DIV/0! | DJ84: =SUM(D84,J84,P84,V84,AD84,AL84,AU84,BC84,BK84,BT84,CB84,CJ84)-CR84 -> 0 | DK84: =SUM(E84,K84,Q84,W84,AE84,AM84,AV84,BD84,BL84,BU84,CC84,CK84)-CS84 -> 0 | DL84: =SUM(G84,M84,S84,AA84,AI84,AR84,AZ84,BH84,BQ84,BY84,CG84,CO84)-CW84 -> 0 | DM84: =SUM(D84,J84,P84,V84,AD84,AL84,AU84,BC84,,BN84,BV84,CD84,CL84)-CT84 -> 0 | DP84: 190417513 | DQ84: =-CR84+DP84/10^6 -> 190.41751 | DR84: =SUM(E84,K84,Q84,W84,AE84,AM84,AV84,BD84,BL84,BU84,CC84,CK84)-CS84 -> 0 | DS84: =SUM(D84,J84,P84,V84,AD84,AL84,AU84,BC84,,BN84,BV84,CD84,CL84)-CT84 -> 0 | DU84: -0.798076 | DV84: =DU84-CJ84 -> -0.798076 | DX84: =(CS84-CZ84)*10^6 -> 0 | DY84: =(CT84-DC84)*10^6 -> 0 | DZ84: =(CW84-DD84)*10^6 -> 0
B85: MAINTENANCE EQUIPEMENTS TECHNI | C85: Opex79 | CU85: =+CR85-CS85 -> 0 | CV85: =+CR85-CT85 -> 0 | CX85: =IFERROR(CR85/CW85-1, "-") -> - | DE85: =+CZ85/DD85-1 -> #DIV/0! | DF85: =+DA85/DD85-1 -> #DIV/0! | DG85: =+DB85/DD85-1 -> #DIV/0! | DH85: =+DC85/DD85-1 -> #DIV/0! | DJ85: =SUM(D85,J85,P85,V85,AD85,AL85,AU85,BC85,BK85,BT85,CB85,CJ85)-CR85 -> 0 | DK85: =SUM(E85,K85,Q85,W85,AE85,AM85,AV85,BD85,BL85,BU85,CC85,CK85)-CS85 -> 0 | DL85: =SUM(G85,M85,S85,AA85,AI85,AR85,AZ85,BH85,BQ85,BY85,CG85,CO85)-CW85 -> 0 | DM85: =SUM(D85,J85,P85,V85,AD85,AL85,AU85,BC85,,BN85,BV85,CD85,CL85)-CT85 -> 0 | DP85: 1056881347 | DQ85: =-CR85+DP85/10^6 -> 1056.8813 | DR85: =SUM(E85,K85,Q85,W85,AE85,AM85,AV85,BD85,BL85,BU85,CC85,CK85)-CS85 -> 0 | DS85: =SUM(D85,J85,P85,V85,AD85,AL85,AU85,BC85,,BN85,BV85,CD85,CL85)-CT85 -> 0 | DU85: 128.64007 | DV85: =DU85-CJ85 -> 128.64007 | DX85: =(CS85-CZ85)*10^6 -> 0 | DY85: =(CT85-DC85)*10^6 -> 0 | DZ85: =(CW85-DD85)*10^6 -> 0
B86: LOYERS D'ESPACES EN CO-LOCATIO | C86: Opex80 | CU86: =+CR86-CS86 -> 0 | CV86: =+CR86-CT86 -> 0 | CX86: =IFERROR(CR86/CW86-1, "-") -> - | DE86: =+CZ86/DD86-1 -> #DIV/0! | DF86: =+DA86/DD86-1 -> #DIV/0! | DG86: =+DB86/DD86-1 -> #DIV/0! | DH86: =+DC86/DD86-1 -> #DIV/0! | DJ86: =SUM(D86,J86,P86,V86,AD86,AL86,AU86,BC86,BK86,BT86,CB86,CJ86)-CR86 -> 0 | DK86: =SUM(E86,K86,Q86,W86,AE86,AM86,AV86,BD86,BL86,BU86,CC86,CK86)-CS86 -> 0 | DL86: =SUM(G86,M86,S86,AA86,AI86,AR86,AZ86,BH86,BQ86,BY86,CG86,CO86)-CW86 -> 0 | DM86: =SUM(D86,J86,P86,V86,AD86,AL86,AU86,BC86,,BN86,BV86,CD86,CL86)-CT86 -> 0 | DP86: 300348843 | DQ86: =-CR86+DP86/10^6 -> 300.34884 | DR86: =SUM(E86,K86,Q86,W86,AE86,AM86,AV86,BD86,BL86,BU86,CC86,CK86)-CS86 -> 0 | DS86: =SUM(D86,J86,P86,V86,AD86,AL86,AU86,BC86,,BN86,BV86,CD86,CL86)-CT86 -> 0 | DU86: 8.100141 | DV86: =DU86-CJ86 -> 8.100141 | DX86: =(CS86-CZ86)*10^6 -> 0 | DY86: =(CT86-DC86)*10^6 -> 0 | DZ86: =(CW86-DD86)*10^6 -> 0
B87: LOYERS LIAISONS SIGNALISATIONS | C87: Opex81 | CU87: =+CR87-CS87 -> 0 | CV87: =+CR87-CT87 -> 0 | CX87: =IFERROR(CR87/CW87-1, "-") -> - | DE87: =+CZ87/DD87-1 -> #DIV/0! | DF87: =+DA87/DD87-1 -> #DIV/0! | DG87: =+DB87/DD87-1 -> #DIV/0! | DH87: =+DC87/DD87-1 -> #DIV/0! | DJ87: =SUM(D87,J87,P87,V87,AD87,AL87,AU87,BC87,BK87,BT87,CB87,CJ87)-CR87 -> 0 | DK87: =SUM(E87,K87,Q87,W87,AE87,AM87,AV87,BD87,BL87,BU87,CC87,CK87)-CS87 -> 0 | DL87: =SUM(G87,M87,S87,AA87,AI87,AR87,AZ87,BH87,BQ87,BY87,CG87,CO87)-CW87 -> 0 | DM87: =SUM(D87,J87,P87,V87,AD87,AL87,AU87,BC87,,BN87,BV87,CD87,CL87)-CT87 -> 0 | DP87: 14595529 | DQ87: =-CR87+DP87/10^6 -> 14.595529 | DR87: =SUM(E87,K87,Q87,W87,AE87,AM87,AV87,BD87,BL87,BU87,CC87,CK87)-CS87 -> 0 | DS87: =SUM(D87,J87,P87,V87,AD87,AL87,AU87,BC87,,BN87,BV87,CD87,CL87)-CT87 -> 0 | DU87: 1.311914 | DV87: =DU87-CJ87 -> 1.311914 | DX87: =(CS87-CZ87)*10^6 -> 0 | DY87: =(CT87-DC87)*10^6 -> 0 | DZ87: =(CW87-DD87)*10^6 -> 0
B88: LOYERS LIAISONS SEGMENT SPACIA | C88: Opex82 | CU88: =+CR88-CS88 -> 0 | CV88: =+CR88-CT88 -> 0 | CX88: =IFERROR(CR88/CW88-1, "-") -> - | DJ88: =SUM(D88,J88,P88,V88,AD88,AL88,AU88,BC88,BK88,BT88,CB88,CJ88)-CR88 -> 0 | DK88: =SUM(E88,K88,Q88,W88,AE88,AM88,AV88,BD88,BL88,BU88,CC88,CK88)-CS88 -> 0 | DL88: =SUM(G88,M88,S88,AA88,AI88,AR88,AZ88,BH88,BQ88,BY88,CG88,CO88)-CW88 -> 0 | DM88: =SUM(D88,J88,P88,V88,AD88,AL88,AU88,BC88,,BN88,BV88,CD88,CL88)-CT88 -> 0 | DP88: 0 | DQ88: =-CR88+DP88/10^6 -> 0 | DR88: =SUM(E88,K88,Q88,W88,AE88,AM88,AV88,BD88,BL88,BU88,CC88,CK88)-CS88 -> 0 | DS88: =SUM(D88,J88,P88,V88,AD88,AL88,AU88,BC88,,BN88,BV88,CD88,CL88)-CT88 -> 0 | DU88: 0 | DV88: =DU88-CJ88 -> 0 | DX88: =(CS88-CZ88)*10^6 -> 0 | DY88: =(CT88-DC88)*10^6 -> 0 | DZ88: =(CW88-DD88)*10^6 -> 0
B89: LOYERS LIAISONS MIC | C89: Opex83 | CU89: =+CR89-CS89 -> 0 | CV89: =+CR89-CT89 -> 0 | CX89: =IFERROR(CR89/CW89-1, "-") -> - | DJ89: =SUM(D89,J89,P89,V89,AD89,AL89,AU89,BC89,BK89,BT89,CB89,CJ89)-CR89 -> 0 | DK89: =SUM(E89,K89,Q89,W89,AE89,AM89,AV89,BD89,BL89,BU89,CC89,CK89)-CS89 -> 0 | DL89: =SUM(G89,M89,S89,AA89,AI89,AR89,AZ89,BH89,BQ89,BY89,CG89,CO89)-CW89 -> 0 | DM89: =SUM(D89,J89,P89,V89,AD89,AL89,AU89,BC89,,BN89,BV89,CD89,CL89)-CT89 -> 0 | DP89: 0 | DQ89: =-CR89+DP89/10^6 -> 0 | DR89: =SUM(E89,K89,Q89,W89,AE89,AM89,AV89,BD89,BL89,BU89,CC89,CK89)-CS89 -> 0 | DS89: =SUM(D89,J89,P89,V89,AD89,AL89,AU89,BC89,,BN89,BV89,CD89,CL89)-CT89 -> 0 | DU89: 0 | DV89: =DU89-CJ89 -> 0 | DX89: =(CS89-CZ89)*10^6 -> 0 | DY89: =(CT89-DC89)*10^6 -> 0 | DZ89: =(CW89-DD89)*10^6 -> 0
B90: LOYERS LIAISONS FIBRES OPTIQUE | C90: Opex84 | CU90: =+CR90-CS90 -> 0 | CV90: =+CR90-CT90 -> 0 | CX90: =IFERROR(CR90/CW90-1, "-") -> - | DE90: =+CZ90/DD90-1 -> #DIV/0! | DF90: =+DA90/DD90-1 -> #DIV/0! | DG90: =+DB90/DD90-1 -> #DIV/0! | DH90: =+DC90/DD90-1 -> #DIV/0! | DJ90: =SUM(D90,J90,P90,V90,AD90,AL90,AU90,BC90,BK90,BT90,CB90,CJ90)-CR90 -> 0 | DK90: =SUM(E90,K90,Q90,W90,AE90,AM90,AV90,BD90,BL90,BU90,CC90,CK90)-CS90 -> 0 | DL90: =SUM(G90,M90,S90,AA90,AI90,AR90,AZ90,BH90,BQ90,BY90,CG90,CO90)-CW90 -> 0 | DM90: =SUM(D90,J90,P90,V90,AD90,AL90,AU90,BC90,,BN90,BV90,CD90,CL90)-CT90 -> 0 | DP90: 2486243611 | DQ90: =-CR90+DP90/10^6 -> 2486.2436 | DR90: =SUM(E90,K90,Q90,W90,AE90,AM90,AV90,BD90,BL90,BU90,CC90,CK90)-CS90 -> 0 | DS90: =SUM(D90,J90,P90,V90,AD90,AL90,AU90,BC90,,BN90,BV90,CD90,CL90)-CT90 -> 0 | DU90: 224.26593 | DV90: =DU90-CJ90 -> 224.26593 | DX90: =(CS90-CZ90)*10^6 -> 0 | DY90: =(CT90-DC90)*10^6 -> 0 | DZ90: =(CW90-DD90)*10^6 -> 0
B91: LOYERS AUTRES LIAISONS | C91: Opex85 | CU91: =+CR91-CS91 -> 0 | CV91: =+CR91-CT91 -> 0 | CX91: =IFERROR(CR91/CW91-1, "-") -> - | DE91: =+CZ91/DD91-1 -> #DIV/0! | DF91: =+DA91/DD91-1 -> #DIV/0! | DG91: =+DB91/DD91-1 -> #DIV/0! | DH91: =+DC91/DD91-1 -> #DIV/0! | DJ91: =SUM(D91,J91,P91,V91,AD91,AL91,AU91,BC91,BK91,BT91,CB91,CJ91)-CR91 -> 0 | DK91: =SUM(E91,K91,Q91,W91,AE91,AM91,AV91,BD91,BL91,BU91,CC91,CK91)-CS91 -> 0 | DL91: =SUM(G91,M91,S91,AA91,AI91,AR91,AZ91,BH91,BQ91,BY91,CG91,CO91)-CW91 -> 0 | DM91: =SUM(D91,J91,P91,V91,AD91,AL91,AU91,BC91,,BN91,BV91,CD91,CL91)-CT91 -> 0 | DP91: 519830522 | DQ91: =-CR91+DP91/10^6 -> 519.83052 | DR91: =SUM(E91,K91,Q91,W91,AE91,AM91,AV91,BD91,BL91,BU91,CC91,CK91)-CS91 -> 0 | DS91: =SUM(D91,J91,P91,V91,AD91,AL91,AU91,BC91,,BN91,BV91,CD91,CL91)-CT91 -> 0 | DU91: 47.063002 | DV91: =DU91-CJ91 -> 47.063002 | DX91: =(CS91-CZ91)*10^6 -> 0 | DY91: =(CT91-DC91)*10^6 -> 0 | DZ91: =(CW91-DD91)*10^6 -> 0
B92: LOCATION D'INFRASTRUCTURES TEL | C92: Opex86 | CU92: =+CR92-CS92 -> 0 | CV92: =+CR92-CT92 -> 0 | CX92: =IFERROR(CR92/CW92-1, "-") -> - | DJ92: =SUM(D92,J92,P92,V92,AD92,AL92,AU92,BC92,BK92,BT92,CB92,CJ92)-CR92 -> 0 | DK92: =SUM(E92,K92,Q92,W92,AE92,AM92,AV92,BD92,BL92,BU92,CC92,CK92)-CS92 -> 0 | DL92: =SUM(G92,M92,S92,AA92,AI92,AR92,AZ92,BH92,BQ92,BY92,CG92,CO92)-CW92 -> 0 | DM92: =SUM(D92,J92,P92,V92,AD92,AL92,AU92,BC92,,BN92,BV92,CD92,CL92)-CT92 -> 0 | DP92: 0 | DQ92: =-CR92+DP92/10^6 -> 0 | DR92: =SUM(E92,K92,Q92,W92,AE92,AM92,AV92,BD92,BL92,BU92,CC92,CK92)-CS92 -> 0 | DS92: =SUM(D92,J92,P92,V92,AD92,AL92,AU92,BC92,,BN92,BV92,CD92,CL92)-CT92 -> 0 | DU92: 0 | DV92: =DU92-CJ92 -> 0 | DX92: =(CS92-CZ92)*10^6 -> 0 | DY92: =(CT92-DC92)*10^6 -> 0 | DZ92: =(CW92-DD92)*10^6 -> 0
B93: LOCATION D'EQUIPEMENTS TELECO | C93: Opex87 | CU93: =+CR93-CS93 -> 0 | CV93: =+CR93-CT93 -> 0 | CX93: =IFERROR(CR93/CW93-1, "-") -> - | DJ93: =SUM(D93,J93,P93,V93,AD93,AL93,AU93,BC93,BK93,BT93,CB93,CJ93)-CR93 -> 0 | DK93: =SUM(E93,K93,Q93,W93,AE93,AM93,AV93,BD93,BL93,BU93,CC93,CK93)-CS93 -> 0 | DL93: =SUM(G93,M93,S93,AA93,AI93,AR93,AZ93,BH93,BQ93,BY93,CG93,CO93)-CW93 -> 0 | DM93: =SUM(D93,J93,P93,V93,AD93,AL93,AU93,BC93,,BN93,BV93,CD93,CL93)-CT93 -> 0 | DP93: 0 | DQ93: =-CR93+DP93/10^6 -> 0 | DR93: =SUM(E93,K93,Q93,W93,AE93,AM93,AV93,BD93,BL93,BU93,CC93,CK93)-CS93 -> 0 | DS93: =SUM(D93,J93,P93,V93,AD93,AL93,AU93,BC93,,BN93,BV93,CD93,CL93)-CT93 -> 0 | DU93: 0 | DV93: =DU93-CJ93 -> 0 | DX93: =(CS93-CZ93)*10^6 -> 0 | DY93: =(CT93-DC93)*10^6 -> 0 | DZ93: =(CW93-DD93)*10^6 -> 0
B94: AUTRES LOCATIONS ET CHARGES LO | C94: Opex88 | CU94: =+CR94-CS94 -> 0 | CV94: =+CR94-CT94 -> 0 | CX94: =IFERROR(CR94/CW94-1, "-") -> - | DG94: =+DB94/DD94-1 -> #DIV/0! | DH94: =+DC94/DD94-1 -> #DIV/0! | DJ94: =SUM(D94,J94,P94,V94,AD94,AL94,AU94,BC94,BK94,BT94,CB94,CJ94)-CR94 -> 0 | DK94: =SUM(E94,K94,Q94,W94,AE94,AM94,AV94,BD94,BL94,BU94,CC94,CK94)-CS94 -> 0 | DL94: =SUM(G94,M94,S94,AA94,AI94,AR94,AZ94,BH94,BQ94,BY94,CG94,CO94)-CW94 -> 0 | DM94: =SUM(D94,J94,P94,V94,AD94,AL94,AU94,BC94,,BN94,BV94,CD94,CL94)-CT94 -> 0 | DP94: 2491688 | DQ94: =-CR94+DP94/10^6 -> 2.491688 | DR94: =SUM(E94,K94,Q94,W94,AE94,AM94,AV94,BD94,BL94,BU94,CC94,CK94)-CS94 -> 0 | DS94: =SUM(D94,J94,P94,V94,AD94,AL94,AU94,BC94,,BN94,BV94,CD94,CL94)-CT94 -> 0 | DU94: 1.28345 | DV94: =DU94-CJ94 -> 1.28345 | DX94: =(CS94-CZ94)*10^6 -> 0 | DY94: =(CT94-DC94)*10^6 -> 0 | DZ94: =(CW94-DD94)*10^6 -> 0
B95: REMUNERATIONS TRANSITAIRES | C95: Opex89 | CU95: =+CR95-CS95 -> 0 | CV95: =+CR95-CT95 -> 0 | CX95: =IFERROR(CR95/CW95-1, "-") -> - | DJ95: =SUM(D95,J95,P95,V95,AD95,AL95,AU95,BC95,BK95,BT95,CB95,CJ95)-CR95 -> 0 | DK95: =SUM(E95,K95,Q95,W95,AE95,AM95,AV95,BD95,BL95,BU95,CC95,CK95)-CS95 -> 0 | DL95: =SUM(G95,M95,S95,AA95,AI95,AR95,AZ95,BH95,BQ95,BY95,CG95,CO95)-CW95 -> 0 | DM95: =SUM(D95,J95,P95,V95,AD95,AL95,AU95,BC95,,BN95,BV95,CD95,CL95)-CT95 -> 0 | DP95: 0 | DQ95: =-CR95+DP95/10^6 -> 0 | DR95: =SUM(E95,K95,Q95,W95,AE95,AM95,AV95,BD95,BL95,BU95,CC95,CK95)-CS95 -> 0 | DS95: =SUM(D95,J95,P95,V95,AD95,AL95,AU95,BC95,,BN95,BV95,CD95,CL95)-CT95 -> 0 | DU95: 0 | DV95: =DU95-CJ95 -> 0 | DX95: =(CS95-CZ95)*10^6 -> 0 | DY95: =(CT95-DC95)*10^6 -> 0 | DZ95: =(CW95-DD95)*10^6 -> 0
B96: FRAIS DE DEBOURS ENLEVEMENT | C96: Opex90 | CU96: =+CR96-CS96 -> 0 | CV96: =+CR96-CT96 -> 0 | CX96: =IFERROR(CR96/CW96-1, "-") -> - | DJ96: =SUM(D96,J96,P96,V96,AD96,AL96,AU96,BC96,BK96,BT96,CB96,CJ96)-CR96 -> 0 | DK96: =SUM(E96,K96,Q96,W96,AE96,AM96,AV96,BD96,BL96,BU96,CC96,CK96)-CS96 -> 0 | DL96: =SUM(G96,M96,S96,AA96,AI96,AR96,AZ96,BH96,BQ96,BY96,CG96,CO96)-CW96 -> 0 | DM96: =SUM(D96,J96,P96,V96,AD96,AL96,AU96,BC96,,BN96,BV96,CD96,CL96)-CT96 -> 0 | DP96: 0 | DQ96: =-CR96+DP96/10^6 -> 0 | DR96: =SUM(E96,K96,Q96,W96,AE96,AM96,AV96,BD96,BL96,BU96,CC96,CK96)-CS96 -> 0 | DS96: =SUM(D96,J96,P96,V96,AD96,AL96,AU96,BC96,,BN96,BV96,CD96,CL96)-CT96 -> 0 | DU96: 0 | DV96: =DU96-CJ96 -> 0 | DX96: =(CS96-CZ96)*10^6 -> 0 | DY96: =(CT96-DC96)*10^6 -> 0 | DZ96: =(CW96-DD96)*10^6 -> 0
B97: Fees du contrat GMNS | C97: Opex91 | CU97: =+CR97-CS97 -> 0 | CV97: =+CR97-CT97 -> 0 | CX97: =IFERROR(CR97/CW97-1, "-") -> - | DE97: =+CZ97/DD97-1 -> #DIV/0! | DF97: =+DA97/DD97-1 -> #DIV/0! | DG97: =+DB97/DD97-1 -> #DIV/0! | DH97: =+DC97/DD97-1 -> #DIV/0! | DJ97: =SUM(D97,J97,P97,V97,AD97,AL97,AU97,BC97,BK97,BT97,CB97,CJ97)-CR97 -> 0 | DK97: =SUM(E97,K97,Q97,W97,AE97,AM97,AV97,BD97,BL97,BU97,CC97,CK97)-CS97 -> 0 | DL97: =SUM(G97,M97,S97,AA97,AI97,AR97,AZ97,BH97,BQ97,BY97,CG97,CO97)-CW97 -> 0 | DM97: =SUM(D97,J97,P97,V97,AD97,AL97,AU97,BC97,,BN97,BV97,CD97,CL97)-CT97 -> 0 | DP97: =+DP98 -> 2092411608 | DQ97: =-CR97+DP97/10^6 -> 2092.4116 | DR97: =SUM(E97,K97,Q97,W97,AE97,AM97,AV97,BD97,BL97,BU97,CC97,CK97)-CS97 -> 0 | DS97: =SUM(D97,J97,P97,V97,AD97,AL97,AU97,BC97,,BN97,BV97,CD97,CL97)-CT97 -> 0 | DU97: 157.63914 | DV97: =DU97-CJ97 -> 157.63914 | DX97: =(CS97-CZ97)*10^6 -> 0 | DY97: =(CT97-DC97)*10^6 -> 0 | DZ97: =(CW97-DD97)*10^6 -> 0
B98: HONORAIRES CONSULTANTS (ERICSSON-GNMS) | C98: Opex92 | CU98: =+CR98-CS98 -> 0 | CV98: =+CR98-CT98 -> 0 | CX98: =IFERROR(CR98/CW98-1, "-") -> - | DE98: =+CZ98/DD98-1 -> #DIV/0! | DF98: =+DA98/DD98-1 -> #DIV/0! | DG98: =+DB98/DD98-1 -> #DIV/0! | DH98: =+DC98/DD98-1 -> #DIV/0! | DJ98: =SUM(D98,J98,P98,V98,AD98,AL98,AU98,BC98,BK98,BT98,CB98,CJ98)-CR98 -> 0 | DK98: =SUM(E98,K98,Q98,W98,AE98,AM98,AV98,BD98,BL98,BU98,CC98,CK98)-CS98 -> 0 | DL98: =SUM(G98,M98,S98,AA98,AI98,AR98,AZ98,BH98,BQ98,BY98,CG98,CO98)-CW98 -> 0 | DM98: =SUM(D98,J98,P98,V98,AD98,AL98,AU98,BC98,,BN98,BV98,CD98,CL98)-CT98 -> 0 | DP98: 2092411608 | DQ98: =-CR98+DP98/10^6 -> 2092.4116 | DR98: =SUM(E98,K98,Q98,W98,AE98,AM98,AV98,BD98,BL98,BU98,CC98,CK98)-CS98 -> 0 | DS98: =SUM(D98,J98,P98,V98,AD98,AL98,AU98,BC98,,BN98,BV98,CD98,CL98)-CT98 -> 0 | DU98: 157.63914 | DV98: =DU98-CJ98 -> 157.63914 | DX98: =(CS98-CZ98)*10^6 -> 0 | DY98: =(CT98-DC98)*10^6 -> 0 | DZ98: =(CW98-DD98)*10^6 -> 0
B99: Fees du contrat IHS (spécifique à CDI) | C99: Opex93 | CU99: =+CR99-CS99 -> 0 | CV99: =+CR99-CT99 -> 0 | CX99: =IFERROR(CR99/CW99-1, "-") -> - | DF99: =+DA99/DD99-1 -> #DIV/0! | DG99: =+DB99/DD99-1 -> #DIV/0! | DJ99: =SUM(D99,J99,P99,V99,AD99,AL99,AU99,BC99,BK99,BT99,CB99,CJ99)-CR99 -> 0 | DK99: =SUM(E99,K99,Q99,W99,AE99,AM99,AV99,BD99,BL99,BU99,CC99,CK99)-CS99 -> 0 | DL99: =SUM(G99,M99,S99,AA99,AI99,AR99,AZ99,BH99,BQ99,BY99,CG99,CO99)-CW99 -> 0 | DM99: =SUM(D99,J99,P99,V99,AD99,AL99,AU99,BC99,,BN99,BV99,CD99,CL99)-CT99 -> 0 | DQ99: =-CR99+DP99/10^6 -> 0 | DR99: =SUM(E99,K99,Q99,W99,AE99,AM99,AV99,BD99,BL99,BU99,CC99,CK99)-CS99 -> 0 | DS99: =SUM(D99,J99,P99,V99,AD99,AL99,AU99,BC99,,BN99,BV99,CD99,CL99)-CT99 -> 0 | DV99: =DU99-CJ99 -> 0 | DX99: =(CS99-CZ99)*10^6 -> 0 | DY99: =(CT99-DC99)*10^6 -> 0 | DZ99: =(CW99-DD99)*10^6 -> 0
B100: Matériel de transport (Entretien et locat°) | C100: Opex94 | CU100: =+CR100-CS100 -> 0 | CV100: =+CR100-CT100 -> 0 | CX100: =IFERROR(CR100/CW100-1, "-") -> - | DE100: =+CZ100/DD100-1 -> #DIV/0! | DF100: =+DA100/DD100-1 -> #DIV/0! | DG100: =+DB100/DD100-1 -> #DIV/0! | DH100: =+DC100/DD100-1 -> #DIV/0! | DJ100: =SUM(D100,J100,P100,V100,AD100,AL100,AU100,BC100,BK100,BT100,CB100,CJ100)-CR100 -> 0 | DK100: =SUM(E100,K100,Q100,W100,AE100,AM100,AV100,BD100,BL100,BU100,CC100,CK100)-CS100 -> 0 | DL100: =SUM(G100,M100,S100,AA100,AI100,AR100,AZ100,BH100,BQ100,BY100,CG100,CO100)-CW100 -> 0 | DM100: =SUM(D100,J100,P100,V100,AD100,AL100,AU100,BC100,,BN100,BV100,CD100,CL100)-CT100 -> 0 | DP100: =SUM(DP101:DP105) -> 68726818 | DQ100: =-CR100+DP100/10^6 -> 68.726818 | DR100: =SUM(E100,K100,Q100,W100,AE100,AM100,AV100,BD100,BL100,BU100,CC100,CK100)-CS100 -> 0 | DS100: =SUM(D100,J100,P100,V100,AD100,AL100,AU100,BC100,,BN100,BV100,CD100,CL100)-CT100 -> 0 | DU100: 25.859749 | DV100: =DU100-CJ100 -> 25.859749 | DX100: =(CS100-CZ100)*10^6 -> 0 | DY100: =(CT100-DC100)*10^6 -> 0 | DZ100: =(CW100-DD100)*10^6 -> 0
...

Sheet CA Mobile
P1: =#REF! -> #REF! | Y1: =Y8/W8 -> #DIV/0! | Z1: =Z8/X8 -> #DIV/0! | AU1: 0 | AV1: 0 | DJ1: 0
A2: CA Mobile | J2: 0 | P2: 8366.7791 | Q2: =P2+P179+P177+P171+P149+P144+P143+P53-P118-P126 -> 8366.7791 | R2: =+P8-Q2 -> -8366.7791 | W2: 0 | AD2: 0 | AG2: =AD8/AF8-1 -> #DIV/0! | BC2: 0 | CK2: 0 | DC2: 0
E3: 0 | CZ3: 0 | DD3: 0
D4: 45292 | J4: 45323 | P4: 45352 | V4: 45383 | AD4: 45413 | AL4: 45444 | AU4: 45474 | BC4: 45505 | BK4: 45536 | BT4: 45566 | CB4: 45597 | CJ4: 45627 | CR4: CUMUL | DB4: ANNUEL
B5: (En Millions ML) | D5: 2024 Réel | E5: 2024 Budget | F5: Ecart / Budget | G5: 2023 Réel | H5: Evol % | J5: 2024 Réel | K5: 2024 Budget | L5: Ecart / Budget | M5: 2023 Réel | N5: Evol % | P5: 2024 Réel | Q5: 2024 Budget | R5: Ecart / Budget | S5: 2023 Réel | T5: Evol % | V5: 2024 Réel | W5: 2024 Budget | X5: 2024 Actu1 | Y5: Ecart / Budget | Z5: Ecart / Actu1 | AA5: 2023 Réel | AB5: Evol % | AD5: 2024 Réel | AE5: 2024 Budget | AF5: 2024 Actu1 | AG5: Ecart / Budget | AH5: Ecart / Actu1 | AI5: 2023 Réel | AJ5: Evol % | AL5: 2024 Réel | AM5: 2024 Budget | AN5: 2024 Actu1 | AO5: 2024 Actu2 | AP5: Ecart / Budget | AQ5: Ecart / Actu1 | AR5: 2023 Réel | AS5: Evol % | AU5: 2024 Réel | AV5: 2024 Budget | AW5: 2024 Actu2 | AX5: Ecart / Budget | AY5: Ecart / Actu2 | AZ5: 2023 Réel | BA5: Evol % | BC5: 2024 Réel | BD5: 2024 Budget | BE5: 2024 Actu2 | BF5: Ecart / Budget | BG5: Ecart / Actu2 | BH5: 2023 Réel | BI5: Evol % | BK5: 2024 Réel | BL5: 2024 Budget | BM5: 2024 Actu2 | BN5: 2024 Actu3 | BO5: Ecart / Budget | BP5: Ecart / Actu2 | BQ5: 2023 Réel | BR5: Evol % | BT5: 2024 Réel | BU5: 2024 Budget | BV5: 2024 Actu3 | BW5: Ecart / Budget | BX5: Ecart / Actu3 | BY5: 2023 Réel | BZ5: Evol % | CB5: 2024 Réel | CC5: 2024 Budget | CD5: 2024 Actu3 | CE5: Ecart / Budget | CF5: Ecart / Actu3 | CG5: 2023 Réel | CH5: Evol % | CJ5: 2024 Réel | CK5: 2024 Budget | CL5: 2024 Actu3 | CM5: Ecart / Budget | CN5: Ecart / Actu3 | CO5: 2023 Réel | CP5: Evol % | CR5: 2024 Réel | CS5: 2024 Budget | CT5: 2024 Actu3 | CU5: Ecart / Budget | CV5: Ecart / Actu3 | CW5: 2023 Réel | CX5: Evol % | CZ5: 2024 Budget | DA5: 2024 Actu1 | DB5: 2024 Actu2 | DC5: 2024 Actu3 | DD5: 2023 Réel | DE5: Bud / 2023 (%) | DF5: Actu 1 / 2023 (%) | DG5: Actu 2 / 2023 (%) | DH5: Actu3 / 2023 (%)
A8: CA Global | C8: CA1 | CU8: =+CR8-CS8 -> 0 | CV8: =+CR8-CT8 -> 0 | CX8: =IFERROR(CR8/CW8-1, "-") -> - | DE8: =(CZ8-DD8)/DD8 -> #DIV/0! | DF8: =(DA8-DD8)/DD8 -> #DIV/0! | DG8: =(DB8-DD8)/DD8 -> #DIV/0! | DH8: =(DC8-DD8)/DD8 -> #DIV/0! | DM8: =CS8-CZ8 -> 0 | DN8: =CT8-DC8 -> 0 | DO8: =CW8-DD8 -> 0
C9: CA2 | CV9: =+CR9-CT9 -> 0 | CX9: =IFERROR(CR9/CW9-1, "-") -> - | DM9: =(CS9-CZ9)*10^6 -> 0 | DN9: =(CT9-DC9)*10^6 -> 0 | DO9: =(CW9-DD9)*10^6 -> 0
B10: dont CA Etat | C10: CA3 | CV10: =+CR10-CT10 -> 0 | CX10: =IFERROR(CR10/CW10-1, "-") -> - | DM10: =(CS10-CZ10)*10^6 -> 0 | DN10: =(CT10-DC10)*10^6 -> 0 | DO10: =(CW10-DD10)*10^6 -> 0
C11: CA4 | CV11: =+CR11-CT11 -> 0 | CX11: =IFERROR(CR11/CW11-1, "-") -> - | DM11: =(CS11-CZ11)*10^6 -> 0 | DN11: =(CT11-DC11)*10^6 -> 0 | DO11: =(CW11-DD11)*10^6 -> 0
A12: CA services Mobile | C12: CA5 | CU12: =+CR12-CS12 -> 0 | CV12: =+CR12-CT12 -> 0 | CX12: =IFERROR(CR12/CW12-1, "-") -> - | DE12: =(CZ12-DD12)/DD12 -> #DIV/0! | DF12: =(DA12-DD12)/DD12 -> #DIV/0! | DG12: =(DB12-DD12)/DD12 -> #DIV/0! | DH12: =(DC12-DD12)/DD12 -> #DIV/0! | DM12: =(CS12-CZ12)*10^6 -> 0 | DN12: =(CT12-DC12)*10^6 -> 0 | DO12: =(CW12-DD12)*10^6 -> 0
C13: CA6 | CV13: =+CR13-CT13 -> 0 | CX13: =IFERROR(CR13/CW13-1, "-") -> - | DM13: =(CS13-CZ13)*10^6 -> 0 | DN13: =(CT13-DC13)*10^6 -> 0 | DO13: =(CW13-DD13)*10^6 -> 0
A14: CA récurrent | C14: CA7 | CU14: =+CR14-CS14 -> 0 | CV14: =+CR14-CT14 -> 0 | CX14: =IFERROR(CR14/CW14-1, "-") -> - | DE14: =(CZ14-DD14)/DD14 -> #DIV/0! | DF14: =(DA14-DD14)/DD14 -> #DIV/0! | DG14: =(DB14-DD14)/DD14 -> #DIV/0! | DH14: =(DC14-DD14)/DD14 -> #DIV/0! | DM14: =(CS14-CZ14)*10^6 -> 0 | DN14: =(CT14-DC14)*10^6 -> 0 | DO14: =(CW14-DD14)*10^6 -> 0
C15: CA8 | CV15: =+CR15-CT15 -> 0 | CX15: =IFERROR(CR15/CW15-1, "-") -> - | DM15: =(CS15-CZ15)*10^6 -> 0 | DN15: =(CT15-DC15)*10^6 -> 0 | DO15: =(CW15-DD15)*10^6 -> 0
A16: CA sortant | C16: CA9 | CU16: =+CR16-CS16 -> 0 | CV16: =+CR16-CT16 -> 0 | CX16: =IFERROR(CR16/CW16-1, "-") -> - | DE16: =(CZ16-DD16)/DD16 -> #DIV/0! | DF16: =(DA16-DD16)/DD16 -> #DIV/0! | DG16: =(DB16-DD16)/DD16 -> #DIV/0! | DH16: =(DC16-DD16)/DD16 -> #DIV/0! | DM16: =(CS16-CZ16)*10^6 -> 0 | DN16: =(CT16-DC16)*10^6 -> 0 | DO16: =(CW16-DD16)*10^6 -> 0
B17: Prépayé (yc commissions) | C17: CA10 | CU17: =+CR17-CS17 -> 0 | CV17: =+CR17-CT17 -> 0 | CX17: =IFERROR(CR17/CW17-1, "-") -> - | DE17: =(CZ17-DD17)/DD17 -> #DIV/0! | DF17: =(DA17-DD17)/DD17 -> #DIV/0! | DG17: =(DB17-DD17)/DD17 -> #DIV/0! | DH17: =(DC17-DD17)/DD17 -> #DIV/0! | DM17: =(CS17-CZ17)*10^6 -> 0 | DN17: =(CT17-DC17)*10^6 -> 0 | DO17: =(CW17-DD17)*10^6 -> 0
A18: Consumer Prepaid | C18: CA11 | CU18: =+CR18-CS18 -> 0 | CV18: =+CR18-CT18 -> 0 | CX18: =+CR18/CW18-1 -> #DIV/0! | DE18: =(CZ18-DD18)/DD18 -> #DIV/0! | DF18: =(DA18-DD18)/DD18 -> #DIV/0! | DG18: =(DB18-DD18)/DD18 -> #DIV/0! | DH18: =(DC18-DD18)/DD18 -> #DIV/0! | DM18: =(CS18-CZ18)*10^6 -> 0 | DN18: =(CT18-DC18)*10^6 -> 0 | DO18: =(CW18-DD18)*10^6 -> 0
B19: Frais d'activation & Sim swap | C19: CA12 | CU19: =+CR19-CS19 -> 0 | CV19: =+CR19-CT19 -> 0 | CX19: =+CR19/CW19-1 -> #DIV/0! | DE19: =(CZ19-DD19)/DD19 -> #DIV/0! | DF19: =(DA19-DD19)/DD19 -> #DIV/0! | DG19: =(DB19-DD19)/DD19 -> #DIV/0! | DH19: =(DC19-DD19)/DD19 -> #DIV/0! | DM19: =(CS19-CZ19)*10^6 -> 0 | DN19: =(CT19-DC19)*10^6 -> 0 | DO19: =(CW19-DD19)*10^6 -> 0
B20: Sortant voix on net | C20: CA13 | CU20: =+CR20-CS20 -> 0 | CV20: =+CR20-CT20 -> 0 | CX20: =+CR20/CW20-1 -> #DIV/0! | DE20: =(CZ20-DD20)/DD20 -> #DIV/0! | DF20: =(DA20-DD20)/DD20 -> #DIV/0! | DG20: =(DB20-DD20)/DD20 -> #DIV/0! | DH20: =(DC20-DD20)/DD20 -> #DIV/0! | DM20: =(CS20-CZ20)*10^6 -> 0 | DN20: =(CT20-DC20)*10^6 -> 0 | DO20: =(CW20-DD20)*10^6 -> 0
B21: Sortant voix MTN | C21: CA14 | CU21: =+CR21-CS21 -> 0 | CV21: =+CR21-CT21 -> 0 | CX21: =+CR21/CW21-1 -> #DIV/0! | DE21: =(CZ21-DD21)/DD21 -> #DIV/0! | DF21: =(DA21-DD21)/DD21 -> #DIV/0! | DG21: =(DB21-DD21)/DD21 -> #DIV/0! | DH21: =(DC21-DD21)/DD21 -> #DIV/0! | DM21: =(CS21-CZ21)*10^6 -> 0 | DN21: =(CT21-DC21)*10^6 -> 0 | DO21: =(CW21-DD21)*10^6 -> 0
B22: Sortant voix GLO | C22: CA15 | CU22: =+CR22-CS22 -> 0 | CV22: =+CR22-CT22 -> 0 | DM22: =(CS22-CZ22)*10^6 -> 0 | DN22: =(CT22-DC22)*10^6 -> 0 | DO22: =(CW22-DD22)*10^6 -> 0
B23: Sortant voix BBCOM | C23: CA16 | CU23: =+CR23-CS23 -> 0 | CV23: =+CR23-CT23 -> 0 | DM23: =(CS23-CZ23)*10^6 -> 0 | DN23: =(CT23-DC23)*10^6 -> 0 | DO23: =(CW23-DD23)*10^6 -> 0
B24: Sortant voix LIBERCOM | C24: CA17 | CU24: =+CR24-CS24 -> 0 | CV24: =+CR24-CT24 -> 0 | DM24: =(CS24-CZ24)*10^6 -> 0 | DN24: =(CT24-DC24)*10^6 -> 0 | DO24: =(CW24-DD24)*10^6 -> 0
B25: Sortant voix BTSA | C25: CA18 | CU25: =+CR25-CS25 -> 0 | CV25: =+CR25-CT25 -> 0 | CX25: =+CR25/CW25-1 -> #DIV/0! | DE25: =(CZ25-DD25)/DD25 -> #DIV/0! | DF25: =(DA25-DD25)/DD25 -> #DIV/0! | DG25: =(DB25-DD25)/DD25 -> #DIV/0! | DH25: =(DC25-DD25)/DD25 -> #DIV/0! | DM25: =(CS25-CZ25)*10^6 -> 0 | DN25: =(CT25-DC25)*10^6 -> 0 | DO25: =(CW25-DD25)*10^6 -> 0
B26: Sortant voix INTERNATIONAL | C26: CA19 | CU26: =+CR26-CS26 -> 0 | CV26: =+CR26-CT26 -> 0 | CX26: =+CR26/CW26-1 -> #DIV/0! | DE26: =(CZ26-DD26)/DD26 -> #DIV/0! | DF26: =(DA26-DD26)/DD26 -> #DIV/0! | DG26: =(DB26-DD26)/DD26 -> #DIV/0! | DH26: =(DC26-DD26)/DD26 -> #DIV/0! | DM26: =(CS26-CZ26)*10^6 -> 0 | DN26: =(CT26-DC26)*10^6 -> 0 | DO26: =(CW26-DD26)*10^6 -> 0
B27: Sortant voix roaming | C27: CA20 | CU27: =+CR27-CS27 -> 0 | CV27: =+CR27-CT27 -> 0 | CX27: =+CR27/CW27-1 -> #DIV/0! | DE27: =(CZ27-DD27)/DD27 -> #DIV/0! | DF27: =(DA27-DD27)/DD27 -> #DIV/0! | DG27: =(DB27-DD27)/DD27 -> #DIV/0! | DH27: =(DC27-DD27)/DD27 -> #DIV/0! | DM27: =(CS27-CZ27)*10^6 -> 0 | DN27: =(CT27-DC27)*10^6 -> 0 | DO27: =(CW27-DD27)*10^6 -> 0
B28: Total VOIX Sortant | C28: CA21 | CU28: =+CR28-CS28 -> 0 | CV28: =+CR28-CT28 -> 0 | CX28: =+CR28/CW28-1 -> #DIV/0! | DE28: =(CZ28-DD28)/DD28 -> #DIV/0! | DF28: =(DA28-DD28)/DD28 -> #DIV/0! | DG28: =(DB28-DD28)/DD28 -> #DIV/0! | DH28: =(DC28-DD28)/DD28 -> #DIV/0! | DM28: =(CS28-CZ28)*10^6 -> 0 | DN28: =(CT28-DC28)*10^6 -> 0 | DO28: =(CW28-DD28)*10^6 -> 0
C29: CA22 | CU29: =+CR29-CS29 -> 0 | CV29: =+CR29-CT29 -> 0 | DM29: =(CS29-CZ29)*10^6 -> 0 | DN29: =(CT29-DC29)*10^6 -> 0 | DO29: =(CW29-DD29)*10^6 -> 0
B30: Sortant sms on net | C30: CA23 | CU30: =+CR30-CS30 -> 0 | CV30: =+CR30-CT30 -> 0 | CX30: =+CR30/CW30-1 -> #DIV/0! | DE30: =(CZ30-DD30)/DD30 -> #DIV/0! | DF30: =(DA30-DD30)/DD30 -> #DIV/0! | DG30: =(DB30-DD30)/DD30 -> #DIV/0! | DH30: =(DC30-DD30)/DD30 -> #DIV/0! | DM30: =(CS30-CZ30)*10^6 -> 0 | DN30: =(CT30-DC30)*10^6 -> 0 | DO30: =(CW30-DD30)*10^6 -> 0
B31: Sortant sms MTN | C31: CA24 | CU31: =+CR31-CS31 -> 0 | CV31: =+CR31-CT31 -> 0 | CX31: =+CR31/CW31-1 -> #DIV/0! | DE31: =(CZ31-DD31)/DD31 -> #DIV/0! | DF31: =(DA31-DD31)/DD31 -> #DIV/0! | DG31: =(DB31-DD31)/DD31 -> #DIV/0! | DH31: =(DC31-DD31)/DD31 -> #DIV/0! | DM31: =(CS31-CZ31)*10^6 -> 0 | DN31: =(CT31-DC31)*10^6 -> 0 | DO31: =(CW31-DD31)*10^6 -> 0
B32: Sortant sms GLO | C32: CA25 | CU32: =+CR32-CS32 -> 0 | CV32: =+CR32-CT32 -> 0 | DM32: =(CS32-CZ32)*10^6 -> 0 | DN32: =(CT32-DC32)*10^6 -> 0 | DO32: =(CW32-DD32)*10^6 -> 0
B33: Sortant sms BBCOM | C33: CA26 | CU33: =+CR33-CS33 -> 0 | CV33: =+CR33-CT33 -> 0 | CX33: =+CR33/CW33-1 -> #DIV/0! | DE33: =(CZ33-DD33)/DD33 -> #DIV/0! | DF33: =(DA33-DD33)/DD33 -> #DIV/0! | DG33: =(DB33-DD33)/DD33 -> #DIV/0! | DH33: =(DC33-DD33)/DD33 -> #DIV/0! | DM33: =(CS33-CZ33)*10^6 -> 0 | DN33: =(CT33-DC33)*10^6 -> 0 | DO33: =(CW33-DD33)*10^6 -> 0
B34: Sortant sms LIBERCOM | C34: CA27 | CU34: =+CR34-CS34 -> 0 | CV34: =+CR34-CT34 -> 0 | CX34: =+CR34/CW34-1 -> #DIV/0! | DE34: =(CZ34-DD34)/DD34 -> #DIV/0! | DF34: =(DA34-DD34)/DD34 -> #DIV/0! | DG34: =(DB34-DD34)/DD34 -> #DIV/0! | DH34: =(DC34-DD34)/DD34 -> #DIV/0! | DM34: =(CS34-CZ34)*10^6 -> 0 | DN34: =(CT34-DC34)*10^6 -> 0 | DO34: =(CW34-DD34)*10^6 -> 0
B35: Sortant sms INTERNATIONAL | C35: CA28 | CU35: =+CR35-CS35 -> 0 | CV35: =+CR35-CT35 -> 0 | CX35: =+CR35/CW35-1 -> #DIV/0! | DE35: =(CZ35-DD35)/DD35 -> #DIV/0! | DF35: =(DA35-DD35)/DD35 -> #DIV/0! | DG35: =(DB35-DD35)/DD35 -> #DIV/0! | DH35: =(DC35-DD35)/DD35 -> #DIV/0! | DM35: =(CS35-CZ35)*10^6 -> 0 | DN35: =(CT35-DC35)*10^6 -> 0 | DO35: =(CW35-DD35)*10^6 -> 0
B36: Total SMS Sortant | C36: CA29 | CU36: =+CR36-CS36 -> 0 | CV36: =+CR36-CT36 -> 0 | CX36: =+CR36/CW36-1 -> #DIV/0! | DE36: =(CZ36-DD36)/DD36 -> #DIV/0! | DF36: =(DA36-DD36)/DD36 -> #DIV/0! | DG36: =(DB36-DD36)/DD36 -> #DIV/0! | DH36: =(DC36-DD36)/DD36 -> #DIV/0! | DM36: =(CS36-CZ36)*10^6 -> 0 | DN36: =(CT36-DC36)*10^6 -> 0 | DO36: =(CW36-DD36)*10^6 -> 0
C37: CA30 | CU37: =+CR37-CS37 -> 0 | CV37: =+CR37-CT37 -> 0 | DM37: =(CS37-CZ37)*10^6 -> 0 | DN37: =(CT37-DC37)*10^6 -> 0 | DO37: =(CW37-DD37)*10^6 -> 0
B38: Revenu Internet 3G | C38: CA31 | CU38: =+CR38-CS38 -> 0 | CV38: =+CR38-CT38 -> 0 | CX38: =+CR38/CW38-1 -> #DIV/0! | DE38: =(CZ38-DD38)/DD38 -> #DIV/0! | DF38: =(DA38-DD38)/DD38 -> #DIV/0! | DG38: =(DB38-DD38)/DD38 -> #DIV/0! | DH38: =(DC38-DD38)/DD38 -> #DIV/0! | DM38: =(CS38-CZ38)*10^6 -> 0 | DN38: =(CT38-DC38)*10^6 -> 0 | DO38: =(CW38-DD38)*10^6 -> 0
C39: CA32 | CU39: =+CR39-CS39 -> 0 | CV39: =+CR39-CT39 -> 0 | DM39: =(CS39-CZ39)*10^6 -> 0 | DN39: =(CT39-DC39)*10^6 -> 0 | DO39: =(CW39-DD39)*10^6 -> 0
B40: CRBT | C40: CA33 | CU40: =+CR40-CS40 -> 0 | CV40: =+CR40-CT40 -> 0 | CX40: =+CR40/CW40-1 -> #DIV/0! | DE40: =(CZ40-DD40)/DD40 -> #DIV/0! | DF40: =(DA40-DD40)/DD40 -> #DIV/0! | DG40: =(DB40-DD40)/DD40 -> #DIV/0! | DH40: =(DC40-DD40)/DD40 -> #DIV/0! | DM40: =(CS40-CZ40)*10^6 -> 0 | DN40: =(CT40-DC40)*10^6 -> 0 | DO40: =(CW40-DD40)*10^6 -> 0
B41: Crédit secours | C41: CA34 | CU41: =+CR41-CS41 -> 0 | CV41: =+CR41-CT41 -> 0 | CX41: =+CR41/CW41-1 -> #DIV/0! | DE41: =(CZ41-DD41)/DD41 -> #DIV/0! | DF41: =(DA41-DD41)/DD41 -> #DIV/0! | DG41: =(DB41-DD41)/DD41 -> #DIV/0! | DH41: =(DC41-DD41)/DD41 -> #DIV/0! | DM41: =(CS41-CZ41)*10^6 -> 0 | DN41: =(CT41-DC41)*10^6 -> 0 | DO41: =(CW41-DD41)*10^6 -> 0
B42: Story Box | C42: CA35 | CU42: =+CR42-CS42 -> 0 | CV42: =+CR42-CT42 -> 0 | DM42: =(CS42-CZ42)*10^6 -> 0 | DN42: =(CT42-DC42)*10^6 -> 0 | DO42: =(CW42-DD42)*10^6 -> 0
B43: Phonebook STK | C43: CA36 | CU43: =+CR43-CS43 -> 0 | CV43: =+CR43-CT43 -> 0 | DM43: =(CS43-CZ43)*10^6 -> 0 | DN43: =(CT43-DC43)*10^6 -> 0 | DO43: =(CW43-DD43)*10^6 -> 0
B44: Gaming | C44: CA37 | CU44: =+CR44-CS44 -> 0 | CV44: =+CR44-CT44 -> 0 | DM44: =(CS44-CZ44)*10^6 -> 0 | DN44: =(CT44-DC44)*10^6 -> 0 | DO44: =(CW44-DD44)*10^6 -> 0
B45: Autres dont BAC17 (VOICEALERT,MOOVKDO...) & SAV agences | C45: CA38 | CU45: =+CR45-CS45 -> 0 | CV45: =+CR45-CT45 -> 0 | CX45: =+CR45/CW45-1 -> #DIV/0! | DE45: =(CZ45-DD45)/DD45 -> #DIV/0! | DF45: =(DA45-DD45)/DD45 -> #DIV/0! | DG45: =(DB45-DD45)/DD45 -> #DIV/0! | DH45: =(DC45-DD45)/DD45 -> #DIV/0! | DM45: =(CS45-CZ45)*10^6 -> 0 | DN45: =(CT45-DC45)*10^6 -> 0 | DO45: =(CW45-DD45)*10^6 -> 0
B46: Videos | C46: CA39 | CU46: =+CR46-CS46 -> 0 | CV46: =+CR46-CT46 -> 0 | DG46: =(DB46-DD46)/DD46 -> #DIV/0! | DM46: =(CS46-CZ46)*10^6 -> 0 | DN46: =(CT46-DC46)*10^6 -> 0 | DO46: =(CW46-DD46)*10^6 -> 0
B47: Total Data | C47: CA40 | CU47: =+CR47-CS47 -> 0 | CV47: =+CR47-CT47 -> 0 | CX47: =+CR47/CW47-1 -> #DIV/0! | DE47: =(CZ47-DD47)/DD47 -> #DIV/0! | DF47: =(DA47-DD47)/DD47 -> #DIV/0! | DG47: =(DB47-DD47)/DD47 -> #DIV/0! | DH47: =(DC47-DD47)/DD47 -> #DIV/0! | DM47: =(CS47-CZ47)*10^6 -> 0 | DN47: =(CT47-DC47)*10^6 -> 0 | DO47: =(CW47-DD47)*10^6 -> 0
C48: CA41 | CU48: =+CR48-CS48 -> 0 | CV48: =+CR48-CT48 -> 0 | DM48: =(CS48-CZ48)*10^6 -> 0 | DN48: =(CT48-DC48)*10^6 -> 0 | DO48: =(CW48-DD48)*10^6 -> 0
B49: dont CA voix | C49: CA42 | CU49: =+CR49-CS49 -> 0 | CV49: =+CR49-CT49 -> 0 | DM49: =(CS49-CZ49)*10^6 -> 0 | DN49: =(CT49-DC49)*10^6 -> 0 | DO49: =(CW49-DD49)*10^6 -> 0
B50: dont CA SMS | C50: CA43 | CU50: =+CR50-CS50 -> 0 | CV50: =+CR50-CT50 -> 0 | DM50: =(CS50-CZ50)*10^6 -> 0 | DN50: =(CT50-DC50)*10^6 -> 0 | DO50: =(CW50-DD50)*10^6 -> 0
B51: dont SVA (Sce à Val. Ajoutée) | C51: CA44 | CU51: =+CR51-CS51 -> 0 | CV51: =+CR51-CT51 -> 0 | DM51: =(CS51-CZ51)*10^6 -> 0 | DN51: =(CT51-DC51)*10^6 -> 0 | DO51: =(CW51-DD51)*10^6 -> 0
B52: dont CA Internet 3G | C52: CA45 | CU52: =+CR52-CS52 -> 0 | CV52: =+CR52-CT52 -> 0 | CX52: =+CR52/CW52-1 -> #DIV/0! | DE52: =(CZ52-DD52)/DD52 -> #DIV/0! | DF52: =(DA52-DD52)/DD52 -> #DIV/0! | DG52: =(DB52-DD52)/DD52 -> #DIV/0! | DH52: =(DC52-DD52)/DD52 -> #DIV/0! | DM52: =(CS52-CZ52)*10^6 -> 0 | DN52: =(CT52-DC52)*10^6 -> 0 | DO52: =(CW52-DD52)*10^6 -> 0
B53: Postpayé | C53: CA46 | CU53: =+CR53-CS53 -> 0 | CV53: =+CR53-CT53 -> 0 | CX53: =IFERROR(CR53/CW53-1, "-") -> - | DE53: =(CZ53-DD53)/DD53 -> #DIV/0! | DF53: =(DA53-DD53)/DD53 -> #DIV/0! | DG53: =(DB53-DD53)/DD53 -> #DIV/0! | DH53: =(DC53-DD53)/DD53 -> #DIV/0! | DM53: =(CS53-CZ53)*10^6 -> 0 | DN53: =(CT53-DC53)*10^6 -> 0 | DO53: =(CW53-DD53)*10^6 -> 0
B54: Redevance d'abonnement | C54: CA47 | CU54: =+CR54-CS54 -> 0 | CV54: =+CR54-CT54 -> 0 | CX54: =IFERROR(CR54/CW54-1, "-") -> - | DE54: =(CZ54-DD54)/DD54 -> #DIV/0! | DF54: =(DA54-DD54)/DD54 -> #DIV/0! | DG54: =(DB54-DD54)/DD54 -> #DIV/0! | DH54: =(DC54-DD54)/DD54 -> #DIV/0! | DM54: =(CS54-CZ54)*10^6 -> 0 | DN54: =(CT54-DC54)*10^6 -> 0 | DO54: =(CW54-DD54)*10^6 -> 0
A55: Consumer Postpaid | C55: CA48 | CU55: =+CR55-CS55 -> 0 | CV55: =+CR55-CT55 -> 0 | CX55: =+CR55/CW55-1 -> #DIV/0! | DE55: =(CZ55-DD55)/DD55 -> #DIV/0! | DF55: =(DA55-DD55)/DD55 -> #DIV/0! | DG55: =(DB55-DD55)/DD55 -> #DIV/0! | DH55: =(DC55-DD55)/DD55 -> #DIV/0! | DM55: =(CS55-CZ55)*10^6 -> 0 | DN55: =(CT55-DC55)*10^6 -> 0 | DO55: =(CW55-DD55)*10^6 -> 0
A56: Business Postpaid | C56: CA49 | CU56: =+CR56-CS56 -> 0 | CV56: =+CR56-CT56 -> 0 | CX56: =+CR56/CW56-1 -> #DIV/0! | DE56: =(CZ56-DD56)/DD56 -> #DIV/0! | DF56: =(DA56-DD56)/DD56 -> #DIV/0! | DG56: =(DB56-DD56)/DD56 -> #DIV/0! | DH56: =(DC56-DD56)/DD56 -> #DIV/0! | DM56: =(CS56-CZ56)*10^6 -> 0 | DN56: =(CT56-DC56)*10^6 -> 0 | DO56: =(CW56-DD56)*10^6 -> 0
A57: Business Prepaid | C57: CA50 | CU57: =+CR57-CS57 -> 0 | CV57: =+CR57-CT57 -> 0 | CX57: =+CR57/CW57-1 -> #DIV/0! | DE57: =(CZ57-DD57)/DD57 -> #DIV/0! | DF57: =(DA57-DD57)/DD57 -> #DIV/0! | DG57: =(DB57-DD57)/DD57 -> #DIV/0! | DH57: =(DC57-DD57)/DD57 -> #DIV/0! | DM57: =(CS57-CZ57)*10^6 -> 0 | DN57: =(CT57-DC57)*10^6 -> 0 | DO57: =(CW57-DD57)*10^6 -> 0
B58: Trafic sortant | C58: CA51 | CU58: =+CR58-CS58 -> 0 | CV58: =+CR58-CT58 -> 0 | CX58: =IFERROR(CR58/CW58-1, "-") -> - | DE58: =(CZ58-DD58)/DD58 -> #DIV/0! | DF58: =(DA58-DD58)/DD58 -> #DIV/0! | DG58: =(DB58-DD58)/DD58 -> #DIV/0! | DH58: =(DC58-DD58)/DD58 -> #DIV/0! | DM58: =(CS58-CZ58)*10^6 -> 0 | DN58: =(CT58-DC58)*10^6 -> 0 | DO58: =(CW58-DD58)*10^6 -> 0
A59: Consumer Postpaid | C59: CA52 | CU59: =+CR59-CS59 -> 0 | CV59: =+CR59-CT59 -> 0 | CX59: =+CR59/CW59-1 -> #DIV/0! | DE59: =(CZ59-DD59)/DD59 -> #DIV/0! | DF59: =(DA59-DD59)/DD59 -> #DIV/0! | DG59: =(DB59-DD59)/DD59 -> #DIV/0! | DH59: =(DC59-DD59)/DD59 -> #DIV/0! | DM59: =(CS59-CZ59)*10^6 -> 0 | DN59: =(CT59-DC59)*10^6 -> 0 | DO59: =(CW59-DD59)*10^6 -> 0
B60: Sortant voix on net | C60: CA53 | CU60: =+CR60-CS60 -> 0 | CV60: =+CR60-CT60 -> 0 | CX60: =+CR60/CW60-1 -> #DIV/0! | DE60: =(CZ60-DD60)/DD60 -> #DIV/0! | DF60: =(DA60-DD60)/DD60 -> #DIV/0! | DG60: =(DB60-DD60)/DD60 -> #DIV/0! | DH60: =(DC60-DD60)/DD60 -> #DIV/0! | DM60: =(CS60-CZ60)*10^6 -> 0 | DN60: =(CT60-DC60)*10^6 -> 0 | DO60: =(CW60-DD60)*10^6 -> 0
B61: Sortant voix MTN | C61: CA54 | CU61: =+CR61-CS61 -> 0 | CV61: =+CR61-CT61 -> 0 | CX61: =+CR61/CW61-1 -> #DIV/0! | DE61: =(CZ61-DD61)/DD61 -> #DIV/0! | DF61: =(DA61-DD61)/DD61 -> #DIV/0! | DG61: =(DB61-DD61)/DD61 -> #DIV/0! | DH61: =(DC61-DD61)/DD61 -> #DIV/0! | DM61: =(CS61-CZ61)*10^6 -> 0 | DN61: =(CT61-DC61)*10^6 -> 0 | DO61: =(CW61-DD61)*10^6 -> 0
B62: Sortant voix GLO | C62: CA55 | CU62: =+CR62-CS62 -> 0 | CV62: =+CR62-CT62 -> 0 | DM62: =(CS62-CZ62)*10^6 -> 0 | DN62: =(CT62-DC62)*10^6 -> 0 | DO62: =(CW62-DD62)*10^6 -> 0
B63: Sortant voix BBCOM | C63: CA56 | CU63: =+CR63-CS63 -> 0 | CV63: =+CR63-CT63 -> 0 | DM63: =(CS63-CZ63)*10^6 -> 0 | DN63: =(CT63-DC63)*10^6 -> 0 | DO63: =(CW63-DD63)*10^6 -> 0
B64: Sortant voix LIBERCOM | C64: CA57 | CU64: =+CR64-CS64 -> 0 | CV64: =+CR64-CT64 -> 0 | DM64: =(CS64-CZ64)*10^6 -> 0 | DN64: =(CT64-DC64)*10^6 -> 0 | DO64: =(CW64-DD64)*10^6 -> 0
B65: Sortant voix BTSA | C65: CA58 | CU65: =+CR65-CS65 -> 0 | CV65: =+CR65-CT65 -> 0 | CX65: =+CR65/CW65-1 -> #DIV/0! | DE65: =(CZ65-DD65)/DD65 -> #DIV/0! | DF65: =(DA65-DD65)/DD65 -> #DIV/0! | DG65: =(DB65-DD65)/DD65 -> #DIV/0! | DH65: =(DC65-DD65)/DD65 -> #DIV/0! | DM65: =(CS65-CZ65)*10^6 -> 0 | DN65: =(CT65-DC65)*10^6 -> 0 | DO65: =(CW65-DD65)*10^6 -> 0
B66: Sortant voix INTERNATIONAL | C66: CA59 | CU66: =+CR66-CS66 -> 0 | CV66: =+CR66-CT66 -> 0 | CX66: =+CR66/CW66-1 -> #DIV/0! | DE66: =(CZ66-DD66)/DD66 -> #DIV/0! | DF66: =(DA66-DD66)/DD66 -> #DIV/0! | DG66: =(DB66-DD66)/DD66 -> #DIV/0! | DH66: =(DC66-DD66)/DD66 -> #DIV/0! | DM66: =(CS66-CZ66)*10^6 -> 0 | DN66: =(CT66-DC66)*10^6 -> 0 | DO66: =(CW66-DD66)*10^6 -> 0
B67: Sortant voix roaming | C67: CA60 | CU67: =+CR67-CS67 -> 0 | CV67: =+CR67-CT67 -> 0 | CX67: =+CR67/CW67-1 -> #DIV/0! | DE67: =(CZ67-DD67)/DD67 -> #DIV/0! | DF67: =(DA67-DD67)/DD67 -> #DIV/0! | DG67: =(DB67-DD67)/DD67 -> #DIV/0! | DH67: =(DC67-DD67)/DD67 -> #DIV/0! | DM67: =(CS67-CZ67)*10^6 -> 0 | DN67: =(CT67-DC67)*10^6 -> 0 | DO67: =(CW67-DD67)*10^6 -> 0
B68: Total VOIX Sortant | C68: CA61 | CU68: =+CR68-CS68 -> 0 | CV68: =+CR68-CT68 -> 0 | CX68: =+CR68/CW68-1 -> #DIV/0! | DE68: =(CZ68-DD68)/DD68 -> #DIV/0! | DF68: =(DA68-DD68)/DD68 -> #DIV/0! | DG68: =(DB68-DD68)/DD68 -> #DIV/0! | DH68: =(DC68-DD68)/DD68 -> #DIV/0! | DM68: =(CS68-CZ68)*10^6 -> 0 | DN68: =(CT68-DC68)*10^6 -> 0 | DO68: =(CW68-DD68)*10^6 -> 0
C69: CA62 | CU69: =+CR69-CS69 -> 0 | CV69: =+CR69-CT69 -> 0 | DM69: =(CS69-CZ69)*10^6 -> 0 | DN69: =(CT69-DC69)*10^6 -> 0 | DO69: =(CW69-DD69)*10^6 -> 0
B70: Sortant sms on net | C70: CA63 | CU70: =+CR70-CS70 -> 0 | CV70: =+CR70-CT70 -> 0 | CX70: =+CR70/CW70-1 -> #DIV/0! | DE70: =(CZ70-DD70)/DD70 -> #DIV/0! | DF70: =(DA70-DD70)/DD70 -> #DIV/0! | DG70: =(DB70-DD70)/DD70 -> #DIV/0! | DH70: =(DC70-DD70)/DD70 -> #DIV/0! | DM70: =(CS70-CZ70)*10^6 -> 0 | DN70: =(CT70-DC70)*10^6 -> 0 | DO70: =(CW70-DD70)*10^6 -> 0
B71: Sortant sms MTN | C71: CA64 | CU71: =+CR71-CS71 -> 0 | CV71: =+CR71-CT71 -> 0 | CX71: =+CR71/CW71-1 -> #DIV/0! | DE71: =(CZ71-DD71)/DD71 -> #DIV/0! | DF71: =(DA71-DD71)/DD71 -> #DIV/0! | DG71: =(DB71-DD71)/DD71 -> #DIV/0! | DH71: =(DC71-DD71)/DD71 -> #DIV/0! | DM71: =(CS71-CZ71)*10^6 -> 0 | DN71: =(CT71-DC71)*10^6 -> 0 | DO71: =(CW71-DD71)*10^6 -> 0
B72: Sortant sms GLO | C72: CA65 | CU72: =+CR72-CS72 -> 0 | CV72: =+CR72-CT72 -> 0 | DM72: =(CS72-CZ72)*10^6 -> 0 | DN72: =(CT72-DC72)*10^6 -> 0 | DO72: =(CW72-DD72)*10^6 -> 0
B73: Sortant sms BBCOM | C73: CA66 | CU73: =+CR73-CS73 -> 0 | CV73: =+CR73-CT73 -> 0 | DM73: =(CS73-CZ73)*10^6 -> 0 | DN73: =(CT73-DC73)*10^6 -> 0 | DO73: =(CW73-DD73)*10^6 -> 0
B74: Sortant sms LIBERCOM | C74: CA67 | CU74: =+CR74-CS74 -> 0 | CV74: =+CR74-CT74 -> 0 | DM74: =(CS74-CZ74)*10^6 -> 0 | DN74: =(CT74-DC74)*10^6 -> 0 | DO74: =(CW74-DD74)*10^6 -> 0
B75: Sortant sms INTERNATIONAL | C75: CA68 | CU75: =+CR75-CS75 -> 0 | CV75: =+CR75-CT75 -> 0 | CX75: =+CR75/CW75-1 -> #DIV/0! | DE75: =(CZ75-DD75)/DD75 -> #DIV/0! | DF75: =(DA75-DD75)/DD75 -> #DIV/0! | DG75: =(DB75-DD75)/DD75 -> #DIV/0! | DH75: =(DC75-DD75)/DD75 -> #DIV/0! | DM75: =(CS75-CZ75)*10^6 -> 0 | DN75: =(CT75-DC75)*10^6 -> 0 | DO75: =(CW75-DD75)*10^6 -> 0
B76: Total SMS Sortant | C76: CA69 | CU76: =+CR76-CS76 -> 0 | CV76: =+CR76-CT76 -> 0 | CX76: =+CR76/CW76-1 -> #DIV/0! | DE76: =(CZ76-DD76)/DD76 -> #DIV/0! | DF76: =(DA76-DD76)/DD76 -> #DIV/0! | DG76: =(DB76-DD76)/DD76 -> #DIV/0! | DH76: =(DC76-DD76)/DD76 -> #DIV/0! | DM76: =(CS76-CZ76)*10^6 -> 0 | DN76: =(CT76-DC76)*10^6 -> 0 | DO76: =(CW76-DD76)*10^6 -> 0
C77: CA70 | CU77: =+CR77-CS77 -> 0 | CV77: =+CR77-CT77 -> 0 | DM77: =(CS77-CZ77)*10^6 -> 0 | DN77: =(CT77-DC77)*10^6 -> 0 | DO77: =(CW77-DD77)*10^6 -> 0
B78: Revenu Internet 3G | C78: CA71 | CU78: =+CR78-CS78 -> 0 | CV78: =+CR78-CT78 -> 0 | CX78: =+CR78/CW78-1 -> #DIV/0! | DE78: =(CZ78-DD78)/DD78 -> #DIV/0! | DF78: =(DA78-DD78)/DD78 -> #DIV/0! | DG78: =(DB78-DD78)/DD78 -> #DIV/0! | DH78: =(DC78-DD78)/DD78 -> #DIV/0! | DM78: =(CS78-CZ78)*10^6 -> 0 | DN78: =(CT78-DC78)*10^6 -> 0 | DO78: =(CW78-DD78)*10^6 -> 0
B79: Transport and Automotive (Traking) | C79: CA72 | CU79: =+CR79-CS79 -> 0 | CV79: =+CR79-CT79 -> 0 | DM79: =(CS79-CZ79)*10^6 -> 0 | DN79: =(CT79-DC79)*10^6 -> 0 | DO79: =(CW79-DD79)*10^6 -> 0
B80: Banking | C80: CA73 | CU80: =+CR80-CS80 -> 0 | CV80: =+CR80-CT80 -> 0 | DM80: =(CS80-CZ80)*10^6 -> 0 | DN80: =(CT80-DC80)*10^6 -> 0 | DO80: =(CW80-DD80)*10^6 -> 0
B81: TPE | C81: CA74 | CU81: =+CR81-CS81 -> 0 | CV81: =+CR81-CT81 -> 0 | DM81: =(CS81-CZ81)*10^6 -> 0 | DN81: =(CT81-DC81)*10^6 -> 0 | DO81: =(CW81-DD81)*10^6 -> 0
B82: Total Data | C82: CA75 | CU82: =+CR82-CS82 -> 0 | CV82: =+CR82-CT82 -> 0 | DM82: =(CS82-CZ82)*10^6 -> 0 | DN82: =(CT82-DC82)*10^6 -> 0 | DO82: =(CW82-DD82)*10^6 -> 0
C83: CA76 | CU83: =+CR83-CS83 -> 0 | CV83: =+CR83-CT83 -> 0 | DH83: =(DC83-DD83)/DD83 -> #DIV/0! | DM83: =(CS83-CZ83)*10^6 -> 0 | DN83: =(CT83-DC83)*10^6 -> 0 | DO83: =(CW83-DD83)*10^6 -> 0
A84: Business Postpaid | C84: CA77 | CU84: =+CR84-CS84 -> 0 | CV84: =+CR84-CT84 -> 0 | CX84: =+CR84/CW84-1 -> #DIV/0! | DE84: =(CZ84-DD84)/DD84 -> #DIV/0! | DF84: =(DA84-DD84)/DD84 -> #DIV/0! | DG84: =(DB84-DD84)/DD84 -> #DIV/0! | DH84: =(DC84-DD84)/DD84 -> #DIV/0! | DM84: =(CS84-CZ84)*10^6 -> 0 | DN84: =(CT84-DC84)*10^6 -> 0 | DO84: =(CW84-DD84)*10^6 -> 0
B85: Sortant voix on net | C85: CA78 | CU85: =+CR85-CS85 -> 0 | CV85: =+CR85-CT85 -> 0 | CX85: =+CR85/CW85-1 -> #DIV/0! | DE85: =(CZ85-DD85)/DD85 -> #DIV/0! | DF85: =(DA85-DD85)/DD85 -> #DIV/0! | DG85: =(DB85-DD85)/DD85 -> #DIV/0! | DH85: =(DC85-DD85)/DD85 -> #DIV/0! | DM85: =(CS85-CZ85)*10^6 -> 0 | DN85: =(CT85-DC85)*10^6 -> 0 | DO85: =(CW85-DD85)*10^6 -> 0
B86: Sortant voix MTN | C86: CA79 | CU86: =+CR86-CS86 -> 0 | CV86: =+CR86-CT86 -> 0 | CX86: =+CR86/CW86-1 -> #DIV/0! | DE86: =(CZ86-DD86)/DD86 -> #DIV/0! | DF86: =(DA86-DD86)/DD86 -> #DIV/0! | DG86: =(DB86-DD86)/DD86 -> #DIV/0! | DH86: =(DC86-DD86)/DD86 -> #DIV/0! | DM86: =(CS86-CZ86)*10^6 -> 0 | DN86: =(CT86-DC86)*10^6 -> 0 | DO86: =(CW86-DD86)*10^6 -> 0
B87: Sortant voix GLO | C87: CA80 | CU87: =+CR87-CS87 -> 0 | CV87: =+CR87-CT87 -> 0 | DM87: =(CS87-CZ87)*10^6 -> 0 | DN87: =(CT87-DC87)*10^6 -> 0 | DO87: =(CW87-DD87)*10^6 -> 0
B88: Sortant voix BBCOM | C88: CA81 | CU88: =+CR88-CS88 -> 0 | CV88: =+CR88-CT88 -> 0 | DM88: =(CS88-CZ88)*10^6 -> 0 | DN88: =(CT88-DC88)*10^6 -> 0 | DO88: =(CW88-DD88)*10^6 -> 0
B89: Sortant voix LIBERCOM | C89: CA82 | CU89: =+CR89-CS89 -> 0 | CV89: =+CR89-CT89 -> 0 | DM89: =(CS89-CZ89)*10^6 -> 0 | DN89: =(CT89-DC89)*10^6 -> 0 | DO89: =(CW89-DD89)*10^6 -> 0
B90: Sortant voix BTSA | C90: CA83 | CU90: =+CR90-CS90 -> 0 | CV90: =+CR90-CT90 -> 0 | CX90: =+CR90/CW90-1 -> #DIV/0! | DE90: =(CZ90-DD90)/DD90 -> #DIV/0! | DF90: =(DA90-DD90)/DD90 -> #DIV/0! | DG90: =(DB90-DD90)/DD90 -> #DIV/0! | DH90: =(DC90-DD90)/DD90 -> #DIV/0! | DM90: =(CS90-CZ90)*10^6 -> 0 | DN90: =(CT90-DC90)*10^6 -> 0 | DO90: =(CW90-DD90)*10^6 -> 0
B91: Sortant voix INTERNATIONAL | C91: CA84 | CU91: =+CR91-CS91 -> 0 | CV91: =+CR91-CT91 -> 0 | CX91: =+CR91/CW91-1 -> #DIV/0! | DE91: =(CZ91-DD91)/DD91 -> #DIV/0! | DF91: =(DA91-DD91)/DD91 -> #DIV/0! | DG91: =(DB91-DD91)/DD91 -> #DIV/0! | DH91: =(DC91-DD91)/DD91 -> #DIV/0! | DM91: =(CS91-CZ91)*10^6 -> 0 | DN91: =(CT91-DC91)*10^6 -> 0 | DO91: =(CW91-DD91)*10^6 -> 0
B92: Sortant voix roaming | C92: CA85 | CU92: =+CR92-CS92 -> 0 | CV92: =+CR92-CT92 -> 0 | CX92: =+CR92/CW92-1 -> #DIV/0! | DE92: =(CZ92-DD92)/DD92 -> #DIV/0! | DF92: =(DA92-DD92)/DD92 -> #DIV/0! | DG92: =(DB92-DD92)/DD92 -> #DIV/0! | DH92: =(DC92-DD92)/DD92 -> #DIV/0! | DM92: =(CS92-CZ92)*10^6 -> 0 | DN92: =(CT92-DC92)*10^6 -> 0 | DO92: =(CW92-DD92)*10^6 -> 0
B93: Total VOIX Sortant | C93: CA86 | CU93: =+CR93-CS93 -> 0 | CV93: =+CR93-CT93 -> 0 | CX93: =+CR93/CW93-1 -> #DIV/0! | DE93: =(CZ93-DD93)/DD93 -> #DIV/0! | DF93: =(DA93-DD93)/DD93 -> #DIV/0! | DG93: =(DB93-DD93)/DD93 -> #DIV/0! | DH93: =(DC93-DD93)/DD93 -> #DIV/0! | DM93: =(CS93-CZ93)*10^6 -> 0 | DN93: =(CT93-DC93)*10^6 -> 0 | DO93: =(CW93-DD93)*10^6 -> 0
C94: CA87 | CU94: =+CR94-CS94 -> 0 | CV94: =+CR94-CT94 -> 0 | DM94: =(CS94-CZ94)*10^6 -> 0 | DN94: =(CT94-DC94)*10^6 -> 0 | DO94: =(CW94-DD94)*10^6 -> 0
B95: Sortant sms on net | C95: CA88 | CU95: =+CR95-CS95 -> 0 | CV95: =+CR95-CT95 -> 0 | CX95: =+CR95/CW95-1 -> #DIV/0! | DE95: =(CZ95-DD95)/DD95 -> #DIV/0! | DF95: =(DA95-DD95)/DD95 -> #DIV/0! | DG95: =(DB95-DD95)/DD95 -> #DIV/0! | DH95: =(DC95-DD95)/DD95 -> #DIV/0! | DM95: =(CS95-CZ95)*10^6 -> 0 | DN95: =(CT95-DC95)*10^6 -> 0 | DO95: =(CW95-DD95)*10^6 -> 0
B96: Sortant sms MTN | C96: CA89 | CU96: =+CR96-CS96 -> 0 | CV96: =+CR96-CT96 -> 0 | CX96: =+CR96/CW96-1 -> #DIV/0! | DE96: =(CZ96-DD96)/DD96 -> #DIV/0! | DF96: =(DA96-DD96)/DD96 -> #DIV/0! | DG96: =(DB96-DD96)/DD96 -> #DIV/0! | DH96: =(DC96-DD96)/DD96 -> #DIV/0! | DM96: =(CS96-CZ96)*10^6 -> 0 | DN96: =(CT96-DC96)*10^6 -> 0 | DO96: =(CW96-DD96)*10^6 -> 0
B97: Sortant sms GLO | C97: CA90 | CU97: =+CR97-CS97 -> 0 | CV97: =+CR97-CT97 -> 0 | DM97: =(CS97-CZ97)*10^6 -> 0 | DN97: =(CT97-DC97)*10^6 -> 0 | DO97: =(CW97-DD97)*10^6 -> 0
B98: Sortant sms BBCOM | C98: CA91 | CU98: =+CR98-CS98 -> 0 | CV98: =+CR98-CT98 -> 0 | CX98: =+CR98/CW98-1 -> #DIV/0! | DE98: =(CZ98-DD98)/DD98 -> #DIV/0! | DF98: =(DA98-DD98)/DD98 -> #DIV/0! | DG98: =(DB98-DD98)/DD98 -> #DIV/0! | DH98: =(DC98-DD98)/DD98 -> #DIV/0! | DM98: =(CS98-CZ98)*10^6 -> 0 | DN98: =(CT98-DC98)*10^6 -> 0 | DO98: =(CW98-DD98)*10^6 -> 0
B99: Sortant sms LIBERCOM | C99: CA92 | CU99: =+CR99-CS99 -> 0 | CV99: =+CR99-CT99 -> 0 | DM99: =(CS99-CZ99)*10^6 -> 0 | DN99: =(CT99-DC99)*10^6 -> 0 | DO99: =(CW99-DD99)*10^6 -> 0
B100: Sortant sms INTERNATIONAL | C100: CA93 | CU100: =+CR100-CS100 -> 0 | CV100: =+CR100-CT100 -> 0 | CX100: =+CR100/CW100-1 -> #DIV/0! | DE100: =(CZ100-DD100)/DD100 -> #DIV/0! | DF100: =(DA100-DD100)/DD100 -> #DIV/0! | DG100: =(DB100-DD100)/DD100 -> #DIV/0! | DH100: =(DC100-DD100)/DD100 -> #DIV/0! | DM100: =(CS100-CZ100)*10^6 -> 0 | DN100: =(CT100-DC100)*10^6 -> 0 | DO100: =(CW100-DD100)*10^6 -> 0
B101: Total SMS Sortant | C101: CA94 | CU101: =+CR101-CS101 -> 0 | CV101: =+CR101-CT101 -> 0 | CX101: =+CR101/CW101-1 -> #DIV/0! | DE101: =(CZ101-DD101)/DD101 -> #DIV/0! | DF101: =(DA101-DD101)/DD101 -> #DIV/0! | DG101: =(DB101-DD101)/DD101 -> #DIV/0! | DH101: =(DC101-DD101)/DD101 -> #DIV/0! | DM101: =(CS101-CZ101)*10^6 -> 0 | DN101: =(CT101-DC101)*10^6 -> 0 | DO101: =(CW101-DD101)*10^6 -> 0
C102: CA95 | CU102: =+CR102-CS102 -> 0 | CV102: =+CR102-CT102 -> 0 | DM102: =(CS102-CZ102)*10^6 -> 0 | DN102: =(CT102-DC102)*10^6 -> 0 | DO102: =(CW102-DD102)*10^6 -> 0
...

Sheet Marge Mobile
A2: Marge brute Mobile | CS2: 25912.891 | CT2: 25481.374 | CW2: 56170.705
E3: 0 | G3: 0 | CZ3: 0 | DD3: 0
D4: 45292 | J4: 45323 | P4: 45352 | V4: 45383 | AD4: 45413 | AL4: 45444 | AU4: 45474 | BC4: 45505 | BK4: 45536 | BT4: 45566 | CB4: 45597 | CJ4: 45627 | CR4: CUMUL | CZ4: ANNUEL
B5: (En Millions ML) | D5: 2024 Réel | E5: 2024 Budget | F5: Ecart / Budget | G5: 2023 Réel | H5: Evol % | J5: 2024 Réel | K5: 2024 Budget | L5: Ecart / Budget | M5: 2023 Réel | N5: Evol % | P5: 2024 Réel | Q5: 2024 Budget | R5: Ecart / Budget | S5: 2023 Réel | T5: Evol % | V5: 2024 Réel | W5: 2024 Budget | X5: 2024 Actu1 | Y5: Ecart / Budget | Z5: Ecart / Actu1 | AA5: 2023 Réel | AB5: Evol % | AD5: 2024 Réel | AE5: 2024 Budget | AF5: 2024 Actu1 | AG5: Ecart / Budget | AH5: Ecart / Actu1 | AI5: 2023 Réel | AJ5: Evol % | AL5: 2024 Réel | AM5: 2024 Budget | AN5: 2024 Actu1 | AO5: 2024 Actu2 | AP5: Ecart / Budget | AQ5: Ecart / Actu1 | AR5: 2023 Réel | AS5: Evol % | AU5: 2024 Réel | AV5: 2024 Budget | AW5: 2024 Actu2 | AX5: Ecart / Budget | AY5: Ecart / Actu2 | AZ5: 2023 Réel | BA5: Evol % | BC5: 2024 Réel | BD5: 2024 Budget | BE5: 2024 Actu2 | BF5: Ecart / Budget | BG5: Ecart / Actu2 | BH5: 2023 Réel | BI5: Evol % | BK5: 2024 Réel | BL5: 2024 Budget | BM5: 2024 Actu2 | BN5: 2024 Actu3 | BO5: Ecart / Budget | BP5: Ecart / Actu2 | BQ5: 2023 Réel | BR5: Evol % | BT5: 2024 Réel | BU5: 2024 Budget | BV5: 2024 Actu3 | BW5: Ecart / Budget | BX5: Ecart / Actu3 | BY5: 2023 Réel | BZ5: Evol % | CB5: 2024 Réel | CC5: 2024 Budget | CD5: 2024 Actu3 | CE5: Ecart / Budget | CF5: Ecart / Actu3 | CG5: 2023 Réel | CH5: Evol % | CJ5: 2024 Réel | CK5: 2024 Budget | CL5: 2024 Actu3 | CM5: Ecart / Budget | CN5: Ecart / Actu3 | CO5: 2023 Réel | CP5: Evol % | CR5: 2024 Réel | CS5: 2024 Budget | CT5: 2024 Actu3 | CU5: Ecart / Budget | CV5: Ecart / Actu3 | CW5: 2023 Réel | CX5: Evol % | CZ5: 2024 Budget | DA5: 2024 Actu1 | DB5: 2024 Actu2 | DC5: 2024 Actu3 | DD5: 2023 Réel | DE5: Bud / 2023 (%) | DF5: Actu 1 / 2023 (%) | DG5: Actu 2 / 2023 (%) | DH5: Actu3 / 2023 (%) | DJ5: 2024 Réel | DK5: 2024 Budget | DL5: 2023 Réel | DM5: Actu
DJ6: =SUM(D6,J6,P6,V6,AD6,AL6,AU6,BC6,BK6,BT6,CB6,CJ6)-CR6 -> 0 | DK6: =SUM(E6,K6,Q6,W6,AE6,AM6,AV6,BD6,BL6,BU6,CC6,CK6)-CS6 -> 0 | DL6: =SUM(G6,M6,S6,AA6,AI6,AR6,AZ6,BH6,BQ6,BY6,CG6,CO6)-CW6 -> 0 | DM6: =SUM(D6,J6,P6,V6,AD6,AL6,AU6,BC6,,BN6,BV6,CD6,CL6)-CT6 -> 0
A7: Total Revenu | C7: MB1 | CU7: =+CR7-CS7 -> 0 | CV7: =+CR7-CT7 -> 0 | CX7: =IFERROR(CR7/CW7-1, "-") -> - | DE7: =CZ7/DD7-1 -> #DIV/0! | DF7: =DA7/DD7-1 -> #DIV/0! | DG7: =DB7/DD7-1 -> #DIV/0! | DH7: =DC7/DD7-1 -> #DIV/0! | DJ7: =SUM(D7,J7,P7,V7,AD7,AL7,AU7,BC7,BK7,BT7,CB7,CJ7)-CR7 -> 0 | DK7: =SUM(E7,K7,Q7,W7,AE7,AM7,AV7,BD7,BL7,BU7,CC7,CK7)-CS7 -> 0 | DL7: =SUM(G7,M7,S7,AA7,AI7,AR7,AZ7,BH7,BQ7,BY7,CG7,CO7)-CW7 -> 0 | DM7: =SUM(D7,J7,P7,V7,AD7,AL7,AU7,BC7,,BN7,BV7,CD7,CL7)-CT7 -> 0
B8: Trafic (mn) | C8: MB2 | CU8: =+CR8-CS8 -> 0 | CV8: =+CR8-CT8 -> 0 | CX8: =IFERROR(CR8/CW8-1, "-") -> - | DE8: =CZ8/DD8-1 -> #DIV/0! | DF8: =DA8/DD8-1 -> #DIV/0! | DG8: =DB8/DD8-1 -> #DIV/0! | DH8: =DC8/DD8-1 -> #DIV/0! | DJ8: =SUM(D8,J8,P8,V8,AD8,AL8,AU8,BC8,BK8,BT8,CB8,CJ8)-CR8 -> 0 | DK8: =SUM(E8,K8,Q8,W8,AE8,AM8,AV8,BD8,BL8,BU8,CC8,CK8)-CS8 -> 0 | DL8: =SUM(G8,M8,S8,AA8,AI8,AR8,AZ8,BH8,BQ8,BY8,CG8,CO8)-CW8 -> 0 | DM8: =SUM(D8,J8,P8,V8,AD8,AL8,AU8,BC8,,BN8,BV8,CD8,CL8)-CT8 -> 0 | DX8: =CS8-CZ8 -> 0 | DY8: =CT8-DC8 -> 0 | DZ8: =CW8-DD8 -> 0
B9: Coût unitaire | C9: MB3 | CU9: =+CR9-CS9 -> 0 | CV9: =+CR9-CT9 -> 0 | CX9: =IFERROR(CR9/CW9-1, "-") -> - | DE9: =CZ9/DD9-1 -> #DIV/0! | DF9: =DA9/DD9-1 -> #DIV/0! | DG9: =DB9/DD9-1 -> #DIV/0! | DH9: =DC9/DD9-1 -> #DIV/0! | DJ9: =SUM(D9,J9,P9,V9,AD9,AL9,AU9,BC9,BK9,BT9,CB9,CJ9)-CR9 -> 0 | DK9: =SUM(E9,K9,Q9,W9,AE9,AM9,AV9,BD9,BL9,BU9,CC9,CK9)-CS9 -> 0 | DL9: =SUM(G9,M9,S9,AA9,AI9,AR9,AZ9,BH9,BQ9,BY9,CG9,CO9)-CW9 -> 0 | DM9: =SUM(D9,J9,P9,V9,AD9,AL9,AU9,BC9,,BN9,BV9,CD9,CL9)-CT9 -> 0 | DX9: =(CS9-CZ9)*10^6 -> 0 | DY9: =(CT9-DC9)*10^6 -> 0 | DZ9: =(CW9-DD9)*10^6 -> 0
B10: International | C10: MB4 | CU10: =+CR10-CS10 -> 0 | CV10: =+CR10-CT10 -> 0 | CX10: =IFERROR(CR10/CW10-1, "-") -> - | DE10: =CZ10/DD10-1 -> #DIV/0! | DF10: =DA10/DD10-1 -> #DIV/0! | DG10: =DB10/DD10-1 -> #DIV/0! | DH10: =DC10/DD10-1 -> #DIV/0! | DJ10: =SUM(D10,J10,P10,V10,AD10,AL10,AU10,BC10,BK10,BT10,CB10,CJ10)-CR10 -> 0 | DK10: =SUM(E10,K10,Q10,W10,AE10,AM10,AV10,BD10,BL10,BU10,CC10,CK10)-CS10 -> 0 | DL10: =SUM(G10,M10,S10,AA10,AI10,AR10,AZ10,BH10,BQ10,BY10,CG10,CO10)-CW10 -> 0 | DM10: =SUM(D10,J10,P10,V10,AD10,AL10,AU10,BC10,,BN10,BV10,CD10,CL10)-CT10 -> 0 | DX10: =(CS10-CZ10)*10^6 -> 0 | DY10: =(CT10-DC10)*10^6 -> 0 | DZ10: =(CW10-DD10)*10^6 -> 0
B11: Trafic (mn) | C11: MB5 | CU11: =+CR11-CS11 -> 0 | CV11: =+CR11-CT11 -> 0 | CX11: =IFERROR(CR11/CW11-1, "-") -> - | DJ11: =SUM(D11,J11,P11,V11,AD11,AL11,AU11,BC11,BK11,BT11,CB11,CJ11)-CR11 -> 0 | DK11: =SUM(E11,K11,Q11,W11,AE11,AM11,AV11,BD11,BL11,BU11,CC11,CK11)-CS11 -> 0 | DL11: =SUM(G11,M11,S11,AA11,AI11,AR11,AZ11,BH11,BQ11,BY11,CG11,CO11)-CW11 -> 0 | DM11: =SUM(D11,J11,P11,V11,AD11,AL11,AU11,BC11,,BN11,BV11,CD11,CL11)-CT11 -> 0 | DX11: =(CS11-CZ11)*10^6 -> 0 | DY11: =(CT11-DC11)*10^6 -> 0 | DZ11: =(CW11-DD11)*10^6 -> 0
B12: Coût unitaire | C12: MB6 | CU12: =+CR12-CS12 -> 0 | CV12: =+CR12-CT12 -> 0 | CX12: =IFERROR(CR12/CW12-1, "-") -> - | DJ12: =SUM(D12,J12,P12,V12,AD12,AL12,AU12,BC12,BK12,BT12,CB12,CJ12)-CR12 -> 0 | DK12: =SUM(E12,K12,Q12,W12,AE12,AM12,AV12,BD12,BL12,BU12,CC12,CK12)-CS12 -> 0 | DL12: =SUM(G12,M12,S12,AA12,AI12,AR12,AZ12,BH12,BQ12,BY12,CG12,CO12)-CW12 -> 0 | DM12: =SUM(D12,J12,P12,V12,AD12,AL12,AU12,BC12,,BN12,BV12,CD12,CL12)-CT12 -> 0 | DX12: =(CS12-CZ12)*10^6 -> 0 | DY12: =(CT12-DC12)*10^6 -> 0 | DZ12: =(CW12-DD12)*10^6 -> 0
B13: Transit Sortant International depuis les concurents | C13: MB7 | CU13: =+CR13-CS13 -> 0 | CV13: =+CR13-CT13 -> 0 | CX13: =IFERROR(CR13/CW13-1, "-") -> - | DJ13: =SUM(D13,J13,P13,V13,AD13,AL13,AU13,BC13,BK13,BT13,CB13,CJ13)-CR13 -> 0 | DK13: =SUM(E13,K13,Q13,W13,AE13,AM13,AV13,BD13,BL13,BU13,CC13,CK13)-CS13 -> 0 | DL13: =SUM(G13,M13,S13,AA13,AI13,AR13,AZ13,BH13,BQ13,BY13,CG13,CO13)-CW13 -> 0 | DM13: =SUM(D13,J13,P13,V13,AD13,AL13,AU13,BC13,,BN13,BV13,CD13,CL13)-CT13 -> 0 | DX13: =(CS13-CZ13)*10^6 -> 0 | DY13: =(CT13-DC13)*10^6 -> 0 | DZ13: =(CW13-DD13)*10^6 -> 0
B14: Trafic (mn) | C14: MB8 | CU14: =+CR14-CS14 -> 0 | CV14: =+CR14-CT14 -> 0 | CX14: =IFERROR(CR14/CW14-1, "-") -> - | DJ14: =SUM(D14,J14,P14,V14,AD14,AL14,AU14,BC14,BK14,BT14,CB14,CJ14)-CR14 -> 0 | DK14: =SUM(E14,K14,Q14,W14,AE14,AM14,AV14,BD14,BL14,BU14,CC14,CK14)-CS14 -> 0 | DL14: =SUM(G14,M14,S14,AA14,AI14,AR14,AZ14,BH14,BQ14,BY14,CG14,CO14)-CW14 -> 0 | DM14: =SUM(D14,J14,P14,V14,AD14,AL14,AU14,BC14,,BN14,BV14,CD14,CL14)-CT14 -> 0 | DX14: =(CS14-CZ14)*10^6 -> 0 | DY14: =(CT14-DC14)*10^6 -> 0 | DZ14: =(CW14-DD14)*10^6 -> 0
B15: Coût unitaire | C15: MB9 | CU15: =+CR15-CS15 -> 0 | CV15: =+CR15-CT15 -> 0 | CX15: =IFERROR(CR15/CW15-1, "-") -> - | DE15: =CZ15/DD15-1 -> #DIV/0! | DF15: =DA15/DD15-1 -> #DIV/0! | DG15: =DB15/DD15-1 -> #DIV/0! | DH15: =DC15/DD15-1 -> #DIV/0! | DJ15: =SUM(D15,J15,P15,V15,AD15,AL15,AU15,BC15,BK15,BT15,CB15,CJ15)-CR15 -> 0 | DK15: =SUM(E15,K15,Q15,W15,AE15,AM15,AV15,BD15,BL15,BU15,CC15,CK15)-CS15 -> 0 | DL15: =SUM(G15,M15,S15,AA15,AI15,AR15,AZ15,BH15,BQ15,BY15,CG15,CO15)-CW15 -> 0 | DM15: =SUM(D15,J15,P15,V15,AD15,AL15,AU15,BC15,,BN15,BV15,CD15,CL15)-CT15 -> 0 | DX15: =(CS15-CZ15)*10^6 -> 0 | DY15: =(CT15-DC15)*10^6 -> 0 | DZ15: =(CW15-DD15)*10^6 -> 0
B16: Opérateur national MTN | C16: MB10 | CU16: =+CR16-CS16 -> 0 | CV16: =+CR16-CT16 -> 0 | CX16: =IFERROR(CR16/CW16-1, "-") -> - | DE16: =CZ16/DD16-1 -> #DIV/0! | DF16: =DA16/DD16-1 -> #DIV/0! | DG16: =DB16/DD16-1 -> #DIV/0! | DH16: =DC16/DD16-1 -> #DIV/0! | DJ16: =SUM(D16,J16,P16,V16,AD16,AL16,AU16,BC16,BK16,BT16,CB16,CJ16)-CR16 -> 0 | DK16: =SUM(E16,K16,Q16,W16,AE16,AM16,AV16,BD16,BL16,BU16,CC16,CK16)-CS16 -> 0 | DL16: =SUM(G16,M16,S16,AA16,AI16,AR16,AZ16,BH16,BQ16,BY16,CG16,CO16)-CW16 -> 0 | DM16: =SUM(D16,J16,P16,V16,AD16,AL16,AU16,BC16,,BN16,BV16,CD16,CL16)-CT16 -> 0 | DX16: =(CS16-CZ16)*10^6 -> 0 | DY16: =(CT16-DC16)*10^6 -> 0 | DZ16: =(CW16-DD16)*10^6 -> 0
B17: Trafic (mn) | C17: MB11 | CU17: =+CR17-CS17 -> 0 | CV17: =+CR17-CT17 -> 0 | CX17: =IFERROR(CR17/CW17-1, "-") -> - | DJ17: =SUM(D17,J17,P17,V17,AD17,AL17,AU17,BC17,BK17,BT17,CB17,CJ17)-CR17 -> 0 | DK17: =SUM(E17,K17,Q17,W17,AE17,AM17,AV17,BD17,BL17,BU17,CC17,CK17)-CS17 -> 0 | DL17: =SUM(G17,M17,S17,AA17,AI17,AR17,AZ17,BH17,BQ17,BY17,CG17,CO17)-CW17 -> 0 | DM17: =SUM(D17,J17,P17,V17,AD17,AL17,AU17,BC17,,BN17,BV17,CD17,CL17)-CT17 -> 0 | DX17: =(CS17-CZ17)*10^6 -> 0 | DY17: =(CT17-DC17)*10^6 -> 0 | DZ17: =(CW17-DD17)*10^6 -> 0
B18: Coût unitaire | C18: MB12 | CU18: =+CR18-CS18 -> 0 | CV18: =+CR18-CT18 -> 0 | CX18: =IFERROR(CR18/CW18-1, "-") -> - | DJ18: =SUM(D18,J18,P18,V18,AD18,AL18,AU18,BC18,BK18,BT18,CB18,CJ18)-CR18 -> 0 | DK18: =SUM(E18,K18,Q18,W18,AE18,AM18,AV18,BD18,BL18,BU18,CC18,CK18)-CS18 -> 0 | DL18: =SUM(G18,M18,S18,AA18,AI18,AR18,AZ18,BH18,BQ18,BY18,CG18,CO18)-CW18 -> 0 | DM18: =SUM(D18,J18,P18,V18,AD18,AL18,AU18,BC18,,BN18,BV18,CD18,CL18)-CT18 -> 0 | DX18: =(CS18-CZ18)*10^6 -> 0 | DY18: =(CT18-DC18)*10^6 -> 0 | DZ18: =(CW18-DD18)*10^6 -> 0
B19: Opérateur national ORANGE | C19: MB13 | CU19: =+CR19-CS19 -> 0 | CV19: =+CR19-CT19 -> 0 | CX19: =IFERROR(CR19/CW19-1, "-") -> - | DJ19: =SUM(D19,J19,P19,V19,AD19,AL19,AU19,BC19,BK19,BT19,CB19,CJ19)-CR19 -> 0 | DK19: =SUM(E19,K19,Q19,W19,AE19,AM19,AV19,BD19,BL19,BU19,CC19,CK19)-CS19 -> 0 | DL19: =SUM(G19,M19,S19,AA19,AI19,AR19,AZ19,BH19,BQ19,BY19,CG19,CO19)-CW19 -> 0 | DM19: =SUM(D19,J19,P19,V19,AD19,AL19,AU19,BC19,,BN19,BV19,CD19,CL19)-CT19 -> 0 | DX19: =(CS19-CZ19)*10^6 -> 0 | DY19: =(CT19-DC19)*10^6 -> 0 | DZ19: =(CW19-DD19)*10^6 -> 0
B20: Trafic (mn) | C20: MB14 | CU20: =+CR20-CS20 -> 0 | CV20: =+CR20-CT20 -> 0 | CX20: =IFERROR(CR20/CW20-1, "-") -> - | DJ20: =SUM(D20,J20,P20,V20,AD20,AL20,AU20,BC20,BK20,BT20,CB20,CJ20)-CR20 -> 0 | DK20: =SUM(E20,K20,Q20,W20,AE20,AM20,AV20,BD20,BL20,BU20,CC20,CK20)-CS20 -> 0 | DL20: =SUM(G20,M20,S20,AA20,AI20,AR20,AZ20,BH20,BQ20,BY20,CG20,CO20)-CW20 -> 0 | DM20: =SUM(D20,J20,P20,V20,AD20,AL20,AU20,BC20,,BN20,BV20,CD20,CL20)-CT20 -> 0 | DX20: =(CS20-CZ20)*10^6 -> 0 | DY20: =(CT20-DC20)*10^6 -> 0 | DZ20: =(CW20-DD20)*10^6 -> 0
B21: Coût unitaire | C21: MB15 | CU21: =+CR21-CS21 -> 0 | CV21: =+CR21-CT21 -> 0 | CX21: =IFERROR(CR21/CW21-1, "-") -> - | DJ21: =SUM(D21,J21,P21,V21,AD21,AL21,AU21,BC21,BK21,BT21,CB21,CJ21)-CR21 -> 0 | DK21: =SUM(E21,K21,Q21,W21,AE21,AM21,AV21,BD21,BL21,BU21,CC21,CK21)-CS21 -> 0 | DL21: =SUM(G21,M21,S21,AA21,AI21,AR21,AZ21,BH21,BQ21,BY21,CG21,CO21)-CW21 -> 0 | DM21: =SUM(D21,J21,P21,V21,AD21,AL21,AU21,BC21,,BN21,BV21,CD21,CL21)-CT21 -> 0 | DX21: =(CS21-CZ21)*10^6 -> 0 | DY21: =(CT21-DC21)*10^6 -> 0 | DZ21: =(CW21-DD21)*10^6 -> 0
B22: Opérateur national AUTRES MOBILES | C22: MB16 | CU22: =+CR22-CS22 -> 0 | CV22: =+CR22-CT22 -> 0 | CX22: =IFERROR(CR22/CW22-1, "-") -> - | DJ22: =SUM(D22,J22,P22,V22,AD22,AL22,AU22,BC22,BK22,BT22,CB22,CJ22)-CR22 -> 0 | DK22: =SUM(E22,K22,Q22,W22,AE22,AM22,AV22,BD22,BL22,BU22,CC22,CK22)-CS22 -> 0 | DL22: =SUM(G22,M22,S22,AA22,AI22,AR22,AZ22,BH22,BQ22,BY22,CG22,CO22)-CW22 -> 0 | DM22: =SUM(D22,J22,P22,V22,AD22,AL22,AU22,BC22,,BN22,BV22,CD22,CL22)-CT22 -> 0 | DX22: =(CS22-CZ22)*10^6 -> 0 | DY22: =(CT22-DC22)*10^6 -> 0 | DZ22: =(CW22-DD22)*10^6 -> 0
B23: Trafic (mn) | C23: MB17 | CU23: =+CR23-CS23 -> 0 | CV23: =+CR23-CT23 -> 0 | CX23: =IFERROR(CR23/CW23-1, "-") -> - | DJ23: =SUM(D23,J23,P23,V23,AD23,AL23,AU23,BC23,BK23,BT23,CB23,CJ23)-CR23 -> 0 | DK23: =SUM(E23,K23,Q23,W23,AE23,AM23,AV23,BD23,BL23,BU23,CC23,CK23)-CS23 -> 0 | DL23: =SUM(G23,M23,S23,AA23,AI23,AR23,AZ23,BH23,BQ23,BY23,CG23,CO23)-CW23 -> 0 | DM23: =SUM(D23,J23,P23,V23,AD23,AL23,AU23,BC23,,BN23,BV23,CD23,CL23)-CT23 -> 0 | DX23: =(CS23-CZ23)*10^6 -> 0 | DY23: =(CT23-DC23)*10^6 -> 0 | DZ23: =(CW23-DD23)*10^6 -> 0
B24: Coût unitaire | C24: MB18 | CU24: =+CR24-CS24 -> 0 | CV24: =+CR24-CT24 -> 0 | CX24: =IFERROR(CR24/CW24-1, "-") -> - | DJ24: =SUM(D24,J24,P24,V24,AD24,AL24,AU24,BC24,BK24,BT24,CB24,CJ24)-CR24 -> 0 | DK24: =SUM(E24,K24,Q24,W24,AE24,AM24,AV24,BD24,BL24,BU24,CC24,CK24)-CS24 -> 0 | DL24: =SUM(G24,M24,S24,AA24,AI24,AR24,AZ24,BH24,BQ24,BY24,CG24,CO24)-CW24 -> 0 | DM24: =SUM(D24,J24,P24,V24,AD24,AL24,AU24,BC24,,BN24,BV24,CD24,CL24)-CT24 -> 0 | DX24: =(CS24-CZ24)*10^6 -> 0 | DY24: =(CT24-DC24)*10^6 -> 0 | DZ24: =(CW24-DD24)*10^6 -> 0
B25: Opérateur national 2 (glo) | C25: MB19 | CU25: =+CR25-CS25 -> 0 | CV25: =+CR25-CT25 -> 0 | CX25: =IFERROR(CR25/CW25-1, "-") -> - | DJ25: =SUM(D25,J25,P25,V25,AD25,AL25,AU25,BC25,BK25,BT25,CB25,CJ25)-CR25 -> 0 | DK25: =SUM(E25,K25,Q25,W25,AE25,AM25,AV25,BD25,BL25,BU25,CC25,CK25)-CS25 -> 0 | DL25: =SUM(G25,M25,S25,AA25,AI25,AR25,AZ25,BH25,BQ25,BY25,CG25,CO25)-CW25 -> 0 | DM25: =SUM(D25,J25,P25,V25,AD25,AL25,AU25,BC25,,BN25,BV25,CD25,CL25)-CT25 -> 0 | DX25: =(CS25-CZ25)*10^6 -> 0 | DY25: =(CT25-DC25)*10^6 -> 0 | DZ25: =(CW25-DD25)*10^6 -> 0
B26: Trafic (mn) | C26: MB20 | CU26: =+CR26-CS26 -> 0 | CV26: =+CR26-CT26 -> 0 | CX26: =IFERROR(CR26/CW26-1, "-") -> - | DE26: =CZ26/DD26-1 -> #DIV/0! | DF26: =DA26/DD26-1 -> #DIV/0! | DG26: =DB26/DD26-1 -> #DIV/0! | DH26: =DC26/DD26-1 -> #DIV/0! | DJ26: =SUM(D26,J26,P26,V26,AD26,AL26,AU26,BC26,BK26,BT26,CB26,CJ26)-CR26 -> 0 | DK26: =SUM(E26,K26,Q26,W26,AE26,AM26,AV26,BD26,BL26,BU26,CC26,CK26)-CS26 -> 0 | DL26: =SUM(G26,M26,S26,AA26,AI26,AR26,AZ26,BH26,BQ26,BY26,CG26,CO26)-CW26 -> 0 | DM26: =SUM(D26,J26,P26,V26,AD26,AL26,AU26,BC26,,BN26,BV26,CD26,CL26)-CT26 -> 0 | DX26: =(CS26-CZ26)*10^6 -> 0 | DY26: =(CT26-DC26)*10^6 -> 0 | DZ26: =(CW26-DD26)*10^6 -> 0
B27: Coût unitaire | C27: MB21 | CU27: =+CR27-CS27 -> 0 | CV27: =+CR27-CT27 -> 0 | CX27: =IFERROR(CR27/CW27-1, "-") -> - | DE27: =CZ27/DD27-1 -> #DIV/0! | DF27: =DA27/DD27-1 -> #DIV/0! | DG27: =DB27/DD27-1 -> #DIV/0! | DH27: =DC27/DD27-1 -> #DIV/0! | DJ27: =SUM(D27,J27,P27,V27,AD27,AL27,AU27,BC27,BK27,BT27,CB27,CJ27)-CR27 -> 0 | DK27: =SUM(E27,K27,Q27,W27,AE27,AM27,AV27,BD27,BL27,BU27,CC27,CK27)-CS27 -> 0 | DL27: =SUM(G27,M27,S27,AA27,AI27,AR27,AZ27,BH27,BQ27,BY27,CG27,CO27)-CW27 -> 0 | DM27: =SUM(D27,J27,P27,V27,AD27,AL27,AU27,BC27,,BN27,BV27,CD27,CL27)-CT27 -> 0 | DX27: =(CS27-CZ27)*10^6 -> 0 | DY27: =(CT27-DC27)*10^6 -> 0 | DZ27: =(CW27-DD27)*10^6 -> 0
B28: Opérateur national 3 (bbcom, libercom & btsa) | C28: MB22 | CU28: =+CR28-CS28 -> 0 | CV28: =+CR28-CT28 -> 0 | CX28: =IFERROR(CR28/CW28-1, "-") -> - | DE28: =CZ28/DD28-1 -> #DIV/0! | DF28: =DA28/DD28-1 -> #DIV/0! | DG28: =DB28/DD28-1 -> #DIV/0! | DH28: =DC28/DD28-1 -> #DIV/0! | DJ28: =SUM(D28,J28,P28,V28,AD28,AL28,AU28,BC28,BK28,BT28,CB28,CJ28)-CR28 -> 0 | DK28: =SUM(E28,K28,Q28,W28,AE28,AM28,AV28,BD28,BL28,BU28,CC28,CK28)-CS28 -> 0 | DL28: =SUM(G28,M28,S28,AA28,AI28,AR28,AZ28,BH28,BQ28,BY28,CG28,CO28)-CW28 -> 0 | DM28: =SUM(D28,J28,P28,V28,AD28,AL28,AU28,BC28,,BN28,BV28,CD28,CL28)-CT28 -> 0 | DX28: =(CS28-CZ28)*10^6 -> 0 | DY28: =(CT28-DC28)*10^6 -> 0 | DZ28: =(CW28-DD28)*10^6 -> 0
B29: Trafic Local (mn) | C29: MB23 | CU29: =+CR29-CS29 -> 0 | CV29: =+CR29-CT29 -> 0 | CX29: =IFERROR(CR29/CW29-1, "-") -> - | DJ29: =SUM(D29,J29,P29,V29,AD29,AL29,AU29,BC29,BK29,BT29,CB29,CJ29)-CR29 -> 0 | DK29: =SUM(E29,K29,Q29,W29,AE29,AM29,AV29,BD29,BL29,BU29,CC29,CK29)-CS29 -> 0 | DL29: =SUM(G29,M29,S29,AA29,AI29,AR29,AZ29,BH29,BQ29,BY29,CG29,CO29)-CW29 -> 0 | DM29: =SUM(D29,J29,P29,V29,AD29,AL29,AU29,BC29,,BN29,BV29,CD29,CL29)-CT29 -> 0 | DX29: =(CS29-CZ29)*10^6 -> 0 | DY29: =(CT29-DC29)*10^6 -> 0 | DZ29: =(CW29-DD29)*10^6 -> 0
B30: Coût unitaire | C30: MB24 | CU30: =+CR30-CS30 -> 0 | CV30: =+CR30-CT30 -> 0 | CX30: =IFERROR(CR30/CW30-1, "-") -> - | DJ30: =SUM(D30,J30,P30,V30,AD30,AL30,AU30,BC30,BK30,BT30,CB30,CJ30)-CR30 -> 0 | DK30: =SUM(E30,K30,Q30,W30,AE30,AM30,AV30,BD30,BL30,BU30,CC30,CK30)-CS30 -> 0 | DL30: =SUM(G30,M30,S30,AA30,AI30,AR30,AZ30,BH30,BQ30,BY30,CG30,CO30)-CW30 -> 0 | DM30: =SUM(D30,J30,P30,V30,AD30,AL30,AU30,BC30,,BN30,BV30,CD30,CL30)-CT30 -> 0 | DX30: =(CS30-CZ30)*10^6 -> 0 | DY30: =(CT30-DC30)*10^6 -> 0 | DZ30: =(CW30-DD30)*10^6 -> 0
B31: Trafic Interurbain (mn) | C31: MB25 | CU31: =+CR31-CS31 -> 0 | CV31: =+CR31-CT31 -> 0 | CX31: =IFERROR(CR31/CW31-1, "-") -> - | DJ31: =SUM(D31,J31,P31,V31,AD31,AL31,AU31,BC31,BK31,BT31,CB31,CJ31)-CR31 -> 0 | DK31: =SUM(E31,K31,Q31,W31,AE31,AM31,AV31,BD31,BL31,BU31,CC31,CK31)-CS31 -> 0 | DL31: =SUM(G31,M31,S31,AA31,AI31,AR31,AZ31,BH31,BQ31,BY31,CG31,CO31)-CW31 -> 0 | DM31: =SUM(D31,J31,P31,V31,AD31,AL31,AU31,BC31,,BN31,BV31,CD31,CL31)-CT31 -> 0 | DX31: =(CS31-CZ31)*10^6 -> 0 | DY31: =(CT31-DC31)*10^6 -> 0 | DZ31: =(CW31-DD31)*10^6 -> 0
B32: Coût unitaire | C32: MB26 | CU32: =+CR32-CS32 -> 0 | CV32: =+CR32-CT32 -> 0 | CX32: =IFERROR(CR32/CW32-1, "-") -> - | DJ32: =SUM(D32,J32,P32,V32,AD32,AL32,AU32,BC32,BK32,BT32,CB32,CJ32)-CR32 -> 0 | DK32: =SUM(E32,K32,Q32,W32,AE32,AM32,AV32,BD32,BL32,BU32,CC32,CK32)-CS32 -> 0 | DL32: =SUM(G32,M32,S32,AA32,AI32,AR32,AZ32,BH32,BQ32,BY32,CG32,CO32)-CW32 -> 0 | DM32: =SUM(D32,J32,P32,V32,AD32,AL32,AU32,BC32,,BN32,BV32,CD32,CL32)-CT32 -> 0 | DX32: =(CS32-CZ32)*10^6 -> 0 | DY32: =(CT32-DC32)*10^6 -> 0 | DZ32: =(CW32-DD32)*10^6 -> 0
B33: Trafic Local (mn) | C33: MB27 | CU33: =+CR33-CS33 -> 0 | CV33: =+CR33-CT33 -> 0 | CX33: =IFERROR(CR33/CW33-1, "-") -> - | DJ33: =SUM(D33,J33,P33,V33,AD33,AL33,AU33,BC33,BK33,BT33,CB33,CJ33)-CR33 -> 0 | DK33: =SUM(E33,K33,Q33,W33,AE33,AM33,AV33,BD33,BL33,BU33,CC33,CK33)-CS33 -> 0 | DL33: =SUM(G33,M33,S33,AA33,AI33,AR33,AZ33,BH33,BQ33,BY33,CG33,CO33)-CW33 -> 0 | DM33: =SUM(D33,J33,P33,V33,AD33,AL33,AU33,BC33,,BN33,BV33,CD33,CL33)-CT33 -> 0 | DX33: =(CS33-CZ33)*10^6 -> 0 | DY33: =(CT33-DC33)*10^6 -> 0 | DZ33: =(CW33-DD33)*10^6 -> 0
B34: Coût unitaire | C34: MB28 | CU34: =+CR34-CS34 -> 0 | CV34: =+CR34-CT34 -> 0 | CX34: =IFERROR(CR34/CW34-1, "-") -> - | DJ34: =SUM(D34,J34,P34,V34,AD34,AL34,AU34,BC34,BK34,BT34,CB34,CJ34)-CR34 -> 0 | DK34: =SUM(E34,K34,Q34,W34,AE34,AM34,AV34,BD34,BL34,BU34,CC34,CK34)-CS34 -> 0 | DL34: =SUM(G34,M34,S34,AA34,AI34,AR34,AZ34,BH34,BQ34,BY34,CG34,CO34)-CW34 -> 0 | DM34: =SUM(D34,J34,P34,V34,AD34,AL34,AU34,BC34,,BN34,BV34,CD34,CL34)-CT34 -> 0 | DX34: =(CS34-CZ34)*10^6 -> 0 | DY34: =(CT34-DC34)*10^6 -> 0 | DZ34: =(CW34-DD34)*10^6 -> 0
B35: Trafic Interurbain (mn) | C35: MB29 | CU35: =+CR35-CS35 -> 0 | CV35: =+CR35-CT35 -> 0 | CX35: =IFERROR(CR35/CW35-1, "-") -> - | DJ35: =SUM(D35,J35,P35,V35,AD35,AL35,AU35,BC35,BK35,BT35,CB35,CJ35)-CR35 -> 0 | DK35: =SUM(E35,K35,Q35,W35,AE35,AM35,AV35,BD35,BL35,BU35,CC35,CK35)-CS35 -> 0 | DL35: =SUM(G35,M35,S35,AA35,AI35,AR35,AZ35,BH35,BQ35,BY35,CG35,CO35)-CW35 -> 0 | DM35: =SUM(D35,J35,P35,V35,AD35,AL35,AU35,BC35,,BN35,BV35,CD35,CL35)-CT35 -> 0 | DX35: =(CS35-CZ35)*10^6 -> 0 | DY35: =(CT35-DC35)*10^6 -> 0 | DZ35: =(CW35-DD35)*10^6 -> 0
B36: Coût unitaire | C36: MB30 | CU36: =+CR36-CS36 -> 0 | CV36: =+CR36-CT36 -> 0 | CX36: =IFERROR(CR36/CW36-1, "-") -> - | DJ36: =SUM(D36,J36,P36,V36,AD36,AL36,AU36,BC36,BK36,BT36,CB36,CJ36)-CR36 -> 0 | DK36: =SUM(E36,K36,Q36,W36,AE36,AM36,AV36,BD36,BL36,BU36,CC36,CK36)-CS36 -> 0 | DL36: =SUM(G36,M36,S36,AA36,AI36,AR36,AZ36,BH36,BQ36,BY36,CG36,CO36)-CW36 -> 0 | DM36: =SUM(D36,J36,P36,V36,AD36,AL36,AU36,BC36,,BN36,BV36,CD36,CL36)-CT36 -> 0 | DX36: =(CS36-CZ36)*10^6 -> 0 | DY36: =(CT36-DC36)*10^6 -> 0 | DZ36: =(CW36-DD36)*10^6 -> 0
B37: Interconnexion Fixe | C37: MB31 | CU37: =+CR37-CS37 -> 0 | CV37: =+CR37-CT37 -> 0 | CX37: =IFERROR(CR37/CW37-1, "-") -> - | DJ37: =SUM(D37,J37,P37,V37,AD37,AL37,AU37,BC37,BK37,BT37,CB37,CJ37)-CR37 -> 0 | DK37: =SUM(E37,K37,Q37,W37,AE37,AM37,AV37,BD37,BL37,BU37,CC37,CK37)-CS37 -> 0 | DL37: =SUM(G37,M37,S37,AA37,AI37,AR37,AZ37,BH37,BQ37,BY37,CG37,CO37)-CW37 -> 0 | DM37: =SUM(D37,J37,P37,V37,AD37,AL37,AU37,BC37,,BN37,BV37,CD37,CL37)-CT37 -> 0 | DX37: =(CS37-CZ37)*10^6 -> 0 | DY37: =(CT37-DC37)*10^6 -> 0 | DZ37: =(CW37-DD37)*10^6 -> 0
B38: Reversements SVA | C38: MB32 | CU38: =+CR38-CS38 -> 0 | CV38: =+CR38-CT38 -> 0 | CX38: =IFERROR(CR38/CW38-1, "-") -> - | DE38: =CZ38/DD38-1 -> #DIV/0! | DF38: =DA38/DD38-1 -> #DIV/0! | DG38: =DB38/DD38-1 -> #DIV/0! | DH38: =DC38/DD38-1 -> #DIV/0! | DJ38: =SUM(D38,J38,P38,V38,AD38,AL38,AU38,BC38,BK38,BT38,CB38,CJ38)-CR38 -> 0 | DK38: =SUM(E38,K38,Q38,W38,AE38,AM38,AV38,BD38,BL38,BU38,CC38,CK38)-CS38 -> 0 | DL38: =SUM(G38,M38,S38,AA38,AI38,AR38,AZ38,BH38,BQ38,BY38,CG38,CO38)-CW38 -> 0 | DM38: =SUM(D38,J38,P38,V38,AD38,AL38,AU38,BC38,,BN38,BV38,CD38,CL38)-CT38 -> 0 | DX38: =(CS38-CZ38)*10^6 -> 0 | DY38: =(CT38-DC38)*10^6 -> 0 | DZ38: =(CW38-DD38)*10^6 -> 0 | EA38: 203.11059 | EB38: =EA38+CR38 -> 203.11059
B39: Achat de capacité | C39: MB55 | CU39: =+CR39-CS39 -> 0 | CV39: =+CR39-CT39 -> 0 | CX39: =IFERROR(CR39/CW39-1, "-") -> - | DJ39: =SUM(D39,J39,P39,V39,AD39,AL39,AU39,BC39,BK39,BT39,CB39,CJ39)-CR39 -> 0 | DK39: =SUM(E39,K39,Q39,W39,AE39,AM39,AV39,BD39,BL39,BU39,CC39,CK39)-CS39 -> 0 | DL39: =SUM(G39,M39,S39,AA39,AI39,AR39,AZ39,BH39,BQ39,BY39,CG39,CO39)-CW39 -> 0 | DM39: =SUM(D39,J39,P39,V39,AD39,AL39,AU39,BC39,,BN39,BV39,CD39,CL39)-CT39 -> 0 | DX39: =(CS39-CZ39)*10^6 -> 0 | DY39: =(CT39-DC39)*10^6 -> 0 | DZ39: =(CW39-DD39)*10^6 -> 0
B40: Nbre SMS | C40: MB33 | CU40: =+CR40-CS40 -> 0 | CV40: =+CR40-CT40 -> 0 | CX40: =IFERROR(CR40/CW40-1, "-") -> - | DE40: =CZ40/DD40-1 -> #DIV/0! | DF40: =DA40/DD40-1 -> #DIV/0! | DG40: =DB40/DD40-1 -> #DIV/0! | DH40: =DC40/DD40-1 -> #DIV/0! | DJ40: =SUM(D40,J40,P40,V40,AD40,AL40,AU40,BC40,BK40,BT40,CB40,CJ40)-CR40 -> 0 | DK40: =SUM(E40,K40,Q40,W40,AE40,AM40,AV40,BD40,BL40,BU40,CC40,CK40)-CS40 -> 0 | DL40: =SUM(G40,M40,S40,AA40,AI40,AR40,AZ40,BH40,BQ40,BY40,CG40,CO40)-CW40 -> 0 | DM40: =SUM(D40,J40,P40,V40,AD40,AL40,AU40,BC40,,BN40,BV40,CD40,CL40)-CT40 -> 0 | DX40: =(CS40-CZ40)*10^6 -> 0 | DY40: =(CT40-DC40)*10^6 -> 0 | DZ40: =(CW40-DD40)*10^6 -> 0
B41: Coût unitaire | C41: MB34 | CU41: =+CR41-CS41 -> 0 | CV41: =+CR41-CT41 -> 0 | CX41: =IFERROR(CR41/CW41-1, "-") -> - | DE41: =CZ41/DD41-1 -> #DIV/0! | DF41: =DA41/DD41-1 -> #DIV/0! | DG41: =DB41/DD41-1 -> #DIV/0! | DH41: =DC41/DD41-1 -> #DIV/0! | DJ41: =SUM(D41,J41,P41,V41,AD41,AL41,AU41,BC41,BK41,BT41,CB41,CJ41)-CR41 -> 0 | DK41: =SUM(E41,K41,Q41,W41,AE41,AM41,AV41,BD41,BL41,BU41,CC41,CK41)-CS41 -> 0 | DL41: =SUM(G41,M41,S41,AA41,AI41,AR41,AZ41,BH41,BQ41,BY41,CG41,CO41)-CW41 -> 0 | DM41: =SUM(D41,J41,P41,V41,AD41,AL41,AU41,BC41,,BN41,BV41,CD41,CL41)-CT41 -> 0 | DX41: =(CS41-CZ41)*10^6 -> 0 | DY41: =(CT41-DC41)*10^6 -> 0 | DZ41: =(CW41-DD41)*10^6 -> 0
B42: Interconnexion SMS | C42: MB35 | CU42: =+CR42-CS42 -> 0 | CV42: =+CR42-CT42 -> 0 | CX42: =IFERROR(CR42/CW42-1, "-") -> - | DE42: =CZ42/DD42-1 -> #DIV/0! | DF42: =DA42/DD42-1 -> #DIV/0! | DG42: =DB42/DD42-1 -> #DIV/0! | DH42: =DC42/DD42-1 -> #DIV/0! | DJ42: =SUM(D42,J42,P42,V42,AD42,AL42,AU42,BC42,BK42,BT42,CB42,CJ42)-CR42 -> 0 | DK42: =SUM(E42,K42,Q42,W42,AE42,AM42,AV42,BD42,BL42,BU42,CC42,CK42)-CS42 -> 0 | DL42: =SUM(G42,M42,S42,AA42,AI42,AR42,AZ42,BH42,BQ42,BY42,CG42,CO42)-CW42 -> 0 | DM42: =SUM(D42,J42,P42,V42,AD42,AL42,AU42,BC42,,BN42,BV42,CD42,CL42)-CT42 -> 0 | DX42: =(CS42-CZ42)*10^6 -> 0 | DY42: =(CT42-DC42)*10^6 -> 0 | DZ42: =(CW42-DD42)*10^6 -> 0 | EA42: 57.488162 | EB42: =EA42+CR42 -> 57.488162
B43: Roaming out | C43: MB36 | CU43: =+CR43-CS43 -> 0 | CV43: =+CR43-CT43 -> 0 | CX43: =IFERROR(CR43/CW43-1, "-") -> - | DE43: =CZ43/DD43-1 -> #DIV/0! | DF43: =DA43/DD43-1 -> #DIV/0! | DG43: =DB43/DD43-1 -> #DIV/0! | DH43: =DC43/DD43-1 -> #DIV/0! | DJ43: =SUM(D43,J43,P43,V43,AD43,AL43,AU43,BC43,BK43,BT43,CB43,CJ43)-CR43 -> 0 | DK43: =SUM(E43,K43,Q43,W43,AE43,AM43,AV43,BD43,BL43,BU43,CC43,CK43)-CS43 -> 0 | DL43: =SUM(G43,M43,S43,AA43,AI43,AR43,AZ43,BH43,BQ43,BY43,CG43,CO43)-CW43 -> 0 | DM43: =SUM(D43,J43,P43,V43,AD43,AL43,AU43,BC43,,BN43,BV43,CD43,CL43)-CT43 -> 0 | DX43: =(CS43-CZ43)*10^6 -> 0 | DY43: =(CT43-DC43)*10^6 -> 0 | DZ43: =(CW43-DD43)*10^6 -> 0
C44: MB37 | CU44: =+CR44-CS44 -> 0 | CV44: =+CR44-CT44 -> 0 | CX44: =IFERROR(CR44/CW44-1, "-") -> - | DJ44: =SUM(D44,J44,P44,V44,AD44,AL44,AU44,BC44,BK44,BT44,CB44,CJ44)-CR44 -> 0 | DK44: =SUM(E44,K44,Q44,W44,AE44,AM44,AV44,BD44,BL44,BU44,CC44,CK44)-CS44 -> 0 | DL44: =SUM(G44,M44,S44,AA44,AI44,AR44,AZ44,BH44,BQ44,BY44,CG44,CO44)-CW44 -> 0 | DM44: =SUM(D44,J44,P44,V44,AD44,AL44,AU44,BC44,,BN44,BV44,CD44,CL44)-CT44 -> 0 | DX44: =(CS44-CZ44)*10^6 -> 0 | DY44: =(CT44-DC44)*10^6 -> 0 | DZ44: =(CW44-DD44)*10^6 -> 0
B45: Coûts des terminaux et cartes | C45: MB38 | CU45: =+CR45-CS45 -> 0 | CV45: =+CR45-CT45 -> 0 | CX45: =IFERROR(CR45/CW45-1, "-") -> - | DE45: =CZ45/DD45-1 -> #DIV/0! | DF45: =DA45/DD45-1 -> #DIV/0! | DG45: =DB45/DD45-1 -> #DIV/0! | DH45: =DC45/DD45-1 -> #DIV/0! | DJ45: =SUM(D45,J45,P45,V45,AD45,AL45,AU45,BC45,BK45,BT45,CB45,CJ45)-CR45 -> 0 | DK45: =SUM(E45,K45,Q45,W45,AE45,AM45,AV45,BD45,BL45,BU45,CC45,CK45)-CS45 -> 0 | DL45: =SUM(G45,M45,S45,AA45,AI45,AR45,AZ45,BH45,BQ45,BY45,CG45,CO45)-CW45 -> 0 | DM45: =SUM(D45,J45,P45,V45,AD45,AL45,AU45,BC45,,BN45,BV45,CD45,CL45)-CT45 -> 0 | DX45: =(CS45-CZ45)*10^6 -> 0 | DY45: =(CT45-DC45)*10^6 -> 0 | DZ45: =(CW45-DD45)*10^6 -> 0
B46: Dont coût des cartes de recharge vendues & des Kits. | C46: MB39 | CX46: =IFERROR(CR46/CW46-1, "-") -> - | DJ46: =SUM(D46,J46,P46,V46,AD46,AL46,AU46,BC46,BK46,BT46,CB46,CJ46)-CR46 -> 0 | DK46: =SUM(E46,K46,Q46,W46,AE46,AM46,AV46,BD46,BL46,BU46,CC46,CK46)-CS46 -> 0 | DL46: =SUM(G46,M46,S46,AA46,AI46,AR46,AZ46,BH46,BQ46,BY46,CG46,CO46)-CW46 -> 0 | DM46: =SUM(D46,J46,P46,V46,AD46,AL46,AU46,BC46,,BN46,BV46,CD46,CL46)-CT46 -> 0 | DX46: =(CS46-CZ46)*10^6 -> 0 | DY46: =(CT46-DC46)*10^6 -> 0 | DZ46: =(CW46-DD46)*10^6 -> 0
B47: Dont coût des cartes SIM | C47: MB40 | CX47: =IFERROR(CR47/CW47-1, "-") -> - | DJ47: =SUM(D47,J47,P47,V47,AD47,AL47,AU47,BC47,BK47,BT47,CB47,CJ47)-CR47 -> 0 | DK47: =SUM(E47,K47,Q47,W47,AE47,AM47,AV47,BD47,BL47,BU47,CC47,CK47)-CS47 -> 0 | DL47: =SUM(G47,M47,S47,AA47,AI47,AR47,AZ47,BH47,BQ47,BY47,CG47,CO47)-CW47 -> 0 | DM47: =SUM(D47,J47,P47,V47,AD47,AL47,AU47,BC47,,BN47,BV47,CD47,CL47)-CT47 -> 0 | DX47: =(CS47-CZ47)*10^6 -> 0 | DY47: =(CT47-DC47)*10^6 -> 0 | DZ47: =(CW47-DD47)*10^6 -> 0
B48: Dont coût des cartes de recharge vendues | C48: MB41 | CX48: =IFERROR(CR48/CW48-1, "-") -> - | DJ48: =SUM(D48,J48,P48,V48,AD48,AL48,AU48,BC48,BK48,BT48,CB48,CJ48)-CR48 -> 0 | DK48: =SUM(E48,K48,Q48,W48,AE48,AM48,AV48,BD48,BL48,BU48,CC48,CK48)-CS48 -> 0 | DL48: =SUM(G48,M48,S48,AA48,AI48,AR48,AZ48,BH48,BQ48,BY48,CG48,CO48)-CW48 -> 0 | DM48: =SUM(D48,J48,P48,V48,AD48,AL48,AU48,BC48,,BN48,BV48,CD48,CL48)-CT48 -> 0 | DX48: =(CS48-CZ48)*10^6 -> 0 | DY48: =(CT48-DC48)*10^6 -> 0 | DZ48: =(CW48-DD48)*10^6 -> 0
B49: Dont coût des terminaux. | C49: MB42 | CU49: =+CR49-CS49 -> 0 | CV49: =+CR49-CT49 -> 0 | CX49: =IFERROR(CR49/CW49-1, "-") -> - | DE49: =CZ49/DD49-1 -> #DIV/0! | DF49: =DA49/DD49-1 -> #DIV/0! | DG49: =DB49/DD49-1 -> #DIV/0! | DH49: =DC49/DD49-1 -> #DIV/0! | DJ49: =SUM(D49,J49,P49,V49,AD49,AL49,AU49,BC49,BK49,BT49,CB49,CJ49)-CR49 -> 0 | DK49: =SUM(E49,K49,Q49,W49,AE49,AM49,AV49,BD49,BL49,BU49,CC49,CK49)-CS49 -> 0 | DL49: =SUM(G49,M49,S49,AA49,AI49,AR49,AZ49,BH49,BQ49,BY49,CG49,CO49)-CW49 -> 0 | DM49: =SUM(D49,J49,P49,V49,AD49,AL49,AU49,BC49,,BN49,BV49,CD49,CL49)-CT49 -> 0 | DX49: =(CS49-CZ49)*10^6 -> 0 | DY49: =(CT49-DC49)*10^6 -> 0 | DZ49: =(CW49-DD49)*10^6 -> 0
B50: Dont Clé Internet Mobile | C50: MB43 | CX50: =IFERROR(CR50/CW50-1, "-") -> - | DJ50: =SUM(D50,J50,P50,V50,AD50,AL50,AU50,BC50,BK50,BT50,CB50,CJ50)-CR50 -> 0 | DK50: =SUM(E50,K50,Q50,W50,AE50,AM50,AV50,BD50,BL50,BU50,CC50,CK50)-CS50 -> 0 | DL50: =SUM(G50,M50,S50,AA50,AI50,AR50,AZ50,BH50,BQ50,BY50,CG50,CO50)-CW50 -> 0 | DM50: =SUM(D50,J50,P50,V50,AD50,AL50,AU50,BC50,,BN50,BV50,CD50,CL50)-CT50 -> 0 | DX50: =(CS50-CZ50)*10^6 -> 0 | DY50: =(CT50-DC50)*10^6 -> 0 | DZ50: =(CW50-DD50)*10^6 -> 0
B51: Dont provisions sur stocks | C51: MB44 | CU51: =+CR51-CS51 -> 0 | CV51: =+CR51-CT51 -> 0 | CX51: =IFERROR(CR51/CW51-1, "-") -> - | DE51: =CZ51/DD51-1 -> #DIV/0! | DF51: =DA51/DD51-1 -> #DIV/0! | DG51: =DB51/DD51-1 -> #DIV/0! | DH51: =DC51/DD51-1 -> #DIV/0! | DJ51: =SUM(D51,J51,P51,V51,AD51,AL51,AU51,BC51,BK51,BT51,CB51,CJ51)-CR51 -> 0 | DK51: =SUM(E51,K51,Q51,W51,AE51,AM51,AV51,BD51,BL51,BU51,CC51,CK51)-CS51 -> 0 | DL51: =SUM(G51,M51,S51,AA51,AI51,AR51,AZ51,BH51,BQ51,BY51,CG51,CO51)-CW51 -> 0 | DM51: =SUM(D51,J51,P51,V51,AD51,AL51,AU51,BC51,,BN51,BV51,CD51,CL51)-CT51 -> 0 | DX51: =(CS51-CZ51)*10^6 -> 0 | DY51: =(CT51-DC51)*10^6 -> 0 | DZ51: =(CW51-DD51)*10^6 -> 0
B52: Commissions | C52: MB45 | CU52: =+CR52-CS52 -> 0 | CV52: =+CR52-CT52 -> 0 | CX52: =IFERROR(CR52/CW52-1, "-") -> - | DE52: =CZ52/DD52-1 -> #DIV/0! | DF52: =DA52/DD52-1 -> #DIV/0! | DG52: =DB52/DD52-1 -> #DIV/0! | DH52: =DC52/DD52-1 -> #DIV/0! | DJ52: =SUM(D52,J52,P52,V52,AD52,AL52,AU52,BC52,BK52,BT52,CB52,CJ52)-CR52 -> 0 | DK52: =SUM(E52,K52,Q52,W52,AE52,AM52,AV52,BD52,BL52,BU52,CC52,CK52)-CS52 -> 0 | DL52: =SUM(G52,M52,S52,AA52,AI52,AR52,AZ52,BH52,BQ52,BY52,CG52,CO52)-CW52 -> 0 | DM52: =SUM(D52,J52,P52,V52,AD52,AL52,AU52,BC52,,BN52,BV52,CD52,CL52)-CT52 -> 0 | DX52: =(CS52-CZ52)*10^6 -> 0 | DY52: =(CT52-DC52)*10^6 -> 0 | DZ52: =(CW52-DD52)*10^6 -> 0
B53: Dont commissions up-front | C53: MB46 | CU53: =+CR53-CS53 -> 0 | CV53: =+CR53-CT53 -> 0 | CX53: =IFERROR(CR53/CW53-1, "-") -> - | DE53: =CZ53/DD53-1 -> #DIV/0! | DF53: =DA53/DD53-1 -> #DIV/0! | DG53: =DB53/DD53-1 -> #DIV/0! | DH53: =DC53/DD53-1 -> #DIV/0! | DJ53: =SUM(D53,J53,P53,V53,AD53,AL53,AU53,BC53,BK53,BT53,CB53,CJ53)-CR53 -> 0 | DK53: =SUM(E53,K53,Q53,W53,AE53,AM53,AV53,BD53,BL53,BU53,CC53,CK53)-CS53 -> 0 | DL53: =SUM(G53,M53,S53,AA53,AI53,AR53,AZ53,BH53,BQ53,BY53,CG53,CO53)-CW53 -> 0 | DM53: =SUM(D53,J53,P53,V53,AD53,AL53,AU53,BC53,,BN53,BV53,CD53,CL53)-CT53 -> 0 | DX53: =(CS53-CZ53)*10^6 -> 0 | DY53: =(CT53-DC53)*10^6 -> 0 | DZ53: =(CW53-DD53)*10^6 -> 0 | EA53: 289.87426 | EB53: 22.828125
B54: Dont avoirs de performance | C54: MB47 | CU54: =+CR54-CS54 -> 0 | CV54: =+CR54-CT54 -> 0 | CX54: =IFERROR(CR54/CW54-1, "-") -> - | DE54: =CZ54/DD54-1 -> #DIV/0! | DF54: =DA54/DD54-1 -> #DIV/0! | DG54: =DB54/DD54-1 -> #DIV/0! | DH54: =DC54/DD54-1 -> #DIV/0! | DJ54: =SUM(D54,J54,P54,V54,AD54,AL54,AU54,BC54,BK54,BT54,CB54,CJ54)-CR54 -> 0 | DK54: =SUM(E54,K54,Q54,W54,AE54,AM54,AV54,BD54,BL54,BU54,CC54,CK54)-CS54 -> 0 | DL54: =SUM(G54,M54,S54,AA54,AI54,AR54,AZ54,BH54,BQ54,BY54,CG54,CO54)-CW54 -> 0 | DM54: =SUM(D54,J54,P54,V54,AD54,AL54,AU54,BC54,,BN54,BV54,CD54,CL54)-CT54 -> 0 | DX54: =(CS54-CZ54)*10^6 -> 0 | DY54: =(CT54-DC54)*10^6 -> 0 | DZ54: =(CW54-DD54)*10^6 -> 0 | EA54: 6659.8478 | EB54: =EA54+CR54 -> 6659.8478 | EC54: 136.14883
B55: Dont Reversement MAB à MM | C55: MB48 | CU55: =+CR55-CS55 -> 0 | CV55: =+CR55-CT55 -> 0 | CX55: =IFERROR(CR55/CW55-1, "-") -> - | DJ55: =SUM(D55,J55,P55,V55,AD55,AL55,AU55,BC55,BK55,BT55,CB55,CJ55)-CR55 -> 0 | DK55: =SUM(E55,K55,Q55,W55,AE55,AM55,AV55,BD55,BL55,BU55,CC55,CK55)-CS55 -> 0 | DL55: =SUM(G55,M55,S55,AA55,AI55,AR55,AZ55,BH55,BQ55,BY55,CG55,CO55)-CW55 -> 0 | DM55: =SUM(D55,J55,P55,V55,AD55,AL55,AU55,BC55,,BN55,BV55,CD55,CL55)-CT55 -> 0 | DX55: =(CS55-CZ55)*10^6 -> 0 | DY55: =(CT55-DC55)*10^6 -> 0 | DZ55: =(CW55-DD55)*10^6 -> 0
B56: Dont Commissions Flooz | C56: MB49 | CU56: =+CR56-CS56 -> 0 | CV56: =+CR56-CT56 -> 0 | CX56: =IFERROR(CR56/CW56-1, "-") -> - | DE56: =CZ56/DD56-1 -> #DIV/0! | DF56: =DA56/DD56-1 -> #DIV/0! | DG56: =DB56/DD56-1 -> #DIV/0! | DH56: =DC56/DD56-1 -> #DIV/0! | DJ56: =SUM(D56,J56,P56,V56,AD56,AL56,AU56,BC56,BK56,BT56,CB56,CJ56)-CR56 -> 0 | DK56: =SUM(E56,K56,Q56,W56,AE56,AM56,AV56,BD56,BL56,BU56,CC56,CK56)-CS56 -> 0 | DL56: =SUM(G56,M56,S56,AA56,AI56,AR56,AZ56,BH56,BQ56,BY56,CG56,CO56)-CW56 -> 0 | DM56: =SUM(D56,J56,P56,V56,AD56,AL56,AU56,BC56,,BN56,BV56,CD56,CL56)-CT56 -> 0 | DX56: =(CS56-CZ56)*10^6 -> 0 | DY56: =(CT56-DC56)*10^6 -> 0 | DZ56: =(CW56-DD56)*10^6 -> 0 | EA56: 4893.5842 | EB56: =+EA56+CR56 -> 4893.5842 | EC56: 524.67435
C57: MB50 | CX57: =IFERROR(CR57/CW57-1, "-") -> - | DJ57: =SUM(D57,J57,P57,V57,AD57,AL57,AU57,BC57,BK57,BT57,CB57,CJ57)-CR57 -> 0 | DK57: =SUM(E57,K57,Q57,W57,AE57,AM57,AV57,BD57,BL57,BU57,CC57,CK57)-CS57 -> 0 | DL57: =SUM(G57,M57,S57,AA57,AI57,AR57,AZ57,BH57,BQ57,BY57,CG57,CO57)-CW57 -> 0 | DM57: =SUM(D57,J57,P57,V57,AD57,AL57,AU57,BC57,,BN57,BV57,CD57,CL57)-CT57 -> 0 | DX57: =(CS57-CZ57)*10^6 -> 0 | DY57: =(CT57-DC57)*10^6 -> 0 | DZ57: =(CW57-DD57)*10^6 -> 0
A58: Coûts des ventes | C58: MB51 | CU58: =+CR58-CS58 -> 0 | CV58: =+CR58-CT58 -> 0 | CX58: =IFERROR(CR58/CW58-1, "-") -> - | DE58: =CZ58/DD58-1 -> #DIV/0! | DF58: =DA58/DD58-1 -> #DIV/0! | DG58: =DB58/DD58-1 -> #DIV/0! | DH58: =DC58/DD58-1 -> #DIV/0! | DJ58: =SUM(D58,J58,P58,V58,AD58,AL58,AU58,BC58,BK58,BT58,CB58,CJ58)-CR58 -> 0 | DK58: =SUM(E58,K58,Q58,W58,AE58,AM58,AV58,BD58,BL58,BU58,CC58,CK58)-CS58 -> 0 | DL58: =SUM(G58,M58,S58,AA58,AI58,AR58,AZ58,BH58,BQ58,BY58,CG58,CO58)-CW58 -> 0 | DM58: =SUM(D58,J58,P58,V58,AD58,AL58,AU58,BC58,,BN58,BV58,CD58,CL58)-CT58 -> 0 | DX58: =(CS58-CZ58)*10^6 -> 0 | DY58: =(CT58-DC58)*10^6 -> 0 | DZ58: =(CW58-DD58)*10^6 -> 0
C59: MB52 | CU59: =+CR59-CS59 -> 0 | CV59: =+CR59-CT59 -> 0 | CX59: =IFERROR(CR59/CW59-1, "-") -> - | DJ59: =SUM(D59,J59,P59,V59,AD59,AL59,AU59,BC59,BK59,BT59,CB59,CJ59)-CR59 -> 0 | DK59: =SUM(E59,K59,Q59,W59,AE59,AM59,AV59,BD59,BL59,BU59,CC59,CK59)-CS59 -> 0 | DL59: =SUM(G59,M59,S59,AA59,AI59,AR59,AZ59,BH59,BQ59,BY59,CG59,CO59)-CW59 -> 0 | DM59: =SUM(D59,J59,P59,V59,AD59,AL59,AU59,BC59,,BN59,BV59,CD59,CL59)-CT59 -> 0 | DX59: =(CS59-CZ59)*10^6 -> 0 | DY59: =(CT59-DC59)*10^6 -> 0 | DZ59: =(CW59-DD59)*10^6 -> 0
A60: Marge Brute | C60: MB53 | CU60: =+CR60-CS60 -> 0 | CV60: =+CR60-CT60 -> 0 | CX60: =IFERROR(CR60/CW60-1, "-") -> - | DE60: =CZ60/DD60-1 -> #DIV/0! | DF60: =DA60/DD60-1 -> #DIV/0! | DG60: =DB60/DD60-1 -> #DIV/0! | DH60: =DC60/DD60-1 -> #DIV/0! | DJ60: =SUM(D60,J60,P60,V60,AD60,AL60,AU60,BC60,BK60,BT60,CB60,CJ60)-CR60 -> 0 | DK60: =SUM(E60,K60,Q60,W60,AE60,AM60,AV60,BD60,BL60,BU60,CC60,CK60)-CS60 -> 0 | DL60: =SUM(G60,M60,S60,AA60,AI60,AR60,AZ60,BH60,BQ60,BY60,CG60,CO60)-CW60 -> 0 | DM60: =SUM(D60,J60,P60,V60,AD60,AL60,AU60,BC60,,BN60,BV60,CD60,CL60)-CT60 -> 0 | DX60: =(CS60-CZ60)*10^6 -> 0 | DY60: =(CT60-DC60)*10^6 -> 0 | DZ60: =(CW60-DD60)*10^6 -> 0
A61: En % du CA | C61: MB54 | CU61: =(CR61-CS61)*100 -> 0 | CV61: =(CR61-CT61)*100 -> 0 | CX61: =IFERROR(CR61/CW61-1, "-") -> - | DE61: =(+CZ61-DD61)*100 -> 0 | DF61: =(+DA61-DD61)*100 -> 0 | DG61: =(+DB61-DD61)*100 -> 0 | DH61: =(+DC61-DD61)*100 -> 0 | DJ61: =SUM(D61,J61,P61,V61,AD61,AL61,AU61,BC61,BK61,BT61,CB61,CJ61)-CR61 -> 0 | DK61: =SUM(E61,K61,Q61,W61,AE61,AM61,AV61,BD61,BL61,BU61,CC61,CK61)-CS61 -> 0 | DL61: =SUM(G61,M61,S61,AA61,AI61,AR61,AZ61,BH61,BQ61,BY61,CG61,CO61)-CW61 -> 0 | DM61: =SUM(D61,J61,P61,V61,AD61,AL61,AU61,BC61,,BN61,BV61,CD61,CL61)-CT61 -> 0 | DX61: =(CS61-CZ61)*10^6 -> 0 | DY61: =(CT61-DC61)*10^6 -> 0 | DZ61: =(CW61-DD61)*10^6 -> 0
CR62: =CR60-SUM(CJ60,CB60,BT60,BK60,BC60,AU60,AL60,AD60,V60,P60,J60,D60) -> 0 | CS62: =CS60-SUM(CK60,CC60,BU60,BL60,BD60,AV60,AM60,AE60,W60,Q60,K60,E60) -> 0 | DD62: 0 | DJ62: =SUM(D62,J62,P62,V62,AD62,AL62,AU62,BC62,BK62,BT62,CB62,CJ62)-CR62 -> 0 | DK62: =SUM(E62,K62,Q62,W62,AE62,AM62,AV62,BD62,BL62,BU62,CC62,CK62)-CS62 -> 0 | DL62: =SUM(G62,M62,S62,AA62,AI62,AR62,AZ62,BH62,BQ62,BY62,CG62,CO62)-CW62 -> 0 | DM62: =SUM(D62,J62,P62,V62,AD62,AL62,AU62,BC62,,BN62,BV62,CD62,CL62)-CT62 -> 0 | DX62: =(CS62-CZ62)*10^6 -> 0 | DY62: =(CT62-DC62)*10^6 -> 0 | DZ62: =(CW62-DD62)*10^6 -> 0
A63: Marge Brute (hors transit) | DX63: =(CS63-CZ63)*10^6 -> 0 | DY63: =(CT63-DC63)*10^6 -> 0 | DZ63: =(CW63-DD63)*10^6 -> 0
A64: % CA | DX64: =(CS64-CZ64)*10^6 -> 0 | DY64: =(CT64-DC64)*10^6 -> 0 | DZ64: =(CW64-DD64)*10^6 -> 0
DX65: =(CS65-CZ65)*10^6 -> 0 | DY65: =(CT65-DC65)*10^6 -> 0 | DZ65: =(CW65-DD65)*10^6 -> 0
B66: Charges d'interco | DX66: =(CS66-CZ66)*10^6 -> 0 | DY66: =(CT66-DC66)*10^6 -> 0 | DZ66: =(CW66-DD66)*10^6 -> 0
DX67: =(CS67-CZ67)*10^6 -> 0 | DY67: =(CT67-DC67)*10^6 -> 0 | DZ67: =(CW67-DD67)*10^6 -> 0
B68: Revenu net | DX68: =(CS68-CZ68)*10^6 -> 0 | DY68: =(CT68-DC68)*10^6 -> 0 | DZ68: =(CW68-DD68)*10^6 -> 0
DX69: =(CS69-CZ69)*10^6 -> 0 | DY69: =(CT69-DC69)*10^6 -> 0 | DZ69: =(CW69-DD69)*10^6 -> 0
B70: Charges d'interco | CR70: 2648.3465 | DX70: =(CS70-CZ70)*10^6 -> 0 | DY70: =(CT70-DC70)*10^6 -> 0 | DZ70: =(CW70-DD70)*10^6 -> 0
CR71: =CR70+CR56 -> 2648.3465 | DX71: =(CS71-CZ71)*10^6 -> 0 | DY71: =(CT71-DC71)*10^6 -> 0 | DZ71: =(CW71-DD71)*10^6 -> 0
DX72: =(CS72-CZ72)*10^6 -> 0 | DY72: =(CT72-DC72)*10^6 -> 0 | DZ72: =(CW72-DD72)*10^6 -> 0
B73: Taux hors flooz mois | DX73: =(CS73-CZ73)*10^6 -> 0 | DY73: =(CT73-DC73)*10^6 -> 0 | DZ73: =(CW73-DD73)*10^6 -> 0
B74: Taux hors flooz moyenne | DX74: =(CS74-CZ74)*10^6 -> 0 | DY74: =(CT74-DC74)*10^6 -> 0 | DZ74: =(CW74-DD74)*10^6 -> 0
CR75: =CR7+CR58-CR60 -> 0 | CS75: =CS7+CS58-CS60 -> 0 | DX75: =(CS75-CZ75)*10^6 -> 0 | DY75: =(CT75-DC75)*10^6 -> 0 | DZ75: =(CW75-DD75)*10^6 -> 0
DX76: =(CS76-CZ76)*10^6 -> 0 | DY76: =(CT76-DC76)*10^6 -> 0 | DZ76: =(CW76-DD76)*10^6 -> 0
DX77: =(CS77-CZ77)*10^6 -> 0 | DY77: =(CT77-DC77)*10^6 -> 0 | DZ77: =(CW77-DD77)*10^6 -> 0
DX78: =(CS78-CZ78)*10^6 -> 0 | DY78: =(CT78-DC78)*10^6 -> 0 | DZ78: =(CW78-DD78)*10^6 -> 0
DX79: =(CS79-CZ79)*10^6 -> 0 | DY79: =(CT79-DC79)*10^6 -> 0 | DZ79: =(CW79-DD79)*10^6 -> 0
CR80: Détermination totale | CS80: 553900786 | DX80: =(CS80-CZ80)*10^6 -> 553900786000000 | DY80: =(CT80-DC80)*10^6 -> 0 | DZ80: =(CW80-DD80)*10^6 -> 0
CR81: Détermination par abonnés | CS81: 56156068 | DX81: =(CS81-CZ81)*10^6 -> 5.6156068e+13 | DY81: =(CT81-DC81)*10^6 -> 0 | DZ81: =(CW81-DD81)*10^6 -> 0
CS82: =CS80-CS81 -> 4.9774472e+08 | DX82: =(CS82-CZ82)*10^6 -> 4.9774472e+14 | DY82: =(CT82-DC82)*10^6 -> 0 | DZ82: =(CW82-DD82)*10^6 -> 0
CS83: 4.9774472e+08 | DX83: =(CS83-CZ83)*10^6 -> 497744717550848 | DY83: =(CT83-DC83)*10^6 -> 0 | DZ83: =(CW83-DD83)*10^6 -> 0
DX84: =(CS84-CZ84)*10^6 -> 0 | DY84: =(CT84-DC84)*10^6 -> 0 | DZ84: =(CW84-DD84)*10^6 -> 0
DX85: =(CS85-CZ85)*10^6 -> 0 | DY85: =(CT85-DC85)*10^6 -> 0 | DZ85: =(CW85-DD85)*10^6 -> 0
DX86: =(CS86-CZ86)*10^6 -> 0 | DY86: =(CT86-DC86)*10^6 -> 0 | DZ86: =(CW86-DD86)*10^6 -> 0
DX87: =(CS87-CZ87)*10^6 -> 0 | DY87: =(CT87-DC87)*10^6 -> 0 | DZ87: =(CW87-DD87)*10^6 -> 0
DX88: =(CS88-CZ88)*10^6 -> 0 | DY88: =(CT88-DC88)*10^6 -> 0 | DZ88: =(CW88-DD88)*10^6 -> 0
DX89: =(CS89-CZ89)*10^6 -> 0 | DY89: =(CT89-DC89)*10^6 -> 0 | DZ89: =(CW89-DD89)*10^6 -> 0
DX90: =(CS90-CZ90)*10^6 -> 0 | DY90: =(CT90-DC90)*10^6 -> 0 | DZ90: =(CW90-DD90)*10^6 -> 0
DX91: =(CS91-CZ91)*10^6 -> 0 | DY91: =(CT91-DC91)*10^6 -> 0 | DZ91: =(CW91-DD91)*10^6 -> 0
DX92: =(CS92-CZ92)*10^6 -> 0 | DY92: =(CT92-DC92)*10^6 -> 0 | DZ92: =(CW92-DD92)*10^6 -> 0
DX93: =(CS93-CZ93)*10^6 -> 0 | DY93: =(CT93-DC93)*10^6 -> 0 | DZ93: =(CW93-DD93)*10^6 -> 0
DX94: =(CS94-CZ94)*10^6 -> 0 | DY94: =(CT94-DC94)*10^6 -> 0 | DZ94: =(CW94-DD94)*10^6 -> 0
DX95: =(CS95-CZ95)*10^6 -> 0 | DY95: =(CT95-DC95)*10^6 -> 0 | DZ95: =(CW95-DD95)*10^6 -> 0
... DX189: =(CS189-CZ189)*10^6 -> 0 | DY189: =(CT189-DC189)*10^6 -> 0 | DZ189: =(CW189-DD189)*10^6 -> 0

Sheet Trafic mobile
B1: Trafic Mobile | CS1: 102.7141 | CW1: 1407.7084 | CZ1: -234.93003
E3: 0 | G3: 0 | DD3: 0
D4: 45292 | J4: 45323 | P4: 45352 | V4: 45383 | AD4: 45413 | AL4: 45444 | AU4: 45474 | BC4: 45505 | BK4: 45536 | BT4: 45566 | CB4: 45597 | CJ4: 45627 | CR4: CUMUL | CZ4: ANNUEL
B5: (En millions minutes) | D5: 2024 Réel | E5: 2024 Budget | F5: Ecart / Budget | G5: 2023 Réel | H5: Evol % | J5: 2024 Réel | K5: 2024 Budget | L5: Ecart / Budget | M5: 2023 Réel | N5: Evol % | P5: 2024 Réel | Q5: 2024 Budget | R5: Ecart / Budget | S5: 2023 Réel | T5: Evol % | V5: 2024 Réel | W5: 2024 Budget | X5: 2024 Actu1 | Y5: Ecart / Budget | Z5: Ecart / Actu1 | AA5: 2023 Réel | AB5: Evol % | AD5: 2024 Réel | AE5: 2024 Budget | AF5: 2024 Actu1 | AG5: Ecart / Budget | AH5: Ecart / Actu1 | AI5: 2023 Réel | AJ5: Evol % | AL5: 2024 Réel | AM5: 2024 Budget | AN5: 2024 Actu1 | AO5: 2024 Actu2 | AP5: Ecart / Budget | AQ5: Ecart / Actu1 | AR5: 2023 Réel | AS5: Evol % | AU5: 2024 Réel | AV5: 2024 Budget | AW5: 2024 Actu2 | AX5: Ecart / Budget | AY5: Ecart / Actu2 | AZ5: 2023 Réel | BA5: Evol % | BC5: 2024 Réel | BD5: 2024 Budget | BE5: 2024 Actu2 | BF5: Ecart / Budget | BG5: Ecart / Actu2 | BH5: 2023 Réel | BI5: Evol % | BK5: 2024 Réel | BL5: 2024 Budget | BM5: 2024 Actu2 | BN5: 2024 Actu3 | BO5: Ecart / Budget | BP5: Ecart / Actu2 | BQ5: 2023 Réel | BR5: Evol % | BT5: 2024 Réel | BU5: 2024 Budget | BV5: 2024 Actu3 | BW5: Ecart / Budget | BX5: Ecart / Actu3 | BY5: 2023 Réel | BZ5: Evol % | CB5: 2024 Réel | CC5: 2024 Budget | CD5: 2024 Actu3 | CE5: Ecart / Budget | CF5: Ecart / Actu3 | CG5: 2023 Réel | CH5: Evol % | CJ5: 2024 Réel | CK5: 2024 Budget | CL5: 2024 Actu3 | CM5: Ecart / Budget | CN5: Ecart / Actu3 | CO5: 2023 Réel | CP5: Evol % | CR5: 2024 Réel | CS5: 2024 Budget | CT5: 2024 Actu3 | CU5: Ecart / Budget | CV5: Ecart / Actu3 | CW5: 2023 Réel | CX5: Evol % | CZ5: 2024 Budget | DA5: 2024 Actu1 | DB5: 2024 Actu2 | DC5: 2024 Actu3 | DD5: 2023 Réel | DE5: Bud / 2023 (%) | DF5: Actu 1 / 2023 (%) | DG5: Actu 2 / 2023 (%) | DH5: Actu3 / 2023 (%) | DJ5: 2024 Réel | DK5: 2024 Budget | DL5: 2023 Réel | DM5: Actu
DJ6: =SUM(D6,J6,P6,V6,AD6,AL6,AU6,BC6,BK6,BT6,CB6,CJ6)-CR6 -> 0 | DK6: =SUM(E6,K6,Q6,W6,AE6,AM6,AV6,BD6,BL6,BU6,CC6,CK6)-CS6 -> 0 | DL6: =SUM(G6,M6,S6,AA6,AI6,AR6,AZ6,BH6,BQ6,BY6,CG6,CO6)-CW6 -> 0 | DM6: =SUM(D6,J6,P6,V6,AD6,AL6,AU6,BC6,,BN6,BV6,CD6,CL6)-CT6 -> 0
B7: Total Trafic sortant | C7: TRAF1 | CU7: =CR7-CS7 -> 0 | CV7: =CR7-CT7 -> 0 | CX7: =IFERROR(CR7/CW7-1, "-") -> - | DE7: =+CZ7/DD7-1 -> #DIV/0! | DF7: =+DA7/DD7-1 -> #DIV/0! | DG7: =+DB7/DD7-1 -> #DIV/0! | DH7: =+DC7/DD7-1 -> #DIV/0! | DJ7: =SUM(D7,J7,P7,V7,AD7,AL7,AU7,BC7,BK7,BT7,CB7,CJ7)-CR7 -> 0 | DK7: =SUM(E7,K7,Q7,W7,AE7,AM7,AV7,BD7,BL7,BU7,CC7,CK7)-CS7 -> 0 | DL7: =SUM(G7,M7,S7,AA7,AI7,AR7,AZ7,BH7,BQ7,BY7,CG7,CO7)-CW7 -> 0 | DM7: =SUM(D7,J7,P7,V7,AD7,AL7,AU7,BC7,,BN7,BV7,CD7,CL7)-CT7 -> 0
C8: TRAF2 | CX8: =IFERROR(CR8/CW8-1, "-") -> - | DJ8: =SUM(D8,J8,P8,V8,AD8,AL8,AU8,BC8,BK8,BT8,CB8,CJ8)-CR8 -> 0 | DK8: =SUM(E8,K8,Q8,W8,AE8,AM8,AV8,BD8,BL8,BU8,CC8,CK8)-CS8 -> 0 | DL8: =SUM(G8,M8,S8,AA8,AI8,AR8,AZ8,BH8,BQ8,BY8,CG8,CO8)-CW8 -> 0 | DM8: =SUM(D8,J8,P8,V8,AD8,AL8,AU8,BC8,,BN8,BV8,CD8,CL8)-CT8 -> 0 | DX8: =CS8-CZ8 -> 0 | DY8: =CT8-DC8 -> 0 | DZ8: =CW8-DD8 -> 0
B9: Trafic sortant prépayé (Consumer) | C9: TRAF3 | CU9: =CR9-CS9 -> 0 | CV9: =CR9-CT9 -> 0 | CX9: =IFERROR(CR9/CW9-1, "-") -> - | DE9: =+CZ9/DD9-1 -> #DIV/0! | DF9: =+DA9/DD9-1 -> #DIV/0! | DG9: =+DB9/DD9-1 -> #DIV/0! | DH9: =+DC9/DD9-1 -> #DIV/0! | DJ9: =SUM(D9,J9,P9,V9,AD9,AL9,AU9,BC9,BK9,BT9,CB9,CJ9)-CR9 -> 0 | DK9: =SUM(E9,K9,Q9,W9,AE9,AM9,AV9,BD9,BL9,BU9,CC9,CK9)-CS9 -> 0 | DL9: =SUM(G9,M9,S9,AA9,AI9,AR9,AZ9,BH9,BQ9,BY9,CG9,CO9)-CW9 -> 0 | DM9: =SUM(D9,J9,P9,V9,AD9,AL9,AU9,BC9,,BN9,BV9,CD9,CL9)-CT9 -> 0 | DX9: =(CS9-CZ9)*10^6 -> 0 | DY9: =(CT9-DC9)*10^6 -> 0 | DZ9: =(CW9-DD9)*10^6 -> 0
B10: vers le fixe | C10: TRAF4 | CU10: =CR10-CS10 -> 0 | CV10: =CR10-CT10 -> 0 | CX10: =IFERROR(CR10/CW10-1, "-") -> - | DE10: =+CZ10/DD10-1 -> #DIV/0! | DF10: =+DA10/DD10-1 -> #DIV/0! | DG10: =+DB10/DD10-1 -> #DIV/0! | DH10: =+DC10/DD10-1 -> #DIV/0! | DJ10: =SUM(D10,J10,P10,V10,AD10,AL10,AU10,BC10,BK10,BT10,CB10,CJ10)-CR10 -> 0 | DK10: =SUM(E10,K10,Q10,W10,AE10,AM10,AV10,BD10,BL10,BU10,CC10,CK10)-CS10 -> 0 | DL10: =SUM(G10,M10,S10,AA10,AI10,AR10,AZ10,BH10,BQ10,BY10,CG10,CO10)-CW10 -> 0 | DM10: =SUM(D10,J10,P10,V10,AD10,AL10,AU10,BC10,,BN10,BV10,CD10,CL10)-CT10 -> 0 | DX10: =(CS10-CZ10)*10^6 -> 0 | DY10: =(CT10-DC10)*10^6 -> 0 | DZ10: =(CW10-DD10)*10^6 -> 0
B11: vers l'international | C11: TRAF5 | CU11: =CR11-CS11 -> 0 | CV11: =CR11-CT11 -> 0 | CX11: =IFERROR(CR11/CW11-1, "-") -> - | DE11: =+CZ11/DD11-1 -> #DIV/0! | DF11: =+DA11/DD11-1 -> #DIV/0! | DG11: =+DB11/DD11-1 -> #DIV/0! | DH11: =+DC11/DD11-1 -> #DIV/0! | DJ11: =SUM(D11,J11,P11,V11,AD11,AL11,AU11,BC11,BK11,BT11,CB11,CJ11)-CR11 -> 0 | DK11: =SUM(E11,K11,Q11,W11,AE11,AM11,AV11,BD11,BL11,BU11,CC11,CK11)-CS11 -> 0 | DL11: =SUM(G11,M11,S11,AA11,AI11,AR11,AZ11,BH11,BQ11,BY11,CG11,CO11)-CW11 -> 0 | DM11: =SUM(D11,J11,P11,V11,AD11,AL11,AU11,BC11,,BN11,BV11,CD11,CL11)-CT11 -> 0 | DX11: =(CS11-CZ11)*10^6 -> 0 | DY11: =(CT11-DC11)*10^6 -> 0 | DZ11: =(CW11-DD11)*10^6 -> 0
B12: vers Mobile (on net) | C12: TRAF6 | CU12: =CR12-CS12 -> 0 | CV12: =CR12-CT12 -> 0 | CX12: =IFERROR(CR12/CW12-1, "-") -> - | DE12: =+CZ12/DD12-1 -> #DIV/0! | DF12: =+DA12/DD12-1 -> #DIV/0! | DG12: =+DB12/DD12-1 -> #DIV/0! | DH12: =+DC12/DD12-1 -> #DIV/0! | DJ12: =SUM(D12,J12,P12,V12,AD12,AL12,AU12,BC12,BK12,BT12,CB12,CJ12)-CR12 -> 0 | DK12: =SUM(E12,K12,Q12,W12,AE12,AM12,AV12,BD12,BL12,BU12,CC12,CK12)-CS12 -> 0 | DL12: =SUM(G12,M12,S12,AA12,AI12,AR12,AZ12,BH12,BQ12,BY12,CG12,CO12)-CW12 -> 0 | DM12: =SUM(D12,J12,P12,V12,AD12,AL12,AU12,BC12,,BN12,BV12,CD12,CL12)-CT12 -> 0 | DX12: =(CS12-CZ12)*10^6 -> 0 | DY12: =(CT12-DC12)*10^6 -> 0 | DZ12: =(CW12-DD12)*10^6 -> 0
B13: vers MTN | C13: TRAF7 | CU13: =CR13-CS13 -> 0 | CV13: =CR13-CT13 -> 0 | CX13: =IFERROR(CR13/CW13-1, "-") -> - | DE13: =+CZ13/DD13-1 -> #DIV/0! | DF13: =+DA13/DD13-1 -> #DIV/0! | DG13: =+DB13/DD13-1 -> #DIV/0! | DH13: =+DC13/DD13-1 -> #DIV/0! | DJ13: =SUM(D13,J13,P13,V13,AD13,AL13,AU13,BC13,BK13,BT13,CB13,CJ13)-CR13 -> 0 | DK13: =SUM(E13,K13,Q13,W13,AE13,AM13,AV13,BD13,BL13,BU13,CC13,CK13)-CS13 -> 0 | DL13: =SUM(G13,M13,S13,AA13,AI13,AR13,AZ13,BH13,BQ13,BY13,CG13,CO13)-CW13 -> 0 | DM13: =SUM(D13,J13,P13,V13,AD13,AL13,AU13,BC13,,BN13,BV13,CD13,CL13)-CT13 -> 0 | DX13: =(CS13-CZ13)*10^6 -> 0 | DY13: =(CT13-DC13)*10^6 -> 0 | DZ13: =(CW13-DD13)*10^6 -> 0
B14: vers SBIN | C14: TRAF8 | CU14: =CR14-CS14 -> 0 | CV14: =CR14-CT14 -> 0 | CX14: =IFERROR(CR14/CW14-1, "-") -> - | DJ14: =SUM(D14,J14,P14,V14,AD14,AL14,AU14,BC14,BK14,BT14,CB14,CJ14)-CR14 -> 0 | DK14: =SUM(E14,K14,Q14,W14,AE14,AM14,AV14,BD14,BL14,BU14,CC14,CK14)-CS14 -> 0 | DL14: =SUM(G14,M14,S14,AA14,AI14,AR14,AZ14,BH14,BQ14,BY14,CG14,CO14)-CW14 -> 0 | DM14: =SUM(D14,J14,P14,V14,AD14,AL14,AU14,BC14,,BN14,BV14,CD14,CL14)-CT14 -> 0 | DX14: =(CS14-CZ14)*10^6 -> 0 | DY14: =(CT14-DC14)*10^6 -> 0 | DZ14: =(CW14-DD14)*10^6 -> 0
B15: vers BBCOM, LIBERCOM | C15: TRAF9 | CU15: =CR15-CS15 -> 0 | CV15: =CR15-CT15 -> 0 | CX15: =IFERROR(CR15/CW15-1, "-") -> - | DJ15: =SUM(D15,J15,P15,V15,AD15,AL15,AU15,BC15,BK15,BT15,CB15,CJ15)-CR15 -> 0 | DK15: =SUM(E15,K15,Q15,W15,AE15,AM15,AV15,BD15,BL15,BU15,CC15,CK15)-CS15 -> 0 | DL15: =SUM(G15,M15,S15,AA15,AI15,AR15,AZ15,BH15,BQ15,BY15,CG15,CO15)-CW15 -> 0 | DM15: =SUM(D15,J15,P15,V15,AD15,AL15,AU15,BC15,,BN15,BV15,CD15,CL15)-CT15 -> 0 | DX15: =(CS15-CZ15)*10^6 -> 0 | DY15: =(CT15-DC15)*10^6 -> 0 | DZ15: =(CW15-DD15)*10^6 -> 0
B16: Outbound roaming | C16: TRAF10 | CU16: =CR16-CS16 -> 0 | CV16: =CR16-CT16 -> 0 | CX16: =IFERROR(CR16/CW16-1, "-") -> - | DE16: =+CZ16/DD16-1 -> #DIV/0! | DF16: =+DA16/DD16-1 -> #DIV/0! | DG16: =+DB16/DD16-1 -> #DIV/0! | DH16: =+DC16/DD16-1 -> #DIV/0! | DJ16: =SUM(D16,J16,P16,V16,AD16,AL16,AU16,BC16,BK16,BT16,CB16,CJ16)-CR16 -> 0 | DK16: =SUM(E16,K16,Q16,W16,AE16,AM16,AV16,BD16,BL16,BU16,CC16,CK16)-CS16 -> 0 | DL16: =SUM(G16,M16,S16,AA16,AI16,AR16,AZ16,BH16,BQ16,BY16,CG16,CO16)-CW16 -> 0 | DM16: =SUM(D16,J16,P16,V16,AD16,AL16,AU16,BC16,,BN16,BV16,CD16,CL16)-CT16 -> 0 | DX16: =(CS16-CZ16)*10^6 -> 0 | DY16: =(CT16-DC16)*10^6 -> 0 | DZ16: =(CW16-DD16)*10^6 -> 0
C17: TRAF11 | CU17: =CR17-CS17 -> 0 | CV17: =CR17-CT17 -> 0 | CX17: =IFERROR(CR17/CW17-1, "-") -> - | DJ17: =SUM(D17,J17,P17,V17,AD17,AL17,AU17,BC17,BK17,BT17,CB17,CJ17)-CR17 -> 0 | DK17: =SUM(E17,K17,Q17,W17,AE17,AM17,AV17,BD17,BL17,BU17,CC17,CK17)-CS17 -> 0 | DL17: =SUM(G17,M17,S17,AA17,AI17,AR17,AZ17,BH17,BQ17,BY17,CG17,CO17)-CW17 -> 0 | DM17: =SUM(D17,J17,P17,V17,AD17,AL17,AU17,BC17,,BN17,BV17,CD17,CL17)-CT17 -> 0 | DX17: =(CS17-CZ17)*10^6 -> 0 | DY17: =(CT17-DC17)*10^6 -> 0 | DZ17: =(CW17-DD17)*10^6 -> 0
B18: Trafic sortant postpayé | C18: TRAF12 | CU18: =CR18-CS18 -> 0 | CV18: =CR18-CT18 -> 0 | CX18: =IFERROR(CR18/CW18-1, "-") -> - | DE18: =+CZ18/DD18-1 -> #DIV/0! | DF18: =+DA18/DD18-1 -> #DIV/0! | DG18: =+DB18/DD18-1 -> #DIV/0! | DH18: =+DC18/DD18-1 -> #DIV/0! | DJ18: =SUM(D18,J18,P18,V18,AD18,AL18,AU18,BC18,BK18,BT18,CB18,CJ18)-CR18 -> 0 | DK18: =SUM(E18,K18,Q18,W18,AE18,AM18,AV18,BD18,BL18,BU18,CC18,CK18)-CS18 -> 0 | DL18: =SUM(G18,M18,S18,AA18,AI18,AR18,AZ18,BH18,BQ18,BY18,CG18,CO18)-CW18 -> 0 | DM18: =SUM(D18,J18,P18,V18,AD18,AL18,AU18,BC18,,BN18,BV18,CD18,CL18)-CT18 -> 0 | DX18: =(CS18-CZ18)*10^6 -> 0 | DY18: =(CT18-DC18)*10^6 -> 0 | DZ18: =(CW18-DD18)*10^6 -> 0
B19: vers le fixe | C19: TRAF13 | CU19: =CR19-CS19 -> 0 | CV19: =CR19-CT19 -> 0 | CX19: =IFERROR(CR19/CW19-1, "-") -> - | DE19: =+CZ19/DD19-1 -> #DIV/0! | DJ19: =SUM(D19,J19,P19,V19,AD19,AL19,AU19,BC19,BK19,BT19,CB19,CJ19)-CR19 -> 0 | DK19: =SUM(E19,K19,Q19,W19,AE19,AM19,AV19,BD19,BL19,BU19,CC19,CK19)-CS19 -> 0 | DL19: =SUM(G19,M19,S19,AA19,AI19,AR19,AZ19,BH19,BQ19,BY19,CG19,CO19)-CW19 -> 0 | DM19: =SUM(D19,J19,P19,V19,AD19,AL19,AU19,BC19,,BN19,BV19,CD19,CL19)-CT19 -> 0 | DX19: =(CS19-CZ19)*10^6 -> 0 | DY19: =(CT19-DC19)*10^6 -> 0 | DZ19: =(CW19-DD19)*10^6 -> 0
B20: vers l'international | C20: TRAF14 | CU20: =CR20-CS20 -> 0 | CV20: =CR20-CT20 -> 0 | CX20: =IFERROR(CR20/CW20-1, "-") -> - | DE20: =+CZ20/DD20-1 -> #DIV/0! | DJ20: =SUM(D20,J20,P20,V20,AD20,AL20,AU20,BC20,BK20,BT20,CB20,CJ20)-CR20 -> 0 | DK20: =SUM(E20,K20,Q20,W20,AE20,AM20,AV20,BD20,BL20,BU20,CC20,CK20)-CS20 -> 0 | DL20: =SUM(G20,M20,S20,AA20,AI20,AR20,AZ20,BH20,BQ20,BY20,CG20,CO20)-CW20 -> 0 | DM20: =SUM(D20,J20,P20,V20,AD20,AL20,AU20,BC20,,BN20,BV20,CD20,CL20)-CT20 -> 0 | DX20: =(CS20-CZ20)*10^6 -> 0 | DY20: =(CT20-DC20)*10^6 -> 0 | DZ20: =(CW20-DD20)*10^6 -> 0
B21: vers Mobile (on net) | C21: TRAF15 | CU21: =CR21-CS21 -> 0 | CV21: =CR21-CT21 -> 0 | CX21: =IFERROR(CR21/CW21-1, "-") -> - | DE21: =+CZ21/DD21-1 -> #DIV/0! | DJ21: =SUM(D21,J21,P21,V21,AD21,AL21,AU21,BC21,BK21,BT21,CB21,CJ21)-CR21 -> 0 | DK21: =SUM(E21,K21,Q21,W21,AE21,AM21,AV21,BD21,BL21,BU21,CC21,CK21)-CS21 -> 0 | DL21: =SUM(G21,M21,S21,AA21,AI21,AR21,AZ21,BH21,BQ21,BY21,CG21,CO21)-CW21 -> 0 | DM21: =SUM(D21,J21,P21,V21,AD21,AL21,AU21,BC21,,BN21,BV21,CD21,CL21)-CT21 -> 0 | DX21: =(CS21-CZ21)*10^6 -> 0 | DY21: =(CT21-DC21)*10^6 -> 0 | DZ21: =(CW21-DD21)*10^6 -> 0
B22: vers MTN | C22: TRAF16 | CU22: =CR22-CS22 -> 0 | CV22: =CR22-CT22 -> 0 | CX22: =IFERROR(CR22/CW22-1, "-") -> - | DE22: =+CZ22/DD22-1 -> #DIV/0! | DJ22: =SUM(D22,J22,P22,V22,AD22,AL22,AU22,BC22,BK22,BT22,CB22,CJ22)-CR22 -> 0 | DK22: =SUM(E22,K22,Q22,W22,AE22,AM22,AV22,BD22,BL22,BU22,CC22,CK22)-CS22 -> 0 | DL22: =SUM(G22,M22,S22,AA22,AI22,AR22,AZ22,BH22,BQ22,BY22,CG22,CO22)-CW22 -> 0 | DM22: =SUM(D22,J22,P22,V22,AD22,AL22,AU22,BC22,,BN22,BV22,CD22,CL22)-CT22 -> 0 | DX22: =(CS22-CZ22)*10^6 -> 0 | DY22: =(CT22-DC22)*10^6 -> 0 | DZ22: =(CW22-DD22)*10^6 -> 0
B23: vers SBIN | C23: TRAF17 | CU23: =CR23-CS23 -> 0 | CV23: =CR23-CT23 -> 0 | CX23: =IFERROR(CR23/CW23-1, "-") -> - | DJ23: =SUM(D23,J23,P23,V23,AD23,AL23,AU23,BC23,BK23,BT23,CB23,CJ23)-CR23 -> 0 | DK23: =SUM(E23,K23,Q23,W23,AE23,AM23,AV23,BD23,BL23,BU23,CC23,CK23)-CS23 -> 0 | DL23: =SUM(G23,M23,S23,AA23,AI23,AR23,AZ23,BH23,BQ23,BY23,CG23,CO23)-CW23 -> 0 | DM23: =SUM(D23,J23,P23,V23,AD23,AL23,AU23,BC23,,BN23,BV23,CD23,CL23)-CT23 -> 0 | DX23: =(CS23-CZ23)*10^6 -> 0 | DY23: =(CT23-DC23)*10^6 -> 0 | DZ23: =(CW23-DD23)*10^6 -> 0
B24: vers BBCOM, LIBERCOM | C24: TRAF18 | CU24: =CR24-CS24 -> 0 | CV24: =CR24-CT24 -> 0 | CX24: =IFERROR(CR24/CW24-1, "-") -> - | DJ24: =SUM(D24,J24,P24,V24,AD24,AL24,AU24,BC24,BK24,BT24,CB24,CJ24)-CR24 -> 0 | DK24: =SUM(E24,K24,Q24,W24,AE24,AM24,AV24,BD24,BL24,BU24,CC24,CK24)-CS24 -> 0 | DL24: =SUM(G24,M24,S24,AA24,AI24,AR24,AZ24,BH24,BQ24,BY24,CG24,CO24)-CW24 -> 0 | DM24: =SUM(D24,J24,P24,V24,AD24,AL24,AU24,BC24,,BN24,BV24,CD24,CL24)-CT24 -> 0 | DX24: =(CS24-CZ24)*10^6 -> 0 | DY24: =(CT24-DC24)*10^6 -> 0 | DZ24: =(CW24-DD24)*10^6 -> 0
B25: Outbound roaming | C25: TRAF19 | CU25: =CR25-CS25 -> 0 | CV25: =CR25-CT25 -> 0 | CX25: =IFERROR(CR25/CW25-1, "-") -> - | DJ25: =SUM(D25,J25,P25,V25,AD25,AL25,AU25,BC25,BK25,BT25,CB25,CJ25)-CR25 -> 0 | DK25: =SUM(E25,K25,Q25,W25,AE25,AM25,AV25,BD25,BL25,BU25,CC25,CK25)-CS25 -> 0 | DL25: =SUM(G25,M25,S25,AA25,AI25,AR25,AZ25,BH25,BQ25,BY25,CG25,CO25)-CW25 -> 0 | DM25: =SUM(D25,J25,P25,V25,AD25,AL25,AU25,BC25,,BN25,BV25,CD25,CL25)-CT25 -> 0 | DX25: =(CS25-CZ25)*10^6 -> 0 | DY25: =(CT25-DC25)*10^6 -> 0 | DZ25: =(CW25-DD25)*10^6 -> 0
C26: TRAF20 | CX26: =IFERROR(CR26/CW26-1, "-") -> - | DJ26: =SUM(D26,J26,P26,V26,AD26,AL26,AU26,BC26,BK26,BT26,CB26,CJ26)-CR26 -> 0 | DK26: =SUM(E26,K26,Q26,W26,AE26,AM26,AV26,BD26,BL26,BU26,CC26,CK26)-CS26 -> 0 | DL26: =SUM(G26,M26,S26,AA26,AI26,AR26,AZ26,BH26,BQ26,BY26,CG26,CO26)-CW26 -> 0 | DM26: =SUM(D26,J26,P26,V26,AD26,AL26,AU26,BC26,,BN26,BV26,CD26,CL26)-CT26 -> 0 | DX26: =(CS26-CZ26)*10^6 -> 0 | DY26: =(CT26-DC26)*10^6 -> 0 | DZ26: =(CW26-DD26)*10^6 -> 0
B27: Consumer Postpaid | C27: TRAF21 | CU27: =CR27-CS27 -> 0 | CV27: =CR27-CT27 -> 0 | CX27: =IFERROR(CR27/CW27-1, "-") -> - | DE27: =+CZ27/DD27-1 -> #DIV/0! | DF27: =+DA27/DD27-1 -> #DIV/0! | DG27: =+DB27/DD27-1 -> #DIV/0! | DH27: =+DC27/DD27-1 -> #DIV/0! | DJ27: =SUM(D27,J27,P27,V27,AD27,AL27,AU27,BC27,BK27,BT27,CB27,CJ27)-CR27 -> 0 | DK27: =SUM(E27,K27,Q27,W27,AE27,AM27,AV27,BD27,BL27,BU27,CC27,CK27)-CS27 -> 0 | DL27: =SUM(G27,M27,S27,AA27,AI27,AR27,AZ27,BH27,BQ27,BY27,CG27,CO27)-CW27 -> 0 | DM27: =SUM(D27,J27,P27,V27,AD27,AL27,AU27,BC27,,BN27,BV27,CD27,CL27)-CT27 -> 0 | DX27: =(CS27-CZ27)*10^6 -> 0 | DY27: =(CT27-DC27)*10^6 -> 0 | DZ27: =(CW27-DD27)*10^6 -> 0
B28: vers le fixe | C28: TRAF22 | CU28: =CR28-CS28 -> 0 | CV28: =CR28-CT28 -> 0 | CX28: =IFERROR(CR28/CW28-1, "-") -> - | DE28: =+CZ28/DD28-1 -> #DIV/0! | DF28: =+DA28/DD28-1 -> #DIV/0! | DG28: =+DB28/DD28-1 -> #DIV/0! | DH28: =+DC28/DD28-1 -> #DIV/0! | DJ28: =SUM(D28,J28,P28,V28,AD28,AL28,AU28,BC28,BK28,BT28,CB28,CJ28)-CR28 -> 0 | DK28: =SUM(E28,K28,Q28,W28,AE28,AM28,AV28,BD28,BL28,BU28,CC28,CK28)-CS28 -> 0 | DL28: =SUM(G28,M28,S28,AA28,AI28,AR28,AZ28,BH28,BQ28,BY28,CG28,CO28)-CW28 -> 0 | DM28: =SUM(D28,J28,P28,V28,AD28,AL28,AU28,BC28,,BN28,BV28,CD28,CL28)-CT28 -> 0 | DX28: =(CS28-CZ28)*10^6 -> 0 | DY28: =(CT28-DC28)*10^6 -> 0 | DZ28: =(CW28-DD28)*10^6 -> 0
B29: vers l'international | C29: TRAF23 | CU29: =CR29-CS29 -> 0 | CV29: =CR29-CT29 -> 0 | CX29: =IFERROR(CR29/CW29-1, "-") -> - | DE29: =+CZ29/DD29-1 -> #DIV/0! | DF29: =+DA29/DD29-1 -> #DIV/0! | DG29: =+DB29/DD29-1 -> #DIV/0! | DH29: =+DC29/DD29-1 -> #DIV/0! | DJ29: =SUM(D29,J29,P29,V29,AD29,AL29,AU29,BC29,BK29,BT29,CB29,CJ29)-CR29 -> 0 | DK29: =SUM(E29,K29,Q29,W29,AE29,AM29,AV29,BD29,BL29,BU29,CC29,CK29)-CS29 -> 0 | DL29: =SUM(G29,M29,S29,AA29,AI29,AR29,AZ29,BH29,BQ29,BY29,CG29,CO29)-CW29 -> 0 | DM29: =SUM(D29,J29,P29,V29,AD29,AL29,AU29,BC29,,BN29,BV29,CD29,CL29)-CT29 -> 0 | DX29: =(CS29-CZ29)*10^6 -> 0 | DY29: =(CT29-DC29)*10^6 -> 0 | DZ29: =(CW29-DD29)*10^6 -> 0
B30: vers Mobile (on net) | C30: TRAF24 | CU30: =CR30-CS30 -> 0 | CV30: =CR30-CT30 -> 0 | CX30: =IFERROR(CR30/CW30-1, "-") -> - | DE30: =+CZ30/DD30-1 -> #DIV/0! | DF30: =+DA30/DD30-1 -> #DIV/0! | DG30: =+DB30/DD30-1 -> #DIV/0! | DH30: =+DC30/DD30-1 -> #DIV/0! | DJ30: =SUM(D30,J30,P30,V30,AD30,AL30,AU30,BC30,BK30,BT30,CB30,CJ30)-CR30 -> 0 | DK30: =SUM(E30,K30,Q30,W30,AE30,AM30,AV30,BD30,BL30,BU30,CC30,CK30)-CS30 -> 0 | DL30: =SUM(G30,M30,S30,AA30,AI30,AR30,AZ30,BH30,BQ30,BY30,CG30,CO30)-CW30 -> 0 | DM30: =SUM(D30,J30,P30,V30,AD30,AL30,AU30,BC30,,BN30,BV30,CD30,CL30)-CT30 -> 0 | DX30: =(CS30-CZ30)*10^6 -> 0 | DY30: =(CT30-DC30)*10^6 -> 0 | DZ30: =(CW30-DD30)*10^6 -> 0
B31: vers MTN | C31: TRAF25 | CU31: =CR31-CS31 -> 0 | CV31: =CR31-CT31 -> 0 | CX31: =IFERROR(CR31/CW31-1, "-") -> - | DE31: =+CZ31/DD31-1 -> #DIV/0! | DF31: =+DA31/DD31-1 -> #DIV/0! | DG31: =+DB31/DD31-1 -> #DIV/0! | DH31: =+DC31/DD31-1 -> #DIV/0! | DJ31: =SUM(D31,J31,P31,V31,AD31,AL31,AU31,BC31,BK31,BT31,CB31,CJ31)-CR31 -> 0 | DK31: =SUM(E31,K31,Q31,W31,AE31,AM31,AV31,BD31,BL31,BU31,CC31,CK31)-CS31 -> 0 | DL31: =SUM(G31,M31,S31,AA31,AI31,AR31,AZ31,BH31,BQ31,BY31,CG31,CO31)-CW31 -> 0 | DM31: =SUM(D31,J31,P31,V31,AD31,AL31,AU31,BC31,,BN31,BV31,CD31,CL31)-CT31 -> 0 | DX31: =(CS31-CZ31)*10^6 -> 0 | DY31: =(CT31-DC31)*10^6 -> 0 | DZ31: =(CW31-DD31)*10^6 -> 0
B32: vers SBIN | C32: TRAF26 | CU32: =CR32-CS32 -> 0 | CV32: =CR32-CT32 -> 0 | CX32: =IFERROR(CR32/CW32-1, "-") -> - | DJ32: =SUM(D32,J32,P32,V32,AD32,AL32,AU32,BC32,BK32,BT32,CB32,CJ32)-CR32 -> 0 | DK32: =SUM(E32,K32,Q32,W32,AE32,AM32,AV32,BD32,BL32,BU32,CC32,CK32)-CS32 -> 0 | DL32: =SUM(G32,M32,S32,AA32,AI32,AR32,AZ32,BH32,BQ32,BY32,CG32,CO32)-CW32 -> 0 | DM32: =SUM(D32,J32,P32,V32,AD32,AL32,AU32,BC32,,BN32,BV32,CD32,CL32)-CT32 -> 0 | DX32: =(CS32-CZ32)*10^6 -> 0 | DY32: =(CT32-DC32)*10^6 -> 0 | DZ32: =(CW32-DD32)*10^6 -> 0
B33: vers BBCOM, LIBERCOM | C33: TRAF27 | CU33: =CR33-CS33 -> 0 | CV33: =CR33-CT33 -> 0 | CX33: =IFERROR(CR33/CW33-1, "-") -> - | DJ33: =SUM(D33,J33,P33,V33,AD33,AL33,AU33,BC33,BK33,BT33,CB33,CJ33)-CR33 -> 0 | DK33: =SUM(E33,K33,Q33,W33,AE33,AM33,AV33,BD33,BL33,BU33,CC33,CK33)-CS33 -> 0 | DL33: =SUM(G33,M33,S33,AA33,AI33,AR33,AZ33,BH33,BQ33,BY33,CG33,CO33)-CW33 -> 0 | DM33: =SUM(D33,J33,P33,V33,AD33,AL33,AU33,BC33,,BN33,BV33,CD33,CL33)-CT33 -> 0 | DX33: =(CS33-CZ33)*10^6 -> 0 | DY33: =(CT33-DC33)*10^6 -> 0 | DZ33: =(CW33-DD33)*10^6 -> 0
B34: Outbound roaming | C34: TRAF28 | CU34: =CR34-CS34 -> 0 | CV34: =CR34-CT34 -> 0 | CX34: =IFERROR(CR34/CW34-1, "-") -> - | DJ34: =SUM(D34,J34,P34,V34,AD34,AL34,AU34,BC34,BK34,BT34,CB34,CJ34)-CR34 -> 0 | DK34: =SUM(E34,K34,Q34,W34,AE34,AM34,AV34,BD34,BL34,BU34,CC34,CK34)-CS34 -> 0 | DL34: =SUM(G34,M34,S34,AA34,AI34,AR34,AZ34,BH34,BQ34,BY34,CG34,CO34)-CW34 -> 0 | DM34: =SUM(D34,J34,P34,V34,AD34,AL34,AU34,BC34,,BN34,BV34,CD34,CL34)-CT34 -> 0 | DX34: =(CS34-CZ34)*10^6 -> 0 | DY34: =(CT34-DC34)*10^6 -> 0 | DZ34: =(CW34-DD34)*10^6 -> 0
C35: TRAF29 | CX35: =IFERROR(CR35/CW35-1, "-") -> - | DJ35: =SUM(D35,J35,P35,V35,AD35,AL35,AU35,BC35,BK35,BT35,CB35,CJ35)-CR35 -> 0 | DK35: =SUM(E35,K35,Q35,W35,AE35,AM35,AV35,BD35,BL35,BU35,CC35,CK35)-CS35 -> 0 | DL35: =SUM(G35,M35,S35,AA35,AI35,AR35,AZ35,BH35,BQ35,BY35,CG35,CO35)-CW35 -> 0 | DM35: =SUM(D35,J35,P35,V35,AD35,AL35,AU35,BC35,,BN35,BV35,CD35,CL35)-CT35 -> 0 | DX35: =(CS35-CZ35)*10^6 -> 0 | DY35: =(CT35-DC35)*10^6 -> 0 | DZ35: =(CW35-DD35)*10^6 -> 0
B36: Business Postpaid | C36: TRAF30 | CU36: =CR36-CS36 -> 0 | CV36: =CR36-CT36 -> 0 | CX36: =IFERROR(CR36/CW36-1, "-") -> - | DE36: =+CZ36/DD36-1 -> #DIV/0! | DF36: =+DA36/DD36-1 -> #DIV/0! | DG36: =+DB36/DD36-1 -> #DIV/0! | DH36: =+DC36/DD36-1 -> #DIV/0! | DJ36: =SUM(D36,J36,P36,V36,AD36,AL36,AU36,BC36,BK36,BT36,CB36,CJ36)-CR36 -> 0 | DK36: =SUM(E36,K36,Q36,W36,AE36,AM36,AV36,BD36,BL36,BU36,CC36,CK36)-CS36 -> 0 | DL36: =SUM(G36,M36,S36,AA36,AI36,AR36,AZ36,BH36,BQ36,BY36,CG36,CO36)-CW36 -> 0 | DM36: =SUM(D36,J36,P36,V36,AD36,AL36,AU36,BC36,,BN36,BV36,CD36,CL36)-CT36 -> 0 | DX36: =(CS36-CZ36)*10^6 -> 0 | DY36: =(CT36-DC36)*10^6 -> 0 | DZ36: =(CW36-DD36)*10^6 -> 0
B37: vers le fixe | C37: TRAF31 | CU37: =CR37-CS37 -> 0 | CV37: =CR37-CT37 -> 0 | CX37: =IFERROR(CR37/CW37-1, "-") -> - | DE37: =+CZ37/DD37-1 -> #DIV/0! | DF37: =+DA37/DD37-1 -> #DIV/0! | DG37: =+DB37/DD37-1 -> #DIV/0! | DH37: =+DC37/DD37-1 -> #DIV/0! | DJ37: =SUM(D37,J37,P37,V37,AD37,AL37,AU37,BC37,BK37,BT37,CB37,CJ37)-CR37 -> 0 | DK37: =SUM(E37,K37,Q37,W37,AE37,AM37,AV37,BD37,BL37,BU37,CC37,CK37)-CS37 -> 0 | DL37: =SUM(G37,M37,S37,AA37,AI37,AR37,AZ37,BH37,BQ37,BY37,CG37,CO37)-CW37 -> 0 | DM37: =SUM(D37,J37,P37,V37,AD37,AL37,AU37,BC37,,BN37,BV37,CD37,CL37)-CT37 -> 0 | DX37: =(CS37-CZ37)*10^6 -> 0 | DY37: =(CT37-DC37)*10^6 -> 0 | DZ37: =(CW37-DD37)*10^6 -> 0
B38: vers l'international | C38: TRAF32 | CU38: =CR38-CS38 -> 0 | CV38: =CR38-CT38 -> 0 | CX38: =IFERROR(CR38/CW38-1, "-") -> - | DE38: =+CZ38/DD38-1 -> #DIV/0! | DF38: =+DA38/DD38-1 -> #DIV/0! | DG38: =+DB38/DD38-1 -> #DIV/0! | DH38: =+DC38/DD38-1 -> #DIV/0! | DJ38: =SUM(D38,J38,P38,V38,AD38,AL38,AU38,BC38,BK38,BT38,CB38,CJ38)-CR38 -> 0 | DK38: =SUM(E38,K38,Q38,W38,AE38,AM38,AV38,BD38,BL38,BU38,CC38,CK38)-CS38 -> 0 | DL38: =SUM(G38,M38,S38,AA38,AI38,AR38,AZ38,BH38,BQ38,BY38,CG38,CO38)-CW38 -> 0 | DM38: =SUM(D38,J38,P38,V38,AD38,AL38,AU38,BC38,,BN38,BV38,CD38,CL38)-CT38 -> 0 | DX38: =(CS38-CZ38)*10^6 -> 0 | DY38: =(CT38-DC38)*10^6 -> 0 | DZ38: =(CW38-DD38)*10^6 -> 0
B39: vers Mobile (on net) | C39: TRAF33 | CU39: =CR39-CS39 -> 0 | CV39: =CR39-CT39 -> 0 | CX39: =IFERROR(CR39/CW39-1, "-") -> - | DE39: =+CZ39/DD39-1 -> #DIV/0! | DF39: =+DA39/DD39-1 -> #DIV/0! | DG39: =+DB39/DD39-1 -> #DIV/0! | DH39: =+DC39/DD39-1 -> #DIV/0! | DJ39: =SUM(D39,J39,P39,V39,AD39,AL39,AU39,BC39,BK39,BT39,CB39,CJ39)-CR39 -> 0 | DK39: =SUM(E39,K39,Q39,W39,AE39,AM39,AV39,BD39,BL39,BU39,CC39,CK39)-CS39 -> 0 | DL39: =SUM(G39,M39,S39,AA39,AI39,AR39,AZ39,BH39,BQ39,BY39,CG39,CO39)-CW39 -> 0 | DM39: =SUM(D39,J39,P39,V39,AD39,AL39,AU39,BC39,,BN39,BV39,CD39,CL39)-CT39 -> 0 | DX39: =(CS39-CZ39)*10^6 -> 0 | DY39: =(CT39-DC39)*10^6 -> 0 | DZ39: =(CW39-DD39)*10^6 -> 0
B40: vers MTN | C40: TRAF34 | CU40: =CR40-CS40 -> 0 | CV40: =CR40-CT40 -> 0 | CX40: =IFERROR(CR40/CW40-1, "-") -> - | DE40: =+CZ40/DD40-1 -> #DIV/0! | DF40: =+DA40/DD40-1 -> #DIV/0! | DG40: =+DB40/DD40-1 -> #DIV/0! | DH40: =+DC40/DD40-1 -> #DIV/0! | DJ40: =SUM(D40,J40,P40,V40,AD40,AL40,AU40,BC40,BK40,BT40,CB40,CJ40)-CR40 -> 0 | DK40: =SUM(E40,K40,Q40,W40,AE40,AM40,AV40,BD40,BL40,BU40,CC40,CK40)-CS40 -> 0 | DL40: =SUM(G40,M40,S40,AA40,AI40,AR40,AZ40,BH40,BQ40,BY40,CG40,CO40)-CW40 -> 0 | DM40: =SUM(D40,J40,P40,V40,AD40,AL40,AU40,BC40,,BN40,BV40,CD40,CL40)-CT40 -> 0 | DX40: =(CS40-CZ40)*10^6 -> 0 | DY40: =(CT40-DC40)*10^6 -> 0 | DZ40: =(CW40-DD40)*10^6 -> 0
B41: vers SBIN | C41: TRAF35 | CU41: =CR41-CS41 -> 0 | CV41: =CR41-CT41 -> 0 | CX41: =IFERROR(CR41/CW41-1, "-") -> - | DJ41: =SUM(D41,J41,P41,V41,AD41,AL41,AU41,BC41,BK41,BT41,CB41,CJ41)-CR41 -> 0 | DK41: =SUM(E41,K41,Q41,W41,AE41,AM41,AV41,BD41,BL41,BU41,CC41,CK41)-CS41 -> 0 | DL41: =SUM(G41,M41,S41,AA41,AI41,AR41,AZ41,BH41,BQ41,BY41,CG41,CO41)-CW41 -> 0 | DM41: =SUM(D41,J41,P41,V41,AD41,AL41,AU41,BC41,,BN41,BV41,CD41,CL41)-CT41 -> 0 | DX41: =(CS41-CZ41)*10^6 -> 0 | DY41: =(CT41-DC41)*10^6 -> 0 | DZ41: =(CW41-DD41)*10^6 -> 0
