Workbook
Name \e: #N/A
Name \M: #REF!
Name \M: #REF!
Name \M: #REF!
Name \M: #REF!
Name \M: #REF!
Name \M: #REF!
Name \p: '[1]Cur Q v Plan'!#REF!
Name \p: '[1]Cur Q v Plan'!#REF!
Name \p: '[1]Cur Q v Plan'!#REF!
Name \p: '[1]Cur Q v Plan'!#REF!
Name \p: '[1]Cur Q v Plan'!#REF!
Name \p: '[1]Cur Q v Plan'!#REF!
Name \r: #N/A
Name \t: #N/A
Name _: #REF!
Name _: #REF!
Name _: #REF!
Name _: #REF!
Name _: #REF!
Name _: #REF!
Name __: #REF!
Name __: #REF!
Name __: #REF!
Name __: #REF!
Name ___________B1: #N/A
Name ___________eng2: #N/A
Name ___________eng3: 'Data Mobile '!___________eng3
Name ___________eng3: 'Mobile Money'!___________eng3
Name ___________eng3: 'Data Mobile '!___________eng3
Name ___________eng4: #N/A
Name __________B1: #N/A
Name __________eng2: #N/A
Name __________eng3: 'Data Mobile '!__________eng3
Name __________eng3: 'Mobile Money'!__________eng3
Name __________eng3: 'Data Mobile '!__________eng3
Name __________eng4: #N/A
Name _________eng3: 'Data Mobile '!_________eng3
Name _________eng3: 'Mobile Money'!_________eng3
Name _________eng3: 'Data Mobile '!_________eng3
Name ________eng3: 'Data Mobile '!________eng3
Name ________eng3: 'Mobile Money'!________eng3
Name ________eng3: 'Data Mobile '!________eng3
Name _______eng3: 'Data Mobile '!_______eng3
Name _______eng3: 'Mobile Money'!_______eng3
Name _______eng3: 'Data Mobile '!_______eng3
Name ______eng3: 'Data Mobile '!______eng3
Name ______eng3: 'Mobile Money'!______eng3
Name ______eng3: 'Data Mobile '!______eng3
Name ______FRF4: '[2]FX Rates'!$G$10
Name ______FRF4: '[2]FX Rates'!$G$10
Name ______GBP4: '[2]FX Rates'!$G$9
Name ______GBP4: '[2]FX Rates'!$G$9
Name _____0: #REF!
Name _____0: #REF!
Name _____0: #REF!
Name _____0: #REF!
Name _____0: #REF!
Name _____12: #REF!
Name _____12: #REF!

Sheet ANALYSE
D4: ELEMENTS | E4: Actu2 | F4: Budget 24 | G4: Variation | J4: ELEMENTS | K4: ACTU2 | L4: Budget 24 | M4: Variation
D5: SORTANT PREPAID (VOIX, SMS, SVA) | E5: =+'CA Mobile'!O14 -> 41713.594 | F5: 42546.216 | G5: =+E5-F5 -> -832.62157 | K5: Coût | L5: Coût
D6: DATA | E6: =+'CA Mobile'!O136 -> 52607.642 | F6: 55738.929 | G6: =+E6-F6 -> -3131.2878 | J6: Commissions Distributeurs | K6: =+'Marge Mobile '!O36+'Marge Mobile '!O37 -> -7604.8287 | L6: -7649.091 | M6: =+K6-L6 -> 44.262322
D7: VENTE DE TERMINAUX | E7: =+'CA Mobile'!O170 -> 2246.6647 | F7: 1788 | G7: =+E7-F7 -> 458.66474 | J7: SVA | K7: =+'Marge Mobile '!O25 -> -374.89955 | L7: -442.21631 | M7: =+K7-L7 -> 67.316763
E8: =SUM(E5:E7) -> 96567.9 | F8: =SUM(F5:F7) -> 100073.14 | G8: =+E8-F8 -> -3505.2447 | J8: Achat de terminaux | K8: =+'Marge Mobile '!O31 -> -2021.9983 | L8: -1609.2 | M8: =+K8-L8 -> -412.79827
D9: SVA | E9: =+'CA Mobile'!O44+'CA Mobile'!O76+'CA Mobile'!O101+SUM('CA Mobile'!O123:O130) -> 1342.5418 | F9: 739.36062 | G9: =+E9-F9 -> 603.18117
D10: POSTPAID | E10: =+'CA Mobile'!O47 -> 3522.7874 | F10: 3720.9151 | G10: =+E10-F10 -> -198.12771
D11: ROAMING | E11: =+'CA Mobile'!O168 -> 1946.1155 | F11: 564.8223 | G11: =+E11-F11 -> 1381.2932 | J11: International sortant | K11: =+'Marge Mobile '!O11 -> -1987.96 | L11: -1651.9842 | M11: =+K11-L11 -> -335.97582
D12: LS ET VENTE DE CAPACITE | E12: =+'CA Mobile'!O135 -> 1762.1956 | F12: 840 | G12: =+E12-F12 -> 922.19558 | J12: Roaming out et interconnexion SMS | K12: =+'Marge Mobile '!O29+'Marge Mobile '!O28 -> -837.76983 | L12: -544.24674 | M12: =+K12-L12 -> -293.52308
D13: COLOCATION | E13: =+'CA Mobile'!O162 -> 864.16902 | F13: 1565.8803 | G13: =+E13-F13 -> -701.71126 | J13: Achat de capacité | K13: =+'Marge Mobile '!O20 -> -590.3613 | L13: 0 | M13: =+K13-L13 -> -590.3613
D14: ENTRANT INTERNATIONAL | E14: =+'CA Mobile'!O156 -> 2352.548 | F14: 2696.9631 | G14: =+E14-F14 -> -344.41501
E15: =SUM(E10:E14) -> 10447.816 | F15: =SUM(F10:F14) -> 9388.5808 | G15: =+E15-F15 -> 1059.2348 | J15: Commissions MM | K15: =+'Marge Mobile '!O38 -> -5233.6426 | L15: -4873.0681 | M15: =+K15-L15 -> -360.57449
D17: MOOV MONEY | E17: =+'CA Mobile'!O134 -> 7318.0478 | F17: 6437.8944 | G17: =+E17-F17 -> 880.15338 | J17: TOTAL | K17: =SUM(K6:K15) -> -18651.46 | L17: =SUM(L6:L15) -> -16769.806 | M17: =+K17-L17 -> -1881.6539
D19: TOTAL | E19: =+E8+E15+E17 -> 114333.76 | F19: =+F8+F15+F17 -> 115899.62 | G19: =+E19-F19 -> -1565.8564
J20: IMPACT MARGE | L20: SVA | M20: =+G9+M7 -> 670.49793
L21: DATA ET VOIX | M21: =+G5+G6+M6 -> -3919.6471
L22: INTERNATIONAL | M22: =+G14+M11 -> -680.39083
L23: CAPACITE | M23: =+G12+M13 -> 331.83428
M24: =SUM(M20:M23) -> -3597.7057

Sheet Cover
E15: MOOV BENIN BUDGET 2025
F5602: U | G5602: 1000 | H5602: U | I5602: XOF | J5602: 847 | K5602: 763 | L5602: 762712 | M5602: ONATEL
A5603: 41743 | B5603: FC DRC1150-014779 | C5603: BL DRC1150-002137 | D5603: DRC11500 | E5603: 1 | F5603: U | G5603: 1 | H5603: U | I5603: XOF | J5603: 848 | K5603: 848 | L5603: 848 | M5603: ONATEL
A5604: 41743 | B5604: FC DRC1150-014784 | C5604: BL DRC1150-002142 | D5604: DRC11500 | E5604: 42 | F5604: U | G5604: 42 | H5604: U | I5604: XOF | J5604: 847 | K5604: 847 | L5604: 35593 | M5604: ONATEL
A5605: 41744 | B5605: FC DRN5010-004909 | C5605: CC DRN5010-004906 | D5605: DI5010004 | E5605: 500 | F5605: U | G5605: 500 | H5605: U | I5605: XOF | J5605: 847 | K5605: 763 | L5605: 381356 | M5605: ONATEL
A5606: 41744 | B5606: FC DRC1130-008172 | C5606: CC DRC1130-008119 | D5606: DRC11300 | E5606: 1 | F5606: U | G5606: 1 | H5606: U | I5606: XOF | J5606: 848 | K5606: 848 | L5606: 848 | M5606: ONATEL
A5607: 41744 | B5607: FC DRC1080-004286 | C5607: CC DRC1080-004381 | D5607: DRC10800 | E5607: 3 | F5607: U | G5607: 3 | H5607: U | I5607: XOF | J5607: 847 | K5607: 847 | L5607: 2542 | M5607: ONATEL
A5608: 41744 | B5608: FC DRC1130-008174 | C5608: CC DRC1130-008121 | D5608: DRC11300 | E5608: 13 | F5608: U | G5608: 13 | H5608: U | I5608: XOF | J5608: 847 | K5608: 847 | L5608: 11016 | M5608: ONATEL
A5609: 41744 | B5609: FC DRC1150-014797 | C5609: CC DRC1150-015116 | D5609: DRC11500 | E5609: 1 | F5609: U | G5609: 1 | H5609: U | I5609: XOF | J5609: 848 | K5609: 848 | L5609: 848 | M5609: ONATEL
A5610: 41744 | B5610: FC DRC1110-004324 | C5610: CC DRC1110-004283 | D5610: DRC11100 | E5610: 1 | F5610: U | G5610: 1 | H5610: U | I5610: XOF | J5610: 848 | K5610: 848 | L5610: 848 | M5610: ONATEL
A5611: 41744 | B5611: FC DRO6070-000412 | C5611: CC DRO6070-000407 | D5611: DRO60700 | E5611: 1 | F5611: U | G5611: 1 | H5611: U | I5611: XOF | J5611: 848 | K5611: 848 | L5611: 848 | M5611: ONATEL
A5612: 41744 | B5612: FC DRC1150-014790 | C5612: CC DRC1150-015109 | D5612: DRC11500 | E5612: 8 | F5612: U | G5612: 8 | H5612: U | I5612: XOF | J5612: 848 | K5612: 848 | L5612: 6780 | M5612: ONATEL
A5613: 41744 | B5613: FC DRC1120-012603 | C5613: CC DRC1120-012589 | D5613: DI1120055 | E5613: 2000 | F5613: U | G5613: 2000 | H5613: U | I5613: XOF | J5613: 847 | K5613: 763 | L5613: 1525424 | M5613: ONATEL
A5614: 41744 | B5614: FC DRC1140-009616 | C5614: CC DRC1140-010229 | D5614: DRC11400 | E5614: 1 | F5614: U | G5614: 1 | H5614: U | I5614: XOF | J5614: 848 | K5614: 848 | L5614: 848 | M5614: ONATEL
A5615: 41744 | B5615: FC DRC1140-009619 | C5615: CC DRC1140-010232 | D5615: DRC11400 | E5615: 3 | F5615: U | G5615: 3 | H5615: U | I5615: XOF | J5615: 847

Sheet P&L conso
B1: P&L consolidé
C2: JANV | D2: FEV | E2: Mars | F2: AVR | G2: MAI | H2: JUIN | I2: JUIL | J2: AOUT | K2: SEPT | L2: OCT | M2: NOV | N2: DEC | O2: ANNUEL | S2: VARIATIONS
B3: (En Millions ML) | C3: 2025 Budget | D3: 2025 Budget | E3: 2025 Budget | F3: 2025 Budget | G3: 2025 Budget | H3: 2025 Budget | I3: 2025 Budget | J3: 2025 Budget | K3: 2025 Budget | L3: 2025 Budget | M3: 2025 Budget | N3: 2025 Budget | O3: 2025 Budget | P3: 2024 Actu3 | Q3: 2023 Réel | R3: Budget initial | S3: Var Budget 25 vs Actu 3. % | T3: Var Actu 3 2024 vs Réel 2023. % | U3: Var Budget 2025 vs Budget 2024. % | AG3: Annuel
AC4: (En Millions Dh) | AG4: 2023 Réel | AH4: 2024 Actu3 | AI4: Budget 2025 | AJ4: A3 / 2023 (%) | AK4: B25 / A3 (%)
B5: Chiffre d'affaires | C5: =C7 -> 9527.0891 | D5: =D7 -> 8782.1227 | E5: =E7 -> 9473.1389 | F5: =F7 -> 9362.5379 | G5: =G7 -> 9772.4636 | H5: =H7 -> 9466.6859 | I5: =I7 -> 9614.0551 | J5: =J7 -> 9618.2497 | ... N5: =N7 -> 10293.443 | O5: =SUM(C5,D5,E5,F5,G5,H5,I5,J5,K5,L5,M5,N5) -> 114333.76 | P5: 108391.85 | Q5: 105542.99 | R5: 115899.62 | S5: =O5/P5-1 -> 0.054818851 | T5: =P5/Q5-1 -> 0.026992374 | U5: =O5/R5-1 -> -0.013510454 | V5: 108887.36 | W5: =P5-V5 -> -495.5082 | AG5: =+AG8-Q5 -> 0 | AH5: =AH8-P5 -> 495.5082 | AI5: =AI8-O5 -> 0.00026070813
B6: Fixe & Internet | C6: 0 | D6: 0 | E6: 0 | F6: 0 | G6: 0 | H6: 0 | I6: 0 | J6: 0 | K6: 0 | L6: 0 | M6: 0 | N6: 0 | Q6: 0 | T6: =P6/Q6-1 -> #DIV/0! | W6: =P6-V6 -> 0 | AC6: Chiffre d'affaires | AG6: 105542.99 | AH6: 108887.36 | AI6: 114333.76 | AJ6: 0.031687221 | AK6: 0.050018743
B7: Mobile | C7: =C8 -> 9527.0891 | D7: =D8 -> 8782.1227 | E7: =E8 -> 9473.1389 | F7: =F8 -> 9362.5379 | G7: =G8 -> 9772.4636 | H7: =H8 -> 9466.6859 | I7: =I8 -> 9614.0551 | J7: =J8 -> 9618.2497 | ... O7: =O8 -> 114333.76 | P7: 108391.85 | Q7: =Q8 -> 105542.99 | R7: 115899.62 | S7: =O7/P7-1 -> 0.054818851 | T7: =P7/Q7-1 -> 0.026992374 | U7: =O7/R7-1 -> -0.013510454 | V7: 108887.36 | W7: =P7-V7 -> -495.5082 | AD7: Fixe & Internet | AJ7: #DIV/0! | AK7: #DIV/0!
B8: Intercompagnie Mobile | C8: ='CA Mobile'!C7 -> 9527.0891 | D8: ='CA Mobile'!D7 -> 8782.1227 | E8: ='CA Mobile'!E7 -> 9473.1389 | F8: ='CA Mobile'!F7 -> 9362.5379 | G8: ='CA Mobile'!G7 -> 9772.4636 | H8: ='CA Mobile'!H7 -> 9466.6859 | I8: ='CA Mobile'!I7 -> 9614.0551 | J8: ='CA Mobile'!J7 -> 9618.2497 | ... O8: ='CA Mobile'!O7 -> 114333.76 | P8: 108391.85 | Q8: =+Q5 -> 105542.99 | R8: 115899.62 | S8: =O8/P8-1 -> 0.054818851 | T8: =P8/Q8-1 -> 0.026992374 | U8: =O8/R8-1 -> -0.013510454 | V8: 108887.36 | W8: =P8-V8 -> -495.5082 | AD8: Mobile | AG8: 105542.99 | AH8: 108887.36 | AI8: 114333.76 | AJ8: 0.031687221 | AK8: 0.050018743
C9: 0 | D9: 0 | E9: 0 | F9: 0 | G9: 0 | H9: 0 | I9: 0 | J9: 0 | K9: 0 | L9: 0 | M9: 0 | N9: 0 | Q9: 0 | S9: =O9-Q9 -> 0 | T9: =P9/Q9-1 -> #DIV/0! | U9: =O9/R9-1 -> #DIV/0! | W9: =P9-V9 -> 0
B10: Intercompagnie | C10: 0 | D10: 0 | E10: 0 | F10: 0 | G10: 0 | H10: 0 | I10: 0 | J10: 0 | K10: 0 | L10: 0 | M10: 0 | N10: 0 | Q10: 0 | S10: =O10-Q10 -> 0 | T10: =P10/Q10-1 -> #DIV/0! | U10: =O10/R10-1 -> #DIV/0! | W10: =P10-V10 -> 0 | AD10: Intercompagnie | AJ10: #DIV/0! | AK10: #DIV/0!
B11: dont Intercompagnie hors trafic | C11: 0 | D11: 0 | E11: 0 | F11: 0 | G11: 0 | H11: 0 | I11: 0 | J11: 0 | K11: 0 | L11: 0 | M11: 0 | N11: 0 | Q11: 0 | S11: =O11-Q11 -> 0 | T11: =P11/Q11-1 -> #DIV/0! | U11: =O11/R11-1 -> #DIV/0! | W11: =P11-V11 -> 0 | AD11: dont intercompagnie hors trafic
C12: 0 | D12: 0 | E12: 0 | F12: 0 | G12: 0 | H12: 0 | I12: 0 | J12: 0 | K12: 0 | L12: 0 | M12: 0 | N12: 0 | P12: -7.2000003e-05 | Q12: 0 | S12: =O12-Q12 -> 0 | V12: 0 | W12: =P12-V12 -> -7.2000003e-05 | AG12: =AG13+Q13 -> 0 | AH12: =+AH13+P13 -> 49.564045 | AI12: =+AI13+O13 -> 0
B13: Coût des ventes | C13: =C15 -> -1517.7256 | D13: =D15 -> -1459.5803 | E13: =E15 -> -1580.7997 | F13: =F15 -> -1545.981 | G13: =G15 -> -1578.2509 | H13: =H15 -> -1551.4919 | I13: =I15 -> -1581.9014 | J13: =J15 -> -1573.4276 | ... N13: =N15 -> -1637.9559 | O13: =SUM(C13,D13,E13,F13,G13,H13,I13,J13,K13,L13,M13,N13) -> -18651.46 | P13: -17895.733 | Q13: -15895.604 | R13: -16769.806 | S13: =O13/P13-1 -> 0.042229479 | T13: =P13/Q13-1 -> 0.12582906 | U13: =O13/R13-1 -> 0.11220487 | V13: -17945.297 | W13: =P13-V13 -> 49.564045 | AD13: Coût des ventes | AG13: 15895.604 | AH13: 17945.297 | AI13: 18651.46 | AJ13: 0.12894716 | AK13: 0.039350891
B14: Fixe & Internet | Q14: 0 | S14: =O14-Q14 -> 0 | T14: =P14/Q14-1 -> #DIV/0! | W14: =P14-V14 -> 0 | AD14: Fixe & Internet | AJ14: #DIV/0! | AK14: #DIV/0!
B15: Mobile | C15: =C16 -> -1517.7256 | D15: =D16 -> -1459.5803 | E15: =E16 -> -1580.7997 | F15: =F16 -> -1545.981 | G15: =G16 -> -1578.2509 | H15: =H16 -> -1551.4919 | I15: =I16 -> -1581.9014 | J15: =J16 -> -1573.4276 | ... N15: =N16 -> -1637.9559 | O15: =O13 -> -18651.46 | P15: -17895.733 | Q15: -15895.604 | R15: -16769.806 | S15: =O15/P15-1 -> 0.042229479 | T15: =P15/Q15-1 -> 0.12582906 | U15: =O15/R15-1 -> 0.11220487 | V15: -17945.297 | W15: =P15-V15 -> 49.564045 | AD15: Mobile | AG15: 15895.604 | AH15: 17945.297 | AI15: 18651.46 | AJ15: 0.12894716 | AK15: 0.039350891
B16: Intercompagnie Mobile | C16: ='Marge Mobile '!C39 -> -1517.7256 | D16: ='Marge Mobile '!D39 -> -1459.5803 | E16: ='Marge Mobile '!E39 -> -1580.7997 | F16: ='Marge Mobile '!F39 -> -1545.981 | G16: ='Marge Mobile '!G39 -> -1578.2509 | H16: ='Marge Mobile '!H39 -> -1551.4919 | I16: ='Marge Mobile '!I39 -> -1581.9014 | J16: ='Marge Mobile '!J39 -> -1573.4276 | ... N16: ='Marge Mobile '!N39 -> -1637.9559 | O16: =O13 -> -18651.46 | P16: -17895.733 | Q16: -15895.604 | R16: -16769.806 | S16: =O16/P16-1 -> 0.042229479 | T16: =P16/Q16-1 -> 0.12582906 | U16: =O16/R16-1 -> 0.11220487 | V16: -17945.297 | W16: =P16-V16 -> 49.564045 | AG16: =+Q18-AG17 -> 0 | AH16: =AH17-P18 -> 445.94416 | AI16: =AI17-O18 -> 0.00026070813
C17: 0 | D17: 0 | E17: 0 | F17: 0 | G17: 0 | H17: 0 | I17: 0 | J17: 0 | K17: 0 | L17: 0 | M17: 0 | N17: 0 | P17: 0.092828847 | Q17: 0 | S17: =O17-Q17 -> 0 | V17: 0 | W17: =P17-V17 -> 0.092828847 | AC17: Marge Brute | AG17: 89647.387 | AH17: 90942.059 | AI17: 95682.304 | AJ17: 0.014441817 | AK17: 0.052123795
B18: Marge Brute | C18: =C5+C13 -> 8009.3634 | D18: =D5+D13 -> 7322.5424 | E18: =E5+E13 -> 7892.3393 | F18: =F5+F13 -> 7816.5569 | G18: =G5+G13 -> 8194.2127 | H18: =H5+H13 -> 7915.194 | I18: =I5+I13 -> 8032.1538 | J18: =J5+J13 -> 8044.8221 | ... N18: =N5+N13 -> 8655.4868 | O18: =+O5+O13 -> 95682.303 | P18: 90496.114 | Q18: 89647.387 | R18: 99129.814 | S18: =O18/P18-1 -> 0.057308417 | T18: =P18/Q18-1 -> 0.0094673922 | U18: =O18/R18-1 -> -0.034777734 | V18: 90942.059 | W18: =P18-V18 -> -445.94416 | AD18: % | AG18: 0.84939214 | AH18: 0.83519393 | AI18: 0.83686831 | AJ18: -1.4198209 | AK18: 0.16743764
B19: % CA | C19: =C18/C5 -> 0.84069366 | D19: =D18/D5 -> 0.83380097 | E19: =E18/E5 -> 0.83312821 | F19: =F18/F5 -> 0.83487586 | G19: =G18/G5 -> 0.8385002 | H19: =H18/H5 -> 0.83611034 | I19: 0.73060125 | J19: =J18/J5 -> 0.83641227 | K19: =K18/K5 -> 0.83585444 | L19: =L18/L5 -> 0.83786985 | M19: =M18/M5 -> 0.83816198 | N19: =N18/N5 -> 0.84087385 | O19: =+O18/O5 -> 0.83686831 | P19: 0.8348978 | Q19: 0.84939214 | R19: 0.8553075 | S19: =O19/P19-1 -> 0.0023601834 | T19: =P19/Q19-1 -> -0.017064374 | U19: =O19/R19-1 -> -0.021558546 | V19: 0.83519393 | W19: =P19-V19 -> -0.00029613586 | AD19: Fixe & Internet | AJ19: #DIV/0! | AK19: #DIV/0!
B20: Fixe & Internet | S20: =O20-Q20 -> 0 | T20: =P20/Q20-1 -> #DIV/0! | W20: =P20-V20 -> 0 | AD20: % | AG20: #DIV/0! | AH20: #DIV/0! | AI20: #DIV/0! | AJ20: #DIV/0! | AK20: #DIV/0!
B21: Mobile | C21: =C18 -> 8009.3634 | D21: =D18 -> 7322.5424 | E21: =E18 -> 7892.3393 | F21: =F18 -> 7816.5569 | G21: =G18 -> 8194.2127 | H21: =H18 -> 7915.194 | I21: =I18 -> 8032.1538 | J21: =J18 -> 8044.8221 | ... N21: =N18 -> 8655.4868 | O21: =+O7+O15 -> 95682.303 | P21: 90496.114 | Q21: 89647.387 | R21: 99129.814 | S21: =O21/P21-1 -> 0.057308417 | T21: =P21/Q21-1 -> 0.0094673922 | U21: =O21/R21-1 -> -0.034777734 | V21: 90942.059 | W21: =P21-V21 -> -445.94416 | AD21: Mobile | AJ21: #DIV/0! | AK21: #DIV/0!
C22: 0 | D22: 0 | E22: 0 | F22: 0 | G22: 0 | H22: 0 | I22: 0 | J22: 0 | K22: 0 | L22: 0 | M22: 0 | N22: 0 | Q22: 0 | S22: =O22-Q22 -> 0 | W22: =P22-V22 -> 0 | AD22: % | AG22: 0 | AH22: 0 | AI22: 0 | AJ22: 0 | AK22: 0
B23: Coûts opérationnels | C23: =C26 -> -5752.8634 | D23: =D26 -> -5412.0079 | E23: =E26 -> -5658.8042 | F23: =F26 -> -5772.0206 | G23: =G26 -> -5682.373 | H23: =H26 -> -5580.6859 | I23: =I26 -> -5830.1077 | J23: =J26 -> -5690.6091 | ... N23: =N26 -> -5706.9963 | O23: =SUM(C23,D23,E23,F23,G23,H23,I23,J23,K23,L23,M23,N23) -> -67535.531 | P23: -64651.048 | Q23: -61867.1 | R23: -69069.6 | S23: =O23/P23-1 -> 0.044616185 | T23: =P23/Q23-1 -> 0.044998838 | U23: =O23/R23-1 -> -0.022210486 | V23: -64817.051 | W23: =P23-V23 -> 166.00342 | AG23: =+Q29-AG26 -> 0 | AH23: =AH26-P29 -> 279.75958 | AI23: =AI26-O29 -> 0.010710858
B24: Fixe & Internet | C24: 0 | D24: 0 | E24: 0 | F24: 0 | G24: 0 | H24: 0 | I24: 0 | J24: 0 | K24: 0 | L24: 0 | M24: 0 | N24: 0 | Q24: 0 | S24: =O24-Q24 -> 0 | W24: =P24-V24 -> 0 | AD24: Coûts opérationnels | AG24: 61867.1 | AH24: 64817.232 | AI24: 67535.52 | AJ24: 0.047684992 | AK24: 0.041937738
B25: Intercompagnie Fixe & Internet | C25: 0 | D25: 0 | E25: 0 | F25: 0 | G25: 0 | H25: 0 | I25: 0 | J25: 0 | K25: 0 | L25: 0 | M25: 0 | N25: 0 | Q25: 0 | S25: =O25-Q25 -> 0 | W25: =P25-V25 -> 0
B26: Mobile | C26: =C27 -> -5752.8634 | D26: =D27 -> -5412.0079 | E26: =E27 -> -5658.8042 | F26: =F27 -> -5772.0206 | G26: =G27 -> -5682.373 | H26: =H27 -> -5580.6859 | I26: =I27 -> -5830.1077 | J26: =J27 -> -5690.6091 | ... N26: =N27 -> -5706.9963 | O26: =+O27 -> -67535.531 | P26: -64651.048 | Q26: -61867.1 | R26: -69069.6 | S26: =O26/P26-1 -> 0.044616185 | T26: =P26/Q26-1 -> 0.044998838 | U26: =O26/R26-1 -> -0.022210486 | V26: -64817.232 | W26: =P26-V26 -> 166.18458 | AC26: EBITDA | AG26: 27780.287 | AH26: 26124.826 | AI26: 28146.783 | AJ26: -0.059591214 | AK26: 0.077396001
B27: Intercompagnie Mobile | C27: =-'Opex Consolidés'!C7 -> -5752.8634 | D27: =-'Opex Consolidés'!D7 -> -5412.0079 | E27: =-'Opex Consolidés'!E7 -> -5658.8042 | F27: =-'Opex Consolidés'!F7 -> -5772.0206 | G27: =-'Opex Consolidés'!G7 -> -5682.373 | H27: =-'Opex Consolidés'!H7 -> -5580.6859 | I27: =-'Opex Consolidés'!I7 -> -5830.1077 | J27: =-'Opex Consolidés'!J7 -> -5690.6091 | ... N27: =-'Opex Consolidés'!N7 -> -5706.9963 | O27: =SUM(C27,D27,E27,F27,G27,H27,I27,J27,K27,L27,M27,N27) -> -67535.531 | P27: -64651.048 | Q27: -61867.1 | R27: -69069.6 | S27: =O27/P27-1 -> 0.044616185 | T27: =P27/Q27-1 -> 0.044998838 | U27: =O27/R27-1 -> -0.022210486 | V27: -64817.232 | W27: =P27-V27 -> 166.18458 | AD27: % | AG27: 0.263213 | AH27: 0.23992525 | AI27: 0.24618085 | AJ27: -2.3287747 | AK27: 0.62555985
C28: 0 | D28: 0 | E28: 0 | F28: 0 | G28: 0 | H28: 0 | I28: 0 | J28: 0 | K28: 0 | L28: 0 | M28: 0 | N28: 0 | S28: =O28-Q28 -> 0 | W28: =P28-V28 -> 0
B29: EBITDA | C29: =C18+C23 -> 2256.5 | D29: =D18+D23 -> 1910.5345 | E29: =E18+E23 -> 2233.5351 | F29: =F18+F23 -> 2044.5363 | G29: =G18+G23 -> 2511.8397 | H29: =H18+H23 -> 2334.508 | I29: =I18+I23 -> 2202.0461 | J29: =J18+J23 -> 2354.213 | ... N29: =N18+N23 -> 2948.4905 | O29: =SUM(C29:N29) -> 28146.773 | P29: 25845.067 | Q29: 27780.287 | R29: 30060.214 | S29: =O29/P29-1 -> 0.089057845 | T29: =P29/Q29-1 -> -0.069661649 | U29: =O29/R29-1 -> -0.063653603 | V29: 26125.008 | W29: =P29-V29 -> -279.94074 | AD29: Amortissements et déprec. des immob | AG29: 18266.7 | AH29: 20724.23 | AI29: 21341.659 | AJ29: 0.13453607 | AK29: 0.02979264
B30: % CA | C30: =C29/C5 -> 0.23685094 | D30: =D29/D5 -> 0.21754815 | E30: =E29/E5 -> 0.23577561 | F30: =F29/F5 -> 0.21837416 | G30: =G29/G5 -> 0.25703239 | H30: =H29/H5 -> 0.24660246 | I30: =I29/I5 -> 0.22904446 | J30: =J29/J5 -> 0.24476522 | ... O30: =O29/O5 -> 0.24618076 | P30: 0.23844106 | Q30: 0.263213 | R30: 0.25936421 | S30: =O30/P30-1 -> 0.032459596 | T30: =P30/Q30-1 -> -0.094113671 | U30: =O30/R30-1 -> -0.050829884 | V30: 0.23992692 | W30: =P30-V30 -> -0.0014858588 | AD30: Autres non courant | AJ30: #DIV/0! | AK30: #DIV/0!
B31: Fixe & Internet | C31: 0 | D31: 0 | E31: 0 | F31: 0 | G31: 0 | H31: 0 | I31: 0 | J31: 0 | K31: 0 | L31: 0 | M31: 0 | N31: 0 | Q31: 0 | S31: =O31-Q31 -> 0 | T31: =P31/Q31-1 -> #DIV/0! | W31: =P31-V31 -> 0 | AD31: Restructuration | AJ31: #DIV/0! | AK31: #DIV/0!
B32: Mobile | C32: =C18+C23 -> 2256.5 | D32: =D18+D23 -> 1910.5345 | E32: =E18+E23 -> 2233.5351 | F32: =F18+F23 -> 2044.5363 | G32: =G18+G23 -> 2511.8397 | H32: =H18+H23 -> 2334.508 | I32: =I18+I23 -> 2202.0461 | J32: =J18+J23 -> 2354.213 | ... N32: =N18+N23 -> 2948.4905 | O32: =+O21+O26 -> 28146.773 | P32: 25845.067 | Q32: 27780.287 | R32: 30060.214 | S32: =O32/P32-1 -> 0.089057845 | T32: =P32/Q32-1 -> -0.069661649 | U32: =O32/R32-1 -> -0.063653603 | V32: 26125.1 | W32: =P32-V32 -> -280.03364
C33: 0 | D33: 0 | E33: 0 | F33: 0 | G33: 0 | H33: 0 | I33: 0 | J33: 0 | K33: 0 | L33: 0 | M33: 0 | N33: 0 | Q33: 0 | S33: =O33-Q33 -> 0 | W33: =P33-V33 -> 0
B34: Amortissements et déprec. Courant | C34: -1755 | D34: -1774.631 | E34: -1774.631 | F34: -1732.131 | G34: -1754.9927 | H34: -1752.6683 | I34: -1746.2313 | J34: -1723.2073 | K34: -1735.4531 | L34: -1773.4636 | M34: -1778.2972 | N34: -1785.9531 | O34: =SUM(C34,D34,E34,F34,G34,H34,I34,J34,K34,L34,M34,N34) -> -21086.659 | P34: -20724.23 | Q34: -18266.7 | R34: -20248.648 | S34: =O34/P34-1 -> 0.017488202 | T34: =P34/Q34-1 -> 0.13453607 | U34: =O34/R34-1 -> 0.041386067 | V34: -20724.23 | W34: =P34-V34 -> 0 | AC34: EBITA | AG34: 9513.5874 | AH34: 5400.5964 | AI34: 6805.1239 | AJ34: -0.43232809 | AK34: 0.26006897
B35: Dotations (Amo. et Pv NC) | C35: 0 | D35: 0 | E35: 0 | F35: 0 | G35: 0 | H35: 0 | I35: 0 | J35: 0 | K35: 0 | L35: 0 | M35: 0 | N35: 0 | O35: =SUM(C35,D35,E35,F35,G35,H35,I35,J35,K35,L35,M35,N35) -> 0 | P35: 0 | Q35: 0 | R35: 0 | S35: =O35-Q35 -> 0 | V35: 0 | W35: =P35-V35 -> 0 | AD35: % | AG35: 0.090139452 | AH35: 0.049598012 | AI35: 0.05951981 | AJ35: -4.054144 | AK35: 0.99217981
B36: Autres non courant | C36: 0 | D36: 0 | E36: 0 | F36: 0 | G36: 0 | H36: 0 | I36: 0 | J36: 0 | K36: 0 | L36: 0 | M36: 0 | N36: 0 | O36: =SUM(C36,D36,E36,F36,G36,H36,I36,J36,K36,L36,M36,N36) -> 0 | P36: 0 | Q36: 0 | R36: 0 | S36: =O36-Q36 -> 0 | V36: 0 | W36: =P36-V36 -> 0
B37: +/- value de cession d'immob. | C37: -1.8e-05 | D37: 0.31512 | E37: 0 | F37: 0 | G37: 0 | H37: 0 | I37: 0 | J37: 0 | K37: 0 | L37: 0 | M37: 0 | N37: 0 | O37: 0 | P37: 0 | Q37: 0 | R37: 0 | S37: =O37-Q37 -> 0 | V37: 0 | W37: =P37-V37 -> 0 | AD37: Résultat financier | AG37: -3438.403 | AH37: -3866.1186 | AI37: -3986 | AJ37: 0.12439368 | AK37: 0.031008207
C38: 0 | D38: 0 | E38: 0 | F38: 0 | G38: 0 | H38: 0 | I38: 0 | J38: 0 | K38: 0 | L38: 0 | M38: 0 | N38: 0 | S38: =O38-Q38 -> 0 | W38: =P38-V38 -> 0
B39: EBITA | C39: =C29+C34 -> 501.49997 | D39: =D29+D34 -> 135.90357 | E39: =E29+E34 -> 458.90413 | F39: =F29+F34 -> 312.40536 | G39: =G29+G34 -> 756.84703 | H39: =H29+H34 -> 581.83976 | I39: =I29+I34 -> 455.81478 | J39: =J29+J34 -> 631.00572 | ... N39: =N29+N34 -> 1162.5374 | O39: =+O29+O34+O35+O36+O37 -> 7060.1132 | P39: 5120.8368 | Q39: 9513.5874 | R39: 9811.566 | S39: =O39/P39-1 -> 0.37870303 | T39: =P39/Q39-1 -> -0.4617344 | U39: =O39/R39-1 -> -0.28042952 | V39: 5400.7775 | W39: =P39-V39 -> -279.94074 | AD39: Contribution Covid | AJ39: #DIV/0! | AK39: #DIV/0!
B40: % CA | C40: =C39/C5 -> 0.052639371 | D40: =D39/D5 -> 0.015475025 | E40: =E39/E5 -> 0.048442669 | F40: =F39/F5 -> 0.033367594 | G40: =G39/G5 -> 0.077446901 | H40: =H39/H5 -> 0.061461822 | I40: =I39/I5 -> 0.047411293 | J40: =J39/J5 -> 0.065605047 | ... N40: =N39/N5 -> 0.11293961 | O40: =+O39/O5 -> 0.061750029 | P40: 0.047243745 | Q40: 0.090139452 | R40: 0.084655722 | S40: =O40/P40-1 -> 0.30705195 | T40: =P40/Q40-1 -> -0.4758816 | U40: =O40/R40-1 -> -0.27057466 | V40: 0.049599676 | W40: =P40-V40 -> -0.0023559308
B41: Fixe & Internet | C41: 0 | D41: 0 | E41: 0 | F41: 0 | G41: 0 | H41: 0 | I41: 0 | J41: 0 | K41: 0 | L41: 0 | M41: 0 | N41: 0 | Q41: 0 | S41: =O41-Q41 -> 0 | W41: =P41-V41 -> 0 | AC41: RESULTAT avant IS | AG41: 6075.1844 | AH41: 1534.4778 | AI41: 2819.1239 | AJ41: 2.9591218 | AK41: -0.45568985
B42: Mobile | C42: 0 | D42: 0 | E42: 0 | F42: 0 | G42: 0 | H42: 0 | I42: 0 | J42: 0 | K42: 0 | L42: 0 | M42: 0 | N42: 0 | Q42: 0 | S42: =O42-Q42 -> 0 | W42: =P42-V42 -> 0 | AD42: IS | AG42: 1068.8041 | AH42: 1088.7108 | AI42: 1143.3376 | AJ42: 0.018625216 | AK42: 0.050175703
C43: 0 | D43: 0 | E43: 0 | F43: 0 | G43: 0 | H43: 0 | I43: 0 | J43: 0 | K43: 0 | L43: 0 | M43: 0 | N43: 0 | Q43: 0 | S43: =O43-Q43 -> 0 | T43: =P43/Q43-1 -> #DIV/0! | W43: =P43-V43 -> 0 | AD43: ID | AG43: -110.37584 | AH43: -127.25439 | AI43: -54 | AJ43: 0.15291883 | AK43: -0.57565314
C44: 0 | D44: 0 | E44: 0 | F44: 0 | G44: 0 | H44: 0 | I44: 0 | J44: 0 | K44: 0 | L44: 0 | M44: 0 | N44: 0 | Q44: 0 | S44: =O44-Q44 -> 0 | W44: =P44-V44 -> 0
B45: Résultat financier | C45: -333.5 | D45: -333.5 | E45: =((+-288+5)+4.5)-50 -> -328.5 | F45: =(+-283.5+1)-50 -> -332.5 | G45: -333.5 | H45: =((+-288+5)+4.5)-50 -> -328.5 | I45: -333.5 | J45: -333.5 | K45: =((+-288+5)+4.5)-50 -> -328.5 | L45: -333.5 | M45: -333.5 | N45: -333.5 | O45: =SUM(C45,D45,E45,F45,G45,H45,I45,J45,K45,L45,M45,N45) -> -3986 | P45: -3866.1186 | Q45: -3438.403 | R45: -3140.6196 | S45: =O45/P45-1 -> 0.031008208 | T45: =P45/Q45-1 -> 0.12439368 | U45: =O45/R45-1 -> 0.2691763 | V45: -3866.1186 | W45: =P45-V45 -> 1.9999998e-06 | AC45: RESULTAT NET | AG45: 4896.0044 | AH45: 318.51258 | AI45: 1621.7863 | AJ45: -0.93494438 | AK45: 4.0917496
B46: dont intérêt sur comptes sequestres MM | C46: =669429401/1000000/12 -> 55.785783 | D46: =669429401/1000000/12 -> 55.785783 | E46: =669429401/1000000/12 -> 55.785783 | F46: =669429401/1000000/12 -> 55.785783 | G46: =669429401/1000000/12 -> 55.785783 | H46: =669429401/1000000/12 -> 55.785783 | I46: =669429401/1000000/12 -> 55.785783 | J46: =669429401/1000000/12 -> 55.785783 | ... N46: =669429401/1000000/12 -> 55.785783 | O46: =SUM(C46,D46,E46,F46,G46,H46,I46,J46,K46,L46,M46,N46) -> 669.4294 | P46: 200 | Q46: 0 | R46: 780 | T46: =P46/Q46-1 -> #DIV/0! | U46: =O46/R46-1 -> -0.14175718 | V46: 250 | W46: =P46-V46 -> -50 | AD46: % | AG46: 0.046388722 | AH46: 0.0029251567 | AI46: 0.014184666 | AJ46: -4.3463565 | AK46: 1.125951
O47: =SUM(C47,D47,E47,F47,G47,H47,I47,J47,K47,L47,M47,N47) -> 0 | Q47: 0 | S47: =O47-Q47 -> 0 | W47: =P47-V47 -> 0
B48: RESULTAT avant IS | C48: =C39+C45 -> 167.99997 | D48: =D39+D45 -> -197.59643 | E48: =E39+E45 -> 130.40413 | F48: =F39+F45 -> -20.094637 | G48: =G39+G45 -> 423.34703 | H48: =H39+H45 -> 253.33976 | I48: =I39+I45 -> 122.31478 | J48: =J39+J45 -> 297.50572 | ... N48: =N39+N45 -> 829.03743 | O48: =SUM(C48,D48,E48,F48,G48,H48,I48,J48,K48,L48,M48,N48) -> 3074.1132 | P48: 1254.7182 | Q48: 6075.1844 | R48: 6670.9464 | S48: =O48/P48-1 -> 1.4500427 | T48: =P48/Q48-1 -> -0.79346829 | U48: =O48/R48-1 -> -0.53917884 | V48: 1534.6589 | W48: =P48-V48 -> -279.94074
B49: IS | C49: =-'CA Mobile'!C7*1% -> -95.270891 | D49: =-'CA Mobile'!D7*1% -> -87.821227 | E49: =-'CA Mobile'!E7*1% -> -94.731389 | F49: =-'CA Mobile'!F7*1% -> -93.625379 | G49: =-'CA Mobile'!G7*1% -> -97.724636 | H49: =-'CA Mobile'!H7*1% -> -94.666859 | I49: =-'CA Mobile'!I7*1% -> -96.140551 | J49: =-'CA Mobile'!J7*1% -> -96.182497 | ... N49: =-'CA Mobile'!N7*1% -> -102.93443 | O49: =SUM(C49,D49,E49,F49,G49,H49,I49,J49,K49,L49,M49,N49) -> -1143.3376 | P49: -1083.9185 | Q49: -1068.8041 | R49: -1158.9962 | S49: =O49/P49-1 -> 0.054818852 | T49: =P49/Q49-1 -> 0.014141384 | U49: =O49/R49-1 -> -0.013510454 | V49: -1088.7108 | W49: =P49-V49 -> 4.7923386
B50: ID | C50: -4.5 | D50: -4.5 | E50: -4.5 | F50: -4.5 | G50: -4.5 | H50: -4.5 | I50: -4.5 | J50: -4.5 | K50: -4.5 | L50: -4.5 | M50: -4.5 | N50: -4.5 | O50: =SUM(C50,D50,E50,F50,G50,H50,I50,J50,K50,L50,M50,N50) -> -54 | P50: -127.25439 | Q50: -110.37584 | R50: 20.579719 | S50: =O50/P50-1 -> -0.57565314 | T50: =P50/Q50-1 -> 0.15291883 | U50: =O50/R50-1 -> -3.6239425 | V50: -127.25439 | W50: =P50-V50 -> 0
C51: 0 | D51: 0 | E51: 0 | F51: 0 | G51: 0 | H51: 0 | I51: 0 | J51: 0 | K51: 0 | L51: 0 | M51: 0 | N51: 0 | S51: =O51-Q51 -> 0 | W51: =P51-V51 -> 0
B52: RESULTAT NET | C52: =C48+C49+C50 -> 68.229082 | D52: =D48+D49+D50 -> -289.91766 | E52: =E48+E49+E50 -> 31.172745 | F52: =F48+F49+F50 -> -118.22002 | G52: =G48+G49+G50 -> 321.12239 | H52: =H48+H49+H50 -> 154.1729 | I52: =I48+I49+I50 -> 21.674233 | J52: =J48+J49+J50 -> 196.82323 | ... N52: =N48+N49+N50 -> 721.603 | O52: =SUM(C52,D52,E52,F52,G52,H52,I52,J52,K52,L52,M52,N52) -> 1876.7756 | P52: 43.545344 | Q52: 4896.0044 | R52: 5532.5299 | S52: NS | T52: =P52/Q52-1 -> -0.99110594 | U52: =O52/R52-1 -> -0.66077443 | V52: 318.69374 | W52: =P52-V52 -> -275.1484
B54: % CA | C54: 0.039260561 | D54: 0.014215891 | E54: 0.061006981 | F54: 0.025746494 | G54: -0.039058344 | H54: 0.0093352554 | I54: -2 | J54: 0.024091527 | K54: 0.017193086 | L54: 0.035099869 | M54: 0.053800338 | N54: 0.070166926 | O54: =+O52/O5 -> 0.016414885 | P54: 0.00040174003 | Q54: 0.046388722 | R54: 0.047735531 | S54: NS | T54: =P54/Q54-1 -> -0.9913397 | U54: =O54/R54-1 -> -0.65612857 | V54: 0.0029268205 | W54: =P54-V54 -> -0.0025250805
C56: 0 | D56: 0 | E56: 0 | F56: 0 | G56: 0 | H56: 0 | I56: 0 | J56: 0 | K56: 0 | L56: 0 | M56: 0 | N56: 0 | O56: 394.35214
C57: 0 | D57: 0 | E57: 0 | F57: 0 | G57: 0 | H57: 0 | I57: 0 | J57: 0 | K57: 0 | L57: 0 | M57: 0 | N57: 0
C58: 0 | D58: 0 | E58: 0 | F58: 0 | G58: 0 | H58: 0 | I58: 0 | J58: 0 | K58: 0 | L58: 0 | M58: 0 | N58: 0
C59: 0 | D59: 0 | E59: 0 | F59: 0 | G59: 0 | H59: 0 | I59: 0 | J59: 0 | K59: 0 | L59: 0 | M59: 0 | N59: 0
C61: 4.5 | E61: 8.3812291 | N61: 6564.8615 | O61: 254.9428 | Q61: =O39+14 -> 7074.1132
D62: -34.900989 | E62: -38.134445 | G62: =E62-SUM(C50:G50) -> -15.634445 | I62: 400 | J62: 175 | L62: 37.520816 | M62: -7199.4188 | O62: -992.60105 | S62: 527.50216
N63: 65.862452 | Q63: -161.94217
H64: 2.823868
H65: 790.6086
H66: 960.56501
H67: 936.11865
H68: =SUM(H64:H67) -> 2690.1161
B86: intercompagnie intern fixe vers telmob | C86: 4.9631861e+08 | D86: 4.9631861e+08 | E86: 4.9631861e+08
B87: interco Telmob après supression inter entrant | C87: -76720802 | D87: -76720802 | E87: -76720802
B90: Interco CA Transit Telmob vers International | C90: 2.6827647e+08 | D90: 2.6827647e+08 | E90: 2.6827647e+08
B92: interco Onatel après supression CA Transit Telmob vers International | C92: -5.0539117e+08 | D92: -5.0539117e+08 | E92: -5.0539117e+08

Sheet Opex Consolidés
K1: 18
A2: Opex Consolidés
C4: JANVIER | D4: FEVRIER | E4: MARS | F4: AVRIL | G4: MAI | H4: JUIN | I4: JUILLET | J4: AOUT | K4: SEPT | L4: OCT | M4: NOV | N4: DEC | O4: ANNUEL | S4: VARIATIONS
B5: (En Millions ML) | C5: 2025 Budget | D5: 2025 Budget | E5: 2025 Budget | F5: 2025 Budget | G5: 2025 Budget | H5: 2025 Budget | I5: 2025 Budget | J5: 2025 Budget | K5: 2025 Budget | L5: 2025 Budget | M5: 2025 Budget | N5: 2025 Budget | O5: 2025 Budget | P5: 2024 Actu 3 | Q5: 2023 Réel | R5: Budget initial | S5: Var Budget Actu 3. % | T5: Var Actu 3 vs Réel 23. % | U5: Var Budget 2025 vs Budget 2024. %
B7: Total Opex | C7: =SUM(C9,C11,C13,C22,C30,C36,C42) -> 5752.8634 | D7: =SUM(D9,D11,D13,D22,D30,D36,D42) -> 5412.0079 | E7: =SUM(E9,E11,E13,E22,E30,E36,E42) -> 5658.8042 | F7: =SUM(F9,F11,F13,F22,F30,F36,F42) -> 5772.0206 | G7: =SUM(G9,G11,G13,G22,G30,G36,G42) -> 5682.373 | H7: =SUM(H9,H11,H13,H22,H30,H36,H42) -> 5580.6859 | I7: =SUM(I9,I11,I13,I22,I30,I36,I42) -> 5830.1077 | J7: =SUM(J9,J11,J13,J22,J30,J36,J42) -> 5690.6091 | ... N7: =SUM(N9,N11,N13,N22,N30,N36,N42) -> 5706.9963 | O7: =SUM(C7,D7,E7,F7,G7,H7,I7,J7,K7,L7,M7,N7) -> 67535.531 | P7: 64651.048 | Q7: 61867.1 | R7: 69069.6 | S7: =O7/P7-1 -> 0.044616185 | T7: =P7/Q7-1 -> 0.044998838 | U7: =O7/R7-1 -> -0.022210486 | W7: 64817.122 | X7: =P7-W7 -> -166.07461
C8: 0 | D8: 0 | E8: 0 | F8: 0 | G8: 0 | H8: 0 | I8: 0 | J8: 0 | K8: 0 | L8: 0 | M8: 0 | N8: 0 | X8: =P8-W8 -> 0
B9: Personnel | C9: 437.22587 | D9: 437.22587 | E9: 437.22587 | F9: 452.22587 | G9: 437.22587 | H9: 437.22587 | I9: 452.22587 | J9: 437.22587 | K9: 437.22587 | L9: 452.22587 | M9: 437.22587 | N9: 452.03587 | O9: =SUM(C9,D9,E9,F9,G9,H9,I9,J9,K9,L9,M9,N9) -> 5306.5205 | P9: 5064.8381 | Q9: 4761.3279 | R9: 5078.2318 | S9: =O9/P9-1 -> 0.04771769 | T9: =P9/Q9-1 -> 0.063744858 | U9: =O9/R9-1 -> 0.044954359 | W9: 5064.8381 | X9: =P9-W9 -> 0
Q10: 0 | X10: =P10-W10 -> 0
B11: Communication | C11: 284.29255 | D11: 281.99255 | E11: 281.99255 | F11: 289.29255 | G11: 281.99255 | H11: 281.99255 | I11: 300.99255 | J11: 281.99255 | K11: 281.99255 | L11: 289.29255 | M11: 281.99255 | N11: 307.29255 | O11: =SUM(C11,D11,E11,F11,G11,H11,I11,J11,K11,L11,M11,N11) -> 3445.1106 | P11: 3438.8998 | Q11: 3337.1979 | R11: 3439.3611 | S11: =O11/P11-1 -> 0.0018060305 | T11: =P11/Q11-1 -> 0.030475238 | U11: =O11/R11-1 -> 0.0016716723 | W11: 3438.8998 | X11: =P11-W11 -> 0
X12: =P12-W12 -> 0
B13: Exploitation & maintenance | C13: =C14+C15+C16+C18+C19 -> 1768.4753 | D13: =D14+D15+D16+D18+D19 -> 1737.3645 | E13: =E14+E15+E16+E18+E19 -> 1726.6695 | F13: =F14+F15+F16+F18+F19 -> 1714.1927 | G13: =G14+G15+G16+G18+G19 -> 1713.7202 | H13: =H14+H15+H16+H18+H19 -> 1732.334 | I13: =I14+I15+I16+I18+I19 -> 1769.6852 | J13: =J14+J15+J16+J18+J19 -> 1769.9477 | ... N13: =N14+N15+N16+N18+N19 -> 1589.2547 | O13: =SUM(C13,D13,E13,F13,G13,H13,I13,J13,K13,L13,M13,N13) -> 20292.074 | P13: 19379.8 | Q13: 17558.215 | R13: 20385.578 | S13: =O13/P13-1 -> 0.047073405 | T13: =P13/Q13-1 -> 0.10374551 | U13: =O13/R13-1 -> -0.0045867789 | W13: 19379.6 | X13: =P13-W13 -> 0.20016
B14: Achat d'énergie - Bâtiment - Gardiennage | C14: 864.64316 | D14: 833.26986 | E14: 821.96986 | F14: 806.11361 | G14: 804.61361 | H14: 821.85736 | I14: 841.34486 | J14: 841.34486 | K14: 709.95989 | L14: 711.65364 | M14: 703.34739 | N14: 706.88193 | O14: =SUM(C14,D14,E14,F14,G14,H14,I14,J14,K14,L14,M14,N14) -> 9467 | P14: 8822.3339 | Q14: 7999.3604 | R14: 9117.9995 | S14: =O14/P14-1 -> 0.073072055 | T14: =P14/Q14-1 -> 0.10287992 | U14: =O14/R14-1 -> 0.038275995 | W14: 8822.3339 | X14: =P14-W14 -> 0
B15: Lignes et réseaux (entretien & achats) | C15: 591.38042 | D15: 591.64292 | E15: 592.24792 | F15: 595.62742 | G15: 596.65492 | H15: 598.02492 | I15: 604.2248 | J15: 604.4873 | K15: 557.44492 | L15: 557.70742 | M15: 557.96992 | N15: 558.31992 | O15: =SUM(C15,D15,E15,F15,G15,H15,I15,J15,K15,L15,M15,N15) -> 7005.7328 | P15: 6471.8001 | Q15: 5895.2442 | R15: 6344.0146 | S15: =O15/P15-1 -> 0.082501411 | T15: =P15/Q15-1 -> 0.097800184 | U15: =O15/R15-1 -> 0.10430591 | W15: 6471.6 | X15: =P15-W15 -> 0.20016
B16: Fees du contrat GMNS | C16: 129.42982 | D16: 129.42982 | E16: 129.42982 | F16: 129.42982 | G16: 129.42982 | H16: 129.42982 | I16: 141.09371 | J16: 141.09371 | K16: 141.09371 | L16: 141.09371 | M16: 141.09371 | N16: 141.09371 | O16: =SUM(C16,D16,E16,F16,G16,H16,I16,J16,K16,L16,M16,N16) -> 1623.1412 | P16: 2203.8709 | Q16: 2329.7488 | R16: 2744.8641 | S16: =O16/P16-1 -> -0.2635044 | T16: =P16/Q16-1 -> -0.054030682 | U16: =O16/R16-1 -> -0.40866245 | W16: 2203.8709 | X16: =P16-W16 -> 0
B17: Fees du contrat IHS (spécifique à CDI) | O17: =SUM(C17,D17,E17,F17,G17,H17,I17,J17,K17,L17,M17,N17) -> 0 | P17: 0 | R17: 0 | S17: =O17-P17 -> 0 | W17: 0 | X17: =P17-W17 -> 0
B18: Matériel de transport (Entretien et locat°) | C18: 9.0052297 | D18: 9.0052297 | E18: 9.0052297 | F18: 9.0052297 | G18: 9.0052297 | H18: 9.0052297 | I18: 9.0052297 | J18: 9.0052297 | K18: 9.0052297 | L18: 9.0052297 | M18: 9.0052297 | N18: 8.9424737 | O18: =SUM(C18,D18,E18,F18,G18,H18,I18,J18,K18,L18,M18,N18) -> 108 | P18: 82.546802 | Q18: 84.490408 | R18: 97.5 | S18: =O18/P18-1 -> 0.30834869 | T18: =P18/Q18-1 -> -0.023003869 | U18: =O18/R18-1 -> 0.10769231 | W18: 82.546802 | X18: =P18-W18 -> 0
B19: Maintenance informatique | C19: 174.01664 | D19: 174.01664 | E19: 174.01664 | F19: 174.01664 | G19: 174.01664 | H19: 174.01664 | I19: 174.01664 | J19: 174.01664 | K19: 174.01664 | L19: 174.01664 | M19: 174.01664 | N19: 174.01664 | O19: =SUM(C19,D19,E19,F19,G19,H19,I19,J19,K19,L19,M19,N19) -> 2088.1997 | P19: 1799.2487 | Q19: 1249.3708 | R19: 2081.1997 | S19: =O19/P19-1 -> 0.16059535 | T19: =P19/Q19-1 -> 0.44012386 | U19: =O19/R19-1 -> 0.0033634446 | W19: 1799.2487 | X19: =P19-W19 -> 0
X20: =P20-W20 -> 0
X21: =P21-W21 -> 0
B22: Frais généraux | C22: =C23+C24+C25+C26+C27 -> 399.65218 | D22: =D23+D24+D25+D26+D27 -> 312.04262 | E22: =E23+E24+E25+E26+E27 -> 338.62234 | F22: =F23+F24+F25+F26+F27 -> 500.54786 | G22: =G23+G24+G25+G26+G27 -> 334.79848 | H22: =H23+H24+H25+H26+H27 -> 301.84274 | I22: =I23+I24+I25+I26+I27 -> 452.52356 | J22: =J23+J24+J25+J26+J27 -> 338.04521 | ... N22: =N23+N24+N25+N26+N27 -> 353.06783 | O22: =SUM(C22,D22,E22,F22,G22,H22,I22,J22,K22,L22,M22,N22) -> 4414.8809 | P22: 3942.5188 | Q22: 3069.902 | R22: 4532.7765 | S22: =O22/P22-1 -> 0.11981225 | T22: =P22/Q22-1 -> 0.28424911 | U22: =O22/R22-1 -> -0.026009585 | W22: 4241.9469 | X22: =P22-W22 -> -299.42804
B23: Frais d'achats d'études, honoraires | C23: 274.14083 | D23: 193.14083 | E23: 200.14083 | F23: 332.89083 | G23: 206.95083 | H23: 176.64083 | I23: 282.89083 | J23: 197.14083 | K23: 187.14083 | L23: 174.89083 | M23: 294.14083 | N23: 175.89083 | O23: =SUM(C23,D23,E23,F23,G23,H23,I23,J23,K23,L23,M23,N23) -> 2696 | P23: 2462.1368 | Q23: 2249.0254 | R23: 2701.3903 | S23: =O23/P23-1 -> 0.094983827 | T23: =P23/Q23-1 -> 0.094757242 | U23: =O23/R23-1 -> -0.001995368 | W23: 2735.1368 | X23: =P23-W23 -> -273
B24: Management fees | C24: 85.055817 | D24: 78.446262 | E24: 85.714381 | F24: 86.189905 | G24: 87.392121 | H24: 84.746383 | I24: 88.165605 | J24: 88.273161 | K24: 87.847669 | L24: 86.825801 | M24: 90.513926 | N24: 95.709873 | O24: =SUM(C24,D24,E24,F24,G24,H24,I24,J24,K24,L24,M24,N24) -> 1044.8809 | P24: 672.11907 | Q24: 244.33975 | R24: 1043.0966 | S24: =O24/P24-1 -> 0.55460683 | T24: =P24/Q24-1 -> 1.7507562 | U24: =O24/R24-1 -> 0.0017106022 | W24: 698.54711 | X24: =P24-W24 -> -26.428037
B25: Transport, déplacement, mission | C25: 14.166667 | D25: 14.166667 | E25: 14.166667 | F25: 14.166667 | G25: 14.166667 | H25: 14.166667 | I25: 14.166667 | J25: 14.166667 | K25: 14.166667 | L25: 14.166667 | M25: 14.166667 | N25: 14.166667 | O25: =SUM(C25,D25,E25,F25,G25,H25,I25,J25,K25,L25,M25,N25) -> 170 | P25: 173.84879 | Q25: 257.91308 | R25: 252.802 | S25: =O25/P25-1 -> -0.022138733 | T25: =P25/Q25-1 -> -0.32594039 | U25: =O25/R25-1 -> -0.32753697 | W25: 173.84879 | X25: =P25-W25 -> 0
B26: Frais postaux, bancaires et assurances | C26: 6.2888588 | D26: 6.2888588 | E26: 18.600459 | F26: 47.300459 | G26: 6.2888588 | H26: 6.2888588 | I26: 47.300459 | J26: 18.464553 | K26: 6.2888588 | L26: 47.300459 | M26: 6.2888588 | N26: 47.300459 | O26: =SUM(C26,D26,E26,F26,G26,H26,I26,J26,K26,L26,M26,N26) -> 264 | P26: 387.91185 | Q26: 271.45921 | R26: 479.08769 | S26: =O26/P26-1 -> -0.31943302 | T26: =P26/Q26-1 -> 0.42898763 | U26: =O26/R26-1 -> -0.44895266 | W26: 387.91185 | X26: =P26-W26 -> 0
B27: Achats de mat. et fournitures consom. | C27: 20 | D27: 20 | E27: 20 | F27: 20 | G27: 20 | H27: 20 | I27: 20 | J27: 20 | K27: 20 | L27: 20 | M27: 20 | N27: 20 | O27: =SUM(C27,D27,E27,F27,G27,H27,I27,J27,K27,L27,M27,N27) -> 240 | P27: 246.5023 | Q27: 47.164529 | R27: 56.4 | S27: =O27/P27-1 -> -0.026378241 | T27: =P27/Q27-1 -> 4.226434 | U27: =O27/R27-1 -> 3.2553191 | W27: 246.5023 | X27: =P27-W27 -> 0
X28: =P28-W28 -> 0
X29: =P29-W29 -> 0
B30: Impôts, taxes et redevances | C30: =+C31+C33 -> 2838.468 | D30: =+D31+D33 -> 2618.6328 | E30: =+E31+E33 -> 2849.5444 | F30: =+F31+F33 -> 2791.012 | G30: =+G31+G33 -> 2889.8863 | H30: =+H31+H33 -> 2802.5413 | I30: =+I31+I33 -> 2829.9309 | J30: =+J31+J33 -> 2838.6482 | ... N30: =+N31+N33 -> 2980.5958 | O30: =SUM(C30,D30,E30,F30,G30,H30,I30,J30,K30,L30,M30,N30) -> 33779.951 | P30: 32432.759 | Q30: 32006.456 | R30: 35342.359 | S30: =O30/P30-1 -> 0.041537992 | T30: =P30/Q30-1 -> 0.013319294 | U30: =O30/R30-1 -> -0.044207825 | W30: 32299.606 | X30: =P30-W30 -> 133.15326
B31: Redevances régulateur | C31: 2676.5734 | D31: 2454.2935 | E31: 2685.3963 | F31: 2624.4416 | G31: 2724.2273 | H31: 2637.5465 | I31: 2665.8633 | J31: 2674.2719 | K31: 2569.6951 | L31: 2687.2893 | M31: 2590.7904 | N31: 2815.8981 | O31: =SUM(C31,D31,E31,F31,G31,H31,I31,J31,K31,L31,M31,N31) -> 31806.287 | P31: 30475.692 | Q31: 30140.154 | R31: 33258.638 | S31: =O31/P31-1 -> 0.043660842 | T31: =P31/Q31-1 -> 0.011132614 | U31: =O31/R31-1 -> -0.043668386 | W31: 30342.539 | X31: =P31-W31 -> 133.15326
B32: Droits sur le trafic International Entrant | O32: =SUM(C32,D32,E32,F32,G32,H32,I32,J32,K32,L32,M32,N32) -> 0 | R32: 0 | X32: =P32-W32 -> 0
B33: Autres impôts et taxes | C33: 161.89465 | D33: 164.33932 | E33: 164.14816 | F33: 166.57042 | G33: 165.65905 | H33: 164.99472 | I33: 164.06759 | J33: 164.37632 | K33: 164.14621 | L33: 164.5967 | M33: 164.17308 | N33: 164.69773 | O33: =SUM(C33,D33,E33,F33,G33,H33,I33,J33,K33,L33,M33,N33) -> 1973.6639 | P33: 1957.0666 | Q33: 1866.3019 | R33: 2083.7218 | S33: =O33/P33-1 -> 0.0084806977 | T33: =P33/Q33-1 -> 0.048633447 | U33: =O33/R33-1 -> -0.052817907 | W33: 1957.0666 | X33: =P33-W33 -> 0
X34: =P34-W34 -> 0
X35: =P35-W35 -> 0
B36: Provision clients, R&C & NC | C36: =C37+C38+C39 -> 24.749544 | D36: =D37+D38+D39 -> 24.749544 | E36: =E37+E38+E39 -> 24.749544 | F36: =F37+F38+F39 -> 24.749544 | G36: =G37+G38+G39 -> 24.749544 | H36: =H37+H38+H39 -> 24.749544 | I36: =I37+I38+I39 -> 24.749544 | J36: =J37+J38+J39 -> 24.749544 | ... N36: =N37+N38+N39 -> 24.749544 | O36: =SUM(C36,D36,E36,F36,G36,H36,I36,J36,K36,L36,M36,N36) -> 296.99453 | P36: 390.82502 | Q36: 1126.97 | R36: 291.29348 | S36: =O36/P36-1 -> -0.24008312 | T36: =P36/Q36-1 -> -0.65320724 | U36: =O36/R36-1 -> 0.019571504 | W36: 390.82502 | X36: =P36-W36 -> 3e-06
B37: Prov. Créances clients | C37: 13.218288 | D37: 13.218288 | E37: 13.218288 | F37: 13.218288 | G37: 13.218288 | H37: 13.218288 | I37: 13.218288 | J37: 13.218288 | K37: 13.218288 | L37: 13.218288 | M37: 13.218288 | N37: 13.218288 | O37: =SUM(C37,D37,E37,F37,G37,H37,I37,J37,K37,L37,M37,N37) -> 158.61946 | P37: 273.5043 | Q37: -717.22245 | R37: 192 | S37: =O37/P37-1 -> -0.42004765 | T37: =P37/Q37-1 -> -1.3813382 | U37: =O37/R37-1 -> -0.17385698 | W37: 262.1169 | X37: =P37-W37 -> 11.387403
B38: Prov. R&C | C38: 0 | D38: 0 | E38: 0 | F38: 0 | G38: 0 | H38: 0 | I38: 0 | J38: 0 | K38: 0 | L38: 0 | M38: 0 | N38: 0 | O38: =SUM(C38,D38,E38,F38,G38,H38,I38,J38,K38,L38,M38,N38) -> 0 | P38: 0 | Q38: 0 | R38: 0 | W38: 11.3874 | X38: =P38-W38 -> -11.3874
B39: PIDR | C39: 11.531256 | D39: 11.531256 | E39: 11.531256 | F39: 11.531256 | G39: 11.531256 | H39: 11.531256 | I39: 11.531256 | J39: 11.531256 | K39: 11.531256 | L39: 11.531256 | M39: 11.531256 | N39: 11.531256 | O39: =SUM(C39,D39,E39,F39,G39,H39,I39,J39,K39,L39,M39,N39) -> 138.37507 | P39: 117.32072 | Q39: 8.34645 | R39: 99.29348 | S39: =O39/P39-1 -> 0.17945977 | T39: =P39/Q39-1 -> 13.056362 | U39: =O39/R39-1 -> 0.39359676 | W39: 117.32072 | X39: =P39-W39 -> 0
B40: Autres provisions | O40: =SUM(C40,D40,E40,F40,G40,H40,I40,J40,K40,L40,M40,N40) -> 0 | Q40: 1835.846 | R40: 0 | T40: =P40/Q40-1 -> -1 | X40: =P40-W40 -> 0
X41: =P41-W41 -> 0
B42: Ecart de change sur exploitation | C42: 0 | D42: 0 | E42: 0 | F42: 0 | G42: 0 | H42: 0 | I42: 0 | J42: 0 | K42: 0 | L42: 0 | M42: 0 | N42: 0 | O42: =SUM(C42,D42,E42,F42,G42,H42,I42,J42,K42,L42,M42,N42) -> 0 | P42: 1.406461 | Q42: 7 | R42: 0 | W42: 1.406461 | X42: =P42-W42 -> 0

Sheet Feuil2
B1: AT CDI
B2: Activité Internationale Mobile
D4: Janvier | F4: AOUT | R4: SEPTEMBRE | AD4: OCTOBRE | AP4: NOVEMBRE | BB4: DECEMBRE | BM4: Fevrier | BO4: Mars | BQ4: AOUT | CC4: SEPTEMBRE | CO4: OCTOBRE | DA4: NOVEMBRE | DM4: DECEMBRE | DX4: Avril | DZ4: Mai | EB4: Juin | ED4: Juil | EF4: Août | EH4: Sept | EJ4: Oct | EL4: Nov | EN4: Déc
D5: 2017 Budget | F5: 2016 Réel | G5: 2016 Budget | H5: 2016 Actu 1 | I5: 2016 Actu 2 | J5: 2016 Actu 3 | K5: Ecart / Budget | L5: Ecart / Actu 1 | M5: Ecart / Actu 2 | N5: Ecart / Actu 3 | O5: 2015 Réel | P5: Evol % | R5: 2016 Réel | S5: 2016 Budget | T5: 2016 Actu 1 | U5: 2016 Actu 2 | V5: 2016 Actu 3 | W5: Ecart / Budget | X5: Ecart / Actu 1 | Y5: Ecart / Actu 2 | Z5: Ecart / Actu 3 | AA5: 2015 Réel | AB5: Evol % | AD5: 2016 Réel | AE5: 2016 Budget | AF5: 2016 Actu 1 | AG5: 2016 Actu 2 | AH5: 2016 Actu 3 | AI5: Ecart / Budget | AJ5: Ecart / Actu 1 | AK5: Ecart / Actu 2 | AL5: Ecart / Actu 3 | AM5: 2015 Réel | AN5: Evol % | AP5: 2016 Réel | AQ5: 2016 Budget | AR5: 2016 Actu 1 | AS5: 2016 Actu 2 | AT5: 2016 Actu 3 | AU5: Ecart / Budget | AV5: Ecart / Actu 1 | AW5: Ecart / Actu 2 | AX5: Ecart / Actu 3 | AY5: 2015 Réel | AZ5: Evol % | BB5: 2016 Réel | BC5: 2016 Budget | BD5: 2016 Actu 1 | BE5: 2016 Actu 2 | BF5: 2016 Actu 3 | BG5: Ecart / Budget | BH5: Ecart / Actu 1 | BI5: Ecart / Actu 2 | BJ5: Ecart / Actu 3 | BK5: 2015 Réel | BL5: Evol % | BM5: 2017 Budget | BO5: 2017 Budget | BQ5: 2016 Réel | BR5: 2016 Budget | BS5: 2016 Actu 1 | BT5: 2016 Actu 2 | BU5: 2016 Actu 3 | BV5: Ecart / Budget | BW5: Ecart / Actu 1 | BX5: Ecart / Actu 2 | BY5: Ecart / Actu 3 | BZ5: 2015 Réel | CA5: Evol % | CC5: 2016 Réel | CD5: 2016 Budget | CE5: 2016 Actu 1 | CF5: 2016 Actu 2 | CG5: 2016 Actu 3 | CH5: Ecart / Budget | CI5: Ecart / Actu 1 | CJ5: Ecart / Actu 2 | CK5: Ecart / Actu 3 | CL5: 2015 Réel | CM5: Evol % | CO5: 2016 Réel | CP5: 2016 Budget | CQ5: 2016 Actu 1 | CR5: 2016 Actu 2 | CS5: 2016 Actu 3 | CT5: Ecart / Budget | CU5: Ecart / Actu 1 | CV5: Ecart / Actu 2 | CW5: Ecart / Actu 3 | CX5: 2015 Réel | CY5: Evol % | DA5: 2016 Réel | DB5: 2016 Budget | DC5: 2016 Actu 1 | DD5: 2016 Actu 2 | DE5: 2016 Actu 3 | DF5: Ecart / Budget | DG5: Ecart / Actu 1 | DH5: Ecart / Actu 2 | DI5: Ecart / Actu 3 | DJ5: 2015 Réel | DK5: Evol % | DM5: 2016 Réel | DN5: 2016 Budget | DO5: 2016 Actu 1 | DP5: 2016 Actu 2 | DQ5: 2016 Actu 3 | DR5: Ecart / Budget | DS5: Ecart / Actu 1 | DT5: Ecart / Actu 2 | DU5: Ecart / Actu 3 | DV5: 2015 Réel | DW5: Evol % | DX5: 2017 Budget | DZ5: 2017 Budget | EB5: 2017 Budget | ED5: 2017 Budget | EF5: 2017 Budget | EH5: 2017 Budget | EJ5: 2017 Budget | EL5: 2017 Budget | EN5: 2017 Budget | EP5: 2017 Budget | EQ5: 2018 Budget | ER5: 2019 Budget | ES5: 2020 Budget | ET5: 2016 Actu 3 | EU5: Ecart / Actu 1 | EV5: Ecart / Actu 2 | EW5: Ecart / Actu 3 | EX5: Var Budget 2017 vs Actu 3 2016 . Val | EY5: Evol %
B6: Chiffre d'affaires (Millions de FCFA)
B7: Entrant International
B8: Voix
B9: dont direct
B10: dont transit
B11: vers concurents
B12: via concurents
B13: SMS
B15: Trafic (Millions de Minutes)
B16: Entrant International
B17: Voix
B18: dont direct
... B31: SMS

Sheet CA Mobile
C1: =SUM(C25,C33,C35,C44,C112,C122,C131) -> 7990.5954 | D1: =SUM(D25,D33,D35,D44,D112,D122,D131) -> 7269.5786 | E1: =SUM(E25,E33,E35,E44,E112,E122,E131) -> 7905.7983 | F1: =SUM(F25,F33,F35,F44,F112,F122,F131) -> 7759.0643 | G1: =SUM(G25,G33,G35,G44,G112,G122,G131) -> 8155.7259 | H1: =SUM(H25,H33,H35,H44,H112,H122,H131) -> 7840.9826 | I1: =SUM(I25,I33,I35,I44,I112,I122,I131) -> 7914.5657 | J1: =SUM(J25,J33,J35,J44,J112,J122,J131) -> 7934.2943 | ... N1: =SUM(N25,N33,N35,N44,N112,N122,N131) -> 8487.0194
A2: CA Mobile | C2: =SUM(C25,C33,C35,C44,C112,C120,C122,C131) -> 7990.9509 | D2: =SUM(D25,D33,D35,D44,D112,D120,D122,D131) -> 7269.8936 | E2: =SUM(E25,E33,E35,E44,E112,E120,E122,E131) -> 7906.1736 | F2: =SUM(F25,F33,F35,F44,F112,F120,F122,F131) -> 7765.7843 | G2: =SUM(G25,G33,G35,G44,G112,G120,G122,G131) -> 8156.0415 | H2: =SUM(H25,H33,H35,H44,H112,H120,H122,H131) -> 7841.2614 | I2: =SUM(I25,I33,I35,I44,I112,I120,I122,I131) -> 7914.8924 | J2: =SUM(J25,J33,J35,J44,J112,J120,J122,J131) -> 7934.5844 | ... N2: =SUM(N25,N33,N35,N44,N112,N120,N122,N131) -> 8487.3309 | O2: =+O7-99188 -> 15145.764 | Q2: =O7-P7 -> 5942.0094
C4: JANVIER | D4: FEVRIER | E4: MARS | F4: AVRIL | G4: MAI | H4: JUIN | I4: JUILLET | J4: AOUT | K4: SEPT | L4: OCT | M4: NOV | N4: DEC | O4: ANNUEL | S4: VARIATIONS
B5: (En Millions ML) | C5: 2025 Budget | D5: 2025 Budget | E5: 2025 Budget | F5: 2025 Budget | G5: 2025 Budget | H5: 2025 Budget | I5: 2025 Budget | J5: 2025 Budget | K5: 2025 Budget | L5: 2025 Budget | M5: 2025 Budget | N5: 2025 Budget | O5: 2025 Budget | P5: 2024 Actu 3 | Q5: 2023 Réel | R5: Budget 2024 | S5: Budget vs Actu 3. % | T5: Var Actu 3 vs réel 23. % | U5: Var Budget 2025 vs Budget 2024. %
C6: 9528.3391 | D6: 8783.3727 | E6: 9474.3889 | F6: 9363.7879 | G6: 9773.7136 | H6: 9467.9359 | I6: 9615.3051 | J6: 9619.4997 | K6: 9286.4369 | L6: 9721.6942 | M6: 9419.597 | N6: 10279.693
A7: CA Global | C7: =C9+C170 -> 9527.0891 | D7: =D9+D170 -> 8782.1227 | E7: =E9+E170 -> 9473.1389 | F7: =F9+F170 -> 9362.5379 | G7: =G9+G170 -> 9772.4636 | H7: =H9+H170 -> 9466.6859 | I7: =I9+I170 -> 9614.0551 | J7: =J9+J170 -> 9618.2497 | ... N7: =N9+N170 -> 10293.443 | O7: =SUM(C7,D7,E7,F7,G7,H7,I7,J7,K7,L7,M7,N7) -> 114333.76 | P7: 108391.75 | Q7: 105542.99 | R7: 115899.62 | S7: =O7/P7-1 -> 0.054819755 | T7: =P7/Q7-1 -> 0.026991494 | U7: =O7/R7-1 -> -0.013510454 | W7: 108887.36 | X7: =+P7-W7 -> -495.6011
X8: =+P8-W8 -> 0
A9: CA services Mobile | C9: =C11+C168 -> 9340.117 | D9: =D11+D168 -> 8595.1506 | E9: =E11+E168 -> 9286.1669 | F9: =F11+F168 -> 9175.5659 | G9: =G11+G168 -> 9585.4915 | H9: =H11+H168 -> 9278.7138 | I9: =I11+I168 -> 9427.0831 | J9: =J11+J168 -> 9430.2776 | ... N9: =N11+N168 -> 10105.471 | O9: =SUM(C9,D9,E9,F9,G9,H9,I9,J9,K9,L9,M9,N9) -> 112087.1 | P9: 106222.97 | Q9: 104258.6 | R9: 114111.62 | S9: =O9/P9-1 -> 0.055205842 | T9: =P9/Q9-1 -> 0.018841361 | U9: =O9/R9-1 -> -0.017741587 | W9: 106727.25 | X9: =+P9-W9 -> -504.2845
S10: =IFERROR(O10/#REF!-1,"") | X10: =+P10-W10 -> 0
A11: CA récurrent | C11: =SUM(C13,C140,C162) -> 9190.3209 | D11: =SUM(D13,D140,D162) -> 8457.9278 | E11: =SUM(E13,E140,E162) -> 9131.6851 | F11: =SUM(F13,F140,F162) -> 9023.3403 | G11: =SUM(G13,G140,G162) -> 9425.3998 | H11: =SUM(H13,H140,H162) -> 9120.928 | I11: =SUM(I13,I140,I162) -> 9261.1067 | J11: =SUM(J13,J140,J162) -> 9261.2516 | ... N11: =SUM(N13,N140,N162) -> 9920.8601 | O11: =SUM(C11,D11,E11,F11,G11,H11,I11,J11,K11,L11,M11,N11) -> 110140.98 | P11: 104772.04 | Q11: 103530.79 | R11: 113546.8 | S11: =O11/P11-1 -> 0.051244084 | T11: =P11/Q11-1 -> 0.011989195 | U11: =O11/R11-1 -> -0.029994808 | W11: 105257.38 | X11: =+P11-W11 -> -485.34531
S12: =IFERROR(O12/#REF!-1,"") | X12: =+P12-W12 -> 0
A13: CA sortant | C13: =C14+C47+C136+C134+C135 -> 8900.1169 | D13: =D14+D47+D136+D134+D135 -> 8185.5921 | E13: =E14+E47+E136+E134+E135 -> 8857.764 | F13: =F14+F47+F136+F134+F135 -> 8752.973 | G13: =G14+G47+G136+G134+G135 -> 9168.8618 | H13: =H14+H47+H136+H134+H135 -> 8852.6956 | I13: =I14+I47+I136+I134+I135 -> 8990.6143 | J13: =J14+J47+J136+J134+J135 -> 9002.7823 | ... N13: =N14+N47+N136+N134+N135 -> 9641.7925 | O13: =SUM(C13,D13,E13,F13,G13,H13,I13,J13,K13,L13,M13,N13) -> 106924.27 | P13: 101290.24 | Q13: 99912.622 | R13: 109283.95 | S13: =O13/P13-1 -> 0.055622578 | T13: =P13/Q13-1 -> 0.013788251 | U13: =O13/R13-1 -> -0.021592265 | W13: 101717.67 | X13: =+P13-W13 -> -427.42809
B14: Prépayé (yc commissions) | C14: =SUM(C16,C25,C33,C44) -> 3844.6975 | D14: =SUM(D16,D25,D33,D44) -> 3485.7674 | E14: =SUM(E16,E25,E33,E44) -> 3661.4635 | F14: =SUM(F16,F25,F33,F44) -> 3589.6058 | G14: =SUM(G16,G25,G33,G44) -> 3709.6789 | H14: =SUM(H16,H25,H33,H44) -> 3487.2954 | I14: =SUM(I16,I25,I33,I44) -> 3393.2811 | J14: =SUM(J16,J25,J33,J44) -> 3277.7306 | ... N14: =SUM(N16,N25,N33,N44) -> 3644.2647 | O14: =SUM(C14,D14,E14,F14,G14,H14,I14,J14,K14,L14,M14,N14) -> 41713.594 | P14: 42221.113 | Q14: 45973.654 | R14: 42546.216 | S14: =O14/P14-1 -> -0.012020505 | T14: =P14/Q14-1 -> -0.081623725 | U14: =O14/R14-1 -> -0.019569815 | W14: 42645.924 | X14: =+P14-W14 -> -424.81051
A15: Consumer Prepaid | Q15: 45973.654 | T15: =P15/Q15-1 -> -1 | X15: =+P15-W15 -> 0
B16: Frais d'activation & Sim swap | C16: -22.461806 | D16: -22.461806 | E16: -22.461806 | F16: -22.461806 | G16: -22.461806 | H16: -22.461806 | I16: -22.461806 | J16: -22.461806 | K16: -22.461806 | L16: -22.461806 | M16: -22.461806 | N16: -22.461806 | O16: =SUM(C16,D16,E16,F16,G16,H16,I16,J16,K16,L16,M16,N16) -> -269.54168 | P16: -122.23531 | Q16: -159.9668 | R16: -110.81714 | S16: =O16/P16-1 -> 1.2051049 | T16: =P16/Q16-1 -> -0.23587076 | U16: =O16/R16-1 -> 1.4323104 | W16: -144.60831 | X16: =+P16-W16 -> 22.372999
B17: Sortant voix on net | C17: 1532.0023 | D17: 1445.4383 | E17: 1509.9634 | F17: 1477.3446 | G17: 1510.8206 | H17: 1404.6592 | I17: 1326.96 | J17: 1220.0911 | K17: 1154.8218 | L17: 1226.802 | M17: 1204.8924 | N17: 1400.6297 | O17: =SUM(C17,D17,E17,F17,G17,H17,I17,J17,K17,L17,M17,N17) -> 16414.425 | P17: 18794.826 | Q17: 21114.269 | R17: 20085.705 | S17: =O17/P17-1 -> -0.12665194 | T17: =P17/Q17-1 -> -0.10985192 | U17: =O17/R17-1 -> -0.18278074 | W17: 19085.647 | X17: =+P17-W17 -> -290.82094
B18: Sortant voix MTN | C18: 1964.2889 | D18: 1734.4496 | E18: 1811.1466 | F18: 1795.8073 | G18: 1879.0664 | H18: 1773.9869 | I18: 1763.7703 | J18: 1753.6863 | K18: 1671.8586 | L18: 1739.7501 | M18: 1706.2775 | N18: 1904.056 | O18: =SUM(C18,D18,E18,F18,G18,H18,I18,J18,K18,L18,M18,N18) -> 21498.145 | P18: 19090.156 | Q18: 21426.061 | R18: 18464.202 | S18: =O18/P18-1 -> 0.12613771 | T18: =P18/Q18-1 -> -0.10902168 | U18: =O18/R18-1 -> 0.16431483 | W18: 19203.304 | X18: =+P18-W18 -> -113.14805
B19: Sortant voix GLO | O19: =SUM(C19,D19,E19,F19,G19,H19,I19,J19,K19,L19,M19,N19) -> 0 | P19: 0 | Q19: 0 | R19: 0 | S19: =IFERROR(O19/#REF!-1,"") | W19: 0 | X19: =+P19-W19 -> 0
B20: Sortant voix BBCOM | O20: =SUM(C20,D20,E20,F20,G20,H20,I20,J20,K20,L20,M20,N20) -> 0 | P20: 0 | Q20: 0 | R20: 0 | S20: =IFERROR(O20/#REF!-1,"") | W20: 0 | X20: =+P20-W20 -> 0
B21: Sortant voix LIBERCOM | C21: 134.85752 | D21: 119.07238 | E21: 124.38783 | F21: 123.28637 | G21: 129.00452 | H21: 121.83573 | I21: 121.13407 | J21: 120.44151 | K21: 114.82166 | L21: 119.48439 | M21: 117.18552 | N21: 130.76876 | O21: =SUM(C21,D21,E21,F21,G21,H21,I21,J21,K21,L21,M21,N21) -> 1476.2803 | P21: 458.77224 | Q21: 0 | R21: 918.64691 | S21: =IFERROR(O21/#REF!-1,"") | U21: =O21/R21-1 -> 0.60701597 | W21: 466.54314 | X21: =+P21-W21 -> -7.7709009
B22: Sortant voix BTSA | C22: 0.26963616 | D22: 0.23807511 | E22: 0.2487029 | F22: 0.24650062 | G22: 0.25793359 | H22: 0.2436002 | I22: 0.24219728 | J22: 0.24081258 | K22: 0.22957616 | L22: 0.23889888 | M22: 0.23430249 | N22: 0.26146102 | O22: =SUM(C22,D22,E22,F22,G22,H22,I22,J22,K22,L22,M22,N22) -> 2.951697 | P22: 753.12036 | Q22: 504.61094 | R22: 503.73856 | S22: =O22/P22-1 -> -0.99608071 | T22: =P22/Q22-1 -> 0.49247728 | U22: =O22/R22-1 -> -0.99414042 | W22: 753.13589 | X22: =+P22-W22 -> -0.015537256
B23: Sortant voix INTERNATIONAL | C23: 134.97915 | D23: 111.99366 | E23: 130.13844 | F23: 106.77848 | G23: 97.116671 | H23: 92.696709 | I23: 79.670356 | J23: 77.686936 | K23: 76.301697 | L23: 79.82422 | M23: 74.539823 | N23: 86.418551 | O23: =SUM(C23,D23,E23,F23,G23,H23,I23,J23,K23,L23,M23,N23) -> 1148.1447 | P23: 1860.7982 | Q23: 2277.915 | R23: 1832.1303 | S23: =O23/P23-1 -> -0.3829827 | T23: =P23/Q23-1 -> -0.18311341 | U23: =O23/R23-1 -> -0.37332803 | W23: 1895.663 | X23: =+P23-W23 -> -34.86479
B24: Sortant voix roaming | C24: 16.595851 | D24: 14.877293 | E24: 16.190098 | F24: 15.999767 | G24: 16.570214 | H24: 16.040831 | I24: 16.621053 | J24: 16.742199 | K24: 16.286464 | L24: 16.926658 | M24: 16.496737 | N24: 17.186085 | O24: =SUM(C24,D24,E24,F24,G24,H24,I24,J24,K24,L24,M24,N24) -> 196.53325 | P24: 156.91299 | Q24: 191.22686 | R24: 208.56604 | S24: =O24/P24-1 -> 0.25249826 | T24: =P24/Q24-1 -> -0.17944063 | U24: =O24/R24-1 -> -0.057692948 | W24: 157.61975 | X24: =+P24-W24 -> -0.70675359
B25: Total VOIX Sortant | C25: =SUM(C17:C24) -> 3782.9934 | D25: =SUM(D17:D24) -> 3426.0693 | E25: =SUM(E17:E24) -> 3592.075 | F25: =SUM(F17:F24) -> 3519.4631 | G25: =SUM(G17:G24) -> 3632.8363 | H25: =SUM(H17:H24) -> 3409.4629 | I25: =SUM(I17:I24) -> 3308.398 | J25: =SUM(J17:J24) -> 3188.8889 | ... N25: =SUM(N17:N24) -> 3539.3205 | O25: =SUM(C25,D25,E25,F25,G25,H25,I25,J25,K25,L25,M25,N25) -> 40736.48 | P25: 41114.586 | Q25: 45514.083 | R25: 42012.989 | S25: =O25/P25-1 -> -0.0091964084 | T25: =P25/Q25-1 -> -0.096662326 | U25: =O25/R25-1 -> -0.030383689 | W25: 41561.913 | X25: =+P25-W25 -> -447.32698
S26: =IFERROR(O26/#REF!-1,"") | X26: =+P26-W26 -> 0
B27: Sortant sms on net | C27: 1.2104351 | D27: 1.0398187 | E27: 1.1670257 | F27: 1.0669521 | G27: 1.0504499 | H27: 1.0113768 | I27: 1.0086457 | J27: 0.95447968 | K27: 0.85628454 | L27: 0.87258911 | M27: 0.80033178 | N27: 0.81720716 | O27: =SUM(C27,D27,E27,F27,G27,H27,I27,J27,K27,L27,M27,N27) -> 11.855596 | P27: 21.744486 | Q27: 25.897273 | R27: 16.214351 | S27: =O27/P27-1 -> -0.4547769 | T27: =P27/Q27-1 -> -0.16035614 | U27: =O27/R27-1 -> -0.26882078 | W27: 21.537112 | X27: =+P27-W27 -> 0.20737405
B28: Sortant sms MTN | C28: 1.3495968 | D28: 1.1374519 | E28: 1.3023064 | F28: 1.1885618 | G28: 1.1962148 | H28: 1.2040726 | I28: 1.2282198 | J28: 1.1609352 | K28: 1.034408 | L28: 1.0342915 | M28: 0.94422095 | N28: 0.95968363 | O28: =SUM(C28,D28,E28,F28,G28,H28,I28,J28,K28,L28,M28,N28) -> 13.739963 | P28: 19.068547 | Q28: 22.816118 | R28: 16.660504 | S28: =O28/P28-1 -> -0.27944361 | T28: =P28/Q28-1 -> -0.16425104 | U28: =O28/R28-1 -> -0.17529727 | W28: 18.786359 | X28: =+P28-W28 -> 0.282188
B29: Sortant sms GLO | O29: =SUM(C29,D29,E29,F29,G29,H29,I29,J29,K29,L29,M29,N29) -> 0 | P29: 0 | Q29: 0 | R29: 0 | S29: =IFERROR(O29/#REF!-1,"") | W29: 0 | X29: =+P29-W29 -> 0
B30: Sortant sms BBCOM | C30: 0.0020104274 | D30: 0.0016762382 | E30: 0.0019295857 | F30: 0.0017563069 | G30: 0.0017700046 | H30: 0.0017804293 | I30: 0.0018167483 | J30: 0.001716933 | K30: 0.0015299382 | L30: 0.0015297013 | M30: 0.0013965179 | N30: 0.0014193724 | O30: =SUM(C30,D30,E30,F30,G30,H30,I30,J30,K30,L30,M30,N30) -> 0.020332203 | P30: 0.020845527 | Q30: 0.036873 | R30: 0 | S30: =O30/P30-1 -> -0.024625116 | T30: =P30/Q30-1 -> -0.43466692 | W30: 0.020435599 | X30: =+P30-W30 -> 0.00040992729
B31: Sortant sms LIBERCOM | C31: 0.40805876 | D31: 0.34140512 | E31: 0.39232378 | F31: 0.35740193 | G31: 0.36003331 | H31: 0.36223221 | I31: 0.36958136 | J31: 0.34929483 | K31: 0.31124397 | L31: 0.31119999 | M31: 0.28410344 | N31: 0.28875388 | O31: =SUM(C31,D31,E31,F31,G31,H31,I31,J31,K31,L31,M31,N31) -> 4.1356326 | P31: 4.9110022 | Q31: 4.265927 | R31: 5.2290122 | S31: =O31/P31-1 -> -0.1578842 | T31: =P31/Q31-1 -> 0.15121572 | U31: =O31/R31-1 -> -0.20909869 | W31: 4.8271228 | X31: =+P31-W31 -> 0.083879474
B32: Sortant sms INTERNATIONAL | C32: 1.7264834 | D32: 1.4070221 | E32: 1.6645672 | F32: 1.4475044 | G32: 1.4659039 | H32: 1.440472 | I32: 1.4342532 | J32: 1.4858452 | K32: 1.262133 | L32: 1.2737513 | M32: 1.1651426 | N32: 1.1646236 | O32: =SUM(C32,D32,E32,F32,G32,H32,I32,J32,K32,L32,M32,N32) -> 16.937702 | P32: 27.091205 | Q32: 34.620099 | R32: 23.294845 | S32: =O32/P32-1 -> -0.37478964 | T32: =P32/Q32-1 -> -0.21747176 | U32: =O32/R32-1 -> -0.27289912 | W32: 28.198017 | X32: =+P32-W32 -> -1.1068121
B33: Total SMS Sortant | C33: =SUM(C27:C32) -> 4.6965846 | D33: =SUM(D27:D32) -> 3.9273741 | E33: =SUM(E27:E32) -> 4.5281527 | F33: =SUM(F27:F32) -> 4.0621766 | G33: =SUM(G27:G32) -> 4.0743719 | H33: =SUM(H27:H32) -> 4.0199341 | I33: =SUM(I27:I32) -> 4.0425168 | J33: =SUM(J27:J32) -> 3.9522718 | ... N33: =SUM(N27:N32) -> 3.2316877 | O33: =SUM(C33,D33,E33,F33,G33,H33,I33,J33,K33,L33,M33,N33) -> 46.689227 | P33: 72.836086 | Q33: 87.63629 | R33: 61.398712 | S33: =O33/P33-1 -> -0.35898222 | T33: =P33/Q33-1 -> -0.16888214 | U33: =O33/R33-1 -> -0.23957319 | W33: 73.369047 | X33: =+P33-W33 -> -0.53296069
S34: =IFERROR(O34/#REF!-1,"") | X34: =+P34-W34 -> 0
B35: Revenu Internet 3G | C35: 3972.9579 | D35: 3623.2346 | E35: 4066.6491 | F35: 3997.4935 | G35: 4278.6044 | H35: 4176.7512 | I35: 4341.7594 | J35: 4475.3446 | K35: 4328.3511 | L35: 4542.2054 | M35: 4352.5713 | N35: 4660.8506 | O35: =SUM(C35,D35,E35,F35,G35,H35,I35,J35,K35,L35,M35,N35) -> 50816.773 | P35: 45701.5 | Q35: 43055.339 | R35: 53656.802 | S35: =O35/P35-1 -> 0.11192791 | T35: =P35/Q35-1 -> 0.061459526 | U35: =O35/R35-1 -> -0.052929523 | W35: 45759.382 | X35: =+P35-W35 -> -57.881779
B36: M-Commerce | C36: 500.40913 | D36: 512.69496 | E36: 544.48982 | F36: 579.99647 | G36: 601.84185 | H36: 600.27115 | I36: 662.46305 | J36: 652.57413 | K36: 628.76187 | L36: 673.95144 | M36: 631.00712 | N36: 729.58683 | Q36: 5130.0771 | T36: =P36/Q36-1 -> -1 | X36: =+P36-W36 -> 0
B37: CRBT | C37: 0.2890989 | D37: 0.2624272 | E37: 0.29199712 | F37: 0.28399075 | G37: 0.29492439 | H37: 0.28683776 | I37: 0.29788101 | J37: 0.29937041 | K37: 0.29116187 | L37: 0.3023716 | M37: 0.29408077 | N37: 0.30540288 | O37: =SUM(C37,D37,E37,F37,G37,H37,I37,J37,K37,L37,M37,N37) -> 3.4995447 | P37: 82.94541 | Q37: 12.158026 | R37: 8.04767 | S37: =O37/P37-1 -> -0.95780906 | T37: =P37/Q37-1 -> 5.8222759 | U37: =O37/R37-1 -> -0.56514809 | W37: 82.80285 | X37: =+P37-W37 -> 0.14255914
B38: Crédit secours | C38: 6.5450633 | D38: 6.0299035 | E38: 6.8094839 | F38: 6.7216195 | G38: 7.084587 | H38: 6.993173 | I38: 7.3708043 | J38: 7.5182204 | K38: 7.4212111 | L38: 7.8219565 | M38: 7.721028 | N38: 8.1379635 | O38: =SUM(C38,D38,E38,F38,G38,H38,I38,J38,K38,L38,M38,N38) -> 86.175014 | P38: 86.55635 | Q38: 320.6121 | R38: 129.19411 | S38: =O38/P38-1 -> -0.0044056388 | T38: =P38/Q38-1 -> -0.73002781 | U38: =O38/R38-1 -> -0.33298032 | W38: 86.022483 | X38: =+P38-W38 -> 0.53386717
B39: Story Box | O39: =SUM(C39,D39,E39,F39,G39,H39,I39,J39,K39,L39,M39,N39) -> 0 | P39: 0 | Q39: 0 | R39: 0 | S39: =IFERROR(O39/#REF!-1,"") | W39: 0 | X39: =+P39-W39 -> 0
B40: Phonebook STK | O40: =SUM(C40,D40,E40,F40,G40,H40,I40,J40,K40,L40,M40,N40) -> 0 | P40: 0 | Q40: 0 | R40: 0 | S40: =IFERROR(O40/#REF!-1,"") | W40: 0 | X40: =+P40-W40 -> 0
B41: Gaming | C41: 0 | D41: 0 | E41: 0 | F41: 0 | G41: 0 | H41: 0 | I41: 0 | J41: 0 | K41: 0 | L41: 0 | M41: 0 | N41: 0 | O41: =SUM(C41,D41,E41,F41,G41,H41,I41,J41,K41,L41,M41,N41) -> 0 | P41: 0 | Q41: 0 | R41: 0 | S41: =IFERROR(O41/#REF!-1,"") | W41: 0 | X41: =+P41-W41 -> 0
B42: Autres (story box, phone book STK) | C42: 72.635227 | D42: 71.940203 | E42: 80.220615 | F42: 81.536753 | G42: 87.850508 | H42: 88.994361 | I42: 95.633766 | J42: 99.533619 | K42: 100.41366 | L42: 107.55171 | M42: 108.25071 | N42: 115.73098 | O42: =SUM(C42,D42,E42,F42,G42,H42,I42,J42,K42,L42,M42,N42) -> 1110.2921 | P42: 986.42426 | Q42: 199.13091 | R42: 445.40284 | T42: =P42/Q42-1 -> 3.9536471 | U42: =O42/R42-1 -> 1.4927818 | W42: 986.42426 | X42: =+P42-W42 -> 0
B43: Videos | O43: =SUM(C43,D43,E43,F43,G43,H43,I43,J43,K43,L43,M43,N43) -> 0 | P43: 0 | Q43: 0 | R43: 0 | S43: =IFERROR(O43/#REF!-1,"") | W43: 0 | X43: =+P43-W43 -> 0
B44: Total Data | C44: =SUM(C37:C43) -> 79.469389 | D44: =SUM(D37:D43) -> 78.232534 | E44: =SUM(E37:E43) -> 87.322096 | F44: =SUM(F37:F43) -> 88.542364 | G44: =SUM(G37:G43) -> 95.23002 | H44: =SUM(H37:H43) -> 96.274371 | I44: =SUM(I37:I43) -> 103.30245 | J44: =SUM(J37:J43) -> 107.35121 | ... N44: =SUM(N37:N43) -> 124.17434 | O44: =SUM(O36:O43) -> 1199.9667 | P44: 1155.926 | Q44: 531.90104 | R44: 582.64462 | S44: =O44/P44-1 -> 0.038099889 | T44: =P44/Q44-1 -> 1.1731975 | U44: =O44/R44-1 -> 1.0595173 | W44: 1155.2496 | X44: =+P44-W44 -> 0.67642632
S45: =IFERROR(O45/#REF!-1,"") | X45: =+P45-W45 -> 0
B46: dont CA Internet 3G | C46: =(C35) -> 3972.9579 | D46: =(D35) -> 3623.2346 | E46: =(E35) -> 4066.6491 | F46: =(F35) -> 3997.4935 | G46: =(G35) -> 4278.6044 | H46: =(H35) -> 4176.7512 | I46: =(I35) -> 4341.7594 | J46: =(J35) -> 4475.3446 | ... N46: =(N35) -> 4660.8506 | O46: =SUM(C46,D46,E46,F46,G46,H46,I46,J46,K46,L46,M46,N46) -> 50816.773 | P46: 45701.5 | Q46: 43055.339 | R46: 53656.802 | S46: =O46/P46-1 -> 0.11192791 | T46: =P46/Q46-1 -> 0.061459526 | U46: =O46/R46-1 -> -0.052929523 | W46: 45759.382 | X46: =+P46-W46 -> -57.881779
B47: Postpayé | C47: =SUM(C48+C52) -> 292.50936 | D47: =SUM(D48+D52) -> 288.83262 | E47: =SUM(E48+E52) -> 295.31681 | F47: =SUM(F48+F52) -> 298.46963 | G47: =SUM(G48+G52) -> 281.4221 | H47: =SUM(H48+H52) -> 294.65284 | I47: =SUM(I48+I52) -> 293.57058 | J47: =SUM(J48+J52) -> 292.88512 | ... N47: =SUM(N48+N52) -> 296.30492 | O47: =SUM(C47,D47,E47,F47,G47,H47,I47,J47,K47,L47,M47,N47) -> 3522.7874 | P47: 3449.0751 | Q47: 3543.7856 | R47: 3720.9151 | S47: =O47/P47-1 -> 0.021371608 | T47: =P47/Q47-1 -> -0.026725789 | U47: =O47/R47-1 -> -0.053247038 | W47: 3440.8456 | X47: =+P47-W47 -> 8.229467
B48: Redevance d'abonnement | C48: =SUM(C49:C51) -> 216.24376 | D48: =SUM(D49:D51) -> 216.8997 | E48: =SUM(E49:E51) -> 217.55563 | F48: =SUM(F49:F51) -> 218.26623 | G48: =SUM(G49:G51) -> 219.14081 | H48: =SUM(H49:H51) -> 220.12472 | I48: =SUM(I49:I51) -> 221.16328 | J48: =SUM(J49:J51) -> 222.36583 | ... N48: =SUM(N49:N51) -> 227.88663 | O48: =SUM(C48,D48,E48,F48,G48,H48,I48,J48,K48,L48,M48,N48) -> 2654.834 | P48: 2560.8162 | Q48: 2450.1415 | R48: 2696.7783 | S48: =O48/P48-1 -> 0.036714001 | T48: =P48/Q48-1 -> 0.045170728 | U48: =O48/R48-1 -> -0.015553479 | W48: 2560.8162 | X48: =+P48-W48 -> 0
A49: Consumer Postpaid | C49: 9.6670395 | D49: 9.6913966 | E49: 9.7157537 | F49: 9.7421406 | G49: 9.7746168 | H49: 9.8111525 | I49: 9.849718 | J49: 9.8943727 | K49: 9.943087 | L49: 9.993831 | M49: 10.046605 | N49: 10.099379 | O49: =SUM(C49,D49,E49,F49,G49,H49,I49,J49,K49,L49,M49,N49) -> 118.22909 | P49: 124.90618 | Q49: 143.773 | R49: 153.91244 | S49: =O49/P49-1 -> -0.053456852 | T49: =P49/Q49-1 -> -0.13122641 | U49: =O49/R49-1 -> -0.23184188 | W49: 124.90618 | X49: =+P49-W49 -> 0
A50: Business Postpaid | C50: 18.503261 | D50: 18.53334 | E50: 18.56342 | F50: 18.596006 | G50: 18.636112 | H50: 18.681231 | I50: 18.728857 | J50: 18.784003 | K50: 18.844162 | L50: 18.906828 | M50: 18.972 | N50: 19.037172 | O50: =SUM(C50,D50,E50,F50,G50,H50,I50,J50,K50,L50,M50,N50) -> 224.78639 | P50: 219.30378 | Q50: 264.77832 | R50: 253.45858 | S50: =O50/P50-1 -> 0.025000082 | T50: =P50/Q50-1 -> -0.17174573 | U50: =O50/R50-1 -> -0.11312377 | W50: 219.30378 | X50: =+P50-W50 -> 0
A51: Business Prepaid | C51: 188.07346 | D51: 188.67496 | E51: 189.27646 | F51: 189.92809 | G51: 190.73009 | H51: 191.63233 | I51: 192.58471 | J51: 193.68746 | K51: 194.89046 | L51: 196.14358 | M51: 197.44683 | N51: 198.75008 | O51: =SUM(C51,D51,E51,F51,G51,H51,I51,J51,K51,L51,M51,N51) -> 2311.8185 | P51: 2216.6062 | Q51: 2041.5902 | R51: 2289.4073 | S51: =O51/P51-1 -> 0.042954083 | T51: =P51/Q51-1 -> 0.085725351 | U51: =O51/R51-1 -> 0.0097891084 | W51: 2216.6062 | X51: =+P51-W51 -> 0
B52: Trafic sortant | C52: =SUM(C53,C78,C103) -> 76.2656 | D52: =SUM(D53,D78,D103) -> 71.93292 | E52: =SUM(E53,E78,E103) -> 77.761173 | F52: =SUM(F53,F78,F103) -> 80.203397 | G52: =SUM(G53,G78,G103) -> 62.281286 | H52: =SUM(H53,H78,H103) -> 74.528119 | I52: =SUM(I53,I78,I103) -> 72.407299 | J52: =SUM(J53,J78,J103) -> 70.519283 | ... N52: =SUM(N53,N78,N103) -> 68.41829 | O52: =SUM(C52,D52,E52,F52,G52,H52,I52,J52,K52,L52,M52,N52) -> 867.9534 | P52: 888.25893 | Q52: 1093.6441 | R52: 1024.1368 | S52: =O52/P52-1 -> -0.022859918 | T52: =P52/Q52-1 -> -0.18779889 | U52: =O52/R52-1 -> -0.1525025 | W52: 880.02946 | X52: =+P52-W52 -> 8.229467
A53: Consumer Postpaid | C53: =SUM(C62,C70,C76) -> 1.7686928 | D53: =SUM(D62,D70,D76) -> 1.6722523 | E53: =SUM(E62,E70,E76) -> 1.7771155 | F53: =SUM(F62,F70,F76) -> 1.8279055 | G53: =SUM(G62,G70,G76) -> 2.017071 | H53: =SUM(H62,H70,H76) -> 2.0041159 | I53: =SUM(I62,I70,I76) -> 1.9978587 | J53: =SUM(J62,J70,J76) -> 1.9959487 | ... N53: =SUM(N62,N70,N76) -> 1.9913733 | O53: =SUM(C53,D53,E53,F53,G53,H53,I53,J53,K53,L53,M53,N53) -> 22.961593 | P53: 15.239807 | Q53: 16.528505 | R53: 24.65529 | S53: =O53/P53-1 -> 0.50668526 | T53: =P53/Q53-1 -> -0.077968204 | U53: =O53/R53-1 -> -0.068695081 | W53: 15.239807 | X53: =+P53-W53 -> 0
B54: Sortant voix on net | C54: 0.1204336 | D54: 0.10566175 | E54: 0.11944795 | F54: 0.1344069 | G54: 0.18445095 | H54: 0.18659662 | I54: 0.1838162 | J54: 0.18280306 | K54: 0.1759994 | L54: 0.18096625 | M54: 0.17429288 | N54: 0.17923822 | O54: =SUM(C54,D54,E54,F54,G54,H54,I54,J54,K54,L54,M54,N54) -> 1.9281138 | P54: 2.4245291 | Q54: 3.302599 | R54: 3.3568154 | S54: =O54/P54-1 -> -0.20474712 | T54: =P54/Q54-1 -> -0.26587239 | U54: =O54/R54-1 -> -0.42561222 | W54: 2.4245291 | X54: =+P54-W54 -> 0
B55: Sortant voix MTN | C55: 0.26936534 | D55: 0.23929552 | E55: 0.27638602 | F55: 0.31138883 | G55: 0.40963295 | H55: 0.40311761 | I55: 0.39547107 | J55: 0.39330282 | K55: 0.37865923 | L55: 0.38934525 | M55: 0.37498947 | N55: 0.38562808 | O55: =SUM(C55,D55,E55,F55,G55,H55,I55,J55,K55,L55,M55,N55) -> 4.2265822 | P55: 5.3047403 | Q55: 7.606098 | R55: 7.6189147 | S55: =O55/P55-1 -> -0.20324428 | T55: =P55/Q55-1 -> -0.30256745 | U55: =O55/R55-1 -> -0.44525141 | W55: 5.3047403 | X55: =+P55-W55 -> 0
B56: Sortant voix GLO | O56: =SUM(C56,D56,E56,F56,G56,H56,I56,J56,K56,L56,M56,N56) -> 0 | P56: 0 | Q56: 0 | R56: 0 | S56: =IFERROR(O56/#REF!-1,"") | W56: 0 | X56: =+P56-W56 -> 0
B57: Sortant voix BBCOM | O57: =SUM(C57,D57,E57,F57,G57,H57,I57,J57,K57,L57,M57,N57) -> 0 | P57: 0 | Q57: 0 | R57: 0 | S57: =IFERROR(O57/#REF!-1,"") | W57: 0 | X57: =+P57-W57 -> 0
B58: Sortant voix LIBERCOM | C58: 0.03092746 | D58: 0.027339681 | E58: 0.031630413 | F58: 0.03565469 | G58: 0.046861333 | H58: 0.046135907 | I58: 0.045261421 | J58: 0.045006357 | K58: 0.043334893 | L58: 0.044557214 | M58: 0.04291332 | N58: 0.044131678 | O58: =SUM(C58,D58,E58,F58,G58,H58,I58,J58,K58,L58,M58,N58) -> 0.48375437 | P58: 0.47682808 | Q58: 0.105279 | R58: 0.060359186 | S58: =IFERROR(O58/#REF!-1,"") | T58: =P58/Q58-1 -> 3.5291851 | U58: =O58/R58-1 -> 7.0145939 | W58: 0.47682808 | X58: =+P58-W58 -> 0
B59: Sortant voix BTSA | C59: 0.004503074 | D59: 0.0039155636 | E59: 0.0045260302 | F59: 0.0051331301 | G59: 0.0067211228 | H59: 0.0066202643 | I59: 0.0065008707 | J59: 0.0064591617 | K59: 0.0062205922 | L59: 0.0063968268 | M59: 0.0061598916 | N59: 0.0063351604 | O59: =SUM(C59,D59,E59,F59,G59,H59,I59,J59,K59,L59,M59,N59) -> 0.069491688 | P59: 0.080437063 | Q59: 0.114778 | R59: 0.11665317 | S59: =O59/P59-1 -> -0.13607377 | T59: =P59/Q59-1 -> -0.29919442 | U59: =O59/R59-1 -> -0.40428802 | W59: 0.080437063 | X59: =+P59-W59 -> 0
B60: Sortant voix INTERNATIONAL | C60: 0.063212938 | D60: 0.052298132 | E60: 0.062692703 | F60: 0.070306513 | G60: 0.084335584 | H60: 0.087628029 | I60: 0.078376036 | J60: 0.077944048 | K60: 0.075043086 | L60: 0.077160864 | M60: 0.074315458 | N60: 0.076424063 | O60: =SUM(C60,D60,E60,F60,G60,H60,I60,J60,K60,L60,M60,N60) -> 0.87973746 | P60: 1.2305743 | Q60: 2.694511 | R60: 2.3117195 | S60: =O60/P60-1 -> -0.28510008 | T60: =P60/Q60-1 -> -0.5433033 | U60: =O60/R60-1 -> -0.61944454 | W60: 1.2305743 | X60: =+P60-W60 -> 0
B61: Sortant voix roaming | C61: 0.38755427 | D61: 0.350931 | E61: 0.38950723 | F61: 0.37796622 | G61: 0.39186707 | H61: 0.38064368 | I61: 0.3948779 | J61: 0.39666812 | K61: 0.38576234 | L61: 0.40065543 | M61: 0.38977853 | N61: 0.40488686 | O61: =SUM(C61,D61,E61,F61,G61,H61,I61,J61,K61,L61,M61,N61) -> 4.6510986 | P61: 3.0060222 | Q61: 2.648893 | R61: 0.74419272 | S61: =O61/P61-1 -> 0.54726026 | T61: =P61/Q61-1 -> 0.13482204 | U61: =O61/R61-1 -> 5.2498577 | W61: 3.0060222 | X61: =+P61-W61 -> 0
B62: Total VOIX Sortant | C62: =SUM(C54:C61) -> 0.87599668 | D62: =SUM(D54:D61) -> 0.77944165 | E62: =SUM(E54:E61) -> 0.88419035 | F62: =SUM(F54:F61) -> 0.93485628 | G62: =SUM(G54:G61) -> 1.123869 | H62: =SUM(H54:H61) -> 1.1107421 | I62: =SUM(I54:I61) -> 1.1043035 | J62: =SUM(J54:J61) -> 1.1021836 | ... N62: =SUM(N54:N61) -> 1.0966441 | O62: =SUM(C62,D62,E62,F62,G62,H62,I62,J62,K62,L62,M62,N62) -> 12.238778 | P62: 12.523131 | Q62: 16.472158 | R62: 14.208655 | S62: =O62/P62-1 -> -0.022706214 | T62: =P62/Q62-1 -> -0.2397395 | U62: =O62/R62-1 -> -0.1386392 | W62: 12.523131 | X62: =+P62-W62 -> 0
S63: =IFERROR(O63/#REF!-1,"") | X63: =+P63-W63 -> 0
B64: Sortant sms on net | C64: 0.0052030414 | D64: 0.0052161511 | E64: 0.0052292607 | F64: 0.0052434628 | G64: 0.0052609422 | H64: 0.0052806067 | I64: 0.0053013636 | J64: 0.0053253979 | K64: 0.0053516171 | L64: 0.0053789288 | M64: 0.005407333 | N64: 0.0054357371 | O64: =SUM(C64,D64,E64,F64,G64,H64,I64,J64,K64,L64,M64,N64) -> 0.063633842 | P64: 0.054960802 | Q64: 0.056347 | R64: 0.06382106 | S64: =O64/P64-1 -> 0.1578041 | T64: =P64/Q64-1 -> -0.024601093 | U64: =O64/R64-1 -> -0.0029334795 | W64: 0.054960802 | X64: =+P64-W64 -> 0
B65: Sortant sms MTN | C65: 0 | D65: 0 | E65: 0 | F65: 0 | G65: 0 | H65: 0 | I65: 0 | J65: 0 | K65: 0 | L65: 0 | M65: 0 | N65: 0 | O65: =SUM(C65,D65,E65,F65,G65,H65,I65,J65,K65,L65,M65,N65) -> 0 | P65: 0 | Q65: 0 | R65: 0 | S65: =O65-P65 -> 0 | W65: 0 | X65: =+P65-W65 -> 0
B66: Sortant sms GLO | O66: =SUM(C66,D66,E66,F66,G66,H66,I66,J66,K66,L66,M66,N66) -> 0 | P66: 0 | Q66: 0 | R66: 0 | S66: =IFERROR(O66/#REF!-1,"") | W66: 0 | X66: =+P66-W66 -> 0
B67: Sortant sms BBCOM | O67: =SUM(C67,D67,E67,F67,G67,H67,I67,J67,K67,L67,M67,N67) -> 0 | P67: 0 | Q67: 0 | R67: 0 | S67: =IFERROR(O67/#REF!-1,"") | W67: 0 | X67: =+P67-W67 -> 0
B68: Sortant sms LIBERCOM | O68: =SUM(C68,D68,E68,F68,G68,H68,I68,J68,K68,L68,M68,N68) -> 0 | P68: 0 | Q68: 0 | R68: 0 | S68: =IFERROR(O68/#REF!-1,"") | W68: 0 | X68: =+P68-W68 -> 0
B69: Sortant sms INTERNATIONAL | C69: 0.04025868 | D69: 0.040360116 | E69: 0.040461552 | F69: 0.040571441 | G69: 0.040706689 | H69: 0.040858843 | I69: 0.04101945 | J69: 0.041205416 | K69: 0.041408288 | L69: 0.041619613 | M69: 0.041839391 | N69: 0.042059169 | O69: =SUM(C69,D69,E69,F69,G69,H69,I69,J69,K69,L69,M69,N69) -> 0.49236865 | P69: 0.12001527 | Q69: 0 | R69: 0.21606802 | S69: =O69/P69-1 -> 3.10255 | U69: =O69/R69-1 -> 1.2787669 | W69: 0.12001527 | X69: =+P69-W69 -> 0
B70: Total SMS Sortant | C70: =SUM(C64:C69) -> 0.045461721 | D70: =SUM(D64:D69) -> 0.045576267 | E70: =SUM(E64:E69) -> 0.045690813 | F70: =SUM(F64:F69) -> 0.045814904 | G70: =SUM(G64:G69) -> 0.045967631 | H70: =SUM(H64:H69) -> 0.04613945 | I70: =SUM(I64:I69) -> 0.046320813 | J70: =SUM(J64:J69) -> 0.046530814 | ... N70: =SUM(N64:N69) -> 0.047494906 | O70: =SUM(C70,D70,E70,F70,G70,H70,I70,J70,K70,L70,M70,N70) -> 0.55600249 | P70: 0.17497607 | Q70: 0.056347 | R70: 0.27988908 | S70: =O70/P70-1 -> 2.1775916 | T70: =P70/Q70-1 -> 2.1053307 | U70: =O70/R70-1 -> 0.98651012 | W70: 0.17497607 | X70: =+P70-W70 -> 0
S71: =IFERROR(O71/#REF!-1,"") | X71: =+P71-W71 -> 0
B72: Revenu Internet 3G | C72: 1.1029799 | D72: 1.0058891 | E72: 1.1289906 | F72: 1.1097915 | G72: 1.1878341 | H72: 1.1595574 | I72: 1.2053673 | J72: 1.2424534 | K72: 1.2016448 | L72: 1.2610154 | M72: 1.2083689 | N72: 1.2939539 | O72: =SUM(C72,D72,E72,F72,G72,H72,I72,J72,K72,L72,M72,N72) -> 14.107846 | P72: 14.004493 | Q72: 14.661799 | R72: 17.521864 | S72: =O72/P72-1 -> 0.0073800316 | T72: =P72/Q72-1 -> -0.044831209 | U72: =O72/R72-1 -> -0.19484329 | W72: 13.29723 | X72: =+P72-W72 -> 0.70726317
B73: Transport and Automotive | O73: =SUM(C73,D73,E73,F73,G73,H73,I73,J73,K73,L73,M73,N73) -> 0 | P73: 0 | Q73: 0 | R73: 0 | S73: =IFERROR(O73/#REF!-1,"") | W73: 0 | X73: =+P73-W73 -> 0
B74: Banking | C74: 0.84723435 | D74: 0.84723435 | E74: 0.84723435 | F74: 0.84723435 | G74: 0.84723435 | H74: 0.84723435 | I74: 0.84723435 | J74: 0.84723435 | K74: 0.84723435 | L74: 0.84723435 | M74: 0.84723435 | N74: 0.84723435 | O74: =SUM(C74,D74,E74,F74,G74,H74,I74,J74,K74,L74,M74,N74) -> 10.166812 | P74: 2.5417001 | Q74: 0 | R74: 10.166746 | S74: =IFERROR(O74/#REF!-1,"") | U74: =O74/R74-1 -> 6.4917525e-06 | W74: 2.5417001 | X74: =+P74-W74 -> 0
B75: Autres | O75: =SUM(C75,D75,E75,F75,G75,H75,I75,J75,K75,L75,M75,N75) -> 0 | P75: 0 | Q75: 0 | R75: 0 | S75: =IFERROR(O75/#REF!-1,"") | W75: 0 | X75: =+P75-W75 -> 0
B76: Total Data | C76: =SUM(C73:C75) -> 0.84723435 | D76: =SUM(D73:D75) -> 0.84723435 | E76: =SUM(E73:E75) -> 0.84723435 | F76: =SUM(F73:F75) -> 0.84723435 | G76: =SUM(G73:G75) -> 0.84723435 | H76: =SUM(H73:H75) -> 0.84723435 | I76: =SUM(I73:I75) -> 0.84723435 | J76: =SUM(J73:J75) -> 0.84723435 | ... N76: =SUM(N73:N75) -> 0.84723435 | O76: =SUM(C76,D76,E76,F76,G76,H76,I76,J76,K76,L76,M76,N76) -> 10.166812 | P76: 2.5417001 | Q76: 0 | R76: 10.166746 | S76: =IFERROR(O76/#REF!-1,"") | U76: =O76/R76-1 -> 6.4917525e-06 | W76: 2.5417001 | X76: =+P76-W76 -> 0
S77: =O77-P77 -> 0 | X77: =+P77-W77 -> 0
A78: Business Postpaid | C78: =SUM(C87,C95,C101) -> 31.633661 | D78: =SUM(D87,D95,D101) -> 30.297125 | E78: =SUM(E87,E95,E101) -> 30.901474 | F78: =SUM(F87,F95,F101) -> 30.789423 | G78: =SUM(G87,G95,G101) -> 31.244623 | H78: =SUM(H87,H95,H101) -> 31.279809 | I78: =SUM(I87,I95,I101) -> 31.012445 | J78: =SUM(J87,J95,J101) -> 31.099347 | ... N78: =SUM(N87,N95,N101) -> 33.337926 | O78: =SUM(C78,D78,E78,F78,G78,H78,I78,J78,K78,L78,M78,N78) -> 375.40868 | P78: 305.23556 | Q78: 348.80536 | R78: 339.99286 | S78: =O78/P78-1 -> 0.22989822 | T78: =P78/Q78-1 -> -0.12491147 | U78: =O78/R78-1 -> 0.10416636 | W78: 305.23556 | X78: =+P78-W78 -> 0
B79: Sortant voix on net | C79: 2.6185885 | D79: 2.3056531 | E79: 2.4182189 | F79: 2.3948168 | G79: 2.543035 | H79: 2.557172 | I79: 2.4302178 | J79: 2.3303878 | K79: 2.3024048 | L79: 2.3045027 | M79: 2.6432847 | N79: 3.066924 | O79: =SUM(C79,D79,E79,F79,G79,H79,I79,J79,K79,L79,M79,N79) -> 29.915206 | P79: 32.612164 | Q79: 45.337826 | R79: 30.102511 | S79: =O79/P79-1 -> -0.082697919 | T79: =P79/Q79-1 -> -0.28068531 | U79: =O79/R79-1 -> -0.0062222462 | W79: 32.612164 | X79: =+P79-W79 -> 0
B80: Sortant voix MTN | C80: 4.9611982 | D80: 4.246496 | E80: 4.4537472 | F80: 4.4332819 | G80: 4.7251075 | H80: 4.7513636 | I80: 4.4464983 | J80: 4.4186597 | K80: 4.3655998 | L80: 4.3695792 | M80: 4.6944886 | N80: 5.5621681 | O80: =SUM(C80,D80,E80,F80,G80,H80,I80,J80,K80,L80,M80,N80) -> 55.428188 | P80: 65.548527 | Q80: 77.995172 | R80: 79.172969 | S80: =O80/P80-1 -> -0.1543946 | T80: =P80/Q80-1 -> -0.15958225 | U80: =O80/R80-1 -> -0.29991019 | W80: 65.548527 | X80: =+P80-W80 -> 0
B81: Sortant voix GLO | O81: =SUM(C81,D81,E81,F81,G81,H81,I81,J81,K81,L81,M81,N81) -> 0 | P81: 0 | Q81: 0 | R81: 0 | S81: =IFERROR(O81/#REF!-1,"") | W81: 0 | X81: =+P81-W81 -> 0
B82: Sortant voix BBCOM | O82: =SUM(C82,D82,E82,F82,G82,H82,I82,J82,K82,L82,M82,N82) -> 0 | P82: 0 | Q82: 0 | R82: 0 | S82: =IFERROR(O82/#REF!-1,"") | W82: 0 | X82: =+P82-W82 -> 0
B83: Sortant voix LIBERCOM | O83: =SUM(C83,D83,E83,F83,G83,H83,I83,J83,K83,L83,M83,N83) -> 0 | P83: 0 | Q83: 0 | R83: 0 | S83: =IFERROR(O83/#REF!-1,"") | W83: 0 | X83: =+P83-W83 -> 0
B84: Sortant voix BTSA | C84: 0.032492996 | D84: 0.027807952 | E84: 0.029235268 | F84: 0.029055841 | G84: 0.030975698 | H84: 0.03115909 | I84: 0.029150511 | J84: 0.02897067 | K84: 0.028624073 | L84: 0.028648428 | M84: 0.030779426 | N84: 0.036468487 | O84: =SUM(C84,D84,E84,F84,G84,H84,I84,J84,K84,L84,M84,N84) -> 0.36336844 | P84: 0.34736903 | Q84: 0.595366 | R84: 0.36727805 | S84: =O84/P84-1 -> 0.046058834 | T84: =P84/Q84-1 -> -0.41654541 | U84: =O84/R84-1 -> -0.010644832 | W84: 0.34736903 | X84: =+P84-W84 -> 0
B85: Sortant voix INTERNATIONAL | C85: 1.2571812 | D85: 1.1103722 | E85: 1.1645824 | F85: 1.1223704 | G85: 1.0234294 | H85: 1.0291187 | I85: 1.0742885 | J85: 1.2235057 | K85: 1.208814 | L85: 1.2099154 | M85: 1.0222312 | N85: 1.2736858 | O85: =SUM(C85,D85,E85,F85,G85,H85,I85,J85,K85,L85,M85,N85) -> 13.719495 | P85: 16.481084 | Q85: 23.435955 | R85: 25.542398 | S85: =O85/P85-1 -> -0.16756115 | T85: =P85/Q85-1 -> -0.29676071 | U85: =O85/R85-1 -> -0.46287365 | W85: 16.481084 | X85: =+P85-W85 -> 0
B86: Sortant voix roaming | C86: 1.218279 | D86: 1.1021699 | E86: 1.22224 | F86: 1.1848892 | G86: 1.2270261 | H86: 1.1903195 | I86: 1.2331326 | J86: 1.2367634 | K86: 1.200701 | L86: 1.2448504 | M86: 1.2088465 | N86: 1.2534324 | O86: =SUM(C86,D86,E86,F86,G86,H86,I86,J86,K86,L86,M86,N86) -> 14.52265 | P86: 15.33062 | Q86: 29.211784 | R86: 15.065306 | S86: =O86/P86-1 -> -0.05270302 | T86: =P86/Q86-1 -> -0.47519057 | U86: =O86/R86-1 -> -0.036020279 | W86: 15.33062 | X86: =+P86-W86 -> 0
B87: Total VOIX Sortant | C87: =SUM(C79:C86) -> 10.08774 | D87: =SUM(D79:D86) -> 8.792499 | E87: =SUM(E79:E86) -> 9.2880237 | F87: =SUM(F79:F86) -> 9.1644141 | G87: =SUM(G79:G86) -> 9.5495737 | H87: =SUM(H79:H86) -> 9.5591328 | I87: =SUM(I79:I86) -> 9.2132877 | J87: =SUM(J79:J86) -> 9.2382872 | ... N87: =SUM(N79:N86) -> 11.192679 | O87: =SUM(C87,D87,E87,F87,G87,H87,I87,J87,K87,L87,M87,N87) -> 113.94891 | P87: 130.31976 | Q87: 176.5761 | R87: 150.25046 | S87: =O87/P87-1 -> -0.12562067 | T87: =P87/Q87-1 -> -0.26196262 | U87: =O87/R87-1 -> -0.24160694 | W87: 130.31976 | X87: =+P87-W87 -> 0
S88: =IFERROR(O88/#REF!-1,"") | X88: =+P88-W88 -> 0
B89: Sortant sms on net | C89: 20.77031 | D89: 20.804075 | E89: 20.837839 | F89: 20.874418 | G89: 20.919438 | H89: 20.970085 | I89: 21.023546 | J89: 21.085449 | K89: 21.152978 | L89: 21.223322 | M89: 21.296479 | N89: 21.369637 | O89: =SUM(C89,D89,E89,F89,G89,H89,I89,J89,K89,L89,M89,N89) -> 252.32758 | P89: 165.57261 | Q89: 162.22638 | R89: 182.36848 | S89: =O89/P89-1 -> 0.52396931 | T89: =P89/Q89-1 -> 0.020626916 | U89: =O89/R89-1 -> 0.38361399 | W89: 165.57261 | X89: =+P89-W89 -> 0
B90: Sortant sms MTN | C90: 0 | D90: 0 | E90: 0 | F90: 0 | G90: 0 | H90: 0 | I90: 0 | J90: 0 | K90: 0 | L90: 0 | M90: 0 | N90: 0 | O90: =SUM(C90,D90,E90,F90,G90,H90,I90,J90,K90,L90,M90,N90) -> 0 | P90: 0 | Q90: 0 | R90: 0 | W90: 0 | X90: =+P90-W90 -> 0
B91: Sortant sms GLO | O91: =SUM(C91,D91,E91,F91,G91,H91,I91,J91,K91,L91,M91,N91) -> 0 | P91: 0 | Q91: 0 | R91: 0 | S91: =IFERROR(O91/#REF!-1,"") | W91: 0 | X91: =+P91-W91 -> 0
B92: Sortant sms BBCOM | O92: =SUM(C92,D92,E92,F92,G92,H92,I92,J92,K92,L92,M92,N92) -> 0 | P92: 0 | Q92: 0 | R92: 0 | S92: =O92-P92 -> 0 | W92: 0 | X92: =+P92-W92 -> 0
B93: Sortant sms LIBERCOM | O93: =SUM(C93,D93,E93,F93,G93,H93,I93,J93,K93,L93,M93,N93) -> 0 | P93: 0 | Q93: 0 | R93: 0 | S93: =IFERROR(O93/#REF!-1,"") | W93: 0 | X93: =+P93-W93 -> 0
B94: Sortant sms INTERNATIONAL | C94: 0 | D94: 0 | E94: 0 | F94: 0 | G94: 0 | H94: 0 | I94: 0 | J94: 0 | K94: 0 | L94: 0 | M94: 0 | N94: 0 | O94: =SUM(C94,D94,E94,F94,G94,H94,I94,J94,K94,L94,M94,N94) -> 0 | P94: 0 | Q94: 0 | R94: 0 | W94: 0 | X94: =+P94-W94 -> 0
B95: Total SMS Sortant | C95: =SUM(C89:C94) -> 20.77031 | D95: =SUM(D89:D94) -> 20.804075 | E95: =SUM(E89:E94) -> 20.837839 | F95: =SUM(F89:F94) -> 20.874418 | G95: =SUM(G89:G94) -> 20.919438 | H95: =SUM(H89:H94) -> 20.970085 | I95: =SUM(I89:I94) -> 21.023546 | J95: =SUM(J89:J94) -> 21.085449 | ... N95: =SUM(N89:N94) -> 21.369637 | O95: =SUM(C95,D95,E95,F95,G95,H95,I95,J95,K95,L95,M95,N95) -> 252.32758 | P95: 165.57261 | Q95: 162.22638 | R95: 182.36848 | S95: =O95/P95-1 -> 0.52396931 | T95: =P95/Q95-1 -> 0.020626916 | U95: =O95/R95-1 -> 0.38361399 | W95: 165.57261 | X95: =+P95-W95 -> 0
S96: =IFERROR(O96/#REF!-1,"") | X96: =+P96-W96 -> 0
B97: Revenu Internet 3G | C97: 30.940344 | D97: 28.216792 | E97: 31.669986 | F97: 31.13142 | G97: 33.320638 | H97: 32.527432 | I97: 33.812472 | J97: 34.852798 | K97: 33.708052 | L97: 35.373492 | M97: 33.896673 | N97: 36.29747 | O97: =SUM(C97,D97,E97,F97,G97,H97,I97,J97,K97,L97,M97,N97) -> 395.74757 | P97: 402.06092 | Q97: 214.44565 | R97: 469.24305 | S97: =O97/P97-1 -> -0.015702483 | T97: =P97/Q97-1 -> 0.87488496 | U97: =O97/R97-1 -> -0.15662562 | W97: 387.69841 | X97: =+P97-W97 -> 14.362511
B98: Transport and Automotive | O98: =SUM(C98,D98,E98,F98,G98,H98,I98,J98,K98,L98,M98,N98) -> 0 | P98: 0 | Q98: 0 | R98: 0 | S98: =IFERROR(O98/#REF!-1,"") | W98: 0 | X98: =+P98-W98 -> 0
B99: Banking | C99: 0.775611 | D99: 0.70055187 | E99: 0.775611 | F99: 0.75059129 | G99: 0.775611 | H99: 0.75059129 | I99: 0.775611 | J99: 0.775611 | K99: 0.75059129 | L99: 0.775611 | M99: 0.75059129 | N99: 0.775611 | O99: =SUM(C99,D99,E99,F99,G99,H99,I99,J99,K99,L99,M99,N99) -> 9.132194 | P99: 9.3431903 | Q99: 10.002872 | R99: 7.3739201 | S99: =O99/P99-1 -> -0.022582892 | T99: =P99/Q99-1 -> -0.06594923 | U99: =O99/R99-1 -> 0.23844495 | W99: 9.3431903 | X99: =+P99-W99 -> 0
B100: Autres | O100: =SUM(C100,D100,E100,F100,G100,H100,I100,J100,K100,L100,M100,N100) -> 0 | P100: 0 | Q100: 0 | R100: 0 | S100: =IFERROR(O100/#REF!-1,"") | W100: 0 | X100: =+P100-W100 -> 0
B101: Total Data | C101: =SUM(C98:C100) -> 0.775611 | D101: =SUM(D98:D100) -> 0.70055187 | E101: =SUM(E98:E100) -> 0.775611 | F101: =SUM(F98:F100) -> 0.75059129 | G101: =SUM(G98:G100) -> 0.775611 | H101: =SUM(H98:H100) -> 0.75059129 | I101: =SUM(I98:I100) -> 0.775611 | J101: =SUM(J98:J100) -> 0.775611 | ... N101: =SUM(N98:N100) -> 0.775611 | O101: =SUM(C101,D101,E101,F101,G101,H101,I101,J101,K101,L101,M101,N101) -> 9.132194 | P101: 9.3431903 | Q101: 10.002872 | R101: 7.3739201 | S101: =O101/P101-1 -> -0.022582892 | T101: =P101/Q101-1 -> -0.06594923 | U101: =O101/R101-1 -> 0.23844495 | W101: 9.3431903 | X101: =+P101-W101 -> 0
...

Sheet Marge Mobile 
A2: Marge brute Mobile | M2: =N8/M8-1 -> 0.092913939 | N2: =N38/M38-1 -> 0.15740584
C5: JANVIER | D5: FEV | E5: MARS | F5: AVR | G5: MAI | H5: JUIN | I5: JUIL | J5: AOUT | K5: SEPT | L5: OCT | M5: NOV | N5: DEC | O5: ANNUEL | S5: VARIATIONS
B6: (En Millions ML) | C6: 2025 Budget | D6: 2025 Budget | E6: 2025 Budget | F6: 2025 Budget | G6: 2025 Budget | H6: 2025 Budget | I6: 2025 Budget | J6: 2025 Budget | K6: 2025 Budget | L6: 2025 Budget | M6: 2025 Budget | N6: 2025 Budget | O6: 2025 Budget | P6: 2024 Actu3 | Q6: 2023 Réel | R6: Budget 2024 | S6: Var Budget vs Actu 3 . | T6: Var Actu 3 vs Réel 23. % | U6: Var Budget vs Budget 2024. %
A8: Total Revenu | C8: =+'CA Mobile'!C7 -> 9527.0891 | D8: =+'CA Mobile'!D7 -> 8782.1227 | E8: =+'CA Mobile'!E7 -> 9473.1389 | F8: =+'CA Mobile'!F7 -> 9362.5379 | G8: =+'CA Mobile'!G7 -> 9772.4636 | H8: =+'CA Mobile'!H7 -> 9466.6859 | I8: =+'CA Mobile'!I7 -> 9614.0551 | J8: =+'CA Mobile'!J7 -> 9618.2497 | ... N8: =+'CA Mobile'!N7 -> 10293.443 | O8: =SUM(C8:N8) -> 114333.76 | P8: 108391.75 | Q8: 105542.99 | R8: 115899.62 | S8: =O8/P8-1 -> 0.054819755 | T8: =P8/Q8-1 -> 0.026991494 | U8: =O8/R8-1 -> -0.013510454 | V8: 108887.36 | X8: =V8-P8 -> 495.6011
B9: Trafic (mn) | C9: 1.3868277 | D9: 1.1541336 | E9: 1.3412454 | F9: 1.1021665 | G9: 1.0043925 | H9: 0.95955033 | I9: 0.82649798 | J9: 0.80746278 | K9: 0.79655808 | L9: 0.83071262 | M9: 0.7756846 | N9: 0.88962797 | O9: =SUM(C9:N9) -> 11.87486 | P9: 18.015451 | Q9: 19.767327 | R9: 15.136436 | S9: =O9/P9-1 -> -0.34085137 | T9: =P9/Q9-1 -> -0.088624816 | U9: =O9/R9-1 -> -0.21547844 | V9: 18.015451 | X9: =V9-P9 -> 0
B10: Coût unitaire | C10: =-C11/C9 -> 115.60917 | D10: =-D11/D9 -> 137.18516 | E10: =-E11/E9 -> 121.0293 | F10: 133.84932 | G10: =-G11/G9 -> 164.60697 | H10: =-H11/H9 -> 173.34161 | I10: =-I11/I9 -> 200.03679 | J10: =-J11/J9 -> 207.22937 | K10: =-K11/K9 -> 212.57709 | L10: =-L11/L9 -> 201.42947 | M10: =-M11/M9 -> 218.29749 | N10: =-N11/N9 -> 192.58612 | O10: =O11/O9 -> -167.40913 | P10: -127.79684 | Q10: -115.602 | R10: -109.13958 | S10: =O10/P10-1 -> 0.30996302 | T10: =P10/Q10-1 -> 0.10548987 | V10: -127.79684 | X10: =V10-P10 -> 0
B11: International | C11: -160.33 | D11: -158.33 | E11: -162.33 | F11: -165.33 | G11: -165.33 | H11: -166.33 | I11: -165.33 | J11: -167.33 | K11: -169.33 | L11: -167.33 | M11: -169.33 | N11: -171.33 | O11: =SUM(C11:N11) -> -1987.96 | P11: -2302.3177 | Q11: -2285.1425 | R11: -1651.9842 | S11: =O11/P11-1 -> -0.13653967 | T11: =P11/Q11-1 -> 0.0075160315 | U11: =O11/R11-1 -> 0.20337714 | V11: -2302.3177 | X11: =V11-P11 -> 0
B12: Trafic (mn) | C12: 75.833719 | D12: 67.040992 | E12: 72.330875 | F12: 66.395866 | G12: 71.830327 | H12: 66.823089 | I12: 66.823089 | J12: 70.355701 | K12: 68.689589 | L12: 70.298771 | M12: 68.905137 | N12: 78.87431 | O12: =SUM(C12:N12) -> 844.20147 | P12: 846.86758 | Q12: 0 | R12: 847.28519 | S12: =O12/Q12-1 -> #DIV/0! | T12: =O12/#REF!-1 -> #REF! | U12: =O12/R12-1 -> -0.0036395295 | V12: 846.86758 | X12: =V12-P12 -> 0
B13: Coût unitaire | C13: -10 | D13: -10 | E13: -10 | F13: 0 | G13: 0 | H13: 0 | I13: 0 | J13: 0 | K13: 0 | L13: 0 | M13: 0 | N13: 0 | O13: =O14/O12 -> 0 | P13: 0 | Q13: 0 | R13: 0 | V13: 0 | X13: =V13-P13 -> 0
B14: Opérateur national 1 (mtn) | C14: 0 | D14: 0 | E14: 0 | F14: 0 | G14: 0 | H14: 0 | I14: 0 | J14: 0 | K14: 0 | L14: 0 | M14: 0 | N14: 0 | O14: =SUM(C14:N14) -> 0 | P14: 0 | Q14: 0 | R14: 0 | V14: 0 | X14: =V14-P14 -> 0
B15: Trafic (mn) | C15: 0 | D15: 0 | E15: 0 | F15: 0 | G15: 0 | H15: 0 | I15: 0 | J15: 0 | K15: 0 | L15: 0 | M15: 0 | N15: 0 | O15: =SUM(C15:N15) -> 0 | P15: 0 | R15: 0 | V15: 0 | X15: =V15-P15 -> 0
B16: Coût unitaire | C16: 0 | D16: 0 | E16: 0 | F16: -10 | G16: -10 | H16: -10 | I16: -10 | J16: -10 | K16: -10 | L16: -10 | M16: -10 | N16: -10 | O16: - | P16: - | Q16: - | R16: - | V16: - | X16: =V16-P16 -> #VALUE!
B17: Opérateur national 2 (glo) | C17: 0 | D17: 0 | E17: 0 | F17: 0 | G17: 0 | H17: 0 | I17: 0 | J17: 0 | K17: 0 | L17: 0 | M17: 0 | N17: 0 | O17: =SUM(C17:N17) -> 0 | P17: 0 | Q17: 0 | R17: 0 | V17: 0 | X17: =V17-P17 -> 0
C18: 0 | D18: 0 | E18: 0 | F18: 0.026719928 | G18: 0.026719928 | H18: 0.026719928 | I18: 0.026719928 | J18: 0.026077273 | K18: 0.02545973 | L18: 0.026056172 | M18: 0.025539623 | N18: 0.029234687 | X18: =V18-P18 -> 0
C19: 0 | D19: 0 | E19: 0 | F19: 0 | G19: 0 | H19: 0 | I19: 0 | J19: -1886.5767 | K19: -1932.3369 | L19: -1888.1045 | M19: -1926.2922 | N19: -1682.822 | X19: =V19-P19 -> 0
B20: Achat de capacité | C20: -49.196775 | D20: -49.196775 | E20: -49.196775 | F20: -49.196775 | G20: -49.196775 | H20: -49.196775 | I20: -49.196775 | J20: -49.196775 | K20: -49.196775 | L20: -49.196775 | M20: -49.196775 | N20: -49.196775 | O20: =SUM(C20:N20) -> -590.3613 | P20: -815.33103 | Q20: -223.12875 | R20: 0 | V20: -815.33103 | X20: =V20-P20 -> 0
C21: 0 | D21: 0 | E21: 0 | F21: 0 | G21: 0 | H21: 0 | I21: 0 | J21: 0 | K21: 0 | L21: 0 | M21: 0 | N21: 0 | X21: =V21-P21 -> 0
C22: 0 | D22: 0 | E22: 0 | F22: 0 | G22: 0 | H22: 0 | I22: 0 | J22: 0 | K22: 0 | L22: 0 | M22: 0 | N22: 0 | X22: =V22-P22 -> 0
C23: 0 | D23: 0 | E23: 0 | F23: 0 | G23: 0 | H23: 0 | I23: 0 | J23: 0 | K23: 0 | L23: 0 | M23: 0 | N23: 0 | X23: =V23-P23 -> 0
C24: 0 | D24: 0 | E24: 0 | F24: 0 | G24: 0 | H24: 0 | I24: 0 | J24: 0 | K24: 0 | L24: 0 | M24: 0 | N24: 0 | X24: =V24-P24 -> 0
B25: Others | C25: -24.828603 | D25: -24.442025 | E25: -27.281852 | F25: -27.663017 | G25: -29.75235 | H25: -30.078558 | I25: -32.274243 | J25: -33.539107 | K25: -33.781112 | L25: -36.139851 | M25: -36.324044 | N25: -38.794787 | O25: =SUM(C25:N25) -> -374.89955 | P25: -250.79531 | Q25: -52.256994 | R25: -442.21631 | S25: =O25/P25-1 -> 0.49484272 | T25: =O25/Q25-1 -> 6.1741507 | U25: =O25/R25-1 -> -0.15222587 | V25: -250.79531 | X25: =V25-P25 -> 0
B26: Nbre SMS | C26: 3.984812 | D26: 3.3659798 | E26: 3.8416679 | F26: 3.4444468 | G26: 3.5317464 | H26: 3.543726 | I26: 3.6202039 | J26: 3.4275861 | K26: 3.068865 | L26: 3.0710263 | M26: 2.8129404 | N26: 2.8653638 | O26: =SUM(C26:N26) -> 40.578364 | P26: 25.197318 | Q26: 20.823426 | R26: 40.372251 | S26: =O26/P26-1 -> 0.61042393 | T26: =P26/Q26-1 -> 0.21004672 | U26: =O26/R26-1 -> 0.0051053295 | V26: 25.197318 | X26: =V26-P26 -> 0
B27: Coût unitaire | C27: =+C28/C26 -> -0.98571952 | D27: =+D28/D26 -> -0.57101027 | E27: =+E28/E26 -> -2.9684442 | F27: -0.87727662 | G27: =+G28/G26 -> -1.2879294 | H27: =+H28/H26 -> -1.3105971 | I27: =+I28/I26 -> -1.7085681 | J27: =+J28/J26 -> -2.4563829 | K27: =+K28/K26 -> -2.7324714 | L27: =+L28/L26 -> -2.7403345 | M27: =+M28/M26 -> -2.9261042 | N27: =+N28/N26 -> -2.8930808 | O27: =+O28/O26 -> -1.9681453 | P27: -2.5651714 | Q27: -2.1396185 | R27: -2.4525634 | S27: =O27/P27-1 -> -0.23274315 | T27: =P27/Q27-1 -> 0.19889192 | U27: =O27/R27-1 -> -0.19751502 | V27: -2.5651714 | X27: =V27-P27 -> 0
B28: Interconnexion SMS | C28: -3.927907 | D28: -1.922009 | E28: -11.403777 | F28: -5.490647 | G28: -4.54864 | H28: -4.644397 | I28: -6.185365 | J28: -8.4194638 | K28: -8.385586 | L28: -8.4156395 | M28: -8.2309567 | N28: -8.2897288 | O28: =SUM(C28:N28) -> -79.864117 | P28: -64.635439 | Q28: -44.554188 | R28: -99.015505 | S28: =O28/P28-1 -> 0.23560879 | T28: =P28/Q28-1 -> 0.45071523 | U28: =O28/R28-1 -> -0.19341807 | V28: -64.635439 | X28: =V28-P28 -> 0
B29: Roaming out | C29: -61.097773 | D29: -58.985164 | E29: -85.478831 | F29: -59.764986 | G29: -60.579673 | H29: -60.856849 | I29: -61.137204 | J29: -61.420775 | K29: -61.707599 | L29: -61.997715 | M29: -62.291163 | N29: -62.587981 | O29: =SUM(C29:N29) -> -757.90571 | P29: -529.77595 | Q29: -453.04329 | R29: -445.23124 | S29: =O29/P29-1 -> 0.43061556 | T29: =P29/Q29-1 -> 0.16937158 | U29: =O29/R29-1 -> 0.70227433 | V29: -529.77595 | X29: =V29-P29 -> 0
C30: 0 | D30: 0 | E30: 0 | F30: 0 | G30: 0 | H30: 0 | I30: 0 | J30: 0 | K30: 0 | L30: 0 | M30: 0 | N30: 0 | O30: =SUM(C30:N30) -> 0 | P30: 0 | Q30: 0 | R30: 0 | V30: 0 | X30: =V30-P30 -> 0
B31: Coûts des terminaux et cartes | C31: =SUM(C33:C34) -> -168.27486 | D31: =SUM(D33:D34) -> -168.27486 | E31: =SUM(E33:E34) -> -168.27486 | F31: =SUM(F33:F34) -> -168.27486 | G31: =SUM(G33:G34) -> -168.27486 | H31: =SUM(H33:H34) -> -169.17486 | I31: =SUM(I33:I34) -> -168.27486 | J31: =SUM(J33:J34) -> -169.17486 | ... N31: =SUM(N33:N34) -> -169.17486 | O31: =SUM(C31:N31) -> -2021.9983 | P31: -1844.9065 | Q31: -1488.5752 | R31: -1609.2 | S31: =O31/P31-1 -> 0.095989575 | T31: =P31/Q31-1 -> 0.23937738 | U31: =O31/R31-1 -> 0.2565239 | V31: -1844.9065 | X31: =V31-P31 -> 0
B32: Dont coût des cartes de recharge vendues & des Kits. | C32: 0 | D32: 0 | E32: 0 | F32: 39.69264 | G32: -71.827091 | H32: -240.07569 | I32: -240.07569 | J32: 0 | K32: 0 | L32: 0 | M32: 0 | N32: 0 | Q32: 0 | R32: 0 | V32: -1879.4747 | X32: =V32-P32 -> -1879.4747
B33: Dont coût des terminaux. | C33: -168.27486 | D33: -168.27486 | E33: -168.27486 | F33: -168.27486 | G33: -168.27486 | H33: -169.17486 | I33: -168.27486 | J33: -169.17486 | K33: -168.27486 | L33: -168.27486 | M33: -168.27486 | N33: -169.17486 | O33: =SUM(C33:N33) -> -2021.9983 | P33: -1881.5461 | Q33: -1519.104 | R33: -1609.2 | T33: =P33/Q33-1 -> 0.23858942 | U33: =O33/R33-1 -> 0.2565239 | V33: -2.071424 | X33: =V33-P33 -> 1879.4747
B34: Dont provisions sur stocks | O34: =SUM(C34:N34) -> 0 | P34: 36.639634 | Q34: 30.528745 | R34: 0 | T34: =P34/Q34-1 -> 0.20016837 | V34: 36.639634 | X34: =V34-P34 -> 0
B35: Commissions | C35: =SUM(C36:C38) -> -1050.0697 | D35: =SUM(D36:D38) -> -998.42946 | E35: =SUM(E36:E38) -> -1076.8336 | F35: =SUM(F36:F38) -> -1070.2607 | G35: =SUM(G36:G38) -> -1100.5686 | H35: =SUM(H36:H38) -> -1071.2105 | I35: =SUM(I36:I38) -> -1099.5029 | J35: =SUM(J36:J38) -> -1084.3466 | ... N35: =SUM(N36:N38) -> -1138.5817 | O35: =SUM(C35:N35) -> -12838.471 | P35: -12087.971 | Q35: -11348.903 | R35: -12522.159 | S35: =O35/P35-1 -> 0.062086558 | T35: =P35/Q35-1 -> 0.065122407 | U35: =O35/R35-1 -> 0.025260194 | V35: -12137.535 | X35: =V35-P35 -> -49.564117
B36: Dont commissions up-front | C36: -20.771197 | D36: -19.015333 | E36: -22.103297 | F36: -20.757939 | G36: -20.948358 | H36: -19.821569 | I36: -21.137568 | J36: -22.111605 | K36: -21.529616 | L36: -23.296821 | M36: -23.027932 | N36: -25.878936 | O36: =SUM(C36:N36) -> -260.40017 | P36: -300.67182 | Q36: -1430.1946 | R36: -1084.2295 | S36: =O36/P36-1 -> -0.13393889 | T36: =P36/Q36-1 -> -0.7897686 | U36: =O36/R36-1 -> -0.7598293 | V36: -300.67182 | X36: =V36-P36 -> 0
B37: Dont avoirs de performance | C37: -663.74807 | D37: -608.7085 | E37: -650.73558 | F37: -628.75003 | G37: -642.93574 | H37: -615.80472 | I37: -612.14734 | J37: -602.96786 | K37: -569.4616 | L37: -586.8822 | M37: -563.52516 | N37: -598.76172 | O37: =SUM(C37:N37) -> -7344.4285 | P37: -7125.8253 | Q37: -5414.3549 | R37: -6564.8615 | S37: =O37/P37-1 -> 0.0306776 | T37: =P37/Q37-1 -> 0.31609868 | U37: =O37/R37-1 -> 0.11874844 | V37: -7175.3894 | X37: =V37-P37 -> -49.564117
B38: Dont Commissions Flooz | C38: -365.55046 | D38: -370.70563 | E38: -403.9947 | F38: -420.75276 | G38: -436.68452 | H38: -435.58421 | I38: -466.218 | J38: -459.26717 | K38: -442.4551 | L38: -474.44326 | M38: -444.0457 | N38: -513.94108 | O38: =SUM(C38:N38) -> -5233.6426 | P38: -4661.4737 | Q38: -4504.3534 | R38: -4873.0681 | S38: =O38/P38-1 -> 0.12274422 | T38: =P38/Q38-1 -> 0.034881865 | U38: =O38/R38-1 -> 0.073993322 | V38: -4661.4737 | X38: =V38-P38 -> 0
A39: Coûts des ventes | C39: =SUM(C11,C14,C17,C20,C25,C28,C29,C31,C35) -> -1517.7256 | D39: =SUM(D11,D14,D17,D20,D25,D28,D29,D31,D35) -> -1459.5803 | E39: =SUM(E11,E14,E17,E20,E25,E28,E29,E31,E35) -> -1580.7997 | F39: =SUM(F11,F14,F17,F20,F25,F28,F29,F31,F35) -> -1545.981 | G39: =SUM(G11,G14,G17,G20,G25,G28,G29,G31,G35) -> -1578.2509 | H39: =SUM(H11,H14,H17,H20,H25,H28,H29,H31,H35) -> -1551.4919 | I39: =SUM(I11,I14,I17,I20,I25,I28,I29,I31,I35) -> -1581.9014 | J39: =SUM(J11,J14,J17,J20,J25,J28,J29,J31,J35) -> -1573.4276 | ... N39: =SUM(N11,N14,N17,N20,N25,N28,N29,N31,N35) -> -1637.9559 | O39: =SUM(C39:N39) -> -18651.46 | P39: -17895.733 | Q39: -15895.604 | R39: -16769.806 | S39: =O39/P39-1 -> 0.042229483 | T39: =P39/Q39-1 -> 0.12582906 | U39: =O39/R39-1 -> 0.11220487 | V39: -17945.297 | X39: =V39-P39 -> -49.564117
O40: =SUM(C40:N40) -> 0 | P40: 0 | Q40: 0 | R40: 0 | V40: 0 | X40: =V40-P40 -> 0
A41: Marge Brute | C41: =C39+C8 -> 8009.3634 | D41: =D39+D8 -> 7322.5424 | E41: =E39+E8 -> 7892.3393 | F41: =F39+F8 -> 7816.5569 | G41: =G39+G8 -> 8194.2127 | H41: =H39+H8 -> 7915.194 | I41: =I39+I8 -> 8032.1538 | J41: =J39+J8 -> 8044.8221 | ... N41: =N39+N8 -> 8655.4868 | O41: =SUM(C41:N41) -> 95682.303 | P41: 90496.022 | Q41: 89647.387 | R41: 99129.814 | S41: =O41/P41-1 -> 0.057309502 | T41: =P41/Q41-1 -> 0.0094663567 | U41: =O41/R41-1 -> -0.034777734 | V41: 90942.059 | X41: =V41-P41 -> 446.03699
A42: En % du CA | C42: =+C41/C8 -> 0.84069366 | D42: =+D41/D8 -> 0.83380097 | E42: =+E41/E8 -> 0.83312821 | F42: =+F41/F8 -> 0.83487586 | G42: =+G41/G8 -> 0.8385002 | H42: =+H41/H8 -> 0.83611034 | I42: =+I41/I8 -> 0.83545951 | J42: =+J41/J8 -> 0.83641227 | ... O42: =+O41/O8 -> 0.83686831 | P42: 0.83489766 | Q42: 0.84939214 | R42: 0.8553075 | S42: =O42/P42-1 -> 0.0023603524 | T42: =P42/Q42-1 -> -0.01706454 | U42: =O42/R42-1 -> -0.021558546 | V42: 0.83519393 | X42: =V42-P42 -> 0.0002962767
C44: =+C38/'CA Mobile'!C134 -> -0.73050319 | D44: =+D38/'CA Mobile'!D134 -> -0.72305301 | E44: =+E38/'CA Mobile'!E134 -> -0.74196925 | F44: =+F38/'CA Mobile'!F134 -> -0.7254402 | G44: =+G38/'CA Mobile'!G134 -> -0.72558018 | H44: =+H38/'CA Mobile'!H134 -> -0.72564575 | I44: =+I38/'CA Mobile'!I134 -> -0.70376454 | J44: =+J38/'CA Mobile'!J134 -> -0.70377776 | ... N44: =+N38/'CA Mobile'!N134 -> -0.70442758
C45: =('CA Mobile'!C134+'Marge Mobile '!C38)/'CA Mobile'!C134 -> 0.26949681 | D45: =('CA Mobile'!D134+'Marge Mobile '!D38)/'CA Mobile'!D134 -> 0.27694699 | E45: =('CA Mobile'!E134+'Marge Mobile '!E38)/'CA Mobile'!E134 -> 0.25803075 | F45: =('CA Mobile'!F134+'Marge Mobile '!F38)/'CA Mobile'!F134 -> 0.2745598 | G45: =('CA Mobile'!G134+'Marge Mobile '!G38)/'CA Mobile'!G134 -> 0.27441982 | H45: =('CA Mobile'!H134+'Marge Mobile '!H38)/'CA Mobile'!H134 -> 0.27435425 | I45: =('CA Mobile'!I134+'Marge Mobile '!I38)/'CA Mobile'!I134 -> 0.29623546 | J45: =('CA Mobile'!J134+'Marge Mobile '!J38)/'CA Mobile'!J134 -> 0.29622224 | ... N45: =('CA Mobile'!N134+'Marge Mobile '!N38)/'CA Mobile'!N134 -> 0.29557242
C47: -8093.7168 | D47: 0 | N47: #REF!
D48: =D8+D39 -> 7322.5424 | V48: -4437.3849
M49: 5331.1452 | V49: 4873.0681
V50: =SUM(V48:V49) -> 435.6832
M51: =M49+O38 -> 97.5026
V52: -6739.8615
V53: 6564.8615
V54: =SUM(V52:V53) -> -175
O57: 0.43778957
Q60: 2.6380985e-07

Sheet Parc Mobile
A2: Parc Mobile
C3: 197148.89 | D3: 244394.05 | E3: 303589.1 | F3: 369220.79 | G3: 447820.44 | H3: 526420.09 | I3: 605019.74 | J3: 683569.39 | K3: 762119.04 | L3: 840718.68 | M3: 919318.33 | N3: 994717.98
C4: JANVIER | D4: FEVRIER | E4: MARS | F4: AVRIL | G4: MAI | H4: JUIN | I4: JUILLET | J4: AOÛT | K4: SEPTEMBRE | L4: OCTOBRE | M4: NOVEMBRE | N4: DECEMBRE | O4: ANNUEL | S4: VARIATIONS
C5: 2025 Budget | D5: 2025 Budget | E5: 2025 Budget | F5: 2025 Budget | G5: 2025 Budget | H5: 2025 Budget | I5: 2025 Budget | J5: 2025 Budget | K5: 2025 Budget | L5: 2025 Budget | M5: 2025 Budget | N5: 2025 Budget | O5: 2025 Budget | P5: 2024 Actu3 | Q5: 2023 Réel | R5: Budget 2024 | S5: Var Budget vs Actu 3 % | T5: Var Actu 3 vs Réel 2023 % | U5: Var Budget Budget 24 %
B7: Parc Total Mobile Actif | C7: 6140897.3 | D7: 6174578.8 | E7: 6187123.7 | F7: 6209527 | G7: 6223085.1 | H7: 6254834.9 | I7: 6278665.8 | J7: 6307305 | K7: 6352166 | L7: 6388455.3 | M7: 6441799.2 | N7: 6486990.5 | O7: =N7 -> 6486990.5 | P7: 6067091.4 | Q7: 5746786 | R7: 6006490.9 | S7: =O7/P7-1 -> 0.069209287 | T7: =P7/Q7-1 -> 0.055736445 | U7: =O7/R7-1 -> 0.079996732 | V7: 6121535.6 | W7: =V7-P7 -> 54444.194
B8: dont parc 3G | C8: 881247.72 | D8: 881247.72 | E8: 881247.72 | F8: 881247.72 | G8: 881247.72 | H8: 881247.72 | I8: 881247.72 | J8: 881247.72 | K8: 881247.72 | L8: 881247.72 | M8: 881247.72 | N8: 881247.72 | O8: 919733.43 | P8: 3327959.1 | Q8: 811471.5 | R8: 919733.43 | V8: 919733.43 | W8: =V8-P8 -> -2408225.7
B9: dont parc Mobile Money | P9: 2891432 | W9: =V9-P9 -> -2891432
W10: =V10-P10 -> 0
B11: Parc Prépayé Actif | W11: =V11-P11 -> 0
B12: Parc prépayé actif début Période | C12: 6054240.1 | D12: 6046415.3 | E12: 6079796.8 | F12: 6092041.7 | G12: 6114095 | H12: 6127203.1 | I12: 6158502.9 | J12: 6181833.8 | K12: 6209873 | L12: 6254134 | M12: 6289773.3 | N12: 6342467.2 | O12: =C12 -> 6054240.1 | P12: 5659555 | Q12: 5409823 | R12: 5528591.6 | S12: =O12/P12-1 -> 0.069737827 | T12: =P12/Q12-1 -> 0.046162693 | U12: =O12/R12-1 -> 0.095078193 | V12: 5659555 | W12: =V12-P12 -> 0
B13: Activations totales | C13: 434521.2 | D13: 428524.8 | E13: 434912.77 | F13: 426587.3 | G13: 426528.35 | H13: 426983.04 | I13: 427705.94 | J13: 427966.2 | K13: 427029.77 | L13: 426816.2 | M13: 427088.11 | N13: 427159.66 | O13: =SUM(C13,D13,E13,F13,G13,H13,I13,J13,K13,L13,M13,N13) -> 5141823.3 | P13: 5258044.7 | Q13: 3959545 | R13: 4050915.6 | S13: =O13/P13-1 -> -0.022103538 | T13: =P13/Q13-1 -> 0.32794164 | U13: =O13/R13-1 -> 0.26929906 | V13: 5352665.8 | W13: =V13-P13 -> 94621.1
B14: Flux d'inactivité | C14: -442345.92 | D14: -395143.33 | E14: -422667.84 | F14: -404534.02 | G14: -413420.29 | H14: -395683.22 | I14: -404375.06 | J14: -399926.94 | K14: -382768.78 | L14: -391176.94 | M14: -374394.18 | N14: -382618.38 | O14: =SUM(C14,D14,E14,F14,G14,H14,I14,J14,K14,L14,M14,N14) -> -4809054.9 | P14: -4944690.3 | Q14: -3709813 | R14: -3663472.3 | S14: =O14/P14-1 -> -0.027430513 | T14: =P14/Q14-1 -> 0.33286779 | U14: =O14/R14-1 -> 0.31270404 | V14: -4983573.2 | W14: =V14-P14 -> -38882.906
B15: Acroissement net | C15: -7824.7263 | D15: 33381.464 | E15: 12244.931 | F15: 22053.282 | G15: 13108.062 | H15: 31299.818 | I15: 23330.876 | J15: 28039.261 | K15: 44260.988 | L15: 35639.259 | M15: 52693.93 | N15: 44541.282 | O15: =SUM(C15,D15,E15,F15,G15,H15,I15,J15,K15,L15,M15,N15) -> 332768.42 | P15: 313354.42 | Q15: 249732 | R15: 387443.28 | S15: =O15/P15-1 -> 0.061955406 | T15: =P15/Q15-1 -> 0.2547628 | U15: =O15/R15-1 -> -0.14111707 | V15: 369092.62 | W15: =V15-P15 -> 55738.194
B16: % churn annualisé | C16: 0.87733282 | D16: 0.7820612 | E16: 0.83340146 | F16: 0.79540454 | G16: 0.81054205 | H16: 0.7729631 | I16: 0.78644544 | J16: 0.77457018 | K16: 0.73703832 | L16: 0.74843079 | M16: 0.7113117 | N16: 0.72138407 | O16: =(-O14/O18) -> 0.77308236 | P16: 0.85015352 | Q16: 0.67028392 | R16: 0.64020828 | S16: =O16/P16-1 -> -0.09065558 | T16: =P16/Q16-1 -> 0.26834838 | U16: =O16/R16-1 -> 0.20754821 | V16: 0.85275271 | W16: =V16-P16 -> 0.0025991842
B17: Parc prépayé actif fin de période | C17: 6046415.3 | D17: 6079796.8 | E17: 6092041.7 | F17: 6114095 | G17: 6127203.1 | H17: 6158502.9 | I17: 6181833.8 | J17: 6209873 | K17: 6254134 | L17: 6289773.3 | M17: 6342467.2 | N17: 6387008.5 | O17: =O12+O15 -> 6387008.5 | P17: 5972909.4 | Q17: 5659555 | R17: 5916034.9 | S17: =O17/P17-1 -> 0.069329541 | T17: =P17/Q17-1 -> 0.055367326 | U17: =O17/R17-1 -> 0.07960968 | V17: 6028647.6 | W17: =V17-P17 -> 55738.194
B18: Parc Actif Moyen | C18: 6050327.7 | D18: 6063106.1 | E18: 6085919.3 | F18: 6103068.4 | G18: 6120649.1 | H18: 6142853 | I18: 6170168.3 | J18: 6195853.4 | K18: 6232003.5 | L18: 6271953.7 | M18: 6316120.2 | N18: 6364737.9 | O18: =(O12+O17)/2 -> 6220624.3 | P18: 5816232.2 | Q18: 5534689 | R18: 5722313.2 | S18: =O18/P18-1 -> 0.069528185 | T18: =P18/Q18-1 -> 0.050868841 | U18: =O18/R18-1 -> 0.087082103 | V18: 5844101.3 | W18: =V18-P18 -> 27869.097
W19: =V19-P19 -> 0
B20: Parc Postpayé | W20: =V20-P20 -> 0
B21: Parc début Période | C21: 94182 | D21: 94482 | E21: 94782 | F21: 95082 | G21: 95432 | H21: 95882 | I21: 96332 | J21: 96832 | K21: 97432 | L21: 98032 | M21: 98682 | N21: 99332 | O21: =C21 -> 94182 | P21: 87231 | Q21: 70390 | R21: 85656 | S21: =O21/P21-1 -> 0.079684974 | T21: =P21/Q21-1 -> 0.23925273 | U21: =O21/R21-1 -> 0.099537686 | V21: 87231 | W21: =V21-P21 -> 0
B22: Activations totales | C22: 2000 | D22: 2000 | E22: 2000 | F22: 2000 | G22: 2100 | H22: 2100 | I22: 2100 | J22: 2200 | K22: 2200 | L22: 2200 | M22: 2200 | N22: 2200 | O22: =SUM(C22,D22,E22,F22,G22,H22,I22,J22,K22,L22,M22,N22) -> 25300 | P22: 32357 | Q22: 38118 | R22: 24900 | S22: =O22/P22-1 -> -0.21809809 | T22: =P22/Q22-1 -> -0.15113595 | U22: =O22/R22-1 -> 0.016064257 | V22: 24514 | W22: =V22-P22 -> -7843
B23: Résiliations totales | C23: -1700 | D23: -1700 | E23: -1700 | F23: -1650 | G23: -1650 | H23: -1650 | I23: -1600 | J23: -1600 | K23: -1600 | L23: -1550 | M23: -1550 | N23: -1550 | O23: =SUM(C23,D23,E23,F23,G23,H23,I23,J23,K23,L23,M23,N23) -> -19500 | P23: -25406 | Q23: -21277 | R23: -20100 | S23: =O23/P23-1 -> -0.23246477 | T23: =P23/Q23-1 -> 0.19405931 | U23: =O23/R23-1 -> -0.029850746 | V23: -29093 | W23: =V23-P23 -> -3687
B24: % résiliation annualisé | C24: 0.21625747 | D24: 0.2155719 | E24: 0.21489066 | F24: 0.20785874 | G24: 0.20698956 | H24: 0.20602037 | I24: 0.19879481 | J24: 0.19766915 | K24: 0.19645561 | L24: 0.18910703 | M24: 0.1878655 | N24: 0.18664018 | O24: =-(O23/O27) -> 0.20086113 | P24: 0.28009018 | Q24: 0.26997672 | R24: 0.22826383 | S24: =O24/P24-1 -> -0.2828698 | T24: =P24/Q24-1 -> 0.037460507 | U24: =O24/R24-1 -> -0.12004839 | V24: 0.34250631 | W24: =V24-P24 -> 0.062416132
B25: Ventes nettes | C25: 300 | D25: 300 | E25: 300 | F25: 350 | G25: 450 | H25: 450 | I25: 500 | J25: 600 | K25: 600 | L25: 650 | M25: 650 | N25: 650 | O25: =SUM(C25,D25,E25,F25,G25,H25,I25,J25,K25,L25,M25,N25) -> 5800 | P25: 6951 | Q25: 16841 | R25: 4800 | S25: =O25/P25-1 -> -0.16558769 | T25: =P25/Q25-1 -> -0.58725729 | U25: =O25/R25-1 -> 0.20833333 | V25: -4579 | W25: =V25-P25 -> -11530
B26: Parc Postpayé | C26: 94482 | D26: 94782 | E26: 95082 | F26: 95432 | G26: 95882 | H26: 96332 | I26: 96832 | J26: 97432 | K26: 98032 | L26: 98682 | M26: 99332 | N26: 99982 | O26: =O21+O25 -> 99982 | P26: 94182 | Q26: 87231 | R26: 90456 | S26: =O26/P26-1 -> 0.061582893 | T26: =P26/Q26-1 -> 0.079684974 | U26: =O26/R26-1 -> 0.10531087 | V26: 82652 | W26: =V26-P26 -> -11530
B27: Parc Moyen Postpayé | C27: 94332 | D27: 94632 | E27: 94932 | F27: 95257 | G27: 95657 | H27: 96107 | I27: 96582 | J27: 97132 | K27: 97732 | L27: 98357 | M27: 99007 | N27: 99657 | O27: =(O21+O26)/2 -> 97082 | P27: 90706.5 | Q27: 78810.5 | R27: 88056 | S27: =O27/P27-1 -> 0.070287135 | T27: =P27/Q27-1 -> 0.15094435 | U27: =O27/R27-1 -> 0.10250295 | V27: 84941.5 | W27: =V27-P27 -> -5765
B32: Parc Total Mobile Actif | C32: 5835646 | D32: 5906397.5 | E32: 5993541.5 | F32: 6098953.7 | G32: 6209309.1 | H32: 6297430.7 | I32: 6418927 | J32: 6544225.7 | K32: 6658558.9 | L32: 6770929.3 | M32: 6880902.4 | N32: 7001208.8
B34: Parc Total Mobile Actif | C34: 5638497.1 | D34: 5662003.4 | E34: 5689952.4 | F34: 5729732.9 | G34: 5761488.7 | H34: 5771010.6 | I34: 5813907.3 | J34: 5860656.3 | K34: 5896439.8 | L34: 5930210.7 | M34: 5961584 | N34: 6006490.9
C35: =C32-C34 -> 197148.89 | D35: =D32-D34 -> 244394.05 | E35: =E32-E34 -> 303589.1 | F35: =F32-F34 -> 369220.79 | G35: =G32-G34 -> 447820.44 | H35: =H32-H34 -> 526420.09 | I35: =I32-I34 -> 605019.74 | J35: =J32-J34 -> 683569.39 | ... N35: =N32-N34 -> 994717.98

Sheet Trafic mobile
B1: Trafic Mobile
C3: JANVIER | D3: FEVRIER | E3: MARS | F3: AVRIL | G3: MAI | H3: JUIN | I3: JUILLET | J3: AOÛT | K3: SEPT | L3: OCT | M3: NOV | N3: DEC | O3: ANNUEL | T3: VARIATIONS
B4: (En millions minutes) | C4: 2025 Budget | D4: 2025 Budget | E4: 2025 Budget | F4: 2025 Budget | G4: 2025 Budget | H4: 2025 Budget | I4: 2025 Budget | J4: 2025 Budget | K4: 2025 Budget | L4: 2025 Budget | M4: 2025 Budget | N4: 2025 Budget | O4: 2025 Budget | P4: 2024 Actu3 | Q4: 2023 Réel | R4: 2022 Réel | S4: Budget 2024 | T4: Var Budget vs Actu 3. % | U4: Var Actu 3 vs Réel 2023 . % | V4: Var Budget vs Budget 24 . %
B6: Total Trafic sortant | C6: =SUM(C8,C17) -> 169.12374 | D6: =SUM(D8,D17) -> 154.28061 | E6: =SUM(E8,E17) -> 162.33797 | F6: =SUM(F8,F17) -> 158.65159 | G6: =SUM(G8,G17) -> 161.4584 | H6: =SUM(H8,H17) -> 154.48038 | I6: =SUM(I8,I17) -> 149.59275 | J6: =SUM(J8,J17) -> 143.51434 | ... N6: =SUM(N8,N17) -> 155.56778 | O6: =SUM(C6,D6,E6,F6,G6,H6,I6,J6,K6,L6,M6,N6) -> 1831.1053 | P6: 1778.1186 | Q6: 1908.6462 | R6: 2012.8978 | S6: 1786.0781 | T6: =O6/P6-1 -> 0.029799284 | U6: =P6/Q6-1 -> -0.068387529 | V6: =O6/S6-1 -> 0.025210099 | X6: 1798.1063 | Y6: =X6-P6 -> 19.987702
Y7: =X7-P7 -> 0
B8: Trafic sortant prépayé (Consumer) | C8: =SUM(C9:C15) -> 156.49686 | D8: =SUM(D9:D15) -> 142.34973 | E8: =SUM(E9:E15) -> 148.95455 | F8: =SUM(F9:F15) -> 146.50146 | G8: =SUM(G9:G15) -> 151.54463 | H8: =SUM(H9:H15) -> 142.18138 | I8: =SUM(I9:I15) -> 138.17133 | J8: =SUM(J9:J15) -> 132.89169 | ... N8: =SUM(N9:N15) -> 146.94705 | O8: =SUM(C8,D8,E8,F8,G8,H8,I8,J8,K8,L8,M8,N8) -> 1695.1829 | P8: 1638.2853 | Q8: 1769.3847 | R8: 1869.8015 | S8: 1654.0294 | T8: =O8/P8-1 -> 0.034729969 | U8: =P8/Q8-1 -> -0.07409319 | V8: =O8/S8-1 -> 0.024880762 | X8: 1656.7153 | Y8: =X8-P8 -> 18.429975
B9: vers le fixe | C9: 0.0088143278 | D9: 0.0087350376 | E9: 0.0083520295 | F9: 0.0086643282 | G9: 0.0088827986 | H9: 0.008772194 | I9: 0.0085366079 | J9: 0.008579898 | K9: 0.0085389761 | L9: 0.008682194 | M9: 0.0088783271 | N9: 0.0096679524 | O9: =SUM(C9,D9,E9,F9,G9,H9,I9,J9,K9,L9,M9,N9) -> 0.10510467 | P9: 0.33457908 | Q9: 0.5634704 | R9: 0.30777089 | S9: 0.31161853 | T9: =O9/P9-1 -> -0.68586001 | U9: =P9/Q9-1 -> -0.4062171 | V9: =O9/S9-1 -> -0.66271367 | X9: 0.33677096 | Y9: =X9-P9 -> 0.0021918793
B10: vers l'international | C10: 1.3480652 | D10: 1.1185043 | E10: 1.29972 | F10: 1.0664192 | G10: 0.96992465 | H10: 0.92578156 | I10: 0.79568462 | J10: 0.77587579 | K10: 0.76204111 | L10: 0.7972213 | M10: 0.74444491 | N10: 0.86308027 | O10: =SUM(C10,D10,E10,F10,G10,H10,I10,J10,K10,L10,M10,N10) -> 11.466763 | P10: 17.213976 | Q10: 19.26176 | R10: 25.959051 | S10: 14.773136 | T10: =O10/P10-1 -> -0.33386902 | U10: =P10/Q10-1 -> -0.10631341 | V10: =O10/S10-1 -> -0.22380985 | X10: 17.562178 | Y10: =X10-P10 -> 0.348202
B11: vers Mobile (on net) | C11: 69.350534 | D11: 65.431963 | E11: 68.352878 | F11: 66.876296 | G11: 68.391682 | H11: 63.585979 | I11: 60.068698 | J11: 55.230967 | K11: 52.276362 | L11: 55.534755 | M11: 54.542957 | N11: 62.724564 | O11: =SUM(C11,D11,E11,F11,G11,H11,I11,J11,K11,L11,M11,N11) -> 742.36764 | P11: 773.5194 | Q11: 857.55422 | R11: 933.2986 | S11: 798.81599 | T11: =O11/P11-1 -> -0.040272767 | U11: =P11/Q11-1 -> -0.097993588 | V11: =O11/S11-1 -> -0.070665033 | W11: 0 | X11: 786.68426 | Y11: =X11-P11 -> 13.164855
B12: vers MTN | C12: 76.140529 | D12: 66.790375 | E12: 69.290048 | F12: 68.170955 | G12: 70.775152 | H12: 66.286465 | I12: 65.323355 | J12: 64.341525 | K12: 60.729633 | L12: 62.53035 | M12: 60.642647 | N12: 66.872572 | O12: =SUM(C12,D12,E12,F12,G12,H12,I12,J12,K12,L12,M12,N12) -> 797.89361 | P12: 787.2296 | Q12: 867.29569 | R12: 906.19173 | S12: 792.95501 | T12: =O12/P12-1 -> 0.013546254 | U12: =P12/Q12-1 -> -0.092316957 | V12: =O12/S12-1 -> 0.0062280892 | X12: 791.75598 | Y12: =X12-P12 -> 4.5263811
B13: vers SBIN | C13: 7.6777517 | D13: 7.2159793 | E13: 8.0207593 | F13: 8.4548755 | G13: 9.4048501 | H13: 9.4375475 | I13: 9.9647406 | J13: 10.516036 | K13: 10.634685 | L13: 11.732162 | M13: 12.190698 | N13: 14.403289 | O13: =SUM(C13,D13,E13,F13,G13,H13,I13,J13,K13,L13,M13,N13) -> 119.65337 | P13: 54.190724 | Q13: 24.549522 | R13: 1.5038872 | S13: 38.307673 | U13: =P13/Q13-1 -> 1.2074045 | V13: =O13/S13-1 -> 2.1234832 | X13: 54.492523 | Y13: =X13-P13 -> 0.30179866
B14: vers BBCOM, LIBERCOM | C14: 0 | D14: 0 | E14: 0 | F14: 0 | G14: 0 | H14: 0 | I14: 0 | J14: 0 | K14: 0 | L14: 0 | M14: 0 | N14: 0 | O14: =SUM(C14,D14,E14,F14,G14,H14,I14,J14,K14,L14,M14,N14) -> 0 | P14: 0 | Q14: 0 | R14: 0 | S14: 0 | X14: 0 | Y14: =X14-P14 -> 0
B15: Outbound roaming | C15: 1.9711659 | D15: 1.7841782 | E15: 1.9827923 | F15: 1.9242525 | G15: 1.9941372 | H15: 1.9368294 | I15: 2.0103133 | J15: 2.0187037 | K15: 1.9650122 | L15: 2.0435628 | M15: 1.9916036 | N15: 2.0738719 | O15: =SUM(C15,D15,E15,F15,G15,H15,I15,J15,K15,L15,M15,N15) -> 23.696423 | P15: 5.7970317 | Q15: 0.48 | R15: 0.486 | S15: 8.8659604 | T15: =O15/P15-1 -> 3.0876822 | U15: =P15/Q15-1 -> 11.077149 | V15: =O15/S15-1 -> 1.6727418 | X15: 5.883578 | Y15: =X15-P15 -> 0.086546277
Y16: =X16-P16 -> 0
B17: Trafic sortant postpayé | C17: =C26+C35+C44 -> 12.62688 | D17: =D26+D35+D44 -> 11.930873 | E17: =E26+E35+E44 -> 13.383415 | F17: =F26+F35+F44 -> 12.150126 | G17: =G26+G35+G44 -> 9.9137732 | H17: =H26+H35+H44 -> 12.299008 | I17: =I26+I35+I44 -> 11.421422 | J17: =J26+J35+J44 -> 10.622652 | ... N17: =N26+N35+N44 -> 8.6207339 | O17: =SUM(C17,D17,E17,F17,G17,H17,I17,J17,K17,L17,M17,N17) -> 135.92235 | P17: 138.63332 | Q17: 139.26153 | R17: 143.09632 | S17: 132.04865 | T17: =O17/P17-1 -> -0.019554961 | U17: =P17/Q17-1 -> -0.0045110115 | V17: =O17/S17-1 -> 0.029335351 | X17: 141.39101 | Y17: =X17-P17 -> 2.7576939
B18: vers le fixe | Q18: 0.062335242 | R18: 0.070295001 | U18: =P18/Q18-1 -> -1 | Y18: =X18-P18 -> 0
B19: vers l'international | Q19: 0.50556721 | R19: 0.67424642 | U19: =P19/Q19-1 -> -1 | Y19: =X19-P19 -> 0
B20: vers Mobile (on net) | Q20: 104.23721 | R20: 105.79902 | U20: =P20/Q20-1 -> -1 | Y20: =X20-P20 -> 0
B21: vers MTN | Q21: 33.810424 | R21: 36.509247 | U21: =P21/Q21-1 -> -1 | Y21: =X21-P21 -> 0
B22: vers GLO | Q22: 0.64599502 | R22: 0.04350526 | U22: =P22/Q22-1 -> -1 | Y22: =X22-P22 -> 0
B23: vers BBCOM, LIBERCOM | Q23: 0 | R23: 0 | T23: =O23-Q23 -> 0 | Y23: =X23-P23 -> 0
B24: Outbound roaming | Q24: 0 | R24: 0 | T24: =O24-Q24 -> 0 | Y24: =X24-P24 -> 0
Y25: =X25-P25 -> 0
B26: Consumer Postpaid | C26: =SUM(C27:C33) -> 0.022562499 | D26: =SUM(D27:D33) -> 0.019926689 | E26: =SUM(E27:E33) -> 0.022776859 | F26: =SUM(F27:F33) -> 0.025242084 | G26: =SUM(G27:G33) -> 0.032878844 | H26: =SUM(H27:H33) -> 0.032741338 | I26: =SUM(I27:I33) -> 0.032187142 | J26: =SUM(J27:J33) -> 0.032036093 | ... N26: =SUM(N27:N33) -> 0.031517372 | O26: =SUM(C26,D26,E26,F26,G26,H26,I26,J26,K26,L26,M26,N25) -> 0.31360973 | P26: 0.28038985 | Q26: 0.3758737 | R26: 0.42466105 | S26: 0.3207637 | T26: =O26/P26-1 -> 0.11847748 | U26: =P26/Q26-1 -> -0.25403174 | V26: =O26/S26-1 -> -0.022302936 | X26: 0.30844517 | Y26: =X26-P26 -> 0.028055319
B27: vers le fixe | C27: 0.00011199502 | D27: 9.9411899e-05 | E27: 0.00011484144 | F27: 0.00012940474 | G27: 0.00017020512 | H27: 0.00016750749 | I27: 0.00016433263 | J27: 0.00016342687 | K27: 0.00015734437 | L27: 0.00016178476 | M27: 0.00015581873 | N27: 0.00016023989 | O27: =SUM(C27,D27,E27,F27,G27,H27,I27,J27,K27,L27,M27,N27) -> 0.001756313 | P27: 0.0014226417 | Q27: 0.0032584286 | R27: 0.0034682336 | S27: 0.0031682096 | T27: =O27/P27-1 -> 0.23454338 | U27: =P27/Q27-1 -> -0.56339637 | V27: =O27/S27-1 -> -0.44564496 | X27: 0.0014226417 | Y27: =X27-P27 -> 0
B28: vers l'international | C28: 0.001056045 | D28: 0.0008737006 | E28: 0.0010473539 | F28: 0.0011745514 | G28: 0.0014089232 | H28: 0.0014639273 | I28: 0.0013093621 | J28: 0.0013021452 | K28: 0.0012536813 | L28: 0.0012890612 | M28: 0.0012415254 | N28: 0.0012767521 | O28: =SUM(C28,D28,E28,F28,G28,H28,I28,J28,K28,L28,M28,N28) -> 0.014697029 | P28: 0.015583288 | Q28: 0.023902621 | R28: 0.028893803 | S28: 0.021409884 | T28: =O28/P28-1 -> -0.056872436 | U28: =P28/Q28-1 -> -0.34805108 | V28: =O28/S28-1 -> -0.31354001 | X28: 0.016800117 | Y28: =X28-P28 -> 0.001216829
B29: vers Mobile (on net) | C29: 0.0080677578 | D29: 0.0070782028 | E29: 0.0080017297 | F29: 0.0090038188 | G29: 0.012356233 | H29: 0.012499969 | I29: 0.012313711 | J29: 0.012245842 | K29: 0.01179007 | L29: 0.012122795 | M29: 0.011675751 | N29: 0.012007036 | O29: =SUM(C29,D29,E29,F29,G29,H29,I29,J29,K29,L29,M29,N29) -> 0.12916292 | P29: 0.1240642 | Q29: 0.13978293 | R29: 0.16266096 | S29: 0.13387254 | T29: =O29/P29-1 -> 0.041097402 | U29: =P29/Q29-1 -> -0.11245099 | V29: =O29/S29-1 -> -0.035179941 | X29: 0.13477999 | Y29: =X29-P29 -> 0.010715792
B30: vers MTN | C30: 0.01033425 | D30: 0.0091731534 | E30: 0.010596902 | F30: 0.011940718 | G30: 0.015705541 | H30: 0.015456619 | I30: 0.015163662 | J30: 0.015080084 | K30: 0.014518826 | L30: 0.014928559 | M30: 0.014378049 | N30: 0.014786008 | O30: =SUM(C30,D30,E30,F30,G30,H30,I30,J30,K30,L30,M30,N30) -> 0.16206237 | P30: 0.15667186 | Q30: 0.19569687 | R30: 0.22950059 | S30: 0.17158865 | T30: =O30/P30-1 -> 0.03440638 | U30: =P30/Q30-1 -> -0.1994156 | V30: =O30/S30-1 -> -0.055518138 | X30: 0.16995403 | Y30: =X30-P30 -> 0.01328217
B31: vers SBIN | C31: 0.00041718147 | D31: 0.00037030935 | E31: 0.00042778441 | F31: 0.00048203268 | G31: 0.00063401411 | H31: 0.00062396544 | I31: 0.0006121391 | J31: 0.00060876515 | K31: 0.00058610781 | L31: 0.00060264826 | M31: 0.00058042483 | N31: 0.00059689364 | O31: =SUM(C31,D31,E31,F31,G31,H31,I31,J31,K31,L31,M31,N31) -> 0.0065422662 | P31: 0.0043273381 | Q31: 0.0018912781 | R31: 0.00013747459 | S31: 0.016919792 | T31: =O31/P31-1 -> 0.5118454 | U31: =P31/Q31-1 -> 1.2880496 | V31: =O31/S31-1 -> -0.61333649 | X31: 0.0047070671 | Y31: =X31-P31 -> 0.00037972901
B32: vers BBCOM, LIBERCOM | C32: 0 | D32: 0 | E32: 0 | F32: 0 | G32: 0 | H32: 0 | I32: 0 | J32: 0 | K32: 0 | L32: 0 | M32: 0 | N32: 0 | O32: =SUM(C32,D32,E32,F32,G32,H32,I32,J32,K32,L32,M32,N32) -> 0 | P32: 0 | Q32: 0 | R32: 0 | S32: 0 | X32: 0 | Y32: =X32-P32 -> 0
B33: Outbound roaming | C33: 0.0025752695 | D33: 0.0023319106 | E33: 0.0025882469 | F33: 0.0025115577 | G33: 0.0026039278 | H33: 0.0025293492 | I33: 0.0026239345 | J33: 0.0026358304 | K33: 0.0025633623 | L33: 0.0026623258 | M33: 0.0025900496 | N33: 0.0026904433 | Q33: 0 | R33: 0 | Y33: =X33-P33 -> 0
T34: =O34/Q34-1 -> #DIV/0! | Y34: =X34-P34 -> 0
B35: Business Postpaid | C35: =SUM(C36:C42) -> 0.23721707 | D35: =SUM(D36:D42) -> 0.20657556 | E35: =SUM(E36:E42) -> 0.21710122 | F35: =SUM(F36:F42) -> 0.2150978 | G35: =SUM(G36:G42) -> 0.22748277 | H35: =SUM(H36:H42) -> 0.22845812 | I35: =SUM(I36:I42) -> 0.21698871 | J35: =SUM(J36:J42) -> 0.21286684 | ... N35: =SUM(N36:N42) -> 0.27028468 | O35: =SUM(C35,D35,E35,F35,G35,H35,I35,J35,K35,L35,M35,N35) -> 2.6841616 | P35: 2.3686868 | Q35: 2.9504232 | R35: 3.4930359 | S35: 2.6278223 | T35: =O35/P35-1 -> 0.13318553 | U35: =P35/Q35-1 -> -0.19717048 | V35: =O35/S35-1 -> 0.02143955 | X35: 2.6027913 | Y35: =X35-P35 -> 0.23410451
B36: vers le fixe | C36: 0.00091914556 | D36: 0.00086455135 | E36: 0.00082507932 | F36: 0.00084665672 | G36: 0.00087527194 | H36: 0.00090733106 | I36: 0.00082359646 | J36: 0.00081840697 | K36: 0.00083355903 | L36: 0.000809251 | M36: 0.00089628154 | N36: 0.0010300368 | O36: =SUM(C36,D36,E36,F36,G36,H36,I36,J36,K36,L36,M36,N36) -> 0.010449168 | P36: 0.0060944501 | Q36: 0.0095560547 | R36: 0.010171354 | S36: 0.009277414 | T36: =O36/P36-1 -> 0.71453824 | U36: =P36/Q36-1 -> -0.36224203 | V36: =O36/S36-1 -> 0.12630176 | X36: 0.0069990681 | Y36: =X36-P36 -> 0.00090461797
B37: vers l'international | C37: 0.0080630764 | D37: 0.0071215 | E37: 0.0074691834 | F37: 0.0071984518 | G37: 0.0065638823 | H37: 0.0066003714 | I37: 0.0068900733 | J37: 0.0078470946 | K37: 0.007752868 | L37: 0.0077599319 | M37: 0.0065561979 | N37: 0.0081689309 | O37: =SUM(C37,D37,E37,F37,G37,H37,I37,J37,K37,L37,M37,N37) -> 0.087991562 | P37: 0.085849665 | Q37: 0.14791548 | R37: 0.17880217 | S37: 0.11724805 | T37: =O37/P37-1 -> 0.024949387 | U37: =P37/Q37-1 -> -0.41960323 | V37: =O37/S37-1 -> -0.24952642 | X37: 0.093250112 | Y37: =X37-P37 -> 0.0074004462
B38: vers Mobile (on net) | C38: 0.11880592 | D38: 0.10460797 | E38: 0.10971511 | F38: 0.10865335 | G38: 0.11537804 | H38: 0.11601944 | I38: 0.1102595 | J38: 0.10573019 | K38: 0.1044606 | L38: 0.10455578 | M38: 0.11992639 | N38: 0.139147 | O38: =SUM(C38,D38,E38,F38,G38,H38,I38,J38,K38,L38,M38,N38) -> 1.3572593 | P38: 1.2101266 | Q38: 1.4747287 | R38: 1.716095 | S38: 1.2108782 | T38: =O38/P38-1 -> 0.12158459 | U38: =P38/Q38-1 -> -0.1794243 | V38: =O38/S38-1 -> 0.12088833 | X38: 1.3289234 | Y38: =X38-P38 -> 0.11879681
B39: vers MTN | C39: 0.095147664 | D39: 0.080835284 | E39: 0.085410161 | F39: 0.08481658 | G39: 0.090605976 | H39: 0.090894829 | I39: 0.085256659 | J39: 0.084719455 | K39: 0.083504476 | L39: 0.083771653 | M39: 0.089787908 | N39: 0.10662685 | O39: =SUM(C39,D39,E39,F39,G39,H39,I39,J39,K39,L39,M39,N39) -> 1.0613775 | P39: 1.0010797 | Q39: 1.3528349 | R39: 1.586517 | S39: 1.1712851 | T39: =O39/P39-1 -> 0.060232735 | U39: =P39/Q39-1 -> -0.2600134 | V39: =O39/S39-1 -> -0.093835042 | X39: 1.0961632 | Y39: =X39-P39 -> 0.095083429
B40: vers SBIN | C40: 0.0061858847 | D40: 0.0058224141 | E40: 0.0055599907 | F40: 0.0057092639 | G40: 0.0059060955 | H40: 0.0061265676 | I40: 0.0055648088 | J40: 0.0055334845 | K40: 0.0056397409 | L40: 0.0054788548 | M40: 0.0060721713 | N40: 0.0069828975 | O40: =SUM(C40,D40,E40,F40,G40,H40,I40,J40,K40,L40,M40,N40) -> 0.070582174 | P40: 0.041609086 | Q40: 0.019953239 | R40: 0.0014503754 | S40: 0.019025664 | U40: =P40/Q40-1 -> 1.08533 | V40: =O40/S40-1 -> 2.7098403 | X40: 0.045757735 | Y40: =X40-P40 -> 0.0041486486
B41: vers BBCOM, LIBERCOM | C41: 0 | D41: 0 | E41: 0 | F41: 0 | G41: 0 | H41: 0 | I41: 0 | J41: 0 | K41: 0 | L41: 0 | M41: 0 | N41: 0 | O41: =SUM(C41,D41,E41,F41,G41,H41,I41,J41,K41,L41,M41,N41) -> 0 | P41: 0 | Q41: 0 | R41: 0 | S41: 0 | X41: 0 | Y41: =X41-P41 -> 0
B42: Outbound roaming | C42: 0.0080953742 | D42: 0.0073238374 | E42: 0.0081216944 | F42: 0.0078735011 | G42: 0.008153498 | H42: 0.0079095853 | I42: 0.008194075 | J42: 0.0082182018 | K42: 0.0079785697 | L42: 0.0082719389 | M42: 0.008032696 | N42: 0.008328966 | O42: =SUM(C42,D42,E42,F42,G42,H42,I42,J42,K42,L42,M42,N42) -> 0.096501938 | P42: 0.023927342 | Q42: 0 | R42: 0 | S42: 0.10010785 | T42: =O42/Q42-1 -> #DIV/0! | X42: 0.031697897 | Y42: =X42-P42 -> 0.0077705552
Y43: =X43-P43 -> 0
B44: Business Prepaid | C44: =SUM(C45:C51) -> 12.3671 | D44: =SUM(D45:D51) -> 11.704371 | E44: =SUM(E45:E51) -> 13.143537 | F44: =SUM(F45:F51) -> 11.909787 | G44: =SUM(G45:G51) -> 9.6534116 | H44: =SUM(H45:H51) -> 12.037809 | I44: =SUM(I45:I51) -> 11.172246 | J44: =SUM(J45:J51) -> 10.377749 | ... N44: =SUM(N45:N51) -> 8.3189318 | O44: =SUM(C44,D44,E44,F44,G44,H44,I44,J44,K44,L44,M44,N44) -> 132.89306 | P44: 124.74315 | Q44: 135.89201 | R44: 139.17862 | S44: 129.06893 | T44: =O44/P44-1 -> 0.065333521 | U44: =P44/Q44-1 -> -0.082042036 | V44: =O44/S44-1 -> 0.029628598 | X44: 127.23868 | Y44: =X44-P44 -> 2.4955341
B45: vers le fixe | C45: 0.0043267545 | D45: 0.0041058465 | E45: 0.0046362039 | F45: 0.0041688977 | G45: 0.00018114643 | H45: 0.0041726473 | I45: 0.0038865416 | J45: 0.0036061118 | K45: 0.0037350215 | L45: 0.0036382747 | M45: 0.0035223925 | N45: 0.0033393039 | O45: =SUM(C45,D45,E45,F45,G45,H45,I45,J45,K45,L45,M45,N45) -> 0.043319142 | P45: 0.046818202 | Q45: 0.049520759 | R45: 0.056655413 | S45: 0.059318732 | T45: =O45/P45-1 -> -0.074737167 | U45: =P45/Q45-1 -> -0.054574222 | V45: =O45/S45-1 -> -0.26972238 | X45: 0.047663203 | Y45: =X45-P45 -> 0.00084500041
B46: vers l'international | C46: 0.029643405 | D46: 0.027634083 | E46: 0.033008857 | F46: 0.027374267 | G46: 0.026495034 | H46: 0.025704472 | I46: 0.022613923 | J46: 0.022437752 | K46: 0.02551042 | L46: 0.024442326 | M46: 0.023441958 | N46: 0.017102023 | O46: =SUM(C46,D46,E46,F46,G46,H46,I46,J46,K46,L46,M46,N46) -> 0.30540852 | P46: 0.34231868 | Q46: 0.33374911 | R46: 0.46655045 | S46: 0.22464125 | T46: =O46/P46-1 -> -0.10782397 | U46: =P46/Q46-1 -> 0.025676684 | V46: =O46/S46-1 -> 0.35953889 | X46: 0.34829595 | Y46: =X46-P46 -> 0.0059772704
B47: vers Mobile (on net) | C47: 9.4159199 | D47: 8.9058117 | E47: 9.982246 | F47: 9.0669989 | G47: 9.4717152 | H47: 9.1938916 | I47: 8.5210861 | J47: 7.9137282 | K47: 7.9185614 | L47: 8.503348 | M47: 8.3373786 | N47: 6.0374057 | O47: =SUM(C47,D47,E47,F47,G47,H47,I47,J47,K47,L47,M47,N47) -> 103.26809 | P47: 92.723122 | Q47: 102.6227 | R47: 103.92027 | S47: 85.161553 | T47: =O47/P47-1 -> 0.11372535 | U47: =P47/Q47-1 -> -0.09646573 | V47: =O47/S47-1 -> 0.212614 | X47: 95.010645 | Y47: =X47-P47 -> 2.2875228
B48: vers MTN | C48: 2.7076612 | D48: 2.5694181 | E48: 2.9013131 | F48: 2.6088752 | G48: 0.11336053 | H48: 2.6112217 | I48: 2.4321782 | J48: 2.2566866 | K48: 2.3373577 | L48: 2.276814 | M48: 2.2042955 | N48: 2.0897196 | O48: =SUM(C48,D48,E48,F48,G48,H48,I48,J48,K48,L48,M48,N48) -> 27.108901 | P48: 29.839092 | Q48: 32.261892 | R48: 34.69323 | S48: 31.532181 | T48: =O48/P48-1 -> -0.091497104 | U48: =P48/Q48-1 -> -0.075097884 | V48: =O48/S48-1 -> -0.14027825 | X48: 30.077517 | Y48: =X48-P48 -> 0.238425
B49: vers SBIN | C49: 0.17572373 | D49: 0.16675193 | E49: 0.18829148 | F49: 0.16931264 | G49: 0.0073569522 | H49: 0.16946493 | I49: 0.15784523 | J49: 0.14645606 | K49: 0.15169151 | L49: 0.1477623 | M49: 0.14305594 | N49: 0.13562011 | O49: =SUM(C49,D49,E49,F49,G49,H49,I49,J49,K49,L49,M49,N49) -> 1.7593328 | P49: 1.6922183 | Q49: 0.62415051 | R49: 0.04191741 | S49: 1.0082604 | U49: =P49/Q49-1 -> 1.7112344 | V49: =O49/S49-1 -> 0.74491915 | X49: 1.622772 | Y49: =X49-P49 -> -0.069446391
B50: vers BBCOM, LIBERCOM | C50: 0 | D50: 0 | E50: 0 | F50: 0 | G50: 0 | H50: 0 | I50: 0 | J50: 0 | K50: 0 | L50: 0 | M50: 0 | N50: 0 | O50: =SUM(C50,D50,E50,F50,G50,H50,I50,J50,K50,L50,M50,N50) -> 0 | P50: 0 | Q50: 0 | R50: 0 | S50: 0 | X50: 0 | Y50: =X50-P50 -> 0
B51: Outbound roaming | C51: 0.033824973 | D51: 0.030649299 | E51: 0.034041332 | F51: 0.033056638 | G51: 0.034302766 | H51: 0.03335326 | I51: 0.03463632 | J51: 0.034834649 | K51: 0.033920331 | L51: 0.035276382 | M51: 0.034365263 | N51: 0.035745161 | O51: =SUM(C51,D51,E51,F51,G51,H51,I51,J51,K51,L51,M51,N51) -> 0.40800637 | P51: 0.099581167 | Q51: 0 | R51: 0 | S51: 11.082974 | X51: 0.13179156 | Y51: =X51-P51 -> 0.032210395
Q52: 0 | T52: =O52-Q52 -> 0 | Y52: =X52-P52 -> 0
T53: =O53-Q53 -> 0 | Y53: =X53-P53 -> 0
B54: Total Trafic entrant | C54: =SUM(C56,C63) -> 99.221479 | D54: =SUM(D56,D63) -> 89.672571 | E54: =SUM(E56,E63) -> 99.645955 | F54: =SUM(F56,F63) -> 96.671092 | G54: =SUM(G56,G63) -> 100.05324 | H54: =SUM(H56,H63) -> 97.283341 | I54: =SUM(I56,I63) -> 100.98892 | J54: =SUM(J56,J63) -> 101.29805 | ... N54: =SUM(N56,N63) -> 104.19815 | O54: =SUM(C54,D54,E54,F54,G54,H54,I54,J54,K54,L54,M54,N54) -> 1190.0588 | P54: 1079.9224 | Q54: 940.67486 | R54: 904.55354 | S54: 1067.0823 | T54: =O54/P54-1 -> 0.10198552 | U54: =P54/Q54-1 -> 0.14802939 | V54: =O54/S54-1 -> 0.11524554 | X54: 1121.3353 | Y54: =X54-P54 -> 41.412956
Y55: =X55-P55 -> 0
B56: Trafic entrant prépayé (Consumer) | C56: =C57+C58+C59+C60+C61 -> 93.08818 | D56: =D57+D58+D59+D60+D61 -> 84.114231 | E56: =E57+E58+E59+E60+E61 -> 93.475076 | F56: =F57+F58+F59+F60+F61 -> 90.678881 | G56: =G57+G58+G59+G60+G61 -> 93.83678 | H56: =H57+H58+H59+H60+H61 -> 91.239421 | I56: =I57+I58+I59+I60+I61 -> 94.714264 | J56: =J57+J58+J59+J60+J61 -> 94.988816 | ... N56: =N57+N58+N59+N60+N61 -> 97.730122 | O56: =SUM(C56,D56,E56,F56,G56,H56,I56,J56,K56,L56,M56,N56) -> 1116.1423 | P56: 1019.0897 | Q56: 911.98618 | R56: 883.84582 | S56: 993.49099 | T56: =O56/P56-1 -> 0.095234571 | U56: =P56/Q56-1 -> 0.11743987 | V56: =O56/S56-1 -> 0.12345487 | X56: 1060.4979 | Y56: =X56-P56 -> 41.408155
B57: du fixe | C57: 0.04051346 | D57: 0.040546027 | E57: 0.04075236 | F57: 0.040850789 | G57: 0.040985475 | H57: 0.041117723 | I57: 0.041317861 | J57: 0.041490266 | K57: 0.041715874 | L57: 0.04200107 | M57: 0.042280252 | N57: 0.04262386 | O57: =SUM(C57,D57,E57,F57,G57,H57,I57,J57,K57,L57,M57,N57) -> 0.49619502 | P57: 0.49321291 | Q57: 0.62909476 | R57: 0.9688506 | S57: 0.658691 | T57: =O57/P57-1 -> 0.0060462932 | U57: =P57/Q57-1 -> -0.21599585 | V57: =O57/S57-1 -> -0.24669532 | X57: 0.48494819 | Y57: =X57-P57 -> -0.008264722
B58: de l'international | C58: 1.3117934 | D58: 1.1488717 | E58: 1.1575027 | F58: 1.1221936 | G58: 0.99112453 | H58: 1.0975392 | I58: 1.1156449 | J58: 0.99964247 | K58: 0.9868438 | L58: 0.99318575 | M58: 1.0064976 | N58: 1.1729817 | O58: =SUM(C58,D58,E58,F58,G58,H58,I58,J58,K58,L58,M58,N58) -> 13.103821 | P58: 15.501887 | Q58: 18.896236 | R58: 22.853483 | S58: 15.651869 | T58: =O58/P58-1 -> -0.15469507 | U58: =P58/Q58-1 -> -0.17963098 | V58: =O58/S58-1 -> -0.16279512 | X58: 15.653084 | Y58: =X58-P58 -> 0.15119759
B59: de MTN | C59: 42.855481 | D59: 38.739292 | E59: 43.108191 | F59: 41.818365 | G59: 43.354782 | H59: 42.09162 | I59: 43.706382 | J59: 43.888754 | K59: 42.70394 | L59: 44.429086 | M59: 43.281685 | N59: 45.08788 | O59: =SUM(C59,D59,E59,F59,G59,H59,I59,J59,K59,L59,M59,N59) -> 515.06546 | P59: 622.24377 | Q59: 825.25082 | R59: 855.34756 | S59: 884.42548 | T59: =O59/P59-1 -> -0.1722449 | U59: =P59/Q59-1 -> -0.24599436 | V59: =O59/S59-1 -> -0.41762707 | X59: 618.68227 | Y59: =X59-P59 -> -3.5615048
B60: de SBIN | C60: 48.880392 | D60: 44.185521 | E60: 49.16863 | F60: 47.697471 | G60: 49.449888 | H60: 48.009143 | I60: 49.850919 | J60: 50.058929 | K60: 48.707546 | L60: 50.675226 | M60: 49.366515 | N60: 51.426637 | O60: =SUM(C60,D60,E60,F60,G60,H60,I60,J60,K60,L60,M60,N60) -> 587.47682 | P60: 380.85085 | Q60: 58.144881 | R60: 4.6759251 | S60: 92.754949 | T60: =O60/P60-1 -> 0.54253777 | U60: =P60/Q60-1 -> 5.5500323 | V60: =O60/S60-1 -> 5.3336439 | X60: 425.67758 | Y60: =X60-P60 -> 44.826727
B61: de BBCOM, LIBERCOM | C61: 0 | D61: 0 | E61: 0 | F61: 0 | G61: 0 | H61: 0 | I61: 0 | J61: 0 | K61: 0 | L61: 0 | M61: 0 | N61: 0 | O61: =SUM(C61,D61,E61,F61,G61,H61,I61,J61,K61,L61,M61,N61) -> 0 | P61: 0 | Q61: 0 | R61: 0 | S61: 0 | T61: =O61-Q61 -> 0 | X61: 0 | Y61: =X61-P61 -> 0
Y62: =X62-P62 -> 0
B63: Trafic entrant postpayé | C63: =C64+C71+C78 -> 6.1332986 | D63: =D64+D71+D78 -> 5.5583407 | E63: =E64+E71+E78 -> 6.1708797 | F63: =F64+F71+F78 -> 5.9922118 | G63: =G64+G71+G78 -> 6.2164629 | H63: =H64+H71+H78 -> 6.0439208 | I63: =I64+I71+I78 -> 6.2746523 | J63: =J64+J71+J78 -> 6.3092328 | ... N63: =N64+N71+N78 -> 6.4680253 | O63: =SUM(C63,D63,E63,F63,G63,H63,I63,J63,K63,L63,M63,N63) -> 73.916537 | P63: 60.832666 | Q63: 28.688683 | R63: 20.707721 | S63: 73.591358 | U63: =P63/Q63-1 -> 1.1204412 | V63: =O63/S63-1 -> 0.0044187103 | X63: 60.837467 | Y63: =X63-P63 -> 0.0048016235
B64: Consumer Postpaid | C64: =SUM(C65:C69) -> 0.089364503 | D64: =SUM(D65:D69) -> 0.082388797 | E64: =SUM(E65:E69) -> 0.089761909 | F64: =SUM(F65:F69) -> 0.087628209 | G64: =SUM(G65:G69) -> 0.090302424 | H64: =SUM(H65:H69) -> 0.088240601 | I64: =SUM(I65:I69) -> 0.091002945 | J64: =SUM(J65:J69) -> 0.091412991 | ... N64: =SUM(N65:N69) -> 0.093308247 | O64: =SUM(C64,D64,E64,F64,G64,H64,I64,J64,K64,L64,M64,N64) -> 1.0755282 | P64: 0.76157988 | Q64: 84.381228 | R64: 0.11566068 | S64: 0.38792397 | T64: =O64/P64-1 -> 0.41223295 | U64: =P64/Q64-1 -> -0.99097453 | V64: =O64/S64-1 -> 1.7725232 | X64: 0.77813319 | Y64: =X64-P64 -> 0.016553306
B65: du fixe | C65: 5.1401718e-05 | D65: 5.1508626e-05 | E65: 5.1660742e-05 | F65: 5.1793976e-05 | G65: 5.197373e-05 | H65: 5.2160876e-05 | I65: 5.2373059e-05 | J65: 5.2610498e-05 | K65: 5.2862304e-05 | L65: 5.3139339e-05 | M65: 5.3412656e-05 | N65: 5.3700558e-05 | O65: =SUM(C65,D65,E65,F65,G65,H65,I65,J65,K65,L65,M65,N65) -> 0.00062859808 | P65: 0.00091621398 | Q65: 0.066323354 | R65: 0.56093711 | S65: 0.00067821545 | T65: =O65/P65-1 -> -0.31391782 | U65: =P65/Q65-1 -> -0.98618565 | V65: =O65/S65-1 -> -0.073158709 | X65: 0.00094770338 | Y65: =X65-P65 -> 3.148941e-05
B66: de l'international | C66: 0.016147148 | D66: 0.016114463 | E66: 0.016175596 | F66: 0.016230319 | G66: 0.016270286 | H66: 0.016336939 | I66: 0.016401997 | J66: 0.016473832 | K66: 0.016556348 | L66: 0.016640749 | M66: 0.016728211 | N66: 0.01681639 | O66: =SUM(C66,D66,E66,F66,G66,H66,I66,J66,K66,L66,M66,N66) -> 0.19689228 | P66: 0.049544501 | Q66: 1.8504663 | R66: 19.599362 | S66: 0.12502256 | T66: =O66/P66-1 -> 2.974049 | U66: =P66/Q66-1 -> -0.97322594 | V66: =O66/S66-1 -> 0.57485395 | X66: 0.068021405 | Y66: =X66-P66 -> 0.018476903
B67: de MTN | C67: 0.014031307 | D67: 0.012699797 | E67: 0.014102013 | F67: 0.013682306 | G67: 0.014187451 | H67: 0.013779229 | I67: 0.014296457 | J67: 0.014361271 | K67: 0.013964524 | L67: 0.014505631 | M67: 0.014109909 | N67: 0.014658829 | O67: =SUM(C67,D67,E67,F67,G67,H67,I67,J67,K67,L67,M67,N67) -> 0.16837872 | P67: 0.17141059 | Q67: 77.708387 | R67: 0.43176165 | S67: 0.16300416 | U67: =P67/Q67-1 -> -0.99779418 | V67: =O67/S67-1 -> 0.032971956 | X67: 0.18032832 | Y67: =X67-P67 -> 0.0089177319
B68: de SBIN | C68: 0.059134648 | D68: 0.053523028 | E68: 0.05943264 | F68: 0.05766379 | G68: 0.059792713 | H68: 0.058072272 | I68: 0.060252118 | J68: 0.060525277 | K68: 0.058853193 | L68: 0.061133677 | M68: 0.059465916 | N68: 0.061779327 | O68: =SUM(C68,D68,E68,F68,G68,H68,I68,J68,K68,L68,M68,N68) -> 0.7096286 | P68: 0.53943751 | Q68: 4.7560514 | R68: 0 | S68: 0.099219036 | X68: 0.5285647 | Y68: =X68-P68 -> -0.010872818
B69: de BBCOM, LIBERCOM | C69: 0 | D69: 0 | E69: 0 | F69: 0 | G69: 0 | H69: 0 | I69: 0 | J69: 0 | K69: 0 | L69: 0 | M69: 0 | N69: 0 | O69: =SUM(C69,D69,E69,F69,G69,H69,I69,J69,K69,L69,M69,N69) -> 0 | P69: 0.00027105889 | Q69: 0 | R69: 0 | S69: 0 | X69: 0.00027105889 | Y69: =X69-P69 -> 0
R70: 0
B71: Business Postpaid | C71: =SUM(C72:C76) -> 0.43785853 | D71: =SUM(D72:D76) -> 0.39673264 | E71: =SUM(E72:E76) -> 0.43924951 | F71: =SUM(F72:F76) -> 0.42604921 | G71: =SUM(G72:G76) -> 0.44096728 | H71: =SUM(H72:H76) -> 0.42799669 | I71: =SUM(I72:I76) -> 0.44316598 | J71: =SUM(J72:J76) -> 0.4444693 | ... N71: =SUM(N72:N76) -> 0.45046058 | O71: =SUM(C71,D71,E71,F71,G71,H71,I71,J71,K71,L71,M71,N71) -> 5.2207133 | P71: 4.3786512 | Q71: 1.9320507 | R71: 1.3951893 | S71: 2.0709618 | T71: =O71/P71-1 -> 0.19231085 | U71: =P71/Q71-1 -> 1.2663231
B72: du fixe | C72: 0.00029216196 | D72: 0.00029233141 | E72: 0.00029311186 | F72: 0.00029353095 | G72: 0.00029425965 | H72: 0.0002948762 | I72: 0.00029572407 | J72: 0.00029659481 | K72: 0.000297448 | L72: 0.00029853418 | M72: 0.00029946587 | N72: 0.00030059229 | O72: =SUM(C72,D72,E72,F72,G72,H72,I72,J72,K72,L72,M72,N72) -> 0.0035486312 | P72: 0.0036887562 | Q72: 0.003788596 | R72: 0.0095623397 | S72: 0.0036530352 | T72: =O72/P72-1 -> -0.037987059 | U72: =P72/Q72-1 -> -0.026352717
B73: de l'international | C73: 0.010581156 | D73: 0.010552573 | E73: 0.010582946 | F73: 0.01060799 | G73: 0.010622115 | H73: 0.010651516 | I73: 0.010679141 | J73: 0.010709036 | K73: 0.010744212 | L73: 0.010779873 | M73: 0.010816782 | N73: 0.01085413 | O73: =SUM(C73,D73,E73,F73,G73,H73,I73,J73,K73,L73,M73,N73) -> 0.12818147 | P73: 0.080191364 | Q73: 0.065129075 | R73: 0.076451192 | S73: 0.082097624 | T73: =O73/P73-1 -> 0.5984448 | U73: =P73/Q73-1 -> 0.23126827
B74: de MTN | C74: 0.091429198 | D74: 0.082629106 | E74: 0.091726458 | F74: 0.08889446 | G74: 0.092085648 | H74: 0.089301863 | I74: 0.092543925 | J74: 0.092816414 | K74: 0.09008072 | L74: 0.093423321 | M74: 0.090691823 | N74: 0.094067385 | O74: =SUM(C74,D74,E74,F74,G74,H74,I74,J74,K74,L74,M74,N74) -> 1.0896903 | P74: 1.2833825 | Q74: 1.4663602 | R74: 1.2779265 | S74: 1.4510674 | T74: =O74/P74-1 -> -0.15092318 | U74: =P74/Q74-1 -> -0.12478361
B75: de SBIN | C75: 0.33555601 | D75: 0.30325863 | E75: 0.33664699 | F75: 0.32625322 | G75: 0.33796526 | H75: 0.32774844 | I75: 0.33964719 | J75: 0.34064726 | K75: 0.33060694 | L75: 0.34287468 | M75: 0.33284976 | N75: 0.34523847 | O75: =SUM(C75,D75,E75,F75,G75,H75,I75,J75,K75,L75,M75,N75) -> 3.9992929 | P75: 3.0113886 | Q75: 0.39677286 | R75: 0.031249345 | S75: 0.53414379 | U75: =P75/Q75-1 -> 6.589704
B76: de BBCOM, LIBERCOM | C76: 0 | D76: 0 | E76: 0 | F76: 0 | G76: 0 | H76: 0 | I76: 0 | J76: 0 | K76: 0 | L76: 0 | M76: 0 | N76: 0 | O76: =SUM(C76,D76,E76,F76,G76,H76,I76,J76,K76,L76,M76,N76) -> 0 | P76: 0 | Q76: 0 | R76: 0 | S76: 0
B78: Business Prepaid | C78: =SUM(C79:C83) -> 5.6060756 | D78: =SUM(D79:D83) -> 5.0792193 | E78: =SUM(E79:E83) -> 5.6418683 | F78: =SUM(F79:F83) -> 5.4785344 | G78: =SUM(G79:G83) -> 5.6851932 | H78: =SUM(H79:H83) -> 5.5276835 | I78: =SUM(I79:I83) -> 5.7404834 | J78: =SUM(J79:J83) -> 5.7733505 | ... N78: =SUM(N79:N83) -> 5.9242565 | O78: =SUM(C78,D78,E78,F78,G78,H78,I78,J78,K78,L78,M78,N78) -> 67.620295 | P78: 54.872735 | Q78: 23.317179 | R78: 19.144891 | S78: 71.132472 | T78: =O78/P78-1 -> 0.23231138 | U78: =P78/Q78-1 -> 1.3533179
B79: du fixe | C79: 0.0038566497 | D79: 0.0038671977 | E79: 0.0038813185 | F79: 0.0038941211 | G79: 0.0039111266 | H79: 0.0039290636 | I79: 0.0039491577 | J79: 0.0039717708 | K79: 0.0039958653 | L79: 0.0040221362 | M79: 0.004048279 | N79: 0.0040755853 | O79: =SUM(C79,D79,E79,F79,G79,H79,I79,J79,K79,L79,M79,N79) -> 0.047402271 | P79: 0.047321493 | Q79: 0.048703425 | R79: 0.10438893 | S79: 0.051887932 | T79: =O79/P79-1 -> 0.0017070131 | U79: =P79/Q79-1 -> -0.028374423
B80: de l'international | C80: 0.015749446 | D80: 0.015708209 | E80: 0.015784034 | F80: 0.015851889 | G80: 0.015901129 | H80: 0.015983658 | I80: 0.016064153 | J80: 0.016152965 | K80: 0.016255062 | L80: 0.016359463 | M80: 0.016467642 | N80: 0.016576725 | O80: =SUM(C80,D80,E80,F80,G80,H80,I80,J80,K80,L80,M80,N80) -> 0.19285437 | P80: 0.22232423 | Q80: 0.28384498 | R80: 0.46576624 | S80: 0.11913244 | T80: =O80/P80-1 -> -0.13255351 | U80: =P80/Q80-1 -> -0.21674067
B81: de MTN | C81: 1.1570018 | D81: 1.047892 | E81: 1.1644024 | F81: 1.130558 | G81: 1.1733449 | H81: 1.1407026 | I81: 1.1847543 | J81: 1.1915383 | K81: 1.1600968 | L81: 1.206648 | M81: 1.1753138 | N81: 1.2226829 | O81: =SUM(C81,D81,E81,F81,G81,H81,I81,J81,K81,L81,M81,N81) -> 13.954936 | P81: 15.756081 | Q81: 18.079363 | R81: 18.180008 | S81: 19.758896 | T81: =O81/P81-1 -> -0.11431426 | U81: =P81/Q81-1 -> -0.12850465
B82: de SBIN | C82: 4.4294677 | D82: 4.0117518 | E82: 4.4578005 | F82: 4.3282303 | G82: 4.492036 | H82: 4.3670681 | I82: 4.5357157 | J82: 4.5616875 | K82: 4.4413168 | L82: 4.6195336 | M82: 4.4995735 | N82: 4.6809213 | O82: =SUM(C82,D82,E82,F82,G82,H82,I82,J82,K82,L82,M82,N82) -> 53.425103 | P82: 38.847008 | Q82: 4.9052681 | R82: 0.39472811 | S82: 6.0061502 | U82: =P82/Q82-1 -> 6.9194466
B83: de BBCOM, LIBERCOM | C83: 0 | D83: 0 | E83: 0 | F83: 0 | G83: 0 | H83: 0 | I83: 0 | J83: 0 | K83: 0 | L83: 0 | M83: 0 | N83: 0 | O83: =SUM(C83,D83,E83,F83,G83,H83,I83,J83,K83,L83,M83,N83) -> 0 | P83: 0 | Q83: 0 | R83: 0 | S83: 0
O84: 0 | P84: 0 | Q84: 0 | T84: =+IFERROR(O84/R84-1,"")

Sheet Indicateurs Mobile
A2: Indicateurs Mobile
C4: JANVIER | D4: FEVRIER | E4: MARS | F4: AVRIL | G4: MAI | H4: JUIN | I4: JUILLET | J4: AOÛT | K4: SEPTEMBRE | L4: OCTOBRE | M4: NOVEMBRE | N4: DECEMBRE | O4: ANNUEL | T4: VARIATIONS
B5: (En Millions ML) | C5: 2025 Budget | D5: 2025 Budget | E5: 2025 Budget | F5: 2025 Budget | G5: 2025 Budget | H5: 2025 Budget | I5: 2025 Budget | J5: 2025 Budget | K5: 2025 Budget | L5: 2025 Budget | M5: 2025 Budget | N5: 2025 Budget | O5: 2025 Budget | P5: 2024 Actu3 | Q5: 2023 Réel | R5: 2022 Réel | S5: Budget 2024 | T5: Var Budget vs Actu 3. % | U5: Var Actu 3 vs Réel 2023. % | V5: Var Budget vs Budget 2024. %
A7: ARPU Global | C7: =+(('CA Mobile'!C13+'CA Mobile'!C140)/('Parc Mobile'!C18+'Parc Mobile'!C27))*1000000 -> 1483.9401 | D7: =+(('CA Mobile'!D13+'CA Mobile'!D140)/('Parc Mobile'!D18+'Parc Mobile'!D27))*1000000 -> 1361.8497 | E7: =+(('CA Mobile'!E13+'CA Mobile'!E140)/('Parc Mobile'!E18+'Parc Mobile'!E27))*1000000 -> 1465.7643 | F7: =+(('CA Mobile'!F13+'CA Mobile'!F140)/('Parc Mobile'!F18+'Parc Mobile'!F27))*1000000 -> 1444.1524 | G7: =+(('CA Mobile'!G13+'CA Mobile'!G140)/('Parc Mobile'!G18+'Parc Mobile'!G27))*1000000 -> 1504.6534 | H7: =+(('CA Mobile'!H13+'CA Mobile'!H140)/('Parc Mobile'!H18+'Parc Mobile'!H27))*1000000 -> 1450.3882 | I7: =+(('CA Mobile'!I13+'CA Mobile'!I140)/('Parc Mobile'!I18+'Parc Mobile'!I27))*1000000 -> 1466.325 | J7: =+(('CA Mobile'!J13+'CA Mobile'!J140)/('Parc Mobile'!J18+'Parc Mobile'!J27))*1000000 -> 1460.235 | ... N7: =+(('CA Mobile'!N13+'CA Mobile'!N140)/('Parc Mobile'!N18+'Parc Mobile'!N27))*1000000 -> 1523.5527 | O7: =+(('CA Mobile'!O13+'CA Mobile'!O140)/('Parc Mobile'!O18+'Parc Mobile'!O27))*1000000/12 -> 1441.4094 | P7: 1465.902 | Q7: 1527.1441 | R7: 1537.7618 | S7: 1606.0499 | T7: =O7/P7-1 -> -0.016708229 | U7: =P7/Q7-1 -> -0.040102366 | V7: =O7/S7-1 -> -0.10251272 | W7: 1462.6796 | X7: =P7-W7 -> 3.2224633
B8: ARPU Sortant | C8: =+('CA Mobile'!C13/('Parc Mobile'!C18+'Parc Mobile'!C27))*1000000 -> 1448.4312 | D8: =+('CA Mobile'!D13/('Parc Mobile'!D18+'Parc Mobile'!D27))*1000000 -> 1329.318 | E8: =+('CA Mobile'!E13/('Parc Mobile'!E18+'Parc Mobile'!E27))*1000000 -> 1433.0977 | F8: =+('CA Mobile'!F13/('Parc Mobile'!F18+'Parc Mobile'!F27))*1000000 -> 1412.1513 | G8: =+('CA Mobile'!G13/('Parc Mobile'!G18+'Parc Mobile'!G27))*1000000 -> 1474.9695 | H8: =+('CA Mobile'!H13/('Parc Mobile'!H18+'Parc Mobile'!H27))*1000000 -> 1418.9377 | I8: =+('CA Mobile'!I13/('Parc Mobile'!I18+'Parc Mobile'!I27))*1000000 -> 1434.6533 | J8: =+('CA Mobile'!J13/('Parc Mobile'!J18+'Parc Mobile'!J27))*1000000 -> 1430.6059 | ... N8: =+('CA Mobile'!N13/('Parc Mobile'!N18+'Parc Mobile'!N27))*1000000 -> 1491.5228 | O8: =+('CA Mobile'!O13/('Parc Mobile'!O18+'Parc Mobile'!O27))*1000000/12 -> 1410.3782 | P8: 1428.9726 | Q8: 1483.2195 | R8: 1482.4183 | S8: 1567.3696 | T8: =O8/P8-1 -> -0.013012383 | U8: =P8/Q8-1 -> -0.036573745 | V8: =O8/S8-1 -> -0.10016232 | W8: 1425.1911 | X8: =P8-W8 -> 3.7814594
B9: ARPU Entrant | C9: =('CA Mobile'!C140/('Parc Mobile'!C18+'Parc Mobile'!C27))*1000000 -> 35.508863 | D9: =('CA Mobile'!D140/('Parc Mobile'!D18+'Parc Mobile'!D27))*1000000 -> 32.531686 | E9: =('CA Mobile'!E140/('Parc Mobile'!E18+'Parc Mobile'!E27))*1000000 -> 32.666528 | F9: =('CA Mobile'!F140/('Parc Mobile'!F18+'Parc Mobile'!F27))*1000000 -> 32.00109 | G9: =('CA Mobile'!G140/('Parc Mobile'!G18+'Parc Mobile'!G27))*1000000 -> 29.683863 | H9: =('CA Mobile'!H140/('Parc Mobile'!H18+'Parc Mobile'!H27))*1000000 -> 31.450486 | I9: =('CA Mobile'!I140/('Parc Mobile'!I18+'Parc Mobile'!I27))*1000000 -> 31.671646 | J9: =('CA Mobile'!J140/('Parc Mobile'!J18+'Parc Mobile'!J27))*1000000 -> 29.629054 | K9: =('CA Mobile'!K140/('Parc Mobile'!K18+'Parc Mobile'!K27))*1000000 -> 29.31758 | L9: =+('CA Mobile'!L140/('Parc Mobile'!L18+'Parc Mobile'!L27))*1000000 -> 29.315709 | M9: =+('CA Mobile'!M140/('Parc Mobile'!M18+'Parc Mobile'!M27))*1000000 -> 29.418661 | N9: =+('CA Mobile'!N140/('Parc Mobile'!N18+'Parc Mobile'!N27))*1000000 -> 32.029834 | O9: =+('CA Mobile'!O140/('Parc Mobile'!O18+'Parc Mobile'!O27))*1000000/12 -> 31.031147 | P9: 36.929436 | Q9: 43.924636 | R9: 55.343447 | S9: 38.680317 | T9: =O9/P9-1 -> -0.15971782 | U9: =P9/Q9-1 -> -0.1592546 | V9: =O9/S9-1 -> -0.19775355 | W9: 37.488432 | X9: =P9-W9 -> -0.5589961
W10: 0 | X10: =P10-W10 -> 0
A11: ARPU Prépayé | C11: =+C12+C13 -> 1327.4837 | D11: =+D12+D13 -> 1204.9151 | E11: =+E12+E13 -> 1302.3824 | F11: =+F12+F13 -> 1275.0462 | G11: =+G12+G13 -> 1334.7132 | H11: =+H12+H13 -> 1278.9737 | I11: =+I12+I13 -> 1285.177 | J11: =+J12+J13 -> 1280.8563 | ... O11: =+O12+O13 -> 1270.4827 | P11: 1296.5352 | Q11: 1384.1111 | R11: 1397.9297 | S11: 1439.5906 | T11: =O11/P11-1 -> -0.020093971 | U11: =P11/Q11-1 -> -0.063272309 | V11: =O11/S11-1 -> -0.11746948 | W11: 1295.2095 | X11: =P11-W11 -> 1.3257313
B12: ARPU Sortant | C12: =(('CA Mobile'!C25+'CA Mobile'!C33+'CA Mobile'!C44+'CA Mobile'!C16+'CA Mobile'!C35)/('Parc Mobile'!C18))*1000000 -> 1292.1045 | D12: =(('CA Mobile'!D25+'CA Mobile'!D33+'CA Mobile'!D44+'CA Mobile'!D16+'CA Mobile'!D35)/('Parc Mobile'!D18))*1000000 -> 1172.5017 | E12: =(('CA Mobile'!E25+'CA Mobile'!E33+'CA Mobile'!E44+'CA Mobile'!E16+'CA Mobile'!E35)/('Parc Mobile'!E18))*1000000 -> 1269.8349 | F12: =(('CA Mobile'!F25+'CA Mobile'!F33+'CA Mobile'!F44+'CA Mobile'!F16+'CA Mobile'!F35)/('Parc Mobile'!F18))*1000000 -> 1243.1614 | G12: =(('CA Mobile'!G25+'CA Mobile'!G33+'CA Mobile'!G44+'CA Mobile'!G16+'CA Mobile'!G35)/('Parc Mobile'!G18))*1000000 -> 1305.1366 | H12: =(('CA Mobile'!H25+'CA Mobile'!H33+'CA Mobile'!H44+'CA Mobile'!H16+'CA Mobile'!H35)/('Parc Mobile'!H18))*1000000 -> 1247.6363 | I12: =(('CA Mobile'!I25+'CA Mobile'!I33+'CA Mobile'!I44+'CA Mobile'!I16+'CA Mobile'!I35)/('Parc Mobile'!I18))*1000000 -> 1253.619 | J12: =(('CA Mobile'!J25+'CA Mobile'!J33+'CA Mobile'!J44+'CA Mobile'!J16+'CA Mobile'!J35)/('Parc Mobile'!J18))*1000000 -> 1251.3329 | ... N12: =(('CA Mobile'!N25+'CA Mobile'!N33+'CA Mobile'!N44+'CA Mobile'!N16+'CA Mobile'!N35)/('Parc Mobile'!N18))*1000000 -> 1304.8637 | O12: =(('CA Mobile'!O25+'CA Mobile'!O33+'CA Mobile'!O44+'CA Mobile'!O16+'CA Mobile'!O35)/('Parc Mobile'!O18))*1000000/12 -> 1239.5643 | P12: 1259.7304 | Q12: 1340.4697 | R12: 1342.9742 | S12: 1400.9925 | T12: =O12/P12-1 -> -0.016008232 | U12: =P12/Q12-1 -> -0.060232093 | V12: =O12/S12-1 -> -0.11522418 | W12: 1257.8517 | X12: =P12-W12 -> 1.878637
B13: ARPU Entrant | C13: =+(('CA Mobile'!C142+'CA Mobile'!C147+'CA Mobile'!C152+'CA Mobile'!C157)/('Parc Mobile'!C18))*1000000 -> 35.379236 | D13: =+(('CA Mobile'!D142+'CA Mobile'!D147+'CA Mobile'!D152+'CA Mobile'!D157)/('Parc Mobile'!D18))*1000000 -> 32.413458 | E13: =+(('CA Mobile'!E142+'CA Mobile'!E147+'CA Mobile'!E152+'CA Mobile'!E157)/('Parc Mobile'!E18))*1000000 -> 32.547515 | F13: =+(('CA Mobile'!F142+'CA Mobile'!F147+'CA Mobile'!F152+'CA Mobile'!F157)/('Parc Mobile'!F18))*1000000 -> 31.884797 | G13: =+(('CA Mobile'!G142+'CA Mobile'!G147+'CA Mobile'!G152+'CA Mobile'!G157)/('Parc Mobile'!G18))*1000000 -> 29.576588 | H13: =+(('CA Mobile'!H142+'CA Mobile'!H147+'CA Mobile'!H152+'CA Mobile'!H157)/('Parc Mobile'!H18))*1000000 -> 31.337344 | I13: =+(('CA Mobile'!I142+'CA Mobile'!I147+'CA Mobile'!I152+'CA Mobile'!I157)/('Parc Mobile'!I18))*1000000 -> 31.557948 | J13: =+(('CA Mobile'!J142+'CA Mobile'!J147+'CA Mobile'!J152+'CA Mobile'!J157)/('Parc Mobile'!J18))*1000000 -> 29.523383 | ... N13: =+(('CA Mobile'!N142+'CA Mobile'!N147+'CA Mobile'!N152+'CA Mobile'!N157)/('Parc Mobile'!N18))*1000000 -> 31.914996 | O13: =+(('CA Mobile'!O142+'CA Mobile'!O147+'CA Mobile'!O152+'CA Mobile'!O157)/('Parc Mobile'!O18))*1000000/12 -> 30.91833 | P13: 36.804814 | Q13: 43.641425 | R13: 54.955527 | S13: 38.598074 | T13: =O13/P13-1 -> -0.15993787 | U13: =P13/Q13-1 -> -0.15665416 | V13: =O13/S13-1 -> -0.19896701 | W13: 37.35772 | X13: =P13-W13 -> -0.55290566
X14: =P14-W14 -> 0
A15: ARPU Postpayé | C15: =+C16+C17 -> 4628.9378 | D15: =+D16+D17 -> 4441.5932 | E15: =+E16+E17 -> 4660.786 | F15: =+F16+F17 -> 4651.6904 | G15: =+G16+G17 -> 4554.8506 | H15: =+H16+H17 -> 4636.1469 | I15: =+I16+I17 -> 4662.7933 | J15: =+J16+J17 -> 4675.4562 | ... O15: =+O16+O17 -> 4599.4004 | P15: 4748.3329 | Q15: 6052.8444 | R15: 6035.1803 | S15: 5535.8352 | T15: =O15/P15-1 -> -0.031365232 | U15: =P15/Q15-1 -> -0.2155204 | V15: =O15/S15-1 -> -0.16915873 | W15: 4712.3817 | X15: =P15-W15 -> 35.951205
B16: ARPU Sortant | C16: =+(('CA Mobile'!C47+'CA Mobile'!C133)/('Parc Mobile'!C27))*1000000 -> 4585.1148 | D16: =+(('CA Mobile'!D47+'CA Mobile'!D133)/('Parc Mobile'!D27))*1000000 -> 4401.4866 | E16: =+(('CA Mobile'!E47+'CA Mobile'!E133)/('Parc Mobile'!E27))*1000000 -> 4620.4898 | F16: =+(('CA Mobile'!F47+'CA Mobile'!F133)/('Parc Mobile'!F27))*1000000 -> 4612.2384 | G16: =+(('CA Mobile'!G47+'CA Mobile'!G133)/('Parc Mobile'!G27))*1000000 -> 4518.3028 | H16: =+(('CA Mobile'!H47+'CA Mobile'!H133)/('Parc Mobile'!H27))*1000000 -> 4597.4648 | I16: =+(('CA Mobile'!I47+'CA Mobile'!I133)/('Parc Mobile'!I27))*1000000 -> 4623.8581 | J16: =+(('CA Mobile'!J47+'CA Mobile'!J133)/('Parc Mobile'!J27))*1000000 -> 4639.0866 | ... N16: =+(('CA Mobile'!N47+'CA Mobile'!N133)/('Parc Mobile'!N27))*1000000 -> 4621.4627 | O16: =+(('CA Mobile'!O47+'CA Mobile'!O133)/('Parc Mobile'!O27))*1000000/12 -> 4561.1404 | P16: 4703.4126 | Q16: 5287.077 | R16: 5932.667 | S16: 5491.8103 | T16: =O16/P16-1 -> -0.030248715 | U16: =P16/Q16-1 -> -0.11039454 | V16: =O16/S16-1 -> -0.16946505 | W16: 4666.4533 | X16: =P16-W16 -> 36.959329
B17: ARPU Entrant | C17: =+(('CA Mobile'!C140-('CA Mobile'!C142+'CA Mobile'!C147+'CA Mobile'!C152+'CA Mobile'!C157))/('Parc Mobile'!C27))*1000000 -> 43.822953 | D17: =+(('CA Mobile'!D140-('CA Mobile'!D142+'CA Mobile'!D147+'CA Mobile'!D152+'CA Mobile'!D157))/('Parc Mobile'!D27))*1000000 -> 40.106599 | E17: =+(('CA Mobile'!E140-('CA Mobile'!E142+'CA Mobile'!E147+'CA Mobile'!E152+'CA Mobile'!E157))/('Parc Mobile'!E27))*1000000 -> 40.296258 | F17: =+(('CA Mobile'!F140-('CA Mobile'!F142+'CA Mobile'!F147+'CA Mobile'!F152+'CA Mobile'!F157))/('Parc Mobile'!F27))*1000000 -> 39.451936 | G17: =+(('CA Mobile'!G140-('CA Mobile'!G142+'CA Mobile'!G147+'CA Mobile'!G152+'CA Mobile'!G157))/('Parc Mobile'!G27))*1000000 -> 36.547874 | H17: =+(('CA Mobile'!H140-('CA Mobile'!H142+'CA Mobile'!H147+'CA Mobile'!H152+'CA Mobile'!H157))/('Parc Mobile'!H27))*1000000 -> 38.682151 | I17: =+(('CA Mobile'!I140-('CA Mobile'!I142+'CA Mobile'!I147+'CA Mobile'!I152+'CA Mobile'!I157))/('Parc Mobile'!I27))*1000000 -> 38.935244 | J17: =+(('CA Mobile'!J140-('CA Mobile'!J142+'CA Mobile'!J147+'CA Mobile'!J152+'CA Mobile'!J157))/('Parc Mobile'!J27))*1000000 -> 36.369577 | ... N17: =+(('CA Mobile'!N140-('CA Mobile'!N142+'CA Mobile'!N147+'CA Mobile'!N152+'CA Mobile'!N157))/('Parc Mobile'!N27))*1000000 -> 39.364146 | O17: =+(('CA Mobile'!O140-('CA Mobile'!O142+'CA Mobile'!O147+'CA Mobile'!O152+'CA Mobile'!O157))/('Parc Mobile'!O27))*1000000/12 -> 38.259969 | P17: 44.920345 | Q17: 765.76735 | R17: 102.5133 | S17: 44.024884 | T17: =O17/P17-1 -> -0.1482708 | U17: =P17/Q17-1 -> -0.94133944 | V17: =O17/S17-1 -> -0.13094674 | W17: 45.928469 | X17: =P17-W17 -> -1.0081244
X18: =P18-W18 -> 0
A19: Usage / client / mois | C19: =SUM('Trafic mobile'!C6,'Trafic mobile'!C54)/(SUM('Parc Mobile'!C18,'Parc Mobile'!C27)/1000000) -> 43.67129 | D19: =SUM('Trafic mobile'!D6,'Trafic mobile'!D54)/(SUM('Parc Mobile'!D18,'Parc Mobile'!D27)/1000000) -> 39.617336 | E19: =SUM('Trafic mobile'!E6,'Trafic mobile'!E54)/(SUM('Parc Mobile'!E18,'Parc Mobile'!E27)/1000000) -> 42.386382 | F19: =SUM('Trafic mobile'!F6,'Trafic mobile'!F54)/(SUM('Parc Mobile'!F18,'Parc Mobile'!F27)/1000000) -> 41.192204 | G19: =SUM('Trafic mobile'!G6,'Trafic mobile'!G54)/(SUM('Parc Mobile'!G18,'Parc Mobile'!G27)/1000000) -> 42.068657 | H19: =SUM('Trafic mobile'!H6,'Trafic mobile'!H54)/(SUM('Parc Mobile'!H18,'Parc Mobile'!H27)/1000000) -> 40.353476 | I19: =SUM('Trafic mobile'!I6,'Trafic mobile'!I54)/(SUM('Parc Mobile'!I18,'Parc Mobile'!I27)/1000000) -> 39.985902 | J19: =SUM('Trafic mobile'!J6,'Trafic mobile'!J54)/(SUM('Parc Mobile'!J18,'Parc Mobile'!J27)/1000000) -> 38.902424 | ... N19: =SUM('Trafic mobile'!N6,'Trafic mobile'!N54)/(SUM('Parc Mobile'!N18,'Parc Mobile'!N27)/1000000) -> 40.184106 | O19: =SUM('Trafic mobile'!O6,'Trafic mobile'!O54)/(SUM('Parc Mobile'!O18,'Parc Mobile'!O27)/1000000)/12 -> 39.850487 | P19: 40.320392 | Q19: 42.298645 | R19: 45.817453 | S19: 40.920526 | T19: =O19/P19-1 -> -0.011654259 | U19: =P19/Q19-1 -> -0.046768713 | V19: =O19/S19-1 -> -0.026149202 | W19: 40.90501 | X19: =P19-W19 -> -0.58461857
B20: Usage Sortant | C20: =SUM('Trafic mobile'!C6)/(SUM('Parc Mobile'!C18,'Parc Mobile'!C27)/1000000) -> 27.523695 | D20: =SUM('Trafic mobile'!D6)/(SUM('Parc Mobile'!D18,'Parc Mobile'!D27)/1000000) -> 25.054753 | E20: =SUM('Trafic mobile'!E6)/(SUM('Parc Mobile'!E18,'Parc Mobile'!E27)/1000000) -> 26.264661 | F20: =SUM('Trafic mobile'!F6)/(SUM('Parc Mobile'!F18,'Parc Mobile'!F27)/1000000) -> 25.595879 | G20: =SUM('Trafic mobile'!G6)/(SUM('Parc Mobile'!G18,'Parc Mobile'!G27)/1000000) -> 25.973368 | H20: =SUM('Trafic mobile'!H6)/(SUM('Parc Mobile'!H18,'Parc Mobile'!H27)/1000000) -> 24.760598 | I20: =SUM('Trafic mobile'!I6)/(SUM('Parc Mobile'!I18,'Parc Mobile'!I27)/1000000) -> 23.870865 | J20: =SUM('Trafic mobile'!J6)/(SUM('Parc Mobile'!J18,'Parc Mobile'!J27)/1000000) -> 22.805446 | ... N20: =SUM('Trafic mobile'!N6)/(SUM('Parc Mobile'!N18,'Parc Mobile'!N27)/1000000) -> 24.065328 | O20: =(SUM('Trafic mobile'!O6)/(SUM('Parc Mobile'!O18,'Parc Mobile'!O27)/1000000))/12 -> 24.153086 | P20: 25.085168 | Q20: 28.33417 | R20: 31.611787 | S20: 25.616244 | T20: =O20/P20-1 -> -0.037156685 | U20: =P20/Q20-1 -> -0.11466728 | V20: =O20/S20-1 -> -0.05711837 | W20: 25.193707 | X20: =P20-W20 -> -0.10853873
B21: Prépayé | C21: =SUM('Trafic mobile'!C8)/('Parc Mobile'!C18/1000000) -> 25.865849 | D21: =SUM('Trafic mobile'!D8)/('Parc Mobile'!D18/1000000) -> 23.478021 | E21: =SUM('Trafic mobile'!E8)/('Parc Mobile'!E18/1000000) -> 24.475275 | F21: =SUM('Trafic mobile'!F8)/('Parc Mobile'!F18/1000000) -> 24.004559 | G21: =SUM('Trafic mobile'!G8)/('Parc Mobile'!G18/1000000) -> 24.759568 | H21: =SUM('Trafic mobile'!H8)/('Parc Mobile'!H18/1000000) -> 23.145821 | I21: =SUM('Trafic mobile'!I8)/('Parc Mobile'!I18/1000000) -> 22.393446 | J21: =SUM('Trafic mobile'!J8)/('Parc Mobile'!J18/1000000) -> 21.448488 | ... N21: =SUM('Trafic mobile'!N8)/('Parc Mobile'!N18/1000000) -> 23.087682 | O21: =(SUM('Trafic mobile'!O8)/('Parc Mobile'!O18/1000000))/12 -> 22.709174 | P21: 23.472889 | Q21: 26.640832 | R21: 29.743153 | S21: 24.087424 | T21: =O21/P21-1 -> -0.032536044 | U21: =P21/Q21-1 -> -0.11891306 | V21: =O21/S21-1 -> -0.057218623 | W21: 23.57214 | X21: =P21-W21 -> -0.099250265
B22: Postpayé | C22: =SUM('Trafic mobile'!C17)/('Parc Mobile'!C27/1000000) -> 133.85574 | D22: =SUM('Trafic mobile'!D17)/('Parc Mobile'!D27/1000000) -> 126.07652 | E22: =SUM('Trafic mobile'!E17)/('Parc Mobile'!E27/1000000) -> 140.97896 | F22: =SUM('Trafic mobile'!F17)/('Parc Mobile'!F27/1000000) -> 127.55101 | G22: =SUM('Trafic mobile'!G17)/('Parc Mobile'!G27/1000000) -> 103.63876 | H22: =SUM('Trafic mobile'!H17)/('Parc Mobile'!H27/1000000) -> 127.97203 | I22: =SUM('Trafic mobile'!I17)/('Parc Mobile'!I27/1000000) -> 118.25622 | J22: =SUM('Trafic mobile'!J17)/('Parc Mobile'!J27/1000000) -> 109.36306 | ... N22: =SUM('Trafic mobile'!N17)/('Parc Mobile'!N27/1000000) -> 86.504048 | O22: =(SUM('Trafic mobile'!O17)/('Parc Mobile'!O27/1000000))/12 -> 116.67315 | P22: 127.36437 | Q22: 147.25357 | R22: 176.53005 | S22: 124.96655 | T22: =O22/P22-1 -> -0.08394205 | U22: =P22/Q22-1 -> -0.13506766 | V22: =O22/S22-1 -> -0.066364994 | W22: 129.8979 | X22: =P22-W22 -> -2.5335321
B23: Usage Entrant | C23: =+'Trafic mobile'!C54/(SUM('Parc Mobile'!C18,'Parc Mobile'!C27)/1000000) -> 16.147595 | D23: =+'Trafic mobile'!D54/(SUM('Parc Mobile'!D18,'Parc Mobile'!D27)/1000000) -> 14.562583 | E23: =+'Trafic mobile'!E54/(SUM('Parc Mobile'!E18,'Parc Mobile'!E27)/1000000) -> 16.12172 | F23: =+'Trafic mobile'!F54/(SUM('Parc Mobile'!F18,'Parc Mobile'!F27)/1000000) -> 15.596324 | G23: =+'Trafic mobile'!G54/(SUM('Parc Mobile'!G18,'Parc Mobile'!G27)/1000000) -> 16.095289 | H23: =+'Trafic mobile'!H54/(SUM('Parc Mobile'!H18,'Parc Mobile'!H27)/1000000) -> 15.592878 | I23: =+'Trafic mobile'!I54/(SUM('Parc Mobile'!I18,'Parc Mobile'!I27)/1000000) -> 16.115038 | J23: =+'Trafic mobile'!J54/(SUM('Parc Mobile'!J18,'Parc Mobile'!J27)/1000000) -> 16.096978 | ... N23: =+'Trafic mobile'!N54/(SUM('Parc Mobile'!N18,'Parc Mobile'!N27)/1000000) -> 16.118778 | O23: =(+'Trafic mobile'!O54/(SUM('Parc Mobile'!O18,'Parc Mobile'!O27)/1000000))/12 -> 15.697401 | P23: 15.235224 | Q23: 13.964475 | R23: 14.205666 | S23: 15.304282 | T23: =O23/P23-1 -> 0.03033611 | U23: =P23/Q23-1 -> 0.09099869 | V23: =O23/S23-1 -> 0.025686864 | W23: 15.711303 | X23: =P23-W23 -> -0.47607985
B24: Prépayé | C24: =+'Trafic mobile'!C56/('Parc Mobile'!C18/1000000) -> 15.385643 | D24: =+'Trafic mobile'!D56/('Parc Mobile'!D18/1000000) -> 13.873125 | E24: =+'Trafic mobile'!E56/('Parc Mobile'!E18/1000000) -> 15.359237 | F24: =+'Trafic mobile'!F56/('Parc Mobile'!F18/1000000) -> 14.857917 | G24: =+'Trafic mobile'!G56/('Parc Mobile'!G18/1000000) -> 15.331181 | H24: =+'Trafic mobile'!H56/('Parc Mobile'!H18/1000000) -> 14.852939 | I24: =+'Trafic mobile'!I56/('Parc Mobile'!I18/1000000) -> 15.350353 | J24: =+'Trafic mobile'!J56/('Parc Mobile'!J18/1000000) -> 15.33103 | ... N24: =+'Trafic mobile'!N56/('Parc Mobile'!N18/1000000) -> 15.354933 | O24: =(+'Trafic mobile'!O56/('Parc Mobile'!O18/1000000))/12 -> 14.952174 | P24: 14.60123 | Q24: 13.731367 | R24: 14.059439 | S24: 14.468085 | T24: =O24/P24-1 -> 0.024035258 | U24: =P24/Q24-1 -> 0.063348565 | V24: =O24/S24-1 -> 0.03345908 | W24: 15.089016 | X24: =P24-W24 -> -0.48778655
B25: Postpayé | C25: =+'Trafic mobile'!C63/('Parc Mobile'!C27/1000000) -> 65.018219 | D25: =+'Trafic mobile'!D63/('Parc Mobile'!D27/1000000) -> 58.736376 | E25: =+'Trafic mobile'!E63/('Parc Mobile'!E27/1000000) -> 65.003157 | F25: =+'Trafic mobile'!F63/('Parc Mobile'!F27/1000000) -> 62.905737 | G25: =+'Trafic mobile'!G63/('Parc Mobile'!G27/1000000) -> 64.987015 | H25: =+'Trafic mobile'!H63/('Parc Mobile'!H27/1000000) -> 62.887415 | I25: =+'Trafic mobile'!I63/('Parc Mobile'!I27/1000000) -> 64.967098 | J25: =+'Trafic mobile'!J63/('Parc Mobile'!J27/1000000) -> 64.955244 | ... N25: =+'Trafic mobile'!N63/('Parc Mobile'!N27/1000000) -> 64.90287 | O25: =(+'Trafic mobile'!O63/('Parc Mobile'!O27/1000000))/12 -> 63.448543 | P25: 55.887823 | Q25: 30.33509 | R25: 25.545976 | S25: 69.644467 | T25: =O25/P25-1 -> 0.13528385 | U25: =P25/Q25-1 -> 0.84234903 | V25: =O25/S25-1 -> -0.088965061 | W25: 55.892234 | X25: =P25-W25 -> -0.0044113188
X26: =P26-W26 -> 0
A27: Prix mn | C27: =((SUM('CA Mobile'!$J$16,'CA Mobile'!C25)+SUM('CA Mobile'!C62,'CA Mobile'!C87,'CA Mobile'!C112))+(SUM('CA Mobile'!C142,'CA Mobile'!C147,'CA Mobile'!C152,'CA Mobile'!C157)+SUM('CA Mobile'!C143:C145,'CA Mobile'!C148:C150,'CA Mobile'!C153:C155,'CA Mobile'!C158:C160)))/(('Trafic mobile'!C8+'Trafic mobile'!C17)+('Trafic mobile'!C56+SUM('Trafic mobile'!C65:C69,'Trafic mobile'!C72:C76,'Trafic mobile'!C$79:C83))) -> 14.987034 | D27: =((SUM('CA Mobile'!$J$16,'CA Mobile'!D25)+SUM('CA Mobile'!D62,'CA Mobile'!D87,'CA Mobile'!D112))+(SUM('CA Mobile'!D142,'CA Mobile'!D147,'CA Mobile'!D152,'CA Mobile'!D157)+SUM('CA Mobile'!D143:D145,'CA Mobile'!D148:D150,'CA Mobile'!D153:D155,'CA Mobile'!D158:D160)))/(('Trafic mobile'!D8+'Trafic mobile'!D17)+('Trafic mobile'!D56+SUM('Trafic mobile'!D65:D69,'Trafic mobile'!D72:D76,'Trafic mobile'!D$79:D83))) -> 14.936441 | E27: =((SUM('CA Mobile'!$J$16,'CA Mobile'!E25)+SUM('CA Mobile'!E62,'CA Mobile'!E87,'CA Mobile'!E112))+(SUM('CA Mobile'!E142,'CA Mobile'!E147,'CA Mobile'!E152,'CA Mobile'!E157)+SUM('CA Mobile'!E143:E145,'CA Mobile'!E148:E150,'CA Mobile'!E153:E155,'CA Mobile'!E158:E160)))/(('Trafic mobile'!E8+'Trafic mobile'!E17)+('Trafic mobile'!E56+SUM('Trafic mobile'!E65:E69,'Trafic mobile'!E72:E76,'Trafic mobile'!E$79:E83))) -> 14.565419 | F27: =((SUM('CA Mobile'!$J$16,'CA Mobile'!F25)+SUM('CA Mobile'!F62,'CA Mobile'!F87,'CA Mobile'!F112))+(SUM('CA Mobile'!F142,'CA Mobile'!F147,'CA Mobile'!F152,'CA Mobile'!F157)+SUM('CA Mobile'!F143:F145,'CA Mobile'!F148:F150,'CA Mobile'!F153:F155,'CA Mobile'!F158:F160)))/(('Trafic mobile'!F8+'Trafic mobile'!F17)+('Trafic mobile'!F56+SUM('Trafic mobile'!F65:F69,'Trafic mobile'!F72:F76,'Trafic mobile'!F$79:F83))) -> 14.633266 | G27: =((SUM('CA Mobile'!$J$16,'CA Mobile'!G25)+SUM('CA Mobile'!G62,'CA Mobile'!G87,'CA Mobile'!G112))+(SUM('CA Mobile'!G142,'CA Mobile'!G147,'CA Mobile'!G152,'CA Mobile'!G157)+SUM('CA Mobile'!G143:G145,'CA Mobile'!G148:G150,'CA Mobile'!G153:G155,'CA Mobile'!G158:G160)))/(('Trafic mobile'!G8+'Trafic mobile'!G17)+('Trafic mobile'!G56+SUM('Trafic mobile'!G65:G69,'Trafic mobile'!G72:G76,'Trafic mobile'!G$79:G83))) -> 14.621842 | H27: =((SUM('CA Mobile'!$J$16,'CA Mobile'!H25)+SUM('CA Mobile'!H62,'CA Mobile'!H87,'CA Mobile'!H112))+(SUM('CA Mobile'!H142,'CA Mobile'!H147,'CA Mobile'!H152,'CA Mobile'!H157)+SUM('CA Mobile'!H143:H145,'CA Mobile'!H148:H150,'CA Mobile'!H153:H155,'CA Mobile'!H158:H160)))/(('Trafic mobile'!H8+'Trafic mobile'!H17)+('Trafic mobile'!H56+SUM('Trafic mobile'!H65:H69,'Trafic mobile'!H72:H76,'Trafic mobile'!H$79:H83))) -> 14.397386 | I27: =((SUM('CA Mobile'!$J$16,'CA Mobile'!I25)+SUM('CA Mobile'!I62,'CA Mobile'!I87,'CA Mobile'!I112))+(SUM('CA Mobile'!I142,'CA Mobile'!I147,'CA Mobile'!I152,'CA Mobile'!I157)+SUM('CA Mobile'!I143:I145,'CA Mobile'!I148:I150,'CA Mobile'!I153:I155,'CA Mobile'!I158:I160)))/(('Trafic mobile'!I8+'Trafic mobile'!I17)+('Trafic mobile'!I56+SUM('Trafic mobile'!I65:I69,'Trafic mobile'!I72:I76,'Trafic mobile'!I$79:I83))) -> 14.060519 | J27: =((SUM('CA Mobile'!$J$16,'CA Mobile'!J25)+SUM('CA Mobile'!J62,'CA Mobile'!J87,'CA Mobile'!J112))+(SUM('CA Mobile'!J142,'CA Mobile'!J147,'CA Mobile'!J152,'CA Mobile'!J157)+SUM('CA Mobile'!J143:J145,'CA Mobile'!J148:J150,'CA Mobile'!J153:J155,'CA Mobile'!J158:J160)))/(('Trafic mobile'!J8+'Trafic mobile'!J17)+('Trafic mobile'!J56+SUM('Trafic mobile'!J65:J69,'Trafic mobile'!J72:J76,'Trafic mobile'!J$79:J83))) -> 13.846778 | K27: =((SUM('CA Mobile'!$K$16,'CA Mobile'!$K$25)+SUM('CA Mobile'!$K$62,'CA Mobile'!$K$87,'CA Mobile'!$K$112))+(SUM('CA Mobile'!$K$142,'CA Mobile'!$K$147,'CA Mobile'!$K$152,'CA Mobile'!$K$157)+SUM('CA Mobile'!$K$143:$K$145,'CA Mobile'!$K$148:$K$150,'CA Mobile'!$K$153:$K$155,'CA Mobile'!$K$158:$K$160)))/(('Trafic mobile'!$K$8+'Trafic mobile'!$K$17)+('Trafic mobile'!$K$56+SUM('Trafic mobile'!$K$65:$K$69,'Trafic mobile'!$K$72:$K$76,'Trafic mobile'!$K$79:$K$83))) -> 13.726332 | L27: =((SUM('CA Mobile'!$L$16,'CA Mobile'!$L$25)+SUM('CA Mobile'!$L$62,'CA Mobile'!$L$87,'CA Mobile'!$L$112))+(SUM('CA Mobile'!$L$142,'CA Mobile'!$L$147,'CA Mobile'!$L$152,'CA Mobile'!$L$157)+SUM('CA Mobile'!$L$143:$L$145,'CA Mobile'!$L$148:$L$150,'CA Mobile'!$L$153:$L$155,'CA Mobile'!$L$158:$L$160)))/(('Trafic mobile'!$L$8+'Trafic mobile'!$L$17)+('Trafic mobile'!$L$56+SUM('Trafic mobile'!$L$65:$L$69,'Trafic mobile'!$L$72:$L$76,'Trafic mobile'!$L$79:$L$83))) -> 13.739247 | M27: =((SUM('CA Mobile'!$M$16,'CA Mobile'!$M$25)+SUM('CA Mobile'!$M$62,'CA Mobile'!$M$87,'CA Mobile'!$M$112))+(SUM('CA Mobile'!$M$142,'CA Mobile'!$M$147,'CA Mobile'!$M$152,'CA Mobile'!$M$157)+SUM('CA Mobile'!$M$143:$M$145,'CA Mobile'!$M$148:$M$150,'CA Mobile'!$M$153:$M$155,'CA Mobile'!$M$158:$M$160)))/(('Trafic mobile'!$M$8+'Trafic mobile'!$M$17)+('Trafic mobile'!$M$56+SUM('Trafic mobile'!$M$65:$M$69,'Trafic mobile'!$M$72:$M$76,'Trafic mobile'!$M$79:$M$83))) -> 13.788558 | N27: =((SUM('CA Mobile'!$M$16,'CA Mobile'!$M$25)+SUM('CA Mobile'!$M$62,'CA Mobile'!$M$87,'CA Mobile'!$M$112))+(SUM('CA Mobile'!$M$142,'CA Mobile'!$M$147,'CA Mobile'!$M$152,'CA Mobile'!$M$157)+SUM('CA Mobile'!$M$143:$M$145,'CA Mobile'!$M$148:$M$150,'CA Mobile'!$M$153:$M$155,'CA Mobile'!$M$158:$M$160)))/(('Trafic mobile'!$M$8+'Trafic mobile'!$M$17)+('Trafic mobile'!$M$56+SUM('Trafic mobile'!$M$65:$M$69,'Trafic mobile'!$M$72:$M$76,'Trafic mobile'!$M$79:$M$83))) -> 13.788558 | O27: =((SUM('CA Mobile'!$M$16,'CA Mobile'!$M$25)+SUM('CA Mobile'!$M$62,'CA Mobile'!$M$87,'CA Mobile'!$M$112))+(SUM('CA Mobile'!$M$142,'CA Mobile'!$M$147,'CA Mobile'!$M$152,'CA Mobile'!$M$157)+SUM('CA Mobile'!$M$143:$M$145,'CA Mobile'!$M$148:$M$150,'CA Mobile'!$M$153:$M$155,'CA Mobile'!$M$158:$M$160)))/(('Trafic mobile'!$M$8+'Trafic mobile'!$M$17)+('Trafic mobile'!$M$56+SUM('Trafic mobile'!$M$65:$M$69,'Trafic mobile'!$M$72:$M$76,'Trafic mobile'!$M$79:$M$83))) -> 13.788558 | P27: 14.047765 | Q27: 17.283757 | R27: 18.5734 | S27: 16.126113 | T27: =O27/P27-1 -> -0.018451847 | U27: =P27/Q27-1 -> -0.18722734 | V27: =O27/S27-1 -> -0.14495462 | W27: 15.290755 | X27: =P27-W27 -> -1.2429901
B28: Prix mn Sortant | C28: =(SUM('CA Mobile'!C16,'CA Mobile'!C25)+SUM('CA Mobile'!C62,'CA Mobile'!C87,'CA Mobile'!C112))/('Trafic mobile'!C8+'Trafic mobile'!C17) -> 22.489505 | D28: =(SUM('CA Mobile'!D16,'CA Mobile'!D25)+SUM('CA Mobile'!D62,'CA Mobile'!D87,'CA Mobile'!D112))/('Trafic mobile'!D8+'Trafic mobile'!D17) -> 22.319529 | E28: =(SUM('CA Mobile'!E16,'CA Mobile'!E25)+SUM('CA Mobile'!E62,'CA Mobile'!E87,'CA Mobile'!E112))/('Trafic mobile'!E8+'Trafic mobile'!E17) -> 22.262191 | F28: =(SUM('CA Mobile'!F16,'CA Mobile'!F25)+SUM('CA Mobile'!F62,'CA Mobile'!F87,'CA Mobile'!F112))/('Trafic mobile'!F8+'Trafic mobile'!F17) -> 22.299502 | G28: =(SUM('CA Mobile'!G16,'CA Mobile'!G25)+SUM('CA Mobile'!G62,'CA Mobile'!G87,'CA Mobile'!G112))/('Trafic mobile'!G8+'Trafic mobile'!G17) -> 22.539911 | H28: =(SUM('CA Mobile'!H16,'CA Mobile'!H25)+SUM('CA Mobile'!H62,'CA Mobile'!H87,'CA Mobile'!H112))/('Trafic mobile'!H8+'Trafic mobile'!H17) -> 22.193894 | I28: =(SUM('CA Mobile'!I16,'CA Mobile'!I25)+SUM('CA Mobile'!I62,'CA Mobile'!I87,'CA Mobile'!I112))/('Trafic mobile'!I8+'Trafic mobile'!I17) -> 22.225877 | J28: =(SUM('CA Mobile'!J16,'CA Mobile'!J25)+SUM('CA Mobile'!J62,'CA Mobile'!J87,'CA Mobile'!J112))/('Trafic mobile'!J8+'Trafic mobile'!J17) -> 22.321167 | ... N28: =(SUM('CA Mobile'!N16,'CA Mobile'!N25)+SUM('CA Mobile'!N62,'CA Mobile'!N87,'CA Mobile'!N112))/('Trafic mobile'!N8+'Trafic mobile'!N17) -> 22.828837 | O28: =('CA Mobile'!O25-17.793953+SUM('CA Mobile'!O87,'CA Mobile'!O112,'CA Mobile'!O48))/('Trafic mobile'!O8+'Trafic mobile'!O17)+0.006684 -> 23.939548 | P28: 24.87707 | Q28: 24.251809 | R28: 25.169169 | S28: 23.842508 | T28: =O28/P28-1 -> -0.037686217 | U28: =P28/Q28-1 -> 0.025782055 | V28: =O28/S28-1 -> 0.0040700102 | W28: 23.338371 | X28: =P28-W28 -> 1.5386991
B29: Prépayé | C29: =SUM('CA Mobile'!C16,'CA Mobile'!C25)/'Trafic mobile'!C8 -> 24.029438 | D29: =SUM('CA Mobile'!D16,'CA Mobile'!D25)/'Trafic mobile'!D8 -> 23.910178 | E29: =SUM('CA Mobile'!E16,'CA Mobile'!E25)/'Trafic mobile'!E8 -> 23.964446 | F29: =SUM('CA Mobile'!F16,'CA Mobile'!F25)/'Trafic mobile'!F8 -> 23.870078 | G29: =SUM('CA Mobile'!G16,'CA Mobile'!G25)/'Trafic mobile'!G8 -> 23.823837 | H29: =SUM('CA Mobile'!H16,'CA Mobile'!H25)/'Trafic mobile'!H8 -> 23.821693 | I29: =SUM('CA Mobile'!I16,'CA Mobile'!I25)/'Trafic mobile'!I8 -> 23.781606 | J29: =SUM('CA Mobile'!J16,'CA Mobile'!J25)/'Trafic mobile'!J8 -> 23.827127 | ... N29: =SUM('CA Mobile'!N16,'CA Mobile'!N25)/'Trafic mobile'!N8 -> 23.93283 | O29: =SUM('CA Mobile'!O16,'CA Mobile'!O25-17.793953)/'Trafic mobile'!O8+0.001648 -> 23.862875 | P29: 25.012284 | Q29: 25.723114 | R29: 26.548959 | S29: 25.33339 | T29: =O29/P29-1 -> -0.045953769 | U29: =P29/Q29-1 -> -0.027633915 | V29: =O29/S29-1 -> -0.058046526 | W29: 24.999652 | X29: =P29-W29 -> 0.012632058
B30: Postpayé | C30: =SUM('CA Mobile'!C62,'CA Mobile'!C87,'CA Mobile'!C112)/'Trafic mobile'!C17 -> 3.4036562 | D30: =SUM('CA Mobile'!D62,'CA Mobile'!D87,'CA Mobile'!D112)/'Trafic mobile'!D17 -> 3.3411688 | E30: =SUM('CA Mobile'!E62,'CA Mobile'!E87,'CA Mobile'!E112)/'Trafic mobile'!E17 -> 3.3164577 | F30: =SUM('CA Mobile'!F62,'CA Mobile'!F87,'CA Mobile'!F112)/'Trafic mobile'!F17 -> 3.3621205 | G30: =SUM('CA Mobile'!G62,'CA Mobile'!G87,'CA Mobile'!G112)/'Trafic mobile'!G17 -> 2.9134675 | H30: =SUM('CA Mobile'!H62,'CA Mobile'!H87,'CA Mobile'!H112)/'Trafic mobile'!H17 -> 3.3758924 | I30: =SUM('CA Mobile'!I62,'CA Mobile'!I87,'CA Mobile'!I112)/'Trafic mobile'!I17 -> 3.4053431 | J30: =SUM('CA Mobile'!J62,'CA Mobile'!J87,'CA Mobile'!J112)/'Trafic mobile'!J17 -> 3.4812815 | ... O30: =SUM('CA Mobile'!O62,'CA Mobile'!O87,'CA Mobile'!O112)/'Trafic mobile'!O17 -> 3.4012888 | P30: 3.9497512 | Q30: 5.5581676 | R30: 7.139828 | S30: 5.1678564 | T30: =O30/P30-1 -> -0.13885998 | U30: =P30/Q30-1 -> -0.2893789 | V30: =O30/S30-1 -> -0.3418376 | W30: 3.8727151 | X30: =P30-W30 -> 0.077036048
B31: Prix mn Entrant | C31: =(SUM('CA Mobile'!C142,'CA Mobile'!C147,'CA Mobile'!C152,'CA Mobile'!C157)+SUM('CA Mobile'!C143:C145,'CA Mobile'!C148:C150,'CA Mobile'!C153:C155,'CA Mobile'!C158:C160))/('Trafic mobile'!C56+'Trafic mobile'!C63) -> 2.1990186 | D31: =(SUM('CA Mobile'!D142,'CA Mobile'!D147,'CA Mobile'!D152,'CA Mobile'!D157)+SUM('CA Mobile'!D143:D145,'CA Mobile'!D148:D150,'CA Mobile'!D153:D155,'CA Mobile'!D158:D160))/('Trafic mobile'!D56+'Trafic mobile'!D63) -> 2.2339228 | E31: =(SUM('CA Mobile'!E142,'CA Mobile'!E147,'CA Mobile'!E152,'CA Mobile'!E157)+SUM('CA Mobile'!E143:E145,'CA Mobile'!E148:E150,'CA Mobile'!E153:E155,'CA Mobile'!E158:E160))/('Trafic mobile'!E56+'Trafic mobile'!E63) -> 2.0262433 | F31: =(SUM('CA Mobile'!F142,'CA Mobile'!F147,'CA Mobile'!F152,'CA Mobile'!F157)+SUM('CA Mobile'!F143:F145,'CA Mobile'!F148:F150,'CA Mobile'!F153:F155,'CA Mobile'!F158:F160))/('Trafic mobile'!F56+'Trafic mobile'!F63) -> 2.0518354 | G31: =(SUM('CA Mobile'!G142,'CA Mobile'!G147,'CA Mobile'!G152,'CA Mobile'!G157)+SUM('CA Mobile'!G143:G145,'CA Mobile'!G148:G150,'CA Mobile'!G153:G155,'CA Mobile'!G158:G160))/('Trafic mobile'!G56+'Trafic mobile'!G63) -> 1.8442578 | H31: =(SUM('CA Mobile'!H142,'CA Mobile'!H147,'CA Mobile'!H152,'CA Mobile'!H157)+SUM('CA Mobile'!H143:H145,'CA Mobile'!H148:H150,'CA Mobile'!H153:H155,'CA Mobile'!H158:H160))/('Trafic mobile'!H56+'Trafic mobile'!H63) -> 2.0169776 | I31: =(SUM('CA Mobile'!I142,'CA Mobile'!I147,'CA Mobile'!I152,'CA Mobile'!I157)+SUM('CA Mobile'!I143:I145,'CA Mobile'!I148:I150,'CA Mobile'!I153:I155,'CA Mobile'!I158:I160))/('Trafic mobile'!I56+'Trafic mobile'!I63) -> 1.9653473 | J31: =(SUM('CA Mobile'!J142,'CA Mobile'!J147,'CA Mobile'!J152,'CA Mobile'!J157)+SUM('CA Mobile'!J143:J145,'CA Mobile'!J148:J150,'CA Mobile'!J153:J155,'CA Mobile'!J158:J160))/('Trafic mobile'!J56+'Trafic mobile'!J63) -> 1.8406594 | ... O31: =(SUM('CA Mobile'!O142,'CA Mobile'!O147,'CA Mobile'!O152,'CA Mobile'!O157)+SUM('CA Mobile'!O143:O145,'CA Mobile'!O148:O150,'CA Mobile'!O153:O155,'CA Mobile'!O158:O160))/('Trafic mobile'!O56+'Trafic mobile'!O63) -> 1.9768334 | P31: 2.423951 | Q31: 3.1454557 | R31: 3.8958713 | S31: 2.6392016 | T31: =O31/P31-1 -> -0.18445818 | U31: =P31/Q31-1 -> -0.22938001 | V31: =O31/S31-1 -> -0.25097296 | W31: 2.3860803 | X31: =P31-W31 -> 0.037870704
B32: Prépayé | C32: =SUM('CA Mobile'!C142,'CA Mobile'!C147,'CA Mobile'!C152,'CA Mobile'!C157)/'Trafic mobile'!C56 -> 2.2994968 | D32: =SUM('CA Mobile'!D142,'CA Mobile'!D147,'CA Mobile'!D152,'CA Mobile'!D157)/'Trafic mobile'!D56 -> 2.3364207 | E32: =SUM('CA Mobile'!E142,'CA Mobile'!E147,'CA Mobile'!E152,'CA Mobile'!E157)/'Trafic mobile'!E56 -> 2.1190841 | F32: =SUM('CA Mobile'!F142,'CA Mobile'!F147,'CA Mobile'!F152,'CA Mobile'!F157)/'Trafic mobile'!F56 -> 2.1459803 | G32: =SUM('CA Mobile'!G142,'CA Mobile'!G147,'CA Mobile'!G152,'CA Mobile'!G157)/'Trafic mobile'!G56 -> 1.9291787 | H32: =SUM('CA Mobile'!H142,'CA Mobile'!H147,'CA Mobile'!H152,'CA Mobile'!H157)/'Trafic mobile'!H56 -> 2.1098413 | I32: =SUM('CA Mobile'!I142,'CA Mobile'!I147,'CA Mobile'!I152,'CA Mobile'!I157)/'Trafic mobile'!I56 -> 2.0558451 | J32: =SUM('CA Mobile'!J142,'CA Mobile'!J147,'CA Mobile'!J152,'CA Mobile'!J157)/'Trafic mobile'!J56 -> 1.9257273 | ... O32: =SUM('CA Mobile'!O142,'CA Mobile'!O147,'CA Mobile'!O152,'CA Mobile'!O157)/'Trafic mobile'!O56 -> 2.067815 | P32: 2.5206653 | Q32: 3.1782286 | R32: 3.9087993 | S32: 2.667808 | T32: =O32/P32-1 -> -0.17965508 | U32: =P32/Q32-1 -> -0.20689615 | V32: =O32/S32-1 -> -0.2249011 | W32: 2.4758221 | X32: =P32-W32 -> 0.04484328
B33: Postpayé | C33: =SUM('CA Mobile'!C143:C145,'CA Mobile'!C148:C150,'CA Mobile'!C153:C155,'CA Mobile'!C158:C160)/'Trafic mobile'!C63 -> 0.67401036 | D33: =SUM('CA Mobile'!D143:D145,'CA Mobile'!D148:D150,'CA Mobile'!D153:D155,'CA Mobile'!D158:D160)/'Trafic mobile'!D63 -> 0.68282387 | E33: =SUM('CA Mobile'!E143:E145,'CA Mobile'!E148:E150,'CA Mobile'!E153:E155,'CA Mobile'!E158:E160)/'Trafic mobile'!E63 -> 0.61991232 | F33: =SUM('CA Mobile'!F143:F145,'CA Mobile'!F148:F150,'CA Mobile'!F153:F155,'CA Mobile'!F158:F160)/'Trafic mobile'!F63 -> 0.62715959 | G33: =SUM('CA Mobile'!G143:G145,'CA Mobile'!G148:G150,'CA Mobile'!G153:G155,'CA Mobile'!G158:G160)/'Trafic mobile'!G63 -> 0.56238734 | H33: =SUM('CA Mobile'!H143:H145,'CA Mobile'!H148:H150,'CA Mobile'!H153:H155,'CA Mobile'!H158:H160)/'Trafic mobile'!H63 -> 0.61510163 | I33: =SUM('CA Mobile'!I143:I145,'CA Mobile'!I148:I150,'CA Mobile'!I153:I155,'CA Mobile'!I158:I160)/'Trafic mobile'!I63 -> 0.59930712 | J33: =SUM('CA Mobile'!J143:J145,'CA Mobile'!J148:J150,'CA Mobile'!J153:J155,'CA Mobile'!J158:J160)/'Trafic mobile'!J63 -> 0.55991749 | ... O33: =SUM('CA Mobile'!O143:O145,'CA Mobile'!O148:O150,'CA Mobile'!O153:O155,'CA Mobile'!O158:O160)/'Trafic mobile'!O63 -> 0.60300785 | P33: 0.80375908 | Q33: 2.1036347 | R33: 3.3440787 | S33: 1.6383145 | T33: =O33/P33-1 -> -0.24976542 | U33: =P33/Q33-1 -> -0.61791889 | V33: =O33/S33-1 -> -0.63193401 | W33: 0.82173257 | X33: =P33-W33 -> -0.017973494
T34: =O34-Q34 -> 0 | X34: =P34-W34 -> 0

Sheet Marge Mobile
A2: Marge brute Mobile
E5: JANVIER | F5: FEV | G5: MARS | H5: AVR | I5: MAI | J5: JUIN | K5: JUIL | L5: AOUT | M5: SEPT | N5: OCT | O5: NOV | P5: DEC | Q5: ANNUEL | R5: ANNUEL | S5: ANNUEL | T5: ANNUEL | U5: ANNUEL | V5: ANNUEL
B6: (En Millions ML) | E6: 2018 Réalisé | F6: 2018 Réalisé | G6: 2018 Réalisé | H6: 2018 Réalisé | I6: 2018 Réalisé | J6: 2018 Actu2 | K6: 2018 Actu2 | L6: 2018 Actu2 | M6: 2018 Actu2 | N6: 2018 Actu2 | O6: 2018 Actu2 | P6: 2018 Actu2 | Q6: 2018 Actu2 | R6: 2018 Budget | S6: 2017 Budget | T6: Var Actu 2 vs Budget 2018 . Val | U6: Var Actu 2 vs Budget 2018. % | V6: Actu 2 vs 2017 . %
F7: 0
A8: Total Revenu | D8: 9271.0829 | E8: 9271.0829 | F8: 8213.463 | G8: 9219.0252 | H8: 8752.4219 | I8: 8597.3305 | J8: 8213.463 | K8: 8233.9196 | L8: -20.456575 | M8: 7292.4198 | N8: 0.12630144 | O8: ='CA Mobile'!M7 -> 9418.347 | P8: 9219.0252 | Q8: 9250.3384 | R8: -31.313149 | S8: 8150.859 | T8: 0.13104953 | V8: 8752.4219 | W8: 9051.8576 | X8: 9199.8091 | Y8: -299.43571 | Z8: -447.38728 | AA8: 8058.1795 | AB8: 0.086153744 | AD8: 8597.3305 | AE8: 9458.3029 | AF8: 9351.0723 | AG8: =AD8-AE8 -> -860.97247 | AH8: =AD8-AF8 -> -753.74185 | AI8: 8342.3122 | AJ8: =+AD8/AI8-1 -> 0.030569254 | AL8: =+D8+J8+P8+V8+AD8 -> 44053.323 | AM8: =+E8+K8+Q8+W8+AE8 -> 45265.501 | AN8: =+D8+J8+P8+X8+AF8 -> 45254.453 | AO8: =+AL8-AM8 -> -1212.1779 | AP8: =+AL8-AN8 -> -1201.1291 | AQ8: =+G8+M8+S8+AA8+AI8 -> 41062.796 | AR8: =+AL8/AQ8-1 -> 0.072828155 | AT8: 115329.32 | AU8: 115329.49 | AX8: 100860.67 | AY8: =AT8/AX8-1 -> 0.14345181 | AZ8: =AU8/AX8-1 -> 0.14345349 | BA8: =+AV8/AX8-1 -> -1 | BB8: =+AW8/AX8-1 -> -1
B9: Trafic (mn) | D9: 4.6556779 | E9: 4.6556779 | F9: 4.9276615 | G9: 5.5552929 | H9: 5.0211892 | I9: 5.9511421 | J9: 4.9276615 | K9: 3.4633764 | L9: 1.4642851 | M9: 3.7433545 | N9: 0.31637586 | P9: 5.5552929 | Q9: 3.9418341 | R9: 1.6134588 | S9: 4.3191444 | T9: 0.28620216 | V9: 5.0211892 | W9: 3.6779496 | X9: 4.8932632 | Y9: 1.3432396 | Z9: 0.12792594 | AA9: 4.2146529 | AB9: 0.19136483 | AD9: 4.9772151 | AE9: 3.9629273 | AF9: 5.0078487 | AG9: =AD9-AE9 -> 1.0142878 | AH9: =AD9-AF9 -> -0.030633578 | AI9: 4.2246618 | AJ9: =+AD9/AI9-1 -> 0.17813339 | AL9: =+D9+J9+P9+V9+AD9 -> 25.137037 | AM9: =+E9+K9+Q9+W9+AE9 -> 19.701765 | AN9: =+D9+J9+P9+X9+AF9 -> 25.039744 | AO9: =+AL9-AM9 -> 5.4352713 | AP9: =+AL9-AN9 -> 0.09729236 | AQ9: =+G9+M9+S9+AA9+AI9 -> 22.057107 | AR9: =+AL9/AQ9-1 -> 0.13963437 | AT9: 46.319381 | AU9: 61.082787 | AX9: 49.688191 | AY9: =AT9/AX9-1 -> -0.067798998 | AZ9: =AU9/AX9-1 -> 0.22932203 | BA9: =+AV9/AX9-1 -> -1 | BB9: =+AW9/AX9-1 -> -1
B10: Coût unitaire | D10: -85.057596 | E10: -85.057596 | F10: -92.080973 | G10: -82.366735 | H10: -90.779332 | I10: -83.737819 | J10: -92.080973 | K10: -93.691808 | L10: 1.6108349 | M10: -89.620576 | N10: 0.027453488 | P10: -82.366735 | Q10: -93.691808 | R10: 11.325073 | S10: -98.621441 | T10: -0.1648192 | V10: -90.779332 | W10: -93.691808 | X10: -88.569284 | Y10: 2.9124757 | Z10: -2.2100478 | AA10: -113.68646 | AB10: -0.20149388 | AD10: =+AD11/AD9 -> -100.12339 | AE10: -93.691808 | AF10: -88.569284 | AG10: =AD10-AE10 -> -6.431584 | AH10: =AD10-AF10 -> -11.554108 | AI10: -108.92116 | AJ10: =+AD10/AI10-1 -> -0.080771903 | AL10: =+AL11/AL9 -> -89.965729 | AM10: =+AM11/AM9 -> -91.651478 | AO10: =+AL10-AM10 -> 1.6857482 | AQ10: =+AQ11/AQ9 -> -97.851329 | AR10: =+AL10/AQ10-1 -> -0.080587562 | AT10: -93.691808 | AU10: -88.020818 | AX10: -99.913869 | AY10: =AT10/AX10-1 -> -0.062274246 | AZ10: =AU10/AX10-1 -> -0.11903303 | BA10: =+AV10/AX10-1 -> -1 | BB10: =+AW10/AX10-1 -> -1
B11: International | D11: -396.00077 | E11: -396.00077 | F11: -453.74386 | G11: -457.57134 | H11: -455.8202 | I11: -498.33566 | J11: -453.74386 | K11: -324.49 | L11: -129.25387 | M11: -335.48158 | N11: 0.35251497 | P11: -457.57134 | Q11: -369.31757 | R11: -88.25377 | S11: -425.96025 | T11: 0.074211357 | V11: -455.8202 | W11: -344.59375 | X11: -433.39282 | Y11: -111.22646 | Z11: -22.427377 | AA11: -479.14896 | AB11: -0.048687895 | AD11: -498.33566 | AE11: -371.29383 | AF11: -443.54158 | AG11: =AD11-AE11 -> -127.04184 | AH11: =AD11-AF11 -> -54.794085 | AI11: -460.15507 | AJ11: =+AD11/AI11-1 -> 0.082973318 | AL11: =+D11+J11+P11+V11+AD11 -> -2261.4718 | AM11: =+E11+K11+Q11+W11+AE11 -> -1805.6959 | AN11: =+D11+J11+P11+X11+AF11 -> -2184.2504 | AO11: =+AL11-AM11 -> -455.77593 | AP11: =+AL11-AN11 -> -77.221462 | AQ11: =+G11+M11+S11+AA11+AI11 -> -2158.3172 | AR11: =+AL11/AQ11-1 -> 0.047794011 | AT11: -4339.7466 | AU11: -5376.5569 | AX11: -4964.5394 | AY11: =AT11/AX11-1 -> -0.12585111 | AZ11: =AU11/AX11-1 -> 0.082992099 | BA11: =+AV11/AX11-1 -> -1 | BB11: =+AW11/AX11-1 -> -1
B12: Trafic (mn) | E12: 0 | F12: 0 | G12: 0 | H12: 0 | I12: 0 | M12: 0 | S12: 0 | X12: 124.81112 | Z12: -124.81112 | AA12: 0 | AF12: 118.09083 | AH12: =AD12-AF12 -> -118.09083 | AI12: 0 | AL12: =+D12 -> 0 | AM12: =+E12 -> 0 | AO12: =+AL12-AM12 -> 0 | AQ12: =+G12 -> 0 | AR12: =+AL12/AQ12-1 -> #DIV/0! | AU12: 1459.9045
B13: Coût unitaire | E13: 0 | F13: 0 | G13: 0 | H13: 0 | I13: 0 | M13: 0 | S13: 0 | X13: -10.23406 | Z13: 10.23406 | AA13: 0 | AF13: -10.234163 | AH13: =AD13-AF13 -> 10.234163 | AI13: 0 | AL13: =+D13 -> 0 | AM13: =+E13 -> 0 | AO13: =+AL13-AM13 -> 0 | AQ13: =+G13 -> 0 | AR13: =+AL13/AQ13-1 -> #DIV/0! | AU13: -10.178548
B14: Transit Sortant International depuis les concurents | E14: 0 | F14: 0 | G14: 0 | H14: 0 | I14: 0 | M14: 0 | S14: 0 | X14: -1277.3245 | Z14: 1277.3245 | AA14: 0 | AF14: -1208.5609 | AH14: =AD14-AF14 -> 1208.5609 | AI14: 0 | AL14: =+D14 -> 0 | AM14: =+E14 -> 0 | AO14: =+AL14-AM14 -> 0 | AQ14: =+G14 -> 0 | AR14: =+AL14/AQ14-1 -> #DIV/0! | AU14: -14859.709
B15: Trafic (mn) | D15: 105.29885 | E15: 105.29885 | F15: 114.32291 | G15: 127.14132 | H15: 126.19471 | I15: 127.80809 | J15: 114.32291 | K15: 90.477907 | L15: 23.845002 | M15: 36.531632 | N15: 2.1294225 | P15: 127.14132 | Q15: 106.40776 | R15: 20.733555 | S15: 47.18207 | T15: 1.6946956 | V15: 126.19471 | W15: 101.08705 | X15: 124.81112 | Y15: 25.10766 | Z15: 1.383587 | AA15: 53.101472 | AB15: 1.3764823 | AD15: =+AD17/AD16 -> 127.80809 | AE15: 104.76692 | AF15: 118.09083 | AG15: =AD15-AE15 -> 23.041172 | AH15: =AD15-AF15 -> 9.7172565 | AI15: 64.434078 | AJ15: =+AD15/AI15-1 -> 0.98354807 | AL15: =+D15+J15+P15+V15+AD15 -> 600.76588 | AM15: =+E15+K15+Q15+W15+AE15 -> 508.03849 | AN15: =+D15+J15+P15+X15+AF15 -> 589.66504 | AO15: =+AL15-AM15 -> 92.72739 | AP15: =+AL15-AN15 -> 11.100844 | AQ15: =+G15+M15+S15+AA15+AI15 -> 328.39057 | AR15: =+AL15/AQ15-1 -> 0.82942489 | AT15: 1270.6633 | AU15: 1459.9045 | AX15: 887.2216 | AY15: =AT15/AX15-1 -> 0.43218256 | AZ15: =AU15/AX15-1 -> 0.64547903 | BA15: =+AV15/AX15-1 -> -1 | BB15: =+AW15/AX15-1 -> -1
B16: Coût unitaire | D16: -10 | E16: -10 | F16: -10 | G16: -10 | H16: -10 | I16: -10 | J16: -10 | K16: -10.010103 | L16: 0.010103197 | M16: -10 | N16: 0 | P16: -10 | Q16: -10.010043 | R16: 0.010043362 | S16: -10 | T16: 0 | V16: -10 | W16: -10.010076 | X16: -10.23406 | Y16: 0.010075588 | Z16: 0.23405961 | AA16: -10 | AB16: 0 | AD16: -10 | AE16: -10.010083 | AF16: -10.234163 | AG16: =AD16-AE16 -> 0.010082977 | AH16: =AD16-AF16 -> 0.2341631 | AI16: -10 | AJ16: =+AD16/AI16-1 -> 0 | AL16: -10 | AM16: -10 | AO16: =+AL16-AM16 -> 0 | AQ16: -10 | AR16: =+AL16/AQ16-1 -> 0 | AT16: -10 | AU16: -10.178548 | AX16: -10 | AY16: =AT16/AX16-1 -> 0 | AZ16: =AU16/AX16-1 -> 0.017854842 | BA16: =+AV16/AX16-1 -> -1 | BB16: =+AW16/AX16-1 -> -1
B17: Opérateur national MTN | D17: -1052.9885 | E17: -1052.9885 | F17: -1143.2291 | G17: -1271.4132 | H17: -1261.9471 | I17: -1278.0809 | J17: -1143.2291 | K17: -905.69318 | L17: -237.53591 | M17: -365.31632 | N17: 2.1294225 | P17: -1271.4132 | Q17: -1065.1463 | R17: -206.26686 | S17: -471.8207 | T17: 1.6946956 | V17: -1261.9471 | W17: -1011.889 | X17: -1277.3245 | Y17: -250.05809 | Z17: 15.377373 | AA17: -531.01472 | AB17: 1.3764823 | AD17: -1278.0809 | AE17: -1048.7256 | AF17: -1208.5609 | AG17: =AD17-AE17 -> -229.35536 | AH17: =AD17-AF17 -> -69.520049 | AI17: -644.34078 | AJ17: =+AD17/AI17-1 -> 0.98354807 | AL17: =+D17+J17+P17+V17+AD17 -> -6007.6588 | AM17: =+E17+K17+Q17+W17+AE17 -> -5084.4426 | AN17: =+D17+J17+P17+X17+AF17 -> -5953.5161 | AO17: =+AL17-AM17 -> -923.21621 | AP17: =+AL17-AN17 -> -54.142677 | AQ17: =+G17+M17+S17+AA17+AI17 -> -3283.9057 | AR17: =+AL17/AQ17-1 -> 0.82942489 | AT17: -12719.45 | AU17: -14859.709 | AX17: -8872.216 | AY17: =AT17/AX17-1 -> 0.4336272 | AZ17: =AU17/AX17-1 -> 0.6748588 | BA17: =+AV17/AX17-1 -> -1 | BB17: =+AW17/AX17-1 -> -1
B18: Trafic (mn) | E18: 0 | F18: 0 | G18: 0 | H18: 0 | I18: 0 | M18: 0 | S18: 0 | X18: 0.11416174 | Z18: -0.11416174 | AA18: 0 | AF18: 0.10827348 | AH18: =AD18-AF18 -> -0.10827348 | AI18: 0 | AL18: =+D18 -> 0 | AM18: =+E18 -> 0 | AO18: =+AL18-AM18 -> 0 | AQ18: =+G18 -> 0 | AR18: =+AL18/AQ18-1 -> #DIV/0! | AU18: 2.9078454 | AX18: 0
B19: Coût unitaire | E19: 0 | F19: 0 | G19: 0 | H19: 0 | I19: 0 | M19: 0 | S19: 0 | X19: -13.078379 | Z19: 13.078379 | AA19: 0 | AF19: -13.047272 | AH19: =AD19-AF19 -> 13.047272 | AI19: 0 | AL19: =+D19 -> 0 | AM19: =+E19 -> 0 | AO19: =+AL19-AM19 -> 0 | AQ19: =+G19 -> 0 | AR19: =+AL19/AQ19-1 -> #DIV/0! | AU19: -11.066933 | AX19: 0
B20: Opérateur national ORANGE | E20: 0 | F20: 0 | G20: 0 | H20: 0 | I20: 0 | M20: 0 | S20: 0 | X20: -1.4930506 | Z20: 1.4930506 | AA20: 0 | AF20: -1.4126735 | AH20: =AD20-AF20 -> 1.4126735 | AI20: 0 | AL20: =+D20 -> 0 | AM20: =+E20 -> 0 | AO20: =+AL20-AM20 -> 0 | AQ20: =+G20 -> 0 | AR20: =+AL20/AQ20-1 -> #DIV/0! | AU20: -32.180929 | AX20: 0
B21: Trafic (mn) | E21: 0 | F21: 0 | G21: 0 | H21: 0 | I21: 0 | M21: 0 | S21: 0 | X21: 0 | Z21: 0 | AA21: 0 | AF21: 0 | AH21: =AD21-AF21 -> 0 | AI21: 0 | AL21: =+D21 -> 0 | AM21: =+E21 -> 0 | AO21: =+AL21-AM21 -> 0 | AQ21: =+G21 -> 0 | AR21: =+AL21/AQ21-1 -> #DIV/0! | AU21: 0 | AX21: 0
B22: Coût unitaire | E22: 0 | F22: 0 | G22: 0 | H22: 0 | I22: 0 | M22: 0 | S22: 0 | X22: 0 | Z22: 0 | AA22: 0 | AF22: 0 | AH22: =AD22-AF22 -> 0 | AI22: 0 | AL22: =+D22 -> 0 | AM22: =+E22 -> 0 | AO22: =+AL22-AM22 -> 0 | AQ22: =+G22 -> 0 | AR22: =+AL22/AQ22-1 -> #DIV/0! | AU22: 0 | AX22: 0
B23: Opérateur national AUTRES MOBILES | E23: 0 | F23: 0 | G23: 0 | H23: 0 | I23: 0 | M23: 0 | S23: 0 | X23: 0 | Z23: 0 | AA23: 0 | AF23: 0 | AH23: =AD23-AF23 -> 0 | AI23: 0 | AL23: =+D23 -> 0 | AM23: =+E23 -> 0 | AO23: =+AL23-AM23 -> 0 | AQ23: =+G23 -> 0 | AR23: =+AL23/AQ23-1 -> #DIV/0! | AU23: 0 | AX23: 0
B24: Trafic (mn) | D24: 0.8925808 | E24: 0.8925808 | F24: 0 | G24: 0 | H24: 0 | I24: 0 | J24: 0 | K24: 2.0355146 | L24: -2.0355146 | M24: 1.2093911 | N24: -1 | P24: 0 | Q24: 2.393991 | R24: -2.393991 | S24: 1.4450053 | T24: -1 | V24: 0 | W24: 2.2742256 | X24: 0 | Y24: -2.2742256 | Z24: 0 | AA24: 1.4128111 | AB24: -1 | AD24: =+AD26/AD25 -> 0 | AE24: 2.3569948 | AF24: 0 | AG24: =AD24-AE24 -> -2.3569948 | AH24: =AD24-AF24 -> 0 | AI24: 1.5849467 | AJ24: =+AD24/AI24-1 -> -1 | AL24: =+D24+J24+P24+V24+AD24 -> 0.8925808 | AM24: =+E24+K24+Q24+W24+AE24 -> 9.9533069 | AN24: =+D24+J24+P24+X24+AF24 -> 0.8925808 | AO24: =+AL24-AM24 -> -9.0607261 | AP24: =+AL24-AN24 -> 0 | AQ24: =+G24+M24+S24+AA24+AI24 -> 5.6521542 | AR24: =+AL24/AQ24-1 -> -0.84208131 | AT24: 28.586384 | AU24: 0.8925808 | AX24: 22.713801 | AY24: =AT24/AX24-1 -> 0.25854694 | AZ24: =AU24/AX24-1 -> -0.96070315 | BA24: =+AV24/AX24-1 -> -1 | BB24: =+AW24/AX24-1 -> -1
B25: Coût unitaire | D25: -10 | E25: -10 | F25: -10 | G25: -10 | H25: -10 | I25: -10 | J25: -10 | K25: -10.08821 | L25: 0.088209678 | M25: -10 | N25: 0 | P25: -10 | Q25: -10.087742 | R25: 0.087742154 | S25: -10 | T25: 0 | V25: -10 | W25: -10.088034 | X25: -10 | Y25: 0.088034368 | Z25: 0 | AA25: -10 | AB25: 0 | AD25: -10 | AE25: -10.088125 | AF25: -10 | AG25: =AD25-AE25 -> 0.088125025 | AH25: =AD25-AF25 -> 0 | AI25: -10 | AJ25: =+AD25/AI25-1 -> 0 | AL25: -10 | AM25: -10 | AO25: =+AL25-AM25 -> 0 | AQ25: -10 | AR25: =+AL25/AQ25-1 -> 0 | AT25: -10 | AU25: -10 | AX25: -10 | AY25: =AT25/AX25-1 -> 0 | AZ25: =AU25/AX25-1 -> 0 | BA25: =+AV25/AX25-1 -> -1 | BB25: =+AW25/AX25-1 -> -1
B26: Opérateur national 2 (glo) | D26: -8.925808 | E26: -8.925808 | F26: 0 | G26: 0 | H26: 0 | I26: 0 | J26: 0 | K26: -20.534698 | L26: 20.534698 | M26: -12.093911 | N26: -1 | P26: 0 | Q26: -24.149964 | R26: 24.149964 | S26: -14.450053 | T26: -1 | V26: 0 | W26: -22.942467 | X26: 0 | Y26: 22.942467 | Z26: 0 | AA26: -14.128111 | AB26: -1 | AD26: 0 | AE26: -23.777658 | AF26: 0 | AG26: =AD26-AE26 -> 23.777658 | AH26: =AD26-AF26 -> 0 | AI26: -15.849467 | AJ26: =+AD26/AI26-1 -> -1 | AL26: =+D26+J26+P26+V26+AD26 -> -8.925808 | AM26: =+E26+K26+Q26+W26+AE26 -> -100.33059 | AN26: =+D26+J26+P26+X26+AF26 -> -8.925808 | AO26: =+AL26-AM26 -> 91.404787 | AP26: =+AL26-AN26 -> 0 | AQ26: =+G26+M26+S26+AA26+AI26 -> -56.521542 | AR26: =+AL26/AQ26-1 -> -0.84208131 | AT26: -288.38692 | AU26: -8.925808 | AX26: -227.13801 | AY26: =AT26/AX26-1 -> 0.26965508 | AZ26: =AU26/AX26-1 -> -0.96070315 | BA26: =+AV26/AX26-1 -> -1 | BB26: =+AW26/AX26-1 -> -1
B27: Trafic (mn) | D27: 1.1540285 | E27: 1.1540285 | F27: 0.3486519 | G27: 0.383805 | H27: 0.3711483 | I27: 0.4693701 | J27: 0.3486519 | K27: 0.083062779 | L27: 0.26558912 | M27: 0.3149668 | N27: 0.1069481 | P27: 0.383805 | Q27: 0.097686517 | R27: 0.28611848 | S27: 0.3733697 | T27: 0.027948974 | V27: 0.3711483 | W27: 0.092802193 | X27: 0.11416174 | Y27: 0.27834611 | Z27: 0.25698656 | AA27: 0.3555117 | AB27: 0.043983363 | AD27: =+AD29/AD28 -> 0.4693701 | AE27: =+AE29/AE28 -> 0.096180539 | AF27: 0.10827348 | AG27: =AD27-AE27 -> 0.37318956 | AH27: =AD27-AF27 -> 0.36109662 | AI27: 0.3940975 | AJ27: =+AD27/AI27-1 -> 0.19099994 | AL27: =+D27+J27+P27+V27+AD27 -> 2.7270038 | AM27: =+E27+K27+Q27+W27+AE27 -> 1.5237605 | AN27: =+D27+J27+P27+X27+AF27 -> 2.1089206 | AO27: =+AL27-AM27 -> 1.2032433 | AP27: =+AL27-AN27 -> 0.61808318 | AQ27: =+G27+M27+S27+AA27+AI27 -> 1.8217507 | AR27: =+AL27/AQ27-1 -> 0.49691382 | AT27: 1.1684312 | AU27: 2.9078454 | AX27: 7.726011 | AY27: =AT27/AX27-1 -> -0.84876656 | AZ27: =AU27/AX27-1 -> -0.62362914 | BA27: =+AV27/AX27-1 -> -1 | BB27: =+AW27/AX27-1 -> -1
B28: Coût unitaire | D28: -10 | E28: -10 | F28: -10 | G28: -10 | H28: -10 | I28: -10 | J28: -10 | K28: -10 | L28: 0 | M28: -10 | N28: 0 | P28: -10 | Q28: -10 | R28: 0 | S28: -10 | T28: 0 | V28: -10 | W28: -10 | X28: -13.078379 | Y28: 0 | Z28: 3.0783794 | AA28: -10 | AB28: 0 | AD28: -10 | AE28: -10 | AF28: -13.047272 | AG28: =AD28-AE28 -> 0 | AH28: =AD28-AF28 -> 3.0472717 | AI28: -10 | AJ28: =+AD28/AI28-1 -> 0 | AL28: -10 | AM28: -10 | AO28: =+AL28-AM28 -> 0 | AQ28: -10 | AR28: =+AL28/AQ28-1 -> 0 | AT28: -10 | AU28: -11.066933 | AX28: -10 | AY28: =AT28/AX28-1 -> 0 | AZ28: =AU28/AX28-1 -> 0.10669325 | BA28: =+AV28/AX28-1 -> -1 | BB28: =+AW28/AX28-1 -> -1
B29: Opérateur national 3 (bbcom, libercom & btsa) | D29: -11.540285 | E29: -11.540285 | F29: -3.486519 | G29: -3.83805 | H29: -3.711483 | I29: -4.693701 | J29: -3.486519 | K29: -0.83062779 | L29: -2.6558912 | M29: -3.149668 | N29: 0.1069481 | P29: -3.83805 | Q29: -0.97686517 | R29: -2.8611848 | S29: -3.733697 | T29: 0.027948974 | V29: -3.711483 | W29: -0.92802193 | X29: -1.4930506 | Y29: -2.7834611 | Z29: -2.2184324 | AA29: -3.555117 | AB29: 0.043983363 | AD29: -4.693701 | AE29: -0.96180539 | AF29: -1.4126735 | AG29: =AD29-AE29 -> -3.7318956 | AH29: =AD29-AF29 -> -3.2810275 | AI29: -3.940975 | AJ29: =+AD29/AI29-1 -> 0.19099994 | AL29: =+D29+J29+P29+V29+AD29 -> -27.270038 | AM29: =+E29+K29+Q29+W29+AE29 -> -15.237605 | AN29: =+D29+J29+P29+X29+AF29 -> -21.770578 | AO29: =+AL29-AM29 -> -12.032433 | AP29: =+AL29-AN29 -> -5.4994599 | AQ29: =+G29+M29+S29+AA29+AI29 -> -18.217507 | AR29: =+AL29/AQ29-1 -> 0.49691382 | AT29: -11.66524 | AU29: -32.180929 | AX29: -77.26011 | AY29: =AT29/AX29-1 -> -0.84901341 | AZ29: =AU29/AX29-1 -> -0.5834729 | BA29: =+AV29/AX29-1 -> -1 | BB29: =+AW29/AX29-1 -> -1
B30: Trafic Local (mn) | E30: 0 | F30: 0 | G30: 0 | H30: 0 | I30: 0 | K30: 0 | L30: 0 | M30: 0 | N30: #DIV/0! | Q30: 0 | R30: 0 | S30: 0 | T30: #DIV/0! | W30: 0 | X30: 0 | Y30: 0 | Z30: 0 | AA30: 0 | AB30: #DIV/0! | AE30: 0 | AF30: 0 | AG30: =AD30-AE30 -> 0 | AH30: =AD30-AF30 -> 0 | AI30: 0 | AJ30: =+AD30/AI30-1 -> #DIV/0! | AL30: =+D30+J30+P30 -> 0 | AM30: =+E30+K30+Q30 -> 0 | AO30: =+AL30-AM30 -> 0 | AQ30: =+G30+M30+S30 -> 0 | AR30: =+AL30/AQ30-1 -> #DIV/0! | AT30: 0 | AU30: 0 | AX30: 0 | BA30: =+AV30/AX30-1 -> #DIV/0! | BB30: =+AW30/AX30-1 -> #DIV/0!
B31: Coût unitaire | E31: 0 | F31: 0 | G31: 0 | H31: 0 | I31: 0 | K31: 0 | L31: 0 | M31: 0 | N31: #DIV/0! | Q31: 0 | R31: 0 | S31: 0 | T31: #DIV/0! | W31: 0 | X31: -42.666667 | Y31: 0 | Z31: 42.666667 | AA31: 0 | AB31: #DIV/0! | AE31: 0 | AF31: -42.666667 | AG31: =AD31-AE31 -> 0 | AH31: =AD31-AF31 -> 42.666667 | AI31: 0 | AJ31: =+AD31/AI31-1 -> #DIV/0! | AL31: =+D31+J31+P31 -> 0 | AM31: =+E31+K31+Q31 -> 0 | AO31: =+AL31-AM31 -> 0 | AQ31: =+G31+M31+S31 -> 0 | AR31: =+AL31/AQ31-1 -> #DIV/0! | AT31: 0 | AU31: -317.02961 | AX31: 0 | BA31: =+AV31/AX31-1 -> #DIV/0! | BB31: =+AW31/AX31-1 -> #DIV/0!
B32: Trafic Interurbain (mn) | E32: 0 | F32: 0 | G32: 0 | H32: 0 | I32: 0 | K32: 0 | L32: 0 | M32: 0 | N32: #DIV/0! | Q32: 0 | R32: 0 | S32: 0 | T32: #DIV/0! | W32: 0 | X32: 0 | Y32: 0 | Z32: 0 | AA32: 0 | AB32: #DIV/0! | AE32: 0 | AF32: 0 | AG32: =AD32-AE32 -> 0 | AH32: =AD32-AF32 -> 0 | AI32: 0 | AJ32: =+AD32/AI32-1 -> #DIV/0! | AL32: =+D32+J32+P32 -> 0 | AM32: =+E32+K32+Q32 -> 0 | AO32: =+AL32-AM32 -> 0 | AQ32: =+G32+M32+S32 -> 0 | AR32: =+AL32/AQ32-1 -> #DIV/0! | AT32: 0 | AU32: -0.318921 | AX32: 0 | BA32: =+AV32/AX32-1 -> #DIV/0! | BB32: =+AW32/AX32-1 -> #DIV/0!
B33: Coût unitaire | E33: 0 | F33: 0 | G33: 0 | H33: 0 | I33: 0 | K33: 0 | L33: 0 | M33: 0 | N33: #DIV/0! | Q33: 0 | R33: 0 | S33: 0 | T33: #DIV/0! | W33: 0 | X33: -42.666667 | Y33: 0 | Z33: 42.666667 | AA33: 0 | AB33: #DIV/0! | AE33: 0 | AF33: -42.666667 | AG33: =AD33-AE33 -> 0 | AH33: =AD33-AF33 -> 42.666667 | AI33: 0 | AJ33: =+AD33/AI33-1 -> #DIV/0! | AL33: =+D33+J33+P33 -> 0 | AM33: =+E33+K33+Q33 -> 0 | AO33: =+AL33-AM33 -> 0 | AQ33: =+G33+M33+S33 -> 0 | AR33: =+AL33/AQ33-1 -> #DIV/0! | AT33: 0 | AU33: -467.67083 | AX33: 0 | BA33: =+AV33/AX33-1 -> #DIV/0! | BB33: =+AW33/AX33-1 -> #DIV/0!
B34: Trafic Local (mn) | E34: 0 | F34: 0 | G34: 0 | H34: 0 | I34: 0 | M34: 0 | S34: 0 | X34: 0 | Z34: 0 | AA34: 0 | AF34: 0 | AH34: =AD34-AF34 -> 0 | AI34: 0 | AL34: =+D34+J34+P34 -> 0 | AM34: =+E34+K34+Q34 -> 0 | AO34: =+AL34-AM34 -> 0 | AQ34: =+G34+M34+S34 -> 0 | AR34: =+AL34/AQ34-1 -> #DIV/0! | AU34: 150.96015
B35: Coût unitaire | E35: 0 | F35: 0 | G35: 0 | H35: 0 | I35: 0 | M35: 0 | S35: 0 | X35: -755.34682 | Z35: 755.34682 | AA35: 0 | AF35: -772.98897 | AH35: =AD35-AF35 -> 772.98897 | AI35: 0 | AL35: =+D35+J35+P35 -> 0 | AM35: =+E35+K35+Q35 -> 0 | AO35: =+AL35-AM35 -> 0 | AQ35: =+G35+M35+S35 -> 0 | AR35: =+AL35/AQ35-1 -> #DIV/0! | AU35: -9743.8169
B36: Trafic Interurbain (mn) | E36: 0 | F36: 0 | G36: 0 | H36: 0 | I36: 0 | M36: 0 | S36: 0 | X36: -447.31137 | Z36: 447.31137 | AA36: 0 | AF36: -452.07773 | AH36: =AD36-AF36 -> 452.07773 | AI36: 0 | AL36: =+D36+J36+P36 -> 0 | AM36: =+E36+K36+Q36 -> 0 | AO36: =+AL36-AM36 -> 0 | AQ36: =+G36+M36+S36 -> 0 | AR36: =+AL36/AQ36-1 -> #DIV/0! | AU36: -5648.2102
B37: Coût unitaire | E37: 0 | F37: 0 | G37: 0 | H37: 0 | I37: 0 | M37: 0 | S37: 0 | X37: -178.99416 | Z37: 178.99416 | AA37: 0 | AF37: -180.90144 | AH37: =AD37-AF37 -> 180.90144 | AI37: 0 | AL37: =+D37+J37+P37 -> 0 | AM37: =+E37+K37+Q37 -> 0 | AO37: =+AL37-AM37 -> 0 | AQ37: =+G37+M37+S37 -> 0 | AR37: =+AL37/AQ37-1 -> #DIV/0! | AU37: -2205.6341
B38: Interconnexion Fixe | E38: 0 | F38: 0 | G38: 0 | H38: 0 | I38: 0 | M38: 0 | S38: 0 | X38: -129.04129 | Z38: 129.04129 | AA38: 0 | AF38: -140.0098 | AH38: =AD38-AF38 -> 140.0098 | AI38: 0 | AL38: =+D38+J38+P38 -> 0 | AM38: =+E38+K38+Q38 -> 0 | AO38: =+AL38-AM38 -> 0 | AQ38: =+G38+M38+S38 -> 0 | AR38: =+AL38/AQ38-1 -> #DIV/0! | AU38: -1889.9726
B39: Others | D39: -50.120972 | E39: -50.120972 | F39: -1.643743 | G39: -28.494756 | H39: -43.482055 | I39: -39.94618 | J39: -1.643743 | K39: -57.28184 | L39: 55.638097 | M39: -52.980149 | N39: -0.96897436 | P39: -28.494756 | Q39: -64.470605 | R39: 35.975849 | S39: -63.628767 | T39: -0.5521718 | V39: -43.482055 | W39: -63.53553 | X39: -41.61313 | Y39: 20.053475 | Z39: -1.8689249 | AA39: -27.27047 | AB39: 0.59447399 | AD39: -39.94618 | AE39: -66.75888 | AF39: -43.712712 | AG39: =AD39-AE39 -> 26.8127 | AH39: =AD39-AF39 -> 3.7665318 | AI39: -28.012518 | AJ39: =+AD39/AI39-1 -> 0.42601176 | AL39: =+D39+J39+P39+V39+AD39 -> -163.68771 | AM39: =+E39+K39+Q39+W39+AE39 -> -302.16783 | AN39: =+D39+J39+P39+X39+AF39 -> -165.58531 | AO39: =+AL39-AM39 -> 138.48012 | AP39: =+AL39-AN39 -> 1.8976069 | AQ39: =+G39+M39+S39+AA39+AI39 -> -200.38666 | AR39: =+AL39/AQ39-1 -> -0.1831407 | AT39: -812.60696 | AU39: -497.98851 | AX39: -638.99738 | AY39: =AT39/AX39-1 -> 0.27169061 | AZ39: =AU39/AX39-1 -> -0.22067206 | BA39: =+AV39/AX39-1 -> -1 | BB39: =+AW39/AX39-1 -> -1
B40: Nbre SMS | D40: 2.417532 | E40: 2.417532 | F40: 5.95334 | G40: 6.621253 | H40: 6.520014 | I40: 6.5429251 | J40: 5.95334 | K40: 2.3477141 | L40: 3.6056259 | M40: 1.474139 | N40: 3.0385201 | P40: 6.621253 | Q40: 2.8465441 | R40: 3.7747089 | S40: 1.629824 | T40: 3.0625571 | V40: 6.520014 | W40: 2.5773759 | X40: 4.2774595 | Y40: 3.9426381 | Z40: 2.2425545 | AA40: 1.629824 | AB40: 3.0004405 | AD40: =6.37813426666667+0.164790833333333 -> 6.5429251 | AE40: =+AE42/AE41 -> 2.8530311 | AF40: 4.5212154 | AG40: =AD40-AE40 -> 3.689894 | AH40: =AD40-AF40 -> 2.0217097 | AI40: 1.666117 | AJ40: =+AD40/AI40-1 -> 2.9270502 | AL40: =+D40+J40+P40+V40+AD40 -> 28.055064 | AM40: =+E40+K40+Q40+W40+AE40 -> 13.042197 | AN40: =+D40+J40+P40+X40+AF40 -> 23.7908 | AO40: =+AL40-AM40 -> 15.012867 | AP40: =+AL40-AN40 -> 4.2642642 | AQ40: =+G40+M40+S40+AA40+AI40 -> 13.021157 | AR40: =+AL40/AQ40-1 -> 1.1545754 | AT40: 22.3461 | AU40: 56.794557 | AX40: 21.662409 | AY40: =AT40/AX40-1 -> 0.031561193 | AZ40: =AU40/AX40-1 -> 1.6218024 | BA40: =+AV40/AX40-1 -> -1 | BB40: =+AW40/AX40-1 -> -1
B41: Coût unitaire | D41: -7.7132605 | E41: -7.7132605 | F41: -6.0522031 | G41: -5.9665261 | H41: -5.8904567 | I41: -5.9625422 | J41: -6.0522031 | K41: -5.4748856 | L41: -0.57731749 | M41: -6.5996124 | N41: -0.082945667 | P41: -5.9665261 | Q41: -5.4748856 | R41: -0.49164045 | S41: -5.8425621 | T41: 0.021217395 | V41: -5.8904567 | W41: -5.4748856 | X41: -6.1532383 | Y41: -0.41557103 | Z41: 0.26278164 | AA41: -4.3419633 | AB41: 0.35663438 | AD41: =+AD42/AD40 -> -5.9625422 | AE41: -5.4748856 | AF41: -6.1530254 | AG41: =AD41-AE41 -> -0.48765655 | AH41: =AD41-AF41 -> 0.19048323 | AI41: -7.2612398 | AJ41: =+AD41/AI41-1 -> -0.17885342 | AL41: =+AL42/AL40 -> -6.116617 | AM41: =+E41 -> -7.7132605 | AO41: =+AL41-AM41 -> 1.5966434 | AQ41: =+G41 -> -5.9665261 | AR41: =+AL41/AQ41-1 -> 0.025155498 | AT41: -8.0260742 | AU41: -6.1773219 | AX41: -7.5087112 | AY41: =AT41/AX41-1 -> 0.068901714 | AZ41: =AU41/AX41-1 -> -0.17731262 | BA41: =+AV41/AX41-1 -> -1 | BB41: =+AW41/AX41-1 -> -1
B42: Interconnexion SMS | D42: -18.647054 | E42: -18.647054 | F42: -36.030823 | G42: -39.505879 | H42: -38.40586 | I42: -39.012467 | J42: -36.030823 | K42: -12.853466 | L42: -23.177357 | M42: -9.728746 | N42: 2.7035424 | P42: -39.505879 | Q42: -15.584504 | R42: -23.921375 | S42: -9.522348 | T42: 3.148754 | V42: -38.40586 | W42: -14.110838 | X42: -26.320228 | Y42: -24.295022 | Z42: -12.085632 | AA42: -7.076636 | AB42: 4.4271352 | AD42: -39.012467 | AE42: -15.620019 | AF42: -27.819154 | AG42: =AD42-AE42 -> -23.392448 | AH42: =AD42-AF42 -> -11.193313 | AI42: -12.098075 | AJ42: =+AD42/AI42-1 -> 2.2246838 | AL42: =+D42+J42+P42+V42+AD42 -> -171.60208 | AM42: =+E42+K42+Q42+W42+AE42 -> -76.815881 | AN42: =+D42+J42+P42+X42+AF42 -> -148.32314 | AO42: =+AL42-AM42 -> -94.786202 | AP42: =+AL42-AN42 -> -23.278946 | AQ42: =+G42+M42+S42+AA42+AI42 -> -77.931684 | AR42: =+AL42/AQ42-1 -> 1.2019553 | AT42: -179.35146 | AU42: -350.83826 | AX42: -162.65677 | AY42: =AT42/AX42-1 -> 0.10263753 | AZ42: =AU42/AX42-1 -> 1.1569238 | BA42: =+AV42/AX42-1 -> -1 | BB42: =+AW42/AX42-1 -> -1
B43: Roaming out | D43: -60.496285 | E43: -60.496285 | F43: -14.99299 | G43: -46.668376 | H43: -43.735944 | I43: -39.602975 | J43: -14.99299 | K43: -55.495292 | L43: 40.502302 | M43: -66.891032 | N43: -0.77585949 | P43: -46.668376 | Q43: -61.024133 | R43: 14.355757 | S43: -74.309641 | T43: -0.37197414 | V43: -43.735944 | W43: -58.900794 | X43: -41.090611 | Y43: 15.16485 | Z43: -2.6453325 | AA43: -51.116833 | AB43: -0.14439253 | AD43: -39.602975 | AE43: -60.965584 | AF43: -42.482524 | AG43: =AD43-AE43 -> 21.362609 | AH43: =AD43-AF43 -> 2.8795492 | AI43: -70.631949 | AJ43: =+AD43/AI43-1 -> -0.43930508 | AL43: =+D43+J43+P43+V43+AD43 -> -205.49657 | AM43: =+E43+K43+Q43+W43+AE43 -> -296.88209 | AN43: =+D43+J43+P43+X43+AF43 -> -205.73079 | AO43: =+AL43-AM43 -> 91.385519 | AP43: =+AL43-AN43 -> 0.23421661 | AQ43: =+G43+M43+S43+AA43+AI43 -> -309.61783 | AR43: =+AL43/AQ43-1 -> -0.33628961 | AT43: -719.46796 | AU43: -504.5926 | AX43: -625.48698 | AY43: =AT43/AX43-1 -> 0.1502525 | AZ43: =AU43/AX43-1 -> -0.19328041 | BA43: =+AV43/AX43-1 -> -1 | BB43: =+AW43/AX43-1 -> -1
E44: 0 | F44: 0 | G44: 0 | H44: 0 | I44: 0 | M44: 0 | S44: 0 | X44: -0.77618122 | Z44: 0.77618122 | AA44: 0 | AF44: -0.77618122 | AH44: =AD44-AF44 -> 0.77618122 | AI44: 0 | AL44: =+D44+J44+P44 -> 0 | AM44: =+E44+K44+Q44 -> 0 | AO44: =+AL44-AM44 -> 0 | AQ44: =+G44+M44+S44 -> 0 | AT44: 0 | AU44: 0 | AX44: 0
B45: Coûts des terminaux et cartes | D45: 161.55799 | E45: 161.55799 | F45: -92.748612 | G45: -1.838983 | H45: -18.718422 | I45: -30.983934 | J45: -92.748612 | K45: -30.444047 | L45: -62.304565 | M45: -15.21009 | N45: 5.0978345 | P45: -1.838983 | Q45: -30.444047 | R45: 28.605064 | S45: 3.440542 | T45: -1.5345039 | V45: -18.718422 | W45: -30.444047 | X45: -42.666667 | Y45: 11.725625 | Z45: 23.948245 | AA45: -24.134972 | AB45: -0.22442744 | AD45: =SUM(AD46:AD51) -> -30.983934 | AE45: -30.444047 | AF45: -42.666667 | AG45: =AD45-AE45 -> -0.53988691 | AH45: =AD45-AF45 -> 11.682733 | AI45: -69.511303 | AJ45: =+AD45/AI45-1 -> -0.55426049 | AL45: =+D45+J45+P45+V45+AD45 -> 17.268038 | AM45: =+E45+K45+Q45+W45+AE45 -> 39.781801 | AN45: =+D45+J45+P45+X45+AF45 -> -18.362939 | AO45: =+AL45-AM45 -> -22.513763 | AP45: =+AL45-AN45 -> 35.630977 | AQ45: =+G45+M45+S45+AA45+AI45 -> -107.25481 | AR45: =+AL45/AQ45-1 -> -1.1610001 | AT45: -365.32857 | AU45: -317.02961 | AX45: -430.15757 | AY45: =AT45/AX45-1 -> -0.15070991 | AZ45: =AU45/AX45-1 -> -0.26299192 | BA45: =+AV45/AX45-1 -> -1 | BB45: =+AW45/AX45-1 -> -1
B46: Dont coût des cartes de recharge vendues & des Kits. | D46: -0.12162 | E46: -0.12162 | F46: -0.092652 | G46: -0.104649 | H46: -0.129977 | I46: -0.141217 | J46: -0.092652 | K46: 0 | L46: -0.092652 | M46: -0.201606 | N46: -0.54043034 | P46: -0.104649 | Q46: 0 | R46: -0.104649 | S46: -0.828427 | T46: -0.87367746 | V46: -0.129977 | W46: 0 | X46: 0 | Y46: -0.129977 | Z46: -0.129977 | AA46: 0.203356 | AB46: -1.6391599 | AD46: -0.141217 | AE46: 0 | AF46: 0 | AG46: =AD46-AE46 -> -0.141217 | AH46: =AD46-AF46 -> -0.141217 | AI46: -0.41494 | AJ46: =+AD46/AI46-1 -> -0.65966887 | AL46: =+D46+J46+P46+V46+AD46 -> -0.590115 | AM46: =+E46+K46+Q46+W46+AE46 -> -0.12162 | AN46: =+D46+J46+P46+X46+AF46 -> -0.318921 | AO46: =+AL46-AM46 -> -0.468495 | AP46: =+AL46-AN46 -> -0.271194 | AQ46: =+G46+M46+S46+AA46+AI46 -> -1.346266 | AR46: =+AL46/AQ46-1 -> -0.56166538 | AT46: 0 | AU46: -0.318921 | AX46: -3.090994 | AY46: =AT46/AX46-1 -> -1 | AZ46: =AU46/AX46-1 -> -0.89682251 | BA46: =+AV46/AX46-1 -> -1 | BB46: =+AW46/AX46-1 -> -1
B47: Dont coût des cartes SIM | E47: 0 | F47: 0 | G47: 0 | H47: 0 | I47: 0 | M47: 0 | S47: 0 | X47: -42.666667 | Z47: 42.666667 | AA47: 0 | AF47: -42.666667 | AH47: =AD47-AF47 -> 42.666667 | AI47: 0 | AL47: =+D47+J47+P47+V47+AD47 -> 0 | AM47: =+E47+K47+Q47+W47+AE47 -> 0 | AN47: =+D47+J47+P47+X47+AF47 -> -85.333333 | AO47: =+AL47-AM47 -> 0 | AP47: =+AL47-AN47 -> 85.333333 | AQ47: =+G47+M47+S47+AA47+AI47 -> 0 | AR47: =+AL47/AQ47-1 -> #DIV/0! | AU47: -467.67083 | AX47: 0
