Workbook
Name \A: #REF!
Name \A: #REF!
Name \A: #REF!
Name \A: #REF!
Name \e: #N/A
Name \i: #REF!
Name \i: #REF!
Name \p: '[1]Cur Q v Plan'!#REF!
Name \p: '[2]Cur Q v Plan'!#REF!
Name \p: #REF!
Name \p: '[1]Cur Q v Plan'!#REF!
Name \p: '[1]Cur Q v Plan'!#REF!
Name \r: #N/A
Name \t: #N/A
Name _: #REF!
Name _: #REF!
Name _: #N/A
Name _: #REF!
Name _: #REF!
Name _???: #N/A
Name __: #REF!
Name __: #REF!
Name __: #N/A
Name __: #REF!
Name __: #REF!
Name __???: #N/A
Name ___???: #N/A
Name ____???: #N/A
Name _____???: #N/A
Name ______???: #N/A
Name _______???: #N/A
Name ________???: #N/A
Name _________________aaa1: #REF!
Name _________________aaa1: #REF!
Name _________________aaa2: #REF!
Name _________________aaa2: #REF!
Name _________________aaa3: #REF!
Name _________________aaa3: #REF!
Name _________________aaa4: #REF!
Name _________________aaa4: #REF!
Name _________________aaa5: #REF!
Name _________________aaa5: #REF!
Name _________________aaa6: #REF!
Name _________________aaa6: #REF!
Name _________________aaa7: #REF!
Name _________________aaa7: #REF!
Name _________________aaa8: #REF!
Name _________________aaa8: #REF!
Name _________________ess1: #REF!
Name _________________ess1: #REF!
Name _________________FRF4: '[3]FX Rates'!$G$10
Name _________________FRU2003: #REF!
Name _________________FRU2003: #REF!
Name _________________GBP4: '[3]FX Rates'!$G$9
Name _________________pg1: #REF!
Name _________________pg1: #REF!
Name _________________pg2: #REF!
Name _________________pg2: #REF!
Name _________________SC16: #REF!
Name _________________SC16: #REF!

Sheet Canevas au 31 Décembre 2023
F2: TBG Filiales (Réels)
C6: Pour info: - Saisir toutes les périodes à charger, une par colonne - Une période doit s'écrire : mmm/aaaa
B7: N° Indicat | C7: Nom Technique | D7: Axe | E7: Sous axe | F7: Description Indicateur | G7: Filiale | H7: 001.2023 | I7: 002.2023 | J7: 003.2023 | K7: 004.2023 | L7: 005.2023 | M7: 006.2023 | N7: 007.2023 | O7: 008.2023 | P7: 009.2023 | Q7: 010.2023 | R7: 011.2023 | S7: 012.2023 | T7: 11.2023
B8: 34 | C8: ZFIL_A01 | D8: Taux de change | E8: Taux de change | F8: Taux de change P&L | G8: Centrafrique | H8: ='[375]Canevas au 31 Janvier 2023'!T8 -> 0 | I8: ='[376]Canevas au 29 Février 2023'!T8 -> 0 | J8: ='[377]Canevas au 31 Mars 2023'!T8 -> 0 | K8: ='[378]Canevas au 30 Avril 2023'!T8 -> 0 | L8: ='[379]Canevas au 31 Mai 2023'!T8 -> 0 | M8: ='[380]Canevas au 30 Juin 2023'!T8 -> 0 | N8: ='[381]Canevas au 31 Juillet 2023'!T8 -> 0 | O8: ='[382]Canevas au 31 Août 2023'!T8 -> 0 | P8: ='[383]Canevas au 30 Septembre 2023'!T8 -> 0 | Q8: ='[384]Canevas au 31 Octobre 2023'!T8 -> 0
B9: 35 | C9: ZFIL_A02 | D9: Taux de change | E9: Taux de change | F9: Taux de change Bilan | G9: Centrafrique | H9: ='[375]Canevas au 31 Janvier 2023'!T9 -> 0 | I9: ='[376]Canevas au 29 Février 2023'!T9 -> 0 | J9: ='[377]Canevas au 31 Mars 2023'!T9 -> 0 | K9: ='[378]Canevas au 30 Avril 2023'!T9 -> 0 | L9: ='[379]Canevas au 31 Mai 2023'!T9 -> 0 | M9: ='[380]Canevas au 30 Juin 2023'!T9 -> 0 | N9: ='[381]Canevas au 31 Juillet 2023'!T9 -> 0 | O9: ='[382]Canevas au 31 Août 2023'!T9 -> 0 | P9: ='[383]Canevas au 30 Septembre 2023'!T9 -> 0 | Q9: ='[384]Canevas au 31 Octobre 2023'!T9 -> 0
B10: 211 | C10: ZFIL_M03 | D10: Parc Mobile actif | E10: Mobile | F10: Parc Mobile actif (PrP) | G10: Centrafrique | H10: ='[375]Canevas au 31 Janvier 2023'!T10 -> 213951 | I10: ='[376]Canevas au 29 Février 2023'!T10 -> 214351 | J10: ='[377]Canevas au 31 Mars 2023'!T10 -> 214604 | K10: ='[378]Canevas au 30 Avril 2023'!T10 -> 214861 | L10: ='[379]Canevas au 31 Mai 2023'!T10 -> 189213 | M10: ='[380]Canevas au 30 Juin 2023'!T10 -> 194034 | N10: ='[381]Canevas au 31 Juillet 2023'!T10 -> 209553 | O10: ='[382]Canevas au 31 Août 2023'!T10 -> 220447 | P10: ='[383]Canevas au 30 Septembre 2023'!T10 -> 225403 | Q10: ='[384]Canevas au 31 Octobre 2023'!T10 -> 232931 | T10: =+'Indicateurs Parc Mobile '!AA9 -> 248517
B11: 212 | C11: ZFIL_M04 | D11: Parc Mobile actif | E11: Mobile | F11: Parc Mobile actif (PoP) | G11: Centrafrique | H11: ='[375]Canevas au 31 Janvier 2023'!T11 -> 4145 | I11: ='[376]Canevas au 29 Février 2023'!T11 -> 4194 | J11: ='[377]Canevas au 31 Mars 2023'!T11 -> 4246 | K11: ='[378]Canevas au 30 Avril 2023'!T11 -> 4291 | L11: ='[379]Canevas au 31 Mai 2023'!T11 -> 4306 | M11: ='[380]Canevas au 30 Juin 2023'!T11 -> 4320 | N11: ='[381]Canevas au 31 Juillet 2023'!T11 -> 4329 | O11: ='[382]Canevas au 31 Août 2023'!T11 -> 4341 | P11: ='[383]Canevas au 30 Septembre 2023'!T11 -> 4355 | Q11: ='[384]Canevas au 31 Octobre 2023'!T11 -> 4371 | T11: =+'Indicateurs Parc Mobile '!AA13 -> 4397
B12: 357 | C12: ZFIL_M82 | D12: Parc Mobile localisé | E12: Mobile | F12: Parc Mobile localisé | G12: Centrafrique | H12: ='[375]Canevas au 31 Janvier 2023'!T12 -> 130333 | I12: ='[376]Canevas au 29 Février 2023'!T12 -> 132912.33 | J12: ='[377]Canevas au 31 Mars 2023'!T12 -> 131644 | K12: ='[378]Canevas au 30 Avril 2023'!T12 -> 137663.67 | L12: ='[379]Canevas au 31 Mai 2023'!T12 -> 154227 | M12: ='[380]Canevas au 30 Juin 2023'!T12 -> 160284.33 | N12: ='[381]Canevas au 31 Juillet 2023'!T12 -> 175803.33 | O12: ='[382]Canevas au 31 Août 2023'!T12 -> 185482.33 | P12: ='[383]Canevas au 30 Septembre 2023'!T12 -> 186210.67 | Q12: ='[384]Canevas au 31 Octobre 2023'!T12 -> 193837.67 | T12: =+'Indicateurs Parc Mobile '!AA16 -> 205130.33
B13: 213 | C13: ZFIL_M05 | D13: Parc Mobile actif | E13: Mobile | F13: Parc Internet Mobile | G13: Centrafrique | H13: ='[375]Canevas au 31 Janvier 2023'!T13 -> 0 | I13: ='[376]Canevas au 29 Février 2023'!T13 -> 0 | J13: ='[377]Canevas au 31 Mars 2023'!T13 -> 0 | K13: ='[378]Canevas au 30 Avril 2023'!T13 -> 0 | L13: ='[379]Canevas au 31 Mai 2023'!T13 -> 0 | M13: ='[380]Canevas au 30 Juin 2023'!T13 -> 0 | N13: ='[381]Canevas au 31 Juillet 2023'!T13 -> 0 | O13: ='[382]Canevas au 31 Août 2023'!T13 -> 0 | P13: ='[383]Canevas au 30 Septembre 2023'!T13 -> 0 | Q13: ='[384]Canevas au 31 Octobre 2023'!T13 -> 0
B14: 214 | C14: ZFIL_M06 | D14: Parc Mobile Money | E14: Mobile | F14: Parc Mobile Money | G14: Centrafrique | H14: ='[375]Canevas au 31 Janvier 2023'!T14 -> 0 | I14: ='[376]Canevas au 29 Février 2023'!T14 -> 0 | J14: ='[377]Canevas au 31 Mars 2023'!T14 -> 0 | K14: ='[378]Canevas au 30 Avril 2023'!T14 -> 0 | L14: ='[379]Canevas au 31 Mai 2023'!T14 -> 0 | M14: ='[380]Canevas au 30 Juin 2023'!T14 -> 0 | N14: ='[381]Canevas au 31 Juillet 2023'!T14 -> 0 | O14: ='[382]Canevas au 31 Août 2023'!T14 -> 0 | P14: ='[383]Canevas au 30 Septembre 2023'!T14 -> 0 | Q14: ='[384]Canevas au 31 Octobre 2023'!T14 -> 0
B15: 227 | C15: ZFIL_M11 | D15: Ventes brutes Mobile | E15: Mobile | F15: Mobile (PrP) | G15: Centrafrique | H15: ='[375]Canevas au 31 Janvier 2023'!T15 -> 11228 | I15: ='[376]Canevas au 29 Février 2023'!T15 -> 11204 | J15: ='[377]Canevas au 31 Mars 2023'!T15 -> 11284 | K15: ='[378]Canevas au 30 Avril 2023'!T15 -> 14010 | L15: ='[379]Canevas au 31 Mai 2023'!T15 -> 14510 | M15: ='[380]Canevas au 30 Juin 2023'!T15 -> 27308 | N15: ='[381]Canevas au 31 Juillet 2023'!T15 -> 30781 | O15: ='[382]Canevas au 31 Août 2023'!T15 -> 31042 | P15: ='[383]Canevas au 30 Septembre 2023'!T15 -> 26419.75 | Q15: ='[384]Canevas au 31 Octobre 2023'!T15 -> 37423 | T15: =+'Indicateurs Parc Mobile '!O20 -> 31553
B16: 228 | C16: ZFIL_M12 | D16: Ventes brutes Mobile | E16: Mobile | F16: Mobile (PoP) | G16: Centrafrique | H16: ='[375]Canevas au 31 Janvier 2023'!T16 -> 82 | I16: ='[376]Canevas au 29 Février 2023'!T16 -> 80 | J16: ='[377]Canevas au 31 Mars 2023'!T16 -> 92 | K16: ='[378]Canevas au 30 Avril 2023'!T16 -> 94 | L16: ='[379]Canevas au 31 Mai 2023'!T16 -> 134 | M16: ='[380]Canevas au 30 Juin 2023'!T16 -> 137 | N16: ='[381]Canevas au 31 Juillet 2023'!T16 -> 127 | O16: ='[382]Canevas au 31 Août 2023'!T16 -> 124 | P16: ='[383]Canevas au 30 Septembre 2023'!T16 -> 124 | Q16: ='[384]Canevas au 31 Octobre 2023'!T16 -> 132 | T16: =+'Indicateurs Parc Mobile '!O21 -> 125
B17: 230 | C17: ZFIL_M13 | D17: Résiliations Mobile yc flux d'inactivité | E17: Mobile | F17: Mobile (PrP) | G17: Centrafrique | H17: ='[375]Canevas au 31 Janvier 2023'!T17 -> 10808 | I17: ='[376]Canevas au 29 Février 2023'!T17 -> 10813 | J17: ='[377]Canevas au 31 Mars 2023'!T17 -> 11031 | K17: ='[378]Canevas au 30 Avril 2023'!T17 -> 13756 | L17: ='[379]Canevas au 31 Mai 2023'!T17 -> 40158 | M17: ='[380]Canevas au 30 Juin 2023'!T17 -> 22487 | N17: ='[381]Canevas au 31 Juillet 2023'!T17 -> 15262 | O17: ='[382]Canevas au 31 Août 2023'!T17 -> 20148 | P17: ='[383]Canevas au 30 Septembre 2023'!T17 -> 21463.75 | Q17: ='[384]Canevas au 31 Octobre 2023'!T17 -> 29895 | T17: =+'Indicateurs Parc Mobile '!O25 -> 21389
B18: 231 | C18: ZFIL_M14 | D18: Résiliations Mobile yc flux d'inactivité | E18: Mobile | F18: Mobile (PoP) | G18: Centrafrique | H18: ='[375]Canevas au 31 Janvier 2023'!T18 -> 22 | I18: ='[376]Canevas au 29 Février 2023'!T18 -> 22 | J18: ='[377]Canevas au 31 Mars 2023'!T18 -> 40 | K18: ='[378]Canevas au 30 Avril 2023'!T18 -> 46 | L18: ='[379]Canevas au 31 Mai 2023'!T18 -> 119 | M18: ='[380]Canevas au 30 Juin 2023'!T18 -> 123 | N18: ='[381]Canevas au 31 Juillet 2023'!T18 -> 118 | O18: ='[382]Canevas au 31 Août 2023'!T18 -> 112 | P18: ='[383]Canevas au 30 Septembre 2023'!T18 -> 110 | Q18: ='[384]Canevas au 31 Octobre 2023'!T18 -> 116 | T18: =+'Indicateurs Parc Mobile '!O26 -> 112
B19: 275 | C19: ZFIL_M16 | D19: Trafic Mobile sortant PrP | E19: Mobile | F19: Trafic sortant PrP vers le fixe | G19: Centrafrique | H19: ='[375]Canevas au 31 Janvier 2023'!T19 -> 1848 | I19: ='[376]Canevas au 29 Février 2023'!T19 -> 216 | J19: ='[377]Canevas au 31 Mars 2023'!T19 -> 407.42857 | K19: ='[378]Canevas au 30 Avril 2023'!T19 -> 407.42857 | L19: ='[379]Canevas au 31 Mai 2023'!T19 -> 511 | M19: ='[380]Canevas au 30 Juin 2023'!T19 -> 1284 | N19: ='[381]Canevas au 31 Juillet 2023'!T19 -> 2448 | O19: ='[382]Canevas au 31 Août 2023'!T19 -> 168 | P19: ='[383]Canevas au 30 Septembre 2023'!T19 -> 100732 | Q19: ='[384]Canevas au 31 Octobre 2023'!T19 -> 100732 | T19: =+'Marge Mobile'!O24*10^6 -> -200000
B20: 276 | C20: ZFIL_M17 | D20: Trafic Mobile sortant PrP | E20: Mobile | F20: Trafic sortant PrP vers l'international | G20: Centrafrique | H20: ='[375]Canevas au 31 Janvier 2023'!T20 -> 159767 | I20: ='[376]Canevas au 29 Février 2023'!T20 -> 146998 | J20: ='[377]Canevas au 31 Mars 2023'!T20 -> 129397.35 | K20: ='[378]Canevas au 30 Avril 2023'!T20 -> 160369 | L20: ='[379]Canevas au 31 Mai 2023'!T20 -> 178535 | M20: ='[380]Canevas au 30 Juin 2023'!T20 -> 163107 | N20: ='[381]Canevas au 31 Juillet 2023'!T20 -> 161155 | O20: ='[382]Canevas au 31 Août 2023'!T20 -> 155166 | P20: ='[383]Canevas au 30 Septembre 2023'!T20 -> 158546 | Q20: ='[384]Canevas au 31 Octobre 2023'!T20 -> 129610 | T20: =+'Trafic '!O16*10^6 -> 773974.82
B21: 277 | C21: ZFIL_M18 | D21: Trafic Mobile sortant PrP | E21: Mobile | F21: Trafic sortant PrP On net | G21: Centrafrique | H21: ='[375]Canevas au 31 Janvier 2023'!T21 -> 2912000 | I21: ='[376]Canevas au 29 Février 2023'!T21 -> 2892000 | J21: ='[377]Canevas au 31 Mars 2023'!T21 -> 2817000 | K21: ='[378]Canevas au 30 Avril 2023'!T21 -> 2891000 | L21: ='[379]Canevas au 31 Mai 2023'!T21 -> 2982000 | M21: ='[380]Canevas au 30 Juin 2023'!T21 -> 3000000 | N21: ='[381]Canevas au 31 Juillet 2023'!T21 -> 3100000 | O21: ='[382]Canevas au 31 Août 2023'!T21 -> 3369700 | P21: ='[383]Canevas au 30 Septembre 2023'!T21 -> 3538185 | Q21: ='[384]Canevas au 31 Octobre 2023'!T21 -> 3608948.7 | T21: =+'Trafic '!O14*10^6 -> 3645038.2
B22: 278 | C22: ZFIL_M19 | D22: Trafic Mobile sortant PrP | E22: Mobile | F22: Trafic sortant PrP vers Telecel | G22: Centrafrique | H22: ='[375]Canevas au 31 Janvier 2023'!T22 -> 113837 | I22: ='[376]Canevas au 29 Février 2023'!T22 -> 133961 | J22: ='[377]Canevas au 31 Mars 2023'!T22 -> 179795.1 | K22: ='[378]Canevas au 30 Avril 2023'!T22 -> 175306.25 | L22: ='[379]Canevas au 31 Mai 2023'!T22 -> 177261.7 | M22: ='[380]Canevas au 30 Juin 2023'!T22 -> 315123 | N22: ='[381]Canevas au 31 Juillet 2023'!T22 -> 337902 | O22: ='[382]Canevas au 31 Août 2023'!T22 -> 392785 | P22: ='[383]Canevas au 30 Septembre 2023'!T22 -> 414337 | Q22: ='[384]Canevas au 31 Octobre 2023'!T22 -> 1581109 | T22: =+'Marge Mobile'!O13*10^6 -> 769969
B23: 279 | C23: ZFIL_M20 | D23: Trafic Mobile sortant PrP | E23: Mobile | F23: Trafic sortant PrP vers Orange | G23: Centrafrique | H23: ='[375]Canevas au 31 Janvier 2023'!T23 -> 135189 | I23: ='[376]Canevas au 29 Février 2023'!T23 -> 184954 | J23: ='[377]Canevas au 31 Mars 2023'!T23 -> 256845.33 | K23: ='[378]Canevas au 30 Avril 2023'!T23 -> 275660 | L23: ='[379]Canevas au 31 Mai 2023'!T23 -> 266252.7 | M23: ='[380]Canevas au 30 Juin 2023'!T23 -> 311753 | N23: ='[381]Canevas au 31 Juillet 2023'!T23 -> 366011 | O23: ='[382]Canevas au 31 Août 2023'!T23 -> 406753 | P23: ='[383]Canevas au 30 Septembre 2023'!T23 -> 438290 | Q23: ='[384]Canevas au 31 Octobre 2023'!T23 -> 1913951 | T23: =+'Marge Mobile'!O16*10^6 -> 1539982
B24: 280 | C24: ZFIL_M21 | D24: Trafic Mobile sortant PrP | E24: Mobile | F24: Trafic sortant PrP vers AZUR | G24: Centrafrique | H24: ='[375]Canevas au 31 Janvier 2023'!T24 -> 0 | I24: ='[376]Canevas au 29 Février 2023'!T24 -> 0 | J24: ='[377]Canevas au 31 Mars 2023'!T24 -> 0 | K24: ='[378]Canevas au 30 Avril 2023'!T24 -> 0 | L24: ='[379]Canevas au 31 Mai 2023'!T24 -> 0 | M24: ='[380]Canevas au 30 Juin 2023'!T24 -> 0 | N24: ='[381]Canevas au 31 Juillet 2023'!T24 -> 0 | O24: ='[382]Canevas au 31 Août 2023'!T24 -> 0 | P24: ='[383]Canevas au 30 Septembre 2023'!T24 -> 0 | Q24: ='[384]Canevas au 31 Octobre 2023'!T24 -> 0 | T24: =+'Marge Mobile'!O19*10^6 -> 0
B25: 292 | C25: ZFIL_M32 | D25: Trafic Mobile sortant PoP | E25: Mobile | F25: Trafic sortant PoP vers le fixe | G25: Centrafrique | H25: ='[375]Canevas au 31 Janvier 2023'!T25 -> 0 | I25: ='[376]Canevas au 29 Février 2023'!T25 -> 0 | J25: ='[377]Canevas au 31 Mars 2023'!T25 -> 0 | K25: ='[378]Canevas au 30 Avril 2023'!T25 -> 0 | L25: ='[379]Canevas au 31 Mai 2023'!T25 -> 0 | M25: ='[380]Canevas au 30 Juin 2023'!T25 -> 0 | N25: ='[381]Canevas au 31 Juillet 2023'!T25 -> 0 | O25: ='[382]Canevas au 31 Août 2023'!T25 -> 0 | P25: ='[383]Canevas au 30 Septembre 2023'!T25 -> 0 | Q25: ='[384]Canevas au 31 Octobre 2023'!T25 -> 0
B26: 293 | C26: ZFIL_M33 | D26: Trafic Mobile sortant PoP | E26: Mobile | F26: Trafic sortant PoP vers l'international | G26: Centrafrique | H26: ='[375]Canevas au 31 Janvier 2023'!T26 -> 0 | I26: ='[376]Canevas au 29 Février 2023'!T26 -> 0 | J26: ='[377]Canevas au 31 Mars 2023'!T26 -> 0 | K26: ='[378]Canevas au 30 Avril 2023'!T26 -> 0 | L26: ='[379]Canevas au 31 Mai 2023'!T26 -> 0 | M26: ='[380]Canevas au 30 Juin 2023'!T26 -> 0 | N26: ='[381]Canevas au 31 Juillet 2023'!T26 -> 0 | O26: ='[382]Canevas au 31 Août 2023'!T26 -> 0 | P26: ='[383]Canevas au 30 Septembre 2023'!T26 -> 0 | Q26: ='[384]Canevas au 31 Octobre 2023'!T26 -> 0
B27: 294 | C27: ZFIL_M34 | D27: Trafic Mobile sortant PoP | E27: Mobile | F27: Trafic sortant PoP On net | G27: Centrafrique | H27: ='[375]Canevas au 31 Janvier 2023'!T27 -> 0 | I27: ='[376]Canevas au 29 Février 2023'!T27 -> 0 | J27: ='[377]Canevas au 31 Mars 2023'!T27 -> 0 | K27: ='[378]Canevas au 30 Avril 2023'!T27 -> 0 | L27: ='[379]Canevas au 31 Mai 2023'!T27 -> 0 | M27: ='[380]Canevas au 30 Juin 2023'!T27 -> 0 | N27: ='[381]Canevas au 31 Juillet 2023'!T27 -> 0 | O27: ='[382]Canevas au 31 Août 2023'!T27 -> 0 | P27: ='[383]Canevas au 30 Septembre 2023'!T27 -> 0 | Q27: ='[384]Canevas au 31 Octobre 2023'!T27 -> 0
B28: 295 | C28: ZFIL_M35 | D28: Trafic Mobile sortant PoP | E28: Mobile | F28: Trafic sortant PoP vers Telecel | G28: Centrafrique | H28: ='[375]Canevas au 31 Janvier 2023'!T28 -> 0 | I28: ='[376]Canevas au 29 Février 2023'!T28 -> 0 | J28: ='[377]Canevas au 31 Mars 2023'!T28 -> 0 | K28: ='[378]Canevas au 30 Avril 2023'!T28 -> 0 | L28: ='[379]Canevas au 31 Mai 2023'!T28 -> 0 | M28: ='[380]Canevas au 30 Juin 2023'!T28 -> 0 | N28: ='[381]Canevas au 31 Juillet 2023'!T28 -> 0 | O28: ='[382]Canevas au 31 Août 2023'!T28 -> 0 | P28: ='[383]Canevas au 30 Septembre 2023'!T28 -> 0 | Q28: ='[384]Canevas au 31 Octobre 2023'!T28 -> 0
B29: 296 | C29: ZFIL_M36 | D29: Trafic Mobile sortant PoP | E29: Mobile | F29: Trafic sortant PoP vers Orange | G29: Centrafrique | H29: ='[375]Canevas au 31 Janvier 2023'!T29 -> 0 | I29: ='[376]Canevas au 29 Février 2023'!T29 -> 0 | J29: ='[377]Canevas au 31 Mars 2023'!T29 -> 0 | K29: ='[378]Canevas au 30 Avril 2023'!T29 -> 0 | L29: ='[379]Canevas au 31 Mai 2023'!T29 -> 0 | M29: ='[380]Canevas au 30 Juin 2023'!T29 -> 0 | N29: ='[381]Canevas au 31 Juillet 2023'!T29 -> 0 | O29: ='[382]Canevas au 31 Août 2023'!T29 -> 0 | P29: ='[383]Canevas au 30 Septembre 2023'!T29 -> 0 | Q29: ='[384]Canevas au 31 Octobre 2023'!T29 -> 0
B30: 297 | C30: ZFIL_M37 | D30: Trafic Mobile sortant PoP | E30: Mobile | F30: Trafic sortant PoP vers AZUR | G30: Centrafrique | H30: ='[375]Canevas au 31 Janvier 2023'!T30 -> 0 | I30: ='[376]Canevas au 29 Février 2023'!T30 -> 0 | J30: ='[377]Canevas au 31 Mars 2023'!T30 -> 0 | K30: ='[378]Canevas au 30 Avril 2023'!T30 -> 0 | L30: ='[379]Canevas au 31 Mai 2023'!T30 -> 0 | M30: ='[380]Canevas au 30 Juin 2023'!T30 -> 0 | N30: ='[381]Canevas au 31 Juillet 2023'!T30 -> 0 | O30: ='[382]Canevas au 31 Août 2023'!T30 -> 0 | P30: ='[383]Canevas au 30 Septembre 2023'!T30 -> 0 | Q30: ='[384]Canevas au 31 Octobre 2023'!T30 -> 0
B31: 311 | C31: ZFIL_M48 | D31: Trafic Mobile entrant PrP | E31: Mobile | F31: Trafic entrant PrP depuis le fixe | G31: Centrafrique | H31: ='[375]Canevas au 31 Janvier 2023'!T31 -> 483 | I31: ='[376]Canevas au 29 Février 2023'!T31 -> 448 | J31: ='[377]Canevas au 31 Mars 2023'!T31 -> 456.14286 | K31: ='[378]Canevas au 30 Avril 2023'!T31 -> 456.14286 | L31: ='[379]Canevas au 31 Mai 2023'!T31 -> 442 | M31: ='[380]Canevas au 30 Juin 2023'!T31 -> 254 | N31: ='[381]Canevas au 31 Juillet 2023'!T31 -> 123 | O31: ='[382]Canevas au 31 Août 2023'!T31 -> 68 | P31: ='[383]Canevas au 30 Septembre 2023'!T31 -> 81 | Q31: ='[384]Canevas au 31 Octobre 2023'!T31 -> 29 | T31: =+'Trafic '!O27*10^6 -> 0
B32: 312 | C32: ZFIL_M49 | D32: Trafic Mobile entrant PrP | E32: Mobile | F32: Trafic entrant PrP depuis l'international | G32: Centrafrique | H32: ='[375]Canevas au 31 Janvier 2023'!T32 -> 31616 | I32: ='[376]Canevas au 29 Février 2023'!T32 -> 30975 | J32: ='[377]Canevas au 31 Mars 2023'!T32 -> 29897.667 | K32: ='[378]Canevas au 30 Avril 2023'!T32 -> 33518 | L32: ='[379]Canevas au 31 Mai 2023'!T32 -> 41531.3 | M32: ='[380]Canevas au 30 Juin 2023'!T32 -> 33861 | N32: ='[381]Canevas au 31 Juillet 2023'!T32 -> 34523 | O32: ='[382]Canevas au 31 Août 2023'!T32 -> 35027 | P32: ='[383]Canevas au 30 Septembre 2023'!T32 -> 35189 | Q32: ='[384]Canevas au 31 Octobre 2023'!T32 -> 60217 | T32: =+'Trafic '!O28*10^6 -> 35968
B33: 313 | C33: ZFIL_M50 | D33: Trafic Mobile entrant PrP | E33: Mobile | F33: Trafic entrant PrP depuis Telecel | G33: Centrafrique | H33: ='[375]Canevas au 31 Janvier 2023'!T33 -> 31616 | I33: ='[376]Canevas au 29 Février 2023'!T33 -> 30502 | J33: ='[377]Canevas au 31 Mars 2023'!T33 -> 31086.667 | K33: ='[378]Canevas au 30 Avril 2023'!T33 -> 39846.25 | L33: ='[379]Canevas au 31 Mai 2023'!T33 -> 38936 | M33: ='[380]Canevas au 30 Juin 2023'!T33 -> 50265 | N33: ='[381]Canevas au 31 Juillet 2023'!T33 -> 55786 | O33: ='[382]Canevas au 31 Août 2023'!T33 -> 62157 | P33: ='[383]Canevas au 30 Septembre 2023'!T33 -> 63098 | Q33: ='[384]Canevas au 31 Octobre 2023'!T33 -> 50060 | T33: =+'Trafic '!O24*10^6 -> 195398
B34: 314 | C34: ZFIL_M51 | D34: Trafic Mobile entrant PrP | E34: Mobile | F34: Trafic entrant PrP depuis Orange | G34: Centrafrique | H34: ='[375]Canevas au 31 Janvier 2023'!T34 -> 45095 | I34: ='[376]Canevas au 29 Février 2023'!T34 -> 49776 | J34: ='[377]Canevas au 31 Mars 2023'!T34 -> 59850.667 | K34: ='[378]Canevas au 30 Avril 2023'!T34 -> 60093.75 | L34: ='[379]Canevas au 31 Mai 2023'!T34 -> 59972 | M34: ='[380]Canevas au 30 Juin 2023'!T34 -> 65011 | N34: ='[381]Canevas au 31 Juillet 2023'!T34 -> 69045 | O34: ='[382]Canevas au 31 Août 2023'!T34 -> 74321 | P34: ='[383]Canevas au 30 Septembre 2023'!T34 -> 76612 | Q34: ='[384]Canevas au 31 Octobre 2023'!T34 -> 628047 | T34: =+'Trafic '!O25*10^6 -> 156385
B35: 315 | C35: ZFIL_M52 | D35: Trafic Mobile entrant PrP | E35: Mobile | F35: Trafic entrant PrP depuis AZUR | G35: Centrafrique | H35: ='[375]Canevas au 31 Janvier 2023'!T35 -> 0 | I35: ='[376]Canevas au 29 Février 2023'!T35 -> 0 | J35: ='[377]Canevas au 31 Mars 2023'!T35 -> 0 | K35: ='[378]Canevas au 30 Avril 2023'!T35 -> 0 | L35: ='[379]Canevas au 31 Mai 2023'!T35 -> 0 | M35: ='[380]Canevas au 30 Juin 2023'!T35 -> 0 | N35: ='[381]Canevas au 31 Juillet 2023'!T35 -> 0 | O35: ='[382]Canevas au 31 Août 2023'!T35 -> 0 | P35: ='[383]Canevas au 30 Septembre 2023'!T35 -> 0 | Q35: ='[384]Canevas au 31 Octobre 2023'!T35 -> 0 | T35: =+'Trafic '!O26*10^6 -> 0
B36: 316 | C36: ZFIL_M53 | D36: Trafic Mobile entrant PrP | E36: Mobile | F36: Transit Entrant PrP International via les concurrents | G36: Centrafrique | H36: ='[375]Canevas au 31 Janvier 2023'!T36 -> 0 | I36: ='[376]Canevas au 29 Février 2023'!T36 -> 0 | J36: ='[377]Canevas au 31 Mars 2023'!T36 -> 0 | K36: ='[378]Canevas au 30 Avril 2023'!T36 -> 0 | L36: ='[379]Canevas au 31 Mai 2023'!T36 -> 0 | M36: ='[380]Canevas au 30 Juin 2023'!T36 -> 0 | N36: ='[381]Canevas au 31 Juillet 2023'!T36 -> 0 | O36: ='[382]Canevas au 31 Août 2023'!T36 -> 0 | P36: ='[383]Canevas au 30 Septembre 2023'!T36 -> 0 | Q36: ='[384]Canevas au 31 Octobre 2023'!T36 -> 0
B37: 317 | C37: ZFIL_M54 | D37: Trafic Mobile entrant PrP | E37: Mobile | F37: Transit Entrant PrP International vers les concurrents | G37: Centrafrique | H37: ='[375]Canevas au 31 Janvier 2023'!T37 -> 0 | I37: ='[376]Canevas au 29 Février 2023'!T37 -> 0 | J37: ='[377]Canevas au 31 Mars 2023'!T37 -> 0 | K37: ='[378]Canevas au 30 Avril 2023'!T37 -> 0 | L37: ='[379]Canevas au 31 Mai 2023'!T37 -> 0 | M37: ='[380]Canevas au 30 Juin 2023'!T37 -> 0 | N37: ='[381]Canevas au 31 Juillet 2023'!T37 -> 0 | O37: ='[382]Canevas au 31 Août 2023'!T37 -> 0 | P37: ='[383]Canevas au 30 Septembre 2023'!T37 -> 0 | Q37: ='[384]Canevas au 31 Octobre 2023'!T37 -> 0
B38: 327 | C38: ZFIL_M62 | D38: Trafic Mobile entrant PoP | E38: Mobile | F38: Trafic entrant PoP depuis le fixe | G38: Centrafrique | H38: ='[375]Canevas au 31 Janvier 2023'!T38 -> 0 | I38: ='[376]Canevas au 29 Février 2023'!T38 -> 0 | J38: ='[377]Canevas au 31 Mars 2023'!T38 -> 0 | K38: ='[378]Canevas au 30 Avril 2023'!T38 -> 0 | L38: ='[379]Canevas au 31 Mai 2023'!T38 -> 0 | M38: ='[380]Canevas au 30 Juin 2023'!T38 -> 0 | N38: ='[381]Canevas au 31 Juillet 2023'!T38 -> 0 | O38: ='[382]Canevas au 31 Août 2023'!T38 -> 0 | P38: ='[383]Canevas au 30 Septembre 2023'!T38 -> 0 | Q38: ='[384]Canevas au 31 Octobre 2023'!T38 -> 0
B39: 328 | C39: ZFIL_M63 | D39: Trafic Mobile entrant PoP | E39: Mobile | F39: Trafic entrant PoP depuis l'international | G39: Centrafrique | H39: ='[375]Canevas au 31 Janvier 2023'!T39 -> 0 | I39: ='[376]Canevas au 29 Février 2023'!T39 -> 0 | J39: ='[377]Canevas au 31 Mars 2023'!T39 -> 0 | K39: ='[378]Canevas au 30 Avril 2023'!T39 -> 0 | L39: ='[379]Canevas au 31 Mai 2023'!T39 -> 0 | M39: ='[380]Canevas au 30 Juin 2023'!T39 -> 0 | N39: ='[381]Canevas au 31 Juillet 2023'!T39 -> 0 | O39: ='[382]Canevas au 31 Août 2023'!T39 -> 0 | P39: ='[383]Canevas au 30 Septembre 2023'!T39 -> 0 | Q39: ='[384]Canevas au 31 Octobre 2023'!T39 -> 0
B40: 329 | C40: ZFIL_M64 | D40: Trafic Mobile entrant PoP | E40: Mobile | F40: Trafic entrant PoP depuis Telecel | G40: Centrafrique | H40: ='[375]Canevas au 31 Janvier 2023'!T40 -> 0 | I40: ='[376]Canevas au 29 Février 2023'!T40 -> 0 | J40: ='[377]Canevas au 31 Mars 2023'!T40 -> 0 | K40: ='[378]Canevas au 30 Avril 2023'!T40 -> 0 | L40: ='[379]Canevas au 31 Mai 2023'!T40 -> 0 | M40: ='[380]Canevas au 30 Juin 2023'!T40 -> 0 | N40: ='[381]Canevas au 31 Juillet 2023'!T40 -> 0 | O40: ='[382]Canevas au 31 Août 2023'!T40 -> 0 | P40: ='[383]Canevas au 30 Septembre 2023'!T40 -> 0 | Q40: ='[384]Canevas au 31 Octobre 2023'!T40 -> 0
B41: 330 | C41: ZFIL_M65 | D41: Trafic Mobile entrant PoP | E41: Mobile | F41: Trafic entrant PoP depuis Orange | G41: Centrafrique | H41: ='[375]Canevas au 31 Janvier 2023'!T41 -> 0 | I41: ='[376]Canevas au 29 Février 2023'!T41 -> 0 | J41: ='[377]Canevas au 31 Mars 2023'!T41 -> 0 | K41: ='[378]Canevas au 30 Avril 2023'!T41 -> 0 | L41: ='[379]Canevas au 31 Mai 2023'!T41 -> 0 | M41: ='[380]Canevas au 30 Juin 2023'!T41 -> 0 | N41: ='[381]Canevas au 31 Juillet 2023'!T41 -> 0 | O41: ='[382]Canevas au 31 Août 2023'!T41 -> 0 | P41: ='[383]Canevas au 30 Septembre 2023'!T41 -> 0 | Q41: ='[384]Canevas au 31 Octobre 2023'!T41 -> 0
B42: 331 | C42: ZFIL_M66 | D42: Trafic Mobile entrant PoP | E42: Mobile | F42: Trafic entrant PoP depuis AZUR | G42: Centrafrique | H42: ='[375]Canevas au 31 Janvier 2023'!T42 -> 0 | I42: ='[376]Canevas au 29 Février 2023'!T42 -> 0 | J42: ='[377]Canevas au 31 Mars 2023'!T42 -> 0 | K42: ='[378]Canevas au 30 Avril 2023'!T42 -> 0 | L42: ='[379]Canevas au 31 Mai 2023'!T42 -> 0 | M42: ='[380]Canevas au 30 Juin 2023'!T42 -> 0 | N42: ='[381]Canevas au 31 Juillet 2023'!T42 -> 0 | O42: ='[382]Canevas au 31 Août 2023'!T42 -> 0 | P42: ='[383]Canevas au 30 Septembre 2023'!T42 -> 0 | Q42: ='[384]Canevas au 31 Octobre 2023'!T42 -> 0
B43: 332 | C43: ZFIL_M67 | D43: Trafic Mobile entrant PoP | E43: Mobile | F43: Transit Entrant PoP International via les concurrents | G43: Centrafrique | H43: ='[375]Canevas au 31 Janvier 2023'!T43 -> 0 | I43: ='[376]Canevas au 29 Février 2023'!T43 -> 0 | J43: ='[377]Canevas au 31 Mars 2023'!T43 -> 0 | K43: ='[378]Canevas au 30 Avril 2023'!T43 -> 0 | L43: ='[379]Canevas au 31 Mai 2023'!T43 -> 0 | M43: ='[380]Canevas au 30 Juin 2023'!T43 -> 0 | N43: ='[381]Canevas au 31 Juillet 2023'!T43 -> 0 | O43: ='[382]Canevas au 31 Août 2023'!T43 -> 0 | P43: ='[383]Canevas au 30 Septembre 2023'!T43 -> 0 | Q43: ='[384]Canevas au 31 Octobre 2023'!T43 -> 0
B44: 333 | C44: ZFIL_M68 | D44: Trafic Mobile entrant PoP | E44: Mobile | F44: Transit Entrant PoP International vers les concurrents | G44: Centrafrique | H44: ='[375]Canevas au 31 Janvier 2023'!T44 -> 0 | I44: ='[376]Canevas au 29 Février 2023'!T44 -> 0 | J44: ='[377]Canevas au 31 Mars 2023'!T44 -> 0 | K44: ='[378]Canevas au 30 Avril 2023'!T44 -> 0 | L44: ='[379]Canevas au 31 Mai 2023'!T44 -> 0 | M44: ='[380]Canevas au 30 Juin 2023'!T44 -> 0 | N44: ='[381]Canevas au 31 Juillet 2023'!T44 -> 0 | O44: ='[382]Canevas au 31 Août 2023'!T44 -> 0 | P44: ='[383]Canevas au 30 Septembre 2023'!T44 -> 0 | Q44: ='[384]Canevas au 31 Octobre 2023'!T44 -> 0
B45: 407 | C45: ZFIL_M90 | D45: CA Sortant | E45: Mobile | F45: Internet Mobile | G45: Centrafrique | H45: ='[375]Canevas au 31 Janvier 2023'!T45 -> 0 | I45: ='[376]Canevas au 29 Février 2023'!T45 -> 0 | J45: ='[377]Canevas au 31 Mars 2023'!T45 -> 0 | K45: ='[378]Canevas au 30 Avril 2023'!T45 -> 0 | L45: ='[379]Canevas au 31 Mai 2023'!T45 -> 0 | M45: ='[380]Canevas au 30 Juin 2023'!T45 -> 0 | N45: ='[381]Canevas au 31 Juillet 2023'!T45 -> 0 | O45: ='[382]Canevas au 31 Août 2023'!T45 -> 0 | P45: ='[383]Canevas au 30 Septembre 2023'!T45 -> 0 | Q45: ='[384]Canevas au 31 Octobre 2023'!T45 -> 0
B46: 413 | C46: ZFIL_M96 | D46: CA Sortant | E46: Mobile | F46: CA Sortant prépayé | G46: Centrafrique | H46: ='[375]Canevas au 31 Janvier 2023'!T46 -> 2.5976557e+08 | I46: ='[376]Canevas au 29 Février 2023'!T46 -> 2.5895645e+08 | J46: ='[377]Canevas au 31 Mars 2023'!T46 -> 2.686211e+08 | K46: ='[378]Canevas au 30 Avril 2023'!T46 -> 2.7172797e+08 | L46: ='[379]Canevas au 31 Mai 2023'!T46 -> 2.9591972e+08 | M46: ='[380]Canevas au 30 Juin 2023'!T46 -> 2.8232171e+08 | N46: ='[381]Canevas au 31 Juillet 2023'!T46 -> 3.0632299e+08 | O46: ='[382]Canevas au 31 Août 2023'!T46 -> 3.2436538e+08 | P46: ='[383]Canevas au 30 Septembre 2023'!T46 -> 3.1890285e+08 | Q46: ='[384]Canevas au 31 Octobre 2023'!T46 -> 3.4102971e+08 | T46: =+'CA Mobile'!P19*10^6 -> 3.2702098e+08
B47: 415 | C47: ZFIL_M97 | D47: CA Sortant | E47: Mobile | F47: CA Sortant postpayé | G47: Centrafrique | H47: ='[375]Canevas au 31 Janvier 2023'!T47 -> 29961157 | I47: ='[376]Canevas au 29 Février 2023'!T47 -> 26625745 | J47: ='[377]Canevas au 31 Mars 2023'!T47 -> 32800000 | K47: ='[378]Canevas au 30 Avril 2023'!T47 -> 30478000 | L47: ='[379]Canevas au 31 Mai 2023'!T47 -> 28973010 | M47: ='[380]Canevas au 30 Juin 2023'!T47 -> 26600109 | N47: ='[381]Canevas au 31 Juillet 2023'!T47 -> 26486463 | O47: ='[382]Canevas au 31 Août 2023'!T47 -> 27000000 | P47: ='[383]Canevas au 30 Septembre 2023'!T47 -> 26620383 | Q47: ='[384]Canevas au 31 Octobre 2023'!T47 -> 30462641 | T47: =+'CA Mobile'!P27*10^6 -> 25063480
B48: 421 | C48: ZFIL_M102 | D48: CA Entrant | E48: Mobile | F48: Depuis Telecel | G48: Centrafrique | H48: ='[375]Canevas au 31 Janvier 2023'!T48 -> 863345 | I48: ='[376]Canevas au 29 Février 2023'!T48 -> 366024 | J48: ='[377]Canevas au 31 Mars 2023'!T48 -> -43680 | K48: ='[378]Canevas au 30 Avril 2023'!T48 -> 478155 | L48: ='[379]Canevas au 31 Mai 2023'!T48 -> 467238 | M48: ='[380]Canevas au 30 Juin 2023'!T48 -> 603180 | N48: ='[381]Canevas au 31 Juillet 2023'!T48 -> 603180 | O48: ='[382]Canevas au 31 Août 2023'!T48 -> 603180 | P48: ='[383]Canevas au 30 Septembre 2023'!T48 -> 898776 | Q48: ='[384]Canevas au 31 Octobre 2023'!T48 -> 640720 | T48: =+'CA Mobile'!P34*10^6 -> 2344776
B49: 422 | C49: ZFIL_M103 | D49: CA Entrant | E49: Mobile | F49: Depuis Orange | G49: Centrafrique | H49: ='[375]Canevas au 31 Janvier 2023'!T49 -> 1578325 | I49: ='[376]Canevas au 29 Février 2023'!T49 -> 0 | J49: ='[377]Canevas au 31 Mars 2023'!T49 -> 318208 | K49: ='[378]Canevas au 30 Avril 2023'!T49 -> 721125 | L49: ='[379]Canevas au 31 Mai 2023'!T49 -> 719667 | M49: ='[380]Canevas au 30 Juin 2023'!T49 -> 780132 | N49: ='[381]Canevas au 31 Juillet 2023'!T49 -> 828540 | O49: ='[382]Canevas au 31 Août 2023'!T49 -> 828540 | P49: ='[383]Canevas au 30 Septembre 2023'!T49 -> 942744 | Q49: ='[384]Canevas au 31 Octobre 2023'!T49 -> 2066564 | T49: =+'CA Mobile'!P35*10^6 -> 1876620
B50: 423 | C50: ZFIL_M104 | D50: CA Entrant | E50: Mobile | F50: Depuis AZUR | G50: Centrafrique | H50: ='[375]Canevas au 31 Janvier 2023'!T50 -> 0 | I50: ='[376]Canevas au 29 Février 2023'!T50 -> 0 | J50: ='[377]Canevas au 31 Mars 2023'!T50 -> 0 | K50: ='[378]Canevas au 30 Avril 2023'!T50 -> 0 | L50: ='[379]Canevas au 31 Mai 2023'!T50 -> 0 | M50: ='[380]Canevas au 30 Juin 2023'!T50 -> 0 | N50: ='[381]Canevas au 31 Juillet 2023'!T50 -> 0 | O50: ='[382]Canevas au 31 Août 2023'!T50 -> 0 | P50: ='[383]Canevas au 30 Septembre 2023'!T50 -> 0 | Q50: ='[384]Canevas au 31 Octobre 2023'!T50 -> 0 | T50: =+'CA Mobile'!P36*10^6 -> 0
B51: 424 | C51: ZFIL_M105 | D51: CA Entrant | E51: Mobile | F51: International Direct | G51: Centrafrique | H51: ='[375]Canevas au 31 Janvier 2023'!T51 -> 7045107.9 | I51: ='[376]Canevas au 29 Février 2023'!T51 -> 6817051 | J51: ='[377]Canevas au 31 Mars 2023'!T51 -> 7124373.8 | K51: ='[378]Canevas au 30 Avril 2023'!T51 -> 7009508.5 | L51: ='[379]Canevas au 31 Mai 2023'!T51 -> 6971730 | M51: ='[380]Canevas au 30 Juin 2023'!T51 -> 7069720.5 | N51: ='[381]Canevas au 31 Juillet 2023'!T51 -> 7221611.5 | O51: ='[382]Canevas au 31 Août 2023'!T51 -> 8371755.3 | P51: ='[383]Canevas au 30 Septembre 2023'!T51 -> 7185638.1 | Q51: ='[384]Canevas au 31 Octobre 2023'!T51 -> 11994642 | T51: =+'CA Mobile'!P38*10^6 -> 7003652
B52: 425 | C52: ZFIL_M106 | D52: CA Entrant | E52: Mobile | F52: Fixe Socatel | G52: Centrafrique | H52: ='[375]Canevas au 31 Janvier 2023'!T52 -> 9660 | I52: ='[376]Canevas au 29 Février 2023'!T52 -> 5376 | J52: ='[377]Canevas au 31 Mars 2023'!T52 -> 1573.7143 | K52: ='[378]Canevas au 30 Avril 2023'!T52 -> 4287.5 | L52: ='[379]Canevas au 31 Mai 2023'!T52 -> 4424 | M52: ='[380]Canevas au 30 Juin 2023'!T52 -> 2540 | N52: ='[381]Canevas au 31 Juillet 2023'!T52 -> 1230 | O52: ='[382]Canevas au 31 Août 2023'!T52 -> 1230 | P52: ='[383]Canevas au 30 Septembre 2023'!T52 -> 810 | Q52: ='[384]Canevas au 31 Octobre 2023'!T52 -> 810 | T52: =+'CA Mobile'!P37*10^6 -> 0
B53: 428 | C53: ZFIL_M109 | D53: CA Entrant | E53: Mobile | F53: Transit Entrant International via les concurrents | G53: Centrafrique | H53: ='[375]Canevas au 31 Janvier 2023'!T53 -> 0 | I53: ='[376]Canevas au 29 Février 2023'!T53 -> 0 | J53: ='[377]Canevas au 31 Mars 2023'!T53 -> 0 | K53: ='[378]Canevas au 30 Avril 2023'!T53 -> 0 | L53: ='[379]Canevas au 31 Mai 2023'!T53 -> 0 | M53: ='[380]Canevas au 30 Juin 2023'!T53 -> 0 | N53: ='[381]Canevas au 31 Juillet 2023'!T53 -> 0 | O53: ='[382]Canevas au 31 Août 2023'!T53 -> 0 | P53: ='[383]Canevas au 30 Septembre 2023'!T53 -> 0 | Q53: ='[384]Canevas au 31 Octobre 2023'!T53 -> 0
B54: 429 | C54: ZFIL_M110 | D54: CA Entrant | E54: Mobile | F54: Transit Entrant International vers les concurrents | G54: Centrafrique | H54: ='[375]Canevas au 31 Janvier 2023'!T54 -> 0 | I54: ='[376]Canevas au 29 Février 2023'!T54 -> 0 | J54: ='[377]Canevas au 31 Mars 2023'!T54 -> 0 | K54: ='[378]Canevas au 30 Avril 2023'!T54 -> 0 | L54: ='[379]Canevas au 31 Mai 2023'!T54 -> 0 | M54: ='[380]Canevas au 30 Juin 2023'!T54 -> 0 | N54: ='[381]Canevas au 31 Juillet 2023'!T54 -> 0 | O54: ='[382]Canevas au 31 Août 2023'!T54 -> 0 | P54: ='[383]Canevas au 30 Septembre 2023'!T54 -> 0 | Q54: ='[384]Canevas au 31 Octobre 2023'!T54 -> 0
B55: 430 | C55: ZFIL_M111 | D55: CA Entrant | E55: Mobile | F55: SMS Internationaux | G55: Centrafrique | H55: ='[375]Canevas au 31 Janvier 2023'!T55 -> 0 | I55: ='[376]Canevas au 29 Février 2023'!T55 -> 0 | J55: ='[377]Canevas au 31 Mars 2023'!T55 -> 0 | K55: ='[378]Canevas au 30 Avril 2023'!T55 -> 0 | L55: ='[379]Canevas au 31 Mai 2023'!T55 -> 0 | M55: ='[380]Canevas au 30 Juin 2023'!T55 -> 0 | N55: ='[381]Canevas au 31 Juillet 2023'!T55 -> 0 | O55: ='[382]Canevas au 31 Août 2023'!T55 -> 0 | P55: ='[383]Canevas au 30 Septembre 2023'!T55 -> 0 | Q55: ='[384]Canevas au 31 Octobre 2023'!T55 -> 0
B56: 435 | C56: ZFIL_M115 | D56: CA colocalisation | E56: Mobile | F56: Colocalisation 1 | G56: Centrafrique | H56: ='[375]Canevas au 31 Janvier 2023'!T56 -> 2380000 | I56: ='[376]Canevas au 29 Février 2023'!T56 -> 2380000 | J56: ='[377]Canevas au 31 Mars 2023'!T56 -> 2380000 | K56: ='[378]Canevas au 30 Avril 2023'!T56 -> 2380000 | L56: ='[379]Canevas au 31 Mai 2023'!T56 -> 2380000 | M56: ='[380]Canevas au 30 Juin 2023'!T56 -> 2380000 | N56: ='[381]Canevas au 31 Juillet 2023'!T56 -> 2380000 | O56: ='[382]Canevas au 31 Août 2023'!T56 -> 2380000 | P56: ='[383]Canevas au 30 Septembre 2023'!T56 -> 2380000 | Q56: ='[384]Canevas au 31 Octobre 2023'!T56 -> 2380000 | T56: =+'CA Mobile'!P47*10^6 -> 2380000
B57: 436 | C57: ZFIL_M116 | D57: CA colocalisation | E57: Mobile | F57: Colocalisation Autres | G57: Centrafrique | H57: ='[375]Canevas au 31 Janvier 2023'!T57 -> 0 | I57: ='[376]Canevas au 29 Février 2023'!T57 -> 0 | J57: ='[377]Canevas au 31 Mars 2023'!T57 -> 0 | K57: ='[378]Canevas au 30 Avril 2023'!T57 -> 0 | L57: ='[379]Canevas au 31 Mai 2023'!T57 -> 0 | M57: ='[380]Canevas au 30 Juin 2023'!T57 -> 0 | N57: ='[381]Canevas au 31 Juillet 2023'!T57 -> 0 | O57: ='[382]Canevas au 31 Août 2023'!T57 -> 0 | P57: ='[383]Canevas au 30 Septembre 2023'!T57 -> 0 | Q57: ='[384]Canevas au 31 Octobre 2023'!T57 -> 0
B58: 437 | C58: ZFIL_M117 | D58: CA colocalisation | E58: Mobile | F58: Colocalisation 3 | G58: Centrafrique | H58: ='[375]Canevas au 31 Janvier 2023'!T58 -> 0 | I58: ='[376]Canevas au 29 Février 2023'!T58 -> 0 | J58: ='[377]Canevas au 31 Mars 2023'!T58 -> 0 | K58: ='[378]Canevas au 30 Avril 2023'!T58 -> 0 | L58: ='[379]Canevas au 31 Mai 2023'!T58 -> 0 | M58: ='[380]Canevas au 30 Juin 2023'!T58 -> 0 | N58: ='[381]Canevas au 31 Juillet 2023'!T58 -> 0 | O58: ='[382]Canevas au 31 Août 2023'!T58 -> 0 | P58: ='[383]Canevas au 30 Septembre 2023'!T58 -> 0 | Q58: ='[384]Canevas au 31 Octobre 2023'!T58 -> 0
B59: 443 | C59: ZFIL_M121 | D59: CA infrastructures | E59: Mobile | F59: CA infrastructures Opérateur 1 | G59: Centrafrique | H59: ='[375]Canevas au 31 Janvier 2023'!T59 -> 0 | I59: ='[376]Canevas au 29 Février 2023'!T59 -> 0 | J59: ='[377]Canevas au 31 Mars 2023'!T59 -> 0 | K59: ='[378]Canevas au 30 Avril 2023'!T59 -> 0 | L59: ='[379]Canevas au 31 Mai 2023'!T59 -> 0 | M59: ='[380]Canevas au 30 Juin 2023'!T59 -> 0 | N59: ='[381]Canevas au 31 Juillet 2023'!T59 -> 0 | O59: ='[382]Canevas au 31 Août 2023'!T59 -> 0 | P59: ='[383]Canevas au 30 Septembre 2023'!T59 -> 0 | Q59: ='[384]Canevas au 31 Octobre 2023'!T59 -> 0
B60: 444 | C60: ZFIL_M122 | D60: CA infrastructures | E60: Mobile | F60: CA infrastructures Opérateur 2 | G60: Centrafrique | H60: ='[375]Canevas au 31 Janvier 2023'!T60 -> 0 | I60: ='[376]Canevas au 29 Février 2023'!T60 -> 0 | J60: ='[377]Canevas au 31 Mars 2023'!T60 -> 0 | K60: ='[378]Canevas au 30 Avril 2023'!T60 -> 0 | L60: ='[379]Canevas au 31 Mai 2023'!T60 -> 0 | M60: ='[380]Canevas au 30 Juin 2023'!T60 -> 0 | N60: ='[381]Canevas au 31 Juillet 2023'!T60 -> 0 | O60: ='[382]Canevas au 31 Août 2023'!T60 -> 0 | P60: ='[383]Canevas au 30 Septembre 2023'!T60 -> 0 | Q60: ='[384]Canevas au 31 Octobre 2023'!T60 -> 0
B61: 445 | C61: ZFIL_M123 | D61: CA infrastructures | E61: Mobile | F61: CA infrastructures Opérateur 3 | G61: Centrafrique | H61: ='[375]Canevas au 31 Janvier 2023'!T61 -> 0 | I61: ='[376]Canevas au 29 Février 2023'!T61 -> 0 | J61: ='[377]Canevas au 31 Mars 2023'!T61 -> 0 | K61: ='[378]Canevas au 30 Avril 2023'!T61 -> 0 | L61: ='[379]Canevas au 31 Mai 2023'!T61 -> 0 | M61: ='[380]Canevas au 30 Juin 2023'!T61 -> 0 | N61: ='[381]Canevas au 31 Juillet 2023'!T61 -> 0 | O61: ='[382]Canevas au 31 Août 2023'!T61 -> 0 | P61: ='[383]Canevas au 30 Septembre 2023'!T61 -> 0 | Q61: ='[384]Canevas au 31 Octobre 2023'!T61 -> 0
B62: 448 | C62: ZFIL_M124 | D62: CA Roaming IN | E62: Mobile | F62: Roaming IN | G62: Centrafrique | H62: ='[375]Canevas au 31 Janvier 2023'!T62 -> 911876.23 | I62: ='[376]Canevas au 29 Février 2023'!T62 -> 910703 | J62: ='[377]Canevas au 31 Mars 2023'!T62 -> 1193765.6 | K62: ='[378]Canevas au 30 Avril 2023'!T62 -> 1329144.3 | L62: ='[379]Canevas au 31 Mai 2023'!T62 -> 1321478.3 | M62: ='[380]Canevas au 30 Juin 2023'!T62 -> 921478.27 | N62: ='[381]Canevas au 31 Juillet 2023'!T62 -> 2378834 | O62: ='[382]Canevas au 31 Août 2023'!T62 -> 2378834 | P62: ='[383]Canevas au 30 Septembre 2023'!T62 -> 1311310 | Q62: ='[384]Canevas au 31 Octobre 2023'!T62 -> 1348608 | T62: =+'CA Mobile'!P46*10^6 -> 692622.9
B63: 450 | C63: ZFIL_M125 | D63: CA équipements | E63: Mobile | F63: Modem 3G/4G | G63: Centrafrique | H63: ='[375]Canevas au 31 Janvier 2023'!T63 -> 0 | I63: ='[376]Canevas au 29 Février 2023'!T63 -> 0 | J63: ='[377]Canevas au 31 Mars 2023'!T63 -> 0 | K63: ='[378]Canevas au 30 Avril 2023'!T63 -> 0 | L63: ='[379]Canevas au 31 Mai 2023'!T63 -> 0 | M63: ='[380]Canevas au 30 Juin 2023'!T63 -> 0 | N63: ='[381]Canevas au 31 Juillet 2023'!T63 -> 0 | O63: ='[382]Canevas au 31 Août 2023'!T63 -> 0 | P63: ='[383]Canevas au 30 Septembre 2023'!T63 -> 0 | Q63: ='[384]Canevas au 31 Octobre 2023'!T63 -> 0
B64: 451 | C64: ZFIL_M126 | D64: CA équipements | E64: Mobile | F64: Kits | G64: Centrafrique | H64: ='[375]Canevas au 31 Janvier 2023'!T64 -> 2500000 | I64: ='[376]Canevas au 29 Février 2023'!T64 -> 1900000 | J64: ='[377]Canevas au 31 Mars 2023'!T64 -> 1600000 | K64: ='[378]Canevas au 30 Avril 2023'!T64 -> 2000000 | L64: ='[379]Canevas au 31 Mai 2023'!T64 -> 6683270.3 | M64: ='[380]Canevas au 30 Juin 2023'!T64 -> 5000000 | N64: ='[381]Canevas au 31 Juillet 2023'!T64 -> 5000000 | O64: ='[382]Canevas au 31 Août 2023'!T64 -> 4800000 | P64: ='[383]Canevas au 30 Septembre 2023'!T64 -> 4500000 | Q64: ='[384]Canevas au 31 Octobre 2023'!T64 -> 2100000 | T64: =+'CA Mobile'!P50*10^6 -> 3089673
B65: 452 | C65: ZFIL_M127 | D65: CA équipements | E65: Mobile | F65: Terminaux | G65: Centrafrique | H65: ='[375]Canevas au 31 Janvier 2023'!T65 -> 3600000 | I65: ='[376]Canevas au 29 Février 2023'!T65 -> 3000000 | J65: ='[377]Canevas au 31 Mars 2023'!T65 -> 3300000 | K65: ='[378]Canevas au 30 Avril 2023'!T65 -> 1771810.6 | L65: ='[379]Canevas au 31 Mai 2023'!T65 -> 2194713 | M65: ='[380]Canevas au 30 Juin 2023'!T65 -> 2886132 | N65: ='[381]Canevas au 31 Juillet 2023'!T65 -> 2917225 | O65: ='[382]Canevas au 31 Août 2023'!T65 -> 3000000 | P65: ='[383]Canevas au 30 Septembre 2023'!T65 -> 2900000 | Q65: ='[384]Canevas au 31 Octobre 2023'!T65 -> 2700000 | T65: =+'CA Mobile'!P51*10^6 -> 5418769
B66: 458 | C66: ZFIL_M133 | D66: CA équipements | E66: Mobile | F66: Autres | G66: Centrafrique | H66: ='[375]Canevas au 31 Janvier 2023'!T66 -> 0 | I66: ='[376]Canevas au 29 Février 2023'!T66 -> 0 | J66: ='[377]Canevas au 31 Mars 2023'!T66 -> 0 | K66: ='[378]Canevas au 30 Avril 2023'!T66 -> 0 | L66: ='[379]Canevas au 31 Mai 2023'!T66 -> 0 | M66: ='[380]Canevas au 30 Juin 2023'!T66 -> 0 | N66: ='[381]Canevas au 31 Juillet 2023'!T66 -> 0 | O66: ='[382]Canevas au 31 Août 2023'!T66 -> 0 | P66: ='[383]Canevas au 30 Septembre 2023'!T66 -> 0 | Q66: ='[384]Canevas au 31 Octobre 2023'!T66 -> 0 | T66: =+'CA Mobile'!P52*10^6 -> 0
B67: 2582 | C67: ZFIL_M325 | D67: CA | E67: mobile | F67: CA Mobile Money | G67: Centrafrique | H67: ='[375]Canevas au 31 Janvier 2023'!T67 -> 0 | I67: ='[376]Canevas au 29 Février 2023'!T67 -> 0 | J67: ='[377]Canevas au 31 Mars 2023'!T67 -> 0 | K67: ='[378]Canevas au 30 Avril 2023'!T67 -> 0 | L67: ='[379]Canevas au 31 Mai 2023'!T67 -> 0 | M67: ='[380]Canevas au 30 Juin 2023'!T67 -> 0 | N67: ='[381]Canevas au 31 Juillet 2023'!T67 -> 0 | O67: ='[382]Canevas au 31 Août 2023'!T67 -> 0 | P67: ='[383]Canevas au 30 Septembre 2023'!T67 -> 0 | Q67: ='[384]Canevas au 31 Octobre 2023'!T67 -> 0
B68: 601 | C68: ZFIL_F177 | D68: Coût des ventes Interconnexion | E68: Mobile | F68: Trafic Sortant international | G68: Centrafrique | H68: ='[375]Canevas au 31 Janvier 2023'!T68 -> 159767 | I68: ='[376]Canevas au 29 Février 2023'!T68 -> 146998 | J68: ='[377]Canevas au 31 Mars 2023'!T68 -> 129397.35 | K68: ='[378]Canevas au 30 Avril 2023'!T68 -> 160369 | L68: ='[379]Canevas au 31 Mai 2023'!T68 -> 178535 | M68: ='[380]Canevas au 30 Juin 2023'!T68 -> 163107 | N68: ='[381]Canevas au 31 Juillet 2023'!T68 -> 161155 | O68: ='[382]Canevas au 31 Août 2023'!T68 -> 155166 | P68: ='[383]Canevas au 30 Septembre 2023'!T68 -> 158546 | Q68: ='[384]Canevas au 31 Octobre 2023'!T68 -> 129610 | T68: =+'Marge Mobile'!O9*10^6 -> 773974.82
B69: 602 | C69: ZFIL_F178 | D69: Coût des ventes Interconnexion | E69: Mobile | F69: Coût / Minute international | G69: Centrafrique | H69: ='[375]Canevas au 31 Janvier 2023'!T69 -> 116.44621 | I69: ='[376]Canevas au 29 Février 2023'!T69 -> 117.35203 | J69: ='[377]Canevas au 31 Mars 2023'!T69 -> 117.08519 | K69: ='[378]Canevas au 30 Avril 2023'!T69 -> 115.98286 | L69: ='[379]Canevas au 31 Mai 2023'!T69 -> 109.04309 | M69: ='[380]Canevas au 30 Juin 2023'!T69 -> 114.73593 | N69: ='[381]Canevas au 31 Juillet 2023'!T69 -> 114.38764 | O69: ='[382]Canevas au 31 Août 2023'!T69 -> 114.95884 | P69: ='[383]Canevas au 30 Septembre 2023'!T69 -> 114.33425 | Q69: ='[384]Canevas au 31 Octobre 2023'!T69 -> 18.447736 | T69: =+'Marge Mobile'!O10 -> 16.011566
B70: 604 | C70: ZFIL_F179 | D70: Coût des ventes Interconnexion | E70: Mobile | F70: Trafic Sortant Telecel | G70: Centrafrique | H70: ='[375]Canevas au 31 Janvier 2023'!T70 -> 113837 | I70: ='[376]Canevas au 29 Février 2023'!T70 -> 133961 | J70: ='[377]Canevas au 31 Mars 2023'!T70 -> 179795.1 | K70: ='[378]Canevas au 30 Avril 2023'!T70 -> 175306.25 | L70: ='[379]Canevas au 31 Mai 2023'!T70 -> 177261.7 | M70: ='[380]Canevas au 30 Juin 2023'!T70 -> 315123 | N70: ='[381]Canevas au 31 Juillet 2023'!T70 -> 337902 | O70: ='[382]Canevas au 31 Août 2023'!T70 -> 392785 | P70: ='[383]Canevas au 30 Septembre 2023'!T70 -> 414337 | Q70: ='[384]Canevas au 31 Octobre 2023'!T70 -> 1581109 | T70: =+T22 -> 769969
B71: 605 | C71: ZFIL_F180 | D71: Coût des ventes Interconnexion | E71: Mobile | F71: Coût / Minute Telecel | G71: Centrafrique | H71: ='[375]Canevas au 31 Janvier 2023'!T71 -> 10 | I71: ='[376]Canevas au 29 Février 2023'!T71 -> 10 | J71: ='[377]Canevas au 31 Mars 2023'!T71 -> 10 | K71: ='[378]Canevas au 30 Avril 2023'!T71 -> 10 | L71: ='[379]Canevas au 31 Mai 2023'!T71 -> 10 | M71: ='[380]Canevas au 30 Juin 2023'!T71 -> 10 | N71: ='[381]Canevas au 31 Juillet 2023'!T71 -> 10 | O71: ='[382]Canevas au 31 Août 2023'!T71 -> 10 | P71: ='[383]Canevas au 30 Septembre 2023'!T71 -> 10 | Q71: ='[384]Canevas au 31 Octobre 2023'!T71 -> 10 | T71: =+'Marge Mobile'!O14 -> 10
B72: 607 | C72: ZFIL_F181 | D72: Coût des ventes Interconnexion | E72: Mobile | F72: Trafic Sortant Orange | G72: Centrafrique | H72: ='[375]Canevas au 31 Janvier 2023'!T72 -> 135189 | I72: ='[376]Canevas au 29 Février 2023'!T72 -> 184954 | J72: ='[377]Canevas au 31 Mars 2023'!T72 -> 256845.33 | K72: ='[378]Canevas au 30 Avril 2023'!T72 -> 275660 | L72: ='[379]Canevas au 31 Mai 2023'!T72 -> 266252.7 | M72: ='[380]Canevas au 30 Juin 2023'!T72 -> 311753 | N72: ='[381]Canevas au 31 Juillet 2023'!T72 -> 366011 | O72: ='[382]Canevas au 31 Août 2023'!T72 -> 406753 | P72: ='[383]Canevas au 30 Septembre 2023'!T72 -> 438290 | Q72: ='[384]Canevas au 31 Octobre 2023'!T72 -> 1913951 | T72: =+'Marge Mobile'!O16*10^6 -> 1539982
B73: 608 | C73: ZFIL_F182 | D73: Coût des ventes Interconnexion | E73: Mobile | F73: Coût / Minute Orange | G73: Centrafrique | H73: ='[375]Canevas au 31 Janvier 2023'!T73 -> 10 | I73: ='[376]Canevas au 29 Février 2023'!T73 -> 10 | J73: ='[377]Canevas au 31 Mars 2023'!T73 -> 10 | K73: ='[378]Canevas au 30 Avril 2023'!T73 -> 10 | L73: ='[379]Canevas au 31 Mai 2023'!T73 -> 10 | M73: ='[380]Canevas au 30 Juin 2023'!T73 -> 10 | N73: ='[381]Canevas au 31 Juillet 2023'!T73 -> 10 | O73: ='[382]Canevas au 31 Août 2023'!T73 -> 10 | P73: ='[383]Canevas au 30 Septembre 2023'!T73 -> 10 | Q73: ='[384]Canevas au 31 Octobre 2023'!T73 -> 10 | T73: =+'Marge Mobile'!O17 -> 10
B74: 610 | C74: ZFIL_F183 | D74: Coût des ventes Interconnexion | E74: Mobile | F74: Trafic Sortant AZUR | G74: Centrafrique | H74: ='[375]Canevas au 31 Janvier 2023'!T74 -> 0 | I74: ='[376]Canevas au 29 Février 2023'!T74 -> 0 | J74: ='[377]Canevas au 31 Mars 2023'!T74 -> 0 | K74: ='[378]Canevas au 30 Avril 2023'!T74 -> 0 | L74: ='[379]Canevas au 31 Mai 2023'!T74 -> 0 | M74: ='[380]Canevas au 30 Juin 2023'!T74 -> 0 | N74: ='[381]Canevas au 31 Juillet 2023'!T74 -> 0 | O74: ='[382]Canevas au 31 Août 2023'!T74 -> 0 | P74: ='[383]Canevas au 30 Septembre 2023'!T74 -> 0 | Q74: ='[384]Canevas au 31 Octobre 2023'!T74 -> 0 | T74: =+'Marge Mobile'!O19*10^6 -> 0
B75: 611 | C75: ZFIL_F184 | D75: Coût des ventes Interconnexion | E75: Mobile | F75: Coût / Minute AZUR | G75: Centrafrique | H75: ='[375]Canevas au 31 Janvier 2023'!T75 -> 10 | I75: ='[376]Canevas au 29 Février 2023'!T75 -> 10 | J75: ='[377]Canevas au 31 Mars 2023'!T75 -> 10 | K75: ='[378]Canevas au 30 Avril 2023'!T75 -> 10 | L75: ='[379]Canevas au 31 Mai 2023'!T75 -> 10 | M75: ='[380]Canevas au 30 Juin 2023'!T75 -> 10 | N75: ='[381]Canevas au 31 Juillet 2023'!T75 -> 10 | O75: ='[382]Canevas au 31 Août 2023'!T75 -> 10 | P75: ='[383]Canevas au 30 Septembre 2023'!T75 -> 10 | Q75: ='[384]Canevas au 31 Octobre 2023'!T75 -> 10 | T75: =+'Marge Mobile'!O20 -> 10
B76: 613 | C76: ZFIL_F185 | D76: Coût des ventes Interconnexion | E76: Mobile | F76: Trafic Sortant Fixe | G76: Centrafrique | H76: ='[375]Canevas au 31 Janvier 2023'!T76 -> 92.4 | I76: ='[376]Canevas au 29 Février 2023'!T76 -> 21.6 | J76: ='[377]Canevas au 31 Mars 2023'!T76 -> 40.742857 | K76: ='[378]Canevas au 30 Avril 2023'!T76 -> 40.742857 | L76: ='[379]Canevas au 31 Mai 2023'!T76 -> 51.1 | M76: ='[380]Canevas au 30 Juin 2023'!T76 -> 128.4 | N76: ='[381]Canevas au 31 Juillet 2023'!T76 -> 244.8 | O76: ='[382]Canevas au 31 Août 2023'!T76 -> 16.8 | P76: ='[383]Canevas au 30 Septembre 2023'!T76 -> 10073.2 | Q76: ='[384]Canevas au 31 Octobre 2023'!T76 -> 10073.2 | T76: =+'Marge Mobile'!O22*10^6 -> -20000
B77: 614 | C77: ZFIL_F186 | D77: Coût des ventes Interconnexion | E77: Mobile | F77: Coût / Minute Fixe | G77: Centrafrique | H77: ='[375]Canevas au 31 Janvier 2023'!T77 -> 20 | I77: ='[376]Canevas au 29 Février 2023'!T77 -> 10 | J77: ='[377]Canevas au 31 Mars 2023'!T77 -> 10 | K77: ='[378]Canevas au 30 Avril 2023'!T77 -> 10 | L77: ='[379]Canevas au 31 Mai 2023'!T77 -> 10 | M77: ='[380]Canevas au 30 Juin 2023'!T77 -> 10 | N77: ='[381]Canevas au 31 Juillet 2023'!T77 -> 10 | O77: ='[382]Canevas au 31 Août 2023'!T77 -> 10 | P77: ='[383]Canevas au 30 Septembre 2023'!T77 -> 10 | Q77: ='[384]Canevas au 31 Octobre 2023'!T77 -> 10 | T77: =+'Marge Mobile'!O23 -> 10
B78: 616 | C78: ZFIL_F187 | D78: Coût des ventes Interconnexion | E78: Mobile | F78: Trafic Transit Entrant International vers les concurrents | G78: Centrafrique | H78: ='[375]Canevas au 31 Janvier 2023'!T78 -> 0 | I78: ='[376]Canevas au 29 Février 2023'!T78 -> 0 | J78: ='[377]Canevas au 31 Mars 2023'!T78 -> 0 | K78: ='[378]Canevas au 30 Avril 2023'!T78 -> 0 | L78: ='[379]Canevas au 31 Mai 2023'!T78 -> 0 | M78: ='[380]Canevas au 30 Juin 2023'!T78 -> 0 | N78: ='[381]Canevas au 31 Juillet 2023'!T78 -> 0 | O78: ='[382]Canevas au 31 Août 2023'!T78 -> 0 | P78: ='[383]Canevas au 30 Septembre 2023'!T78 -> 0 | Q78: ='[384]Canevas au 31 Octobre 2023'!T78 -> 0
B79: 617 | C79: ZFIL_F188 | D79: Coût des ventes Interconnexion | E79: Mobile | F79: Coût Transit Entrant International vers les concurrents | G79: Centrafrique | H79: ='[375]Canevas au 31 Janvier 2023'!T79 -> 0 | I79: ='[376]Canevas au 29 Février 2023'!T79 -> 0 | J79: ='[377]Canevas au 31 Mars 2023'!T79 -> 0 | K79: ='[378]Canevas au 30 Avril 2023'!T79 -> 0 | L79: ='[379]Canevas au 31 Mai 2023'!T79 -> 0 | M79: ='[380]Canevas au 30 Juin 2023'!T79 -> 0 | N79: ='[381]Canevas au 31 Juillet 2023'!T79 -> 0 | O79: ='[382]Canevas au 31 Août 2023'!T79 -> 0 | P79: ='[383]Canevas au 30 Septembre 2023'!T79 -> 0 | Q79: ='[384]Canevas au 31 Octobre 2023'!T79 -> 0
B80: 630 | C80: ZFIL_F197 | D80: Coût des ventes Interconnexion | E80: Mobile | F80: Nbre SMS | G80: Centrafrique | H80: ='[375]Canevas au 31 Janvier 2023'!T80 -> 0 | I80: ='[376]Canevas au 29 Février 2023'!T80 -> 0 | J80: ='[377]Canevas au 31 Mars 2023'!T80 -> 0 | K80: ='[378]Canevas au 30 Avril 2023'!T80 -> 0 | L80: ='[379]Canevas au 31 Mai 2023'!T80 -> 0 | M80: ='[380]Canevas au 30 Juin 2023'!T80 -> 0 | N80: ='[381]Canevas au 31 Juillet 2023'!T80 -> 0 | O80: ='[382]Canevas au 31 Août 2023'!T80 -> 0 | P80: ='[383]Canevas au 30 Septembre 2023'!T80 -> 0 | Q80: ='[384]Canevas au 31 Octobre 2023'!T80 -> 0
B81: 631 | C81: ZFIL_F198 | D81: Coût des ventes Interconnexion | E81: Mobile | F81: Coût SMS | G81: Centrafrique | H81: ='[375]Canevas au 31 Janvier 2023'!T81 -> 0 | I81: ='[376]Canevas au 29 Février 2023'!T81 -> 0 | J81: ='[377]Canevas au 31 Mars 2023'!T81 -> 0 | K81: ='[378]Canevas au 30 Avril 2023'!T81 -> 0 | L81: ='[379]Canevas au 31 Mai 2023'!T81 -> 0 | M81: ='[380]Canevas au 30 Juin 2023'!T81 -> 0 | N81: ='[381]Canevas au 31 Juillet 2023'!T81 -> 0 | O81: ='[382]Canevas au 31 Août 2023'!T81 -> 0 | P81: ='[383]Canevas au 30 Septembre 2023'!T81 -> 0 | Q81: ='[384]Canevas au 31 Octobre 2023'!T81 -> 0
B82: 632 | C82: ZFIL_F199 | D82: Coût des ventes Interconnexion | E82: Mobile | F82: Interconnexion SMS | G82: Centrafrique | H82: ='[375]Canevas au 31 Janvier 2023'!T82 -> 258148 | I82: ='[376]Canevas au 29 Février 2023'!T82 -> 274296 | J82: ='[377]Canevas au 31 Mars 2023'!T82 -> 266244 | K82: ='[378]Canevas au 30 Avril 2023'!T82 -> 289432 | L82: ='[379]Canevas au 31 Mai 2023'!T82 -> 277838.28 | M82: ='[380]Canevas au 30 Juin 2023'!T82 -> 317856 | N82: ='[381]Canevas au 31 Juillet 2023'!T82 -> 310860 | O82: ='[382]Canevas au 31 Août 2023'!T82 -> 328196 | P82: ='[383]Canevas au 30 Septembre 2023'!T82 -> 388240 | Q82: ='[384]Canevas au 31 Octobre 2023'!T82 -> -405076.48 | T82: =+'Marge Mobile'!O25*10^6 -> 241535.67
B83: 2604 | C83: ZFIL_M340 | D83: Coût des ventes Interconnexion | E83: mobile | F83: Others - Autres coûts SVA | G83: Centrafrique | H83: ='[375]Canevas au 31 Janvier 2023'!T83 -> 0 | I83: ='[376]Canevas au 29 Février 2023'!T83 -> 0 | J83: ='[377]Canevas au 31 Mars 2023'!T83 -> 0 | K83: ='[378]Canevas au 30 Avril 2023'!T83 -> 0 | L83: ='[379]Canevas au 31 Mai 2023'!T83 -> 0 | M83: ='[380]Canevas au 30 Juin 2023'!T83 -> 0 | N83: ='[381]Canevas au 31 Juillet 2023'!T83 -> 0 | O83: ='[382]Canevas au 31 Août 2023'!T83 -> 0 | P83: ='[383]Canevas au 30 Septembre 2023'!T83 -> 0 | Q83: ='[384]Canevas au 31 Octobre 2023'!T83 -> 0 | T83: =+'Marge Mobile'!O33*10^6 -> 0
B84: 634 | C84: ZFIL_F200 | D84: Coût des ventes Roaming Out | E84: Mobile | F84: Roaming Out | G84: Centrafrique | H84: ='[375]Canevas au 31 Janvier 2023'!T84 -> 1754758.7 | I84: ='[376]Canevas au 29 Février 2023'!T84 -> 1770601 | J84: ='[377]Canevas au 31 Mars 2023'!T84 -> 1965201.9 | K84: ='[378]Canevas au 30 Avril 2023'!T84 -> 1718709 | L84: ='[379]Canevas au 31 Mai 2023'!T84 -> 1862998.5 | M84: ='[380]Canevas au 30 Juin 2023'!T84 -> 1914368 | N84: ='[381]Canevas au 31 Juillet 2023'!T84 -> 2571572 | O84: ='[382]Canevas au 31 Août 2023'!T84 -> 2236382.9 | P84: ='[383]Canevas au 30 Septembre 2023'!T84 -> 2759830 | Q84: ='[384]Canevas au 31 Octobre 2023'!T84 -> 2218714 | T84: =+'Marge Mobile'!O26*10^6 -> 826719.71
B85: 635 | C85: ZFIL_F201 | D85: Coût des ventes terminaux et cartes | E85: Mobile | F85: Blackberry RIM Fees | G85: Centrafrique | H85: ='[375]Canevas au 31 Janvier 2023'!T85 -> 0 | I85: ='[376]Canevas au 29 Février 2023'!T85 -> 0 | J85: ='[377]Canevas au 31 Mars 2023'!T85 -> 0 | K85: ='[378]Canevas au 30 Avril 2023'!T85 -> 0 | L85: ='[379]Canevas au 31 Mai 2023'!T85 -> 0 | M85: ='[380]Canevas au 30 Juin 2023'!T85 -> 0 | N85: ='[381]Canevas au 31 Juillet 2023'!T85 -> 0 | O85: ='[382]Canevas au 31 Août 2023'!T85 -> 0 | P85: ='[383]Canevas au 30 Septembre 2023'!T85 -> 0 | Q85: ='[384]Canevas au 31 Octobre 2023'!T85 -> 0
B86: 636 | C86: ZFIL_F202 | D86: Coût des ventes terminaux et cartes | E86: Mobile | F86: Modem 3G/4G | G86: Centrafrique | H86: ='[375]Canevas au 31 Janvier 2023'!T86 -> 0 | I86: ='[376]Canevas au 29 Février 2023'!T86 -> 0 | J86: ='[377]Canevas au 31 Mars 2023'!T86 -> 0 | K86: ='[378]Canevas au 30 Avril 2023'!T86 -> 0 | L86: ='[379]Canevas au 31 Mai 2023'!T86 -> 0 | M86: ='[380]Canevas au 30 Juin 2023'!T86 -> 0 | N86: ='[381]Canevas au 31 Juillet 2023'!T86 -> 0 | O86: ='[382]Canevas au 31 Août 2023'!T86 -> 0 | P86: ='[383]Canevas au 30 Septembre 2023'!T86 -> 0 | Q86: ='[384]Canevas au 31 Octobre 2023'!T86 -> 0
B87: 637 | C87: ZFIL_F203 | D87: Coût des ventes terminaux et cartes | E87: Mobile | F87: Terminaux | G87: Centrafrique | H87: ='[375]Canevas au 31 Janvier 2023'!T87 -> 3132000 | I87: ='[376]Canevas au 29 Février 2023'!T87 -> 2610000 | J87: ='[377]Canevas au 31 Mars 2023'!T87 -> 2871000 | K87: ='[378]Canevas au 30 Avril 2023'!T87 -> 1541475.3 | L87: ='[379]Canevas au 31 Mai 2023'!T87 -> 1909400.3 | M87: ='[380]Canevas au 30 Juin 2023'!T87 -> 3310934.8 | N87: ='[381]Canevas au 31 Juillet 2023'!T87 -> 3337985.7 | O87: ='[382]Canevas au 31 Août 2023'!T87 -> 3410000 | P87: ='[383]Canevas au 30 Septembre 2023'!T87 -> 3323000 | Q87: ='[384]Canevas au 31 Octobre 2023'!T87 -> 2349000 | T87: =+'Marge Mobile'!O31*10^6 -> 4714329
B88: 638 | C88: ZFIL_F204 | D88: Coût des ventes terminaux et cartes | E88: Mobile | F88: Provision stocks | G88: Centrafrique | H88: ='[375]Canevas au 31 Janvier 2023'!T88 -> 0 | I88: ='[376]Canevas au 29 Février 2023'!T88 -> 0 | J88: ='[377]Canevas au 31 Mars 2023'!T88 -> 0 | K88: ='[378]Canevas au 30 Avril 2023'!T88 -> 0 | L88: ='[379]Canevas au 31 Mai 2023'!T88 -> 0 | M88: ='[380]Canevas au 30 Juin 2023'!T88 -> 0 | N88: ='[381]Canevas au 31 Juillet 2023'!T88 -> 0 | O88: ='[382]Canevas au 31 Août 2023'!T88 -> 0 | P88: ='[383]Canevas au 30 Septembre 2023'!T88 -> 0 | Q88: ='[384]Canevas au 31 Octobre 2023'!T88 -> 0 | T88: =+'Marge Mobile'!O32*10^6 -> 0
B89: 2614 | C89: ZFIL_M348 | D89: Coût des ventes terminaux et cartes | E89: mobile | F89: Coût des cartes SIM | G89: Centrafrique | H89: ='[375]Canevas au 31 Janvier 2023'!T89 -> 0 | I89: ='[376]Canevas au 29 Février 2023'!T89 -> 0 | J89: ='[377]Canevas au 31 Mars 2023'!T89 -> 0 | K89: ='[378]Canevas au 30 Avril 2023'!T89 -> 0 | L89: ='[379]Canevas au 31 Mai 2023'!T89 -> 0 | M89: ='[380]Canevas au 30 Juin 2023'!T89 -> 0 | N89: ='[381]Canevas au 31 Juillet 2023'!T89 -> 0 | O89: ='[382]Canevas au 31 Août 2023'!T89 -> 0 | P89: ='[383]Canevas au 30 Septembre 2023'!T89 -> 0 | Q89: ='[384]Canevas au 31 Octobre 2023'!T89 -> 0
B90: 2615 | C90: ZFIL_M349 | D90: Coût des ventes terminaux et cartes | E90: mobile | F90: Coût des cartes de recharge vendues | G90: Centrafrique | H90: ='[375]Canevas au 31 Janvier 2023'!T90 -> 0.3 | I90: ='[376]Canevas au 29 Février 2023'!T90 -> 0.3 | J90: ='[377]Canevas au 31 Mars 2023'!T90 -> 0.3 | K90: ='[378]Canevas au 30 Avril 2023'!T90 -> 0.3 | L90: ='[379]Canevas au 31 Mai 2023'!T90 -> 0.3 | M90: ='[380]Canevas au 30 Juin 2023'!T90 -> 0.3 | N90: ='[381]Canevas au 31 Juillet 2023'!T90 -> 0.3 | O90: ='[382]Canevas au 31 Août 2023'!T90 -> 0.3 | P90: ='[383]Canevas au 30 Septembre 2023'!T90 -> 0.3 | Q90: ='[384]Canevas au 31 Octobre 2023'!T90 -> 0.3 | T90: =+'Marge Mobile'!O29 -> 0.3
B91: 649 | C91: ZFIL_F214 | D91: Coût des ventes Commissions | E91: Mobile | F91: Commissions - Avoir de performance | G91: Centrafrique | H91: ='[375]Canevas au 31 Janvier 2023'!T91 -> 5200000 | I91: ='[376]Canevas au 29 Février 2023'!T91 -> 5400000 | J91: ='[377]Canevas au 31 Mars 2023'!T91 -> 5400000 | K91: ='[378]Canevas au 30 Avril 2023'!T91 -> 5500000 | L91: ='[379]Canevas au 31 Mai 2023'!T91 -> 6300000 | M91: ='[380]Canevas au 30 Juin 2023'!T91 -> 6000000 | N91: ='[381]Canevas au 31 Juillet 2023'!T91 -> 6400000 | O91: ='[382]Canevas au 31 Août 2023'!T91 -> 7000000 | P91: ='[383]Canevas au 30 Septembre 2023'!T91 -> 7000000 | Q91: ='[384]Canevas au 31 Octobre 2023'!T91 -> 7000000 | T91: =+'Marge Mobile'!O37*10^6 -> 8000000
B92: 2611 | C92: ZFIL_M345 | D92: Coût des ventes Commissions | E92: mobile | F92: Commissions - up-front | G92: Centrafrique | H92: ='[375]Canevas au 31 Janvier 2023'!T92 -> 24553671 | I92: ='[376]Canevas au 29 Février 2023'!T92 -> 24128862 | J92: ='[377]Canevas au 31 Mars 2023'!T92 -> 25536637 | K92: ='[378]Canevas au 30 Avril 2023'!T92 -> 26029043 | L92: ='[379]Canevas au 31 Mai 2023'!T92 -> 28445264 | M92: ='[380]Canevas au 30 Juin 2023'!T92 -> 27431005 | N92: ='[381]Canevas au 31 Juillet 2023'!T92 -> 29830827 | O92: ='[382]Canevas au 31 Août 2023'!T92 -> 31478808 | P92: ='[383]Canevas au 30 Septembre 2023'!T92 -> 31044113 | Q92: ='[384]Canevas au 31 Octobre 2023'!T92 -> 33320759 | T92: =+'Marge Mobile'!O36*10^6 -> 32343434
B93: 2612 | C93: ZFIL_M346 | D93: Coût des ventes Commissions | E93: mobile | F93: Commissions - Mobile Money | G93: Centrafrique | H93: ='[375]Canevas au 31 Janvier 2023'!T93 -> 0 | I93: ='[376]Canevas au 29 Février 2023'!T93 -> 0 | J93: ='[377]Canevas au 31 Mars 2023'!T93 -> 0 | K93: ='[378]Canevas au 30 Avril 2023'!T93 -> 0 | L93: ='[379]Canevas au 31 Mai 2023'!T93 -> 0 | M93: ='[380]Canevas au 30 Juin 2023'!T93 -> 0 | N93: ='[381]Canevas au 31 Juillet 2023'!T93 -> 0 | O93: ='[382]Canevas au 31 Août 2023'!T93 -> 0 | P93: ='[383]Canevas au 30 Septembre 2023'!T93 -> 0 | Q93: ='[384]Canevas au 31 Octobre 2023'!T93 -> 0
B94: 713 | C94: ZFIL_M142 | D94: Opex Personnel | E94: Mobile | F94: Personnel | G94: Centrafrique | H94: ='[375]Canevas au 31 Janvier 2023'!T94 -> 48100000 | I94: ='[376]Canevas au 29 Février 2023'!T94 -> 48100000 | J94: ='[377]Canevas au 31 Mars 2023'!T94 -> 47450000 | K94: ='[378]Canevas au 30 Avril 2023'!T94 -> 45383620 | L94: ='[379]Canevas au 31 Mai 2023'!T94 -> 45659320 | M94: ='[380]Canevas au 30 Juin 2023'!T94 -> 44510135 | N94: ='[381]Canevas au 31 Juillet 2023'!T94 -> 44560135 | O94: ='[382]Canevas au 31 Août 2023'!T94 -> 44560135 | P94: ='[383]Canevas au 30 Septembre 2023'!T94 -> 44560135 | Q94: ='[384]Canevas au 31 Octobre 2023'!T94 -> 44560135 | T94: =+'Opex '!P13*10^6 -> 44560135
B95: 715 | C95: ZFIL_M143 | D95: Opex Communication | E95: Mobile | F95: Communication | G95: Centrafrique | H95: ='[375]Canevas au 31 Janvier 2023'!T95 -> 1025000 | I95: ='[376]Canevas au 29 Février 2023'!T95 -> 2000000 | J95: ='[377]Canevas au 31 Mars 2023'!T95 -> 2000000 | K95: ='[378]Canevas au 30 Avril 2023'!T95 -> 2814940 | L95: ='[379]Canevas au 31 Mai 2023'!T95 -> 9451916 | M95: ='[380]Canevas au 30 Juin 2023'!T95 -> 7544000 | N95: ='[381]Canevas au 31 Juillet 2023'!T95 -> 4300000 | O95: ='[382]Canevas au 31 Août 2023'!T95 -> 4300000 | P95: ='[383]Canevas au 30 Septembre 2023'!T95 -> 4445000 | Q95: ='[384]Canevas au 31 Octobre 2023'!T95 -> 39500000 | T95: =+'Opex '!P18*10^6 -> 5800000
B96: 718 | C96: ZFIL_M146 | D96: Opex Exploitation & maintenance | E96: Mobile | F96: Achat d'énergie - Bâtiment - Gardiennage | G96: Centrafrique | H96: ='[375]Canevas au 31 Janvier 2023'!T96 -> 56000000 | I96: ='[376]Canevas au 29 Février 2023'!T96 -> 55000000 | J96: ='[377]Canevas au 31 Mars 2023'!T96 -> 56000000 | K96: ='[378]Canevas au 30 Avril 2023'!T96 -> 58114150 | L96: ='[379]Canevas au 31 Mai 2023'!T96 -> 61583932 | M96: ='[380]Canevas au 30 Juin 2023'!T96 -> 51999976 | N96: ='[381]Canevas au 31 Juillet 2023'!T96 -> 52636172 | O96: ='[382]Canevas au 31 Août 2023'!T96 -> 49000000 | P96: ='[383]Canevas au 30 Septembre 2023'!T96 -> 46921260 | Q96: ='[384]Canevas au 31 Octobre 2023'!T96 -> 48250000 | T96: =+'Opex '!P21*10^6 -> 49981137
B97: 719 | C97: ZFIL_M147 | D97: Opex Exploitation & maintenance | E97: Mobile | F97: Lignes et réseaux (entretien & achats) | G97: Centrafrique | H97: ='[375]Canevas au 31 Janvier 2023'!T97 -> 129000000 | I97: ='[376]Canevas au 29 Février 2023'!T97 -> 124000000 | J97: ='[377]Canevas au 31 Mars 2023'!T97 -> 129792000 | K97: ='[378]Canevas au 30 Avril 2023'!T97 -> 1.304362e+08 | L97: ='[379]Canevas au 31 Mai 2023'!T97 -> 130456040 | M97: ='[380]Canevas au 30 Juin 2023'!T97 -> 125200034 | N97: ='[381]Canevas au 31 Juillet 2023'!T97 -> 108514892 | O97: ='[382]Canevas au 31 Août 2023'!T97 -> 1.1539212e+08 | P97: ='[383]Canevas au 30 Septembre 2023'!T97 -> 1.156452e+08 | Q97: ='[384]Canevas au 31 Octobre 2023'!T97 -> -1.0928867e+08 | T97: =+'Opex '!P22*10^6 -> 81122402
B98: 716 | C98: ZFIL_M144 | D98: Opex Exploitation & maintenance | E98: Mobile | F98: Segment spatial | G98: Centrafrique | H98: ='[375]Canevas au 31 Janvier 2023'!T98 -> 0 | I98: ='[376]Canevas au 29 Février 2023'!T98 -> 0 | J98: ='[377]Canevas au 31 Mars 2023'!T98 -> 0 | K98: ='[378]Canevas au 30 Avril 2023'!T98 -> 0 | L98: ='[379]Canevas au 31 Mai 2023'!T98 -> 0 | M98: ='[380]Canevas au 30 Juin 2023'!T98 -> 0 | N98: ='[381]Canevas au 31 Juillet 2023'!T98 -> 0 | O98: ='[382]Canevas au 31 Août 2023'!T98 -> 0 | P98: ='[383]Canevas au 30 Septembre 2023'!T98 -> 0 | Q98: ='[384]Canevas au 31 Octobre 2023'!T98 -> 0
B99: 717 | C99: ZFIL_M145 | D99: Opex Exploitation & maintenance | E99: Mobile | F99: Bande passante Internet | G99: Centrafrique | H99: ='[375]Canevas au 31 Janvier 2023'!T99 -> 0 | I99: ='[376]Canevas au 29 Février 2023'!T99 -> 0 | J99: ='[377]Canevas au 31 Mars 2023'!T99 -> 0 | K99: ='[378]Canevas au 30 Avril 2023'!T99 -> 0 | L99: ='[379]Canevas au 31 Mai 2023'!T99 -> 0 | M99: ='[380]Canevas au 30 Juin 2023'!T99 -> 0 | N99: ='[381]Canevas au 31 Juillet 2023'!T99 -> 0 | O99: ='[382]Canevas au 31 Août 2023'!T99 -> 0 | P99: ='[383]Canevas au 30 Septembre 2023'!T99 -> 0 | Q99: ='[384]Canevas au 31 Octobre 2023'!T99 -> 0
B100: 2618 | C100: ZFIL_M352 | D100: Opex Exploitation & maintenance | E100: mobile | F100: Fees du contrat GMNS | G100: Centrafrique | H100: ='[375]Canevas au 31 Janvier 2023'!T100 -> 0 | I100: ='[376]Canevas au 29 Février 2023'!T100 -> 0 | J100: ='[377]Canevas au 31 Mars 2023'!T100 -> 0 | K100: ='[378]Canevas au 30 Avril 2023'!T100 -> 0 | L100: ='[379]Canevas au 31 Mai 2023'!T100 -> 0 | M100: ='[380]Canevas au 30 Juin 2023'!T100 -> 0 | N100: ='[381]Canevas au 31 Juillet 2023'!T100 -> 0 | O100: ='[382]Canevas au 31 Août 2023'!T100 -> 0 | P100: ='[383]Canevas au 30 Septembre 2023'!T100 -> 0 | Q100: ='[384]Canevas au 31 Octobre 2023'!T100 -> 0
B101: 723 | C101: ZFIL_M151 | D101: Opex Exploitation & maintenance | E101: Mobile | F101: Matériel de transport (Entretien et locations) | G101: Centrafrique | H101: ='[375]Canevas au 31 Janvier 2023'!T101 -> 2000000 | I101: ='[376]Canevas au 29 Février 2023'!T101 -> 1500000 | J101: ='[377]Canevas au 31 Mars 2023'!T101 -> 1000000 | K101: ='[378]Canevas au 30 Avril 2023'!T101 -> 2913000 | L101: ='[379]Canevas au 31 Mai 2023'!T101 -> 3773415 | M101: ='[380]Canevas au 30 Juin 2023'!T101 -> 4601000 | N101: ='[381]Canevas au 31 Juillet 2023'!T101 -> 3611000 | O101: ='[382]Canevas au 31 Août 2023'!T101 -> 3000000 | P101: ='[383]Canevas au 30 Septembre 2023'!T101 -> 1277050 | Q101: ='[384]Canevas au 31 Octobre 2023'!T101 -> 1500000 | T101: =+'Opex '!P26*10^6 -> 2678000
B102: 724 | C102: ZFIL_M152 | D102: Opex Exploitation & maintenance | E102: Mobile | F102: Maintenance informatique | G102: Centrafrique | H102: ='[375]Canevas au 31 Janvier 2023'!T102 -> 2000000 | I102: ='[376]Canevas au 29 Février 2023'!T102 -> 1800000 | J102: ='[377]Canevas au 31 Mars 2023'!T102 -> 1800000 | K102: ='[378]Canevas au 30 Avril 2023'!T102 -> 800000 | L102: ='[379]Canevas au 31 Mai 2023'!T102 -> 3912567 | M102: ='[380]Canevas au 30 Juin 2023'!T102 -> 3100000 | N102: ='[381]Canevas au 31 Juillet 2023'!T102 -> 1441129 | O102: ='[382]Canevas au 31 Août 2023'!T102 -> 2000000 | P102: ='[383]Canevas au 30 Septembre 2023'!T102 -> 805000 | Q102: ='[384]Canevas au 31 Octobre 2023'!T102 -> 1481129 | T102: =+'Opex '!P27*10^6 -> 3394932
B103: 2617 | C103: ZFIL_M351 | D103: Opex Exploitation & maintenance | E103: mobile | F103: IFRS Lease | G103: Centrafrique | H103: ='[375]Canevas au 31 Janvier 2023'!T103 -> 0 | I103: ='[376]Canevas au 29 Février 2023'!T103 -> 0 | J103: ='[377]Canevas au 31 Mars 2023'!T103 -> 0 | K103: ='[378]Canevas au 30 Avril 2023'!T103 -> 0 | L103: ='[379]Canevas au 31 Mai 2023'!T103 -> 0 | M103: ='[380]Canevas au 30 Juin 2023'!T103 -> 0 | N103: ='[381]Canevas au 31 Juillet 2023'!T103 -> 0 | O103: ='[382]Canevas au 31 Août 2023'!T103 -> 0 | P103: ='[383]Canevas au 30 Septembre 2023'!T103 -> 0 | Q103: ='[384]Canevas au 31 Octobre 2023'!T103 -> 0
B104: 726 | C104: ZFIL_M153 | D104: Opex Frais généraux | E104: Mobile | F104: Frais d'achats d'études, honoraires & CES | G104: Centrafrique | H104: ='[375]Canevas au 31 Janvier 2023'!T104 -> 3000000 | I104: ='[376]Canevas au 29 Février 2023'!T104 -> 3400000 | J104: ='[377]Canevas au 31 Mars 2023'!T104 -> 3500000 | K104: ='[378]Canevas au 30 Avril 2023'!T104 -> 5865378 | L104: ='[379]Canevas au 31 Mai 2023'!T104 -> 3600000 | M104: ='[380]Canevas au 30 Juin 2023'!T104 -> 3776378 | N104: ='[381]Canevas au 31 Juillet 2023'!T104 -> 3909378 | O104: ='[382]Canevas au 31 Août 2023'!T104 -> 4000000 | P104: ='[383]Canevas au 30 Septembre 2023'!T104 -> 4790165 | Q104: ='[384]Canevas au 31 Octobre 2023'!T104 -> 6731378 | T104: =+'Opex '!P30*10^6 -> 7115378
...

Sheet Page de garde
F16: Tableau de bord
H19: Décembre 2023
D23: Filiale Moov - Republique Centraficaine
D34: CONFIDENTIEL

Sheet Sommaire
B3: Table des matières
B6: I . Synthèse Moov RCA | L6: P. 2
B8: 1 . Commentaires | L8: P. 2
B10: 1. Tableau de Cash | L10: P. 3
B12: 2. P&L | L12: P. 4
B14: 3. Opex | L14: P. 5
B15: 4 . Indicateurs Parc | L15: P. 7
B17: 5 . ARPU & Usage | L17: P. 8
B19: 6 . Chiffre d'affaires | L19: P. 9
B21: 7 . Marge brute | L21: P. 10
B23: 8. Mobile Money | L23: P. 11
B25: 9. Trafic | L25: P. 12

Sheet Cash 
A2: Moov RCA : Flux Financier consolidé | N2: -4.174705 | P2: 142.22 | Z2: 146.3947
Z4: 0 | AA4: 8.621609
N5: Mensuel | T5: CUMUL M-1 | Z5: CUMUL | AH5: Annuel
C6: Janvier | D6: Février | E6: Mars | F6: Avril | G6: Mai | H6: Juin | I6: Juillet | J6: Août | K6: Septembre | L6: Octobre | M6: Novembre | N6: 2023 | O6: 2023 Budget | P6: Ecart / Budget | Q6: 2022 Réel | R6: Evol % | T6: 2023 | U6: 2023 Budget | V6: Ecart / Budget | W6: 2021 Réel | X6: Evol % | Z6: 2023 | AA6: 2023 Budget | AB6: Ecart / Budget | AC6: 2022 Réel | AD6: Evol % | AF6: 2023 Actu 1 | AG6: 2023 Actu 2 | AH6: 2023 Actu3 | AI6: 2023 Budget | AJ6: 2020 Actu3 | AK6: 2022 Réel | AL6: Ecart / Budget | AM6: Var Actu1/ Budget (%) | AN6: Var Actu1/ 2018 (%) | AO6: B23/ 2022 (%) | AP6: Var Actu3/ 2019 (%)
A8: EBITDA | C8: -35.396924 | D8: -2.0441189 | E8: -50.161313 | F8: -52.420881 | G8: -52.344836 | H8: -46.847419 | I8: -0.54119978 | J8: 11.749142 | K8: 10.20646 | L8: 210.00689 | M8: 26.632439 | N8: 24.782787 | O8: 188.746 | P8: -163.96322 | Q8: -49.495703 | R8: ns | T8: 18.838241 | U8: 596.02418 | V8: -577.18593 | W8: -113.53462 | X8: ns | Z8: 43.621029 | AA8: 784.77018 | AB8: -741.14915 | AC8: -163.03033 | AD8: ns | AF8: 894.0842 | AI8: 784.77018 | AK8: -163.03033 | AL8: -784.77018 | AM8: ns | AN8: ns | AO8: ns | AP8: ns
A10: Autres résultat non courant ( -) | C10: 0 | D10: 0 | E10: 0 | F10: 0 | G10: 0 | H10: 0 | I10: 0 | J10: 0 | K10: 0 | L10: 0 | M10: 0 | N10: -15.688708 | P10: -15.688708 | Q10: 0 | R10: ns | T10: 0 | U10: 0 | V10: 0 | W10: -61.1 | X10: ns | Z10: -15.688708 | AA10: 0 | AB10: -15.688708 | AC10: -61.1 | AD10: 0.743229 | AF10: 0 | AI10: 0 | AK10: -61.1
A12: Neutralisation de la variation de provisions incluses dans l'Ebitda (-) | C12: 2 | D12: 2 | E12: -50.423 | F12: 3 | G12: 3 | H12: 5.88 | I12: 2 | J12: 2 | K12: 0.21534 | L12: 3.177 | M12: -38.2 | N12: 43.11066 | O12: 1.8 | P12: 41.31066 | Q12: -25.380195 | R12: ns | T12: -65.35066 | U12: 17.155484 | V12: -82.506144 | W12: 17.575098 | X12: ns | Z12: -22.24 | AA12: 18.955484 | AB12: -41.195484 | AC12: -7.8050977 | AD12: -1.8494198 | AF12: -30.4998 | AI12: 18.955484 | AK12: -7.8050977 | AL12: -18.955484 | AM12: ns | AN12: ns | AO12: ns | AP12: ns
AN13: ns
A14: Variation de BFR opérationnel (+/-) | C14: -1031.6071 | D14: 1077.7852 | E14: 513.28175 | F14: 74.897301 | G14: 133.11722 | H14: 284.03278 | I14: 153.89029 | J14: -59.950994 | K14: 378.22519 | L14: -152.42723 | M14: 40.379556 | N14: 1244.2013 | O14: 57.731459 | P14: 1186.4698 | Q14: 220.16609 | R14: 4.651194 | S14: 0 | T14: 1411.5239 | U14: 755.39224 | V14: 656.13167 | W14: 669.52263 | X14: 1.1082542 | Z14: 2655.7252 | AA14: 813.1237 | AB14: 1842.6015 | AC14: 889.68872 | AD14: 1.9850049 | AF14: 741.59604 | AI14: 813.1237 | AK14: 889.68872 | AL14: -813.1237 | AM14: ns | AN14: ns | AO14: -0.086058211 | AP14: ns
C15: 0 | D15: 0 | E15: 0 | F15: 0 | G15: 0 | H15: 0 | I15: 0 | J15: 0 | K15: 0 | L15: 0 | M15: 0 | N15: 0 | O15: #REF! | P15: #REF! | Q15: 0 | R15: ns | T15: 0 | V15: 0 | W15: 0 | X15: ns | Z15: 0 | AB15: 0 | AC15: 0 | AD15: ns | AK15: 0 | AL15: 0 | AM15: ns | AN15: ns
A16: Flux net de cash flow provenant des activités opérationnelles avant impôt | C16: #REF! | D16: #REF! | E16: #REF! | F16: #REF! | G16: #REF! | H16: #REF! | I16: #REF! | J16: #REF! | K16: #REF! | L16: #REF! | M16: #REF! | N16: #REF! | O16: #REF! | P16: #REF! | Q16: #REF! | R16: #REF! | T16: #REF! | V16: #REF! | W16: #REF! | X16: #REF! | Z16: #REF! | AB16: #REF! | AC16: #REF! | AD16: #REF! | AK16: #REF! | AL16: 0 | AM16: ns | AN16: #REF!
C17: #REF! | D17: #REF! | E17: #REF! | F17: #REF! | G17: #REF! | H17: #REF! | I17: #REF! | J17: #REF! | K17: #REF! | L17: #REF! | M17: #REF! | N17: #REF! | O17: #REF! | P17: #REF! | Q17: #REF! | R17: #REF! | T17: #REF! | V17: #REF! | W17: #REF! | X17: #REF! | Z17: #REF! | AB17: #REF! | AC17: #REF! | AD17: #REF! | AK17: #REF! | AL17: 0 | AM17: ns | AN17: #REF!
A18: Dividendes reçus de sociétés mises en équivalence (+) | C18: #REF! | D18: #REF! | E18: #REF! | F18: #REF! | G18: #REF! | H18: #REF! | I18: #REF! | J18: #REF! | K18: #REF! | L18: #REF! | M18: #REF! | N18: #REF! | O18: #REF! | P18: #REF! | Q18: #REF! | R18: #REF! | T18: #REF! | V18: #REF! | W18: #REF! | X18: #REF! | Z18: #REF! | AB18: #REF! | AC18: #REF! | AD18: #REF! | AK18: #REF! | AL18: 0 | AM18: ns | AN18: #REF!
A19: Dividendes reçus des participations non consolidées (+) | C19: #REF! | D19: #REF! | E19: #REF! | F19: #REF! | G19: #REF! | H19: #REF! | I19: #REF! | J19: #REF! | K19: #REF! | L19: #REF! | M19: #REF! | N19: #REF! | O19: #REF! | P19: #REF! | Q19: #REF! | R19: #REF! | T19: #REF! | V19: #REF! | W19: #REF! | X19: #REF! | Z19: #REF! | AB19: #REF! | AC19: #REF! | AD19: #REF! | AK19: #REF! | AL19: 0 | AM19: ns | AN19: #REF!
C20: #REF! | D20: #REF! | E20: #REF! | F20: #REF! | G20: #REF! | H20: #REF! | I20: #REF! | J20: #REF! | K20: #REF! | L20: #REF! | M20: #REF! | N20: #REF! | O20: #REF! | P20: #REF! | Q20: #REF! | R20: #REF! | T20: #REF! | V20: #REF! | W20: #REF! | X20: #REF! | Z20: #REF! | AB20: #REF! | AC20: #REF! | AD20: #REF! | AK20: #REF! | AL20: 0 | AM20: ns | AN20: #REF!
A21: CFFO avant capex | C21: 0 | D21: 0 | E21: 0 | F21: 0 | G21: 0 | H21: 0 | I21: 0 | J21: 0 | K21: 0 | L21: 0 | M21: 0 | N21: 0 | O21: #REF! | P21: #REF! | Q21: 0 | R21: ns | T21: 0 | V21: 0 | W21: 0 | X21: ns | Z21: 0 | AB21: 0 | AC21: 0 | AD21: ns | AK21: 0 | AL21: 0 | AM21: ns | AN21: ns | AO21: #DIV/0!
A22: Investissements en SIMs | O22: 0 | P22: 0 | R22: ns | AL22: 0 | AM22: ns | AN22: ns | AO22: ns
A23: Investissements nets (Capex brutes - cession d'immo.) (-) | C23: -4.417442 | D23: -6.207719 | E23: -40.9 | F23: -8.8751244 | G23: -9.0265526 | H23: -10.940375 | I23: -10.857476 | J23: -39.247704 | K23: -3.839499 | L23: -19.762526 | M23: -2.874499 | N23: -1469.7964 | O23: -74.600871 | P23: -1395.1955 | Q23: -10.863914 | R23: -134.2916 | T23: -156.84894 | U23: -3665.3992 | V23: 3508.5503 | W23: -102.55571 | X23: -0.52940221 | Z23: -1626.6453 | AA23: -3740.0001 | AB23: 2113.3548 | AC23: -113.41963 | AD23: -13.341832 | AF23: -3739.9804 | AI23: -3740.0001 | AK23: -113.41963 | AL23: 3740.0001 | AM23: ns | AN23: ns | AO23: 31.974892 | AP23: ns
A24: Neutralisation element non cash
O25: 0
A26: Produits de cession d'immobilisations | O26: 0
A27: CFFO | C27: -1069.4215 | D27: 1071.5333 | E27: 371.79743 | F27: 16.601295 | G27: 74.745834 | H27: 232.12499 | I27: 144.49161 | J27: -85.449557 | K27: 384.8075 | L27: 40.994134 | M27: 25.937496 | N27: -173.39033 | O27: 173.67659 | P27: -347.06692 | Q27: 134.42628 | R27: ns | T27: 1208.1626 | U27: -2296.8273 | V27: 3504.9898 | W27: 409.90739 | X27: 1.9474037 | Z27: 1034.7722 | AA27: -2123.1507 | AB27: 3157.9229 | AC27: 544.33367 | AD27: 0.90098883 | AF27: -2134.7999 | AI27: -2123.1507 | AK27: 544.33367 | AL27: 2123.1507 | AM27: ns | AN27: ns | AO27: ns | AP27: ns
A29: Résultat financier hors dividendes des sociétés non consolidées (+/-) | C29: -15 | D29: 0 | E29: -36.1 | F29: -12.04875 | G29: -7.108665 | H29: 9.624156 | I29: -28.38998 | J29: -18 | K29: -22.3326 | L29: -18.705842 | M29: -57.75 | N29: -53.488319 | O29: -41.676592 | P29: -11.811727 | Q29: -14.08724 | R29: -2.7969339 | T29: -205.81168 | U29: -479.04269 | V29: 273.23101 | W29: -499.84343 | X29: 0.5882477 | Z29: -259.3 | AA29: -520.71928 | AB29: 261.41928 | AC29: -513.93066 | AD29: 0.49545723 | AF29: -237.10007 | AI29: -520.71928 | AK29: -513.93066 | AL29: 520.71928 | AM29: ns | AN29: ns | AO29: -0.013209206 | AP29: ns
A31: Impôts payés (-) | C31: 0 | D31: 0 | E31: 0 | F31: 0 | G31: 0 | H31: 0 | I31: 0 | J31: 0 | K31: 0 | L31: 0 | M31: 0 | N31: 0 | P31: 0 | Q31: 0 | R31: ns | U31: -62.130023 | V31: 62.130023 | X31: ns | AA31: -62.130023 | AB31: 62.130023 | AD31: ns | AI31: -62.130023 | AL31: 62.130023 | AM31: ns | AN31: ns | AO31: ns
A33: Intérêts financiers payés + produits financiers encaissés | C33: 0 | D33: 0 | E33: 0 | F33: 0 | G33: 0 | H33: 0 | I33: 0 | J33: 0 | K33: 0 | L33: 0 | M33: 0 | N33: 0 | Q33: 0 | CS33: Intérêts financiers payés + produits financiers encaissés | CT33: Intérêts financiers payés + produits financiers encaissés | CU33: Intérêts financiers payés + produits financiers encaissés | CV33: Intérêts financiers payés + produits financiers encaissés | CW33: Intérêts financiers payés + produits financiers encaissés | CX33: Intérêts financiers payés + produits financiers encaissés | CY33: Intérêts financiers payés + produits financiers encaissés | CZ33: Intérêts financiers payés + produits financiers encaissés | DA33: Intérêts financiers payés + produits financiers encaissés | DB33: Intérêts financiers payés + produits financiers encaissés | DC33: Intérêts financiers payés + produits financiers encaissés | DD33: Intérêts financiers payés + produits financiers encaissés | DE33: Intérêts financiers payés + produits financiers encaissés | DF33: Intérêts financiers payés + produits financiers encaissés | DG33: Intérêts financiers payés + produits financiers encaissés | DH33: Intérêts financiers payés + produits financiers encaissés | DI33: Intérêts financiers payés + produits financiers encaissés | DJ33: Intérêts financiers payés + produits financiers encaissés | DK33: Intérêts financiers payés + produits financiers encaissés | DL33: Intérêts financiers payés + produits financiers encaissés | DM33: Intérêts financiers payés + produits financiers encaissés | DN33: Intérêts financiers payés + produits financiers encaissés | DO33: Intérêts financiers payés + produits financiers encaissés | DP33: Intérêts financiers payés + produits financiers encaissés | DQ33: Intérêts financiers payés + produits financiers encaissés | DR33: Intérêts financiers payés + produits financiers encaissés | DS33: Intérêts financiers payés + produits financiers encaissés | DT33: Intérêts financiers payés + produits financiers encaissés | DU33: Intérêts financiers payés + produits financiers encaissés | DV33: Intérêts financiers payés + produits financiers encaissés | DW33: Intérêts financiers payés + produits financiers encaissés | DX33: Intérêts financiers payés + produits financiers encaissés | DY33: Intérêts financiers payés + produits financiers encaissés | DZ33: Intérêts financiers payés + produits financiers encaissés | EA33: Intérêts financiers payés + produits financiers encaissés | EB33: Intérêts financiers payés + produits financiers encaissés | EC33: Intérêts financiers payés + produits financiers encaissés | ED33: Intérêts financiers payés + produits financiers encaissés | EE33: Intérêts financiers payés + produits financiers encaissés | EF33: Intérêts financiers payés + produits financiers encaissés | EG33: Intérêts financiers payés + produits financiers encaissés | EH33: Intérêts financiers payés + produits financiers encaissés | EI33: Intérêts financiers payés + produits financiers encaissés | EJ33: Intérêts financiers payés + produits financiers encaissés | EK33: Intérêts financiers payés + produits financiers encaissés | EL33: Intérêts financiers payés + produits financiers encaissés | EM33: Intérêts financiers payés + produits financiers encaissés | EN33: Intérêts financiers payés + produits financiers encaissés | EO33: Intérêts financiers payés + produits financiers encaissés | EP33: Intérêts financiers payés + produits financiers encaissés | EQ33: Intérêts financiers payés + produits financiers encaissés | ER33: Intérêts financiers payés + produits financiers encaissés | ES33: Intérêts financiers payés + produits financiers encaissés | ET33: Intérêts financiers payés + produits financiers encaissés | EU33: Intérêts financiers payés + produits financiers encaissés | EV33: Intérêts financiers payés + produits financiers encaissés | EW33: Intérêts financiers payés + produits financiers encaissés | EX33: Intérêts financiers payés + produits financiers encaissés | EY33: Intérêts financiers payés + produits financiers encaissés | EZ33: Intérêts financiers payés + produits financiers encaissés | FA33: Intérêts financiers payés + produits financiers encaissés | FB33: Intérêts financiers payés + produits financiers encaissés | FC33: Intérêts financiers payés + produits financiers encaissés | FD33: Intérêts financiers payés + produits financiers encaissés | FE33: Intérêts financiers payés + produits financiers encaissés | FF33: Intérêts financiers payés + produits financiers encaissés | FG33: Intérêts financiers payés + produits financiers encaissés | FH33: Intérêts financiers payés + produits financiers encaissés | FI33: Intérêts financiers payés + produits financiers encaissés | FJ33: Intérêts financiers payés + produits financiers encaissés | FK33: Intérêts financiers payés + produits financiers encaissés | FL33: Intérêts financiers payés + produits financiers encaissés | FM33: Intérêts financiers payés + produits financiers encaissés | FN33: Intérêts financiers payés + produits financiers encaissés | FO33: Intérêts financiers payés + produits financiers encaissés | FP33: Intérêts financiers payés + produits financiers encaissés | FQ33: Intérêts financiers payés + produits financiers encaissés | FR33: Intérêts financiers payés + produits financiers encaissés | FS33: Intérêts financiers payés + produits financiers encaissés | FT33: Intérêts financiers payés + produits financiers encaissés | FU33: Intérêts financiers payés + produits financiers encaissés | FV33: Intérêts financiers payés + produits financiers encaissés | FW33: Intérêts financiers payés + produits financiers encaissés | FX33: Intérêts financiers payés + produits financiers encaissés | FY33: Intérêts financiers payés + produits financiers encaissés | FZ33: Intérêts financiers payés + produits financiers encaissés | GA33: Intérêts financiers payés + produits financiers encaissés | GB33: Intérêts financiers payés + produits financiers encaissés | GC33: Intérêts financiers payés + produits financiers encaissés | GD33: Intérêts financiers payés + produits financiers encaissés | GE33: Intérêts financiers payés + produits financiers encaissés | GF33: Intérêts financiers payés + produits financiers encaissés | GG33: Intérêts financiers payés + produits financiers encaissés | GH33: Intérêts financiers payés + produits financiers encaissés | GI33: Intérêts financiers payés + produits financiers encaissés | GJ33: Intérêts financiers payés + produits financiers encaissés | GK33: Intérêts financiers payés + produits financiers encaissés | GL33: Intérêts financiers payés + produits financiers encaissés | GM33: Intérêts financiers payés + produits financiers encaissés | GN33: Intérêts financiers payés + produits financiers encaissés | GO33: Intérêts financiers payés + produits financiers encaissés | GP33: Intérêts financiers payés + produits financiers encaissés | GQ33: Intérêts financiers payés + produits financiers encaissés | GR33: Intérêts financiers payés + produits financiers encaissés | GS33: Intérêts financiers payés + produits financiers encaissés | GT33: Intérêts financiers payés + produits financiers encaissés | GU33: Intérêts financiers payés + produits financiers encaissés | GV33: Intérêts financiers payés + produits financiers encaissés | GW33: Intérêts financiers payés + produits financiers encaissés | GX33: Intérêts financiers payés + produits financiers encaissés | GY33: Intérêts financiers payés + produits financiers encaissés | GZ33: Intérêts financiers payés + produits financiers encaissés | HA33: Intérêts financiers payés + produits financiers encaissés | HB33: Intérêts financiers payés + produits financiers encaissés | HC33: Intérêts financiers payés + produits financiers encaissés | HD33: Intérêts financiers payés + produits financiers encaissés | HE33: Intérêts financiers payés + produits financiers encaissés | HF33: Intérêts financiers payés + produits financiers encaissés | HG33: Intérêts financiers payés + produits financiers encaissés | HH33: Intérêts financiers payés + produits financiers encaissés | HI33: Intérêts financiers payés + produits financiers encaissés | HJ33: Intérêts financiers payés + produits financiers encaissés | HK33: Intérêts financiers payés + produits financiers encaissés | HL33: Intérêts financiers payés + produits financiers encaissés | HM33: Intérêts financiers payés + produits financiers encaissés | HN33: Intérêts financiers payés + produits financiers encaissés | HO33: Intérêts financiers payés + produits financiers encaissés | HP33: Intérêts financiers payés + produits financiers encaissés | HQ33: Intérêts financiers payés + produits financiers encaissés | HR33: Intérêts financiers payés + produits financiers encaissés | HS33: Intérêts financiers payés + produits financiers encaissés | HT33: Intérêts financiers payés + produits financiers encaissés | HU33: Intérêts financiers payés + produits financiers encaissés | HV33: Intérêts financiers payés + produits financiers encaissés | HW33: Intérêts financiers payés + produits financiers encaissés | HX33: Intérêts financiers payés + produits financiers encaissés | HY33: Intérêts financiers payés + produits financiers encaissés | HZ33: Intérêts financiers payés + produits financiers encaissés | IA33: Intérêts financiers payés + produits financiers encaissés | IB33: Intérêts financiers payés + produits financiers encaissés | IC33: Intérêts financiers payés + produits financiers encaissés | ID33: Intérêts financiers payés + produits financiers encaissés | IE33: Intérêts financiers payés + produits financiers encaissés | IF33: Intérêts financiers payés + produits financiers encaissés | IG33: Intérêts financiers payés + produits financiers encaissés | IH33: Intérêts financiers payés + produits financiers encaissés | II33: Intérêts financiers payés + produits financiers encaissés | IJ33: Intérêts financiers payés + produits financiers encaissés | IK33: Intérêts financiers payés + produits financiers encaissés | IL33: Intérêts financiers payés + produits financiers encaissés | IM33: Intérêts financiers payés + produits financiers encaissés | IN33: Intérêts financiers payés + produits financiers encaissés | IO33: Intérêts financiers payés + produits financiers encaissés | IP33: Intérêts financiers payés + produits financiers encaissés | IQ33: Intérêts financiers payés + produits financiers encaissés | IR33: Intérêts financiers payés + produits financiers encaissés | IS33: Intérêts financiers payés + produits financiers encaissés | IT33: Intérêts financiers payés + produits financiers encaissés | IU33: Intérêts financiers payés + produits financiers encaissés | IV33: Intérêts financiers payés + produits financiers encaissés | IW33: Intérêts financiers payés + produits financiers encaissés | IX33: Intérêts financiers payés + produits financiers encaissés | IY33: Intérêts financiers payés + produits financiers encaissés | IZ33: Intérêts financiers payés + produits financiers encaissés | JA33: Intérêts financiers payés + produits financiers encaissés | JB33: Intérêts financiers payés + produits financiers encaissés | JC33: Intérêts financiers payés + produits financiers encaissés | JD33: Intérêts financiers payés + produits financiers encaissés | JE33: Intérêts financiers payés + produits financiers encaissés | JF33: Intérêts financiers payés + produits financiers encaissés | JG33: Intérêts financiers payés + produits financiers encaissés | JH33: Intérêts financiers payés + produits financiers encaissés
A34: Dividendes payés (-) | C34: 0 | D34: 0 | E34: 0 | F34: 0 | G34: 0 | H34: 0 | I34: 0 | J34: 0 | K34: 0 | L34: 0 | M34: 0 | N34: 0 | Q34: 0
A35: Cash flow used for financing and taxes | C35: -15 | D35: 0 | E35: -36.1 | F35: -12.04875 | G35: -7.108665 | H35: 9.624156 | I35: -28.38998 | J35: -18 | K35: -22.3326 | L35: -18.705842 | M35: -57.75 | N35: -53.488319 | Q35: -14.08724
A36: Decaissements solde antériorité (-)
C38: -15 | D38: 0 | E38: -36.1 | F38: -12.04875 | G38: -7.108665 | H38: 9.624156 | I38: -28.38998 | J38: -18 | K38: -22.3326 | L38: -18.705842 | M38: -57.75 | N38: -53.488319 | O38: -41.676592 | P38: -11.811727 | Q38: -14.08724 | R38: -2.7969339 | S38: 0 | T38: -205.81168 | U38: -541.17271 | V38: 335.36103 | W38: -499.84343 | X38: 0.5882477 | Z38: -259.3 | AA38: -582.8493 | AB38: 323.5493 | AC38: -513.93066 | AD38: 0.49545723 | AF38: -237.10007 | AI38: -582.8493 | AK38: -513.93066 | AL38: 582.8493 | AM38: ns | AN38: ns | AO38: -0.13410104
A40: Cash flow used for investment (+/-) | C40: 0 | D40: 0 | E40: 0 | F40: 0 | G40: 0 | H40: 0 | I40: 0 | J40: 0 | K40: 0 | L40: 0 | M40: 745.33 | N40: 0.3 | P40: 0.3 | Q40: 0 | R40: ns | T40: 745.33 | U40: 0 | V40: 745.33 | W40: 6.1 | X40: 121.18525 | Z40: 745.63 | AA40: 0 | AB40: 745.63 | AC40: 6.1 | AD40: 121.23443 | AF40: 0 | AI40: 0 | AK40: 6.1 | AL40: 0 | AM40: ns | AN40: ns | AO40: ns | AP40: ns
AM41: ns
A42: Elements non cash | C42: -102.27137 | D42: -119 | E42: -126.2 | F42: -101.32034 | G42: -128.08311 | H42: -131.12416 | I42: -98.471234 | J42: -73.233975 | K42: 11308.893 | L42: -31.234158 | M42: 8.31 | N42: 12.518319 | O42: 0 | Q42: -126.29796 | R42: ns | T42: 10406.264 | U42: 0 | W42: -1017.8493 | X42: ns | Z42: 10418.783 | AA42: 0 | AC42: -1144.1473 | AD42: ns | AF42: 10412.836 | AI42: 0 | AK42: -1144.1473 | AL42: 0 | AM42: ns | AN42: ns | AO42: ns | AP42: ns
A44: Net cash flow | C44: -1186.6929 | D44: 952.53331 | E44: 209.49743 | F44: -96.767792 | G44: -60.445944 | H44: 110.62499 | I44: 17.6304 | J44: -176.68353 | K44: 11671.367 | L44: -8.945866 | M44: 721.8275 | N44: -214.06033 | O44: 132 | P44: -346.06033 | Q44: -5.958921 | R44: -34.922667 | T44: 12153.945 | U44: -2838 | V44: 14991.945 | W44: -1101.6853 | X44: ns | Z44: 11939.885 | AA44: -2706 | AB44: 14645.885 | AC44: -1107.6443 | AD44: ns | AF44: 8040.9359 | AI44: -2706 | AK44: -1107.6443 | AL44: 2706 | AM44: ns | AN44: ns | AO44: -1.4430226 | AP44: ns
A46: Dettes brutes | C46: -18486.424 | D46: -18605.835 | E46: -18455.984 | F46: -18562.984 | G46: -18634.176 | H46: -18476.309 | I46: -18603.17 | J46: -18694.004 | K46: -6969.1424 | L46: -7018.5824 | M46: -7068.0224 | N46: -6846.3357 | O46: -10127.25 | P46: 3280.914 | Q46: -18384.835 | R46: -0.62760962 | T46: -7068.0224 | U46: -10259.25 | V46: 3191.2273 | W46: -18396.771 | X46: -0.61580093 | Z46: -6846.3357 | AA46: -10127.25 | AB46: 3280.914 | AC46: -18384.835 | AD46: -0.62760962 | AF46: -10324.764 | AI46: -10127.25 | AK46: -18384.835 | AL46: 10127.25 | AM46: ns | AN46: #REF! | AO46: 0.449152 | AP46: #REF!
A48: Trésorerie brute (+) | C48: 41.645075 | D48: 5.945667 | E48: 65.621958 | F48: 75.854166 | G48: 86.6 | H48: 39.357943 | I48: 183.84956 | J48: 98 | K48: 44.505866 | L48: 85 | M48: 856.2675 | N48: 420.52048 | O48: 0 | P48: 420.52048 | Q48: 19.10522 | R48: 21.010764 | T48: 856.2675 | V48: 856.2675 | W48: 37 | X48: 22.142365 | Z48: 420.52048 | AB48: 420.52048 | AC48: 19.10522 | AD48: 21.010764 | AF48: 0 | AI48: 0 | AK48: 19.10522 | AL48: 0 | AM48: ns | AN48: ns | AO48: ns | AP48: ns
A50: Trésorerie nette fin de période | C50: -18444.779 | D50: -18599.889 | E50: -18390.362 | F50: -18487.13 | G50: -18547.576 | H50: -18436.951 | I50: -18419.32 | J50: -18596.004 | K50: -6924.6365 | L50: -6933.5824 | M50: -6211.7549 | N50: -6425.8152 | O50: -10127.25 | P50: 3701.4345 | Q50: -18365.73 | R50: 0.65011926 | T50: -6211.7549 | U50: -10259.25 | V50: 4047.4948 | W50: -18359.771 | X50: 0.6616649 | Z50: -6425.8152 | AA50: -10127.25 | AB50: 3701.4345 | AC50: -18365.73 | AD50: 0.65011926 | AF50: -10324.764 | AI50: -10127.25 | AK50: -18365.73 | AL50: 10127.25 | AM50: ns | AN50: ns | AO50: -0.44857897 | AP50: ns
A52: Trésorerie nette début de période | T52: -18365.7 | W52: -17258.086 | Z52: -18365.7 | AC52: -17258.086 | AK52: -17258.086 | AM52: ns
AA54: -6425.8152

Sheet P&L 
B2: Moov - RCA : P&L | AA2: -0.79344379
O4: MENSUEL | U4: CUMUL (m-1) | AA4: CUMUL | AK4: ANNUEL
D5: Janvier | E5: Février | F5: Mars | G5: Avril | H5: Mai | I5: Juin | J5: Juillet | K5: Août | L5: Septembre | M5: Octobre | N5: Novembre | O5: 2023 | P5: 2023 Budget | Q5: Ecart / Budget | R5: 2022 Réel | S5: Evol % | U5: 2023 | V5: 2023 Budget | W5: Ecart / Budget | X5: 2021 Réel | Y5: Evol % | AA5: 2023 | AB5: 2023 Budget | AC5: Ecart / Budget | AD5: 2022 Réel | AE5: Evol % | AG5: 2017 Actu 1 | AH5: 2017 Actu 2 | AI5: 2023 Actu 1 | AJ5: 2023 Actu 2 | AK5: 2023 Actu3 | AL5: 2023 Budget | AM5: 2019 Actu3 | AN5: 2022 Réel | AO5: Ecart / Budget | AP5: Var Actu1/ Budget (%) | AQ5: Var Actu1/ 2018 (%) | AR5: B23/ 2022 (%) | AS5: Var Actu3/ 2019 (%) | AT5: Var Actu1/ 2017 (%)
B7: Chiffre d'affaires | D7: 308.61504 | E7: 300.96135 | F7: 317.29534 | G7: 317.9 | H7: 345.63525 | I7: 328.565 | J7: 354.14007 | K7: 373.72891 | L7: 365.64251 | M7: 394.72369 | N7: 368.20351 | O7: 374.89057 | P7: 575.53449 | Q7: -200.64392 | R7: 315.53342 | S7: 0.18811686 | U7: 3775.4107 | V7: 4580.7294 | W7: -805.31869 | X7: 3545.3164 | Y7: 0.064900928 | AA7: 4150.3013 | AB7: 5156.2639 | AC7: -1005.9626 | AD7: 3860.8498 | AE7: 0.074970925 | AG7: 4718.995 | AH7: 4718.6895 | AI7: 5156.1148 | AL7: 5156.2639 | AN7: 3860.8498 | AO7: 1295.4141 | AP7: -2.8906658e-05 | AQ7: 0.33548703 | AR7: 0.33552564 | AS7: ns | AT7: 3860.2941
B8: Services | D8: 302.51504 | E8: 296.06135 | F8: 312.39534 | G8: 314.12819 | H8: 336.75726 | I8: 320.67887 | J8: 346.22285 | K8: 365.92891 | L8: 358.24251 | M8: 389.92369 | N8: 363.20351 | O8: 366.38213 | P8: 562.35455 | Q8: -195.97243 | R8: 309.5856 | S8: 0.18345987 | U8: 3706.0575 | V8: 4483.4152 | W8: -777.35771 | X8: 3492.7382 | Y8: 0.061075108 | AA8: 4072.4397 | AB8: 5045.7698 | AC8: -973.33014 | AD8: 3802.3238 | AE8: 0.071039689 | AG8: 4619.8687 | AH8: 4643.7486 | AI8: 5080.443 | AL8: 5045.7698 | AN8: 3802.3238 | AO8: 1243.446 | AP8: 0.0068717386 | AQ8: 0.33614161 | AR8: 0.32702266 | AS8: ns
B9: Equipements | D9: 6.1 | E9: 4.9 | F9: 4.9 | G9: 3.7718106 | H9: 8.8779833 | I9: 7.886132 | J9: 7.917225 | K9: 7.8 | L9: 7.4 | M9: 4.8 | N9: 5 | O9: 8.508442 | P9: 13.179939 | Q9: -4.6714974 | R9: 5.947819 | S9: 0.43051461 | U9: 69.353151 | V9: 97.314132 | W9: -27.960982 | X9: 52.578192 | Y9: 0.31904785 | AA9: 77.861593 | AB9: 110.49407 | AC9: -32.632479 | AD9: 58.526011 | AE9: 0.33037587 | AG9: 99.126234 | AH9: 74.940828 | AI9: 75.671811 | AL9: 110.49407 | AN9: 58.526011 | AO9: 51.968061 | AP9: -0.31515049 | AQ9: 0.29296033 | AR9: 0.88794811 | AS9: ns
AI10: 0 | AL10: 0
B11: Coût des ventes | D11: -56.293099 | E11: -54.923423 | F11: -55.856001 | G11: -58.488376 | H11: -62.998653 | I11: -64.257158 | J11: -68.224515 | K11: -70.58647 | L11: -71.46869 | M11: -82.125007 | N11: -86.50999 | O11: -81.918077 | P11: -96.750103 | Q11: -14.832026 | R11: -71.378209 | S11: 0.14766226 | U11: -731.73138 | V11: -790.36485 | W11: -58.633464 | X11: -697.97246 | Y11: 0.048367122 | AA11: -813.64946 | AB11: -887.11495 | AC11: -73.46549 | AD11: -769.35067 | AE11: 0.057579449 | AG11: -1285.1415 | AH11: -1314.6028 | AI11: -922.94242 | AL11: -887.11495 | AN11: -769.35067 | AO11: -117.76428 | AP11: -0.040386498 | AQ11: 0.19963815 | AR11: -0.1530697 | AS11: ns
B13: Marge Brute | D13: 252.32194 | E13: 246.03792 | F13: 261.43934 | G13: 259.41162 | H13: 282.63659 | I13: 264.30784 | J13: 285.91556 | K13: 303.14244 | L13: 294.17382 | M13: 312.59869 | N13: 281.69352 | O13: 292.97249 | P13: 478.78439 | Q13: -185.8119 | R13: 244.15521 | S13: 0.19994367 | U13: 3043.6793 | V13: 3790.3645 | W13: -746.68523 | X13: 2847.3439 | Y13: 0.068953877 | AA13: 3336.6518 | AB13: 4269.1489 | AC13: -932.49712 | AD13: 3091.4991 | AE13: 0.079298969 | AG13: 3433.8535 | AH13: 3404.0867 | AI13: 4233.1724 | AL13: 4269.1489 | AN13: 3091.4991 | AO13: 1177.6498 | AP13: -0.0084270934 | AQ13: 0.3692944 | AR13: 0.38093164 | AS13: ns
B14: Taux de marge brute (%) | D14: 0.81759444 | E14: 0.81750672 | F14: 0.82396212 | G14: 0.81601643 | H14: 0.81773082 | I14: 0.80443091 | J14: 0.80735161 | K14: 0.81112922 | L14: 0.80453944 | M14: 0.79194305 | N14: 0.76504844 | O14: 0.78148803 | P14: 0.83189521 | Q14: -5.0407184 | R14: 0.77378558 | S14: 0.77024524 | U14: 0.80618496 | V14: 0.82745873 | W14: -2.1273776 | X14: 0.8031283 | Y14: 0.30566585 | AA14: 0.80395412 | AB14: 0.82795393 | AC14: -2.3999807 | AD14: 0.80073022 | AE14: 0.3223897 | AG14: 0.72766628 | AH14: 0.72140511 | AI14: 0.82100041 | AL14: 0.82795393 | AN14: 0.80073022 | AO14: 2.7223704 | AP14: -0.69535127 | AQ14: 2.0270191 | AR14: 2.7223704 | AS14: -80.073022
B15: Coûts opérationnels | D15: -287.71886 | E15: -248.08204 | F15: -311.60066 | G15: -311.83251 | H15: -334.98143 | I15: -311.15526 | J15: -286.45676 | K15: -291.3933 | L15: -283.96736 | M15: -102.59179 | N15: -255.06108 | O15: -268.18971 | P15: -290.03839 | Q15: -21.848679 | R15: -293.65091 | S15: -0.086705682 | U15: -3024.8411 | V15: -3194.3403 | W15: -169.49929 | X15: -2960.8785 | Y15: 0.021602554 | AA15: -3293.0308 | AB15: -3484.3787 | AC15: -191.34797 | AD15: -3254.5294 | AE15: 0.011830078 | AG15: -3384.769 | AH15: -3358.6879 | AI15: -3339.0882 | AL15: -3484.3787 | AN15: -3254.5294 | AO15: -229.84931 | AP15: 0.041697687 | AQ15: 0.025981874 | AR15: -0.070624437 | AS15: ns
B17: EBITDA | D17: -35.396924 | E17: -2.0441189 | F17: -50.161313 | G17: -52.420881 | H17: -52.344836 | I17: -46.847419 | J17: -0.54119978 | K17: 11.749142 | L17: 10.20646 | M17: 210.00689 | N17: 26.632439 | O17: 24.782787 | P17: 188.746 | Q17: -163.96322 | R17: -49.495703 | S17: ns | U17: 18.838241 | V17: 596.02418 | W17: -577.18593 | X17: -113.53462 | Y17: ns | AA17: 43.621029 | AB17: 784.77018 | AC17: -741.14915 | AD17: -163.03033 | AE17: ns | AG17: 49.084496 | AH17: 45.39884 | AI17: 894.0842 | AL17: 784.77018 | AN17: -163.03033 | AO17: 947.80051 | AP17: 0.13929431 | AQ17: ns | AR17: ns | AS17: ns
B18: Marge d'Ebitda (%) | D18: -0.11469604 | E18: -0.0033533433 | F18: -0.054118937 | G18: -0.042112847 | H18: -0.032912856 | I18: -0.024412769 | J18: -0.0002380876 | K18: 0.00443893 | L18: 0.0033880551 | M18: 0.06163608 | N18: 0.0070541832 | O18: 0.0059713225 | P18: 0.32794907 | Q18: -32.197775 | R18: -0.012819899 | U18: 0.0049897198 | V18: 0.13011556 | W18: -12.512584 | X18: -0.032023834 | Y18: 3.7013554 | AA18: 0.010510328 | AB18: 0.15219744 | AC18: -14.168712 | AD18: -0.04222654 | AE18: 5.2736868 | AG18: 0.010401472 | AH18: 0.0096210696 | AI18: 0.17340269 | AL18: 0.15219744 | AN18: -0.04222654 | AO18: 19.442398 | AP18: 2.120525 | AQ18: 21.562923 | AR18: 19.442398 | AS18: 4.222654
B19: Amortissements et déprec. Courant | D19: -186 | E19: -190.20877 | F19: -190.25877 | G19: 16.602385 | H19: -138.8621 | I19: -140.47944 | J19: -139.10884 | K19: -139.36394 | L19: -140.70207 | M19: -139.74902 | N19: -139.74902 | O19: -142.79902 | P19: -206.89399 | Q19: -64.094973 | R19: -166.20717 | S19: -0.14083719 | U19: -1527.8796 | V19: -2195.9768 | W19: -668.09719 | X19: -2088.4551 | Y19: -0.26841637 | AA19: -1670.6786 | AB19: -2402.8707 | AC19: -732.19216 | AD19: -2254.6623 | AE19: -0.2590116 | AG19: -744.46314 | AH19: -739.62521 | AI19: -2011.0651 | AL19: -2402.8707 | AN19: -2254.6623 | AO19: -148.20849 | AP19: 0.16305729 | AQ19: -0.10804151 | AR19: -0.065734231 | AS19: ns
B20: Dotations (amo. et provisions non courants) | Q20: 0 | S20: ns | U20: 0 | W20: 0 | X20: 0 | Y20: ns | AA20: 0 | AC20: 0 | AD20: 0 | AE20: ns | AN20: 0 | AO20: 0 | AP20: ns | AQ20: ns | AR20: ns | AS20: ns
B21: Autres non courant | D21: 0 | E21: 0 | F21: 0 | G21: 0 | H21: 0 | I21: 0 | J21: 0 | K21: 0 | L21: 0 | M21: 0 | N21: 0 | O21: -15.688708 | Q21: 15.688708 | S21: ns | U21: 0 | W21: 0 | X21: -61.1 | Y21: ns | AA21: -15.688708 | AC21: 15.688708 | AD21: -61.1 | AE21: 0.743229 | AI21: 0 | AL21: 0 | AN21: -61.1 | AO21: 61.1 | AP21: ns | AQ21: ns | AR21: ns | AS21: ns
B22: +/- value de cession d'immobilisations | Q22: 0 | S22: ns | U22: 0 | W22: 0 | X22: 0 | Y22: ns | AA22: 0 | AC22: 0 | AD22: 0 | AE22: ns | AN22: 0 | AO22: 0 | AR22: ns | AS22: ns
B23: PIDR | D23: 0 | E23: 0 | F23: -0.208 | G23: -0.208 | H23: -0.208 | I23: 0.23 | J23: 0.23 | K23: 0.23 | L23: -0.69 | M23: 0.23 | N23: -0.366 | O23: 16.86 | P23: -0.1 | Q23: -16.96 | R23: 3.4 | S23: 3.9588235 | U23: -0.76 | V23: 0 | W23: 0.76 | X23: -0.38 | Y23: 1 | AA23: 16.1 | AB23: 0 | AC23: -16.1 | AD23: 3.02 | AE23: 4.3311258 | AI23: -0.97066667 | AL23: -0.4 | AN23: 3.02 | AO23: -3.42 | AR23: ns | AS23: ns
B25: EBITA | D25: -221.39692 | E25: -192.25288 | F25: -240.62808 | G25: -36.026496 | H25: -191.41493 | I25: -187.09686 | J25: -139.42004 | K25: -127.3848 | L25: -131.18561 | M25: 70.487875 | N25: -113.48258 | O25: -116.84494 | P25: -18.247985 | Q25: -98.596952 | R25: -212.30287 | S25: 0.44963091 | U25: -1509.8013 | V25: -1600.2526 | W25: 90.451257 | X25: -2263.4697 | Y25: 0.33297039 | AA25: -1626.6463 | AB25: -1618.5006 | AC25: -8.1456951 | AD25: -2475.7726 | AE25: 0.34297428 | AG25: -695.37864 | AH25: -694.22637 | AI25: -1117.9516 | AL25: -1618.5006 | AN25: -2475.7726 | AO25: 857.27202 | AP25: 0.30926708 | AQ25: -0.54844333 | AR25: 0.34626444 | AS25: ns
B26: Marge d'Ebita (%) | D26: -0.71738864 | E26: -0.31538769 | F26: -0.25961314 | G26: -0.028942251 | H26: -0.12035594 | I26: -0.097498483 | J26: -0.061334435 | K26: -0.048127107 | L26: -0.043547328 | M26: 0.020687875 | N26: -0.03005834 | O26: -0.028153363 | P26: -0.031706154 | Q26: 0.35527913 | R26: -0.054988638 | U26: -0.39990386 | V26: -0.34934449 | W26: -5.0559372 | X26: -0.63843942 | Y26: 23.853555 | AA26: -0.3919345 | AB26: -0.31389017 | AC26: -7.8044329 | AD26: -0.64125069 | AE26: 24.931619 | AG26: -0.14735736 | AH26: -0.14712271 | AI26: -0.21682054 | AL26: -0.31389017 | AN26: -0.64125069 | AO26: 32.736052 | AP26: 9.7069631 | AQ26: 42.443015 | AR26: 32.736052 | AS26: 64.125069
B28: Résultat financier | D28: -117.27137 | E28: -119 | F28: -162.4 | G28: -113.26909 | H28: -135.19178 | I28: -121.9 | J28: -126.86121 | K28: -90.833975 | L28: -44.94 | M28: -49.44 | N28: -49.44 | O28: -41.67 | P28: -41.676592 | Q28: 0.006592 | R28: -140.8852 | S28: 0.70422727 | U28: -1130.5474 | V28: -479.04269 | W28: -651.50474 | X28: -1517.6927 | Y28: 0.25508806 | AA28: -1172.2174 | AB28: -520.71928 | AC28: -651.49814 | AD28: -1658.5779 | AE28: 0.29323946 | AG28: -629.15731 | AH28: -596.02363 | AI28: -1054.0885 | AL28: -520.71928 | AN28: -1658.5779 | AO28: 1137.8586 | AP28: -1.0242933 | AQ28: -0.36446246 | AR28: 0.68604473 | AS28: ns
B29: dont intérêt SHL | D29: -116.89929 | E29: 0 | F29: 0 | G29: 0 | H29: 0 | I29: 0 | J29: 0 | K29: 0 | L29: 0 | M29: 0 | N29: 0 | O29: 0 | Q29: 0 | R29: 0 | S29: ns | U29: -116.89929 | W29: -116.89929 | X29: -116.89929 | Y29: 0 | AA29: -116.89929 | AC29: -116.89929 | AD29: -116.89929 | AE29: 0 | AN29: -116.89929 | AO29: 116.89929 | AP29: ns | AQ29: ns | AR29: ns | AS29: ns
B30: RESULTAT avant IS | D30: -338.66829 | E30: -311.25288 | F30: -403.02808 | G30: -149.29558 | H30: -326.60671 | I30: -308.99686 | J30: -266.28126 | K30: -218.21877 | L30: -176.12561 | M30: 21.047875 | N30: -162.92258 | O30: -158.51494 | P30: -59.924577 | Q30: -98.59036 | R30: -353.18807 | S30: 0.5511883 | U30: -2640.3487 | V30: -2079.2953 | W30: -561.05348 | X30: -3781.1624 | Y30: 0.30170978 | AA30: -2798.8637 | AB30: -2139.2198 | AC30: -659.64384 | AD30: -4134.3505 | AE30: 0.32302216 | AI30: -2172.0401 | AL30: -2139.2198 | AN30: -4134.3505 | AO30: 1995.1307 | AP30: -0.015342183 | AQ30: -0.4746357 | AR30: 0.48257414 | AS30: ns
V31: 0 | AB31: 0 | AP31: ns | AQ31: ns
B32: IS | D32: -5.3441685 | E32: -5.3441685 | F32: 9.6 | G32: -1 | H32: -1 | I32: -1.5 | J32: -1.5 | K32: -1.5 | L32: 1 | M32: -1.5 | N32: 23.9 | O32: 1.4 | P32: -5.4693238 | Q32: -6.8693238 | R32: -10.544169 | S32: ns | U32: 15.811663 | V32: -60.162561 | W32: -75.974224 | X32: -59.585854 | Y32: ns | AA32: 17.211663 | AB32: -65.631885 | AC32: -82.843548 | AD32: -70.130023 | AE32: ns | AG32: -86.43809 | AH32: -12.181056 | AI32: -10.088337 | AL32: -65.631885 | AN32: -70.130023 | AO32: 4.4981373 | AP32: 0.84628909 | AQ32: -0.8561481 | AR32: 0.064139966 | AS32: ns
B33: ID | D33: 0 | E33: 0 | F33: 0 | G33: 0 | H33: 0 | I33: 0 | J33: 0 | K33: 0 | L33: 0 | M33: 0 | N33: 0 | O33: 0 | R33: 0 | V33: 0 | Y33: ns | AB33: 0 | AE33: ns | AI33: #REF! | AL33: #REF!
V34: #REF! | AB34: #REF! | AI34: 0 | AL34: 0
B35: RESULTAT NET | D35: -344.01246 | E35: -316.59705 | F35: -393.42808 | G35: -150.29558 | H35: -327.60671 | I35: -310.49686 | J35: -267.78126 | K35: -219.71877 | L35: -175.12561 | M35: 19.547875 | N35: -139.02258 | O35: -157.11494 | P35: -65.393901 | Q35: -91.721036 | R35: -363.73224 | S35: 0.56804781 | U35: -2624.5371 | V35: -2139.4578 | W35: -485.07925 | X35: -3840.7483 | Y35: 0.31665996 | AA35: -2781.652 | AB35: -2204.8517 | AC35: -576.80029 | AD35: -4204.4805 | AE35: 0.33840768 | AG35: -1410.974 | AH35: -1302.4311 | AI35: -2182.1285 | AL35: -2204.8517 | AN35: -4204.4805 | AO35: 1999.6288 | AP35: 0.01030602 | AQ35: -0.48099926 | AR35: 0.47559473 | AS35: ns
B38: Contrôle | AF38: #REF! | AL38: #REF!
P39: 0 | Q39: 0 | R39: #REF! | T39: #REF! | AL39: #REF! | AM39: #REF!
B40: Ctrl | P40: #REF! | Q40: #REF! | R40: #REF! | T40: #REF! | AL40: #REF! | AM40: #REF!
P42: -5.7553449 | Q42: 2.0064392 | R42: -3.1553342 | T42: 0 | AL42: -51.562639 | AM42: -38.608498
P43: -6.3308794 | Q43: 2.2070831 | R43: -3.4708676 | T43: 0 | AL43: -56.718903 | AM43: -42.469348

Sheet Opex 
B2: Moov RCA : Opex | O2: -32.574656
P3: MENSUEL | V3: CUMUL (m-1) | AB3: CUMUL
O5: MENSUEL | P5: MENSUEL | V5: CUMUL (m-1) | AB5: CUMUL | AL5: ANNUEL
E6: Janvier | F6: Février | G6: Mars | H6: Avril | I6: Mai | J6: Juin | K6: Juillet | L6: Août | M6: Septembre | N6: Octobre | O6: Novembre | P6: 2023 | Q6: 2023 Budget | R6: Ecart / Budget | S6: 2022 Réel | T6: Evol % | V6: 2023 | W6: 2023 Budget | X6: Ecart / Budget | Y6: 2021 Réel | Z6: Evol % | AB6: 2023 | AC6: 2023 Budget | AD6: Ecart / Budget | AE6: 2022 Réel | AF6: Evol % | AH6: 2017 Actu 1 | AI6: 2017 Actu 2 | AJ6: 2023 Actu 1 | AK6: 2023 Actu 2 | AL6: 2023 Actu3 | AM6: 2023 Budget | AN6: 2019 Actu3 | AO6: 2022 Réel | AP6: Ecart / Budget | AQ6: Var Actu1/ Budget (%) | AR6: Var Actu1/ 2018 (%) | AS6: B23/ 2022 (%) | AT6: Var Actu3/ 2019 (%) | AU6: 0
B8: Total Opex | E8: 287.74386 | F8: 248.10704 | G8: 311.75866 | H8: 311.83251 | I8: 334.98143 | J8: 311.31526 | K8: 286.61676 | L8: 291.5533 | M8: 283.89436 | N8: 102.75179 | O8: 255.04608 | P8: 251.31971 | Q8: 290.03839 | R8: -38.718679 | S8: 290.05091 | T8: -0.13353243 | V8: 3025.6011 | W8: 3188.8941 | X8: -163.29306 | Y8: 2961.4385 | Z8: 0.021666004 | AB8: 3276.9208 | AC8: 3478.9325 | AD8: -202.01174 | AE8: 3251.4894 | AF8: 0.007821442 | AJ8: 3339.2962 | AM8: 3484.3787 | AO8: 3251.4894 | AP8: 232.88931 | AQ8: -0.041637992 | AR8: 0.027005093 | AS8: 0.071625424 | AT8: ns
B9: Total Opex hors NRI | E9: 287.74386 | F9: 248.10704 | G9: 311.75866 | H9: 311.83251 | I9: 334.98143 | J9: 311.31526 | K9: 286.61676 | L9: 291.5533 | M9: 283.89436 | N9: 102.75179 | O9: 255.04608 | P9: 251.31971 | R9: 251.31971 | S9: 290.05091 | T9: -0.13353243 | AS9: ns
B13: Personnel | E13: 48.1 | F13: 48.1 | G13: 47.45 | H13: 45.38362 | I13: 45.65932 | J13: 44.510135 | K13: 44.560135 | L13: 44.560135 | M13: 44.560135 | N13: 44.560135 | O13: 44.560135 | P13: 44.560135 | Q13: 48.3 | R13: -3.739865 | S13: 52.014591 | T13: -0.14331471 | V13: 502.00375 | W13: 531.3 | X13: -29.29625 | Y13: 585.97553 | Z13: -0.14330254 | AB13: 546.56389 | AC13: 579.6 | AD13: -33.036115 | AE13: 637.99012 | AF13: -0.14330353 | AJ13: 552.23362 | AM13: 579.6 | AO13: 637.99012 | AP13: -58.390124 | AQ13: -0.047215977 | AR13: -0.13441666 | AS13: -0.091521988 | AT13: ns
B14: Personnel masse salariale | E14: 44.9 | F14: 44.9 | G14: 44.25 | H14: 42.823485 | I14: 43.099185 | J14: 41.95 | K14: 42 | L14: 42 | M14: 42 | N14: 42 | O14: 42 | P14: 42 | Q14: 45 | R14: -3 | S14: 48.2 | T14: -0.12863071 | V14: 471.92267 | W14: 495 | X14: -23.07733 | Y14: 544.01503 | Z14: -0.13251906 | AB14: 513.92267 | AC14: 540 | AD14: -26.07733 | AE14: 592.21503 | AF14: -0.13220259 | AJ14: 520.87349 | AM14: 540 | AO14: 592.21503 | AP14: -52.21503 | AQ14: -0.035419472 | AR14: -0.12046561 | AS14: -0.088169039 | AT14: ns
B15: Personnel externe (prestataires) | R15: 0 | T15: ns | V15: 0 | X15: 0 | Y15: 0 | Z15: ns | AB15: 0 | AD15: 0 | AE15: 0 | AF15: ns | AO15: 0 | AP15: 0 | AQ15: ns | AR15: ns | AS15: ns | AT15: ns
B16: Assurance maladie | E16: 3.2 | F16: 3.2 | G16: 3.2 | H16: 2.560135 | I16: 2.560135 | J16: 2.560135 | K16: 2.560135 | L16: 2.560135 | M16: 2.560135 | N16: 2.560135 | O16: 2.560135 | P16: 2.560135 | Q16: 3.3 | R16: -0.739865 | S16: 3.8145912 | T16: -0.32885731 | V16: 30.08108 | W16: 36.3 | X16: -6.21892 | Y16: 41.960503 | Z16: -0.28310964 | AB16: 32.641215 | AC16: 39.6 | AD16: -6.958785 | AE16: 45.775094 | AF16: -0.28692195 | AJ16: 31.360135 | AM16: 39.6 | AO16: 45.775094 | AP16: -6.1750943 | AQ16: -0.2080774 | AR16: -0.31490835 | AS16: -0.13490075 | AT16: ns
B18: Communication | E18: 1.025 | F18: 2 | G18: 2 | H18: 2.81494 | I18: 9.451916 | J18: 7.544 | K18: 4.3 | L18: 4.3 | M18: 4.445 | N18: 39.5 | O18: 22.306933 | P18: 5.8 | Q18: 4 | R18: 1.8 | S18: 5.937965 | T18: -0.023234391 | V18: 99.687789 | W18: 31 | X18: 68.687789 | Y18: 29.2335 | Z18: 2.4100532 | AB18: 105.48779 | AC18: 35 | AD18: 70.487789 | AE18: 35.171465 | AF18: 1.9992435 | AJ18: 32.83994 | AM18: 34 | AO18: 35.171465 | AP18: -1.171465 | AQ18: -0.034119412 | AR18: -0.066290244 | AS18: -0.033307256 | AT18: ns
B20: Exploitation & maintenance | E20: 189 | F20: 182.3 | G20: 188.592 | H20: 192.26335 | I20: 199.72595 | J20: 184.90101 | K20: 166.20319 | L20: 169.39212 | M20: 164.64851 | N20: -58.057537 | O20: 150.15469 | P20: 137.17647 | Q20: 172.96 | R20: -35.783529 | S20: 190.94 | T20: -0.2815729 | V20: 1729.1233 | W20: 1934.3794 | X20: -205.25611 | Y20: 1725.4893 | Z20: 0.0021060878 | AB20: 1866.2998 | AC20: 2107.3394 | AD20: -241.03964 | AE20: 1916.4293 | AF20: -0.02615776 | AJ20: 1871.0525 | AM20: 2113.0028 | AO20: 1916.4293 | AP20: 196.57354 | AQ20: -0.11450542 | AR20: -0.023677747 | AS20: 0.10257282 | AT20: ns
C21: Achat d'énergie - Bâtiment - Gardiennage | E21: 56 | F21: 55 | G21: 56 | H21: 58.11415 | I21: 61.583932 | J21: 51.999976 | K21: 52.636172 | L21: 49 | M21: 46.92126 | N21: 48.25 | O21: 51.4 | P21: 49.981137 | Q21: 66 | R21: -16.018863 | S21: 56 | T21: -0.1074797 | V21: 586.90549 | W21: 686 | X21: -99.09451 | Y21: 571.13928 | Z21: 0.027604834 | AB21: 636.88663 | AC21: 752 | AD21: -115.11337 | AE21: 627.13928 | AF21: 0.015542548 | AJ21: 709.11415 | AM21: 752 | AO21: 627.13928 | AP21: ns | AQ21: -0.057029056 | AR21: 0.13071238 | AS21: 0.19909567 | AT21: ns
C22: Lignes et réseaux (entretien & achats) | E22: 129 | F22: 124 | G22: 129.792 | H22: 130.4362 | I22: 130.45604 | J22: 125.20003 | K22: 108.51489 | L22: 115.39212 | M22: 115.6452 | N22: -109.28867 | O22: 93.429355 | P22: 81.122402 | Q22: 102.46 | R22: -21.337598 | S22: 129.94 | T22: -0.37569338 | V22: 1092.5772 | W22: 1196.82 | X22: -104.24283 | Y22: 1103.9057 | Z22: -0.010262251 | AB22: 1173.6996 | AC22: 1299.28 | AD22: -125.58042 | AE22: 1233.8457 | AF22: -0.048746901 | AJ22: 1110.2282 | AM22: 1304.28 | AO22: 1233.8457 | AP22: 70.434268 | AQ22: -0.14878078 | AR22: -0.10018881 | AS22: 0.057085149 | AT22: ns
C23: Fees du contrat GMNS | E23: #DIV/0! | F23: #DIV/0! | G23: #DIV/0! | H23: #DIV/0! | I23: #DIV/0! | J23: #DIV/0! | K23: #DIV/0! | L23: #DIV/0! | M23: #DIV/0! | N23: #DIV/0! | O23: #DIV/0! | P23: #DIV/0! | R23: #DIV/0! | S23: #DIV/0! | T23: #DIV/0! | V23: #DIV/0! | X23: #DIV/0! | Y23: #DIV/0! | AB23: #DIV/0! | AD23: #DIV/0! | AE23: #DIV/0! | AJ23: #DIV/0! | AO23: #DIV/0! | AP23: #DIV/0! | AQ23: #DIV/0! | AR23: #DIV/0!
C24: Fees du contrat IHS (spécifique à CDI) | E24: #DIV/0! | F24: #DIV/0! | G24: #DIV/0! | H24: #DIV/0! | I24: #DIV/0! | J24: #DIV/0! | K24: #DIV/0! | L24: #DIV/0! | M24: #DIV/0! | N24: #DIV/0! | O24: #DIV/0! | P24: #DIV/0! | R24: #DIV/0! | S24: #DIV/0! | T24: #DIV/0! | V24: #DIV/0! | X24: #DIV/0! | Y24: #DIV/0! | AB24: #DIV/0! | AD24: #DIV/0! | AE24: #DIV/0! | AJ24: #DIV/0! | AO24: #DIV/0! | AP24: #DIV/0! | AQ24: #DIV/0! | AR24: #DIV/0!
C25: Dont co-localisation | E25: #DIV/0! | F25: #DIV/0! | G25: #DIV/0! | H25: #DIV/0! | I25: #DIV/0! | J25: #DIV/0! | K25: #DIV/0! | L25: #DIV/0! | M25: #DIV/0! | N25: #DIV/0! | O25: #DIV/0! | P25: #DIV/0! | R25: #DIV/0! | S25: #DIV/0! | T25: #DIV/0! | V25: #DIV/0! | X25: #DIV/0! | Y25: #DIV/0! | AB25: #DIV/0! | AD25: #DIV/0! | AE25: #DIV/0! | AJ25: #DIV/0! | AO25: #DIV/0! | AP25: #DIV/0! | AQ25: #DIV/0! | AR25: #DIV/0! | AS25: #DIV/0!
C26: Matériel de transport (Entretien et locations) | E26: 2 | F26: 1.5 | G26: 1 | H26: 2.913 | I26: 3.773415 | J26: 4.601 | K26: 3.611 | L26: 3 | M26: 1.27705 | N26: 1.5 | O26: 1.9304 | P26: 2.678 | Q26: 1.5 | R26: 1.178 | S26: 2 | T26: 0.339 | V26: 27.105865 | W26: 18.559398 | X26: 8.546467 | Y26: 20.307464 | Z26: 0.33477351 | AB26: 29.783865 | AC26: 20.059398 | AD26: 9.724467 | AE26: 22.307464 | AF26: 0.33515244 | AJ26: 22.092332 | AM26: 20.722798 | AO26: 22.307464 | AP26: -1.584666 | AQ26: 0.066088276 | AR26: -0.009643947 | AS26: -0.071037479 | AT26: ns
C27: Maintenance informatique | E27: 2 | F27: 1.8 | G27: 1.8 | H27: 0.8 | I27: 3.912567 | J27: 3.1 | K27: 1.441129 | L27: 2 | M27: 0.805 | N27: 1.481129 | O27: 3.394932 | P27: 3.394932 | Q27: 3 | R27: 0.394932 | S27: 3 | T27: 0.131644 | V27: 22.534757 | W27: 33 | X27: -10.465243 | Y27: 30.136774 | Z27: -0.25225052 | AB27: 25.929689 | AC27: 36 | AD27: -10.070311 | AE27: 33.136774 | AF27: -0.21749507 | AJ27: 30.4 | AM27: 36 | AO27: 33.136774 | AP27: 2.8632262 | AQ27: -0.15555556 | AR27: -0.082590232 | AS27: ns | AT27: ns
B29: Frais géneraux | E29: 9.7366541 | F29: 11.865216 | G29: 14.019703 | H29: 13.504578 | I29: 18.976445 | J29: 15.186915 | K29: 14.009979 | L29: 14.542289 | M29: 13.690928 | N29: 15.123514 | O29: 20.260289 | P29: 15.295245 | Q29: 13.890659 | R29: 1.404586 | S29: 12.207099 | T29: 0.25297949 | V29: 160.91651 | W29: 155.93479 | X29: 4.9817198 | Y29: 181.05985 | Z29: -0.11125239 | AB29: 176.21176 | AC29: 169.82545 | AD29: 6.3863058 | AE29: 193.26695 | AF29: -0.088246826 | AJ29: 168.00707 | AM29: 170.7422 | AO29: 193.26695 | AP29: -22.524753 | AQ29: -0.016019038 | AR29: -0.13069942 | AS29: -0.11654736 | AT29: ns
C30: Frais d'achats d'études, honoraires | E30: 3 | F30: 3.4 | G30: 3.5 | H30: 5.865378 | I30: 3.6 | J30: 3.776378 | K30: 3.909378 | L30: 4 | M30: 4.790165 | N30: 6.731378 | O30: 6.4 | P30: 7.115378 | Q30: 4 | R30: 3.115378 | S30: 4 | T30: 0.7788445 | V30: 48.972677 | W30: 44.3 | X30: 4.672677 | Y30: 76.198792 | Z30: -0.35730376 | AB30: 56.088055 | AC30: 48.3 | AD30: 7.788055 | AE30: 80.198792 | AF30: -0.30063716 | AJ30: 47.765378 | AM30: 48.3 | AO30: 80.198792 | AP30: -31.898792 | AQ30: -0.011068778 | AR30: -0.40441275 | AS30: -0.39774654 | AT30: ns
C31: Management FEES | E31: 2.9400351 | F31: 2.8652162 | G31: 3.0197026 | H31: 3.0208644 | I31: 3.2829163 | J31: 3.1167368 | K31: 3.3566007 | L31: 3.5422886 | M31: 3.4630934 | N31: 3.7405204 | O31: 3.4852886 | P31: 2.8453672 | Q31: 5.3906592 | R31: -2.545292 | S31: 3.0037754 | T31: -0.052736384 | V31: 35.833263 | W31: 43.142299 | X31: -7.3090359 | Y31: 33.809003 | Z31: 0.059873399 | AB31: 38.67863 | AC31: 48.532958 | AD31: -9.8543279 | AE31: 36.812779 | AF31: 0.050684892 | AJ31: 48.893838 | AM31: 48.280374 | AO31: 36.812779 | AP31: 11.467595 | AQ31: 0.01270628 | AR31: 0.32817569 | AS31: 0.31151126 | AT31: ns
C32: Transport, déplacement, mission et réception | E32: 2 | F32: 4 | G32: 5 | H32: 3.1298 | I32: 9.94264 | J32: 2.6938 | K32: 4 | L32: 4 | M32: 4.637 | N32: 3 | O32: 8.875 | P32: 1.7345 | Q32: 3 | R32: -1.2655 | S32: 4.040762 | T32: -0.57074928 | V32: 51.27824 | W32: 31.334495 | X32: 19.943745 | Y32: 47.760367 | Z32: 0.073656741 | AB32: 53.01274 | AC32: 34.334495 | AD32: 18.678245 | AE32: 51.801129 | AF32: 0.023389664 | AJ32: 36.226543 | AM32: 36.465619 | AO32: 51.801129 | AP32: -15.33551 | AQ32: -0.006556203 | AR32: -0.30066113 | AS32: -0.29604586 | AT32: ns
C33: Frais postaux, bancaires et assurances | E33: 0.92357 | F33: 0.8 | G33: 2.3 | H33: 0.740536 | I33: 0.893389 | J33: 3.8 | K33: 1 | L33: 2 | M33: 0.104954 | N33: 0.732616 | O33: 1 | P33: 1.7 | Q33: 1 | R33: 0.7 | S33: 1.162562 | T33: 0.4622876 | V33: 14.295065 | W33: 28.545638 | X33: -14.250573 | Y33: 14.391122 | Z33: -0.0066747402 | AB33: 15.995065 | AC33: 29.545638 | AD33: -13.550573 | AE33: 15.553684 | AF33: 0.028377907 | AJ33: 26.730764 | AM33: 28.545638 | AO33: 15.553684 | AP33: 12.991954 | AQ33: -0.06357798 | AR33: 0.71861303 | AS33: 0.83529754 | AT33: ns
C34: Achats de matières et fournitures consommables | E34: 0.873049 | F34: 0.8 | G34: 0.2 | H34: 0.748 | I34: 1.2575 | J34: 1.8 | K34: 1.744 | L34: 1 | M34: 0.695716 | N34: 0.919 | O34: 0.5 | P34: 1.9 | Q34: 0.5 | R34: 1.4 | S34: 0 | T34: ns | V34: 10.537265 | W34: 8.6123583 | X34: 1.9249067 | Y34: 8.9005667 | Z34: 0.18388698 | AB34: 12.437265 | AC34: 9.1123583 | AD34: 3.3249067 | AE34: 8.9005667 | AF34: 0.39735654 | AJ34: 8.390549 | AM34: 9.1505667 | AO34: 8.9005667 | AP34: 0.25 | AQ34: -0.083056896 | AR34: -0.057301707 | AS34: 0.028088099 | AT34: ns
B36: Impôts et taxes | E36: 20.442208 | F36: 37.401825 | G36: 39.333953 | H36: 37.444019 | I36: 39.367794 | J36: 37.1332 | K36: 39.383453 | L36: 40.598761 | M36: 39.730446 | N36: 42.965682 | O36: 39.97904 | P36: 40.147856 | Q36: 23.709238 | R36: 16.438618 | S36: 18.003616 | T36: 1.2299885 | V36: 413.78038 | W36: 239.82715 | X36: 173.95323 | Y36: 182.08882 | Z36: 1.2724095 | AB36: 453.92824 | AC36: 263.53638 | AD36: 190.39185 | AE36: 200.09244 | AF36: 1.2685926 | AJ36: 528.90818 | AM36: 263.53638 | AO36: 200.09244 | AP36: 63.443945 | AQ36: 1.0069645 | AR36: 1.6433191 | AS36: ns | AT36: ns
C37: dont à l'international | E37: 1.991808 | F37: 1.951425 | G37: 1.883553 | H37: 2.111634 | I37: 2.6164719 | J37: 2.133243 | K37: 2.174949 | L37: 2.206701 | M37: 1.716907 | N37: 3.293671 | O37: 1.908931 | P37: 1.765984 | Q37: 5.7092379 | R37: -3.9432539 | S37: 2.0036155 | T37: -0.11860136 | V37: 23.989294 | W37: 49.827147 | X37: -25.837853 | Y37: 23.837624 | Z37: 0.0063626208 | AB37: 25.755278 | AC37: 55.536385 | AD37: -29.781107 | AE37: 25.84124 | AF37: -0.0033265341 | AJ37: 35.712457 | AM37: 55.536385 | AO37: 25.84124 | AP37: 29.695145 | AQ37: -0.35695387 | AR37: 0.38199474 | AS37: 1.1491378 | AT37: ns
C38: Autres impots et taxes | E38: 18.4504 | F38: 35.4504 | G38: 37.4504 | H38: 35.332385 | I38: 36.751322 | J38: 34.999957 | K38: 37.208504 | L38: 38.39206 | M38: 38.013539 | N38: 39.672011 | O38: 38.070109 | P38: 38.381872 | Q38: 18 | R38: 20.381872 | S38: 16 | T38: 1.398867 | V38: 389.79109 | W38: 190 | X38: 199.79109 | Y38: 158.2512 | Z38: 1.4631162 | AB38: 428.17296 | AC38: 208 | AD38: 220.17296 | AE38: 174.2512 | AF38: 1.4572167 | AJ38: 493.19572 | AM38: 208 | AO38: 174.2512 | AP38: 33.7488 | AQ38: 1.3711333 | AR38: 1.830372 | AS38: 0.19367901 | AT38: ns
B40: Redevance ART (SU, Formation, Fréquences,Marques) | E40: 18 | F40: 18 | G40: 18 | H40: 18 | I40: 18 | J40: 16 | K40: 16 | L40: 16 | M40: 16 | N40: 16 | O40: 16 | P40: 16 | Q40: 25.045156 | R40: -9.045156 | S40: 24.662737 | T40: -0.351248 | V40: 186 | W40: 275.49672 | X40: -89.496716 | Y40: 271.29011 | Z40: -0.31438709 | AB40: 202 | AC40: 300.54187 | AD40: -98.541872 | AE40: 295.95285 | AF40: -0.31745884 | AJ40: 216 | AM40: 300.54187 | AO40: 295.95285 | AP40: 4.589025 | AQ40: -0.28129815 | AR40: -0.270154 | AS40: 0.015505933 | AT40: ns
B42: Provision clients, R&C & NC | E42: 2.025 | F42: -50.975 | G42: 2.958 | H42: 3 | I42: 3 | J42: 6.04 | K42: 2.16 | L42: 2.16 | M42: 0.81934 | N42: 2.66 | O42: -38.215 | P42: -7.66 | Q42: 1.8833333 | R42: -9.5433333 | S42: -13.97 | T42: 0.45168218 | V42: -64.36766 | W42: 18.206067 | X42: -82.573727 | Y42: -20.264902 | Z42: -2.1763124 | AB42: -72.02766 | AC42: 20.0894 | AD42: -92.11706 | AE42: -34.234902 | AF42: -1.1039248 | AJ42: -29.402133 | AM42: 19.955484 | AO42: -34.234902 | AP42: 54.190386 | AQ42: ns | AR42: -0.14116497 | AS42: ns | AT42: ns
C43: Dont provisions Créances clients | E43: 2 | F43: 2 | G43: 2.8 | H43: 3 | I43: 3 | J43: 2 | K43: 2 | L43: 2 | M43: 0.89234 | N43: 2.5 | O43: 3 | P43: 10.1 | Q43: 1.8 | R43: 8.3 | S43: -10.37 | T43: ns | V43: 25.19234 | W43: 17.2894 | X43: 7.90294 | Y43: 17.575098 | Z43: 0.4334111 | AB43: 35.29234 | AC43: 19.0894 | AD43: 16.20294 | AE43: 7.2050977 | AF43: 3.8982459 | AJ43: 22.7232 | AM43: 18.955484 | AO43: 7.2050977 | AP43: 11.750386 | AQ43: 0.19876655 | AR43: 2.1537671 | AS43: 1.6308434 | AT43: ns
C44: Dont provisions risques / charges et autres | E44: 0 | F44: -53 | G44: 0 | H44: 0 | I44: 0 | J44: 3.88 | K44: 0 | L44: 0 | M44: 0 | N44: 0 | O44: -41.2 | P44: -0.89 | Q44: 0 | R44: -0.89 | S44: 0 | T44: ns | V44: -90.32 | W44: 0 | X44: -90.32 | Y44: -38.4 | Z44: -1.3520833 | AB44: -91.21 | AC44: 0 | AD44: -91.21 | AE44: -38.4 | AF44: -1.3752604 | AJ44: -53 | AM44: 0 | AO44: -38.4 | AP44: 38.4 | AQ44: ns | AR44: 0.38020833 | AS44: ns | AT44: ns
C45: PIDR | E45: 0.025 | F45: 0.025 | G45: 0.158 | H45: 0 | I45: 0 | J45: 0.16 | K45: 0.16 | L45: 0.16 | M45: -0.073 | N45: 0.16 | O45: -0.015 | P45: -16.87 | Q45: 0.083333333 | R45: -16.953333 | S45: -3.6 | T45: -3.6861111 | V45: 0.76 | W45: 0.91666667 | X45: -0.15666667 | Y45: 0.56 | Z45: 0.35714286 | AB45: -16.11 | AC45: 1 | AD45: -17.11 | AE45: -3.04 | AF45: -4.2993421 | AJ45: 0.87466667 | AM45: 1 | AO45: -3.04 | AP45: 4.04 | AQ45: -0.12533333 | AR45: ns | AS45: ns | AT45: ns
C46: Autres provisions | R46: 0 | S46: 0 | T46: ns | V46: 0 | X46: 0 | Y46: 0 | Z46: ns | AB46: 0 | AD46: 0 | AE46: 0 | AF46: ns | AJ46: 0 | AM46: 0 | AO46: 0 | AP46: 0 | AQ46: ns | AR46: ns | AS46: ns | AT46: ns
C47: Provisions stocks commerciaux | E47: 0 | F47: 0 | G47: 0 | H47: 0 | I47: 0 | J47: 0 | K47: 0 | L47: 0 | M47: 0 | N47: 0 | O47: 0 | P47: 0 | Q47: 0 | S47: 0 | T47: ns | W47: 0 | Z47: ns | AC47: 0 | AF47: ns | AJ47: 0 | AM47: 0 | AP47: ns | AS47: ns
C48: Autres (pertes ou gain exceptionnels sur créances) | E48: 0 | F48: 0 | G48: 0 | H48: 0 | I48: 0 | J48: 0 | K48: 0 | L48: 0 | M48: 0 | N48: 0 | O48: 0 | P48: 0 | Q48: 0 | S48: 0 | W48: 0 | Z48: ns | AC48: 0 | AF48: ns | AJ48: 0 | AM48: 0 | AP48: ns | AS48: ns
AM49: 0
B50: Ecart de change sur exploitation | E50: -0.585 | F50: -0.585 | G50: -0.595 | H50: -0.578 | I50: 0.8 | J50: 0 | K50: 0 | L50: 0 | M50: 0 | N50: 0 | O50: 0 | P50: 0 | Q50: 0.25 | R50: -0.25 | S50: 0.254901 | T50: ns | V50: -1.543 | W50: 2.75 | X50: -4.293 | Y50: 6.566348 | Z50: ns | AA50: 0 | AB50: -1.543 | AC50: 3 | AD50: -4.543 | AE50: 6.821249 | AF50: ns | AJ50: -0.343 | AM50: 3 | AO50: 6.821249 | AP50: -3.821249 | AQ50: ns | AR50: ns | AS50: -0.56019785 | AT50: ns
C53: CA | F53: =+'CA Mobile'!F18-'Marge Mobile'!E36 -> 261.45333 | G53: =+'CA Mobile'!G18-'Marge Mobile'!F36 -> 275.88447 | H53: =+'CA Mobile'!H18-'Marge Mobile'!G36 -> 276.17693 | I53: =+'CA Mobile'!I18-'Marge Mobile'!H36 -> 296.44746 | J53: =+'CA Mobile'!J18-'Marge Mobile'!I36 -> 281.49081 | K53: =+'CA Mobile'!K18-'Marge Mobile'!J36 -> 302.97863 | L53: =+'CA Mobile'!L18-'Marge Mobile'!K36 -> 319.88657 | M53: =+'CA Mobile'!M18-'Marge Mobile'!L36 -> 314.47912 | ... P53: =+'CA Mobile'!P18-'Marge Mobile'!O36 -> 319.74102 | Q53: =SUM(F53:P53) -> 3301.9972
C54: Tic-Tech | F54: =+F53*7% -> 18.301733 | G54: =+G53*7% -> 19.311913 | H54: =+H53*7% -> 19.332385 | I54: =+I53*7% -> 20.751322 | J54: =+J53*7% -> 19.704357 | K54: =+K53*7% -> 21.208504 | L54: =+L53*7% -> 22.39206 | M54: =+M53*7% -> 22.013539 | ... P54: =+P53*7% -> 22.381872 | Q54: =SUM(F54:P54) -> 231.1398
F55: =+F38-F54 -> 17.148667 | G55: =+G38-G54 -> 18.138487 | H55: =+H38-H54 -> 16 | I55: =+I38-I54 -> 16 | J55: =+J38-J54 -> 15.2956 | K55: =+K38-K54 -> 16 | L55: =+L38-L54 -> 16 | M55: =+M38-M54 -> 16 | ... P55: =+P38-P54 -> 16 | Q55: =SUM(F55:P55) -> 178.58275
F56: =+F54+F55 -> 35.4504 | G56: =+G54+G55 -> 37.4504 | H56: =+H54+H55 -> 35.332385 | I56: =+I54+I55 -> 36.751322 | J56: =+J54+J55 -> 34.999957 | K56: =+K54+K55 -> 37.208504 | L56: =+L54+L55 -> 38.39206 | M56: =+M54+M55 -> 38.013539 | ... P56: =+P54+P55 -> 38.381872
C61: Provision Tic-Tech TBG | E61: 231.1398
C62: Tic-Tech Compta | E62: 199.004
C63: Ecart | E63: =+E62-Q54 -> -32.135806

Sheet Indicateurs Parc Mobile  
A2: Moov RCA : Indicateurs Parc Mobile | AT2: 42644
O3: 252914 | P3: 0 | AA3: 0
O5: MENSUEL | U5: CUMUL (m-1) | AA5: CUMUL | AK5: ANNUEL
D6: Janvier | E6: Février | F6: Mars | G6: Avril | H6: Mai | I6: Juin | J6: Juillet | K6: Août | L6: Septembre | M6: Octobre | N6: Novembre | O6: 2023 | P6: 2023 Budget | Q6: Ecart / Budget | R6: 2022 Réel | S6: Evol % | U6: 2023 | V6: 2023 Budget | W6: Ecart / Budget | X6: 2021 Réel | Y6: Evol % | AA6: 2023 | AB6: 2023 Budget | AC6: Ecart / Budget | AD6: 2022 Réel | AE6: Evol % | AG6: 2017 Actu 1 | AH6: 2017 Actu 2 | AI6: 2023 Actu 1 | AJ6: 2023 Actu 2 | AK6: 2023 Actu3 | AL6: 2023 Budget | AM6: 2019 Actu3 | AN6: 2022 Réel | AO6: Ecart / Budget | AP6: Var Actu1/ Budget (%) | AQ6: Var Actu1/ 2018 (%) | AR6: B23/ 2022 (%)
A8: Parc actif à 3 mois | D8: 218096 | E8: 218545 | F8: 218850 | G8: 219152 | H8: 193519 | I8: 198354 | J8: 213882 | K8: 224788 | L8: 229758 | M8: 237302 | N8: 242737 | O8: 252914 | P8: 268030.85 | Q8: -15116.854 | R8: 217616 | S8: 0.16220315 | U8: 242737 | V8: 258767.38 | W8: -16030.38 | X8: 217091 | Y8: 0.11813479 | AA8: 252914 | AB8: 268030.85 | AC8: -15116.854 | AD8: 217616 | AE8: 0.16220315 | AG8: 215800.27 | AH8: 185163.97 | AI8: 267961 | AL8: 268030.85 | AN8: 217616 | AO8: 50414.854 | AP8: -0.0002606179 | AQ8: 0.23134788 | AR8: 0.23166887 | AS8: ns
A9: Prépayé | D9: 213951 | E9: 214351 | F9: 214604 | G9: 214861 | H9: 189213 | I9: 194034 | J9: 209553 | K9: 220447 | L9: 225403 | M9: 232931 | N9: 238353 | O9: 248517 | P9: 262568.42 | Q9: -14051.417 | R9: 213531 | S9: 0.16384506 | U9: 238353 | V9: 253392.51 | W9: -15039.508 | X9: 213048 | Y9: 0.11877605 | AA9: 248517 | AB9: 262568.42 | AC9: -14051.417 | AD9: 213531 | AE9: 0.16384506 | AG9: 213860.27 | AH9: 183259.97 | AI9: 263149.6 | AL9: 262568.42 | AN9: 213531 | AO9: 49037.417 | AP9: 0.0022134531 | AQ9: 0.23237188 | AR9: 0.22965011 | AS9: ns
B10: dont parc internet mobile 2G -GPRS | D10: 0 | E10: 0 | F10: 0 | G10: 0 | H10: 0 | I10: 0 | J10: 0 | K10: 0 | M10: 0 | N10: 0 | O10: 0 | Q10: ns | R10: 0 | S10: ns | W10: ns | X10: 0 | Y10: ns | AC10: ns | AD10: 0 | AE10: ns | AG10: 1200 | AH10: 1250 | AL10: 126032.84
B11: dont parc 3G | D11: 100730 | E11: 100890 | F11: 101011 | G11: 107819 | H11: 116325 | I11: 123016 | J11: 135833 | K11: 143523 | L11: 149735.5 | M11: 152216 | N11: 153185 | O11: 157175 | P11: 126032.84 | Q11: 31142.16 | R11: 100550 | S11: 0.56315266 | U11: 153185 | V11: 121628.4 | W11: 31556.596 | X11: 100368 | Y11: 0.52623346 | AA11: 157175 | AB11: 126032.84 | AC11: 31142.16 | AD11: 100550 | AE11: 0.56315266 | AG11: 0 | AH11: 0 | AI11: 128668.87 | AL11: 126032.84 | AN11: 100550 | AO11: 25482.84 | AP11: 0.020915397 | AQ11: 0.27965059 | AR11: 0.25343451 | AS11: ns
B12: Dont Mobile Money | P12: 10701.6 | AI12: 10701.6 | AL12: 10701.6
A13: Postpayé yc pré credit | D13: 4145 | E13: 4194 | F13: 4246 | G13: 4291 | H13: 4306 | I13: 4320 | J13: 4329 | K13: 4341 | L13: 4355 | M13: 4371 | N13: 4384 | O13: 4397 | P13: 5462.4365 | Q13: -1065.4365 | R13: 4085 | S13: 0.076376989 | U13: 4384 | V13: 5374.8722 | W13: -990.87218 | X13: 4043 | Y13: 0.084343309 | AA13: 4397 | AB13: 5462.4365 | AC13: -1065.4365 | AD13: 4085 | AE13: 0.076376989 | AG13: 1940 | AH13: 1904 | AI13: 4811.4 | AL13: 5462.4365 | AN13: 4085 | AO13: 1377.4365 | AP13: -0.11918427 | AQ13: 0.1778213 | AR13: 0.33719376 | AS13: ns
B14: dont parc internet mobile 3G | D14: -64515 | E14: -64675 | F14: -64796 | G14: -71604 | H14: -80110 | I14: -86801 | J14: -99618 | K14: -107308 | L14: 832 | M14: -116001 | N14: -116970 | O14: -120960 | P14: 0.47060889 | R14: -12180 | U14: -116970 | W14: -116970 | X14: -12180 | AA14: -120960 | AC14: -120960 | AD14: -12180 | AN14: -64335 | AR14: 0
A16: Parc localisé | D16: 130333 | E16: 132912.33 | F16: 131644 | G16: 137663.67 | H16: 154227 | I16: 160284.33 | J16: 175803.33 | K16: 185482.33 | L16: 186210.67 | M16: 193837.67 | N16: 197844 | O16: 205130.33 | P16: 173446.51 | Q16: 31683.822 | R16: 130999 | S16: 0.56589236 | U16: 197844 | V16: 167451.99 | W16: 30392.012 | X16: 131174 | Y16: 0.50825621 | AA16: 205130.33 | AB16: 173446.51 | AC16: 31683.822 | AD16: 130999 | AE16: 0.56589236 | AG16: 149702.19 | AI16: 149265.39 | AL16: 152699.88 | AN16: 130999 | AO16: 21700.878 | AP16: -0.022491725 | AQ16: 0.13943919 | AR16: 0.16565682 | AS16: ns
A19: Ventes brutes | D19: 11310 | E19: 11284 | F19: 11376 | G19: 14104 | H19: 14644 | I19: 27445 | J19: 30908 | K19: 31166 | L19: 26543.75 | M19: 37555 | N19: 27184 | O19: 31678 | P19: 19357.093 | Q19: 12320.907 | R19: 12090 | S19: 1.620182 | U19: 243519.75 | V19: 157929.39 | W19: 85590.358 | X19: 129217 | Y19: 0.88457982 | AA19: 275197.75 | AB19: 177286.49 | AC19: 97911.265 | AD19: 141307 | AE19: 0.94751675 | AG19: 171206.24 | AH19: 184778.54 | AI19: 192700 | AL19: 177286.49 | AN19: 141307 | AO19: 35979.485 | AP19: 0.086941285 | AQ19: 0.36369748 | AR19: 0.25461927 | AS19: ns
A20: Prépayé | D20: 11228 | E20: 11204 | F20: 11284 | G20: 14010 | H20: 14510 | I20: 27308 | J20: 30781 | K20: 31042 | L20: 26419.75 | M20: 37423 | N20: 27059 | O20: 31553 | P20: 19059.887 | Q20: 12493.113 | R20: 11966 | S20: 1.6368878 | U20: 242268.75 | V20: 155897.42 | W20: 86371.327 | X20: 128034 | Y20: 0.89222199 | AA20: 273821.75 | AB20: 174957.31 | AC20: 98864.44 | AD20: 140000 | AE20: 0.95586964 | AG20: 170282.24 | AH20: 183882.54 | AI20: 191156.6 | AL20: 174957.31 | AN20: 140000 | AO20: 34957.31 | AP20: 0.092589961 | AQ20: 0.36540429 | AR20: 0.24969507 | AS20: ns
A21: Postpayé yc pré credit | D21: 82 | E21: 80 | F21: 92 | G21: 94 | H21: 134 | I21: 137 | J21: 127 | K21: 124 | L21: 124 | M21: 132 | N21: 125 | O21: 125 | P21: 297.20623 | Q21: -172.20623 | R21: 124 | S21: 0.0080645161 | U21: 1251 | V21: 2031.9694 | W21: -780.96943 | X21: 1183 | Y21: 0.057480981 | AA21: 1376 | AB21: 2329.1757 | AC21: -953.17566 | AD21: 1307 | AE21: 0.052792655 | AG21: 924 | AH21: 896 | AI21: 1543.4 | AL21: 2329.1757 | AN21: 1307 | AO21: 1022.1757 | AP21: -0.33736213 | AQ21: 0.18087223 | AR21: 0.78207778 | AS21: ns
A24: Flux d'inactivités | D24: 10830 | E24: 10835 | F24: 11071 | G24: 13802 | H24: 40277 | I24: 22610 | J24: 15380 | K24: 20260 | L24: 21573.75 | M24: 30011 | N24: 21749 | O24: 21501 | P24: 10967.79 | Q24: 10533.21 | R24: 11565 | S24: 0.85914397 | U24: 218398.75 | V24: 119658.01 | W24: 98740.738 | X24: 122115 | Y24: 0.78846784 | AA24: 239896.75 | AB24: 130625.8 | AC24: 109270.95 | AD24: 133680 | AE24: 0.79455977 | AG24: 96748 | AH24: 143729.57 | AI24: 142355 | AL24: 130625.8 | AN24: 133680 | AO24: -3054.1984 | AP24: 0.089792356 | AQ24: 0.064893776 | AR24: -0.022847086 | AS24: ns
A25: Prépayé | D25: 10808 | E25: 10813 | F25: 11031 | G25: 13756 | H25: 40158 | I25: 22487 | J25: 15262 | K25: 20148 | L25: 21463.75 | M25: 29895 | N25: 21637 | O25: 21389 | P25: 10882.118 | Q25: 10506.882 | R25: 11483 | S25: 0.86266655 | U25: 217458.75 | V25: 118917.91 | W25: 98540.836 | X25: 121402 | Y25: 0.79122873 | AA25: 238847.75 | AB25: 129800.03 | AC25: 109047.72 | AD25: 132885 | AE25: 0.79740189 | AG25: 96168 | AH25: 143129.57 | AI25: 141550 | AL25: 129800.03 | AN25: 132885 | AO25: -3084.9676 | AP25: 0.090523611 | AQ25: 0.065206758 | AR25: -0.023215318 | AS25: ns
A26: Postpayé yc pré credit | D26: 22 | E26: 22 | F26: 40 | G26: 46 | H26: 119 | I26: 123 | J26: 118 | K26: 112 | L26: 110 | M26: 116 | N26: 109 | O26: 112 | P26: 85.671893 | Q26: 26.328107 | R26: 82 | S26: 0.36585366 | U26: 937 | V26: 740.09725 | W26: 199.90275 | X26: 713 | Y26: 0.31837307 | AA26: 1049 | AB26: 825.76914 | AC26: 223.23086 | AD26: 795 | AE26: 0.31949686 | AG26: 580 | AH26: 600 | AI26: 805 | AL26: 825.76914 | AN26: 795 | AO26: 30.769142 | AP26: -0.02515127 | AQ26: 0.012578616 | AR26: 0.038703324 | AS26: ns
A28: Désactivés | D28: 0 | E28: 0 | F28: 0 | G28: 0 | H28: 0 | I28: 0 | J28: 0 | K28: 0 | L28: 0 | M28: 0 | N28: 0 | O28: 0 | Q28: 0 | R28: 0 | S28: ns | U28: 0 | V28: 0 | W28: 0 | X28: 0 | Y28: ns | AA28: 0 | AB28: 0 | AC28: 0 | AD28: 0 | AE28: ns | AG28: 31518.965 | AH28: 28684 | AN28: 0 | AO28: 35159.853 | AR28: -35159.853
A29: Prépayé | D29: 0 | E29: 0 | F29: 0 | G29: 0 | H29: 0 | I29: 0 | J29: 0 | K29: 0 | L29: 0 | M29: 0 | N29: 0 | O29: 0 | Q29: 0 | R29: 0 | S29: ns | V29: 0 | Y29: ns | AB29: 0 | AE29: ns | AG29: 30284.965 | AH29: 27524 | AO29: 33358.853 | AR29: -33358.853
A30: Postpayé yc pré credit | D30: 0 | E30: 0 | F30: 0 | G30: 0 | H30: 0 | I30: 0 | J30: 0 | K30: 0 | L30: 0 | M30: 0 | N30: 0 | O30: 0 | Q30: 0 | R30: 0 | S30: ns | V30: 0 | Y30: ns | AB30: 0 | AE30: ns | AG30: 1234 | AH30: 1160 | AO30: 1801 | AR30: -1801
AR32: 0
A33: Accroissement net | D33: 480 | E33: 449 | F33: 305 | G33: 302 | H33: -25633 | I33: 4835 | J33: 15528 | K33: 10906 | L33: 4970 | M33: 7544 | N33: 5435 | O33: 10177 | P33: 8389.3033 | Q33: 1787.6967 | R33: 525 | S33: 18.384762 | U33: 25123 | V33: 38271.38 | W33: -13150.38 | X33: 7102 | Y33: 2.5371726 | AA33: 35300 | AB33: 46660.684 | AC33: -11360.684 | AD33: 7627 | AE33: 3.6282942 | AG33: 71623.272 | AH33: 41048.965 | AI33: 50345 | AL33: 46660.684 | AN33: 7627 | AO33: 39033.684 | AP33: 0.07895976 | AQ33: 5.6008916 | AR33: 5.1178292 | AS33: ns
A34: Prépayé | D34: 420 | E34: 391 | F34: 253 | G34: 254 | H34: -25648 | I34: 4821 | J34: 15519 | K34: 10894 | L34: 4956 | M34: 7528 | N34: 5422 | O34: 10164 | P34: 8177.7689 | Q34: 1986.2311 | R34: 483 | S34: 20.043478 | U34: 24810 | V34: 36979.508 | W34: -12169.508 | X34: 6632 | Y34: 2.740953 | AA34: 34974 | AB34: 45157.277 | AC34: -10183.277 | AD34: 7115 | AE34: 3.9155306 | AG34: 71353.272 | AH34: 40752.965 | AI34: 49606.6 | AL34: 45157.277 | AN34: 7115 | AO34: 38042.277 | AP34: 0.098529477 | AQ34: 5.9721152 | AR34: 5.3467712 | AS34: ns
A35: Postpayé yc pré credit | D35: 60 | E35: 58 | F35: 52 | G35: 48 | H35: 15 | I35: 14 | J35: 9 | K35: 12 | L35: 14 | M35: 16 | N35: 15 | O35: 13 | P35: 211.53434 | Q35: -198.53434 | R35: 42 | S35: -0.69047619 | U35: 313 | V35: 1291.8722 | W35: -980.87218 | X35: 470 | Y35: -0.33829787 | AA35: 326 | AB35: 1503.4065 | AC35: -1177.4065 | AD35: 512 | AE35: -0.36328125 | AG35: 270 | AH35: 296 | AI35: 738.4 | AL35: 1503.4065 | AN35: 512 | AO35: 991.40652 | AP35: -0.50884874 | AQ35: 0.4421875 | AR35: 1.9363409 | AS35: ns
A37: Flux d'inactivité | D37: 0 | E37: 0 | F37: 0 | G37: 0 | H37: 0 | I37: 0 | J37: 0 | K37: 0 | L37: 0 | M37: 0 | N37: 0 | O37: 0 | Q37: 0 | R37: 0 | S37: ns | U37: 0 | V37: 0 | W37: 0 | X37: 0 | Y37: ns | AA37: 1 | AB37: 0 | AC37: 1 | AD37: 0 | AE37: ns | AN37: 0 | AO37: 0
B39: Churn annualisé | D39: 0.59588438 | E39: 0.59493468 | F39: 0.60704592 | G39: 0.75574943 | H39: 2.4975532 | I39: 1.3847343 | J39: 0.90603607 | K39: 1.1084414 | L39: 1.1670949 | M39: 1.5963864 | N39: 1.1431325 | O39: 1.1054593 | P39: 0.49103853 | Q39: -1.1196131 | R39: 0.63772884 | S39: -42.27908 | U39: 1.123363 | V39: 0.70909936 | W39: 41.426367 | X39: 0.62030922 | Y39: 50.305381 | AA39: 1.1218711 | AB39: 0.70909936 | AC39: 41.277169 | AD39: 0.62176085 | AE39: 50.01102 | AG39: 0.48 | AH39: 0.48 | AI39: 0.61072787 | AL39: 0.55491166 | AN39: 0.62176085 | AO39: -0.066849196 | AP39: 0.10058576 | AQ39: -0.017744742 | AR39: -0.10751593 | AS39: ns
B40: Prépayé | D40: 0.60619488 | E40: 0.60534357 | F40: 0.61681982 | G40: 0.76827344 | H40: 2.546844 | I40: 1.4081989 | J40: 0.91855374 | K40: 1.180374 | L40: 1.2424267 | M40: 1.6996096 | N40: 1.2145213 | O40: 1.1727229 | P40: 0.49733862 | Q40: -4.3044501 | R40: 0.64532082 | S40: -45.870096 | U40: 1.1642873 | V40: 0.71762162 | W40: 44.666564 | X40: 0.62801499 | Y40: 53.627228 | AA40: 1.1649902 | AB40: 0.71762162 | AC40: 44.736861 | AD40: 0.62945714 | AE40: 53.553309 | AG40: 0.47 | AH40: 0.47 | AI40: 0.61924826 | AL40: 0.56287807 | AN40: 0.62945714 | AO40: -0.066579073 | AP40: 0.10014635 | AQ40: -0.016218557 | AR40: -0.10577221 | AS40: ns
B41: Postpayé | D41: 0.063691194 | E41: 0.062947067 | F41: 0.11304757 | G41: 0.12864134 | H41: 0.33163028 | I41: 0.34222119 | J41: 0.32796757 | K41: 0.31085926 | L41: 0.30481469 | M41: 0.32084822 | N41: 0.30932106 | O41: 0.30885901 | P41: 0.18820589 | Q41: 245.58756 | R41: 0.24088127 | S41: 256.2526 | U41: 0.23781722 | V41: 0.21654167 | W41: 2.1275549 | X41: 0.19970759 | Y41: 3.8109629 | AA41: 0.24373737 | AB41: 0.21654167 | AC41: 2.7195698 | AD41: 0.20313873 | AE41: 4.0598638 | AG41: 0.52 | AH41: 0.52 | AI41: 0.17661482 | AL41: 0.17036781 | AN41: 0.20313873 | AO41: -0.032770925 | AP41: 0.03666781 | AQ41: -0.13057043 | AR41: -0.16132288 | AS41: ns
A43: Taux de gratuité | D43: 0.53 | E43: 0.53 | F43: 0.53 | G43: 0.53 | H43: 0.53 | I43: 0.53 | J43: 0.53 | K43: 0.53 | L43: 0.53 | M43: 0.53 | N43: 0.53 | O43: 0.53 | P43: 0.53 | Q43: 10 | R43: 0.53 | S43: 7 | U43: 0.53 | V43: 0.54 | W43: -1 | X43: 0.53 | Y43: 0 | AA43: 0.53 | AB43: 0.54 | AC43: -1 | AD43: 0.53 | AE43: 0 | AG43: 0.5 | AH43: 0.5 | AI43: 0.5325 | AL43: 0.53 | AN43: 0.53 | AO43: 0 | AP43: 0.0047169811 | AQ43: 0.0047169811 | AR43: 0 | AS43: ns
A45: Poids de la recharge electronique | D45: 0.943 | E45: 0.943 | F45: 0.943 | G45: 0.943 | H45: 0.943 | I45: 0.943 | J45: 0.943 | K45: 0.943 | L45: 0.943 | M45: 0.943 | N45: 0.943 | O45: 0.943 | P45: 0.94 | Q45: 0 | R45: 0.943 | S45: -2 | U45: 0.943 | V45: 0.94 | W45: 0.3 | X45: 0.943 | Y45: 0 | AA45: 0.943 | AB45: 0.94 | AC45: 0.3 | AD45: 0.943 | AE45: 0 | AG45: 0.98 | AH45: 0.98 | AI45: 0.941 | AL45: 0.94 | AN45: 0.943 | AO45: -0.3 | AP45: 0.0010638298 | AQ45: -0.0021208908 | AR45: -0.0031813362 | AS45: ns
A47: Site | D47: 58 | E47: 58 | F47: 58 | G47: 58 | H47: 58 | I47: 58 | J47: 59 | K47: 59 | L47: 59 | M47: 56 | N47: 58 | O47: 60 | P47: 73 | Q47: -13 | R47: 58 | S47: 0.034482759 | U47: 58 | V47: 73 | W47: -15 | X47: 58 | Y47: 0 | AA47: 60 | AB47: 73 | AC47: -13 | AD47: 58 | AE47: 0.034482759 | AG47: 48 | AH47: 48 | AI47: 88 | AL47: 73 | AN47: 58 | AO47: 15 | AP47: 0.20547945 | AQ47: 0.51724138 | AR47: 0.25862069 | AS47: ns
A48: Site 2G | D48: 58 | E48: 58 | F48: 58 | G48: 58 | H48: 58 | I48: 58 | J48: 59 | K48: 59 | L48: 59 | M48: 56 | N48: 58 | O48: 60 | P48: 73 | Q48: -13 | R48: 58 | S48: 0.034482759 | U48: 58 | V48: 73 | W48: -15 | X48: 58 | Y48: 0 | AA48: 60 | AB48: 73 | AC48: -13 | AD48: 58 | AE48: 0.034482759 | AG48: 48 | AH48: 48 | AI48: 73 | AL48: 73 | AN48: 58 | AO48: 15 | AP48: 0 | AQ48: 0.25862069 | AR48: 0.25862069 | AS48: ns
A49: Site 3G / 4G | D49: 58 | E49: 58 | F49: 58 | G49: 58 | H49: 58 | I49: 58 | J49: 59 | K49: 59 | L49: 59 | M49: 56 | N49: 58 | O49: 60 | P49: 73 | Q49: -13 | R49: 58 | S49: 0.034482759 | U49: 58 | V49: 73 | W49: -15 | X49: 58 | Y49: 0 | AA49: 60 | AB49: 73 | AC49: -13 | AD49: 58 | AE49: 0.034482759 | AG49: 0 | AH49: 0 | AI49: 73 | AL49: 73 | AN49: 58 | AO49: 15 | AP49: 0 | AQ49: 0.25862069 | AR49: 0.25862069 | AS49: ns
AC50: 0 | AO50: -1.25 | AT50: ns
AL51: 58 | AO51: 4.8333333 | AT51: ns
AL52: 58 | AO52: 4.8333333 | AT52: ns
AT53: ns
AO54: 15 | AT54: ns
AT55: ns
AL56: 115 | AT56: ns
AL57: 67.083333 | AT57: ns
AT58: ns
AO59: 1.25 | AT59: ns
AT60: ns
AT61: ns
AI62: 471.57538 | AT62: ns
AI63: 394.04883 | AT63: ns
AI64: 367.33756 | AT64: ns
AI65: 25.101853 | AT65: ns
B69: Prix minute postpayé pure | O69: 0.65558247
B70: Usage postpayé | O70: 448.15299

Sheet  ARPU & Usage
A2: Moov RCA : ARPU & Usage Mobile
O5: MENSUEL | U5: CUMUL (m-1) | AA5: CUMUL | AI5: ANNUEL
D6: Janvier | E6: Février | F6: Mars | G6: Avril | H6: Mai | I6: Juin | J6: Juillet | K6: Août | L6: Septembre | M6: Octobre | N6: Novembre | O6: 2023 | P6: 2023 Budget | Q6: Ecart / Budget | R6: 2022 Réel | S6: Evol % | U6: 2020 Réel | V6: 2020 Budget | W6: Ecart / Budget | X6: 2019 Réel | Y6: Evol % | AA6: 2023 | AB6: 2023 Budget | AC6: Ecart / Budget | AD6: 2022 Réel | AE6: Evol % | AG6: 2023 Actu 1 | AH6: 2023 Actu 2 | AI6: 2023 Actu3 | AJ6: 2023 Budget | AK6: 2019 Actu3 | AL6: 2022 Réel | AM6: Ecart / Budget | AN6: B23/ 2022 (%) | AO6: Var Actu3/ 2019 (%)
A8: ARPU GLOBAL (sortant+entrant) Parc 3 mois | D8: 1371.9791 | E8: 1341.0131 | F8: 1412.0947 | G8: 1417.4321 | H8: 1614.1468 | I8: 1619.7972 | J8: 1656.6434 | K8: 1646.6596 | L8: 1560.0234 | M8: 1653.7279 | N8: 1497.0577 | O8: 1465.9892 | P8: 2093.2286 | Q8: -627.23936 | R8: 1409.1572 | S8: 0.040330501 | U8: 1533.5493 | V8: 1716.7697 | W8: -183.22039 | X8: 1455.2771 | Y8: 0.053785091 | AA8: 1528.806 | AB8: 1748.1413 | AC8: -219.33529 | AD8: 1451.2444 | AE8: 0.0534449 | AG8: 1780.8424 | AJ8: 1748.1413 | AL8: 1451.2444 | AM8: 296.8969 | AN8: 0.20458091 | AO8: ns
A10: ARPU Sortant global | D10: 1328.4367 | E10: 1308.0869 | F10: 1378.2558 | G10: 1379.9296 | H10: 1574.5847 | I10: 1576.6425 | J10: 1614.655 | K10: 1601.9576 | L10: 1520.3004 | M10: 1590.7693 | N10: 1444.6656 | O10: 1420.695 | P10: 2010.7368 | Q10: -590.04176 | R10: 1365.4455 | S10: 0.040462642 | U10: 1490.1581 | V10: 1650.2572 | W10: -160.09913 | X10: 1405.373 | Y10: 0.060329257 | AA10: 1485.1901 | AB10: 1680.2972 | AC10: -195.10704 | AD10: 1401.8669 | AE10: 0.059437329 | AG10: 1738.7585 | AJ10: 1680.2972 | AL10: 1401.8669 | AM10: 278.43026 | AN10: 0.19861391 | AO10: ns
A11: Sortant prépayé | D11: 1214.1358 | E11: 1209.2236 | F11: 1252.4442 | G11: 1265.4254 | H11: 1464.6808 | I11: 1473.3146 | J11: 1518.0023 | K11: 1508.6762 | L11: 1430.5388 | M11: 1488.1275 | N11: 1347.7853 | O11: 1343.3606 | P11: 1859.1574 | Q11: -515.79688 | R11: 1254.9345 | S11: 0.070462659 | U11: 1385.6261 | V11: 1534.1988 | W11: -148.57267 | X11: 1305.3394 | Y11: 0.061506425 | AA11: 1383.1294 | AB11: 1561.2787 | AC11: -178.14931 | AD11: 1300.9719 | AE11: 0.063150814 | AG11: 1596.5113 | AJ11: 1561.2787 | AL11: 1300.9719 | AM11: 260.30675 | AN11: 0.20008637 | AO11: ns
A12: Sortant postpayé | D12: 7228.2645 | E12: 6385.8364 | F12: 7772.5118 | G12: 7140.2132 | H12: 6740.2606 | I12: 6167.4262 | J12: 6124.7458 | K12: 6228.3737 | L12: 6122.4431 | M12: 6982.0401 | N12: 6659.7624 | O12: 5708.5709 | P12: 9227.3832 | Q12: -3518.8123 | R12: 7165.3543 | S12: -0.20330934 | U12: 6678.858 | V12: 7225.3705 | W12: -546.51245 | X12: 6851.2038 | Y12: -0.02515555 | AA12: 6596.0004 | AB12: 7392.2049 | AC12: -796.20451 | AD12: 6875.4589 | AE12: -0.040645799 | AG12: 9012.7696 | AJ12: 7392.2049 | AL12: 6875.4589 | AM12: 516.74599 | AN12: 0.075158036 | AO12: ns
A13: ARPU Sortant global (voix + data + sms) | D13: 0 | E13: 0 | F13: 0 | G13: 0 | H13: 0 | I13: 0 | J13: 0 | K13: 0 | L13: 0 | M13: 0 | N13: 0 | O13: 0 | Q13: 0 | R13: 0 | S13: ns | V13: 1321.5724 | Y13: ns | AB13: 1321.5724 | AE13: ns | AN13: 0
A15: ARPU Entrant global | D15: 43.542467 | E15: 32.926138 | F15: 33.838866 | G15: 37.502459 | H15: 39.562068 | I15: 43.154657 | J15: 41.988383 | K15: 44.701964 | L15: 39.723012 | M15: 62.95866 | N15: 52.392006 | O15: 45.294161 | P15: 82.491764 | Q15: -37.197604 | R15: 43.711678 | S15: 0.036202734 | U15: 43.391262 | V15: 66.512519 | W15: -23.121257 | X15: 49.904157 | Y15: -0.13050806 | AA15: 43.615874 | AB15: 67.844123 | AC15: -24.228249 | AD15: 49.377487 | AE15: -0.11668502 | AG15: 42.083914 | AJ15: 67.844123 | AL15: 49.377487 | AM15: 18.466636 | AN15: 0.37398899 | AO15: ns
A16: Entrant prépayé | D16: 43.053972 | E16: 32.559822 | F16: 33.469151 | G16: 37.100082 | H16: 39.191225 | I16: 42.801704 | J16: 41.601089 | K16: 44.234681 | L16: 39.282403 | M16: 62.231875 | N16: 51.763742 | O16: 44.727229 | P16: 81.697699 | Q16: -36.970469 | R16: 43.20773 | S16: 0.035167298 | U16: 42.936976 | V16: 65.866071 | W16: -22.929095 | X16: 49.295654 | Y16: -0.12899064 | AA16: 43.151769 | AB16: 67.185373 | AC16: -24.033604 | AD16: 48.778481 | AE16: -0.11535233 | AG16: 41.61903 | AJ16: 67.185373 | AL16: 48.778481 | AM16: 18.406892 | AN16: 0.37735682 | AO16: ns
A17: Entrant postpayé | D17: 68.75696 | E17: 51.740641 | F17: 52.629306 | G17: 57.744553 | H17: 56.992338 | I17: 58.83612 | J17: 60.060595 | K17: 67.877511 | L17: 62.313328 | M17: 101.13312 | N17: 86.211632 | O17: 76.728144 | P17: 120.29698 | Q17: -43.568833 | R17: 70.160211 | S17: 0.093613354 | U17: 65.940876 | V17: 97.498125 | W17: -31.557249 | X17: 83.03107 | Y17: -0.2058289 | AA17: 66.856446 | AB17: 99.398029 | AC17: -32.541584 | AD17: 81.873788 | AE17: -0.18342064 | AG17: 65.907064 | AJ17: 99.398029 | AL17: 81.873788 | AM17: 17.524241 | AN17: 0.2140397 | AO17: ns
A20: USAGE GLOBAL (sortant+entrant) Parc 3 mois | D20: 15.725623 | E20: 15.892395 | F20: 16.023821 | G20: 16.603989 | H20: 18.149964 | I20: 20.106016 | J20: 20.011788 | K20: 20.498296 | L20: 20.831384 | M20: 34.179955 | N20: 28.543363 | O20: 28.635935 | P20: 23.337182 | Q20: 5.2987531 | R20: 15.367621 | S20: 0.86339421 | U20: 20.888593 | V20: 18.047201 | W20: 2.8413922 | X20: 15.630476 | Y20: 0.33640154 | AA20: 21.639329 | AB20: 18.488032 | AC20: 3.1512961 | AD20: 15.606746 | AE20: 0.38653686 | AG20: 20.922382 | AJ20: 18.488032 | AL20: 15.606746 | AM20: 2.8812864 | AN20: 0.18461801 | AO20: ns
A22: Usage sortant / clt / mois | D22: 15.226714 | E22: 15.380757 | F22: 15.469214 | G22: 15.992511 | H22: 17.467186 | I22: 19.34357 | J22: 19.238071 | K22: 19.716054 | L22: 20.061473 | M22: 31.01825 | N22: 27.397927 | O22: 27.071322 | P22: 21.182245 | Q22: 5.8890772 | R22: 14.874455 | S22: 0.81998748 | U22: 19.932189 | V22: 16.452053 | W22: 3.4801359 | X22: 15.124809 | Y22: 0.31784728 | AA22: 20.624706 | AB22: 16.846236 | AC22: 3.7784705 | AD22: 15.102184 | AE22: 0.36567711 | AG22: 20.081117 | AJ22: 16.846236 | AL22: 15.102184 | AM22: 1.7440524 | AN22: 0.11548346 | AO22: ns
A23: Sortant prépayé | D23: 14.43519 | E23: 14.582604 | F23: 14.669432 | G23: 15.168685 | H23: 16.590097 | I23: 18.394422 | J23: 18.274825 | K23: 18.705634 | L23: 19.021065 | M23: 29.396176 | N23: 25.953413 | O23: 25.6304 | P23: 20.113259 | Q23: 5.5171418 | R23: 14.096821 | S23: 0.81816884 | U23: 18.910382 | V23: 15.619241 | W23: 3.291141 | X23: 14.32445 | Y23: 0.32014716 | AA23: 19.564013 | AB23: 15.993743 | AC23: 3.5702703 | AD23: 14.303923 | AE23: 0.36773755 | AG23: 19.039827 | AJ23: 15.993743 | AL23: 14.303923 | AM23: 1.6898194 | AN23: 0.11813678 | AO23: ns
A24: Sortant postpayé | D24: 56.082504 | E24: 56.374966 | F24: 56.117416 | G24: 57.436177 | H24: 58.691877 | I24: 61.513517 | J24: 64.185893 | K24: 69.829171 | L24: 73.403906 | M24: 116.21784 | N24: 105.1565 | O24: 106.96446 | P24: 72.076369 | Q24: 34.888096 | R24: 55.686773 | S24: 0.92082355 | U24: 70.652088 | V24: 56.45975 | W24: 14.192338 | X24: 58.69639 | Y24: 0.2036871 | AA24: 73.740156 | AB24: 57.761135 | AC24: 15.979021 | AD24: 58.408119 | AE24: 0.26249839 | AG24: 73.49195 | AJ24: 57.761135 | AL24: 58.408119 | AM24: -0.64698435 | AN24: -0.011076959 | AO24: ns
A26: Usage entrant / clt / mois | D26: 0.49890874 | E26: 0.51163771 | F26: 0.5546069 | G26: 0.61147731 | H26: 0.68277781 | I26: 0.762446 | J26: 0.773717 | K26: 0.78224178 | L26: 0.76991108 | M26: 3.1617051 | N26: 1.1454361 | O26: 1.564613 | P26: 2.1549371 | Q26: -0.59032407 | R26: 0.4931654 | S26: 2.1725928 | U26: 0.95640373 | V26: 1.5951474 | W26: -0.63874369 | X26: 0.50566695 | Y26: 0.89137083 | AA26: 1.0146222 | AB26: 1.6417966 | AC26: -0.62717432 | AD26: 0.50456251 | AE26: 1.010895 | AG26: 0.84126453 | AJ26: 1.6417966 | AL26: 0.50456251 | AM26: 1.1372341 | AN26: 2.2539012 | AO26: ns
A27: Entrant prépayé | D27: 0.49331716 | E27: 0.49285644 | F27: 0.54855362 | G27: 0.60492342 | H27: 0.67638532 | I27: 0.7131425 | J27: 0.76658906 | K27: 0.77407353 | L27: 0.76137984 | M27: 3.1252423 | N27: 1.1317133 | O27: 1.5450468 | P27: 2.1341937 | Q27: -0.58914685 | R27: 0.48748527 | S27: 2.1694226 | U27: 0.94168004 | V27: 1.5796391 | W27: -0.63795905 | X27: 0.4995068 | Y27: 0.88521964 | AA27: 0.99955588 | AB27: 1.625852 | AC27: -0.62629608 | AD27: 0.49844724 | AE27: 1.0053394 | AG27: 0.83086604 | AJ27: 1.625852 | AL27: 0.49844724 | AM27: 1.1274047 | AN27: 2.2618337 | AO27: ns
A28: Entrant postpayé | D28: 0.78752714 | E28: 0.78289963 | F28: 0.86225931 | G28: 0.9411794 | H28: 0.98323578 | I28: 0.97993021 | J28: 1.1063267 | K28: 1.1873564 | L28: 1.2073137 | M28: 5.0769173 | N28: 1.8841371 | O28: 2.6494773 | P28: 3.1425248 | Q28: -0.49304752 | R28: 0.79127381 | S28: 2.3483697 | U28: 1.4456477 | V28: 2.3386673 | W28: -0.89301953 | X28: 0.84102571 | Y28: 0.71891029 | AA28: 1.5480594 | AB28: 2.4056554 | AC28: -0.857596 | AD28: 0.83631843 | AE28: 0.85104063 | AG28: 1.3170546 | AJ28: 2.4056554 | AL28: 0.83631843 | AM28: 1.569337 | AN28: 1.8764826 | AO28: ns
A31: ARPM sortant Global | D31: 23.644927 | E31: 24.770854 | F31: 25.913214 | G31: 27.145693 | H31: 28.680782 | I31: 26.199816 | J31: 25.35264 | K31: 24.120286 | L31: 23.017057 | M31: 16.3219 | N31: 18.280909 | O31: 17.487006 | P31: 28.676997 | Q31: -11.189991 | R31: 26.09843 | S31: -0.32995945 | U31: 23.949825 | V31: 28.213268 | W31: -4.2634423 | X31: 26.721893 | Y31: -0.10373771 | AA31: 23.411257 | AB31: 28.251912 | AC31: -4.8406547 | AD31: 26.669938 | AE31: -0.12218555 | AG31: 26.89559 | AJ31: 28.450673 | AL31: 26.669938 | AM31: 1.7807346 | AN31: 0.066769356 | AO31: ns
A33: ARPM sortant prépayé voix | D33: 18.961433 | E33: 21.127688 | F33: 21.252654 | G33: 23.012772 | H33: 24.803211 | I33: 22.894902 | J33: 22.221978 | K33: 21.211435 | L33: 20.17717 | M33: 14.652827 | N33: 16.197925 | O33: 15.893391 | P33: 26.017437 | Q33: -10.124046 | R33: 21.710357 | S33: -0.26793506 | U33: 20.592181 | V33: 24.439921 | W33: -3.8477395 | X33: 22.972005 | Y33: -0.10359668 | AA33: 20.200616 | AB33: 24.571381 | AC33: -4.3707651 | AD33: 22.866867 | AE33: -0.11659891 | AG33: 22.46167 | AJ33: 24.851913 | AL33: 22.866867 | AM33: 1.9850456 | AN33: 0.086808813 | AO33: ns
A35: ARPM sortant post payé voix | D35: 85.868479 | E35: 73.172921 | F35: 87.83209 | G35: 82.054501 | H35: 80.197074 | I35: 70.107969 | J35: 66.945711 | K35: 62.766457 | L35: 60.746994 | M35: 38.496731 | N35: 45.954833 | O35: 38.659323 | P35: 64.011155 | Q35: -25.351832 | R35: 84.397119 | S35: -0.54193551 | U35: 68.558524 | V35: 78.344874 | W35: -9.7863507 | X35: 76.541841 | Y35: -0.10430004 | AA35: 66.066924 | AB35: 77.150398 | AC35: -11.083474 | AD35: 77.196448 | AE35: -0.14417145 | AG35: 85.803385 | AJ35: 76.262764 | AL35: 77.196448 | AM35: -0.93368329 | AN35: -0.0120949 | AO35: ns
AJ38: 115
AJ39: 67.083333
AD42: 4.9787062
R44: 67.166525 | AD44: 59.209722 | AG44: 471.57538
AG45: 394.04883
R46: 26.333743 | AD46: 30.311054 | AG46: 367.33756
AG47: 25.101853
R48: 204.17445 | AD48: 140.3669
B51: Prix minute postpayé pure | O51: -1.8830218
B52: Usage postpayé | O52: 448.15299

Sheet CA Mobile
AO1: =+AB2-AO2 -> 105.49346
B2: Moov RCA : CA Mobile | AB2: =+AB21+AB22+AB29 -> 2577.8263 | AO2: =+AO21+AO22+AO29 -> 2472.3328
K5: =+K9*10^6*1.19 -> 4.2142669e+08 | P5: MENSUEL | V5: CUMUL (m-1) | AB5: CUMUL | AJ5: ANNUEL
E6: Janvier | F6: Février | G6: Mars | H6: Avril | I6: Mai | J6: Juin | K6: Juillet | L6: Août | M6: Septembre | N6: Octobre | O6: Novembre | P6: 2023 | Q6: 2023 Budget | R6: Ecart / Budget | S6: 2022 Réel | T6: Evol % | V6: 2023 | W6: 2023 Budget | X6: Ecart / Budget | Y6: 2021 Réel | Z6: Evol % | AB6: 2023 | AC6: 2023 Budget | AD6: Ecart / Budget | AE6: 2022 Réel | AF6: Evol % | AH6: 2017 Actu 1 | AI6: 2017 Actu 2 | AJ6: 2023 Actu 1 | AK6: 2023 Actu 2 | AL6: 2023 Actu3 | AM6: 2023 Budget | AN6: 2019 Actu3 | AO6: 2022 Réel | AP6: Ecart / Budget | AQ6: Var Actu1/ Budget (%) | AR6: Var Actu1/ 2018 (%) | AS6: B23/ 2022 (%) | AT6: Var Actu3/ 2018 (%) | AX6: =+AB9-'Marge Mobile'!AA35 -> 3728.4982
B9: CA Global | E9: 308.61504 | F9: 300.96135 | G9: 317.29534 | H9: 317.9 | I9: 345.63525 | J9: 328.565 | K9: 354.14007 | L9: 373.72891 | M9: 365.64251 | N9: 394.72369 | O9: 368.20351 | P9: 374.89057 | Q9: 575.53449 | R9: -200.64392 | S9: 315.53342 | T9: 0.18811686 | V9: 3775.4107 | W9: 4580.7294 | X9: -805.31869 | Y9: 3545.3164 | Z9: 0.064900928 | AB9: 4150.3013 | AC9: 5156.2639 | AD9: -1005.9626 | AE9: 3860.8498 | AF9: 0.074970925 | AH9: 4718.995 | AI9: 4718.6895 | AJ9: 5156.1148 | AM9: 5156.2639 | AO9: 3860.8498 | AP9: 1295.4141 | AQ9: -2.8906658e-05 | AR9: 0.33548703 | AS9: 0.33552564 | AT9: ns
B11: CA Global hors transit et collocalisation | E11: 306.23504 | F11: 298.58135 | G11: 314.91534 | H11: 315.52 | I11: 343.25525 | J11: 326.185 | K11: 351.76007 | L11: 371.34891 | M11: 363.26251 | N11: 392.34369 | O11: 365.82351 | P11: 372.51057 | Q11: 568.53449 | R11: -196.02392 | S11: 313.15342 | T11: 0.18954657 | V11: 3749.2307 | W11: 4571.8423 | X11: -822.61166 | Y11: 3508.2164 | Z11: 0.068699959 | AB11: 4121.7413 | AC11: 5147.0825 | AD11: -1025.3413 | AE11: 3821.3698 | AF11: 0.078603091 | AJ11: 5127.5548 | AM11: 5097.2639 | AN11: 0 | AO11: 3821.3698 | AP11: 1275.8941 | AQ11: 0.0059425901 | AR11: 0.34181069 | AS11: 0.33388397 | AT11: ns
B13: CA transit international Azur | E13: 0 | F13: 0 | G13: 0 | H13: 0 | I13: 0 | J13: 0 | K13: 0 | L13: 0 | M13: 0 | N13: 0 | O13: 0 | P13: 0 | Q13: 0 | S13: 0 | V13: 0 | W13: 0 | Y13: 0 | AB13: 0 | AC13: 0 | AE13: 0 | AM13: 0 | AO13: 0 | AQ13: ns | AR13: ns | AS13: ns
B14: CA transit Orange vers international | V14: 0 | Y14: 0 | AB14: 0 | AE14: 0 | AO14: 0 | AQ14: ns | AR14: ns | AS14: ns
B16: CA services | E16: 302.51504 | F16: 296.06135 | G16: 312.39534 | H16: 314.12819 | I16: 336.75726 | J16: 320.67887 | K16: 346.22285 | L16: 365.92891 | M16: 358.24251 | N16: 389.92369 | O16: 363.20351 | P16: 366.38213 | Q16: 562.35455 | R16: -195.97243 | S16: 309.5856 | T16: 0.18345987 | V16: 3706.0575 | W16: 4483.4152 | X16: -777.35771 | Y16: 3492.7382 | Z16: 0.061075108 | AB16: 4072.4397 | AC16: 5045.7698 | AD16: -973.33014 | AE16: 3802.3238 | AF16: 0.071039689 | AH16: 4619.8687 | AI16: 4643.7486 | AJ16: 5080.443 | AM16: 5045.7698 | AO16: 3802.3238 | AP16: 1243.446 | AQ16: 0.0068717386 | AR16: 0.33614161 | AS16: 0.32702266 | AT16: ns
B18: CA sortant | E18: 289.72672 | F18: 285.58219 | G18: 301.4211 | H18: 302.20597 | I18: 324.89273 | J18: 308.92182 | K18: 332.80945 | L18: 351.36538 | M18: 345.52323 | N18: 371.49235 | O18: 346.74793 | P18: 352.08446 | Q18: 529.6263 | R18: -177.54184 | S18: 296.78436 | T18: 0.18633091 | V18: 3560.6889 | W18: 4232.0772 | X18: -671.38835 | Y18: 3320.6911 | Z18: 0.07227344 | AB18: 3912.7733 | AC18: 4761.7035 | AD18: -848.93019 | AE18: 3617.4755 | AF18: 0.081630925 | AH18: 3781.0121 | AI18: 3834.9697 | AJ18: 4918.0765 | AM18: 4761.7035 | AO18: 3617.4755 | AP18: 1144.2281 | AQ18: 0.032839709 | AR18: 0.35953278 | AS18: 0.31630569 | AT18: ns | AW18: =+AB18/AO18-1 -> 0.081630925 | AX18: =+AB19-'Marge Mobile'!AA36 -> 3226.9462
C19: Prépayé (yc commissions) | E19: 259.76557 | F19: 258.95645 | G19: 268.6211 | H19: 271.72797 | I19: 295.91972 | J19: 282.32171 | K19: 306.32299 | L19: 324.36538 | M19: 318.90285 | N19: 341.02971 | O19: 317.59482 | P19: 327.02098 | Q19: 479.6263 | R19: -152.60532 | S19: 267.66436 | T19: 0.22175765 | V19: 3245.5283 | W19: 3853.4592 | X19: -607.93091 | Y19: 3028.6928 | Z19: 0.071593745 | AB19: 3572.5492 | AC19: 4333.0855 | AD19: -760.53622 | AE19: 3296.3572 | AF19: 0.083787061 | AH19: 3258.2173 | AI19: 3462.5764 | AJ19: 4431.9148 | AM19: 4333.0855 | AO19: 3296.3572 | AP19: 1036.7283 | AQ19: 0.022808076 | AR19: 0.34448866 | AS19: 0.31450727 | AT19: ns | AW19: =+AB19/AO19-1 -> 0.083787061 | AX19: =+AX18-5 -> 3221.9462
C20: dont voix | E20: 58.560935 | F20: 65.979217 | G20: 66.866438 | H20: 74.957424 | I20: 83.135737 | J20: 80.700032 | K20: 81.948899 | L20: 85.306268 | M20: 85.556668 | N20: 98.710724 | O20: 99.061881 | P20: 99.164217 | Q20: 135 | R20: -35.835783 | S20: 65.276614 | T20: 0.51913848 | V20: 880.78422 | W20: 976.14359 | X20: -95.359366 | Y20: 764.11255 | Z20: 0.15268912 | AB20: 979.94844 | AC20: 1111.1436 | AD20: -131.19515 | AE20: 829.38917 | AF20: 0.18153031 | AG20: 0.27429949 | AH20: 2860.386 | AI20: 3086.2415 | AJ20: 1207.7431 | AM20: 1111.1436 | AO20: 829.38917 | AP20: 281.75442 | AQ20: 0.086937058 | AR20: 0.45618389 | AS20: 0.33971317 | AT20: ns | AW20: =+AB20/AO20-1 -> 0.18153031
C21: dont 2G/3G | E21: 177.53206 | F21: 166.02908 | G21: 178.67815 | H21: 175.32183 | I21: 190.37642 | J21: 183.05963 | K21: 204.88597 | L21: 217.37458 | M21: 212.94442 | N21: 221.68118 | O21: 203.44442 | P21: 211.83034 | Q21: 284.6263 | R21: -72.795953 | S21: 178.12307 | T21: 0.18923589 | V21: 2131.3277 | W21: 2397.8327 | X21: -266.50493 | Y21: 1906.3985 | Z21: 0.1179865 | AB21: 2343.1581 | AC21: 2682.459 | AD21: -339.30088 | AE21: 2084.5215 | AF21: 0.12407478 | AG21: 0.65587846 | AH21: 372.55707 | AI21: 349.2514 | AJ21: 2902.7651 | AM21: 2682.459 | AO21: 2084.5215 | AP21: 597.93743 | AQ21: 0.08212842 | AR21: 0.39253303 | AS21: 0.28684637 | AT21: ns | AW21: =+AB21/AO21-1 -> 0.12407478
C22: dont BLR | E22: 16.127506 | F22: 12.191772 | G22: 10.752526 | H22: 13 | I22: 9.2765834 | J22: 9.5768805 | K22: 10.337186 | L22: 8.5544331 | M22: 7.9549235 | N22: 12.645535 | O22: 8.3686909 | P22: 8.3686909 | Q22: 36 | R22: -27.631309 | S22: 16.231903 | T22: -0.48442947 | V22: 118.78604 | W22: 325.3 | X22: -206.51396 | Y22: 260.66351 | Z22: -0.54429356 | AB22: 127.15473 | AC22: 361.3 | AD22: -234.14527 | AE22: 276.89541 | AF22: -0.54078427 | AJ22: 140.0718 | AM22: 361.3 | AO22: 276.89541 | AP22: 84.404592 | AS22: 0.30482482 | AT22: ns | AW22: =+AB22/AO22-1 -> -0.54078427
C23: dont MIHD | E23: 5.9275286 | F23: 12.810683 | G23: 10.723991 | H23: 6.3374368 | I23: 10.560215 | J23: 6.3374368 | K23: 6.3374368 | L23: 9.7021048 | M23: 9.7021048 | N23: 4.9364473 | O23: 1.4364473 | P23: 4.1364473 | Q23: 15 | R23: -10.863553 | S23: 5.9275286 | T23: -0.30216325 | V23: 84.811832 | W23: 108.5 | X23: -23.688168 | Y23: 71.434307 | Z23: 0.18727031 | AB23: 88.94828 | AC23: 123.5 | AD23: -34.55172 | AE23: 77.361836 | AF23: 0.1497695 | AJ23: 155.40964 | AM23: 123.5 | AO23: 77.361836 | AP23: 46.138164 | AS23: 0.59639438 | AT23: ns | AW23: =+AB23/AO23-1 -> 0.1497695
C24: dont sms | E24: 1.6175378 | F24: 1.9456992 | G24: 1.6 | H24: 2.1112768 | I24: 2.5707613 | J24: 2.6477227 | K24: 2.813495 | L24: 3.4279917 | M24: 2.7447391 | N24: 3.0558168 | O24: 5.2833824 | P24: 3.5212798 | Q24: 6 | R24: -2.4787202 | S24: 2.1052471 | T24: 0.67262071 | V24: 29.818423 | W24: 36.132906 | X24: -6.3144833 | Y24: 26.083968 | Z24: 0.14317049 | AB24: 33.339702 | AC24: 42.132906 | AD24: -8.7932034 | AE24: 28.189215 | AF24: 0.18271127 | AG24: 0.0093321884 | AH24: 25.274234 | AI24: 27.083535 | AJ24: 22.925136 | AM24: 42.132906 | AO24: 28.189215 | AP24: 13.943691 | AQ24: -0.45588525 | AR24: -0.1867409 | AS24: 0.49464629 | AT24: ns | AW24: =+AB24/AO24-1 -> 0.18271127
C25: dont BBY | R25: 0 | T25: ns | V25: 0 | W25: 0 | X25: 0 | Y25: 0 | Z25: ns | AB25: 0 | AC25: 0 | AD25: 0 | AE25: 0 | AF25: ns | AH25: 284.13879 | AI25: 220.99684 | AJ25: 3 | AO25: 0 | AP25: 0 | AQ25: ns | AR25: ns | AS25: ns | AW25: =+AB25/AO25-1 -> #DIV/0!
C26: Mobile Money | E26: 0 | F26: 0 | G26: 0 | H26: 0 | I26: 0 | J26: 0 | K26: 0 | L26: 0 | M26: 0 | N26: 0 | O26: 0 | P26: 0 | Q26: 3 | R26: -3 | S26: 0 | T26: ns | V26: 0 | W26: 9.55 | X26: -9.55 | Y26: 0 | Z26: ns | AB26: 0 | AC26: 12.55 | AD26: -12.55 | AE26: 0 | AF26: ns | AJ26: 3 | AM26: 12.55 | AO26: 0 | AP26: 12.55 | AS26: ns | AW26: =+AB26/AO26-1 -> #DIV/0!
C27: Postpayé | E27: 29.961157 | F27: 26.625745 | G27: 32.8 | H27: 30.478 | I27: 28.97301 | J27: 26.600109 | K27: 26.486463 | L27: 27 | M27: 26.620383 | N27: 30.462641 | O27: 29.15311 | P27: 25.06348 | Q27: 50 | R27: -24.93652 | S27: 29.12 | T27: -0.13930356 | V27: 315.16062 | W27: 378.61806 | X27: -63.457448 | Y27: 291.99831 | Z27: 0.079323439 | AB27: 340.2241 | AC27: 428.61806 | AD27: -88.393967 | AE27: 321.11831 | AF27: 0.059497667 | AH27: 522.79481 | AI27: 372.39331 | AJ27: 486.16168 | AM27: 428.61806 | AO27: 321.11831 | AP27: 107.49976 | AQ27: 0.13425382 | AR27: 0.51396438 | AS27: 0.33476683 | AT27: ns | AW27: =+AB27/AO27-1 -> 0.059497667
C28: dont voix +sms | E28: 19.961157 | F28: 17.199692 | G28: 20.8 | H28: 20.117 | I28: 20.232682 | J28: 18.600191 | K28: 18.582248 | L28: 19 | M28: 19.388022 | N28: 19.520092 | O28: 21.154047 | P28: 18.15548 | Q28: 25 | R28: -6.8445196 | S28: 19.1 | T28: -0.049451289 | V28: 214.55513 | W28: 231.64806 | Y28: 191.1024 | AB28: 232.71061 | AC28: 256.64806 | AE28: 210.2024 | AH28: 0 | AI28: 0 | AJ28: 334.87463 | AM28: 256.64806 | AO28: 210.2024 | AP28: 46.445661 | AQ28: 0.3048009 | AR28: 0.59310559 | AS28: 0.22095685 | AW28: =+AB28/AO28-1 -> 0.10707873
C29: dont data 3G | E29: 10 | F29: 9.4260531 | G29: 12 | H29: 10.361 | I29: 8.740328 | J29: 7.999918 | K29: 7.904215 | L29: 8 | M29: 7.2323609 | N29: 10.942549 | O29: 7.9990627 | P29: 6.908 | Q29: 25 | R29: -18.092 | S29: 10.02 | T29: -0.31057885 | V29: 100.60549 | W29: 146.97 | Y29: 100.8959 | AB29: 107.51349 | AC29: 171.97 | AE29: 110.9159 | AH29: 0 | AI29: 0 | AJ29: 151.28705 | AM29: 171.97 | AO29: 110.9159 | AP29: 61.054097 | AQ29: -0.12027067 | AR29: 0.36397982 | AS29: 0.55045395 | AW29: =+AB29/AO29-1 -> -0.030675642
AW30: =+AB30/AO30-1 -> #DIV/0!
B31: CA entrant | E31: 9.4964379 | F31: 7.188451 | G31: 7.4004755 | H31: 8.213076 | I31: 8.163059 | J31: 8.4555725 | K31: 8.6545615 | L31: 9.8047053 | M31: 9.0279681 | N31: 14.702736 | O31: 12.575103 | P31: 11.225048 | Q31: 21.728258 | R31: -10.50321 | S31: 9.5008863 | T31: 0.18147378 | V31: 103.68215 | W31: 172.23352 | X31: -68.551374 | Y31: 117.91624 | Z31: -0.12071358 | AB31: 114.90719 | AC31: 193.96178 | AD31: -79.054583 | AE31: 127.41712 | AF31: -0.098180914 | AH31: 625.48065 | AI31: 591.35584 | AJ31: 118.29844 | AM31: 193.96178 | AO31: 127.41712 | AP31: 66.544654 | AQ31: -0.39009404 | AR31: -0.071565568 | AS31: 0.52225833 | AT31: ns
C32: Prépayé | E32: 9.2114403 | F32: 6.9727184 | G32: 7.1783798 | H32: 7.9665934 | I32: 7.9180774 | J32: 8.2018123 | K32: 8.3948294 | L32: 9.5104563 | M32: 8.7570297 | N32: 14.261492 | O32: 12.197712 | P32: 10.888173 | Q32: 21.052509 | R32: -10.164336 | S32: 9.2157552 | T32: 0.18147378 | V32: 100.57054 | W32: 166.87706 | X32: -66.306516 | Y32: 114.37745 | Z32: -0.12071358 | AB32: 111.45871 | AC32: 187.92957 | AD32: -76.470852 | AE32: 123.59321 | AF32: -0.098180914 | AJ32: 114.74914 | AM32: 188.14292 | AO32: 123.59321 | AP32: 64.549716 | AS32: 0.52227559
C33: Postpayé | E33: 0.2849976 | F33: 0.2157326 | G33: 0.22209567 | H33: 0.24648262 | I33: 0.24498156 | J33: 0.25376019 | K33: 0.25973204 | L33: 0.29424901 | M33: 0.27093835 | N33: 0.4412438 | O33: 0.37739142 | P33: 0.33687492 | Q33: 0.67574882 | R33: -0.3388739 | S33: 0.2851311 | T33: 0.18147378 | V33: 3.1116049 | W33: 5.3564624 | X33: -2.2448576 | Y33: 3.5387842 | Z33: -0.12071358 | AB33: 3.4484798 | AC33: 6.0322113 | AD33: -2.5837315 | AE33: 3.8239153 | AF33: -0.098180914 | AJ33: 3.5493086 | AM33: 5.8188533 | AO33: 3.8239153 | AP33: 1.994938 | AS33: 0.52170037 | AV33: =SUM(AB34:AB37) -> 22.47665
C34: Telecel | E34: 0.863345 | F34: 0.366024 | G34: -0.04368 | H34: 0.478155 | I34: 0.467238 | J34: 0.60318 | K34: 0.60318 | L34: 0.60318 | M34: 0.898776 | N34: 0.64072 | O34: 1.1294 | P34: 2.344776 | Q34: 2.4551489 | R34: -0.11037291 | S34: 1.0968626 | T34: 1.1377116 | V34: 6.609518 | W34: 19.282558 | X34: -12.67304 | Y34: 12.986885 | Z34: -0.49106211 | AB34: 8.954294 | AC34: 21.737707 | AD34: -12.783413 | AE34: 14.083748 | AF34: -0.36421086 | AH34: 65.151647 | AI34: 66.659952 | AJ34: 7.6792924 | AM34: 21.737707 | AO34: 14.083748 | AP34: 7.6539586 | AQ34: -0.64672941 | AR34: -0.45474085 | AS34: 0.54346035 | AT34: ns | AV34: ok | AW34: =+AE34-13.123 -> 0.96074791
C35: Orange | E35: 1.578325 | F35: 0 | G35: 0.318208 | H35: 0.721125 | I35: 0.719667 | J35: 0.780132 | K35: 0.82854 | L35: 0.82854 | M35: 0.942744 | N35: 2.066564 | O35: 2.8253 | P35: 1.87662 | Q35: 3.2551489 | R35: -1.3785289 | S35: 1.3441263 | T35: 0.39616342 | V35: 11.609145 | W35: 20.692558 | X35: -9.0834126 | Y35: 15.970445 | Z35: -0.2730857 | AB35: 13.485765 | AC35: 23.947707 | AD35: -10.461942 | AE35: 17.314572 | AF35: -0.22113204 | AH35: 36.264994 | AI35: 30.088248 | AJ35: 14.238463 | AM35: 23.947707 | AO35: 17.314572 | AP35: 6.633135 | AQ35: -0.40543521 | AR35: -0.17766009 | AS35: 0.38309553 | AT35: ns
C36: Azur | E36: 0 | F36: 0 | G36: 0 | H36: 0 | I36: 0 | J36: 0 | K36: 0 | L36: 0 | M36: 0 | N36: 0 | O36: 0 | P36: 0 | Q36: 0 | R36: 0 | S36: 0 | T36: ns | V36: 0 | W36: 0 | X36: 0 | Y36: 0 | Z36: ns | AB36: 0 | AC36: 0 | AD36: 0 | AE36: 0 | AF36: ns | AH36: 11.450571 | AI36: 8.8070196 | AJ36: 0 | AM36: 0 | AO36: 0 | AP36: 0 | AQ36: ns | AR36: ns | AS36: ns | AT36: ns
C37: Socatel (Fixe) | E37: 0.00966 | F37: 0.005376 | G37: 0.0015737143 | H37: 0.0042875 | I37: 0.004424 | J37: 0.00254 | K37: 0.00123 | L37: 0.00123 | M37: 0.00081 | N37: 0.00081 | O37: 0.00465 | P37: 0 | Q37: 0.01796 | R37: -0.01796 | S37: 0 | T37: ns | V37: 0.036591214 | W37: 0.158404 | X37: -0.12181279 | Y37: 0.19606085 | Z37: -0.81336807 | AB37: 0.036591214 | AC37: 0.176364 | AD37: -0.13977279 | AE37: 0.19606085 | AF37: -0.81336807 | AH37: 0.88759647 | AI37: 0.19234473 | AJ37: 0.051698574 | AM37: 0.176364 | AO37: 0.19606085 | AP37: -0.01969685 | AQ37: -0.70686436 | AR37: -0.73631363 | AS37: -0.10046294 | AT37: ns
C38: International | E38: 7.0451079 | F38: 6.817051 | G38: 7.1243738 | H38: 7.0095085 | I38: 6.97173 | J38: 7.0697205 | K38: 7.2216115 | L38: 8.3717553 | M38: 7.1856381 | N38: 11.994642 | O38: 8.6157532 | P38: 7.003652 | Q38: 16 | R38: -8.996348 | S38: 7.0598973 | T38: -0.0079668774 | V38: 85.426891 | W38: 132.1 | X38: -46.673109 | Y38: 88.762846 | Z38: -0.037582777 | AB38: 92.430543 | AC38: 148.1 | AD38: -55.669457 | AE38: 95.822743 | AF38: -0.035400777 | AH38: 511.72585 | AI38: 485.60827 | AJ38: 96.32899 | AM38: 148.1 | AO38: 95.822743 | AP38: 52.277257 | AQ38: -0.34956793 | AR38: 0.0052831639 | AS38: 0.5455621 | AT38: ns
B40: CA infrastructures | E40: 0 | F40: 0 | G40: 0 | H40: 0 | I40: 0 | J40: 0 | K40: 0 | L40: 0 | M40: 0 | N40: 0 | O40: 0 | P40: 0 | R40: 0 | S40: 0 | T40: ns | V40: 0 | W40: 0 | X40: 0 | Y40: 0 | Z40: ns | AB40: 0 | AC40: 0 | AD40: 0 | AE40: 0 | AF40: ns | AJ40: 0 | AO40: 0 | AP40: ns | AS40: ns
B41: Telecel | E41: 0 | F41: 0 | G41: 0 | H41: 0 | I41: 0 | J41: 0 | K41: 0 | L41: 0 | M41: 0 | N41: 0 | O41: 0 | P41: 0 | R41: 0 | S41: 0 | T41: ns | V41: 0 | W41: 0 | X41: 0 | Y41: 0 | Z41: ns | AB41: 0 | AC41: 0 | AD41: 0 | AE41: 0 | AF41: ns | AJ41: 0 | AO41: 0 | AP41: ns | AS41: ns
B42: Orange | E42: 0 | F42: 0 | G42: 0 | H42: 0 | I42: 0 | J42: 0 | K42: 0 | L42: 0 | M42: 0 | N42: 0 | O42: 0 | P42: 0 | R42: 0 | S42: 0 | T42: ns | V42: 0 | W42: 0 | X42: 0 | Y42: 0 | Z42: ns | AB42: 0 | AC42: 0 | AD42: 0 | AE42: 0 | AF42: ns | AJ42: 0 | AO42: 0 | AP42: ns | AS42: ns
C43: Clients hors opérateurs | AJ43: 0 | AP43: ns | AS43: ns
C44: Airtel | E44: 0 | F44: 0 | G44: 0 | H44: 0 | I44: 0 | J44: 0 | K44: 0 | L44: 0 | M44: 0 | N44: 0 | O44: 0 | P44: 0 | Q44: 9.1813419 | R44: -9.1813419 | S44: 0 | T44: ns | W44: 0 | X44: 0 | Z44: ns | AC44: 0 | AD44: 0 | AF44: ns | AH44: 61 | AI44: 61 | AJ44: 43.990301 | AP44: ns | AS44: ns
B46: Roaming | E46: 0.91187623 | F46: 0.910703 | G46: 1.1937656 | H46: 1.3291443 | I46: 1.3214783 | J46: 0.92147827 | K46: 2.378834 | L46: 2.378834 | M46: 1.31131 | N46: 1.348608 | O46: 1.500482 | P46: 0.6926229 | Q46: 4 | R46: -3.3073771 | S46: 0.92035002 | T46: -0.24743534 | V46: 15.506514 | W46: 27.104497 | X46: -11.597983 | Y46: 17.030829 | Z46: -0.089503277 | AB46: 16.199137 | AC46: 31.104497 | AD46: -14.90536 | AE46: 17.951179 | AF46: -0.097600393 | AH46: 133.60098 | AI46: 138.46305 | AJ46: 15.508083 | AM46: 31.104497 | AO46: 17.951179 | AP46: 13.153318 | AQ46: -0.50141991 | AR46: -0.13609668 | AS46: 0.73272726 | AT46: ns
B47: Co-localisation | E47: 2.38 | F47: 2.38 | G47: 2.38 | H47: 2.38 | I47: 2.38 | J47: 2.38 | K47: 2.38 | L47: 2.38 | M47: 2.38 | N47: 2.38 | O47: 2.38 | P47: 2.38 | Q47: 7 | R47: -4.62 | S47: 2.38 | T47: 0 | V47: 26.18 | W47: 52 | X47: -25.82 | Y47: 37.1 | Z47: -0.29433962 | AB47: 28.56 | AC47: 59 | AD47: -30.44 | AE47: 39.48 | AF47: -0.27659574 | AH47: 79.775 | AI47: 78.96 | AJ47: 28.56 | AM47: 59 | AO47: 39.48 | AP47: 19.52 | AQ47: -0.5159322 | AR47: -0.27659574 | AS47: 0.49442756 | AT47: ns
B49: CA equipements | E49: 6.1 | F49: 4.9 | G49: 4.9 | H49: 3.7718106 | I49: 8.8779833 | J49: 7.886132 | K49: 7.917225 | L49: 7.8 | M49: 7.4 | N49: 4.8 | O49: 5 | P49: 8.508442 | Q49: 13.179939 | R49: -4.6714974 | S49: 5.947819 | T49: 0.43051461 | V49: 69.353151 | W49: 97.314132 | X49: -27.960982 | Y49: 52.578192 | Z49: 0.31904785 | AB49: 77.861593 | AC49: 110.49407 | AD49: -32.632479 | AE49: 58.526011 | AF49: 0.33037587 | AH49: 99.126234 | AI49: 74.940828 | AJ49: 75.671811 | AM49: 110.49407 | AO49: 58.526011 | AP49: 51.968061 | AQ49: -0.31515049 | AR49: 0.29296033 | AS49: 0.88794811 | AT49: ns
C50: Kits | E50: 2.5 | F50: 1.9 | G50: 1.6 | H50: 2 | I50: 6.6832703 | J50: 5 | K50: 5 | L50: 4.8 | M50: 4.5 | N50: 2.1 | O50: 2 | P50: 3.089673 | Q50: 4.8799394 | R50: -1.7902664 | S50: 1.647819 | T50: 0.87500751 | V50: 38.08327 | W50: 39.814132 | X50: -1.7308622 | Y50: 20.223244 | Z50: 0.88314349 | AB50: 41.172943 | AC50: 44.694072 | AD50: -3.5211286 | AE50: 21.871063 | AF50: 0.8825305 | AH50: 26.898023 | AI50: 32.640617 | AJ50: 31 | AM50: 44.694072 | AO50: 21.871063 | AP50: 22.823009 | AQ50: -0.30639571 | AR50: 0.41739796 | AS50: 1.0435254 | AT50: ns
C51: Terminaux | E51: 3.6 | F51: 3 | G51: 3.3 | H51: 1.7718106 | I51: 2.194713 | J51: 2.886132 | K51: 2.917225 | L51: 3 | M51: 2.9 | N51: 2.7 | O51: 3 | P51: 5.418769 | Q51: 8.3 | R51: -2.881231 | S51: 4.3 | T51: 0.26017884 | V51: 31.269881 | W51: 57.5 | X51: -26.230119 | Y51: 32.354948 | Z51: -0.033536365 | AB51: 36.68865 | AC51: 65.8 | AD51: -29.11135 | AE51: 36.654948 | AF51: 0.00091942949 | AH51: 72.228211 | AI51: 42.300211 | AJ51: 44.671811 | AM51: 65.8 | AO51: 36.654948 | AP51: 29.145052 | AQ51: -0.3210971 | AR51: 0.21871161 | AS51: 0.79511917 | AT51: ns
C52: Autres | R52: 0 | T52: ns | V52: 0 | X52: 0 | Y52: 0 | Z52: ns | AB52: 0 | AD52: 0 | AE52: 0 | AF52: ns | AJ52: 0 | AM52: 0 | AO52: 0 | AP52: 0 | AQ52: ns | AR52: ns | AS52: ns | AT52: ns
C56: service voix | E56: =(+E20+E28) -> 78.522092 | F56: =(+F20+F28) -> 83.178909 | G56: =(+G20+G28) -> 87.666438 | H56: =(+H20+H28) -> 95.074424 | I56: =(+I20+I28) -> 103.36842 | J56: =(+J20+J28) -> 99.300223 | K56: =(+K20+K28) -> 100.53115 | L56: =(+L20+L28) -> 104.30627 | ... P56: =(+P20+P28) -> 117.3197
C57: internet | E57: =(+E21+E22+E23+E29) -> 209.58709 | F57: =(+F21+F22+F23+F29) -> 200.45758 | G57: =(+G21+G22+G23+G29) -> 212.15466 | H57: =(+H21+H22+H23+H29) -> 205.02027 | I57: =(+I21+I22+I23+I29) -> 218.95355 | J57: =(+J21+J22+J23+J29) -> 206.97387 | K57: =(+K21+K22+K23+K29) -> 229.46481 | L57: =(+L21+L22+L23+L29) -> 243.63111 | ... P57: =(+P21+P22+P23+P29) -> 231.24348
C58: sms | E58: =(+E24) -> 1.6175378 | F58: =(+F24) -> 1.9456992 | G58: =(+G24) -> 1.6 | H58: =(+H24) -> 2.1112768 | I58: =(+I24) -> 2.5707613 | J58: =(+J24) -> 2.6477227 | K58: =(+K24) -> 2.813495 | L58: =(+L24) -> 3.4279917 | ... P58: =(+P24) -> 3.5212798
C59: Roaming | E59: =+E46 -> 0.91187623 | F59: =+F46 -> 0.910703 | G59: =+G46 -> 1.1937656 | H59: =+H46 -> 1.3291443 | I59: =+I46 -> 1.3214783 | J59: =+J46 -> 0.92147827 | K59: =+K46 -> 2.378834 | L59: =+L46 -> 2.378834 | ... P59: =+P46 -> 0.6926229
C60: Entrant International | E60: =+E38 -> 7.0451079 | F60: =+F38 -> 6.817051 | G60: =+G38 -> 7.1243738 | H60: =+H38 -> 7.0095085 | I60: =+I38 -> 6.97173 | J60: =+J38 -> 7.0697205 | K60: =+K38 -> 7.2216115 | L60: =+L38 -> 8.3717553 | ... P60: =+P38 -> 7.003652
C61: autre services | E61: =(+E31-E38+E50+E47) -> 7.33133 | F61: =(+F31-F38+F50+F47) -> 4.6514 | G61: =(+G31-G38+G50+G47) -> 4.2561017 | H61: =(+H31-H38+H50+H47) -> 5.5835675 | I61: =(+I31-I38+I50+I47) -> 10.254599 | J61: =(+J31-J38+J50+J47) -> 8.765852 | K61: =(+K31-K38+K50+K47) -> 8.81295 | L61: =(+L31-L38+L50+L47) -> 8.61295 | ... P61: =(+P31-P38+P50+P47) -> 9.691069
C62: Terminaux | E62: =+E51 -> 3.6 | F62: =+F51 -> 3 | G62: =+G51 -> 3.3 | H62: =+H51 -> 1.7718106 | I62: =+I51 -> 2.194713 | J62: =+J51 -> 2.886132 | K62: =+K51 -> 2.917225 | L62: =+L51 -> 3 | ... P62: =+P51 -> 5.418769
E63: =SUM(E56:E62) -> 308.61504 | F63: =SUM(F56:F62) -> 300.96135 | G63: =SUM(G56:G62) -> 317.29534 | H63: =SUM(H56:H62) -> 317.9 | I63: =SUM(I56:I62) -> 345.63525 | J63: =SUM(J56:J62) -> 328.565 | K63: =SUM(K56:K62) -> 354.14007 | L63: =SUM(L56:L62) -> 373.72891 | ... P63: =SUM(P56:P62) -> 374.89057
E64: =+E63-E9 -> 0 | F64: =+F63-F9 -> 0 | G64: =+G63-G9 -> 0 | H64: =+H63-H9 -> 0 | I64: =+I63-I9 -> 0 | J64: =+J63-J9 -> 0 | K64: =+K63-K9 -> 0 | L64: =+L63-L9 -> 0 | ... P64: =+P63-P9 -> 0

Sheet Marge Mobile
AA1: 3804700093
A2: Moov RCA : Marge brute Mobile | AA2: =+(AA8-AA36)*10^6 -> 3.8046982e+09 | AB2: =+AA2-AA1 -> -1919.4058
O5: MENSUEL | U5: CUMUL (m-1) | AA5: CUMUL | AI5: ANNUEL
D6: Janvier | E6: Février | F6: Mars | G6: Avril | H6: Mai | I6: Juin | J6: Juillet | K6: Août | L6: Septembre | M6: Octobre | N6: Novembre | O6: 2023 | P6: 2023 Budget | Q6: Ecart / Budget | R6: 2022 Réel | S6: Evol % | U6: 2023 | V6: 2023 Budget | W6: Ecart / Budget | X6: 2021 Réel | Y6: Evol % | AA6: 2023 | AB6: 2023 Budget | AC6: Ecart / Budget | AD6: 2022 Réel | AE6: Evol % | AG6: 2017 Actu 1 | AH6: 2017 Actu 2 | AI6: 2023 Actu 1 | AJ6: 2023 Actu 2 | AK6: 2023 Actu3 | AL6: 2023 Budget | AM6: 2019 Actu3 | AN6: 2022 Réel | AO6: Ecart / Budget | AP6: Var Actu1/ Budget (%) | AQ6: Var Actu1/ 2018 (%) | AR6: B23/ 2022 (%) | AS6: Var Actu3/ 2019 (%) | AU6: 0
A8: Total Revenu | D8: 308.61504 | E8: 300.96135 | F8: 317.29534 | G8: 317.9 | H8: 345.63525 | I8: 328.565 | J8: 354.14007 | K8: 373.72891 | L8: 365.64251 | M8: 394.72369 | N8: 368.20351 | O8: 374.89057 | P8: 575.53449 | Q8: -200.64392 | R8: 315.53342 | S8: 0.18811686 | U8: 3775.4107 | V8: 4580.7294 | W8: -805.31869 | X8: 3545.3164 | Y8: 0.064900928 | AA8: 4150.3013 | AB8: 5156.2639 | AC8: -1005.9626 | AD8: 3860.8498 | AE8: 0.074970925 | AG8: 4718.995 | AH8: 4718.6895 | AI8: 5156.1148 | AL8: 5156.2639 | AN8: 3860.8498 | AO8: 1295.4141 | AP8: -2.8906658e-05 | AQ8: 0.33548703 | AR8: 0.33552564 | AS8: ns | AW8: 21664.693
B9: Trafic (mn) | D9: 0.159767 | E9: 0.146998 | F9: 0.12939735 | G9: 0.160369 | H9: 0.178535 | I9: 0.163107 | J9: 0.161155 | K9: 0.155166 | L9: 0.158546 | M9: 0.12961 | N9: 0.130629 | O9: 0.77397482 | P9: 0.23895511 | Q9: 0.53501971 | R9: 0.16800558 | S9: 3.60684 | U9: 1.6732794 | V9: 2.1155475 | W9: -0.44226813 | X9: 1.8724449 | Y9: -0.10636656 | AA9: 2.4472542 | AB9: 2.3545026 | AC9: 0.092751588 | AD9: 2.0404505 | AE9: 0.19936956 | AG9: 5.581635 | AH9: 5.2866842 | AI9: 2.3963971 | AL9: 2.3545026 | AN9: 2.0404505 | AO9: 0.31405213 | AP9: 0.017793346 | AQ9: 0.17444511 | AR9: 0.15391314 | AS9: ns | AX9: 0
B10: Coût unitaire | D10: 116.44621 | E10: 117.35203 | F10: 117.08519 | G10: 115.98286 | H10: 109.04309 | I10: 114.73593 | J10: 114.38764 | K10: 114.95884 | L10: 114.33425 | M10: 18.447736 | N10: 114.6175 | O10: 16.011566 | P10: 109.02544 | Q10: -93.01387 | R10: 137.37818 | S10: -0.88344899 | U10: 107.30429 | V10: 109.06426 | W10: -1.7599728 | X10: 107.74746 | Y10: -0.0041130625 | AA10: 78.431818 | AB10: 109.06032 | AC10: -30.6285 | AD10: 110.18718 | AE10: -0.28819469 | AG10: 87.40161 | AH10: 98.349518 | AI10: 116.90552 | AL10: 109.05665 | AN10: 110.18718 | AO10: -1.1305279 | AP10: 0.071970616 | AQ10: 0.060972125 | AR10: -0.010260067 | AS10: ns
B11: International | D11: 18.604261 | E11: 17.250514 | F11: 15.150514 | G11: 18.600055 | H11: 19.468008 | I11: 18.714233 | J11: 18.43414 | K11: 17.837704 | L11: 18.127237 | M11: 2.391011 | N11: 14.972369 | O11: 12.392549 | P11: 26.052185 | Q11: -13.659636 | R11: 23.0803 | S11: -0.46306813 | U11: 179.55005 | V11: 230.73062 | W11: -51.180572 | X11: 201.75118 | Y11: -0.11004213 | AA11: 191.9426 | AB11: 256.7828 | AC11: -64.840208 | AD11: 224.83148 | AE11: -0.14628237 | AG11: 487.84388 | AH11: 519.94284 | AI11: 280.18963 | AL11: 256.77416 | AN11: 224.83148 | AO11: 31.942687 | AP11: 0.091190906 | AQ11: 0.24622066 | AR11: 0.14207391 | AS11: ns | AV11: 0 | AW11: 428.92726
B12: dont transit | D12: 0 | E12: 0 | F12: 0 | G12: 0 | H12: 0 | I12: 0 | J12: 0 | K12: 0 | L12: 0 | M12: 0 | N12: 0 | O12: 0 | R12: 0 | U12: 0 | X12: 0 | AA12: 0 | AD12: 0 | AN12: 0 | AO12: 0 | AP12: ns | AQ12: ns
B13: Trafic (mn) | D13: 0.113837 | E13: 0.133961 | F13: 0.1797951 | G13: 0.17530625 | H13: 0.1772617 | I13: 0.315123 | J13: 0.337902 | K13: 0.392785 | L13: 0.414337 | M13: 1.581109 | N13: 0.611742 | O13: 0.769969 | P13: 0.23429288 | Q13: 0.53567612 | R13: 0.092016744 | S13: 7.3677053 | U13: 4.433159 | V13: 1.7906706 | W13: 2.6424884 | X13: 1.5950972 | Y13: 1.7792406 | AA13: 5.203128 | AB13: 2.0249635 | AC13: 3.1781646 | AD13: 1.687114 | AE13: 2.0840406 | AG13: 3.6030375 | AH13: 5.0739522 | AI13: 2.0968628 | AL13: 2.0249635 | AN13: 1.687114 | AO13: 0.33784951 | AP13: 0.03550649 | AQ13: 0.24286969 | AR13: 0.20025292 | AS13: ns | AV13: 10 | AW13: 45.261808 | AX13: -2.0249635
B14: Coût unitaire | D14: 10 | E14: 10 | F14: 10 | G14: 10 | H14: 10 | I14: 10 | J14: 10 | K14: 10 | L14: 10 | M14: 10 | N14: 10 | O14: 10 | P14: 10 | Q14: 0 | R14: 35 | S14: -0.71428571 | U14: 10 | V14: 10 | W14: 0 | X14: 35 | Y14: -0.71428571 | AA14: 10 | AB14: 10 | AC14: 0 | AD14: 35 | AE14: -0.71428571 | AG14: 35 | AH14: 35 | AI14: 10 | AL14: 10 | AN14: 35 | AO14: -25 | AP14: 0 | AQ14: -0.71428571 | AR14: -0.71428571 | AS14: ns | AW14: 37.999994 | BB14: =+AA15+AA18+AA24 -> 134.8818
B15: Telecel | D15: 1.13837 | E15: 1.33961 | F15: 1.797951 | G15: 1.7530625 | H15: 1.772617 | I15: 3.15123 | J15: 3.37902 | K15: 3.92785 | L15: 4.14337 | M15: 15.81109 | N15: 6.11742 | O15: 7.69969 | P15: 2.3429288 | Q15: 5.3567612 | R15: 3.2205861 | S15: 1.3907729 | U15: 44.33159 | V15: 17.906706 | W15: 26.424884 | X15: 55.828403 | Y15: -0.20593125 | AA15: 52.03128 | AB15: 20.249635 | AC15: 31.781646 | AD15: 59.048989 | AE15: -0.11884554 | AG15: 127.40012 | AH15: 179.4054 | AI15: 20.968628 | AL15: 20.249635 | AN15: 59.048989 | AO15: -38.799354 | AP15: 0.03550649 | AQ15: -0.64489437 | AR15: -0.65707059 | AS15: ns | AV15: -20.249635 | AW15: 1719.9484 | BA15: ok | BB15: =+AD15-53.297746 -> 5.7512432
B16: Trafic (mn) | D16: 0.135189 | E16: 0.184954 | F16: 0.25684533 | G16: 0.27566 | H16: 0.2662527 | I16: 0.311753 | J16: 0.366011 | K16: 0.406753 | L16: 0.43829 | M16: 1.913951 | N16: 2.188492 | O16: 1.539982 | P16: 0.28635797 | Q16: 1.253624 | R16: 0.21222924 | S16: 6.2562197 | U16: 6.744151 | V16: 2.1885974 | W16: 4.5555536 | X16: 1.2469944 | Y16: 4.4083249 | AA16: 8.284133 | AB16: 2.4749554 | AC16: 5.8091777 | AD16: 1.4592237 | AE16: 4.6770824 | AG16: 1.4556229 | AH16: 1.9946612 | AI16: 2.6786037 | AL16: 2.4749554 | AN16: 1.4592237 | AO16: 1.0157317 | AP16: 0.082283639 | AQ16: 0.83563614 | AR16: 0.69607677 | AS16: ns | AV16: 6 | AW16: 6.1038663
B17: Coût unitaire | D17: 10 | E17: 10 | F17: 10 | G17: 10 | H17: 10 | I17: 10 | J17: 10 | K17: 10 | L17: 10 | M17: 10 | N17: 10 | O17: 10 | P17: 10 | Q17: 0 | R17: 35 | S17: -0.71428571 | U17: 10 | V17: 10 | W17: 0 | X17: 35 | Y17: -0.71428571 | AA17: 10 | AB17: 10 | AC17: 0 | AD17: 35 | AE17: -0.71428571 | AG17: 35 | AH17: 35 | AI17: 10 | AL17: 10 | AN17: 35 | AO17: -25 | AP17: 0 | AQ17: -0.71428571 | AR17: -0.71428571 | AS17: ns
B18: Orange | D18: 1.35189 | E18: 1.84954 | F18: 2.5684533 | G18: 2.7566 | H18: 2.662527 | I18: 3.11753 | J18: 3.66011 | K18: 4.06753 | L18: 4.3829 | M18: 19.13951 | N18: 21.88492 | O18: 15.39982 | P18: 2.8635797 | Q18: 12.53624 | R18: 7.4280234 | S18: 1.0732056 | U18: 67.44151 | V18: 21.885974 | W18: 45.555536 | X18: 43.644805 | Y18: 0.54523569 | AA18: 82.84133 | AB18: 24.749554 | AC18: 58.091777 | AD18: 51.072828 | AE18: 0.62202355 | AG18: 50.466824 | AH18: 69.281676 | AI18: 26.786037 | AL18: 24.749554 | AN18: 51.072828 | AO18: -26.323275 | AP18: 0.082283639 | AQ18: -0.47553253 | AR18: -0.51540664 | AS18: ns | AW18: 231.94626
B19: Trafic (mn) | D19: 0 | E19: 0 | F19: 0 | G19: 0 | H19: 0 | I19: 0 | J19: 0 | K19: 0 | L19: 0 | M19: 0 | N19: 0 | O19: 0 | P19: 0 | Q19: 0 | R19: 0 | S19: ns | U19: 0 | V19: 0 | W19: 0 | X19: 0 | Y19: ns | AA19: 0 | AB19: 0 | AC19: 0 | AD19: 0 | AE19: ns | AG19: 0.37670687 | AH19: 0.29543473 | AI19: 0 | AL19: 0 | AN19: 0 | AO19: 0 | AP19: ns | AQ19: ns | AR19: ns | AS19: ns | AV19: 1.75 | AW19: 2.7549218
B20: Coût unitaire | D20: 10 | E20: 10 | F20: 10 | G20: 10 | H20: 10 | I20: 10 | J20: 10 | K20: 10 | L20: 10 | M20: 10 | N20: 10 | O20: 10 | P20: 10 | Q20: 0 | R20: 35 | S20: -0.71428571 | U20: 10 | X20: 35 | Y20: -0.71428571 | AA20: 10 | AD20: 35 | AE20: -0.71428571 | AG20: 35 | AH20: 35 | AI20: 8.6666667 | AL20: 10 | AN20: 35 | AO20: -25 | AP20: -0.13333333 | AQ20: -0.75238095 | AR20: -0.71428571 | AS20: ns | AW20: 38
B21: AZUR | D21: 0 | E21: 0 | F21: 0 | G21: 0 | H21: 0 | I21: 0 | J21: 0 | K21: 0 | L21: 0 | M21: 0 | N21: 0 | O21: 0 | P21: 0 | Q21: 0 | R21: 0 | S21: ns | U21: 0 | V21: 0 | W21: 0 | X21: 0 | Y21: ns | AA21: 0 | AB21: 0 | AC21: 0 | AD21: 0 | AE21: ns | AG21: 13.056222 | AH21: 10.298282 | AI21: 0 | AL21: 0 | AN21: 0 | AO21: 0 | AP21: ns | AQ21: ns | AR21: ns | AS21: ns | AW21: 104.68703
B22: Trafic (mn) | D22: 9.24e-05 | E22: 2.16e-05 | F22: 4.0742857e-05 | G22: 4.0742857e-05 | H22: 5.11e-05 | I22: 0.0001284 | J22: 0.0002448 | K22: 1.68e-05 | L22: 0.0100732 | M22: 0.0100732 | N22: 0.0001356 | O22: -0.02 | P22: 0.0011275474 | Q22: -0.021127547 | R22: 0.0001181875 | S22: ns | U22: 0.020918586 | V22: 0.012218974 | W22: 0.0086996113 | X22: 0.00053491368 | Y22: 38.10647 | AA22: 0.00091858571 | AB22: 0.013346522 | AC22: -0.012427936 | AD22: 0.00065310118 | AE22: 0.40649831 | AG22: 0.0092640749 | AH22: 0.0046556153 | AI22: 0.0029151248 | AL22: 0.013346522 | AN22: 0.00065310118 | AO22: 0.012693421 | AP22: -0.78158169 | AQ22: 3.4635117 | AR22: ns | AS22: ns | AW22: 19.509177
B23: Coût unitaire | D23: 10 | E23: 10 | F23: 10 | G23: 10 | H23: 10 | I23: 10 | J23: 10 | K23: 10 | L23: 10 | M23: 10 | N23: 10 | O23: 10 | P23: 20 | Q23: -10 | R23: 20 | S23: -0.5 | U23: 10.044171 | V23: 10 | W23: 0.044171246 | X23: 20 | Y23: -0.49779144 | AA23: 10 | AB23: 10 | AC23: -2.8421709e-14 | AD23: 20 | AE23: -0.5 | AG23: 20 | AH23: 20 | AI23: 16.666667 | AL23: 10 | AN23: 20 | AO23: -10 | AP23: 0.66666667 | AQ23: -0.16666667 | AR23: ns | AS23: ns | AW23: 43.969591
B24: Socatel (fixe) | D24: 0.001848 | E24: 0.000216 | F24: 0.00040742857 | G24: 0.00040742857 | H24: 0.000511 | I24: 0.001284 | J24: 0.002448 | K24: 0.000168 | L24: 0.100732 | M24: 0.100732 | N24: 0.001356 | O24: -0.2 | P24: 0.022550949 | Q24: -0.22255095 | R24: 0.00236375 | S24: ns | U24: 0.21010986 | V24: 0.24437949 | W24: -0.034269632 | X24: 0.010698274 | Y24: 18.639604 | AA24: 0.0091858571 | AB24: 0.26693044 | AC24: -0.25774458 | AD24: 0.013062024 | AE24: -0.29675084 | AG24: 0.16348544 | AH24: 0.071236248 | AI24: 0.057271638 | AL24: 0.26693044 | AN24: 0.013062024 | AO24: 0.25386841 | AP24: -0.78544358 | AQ24: 3.3845915 | AR24: ns | AS24: ns | AW24: 857.81054
B25: Interconnexion SMS | D25: 0.258148 | E25: 0.274296 | F25: 0.266244 | G25: 0.289432 | H25: 0.27783828 | I25: 0.317856 | J25: 0.31086 | K25: 0.328196 | L25: 0.38824 | M25: -0.40507648 | N25: 0.19241749 | O25: 0.24153567 | P25: 0.74 | Q25: -0.49846433 | R25: 0.19847678 | S25: 0.21694671 | U25: 2.4984513 | V25: 5.2665812 | W25: -2.7681299 | X25: 3.4966107 | Y25: -0.28546484 | AA25: 2.739987 | AB25: 6.0065812 | AC25: -3.2665942 | AD25: 3.6950875 | AE25: -0.25847846 | AG25: 4.3106117 | AH25: 8.5871263 | AI25: 5.64812 | AL25: 6.0065812 | AN25: 3.6950875 | AO25: 2.3114937 | AP25: -0.059678071 | AQ25: 0.52854839 | AR25: 0.62555859 | AS25: ns | AW25: 69.375331
B26: Interconnexion RO | D26: 1.7547587 | E26: 1.770601 | F26: 1.9652019 | G26: 1.718709 | H26: 1.8629985 | I26: 1.914368 | J26: 2.571572 | K26: 2.2363829 | L26: 2.75983 | M26: 2.218714 | N26: 1.972208 | O26: 0.82671971 | P26: 2.4 | Q26: -1.5732803 | R26: 2.7962559 | S26: -0.70434762 | U26: 22.745344 | V26: 23 | W26: -0.2546559 | X26: 24.25667 | Y26: -0.062305562 | AA26: 23.572064 | AB26: 25.4 | AC26: -1.8279362 | AD26: 27.052925 | AE26: -0.12866858 | AG26: 60.34698 | AH26: 70.699178 | AI26: 25.209271 | AL26: 25.4 | AN26: 27.052925 | AO26: -1.6529254 | AP26: -0.0075090289 | AQ26: -0.068149921 | AR26: -0.061099692 | AS26: ns | AW26: 334.99712
B28: Coûts des terminaux | D28: 3.432 | E28: 2.91 | F28: 3.171 | G28: 1.8414753 | H28: 2.2094003 | I28: 3.6109348 | J28: 3.6379857 | K28: 3.71 | L28: 3.623 | M28: 2.649 | N28: 2.91 | O28: 5.014329 | P28: 7.631 | Q28: -2.616671 | R28: 4.141 | S28: 0.2108981 | U28: 33.704796 | V28: 54.535 | W28: -20.830204 | X28: 32.848805 | Y28: 0.026058525 | AA28: 38.719125 | AB28: 62.166 | AC28: -23.446875 | AD28: 36.989805 | AE28: 0.046751272 | AG28: 68.882196 | AH28: 44.350585 | AI28: 43.344475 | AL28: 62.166 | AN28: 36.989805 | AO28: 25.176195 | AP28: -0.30276236 | AQ28: 0.17179519 | AR28: 0.68062525 | AS28: ns | AW28: 793.75773
B29: Dont coût des cartes de recharge vendues | D29: 0.3 | E29: 0.3 | F29: 0.3 | G29: 0.3 | H29: 0.3 | I29: 0.3 | J29: 0.3 | K29: 0.3 | L29: 0.3 | M29: 0.3 | N29: 0.3 | O29: 0.3 | P29: 0.21 | Q29: 0.09 | R29: 0.4 | S29: -0.25 | U29: 3.3 | V29: 2.31 | W29: 0.99 | X29: 4.7 | Y29: -0.29787234 | AA29: 3.6 | AB29: 2.52 | AC29: 1.08 | AD29: 5.1 | AE29: -0.29411765 | AG29: 5.6850457 | AH29: 4.3353046 | AI29: 2.88 | AL29: 2.52 | AN29: 5.1 | AO29: -2.58 | AP29: 0.14285714 | AQ29: -0.43529412 | AR29: -0.50588235 | AS29: ns
B30: Dont coût des SIM | P30: 0 | S30: ns | V30: 0 | W30: 0 | Y30: ns | AB30: 0 | AC30: 0 | AE30: ns | AG30: 50.13194 | AH30: 50.13194 | AI30: 0 | AL30: 0 | AO30: 0 | AP30: ns | AQ30: ns | AR30: ns | AS30: ns
B31: Dont coût des Terminaux | D31: 3.132 | E31: 2.61 | F31: 2.871 | G31: 1.5414753 | H31: 1.9094003 | I31: 3.3109348 | J31: 3.3379857 | K31: 3.41 | L31: 3.323 | M31: 2.349 | N31: 2.61 | O31: 4.714329 | P31: 7.221 | Q31: -2.506671 | R31: 3.741 | S31: 0.26017884 | U31: 30.404796 | V31: 50.025 | W31: -19.620204 | X31: 28.148805 | Y31: 0.080145193 | AA31: 35.119125 | AB31: 57.246 | AC31: -22.126875 | AD31: 31.889805 | AE31: 0.10126498 | AG31: 56.06528 | AH31: 32.86528 | AI31: 38.864475 | AL31: 57.246 | AN31: 31.889805 | AO31: 25.356195 | AP31: -0.3210971 | AQ31: 0.21871161 | AR31: 0.79511917 | AS31: ns
B32: Dont provisions sur stocks | D32: 0 | E32: 0 | F32: 0 | G32: 0 | H32: 0 | I32: 0 | J32: 0 | K32: 0 | L32: 0 | M32: 0 | N32: 0 | O32: 0 | Q32: 0 | R32: 0 | S32: ns | U32: 0 | V32: 0 | W32: 0 | X32: 0 | Y32: ns | AA32: 0 | AB32: 0 | AC32: 0 | AD32: 0 | AE32: ns | AG32: 3.4 | AH32: 6.8 | AI32: 0 | AL32: 0 | AN32: 0 | AO32: 0 | AP32: ns | AQ32: ns | AR32: ns | AS32: ns
B33: Autres Coût de Ventes | D33: 0 | E33: 0 | F33: 0 | G33: 0 | H33: 0 | I33: 0 | J33: 0 | K33: 0 | L33: 0 | M33: 0 | N33: 0 | O33: 0 | P33: 0 | Q33: 0 | R33: 0 | S33: ns | U33: 0 | V33: 0 | W33: 0 | X33: 0 | Y33: ns | AA33: 0 | AB33: 0 | AC33: 0 | AD33: 0 | AE33: ns | AG33: 24 | AH33: 24 | AI33: 0 | AL33: 0 | AN33: 0 | AO33: 0 | AP33: ns | AQ33: ns | AR33: ns | AS33: ns
B34: Reversement SVA | D34: 0 | E34: 0 | F34: 0 | G34: 0 | H34: 0 | I34: 0 | J34: 0 | K34: 0 | L34: 0 | M34: 0 | N34: 0 | O34: 0 | P34: 0.2 | Q34: -0.2 | R34: 0 | S34: ns | U34: 0 | V34: 2.2 | W34: -2.2 | X34: 0 | Y34: ns | AA34: 0 | AB34: 2.4 | AC34: -2.4 | AD34: 0 | AE34: ns | AG34: 3.7318707 | AH34: 0.35 | AI34: 1.6 | AL34: 2.4 | AN34: 0 | AO34: 2.4 | AP34: -0.33333333 | AQ34: ns | AR34: ns | AS34: ns
B35: Commissions | D35: 29.753671 | E35: 29.528862 | F35: 30.936637 | G35: 31.529043 | H35: 34.745264 | I35: 33.431005 | J35: 36.230827 | K35: 38.478808 | L35: 38.044113 | M35: 40.320759 | N35: 38.460655 | O35: 40.343434 | P35: 54.697859 | Q35: -14.354425 | R35: 30.513567 | S35: 0.32214744 | U35: 381.45964 | V35: 436.79559 | W35: -55.335944 | X35: 336.14599 | Y35: 0.13480348 | AA35: 421.80308 | AB35: 491.49345 | AC35: -69.690369 | AD35: 366.65956 | AE35: 0.15039433 | AG35: 472.69519 | AH35: 412.00081 | AI35: 520.74186 | AL35: 491.49345 | AN35: 366.65956 | AO35: 124.83389 | AP35: 0.059509264 | AQ35: 0.4202326 | AR35: 0.34046265 | AS35: ns | AW35: 1624.5392
B36: Dont commissions up-front | D36: 24.553671 | E36: 24.128862 | F36: 25.536637 | G36: 26.029043 | H36: 28.445264 | I36: 27.431005 | J36: 29.830827 | K36: 31.478808 | L36: 31.044113 | M36: 33.320759 | N36: 31.460655 | O36: 32.343434 | P36: 44.834311 | Q36: -12.490876 | R36: 25.313567 | S36: 0.27771145 | U36: 313.25964 | V36: 358.02917 | W36: -44.769527 | X36: 278.74599 | Y36: 0.12381756 | AA36: 345.60308 | AB36: 402.86348 | AC36: -57.260403 | AD36: 304.05956 | AE36: 0.13662954 | AG36: 441.33013 | AH36: 379.76781 | AI36: 432.07252 | AL36: 402.86348 | AN36: 304.05956 | AO36: 98.80392 | AP36: 0.072503564 | AQ36: 0.42101277 | AR36: 0.32494923 | AS36: ns
B37: Dont avoirs de performance | D37: 5.2 | E37: 5.4 | F37: 5.4 | G37: 5.5 | H37: 6.3 | I37: 6 | J37: 6.4 | K37: 7 | L37: 7 | M37: 7 | N37: 7 | O37: 8 | P37: 9.8635484 | Q37: -1.8635484 | R37: 5.2 | S37: 0.53846154 | U37: 68.2 | V37: 78.766418 | W37: -10.566418 | X37: 57.4 | Y37: 0.18815331 | AA37: 76.2 | AB37: 88.629966 | AC37: -12.429966 | AD37: 62.6 | AE37: 0.2172524 | AG37: 31.365055 | AH37: 32.233003 | AI37: 88.669341 | AL37: 88.629966 | AN37: 62.6 | AO37: 26.029966 | AP37: 0.00044426227 | AQ37: 0.41644314 | AR37: 0.41581415 | AS37: ns
A39: Coûts des ventes | D39: 56.293099 | E39: 54.923423 | F39: 55.856001 | G39: 58.488376 | H39: 62.998653 | I39: 64.257158 | J39: 68.224515 | K39: 70.58647 | L39: 71.46869 | M39: 82.125007 | N39: 86.50999 | O39: 81.918077 | P39: 96.750103 | Q39: -14.832026 | R39: 71.378209 | S39: 0.14766226 | U39: 731.73138 | V39: 790.36485 | W39: -58.633464 | X39: 697.97246 | Y39: 0.048367122 | AA39: 813.64946 | AB39: 887.11495 | AC39: -73.46549 | AD39: 769.35067 | AE39: 0.057579449 | AG39: 1285.1415 | AH39: 1314.6028 | AI39: 922.9453 | AL39: 887.11495 | AN39: 769.35067 | AO39: 117.76428 | AP39: 0.040389743 | AQ39: 0.19964189 | AR39: 0.1530697 | AS39: ns | AW39: 6165.9889
A41: Marge Brute | D41: 252.32194 | E41: 246.03792 | F41: 261.43934 | G41: 259.41162 | H41: 282.63659 | I41: 264.30784 | J41: 285.91556 | K41: 303.14244 | L41: 294.17382 | M41: 312.59869 | N41: 281.69352 | O41: 292.97249 | P41: 478.78439 | Q41: -185.8119 | R41: 244.15521 | S41: 0.19994367 | U41: 3043.6793 | V41: 3790.3645 | W41: -746.68523 | X41: 2847.3439 | Y41: 0.068953877 | AA41: 3336.6518 | AB41: 4269.1489 | AC41: -932.49712 | AD41: 3091.4991 | AE41: 0.079298969 | AG41: 3433.8535 | AH41: 3404.0867 | AI41: 4233.1695 | AL41: 4269.1489 | AN41: 3091.4991 | AO41: 1177.6498 | AP41: -0.0084277678 | AQ41: 0.36929347 | AR41: 0.38093164 | AS41: ns | AW41: 15498.704
A43: Marge Brute hors transit | D43: 249.94194 | E43: 243.65792 | F43: 259.05934 | G43: 257.03162 | I43: 261.92784 | J43: 283.53556 | K43: 300.76244 | L43: 291.79382 | M43: 310.21869 | N43: 279.31352 | O43: 290.59249 | P43: 0.83285244 | Q43: 289.75964 | R43: 241.77521 | S43: 0.20191189 | U43: 3017.4993 | V43: 0.76172883 | W43: 3016.7376 | X43: 2810.2439 | Y43: 0.07374997 | AA43: 3308.0918 | AB43: 0.76172883 | AC43: 3307.3301 | AD43: 3052.0191 | AE43: 0.083902715 | AI43: 0.82099986 | AL43: 0.82795393 | AN43: 3052.0191 | AO43: ns | AR43: ns | AW43: 15498.704
B45: Taux de marge | D45: 0.81759444 | E45: 0.81750672 | F45: 0.82396212 | G45: 0.81601643 | H45: 0.81773082 | I45: 0.80443091 | J45: 0.80735161 | K45: 0.81112922 | L45: 0.80453944 | M45: 0.79194305 | N45: 0.76504844 | O45: 0.78148803 | P45: 0.83189521 | Q45: -5.0407184 | R45: 0.77378558 | S45: 0.77024524 | U45: 0.80618496 | V45: 0.76172883 | W45: 4.4456128 | X45: 0.8031283 | Y45: 0.30566585 | AA45: 0.80395412 | AB45: 0.76172883 | AC45: 4.2225291 | AD45: 0.80073022 | AE45: 0.3223897 | AG45: 0.72766628 | AH45: 0.72140511 | AI45: 0.82099986 | AL45: 0.82795393 | AN45: 0.80073022 | AO45: 2.7223704 | AP45: -0.69540711 | AQ45: 2.0269633 | AR45: 2.7223704
AN47: =+AA41-AN41 -> 245.15269
M48: 28.883492 | O48: 49.053147 | R48: 0.094572049
M52: 0.15 | O52: 0.15
M55: 2 | O55: 2
O62: 0.09890324 | P62: 0.093477591 | Q62: 0.081850859 | R62: 0.094572049 | AD62: 0.092241085

Sheet Mobile Money
D2: Mensuel | J2: Cumulé
D3: Réel <Mois> | E3: Réel <Mois> | F3: Budget | G3: Ecart vs. | H3: % Evol/ | J3: Réel <Mois> | K3: Réel <Mois> | L3: Budget | M3: Ecart vs. | N3: % Evol/
B4: En monnaie locale | D4: 2019 | E4: 2018 | F4: 2019 | G4: Budget | H4: 2019 | J4: 2019 | K4: 2018 | L4: 2019 | M4: Budget | N4: 2019
A6: Parc clients Total | G6: =D6-F6 -> 0 | H6: =IFERROR(D6/E6-1,"-") -> - | M6: =J6-L6 -> 0 | N6: =IFERROR(J6/K6-1,"-") -> -
A8: Parc clients actif (90 jours) | G8: =D8-F8 -> 0 | H8: =IFERROR(D8/E8-1,"-") -> - | M8: =J8-L8 -> 0 | N8: =IFERROR(J8/K8-1,"-") -> -
A10: Nombre de points de ventes | G10: =D10-F10 -> 0 | H10: =IFERROR(D10/E10-1,"-") -> - | M10: =J10-L10 -> 0 | N10: =IFERROR(J10/K10-1,"-") -> -
A12: Total Montant des transactions | D12: =SUM(D13:D21) -> 0 | E12: =SUM(E13:E21) -> 0 | F12: =SUM(F13:F21) -> 0 | G12: =D12-F12 -> 0 | H12: =IFERROR(D12/E12-1,"-") -> - | J12: =SUM(J13:J21) -> 0 | K12: =SUM(K13:K21) -> 0 | L12: =SUM(L13:L21) -> 0 | M12: =J12-L12 -> 0 | N12: =IFERROR(J12/K12-1,"-") -> -
B13: Dépôt d’argent | G13: =D13-F13 -> 0 | H13: =IFERROR(D13/E13-1,"-") -> - | M13: =J13-L13 -> 0 | N13: =IFERROR(J13/K13-1,"-") -> -
B14: Retrait d’argent | G14: =D14-F14 -> 0 | H14: =IFERROR(D14/E14-1,"-") -> - | M14: =J14-L14 -> 0 | N14: =IFERROR(J14/K14-1,"-") -> -
B15: Transfert d’argent national | G15: =D15-F15 -> 0 | H15: =IFERROR(D15/E15-1,"-") -> - | M15: =J15-L15 -> 0 | N15: =IFERROR(J15/K15-1,"-") -> -
B16: Transfert d’argent international | G16: =D16-F16 -> 0 | H16: =IFERROR(D16/E16-1,"-") -> - | M16: =J16-L16 -> 0 | N16: =IFERROR(J16/K16-1,"-") -> -
B17: Recharge Mobile | G17: =D17-F17 -> 0 | H17: =IFERROR(D17/E17-1,"-") -> - | M17: =J17-L17 -> 0 | N17: =IFERROR(J17/K17-1,"-") -> -
B18: Achat de biens et services | G18: =D18-F18 -> 0 | H18: =IFERROR(D18/E18-1,"-") -> - | M18: =J18-L18 -> 0 | N18: =IFERROR(J18/K18-1,"-") -> -
B19: Paiement de factures | G19: =D19-F19 -> 0 | H19: =IFERROR(D19/E19-1,"-") -> - | M19: =J19-L19 -> 0 | N19: =IFERROR(J19/K19-1,"-") -> -
B20: Paiement de salaires | G20: =D20-F20 -> 0 | H20: =IFERROR(D20/E20-1,"-") -> - | M20: =J20-L20 -> 0 | N20: =IFERROR(J20/K20-1,"-") -> -
B21: Autres (à préciser) | G21: =D21-F21 -> 0 | H21: =IFERROR(D21/E21-1,"-") -> - | M21: =J21-L21 -> 0 | N21: =IFERROR(J21/K21-1,"-") -> -
A23: Chiffre d'affaires | D23: =SUM(D24:D32) -> 0 | E23: =SUM(E24:E32) -> 0 | F23: =SUM(F24:F32) -> 0 | G23: =D23-F23 -> 0 | H23: =IFERROR(D23/E23-1,"-") -> - | J23: =SUM(J24:J32) -> 0 | K23: =SUM(K24:K32) -> 0 | L23: =SUM(L24:L32) -> 0 | M23: =J23-L23 -> 0 | N23: =IFERROR(J23/K23-1,"-") -> -
B24: Dépôt d’argent | G24: =D24-F24 -> 0 | H24: =IFERROR(D24/E24-1,"-") -> - | M24: =J24-L24 -> 0 | N24: =IFERROR(J24/K24-1,"-") -> -
B25: Retrait d’argent | G25: =D25-F25 -> 0 | H25: =IFERROR(D25/E25-1,"-") -> - | M25: =J25-L25 -> 0 | N25: =IFERROR(J25/K25-1,"-") -> -
B26: Transfert d’argent national | G26: =D26-F26 -> 0 | H26: =IFERROR(D26/E26-1,"-") -> - | M26: =J26-L26 -> 0 | N26: =IFERROR(J26/K26-1,"-") -> -
B27: Transfert d’argent international | G27: =D27-F27 -> 0 | H27: =IFERROR(D27/E27-1,"-") -> - | M27: =J27-L27 -> 0 | N27: =IFERROR(J27/K27-1,"-") -> -
B28: Recharge Mobile | G28: =D28-F28 -> 0 | H28: =IFERROR(D28/E28-1,"-") -> - | M28: =J28-L28 -> 0 | N28: =IFERROR(J28/K28-1,"-") -> -
B29: Achat de biens et services | G29: =D29-F29 -> 0 | H29: =IFERROR(D29/E29-1,"-") -> - | M29: =J29-L29 -> 0 | N29: =IFERROR(J29/K29-1,"-") -> -
B30: Paiement de factures | G30: =D30-F30 -> 0 | H30: =IFERROR(D30/E30-1,"-") -> - | M30: =J30-L30 -> 0 | N30: =IFERROR(J30/K30-1,"-") -> -
B31: Paiement de salaires | G31: =D31-F31 -> 0 | H31: =IFERROR(D31/E31-1,"-") -> - | M31: =J31-L31 -> 0 | N31: =IFERROR(J31/K31-1,"-") -> -
B32: Autres (à préciser) | G32: =D32-F32 -> 0 | H32: =IFERROR(D32/E32-1,"-") -> - | M32: =J32-L32 -> 0 | N32: =IFERROR(J32/K32-1,"-") -> -
A34: Total Commissions | D34: =D35+D45 -> 0 | E34: =E35+E45 -> 0 | F34: =F35+F45 -> 0 | G34: =D34-F34 -> 0 | H34: =IFERROR(D34/E34-1,"-") -> - | J34: =J35+J45 -> 0 | K34: =K35+K45 -> 0 | L34: =L35+L45 -> 0 | M34: =J34-L34 -> 0 | N34: =IFERROR(J34/K34-1,"-") -> -
B35: Dont commissions Revendeurs | D35: =SUM(D36:D44) -> 0 | E35: =SUM(E36:E44) -> 0 | F35: =SUM(F36:F44) -> 0 | G35: =D35-F35 -> 0 | H35: =IFERROR(D35/E35-1,"-") -> - | J35: =SUM(J36:J44) -> 0 | K35: =SUM(K36:K44) -> 0 | L35: =SUM(L36:L44) -> 0 | M35: =J35-L35 -> 0 | N35: =IFERROR(J35/K35-1,"-") -> -
B36: Dépôt d’argent | G36: =D36-F36 -> 0 | H36: =IFERROR(D36/E36-1,"-") -> - | M36: =J36-L36 -> 0 | N36: =IFERROR(J36/K36-1,"-") -> -
B37: Retrait d’argent | G37: =D37-F37 -> 0 | H37: =IFERROR(D37/E37-1,"-") -> - | M37: =J37-L37 -> 0 | N37: =IFERROR(J37/K37-1,"-") -> -
B38: Transfert d’argent national | G38: =D38-F38 -> 0 | H38: =IFERROR(D38/E38-1,"-") -> - | M38: =J38-L38 -> 0 | N38: =IFERROR(J38/K38-1,"-") -> -
B39: Transfert d’argent international | G39: =D39-F39 -> 0 | H39: =IFERROR(D39/E39-1,"-") -> - | M39: =J39-L39 -> 0 | N39: =IFERROR(J39/K39-1,"-") -> -
B40: Recharge Mobile | G40: =D40-F40 -> 0 | H40: =IFERROR(D40/E40-1,"-") -> - | M40: =J40-L40 -> 0 | N40: =IFERROR(J40/K40-1,"-") -> -
B41: Achat de biens et services | G41: =D41-F41 -> 0 | H41: =IFERROR(D41/E41-1,"-") -> - | M41: =J41-L41 -> 0 | N41: =IFERROR(J41/K41-1,"-") -> -
B42: Paiement de factures | G42: =D42-F42 -> 0 | H42: =IFERROR(D42/E42-1,"-") -> - | M42: =J42-L42 -> 0 | N42: =IFERROR(J42/K42-1,"-") -> -
B43: Paiement de salaires | G43: =D43-F43 -> 0 | H43: =IFERROR(D43/E43-1,"-") -> - | M43: =J43-L43 -> 0 | N43: =IFERROR(J43/K43-1,"-") -> -
B44: Autres (à préciser) | G44: =D44-F44 -> 0 | H44: =IFERROR(D44/E44-1,"-") -> - | M44: =J44-L44 -> 0 | N44: =IFERROR(J44/K44-1,"-") -> -
B45: Dont commissions Banques | D45: =SUM(D46:D54) -> 0 | E45: =SUM(E46:E54) -> 0 | F45: =SUM(F46:F54) -> 0 | G45: =D45-F45 -> 0 | H45: =IFERROR(D45/E45-1,"-") -> - | J45: =SUM(J46:J54) -> 0 | K45: =SUM(K46:K54) -> 0 | L45: =SUM(L46:L54) -> 0 | M45: =J45-L45 -> 0 | N45: =IFERROR(J45/K45-1,"-") -> -
B46: Dépôt d’argent | G46: =D46-F46 -> 0 | H46: =IFERROR(D46/E46-1,"-") -> - | M46: =J46-L46 -> 0 | N46: =IFERROR(J46/K46-1,"-") -> -
B47: Retrait d’argent | G47: =D47-F47 -> 0 | H47: =IFERROR(D47/E47-1,"-") -> - | M47: =J47-L47 -> 0 | N47: =IFERROR(J47/K47-1,"-") -> -
B48: Transfert d’argent national | G48: =D48-F48 -> 0 | H48: =IFERROR(D48/E48-1,"-") -> - | M48: =J48-L48 -> 0 | N48: =IFERROR(J48/K48-1,"-") -> -
B49: Transfert d’argent international | G49: =D49-F49 -> 0 | H49: =IFERROR(D49/E49-1,"-") -> - | M49: =J49-L49 -> 0 | N49: =IFERROR(J49/K49-1,"-") -> -
B50: Recharge Mobile | G50: =D50-F50 -> 0 | H50: =IFERROR(D50/E50-1,"-") -> - | M50: =J50-L50 -> 0 | N50: =IFERROR(J50/K50-1,"-") -> -
B51: Achat de biens et services | G51: =D51-F51 -> 0 | H51: =IFERROR(D51/E51-1,"-") -> - | M51: =J51-L51 -> 0 | N51: =IFERROR(J51/K51-1,"-") -> -
B52: Paiement de factures | G52: =D52-F52 -> 0 | H52: =IFERROR(D52/E52-1,"-") -> - | M52: =J52-L52 -> 0 | N52: =IFERROR(J52/K52-1,"-") -> -
B53: Paiement de salaires | G53: =D53-F53 -> 0 | H53: =IFERROR(D53/E53-1,"-") -> - | M53: =J53-L53 -> 0 | N53: =IFERROR(J53/K53-1,"-") -> -
B54: Autres (à préciser) | G54: =D54-F54 -> 0 | H54: =IFERROR(D54/E54-1,"-") -> - | M54: =J54-L54 -> 0 | N54: =IFERROR(J54/K54-1,"-") -> -
A56: Marge Brute (en monnaie locale) | D56: =D23-D34 -> 0 | E56: =E23-E34 -> 0 | F56: =F23-F34 -> 0 | G56: =D56-F56 -> 0 | H56: =IFERROR(D56/E56-1,"-") -> - | J56: =J23-J34 -> 0 | K56: =K23-K34 -> 0 | L56: =L23-L34 -> 0 | M56: =J56-L56 -> 0 | N56: =IFERROR(J56/K56-1,"-") -> -
B57: % Marge Brute/CA | D57: =IFERROR(D56/D23,"-") -> - | E57: =IFERROR(E56/E23,"-") -> - | F57: =IFERROR(F56/F23,"-") -> - | G57: =IFERROR((D57-F57)*100,"-") -> - | H57: =IFERROR((D57-E57)*100,"-") -> - | J57: =IFERROR(J56/J23,"-") -> - | K57: =IFERROR(K56/K23,"-") -> - | L57: =IFERROR(L56/L23,"-") -> - | M57: =IFERROR((J57-L57)*100,"-") -> - | N57: =IFERROR((J57-K57)*100,"-") -> -

Sheet Trafic 
A2: Moov RCA : Trafic
O5: MENSUEL | U5: CUMUL (m-1) | AA5: CUMUL | AG5: ANNUEL
D6: Janvier | E6: Février | F6: Mars | G6: Avril | H6: Mai | I6: Juin | J6: Juillet | K6: Août | L6: Septembre | M6: Octobre | N6: Novembre | O6: 2023 | P6: 2023 Budget | Q6: Ecart / Budget | R6: 2022 Réel | S6: Evol % | U6: 2023 | V6: 2023 Budget | W6: Ecart / Budget | X6: 2021 Réel | Y6: Evol % | AA6: 2023 | AB6: 2023 Budget | AC6: Ecart / Budget | AD6: 2022 Réel | AE6: Evol % | AG6: 2023 Actu 1 | AH6: 2023 Actu 2 | AI6: 2023 Actu3 | AJ6: 2023 Budget | AK6: 2023 Actu3 | AL6: 2022 Réel | AM6: Ecart / Budget | AN6: B23/ 2022 (%) | AO6: Var Actu3/ 2019 (%)
