Workbook

Sheet Cover
E13: Tableau de Bord de Gestion
E15: Octobre 2025

Sheet RH QS
A2: Effectif et Sites BTS | D2: RH & QS
D4: 45658 | E4: 45689 | F4: 45717 | G4: 45748 | H4: 45778 | I4: 45809 | J4: 45839 | K4: 45870 | L4: 45901 | M4: 45931 | N4: 45962 | O4: 45992
B6: Effectif fin de période | D6: =+SUM(D7:D8) -> 116 | E6: =+SUM(E7:E8) -> 118 | F6: =+SUM(F7:F8) -> 118 | G6: =+SUM(G7:G8) -> 118 | H6: =+SUM(H7:H8) -> 118 | I6: =+SUM(I7:I8) -> 118 | J6: =+SUM(J7:J8) -> 118 | K6: =+SUM(K7:K8) -> 118 | ... O6: =+SUM(O7:O8) -> 118
B7: Variation (+/-) | D7: 1 | E7: 2 | F7: 0 | G7: 0 | H7: 0 | I7: 0 | J7: 0 | K7: 0 | L7: 0 | M7: 0 | N7: 0 | O7: 0
B8: Effectif début de période | D8: 115 | E8: =+D6 -> 116 | F8: =+E6 -> 118 | G8: =+F6 -> 118 | H8: =+G6 -> 118 | I8: =+H6 -> 118 | J8: =+I6 -> 118 | K8: =+J6 -> 118 | L8: =+K6 -> 118 | ... O8: =+N6 -> 118
B10: Nombre de BTS Total | D10: =+SUM(D11,D14) -> 1062 | E10: =+SUM(E11,E14) -> 1068 | F10: =+SUM(F11,F14) -> 1089 | G10: =+SUM(G11,G14) -> 1119 | H10: =+SUM(H11,H14) -> 1139 | I10: =+SUM(I11,I14) -> 1139 | J10: =+SUM(J11,J14) -> 1139 | K10: =+SUM(K11,K14) -> 1139 | ... O10: =+SUM(O11,O14) -> 1139
B11: Nbre fin de période 2G | D11: =+SUM(D12:D13) -> 678 | E11: =+SUM(E12:E13) -> 679 | F11: =+SUM(F12:F13) -> 690 | G11: =+SUM(G12:G13) -> 705 | H11: =+SUM(H12:H13) -> 715 | I11: =+SUM(I12:I13) -> 715 | J11: =+SUM(J12:J13) -> 715 | K11: =+SUM(K12:K13) -> 715 | ... O11: =+SUM(O12:O13) -> 715
B12: Variation (+/-) | D12: 2 | E12: 1 | F12: 11 | G12: 15 | H12: 10 | I12: 0 | J12: 0 | K12: 0 | L12: 0 | M12: 0 | N12: 0 | O12: 0
B13: Nbre début de période 2G | D13: 676 | E13: =+D11 -> 678 | F13: =+E11 -> 679 | G13: =+F11 -> 690 | H13: =+G11 -> 705 | I13: =+H11 -> 715 | J13: =+I11 -> 715 | K13: =+J11 -> 715 | L13: =+K11 -> 715 | ... O13: =+N11 -> 715
B14: Nbre fin de période 3G/4G | D14: =+SUM(D15:D16) -> 384 | E14: =+SUM(E15:E16) -> 389 | F14: =+SUM(F15:F16) -> 399 | G14: =+SUM(G15:G16) -> 414 | H14: =+SUM(H15:H16) -> 424 | I14: =+SUM(I15:I16) -> 424 | J14: =+SUM(J15:J16) -> 424 | K14: =+SUM(K15:K16) -> 424 | ... O14: =+SUM(O15:O16) -> 424
B15: Variation (+/-) | D15: 6 | E15: 5 | F15: 10 | G15: 15 | H15: 10 | I15: 0 | J15: 0 | K15: 0 | L15: 0 | M15: 0 | N15: 0 | O15: 0
B16: Nbre début de période 3G/4G | D16: 378 | E16: =+D14 -> 384 | F16: =+E14 -> 389 | G16: =+F14 -> 399 | H16: =+G14 -> 414 | I16: =+H14 -> 424 | J16: =+I14 -> 424 | K16: =+J14 -> 424 | L16: =+K14 -> 424 | ... O16: =+N14 -> 424
B18: Nombre de sites Total
B19: Nbre fin de période 2G/3G/4G | D19: =+SUM(D20:D21) -> 504 | E19: =+SUM(E20:E21) -> 506 | F19: =+SUM(F20:F21) -> 512 | G19: =+SUM(G20:G21) -> 527 | H19: =+SUM(H20:H21) -> 537 | I19: =+SUM(I20:I21) -> 537 | J19: =+SUM(J20:J21) -> 537 | K19: =+SUM(K20:K21) -> 537 | ... O19: =+SUM(O20:O21) -> 537
B20: Variation (+/-) | D20: 1 | E20: 2 | F20: 6 | G20: 15 | H20: 10 | I20: 0 | J20: 0 | K20: 0 | L20: 0 | M20: 0 | N20: 0 | O20: 0
B21: Nbre début de période 2G/3G/4G | D21: 503 | E21: =+D19 -> 504 | F21: =+E19 -> 506 | G21: =+F19 -> 512 | H21: =+G19 -> 527 | I21: =+H19 -> 537 | J21: =+I19 -> 537 | K21: =+J19 -> 537 | L21: =+K19 -> 537 | ... O21: =+N19 -> 537

Sheet Parc 
D2: 0.61715886 | J2: 0.61586377 | P2: 0.5927915 | V2: 0.59067085 | BJ2: 0.55666499
B4: Parc d'abonnés | D4: JANVIER | J4: FEVRIER | P4: MARS | V4: AVRIL | AD4: MAI | AL4: JUIN | AT4: JUILLET | BB4: AOUT | BJ4: SEPTEMBRE | BR4: OCTOBRE | BZ4: NOVEMBRE | CH4: DECEMBRE | CP4: CUMUL | CX4: ANNUEL
D5: 2025 Réel | E5: 2025 Budget | F5: Ecart / Budget | G5: 2024 Réel | H5: Evol % | J5: 2025 Réel | K5: 2025 Budget | L5: Ecart / Budget | M5: 2024 Réel | N5: Evol % | P5: 2025 Réel | Q5: 2025 Budget | R5: Ecart / Budget | S5: 2024 Réel | T5: Evol % | V5: 2025 Réel | W5: 2025 Budget | X5: 2025 Actu 1 | Y5: Ecart / Budget | Z5: Ecart / Actu 1 | AA5: 2024 Réel | AB5: Evol % | AD5: 2025 Réel | AE5: 2025 Budget | AF5: 2025 Actu 1 | AG5: Ecart / Budget | AH5: Ecart / Actu 1 | AI5: 2024 Réel | AJ5: Evol % | AL5: 2025 Réel | AM5: 2025 Budget | AN5: 2025 Actu 1 | AO5: Ecart / Budget | AP5: Ecart / Actu 1 | AQ5: 2024 Réel | AR5: Evol % | AT5: 2025 Réel | AU5: 2025 Budget | AV5: 2025 Actu 2 | AW5: Ecart / Budget | AX5: Ecart / Actu 2 | AY5: 2024 Réel | AZ5: Evol % | BB5: 2025 Réel | BC5: 2025 Budget | BD5: 2025 Actu3 | BE5: Ecart / Budget | BF5: Ecart / Actu 3 | BG5: 2024 Réel | BH5: Evol % | BJ5: 2025 Réel | BK5: 2025 Budget | BL5: 2025 Actu3 | BM5: Ecart / Budget | BN5: Ecart / Actu 3 | BO5: 2024 Réel | BP5: Evol % | BR5: 2025 Réel | BS5: 2025 Budget | BT5: 2025 Actu 3 | BU5: Ecart / Budget | BV5: Ecart / Actu 3 | BW5: 2024 Réel | BX5: Evol % | BZ5: 2025 Réel | CA5: 2025 Budget | CB5: 2025 Actu 3 | CC5: Ecart / Budget | CD5: Ecart / Actu 3 | CE5: 2024 Réel | CF5: Evol % | CH5: 2025 Réel | CI5: 2025 Budget | CJ5: 2025 Actu 3 | CK5: Ecart / Budget | CL5: Ecart / Actu 3 | CM5: 2024 Réel | CN5: Evol % | CP5: 2025 Réel | CQ5: 2025 Budget | CR5: 2025 Actu 3 | CS5: Ecart / Budget | CT5: Ecart / Actu 3 | CU5: 2024 Réel | CV5: Evol % | CX5: 2025 Budget | CY5: 2024 Actu 1 | CZ5: 2024 Actu 2 | DA5: 2025 Actu 3 | DB5: 2024 Réel | DC5: Bud / 2024 (%) | DD5: Actu 1 / 2023 (%) | DE5: Actu 2 / 2023 (%) | DF5: Actu 3 / 2019 (%)
B7: Parc Total Mobile Actif | D7: 256415.34 | E7: 257215.34 | F7: -800 | G7: 261327.34 | H7: -0.018796349 | J7: 257227.34 | K7: 259498.34 | L7: -2271 | M7: 263850.34 | N7: -0.025101351 | P7: 257252.34 | Q7: 273811.34 | R7: -16559 | S7: 267523.34 | T7: -0.038392912 | V7: 258416.34 | W7: 295411.34 | X7: 260852.34 | Y7: -36995 | Z7: -2436 | AA7: 271367.34 | AB7: -0.047724977 | AD7: 268420.34 | AE7: 320661.34 | AF7: 277602.34 | AG7: -52241 | AH7: -9182 | AI7: 272718.34 | AJ7: -0.01575985 | AL7: 280436.34 | AM7: 347666.34 | AN7: 301107.34 | AO7: -67230 | AP7: -20671 | AQ7: 274567.34 | AR7: 0.021375448 | AT7: 292361.34 | AU7: 372681.34 | AV7: 302440.34 | AW7: -80320 | AX7: -10079 | AY7: 276485.34 | AZ7: 0.057420766 | BB7: 304463.34 | BC7: 388881.34 | BD7: 359445.34 | BE7: -84418 | BF7: -54982 | BG7: 276903.34 | BH7: 0.099529316 | BJ7: 308997.34 | BK7: 404381.34 | BL7: 319963.34 | BM7: -95384 | BN7: -10966 | BO7: 276903.34 | BP7: 0.11590326 | BR7: 312650.34 | BS7: 422881.34 | BT7: 331265.34 | BU7: -110231 | BV7: -18615 | BW7: 274494.34 | BX7: 0.13900469 | BZ7: 312650.34 | CA7: 422881.34 | CB7: 312650.34 | CC7: -110231 | CD7: 0 | CE7: 274494.34 | CF7: 0.13900469 | CH7: 312650.34 | CI7: 422881.34 | CJ7: 312650.34 | CK7: -110231 | CL7: 0 | CM7: 274494.34 | CN7: 0.13900469 | CP7: 312650.34 | CQ7: 422881.34 | CR7: 331265.34 | CS7: -110231 | CT7: -18615 | CU7: 267523.34 | CV7: 0.16868435 | CX7: 460481.34 | CY7: 0 | CZ7: 0 | DA7: 370122 | DB7: 256234.34 | DC7: 0.79711018 | DD7: -1 | DE7: -1 | DF7: 0.44446681
B8: Activations totales | D8: 23283 | E8: 21745 | F8: 1538 | G8: 26228 | H8: -0.11228458 | J8: 22183 | K8: 22915 | L8: -732 | M8: 17015 | N8: 0.303732 | P8: 20785 | Q8: 34405 | R8: -13620 | S8: 19800 | T8: 0.049747475 | V8: 29250 | W8: 42452 | X8: 24452 | Y8: -13202 | Z8: 4798 | AA8: 18148 | AB8: 0.61174785 | AD8: 34803 | AE8: 47713 | AF8: 37713 | AG8: -12910 | AH8: -2910 | AI8: 16425 | AJ8: 1.1189041 | AL8: 31208 | AM8: 47900 | AN8: 42900 | AO8: -16692 | AP8: -11692 | AQ8: 17800 | AR8: 0.75325843 | AT8: 32758 | AU8: 45905 | AV8: 42894 | AW8: -13147 | AX8: -10136 | AY8: 25021 | AZ8: 0.30922025 | BB8: 31311 | BC8: 38237 | BD8: 33309 | BE8: -6926 | BF8: -1998 | BG8: 26384 | BH8: 0.18674196 | BJ8: 28120 | BK8: 38358 | BL8: 36358 | BM8: -10238 | BN8: -8238 | BO8: 26384 | BP8: 0.065797453 | BR8: 28253 | BS8: 40356 | BT8: 30722 | BU8: -12103 | BV8: -2469 | BW8: 16113 | BX8: 0.75342891 | BZ8: 0 | CA8: 0 | CB8: 0 | CC8: 0 | CD8: 0 | CE8: 0 | CH8: 0 | CI8: 0 | CJ8: 0 | CK8: 0 | CL8: 0 | CM8: 0 | CP8: 281954 | CQ8: 380118 | CR8: 305147 | CS8: -98164 | CT8: -23193 | CU8: 209318 | CV8: 0.34701268 | CX8: 462966 | CY8: 0 | CZ8: 0 | DA8: 362587 | DB8: 250537 | DC8: 0.84789472 | DD8: -1 | DE8: -1 | DF8: 0.44723933
B9: Flux d'inactivité | D9: -22571 | E9: -20634 | F9: -1937 | G9: -17576 | H9: 0.28419436 | J9: -21680 | K9: -20500 | L9: -1180 | M9: -14300 | N9: 0.51608392 | P9: -20744 | Q9: -19960 | R9: -784 | S9: -15877 | T9: 0.30654406 | V9: -28074 | W9: -20716 | X9: -20716 | Y9: -7358 | Z9: -7358 | AA9: -14212 | AB9: 0.97537292 | AD9: -24785 | AE9: -22329 | AF9: -20829 | AG9: -2456 | AH9: -3956 | AI9: -14856 | AJ9: 0.66834949 | AL9: -19174 | AM9: -20759 | AN9: -19259 | AO9: 1585 | AP9: 85 | AQ9: -15783 | AR9: 0.21485142 | AT9: -20813 | AU9: -20756 | AV9: -20756 | AW9: -57 | AX9: -57 | AY9: -22929 | AZ9: -0.092284879 | BB9: -19187 | BC9: -22033 | BD9: 20853 | BE9: 2846 | BF9: -40040 | BG9: -25830 | BH9: ns | BJ9: -23566 | BK9: -22720 | BL9: -20720 | BM9: -846 | BN9: -2846 | BO9: -25830 | BP9: -0.087650019 | BR9: -24578 | BS9: -21720 | BT9: -19220 | BU9: -2858 | BV9: -5358 | BW9: -18400 | BX9: 0.33576087 | BZ9: 0 | CA9: 0 | CB9: 0 | CC9: 0 | CD9: 0 | CE9: 0 | CH9: 0 | CI9: 0 | CJ9: 0 | CK9: 0 | CL9: 0 | CM9: 0 | CP9: -225172 | CQ9: -212127 | CR9: -165642 | CS9: -13045 | CT9: -59530 | CU9: -185593 | CV9: 0.21325697 | CX9: -258719 | CY9: 0 | CZ9: 0 | DA9: -247711 | DB9: -247166 | DC9: 0.046741866 | DD9: -1 | DE9: -1 | DF9: 0.0022049958
B10: Acroissement net | D10: 508 | E10: 981 | F10: -473 | G10: 8464 | H10: -0.9399811 | J10: 485 | K10: 2283 | L10: -1798 | M10: 2523 | N10: -0.80776853 | P10: 25 | Q10: 14313 | R10: -14288 | S10: 3673 | T10: -0.99319357 | V10: 1164 | W10: 21600 | X10: 3600 | Y10: -20436 | Z10: -2436 | AA10: 3844 | AB10: -0.69719043 | AD10: 10004 | AE10: 25250 | AF10: 16750 | AG10: -15246 | AH10: -6746 | AI10: 1351 | AJ10: 6.4048853 | AL10: 12016 | AM10: 27005 | AN10: 23505 | AO10: -14989 | AP10: -11489 | AQ10: 1849 | AR10: 5.4986479 | AT10: 11925 | AU10: 25015 | AV10: 22004 | AW10: -13090 | AX10: -10079 | AY10: 1918 | AZ10: 5.217414 | BB10: 12102 | BC10: 16068 | BD10: 54146 | BE10: -3966 | BF10: -42044 | BG10: 418 | BH10: 27.952153 | BJ10: 4534 | BK10: 15500 | BL10: 15500 | BM10: -10966 | BN10: -10966 | BO10: 418 | BP10: 9.84689 | BR10: 3653 | BS10: 18500 | BT10: 11366 | BU10: -14847 | BV10: -7713 | BW10: -2409 | BX10: -2.5163968 | BZ10: 0 | CA10: 0 | CB10: 0 | CC10: 0 | CD10: 0 | CE10: 0 | CH10: 0 | CI10: 0 | CJ10: 0 | CK10: 0 | CL10: 0 | CM10: 0 | CP10: 56416 | CQ10: 166647 | CR10: 138437 | CS10: -110231 | CT10: -82021 | CU10: 22049 | CV10: 1.5586648 | CX10: 204247 | CY10: 0 | CZ10: 0 | DA10: 113888 | DB10: 3371 | DC10: 59.589439 | DD10: -1 | DE10: -1 | DF10: 32.784634
B11: % churn annualisé | D11: -1.0560012 | E11: -0.96448789 | F11: -0.091513327 | G11: -0.068357009 | H11: -98.764421 | J11: -1.0123554 | K11: -0.95217142 | L11: -0.060184014 | M11: -0.65349312 | N11: 0.54914475 | P11: -0.96768836 | Q11: -0.89823984 | R11: -0.069448527 | S11: -0.71709988 | T11: 0.34944712 | V11: -1.3066064 | W11: -0.87344376 | X11: -0.95962075 | Y11: -0.43316264 | Z11: -0.34698566 | AA11: -0.052745392 | AB11: 23.771954 | AD11: -1.1290786 | AE11: -0.78854554 | AF11: -0.93679325 | AG11: -0.34053302 | AH11: -0.19228531 | AI11: -0.65530855 | AJ11: 0.72297241 | AL11: -0.83842653 | AM11: -0.74546665 | AN11: -0.798701 | AO11: -0.092959872 | AP11: -0.039725527 | AQ11: -0.69212847 | AR11: 0.21137414 | AT11: -0.8720566 | AU11: -0.69153273 | AV11: -0.85463018 | AW11: -0.18052387 | AX11: -0.017426428 | AY11: -0.99862685 | AZ11: -0.12674428 | BB11: -0.77156327 | BC11: -0.69447162 | BD11: 0.75287853 | BE11: -0.077091644 | BF11: -1.5244418 | BG11: -1.1202253 | BH11: -0.31124278 | BJ11: -0.9219564 | BK11: -0.68738895 | BL11: -0.79637853 | BM11: -0.23456745 | BN11: -0.12557787 | BO11: -1.1202253 | BP11: -0.1769902 | BR11: -0.94888474 | BS11: -0.63012633 | BT11: -0.70839223 | BU11: -0.31875841 | BV11: -0.24049251 | BW11: -0.80087388 | BX11: 0.1848117 | BZ11: 0 | CA11: 0 | CB11: 0 | CC11: 0 | CD11: 0 | CE11: 0 | CH11: 0 | CI11: 0 | CJ11: 0 | CK11: 0 | CL11: 0 | CM11: 0 | CP11: -8.6932328 | CQ11: -7.4965844 | CR11: -0.63175638 | CS11: -1.1966484 | CT11: -8.0614764 | CU11: -0.69854043 | CV11: -799.46924 | CX11: -0.72195714 | CY11: #DIV/0! | CZ11: #DIV/0! | DA11: -0.79095914 | DB11: -2.8400599 | DC11: 211.81027 | DF11: -0.72149913
B12: Parc Actif Moyen | D12: 256488.34 | E12: 256724.84 | F12: -236.5 | G12: 257120.67 | H12: -0.0024592733 | J12: 256984.84 | K12: 258356.84 | L12: -1372 | M12: 262588.84 | N12: -0.021341349 | P12: 257239.84 | Q12: 266654.84 | R12: -9415 | S12: 265686.84 | T12: -0.031793069 | V12: 257834.34 | W12: 284611.34 | X12: 259052.34 | Y12: -26777 | Z12: -1218 | AA12: 269445.34 | AB12: -0.043092228 | AD12: 263418.34 | AE12: 305498.84 | AF12: 266812.34 | AG12: -42080.5 | AH12: -3394 | AI12: 272042.84 | AJ12: -0.031702727 | AL12: 274428.34 | AM12: 334163.84 | AN12: 289354.84 | AO12: -59735.5 | AP12: -14926.5 | AQ12: 273642.84 | AR12: 0.0028705301 | AT12: 286398.84 | AU12: 360173.84 | AV12: 291438.34 | AW12: -73775 | AX12: -5039.5 | AY12: 275526.34 | AZ12: 0.039460837 | BB12: 298412.34 | BC12: 380715.34 | BD12: 332372.34 | BE12: -82303 | BF12: -33960 | BG12: 276694.34 | BH12: 0.078490944 | BJ12: 306730.34 | BK12: 396631.34 | BL12: 312213.34 | BM12: -89901 | BN12: -5483 | BO12: 276694.34 | BP12: 0.108553 | BR12: 310823.84 | BS12: 413631.34 | BT12: 325582.34 | BU12: -102807.5 | BV12: -14758.5 | BW12: 275698.84 | BX12: 0.12740351 | BZ12: 312650.34 | CA12: 422881.34 | CB12: 312650.34 | CC12: -110231 | CD12: 0 | CE12: 274494.34 | CF12: 0.13900469 | CH12: 312650.34 | CI12: 422881.34 | CJ12: 312650.34 | CK12: -110231 | CL12: 0 | CM12: 274494.34 | CN12: 0.13900469 | CP12: 310823.84 | CQ12: 339557.84 | CR12: 262192.84 | CS12: -28734 | CT12: 48631 | CU12: 265686.84 | CV12: 0.16988798 | CX12: 358357.84 | CY12: 0 | CZ12: 0 | DA12: 313178 | DB12: 261085.34 | DC12: 0.37256975 | DD12: -1 | DE12: -1 | DF12: 0.1995235
B13: Parc actif localisé | D13: 203255.33 | E13: 203200.12 | F13: 55.214733 | G13: 208760 | H13: -0.026368398 | J13: 202795.33 | K13: 205003.69 | L13: -2208.3553 | M13: 216277 | N13: -0.062335184 | P13: 203570 | Q13: 216310.96 | R13: -12740.959 | S13: 212639.67 | T13: -0.042652751 | V13: 206275 | W13: 233374.96 | X13: 206073.35 | Y13: -27099.959 | Z13: 201.6514 | AA13: 207498 | AB13: -0.0058940327 | AD13: #REF! | AE13: 256529.07 | AF13: 222081.87 | AG13: #REF! | AH13: #REF! | AI13: 210486 | AL13: 219174.67 | AM13: 278133.07 | AN13: 240885.87 | AO13: -58958.405 | AP13: -21711.205 | AQ13: 212214.67 | AR13: 0.032796979 | AT13: 226835 | AU13: 298145.07 | AV13: 241952.27 | AW13: -71310.072 | AX13: -15117.272 | AY13: 218811 | AZ13: 0.036670917 | BB13: 237409 | BC13: 311105.07 | BD13: 243863.47 | BE13: -73696.072 | BF13: -6454.472 | BG13: 218442 | BH13: 0.08682854 | BJ13: 182933 | BK13: 323505.07 | BL13: 263970.67 | BM13: -140572.07 | BN13: -81037.672 | BO13: 218442 | BP13: -0.16255574 | BR13: 245567 | BS13: 338305.07 | BT13: 265063.47 | BU13: -92738.072 | BV13: -19496.472 | BW13: 215600.67 | BX13: 0.13898998 | BZ13: 0 | CA13: 0 | CB13: 0 | CC13: 0 | CD13: 0 | CE13: 0 | CH13: 0 | CI13: 0 | CJ13: 0 | CK13: 0 | CL13: 0 | CM13: 0 | CP13: 245567 | CQ13: 203200.12 | CR13: 265063.47 | CS13: 42366.881 | CT13: -19496.472 | CU13: 212639.67 | CV13: 0.15485038 | CX13: 368385.07 | CY13: 0 | CZ13: 0 | DA13: 296097.87 | DB13: 208204.3 | DC13: 0.76934425 | DD13: -1 | DE13: -1 | DF13: 0.42215064
B14: Parc internet | D14: 158249 | E14: 160927.47 | F14: -2678.471 | G14: 164229 | H14: -0.03641257 | J14: 158417 | K14: 163618.89 | L14: -5201.8933 | M14: 163886 | N14: -0.033370758 | P14: 152497 | Q14: 172665.43 | R14: -20168.431 | S14: 167668 | T14: -0.090482382 | V14: 152639 | W14: 186404.56 | X14: 164597.83 | Y14: -33765.556 | Z14: -11958.827 | AA14: 180500 | AB14: -0.15435457 | AD14: 156325 | AE14: 205223.26 | AF14: 177665.5 | AG14: -48898.258 | AH14: -21340.498 | AI14: 181750 | AJ14: -0.13988996 | AL14: 160210 | AM14: 224244.79 | AN14: 194214.23 | AO14: -64034.789 | AP14: -34004.234 | AQ14: 182575 | AR14: -0.1224976 | AT14: 168220.5 | AU14: 242242.87 | AV14: 196586.22 | AW14: -74022.371 | AX14: -28365.721 | AY14: 183318 | AZ14: -0.082356888 | BB14: 171743 | BC14: 254717.28 | BD14: 199663.22 | BE14: -82974.278 | BF14: -27920.218 | BG14: 184218 | BH14: -0.067718681 | BJ14: 172008 | BK14: 264869.78 | BL14: 216125.99 | BM14: -92861.778 | BN14: -44117.988 | BO14: 184218 | BP14: -0.066280168 | BR14: 175621 | BS14: 277410.16 | BT14: 217352.05 | BU14: -101789.16 | BV14: -41731.047 | BW14: 184698 | BX14: -0.049145091 | BZ14: 0 | CA14: 0 | CB14: 0 | CC14: 0 | CD14: 0 | CE14: 0 | CH14: 0 | CI14: 0 | CJ14: 0 | CK14: 0 | CL14: 0 | CM14: 0 | CP14: 175621 | CQ14: 160927.47 | CR14: 217352.05 | CS14: 14693.529 | CT14: -41731.047 | CU14: 163886 | CV14: 0.071604652 | CX14: 307141.05 | CY14: 0 | CZ14: 0 | DA14: 191500 | DB14: 155803 | DC14: 0.97134236 | DD14: -1 | DE14: -1 | DF14: 0.22911626
B15: Parc actif Mobile Money | D15: 0 | E15: 0 | F15: 0 | G15: 0 | J15: 0 | K15: 0 | L15: 0 | M15: 0 | P15: 0 | Q15: 0 | R15: 0 | S15: 0 | V15: 0 | W15: 0 | X15: 0 | Y15: 0 | Z15: 0 | AA15: 0 | AD15: 0 | AE15: 0 | AF15: 0 | AG15: 0 | AH15: 0 | AI15: 0 | AL15: 0 | AM15: 0 | AN15: 0 | AO15: 0 | AP15: 0 | AQ15: 0 | AT15: 0 | AU15: 0 | AV15: 0 | AW15: 0 | AX15: 0 | AY15: 0 | BB15: 0 | BC15: 0 | BE15: 0 | BF15: 0 | BG15: 0 | BJ15: 0 | BK15: 0 | BL15: 0 | BM15: 0 | BN15: 0 | BO15: 0 | BR15: 0 | BS15: 0 | BT15: 0 | BU15: 0 | BV15: 0 | BW15: 0 | BZ15: 0 | CA15: 0 | CB15: 0 | CC15: 0 | CD15: 0 | CE15: 0 | CH15: 0 | CI15: 0 | CJ15: 0 | CK15: 0 | CL15: 0 | CM15: 0 | CP15: 0 | CQ15: 0 | CR15: 0 | CS15: 0 | CT15: 0 | CU15: 0 | CY15: 0 | CZ15: 0 | DA15: 413541.86 | DB15: 0 | DD15: #DIV/0! | DE15: #DIV/0! | DF15: #DIV/0!
B17: Parc Prépayé Actif | Z17: 0 | AH17: 0 | AP17: 0 | AX17: 0 | BF17: 0 | BN17: 0 | BV17: 0 | CD17: 0 | CL17: 0
B18: Parc prépayé actif début Période | D18: 251459.34 | E18: 251459.34 | F18: 0 | G18: 248517 | H18: 0.011839592 | J18: 251962.34 | K18: 252355.34 | L18: -393 | M18: 256879.34 | N18: 0.20064566 | P18: 252451.34 | Q18: 254552.34 | R18: -2101 | S18: 259366.34 | T18: -0.026661131 | V18: 252479.34 | W18: 268793.34 | X18: 252479.34 | Y18: -16314 | Z18: 0 | AA18: 263022.34 | AB18: -0.040084048 | AD18: 253641.34 | AE18: 290336.34 | AF18: 256022.34 | AG18: -36695 | AH18: -2381 | AI18: 266722.34 | AJ18: -0.049043511 | AL18: 263643.34 | AM18: 315516.34 | AN18: 272702.34 | AO18: -51873 | AP18: -9059 | AQ18: 268007.34 | AR18: -0.016283136 | AT18: 275657.34 | AU18: 342471.34 | AV18: 275657.34 | AW18: -66814 | AX18: 0 | AY18: 269842.34 | AZ18: 0.02154962 | BB18: 287579.34 | BC18: 367425.34 | BD18: 300043.34 | BE18: -79846 | BF18: -12464 | BG18: 271744.34 | BH18: 0.058271683 | BJ18: 299678.34 | BK18: 383561.34 | BL18: 299678.34 | BM18: -83883 | BN18: 0 | BO18: 271744.34 | BP18: 0.10279515 | BR18: 304210.34 | BS18: 398995.34 | BT18: 315112.34 | BU18: -94785 | BV18: -10902 | BW18: 272153.34 | BX18: 0.11779021 | BZ18: 307861.34 | CA18: 417424.34 | CB18: 307861.34 | CC18: -109563 | CD18: 0 | CE18: 269737.34 | CF18: 0.1413375 | CH18: 307861.34 | CI18: 417424.34 | CJ18: 307861.34 | CK18: -109563 | CL18: 0 | CM18: 269737.34 | CN18: 0.1413375 | CP18: 304210.34 | CQ18: 251459.34 | CR18: 188335.34 | CS18: 52751 | CT18: 115875 | CU18: 259366.34 | CV18: 0.1728983 | CX18: 251459.34 | DA18: 251514 | DB18: 261173.34 | DC18: -0.037193689 | DD18: -1 | DE18: -1 | DF18: -0.036984403
B19: Activations totales | D19: 23176 | E19: 21595 | F19: 1581 | G19: 26083 | H19: -0.1114519 | J19: 22178 | K19: 22763 | L19: -585 | M19: 16883 | N19: 0.31362909 | P19: 20780 | Q19: 34267 | R19: -13487 | S19: 19658 | T19: 0.057076 | V19: 29242 | W19: 42327 | X19: 24327 | Y19: -13085 | Z19: 4915 | AA19: 17958 | AB19: 0.62835505 | AD19: 34794 | AE19: 47576 | AF19: 37576 | AG19: -12782 | AH19: -2782 | AI19: 16250 | AJ19: 1.1411692 | AL19: 31197 | AM19: 47782 | AN19: 42782 | AO19: -16585 | AP19: -11585 | AQ19: 17702 | AR19: 0.76234324 | AT19: 32745 | AU19: 45777 | AV19: 42766 | AW19: -13032 | AX19: -10021 | AY19: 24918 | AZ19: 0.31411028 | BB19: 31297 | BC19: 38237 | BD19: 33309 | BE19: -6940 | BF19: -2012 | BG19: 26307 | BH19: 0.18968335 | BJ19: 28108 | BK19: 38223 | BL19: 36223 | BM19: -10115 | BN19: -8115 | BO19: 26307 | BP19: 0.068460866 | BR19: 28240 | BS19: 40217 | BT19: 30583 | BU19: -11977 | BV19: -2343 | BW19: 16045 | BX19: 0.76004986 | CC19: 0 | CD19: 0 | CK19: 0 | CL19: 0 | CP19: 281757 | CQ19: 378764 | CR19: 304248 | CS19: -97007 | CT19: -22491 | CU19: 208111 | CV19: 0.35387846 | CX19: 461319 | DA19: 361731 | DB19: 249225 | DC19: 0.85101414 | DD19: -1 | DE19: -1 | DF19: 0.45142341
B20: Flux d'inactivité | D20: -22673 | E20: -20699 | F20: -1974 | G20: -17670 | H20: 0.28313526 | J20: -21689 | K20: -20566 | L20: -1123 | M20: -14396 | N20: 0.50659906 | P20: -20752 | Q20: -20026 | R20: -726 | S20: -16002 | T20: 0.2968379 | V20: -28080 | W20: -20784 | X20: -20784 | Y20: -7296 | Z20: -7296 | AA20: -14258 | AB20: 0.96942068 | AD20: -24792 | AE20: -22396 | AF20: -20896 | AG20: -2396 | AH20: -3896 | AI20: -14965 | AJ20: 0.65666555 | AL20: -19183 | AM20: -20827 | AN20: -19327 | AO20: 1644 | AP20: 144 | AQ20: -15867 | AR20: 0.20898721 | AT20: -20823 | AU20: -20823 | AV20: -20823 | AW20: 0 | AX20: 0 | AY20: -23016 | AZ20: -0.095281543 | BB20: -19198 | BC20: -22101 | BD20: 20845 | BE20: 2903 | BF20: -40043 | BG20: -25898 | BH20: -0.25870724 | BJ20: -23576 | BK20: -22789 | BL20: -20789 | BM20: -787 | BN20: -2787 | BO20: -25898 | BP20: -0.089659433 | BR20: -24589 | BS20: -21788 | BT20: -19288 | BU20: -2801 | BV20: -5301 | BW20: -18461 | BX20: 0.33194302 | CC20: 0 | CD20: 0 | CK20: 0 | CL20: 0 | CP20: -225355 | CQ20: -212799 | CR20: -166176 | CS20: -12556 | CT20: -59179 | CU20: -186431 | CV20: 0.20878502 | CX20: -257914 | DA20: -248205 | DB20: -246232 | DC20: 0.047443062 | DD20: -1 | DE20: -1 | DF20: 0.0080127684
B21: Acroissement net | D21: 503 | E21: 896 | F21: -393 | G21: 8413 | H21: -0.94021158 | J21: 489 | K21: 2197 | L21: -1708 | M21: 2487 | N21: -0.80337756 | P21: 28 | Q21: 14241 | R21: -14213 | S21: 3656 | T21: -0.99234136 | V21: 1162 | W21: 21543 | X21: 3543 | Y21: -20381 | Z21: -2381 | AA21: 3700 | AB21: -0.68594595 | AD21: 10002 | AE21: 25180 | AF21: 16680 | AG21: -15178 | AH21: -6678 | AI21: 1285 | AJ21: 6.7836576 | AL21: 12014 | AM21: 26955 | AN21: 23455 | AO21: -14941 | AP21: -11441 | AQ21: 1835 | AR21: 5.547139 | AT21: 11922 | AU21: 24954 | AV21: 21943 | AW21: -13032 | AX21: -10021 | AY21: 1902 | AZ21: 5.2681388 | BB21: 12099 | BC21: 16136 | BD21: 54154 | BE21: -4037 | BF21: -42055 | BG21: 409 | BH21: 28.581907 | BJ21: 4532 | BK21: 15434 | BL21: 15434 | BM21: -10902 | BN21: -10902 | BO21: 409 | BP21: 10.080685 | BR21: 3651 | BS21: 18429 | BT21: 11295 | BU21: -14778 | BV21: -7644 | BW21: -2416 | BX21: -2.5111755 | BZ21: 0 | CA21: 0 | CB21: 0 | CC21: 0 | CD21: 0 | CE21: 0 | CH21: 0 | CI21: 0 | CJ21: 0 | CK21: 0 | CL21: 0 | CM21: 0 | CP21: 56402 | CQ21: 165965 | CR21: 138072 | CS21: -109563 | CT21: -81670 | CU21: 21680 | CV21: 1.6015683 | CX21: 203405 | CY21: 0 | CZ21: 0 | DA21: 113526 | DB21: 2993 | DC21: 66.960241 | DD21: -1 | DE21: -1 | DF21: 36.930505
B22: % churn annualisé | D22: -1.079828 | E22: -0.98602923 | F22: -0.093798813 | G22: -0.091716212 | H22: -98.811183 | J22: -1.0319625 | K22: -0.97371577 | L22: -0.058246729 | M22: -0.66926274 | N22: 0.54193925 | P22: -0.98636906 | Q22: -0.91836814 | R22: -0.068000917 | S22: -0.73517673 | T22: 0.34167612 | V22: -1.3315401 | W22: -0.89212935 | X22: -0.98095251 | Y22: -0.43941078 | Z22: -0.35058763 | AA22: -0.053829705 | AB22: 17.223256 | AD22: -1.1502525 | AE22: -0.88718597 | AF22: -0.94851634 | AG22: -0.26306653 | AH22: -0.20173616 | AI22: -0.67166648 | AL22: -0.85368333 | AM22: -0.75966164 | AN22: -0.78311076 | AO22: -0.094021689 | AP22: -0.070572568 | AQ22: -0.70801939 | AT22: -0.88728596 | AU22: -0.7039785 | AV22: -0.8717755 | AW22: -0.18330746 | AX22: -0.015510464 | AY22: -1.0199365 | BB22: -0.78458233 | BC22: -0.70630281 | BD22: 0.76467272 | BE22: -0.078279525 | BF22: -1.5492551 | BG22: -1.1427738 | BJ22: -0.93696739 | BK22: -0.69890912 | BL22: -0.81155427 | BM22: -0.23805827 | BN22: -0.12541312 | BO22: -1.1427738 | BR22: -0.96416158 | BS22: -0.64049411 | BT22: -0.72158659 | BU22: -0.32366747 | BV22: -0.24257499 | BW22: -0.81762617 | BZ22: 0 | CA22: 0 | CB22: 0 | CC22: 0 | CD22: 0 | CE22: 0 | CH22: 0 | CI22: 0 | CJ22: 0 | CK22: 0 | CL22: 0 | CM22: 0 | CP22: -8.7840195 | CQ22: -0.67972078 | CR22: -0.6456663 | CS22: -8.1042987 | CT22: -8.1383532 | CU22: -0.94507055 | CV22: -783.89489 | CX22: -0.73029974 | CY22: #DIV/0! | CZ22: #DIV/0! | DA22: -0.80513629 | DB22: -1.305616 | DC22: 57.531624 | DF22: -0.38332841
B23: Parc prépayé actif fin de période | D23: 251962.34 | E23: 252355.34 | F23: -393 | G23: 256879.34 | H23: -0.019141282 | J23: 252451.34 | K23: 254552.34 | L23: -2101 | M23: 259366.34 | N23: -0.026661131 | P23: 252479.34 | Q23: 268793.34 | R23: -16314 | S23: 263022.34 | T23: -0.040084048 | V23: 253641.34 | W23: 290336.34 | X23: 256022.34 | Y23: -36695 | Z23: -2381 | AA23: 266722.34 | AB23: -0.049043511 | AD23: 263643.34 | AE23: 315516.34 | AF23: 272702.34 | AG23: -51873 | AH23: -9059 | AI23: 268007.34 | AJ23: -0.016283136 | AL23: 275657.34 | AM23: 342471.34 | AN23: 296157.34 | AO23: -66814 | AP23: -20500 | AQ23: 269842.34 | AR23: 0.02154962 | AT23: 287579.34 | AU23: 367425.34 | AV23: 297600.34 | AW23: -79846 | AX23: -10021 | AY23: 271744.34 | AZ23: 0.058271683 | BB23: 299678.34 | BC23: 383561.34 | BD23: 354197.34 | BE23: -83883 | BF23: -54519 | BG23: 272153.34 | BH23: 0.10113784 | BJ23: 304210.34 | BK23: 398995.34 | BL23: 315112.34 | BM23: -94785 | BN23: -10902 | BO23: 272153.34 | BP23: 0.11779021 | BR23: 307861.34 | BS23: 417424.34 | BT23: 326407.34 | BU23: -109563 | BV23: -18546 | BW23: 269737.34 | BX23: 0.1413375 | BZ23: 307861.34 | CA23: 417424.34 | CB23: 307861.34 | CC23: -109563 | CD23: 0 | CE23: 269737.34 | CF23: 0.1413375 | CH23: 307861.34 | CI23: 417424.34 | CJ23: 307861.34 | CK23: -109563 | CL23: 0 | CM23: 269737.34 | CN23: 0.1413375 | CP23: 307861.34 | CQ23: 417424.34 | CR23: 326407.34 | CS23: -109563 | CT23: -18546 | CU23: 263022.34 | CV23: 0.17047601 | CX23: 454864.34 | CY23: 0 | CZ23: 0 | DA23: 365040 | DB23: 251459.34 | DC23: 0.80889817 | DD23: -1 | DE23: -1 | DF23: 0.45168599
B24: Parc Actif Moyen | D24: 251710.84 | E24: 251907.34 | F24: -196.5 | G24: 252698.17 | H24: -0.0039071514 | J24: 252206.84 | K24: 253453.84 | L24: -1247 | M24: 258122.84 | N24: -0.02291932 | P24: 252465.34 | Q24: 261672.84 | R24: -9207.5 | S24: 261194.34 | T24: -0.03341956 | V24: 253060.34 | W24: 279564.84 | X24: 254250.84 | Y24: -26504.5 | Z24: -1190.5 | AA24: 264872.34 | AB24: -0.044595068 | AD24: 258642.34 | AE24: 302926.34 | AF24: 264362.34 | AG24: -44284 | AH24: -5720 | AI24: 267364.84 | AJ24: -0.032623961 | AL24: 269650.34 | AM24: 328993.84 | AN24: 284429.84 | AO24: -59343.5 | AP24: -14779.5 | AQ24: 268924.84 | AR24: 0.0026977798 | AT24: 281618.34 | AU24: 354948.34 | AV24: 286628.84 | AW24: -73330 | AX24: -5010.5 | AY24: 270793.34 | AZ24: 0.039975134 | BB24: 293628.84 | BC24: 375493.34 | BD24: 327120.34 | BE24: -81864.5 | BF24: -33491.5 | BG24: 271948.84 | BH24: 0.079720877 | BJ24: 301944.34 | BK24: 391278.34 | BL24: 307395.34 | BM24: -89334 | BN24: -5451 | BO24: 271948.84 | BP24: 0.11029832 | BR24: 306035.84 | BS24: 408209.84 | BT24: 320759.84 | BU24: -102174 | BV24: -14724 | BW24: 270945.34 | BX24: 0.12951136 | BZ24: 307861.34 | CA24: 417424.34 | CB24: 307861.34 | CC24: -109563 | CD24: 0 | CE24: 269737.34 | CF24: 0.1413375 | CH24: 307861.34 | CI24: 417424.34 | CJ24: 307861.34 | CK24: -109563 | CL24: 0 | CM24: 269737.34 | CN24: 0.1413375 | CP24: 306035.84 | CQ24: 334441.84 | CR24: 257371.34 | CS24: -28406 | CT24: 48664.5 | CU24: 261194.34 | CV24: 0.17167868 | CX24: 353161.84 | CY24: 0 | CZ24: 0 | DA24: 308277 | DB24: 256316.34 | DC24: 0.37783584 | DD24: -1 | DE24: -1 | DF24: 0.20272083
B25: Parc actif localisé | D25: 203255.33 | E25: 203200.12 | F25: 55.214733 | G25: 208760 | H25: -0.026368398 | J25: 202795.33 | K25: 205003.69 | L25: -2208.3553 | M25: 216277 | N25: -0.062335184 | P25: 203570 | Q25: 216310.96 | R25: -12740.959 | S25: 212639.67 | T25: -0.042652751 | V25: 206275 | W25: 233374.96 | X25: 206073.35 | Y25: -27099.959 | Z25: 201.6514 | AA25: 207498 | AB25: -0.0058940327 | AD25: #REF! | AE25: 256529.07 | AF25: 222081.87 | AG25: #REF! | AH25: #REF! | AI25: 210486 | AL25: 219174.67 | AM25: 278133.07 | AN25: 240885.87 | AO25: -58958.405 | AP25: -21711.205 | AQ25: 212214.67 | AR25: 0.032796979 | AT25: 226835 | AU25: 298145.07 | AV25: 241952.27 | AW25: -71310.072 | AX25: -15117.272 | AY25: 218811 | AZ25: 0.036670917 | BB25: 237409 | BC25: 311105.07 | BD25: 243863.47 | BE25: -73696.072 | BF25: -6454.472 | BG25: 218442 | BH25: 0.08682854 | BJ25: 182933 | BK25: 323505.07 | BL25: 263970.67 | BM25: -140572.07 | BN25: -81037.672 | BO25: 218442 | BP25: -0.16255574 | BR25: 245567 | BS25: 338305.07 | BT25: 265063.47 | BU25: -92738.072 | BV25: -19496.472 | BW25: 215600.67 | BX25: 0.13898998 | CC25: 0 | CD25: 0 | CK25: 0 | CL25: 0 | CP25: 245567 | CQ25: 203200.12 | CR25: 265063.47 | CS25: 42366.881 | CT25: -19496.472 | CU25: 212639.67 | CV25: 0.15485038 | CX25: 368385.07 | DA25: 296097.87 | DB25: 208204.3 | DC25: 0.76934425 | DD25: -1 | DE25: -1 | DF25: 0.42215064
B26: Parc internet | D26: 158249 | E26: 160927.47 | F26: -2678.471 | G26: 164229 | H26: -0.03641257 | J26: 158417 | K26: 163618.89 | L26: -5201.8933 | M26: 163886 | N26: -0.033370758 | P26: 152497 | Q26: 172665.43 | R26: -20168.431 | S26: 167668 | T26: -0.090482382 | V26: 152639 | W26: 186404.56 | X26: 164597.83 | Y26: -33765.556 | Z26: -11958.827 | AA26: 180500 | AB26: -0.15435457 | AD26: 156325 | AE26: 205223.26 | AF26: 177665.5 | AG26: -48898.258 | AH26: -21340.498 | AI26: 181750 | AJ26: -0.13988996 | AL26: 160210 | AM26: 224244.79 | AN26: 194214.23 | AO26: -64034.789 | AP26: -34004.234 | AQ26: 182575 | AR26: -0.1224976 | AT26: 168220.5 | AU26: 242242.87 | AV26: 196586.22 | AW26: -74022.371 | AX26: -28365.721 | AY26: 183318 | AZ26: -0.082356888 | BB26: 171743 | BC26: 254717.28 | BD26: 199663.22 | BE26: -82974.278 | BF26: -27920.218 | BG26: 184218 | BH26: -0.067718681 | BJ26: 172008 | BK26: 264869.78 | BL26: 216125.99 | BM26: -92861.778 | BN26: -44117.988 | BO26: 184218 | BP26: -0.066280168 | BR26: 175621 | BS26: 277410.16 | BT26: 217352.05 | BU26: -101789.16 | BV26: -41731.047 | BW26: 184698 | BX26: -0.049145091 | CC26: 0 | CD26: 0 | CK26: 0 | CL26: 0 | CP26: 175621 | CQ26: 160927.47 | CR26: 217352.05 | CS26: 14693.529 | CT26: -41731.047 | CU26: 167668 | CV26: 0.047433022 | CX26: 307141.05 | DA26: 191500 | DB26: 155803 | DC26: 0.97134236 | DD26: -1 | DE26: -1 | DF26: 0.22911626
B27: Parc actif Mobile Money | D27: 0 | F27: 0 | G27: 0 | L27: 0 | P27: 0 | R27: 0 | S27: 0 | Y27: 0 | Z27: 0 | AA27: 0 | AE27: 0 | AF27: 0 | AG27: 0 | AH27: 0 | AO27: 0 | AP27: 0 | AW27: 0 | AX27: 0 | BE27: 0 | BF27: 0 | BM27: 0 | BN27: 0 | BU27: 0 | BV27: 0 | CC27: 0 | CD27: 0 | CK27: 0 | CL27: 0 | CP27: 0 | CQ27: 0 | CR27: 0 | CS27: 0 | CT27: 0 | CU27: 0 | DB27: 0 | DD27: #DIV/0! | DE27: #DIV/0! | DF27: #DIV/0!
B29: Parc Postpayé | Z29: 0 | AH29: 0 | AP29: 0 | AX29: 0 | BF29: 0 | BN29: 0 | BV29: 0 | CD29: 0 | CL29: 0
B30: Parc début Période | D30: 4775 | E30: 4775 | F30: 0 | G30: 4397 | H30: 0.085967705 | J30: 4780 | K30: 4860 | L30: -80 | M30: 4448 | N30: 0.074640288 | P30: 4776 | Q30: 4946 | R30: -170 | S30: 4484 | T30: 0.065120428 | V30: 4773 | W30: 5018 | X30: 4773 | Y30: -245 | Z30: 0 | AA30: 4501 | AB30: 0.060431015 | AD30: 4775 | AE30: 5075 | AF30: 4830 | AG30: -300 | AH30: -55 | AI30: 4645 | AJ30: 0.027987083 | AL30: 4777 | AM30: 5145 | AN30: 4900 | AO30: -368 | AP30: -123 | AQ30: 4711 | AR30: 0.014009764 | AT30: 4779 | AU30: 5195 | AV30: 4779 | AW30: -416 | AX30: 0 | AY30: 4725 | AZ30: 0.011428571 | BB30: 4782 | BC30: 5256 | BD30: 5256 | BE30: -474 | BF30: -474 | BG30: 4741 | BH30: 0.0086479646 | BJ30: 4785 | BK30: 5320 | BL30: 4785 | BM30: -535 | BN30: 0 | BO30: 4741 | BP30: 0.0092807425 | BR30: 4787 | BS30: 5386 | BT30: 4787 | BU30: -599 | BV30: 0 | BW30: 4750 | BX30: 0.0077894737 | BZ30: 4789 | CA30: 5457 | CB30: 4789 | CC30: -668 | CD30: 0 | CE30: 4757 | CF30: 0.0067269287 | CH30: 4789 | CI30: 5457 | CJ30: 4789 | CK30: -668 | CL30: 0 | CM30: 4757 | CN30: 0.0067269287 | CP30: 4787 | CQ30: 4775 | CR30: 4785 | CS30: 12 | CT30: 2 | CU30: 4484 | CV30: 0.067573595 | CX30: 4775 | DA30: 4720 | DB30: 4763 | DC30: 0.0025194205 | DD30: -1 | DE30: -1 | DF30: -0.0090279236
B31: Activations totales | D31: 107 | E31: 150 | F31: -43 | G31: 145 | H31: -0.26206897 | J31: 5 | K31: 152 | L31: -147 | M31: 132 | N31: -0.96212121 | P31: 5 | Q31: 138 | R31: -133 | S31: 142 | T31: -0.96478873 | V31: 8 | W31: 125 | X31: 125 | Y31: -117 | Z31: -117 | AA31: 190 | AB31: -0.95789474 | AD31: 9 | AE31: 137 | AF31: 137 | AG31: -128 | AH31: -128 | AI31: 175 | AJ31: -0.94857143 | AL31: 11 | AM31: 118 | AN31: 118 | AO31: -107 | AP31: -107 | AQ31: 98 | AR31: -0.8877551 | AT31: 13 | AU31: 128 | AV31: 128 | AW31: -115 | AX31: -115 | AY31: 103 | AZ31: -0.87378641 | BB31: 14 | BC31: 132 | BE31: -118 | BF31: 14 | BG31: 77 | BH31: -0.81818182 | BJ31: 12 | BK31: 135 | BL31: 135 | BM31: -123 | BN31: -123 | BO31: 77 | BP31: -0.84415584 | BR31: 13 | BS31: 139 | BT31: 139 | BU31: -126 | BV31: -126 | BW31: 68 | BX31: -0.80882353 | CC31: 0 | CD31: 0 | CK31: 0 | CL31: 0 | CP31: 197 | CQ31: 1354 | CR31: 899 | CS31: -1157 | CT31: -702 | CU31: 1207 | CV31: -0.83678542 | CX31: 1647 | DA31: 856 | DB31: 1312 | DC31: 0.25533537 | DD31: -1 | DE31: -1 | DF31: -0.34756098
B32: Résiliations totales | D32: 102 | E32: 65 | F32: 37 | G32: 94 | H32: 0.085106383 | J32: 9 | K32: 66 | L32: -57 | M32: 96 | N32: -0.90625 | P32: 8 | Q32: 66 | R32: -58 | S32: 125 | T32: -0.936 | V32: 6 | W32: 68 | X32: 68 | Y32: -62 | Z32: -62 | AA32: 46 | AB32: -0.86956522 | AD32: 7 | AE32: 67 | AF32: 67 | AG32: -60 | AH32: -60 | AI32: 109 | AJ32: -0.93577982 | AL32: 9 | AM32: 68 | AN32: 68 | AO32: -59 | AP32: -59 | AQ32: 84 | AR32: -0.89285714 | AT32: 10 | AU32: 67 | AV32: 67 | AW32: -57 | AX32: -57 | AY32: 87 | AZ32: -0.88505747 | BB32: 11 | BC32: 68 | BD32: 8 | BE32: -57 | BF32: 3 | BG32: 68 | BH32: -0.83823529 | BJ32: 10 | BK32: 69 | BL32: 69 | BM32: -59 | BN32: -59 | BO32: 68 | BP32: -0.85294118 | BR32: 11 | BS32: 68 | BT32: 68 | BU32: -57 | BV32: -57 | BW32: 61 | BX32: -0.81967213 | CC32: 0 | CD32: 0 | CK32: 0 | CL32: 0 | CP32: 183 | CQ32: 672 | CR32: 534 | CS32: -489 | CT32: -351 | CU32: 838 | CV32: -0.78162291 | CX32: 805 | DA32: 494 | DB32: 934 | DC32: -0.13811563 | DD32: -1 | DE32: -1 | DF32: -0.47109208
B33: % résiliation annualisé | D33: -0.25620094 | E33: -0.1619097 | F33: -0.094291238 | G33: -0.25505936 | H33: 0.0044757674 | J33: -0.0226036 | K33: -0.16153375 | L33: 0.13893016 | M33: -0.25794895 | N33: -0.91237181 | P33: -0.020106817 | Q33: -0.1589723 | R33: 0.13886548 | S33: -0.33388982 | T33: -0.93978008 | V33: -0.015081693 | W33: -0.16169623 | X33: -0.16994689 | Y33: 0.14661453 | Z33: 0.1548652 | AA33: -0.12070851 | AB33: -0.87505692 | AD33: -0.01758794 | AE33: 0 | AF33: -0.16526208 | AG33: -0.01758794 | AH33: 0.14767414 | AI33: -0.27960667 | AJ33: -0.93709757 | AL33: -0.0226036 | AM33: -0.15783366 | AN33: -0.16568528 | AO33: 0.13523006 | AP33: 0.14308168 | AQ33: -0.21364985 | AR33: -0.8942026 | AT33: -0.025101977 | AU33: -0.15386087 | AV33: -0.16716914 | AW33: 0.1287589 | AX33: 0.14206717 | AY33: -0.22057891 | AZ33: -0.88619956 | BB33: -0.027594857 | BC33: -0.15626197 | BD33: -0.018278751 | BE33: 0.12866711 | BF33: -0.0093161064 | BG33: -0.17195238 | BH33: -0.83952035 | BJ33: -0.02507313 | BK33: -0.15467962 | BL33: -0.17185554 | BM33: 0.12960649 | BN33: 0.14678241 | BO33: -0.17195238 | BP33: -0.85418561 | BR33: -0.027568922 | BS33: -0.15051185 | BT33: -0.16920684 | BU33: 0.12294293 | BV33: 0.14163792 | BW33: -0.1539918 | BX33: -0.82097149 | BZ33: 0 | CA33: 0 | CB33: 0 | CC33: 0 | CD33: 0 | CE33: 0 | CH33: 0 | CI33: 0 | CJ33: 0 | CK33: 0 | CL33: 0 | CM33: 0 | CP33: -0.45864662 | CQ33: -0.17513683 | CR33: -0.14767189 | CS33: -0.28350979 | CT33: -0.31097473 | CU33: -0.24871081 | CV33: -20.99358 | CX33: -0.15492687 | CY33: #DIV/0! | CZ33: #DIV/0! | DA33: -0.10079576 | DB33: -0.26113091 | DC33: 10.620405 | DF33: -0.61400298
B34: Ventes nettes | D34: 5 | E34: 85 | F34: -80 | G34: 51 | H34: -0.90196078 | J34: -4 | K34: 86 | L34: -90 | M34: 36 | N34: -1.1111111 | P34: -3 | Q34: 72 | R34: -75 | S34: 17 | T34: -1.1764706 | V34: 2 | W34: 57 | X34: 57 | Y34: -55 | Z34: -55 | AA34: 144 | AB34: -0.98611111 | AD34: 2 | AE34: 70 | AF34: 70 | AG34: -68 | AH34: -68 | AI34: 66 | AJ34: -0.96969697 | AL34: 2 | AM34: 50 | AN34: 50 | AO34: -48 | AP34: -48 | AQ34: 14 | AR34: -0.85714286 | AT34: 3 | AU34: 61 | AV34: 61 | AW34: -58 | AX34: -58 | AY34: 16 | AZ34: -0.8125 | BB34: 3 | BC34: 64 | BD34: -8 | BE34: -61 | BF34: 11 | BG34: 9 | BH34: -0.66666667 | BJ34: 2 | BK34: 66 | BL34: 66 | BM34: -64 | BN34: -64 | BO34: 9 | BP34: -0.77777778 | BR34: 2 | BS34: 71 | BT34: 71 | BU34: -69 | BV34: -69 | BW34: 7 | BX34: -0.71428571 | BZ34: 0 | CA34: 0 | CB34: 0 | CC34: 0 | CD34: 0 | CE34: 0 | CH34: 0 | CI34: 0 | CJ34: 0 | CK34: 0 | CL34: 0 | CM34: 0 | CP34: 14 | CQ34: 682 | CR34: 365 | CS34: -668 | CT34: -351 | CU34: 369 | CV34: -0.96205962 | CX34: 842 | CY34: 0 | CZ34: 0 | DA34: 362 | DB34: 378 | DC34: 1.2275132 | DD34: -1 | DE34: -1 | DF34: -0.042328042
B35: Parc Postpayé | D35: 4780 | E35: 4860 | F35: -80 | G35: 4448 | H35: 0.074640288 | J35: 4776 | K35: 4946 | L35: -170 | M35: 4484 | N35: 0.065120428 | P35: 4773 | Q35: 5018 | R35: -245 | S35: 4501 | T35: 0.060431015 | V35: 4775 | W35: 5075 | X35: 4830 | Y35: -300 | Z35: -55 | AA35: 4645 | AB35: 0.027987083 | AD35: 4777 | AE35: 5145 | AF35: 4900 | AG35: -368 | AH35: -123 | AI35: 4711 | AJ35: 0.014009764 | AL35: 4779 | AM35: 5195 | AN35: 4950 | AO35: -416 | AP35: -171 | AQ35: 4725 | AR35: 0.011428571 | AT35: 4782 | AU35: 5256 | AV35: 4840 | AW35: -474 | AX35: -58 | AY35: 4741 | AZ35: 0.0086479646 | BB35: 4785 | BC35: 5320 | BD35: 5248 | BE35: -535 | BF35: -463 | BG35: 4750 | BH35: 0.0073684211 | BJ35: 4787 | BK35: 5386 | BL35: 4851 | BM35: -599 | BN35: -64 | BO35: 4750 | BP35: 0.0077894737 | BR35: 4789 | BS35: 5457 | BT35: 4858 | BU35: -668 | BV35: -69 | BW35: 4757 | BX35: 0.0067269287 | BZ35: 4789 | CA35: 5457 | CB35: 4789 | CC35: -668 | CD35: 0 | CE35: 4757 | CF35: 0.0067269287 | CH35: 4789 | CI35: 5457 | CJ35: 4789 | CK35: -668 | CL35: 0 | CM35: 4757 | CN35: 0.0067269287 | CP35: 4789 | CQ35: 5457 | CR35: 4858 | CS35: -668 | CT35: -69 | CU35: 4501 | CV35: 0.063985781 | CX35: 5617 | CY35: 0 | CZ35: 0 | DA35: 5082 | DB35: 4775 | DC35: 0.17633508 | DD35: -1 | DE35: -1 | DF35: 0.064293194
B36: Parc Moyen Postpayé | D36: 4777.5 | E36: 4817.5 | F36: -40 | G36: 4422.5 | H36: 0.08027134 | J36: 4778 | K36: 4903 | L36: -125 | M36: 4466 | N36: 0.069861173 | P36: 4774.5 | Q36: 4982 | R36: -207.5 | S36: 4492.5 | T36: 0.062771285 | V36: 4774 | W36: 5046.5 | X36: 4801.5 | Y36: -272.5 | Z36: -27.5 | AA36: 4573 | AB36: 0.043953641 | AD36: 4776 | AE36: 5110 | AF36: 4865 | AG36: -334 | AH36: -89 | AI36: 4678 | AJ36: 0.020949124 | AL36: 4778 | AM36: 5170 | AN36: 4925 | AO36: -392 | AP36: -147 | AQ36: 4718 | AR36: 0.012717253 | AT36: 4780.5 | AU36: 5225.5 | AV36: 4809.5 | AW36: -445 | AX36: -29 | AY36: 4733 | AZ36: 0.010035918 | BB36: 4783.5 | BC36: 5222 | BD36: 5252 | BE36: -438.5 | BF36: -468.5 | BG36: 4745.5 | BH36: 0.0080075861 | BJ36: 4786 | BK36: 5353 | BL36: 4818 | BM36: -567 | BN36: -32 | BO36: 4745.5 | BP36: 0.008534401 | BR36: 4788 | BS36: 5421.5 | BT36: 4822.5 | BU36: -633.5 | BV36: -34.5 | BW36: 4753.5 | BX36: 0.00725781 | BZ36: 4789 | CA36: 5457 | CB36: 4789 | CC36: -668 | CD36: 0 | CE36: 4757 | CF36: 0.0067269287 | CH36: 4789 | CI36: 5457 | CJ36: 4789 | CK36: -668 | CL36: 0 | CM36: 4757 | CN36: 0.0067269287 | CP36: 4788 | CQ36: 5116 | CR36: 4821.5 | CS36: -328 | CT36: -33.5 | CU36: 4492.5 | CV36: 0.065776294 | CX36: 5196 | CY36: 0 | CZ36: 0 | DA36: 4901 | DB36: 4769 | DC36: 0.08953659 | DD36: -1 | DE36: -1 | DF36: 0.027678759
DG38: 2.6724945e+09

Sheet CA
B2: Chiffre d'affaires
D4: JANVIER | J4: FEVRIER | P4: MARS | V4: AVRIL | AD4: MAI | AL4: JUIN | AT4: JUILLET | BB4: AOUT | BJ4: SEPTEMBRE | BR4: OCTOBRE | BZ4: NOVEMBRE | CH4: DECEMBRE | CP4: CUMUL | CX4: ANNUEL
B5: ( Montant MFCFA) | D5: 2025 Réel | E5: 2025 Budget | F5: Ecart / Budget | G5: 2024 Réel | H5: Evol % | J5: 2025 Réel | K5: 2025 Budget | L5: Ecart / Budget | M5: 2024 Réel | N5: Evol % | P5: 2025 Réel | Q5: 2025 Budget | R5: Ecart / Budget | S5: 2024 Réel | T5: Evol % | V5: 2025 Réel | W5: 2025 Budget | X5: 2025 Actu 1 | Y5: Ecart / Budget | Z5: Ecart / Actu 1 | AA5: 2024 Réel | AB5: Evol % | AD5: 2025 Réel | AE5: 2025 Budget | AF5: 2025 Actu 1 | AG5: Ecart / Budget | AH5: Ecart / Actu 1 | AI5: 2024 Réel | AJ5: Evol % | AL5: 2025 Réel | AM5: 2025 Budget | AN5: 2025 Actu 1 | AO5: Ecart / Budget | AP5: Ecart / Actu 1 | AQ5: 2024 Réel | AR5: Evol % | AT5: 2025 Réel | AU5: 2025 Budget | AV5: 2025 Actu 2 | AW5: Ecart / Budget | AX5: Ecart / Actu 2 | AY5: 2024 Réel | AZ5: Evol % | BB5: 2025 Réel | BC5: 2025 Budget | BD5: 2025 Actu3 | BE5: Ecart / Budget | BF5: Ecart / Actu 3 | BG5: 2024 Réel | BH5: Evol % | BJ5: 2025 Réel | BK5: 2025 Budget | BL5: 2025 Actu3 | BM5: Ecart / Budget | BN5: Ecart / Actu 3 | BO5: 2024 Réel | BP5: Evol % | BR5: 2025 Réel | BS5: 2025 Budget | BT5: 2025 Actu 3 | BU5: Ecart / Budget | BV5: Ecart / Actu 3 | BW5: 2024 Réel | BX5: Evol % | BZ5: 2025 Réel | CA5: 2025 Budget | CB5: 2025 Actu 3 | CC5: Ecart / Budget | CD5: Ecart / Actu 3 | CE5: 2024 Réel | CF5: Evol % | CH5: 2025 Réel | CI5: 2025 Budget | CJ5: 2025 Actu 3 | CK5: Ecart / Budget | CL5: Ecart / Actu 3 | CM5: 2024 Réel | CN5: Evol % | CP5: 2025 Réel | CQ5: 2025 Budget | CR5: 2025 Actu 3 | CS5: Ecart / Budget | CT5: Ecart / Actu 3 | CU5: 2024 Réel | CV5: Evol % | CX5: 2025 Budget | CY5: 2024 Actu 1 | CZ5: 2024 Actu 2 | DA5: 2025 Actu 3 | DB5: 2024 Réel | DC5: Bud / 2024 (%) | DD5: Actu 1 / 2023 (%) | DE5: Actu 2 / 2023 (%) | DF5: Actu 3 / 2019 (%)
B7: CA Global | D7: 3.6285608e+08 | E7: 3.5669185e+08 | F7: 6164234.3 | G7: 4.029166e+08 | H7: -0.099426324 | J7: 3.1716648e+08 | K7: 3.2553763e+08 | L7: -8371149.5 | M7: 3.2662376e+08 | N7: -0.028954673 | P7: 3.4779065e+08 | Q7: 4.0733975e+08 | R7: -59549100 | S7: 3.7071492e+08 | T7: -0.061837992 | V7: 3.886432e+08 | W7: 4.7545806e+08 | X7: 3.9549e+08 | Y7: -86814858 | Z7: -6846804.5 | AA7: 3.9318629e+08 | AB7: -0.011554549 | AD7: 3.7969038e+08 | AE7: 5.1915384e+08 | AF7: 4.6467864e+08 | AG7: -1.3946345e+08 | AH7: -84988254 | AI7: 3.786904e+08 | AJ7: 0.0026406309 | AL7: 3.5631472e+08 | AM7: 5.6135971e+08 | AN7: 5.7117526e+08 | AO7: -2.0504499e+08 | AP7: -2.1486054e+08 | AQ7: 3.6322803e+08 | AR7: -0.019032983 | AT7: 3.9726618e+08 | AU7: 5.985446e+08 | AV7: 4.2375612e+08 | AW7: -2.0127842e+08 | AX7: -26489944 | AY7: 3.8931613e+08 | AZ7: 0.02042054 | BB7: 3.9608218e+08 | BC7: 6.2103624e+08 | BD7: 3.9999793e+08 | BE7: -2.2495406e+08 | BF7: -3915749 | BG7: 3.7892957e+08 | BH7: 0.045265947 | BJ7: 3.8907851e+08 | BK7: 6.3756647e+08 | BL7: 3.9831703e+08 | BM7: -2.4848796e+08 | BN7: -9238517.4 | BO7: 3.6587225e+08 | BP7: 0.063427215 | BR7: 4.3433758e+08 | BS7: 6.7285925e+08 | BT7: 4.0363699e+08 | BU7: -2.3852166e+08 | BV7: 30700598 | BW7: 3.6389707e+08 | BX7: 0.19357264 | BZ7: 0 | CA7: 0 | CB7: 0 | CC7: 0 | CD7: 0 | CE7: 0 | CH7: 0 | CI7: 0 | CJ7: 0 | CK7: 0 | CL7: 0 | CM7: 0 | CP7: 3.769226e+09 | CQ7: 5.1755474e+09 | CR7: 3.7385254e+09 | CS7: -1.4063214e+09 | CT7: 30700598 | CU7: 3.733375e+09 | CV7: 0.0096028226 | CX7: 6.6367354e+09 | CY7: 0 | CZ7: 0 | DA7: 4.557486e+09 | DB7: 4.4447559e+09 | DC7: 0.49316083 | DD7: -1 | DE7: -1 | DF7: 0.025362485
BL8: 0 | BO8: 0
B9: CA services Mobile | D9: 3.5515608e+08 | E9: 3.4381935e+08 | F9: 11336734 | G9: 3.975065e+08 | H9: -0.10654019 | J9: 3.1166648e+08 | K9: 3.1208013e+08 | L9: -413649.47 | M9: 3.2253376e+08 | N9: -0.033693478 | P9: 3.4346228e+08 | Q9: 3.8613725e+08 | R9: -42674975 | S9: 3.6621492e+08 | T9: -0.062129204 | V9: 3.829932e+08 | W9: 4.1998686e+08 | X9: 3.873188e+08 | Y9: -36993658 | Z9: -4325604.5 | AA9: 3.8868629e+08 | AB9: -0.014647006 | AD9: 3.7639038e+08 | AE9: 4.6052604e+08 | AF9: 4.5105084e+08 | AG9: -84135654 | AH9: -74660454 | AI9: 3.742365e+08 | AJ9: 0.0057554021 | AL9: 3.4953472e+08 | AM9: 5.0261971e+08 | AN9: 5.2943526e+08 | AO9: -1.5308499e+08 | AP9: -1.7990054e+08 | AQ9: 3.573815e+08 | AR9: -0.021956307 | AT9: 3.8976618e+08 | AU9: 5.610016e+08 | AV9: 4.0930362e+08 | AW9: -1.7123542e+08 | AX9: -19537444 | AY9: 3.8311613e+08 | AZ9: 0.017357781 | BB9: 3.8588218e+08 | BC9: 5.8919131e+08 | BD9: 3.9261115e+08 | BE9: -2.0330913e+08 | BF9: -6728969 | BG9: 3.7464957e+08 | BH9: 0.029981633 | BJ9: 3.8157851e+08 | BK9: 6.0855167e+08 | BL9: 3.8811703e+08 | BM9: -2.2697316e+08 | BN9: -6538517.4 | BO9: 3.5967225e+08 | BP9: 0.060906166 | BR9: 4.2703758e+08 | BS9: 6.4264565e+08 | BT9: 3.9343699e+08 | BU9: -2.1560806e+08 | BV9: 33600598 | BW9: 3.5906707e+08 | BX9: 0.18929755 | BZ9: 0 | CA9: 0 | CB9: 0 | CC9: 0 | CD9: 0 | CE9: 0 | CH9: 0 | CI9: 0 | CJ9: 0 | CK9: 0 | CL9: 0 | CM9: 0 | CP9: 3.7034676e+09 | CQ9: 4.8265596e+09 | CR9: 3.669867e+09 | CS9: -1.123092e+09 | CT9: 33600598 | CU9: 3.6830645e+09 | CV9: 0.005539707 | CX9: 6.2200388e+09 | CY9: 0 | CZ9: 0 | DA9: 4.4649276e+09 | DB9: 4.3792454e+09 | DC9: 0.42034489 | DD9: -1 | DE9: -1 | DF9: 0.01956552
BL10: 0 | BO10: 0
B11: CA récurrent | D11: 3.5415608e+08 | E11: 3.4181935e+08 | F11: 12336734 | G11: 3.9643693e+08 | H11: -0.10665215 | J11: 3.1086929e+08 | K11: 3.1008013e+08 | L11: 789161.53 | M11: 3.2168205e+08 | N11: -0.033613189 | P11: 3.4286102e+08 | Q11: 3.8413725e+08 | R11: -41276237 | S11: 3.6538763e+08 | T11: -0.061651285 | V11: 3.819932e+08 | W11: 4.1798686e+08 | X11: 3.863188e+08 | Y11: -35993658 | Z11: -4325604.5 | AA11: 3.8768629e+08 | AB11: -0.014684786 | AD11: 3.757148e+08 | AE11: 4.5852604e+08 | AF11: 4.4905084e+08 | AG11: -82811242 | AH11: -73336041 | AI11: 3.732365e+08 | AJ11: 0.0066400104 | AL11: 3.4884988e+08 | AM11: 5.0061971e+08 | AN11: 5.2743526e+08 | AO11: -1.5176983e+08 | AP11: -1.7858537e+08 | AQ11: 3.5593534e+08 | AR11: -0.019906579 | AT11: 3.8896618e+08 | AU11: 5.590016e+08 | AV11: 4.0730362e+08 | AW11: -1.7003542e+08 | AX11: -18337444 | AY11: 3.821592e+08 | AZ11: 0.017811878 | BB11: 3.8511415e+08 | BC11: 5.8719131e+08 | BD11: 3.9161115e+08 | BE11: -2.0207715e+08 | BF11: -6496994 | BG11: 3.7369264e+08 | BH11: 0.03056391 | BJ11: 3.80813e+08 | BK11: 6.0655167e+08 | BL11: 3.7336051e+08 | BM11: -2.2573867e+08 | BN11: 7452493.4 | BO11: 3.5873044e+08 | BP11: 0.061557536 | BR11: 4.2627208e+08 | BS11: 6.4064565e+08 | BT11: 3.9143699e+08 | BU11: -2.1437357e+08 | BV11: 34835092 | BW11: 3.5815629e+08 | BX11: 0.19018453 | BZ11: 0 | CA11: 0 | CB11: 0 | CC11: 0 | CD11: 0 | CE11: 0 | CH11: 0 | CI11: 0 | CJ11: 0 | CK11: 0 | CL11: 0 | CM11: 0 | CP11: 3.6956097e+09 | CQ11: 4.8065596e+09 | CR11: 3.6607746e+09 | CS11: -1.1109499e+09 | CT11: 34835092 | CU11: 3.6731033e+09 | CV11: 0.0061273397 | CX11: 6.1960388e+09 | CY11: 0 | CZ11: 0 | DA11: 4.4506007e+09 | DB11: 4.3678001e+09 | DC11: 0.41857196 | DD11: -1 | DE11: -1 | DF11: 0.01895704
BL12: 3.5146655e+08 | BO12: 0
B13: CA sortant | D13: 3.4271401e+08 | E13: 3.29278e+08 | F13: 13436005 | G13: 3.8275475e+08 | H13: -0.104612 | J13: 2.9995503e+08 | K13: 2.971768e+08 | L13: 2778225.2 | M13: 3.0980918e+08 | N13: -0.031807153 | P13: 3.3111528e+08 | Q13: 368068600 | R13: -36953317 | S13: 3.5326447e+08 | T13: -0.062698606 | V13: 3.7131454e+08 | W13: 401411752 | X13: 373926952 | Y13: -30097212 | Z13: -2612411.8 | AA13: 3.7583969e+08 | AB13: -0.01204011 | AD13: 3.6329857e+08 | AE13: 4.4138928e+08 | AF13: 4.3538609e+08 | AG13: -78090708 | AH13: -72087516 | AI13: 3.6132845e+08 | AJ13: 0.0054524616 | AL13: 3.3689792e+08 | AM13: 4.8289302e+08 | AN13: 5.1307895e+08 | AO13: -1.459951e+08 | AP13: -1.7618103e+08 | AQ13: 3.4321321e+08 | AR13: -0.018400466 | AT13: 3.7698958e+08 | AU13: 5.4065501e+08 | AV13: 3.9357848e+08 | AW13: -1.6366542e+08 | AX13: -16588891 | AY13: 3.7009559e+08 | AZ13: 0.018627614 | BB13: 3.7190975e+08 | BC13: 5.6655155e+08 | BD13: 378603400 | BE13: -1.9464181e+08 | BF13: -6693652.9 | BG13: 3.6188731e+08 | BH13: 0.027694918 | BJ13: 3.6826125e+08 | BK13: 5.8521914e+08 | BL13: 3.7336051e+08 | BM13: -2.1695789e+08 | BN13: -5099256.1 | BO13: 3.4695553e+08 | BP13: 0.061407639 | BR13: 4.1297286e+08 | BS13: 6.1858413e+08 | BT13: 3.7814164e+08 | BU13: -2.0561126e+08 | BV13: 34831221 | BW13: 3.4674022e+08 | BX13: 0.19101517 | BZ13: 0 | CA13: 0 | CB13: 0 | CC13: 0 | CD13: 0 | CE13: 0 | CH13: 0 | CI13: 0 | CJ13: 0 | CK13: 0 | CL13: 0 | CM13: 0 | CP13: 3.5754288e+09 | CQ13: 4.6312273e+09 | CR13: 3.5405976e+09 | CS13: -1.0557985e+09 | CT13: 34831221 | CU13: 3.5518884e+09 | CV13: 0.0066275785 | CX13: 5.9737202e+09 | CY13: 0 | CZ13: 0 | DA13: 4.3019026e+09 | DB13: 4.2240867e+09 | DC13: 0.41420396 | DD13: -1 | DE13: -1 | DF13: 0.01842195
B14: Prépayé (yc commissions) | D14: 3.2212346e+08 | E14: 3.05878e+08 | F14: 16245460 | G14: 3.6985475e+08 | H14: -0.12905413 | J14: 2.7933738e+08 | K14: 2.737768e+08 | L14: 5560580.1 | M14: 2.9752918e+08 | N14: -0.061142888 | P14: 3.1011528e+08 | Q14: 344656600 | R14: -34541317 | S14: 3.4088447e+08 | T14: -0.090262809 | V14: 3.5031454e+08 | W14: 377011752 | X14: 352926952 | Y14: -26697212 | Z14: -2612411.8 | AA14: 3.6404451e+08 | AB14: -0.037715093 | AD14: 3.4299857e+08 | AE14: 4.1381228e+08 | AF14: 4.0851609e+08 | AG14: -70813708 | AH14: -65517516 | AI14: 3.4992845e+08 | AJ14: -0.019803679 | AL14: 3.1659792e+08 | AM14: 4.5513725e+08 | AN14: 4.8603725e+08 | AO14: -1.3853933e+08 | AP14: -1.6943933e+08 | AQ14: 3.3371321e+08 | AR14: -0.051287401 | AT14: 3.5668958e+08 | AU14: 5.1223368e+08 | AV14: 3.7327848e+08 | AW14: -1.5554409e+08 | AX14: -16588891 | AY14: 3.6009559e+08 | AZ14: -0.0094586057 | BB14: 3.5040975e+08 | BC14: 5.3743861e+08 | BD14: 358603400 | BE14: -1.8702886e+08 | BF14: -8193652.9 | BG14: 3.3997497e+08 | BH14: 0.030692785 | BJ14: 3.4726125e+08 | BK14: 5.553873e+08 | BL14: 3.5146655e+08 | BM14: -2.0812605e+08 | BN14: -4205293.6 | BO14: 3.2375553e+08 | BP14: 0.072603301 | BR14: 3.9287286e+08 | BS14: 5.8800481e+08 | BT14: 3.5608103e+08 | BU14: -1.9513195e+08 | BV14: 36791833 | BW14: 3.2464022e+08 | BX14: 0.21017927 | BZ14: 0 | CA14: 0 | CB14: 0 | CC14: 0 | CD14: 0 | CE14: 0 | CH14: 0 | CI14: 0 | CJ14: 0 | CK14: 0 | CL14: 0 | CM14: 0 | CP14: 3.3687206e+09 | CQ14: 4.3633371e+09 | CR14: 3.3319288e+09 | CS14: -9.9461648e+08 | CT14: 36791833 | CU14: 3.4044209e+09 | CV14: -0.010486439 | CX14: 5.6423078e+09 | CY14: 0 | CZ14: 0 | DA14: 4.047712e+09 | DB14: 4.0046177e+09 | DC14: 0.4089504 | DD14: -1 | DE14: -1 | DF14: 0.010761146
B15: dont voix | D15: 82222561 | E15: 77450375 | F15: 4772185.8 | G15: 1.0971993e+08 | H15: -0.25061419 | J15: 76128865 | K15: 66000000 | L15: 10128865 | M15: 1.0772944e+08 | N15: -0.29333275 | P15: 85856478 | Q15: 81029000 | R15: 4827477.7 | S15: 1.0226094e+08 | T15: -0.1604177 | V15: 88000000 | W15: 89000000 | X15: 91000000 | Y15: -1000000 | Z15: -3000000 | AA15: 1.0455777e+08 | AB15: -0.15835999 | AD15: 87700000 | AE15: 96000000 | AF15: 98000000 | AG15: -8300000 | AH15: -10300000 | AI15: 1.0222376e+08 | AJ15: -0.14207816 | AL15: 83747338 | AM15: 101000000 | AN15: 103000000 | AO15: -17252662 | AP15: -19252662 | AQ15: 93455764 | AR15: -0.10388258 | AT15: 94678201 | AU15: 106000000 | AV15: 91992915 | AW15: -11321799 | AX15: 2685286.5 | AY15: 1.0044708e+08 | AZ15: -0.057432017 | BB15: 95767645 | BC15: 113000000 | BD15: 95700000 | BE15: -17232355 | BF15: 67644.538 | BG15: 86177399 | BH15: 0.11128493 | BJ15: 88303361 | BK15: 119000000 | BL15: 97682997 | BM15: -30696639 | BN15: -9379636.1 | BO15: 79334418 | BP15: 0.11305237 | BR15: 96076457 | BS15: 124000000 | BT15: 99636657 | BU15: -27923543 | BV15: -3560200.2 | BW15: 77835997 | BX15: 0.23434478 | CC15: 0 | CD15: 0 | CK15: 0 | CL15: 0 | CP15: 8.7848091e+08 | CQ15: 972479375 | CR15: 8.8204111e+08 | CS15: -93998469 | CT15: -3560200.2 | CU15: 9.637425e+08 | CV15: -0.088469271 | CX15: 1249479375 | DA15: 1.0970365e+09 | DB15: 1.1157659e+09 | DC15: 0.11984004 | DD15: -1 | DE15: -1 | DF15: -0.016786149
B16: CA Internet 2G/3G/4G | D16: 2.0599548e+08 | E16: 1.9642763e+08 | F16: 9567850.7 | G16: 2.3494905e+08 | H16: -0.12323338 | J16: 1.7203059e+08 | K16: 1.753968e+08 | L16: -3366211 | M16: 1.704311e+08 | N16: 0.0093849997 | P16: 2.1038982e+08 | Q16: 230160000 | R16: -19770184 | S16: 2.2140139e+08 | T16: -0.04973578 | V16: 234000000 | W16: 252670000 | X16: 234870000 | Y16: -18670000 | Z16: -870000 | AA16: 2.3754931e+08 | AB16: -0.014941365 | AD16: 230000000 | AE16: 280658000 | AF16: 280658000 | AG16: -50658000 | AH16: -50658000 | AI16: 2.2261312e+08 | AJ16: 0.033182582 | AL16: 2.0735058e+08 | AM16: 307866000 | AN16: 346766000 | AO16: -1.0051542e+08 | AP16: -1.3941542e+08 | AQ16: 2.0891092e+08 | AR16: -0.0074689145 | AT16: 2.3628268e+08 | AU16: 356337000 | AV16: 252747000 | AW16: -1.2005432e+08 | AX16: -16464323 | AY16: 2.3161649e+08 | AZ16: 0.020146191 | BB16: 2.2873477e+08 | BC16: 372580000 | BD16: 238000000 | BE16: -1.4384523e+08 | BF16: -9265231.1 | BG16: 2.2272204e+08 | BH16: 0.02699657 | BJ16: 2.3246327e+08 | BK16: 384212000 | BL16: 2.2660825e+08 | BM16: -1.5174873e+08 | BN16: 5855020.3 | BO16: 2.1026474e+08 | BP16: 0.1055742 | BR16: 2.7217593e+08 | BS16: 409687000 | BT16: 2.2926907e+08 | BU16: -1.3751107e+08 | BV16: 42906858 | BW16: 2.1312868e+08 | BX16: 0.27704975 | CC16: 0 | CD16: 0 | CK16: 0 | CL16: 0 | CP16: 2.2294231e+09 | CQ16: 2.9659944e+09 | CR16: 2.1865163e+09 | CS16: -7.3657132e+08 | CT16: 42906858 | CU16: 2.1735868e+09 | CV16: 0.025688548 | CX16: 3.8537854e+09 | DA16: 2.6322728e+09 | DB16: 2.5649384e+09 | DC16: 0.50248653 | DD16: -1 | DE16: -1
B17: dont BLR | D17: 30090726 | E17: 28000000 | F17: 2090726.4 | G17: 20206769 | H17: 0.48914091 | J17: 28000000 | K17: 28000000 | L17: 0.36134454 | M17: 15326153 | N17: 0.82694256 | P17: 10627069 | Q17: 29000000 | R17: -18372931 | S17: 13816661 | T17: -0.23085115 | V17: 24580000 | W17: 30284800 | X17: 22000000 | Y17: -5704800 | Z17: 2580000 | AA17: 18457932 | AB17: 0.3316768 | AD17: 22000000 | AE17: 31496192 | AF17: 24200000 | AG17: -9496192 | AH17: -2200000 | AI17: 21197838 | AJ17: 0.037841695 | AL17: 21500000 | AM17: 40000000 | AN17: 30000000 | AO17: -18500000 | AP17: -8500000 | AQ17: 27380617 | AR17: -0.21477299 | AT17: 22000000 | AU17: 43000000 | AV17: 24500000 | AW17: -21000000 | AX17: -2500000 | AY17: 23967595 | AZ17: -0.082093984 | BB17: 22000000 | BC17: 44824000 | BD17: 21500000 | BE17: -22824000 | BF17: 500000 | BG17: 27019869 | BH17: -0.18578435 | BJ17: 22000000 | BK17: 45000000 | BL17: 22000000 | BM17: -23000000 | BN17: 0 | BO17: 30365281 | BP17: -0.27548834 | BR17: 20000000 | BS17: 46999000 | BT17: 22000000 | BU17: -26999000 | BV17: -2000000 | BW17: 30365281 | BX17: -0.34135304 | CC17: 0 | CD17: 0 | CK17: 0 | CL17: 0 | CP17: 2.227978e+08 | CQ17: 366603992 | CR17: 2.247978e+08 | CS17: -1.438062e+08 | CT17: -2000000 | CU17: 2.28104e+08 | CV17: -0.023262196 | CX17: 465103992 | DA17: 2.687978e+08 | DB17: 2.7732939e+08 | DC17: 0.67708151 | DD17: -1 | DE17: -1
B18: dont MIHD | F18: 0 | G18: 1311839 | H18: -1 | L18: 0 | M18: 898110 | N18: -1 | R18: 0 | S18: 0 | Y18: 0 | Z18: 0 | AG18: 0 | AH18: 0 | AI18: 0 | AO18: 0 | AP18: 0 | AQ18: 0 | AW18: 0 | AX18: 0 | AY18: 0 | BE18: 0 | BF18: 0 | BG18: 0 | BL18: 0 | BM18: 0 | BN18: 0 | BO18: 0 | BU18: 0 | BV18: 0 | CC18: 0 | CD18: 0 | CK18: 0 | CL18: 0 | CP18: 0 | CQ18: 0 | CR18: 0 | CS18: 0 | CT18: 0 | CU18: 2209949 | CV18: -1 | DB18: 2209949 | DC18: -1 | DD18: -1 | DE18: -1
B19: dont sms | D19: 3814697.5 | E19: 4000000 | F19: -185302.52 | G19: 3667161.3 | H19: 0.0402317 | J19: 3177926.1 | K19: 4380000 | L19: -1202073.9 | M19: 3144380.7 | N19: 0.010668358 | P19: 3241920.5 | Q19: 4467600 | R19: -1225679.5 | S19: 3405482.4 | T19: -0.048028997 | V19: 3734540.2 | W19: 5056952 | X19: 5056952 | Y19: -1322411.8 | Z19: -1322411.8 | AA19: 3479502.5 | AB19: 0.073297172 | AD19: 3298574.9 | AE19: 5658091 | AF19: 5658091 | AG19: -2359516.1 | AH19: -2359516.1 | AI19: 3893721 | AJ19: -0.15284765 | AL19: 4000000 | AM19: 6271252.9 | AN19: 6271252.9 | AO19: -2271252.9 | AP19: -2271252.9 | AQ19: 3965902.8 | AR19: 0.0085975983 | AT19: 3728705.9 | AU19: 6896677.9 | AV19: 4038560.7 | AW19: -3167972 | AX19: -309854.78 | AY19: 4064424.4 | AZ19: -0.08259927 | BB19: 3907333.6 | BC19: 7034611.5 | BD19: 3403400 | BE19: -3127277.9 | BF19: 503933.61 | BG19: 4055663 | BH19: -0.036573406 | BJ19: 4494625.9 | BK19: 7175303.7 | BL19: 5175303.7 | BM19: -2680677.8 | BN19: -680677.84 | BO19: 3791099.2 | BP19: 0.18557328 | BR19: 4620479 | BS19: 7318809.8 | BT19: 5175303.7 | BU19: -2698330.8 | BV19: -554824.71 | BW19: 3310262.2 | BX19: 0.39580454 | CC19: 0 | CD19: 0 | CK19: 0 | CL19: 0 | CP19: 38018804 | CQ19: 58259299 | CR19: 38573628 | CS19: -20240495 | CT19: -554824.71 | CU19: 36777599 | CV19: 0.033748914 | CX19: 73938974 | DA19: 49604913 | DB19: 44374040 | DC19: 0.66626647 | DD19: -1 | DE19: -1
B20: CA Mobile money | F20: 0 | G20: 0 | L20: 0 | R20: 0 | Y20: 0 | Z20: 0 | AG20: 0 | AH20: 0 | AI20: 0 | AO20: 0 | AP20: 0 | AW20: 0 | AX20: 0 | AY20: 0 | BE20: 0 | BF20: 0 | BL20: 16665000 | BM20: 0 | BN20: -16665000 | BO20: 0 | BU20: 0 | BV20: 0 | CC20: 0 | CD20: 0 | CK20: 0 | CL20: 0 | CP20: 0 | CQ20: 0 | CS20: 0 | CT20: 0 | CU20: 0 | DB20: 0
B21: Postpayé | D21: 20590545 | E21: 23400000 | F21: -2809455.3 | G21: 12900000 | H21: 0.59616626 | J21: 20617645 | K21: 23400000 | L21: -2782354.9 | M21: 12280000 | N21: 0.67896133 | P21: 21000000 | Q21: 23412000 | R21: -2412000 | S21: 12380000 | T21: 0.69628433 | V21: 21000000 | W21: 24400000 | X21: 21000000 | Y21: -3400000 | Z21: 0 | AA21: 11795179 | AB21: 0.78038847 | AD21: 20300000 | AE21: 27577000 | AF21: 26870000 | AG21: -7277000 | AH21: -6570000 | AI21: 11400000 | AJ21: 0.78070175 | AL21: 20300000 | AM21: 27755770 | AN21: 27041700 | AO21: -7455770 | AP21: -6741700 | AQ21: 9500000 | AR21: 1.1368421 | AT21: 20300000 | AU21: 28421328 | AV21: 20300000 | AW21: -8121327.7 | AX21: 0 | AY21: 10000000 | AZ21: 1.03 | BB21: 21500000 | BC21: 29112941 | BD21: 20000000 | BE21: -7612941 | BF21: 1500000 | BG21: 21912339 | BH21: -0.018817669 | BJ21: 21000000 | BK21: 29831840 | BL21: 21893962 | BM21: -8831840.4 | BN21: -893962.5 | BO21: 23200000 | BP21: -0.094827586 | BR21: 20100000 | BS21: 30579317 | BT21: 22060612 | BU21: -10479317 | BV21: -1960612.5 | BW21: 22100000 | BX21: -0.090497738 | BZ21: 0 | CA21: 0 | CB21: 0 | CC21: 0 | CD21: 0 | CE21: 0 | CH21: 0 | CI21: 0 | CJ21: 0 | CK21: 0 | CL21: 0 | CM21: 0 | CP21: 2.0670819e+08 | CQ21: 2.678902e+08 | CR21: 2.086688e+08 | CS21: -61182007 | CT21: -1960612.5 | CU21: 1.4746752e+08 | CV21: 0.40172014 | CX21: 3.3141241e+08 | CY21: 0 | CZ21: 0 | DA21: 2.5419062e+08 | DB21: 2.1946898e+08 | DC21: 0.51006492 | DD21: -1 | DE21: -1 | DF21: 0.15820749
B22: dont voix +sms | D22: 13590545 | E22: 17700000 | F22: -4109455.3 | G22: 7200000 | H22: 0.88757566 | J22: 16617645 | K22: 17700000 | L22: -1082354.9 | M22: 6880000 | N22: 1.4153554 | P22: 17000000 | Q22: 17712000 | R22: -712000 | S22: 6380000 | T22: 1.6645768 | V22: 17000000 | W22: 17700000 | X22: 17000000 | Y22: -700000 | Z22: 0 | AA22: 6000000 | AB22: 1.8333333 | AD22: 16500000 | AE22: 17877000 | AF22: 17170000 | AG22: -1377000 | AH22: -670000 | AI22: 5900000 | AJ22: 1.7966102 | AL22: 16500000 | AM22: 18055770 | AN22: 17341700 | AO22: -1555770 | AP22: -841700 | AQ22: 5000000 | AR22: 2.3 | AT22: 16500000 | AU22: 18236328 | AV22: 16500000 | AW22: -1736327.7 | AX22: 0 | AY22: 5200000 | AZ22: 2.1730769 | BB22: 16500000 | BC22: 18418691 | BD22: 16500000 | BE22: -1918691 | BF22: 0 | BG22: 17253731 | BH22: -0.043685102 | BJ22: 16500000 | BK22: 18602878 | BL22: 16665000 | BM22: -2102877.9 | BN22: -165000 | BO22: 18000000 | BP22: -0.083333333 | BR22: 16500000 | BS22: 18788907 | BT22: 16831650 | BU22: -2288906.7 | BV22: -331650 | BW22: 17000000 | BX22: -0.029411765 | CC22: 0 | CD22: 0 | CK22: 0 | CL22: 0 | CP22: 1.6320819e+08 | CQ22: 1.8079157e+08 | CR22: 1.6353984e+08 | CS22: -17583383 | CT22: -331650 | CU22: 94813731 | CV22: 0.72135605 | CX22: 2.1893493e+08 | DA22: 1.9787477e+08 | DB22: 1.5320613e+08 | DC22: 0.42902204 | DD22: -1 | DE22: -1 | DF22: 0.29155913
B23: dont data 3G | D23: 7000000 | E23: 5700000 | F23: 1300000 | G23: 5700000 | H23: 0.22807018 | J23: 4000000 | K23: 5700000 | L23: -1700000 | M23: 5400000 | N23: -0.25925926 | P23: 4000000 | Q23: 5700000 | R23: -1700000 | S23: 6000000 | T23: -0.33333333 | V23: 4000000 | W23: 6700000 | X23: 4000000 | Y23: -2700000 | Z23: 0 | AA23: 5795178.6 | AB23: -0.30977106 | AD23: 3800000 | AE23: 9700000 | AF23: 9700000 | AG23: -5900000 | AH23: -5900000 | AI23: 5500000 | AJ23: -0.30909091 | AL23: 3800000 | AM23: 9700000 | AN23: 9700000 | AO23: -5900000 | AP23: -5900000 | AQ23: 4500000 | AR23: -0.15555556 | AT23: 3800000 | AU23: 10185000 | AV23: 3800000 | AW23: -6385000 | AX23: 0 | AY23: 4800000 | AZ23: -0.20833333 | BB23: 5000000 | BC23: 10694250 | BD23: 3500000 | BE23: -5694250 | BF23: 1500000 | BG23: 4658608.2 | BH23: 0.073281941 | BJ23: 4500000 | BK23: 11228962 | BL23: 5228962.5 | BM23: -6728962.5 | BN23: -728962.5 | BO23: 5200000 | BP23: -0.13461538 | BR23: 3600000 | BS23: 11790411 | BT23: 5228962.5 | BU23: -8190410.6 | BV23: -1628962.5 | BW23: 5100000 | BX23: -0.29411765 | CC23: 0 | CD23: 0 | CK23: 0 | CL23: 0 | CP23: 43500000 | CQ23: 87098623 | CR23: 45128962 | CS23: -43598623 | CT23: -1628962.5 | CU23: 52653787 | CV23: -0.17384859 | CX23: 1.1247748e+08 | DA23: 56315850 | DB23: 66262857 | DC23: 0.69744389 | DD23: -1 | DE23: -1 | DF23: -0.15011437
B24: CA Internet EDGE | F24: 0 | G24: 0 | L24: 0 | R24: 0 | Y24: 0 | Z24: 0 | AG24: 0 | AH24: 0 | AO24: 0 | AP24: 0 | AT24: 0 | AW24: 0 | AX24: 0 | AY24: 0 | BE24: 0 | BF24: 0 | BL24: 10453221 | BM24: 0 | BN24: -10453221 | BO24: 0 | BU24: 0 | BV24: 0 | CC24: 0 | CD24: 0 | CK24: 0 | CL24: 0 | CP24: 0 | CQ24: 0 | CS24: 0 | CT24: 0 | CU24: 0 | DB24: 0
BL25: 323295.5 | BO25: 0
B26: CA entrant | D26: 10242073 | E26: 10561344 | F26: -319270.75 | G26: 11302184 | H26: -0.093796994 | J26: 9714261.8 | K26: 10923325 | L26: -1209063.7 | M26: 9492873.3 | N26: 0.02332155 | P26: 10545732 | Q26: 14088652 | R26: -3542919.8 | S26: 9743159 | T26: 0.082372965 | V26: 9478658.1 | W26: 14595104 | X26: 11191851 | Y26: -5116446.3 | Z26: -1713192.7 | AA26: 9466597.2 | AB26: 0.0012740452 | AD26: 11216222 | AE26: 15156755 | AF26: 11684747 | AG26: -3940533.4 | AH26: -468524.8 | AI26: 9928057 | AJ26: 0.12974994 | AL26: 10751961 | AM26: 15746690 | AN26: 12376305 | AO26: -4994728.7 | AP26: -1624344.1 | AQ26: 10742133 | AR26: 0.0009149119 | AT26: 10776591 | AU26: 16366594 | AV26: 11745144 | AW26: -5590003.2 | AX26: -968552.77 | AY26: 10083616 | AZ26: 0.068722892 | BB26: 12004405 | BC26: 18659754 | BD26: 11807746 | BE26: -6655349.6 | BF26: 196658.95 | BG26: 9825335.8 | BH26: 0.2217806 | BJ26: 11351750 | BK26: 19352524 | BL26: 2387700 | BM26: -8000774.6 | BN26: 8964049.5 | BO26: 9794907.8 | BP26: 0.15894399 | BR26: 12099214 | BS26: 20081520 | BT26: 11315343 | BU26: -7982306.1 | BV26: 783870.87 | BW26: 9436070.6 | BX26: 0.28223008 | BZ26: 0 | CA26: 0 | CB26: 0 | CC26: 0 | CD26: 0 | CE26: 0 | CH26: 0 | CI26: 0 | CJ26: 0 | CK26: 0 | CL26: 0 | CM26: 0 | CP26: 1.0818087e+08 | CQ26: 1.5553226e+08 | CR26: 1.07397e+08 | CS26: -64740113 | CT26: 1567741.7 | CU26: 99814934 | CV26: 0.083814442 | CX26: 1.9855859e+08 | CY26: 0 | CZ26: 0 | DA26: 1.3117804e+08 | DB26: 1.1835339e+08 | DC26: 0.67767557 | DD26: -1 | DE26: -1 | DF26: 0.10835892
B27: Prépayé | D27: 9934810.9 | E27: 10244504 | F27: -309692.63 | G27: 10963118 | H27: -0.093796994 | J27: 9422834 | K27: 10595626 | L27: -1172791.8 | M27: 9208087.1 | N27: 0.02332155 | P27: 10229360 | Q27: 13665992 | R27: -3436632.2 | S27: 9450864.2 | T27: 0.082372965 | V27: 9194298.4 | W27: 14157251 | X27: 10856095 | Y27: -4962952.9 | Z27: -1661797 | AA27: 9182599.3 | AB27: 0.0012740452 | AD27: 10879735 | AE27: 14702053 | AF27: 11334204 | AG27: -3822317.4 | AH27: -454469.06 | AI27: 9630215.3 | AJ27: 0.12974994 | AL27: 10429402 | AM27: 15274289 | AN27: 12005016 | AO27: -4844886.9 | AP27: -1575613.8 | AQ27: 10419869 | AR27: 0.0009149119 | AT27: 10453293 | AU27: 15875596 | AV27: 11392790 | AW27: -5422303.1 | AX27: -939496.19 | AY27: 9781107.3 | AZ27: 0.068722892 | BB27: 11644273 | BC27: 18099962 | BD27: 11453513 | BE27: -6455689.1 | BF27: 190759.18 | BG27: 9530575.7 | BH27: 0.2217806 | BJ27: 11011197 | BK27: 18771948 | BL27: 2316069 | BM27: -7760751.3 | BN27: 8695128 | BO27: 9501060.6 | BP27: 0.15894399 | BR27: 11736237 | BS27: 19479074 | BT27: 10975882 | BU27: -7742836.9 | BV27: 760354.75 | BW27: 9152988.5 | BX27: 0.28223008 | BZ27: 0 | CA27: 0 | CB27: 0 | CC27: 0 | CD27: 0 | CE27: 0 | CH27: 0 | CI27: 0 | CJ27: 0 | CK27: 0 | CL27: 0 | CM27: 0 | CP27: 1.0493544e+08 | CQ27: 1.5086629e+08 | CR27: 1.0417509e+08 | CS27: -45930854 | CT27: 760354.75 | CU27: 96820486 | CV27: 0.083814442 | CX27: 1.9260184e+08 | DA27: 1.272427e+08 | DB27: 1.1480279e+08 | DC27: 0.67767557 | DD27: -1 | DE27: -1 | DF27: 0.10835892
B28: Postpayé | D28: 307262.19 | E28: 316840.32 | F28: -9578.1226 | G28: 339065.52 | H28: -0.093796994 | J28: 291427.85 | K28: 327699.76 | L28: -36271.91 | M28: 284786.2 | N28: 0.02332155 | P28: 316371.96 | Q28: 422659.55 | R28: -106287.59 | S28: 292294.77 | T28: 0.082372965 | V28: 284359.74 | W28: 437853.13 | X28: 335755.53 | Y28: -153493.39 | Z28: -51395.782 | AA28: 283997.92 | AB28: 0.0012740452 | AD28: 336486.65 | AE28: 454702.66 | AF28: 350542.4 | AG28: -118216 | AH28: -14055.744 | AI28: 297841.71 | AJ28: 0.12974994 | AL28: 322558.83 | AM28: 472400.7 | AN28: 371289.16 | AO28: -149841.86 | AQ28: 322263.99 | AR28: 0.0009149119 | AT28: 323297.73 | AU28: 490997.83 | AV28: 352354.31 | AW28: -167700.1 | AX28: -29056.583 | AY28: 302508.47 | AZ28: 0.068722892 | BB28: 360132.14 | BC28: 559792.63 | BD28: 354232.37 | BE28: -199660.49 | BF28: 5899.7684 | BG28: 294760.07 | BH28: 0.2217806 | BJ28: 340552.49 | BK28: 580575.72 | BL28: 71631 | BM28: -240023.24 | BN28: 268921.49 | BO28: 293847.23 | BP28: 0.15894399 | BR28: 362976.41 | BS28: 602445.59 | BT28: 339460.28 | BU28: -239469.18 | BV28: 23516.126 | BW28: 283082.12 | BX28: 0.28223008 | BZ28: 0 | CA28: 0 | CB28: 0 | CC28: 0 | CD28: 0 | CE28: 0 | CH28: 0 | CI28: 0 | CJ28: 0 | CK28: 0 | CL28: 0 | CM28: 0 | CP28: 3245426 | CQ28: 4665967.9 | CR28: 3221909.9 | CS28: -1420541.9 | CT28: 23516.126 | CU28: 2994448 | CV28: 0.083814442 | CX28: 5956757.8 | DA28: 3935341.1 | DB28: 3550601.8 | DC28: 0.67767557 | DD28: -1 | DE28: -1 | DF28: 0.10835892
B29: Telecel | D29: 1597944 | E29: 2055336 | F29: -457392 | G29: 2055336 | H29: -0.2225388 | J29: 1621296 | K29: 2116996.1 | L29: -495700.08 | M29: 869112 | N29: 0.86546268 | P29: 1970772 | Q29: 2963794.5 | R29: -993022.51 | S29: 1198224 | T29: 0.64474422 | V29: 1777812.5 | W29: 3052708.3 | X29: 2562003.6 | Y29: -1274895.9 | Z29: -784191.15 | AA29: 435972 | AB29: 3.0778134 | AD29: 2866452 | AE29: 3174816.7 | AF29: 2690103.8 | AG29: -308364.68 | AH29: 176348.22 | AI29: 564576 | AJ29: 4.0771765 | AL29: 2645448 | AM29: 3301809.3 | AN29: 2824609 | AO29: -656361.35 | AP29: -179160.97 | AQ29: 500280 | AR29: 4.2879348 | AT29: 2849197.1 | AU29: 3433881.7 | AV29: 3160263.3 | AW29: -584684.67 | AX29: -311066.28 | AY29: 482424 | AZ29: 4.9060019 | BB29: 2674000 | BC29: 4292352.2 | BD29: 3050738.9 | BE29: -1618352.2 | BF29: -376738.9 | BG29: 552444 | BH29: 3.8403096 | BJ29: 3559724 | BK29: 4378199.2 | BL29: 2387700 | BM29: -818475.2 | BN29: 1172024 | BO29: 517440 | BP29: 5.8794913 | BR29: 4366400 | BS29: 4465763.2 | BT29: 2507085 | BU29: -99363.18 | BV29: 1859315 | BW29: 670813.68 | BX29: 5.50911 | CC29: 0 | CD29: 0 | CK29: 0 | CL29: 0 | CP29: 25929046 | CQ29: 33235657 | CR29: 24069731 | CS29: -7306611.7 | CT29: 1859315 | CU29: 7846621.7 | CV29: 2.3044852 | CX29: 42436916 | DA29: 31553257 | DB29: 9910921.7 | DC29: 3.2818334 | DD29: -1 | DE29: -1 | DF29: 2.1836855
B30: Orange | D30: 3779568 | E30: 2604027.6 | F30: 1175540.4 | G30: 2040276 | H30: 0.85247878 | J30: 3445980 | K30: 2786309.5 | L30: 659670.47 | M30: 2065236 | N30: 0.66856475 | P30: 3612780 | Q30: 3900833.3 | R30: -288053.34 | S30: 2292756 | T30: 0.5757368 | V30: 3259050.4 | W30: 4173891.7 | X30: 3974058 | Y30: -914841.28 | Z30: -715007.6 | AA30: 2274480 | AB30: 0.43287714 | AD30: 4011132 | AE30: 4466064.1 | AF30: 4106064.1 | AG30: -454932.1 | AH30: -94932.096 | AI30: 2534652 | AJ30: 0.58251784 | AL30: 3825840 | AM30: 4778688.6 | AN30: 4418688.6 | AO30: -952848.58 | AP30: -592848.58 | AQ30: 2404572 | AR30: 0.59106901 | AT30: 4054340.5 | AU30: 5113196.8 | AV30: 4088688.6 | AW30: -1058856.3 | AX30: -34348.127 | AY30: 2964288 | AZ30: 0.36772826 | BB30: 4387016 | BC30: 6391496 | BD30: 4233491.7 | BE30: -2004480 | BF30: 153524.32 | BG30: 2799396 | BH30: 0.56712948 | BJ30: 3960780 | BK30: 6838900.7 | BL30: 4081366.8 | BM30: -2878120.7 | BN30: -120586.8 | BO30: 2881848 | BP30: 0.37438893 | BR30: 3952440 | BS30: 7317623.7 | BT30: 4285435.1 | BU30: -3365183.7 | BV30: -332995.14 | BW30: 2836752.2 | BX30: 0.39329757 | CC30: 0 | CD30: 0 | CK30: 0 | CL30: 0 | CP30: 38288927 | CQ30: 48371032 | CR30: 38621922 | CS30: -10082105 | CT30: -332995.14 | CU30: 25094256 | CV30: -0.10565042 | CX30: 64578837 | DA30: 44707858 | DB30: 31446984 | DC30: 1.0535781 | DD30: -1 | DE30: -1 | DF30: 0.42168983
B31: Socatel | F31: 0 | L31: 0 | R31: 0 | AW31: 0 | AX31: 0 | BL31: 0 | BM31: 0 | BN31: 0 | BO31: 0 | BU31: 0 | BV31: 0 | CK31: 0 | CL31: 0 | CR31: 0
B32: International | D32: 4864561.1 | E32: 5901980.3 | F32: -1037419.2 | G32: 7206572 | H32: -0.32498265 | J32: 4646985.8 | K32: 6020019.9 | L32: -1373034.1 | M32: 6558525.3 | N32: -0.29145873 | P32: 4962179.9 | Q32: 7224023.9 | R32: -2261844 | S32: 6252179 | T32: -0.20632792 | V32: 4441795.2 | W32: 7368504.3 | X32: 4655789.2 | Y32: -2926709.1 | Z32: -213994 | AA32: 6756145.2 | AB32: -0.3425548 | AD32: 4338637.8 | AE32: 7515874.4 | AF32: 4888578.7 | AG32: -3177236.6 | AH32: -549940.93 | AI32: 6828829 | AJ32: -0.3646586 | AL32: 4280673.1 | AM32: 7666191.9 | AN32: 5133007.6 | AO32: -3385518.8 | AP32: -852334.54 | AQ32: 7837281 | AR32: -0.45380635 | AT32: 3873053.5 | AU32: 7819515.8 | AV32: 4496191.9 | AW32: -3946462.2 | AX32: -623138.37 | AY32: 6636903.8 | AZ32: -0.41643669 | BB32: 4943388.6 | BC32: 7975906.1 | BD32: 4523515.1 | BG32: 6473495.8 | BH32: -0.2363649 | BJ32: 3831245.5 | BK32: 8135424.2 | BL32: 4307450 | BM32: -4304178.7 | BN32: -476204.5 | BO32: 6395619.8 | BP32: -0.4009579 | BR32: 3780373.5 | BS32: 8298132.7 | BT32: 4522822.5 | BU32: -4517759.2 | BV32: -742448.99 | BW32: 5928504.7 | BX32: -0.36233945 | CK32: 0 | CL32: 0 | CP32: 43962894 | CQ32: 73925573 | CR32: 44705343 | CS32: -29962679 | CT32: -742448.99 | CU32: 66874056 | CV32: -0.34260164 | CX32: 91542842 | DA32: 54916923 | DB32: 76995486 | DC32: 0.18893777 | DE32: -1
B33: Colocation | D33: 1200000 | E33: 1980000 | F33: -780000 | G33: 2380000 | H33: -0.49579832 | J33: 1200000 | K33: 1980000 | L33: -780000 | M33: 2380000 | N33: -0.49579832 | P33: 1200000 | Q33: 1980000 | R33: -780000 | S33: 2380000 | T33: -0.49579832 | V33: 1200000 | W33: 1980000 | X33: 1200000 | Y33: -780000 | Z33: 0 | AA33: 2380000 | AB33: -0.49579832 | AD33: 1200000 | AE33: 1980000 | AF33: 1980000 | AG33: -780000 | AH33: -780000 | AI33: 1980000 | AJ33: -0.39393939 | AL33: 1200000 | AM33: 1980000 | AN33: 1980000 | AO33: -780000 | AP33: -780000 | AQ33: 1980000 | AR33: -0.39393939 | AT33: 1200000 | AU33: 1980000 | AV33: 1980000 | AW33: -780000 | AX33: -780000 | AY33: 1980000 | AZ33: -0.39393939 | BB33: 1200000 | BC33: 1980000 | BD33: 1200000 | BE33: -780000 | BF33: 0 | BG33: 1980000 | BH33: -0.39393939 | BJ33: 1200000 | BK33: 1980000 | BL33: 1980000 | BM33: -780000 | BN33: -780000 | BO33: 1980000 | BP33: -0.39393939 | BR33: 1200000 | BS33: 1980000 | BT33: 1980000 | BU33: -780000 | BV33: -780000 | BW33: 1980000 | BX33: -0.39393939 | CC33: 0 | CD33: 0 | CK33: 0 | CL33: 0 | CP33: 12000000 | CQ33: 19800000 | CR33: 12780000 | CS33: -7800000 | CT33: -780000 | CU33: 21400000 | CV33: -0.43925234 | CX33: 23760000 | DA33: 17520000 | DB33: 25360000 | DC33: -0.063091483 | DD33: -1 | DE33: -1 | DF33: -0.30914826
B34: Opérateur national 1 | F34: 0 | G34: 0 | L34: 0 | R34: 0 | Y34: 0 | Z34: 0 | AG34: 0 | AH34: 0 | AO34: 0 | AP34: 0 | AW34: 0 | AX34: 0 | AY34: 0 | BE34: 0 | BF34: 0 | BL34: 0 | BM34: 0 | BN34: 0 | BO34: 0 | BU34: 0 | BV34: 0 | CC34: 0 | CD34: 0 | CK34: 0 | CL34: 0 | CP34: 0 | CQ34: 0 | CS34: 0 | CT34: 0 | CU34: 0 | DB34: 0
B35: Opérateur national 2 | F35: 0 | G35: 0 | L35: 0 | R35: 0 | Y35: 0 | Z35: 0 | AG35: 0 | AH35: 0 | AO35: 0 | AP35: 0 | AW35: 0 | AX35: 0 | AY35: 0 | BE35: 0 | BF35: 0 | BL35: 0 | BM35: 0 | BN35: 0 | BO35: 0 | BU35: 0 | BV35: 0 | CC35: 0 | CD35: 0 | CK35: 0 | CL35: 0 | CP35: 0 | CQ35: 0 | CS35: 0 | CT35: 0 | CU35: 0 | DB35: 0
B36: Opérateur national 3 | F36: 0 | G36: 0 | L36: 0 | R36: 0 | Y36: 0 | Z36: 0 | AG36: 0 | AH36: 0 | AO36: 0 | AP36: 0 | AW36: 0 | AX36: 0 | AY36: 0 | BE36: 0 | BF36: 0 | BL36: 8627592.3 | BM36: 0 | BN36: -8627592.3 | BO36: 0 | BU36: 0 | BV36: 0 | CC36: 0 | CD36: 0 | CK36: 0 | CL36: 0 | CP36: 0 | CQ36: 0 | CS36: 0 | CT36: 0 | CU36: 0 | DB36: 0
AU37: + | BC37: + | BO37: 0
B38: Roaming in | D38: 1000000 | E38: 2000000 | F38: -1000000 | G38: 1069565.9 | H38: -0.065041207 | J38: 797189 | K38: 2000000 | L38: -1202811 | M38: 851714 | N38: -0.064017968 | P38: 601262 | Q38: 2000000 | R38: -1398738 | S38: 827286 | T38: -0.27321144 | V38: 1000000 | W38: 2000000 | X38: 1000000 | Y38: -1000000 | Z38: 0 | AA38: 1000000 | AB38: 0 | AD38: 675587.32 | AE38: 2000000 | AF38: 2000000 | AG38: -1324412.7 | AH38: -1324412.7 | AI38: 1000000 | AJ38: -0.32441268 | AL38: 684836 | AM38: 2000000 | AN38: 2000000 | AO38: -1315164 | AP38: -1315164 | AQ38: 1446159 | AR38: -0.52644488 | AT38: 800000 | AU38: 2000000 | AV38: 2000000 | AW38: -1200000 | AX38: -1200000 | AY38: 956927.35 | AZ38: -0.16399087 | BB38: 768025 | BC38: 2000000 | BD38: 1000000 | BE38: -1231975 | BF38: -231975 | BG38: 956927.35 | BH38: -0.19740511 | BJ38: 765506 | BK38: 2000000 | BL38: 2000000 | BM38: -1234494 | BN38: -1234494 | BO38: 941810 | BP38: -0.18719699 | BR38: 765506 | BS38: 2000000 | BT38: 2000000 | BU38: -1234494 | BV38: -1234494 | BW38: 910775.54 | BX38: -0.15950092 | CC38: 0 | CD38: 0 | CK38: 0 | CL38: 0 | CP38: 7857911.3 | CQ38: 20000000 | CR38: 9092405.3 | CS38: -12142089 | CT38: -1234494 | CU38: 9961165.1 | CV38: -0.21114536 | CX38: 24000000 | DA38: 14326899 | DB38: 11445248 | DC38: 1.0969402 | DD38: -1 | DE38: -1 | DF38: 0.25177714 | DG38: 2.6724945e+09
BL39: 1980000 | BO39: 0 | CM39: +
B40: CA équipement | D40: 7700000 | E40: 12872500 | F40: -5172500 | G40: 5410100 | H40: 0.4232639 | J40: 5500000 | K40: 13457500 | L40: -7957500 | M40: 4090000 | N40: 0.34474328 | P40: 4328375 | Q40: 21202500 | R40: -16874125 | S40: 4500000 | T40: -0.038138889 | V40: 5650000 | W40: 55471200 | X40: 8171200 | Y40: -49821200 | Z40: -2521200 | AA40: 4500000 | AB40: 0.25555556 | AD40: 3300000 | AE40: 58627800 | AF40: 13627800 | AG40: -55327800 | AH40: -10327800 | AI40: 4453900 | AJ40: -0.25907632 | AL40: 6780000 | AM40: 58740000 | AN40: 41740000 | AO40: -51960000 | AP40: -34960000 | AQ40: 5846535.2 | AR40: 0.1596612 | AT40: 7500000 | AU40: 37543000 | AV40: 14452500 | AW40: -30043000 | AX40: -6952500 | AY40: 6200000 | AZ40: 0.20967742 | BB40: 10200000 | BC40: 31844929 | BD40: 7386780 | BE40: -21644929 | BF40: 2813220 | BG40: 4280000 | BH40: 1.3831776 | BJ40: 7500000 | BK40: 29014800 | BL40: 10200000 | BM40: -21514800 | BN40: -2700000 | BO40: 6200000 | BP40: 0.20967742 | BR40: 7300000 | BS40: 30213600 | BT40: 10200000 | BU40: -22913600 | BV40: -2900000 | BW40: 4830000 | BX40: 0.51138716 | BZ40: 0 | CA40: 0 | CB40: 0 | CC40: 0 | CD40: 0 | CE40: 0 | CH40: 0 | CI40: 0 | CJ40: 0 | CK40: 0 | CL40: 0 | CM40: 0 | CP40: 65758375 | CQ40: 3.4898783e+08 | CR40: 68658375 | CS40: -2.8322945e+08 | CT40: -2900000 | CU40: 50310535 | CV40: 0.3070498 | CX40: 4.1669663e+08 | CY40: 0 | CZ40: 0 | DA40: 92558375 | DB40: 65510535 | DC40: 5.3607575 | DD40: -1 | DE40: -1 | DF40: 0.41287771
B41: Vente de SIM | D41: 6000000 | E41: 10872500 | F41: -4872500 | G41: 3410100 | H41: 0.75947919 | J41: 3400000 | K41: 11457500 | L41: -8057500 | M41: 2100000 | N41: 0.61904762 | P41: 2778375 | Q41: 17202500 | R41: -14424125 | S41: 2500000 | T41: 0.11135 | V41: 3200000 | W41: 25471200 | X41: 5171200 | Y41: -22271200 | Z41: -1971200 | AA41: 2600000 | AB41: 0.23076923 | AD41: 2500000 | AE41: 28627800 | AF41: 10627800 | AG41: -26127800 | AH41: -8127800 | AI41: 2953900 | AJ41: -0.15366126 | AL41: 4200000 | AM41: 28740000 | AN41: 19740000 | AO41: -24540000 | AP41: -15540000 | AQ41: 4646535.2 | AR41: -0.096100682 | AT41: 4500000 | AU41: 27543000 | AV41: 10452500 | AW41: -23043000 | AX41: -5952500 | AY41: 4800000 | AZ41: -0.0625 | BB41: 6300000 | BC41: 23021400 | BD41: 4504200 | BE41: -16721400 | BF41: 1795800 | BG41: 2880000 | BH41: 1.1875 | BJ41: 4100000 | BK41: 23014800 | BL41: 6300000 | BM41: -18914800 | BN41: -2200000 | BO41: 4800000 | BP41: -0.14583333 | BR41: 4500000 | BS41: 24213600 | BT41: 6300000 | BU41: -19713600 | BV41: -1800000 | BW41: 2830000 | BX41: 0.59010601 | CC41: 0 | CD41: 0 | CK41: 0 | CL41: 0 | CP41: 41478375 | CQ41: 220164300 | CR41: 43278375 | CS41: -178685925 | CU41: 33520535 | CV41: 0.23740193 | CX41: 269873100 | DA41: 58078375 | DB41: 44820535 | DC41: 5.0211932 | DD41: -1 | DE41: -1 | DF41: 0.29579834
B42: Terminaux | D42: 1700000 | E42: 2000000 | F42: -300000 | G42: 2000000 | H42: -0.15 | J42: 2100000 | K42: 2000000 | L42: 100000 | M42: 1990000 | N42: 0.055276382 | P42: 1550000 | Q42: 4000000 | R42: -2450000 | S42: 2000000 | T42: -0.225 | V42: 2450000 | W42: 30000000 | X42: 3000000 | Y42: -27550000 | Z42: -550000 | AA42: 1900000 | AB42: 0.28947368 | AD42: 800000 | AE42: 30000000 | AF42: 3000000 | AG42: -29200000 | AH42: -2200000 | AI42: 1500000 | AJ42: -0.46666667 | AL42: 2580000 | AM42: 30000000 | AN42: 22000000 | AO42: -27420000 | AP42: -19420000 | AQ42: 1200000 | AR42: 1.15 | AT42: 3000000 | AU42: 10000000 | AV42: 4000000 | AW42: -7000000 | AX42: -1000000 | AY42: 1400000 | AZ42: 1.1428571 | BB42: 3900000 | BC42: 8823529.4 | BD42: 2882580 | BE42: -4923529.4 | BF42: 1017420 | BG42: 1400000 | BH42: 1.7857143 | BJ42: 3400000 | BK42: 6000000 | BL42: 3900000 | BM42: -2600000 | BN42: -500000 | BO42: 1400000 | BP42: 1.4285714 | BR42: 2800000 | BS42: 6000000 | BT42: 3900000 | BU42: -3200000 | BV42: -1100000 | BW42: 2000000 | BX42: 0.4 | CC42: 0 | CD42: 0 | CK42: 0 | CL42: 0 | CP42: 24280000 | CQ42: 1.2882353e+08 | CR42: 25380000 | CS42: -1.0454353e+08 | CU42: 16790000 | CV42: 0.44609887 | CX42: 1.4682353e+08 | DA42: 34480000 | DB42: 20690000 | DC42: 6.0963523 | DD42: -1 | DE42: -1 | DF42: 0.66650556
B43: Accessoire | F43: 0 | L43: 0 | R43: 0 | Y43: 0 | Z43: 0 | AG43: 0 | AH43: 0 | AW43: 0 | AX43: 0 | AY43: 0 | BE43: 0 | BF43: 0 | BM43: 0 | BN43: 0 | BO43: 0 | BU43: 0 | BV43: 0 | CC43: 0 | CD43: 0 | CK43: 0 | CL43: 0

Sheet MB
D3: JANVIER | J3: FEVRIER | P3: MARS | V3: AVRIL | AD3: MAI | AL3: JUIN | AT3: JUILLET | BB3: AOUT | BJ3: SEPTEMBRE | BR3: OCTOBRE | BZ3: NOVEMBRE | CH3: DECEMBRE | CP3: CUMUL | CX3: ANNUEL
B4: (En Millions FCFA) | D4: 2025 Réel | E4: 2025 Budget | F4: Ecart / Budget | G4: 2024 Réel | H4: Evol % | J4: 2025 Réel | K4: 2025 Budget | L4: Ecart / Budget | M4: 2024 Réel | N4: Evol % | P4: 2025 Réel | Q4: 2025 Budget | R4: Ecart / Budget | S4: 2024 Réel | T4: Evol % | V4: 2025 Réel | W4: 2025 Budget | X4: 2025 Actu 1 | Y4: Ecart / Budget | Z4: Ecart / Actu 1 | AA4: 2024 Réel | AB4: Evol % | AD4: 2025 Réel | AE4: 2025 Budget | AF4: 2025 Actu 1 | AG4: Ecart / Budget | AH4: Ecart / Actu 1 | AI4: 2024 Réel | AJ4: Evol % | AL4: 2025 Réel | AM4: 2025 Budget | AN4: 2025 Actu 1 | AO4: Ecart / Budget | AP4: Ecart / Actu 1 | AQ4: 2024 Réel | AR4: Evol % | AT4: 2025 Réel | AU4: 2025 Budget | AV4: 2025 Actu 2 | AW4: Ecart / Budget | AX4: Ecart / Actu 2 | AY4: 2024 Réel | AZ4: Evol % | BB4: 2025 Réel | BC4: 2025 Budget | BD4: 2025 Actu3 | BE4: Ecart / Budget | BF4: Ecart / Actu 3 | BG4: 2024 Réel | BH4: Evol % | BJ4: 2025 Réel | BK4: 2025 Budget | BL4: 2025 Actu3 | BM4: Ecart / Budget | BN4: Ecart / Actu 3 | BO4: 2024 Réel | BP4: Evol % | BR4: 2025 Réel | BS4: 2025 Budget | BT4: 2024 Actu 3 | BU4: Ecart / Budget | BV4: Ecart / Actu 3 | BW4: 2024 Réel | BX4: Evol % | BZ4: 2025 Réel | CA4: 2025 Budget | CB4: 2025 Actu 3 | CC4: Ecart / Budget | CD4: Ecart / Actu 3 | CE4: 2024 Réel | CF4: Evol % | CH4: 2025 Réel | CI4: 2025 Budget | CJ4: 2025 Actu 3 | CK4: Ecart / Budget | CL4: Ecart / Actu 3 | CM4: 2024 Réel | CN4: Evol % | CP4: 2025 Réel | CQ4: 2025 Budget | CR4: 2025 Actu 3 | CS4: Ecart / Budget | CT4: Ecart / Actu 3 | CU4: 2024 Réel | CV4: Evol % | CX4: 2025 Budget | CY4: 2024 Actu 1 | CZ4: 2024 Actu 2 | DA4: 2025 Actu 3 | DB4: 2024 Réel | DC4: Bud / 2024 (%) | DD4: Actu 1 / 2023 (%) | DE4: Actu 2 / 2023 (%) | DF4: Actu 3 / 2019 (%)
B6: Total Revenu | D6: 3.6285608e+08 | E6: 3.5669185e+08 | F6: 6164234.3 | G6: 4.029166e+08 | H6: -0.099426324 | J6: 3.1716648e+08 | K6: 3.2553763e+08 | L6: -8371149.5 | M6: 3.2662376e+08 | N6: -0.028954673 | P6: 3.4779065e+08 | Q6: 4.0733975e+08 | R6: -59549100 | S6: 3.7071492e+08 | T6: -0.061837992 | V6: 3.886432e+08 | W6: 4.7545806e+08 | X6: 3.9549e+08 | Y6: -86814858 | Z6: -6846804.5 | AA6: 3.9318629e+08 | AB6: -0.011554549 | AD6: 3.7969038e+08 | AE6: 5.1915384e+08 | AF6: 4.6467864e+08 | AG6: -1.3946345e+08 | AH6: -84988254 | AI6: 3.786904e+08 | AJ6: 0.0026406309 | AL6: 3.5631472e+08 | AM6: 5.6135971e+08 | AN6: 5.7117526e+08 | AO6: -2.0504499e+08 | AP6: -2.1486054e+08 | AQ6: 3.6322803e+08 | AR6: -0.019032983 | AT6: 3.9726618e+08 | AU6: 5.985446e+08 | AV6: 4.2375612e+08 | AW6: -2.0127842e+08 | AX6: -26489944 | AY6: 3.8931613e+08 | AZ6: 0.02042054 | BB6: 3.9608218e+08 | BC6: 6.2103624e+08 | BD6: 3.9999793e+08 | BE6: -2.2495406e+08 | BF6: -3915749 | BG6: 3.7892957e+08 | BH6: 0.045265947 | BJ6: 3.8907851e+08 | BK6: 6.3756647e+08 | BL6: 3.9831703e+08 | BM6: -2.4848796e+08 | BN6: -9238517.4 | BO6: 3.6587225e+08 | BP6: 0.063427215 | BR6: 4.3433758e+08 | BS6: 6.7285925e+08 | BT6: 4.0363699e+08 | BU6: -2.3852166e+08 | BV6: 30700598 | BW6: 3.6389707e+08 | BX6: 0.19357264 | BZ6: 0 | CA6: 0 | CB6: 0 | CC6: 0 | CD6: 0 | CE6: 0 | CH6: 0 | CI6: 0 | CJ6: 0 | CK6: 0 | CL6: 0 | CM6: 0 | CP6: 3.769226e+09 | CQ6: 5.1755474e+09 | CR6: 3.7385254e+09 | CS6: -1.4063214e+09 | CT6: 30700598 | CU6: 3.733375e+09 | CV6: 0.0096028226 | CX6: 6.6367354e+09 | CY6: 0 | CZ6: 0 | DA6: 4.557486e+09 | DB6: 4.4447559e+09 | DC6: 0.49316083 | DD6: -1 | DE6: -1 | DF6: 0.025362485
B7: Trafic (mn) | D7: 91847 | E7: 155000 | F7: -63153 | G7: 114191 | H7: -0.19567216 | J7: 88293 | K7: 162750 | L7: -74457 | M7: 84986 | N7: 0.038912291 | P7: 90070 | Q7: 170887.5 | R7: -80817.5 | S7: 99589 | T7: -0.095582845 | V7: 88115 | W7: 176014.12 | X7: 97275.6 | Y7: -87899.125 | Z7: -2.0024559 | AA7: 104631 | AB7: -0.15784997 | AD7: 80415 | AE7: 181294.55 | AF7: 105057.65 | AG7: -100879.55 | AH7: -1.7971388 | AI7: 89608 | AJ7: -0.10259129 | AL7: 84265 | AM7: 184920.44 | AN7: 113462.26 | AO7: -100655.44 | AP7: -1.8371629 | AQ7: 96636 | AR7: -0.12801647 | AT7: 85444.71 | AU7: 188618.85 | AV7: 93796.056 | AW7: -103174.14 | AX7: -1.8281601 | AY7: 98682 | AZ7: -0.13414088 | BB7: 87153.604 | BC7: 192391.23 | BD7: 87153.604 | BE7: -105237.62 | BF7: -1.8281601 | BG7: 95118 | BH7: -0.083731742 | BJ7: 82471 | BK7: 196239.05 | BL7: 94125.893 | BM7: -113768.05 | BN7: -1.7249048 | BO7: 96272 | BP7: -0.14335425 | BR7: 69176 | BS7: 198201.44 | BT7: 101655.96 | BU7: -129025.44 | BV7: -1.5361423 | BW7: 86587.15 | BX7: -0.20108238 | CC7: 0 | CK7: 0 | CP7: 847250.31 | CQ7: 1806317.2 | CR7: 879730.28 | CS7: -959066.86 | CT7: -32479.964 | CU7: 966300.15 | CV7: -0.12320172 | CX7: 2208685.9 | CY7: 0 | DA7: 1130707.1 | DB7: 1160728.1 | DC7: 0.90284514 | DD7: -1 | DE7: -1 | DF7: -0.025863956
B8: Coût unitaire | D8: 106.08321 | E8: 112 | F8: -5.9167855 | G8: 110.49999 | H8: -0.039970796 | J8: 105.61538 | K8: 112 | L8: -6.3846171 | M8: 112.39299 | N8: -0.060302791 | P8: 105.85391 | Q8: 112 | R8: -6.1460864 | S8: 111.30715 | T8: -0.048992708 | V8: 109.27587 | W8: 112 | X8: 112 | Y8: -2.7241332 | Z8: -2.7241332 | AA8: 114.00281 | AB8: -0.041463391 | AD8: 108.66071 | AE8: 112 | AF8: 112 | AG8: -3.3392899 | AH8: -3.3392899 | AI8: 114.01442 | AJ8: -0.046956415 | AL8: 108.98234 | AM8: 112 | AN8: 112 | AO8: -3.0176586 | AP8: -3.0176586 | AQ8: 113.31217 | AR8: -0.038211518 | AT8: 108.66071 | AU8: 112 | AV8: 108.66071 | AW8: -3.3392899 | AX8: 0 | AY8: 111.35339 | AZ8: -0.024181371 | BB8: 108.66071 | BC8: 112 | BD8: 108.66071 | BE8: -3.3392899 | BF8: 0 | BG8: 109.16788 | BH8: -0.0046457405 | BJ8: 108.59678 | BK8: 112 | BL8: 108.66071 | BM8: -3.4032205 | BN8: -0.063930593 | BO8: 109.21695 | BP8: -0.005678316 | BR8: 109.74942 | BS8: 112 | BT8: 108.66071 | BU8: -2.2505818 | BV8: 1.0887081 | BW8: 108.89402 | BX8: 0.0078553319 | CC8: 0 | CD8: 0 | CP8: 107.94418 | CQ8: 112 | CR8: 107.88503 | CS8: -4.0558168 | CT8: 0.059154158 | CU8: 111.42038 | CV8: -0.031198949 | CX8: 112 | CY8: 68.912786 | DA8: 117.01606 | DB8: 111.36894 | DC8: 0.005666375 | DD8: -0.38122079 | DE8: #VALUE! | DF8: 0.050706409
B9: International | D9: 9743425 | E9: 17360000 | F9: -7616575 | G9: 12618104 | H9: -0.22782179 | J9: 9325099 | K9: 18228000 | L9: -8902901 | M9: 9551831 | N9: -0.02373702 | P9: 9534262 | Q9: 19139400 | R9: -9605138 | S9: 11084968 | T9: -0.13989269 | V9: 9628843 | W9: 19713582 | X9: 10894867 | Y9: -10084739 | Z9: -1266024.2 | AA9: 11928228 | AB9: -0.19276836 | AD9: 8737951 | AE9: 20304989 | AF9: 11766457 | AG9: -11567038 | AH9: -3028505.6 | AI9: 10216604 | AJ9: -0.14473038 | AL9: 9183397 | AM9: 20711089 | AN9: 12707773 | AO9: -11527692 | AP9: -3524376.1 | AQ9: 10950035 | AR9: -0.16133629 | AT9: 9284482.9 | AU9: 21125311 | AV9: 10191946 | AW9: -11840828 | AX9: -907463.19 | AY9: 10988575 | AZ9: -0.15507854 | BB9: 9470172.5 | BC9: 21547817 | BD9: 9470172.5 | BE9: -12077645 | BF9: 0 | BG9: 10383830 | BH9: -0.087988486 | BJ9: 8956085 | BK9: 21978774 | BL9: 10227786 | BM9: -13022689 | BN9: -1271701.3 | BO9: 10514534 | BP9: -0.14821855 | BR9: 7592025.8 | BS9: 22198561 | BT9: 11046009 | BU9: -14606536 | BV9: -3453983.5 | BW9: 9428822.8 | BX9: -0.19480661 | CC9: 0 | CD9: 0 | CK9: 0 | CL9: 0 | CP9: 91455743 | CQ9: 2.0230752e+08 | CR9: 94909727 | CS9: -1.1085178e+08 | CT9: -3453983.5 | CU9: 1.0766553e+08 | CV9: -0.1505569 | CX9: 2.4737282e+08 | DA9: 1.3231089e+08 | DB9: 1.2926907e+08 | DC9: 0.91362738 | DD9: -1 | DE9: -1 | DF9: 0.023530985
B10: Trafic (mn) | D10: 39132 | E10: 222250 | F10: -183118 | G10: 793506 | H10: -0.95068468 | J10: 130647 | K10: 226692.5 | L10: -96045.5 | M10: 641952 | N10: -0.79648478 | P10: 448198 | Q10: 233493.27 | R10: 214704.73 | S10: 657729 | T10: -0.31856737 | V10: 581967 | W10: 235431 | X10: 490748.74 | Y10: 346536 | Z10: 0.67938397 | AA10: 474988 | AB10: 0.22522464 | AD10: 691695 | AE10: 236891.78 | AF10: 495165.48 | AG10: 454803.22 | AH10: 0.52086653 | AI10: 124660 | AJ10: 4.5486523 | AL10: 696831 | AM10: 237658.14 | AN10: 499621.97 | AO10: 459172.86 | AP10: 0.51757881 | AQ10: 99824 | AR10: 5.9805958 | AT10: 239017.52 | AU10: 238410.48 | AV10: 575201.57 | AW10: 607.04416 | AX10: 392.73993 | AY10: 38249 | AZ10: 5.2489875 | BB10: 239017.52 | BC10: 238683.79 | BD10: 717875.3 | BE10: 333.73438 | BF10: 715.19089 | BG10: 36603 | BH10: 5.5299981 | BJ10: 645975 | BK10: 239017.52 | BL10: 563057.36 | BM10: 406957.48 | BN10: 0.587328 | BO10: 37426 | BP10: 16.26006 | BR10: 1096384 | BS10: 241815.68 | BT10: 568124.87 | BU10: 854568.32 | BV10: 0.28296822 | BW10: 33395.19 | BX10: 31.830596 | CC10: 0 | CK10: 0 | CP10: 4808864 | CQ10: 2350344.2 | CR10: 4280604.9 | CS10: 2458519.9 | CT10: 528259.13 | CU10: 2938332.2 | CV10: 0.63659645 | CX10: 2841003.5 | CY10: 0 | CZ10: 0 | DA10: 5898078.5 | DB10: 3012028.2 | DC10: -0.056780588 | DD10: -1 | DE10: -1 | DF10: 0.95817508
B11: Coût unitaire | D11: 10 | E11: 10 | F11: 0 | G11: 10 | H11: 0 | J11: 10 | K11: 10 | L11: 0 | M11: 10 | N11: 0 | P11: 10 | Q11: 10 | R11: 0 | S11: 10 | T11: 0 | V11: 10 | W11: 10 | X11: 10 | Y11: 0 | Z11: 0 | AA11: -832.12654 | AB11: ns | AD11: 10 | AE11: 10 | AF11: 10 | AG11: 0 | AH11: 0 | AI11: 10 | AJ11: 0 | AL11: 10 | AM11: 10 | AN11: 10 | AO11: 0 | AP11: 0 | AQ11: 10 | AR11: 0 | AT11: 10 | AU11: 10 | AV11: 10 | AW11: 0 | AX11: 0 | AY11: 10 | AZ11: 0 | BB11: 10 | BC11: 10 | BD11: 10 | BE11: 0 | BF11: 0 | BG11: 10 | BH11: 0 | BJ11: 10 | BK11: 10 | BL11: 10 | BM11: 0 | BN11: 0 | BO11: 10 | BP11: 0 | BR11: 10 | BS11: 10 | BT11: 10 | BU11: 0 | BV11: 1.7763568e-15 | BW11: 10 | BX11: 2.220446e-16 | BZ11: 10 | CA11: 10 | CB11: 10 | CC11: 0 | CD11: 0 | CE11: 10 | CF11: 0 | CH11: 10 | CI11: 10 | CJ11: 10 | CK11: 0 | CL11: 0 | CM11: 10 | CN11: 0 | CP11: 10 | CQ11: 10 | CR11: 10 | CS11: 0 | CT11: 0 | CU11: -126.13165 | CV11: -1.0792822 | CX11: 10 | CY11: 10 | DA11: 10 | DB11: -122.80088 | DC11: -1.0814326 | DD11: -1.0814326 | DE11: #VALUE! | DF11: -1.0814326
B12: Telecel | D12: 391320 | E12: 2222500 | F12: -1831180 | G12: 7935060 | H12: -0.95068468 | J12: 1306470 | K12: 2266925 | L12: -960455 | M12: 6419520 | N12: -0.79648478 | P12: 4481980 | Q12: 2334932.8 | R12: 2147047.2 | S12: 6577290 | T12: -0.31856737 | V12: 5819670 | W12: 2354310 | X12: 4907487.4 | Y12: 3465360 | Z12: 912182.57 | AA12: -395250120 | AB12: ns | AD12: 6916950 | AE12: 2368917.8 | AF12: 4951654.8 | AG12: 4548032.2 | AH12: 1965295.2 | AI12: 1246600 | AJ12: 4.5486523 | AL12: 6968310 | AM12: 2376581.4 | AN12: 4996219.7 | AO12: 4591728.6 | AP12: 1972090.3 | AQ12: -59001760 | AR12: -1.1181034 | AT12: 2390175.2 | AU12: 2384104.8 | AV12: 5752015.7 | AW12: 6070.4416 | AX12: -3361840.5 | AY12: 382490 | AZ12: 5.2489875 | BB12: 2390175.2 | BC12: 2386837.9 | BD12: 7178753 | BE12: 3337.3438 | BF12: -4788577.7 | BG12: 366030 | BH12: 5.5299981 | BJ12: 6459750 | BK12: 2390175.2 | BL12: 5630573.6 | BM12: 4069574.8 | BN12: 829176.41 | BO12: 60374260 | BP12: -0.8930049 | BR12: 10963840 | BS12: 2418156.8 | BT12: 5681248.7 | BU12: 8545683.2 | BV12: 5282591.3 | BW12: 333951.9 | BX12: 31.830596 | BZ12: 0 | CA12: 0 | CB12: 0 | CC12: 0 | CD12: 0 | CE12: 0 | CH12: 0 | CI12: 0 | CJ12: 0 | CK12: 0 | CL12: 0 | CM12: 0 | CP12: 48088640 | CQ12: 23503442 | CR12: 42806049 | CS12: 24585199 | CT12: 5282591.3 | CU12: -3.7061668e+08 | CV12: -1.129753 | CX12: 28410035 | CY12: 0 | DA12: 58980785 | DB12: -3.6987972e+08 | DC12: -1.0768088 | DD12: -1 | DE12: -1 | DF12: -1.1594594
B13: Trafic (mn) | D13: 1912803 | E13: 2000250 | F13: -87447 | G13: 1494879 | H13: 0.27957045 | J13: 1740409 | K13: 2040232.5 | L13: -299823.5 | M13: 1291670 | N13: 0.34740994 | P13: 1983659 | Q13: 2101439.5 | R13: -117780.48 | S13: 1313275 | T13: 0.51046734 | V13: 1898511 | W13: 2118879 | X13: 1962995 | Y13: -220368.02 | Z13: -9.6151839 | AA13: 1869277 | AB13: 0.015639202 | AD13: 2124861 | AE13: 2132026 | AF13: 1980661.9 | AG13: -7164.9934 | AH13: -297.56147 | AI13: 1960225 | AJ13: 0.083988318 | AL13: 2135940 | AM13: 2138923.3 | AN13: 1998487.9 | AO13: -2983.2664 | AP13: -716.9736 | AQ13: 1752702 | AR13: 0.21865554 | AT13: 2151157.7 | AU13: 2145694.3 | AV13: 2300806.3 | AW13: 5463.3974 | AX13: 392.73993 | AY13: 2038277 | AZ13: 0.055380449 | BB13: 2151157.7 | BC13: 2148154.1 | BD13: 2148154.1 | BE13: 3003.6094 | BF13: 715.19089 | BG13: 1824761 | BH13: 0.17887093 | BJ13: 1674688 | BK13: 2151157.7 | BL13: 2252229.4 | BM13: -476469.69 | BN13: -4.5147839 | BO13: 1901519 | BP13: -0.11928937 | BR13: 2004919 | BS13: 2176341.1 | BT13: 2272499.5 | BU13: -171422.1 | BV13: -12.695802 | BW13: 1758982.8 | BX13: 0.1398173 | CC13: 0 | CK13: 0 | CP13: 19778105 | CQ13: 21153097 | CR13: 20045686 | CS13: -1374992 | CT13: -267580.5 | CU13: 17205568 | CV13: 0.14951774 | CX13: 25569031 | CY13: #DIV/0! | CZ13: #DIV/0! | DA13: 26244057 | DB13: 20993984 | DC13: 0.21792183 | DD13: #DIV/0! | DE13: #DIV/0! | DF13: 0.25007512
B14: Coût unitaire | D14: 10 | E14: 10 | F14: 0 | G14: 10 | H14: 0 | J14: 10 | K14: 10 | L14: 0 | M14: 10 | N14: 0 | P14: 10 | Q14: 10 | R14: 0 | S14: 10 | T14: 0 | V14: 10 | W14: 10 | X14: 10 | Y14: 0 | Z14: 0 | AA14: 10 | AB14: 0 | AD14: 10 | AE14: 10 | AF14: 10 | AG14: 0 | AH14: 0 | AI14: 10 | AJ14: 0 | AL14: 10 | AM14: 10 | AN14: 10 | AO14: 0 | AP14: 0 | AQ14: 10 | AR14: 0 | AT14: 10 | AU14: 10 | AV14: 10 | AW14: 0 | AX14: 0 | AY14: 10 | AZ14: 0 | BB14: 10 | BC14: 10 | BD14: 10 | BE14: 0 | BF14: 0 | BG14: 10 | BH14: 0 | BJ14: 10 | BK14: 10 | BL14: 10 | BM14: 0 | BN14: 0 | BO14: 10 | BP14: 0 | BR14: 10 | BS14: 10 | BT14: 10 | BU14: 0 | BV14: 0 | BW14: 10 | BX14: 0 | BZ14: 10 | CA14: 10 | CB14: 10 | CC14: 0 | CD14: 0 | CE14: 10 | CF14: 0 | CH14: 10 | CI14: 10 | CJ14: 10 | CK14: 0 | CL14: 0 | CM14: 10 | CN14: 0 | CP14: 10 | CQ14: 10 | CR14: 10 | CS14: -1.7763568e-15 | CT14: -1.7763568e-15 | CU14: 10 | CV14: 0 | CX14: 10 | DA14: 10 | DB14: 10 | DC14: 0 | DD14: -1 | DE14: -1 | DF14: 0
B15: Opérateur nationaux (Transit) | BO15: 0
B16: Orange | D16: 19128030 | E16: 20002500 | F16: -874470 | G16: 14948790 | H16: 0.27957045 | J16: 17404090 | K16: 20402325 | L16: -2998235 | M16: 12916700 | N16: 0.34740994 | P16: 19836590 | Q16: 21014395 | R16: -1177804.8 | S16: 13132750 | T16: 0.51046734 | V16: 18985110 | W16: 21188790 | X16: 19629950 | Y16: -2203680.2 | Z16: -644839.7 | AA16: 18692770 | AB16: 0.015639202 | AD16: 21248610 | AE16: 21320260 | AF16: 19806619 | AG16: -71649.935 | AH16: 1441990.7 | AI16: 19602250 | AJ16: 0.083988318 | AL16: 21359400 | AM16: 21389233 | AN16: 19984879 | AO16: -29832.664 | AP16: 1374521.2 | AQ16: 17527020 | AR16: 0.21865554 | AT16: 21511577 | AU16: 21456943 | AV16: 23008063 | AW16: 54633.974 | AX16: -1496486 | AY16: 20382770 | AZ16: 0.055380449 | BB16: 21511577 | BC16: 21481541 | BD16: 21481541 | BE16: 30036.094 | BF16: 30036.094 | BG16: 18247610 | BH16: 0.17887093 | BJ16: 16746880 | BK16: 21511577 | BL16: 22522294 | BM16: -4764696.9 | BN16: -5775414.3 | BO16: 19015190 | BP16: -0.11928937 | BR16: 20049190 | BS16: 21763411 | BT16: 22724995 | BU16: -1714221 | BV16: -2675805 | BW16: 17589828 | BX16: 0.1398173 | BZ16: 0 | CA16: 0 | CB16: 0 | CC16: 0 | CD16: 0 | CE16: 0 | CH16: 0 | CI16: 0 | CJ16: 0 | CK16: 0 | CL16: 0 | CM16: 0 | CP16: 1.9778105e+08 | CQ16: 2.1153097e+08 | CR16: 2.0045686e+08 | CS16: -13749920 | CT16: -2675805 | CU16: 1.7205568e+08 | CV16: 0.14951774 | CX16: 2.5569031e+08 | DA16: 2.6244057e+08 | DB16: 2.0993984e+08 | DC16: 0.21792183 | DD16: -1 | DE16: -1 | DF16: 0.25007512
B17: Nbre SMS | E17: 67064933 | BO17: 0 | CX17: 1.6484325e+09 | DE17: #DIV/0! | DF17: #DIV/0!
B18: Coût unitaire | E18: 67064933 | BO18: 0 | CX18: 1.6484325e+09 | DE18: #DIV/0! | DF18: #DIV/0!
B19: Reversement SVA | D19: 0 | E19: 0 | F19: 0 | G19: 0 | J19: 0 | L19: 0 | M19: 0 | P19: 0 | R19: 0 | S19: 0 | V19: 0 | Y19: 0 | Z19: 0 | AD19: 0 | AG19: 0 | AH19: 0 | AI19: 0 | AL19: 0 | AO19: 0 | AP19: 0 | AQ19: 0 | AT19: 0 | AU19: 0 | AV19: 0 | AW19: 0 | AX19: 0 | AY19: 0 | BB19: 0 | BC19: 0 | BD19: 0 | BE19: 0 | BF19: 0 | BG19: 0 | BJ19: 0 | BK19: 0 | BL19: 0 | BM19: 0 | BN19: 0 | BO19: 0 | BS19: 0 | BT19: 0 | BU19: 0 | BV19: 0 | BW19: 0 | CC19: 0 | CD19: 0 | CK19: 0 | CL19: 0 | CP19: 0 | CQ19: 0 | CR19: 0 | CS19: 0 | CT19: 0 | CU19: 0 | DB19: 0 | DD19: #DIV/0! | DE19: #DIV/0! | DF19: #DIV/0!
B20: Interconnexion SMS | D20: 0 | E20: 258148 | F20: -258148 | G20: 258148 | J20: 0 | K20: 0 | L20: 0 | M20: 208840 | P20: 0 | R20: 0 | S20: 233494 | V20: 0 | AD20: 0 | AG20: 0 | AH20: 0 | AI20: 0 | AL20: 0 | AO20: 0 | AP20: 0 | AQ20: 0 | AT20: 0 | AU20: 310860 | AV20: 310860 | AY20: 0 | BB20: 0 | BC20: 323294.4 | BD20: 0 | BG20: 0 | BJ20: 0 | BK20: 336226.18 | BL20: 0 | BO20: 0 | BR20: 0 | BS20: 349675.22 | BT20: 0 | BU20: 0 | BV20: 0 | BW20: 0 | CP20: 0 | CQ20: 1578203.8 | CR20: 0 | CX20: 2787062.8 | DA20: 2061926.8 | DB20: 933976 | DC20: 1.9840839
B21: Roaming out | D21: 1435540.9 | E21: 1800000 | F21: -364459.09 | G21: 1435540.9 | H21: 0 | J21: 1524917 | K21: 1800000 | L21: -275083 | M21: 1246287 | N21: 0.22356809 | P21: 1567900 | Q21: 1800000 | R21: -232100 | S21: 1654396 | T21: -0.052282525 | V21: 1199975.2 | W21: 1800000 | X21: 1800000 | Y21: -600024.75 | Z21: -600024.75 | AA21: 1329349 | AB21: -0.097321132 | AD21: 1524752 | AE21: 1800000 | AF21: 1800000 | AG21: -275248 | AH21: -275248 | AI21: 2569247.5 | AJ21: -0.40653751 | AL21: 1952365 | AM21: 1800000 | AN21: 1800000 | AO21: 152365 | AP21: 152365 | AQ21: 393388 | AR21: 3.9629501 | AT21: 1952365 | AU21: 1800000 | AV21: 1800000 | AW21: 152365 | AX21: 152365 | AY21: 1773914.8 | AZ21: 0.10059683 | BB21: 1335564 | BC21: 2000000 | BD21: 1400000 | BE21: -664436 | BF21: -64436 | BG21: 2462402 | BH21: -0.4576174 | BJ21: 1385737 | BK21: 2000000 | BL21: 1335564 | BM21: -614263 | BN21: 50173 | BO21: 1131892 | BP21: 0.2242661 | BR21: 1419185 | BS21: 2050000 | BT21: 2050000 | BU21: -630815 | BV21: -630815 | BW21: 1647548 | BX21: -0.1386078 | CC21: 0 | CD21: 0 | CK21: 0 | CL21: 0 | CP21: 15298301 | CQ21: 18650000 | CR21: 15929116 | CS21: -3351698.8 | CT21: -630815 | CU21: 15643965 | CV21: -0.022095679 | CX21: 22840000 | DA21: 21693110 | DB21: 18758185 | DC21: 0.2176018 | DD21: -1 | DE21: -1 | DF21: 0.15646102
B23: Coûts des terminaux et cartes | D23: 3845000 | E23: 6349000 | F23: -2504000 | G23: 2040000 | H23: 0.88480392 | J23: 3145000 | K23: 6583000 | L23: -3438000 | M23: 1941300 | N23: 0.62004842 | P23: 2428850 | Q23: 10281000 | R23: -7852150 | S23: 400000 | T23: 5.072125 | V23: 3362500 | W23: 36113000 | X23: 8663000 | Y23: -32750500 | Z23: -5300500 | AA23: 1653000 | AB23: 1.0341803 | AD23: 1680000 | AE23: 37728250 | AF23: 11978250 | AG23: -36048250 | AH23: -10298250 | AI23: 1305000 | AJ23: 0.28735632 | AL23: 3373000 | AM23: 37475000 | AN23: 29425000 | AO23: -34102000 | AP23: -26052000 | AQ23: 600000 | AR23: 4.6216667 | AT23: 4050000 | AU23: 20276250 | AV23: 13926250 | AW23: -16226250 | AX23: -9876250 | AY23: 700000 | AZ23: 4.7857143 | BB23: 5535000 | BC23: 17302250 | BD23: 4461873 | BE23: -11767250 | BF23: 1073127 | BG23: 700000 | BH23: 6.9071429 | BJ23: 4530000 | BK23: 14899500 | BL23: 16899500 | BM23: -10369500 | BN23: -12369500 | BO23: 700000 | BP23: 5.4714286 | BR23: 4180000 | BS23: 15399000 | BT23: 11205500 | BU23: -11219000 | BV23: -7025500 | BW23: 1000000 | BX23: 3.18 | BZ23: 0 | CA23: 0 | CB23: 0 | CC23: 0 | CD23: 0 | CE23: 0 | CH23: 0 | CI23: 0 | CJ23: 0 | CK23: 0 | CL23: 0 | CM23: 0 | CP23: 36129350 | CQ23: 202406250 | CR23: 43154850 | CS23: -166276900 | CT23: -7025500 | CU23: 11039300 | CV23: 2.2727936 | CX23: 239438250 | CY23: 0 | CZ23: 0 | DA23: 125176950 | DB23: 14549300 | DC23: 15.457029 | DD23: -1 | DE23: -1 | DF23: 7.6036407
B24: Dont coût des cartes de recharge vendues | E24: 300000 | F24: -300000 | G24: 300000 | H24: -1 | K24: 300000 | L24: -300000 | M24: 210000 | N24: -1 | R24: 0 | Y24: 0 | Z24: 0 | AE24: 300000 | AG24: -300000 | AH24: 0 | AL24: 0 | AO24: 0 | AP24: 0 | AQ24: 0 | AT24: 200000 | AU24: 300000 | AV24: 300000 | AW24: -100000 | AX24: -100000 | AY24: 0 | BB24: 200000 | BC24: 210000 | BD24: 210000 | BE24: -10000 | BF24: -10000 | BG24: 0 | BK24: 210000 | BL24: 210000 | BM24: -210000 | BN24: -210000 | BS24: 210000 | BT24: 210000 | BU24: -210000 | BV24: -210000 | CC24: 0 | CD24: 0 | CK24: 0 | CL24: 0 | CP24: 400000 | CQ24: 1830000 | CR24: 610000 | CS24: -1430000 | CT24: -210000 | CU24: 510000 | CV24: -0.21568627 | CX24: 2850000 | DA24: 2550000 | DB24: 510000 | DC24: 4.5882353 | DD24: -1 | DE24: -1 | DF24: 4
B25: Dont coût des SIM | D25: 2400000 | E25: 4349000 | J25: 1360000 | K25: 4583000 | P25: 1111350 | Q25: 6881000 | V25: 1280000 | W25: 10613000 | X25: 6113000 | AD25: 1000000 | AE25: 11928250 | AF25: 9428250 | AL25: 1680000 | AM25: 11975000 | AN25: 10725000 | AT25: 1800000 | AU25: 11476250 | AV25: 10226250 | AW25: -9676250 | AX25: -8426250 | AY25: 0 | BB25: 2520000 | BC25: 9592250 | BD25: 1801680 | BJ25: 1640000 | BK25: 9589500 | BL25: 11589500 | BR25: 1800000 | BS25: 10089000 | BT25: 7680500 | CP25: 16591350 | CQ25: 91076250 | CR25: 22471850 | CS25: -74484900 | CX25: 111788250 | DA25: 74576450
B26: Dont coût des terminaux* | D26: 1445000 | E26: 1700000 | F26: -255000 | G26: 1740000 | H26: -0.16954023 | J26: 1785000 | K26: 1700000 | L26: 85000 | M26: 1731300 | N26: 0.031017155 | P26: 1317500 | Q26: 3400000 | R26: -2082500 | S26: 0 | V26: 2082500 | W26: 25500000 | X26: 2550000 | Y26: -23417500 | Z26: -467500 | AA26: 1653000 | AB26: 0.25983061 | AD26: 680000 | AE26: 25500000 | AF26: 2550000 | AG26: -24820000 | AH26: -1870000 | AI26: 1305000 | AJ26: -0.4789272 | AL26: 1693000 | AM26: 25500000 | AN26: 18700000 | AO26: -23807000 | AP26: -17007000 | AQ26: 600000 | AR26: 1.8216667 | AT26: 2050000 | AU26: 8500000 | AV26: 3400000 | AW26: -6450000 | AX26: -1350000 | AY26: 700000 | AZ26: 1.9285714 | BB26: 2815000 | BC26: 7500000 | BD26: 2450193 | BE26: -4685000 | BF26: 364807 | BG26: 700000 | BH26: 3.0214286 | BJ26: 2890000 | BK26: 5100000 | BL26: 5100000 | BM26: -2210000 | BN26: -2210000 | BO26: 700000 | BP26: 3.1285714 | BR26: 2380000 | BS26: 5100000 | BT26: 3315000 | BU26: -2720000 | BV26: -935000 | BW26: 1000000 | BX26: 1.38 | CC26: 0 | CD26: 0 | CK26: 0 | CL26: 0 | CP26: 19138000 | CQ26: 109500000 | CR26: 20073000 | CS26: -90362000 | CT26: -935000 | CU26: 10129300 | CV26: 0.88937044 | CX26: 124800000 | DA26: 48050500 | DB26: 13639300 | DC26: 8.1500297 | DD26: -1 | DE26: -1 | DF26: 2.5229447
B27: Dont provisions sur stocks | E27: 0 | F27: 0 | G27: 0 | K27: 0 | L27: 0 | M27: 0 | Q27: 0 | R27: 0 | S27: 0 | W27: 0 | X27: 0 | Y27: 0 | Z27: 0 | AA27: 0 | AD27: 0 | AE27: 0 | AF27: 0 | AG27: 0 | AH27: 0 | AI27: 0 | AO27: 0 | AP27: 0 | AQ27: 0 | AY27: 0 | BE27: 0 | BF27: 0 | BM27: 0 | BN27: 0 | BO27: 0 | BU27: 0 | BV27: 0 | CC27: 0 | CD27: 0 | CK27: 0 | CL27: 0 | CP27: 0 | CQ27: 0 | CR27: 0 | CS27: 0 | CT27: 0 | CU27: 0 | CX27: 0 | DB27: 0
B28: Commissions | D28: 39243929 | E28: 37479198 | F28: 1764731.1 | G28: 45016127 | H28: -0.12822513 | J28: 32260486 | K28: 33003969 | L28: -743483.01 | M28: 37461449 | N28: -0.13883507 | P28: 40238586 | Q28: 43025587 | R28: -2787001.3 | S28: 43204036 | T28: -0.068638265 | V28: 43188145 | W28: 48116395 | X28: 44621034 | Y28: -4928250.5 | Z28: -1432889.5 | AA28: 45414966 | AB28: -0.049032764 | AD28: 42619829 | AE28: 53261008 | AF28: 52411504 | AG28: -10641179 | AH28: -9791674.7 | AI28: 44238405 | AJ28: -0.036587581 | AL28: 29111751 | AM28: 58043665 | AN28: 63147976 | AO28: -28931914 | AP28: -34036225 | AQ28: 41679961 | AR28: -0.30154083 | AT28: 42762750 | AU28: 65278933 | AV28: 47328539 | AW28: -22516183 | AX28: -4565789.3 | AY28: 45205409 | AZ28: -0.054034658 | BB28: 43509170 | BC28: 68534478 | BD28: 43170173 | BE28: -25025308 | BF28: 338996.37 | BG28: 43354612 | BH28: 0.0035649648 | BJ28: 56581350 | BK28: 70997806 | BL28: 49228130 | BM28: -14416455 | BN28: 7353220.1 | BO28: 41706828 | BP28: 0.35664479 | BR28: 50344744 | BS28: 75377882 | BT28: 45162464 | BU28: -25033138 | BV28: 5182280.3 | BW28: 41812990 | BX28: 0.20404553 | BZ28: 0 | CA28: 0 | CB28: 0 | CC28: 0 | CD28: 0 | CE28: 0 | CH28: 0 | CI28: 0 | CJ28: 0 | CK28: 0 | CL28: 0 | CM28: 0 | CP28: 4.1986074e+08 | CQ28: 5.5311892e+08 | CR28: 4.1467846e+08 | CS28: -1.3325818e+08 | CT28: 5182280.3 | CU28: 4.2909478e+08 | CV28: -0.021519823 | CX28: 7.1799916e+08 | CY28: 0 | CZ28: 0 | DA28: 5.9864108e+08 | DB28: 5.0821135e+08 | DC28: 0.41279638 | DD28: -1 | DE28: -1 | DF28: 0.17793725
B29: Dont Commission Flooz | F29: 0 | L29: 0 | R29: 0 | Y29: 0 | Z29: 0 | AG29: 0 | AH29: 0 | AO29: 0 | AP29: 0 | AW29: 0 | AX29: 0 | BE29: 0 | BF29: 0 | BM29: 0 | BN29: 0 | BO29: 0 | BU29: 0 | BV29: 0 | CC29: 0 | CD29: 0 | CK29: 0 | CL29: 0 | CP29: 0 | CQ29: 0 | CR29: 0 | CS29: 0 | CT29: 0 | CU29: 0 | DB29: 0
B30: Dont commissions up-front | D30: 32643929 | E30: 30345361 | F30: 2298568.1 | G30: 38016127 | H30: -0.14131368 | J30: 27760486 | K30: 26493216 | L30: 1267269.6 | M30: 30861449 | N30: -0.10048014 | P30: 33538586 | Q30: 34878792 | R30: -1340206.3 | S30: 36304036 | T30: -0.076174728 | V30: 36688145 | W30: 38607234 | X30: 36711234 | Y30: -1919089.4 | Z30: -23089.414 | AA30: 38414966 | AB30: -0.044951785 | AD30: 36119829 | AE30: 42877931 | AF30: 43117931 | AG30: -6758101.9 | AH30: -6998101.9 | AI30: 35738405 | AJ30: 0.010672657 | AL30: 36011751 | AM30: 46816470 | AN30: 51724470 | AO30: -10804720 | AP30: -15712720 | AQ30: 33179961 | AR30: 0.085346397 | AT30: 36262750 | AU30: 53308041 | AV30: 38853417 | AW30: -17045291 | AX30: -2590666.9 | AY30: 36755409 | AZ30: -0.013403709 | BB30: 37009170 | BC30: 56113753 | BD30: 36670173 | BE30: -19104584 | BF30: 338996.37 | BG30: 36354612 | BH30: 0.018004804 | BJ30: 36631350 | BK30: 58246476 | BL30: 40120749 | BM30: -21615126 | BN30: -3489398.8 | BO30: 35206828 | BP30: 0.040461549 | BR30: 42344744 | BS30: 61920697 | BT30: 37089724 | BU30: -19575953 | BV30: 5255020 | BW30: 35312990 | BX30: 0.19912654 | CC30: 0 | CD30: 0 | CK30: 0 | CL30: 0 | CP30: 3.5501074e+08 | CQ30: 4.4960797e+08 | CR30: 3.4975572e+08 | CS30: -94597234 | CT30: 5255020 | CU30: 3.5614478e+08 | CV30: -0.0031842216 | CX30: 5.8526445e+08 | DA30: 4.9617718e+08 | DB30: 4.2226135e+08 | DC30: 0.3860242 | DD30: -1 | DE30: -1 | DF30: 0.17504757
B31: Dont avoirs de performance | D31: 6600000 | E31: 7133837 | F31: -533836.97 | G31: 7000000 | H31: -0.057142857 | J31: 4500000 | K31: 6510752.6 | L31: -2010752.6 | M31: 6600000 | N31: -0.31818182 | P31: 6700000 | Q31: 8146795 | R31: -1446795 | S31: 6900000 | T31: -0.028985507 | V31: 6500000 | W31: 9509161.1 | X31: 7909800.1 | Y31: -3009161.1 | Z31: -1409800.1 | AA31: 7000000 | AB31: -0.071428571 | AD31: 6500000 | AE31: 10383077 | AF31: 9293572.8 | AG31: -3883076.8 | AH31: -2793572.8 | AI31: 8500000 | AJ31: -0.23529412 | AL31: -6900000 | AM31: 11227194 | AN31: 11423505 | AO31: -18127194 | AP31: -18323505 | AQ31: 8500000 | AR31: -1.8117647 | AT31: 6500000 | AU31: 11970892 | AV31: 8475122.4 | AW31: -5470892 | AX31: -1975122.4 | AY31: 8450000 | AZ31: -0.23076923 | BB31: 6500000 | BC31: 12420725 | BD31: 6500000 | BE31: -5920724.7 | BF31: 0 | BG31: 7000000 | BH31: -0.071428571 | BJ31: 19950000 | BK31: 12751329 | BL31: 9107381.1 | BM31: 7198670.6 | BN31: 10842619 | BO31: 6500000 | BP31: 2.0692308 | BR31: 8000000 | BS31: 13457185 | BT31: 8072739.7 | BU31: -5457184.9 | BV31: -72739.732 | BW31: 6500000 | BX31: 0.23076923 | CC31: 0 | CD31: 0 | CK31: 0 | CL31: 0 | CP31: 64850000 | CQ31: 1.0351095e+08 | CR31: 64922740 | CS31: -38660948 | CT31: -72739.732 | CU31: 72950000 | CV31: -0.11103496 | CX31: 1.3273471e+08 | DA31: 1.0246391e+08 | DB31: 85950000 | DC31: 0.5443247 | DD31: -1 | DE31: -1 | DF31: 0.19213386
BO32: 0
B33: Coûts des ventes | D33: 73787245 | E33: 85471346 | F33: -11684101 | G33: 84251770 | H33: -0.12420541 | J33: 64966062 | K33: 82284219 | L33: -17318157 | M33: 69745927 | N33: -0.06853253 | P33: 78088168 | Q33: 97595315 | R33: -19507147 | S33: 76053440 | T33: 0.026753924 | V33: 82184243 | W33: 1.2928608e+08 | X33: 90516339 | Y33: -47101834 | Z33: -8332095.6 | AA33: -3.1623181e+08 | AB33: -1.2598861 | AD33: 82728092 | AE33: 1.3678342e+08 | AF33: 1.0271448e+08 | AG33: -54055333 | AH33: -19986392 | AI33: 79178107 | AJ33: 0.04483544 | AL33: 71948223 | AM33: 1.4179557e+08 | AN33: 1.3206185e+08 | AO33: -69847345 | AP33: -60113624 | AQ33: 12148644 | AR33: 4.9223256 | AT33: 81951350 | AU33: 1.326324e+08 | AV33: 1.0200681e+08 | AW33: -50681052 | AX33: -20055464 | AY33: 79433159 | AZ33: 0.031702018 | BB33: 83751658 | BC33: 1.3325292e+08 | BD33: 87162513 | BE33: -49501266 | BF33: -3410854.3 | BG33: 75514484 | BH33: 0.10908072 | BJ33: 94659802 | BK33: 1.3377783e+08 | BL33: 1.0584385e+08 | BM33: -39118029 | BN33: -11184046 | BO33: 1.334427e+08 | BP33: -0.29063336 | BR33: 94548985 | BS33: 1.3920701e+08 | BT33: 97870216 | BU33: -44658027 | BV33: -3321232 | BW33: 71813141 | BX33: 0.31659727 | BZ33: 0 | CA33: 0 | CB33: 0 | CC33: 0 | CD33: 0 | CE33: 0 | CH33: 0 | CI33: 0 | CJ33: 0 | CK33: 0 | CL33: 0 | CM33: 0 | CP33: 8.0861383e+08 | CQ33: 1.2130953e+09 | CR33: 8.1193506e+08 | CS33: -4.0448149e+08 | CT33: -3321232 | CU33: 3.6488258e+08 | CV33: 1.2160933 | CX33: 1.5145376e+09 | CY33: 0 | CZ33: 0 | DA33: 1.1992434e+09 | DB33: 5.08482e+08 | DC33: 1.9785472 | DD33: -1 | DE33: -1 | DF33: 1.3584776
B35: Marge Brute | D35: 2.8906884e+08 | E35: 2.712205e+08 | F35: 17848335 | G35: 3.1866483e+08 | H35: -0.092874982 | J35: 2.5220042e+08 | K35: 2.4325341e+08 | L35: 8947007.5 | M35: 2.5687784e+08 | N35: -0.018208732 | P35: 2.6970248e+08 | Q35: 3.0974444e+08 | R35: -40041953 | S35: 2.9466148e+08 | T35: -0.08470396 | V35: 3.0645896e+08 | W35: 3.4617198e+08 | X35: 3.0497366e+08 | Y35: -39713024 | Z35: 1485291 | AA35: 7.094181e+08 | AB35: -0.56801362 | AD35: 2.9696229e+08 | AE35: 3.8237041e+08 | AF35: 3.6196415e+08 | AG35: -85408121 | AH35: -65001861 | AI35: 2.995123e+08 | AJ35: -0.0085138531 | AL35: 2.843665e+08 | AM35: 4.1956414e+08 | AN35: 4.3911341e+08 | AO35: -1.3519765e+08 | AP35: -1.5474691e+08 | AQ35: 3.5107939e+08 | AR35: -0.19002224 | AT35: 3.1531483e+08 | AU35: 4.659122e+08 | AV35: 3.2174931e+08 | AW35: -1.5059737e+08 | AX35: -6434479.7 | AY35: 3.0988297e+08 | AZ35: 0.017528728 | BB35: 3.1233052e+08 | BC35: 4.8778331e+08 | BD35: 3.1283541e+08 | BE35: -1.7545279e+08 | BF35: -504894.71 | BG35: 3.0341509e+08 | BH35: 0.029383613 | BJ35: 2.9441871e+08 | BK35: 5.0378864e+08 | BL35: 2.9247318e+08 | BM35: -2.0936993e+08 | BN35: 1945528.7 | BO35: 2.3242955e+08 | BP35: 0.26670086 | BR35: 3.397886e+08 | BS35: 5.3365224e+08 | BT35: 3.0576677e+08 | BU35: -1.9386364e+08 | BV35: 34021830 | BW35: 2.9208393e+08 | BX35: 0.16332523 | BZ35: 0 | CA35: 0 | CB35: 0 | CC35: 0 | CD35: 0 | CE35: 0 | CH35: 0 | CI35: 0 | CJ35: 0 | CK35: 0 | CL35: 0 | CM35: 0 | CP35: 2.9606121e+09 | CQ35: 3.9624521e+09 | CR35: 2.9265903e+09 | CS35: -1.0018399e+09 | CT35: 34021830 | CU35: 3.3684924e+09 | CV35: -0.1210869 | CX35: 5.1221978e+09 | CY35: 0 | CZ35: 0 | DA35: 3.3582426e+09 | DB35: 3.9362739e+09 | DC35: 0.30128083 | DD35: -1 | DE35: -1 | DF35: -0.14684734
B36: En % du CA | D36: 0.79664873 | E36: 0.76037763 | F36: 3.62711 | G36: 0.79089526 | H36: 0.57534712 | J36: 0.79516731 | K36: 0.74723592 | L36: 4.7931393 | M36: 0.79089526 | N36: 0.4272053 | P36: 0.77547364 | Q36: 0.76040808 | R36: 1.5065568 | S36: 0.79484656 | T36: -1.9372918 | V36: 0.78853549 | W36: 0.728081 | X36: 0.77112863 | Y36: 0.79484656 | Z36: 1.7406861 | AA36: 1.8042798 | AB36: -101.57444 | AD36: 0.78211697 | AE36: 0.73652622 | AF36: 0.77895587 | AG36: 4.559075 | AH36: 0.0031610964 | AI36: 0.79091599 | AJ36: -0.87990248 | AL36: 0.79807676 | AM36: 0.74740694 | AN36: 0.76878927 | AO36: 5.066982 | AP36: 0.029287488 | AQ36: 0.96655367 | AR36: -16.847691 | AT36: 0.79371173 | AU36: 0.77840849 | AV36: 0.75927943 | AW36: 1.5303246 | AX36: 0.034432304 | AY36: 0.79596746 | AZ36: -0.22557254 | BB36: 0.78854979 | BC36: 0.78543454 | BD36: 0.78209259 | BE36: 0.31152503 | BF36: 0.0064572043 | BG36: 0.80071631 | BH36: -1.2166515 | BJ36: 0.75670771 | BK36: 0.7901743 | BL36: 0.73427235 | BM36: -3.3466591 | BN36: 0.02243536 | BO36: 0.63527515 | BP36: 12.143256 | BR36: 0.78231452 | BS36: 0.79311125 | BT36: 0.75752912 | BU36: -1.0796724 | BV36: 0.024785405 | BW36: 0.80265535 | BX36: -2.0340824 | BZ36: #DIV/0! | CA36: #DIV/0! | CB36: #DIV/0! | CC36: - | CE36: #DIV/0! | CF36: - | CH36: #DIV/0! | CI36: #DIV/0! | CJ36: #DIV/0! | CK36: - | CM36: #DIV/0! | CN36: - | CP36: 0.78546953 | CQ36: 0.76561024 | CR36: 0.78281943 | CS36: 1.9859288 | CT36: 0.26500945 | CU36: 0.90226469 | CV36: -11.679516 | CX36: 0.77179478 | CY36: #DIV/0! | CZ36: #DIV/0! | DA36: 0.73686295 | DB36: 0.88559957 | DC36: -11.380478 | DF36: -14.873661 | DG36: 2.6724945e+09
B38: Marge Brute hors transit | D38: 2.8906884e+08 | E38: 2.712205e+08 | F38: 17848335 | G38: 3.1866483e+08 | H38: -0.092874982 | J38: 2.5220042e+08 | K38: 2.4325341e+08 | L38: 8947007.5 | M38: 3.1866483e+08 | N38: -0.20857153 | P38: 2.6970248e+08 | Q38: 3.0974444e+08 | R38: -40041953 | S38: 2.9466148e+08 | T38: -0.08470396 | V38: 3.0645896e+08 | W38: 3.4617198e+08 | X38: 3.0497366e+08 | Y38: 2.9466148e+08 | Z38: 0.0048702272 | AA38: 7.094181e+08 | AB38: -0.56801362 | AD38: 2.9696229e+08 | AE38: 3.8237041e+08 | AF38: 3.6196415e+08 | AG38: -85408121 | AH38: -65001861 | AI38: 2.995123e+08 | AJ38: -0.0085138531 | AL38: 2.843665e+08 | AM38: 4.1956414e+08 | AN38: 4.3911341e+08 | AO38: -1.3519765e+08 | AP38: -1.5474691e+08 | AQ38: 3.5107939e+08 | AR38: -0.19002224 | AT38: 3.1531483e+08 | AU38: 4.659122e+08 | AV38: 3.2174931e+08 | AW38: -1.5059737e+08 | AX38: -6434479.7 | AY38: 3.0988297e+08 | AZ38: 0.017528728 | BB38: 3.1233052e+08 | BC38: 4.8778331e+08 | BD38: 3.1283541e+08 | BE38: -1.7545279e+08 | BF38: -504894.71 | BG38: 3.0341509e+08 | BH38: 0.029383613 | BJ38: 2.9441871e+08 | BK38: 5.0378864e+08 | BL38: 2.9247318e+08 | BM38: -2.0936993e+08 | BN38: 1945528.7 | BO38: 2.3242955e+08 | BP38: 0.26670086 | BR38: 3.397886e+08 | BS38: 5.3365224e+08 | BT38: 3.0576677e+08 | BU38: -1.9386364e+08 | BV38: 34021830 | BW38: 2.9208393e+08 | BX38: 0.16332523 | BZ38: 0 | CA38: 0 | CB38: 2.9453206e+08 | CC38: 0 | CD38: -2.9453206e+08 | CE38: 0 | CH38: 0 | CI38: 0 | CJ38: 2.9453206e+08 | CK38: 0 | CL38: -2.9453206e+08 | CM38: 0 | CP38: 2.9606121e+09 | CQ38: 3.9624521e+09 | CR38: 2.9025206e+09 | CS38: -9.9453333e+08 | CT38: 32162515 | CU38: 3.3684924e+09 | CV38: -0.1210869 | CX38: 5.1221978e+09 | CY38: 0 | CZ38: 0 | DA38: 3.5891299e+09 | DB38: 3.9362739e+09 | DC38: 0.30128083 | DD38: -1 | DE38: -1 | DF38: -0.088191024
B39: En % du CA | D39: 0.79664873 | E39: 0.76037763 | F39: 3.62711 | G39: 0.79495042 | H39: 0.16983139 | J39: 0.79516731 | K39: 0.74723592 | L39: 4.7931393 | M39: 0.79495042 | N39: 0.021689568 | P39: 0.77547364 | Q39: 0.76040808 | R39: 1.5065568 | S39: 0.79484656 | T39: -1.9372918 | V39: 0.78853549 | W39: 0.728081 | X39: 0.77112863 | Y39: 0.79484656 | Z39: 1.7406861 | AA39: 1.8042798 | AB39: -101.57444 | AD39: 0.78211697 | AE39: 0.73652622 | AF39: 0.77895587 | AG39: 4.559075 | AH39: 0.0031610964 | AI39: 0.79091599 | AJ39: -0.87990248 | AL39: 0.79807676 | AM39: 0.74740694 | AN39: 0.76878927 | AO39: 5.066982 | AP39: 0.029287488 | AQ39: 0.96655367 | AR39: -16.847691 | AT39: 0.79371173 | AU39: 0.77840849 | AV39: 0.75927943 | AW39: 1.5303246 | AX39: 0.034432304 | AY39: 0.79596746 | AZ39: -0.22557254 | BB39: 0.79390958 | BC39: 0.79090093 | BD39: 0.78810336 | BE39: 0.3008644 | BF39: 0.0058062114 | BG39: 0.80188538 | BH39: -0.79758069 | BJ39: 0.75670771 | BK39: 0.7901743 | BL39: 0.73427235 | BM39: -3.3466591 | BN39: 0.02243536 | BO39: 0.63527515 | BP39: 12.143256 | BR39: 0.78231452 | BS39: 0.79311125 | BT39: 0.75752912 | BU39: -1.0796724 | BV39: 0.024785405 | BW39: 0.80265535 | BX39: -2.0340824 | BZ39: #DIV/0! | CA39: #DIV/0! | CB39: 0.79435516 | CC39: - | CE39: #DIV/0! | CF39: - | CH39: #DIV/0! | CI39: #DIV/0! | CJ39: 0.79435516 | CK39: - | CM39: #DIV/0! | CN39: - | CP39: 0.78546953 | CQ39: 0.76561024 | CR39: 0.77638114 | CS39: 1.9859288 | CU39: 0.90226469 | CV39: -11.679516 | CX39: 0.77179478 | CY39: #DIV/0! | CZ39: #DIV/0! | DA39: 0.79301442 | DB39: 0.88559957 | DC39: -11.380478 | DF39: -9.2585151

Sheet Opex
B4: opex | D4: JANVIER | J4: FEVRIER | P4: MARS | V4: AVRIL | AD4: MAI | AL4: JUIN | AT4: JUILLET | BB4: AOUT | BJ4: SEPTEMBRE | BR4: OCTOBRE | BZ4: NOVEMBRE | CH4: DECEMBRE | CP4: CUMUL | CX4: ANNUEL
B5: (En Millions FCFA) | D5: 2025 Réel | E5: 2025 Budget | F5: Ecart / Budget | G5: 2024 Réel | H5: Evol % | J5: 2025 Réel | K5: 2025 Budget | L5: Ecart / Budget | M5: 2024 Réel | N5: Evol % | P5: 2025 Réel | Q5: 2025 Budget | R5: Ecart / Budget | S5: 2024 Réel | T5: Evol % | V5: 2025 Réel | W5: 2025 Budget | X5: 2025 Actu 1 | Y5: Ecart / Budget | Z5: Ecart / Actu 1 | AA5: 2024 Réel | AB5: Evol % | AD5: 2025 Réel | AE5: 2025 Budget | AF5: 2025 Actu 1 | AG5: Ecart / Budget | AH5: Ecart / Actu 1 | AI5: 2024 Réel | AJ5: Evol % | AL5: 2025 Réel | AM5: 2025 Budget | AN5: 2025 Actu 1 | AO5: Ecart / Budget | AP5: Ecart / Actu 1 | AQ5: 2024 Réel | AR5: Evol % | AT5: 2025 Réel | AU5: 2025 Budget | AV5: 2025 Actu 2 | AW5: Ecart / Budget | AX5: Ecart / Actu 2 | AY5: 2024 Réel | AZ5: Evol % | BB5: 2025 Réel | BC5: 2025 Budget | BD5: 2025 Actu3 | BE5: Ecart / Budget | BF5: Ecart / Actu 3 | BG5: 2024 Réel | BH5: Evol % | BJ5: 2025 Réel | BK5: 2025 Budget | BL5: 2025 Actu3 | BM5: Ecart / Budget | BN5: Ecart / Actu 3 | BO5: 2024 Réel | BP5: Evol % | BR5: 2025 Réel | BS5: 2025 Budget | BT5: 2024 Actu 3 | BU5: Ecart / Budget | BV5: Ecart / Actu 3 | BW5: 2024 Réel | BX5: Evol % | BZ5: 2025 Réel | CA5: 2025 Budget | CB5: 2025 Actu 3 | CC5: Ecart / Budget | CD5: Ecart / Actu 3 | CE5: 2024 Réel | CF5: Evol % | CH5: 2025 Réel | CI5: 2025 Budget | CJ5: 2025 Actu 3 | CK5: Ecart / Budget | CL5: Ecart / Actu 3 | CM5: 2024 Réel | CN5: Evol % | CP5: 2025 Réel | CQ5: 2025 Budget | CR5: 2025 Actu 3 | CS5: Ecart / Budget | CT5: Ecart / Actu 3 | CU5: 2024 Réel | CV5: Evol % | CX5: 2025 Budget | CY5: 2024 Actu 1 | CZ5: 2024 Actu 2 | DA5: 2025 Actu 3 | DB5: 2024 Réel | DC5: Bud / 2024 (%) | DD5: Actu 1 / 2023 (%) | DE5: Actu 2 / 2023 (%) | DF5: Actu 3 / 2019 (%)
B7: Total Opex | D7: -4.3008703e+08 | E7: -5.0533119e+08 | F7: 75244162 | G7: -5.1671866e+08 | H7: -0.16765726 | J7: 2.7538477e+08 | K7: 2.8346913e+08 | L7: -8084361.8 | M7: 2.6702784e+08 | N7: 0.03129612 | P7: 2.7879471e+08 | Q7: 3.0116296e+08 | R7: -22368251 | S7: 2.892103e+08 | T7: -0.036013923 | V7: 3.3104575e+08 | W7: 3.1990533e+08 | X7: 3.1413257e+08 | Y7: 11140414 | Z7: 16913179 | AA7: 3.250663e+08 | AB7: 0.018394548 | AD7: 2.9949904e+08 | AE7: 3.40253e+08 | AF7: 3.3599681e+08 | AG7: -39634094 | AH7: -35377900 | AI7: 2.8998261e+08 | AJ7: 0.036679086 | AL7: 3.849825e+08 | AM7: 3.415031e+08 | AN7: 3.405865e+08 | AO7: 43479395 | AP7: 44395993 | AQ7: 3.447776e+08 | AR7: 0.1166111 | AT7: 4.0543024e+08 | AU7: 3.8130516e+08 | AV7: 3.1758136e+08 | AW7: 24125080 | AX7: 87848877 | AY7: 3.0837419e+08 | AZ7: 0.31473465 | BB7: 3.9313047e+08 | BC7: 3.5280266e+08 | BD7: 3.4547022e+08 | BE7: 40327808 | BF7: 47660254 | BG7: 3.0311531e+08 | BH7: 0.29696674 | BJ7: 4.5801206e+08 | BK7: 3.3282608e+08 | BL7: 3.4854651e+08 | BM7: 1.2518598e+08 | BN7: 1.0946555e+08 | BO7: 2.8799012e+08 | BP7: 0.59037419 | BR7: 1.9142916e+08 | BS7: 3.3505833e+08 | BT7: 3.4606173e+08 | BU7: -1.4362917e+08 | BV7: -1.5463257e+08 | BW7: 2.8795142e+08 | BX7: -0.33520329 | BZ7: 0 | CA7: 0 | CB7: 0 | CC7: 0 | CD7: 0 | CE7: 0 | CH7: 0 | CI7: 0 | CJ7: 250000 | CK7: 0 | CL7: -250000 | CM7: 0 | CP7: 2.5876217e+09 | CQ7: 2.4829546e+09 | CR7: 2.7422542e+09 | CS7: 1.0466709e+08 | CT7: -1.5463257e+08 | CU7: 2.186777e+09 | CV7: 0.18330384 | CX7: 3.1108971e+09 | CY7: 0 | CZ7: 0 | DA7: 0 | DB7: 1.5391511e+09 | DC7: 1.0211772 | DD7: -1 | DE7: -1 | DF7: -1
B9: Personnel | D9: -87430619 | E9: -87430619 | F9: 0 | G9: 42926313 | H9: -3.0367605 | J9: 46916667 | K9: 46916667 | L9: 0 | M9: 45354090 | N9: 0.034452822 | P9: 35889510 | Q9: 46916667 | R9: -11027157 | S9: 48150732 | T9: -0.25464249 | V9: 46916667 | W9: 46916667 | X9: 46916667 | Y9: 0 | Z9: 0 | AA9: 46072156 | AB9: 0.018330169 | AD9: 46916667 | AE9: 46916667 | AF9: 46916667 | AG9: 1119872.3 | AH9: 1119872.3 | AI9: 46029360 | AJ9: 0.043606494 | AL9: 52353749 | AM9: 46916667 | AN9: 46916667 | AO9: 5437082 | AP9: 5437082 | AQ9: 49091809 | AR9: 0.066445701 | AT9: 46916667 | AU9: 46916667 | AV9: 46916667 | AW9: 0 | AX9: 0 | AY9: 46029360 | AZ9: 0.019276972 | BB9: 48570142 | BC9: 46916667 | BD9: 46916667 | BE9: 1653475.3 | BF9: 1653475.3 | BG9: 44029360 | BH9: 0.10313077 | BJ9: 48570142 | BK9: 46916667 | BL9: 46916667 | BM9: 1653475.3 | BN9: 1653475.3 | BO9: 44437206 | BP9: 0.093006207 | BR9: 48570142 | BS9: 46916667 | BT9: 46916667 | BU9: 1653475.3 | BV9: 1653475.3 | BW9: 45629360 | BX9: 0.064449337 | BZ9: 0 | CA9: 0 | CB9: 0 | CC9: 0 | CD9: 0 | CE9: 0 | CH9: 0 | CI9: 0 | CJ9: 0 | CK9: 0 | CL9: 0 | CM9: 0 | CP9: 3.3418973e+08 | CQ9: 3.3481938e+08 | CR9: 3.3253626e+08 | CS9: -629649 | CT9: 1653475.3 | CU9: 457749747 | CV9: -0.26992918 | CX9: 428652714 | CY9: 0 | CZ9: 0 | DA9: 0 | DB9: 544657150 | DC9: -0.21298616 | DD9: -1 | DE9: -1 | DF9: -1
B10: Traitement & salaires et autres | D10: -90030619 | E10: -90030619 | F10: 0 | G10: 39883517 | H10: -3.257339 | J10: 44316667 | K10: 44316667 | L10: 0 | M10: 42311294 | N10: 0.047395683 | P10: 33289510 | Q10: 44316667 | R10: -11027157 | S10: 45107936 | T10: -0.26200326 | V10: 44316667 | W10: 44316667 | X10: 44316667 | Y10: 0 | Z10: 0 | AA10: 43029360 | AB10: 0.029916937 | AD10: 44316667 | AE10: 44316667 | AF10: 44316667 | AG10: 1119872.3 | AH10: 1119872.3 | AI10: 43029360 | AJ10: 0.05594271 | AL10: 49753749 | AM10: 44316667 | AN10: 44316667 | AO10: 5437082 | AP10: 5437082 | AQ10: 45934837 | AR10: 0.08313759 | AT10: 44316667 | AU10: 44316667 | AV10: 44316667 | AW10: 0 | AX10: 0 | AY10: 43029360 | AZ10: 0.029916937 | BB10: 45970142 | BC10: 44316667 | BD10: 44316667 | BE10: 1653475.3 | BF10: 1653475.3 | BG10: 41029360 | BH10: 0.12042065 | BJ10: 45970142 | BK10: 44316667 | BL10: 44316667 | BM10: 1653475.3 | BN10: 1653475.3 | BO10: 41837206 | BP10: 0.098786138 | BR10: 45970142 | BS10: 44316667 | BT10: 44316667 | BU10: 1653475.3 | BV10: 1653475.3 | BW10: 43029360 | BX10: 0.068343615 | CC10: 0 | CD10: 0 | CK10: 0 | CL10: 0 | CP10: 3.0818973e+08 | CQ10: 3.0881938e+08 | CR10: 3.0653626e+08 | CS10: -629649 | CT10: 1653475.3 | CU10: 428221590 | CV10: -0.28030314 | CX10: 397452714 | DB10: 510628993 | DC10: -0.22164092 | DD10: -1 | DE10: -1 | DF10: -1
B11: Assurance maladie | D11: 2600000 | E11: 2600000 | F11: 0 | G11: 3042796.2 | H11: -0.14552281 | J11: 2600000 | K11: 2600000 | L11: 0 | M11: 3042796.2 | N11: -0.14552281 | P11: 2600000 | Q11: 2600000 | R11: 0 | S11: 3042796.2 | T11: -0.14552281 | V11: 2600000 | W11: 2600000 | X11: 2600000 | Y11: 0 | Z11: 0 | AA11: 3042796.2 | AB11: -0.14552281 | AD11: 2600000 | AE11: 2600000 | AF11: 2600000 | AG11: 0 | AH11: 0 | AI11: 3000000 | AL11: 2600000 | AM11: 2600000 | AN11: 2600000 | AQ11: 3156972 | AT11: 2600000 | AU11: 2600000 | AV11: 2600000 | AW11: 0 | AX11: 0 | AY11: 3000000 | AZ11: -0.13333333 | BB11: 2600000 | BC11: 2600000 | BD11: 2600000 | BE11: 0 | BF11: 0 | BG11: 3000000 | BH11: -0.13333333 | BJ11: 2600000 | BK11: 2600000 | BL11: 2600000 | BM11: 0 | BN11: 0 | BO11: 2600000 | BR11: 2600000 | BS11: 2600000 | BT11: 2600000 | BU11: 0 | BV11: 0 | BW11: 2600000 | BX11: 0 | CC11: 0 | CD11: 0 | CK11: 0 | CP11: 26000000 | CQ11: 26000000 | CR11: 26000000 | CS11: 0 | CT11: 0 | CU11: 29528157 | CV11: -0.1194845 | CX11: 31200000 | DB11: 34028157 | DC11: -0.083112259
B12: Activation des charges du personnel | AW12: 0 | BE12: 0 | BL12: 2600000 | BM12: 0 | BO12: 0 | BU12: 0 | CC12: 0 | CK12: 0 | CP12: 0 | CQ12: 0 | CR12: 0 | CS12: 0 | CT12: 0 | CU12: 0 | CX12: 0 | DB12: 0 | DE12: #DIV/0! | DF12: #DIV/0!
BL13: 0 | BO13: 0 | CR13: 0
B14: Communication | D14: 14539100 | E14: 8580000 | F14: 5959100 | G14: 4687346 | H14: 2.1017766 | J14: 8728652 | K14: 8500000 | L14: 228652 | M14: 7287833.3 | N14: 0.19770192 | P14: 12000000 | Q14: 12000000 | R14: 0 | S14: 9232310.6 | T14: 0.29978296 | V14: 9879642 | W14: 30000000 | X14: 30000000 | Y14: -20120358 | Z14: -20120358 | AA14: 9153851 | AB14: 0.07928805 | AD14: 22846878 | AE14: 20000000 | AF14: 20000000 | AG14: 2846878 | AH14: 2846878 | AI14: 12382383 | AJ14: 0.84511156 | AL14: 22848916 | AM14: 20000000 | AN14: 20000000 | AO14: 2848916 | AP14: 2848916 | AQ14: 12258193 | AR14: 0.86397098 | AT14: 79761941 | AU14: 37000000 | AV14: 12000000 | AW14: 42761941 | AX14: 67761941 | AY14: 9614000 | AZ14: 7.2964366 | BB14: 61708174 | BC14: 20000000 | BD14: 20000000 | BE14: 41708174 | BF14: 41708174 | BG14: 6410527 | BH14: 8.6260688 | BJ14: 44613209 | BK14: 9000000 | BL14: 20000000 | BM14: 35613209 | BN14: 24613209 | BO14: 8356931 | BP14: 4.338468 | BR14: 40000000 | BS14: 9000000 | BT14: 20000000 | BU14: 31000000 | BV14: 20000000 | BW14: 13978287 | BX14: 1.861581 | CC14: 0 | CD14: 0 | CK14: 0 | CL14: 0 | CP14: 316926512 | CQ14: 174080000 | CR14: 296926512 | CS14: 142846512 | CT14: 20000000 | CU14: 93361662 | CV14: 2.3946109 | CX14: 173080000 | DB14: 130662347 | DC14: 0.32463563 | DD14: -1 | DE14: -1 | DF14: -1
AM15: + | BO15: 0 | CR15: 0
B16: Exploitation & maintenance | D16: 1.1220175e+08 | E16: 1.2181435e+08 | F16: -9612595.5 | G16: 1.6009139e+08 | H16: -0.29913935 | J16: 1.2957029e+08 | K16: 1.3103385e+08 | L16: -1463563.5 | M16: 1.5689164e+08 | N16: -0.17414154 | P16: 117727655 | Q16: 1.3944939e+08 | R16: -21721733 | S16: 1.6169545e+08 | T16: -0.27191734 | V16: 1.619003e+08 | W16: 1.3799454e+08 | X16: 1.3757965e+08 | Y16: 23905764 | Z16: 24320656 | AA16: 1.9409647e+08 | AB16: -0.16587716 | AD16: 1.338083e+08 | AE16: 1.6569592e+08 | AF16: 1.6569592e+08 | AG16: -31887620 | AH16: -31887620 | AI16: 1.285268e+08 | AJ16: 0.041092564 | AL16: 1.9516028e+08 | AM16: 1.6552092e+08 | AN16: 1.6552092e+08 | AO16: 29639360 | AP16: 29639360 | AQ16: 191334840 | AR16: 0.019993428 | AT16: 1.8090469e+08 | AU16: 1.8209242e+08 | AV16: 1.6167092e+08 | AW16: -1187728.9 | AX16: 19233771 | AY16: 1.6318724e+08 | AZ16: 0.10857127 | BB16: 181790480 | BC16: 1.8348054e+08 | BD16: 1.8348054e+08 | BE16: -1690062.6 | BF16: -1690062.6 | BG16: 171210748 | BH16: 0.061793621 | BJ16: 2.1328279e+08 | BK16: 1.6057092e+08 | BL16: 1.8348054e+08 | BM16: 52711876 | BN16: 29802252 | BO16: 1.4628801e+08 | BP16: 0.45796493 | BR16: 2.0384571e+08 | BS16: 1.6037092e+08 | BT16: 1.8107537e+08 | BU16: 43474791 | BV16: 22770343 | BW16: 1.2585414e+08 | BX16: 0.61969812 | BZ16: 0 | CA16: 0 | CB16: 0 | CC16: 0 | CD16: 0 | CE16: 0 | CH16: 0 | CI16: 0 | CJ16: 0 | CK16: 0 | CL16: 0 | CM16: 0 | CP16: 1.6301922e+09 | CQ16: 1.5480238e+09 | CR16: 1.6074219e+09 | CS16: 82168487 | CT16: 22770343 | CU16: 1.5991767e+09 | CV16: 0.019394673 | CX16: 1.8272845e+09 | CY16: 0 | CZ16: 0 | DA16: 0 | DB16: 5.171164e+08 | DC16: 2.5336038 | DD16: -1 | DE16: -1 | DF16: -1
B17: Achat d'énergie - Bâtiment - Gardiennage | D17: 48834893 | E17: 58045988 | F17: -9211095.5 | G17: 51908026 | H17: -0.059203426 | J17: 54451425 | K17: 56365988 | L17: -1914563.5 | M17: 51989276 | N17: 0.047358786 | P17: 63227655 | Q17: 59570988 | R17: 3656666.5 | S17: 42987622 | T17: 0.47083398 | V17: 77087827 | W17: 57920988 | X17: 57920988 | Y17: 19166838 | Z17: 19166838 | AA17: 53459622 | AB17: 0.44198227 | AD17: 62437559 | AE17: 58170988 | AF17: 58170988 | AG17: 4266570.5 | AH17: 4266570.5 | AI17: 69211676 | AJ17: -0.09787535 | AL17: 82216262 | AM17: 57995988 | AN17: 57995988 | AO17: 24220274 | AP17: 24220274 | AQ17: 59788102 | AR17: 0.37512748 | AT17: 85088676 | AU17: 75812312 | AV17: 54795988 | AW17: 9276363.5 | AX17: 30292688 | AY17: 51814122 | AZ17: 0.64219083 | BB17: 76747055 | BC17: 75812312 | BD17: 75812312 | BE17: 934742.5 | BF17: 934742.5 | BG17: 52126743 | BH17: 0.47231633 | BJ17: 92324706 | BK17: 53695988 | BL17: 75812312 | BM17: 38628718 | BN17: 16512394 | BO17: 59026347 | BP17: 0.56412704 | BR17: 91378834 | BS17: 53495988 | BT17: 75812312 | BU17: 37882846 | BV17: 15566522 | BW17: 61252780 | BX17: 0.49183161 | CC17: 0 | CD17: 0 | CK17: 0 | CL17: 0 | CP17: 733794892 | CQ17: 606887533 | CR17: 7.1822837e+08 | CS17: 126907359 | CT17: 15566522 | CU17: 5.5356432e+08 | CV17: 0.325582 | CX17: 672596862 | DB17: 668946781 | DC17: 0.0054564595 | DD17: -1 | DE17: -1 | DF17: -1
B18: Lignes et réseaux (entretien & achats) | D18: 61418361 | E18: 61418361 | F18: 0 | G18: 1.0393836e+08 | H18: -0.40908862 | J18: 72317861 | K18: 72317861 | L18: 0 | M18: 1.0393836e+08 | N18: -0.30422358 | P18: 53400000 | Q18: 77073549 | R18: -23673549 | S18: 1.1807783e+08 | T18: -0.54775592 | V18: 81365475 | W18: 77073549 | X18: 76658657 | Y18: 4291925.7 | Z18: 4706817.7 | AA18: 1.3923685e+08 | AB18: -0.41563262 | AD18: 65916240 | AE18: 1.0407008e+08 | AF18: 1.0407008e+08 | AG18: -38153841 | AH18: -38153841 | AI18: 55615127 | AJ18: 0.18522142 | AL18: 1.0950247e+08 | AM18: 1.0407008e+08 | AN18: 1.0407008e+08 | AO18: 5432391.3 | AP18: 5432391.3 | AQ18: 118730693 | AR18: -0.077723977 | AT18: 91382166 | AU18: 1.0347526e+08 | AV18: 1.0407008e+08 | AW18: -12093090 | AX18: -12687914 | AY18: 1.0818312e+08 | AZ18: -0.15530109 | BB18: 101275031 | BC18: 1.0486338e+08 | BD18: 1.0486338e+08 | BE18: -3588348.7 | BF18: -3588348.7 | BG18: 114878963 | BH18: -0.1184197 | BJ18: 1.1508448e+08 | BK18: 1.0407008e+08 | BL18: 1.0486338e+08 | BM18: 11014403 | BN18: 10221103 | BO18: 86359721 | BP18: 0.33261758 | BR18: 1.0611924e+08 | BS18: 1.0407008e+08 | BT18: 1.024582e+08 | BU18: 2049162.8 | BV18: 3661038.8 | BW18: 62307861 | BX18: 0.70314373 | CC18: 0 | CD18: 0 | CK18: 0 | CL18: 0 | CP18: 8.5778133e+08 | CQ18: 9.1250228e+08 | CR18: 8.5412029e+08 | CS18: -54720946 | CT18: 3661038.8 | CU18: 1011266893 | CV18: -0.15177552 | CX18: 1.120444e+09 | DB18: -1.9175726e+08 | DC18: -6.8430327 | DD18: -1 | DE18: -1 | DF18: -1
B19: Fees du contrat GMNS | F19: 0 | L19: 0 | R19: 0 | Y19: 0 | Z19: 0 | AA19: 0 | AG19: 0 | AH19: 0 | AO19: 0 | AP19: 0 | AW19: 0 | AX19: 0 | BE19: 0 | BF19: 0 | BL19: 0 | BM19: 0 | BN19: 0 | BO19: 0 | BU19: 0 | BV19: 0 | CC19: 0 | CD19: 0 | CK19: 0 | CL19: 0 | CP19: 0 | CQ19: 0 | CR19: 0 | CS19: 0 | CT19: 0 | CU19: 0 | DB19: 0 | DE19: #DIV/0! | DF19: #DIV/0!
B20: Matériel de transport (Entretien et locat°) | D20: 1948500 | E20: 1050000 | F20: 898500 | G20: 1260000 | H20: 0.54642857 | J20: 1501000 | K20: 1050000 | L20: 451000 | M20: 799000 | N20: 0.87859825 | P20: 950000 | Q20: 1050000 | R20: -100000 | S20: 610000 | T20: 0.55737705 | V20: 3447000 | W20: 1700000 | X20: 1700000 | Y20: 1747000 | Z20: 1747000 | AA20: 1400000 | AB20: 1.4621429 | AD20: 5454500 | AE20: 1700000 | AF20: 1700000 | AG20: 3754500 | AH20: 3754500 | AI20: 2700000 | AJ20: 1.0201852 | AL20: 3441546.1 | AM20: 1700000 | AN20: 1700000 | AO20: 1741546.1 | AP20: 1741546.1 | AQ20: 6378700 | AR20: -0.46046278 | AT20: 4731453.9 | AU20: 1050000 | AV20: 1050000 | AW20: 3681453.9 | AX20: 3681453.9 | AY20: 2620000 | AZ20: 0.80589845 | BB20: 4066000 | BC20: 1050000 | BD20: 1050000 | BE20: 3016000 | BF20: 3016000 | BG20: 3720046 | BH20: 0.092997237 | BJ20: 5576000 | BK20: 1050000 | BL20: 1050000 | BM20: 4526000 | BN20: 4526000 | BO20: 425454 | BP20: 12.106 | BR20: 6347633 | BS20: 1050000 | BT20: 1050000 | BU20: 5297633 | BV20: 5297633 | BW20: 1808500 | BX20: 2.5098883 | CC20: 0 | CD20: 0 | CK20: 0 | CL20: 0 | CP20: 37463633 | CQ20: 12450000 | CR20: 32166000 | CS20: 25013633 | CT20: 5297633 | CU20: 21721700 | CV20: 0.72470999 | CX20: 14550000 | DB20: 26818058 | DC20: -0.45745512 | DD20: -1 | DE20: -1 | DF20: -1
B21: Maintenance informatique | D21: 0 | E21: 1300000 | F21: -1300000 | G21: 2985000 | H21: -1 | J21: 1300000 | K21: 1300000 | L21: 0 | M21: 165000 | N21: 6.8787879 | P21: 150000 | Q21: 1754850.4 | R21: -1604850.4 | S21: 20000 | T21: 6.5 | V21: 0 | W21: 1300000 | X21: 1300000 | Y21: -1300000 | Z21: -1300000 | AA21: 0 | AD21: 0 | AE21: 1754850.4 | AF21: 1754850.4 | AG21: -1754850.4 | AH21: -1754850.4 | AI21: 1000000 | AJ21: -1 | AL21: 0 | AM21: 1754850.4 | AN21: 1754850.4 | AO21: -1754850.4 | AP21: -1754850.4 | AQ21: 6437345 | AR21: -1 | AT21: -297606 | AU21: 1754850.4 | AV21: 1754850.4 | AW21: -2052456.4 | AX21: -2052456.4 | AY21: 570000 | AZ21: -1.5221158 | BB21: -297606 | BC21: 1754850.4 | BD21: 1754850.4 | BE21: -2052456.4 | BF21: -2052456.4 | BG21: 484996 | BH21: -1.6136257 | BJ21: 297606 | BK21: 1754850.4 | BL21: 1754850.4 | BM21: -1457244.4 | BN21: -1457244.4 | BO21: 476492 | BP21: -0.37542288 | BR21: 0 | BS21: 1754850.4 | BT21: 1754850.4 | BU21: -1754850.4 | BV21: -1754850.4 | BW21: 484996.4 | BX21: -1 | CC21: 0 | CD21: 0 | CK21: 0 | CL21: 0 | CP21: 1152394 | CQ21: 16183953 | CR21: 2907244.4 | CS21: -15031559 | CT21: -1754850.4 | CU21: 12623829 | CV21: -0.9087128 | CX21: 19693654 | DB21: 13108825 | DC21: 0.50232027 | DD21: -1 | DE21: -1 | DF21: -1
X22: * | BO22: 0 | CR22: 0
B23: Frais généraux | D23: 25470165 | E23: 23810184 | F23: 1659980.9 | G23: 1.5730827e+08 | H23: -0.83808756 | J23: 19797251 | K23: 23357608 | L23: -3560357.4 | M23: 14542083 | N23: 0.36137651 | P23: 25652491 | Q23: 24287469 | R23: 1365021.6 | S23: 15612570 | T23: 0.64306653 | V23: 36283015 | W23: 24953904 | X23: 28645859 | Y23: 11329110 | Z23: 7637156.1 | AA23: 11092346 | AB23: 2.2709956 | AD23: 18782639 | AE23: 25361954 | AF23: 29295652 | AG23: -6579314.6 | AH23: -10513012 | AI23: 36286115 | AJ23: -0.48237392 | AL23: 18674111 | AM23: 25758021 | AN23: 30308814 | AO23: -7083909.4 | AP23: -11634703 | AQ23: 29095759 | AR23: -0.35818442 | AT23: 16215398 | AU23: 28916241 | AV23: 26075697 | AW23: -12700843 | AX23: -9860298.9 | AY23: 24120071 | AZ23: -0.3277218 | BB23: 17935288 | BC23: 29474122 | BD23: 25692940 | BE23: -11538834 | BF23: -7757652.5 | BG23: 18129380 | BH23: -0.01070596 | BJ23: 19453740 | BK23: 26428460 | BL23: 28676932 | BM23: -6974720.4 | BN23: -9223192.3 | BO23: 26928610 | BP23: -0.27758099 | BR23: 30077721 | BS23: 26755712 | BT23: 28726262 | BU23: 3322008.8 | BV23: 1351458.6 | BW23: 36850854 | BX23: -0.18379853 | BZ23: 0 | CA23: 0 | CB23: 0 | CC23: 0 | CD23: 0 | CE23: 0 | CH23: 0 | CI23: 0 | CJ23: 0 | CK23: 0 | CL23: 0 | CM23: 0 | CP23: 2.2834182e+08 | CQ23: 2.5910368e+08 | CR23: 2.2699036e+08 | CS23: -30761858 | CT23: 1351458.6 | CU23: 3.6996606e+08 | CV23: -0.38280333 | CX23: 3.076527e+08 | CY23: 0 | CZ23: 0 | DA23: 0 | DB23: 4.7389019e+08 | DC23: -0.35079327 | DD23: -1 | DE23: -1 | DF23: -1
B24: Frais d'achats d'études, honoraires | D24: 12558275 | E24: 9462498.2 | F24: 3095776.8 | G24: 1.431925e+08 | H24: -0.91229795 | J24: 10636753 | K24: 9462498.2 | L24: 1174254.8 | M24: 3452498.2 | N24: 2.0808858 | P24: 17838690 | Q24: 9462498.2 | R24: 8376191.8 | S24: 3152498.2 | T24: 4.6585884 | V24: 15462498 | W24: 9462498.2 | X24: 13962498 | Y24: 6000000 | Z24: 1500000 | AA24: 4000000 | AB24: 2.8656246 | AD24: 12244418 | AE24: 9462498.2 | AF24: 13962498 | AG24: 2781920 | AH24: -1718080 | AI24: 16988196 | AJ24: -0.27923964 | AL24: 5615647.5 | AM24: 9462498.2 | AN24: 13962498 | AO24: -3846850.8 | AP24: -8346850.8 | AQ24: 15000000 | AR24: -0.6256235 | AT24: 6675665 | AU24: 13962498 | AV24: 9462498.2 | AW24: -7286833.2 | AX24: -2786833.2 | AY24: 10000000 | AZ24: -0.3324335 | BB24: 5416499 | BC24: 13962498 | BD24: 12962498 | BE24: -8545999.2 | BF24: -7545999.2 | BG24: 5666665 | BH24: -0.044146954 | BJ24: 5462498.2 | BK24: 9462498.2 | BL24: 13962498 | BM24: -4000000 | BN24: -8500000 | BO24: 13000000 | BP24: -0.57980783 | BR24: 4800000 | BS24: 9462498.2 | BT24: 13962498 | BU24: -4662498.2 | BV24: -9162498.2 | BW24: 20077424 | BX24: -0.7609255 | CC24: 0 | CD24: 0 | CK24: 0 | CL24: 0 | CP24: 96710944 | CQ24: 1.0362498e+08 | CR24: 1.0587344e+08 | CS24: -6914038.2 | CT24: -9162498.2 | CU24: 2.3452978e+08 | CV24: -0.58763896 | CX24: 113549979 | DB24: 267361897 | DC24: -0.57529483 | DD24: -1 | DE24: -1 | DF24: -1
B25: Management fees | D25: 3209225.3 | E25: 3377686.1 | F25: -168460.81 | G25: 3776719.9 | H25: -0.15026122 | J25: 2817213.5 | K25: 3095109.7 | L25: -277896.15 | M25: 2887109 | N25: -0.0242095 | P25: 3079918.8 | Q25: 3854970.9 | R25: -775052.11 | S25: 3280540.5 | T25: -0.061155077 | V25: 3486531.4 | W25: 4521406 | X25: 3713360.3 | Y25: -1034874.7 | Z25: -226828.9 | AA25: 3492345.9 | AB25: -0.0016649417 | AD25: 3386300 | AE25: 4929455.6 | AF25: 4363153.3 | AG25: -1543155.6 | AH25: -976853.29 | AI25: 2583957.9 | AJ25: 0.31050897 | AL25: 3124171.9 | AM25: 5325522.6 | AN25: 5376315.7 | AO25: -2201350.7 | AP25: -2252143.8 | AQ25: 3208844.1 | AR25: -0.026387137 | AT25: 3526522.7 | AU25: 3983743 | AV25: 5643198.4 | AW25: -457220.23 | AX25: -2116675.6 | AY25: 3450070.8 | AZ25: 0.022159515 | BB25: 3466221 | BC25: 4541623.8 | BD25: 3760442.2 | BE25: -1075402.8 | BF25: -294221.26 | BG25: 3369263.4 | BH25: 0.028777084 | BJ25: 3432369.5 | BK25: 5995961.9 | BL25: 3744433.8 | BM25: -2563592.4 | BN25: -312064.27 | BO25: 3226599.1 | BP25: 0.063773152 | BR25: 3836001.1 | BS25: 6323214 | BT25: 3793764.2 | BU25: -2487212.9 | BV25: 42236.881 | BW25: 3223271.8 | BX25: 0.19009542 | CC25: 0 | CD25: 0 | CK25: 0 | CL25: 0 | CP25: 33364475 | CQ25: 45948694 | CR25: 33322238 | CS25: -12584218 | CT25: 42236.881 | CU25: 32498722 | CV25: 0.026639592 | CX25: 62632724 | DB25: 38771669 | DC25: 0.61542504 | DD25: -1 | DE25: -1 | DF25: -1
B26: Transport, déplacement, mission | D26: 5692000 | E26: 7500000 | F26: -1808000 | G26: 10246800 | H26: -0.44450951 | J26: 5493250 | K26: 7500000 | L26: -2006750 | M26: 4164600 | N26: 0.31903424 | P26: 1500882 | Q26: 7500000 | R26: -5999118 | S26: 2439000 | T26: -0.38463223 | V26: 8596500 | W26: 7500000 | X26: 7500000 | Y26: 1096500 | Z26: 1096500 | AA26: 5000000 | AB26: 0.7193 | AD26: 6044840 | AE26: 7500000 | AF26: 7500000 | AG26: -1455160 | AH26: -1455160 | AI26: 11000000 | AJ26: -0.45046909 | AL26: 8652971 | AM26: 7500000 | AN26: 7500000 | AO26: 1152971 | AP26: 1152971 | AQ26: 10140904 | AR26: -0.14672587 | AT26: 5104528 | AU26: 7500000 | AV26: 7500000 | AW26: -2395472 | AX26: -2395472 | AY26: 8500000 | AZ26: -0.39946729 | BB26: 5104528 | BC26: 7500000 | BD26: 7500000 | BE26: -2395472 | BF26: -2395472 | BG26: 7912281 | BH26: -0.35486012 | BJ26: 6263872 | BK26: 7500000 | BL26: 7500000 | BM26: -1236128 | BN26: -1236128 | BO26: 10101276 | BP26: -0.379893 | BR26: 8700000 | BS26: 7500000 | BT26: 7500000 | BU26: 1200000 | BV26: 1200000 | BW26: 12518775 | BX26: -0.30504382 | CC26: 0 | CD26: 0 | CK26: 0 | CL26: 0 | CP26: 61153371 | CQ26: 75000000 | CR26: 59953371 | CS26: -13846629 | CT26: 1200000 | CU26: 82023636 | CV26: -0.25444209 | CX26: 90000000 | DB26: 111679844 | DC26: -0.19412495 | DD26: -1 | DE26: -1 | DF26: -1
B27: Frais postaux, bancaires et assurances | D27: 1913327 | E27: 3170000 | F27: -1256673 | G27: 0 | J27: 420034 | K27: 3000000 | L27: -2579966 | M27: 4037876 | N27: -0.8959765 | P27: 3170000 | Q27: 3170000 | R27: 0 | S27: 6740531 | T27: -0.52971064 | V27: 8437485 | W27: 3170000 | X27: 3170000 | Y27: 5267485 | Z27: 5267485 | AA27: -1500000 | AB27: -6.62499 | AD27: -3671919 | AE27: 3170000 | AF27: 3170000 | AG27: -6841919 | AH27: -6841919 | AI27: 4713961 | AJ27: -1.7789456 | AL27: 716321 | AM27: 3170000 | AN27: 3170000 | AO27: -2453679 | AP27: -2453679 | AQ27: 524261 | AR27: 0.36634424 | AT27: 338682 | AU27: 3170000 | AV27: 3170000 | AW27: -2831318 | AX27: -2831318 | AY27: 2080000 | AZ27: -0.83717212 | BB27: 2532720 | BC27: 3170000 | BD27: 1170000 | BE27: -637280 | BF27: 1362720 | BG27: 1141171 | BH27: 1.2194045 | BJ27: 4170000 | BK27: 3170000 | BL27: 3170000 | BM27: 1000000 | BN27: 1000000 | BO27: 555735 | BP27: 6.5035763 | BR27: 12661720 | BS27: 3170000 | BT27: 3170000 | BU27: 9491720 | BV27: 9491720 | BW27: 216383 | BX27: 57.515318 | CC27: 0 | CD27: 0 | CK27: 0 | CL27: 0 | CP27: 30688370 | CQ27: 31530000 | CR27: 21196650 | CS27: -841630 | CT27: 9491720 | CU27: 18509918 | CV27: 0.65794197 | CX27: 37870000 | DB27: 53459783 | DC27: -0.29161703 | DD27: -1 | DE27: -1 | DF27: -1
B28: Achats de mat. et fournitures consom. | D28: 2097338 | E28: 300000 | F28: 1797338 | G28: 92250 | H28: 21.735371 | J28: 430000 | K28: 300000 | L28: 130000 | M28: 0 | P28: 63000 | Q28: 300000 | R28: -237000 | S28: 0 | V28: 300000 | W28: 300000 | X28: 300000 | Y28: 0 | Z28: 0 | AA28: 100000 | AB28: 2 | AD28: 779000 | AE28: 300000 | AF28: 300000 | AG28: 479000 | AH28: 479000 | AI28: 1000000 | AJ28: -0.221 | AL28: 565000 | AM28: 300000 | AN28: 300000 | AO28: 265000 | AP28: 265000 | AQ28: 221750 | AR28: 1.5479143 | AT28: 570000 | AU28: 300000 | AV28: 300000 | AW28: 270000 | AX28: 270000 | AY28: 90000 | AZ28: 5.3333333 | BB28: 1415320 | BC28: 300000 | BD28: 300000 | BE28: 1115320 | BF28: 1115320 | BG28: 40000 | BH28: ns | BJ28: 125000 | BK28: 300000 | BL28: 300000 | BM28: -175000 | BN28: -175000 | BO28: 45000 | BP28: 1.7777778 | BR28: 80000 | BS28: 300000 | BT28: 300000 | BU28: -220000 | BV28: -220000 | BW28: 815000 | BX28: -0.90184049 | CC28: 0 | CD28: 0 | CK28: 0 | CL28: 0 | CP28: 6424658 | CQ28: 3000000 | CR28: 6644658 | CS28: 3424658 | CT28: -220000 | CU28: 2404000 | CV28: 1.6724867 | CX28: 3600000 | DB28: 2617000 | DC28: 0.37562094 | DD28: -1 | DE28: -1 | DF28: -1
BO29: 0 | CR29: 0
B30: Impôts, taxes et redevances | D30: -6.0041743e+08 | E30: -6.776551e+08 | F30: 77237676 | G30: -8.8373198e+08 | H30: -0.32058877 | J30: 66821916 | K30: 70111009 | L30: -3289092.9 | M30: 53514299 | N30: 0.24867403 | P30: 66527556 | Q30: 74959434 | R30: -8431877.7 | S30: 47465386 | T30: 0.40160149 | V30: 70516124 | W30: 76490227 | X30: 67440400 | Y30: -5974102.4 | Z30: 3075724.4 | AA30: 62651474 | AB30: 0.12553017 | AD30: 67844555 | AE30: 78728465 | AF30: 70538573 | AG30: -10883910 | AH30: -2694017.7 | AI30: 63377404 | AJ30: 0.070484917 | AL30: 71802732 | AM30: 79757497 | AN30: 74290105 | AO30: -7954764.4 | AP30: -2487372.7 | AQ30: 65616453 | AR30: 0.0942794 | AT30: 70581544 | AU30: 82829833 | AV30: 67368081 | AW30: -12248289 | AX30: 3213463.9 | AY30: 62042971 | AZ30: 0.13762353 | BB30: 70576386 | BC30: 69381331 | BD30: 65830067 | BE30: 1195055.3 | BF30: 4746319.4 | BG30: 61454742 | BH30: 0.14842866 | BJ30: 72029173 | BK30: 86360033 | BL30: 65922366 | BM30: -14330860 | BN30: 6106807.5 | BO30: 59316016 | BP30: 0.21432925 | BR30: -1.4657053e+08 | BS30: 88465032 | BT30: 65793434 | BU30: -2.3503556e+08 | BV30: -2.1236396e+08 | BW30: 64801023 | BX30: -3.2618552 | BZ30: 0 | CA30: 0 | CB30: 0 | CC30: 0 | CD30: 0 | CE30: 0 | CH30: 0 | CI30: 0 | CJ30: 0 | CK30: 0 | CL30: 0 | CM30: 0 | CP30: -1.9028797e+08 | CQ30: 29427756 | CR30: 22075994 | CS30: -2.1971572e+08 | CT30: -2.1236396e+08 | CU30: -3.4349221e+08 | CV30: -0.44601955 | CX30: 2.2962719e+08 | CY30: 0 | CZ30: 0 | DA30: 0 | DB30: -2.1145676e+08 | DC30: -2.0859298 | DD30: -1 | DE30: -1 | DF30: -1
B31: Redevances régulateur | D31: -6.5397926e+08 | E31: -7.3397926e+08 | F31: 80000000 | G31: 17088950 | H31: ns | J31: 16020741 | K31: 16020741 | L31: 0 | M31: 17088950 | N31: -0.062508746 | P31: 14856246 | Q31: 16020741 | R31: -1164495.4 | S31: 11688950 | T31: 0.27096495 | V31: 15244421 | W31: 16020741 | X31: 16020741 | Y31: -776320.12 | Z31: -776320.12 | AA31: 22088950 | AB31: -0.30986212 | AD31: 16020741 | AE31: 16020741 | AF31: 16020741 | AG31: 0 | AH31: 0 | AI31: 17088950 | AJ31: -0.062508746 | AL31: 15632566 | AM31: 16020741 | AN31: 16020741 | AO31: -388175.24 | AP31: -388175.24 | AQ31: 19584498 | AR31: -0.20178879 | AT31: 15632576 | AU31: 16020741 | AV31: 16020741 | AW31: -388165.13 | AX31: -388165.13 | AY31: 17500000 | AZ31: -0.10670994 | BB31: 15632576 | BC31: 16020741 | BD31: 16020741 | BE31: -388165.13 | BF31: -388165.13 | BG31: 17500000 | BH31: -0.10670994 | BJ31: 16632576 | BK31: 16020741 | BL31: 16020741 | BM31: 611835 | BN31: 611835 | BO31: 17314624 | BP31: -0.039391435 | BR31: -53267000 | BS31: 16020741 | BT31: 16020741 | BU31: -69287741 | BV31: -69287741 | BW31: 17438208 | BX31: -4.0546143 | CC31: 0 | CD31: 0 | CK31: 0 | CL31: 0 | CP31: -5.8157382e+08 | CQ31: -5.8979259e+08 | CR31: -5.1228607e+08 | CS31: 8218772.9 | CT31: -69287741 | CU31: 1.7438208e+08 | CV31: ns | CX31: -5.5775111e+08 | DB31: 209258507 | DC31: -3.6653689 | DD31: -1 | DE31: -1 | DF31: -1
B32: Autres impôts et taxes | D32: 53561831 | E32: 56324154 | F32: -2762323.8 | G32: -9.0082093e+08 | H32: -1.0594589 | J32: 50801175 | K32: 54090268 | L32: -3289092.9 | M32: 36425349 | N32: 0.39466541 | P32: 51671310 | Q32: 58938693 | R32: -7267382.4 | S32: 35776436 | T32: 0.44428333 | V32: 55271703 | W32: 60469486 | X32: 51419659 | Y32: -5197782.2 | Z32: 3852044.5 | AA32: 40562524 | AB32: 0.36262977 | AD32: 51823814 | AE32: 62707724 | AF32: 54517832 | AG32: -10883910 | AH32: -2694017.7 | AI32: 46288454 | AJ32: 0.11958403 | AL32: 56170166 | AM32: 63736756 | AN32: 58269364 | AO32: -7566589.1 | AP32: -2099197.5 | AQ32: 46031955 | AR32: 0.22024292 | AT32: 54948968 | AU32: 66809092 | AV32: 51347339 | AW32: -11860124 | AX32: 3601629 | AY32: 44542971 | AZ32: 0.23361704 | BB32: 54943810 | BC32: 53360590 | BD32: 49809326 | BE32: 1583220.4 | BF32: 5134484.5 | BG32: 43954742 | BH32: 0.25000872 | BJ32: 55396597 | BK32: 70339292 | BL32: 49901625 | BM32: -14942695 | BN32: 5494972.5 | BO32: 42001392 | BP32: 0.31892289 | BR32: -93303529 | BS32: 72444291 | BT32: 49772693 | BU32: -1.6574782e+08 | BV32: -1.4307622e+08 | BW32: 47362815 | BX32: -2.9699743 | CC32: 0 | CD32: 0 | CK32: 0 | CL32: 0 | CP32: 3.9128585e+08 | CQ32: 6.1922034e+08 | CR32: 5.3436207e+08 | CS32: -2.279345e+08 | CT32: -1.4307622e+08 | CU32: -5.1787429e+08 | CV32: -1.7555614 | CX32: 7.873783e+08 | DB32: -4.2071527e+08 | DC32: -2.871523 | DD32: -1 | DE32: -1 | DF32: -1
B33: Dont Taxe sur l'entrant international | D33: 1856925 | E33: 2398869.4 | F33: -541944.4 | G33: 1760251 | H33: 0.054920577 | J33: 1747557 | K33: 2446846.8 | L33: -699289.79 | M33: 1899008.5 | N33: -0.079752934 | P33: 2434068 | Q33: 2936216.2 | R33: -502148.15 | S33: 2089205.5 | T33: 0.16506873 | V33: 1691298 | W33: 2554839.3 | X33: 1892353.1 | Y33: -863541.28 | Z33: -201055.05 | AA33: 1942793.5 | AB33: -0.12945045 | AD33: 738171 | AE33: 2554839.3 | AF33: 1486970.7 | AH33: -748799.7 | AI33: 1897151.5 | AJ33: -0.61090561 | AL33: 1710576 | AM33: 1046374.4 | AN33: 634527.7 | AO33: 664201.57 | AP33: 1076048.3 | AQ33: 2329627.5 | AR33: -0.26572982 | AT33: 1098090 | AU33: 562837.83 | AV33: 1071301.9 | AW33: 535252.17 | AX33: 26788.083 | AY33: 1209159 | AZ33: -0.091856406 | BB33: 1500770 | BC33: 555209.45 | BD33: 490545.67 | BE33: 945560.55 | BF33: 1010224.3 | BG33: 1167453 | BH33: 0.28550785 | BJ33: 622456 | BK33: 1122662.5 | BL33: 500308 | BO33: 2796255.5 | BP33: -0.77739659 | BR33: 1824606 | BS33: 1149115.8 | BT33: 535323.4 | BU33: 675490.24 | BV33: 1289282.6 | BW33: 1509335.6 | BX33: 0.20888027 | CP33: 15224517 | CQ33: 17327811 | CR33: 13935234 | CS33: -2103293.9 | CT33: 1289282.6 | CU33: 18600241 | CV33: -0.18148817 | CX33: 21282122 | DB33: 21676257 | DC33: -0.018182799 | DD33: -1
B34: Dont la Turtel | F34: 0 | L34: 0 | R34: 0 | AA34: 0 | AH34: 0 | AO34: 0 | AP34: 0 | BE34: 0 | BF34: 0 | BL34: 49401317 | BO34: 0 | CP34: 0 | CQ34: 0 | CR34: 0 | CS34: 0 | CT34: 0 | CU34: 0 | DB34: 0
B35: Dont Autres impôts | D35: 51704906 | E35: 53925285 | F35: -2220379.4 | G35: -9.0258118e+08 | H35: -1.0572856 | J35: 49053618 | K35: 51643421 | L35: -2589803.1 | M35: 34526341 | N35: 0.42075924 | P35: 49237242 | Q35: 56002477 | R35: -6765234.2 | S35: 33687231 | T35: 0.46159959 | V35: 53580405 | W35: 57914646 | X35: 49527306 | Y35: -4334240.9 | Z35: 4053099.6 | AA35: 38619731 | AB35: 0.38738423 | AD35: 51085643 | AE35: 60152885 | AF35: 53030861 | AG35: -9067241.4 | AH35: -1945218 | AI35: 44391303 | AJ35: 0.15080297 | AL35: 54459590 | AM35: 62690381 | AN35: 57634836 | AO35: -8230790.7 | AP35: -3175245.8 | AQ35: 43702327 | AR35: 0.24614853 | AT35: 53850878 | AU35: 66246254 | AV35: 50276037 | AW35: -12395376 | AX35: 3574840.9 | AY35: 43333812 | AZ35: 0.24269884 | BB35: 53443040 | BC35: 52805381 | BD35: 51000000 | BE35: 637659.89 | BF35: 2443040.4 | BG35: 42787289 | BH35: 0.24904012 | BJ35: 54774141 | BK35: 69216629 | BL35: 49401317 | BM35: -14442488 | BN35: 5372824.5 | BO35: 39205136 | BP35: 0.39711645 | BR35: -95128135 | BS35: 71295175 | BT35: 49237369 | BU35: -1.6642331e+08 | BV35: -1.443655e+08 | BW35: 45853479 | BX35: -3.074611 | CC35: 0 | CD35: 0 | CK35: 0 | CL35: 0 | CP35: 3.7606133e+08 | CQ35: 6.0189253e+08 | CR35: 5.2042683e+08 | CS35: -2.258312e+08 | CT35: -1.443655e+08 | CU35: -5.3647453e+08 | CV35: -1.7009864 | CX35: 7.6609618e+08 | DB35: -4.4239152e+08 | DC35: -2.7317153 | DD35: -1 | DE35: -1 | DF35: -1
CR36: 0
B37: Provision clients, R&C & NC | D37: 105300000 | E37: 105300000 | F37: 0 | G37: 2000000 | H37: ns | J37: 3300000 | K37: 3300000 | L37: 0 | M37: -10562108 | N37: -1.3124376 | P37: 20747495 | Q37: 3300000 | R37: 17447495 | S37: 7053853.3 | T37: 1.9412995 | V37: 5300000 | W37: 3300000 | X37: 3300000 | Y37: 2000000 | Z37: 2000000 | AA37: 2000000 | AB37: 1.65 | AD37: 9300000 | AE37: 3300000 | AF37: 3300000 | AG37: 6000000 | AH37: 6000000 | AI37: 3380548 | AJ37: 1.7510333 | AL37: 24142710 | AM37: 3300000 | AN37: 3300000 | AO37: 20842710 | AP37: 20842710 | AQ37: -2619452 | AR37: -10.216703 | AT37: 10800000 | AU37: 3300000 | AV37: 3300000 | AW37: 7500000 | AX37: 7500000 | AY37: 3380548 | AZ37: 2.1947483 | BB37: 12300000 | BC37: 3300000 | BD37: 3300000 | BE37: 9000000 | BF37: 9000000 | BG37: 1880548 | BH37: 5.5406467 | BJ37: 60300000 | BK37: 3300000 | BL37: 3300000 | BM37: 57000000 | BN37: 57000000 | BO37: 2663346.3 | BP37: 21.64069 | BR37: 15506115 | BS37: 3300000 | BT37: 3300000 | BU37: 12206115 | BV37: 12206115 | BW37: 837762.67 | BX37: 17.508959 | BZ37: 0 | CA37: 0 | CB37: 0 | CC37: 0 | CD37: 0 | CE37: 0 | CH37: 0 | CI37: 0 | CJ37: 0 | CK37: 0 | CL37: 0 | CM37: 0 | CP37: 266996320 | CQ37: 135000000 | CR37: 254790205 | CS37: 131996320 | CT37: 12206115 | CU37: 10015047 | CV37: ns | CX37: 141600000 | CY37: 0 | CZ37: 0 | DA37: 0 | DB37: 84281783 | DC37: 0.68007836 | DD37: -1 | DE37: -1 | DF37: -1
B38: Prov. Créances clients | D38: 104000000 | E38: 104000000 | F38: 0 | G38: 2000000 | H38: ns | J38: 2000000 | K38: 2000000 | L38: 0 | M38: -10562108 | N38: -1.1893561 | P38: 19505495 | Q38: 2000000 | R38: 17505495 | S38: 2912209.3 | T38: 5.6978342 | V38: 4000000 | W38: 2000000 | X38: 2000000 | Y38: 2000000 | Z38: 2000000 | AA38: 2000000 | AB38: 1 | AD38: 8000000 | AE38: 2000000 | AF38: 2000000 | AG38: 6000000 | AH38: 6000000 | AI38: 2000000 | AJ38: 3 | AL38: 22842710 | AM38: 2000000 | AN38: 2000000 | AO38: 20842710 | AP38: 20842710 | AQ38: -4000000 | AR38: -6.7106775 | AT38: 9500000 | AU38: 2000000 | AV38: 2000000 | AW38: 7500000 | AX38: 7500000 | AY38: 2000000 | AZ38: 3.75 | BB38: 11000000 | BC38: 2000000 | BD38: 2000000 | BE38: 9000000 | BF38: 9000000 | BG38: 500000 | BH38: ns | BJ38: 2000000 | BK38: 2000000 | BL38: 2000000 | BM38: 0 | BN38: 0 | BO38: 1843333.3 | BP38: 0.084990958 | BR38: 14000000 | BS38: 2000000 | BT38: 2000000 | BU38: 12000000 | BV38: 12000000 | BW38: -1923333.3 | BX38: -8.2790295 | CC38: 0 | CD38: 0 | CK38: 0 | CL38: 0 | CP38: 196848205 | CQ38: 122000000 | CR38: 184848205 | CS38: 74848205 | CT38: 12000000 | CU38: -3229898.4 | CV38: - | CX38: 126000000 | DB38: 68468032 | DC38: 0.84027488 | DD38: -1 | DE38: -1 | DF38: -1
B39: Prov. R&C | E39: 0 | F39: 0 | L39: 0 | Q39: 0 | R39: 0 | S39: 0 | Y39: 0 | Z39: 0 | AG39: 0 | AH39: 0 | AO39: 0 | AP39: 0 | AW39: 0 | AX39: 0 | BD39: 0 | BE39: 0 | BF39: 0 | BJ39: 52000000 | BK39: 0 | BM39: 52000000 | BN39: 52000000 | BO39: 0 | BU39: 0 | BV39: 0 | CC39: 0 | CD39: 0 | CK39: 0 | CL39: 0 | CP39: 52000000 | CQ39: 0 | CR39: 52000000 | CS39: 52000000 | CT39: 0 | CU39: 0 | CX39: 0 | DB39: 0 | DE39: #DIV/0! | DF39: #DIV/0!
B40: PIDR | D40: 1300000 | E40: 1300000 | F40: 0 | J40: 1300000 | K40: 1300000 | L40: 0 | P40: 1300000 | Q40: 1300000 | R40: 0 | S40: 4141644 | T40: -0.68611498 | V40: 1300000 | W40: 1300000 | X40: 1300000 | Y40: 0 | Z40: 0 | AD40: 1300000 | AE40: 1300000 | AF40: 1300000 | AG40: 0 | AH40: 0 | AI40: 1380548 | AJ40: -0.058344947 | AL40: 1300000 | AM40: 1300000 | AN40: 1300000 | AO40: 0 | AP40: 0 | AQ40: 1380548 | AR40: -0.058344947 | AT40: 1300000 | AU40: 1300000 | AV40: 1300000 | AW40: 0 | AX40: 0 | AY40: 1380548 | AZ40: -0.058344947 | BB40: 1300000 | BC40: 1300000 | BD40: 1300000 | BE40: 0 | BF40: 0 | BG40: 1380548 | BH40: -0.058344947 | BJ40: 6300000 | BK40: 1300000 | BL40: 1300000 | BM40: 5000000 | BN40: 5000000 | BO40: 0 | BR40: 1300000 | BS40: 1300000 | BT40: 1300000 | BU40: 0 | BV40: 0 | BW40: 2761096 | BX40: -0.52917247 | CC40: 0 | CD40: 0 | CK40: 0 | CL40: 0 | CP40: 18000000 | CQ40: 13000000 | CR40: 18000000 | CS40: 5000000 | CT40: 0 | CU40: 12424932 | CV40: ns | CX40: 15600000 | DB40: 16566573 | DC40: -0.058344758 | DD40: -1 | DE40: -1 | DF40: -1
B41: Autres provisions (Stock) | F41: 0 | L41: 0 | P41: -58000 | R41: -58000 | Y41: 0 | Z41: 0 | AG41: 0 | AH41: 0 | AO41: 0 | AP41: 0 | AW41: 0 | AX41: 0 | BD41: 0 | BE41: 0 | BF41: 0 | BM41: 0 | BN41: 0 | BO41: 820013 | BP41: -1 | BR41: 206115 | BU41: 206115 | BV41: 206115 | CC41: 0 | CD41: 0 | CK41: 0 | CL41: 0 | CP41: 148115 | CQ41: 0 | CR41: -58000 | CS41: 148115 | CT41: 206115 | CU41: 820013 | CV41: -0.81937481 | DB41: -752822 | DC41: -1 | DD41: -1
CR42: 0
B43: Ecart de change sur exploitation | D43: 250000 | E43: 250000 | F43: 0 | G43: 0 | J43: 250000 | K43: 250000 | L43: 0 | M43: 0 | P43: 250000 | Q43: 250000 | R43: 0 | S43: 0 | V43: 250000 | W43: 250000 | X43: 250000 | Y43: 0 | Z43: 0 | AD43: 0 | AE43: 250000 | AF43: 250000 | AG43: -250000 | AH43: -250000 | AI43: 0 | AL43: 0 | AM43: 250000 | AN43: 250000 | AO43: -250000 | AP43: -250000 | AQ43: 0 | AT43: 250000 | AU43: 250000 | AV43: 250000 | AW43: 0 | AX43: 0 | AY43: 0 | BB43: 250000 | BC43: 250000 | BD43: 250000 | BE43: 0 | BF43: 0 | BG43: 0 | BJ43: -237000 | BK43: 250000 | BL43: 250000 | BM43: -487000 | BN43: -487000 | BO43: 0 | BS43: 250000 | BT43: 250000 | BU43: -250000 | BV43: -250000 | BW43: 0 | CC43: 0 | CD43: 0 | CJ43: 250000 | CK43: 0 | CL43: -250000 | CM43: 0 | CP43: 1263000 | CQ43: 2500000 | CR43: 1513000 | CS43: -1237000 | CT43: -250000 | CU43: 0 | CX43: 3000000 | DB43: 0

Sheet P&L
B2: P&L | D2: JANVIER | J2: FEVRIER | P2: MARS | V2: AVRIL | AD2: MAI | AL2: JUIN | AT2: JUILLET | BB2: AOUT | BJ2: SEPTEMBRE | BR2: OCTOBRE | BZ2: NOVEMBRE | CH2: DECEMBRE | CP2: CUMUL | CX2: ANNUEL
B3: (En Millions FCFA) | D3: 2025 Réel | E3: 2025 Budget | F3: Ecart / Budget | G3: 2024 Réel | H3: Evol % | J3: 2025 Réel | K3: 2025 Budget | L3: Ecart / Budget | M3: 2024 Réel | N3: Evol % | P3: 2025 Réel | Q3: 2025 Budget | R3: Ecart / Budget | S3: 2024 Réel | T3: Evol % | V3: 2025 Réel | W3: 2025 Budget | X3: 2025 Actu 1 | Y3: Ecart / Budget | Z3: Ecart / Actu 1 | AA3: 2024 Réel | AB3: Evol % | AD3: 2025 Réel | AE3: 2025 Budget | AF3: 2025 Actu 1 | AG3: Ecart / Budget | AH3: Ecart / Actu 1 | AI3: 2024 Réel | AJ3: Evol % | AL3: 2025 Réel | AM3: 2025 Budget | AN3: 2025 Actu 1 | AO3: Ecart / Budget | AP3: Ecart / Actu 1 | AQ3: 2024 Réel | AR3: Evol % | AT3: 2025 Réel | AU3: 2025 Budget | AV3: 2025 Actu 2 | AW3: Ecart / Budget | AX3: Ecart / Actu 2 | AY3: 2024 Réel | AZ3: Evol % | BB3: 2025 Réel | BC3: 2025 Budget | BD3: 2025 Actu3 | BE3: Ecart / Budget | BF3: Ecart / Actu 3 | BG3: 2024 Réel | BH3: Evol % | BJ3: 2025 Réel | BK3: 2025 Budget | BL3: 2025 Actu3 | BM3: Ecart / Budget | BN3: Ecart / Actu 3 | BO3: 2024 Réel | BP3: Evol % | BR3: 2025 Réel | BS3: 2025 Budget | BT3: 2025 Actu 3 | BU3: Ecart / Budget | BV3: Ecart / Actu 3 | BW3: 2024 Réel | BX3: Evol % | BZ3: 2025 Réel | CA3: 2025 Budget | CB3: 2025 Actu 3 | CC3: Ecart / Budget | CD3: Ecart / Actu 3 | CE3: 2024 Réel | CF3: Evol % | CH3: 2025 Réel | CI3: 2025 Budget | CJ3: 2025 Actu 3 | CK3: Ecart / Budget | CL3: Ecart / Actu 3 | CM3: 2024 Réel | CN3: Evol % | CP3: 2025 Réel | CQ3: 2025 Budget | CR3: 2025 Actu 3 | CS3: Ecart / Budget | CT3: Ecart / Actu 3 | CU3: 2024 Réel | CV3: Evol % | CX3: 2025 Budget | CY3: 2024 Actu 1 | CZ3: 2024 Actu 2 | DA3: 2025 Actu 3 | DB3: 2024 Réel | DC3: Bud / 2024 (%) | DD3: Actu 1 / 2023 (%) | DE3: Actu 2 / 2023 (%) | DF3: Actu 3 / 2019 (%)
B5: Chiffre d'affaires | D5: 3.6285608e+08 | E5: 3.5669185e+08 | F5: 6164234.3 | G5: 4.029166e+08 | H5: -0.099426324 | J5: 3.1716648e+08 | K5: 3.2553763e+08 | L5: -8371149.5 | M5: 3.2662376e+08 | N5: -0.028954673 | P5: 3.4779065e+08 | Q5: 4.0733975e+08 | R5: -59549100 | S5: 3.7071492e+08 | T5: -0.061837992 | V5: 3.886432e+08 | W5: 4.7545806e+08 | X5: 3.9549e+08 | Y5: -86814858 | Z5: -6846804.5 | AA5: 3.9318629e+08 | AB5: -0.011554549 | AD5: 3.7969038e+08 | AE5: 5.1915384e+08 | AF5: 4.6467864e+08 | AG5: -1.3946345e+08 | AH5: -84988254 | AI5: 3.786904e+08 | AJ5: 0.0026406309 | AL5: 3.5631472e+08 | AM5: 5.6135971e+08 | AN5: 5.7117526e+08 | AO5: -2.0504499e+08 | AP5: -2.1486054e+08 | AQ5: 3.6322803e+08 | AR5: -0.019032983 | AT5: 3.9726618e+08 | AU5: 5.985446e+08 | AV5: 4.2375612e+08 | AW5: -2.0127842e+08 | AX5: -26489944 | AY5: 3.8931613e+08 | AZ5: 0.02042054 | BB5: 3.9608218e+08 | BC5: 6.2103624e+08 | BD5: 3.9999793e+08 | BE5: -2.2495406e+08 | BF5: -3915749 | BG5: 3.7892957e+08 | BH5: 0.045265947 | BJ5: 3.8907851e+08 | BK5: 6.3756647e+08 | BL5: 3.9831703e+08 | BM5: -2.4848796e+08 | BN5: -9238517.4 | BO5: 3.6587225e+08 | BP5: 0.063427215 | BR5: 4.3433758e+08 | BS5: 6.7285925e+08 | BT5: 4.0363699e+08 | BU5: -2.3852166e+08 | BV5: 30700598 | BW5: 3.6389707e+08 | BX5: 0.19357264 | BZ5: 0 | CA5: 0 | CB5: 0 | CC5: 0 | CD5: 0 | CE5: 0 | CH5: 0 | CI5: 0 | CJ5: 0 | CK5: 0 | CL5: 0 | CM5: 0 | CP5: 3.769226e+09 | CQ5: 5.1755474e+09 | CR5: 3.7385254e+09 | CS5: -1.4063214e+09 | CT5: 30700598 | CU5: 3.733375e+09 | CV5: 0.0096028226 | CX5: 6.6367354e+09 | CY5: 0 | CZ5: 0 | DA5: 4.557486e+09 | DB5: 4.4447559e+09 | DC5: 0.49316083 | DD5: -1 | DE5: -1 | DF5: 0.025362485
B6: Mobile | D6: 3.6285608e+08 | E6: 3.5669185e+08 | F6: 6164234.3 | G6: 4.029166e+08 | H6: -0.099426324 | J6: 3.1716648e+08 | K6: 3.2553763e+08 | L6: -8371149.5 | M6: 3.2662376e+08 | N6: -0.028954673 | P6: 3.4779065e+08 | Q6: 4.0733975e+08 | R6: -59549100 | S6: 3.7071492e+08 | T6: -0.061837992 | V6: 3.886432e+08 | W6: 4.7545806e+08 | X6: 3.9549e+08 | Y6: -86814858 | Z6: -6846804.5 | AA6: 3.9318629e+08 | AB6: -0.011554549 | AD6: 3.7969038e+08 | AE6: 5.1915384e+08 | AF6: 4.6467864e+08 | AG6: -1.3946345e+08 | AH6: -84988254 | AI6: 3.786904e+08 | AJ6: 0.0026406309 | AL6: 3.5631472e+08 | AM6: 5.6135971e+08 | AN6: 5.7117526e+08 | AO6: -2.0504499e+08 | AP6: -2.1486054e+08 | AQ6: 3.6322803e+08 | AR6: -0.019032983 | AT6: 3.9726618e+08 | AU6: 5.985446e+08 | AV6: 4.2375612e+08 | AW6: -2.0127842e+08 | AX6: -26489944 | AY6: 3.8931613e+08 | AZ6: 0.02042054 | BB6: 3.9608218e+08 | BC6: 6.2103624e+08 | BD6: 3.9999793e+08 | BE6: -2.2495406e+08 | BF6: -3915749 | BG6: 3.7892957e+08 | BH6: 0.045265947 | BJ6: 3.8907851e+08 | BK6: 6.3756647e+08 | BL6: 3.9831703e+08 | BM6: -2.4848796e+08 | BN6: -9238517.4 | BO6: 3.6587225e+08 | BP6: 0.063427215 | BR6: 4.3433758e+08 | BS6: 6.7285925e+08 | BT6: 4.0363699e+08 | BU6: -2.3852166e+08 | BV6: 30700598 | BW6: 3.6389707e+08 | BX6: 0.19357264 | BZ6: 0 | CA6: 0 | CB6: 0 | CC6: 0 | CD6: 0 | CE6: 0 | CH6: 0 | CI6: 0 | CJ6: 0 | CK6: 0 | CL6: 0 | CM6: 0 | CP6: 3.769226e+09 | CQ6: 5.1755474e+09 | CR6: 3.7385254e+09 | CS6: -1.4063214e+09 | CT6: 30700598 | CU6: 3.733375e+09 | CV6: 0.0096028226 | CX6: 6.6367354e+09 | CY6: 0 | CZ6: 0 | DA6: 4.557486e+09 | DB6: 4.4447559e+09 | DC6: 0.49316083 | DD6: -1 | DE6: -1 | DF6: 0.025362485
B8: Coût des ventes | D8: -73787245 | E8: -85471346 | F8: 11684101 | G8: -84251770 | H8: -0.12420541 | J8: -64966062 | K8: -82284219 | L8: 17318157 | M8: -69745927 | N8: -0.06853253 | P8: -78088168 | Q8: -97595315 | R8: 19507147 | S8: -76053440 | T8: 0.026753924 | V8: -82184243 | W8: -1.2928608e+08 | X8: -90516339 | Y8: 47101834 | Z8: 8332095.6 | AA8: 3.1623181e+08 | AB8: -1.2598861 | AD8: -82728092 | AE8: -1.3678342e+08 | AF8: -1.0271448e+08 | AG8: 54055333 | AH8: 19986392 | AI8: -79178107 | AJ8: 0.04483544 | AL8: -71948223 | AM8: -1.4179557e+08 | AN8: -1.3206185e+08 | AO8: 69847345 | AP8: 60113624 | AQ8: -12148644 | AR8: 4.9223256 | AT8: -81951350 | AU8: -1.326324e+08 | AV8: -1.0200681e+08 | AW8: 50681052 | AX8: 20055464 | AY8: -79433159 | AZ8: 0.031702018 | BB8: -83751658 | BC8: -1.3325292e+08 | BD8: -87162513 | BE8: 49501266 | BF8: 3410854.3 | BG8: -75514484 | BH8: 0.10908072 | BJ8: -94659802 | BK8: -1.3377783e+08 | BL8: -1.0584385e+08 | BM8: 39118029 | BN8: 11184046 | BO8: -1.334427e+08 | BP8: -0.29063336 | BR8: -94548985 | BS8: -1.3920701e+08 | BT8: -97870216 | BU8: 44658027 | BV8: 3321232 | BW8: -71813141 | BX8: 0.31659727 | BZ8: 0 | CA8: 0 | CB8: 0 | CC8: 0 | CD8: 0 | CE8: 0 | CH8: 0 | CI8: 0 | CJ8: 0 | CK8: 0 | CL8: 0 | CM8: 0 | CP8: -8.0861383e+08 | CQ8: -1.2130953e+09 | CR8: -8.1193506e+08 | CS8: 4.0448149e+08 | CT8: 3321232 | CU8: -3.6488258e+08 | CV8: 1.2160933 | CX8: -1.5145497e+09 | CY8: 0 | CZ8: 0 | DA8: -1.1992434e+09 | DB8: -5.08482e+08 | DC8: 1.9785708 | DD8: -1 | DE8: -1 | DF8: 1.3584776
B9: Mobile | D9: -73787245 | E9: -85471346 | F9: 11684101 | G9: -84251770 | H9: -0.12420541 | J9: -64966062 | K9: -82284219 | L9: 17318157 | M9: -69745927 | N9: -0.06853253 | P9: -78088168 | Q9: -97595315 | R9: 19507147 | S9: -76053440 | T9: 0.026753924 | V9: -82184243 | W9: -1.2928608e+08 | X9: -90516339 | Y9: 47101834 | Z9: 8332095.6 | AA9: 3.1623181e+08 | AB9: -1.2598861 | AD9: -82728092 | AE9: -1.3678342e+08 | AF9: -1.0271448e+08 | AG9: 54055333 | AH9: 19986392 | AI9: -79178107 | AJ9: 0.04483544 | AL9: -71948223 | AM9: -1.4179557e+08 | AN9: -1.3206185e+08 | AO9: 69847345 | AP9: 60113624 | AQ9: -12148644 | AR9: 4.9223256 | AT9: -81951350 | AU9: -1.326324e+08 | AV9: -1.0200681e+08 | AW9: 50681052 | AX9: 20055464 | AY9: -79433159 | AZ9: 0.031702018 | BB9: -83751658 | BC9: -1.3325292e+08 | BD9: -87162513 | BE9: 49501266 | BF9: 3410854.3 | BG9: -75514484 | BH9: 0.10908072 | BJ9: -94659802 | BK9: -1.3377783e+08 | BL9: -1.0584385e+08 | BM9: 39118029 | BN9: 11184046 | BO9: -1.334427e+08 | BP9: -0.29063336 | BR9: -94548985 | BS9: -1.3920701e+08 | BT9: -97870216 | BU9: 44658027 | BV9: 3321232 | BW9: -71813141 | BX9: 0.31659727 | BZ9: 0 | CA9: 0 | CB9: 0 | CC9: 0 | CD9: 0 | CE9: 0 | CH9: 0 | CI9: 0 | CJ9: 0 | CK9: 0 | CL9: 0 | CM9: 0 | CP9: -8.0861383e+08 | CQ9: -1.2130953e+09 | CR9: -8.1193506e+08 | CS9: 4.0448149e+08 | CT9: 3321232 | CU9: -3.6488258e+08 | CV9: 1.2160933 | CX9: -1.5145497e+09 | CY9: 0 | CZ9: 0 | DA9: -1.1992434e+09 | DB9: -5.08482e+08 | DC9: 1.9785708 | DD9: -1 | DE9: -1 | DF9: 1.3584776
B11: Marge Brute | D11: 2.8906884e+08 | E11: 2.712205e+08 | F11: 17848335 | G11: 3.1866483e+08 | H11: -0.092874982 | J11: 2.5220042e+08 | K11: 2.4325341e+08 | L11: 8947007.5 | M11: 2.5687784e+08 | N11: -0.018208732 | P11: 2.6970248e+08 | Q11: 3.0974444e+08 | R11: -40041953 | S11: 2.9466148e+08 | T11: -0.08470396 | V11: 3.0645896e+08 | W11: 3.4617198e+08 | X11: 3.0497366e+08 | Y11: -39713024 | Z11: 1485291 | AA11: 7.094181e+08 | AB11: -0.56801362 | AD11: 2.9696229e+08 | AE11: 3.8237041e+08 | AF11: 3.6196415e+08 | AG11: -85408121 | AH11: -65001861 | AI11: 2.995123e+08 | AJ11: -0.0085138531 | AL11: 2.843665e+08 | AM11: 4.1956414e+08 | AN11: 4.3911341e+08 | AO11: -1.3519765e+08 | AP11: -1.5474691e+08 | AQ11: 3.5107939e+08 | AR11: -0.19002224 | AT11: 3.1531483e+08 | AU11: 4.659122e+08 | AV11: 3.2174931e+08 | AW11: -1.5059737e+08 | AX11: -6434479.7 | AY11: 3.0988297e+08 | AZ11: 0.017528728 | BB11: 3.1233052e+08 | BC11: 4.8778331e+08 | BD11: 3.1283541e+08 | BE11: -1.7545279e+08 | BF11: -504894.71 | BG11: 3.0341509e+08 | BH11: 0.029383613 | BJ11: 2.9441871e+08 | BK11: 5.0378864e+08 | BL11: 2.9247318e+08 | BM11: -2.0936993e+08 | BN11: 1945528.7 | BO11: 2.3242955e+08 | BP11: 0.26670086 | BR11: 3.397886e+08 | BS11: 5.3365224e+08 | BT11: 3.0576677e+08 | BU11: -1.9386364e+08 | BV11: 34021830 | BW11: 2.9208393e+08 | BX11: 0.16332523 | BZ11: 0 | CA11: 0 | CB11: 0 | CC11: 0 | CD11: 0 | CE11: 0 | CH11: 0 | CI11: 0 | CJ11: 0 | CK11: 0 | CL11: 0 | CM11: 0 | CP11: 2.9606121e+09 | CQ11: 3.9624521e+09 | CR11: 2.9265903e+09 | CS11: -1.0018399e+09 | CT11: 34021830 | CU11: 3.3684924e+09 | CV11: -0.1210869 | CX11: 5.1221978e+09 | CY11: 0 | CZ11: 0 | DA11: 3.3582426e+09 | DB11: 3.9362739e+09 | DC11: 0.30128083 | DD11: -1 | DE11: -1 | DF11: -0.14684734
B12: % CA | D12: 0.79664873 | E12: 0.76037763 | F12: 0.0362711 | G12: 0.79089526 | H12: 0.0072746311 | J12: 0.79516731 | K12: 0.74723592 | L12: 0.047931393 | M12: 0.78646402 | N12: 0.011066365 | P12: 0.77547364 | Q12: 0.76040808 | R12: 0.015065568 | S12: 0.79484656 | T12: -0.024373155 | V12: 0.78853549 | W12: 0.728081 | X12: 0.77112863 | Y12: 0.060454488 | Z12: 0.017406861 | AA12: 1.8042798 | AB12: -0.56296386 | AD12: 0.78211697 | AE12: 0.73652622 | AF12: 0.77895587 | AG12: 0.04559075 | AH12: 0.0031610964 | AI12: 0.79091599 | AJ12: -0.011125107 | AL12: 0.79807676 | AM12: 0.74740694 | AN12: 0.76878927 | AO12: 0.05066982 | AP12: 0.029287488 | AQ12: 0.96655367 | AR12: -0.17430684 | AT12: 0.79371173 | AU12: 0.77840849 | AV12: 0.75927943 | AW12: 0.015303246 | AX12: 0.034432304 | AY12: 0.79596746 | AZ12: -0.0028339418 | BB12: 0.78854979 | BC12: 0.78543454 | BD12: 0.78209259 | BE12: 0.0031152503 | BF12: 0.0064572043 | BG12: 0.80071631 | BH12: -0.015194539 | BJ12: 0.75670771 | BK12: 0.7901743 | BL12: 0.73427235 | BM12: -0.033466591 | BN12: 0.02243536 | BO12: 0.63527515 | BP12: 0.19114956 | BR12: 0.78231452 | BS12: 0.79311125 | BT12: 0.75752912 | BU12: -0.010796724 | BV12: 0.024785405 | BW12: 0.80265535 | BX12: -0.025341916 | BZ12: #DIV/0! | CA12: #DIV/0! | CB12: #DIV/0! | CC12: #DIV/0! | CD12: #DIV/0! | CE12: #DIV/0! | CH12: #DIV/0! | CI12: #DIV/0! | CJ12: #DIV/0! | CK12: #DIV/0! | CL12: #DIV/0! | CM12: #DIV/0! | CP12: 0.78546953 | CQ12: 0.76561024 | CR12: 0.78281943 | CS12: 0.71238333 | CT12: 0.0026500945 | CU12: 0.90226469 | CV12: -11.679516 | CX12: 0.77179478 | CY12: #DIV/0! | CZ12: #DIV/0! | DA12: 0.73686295 | DB12: 0.88559957 | DC12: -11.380478 | DF12: -14.873661
B14: Coûts opérationnels | D14: 4.3008703e+08 | E14: 5.0533119e+08 | F14: -75244162 | G14: 5.1671866e+08 | H14: -0.16765726 | J14: -2.7538477e+08 | K14: -2.8346913e+08 | L14: 8084361.8 | M14: -2.6702784e+08 | N14: 0.03129612 | P14: -2.7879471e+08 | Q14: -3.0116296e+08 | R14: 22368251 | S14: -2.892103e+08 | T14: -0.036013923 | V14: -3.3104575e+08 | W14: -3.1990533e+08 | X14: -3.1413257e+08 | Y14: -11140414 | Z14: -16913179 | AA14: -3.250663e+08 | AB14: 0.018394548 | AD14: -2.9949904e+08 | AE14: -3.40253e+08 | AF14: -3.3599681e+08 | AG14: 40753967 | AH14: 36497772 | AI14: -2.8998261e+08 | AJ14: 0.032817226 | AL14: -3.849825e+08 | AM14: -3.415031e+08 | AN14: -3.405865e+08 | AO14: -43479395 | AP14: -44395993 | AQ14: -3.447776e+08 | AR14: 0.1166111 | AT14: -4.0543024e+08 | AU14: -3.8130516e+08 | AV14: -3.1758136e+08 | AW14: -24125080 | AX14: -87848877 | AY14: -3.0837419e+08 | AZ14: 0.31473465 | BB14: -3.9313047e+08 | BC14: -3.5280266e+08 | BD14: -3.4547022e+08 | BE14: -40327808 | BF14: -47660254 | BG14: -3.0311531e+08 | BH14: 0.29696674 | BJ14: -4.5801206e+08 | BK14: -3.3282608e+08 | BL14: -3.4854651e+08 | BM14: -1.2518598e+08 | BN14: -1.0946555e+08 | BO14: -2.8799012e+08 | BP14: 0.59037419 | BR14: -1.9142916e+08 | BS14: -3.3505833e+08 | BT14: -3.4606173e+08 | BU14: 1.4362917e+08 | BV14: 1.5463257e+08 | BW14: -2.8795142e+08 | BX14: -0.33520329 | BZ14: 0 | CA14: 0 | CB14: 0 | CC14: 0 | CD14: 0 | CE14: 0 | CH14: 0 | CI14: 0 | CJ14: -250000 | CK14: 0 | CL14: 250000 | CP14: -2.5876217e+09 | CQ14: -2.4829546e+09 | CR14: -2.7422542e+09 | CS14: -1.0466709e+08 | CT14: 1.5463257e+08 | CU14: -2.186777e+09 | CV14: 0.18330384 | CX14: -3.1108971e+09 | CY14: 0 | CZ14: 0 | DA14: 0 | DB14: -1.5391511e+09 | DC14: 1.0211772 | DD14: -1 | DE14: -1 | DF14: -1
B15: % CA | D15: -1.1852827 | E15: -1.4167164 | F15: 0.23143372 | G15: -1.2824457 | H15: -0.075763859 | J15: 0.86826569 | K15: 0.87077225 | L15: -0.0025065611 | M15: 0.81753952 | N15: 0.062047354 | P15: 0.80161645 | Q15: 0.73934095 | R15: 0.0622755 | S15: 0.78014207 | T15: 0.027526236 | V15: 0.85179864 | W15: 0.67283608 | X15: 0.79428701 | Y15: 0.17896256 | Z15: 0.057511637 | AA15: 0.82674882 | AB15: 0.030299191 | AD15: 0.78879806 | AE15: 0.65539919 | AF15: 0.7230735 | AG15: 0.13339887 | AH15: 0.065724556 | AI15: 0.76575115 | AJ15: 0.03009712 | AL15: 1.0804563 | AM15: 0.60834986 | AN15: 0.59629072 | AO15: 0.47210648 | AP15: 0.48416562 | AQ15: 0.94920428 | AR15: 0.13827589 | AT15: 1.0205506 | AU15: 0.63705388 | AV15: 0.74944372 | AW15: 0.38349673 | AX15: 0.27110689 | AY15: 0.79209201 | AZ15: 0.28842433 | BB15: 0.99254774 | BC15: 0.56808708 | BD15: 0.86368002 | BE15: 0.42446066 | BF15: 0.12886772 | BG15: 0.79992518 | BH15: 0.24080072 | BJ15: 1.1771713 | BK15: 0.5220257 | BL15: 0.87504797 | BM15: 0.65514562 | BN15: 0.30212334 | BO15: 0.787133 | BP15: 0.49551766 | BR15: 0.44073819 | BS15: 0.49796199 | BT15: 0.85735882 | BU15: -0.057223804 | BV15: -0.41662063 | BW15: 0.79129911 | BX15: -0.44301948 | BZ15: #DIV/0! | CA15: #DIV/0! | CB15: #DIV/0! | CC15: #DIV/0! | CD15: #DIV/0! | CE15: #DIV/0! | CH15: #DIV/0! | CI15: #DIV/0! | CJ15: #DIV/0! | CK15: #DIV/0! | CL15: #DIV/0! | CM15: #DIV/0! | CP15: 0.68651275 | CQ15: 0.47974724 | CR15: 0.73351227 | CS15: -0.074426149 | CU15: 0.58573731 | CV15: 0.17204886 | CX15: 0.46873905 | CY15: #DIV/0! | CZ15: #DIV/0! | DA15: 0 | DB15: 0.34628473 | DC15: 12.245432 | DF15: -34.628473
B17: EBITDA | D17: 7.1915587e+08 | E17: 7.7655169e+08 | F17: -57395826 | G17: 8.3538349e+08 | H17: -0.13913086 | J17: -23184354 | K17: -40215723 | L17: 17031369 | M17: -10149999 | N17: 1.284173 | P17: -9092222.1 | Q17: 8581479.7 | R17: -17673702 | S17: 5451174.4 | T17: -2.6679382 | V17: -24586794 | W17: 26266644 | X17: -9158906.2 | Y17: -50853438 | Z17: -15427888 | AA17: 3.8435179e+08 | AB17: -1.0639695 | AD17: -2536745.8 | AE17: 42117409 | AF17: 25967343 | AG17: -44654155 | AH17: -28504089 | AI17: 9529682.9 | AJ17: -1.2661941 | AL17: -1.00616e+08 | AM17: 78061042 | AN17: 98526906 | AO17: -1.7867704e+08 | AP17: -1.9914291e+08 | AQ17: 6301787 | AR17: -16.966265 | AT17: -90115414 | AU17: 84607038 | AV17: 4167942.5 | AW17: -1.7472245e+08 | AX17: -94283356 | AY17: 1508777 | AZ17: -60.727458 | BB17: -80799952 | BC17: 1.3498065e+08 | BD17: -32634804 | BE17: -2.157806e+08 | BF17: -48165148 | BG17: 299781.73 | BH17: -270.52927 | BJ17: -1.6359335e+08 | BK17: 1.7096256e+08 | BL17: -56073329 | BM17: -3.3455591e+08 | BN17: -1.0752002e+08 | BO17: -55560577 | BP17: 1.9444142 | BR17: 1.4835944e+08 | BS17: 1.9859391e+08 | BT17: -40294960 | BU17: -50234465 | BV17: 1.886544e+08 | BW17: 4132502.6 | BX17: 34.900628 | BZ17: 0 | CA17: 0 | CB17: 0 | CC17: 0 | CD17: 0 | CE17: 0 | CH17: 0 | CI17: 0 | CJ17: -250000 | CK17: 0 | CL17: 250000 | CM17: 0 | CP17: 3.7299047e+08 | CQ17: 1.4794975e+09 | CR17: 1.8433607e+08 | CS17: -1.106507e+09 | CT17: 1.886544e+08 | CU17: 1.1817154e+09 | CV17: ns | CX17: 2.0113007e+09 | CY17: 0 | CZ17: 0 | DA17: 3.3582426e+09 | DB17: 2.3971228e+09 | DC17: -0.16095216 | DD17: -1 | DE17: -1 | DF17: 0.40094725
B18: % CA | D18: 1.9819314 | E18: 2.177094 | F18: -0.19516262 | G18: 2.073341 | H18: -0.044088052 | J18: -0.073098374 | K18: -0.12353633 | L18: 0.050437954 | M18: -0.031075508 | N18: 1.3522826 | P18: -0.026142802 | Q18: 0.021067131 | R18: -0.047209932 | S18: 0.014704491 | T18: -2.7778787 | V18: -0.063263152 | W18: 0.055244923 | X18: -0.023158376 | Y18: -0.11850808 | Z18: -0.040104776 | AA18: 0.97753102 | AB18: -1.0647173 | AD18: -0.0066810904 | AE18: 0.08112703 | AF18: 0.055882369 | AG18: -0.08780812 | AH18: -0.062563459 | AI18: 0.025164839 | AJ18: -1.2654931 | AL18: -0.28237958 | AM18: 0.13905708 | AN18: 0.17249855 | AO18: -0.42143666 | AP18: -0.45487814 | AQ18: 0.017349396 | AR18: -17.276047 | AT18: -0.22683888 | AU18: 0.14135461 | AV18: 0.0098357105 | AW18: -0.36819349 | AX18: -0.23667459 | AY18: 0.0038754546 | AZ18: -59.532199 | BB18: -0.20399795 | BC18: 0.21734746 | BD18: -0.081587432 | BE18: -0.42134541 | BF18: -0.12241052 | BG18: 0.00079112783 | BH18: -258.85713 | BJ18: -0.4204636 | BK18: 0.2681486 | BL18: -0.14077563 | BM18: -0.68861221 | BN18: -0.27968798 | BO18: -0.15185786 | BP18: 1.7687971 | BR18: 0.34157634 | BS18: 0.29514926 | BT18: -0.099829701 | BU18: 0.04642708 | BV18: 0.44140604 | BW18: 0.011356241 | BX18: 29.078293 | BZ18: #DIV/0! | CA18: #DIV/0! | CB18: #DIV/0! | CC18: #DIV/0! | CD18: #DIV/0! | CE18: #DIV/0! | CH18: #DIV/0! | CI18: #DIV/0! | CJ18: #DIV/0! | CK18: #DIV/0! | CL18: #DIV/0! | CM18: #DIV/0! | CP18: 0.098956782 | CQ18: 0.285863 | CR18: 0.049307161 | CS18: -0.18690622 | CT18: -1pt | CU18: 0.31652738 | CV18: -21.75706 | CX18: 0.30305573 | CY18: #DIV/0! | CZ18: #DIV/0! | DA18: 0.73686295 | DB18: 0.53931483 | DC18: -23.62591 | DF18: 19.754812
B20: Amortissements et déprec. Courant | D20: -135314991 | E20: -1.350207e+08 | F20: -294287.25 | G20: -134238751 | H20: 0.0080173571 | J20: -135972076 | K20: -1.350207e+08 | L20: -951372.25 | M20: -134238751 | N20: 0.012912255 | P20: -135465275 | Q20: -2.2235282e+08 | R20: 86887540 | S20: -140848751 | T20: -0.038221681 | V20: -136595055 | W20: -3.0749165e+09 | X20: -1.4037548e+08 | Y20: 2.9383215e+09 | Z20: 3780427.9 | AA20: -136238751 | AB20: 0.0026152912 | AD20: -151953696 | AE20: -2.1479868e+08 | AF20: -2.6744479e+08 | AG20: 62844982 | AH20: 1.1549109e+08 | AI20: -138238751 | AJ20: 0.099212015 | AL20: -159361625 | AM20: -2.1479868e+08 | AN20: -2.6744479e+08 | AO20: 55437053 | AP20: 1.0808317e+08 | AQ20: -139838751 | AR20: 0.1396099 | AT20: -186069893 | AU20: -2.1479868e+08 | AV20: -2.6744479e+08 | AW20: 28728785 | AX20: 81374899 | AY20: -137000000 | AZ20: 0.3581744 | BB20: -242278820 | BD20: -2.6744479e+08 | BE20: -242278820 | BF20: 25165973 | BG20: -136812004 | BH20: 0.77088861 | BJ20: -284535957 | BK20: -2.1479868e+08 | BL20: -2.6744479e+08 | BM20: -69737279 | BN20: -17091163 | BO20: -136812004 | BP20: 1.0797587 | BR20: -257341525 | BS20: -2.1479868e+08 | BT20: -2.674448e+08 | BU20: -42542847 | BV20: 10103270 | BW20: -136812004 | BX20: 0.88098644 | CC20: 0 | CD20: 0 | CK20: 0 | CL20: 0 | CP20: -1876888913 | CQ20: -4.6413042e+09 | CR20: -1.8349922e+09 | CS20: 2.7644152e+09 | CT20: -41896730 | CU20: -1371078518 | CV20: 0.36891424 | CX20: -5.2857002e+09 | DB20: -1645356299 | DC20: 2.2124958 | DD20: -1 | DE20: -1 | DF20: -1
B21: Dotations (Amo. et Pv NC) | D21: 0 | E21: 0 | F21: 0 | G21: 0 | J21: 0 | K21: 0 | L21: 0 | M21: 0 | P21: 0 | Q21: 0 | R21: 0 | S21: 0 | V21: 0 | W21: 0 | X21: 0 | Y21: 0 | Z21: 0 | AA21: 0 | AD21: 0 | AE21: 0 | AF21: 0 | AG21: 0 | AH21: 0 | AI21: 0 | AL21: 0 | AM21: 0 | AN21: 0 | AO21: 0 | AP21: 0 | AQ21: 0 | AT21: 0 | AU21: 0 | AV21: 0 | AW21: 0 | AX21: 0 | AY21: 0 | BB21: 0 | BC21: 0 | BD21: 0 | BE21: 0 | BF21: 0 | BG21: 0 | BJ21: 0 | BK21: 0 | BL21: 0 | BM21: 0 | BN21: 0 | BO21: 0 | BS21: 0 | BT21: 0 | BU21: 0 | BV21: 0 | BW21: 0 | BZ21: 0 | CA21: 0 | CB21: 0 | CC21: 0 | CD21: 0 | CE21: 0 | CH21: 0 | CI21: 0 | CJ21: 0 | CK21: 0 | CL21: 0 | CM21: 0 | CP21: 0 | CQ21: 0 | CR21: 0 | CS21: 0 | CT21: 0 | CU21: 0 | CX21: 0 | CY21: 0 | CZ21: 0 | DA21: 0 | DB21: 0
B22: Autres non courant | E22: 0 | F22: 0 | G22: 0 | K22: 0 | L22: 0 | M22: 0 | P22: 2.4452509e+09 | Q22: 0 | R22: 2.4452509e+09 | S22: 3150000 | T22: 775.27012 | W22: 0 | X22: 0 | Y22: 0 | Z22: 0 | AA22: 0 | AG22: 0 | AH22: 0 | AL22: -125700000 | AM22: 0 | AN22: 0 | AO22: -125700000 | AP22: -125700000 | AQ22: 129000000 | AR22: -1.9744186 | AW22: 0 | AX22: 0 | AY22: 0 | BB22: 0 | BC22: 0 | BD22: 0 | BE22: 0 | BF22: 0 | BG22: 0 | BJ22: 300000 | BK22: 0 | BL22: 0 | BM22: 300000 | BN22: 300000 | BO22: 0 | BR22: 96790000 | BS22: 0 | BT22: 0 | BU22: 96790000 | BV22: 96790000 | BW22: -60000000 | BX22: -2.6131667 | CA22: 0 | CB22: 0 | CC22: 0 | CD22: 0 | CE22: 0 | CI22: 0 | CJ22: 0 | CK22: 0 | CL22: 0 | CP22: 2.4686409e+09 | CQ22: 0 | CR22: 2.4452509e+09 | CS22: 2.4686409e+09 | CT22: 23390000 | CU22: 72150000 | CV22: 33.215397 | CX22: 3.4420964e+09 | CY22: 90000000 | CZ22: 0 | DA22: 0 | DB22: 1.1077498e+09 | DC22: 2.1072869 | DD22: -0.91875422 | DE22: -1 | DF22: -1
B23: +/- value de cession d'immob. | D23: 0 | E23: 0 | F23: 0 | G23: 0 | J23: 0 | K23: 0 | L23: 0 | M23: 0 | P23: 0 | Q23: 0 | R23: 0 | S23: 0 | V23: 0 | W23: 0 | X23: 0 | Y23: 0 | Z23: 0 | AA23: 0 | AD23: 0 | AF23: 0 | AG23: 0 | AH23: 0 | AI23: 0 | AL23: 0 | AM23: 0 | AN23: 0 | AO23: 0 | AP23: 0 | AQ23: 0 | AT23: 0 | AU23: 0 | AV23: 0 | AW23: 0 | AX23: 0 | AY23: 0 | BB23: 0 | BC23: 0 | BD23: 0 | BE23: 0 | BF23: 0 | BG23: 0 | BJ23: 0 | BK23: 0 | BL23: 0 | BM23: 0 | BN23: 0 | BO23: 0 | BR23: 0 | BS23: 0 | BT23: 0 | BU23: 0 | BV23: 0 | BW23: 0 | BZ23: 0 | CA23: 0 | CB23: 0 | CC23: 0 | CD23: 0 | CE23: 0 | CH23: 0 | CI23: 0 | CJ23: 0 | CK23: 0 | CL23: 0 | CM23: 0 | CP23: 0 | CQ23: 0 | CR23: 0 | CS23: 0 | CT23: 0 | CU23: 0 | CX23: 0 | CY23: 0 | CZ23: 0 | DA23: 0 | DB23: 0
B24: PIDR | BO24: 0
B25: EBITA | D25: 5.8384088e+08 | E25: 6.4153099e+08 | F25: -57690114 | G25: 7.0114474e+08 | H25: -0.16730335 | J25: -1.5915643e+08 | K25: -1.7523643e+08 | L25: 16079997 | M25: -1.4438875e+08 | N25: 0.10227722 | P25: 2.3006934e+09 | Q25: -2.1377134e+08 | R25: 2.5144647e+09 | S25: -1.3224758e+08 | T25: -18.396866 | V25: -1.6118185e+08 | W25: -3.0486499e+09 | X25: -1.4953439e+08 | Y25: 2.887468e+09 | Z25: -11647460 | AA25: 2.4811304e+08 | AB25: -1.6496307 | AD25: -1.5449044e+08 | AE25: -1.7268127e+08 | AF25: -2.4147745e+08 | AG25: 18190828 | AH25: 86987006 | AI25: -1.2870907e+08 | AJ25: 0.20030736 | AL25: -3.8567763e+08 | AM25: -1.3673764e+08 | AN25: -1.6891789e+08 | AO25: -2.4893999e+08 | AP25: -2.1675974e+08 | AQ25: -4536964 | AR25: 84.007867 | AT25: -2.7618531e+08 | AU25: -1.3019164e+08 | AV25: -2.6327685e+08 | AW25: -1.4599367e+08 | AX25: -12908457 | AY25: -1.3549122e+08 | AZ25: 1.0384 | BB25: -3.2307877e+08 | BC25: 1.3498065e+08 | BD25: -3.000796e+08 | BE25: -4.5805942e+08 | BF25: -22999175 | BG25: -1.3651222e+08 | BH25: 1.3666655 | BJ25: -4.4782931e+08 | BK25: -43836120 | BL25: -3.2351812e+08 | BM25: -4.0399319e+08 | BN25: -1.2431119e+08 | BO25: -1.9237258e+08 | BP25: 1.3279269 | BR25: -12192085 | BS25: -16204773 | BT25: -3.0773976e+08 | BU25: 4012688.1 | BV25: 2.9554767e+08 | BW25: -1.926795e+08 | BX25: -0.9367235 | BZ25: 0 | CA25: 0 | CB25: 0 | CC25: 0 | CD25: 0 | CE25: 0 | CH25: 0 | CI25: 0 | CJ25: -250000 | CK25: 0 | CL25: 250000 | CM25: 0 | CP25: 9.6474243e+08 | CQ25: -3.1618067e+09 | CR25: 7.9459476e+08 | CS25: 4.1265491e+09 | CT25: 1.7014767e+08 | CU25: -1.1721311e+08 | CV25: -9.2306698 | CX25: 1.6769685e+08 | CY25: 90000000 | CZ25: 0 | DA25: 3.3582426e+09 | DB25: 1.8595163e+09 | DC25: -0.90981695 | DD25: -0.95160032 | DE25: -1 | DF25: 0.80597644
B26: % CA | D26: 1.609015 | E26: 1.798558 | F26: -0.18954304 | G26: 1.7401734 | H26: -0.075370879 | J26: -0.50180722 | K26: -0.53829853 | L26: 0.036491308 | M26: -0.44206444 | N26: 0.13514497 | P26: 6.6151674 | Q26: -0.52479861 | R26: 7.139966 | S26: -0.35673659 | T26: -19.543563 | V26: -0.41472963 | W26: -6.412027 | X26: -0.37809904 | Y26: 5.9972974 | Z26: -0.036630591 | AA26: 0.63103178 | AB26: -1.6572246 | AD26: -0.40688532 | AE26: -0.33262062 | AF26: -0.51966548 | AG26: -0.0742647 | AH26: 0.11278016 | AI26: -0.3398794 | AJ26: 0.19714614 | AL26: -1.0824072 | AM26: -0.24358292 | AN26: -0.2957374 | AO26: -0.83882431 | AP26: -0.78666983 | AQ26: -0.012490677 | AR26: 85.657212 | AT26: -0.69521475 | AU26: -0.21751368 | AV26: -0.62129333 | AW26: -0.47770107 | AX26: -0.073921426 | AY26: -0.34802366 | AZ26: 0.99760775 | BB26: -0.81568622 | BC26: 0.21734746 | BD26: -0.75020288 | BE26: -1.0330337 | BF26: -0.065483333 | BG26: -0.36025751 | BH26: 1.2641755 | BJ26: -1.1509999 | BK26: -0.068755373 | BL26: -0.81221264 | BM26: -1.0822445 | BN26: -0.33878722 | BO26: -0.52579167 | BP26: 1.1890797 | BR26: -0.028070526 | BS26: -0.024083451 | BT26: -0.76241714 | BU26: -0.0039870754 | BV26: 0.73434661 | BW26: -0.52948902 | BX26: -0.94698563 | BZ26: #DIV/0! | CA26: #DIV/0! | CB26: #DIV/0! | CC26: #DIV/0! | CD26: #DIV/0! | CE26: #DIV/0! | CH26: #DIV/0! | CI26: #DIV/0! | CJ26: #DIV/0! | CK26: #DIV/0! | CL26: #DIV/0! | CM26: #DIV/0! | CP26: 0.2559524 | CQ26: -0.61091251 | CR26: 0.2125423 | CS26: 0.86686491 | CT26: 0.043410105 | CU26: -0.031396019 | CV26: -9.1523839 | CX26: 0.025267973 | CY26: #DIV/0! | CZ26: #DIV/0! | DA26: 0.73686295 | DB26: 0.41836184 | DC26: -39.309387 | DF26: 31.850111
B28: Résultat financier | D28: -95511897 | E28: -1.0578605e+08 | F28: 10274155 | G28: -43710000 | H28: 1.1851269 | J28: -101282465 | K28: -1.0529685e+08 | L28: 4014388.2 | M28: -41134707 | N28: 1.4622143 | P28: -102216675 | Q28: -1.0392612e+08 | R28: 1709446.2 | S28: -43780313 | T28: 1.3347635 | V28: -102216675 | W28: -1.0426584e+08 | X28: -1.0426584e+08 | Y28: 2049162.2 | Z28: 2049162.2 | AA28: -42549392 | AB28: 1.4023063 | AD28: -158473885 | AE28: -1.0350814e+08 | AF28: -1.0350814e+08 | AG28: -54965747 | AH28: -54965747 | AI28: -46354606 | AJ28: 2.4187301 | AL28: -107890682 | AM28: -1.0325404e+08 | AN28: -1.0325404e+08 | AO28: -4636641.8 | AP28: -4636641.8 | AQ28: -49265600 | AR28: 1.1899801 | AT28: -99239348 | AU28: -96571863 | AV28: -1.0249833e+08 | AW28: -2667484.9 | AX28: 3258977.2 | AY28: -49265600 | AZ28: 1.0143741 | BB28: -102216675 | BC28: -96286379 | BD28: -95765128 | BE28: -5930295.9 | BF28: -6451546.9 | BG28: -49265600 | BH28: 1.0748083 | BJ28: -97444328 | BK28: -95765128 | BL28: -95765128 | BM28: -1679199.9 | BN28: -1679199.9 | BO28: -49265600 | BP28: 0.97793852 | BR28: -97285759 | BT28: -95026227 | BU28: -97285759 | BV28: -2259531.9 | BW28: -42899546 | BX28: 1.2677573 | CC28: 0 | CD28: 0 | CK28: 0 | CL28: 0 | CP28: -1063778389 | CQ28: -9.1466041e+08 | CR28: -1.0615189e+09 | CS28: -1.4911798e+08 | CT28: -2259531.9 | CU28: -4.5749096e+08 | CV28: 1.3252446 | CX28: -1.1983527e+09 | DB28: -664958215 | DC28: 0.80214737 | DD28: -1 | DE28: -1 | DF28: -1
B29: dont intérêt sur SHL | F29: 0 | G29: 0 | L29: 0 | R29: 0 | S29: 0 | V29: 0 | X29: 0 | Y29: 0 | Z29: 0 | AF29: 0 | AG29: 0 | AH29: 0 | AO29: 0 | AP29: 0 | AU29: 0 | AV29: 0 | AW29: 0 | AX29: 0 | BE29: 0 | BF29: 0 | BM29: 0 | BN29: 0 | BO29: 0 | BU29: 0 | BV29: 0 | CC29: 0 | CD29: 0 | CK29: 0 | CL29: 0 | DB29: 0
B30: Contribution au fond spécial COVID-19 | D30: 0 | J30: 0 | P30: 0 | X30: 0 | AE30: 0 | AF30: 0 | AV30: 0 | BO30: 0 | CR30: 0
B31: RESULTAT avant IS | D31: 4.8832898e+08 | E31: 5.3574494e+08 | F31: -47415958 | G31: 6.5743474e+08 | H31: -0.25722061 | J31: -2.604389e+08 | K31: -2.8053328e+08 | L31: 20094385 | M31: -1.8552346e+08 | N31: 0.40380574 | P31: 2.1984767e+09 | Q31: -3.1769746e+08 | R31: 2.5161742e+09 | S31: -1.7602789e+08 | T31: -13.489366 | V31: -2.6339852e+08 | W31: -3.1529157e+09 | X31: -2.5380023e+08 | Y31: 2.8895172e+09 | Z31: -9598297.5 | AA31: 2.0556365e+08 | AB31: -2.2813478 | AD31: -3.1296433e+08 | AE31: -2.7618941e+08 | AF31: -3.4498559e+08 | AG31: -36774919 | AH31: 32021259 | AI31: -1.7506367e+08 | AJ31: 0.78771712 | AL31: -4.9356831e+08 | AM31: -2.3999168e+08 | AN31: -2.7217193e+08 | AO31: -2.5357663e+08 | AP31: -2.2139638e+08 | AQ31: -53802564 | AR31: 8.1736949 | AT31: -3.7542465e+08 | AU31: -2.267635e+08 | AV31: -3.6577518e+08 | AW31: -1.4866115e+08 | AX31: -9649479.8 | AY31: -1.8475682e+08 | AZ31: 1.0319935 | BB31: -4.2529545e+08 | BC31: 38694270 | BD31: -3.9584473e+08 | BE31: -4.6398972e+08 | BF31: -29450722 | BG31: -1.8577782e+08 | BH31: 1.2892692 | BJ31: -5.4527364e+08 | BK31: -1.3960125e+08 | BL31: -4.1928325e+08 | BM31: -4.0567239e+08 | BN31: -1.2599039e+08 | BO31: -2.4163818e+08 | BP31: 1.2565707 | BR31: -1.0947784e+08 | BS31: -16204773 | BT31: -4.0276598e+08 | BU31: -93273071 | BV31: 2.9328814e+08 | BW31: -2.3557905e+08 | BX31: -0.53528192 | BZ31: 0 | CA31: 0 | CB31: 0 | CC31: 0 | CD31: 0 | CE31: 0 | CH31: 0 | CI31: 0 | CJ31: -250000 | CK31: 0 | CL31: 250000 | CM31: 0 | CP31: -99035957 | CQ31: -4.0754579e+09 | CR31: -2.669241e+08 | CS31: 3.9764219e+09 | CT31: 1.6788814e+08 | CU31: -5.7470408e+08 | CV31: -0.82767487 | CX31: -1.0306558e+09 | CY31: 90000000 | CZ31: 0 | DA31: 3.3582426e+09 | DB31: 1.194558e+09 | DC31: -1.8627926 | DD31: -0.92465833 | DE31: -1 | DF31: 1.8112845
B32: IS | D32: -6201345.8 | E32: -6201345.8 | F32: 0 | G32: 9600000 | H32: -1.6459735 | J32: 6201345.8 | K32: -6201345.8 | L32: 12402692 | M32: -5865576.4 | N32: -2.0572441 | Q32: -6201345.8 | R32: 6201345.8 | S32: 7831152.7 | T32: -1 | Y32: 0 | Z32: 0 | AG32: 0 | AH32: 0 | AO32: 0 | AP32: 0 | AQ32: 2100000 | AR32: -1 | AW32: 0 | AX32: 0 | BB32: 0 | BE32: 0 | BF32: 0 | BM32: 0 | BN32: 0 | BO32: 0 | BU32: 0 | BV32: 0 | CC32: 0 | CD32: 0 | CK32: 0 | CL32: 0 | CP32: 0 | CQ32: -18604037 | CR32: 0 | CS32: 18604037 | CT32: 0 | CX32: -74416149 | DB32: 1800000 | DC32: -42.342305 | DD32: -1 | DE32: -1 | DF32: -1
B33: ID | L33: 0 | P33: -14500000 | R33: -14500000 | V33: -4833333.3 | Y33: -4833333.3 | Z33: -4833333.3 | AG33: 0 | AH33: 0 | AL33: 6800000 | AO33: 6800000 | AP33: 6800000 | AW33: 0 | AX33: 0 | BB33: 0 | BE33: 0 | BF33: 0 | BJ33: 18000000 | BM33: 18000000 | BN33: 18000000 | BO33: 0 | BU33: 0 | BV33: 0 | CC33: 0 | CD33: 0 | CK33: 0 | CL33: 0 | CP33: 5466666.7 | CQ33: 0 | CR33: -12533333 | CS33: 5466666.7 | CT33: 18000000 | CU33: 0 | DB33: 0 | DD33: #DIV/0!
BO34: 0
B35: RESULTAT NET | D35: 4.8212763e+08 | E35: 5.2954359e+08 | F35: -47415958 | G35: 6.6703474e+08 | H35: -0.27720761 | J35: -2.5423755e+08 | K35: -2.8673463e+08 | L35: 32497077 | M35: -1.9138903e+08 | N35: 0.32838097 | P35: 2.1839767e+09 | Q35: -3.238988e+08 | R35: 2.5078755e+09 | S35: -1.6819674e+08 | T35: -13.984656 | V35: -2.6823186e+08 | W35: -3.1529157e+09 | X35: -2.5380023e+08 | Y35: 2.8846839e+09 | Z35: -14431631 | AA35: 2.0556365e+08 | AB35: -2.3048604 | AD35: -3.1296433e+08 | AE35: -2.7618941e+08 | AF35: -3.4498559e+08 | AG35: -36774919 | AH35: 32021259 | AI35: -1.7506367e+08 | AJ35: 0.78771712 | AL35: -4.8676831e+08 | AM35: -2.3999168e+08 | AN35: -2.7217193e+08 | AO35: -2.4677663e+08 | AP35: -2.1459638e+08 | AQ35: -51702564 | AR35: 8.4147808 | AT35: -3.7542465e+08 | AU35: -2.267635e+08 | AV35: -3.6577518e+08 | AW35: -1.4866115e+08 | AX35: -9649479.8 | AY35: -1.8475682e+08 | AZ35: 1.0319935 | BB35: -4.2529545e+08 | BC35: 38694270 | BD35: -3.9584473e+08 | BE35: -4.6398972e+08 | BF35: -29450722 | BG35: -1.8577782e+08 | BH35: 1.2892692 | BJ35: -5.2727364e+08 | BK35: -1.3960125e+08 | BL35: -4.1928325e+08 | BM35: -3.8767239e+08 | BN35: -1.0799039e+08 | BO35: -2.4163818e+08 | BP35: 1.1820792 | BR35: -1.0947784e+08 | BS35: -16204773 | BT35: -4.0276598e+08 | BU35: -93273071 | BV35: 2.9328814e+08 | BW35: -2.3557905e+08 | BX35: -0.53528192 | BZ35: 0 | CA35: 0 | CB35: 0 | CC35: 0 | CE35: 0 | CH35: 0 | CI35: 0 | CJ35: -250000 | CK35: 0 | CL35: 250000 | CM35: 0 | CP35: -93569290 | CQ35: -4.0940619e+09 | CR35: -2.7945743e+08 | CS35: 4.0004926e+09 | CT35: 1.8588814e+08 | CU35: -5.7470408e+08 | CV35: 0.83718701 | CX35: -1.105072e+09 | CY35: 90000000 | CZ35: 0 | DA35: 3.3582426e+09 | DB35: 1.196358e+09 | DC35: -1.9236967 | DD35: -0.92477169 | DE35: -1 | DF35: 1.8070548
B37: % CA | D37: 1.3287021 | E37: 1.4845968 | G37: 1.6555157 | J37: -0.80159022 | K37: -0.88080333 | M37: -0.58596175 | P37: 6.2795727 | Q37: -0.79515638 | S37: -0.45370911 | V37: -0.6901751 | W37: -6.6313226 | X37: -0.64173614 | AA37: 0.5228149 | AD37: -0.82426192 | AE37: -0.53199916 | AF37: -0.74241757 | AI37: -0.46228706 | AL37: -1.366119 | AM37: -0.42751853 | AN37: -0.47651211 | AQ37: -0.14234189 | AT37: -0.94502044 | AU37: -0.37885816 | AV37: -0.86317379 | AY37: -0.4745676 | BB37: -1.0737556 | BC37: 0.062305979 | BD37: -0.98961694 | BE37: 2.0625977 | BF37: 7.5210954 | BG37: -0.49027006 | BJ37: -1.3551857 | BK37: -0.21895952 | BL37: -1.052637 | BO37: -0.66044413 | BR37: -0.25205703 | BS37: -0.024083451 | BT37: -0.99784211 | BW37: -0.64737825 | BZ37: #DIV/0! | CA37: #DIV/0! | CB37: #DIV/0! | CE37: #DIV/0! | CH37: #DIV/0! | CI37: #DIV/0! | CJ37: #DIV/0! | CM37: #DIV/0! | CP37: -0.024824537 | CQ37: -0.7910394 | CR37: -0.074750711 | CU37: -0.15393687 | CX37: -0.16650837 | CY37: #DIV/0! | CZ37: #DIV/0! | DA37: 0.73686295 | DB37: -0.30630706 | DC37: 13.979869 | DF37: 104.317
BO38: 0
P40: -4833333.3

Sheet Trafic
B2: Trafic
D3: JANVIER | J3: FEVRIER | P3: MARS | V3: AVRIL | AD3: MAI | AL3: JUIN | AT3: JUILLET | BB3: AOUT | BJ3: SEPTEMBRE | BR3: OCTOBRE | BZ3: NOVEMBRE | CH3: DECEMBRE | CP3: CUMUL | CX3: ANNUEL
B4: (En Millions Minute) | D4: 2025 Réel | E4: 2025 Budget | F4: Ecart / Budget | G4: 2024 Réel | H4: Evol % | J4: 2025 Réel | K4: 2025 Budget | L4: Ecart / Budget | M4: 2024 Réel | N4: Evol % | P4: 2025 Réel | Q4: 2025 Budget | R4: Ecart / Budget | S4: 2024 Réel | T4: Evol % | V4: 2025 Réel | W4: 2025 Budget | X4: 2025 Actu 1 | Y4: Ecart / Budget | Z4: Ecart / Actu 1 | AA4: 2024 Réel | AB4: Evol % | AD4: 2025 Réel | AE4: 2025 Budget | AF4: 2025 Actu 1 | AG4: Ecart / Budget | AH4: Ecart / Actu 1 | AI4: 2024 Réel | AJ4: Evol % | AL4: 2025 Réel | AM4: 2025 Budget | AN4: 2025 Actu 1 | AO4: Ecart / Budget | AP4: Ecart / Actu 1 | AQ4: 2024 Réel | AR4: Evol % | AT4: 2025 Réel | AU4: 2025 Budget | AV4: 2025 Actu 2 | AW4: Ecart / Budget | AX4: Ecart / Actu 2 | AY4: 2024 Réel | AZ4: Evol % | BB4: 2025 Réel | BC4: 2025 Budget | BD4: 2025 Actu3 | BE4: Ecart / Budget | BF4: Ecart / Actu 3 | BG4: 2024 Réel | BH4: Evol % | BJ4: 2025 Réel | BK4: 2025 Budget | BL4: 2025 Actu3 | BM4: Ecart / Budget | BN4: Ecart / Actu 3 | BO4: 2024 Réel | BP4: Evol % | BR4: 2025 Réel | BS4: 2025 Budget | BT4: 2025 Actu 3 | BU4: Ecart / Budget | BV4: Ecart / Actu 3 | BW4: 2024 Réel | BX4: Evol % | BZ4: 2025 Réel | CA4: 2025 Budget | CB4: 2025 Actu 3 | CC4: Ecart / Budget | CD4: Ecart / Actu 3 | CE4: 2024 Réel | CF4: Evol % | CH4: 2025 Réel | CI4: 2025 Budget | CJ4: 2025 Actu 3 | CK4: Ecart / Budget | CL4: Ecart / Actu 3 | CM4: 2024 Réel | CN4: Evol % | CP4: 2025 Réel | CQ4: 2025 Budget | CR4: 2025 Actu 3 | CS4: Ecart / Budget | CT4: Ecart / Actu 3 | CU4: 2024 Réel | CV4: Evol % | CX4: 2025 Budget | CY4: 2024 Actu 1 | CZ4: 2024 Actu 2 | DA4: 2025 Actu 3 | DB4: 2024 Réel | DC4: Bud / 2024 (%) | DD4: Actu 1 / 2023 (%) | DE4: Actu 2 / 2023 (%) | DF4: Actu 3 / 2019 (%)
B6: Total Trafic | D6: 5855974.7 | E6: 6722757.6 | F6: -866782.91 | G6: 6497693 | H6: -0.09876094 | J6: 5606193.6 | K6: 7793242.6 | L6: -2187049.1 | M6: 5699367.6 | N6: -0.016348127 | P6: 7130553 | Q6: 8095755.7 | R6: -965202.66 | S6: 6038622 | T6: 0.18082454 | V6: 7325602.3 | W6: 8174786.4 | X6: 8320435.3 | Y6: -849184.11 | Z6: -994833.02 | AA6: 6385996.5 | AB6: 0.14713534 | AD6: 8224196.9 | AE6: 8193137 | AF6: 8536466.7 | AG6: 31059.903 | AH6: -312269.8 | AI6: 6134259.5 | AJ6: 0.34069921 | AL6: 8242836.5 | AM6: 8537185 | AN6: 8641145.4 | AO6: -294348.45 | AP6: -398308.89 | AQ6: 5910984.5 | AR6: 0.3944947 | AT6: 7083426.4 | AU6: 8730920.1 | AV6: 9157021.7 | AW6: -1647493.8 | AX6: -2073595.4 | AY6: 6199521 | AZ6: 0.1425764 | BB6: 8293125.9 | BC6: 8927769.8 | BD6: 9286274.6 | BE6: -634643.84 | BF6: -993148.7 | BG6: 5978962.4 | BH6: 0.38705103 | BJ6: 7939218.9 | BK6: 8167564.9 | BL6: 9457442.3 | BM6: -228346.03 | BN6: -1518223.3 | BO6: 5978962.4 | BP6: 0.32785899 | BR6: 9101786.8 | BS6: 9331904.2 | BT6: 9617564 | BU6: -230117.45 | BV6: -515777.17 | BW6: 5899999.6 | BX6: 0.54267584 | BZ6: 0 | CA6: 0 | CB6: 0 | CC6: 0 | CD6: 0 | CE6: 0 | CH6: 0 | CI6: 0 | CJ6: 0 | CK6: 0 | CL6: 0 | CM6: 0 | CP6: 74802915 | CQ6: 83662268 | CR6: 75318692 | CS6: -8859353.3 | CT6: -515777.17 | CU6: 60999040 | CV6: 0.22629659 | CX6: 1.0289937e+08 | CY6: 0 | CZ6: 0 | DA6: 91546131 | DB6: 73272032 | DC6: 0.40434715 | DD6: -1 | DE6: -1 | DF6: 0.24940075
B8: Trafic sortant | D8: 5378373.7 | E8: 6296400 | F8: -918026.32 | G8: 6120515 | H8: -0.12125471 | J8: 5156181.6 | K8: 7345795 | L8: -2189613.4 | M8: 5699367.6 | N8: -0.095306361 | P8: 6636650 | Q8: 7477096.7 | R8: -840446.73 | S8: 5714545 | T8: 0.16136106 | V8: 6759455.3 | W8: 7525031 | X8: 7745726.1 | Y8: -765575.7 | Z8: -986270.87 | AA8: 6129287.5 | AB8: 0.10281257 | AD8: 7623607.9 | AE8: 7507907.4 | AF8: 7938580.1 | AG8: 115700.48 | AH8: -314972.25 | AI8: 5836482.5 | AJ8: 0.30619904 | AL8: 7676410.5 | AM8: 7814350.8 | AN8: 8004421.1 | AO8: -137940.32 | AP8: -328010.58 | AQ8: 5629461.5 | AR8: 0.36361365 | AT8: 6514789.3 | AU8: 7968215.1 | AV8: 8465295.4 | AW8: -1453425.8 | AX8: -1950506.1 | AY8: 5873909 | AZ8: 0.10910627 | BB8: 7751917.9 | BC8: 7985991.7 | BD8: 8690866.5 | BE8: -234073.71 | BF8: -938948.54 | BG8: 5662580.4 | BH8: 0.3689727 | BJ8: 7375214.9 | BK8: 8167564.9 | BL8: 8890563.4 | BM8: -792350.03 | BN8: -1515348.4 | BO8: 5662580.4 | BP8: 0.30244772 | BR8: 8343365.8 | BS8: 8296419 | BT8: 9022341.1 | BU8: 46946.796 | BV8: -678975.32 | BW8: 5599902.7 | BX8: 0.48991263 | BZ8: 0 | CA8: 0 | CB8: 0 | CC8: 0 | CD8: 0 | CE8: 0 | CH8: 0 | CI8: 0 | CJ8: 0 | CK8: 0 | CL8: 0 | CM8: 0 | CP8: 69215967 | CQ8: 76384772 | CR8: 69894942 | CS8: -7168804.7 | CT8: -678975.32 | CU8: 57928631 | CV8: 0.19484899 | CX8: 93390790 | CY8: 0 | CZ8: 0 | DA8: 91546131 | DB8: 69437287 | DC8: 0.34496601 | DD8: -1 | DE8: -1 | DF8: 0.31840018
B9: Dont Prépayé | D9: 5001887.5 | E9: 5855652 | F9: -853764.47 | G9: 5692078.9 | H9: -0.12125471 | J9: 4795248.9 | K9: 6831589.3 | L9: -2036340.5 | M9: 5300411.8 | N9: -0.095306361 | P9: 6172084.5 | Q9: 6953700 | R9: -781615.46 | S9: 5314526.8 | T9: 0.16136106 | V9: 6286293.4 | W9: 6998278.8 | X9: 7203525.3 | Y9: -711985.4 | Z9: -917231.91 | AA9: 5700237.4 | AB9: 0.10281257 | AD9: 7089955.3 | AE9: 6982353.9 | AF9: 7382879.5 | AG9: 107601.45 | AH9: -292924.2 | AI9: 5427928.8 | AJ9: 0.30619904 | AL9: 7139061.8 | AM9: 7267346.3 | AN9: 7444111.6 | AO9: -128284.5 | AP9: -305049.84 | AQ9: 5235399.2 | AR9: 0.36361365 | AT9: 6058754 | AU9: 7410440 | AV9: 7872724.7 | AW9: -1351686 | AX9: -1813970.7 | AY9: 5462735.3 | AZ9: 0.10910627 | BB9: 7209283.7 | BC9: 7426972.2 | BD9: 8082505.8 | BE9: -217688.55 | BF9: -873222.14 | BG9: 5266199.7 | BH9: 0.3689727 | BJ9: 6858949.9 | BK9: 7595835.4 | BL9: 8268223.9 | BM9: -736885.53 | BN9: -1409274.1 | BO9: 5266199.7 | BP9: 0.30244772 | BR9: 7759330.2 | BS9: 7715669.7 | BT9: 8390777.2 | BU9: 43660.52 | BV9: -631447.05 | BW9: 5207909.5 | BX9: 0.48991263 | BZ9: 0 | CA9: 0 | CB9: 0 | CC9: 0 | CD9: 0 | CE9: 0 | CH9: 0 | CI9: 0 | CJ9: 0 | CK9: 0 | CL9: 0 | CM9: 0 | CP9: 64370849 | CQ9: 71037838 | CR9: 65002296 | CS9: -6666988.4 | CT9: -631447.05 | CU9: 53873627 | CV9: 0.19484899 | CX9: 86853435 | DA9: 85164794 | DB9: 64576677 | DC9: 0.34496601 | DD9: -1 | DE9: -1 | DF9: 0.31881661
B10: Dont Postpayé | D10: 376486.16 | E10: 440748 | F10: -64261.842 | G10: 428436.05 | H10: -0.12125471 | J10: 360932.71 | K10: 514205.65 | L10: -153272.94 | M10: 398955.73 | N10: -0.095306361 | P10: 464565.5 | Q10: 523396.77 | R10: -58831.271 | S10: 400018.15 | T10: 0.16136106 | V10: 473161.87 | W10: 526752.17 | X10: 542200.83 | Y10: -53590.299 | Z10: -69038.961 | AA10: 429050.12 | AB10: 0.10281257 | AD10: 533652.55 | AE10: 525553.52 | AF10: 555700.61 | AG10: 8099.0336 | AH10: -22048.058 | AI10: 408553.78 | AJ10: 0.30619904 | AL10: 537348.74 | AM10: 547004.56 | AN10: 560309.48 | AO10: -9655.8222 | AP10: -22960.741 | AQ10: 394062.3 | AR10: 0.36361365 | AT10: 456035.25 | AU10: 557775.05 | AV10: 592570.68 | AW10: -101739.81 | AX10: -136535.43 | AY10: 411173.63 | AZ10: 0.10910627 | BB10: 542634.26 | BC10: 559019.42 | BD10: 608360.65 | BE10: -16385.159 | BF10: -65726.398 | BG10: 396380.63 | BH10: 0.3689727 | BJ10: 516265.04 | BK10: 571729.55 | BL10: 622339.44 | BM10: -55464.502 | BN10: -106074.39 | BO10: 396380.63 | BP10: 0.30244772 | BR10: 584035.61 | BS10: 580749.33 | BT10: 631563.88 | BU10: 3286.2757 | BV10: -47528.273 | BW10: 391993.19 | BX10: 0.48991263 | BZ10: 0 | CA10: 0 | CB10: 0 | CC10: 0 | CD10: 0 | CE10: 0 | CH10: 0 | CI10: 0 | CJ10: 0 | CK10: 0 | CL10: 0 | CM10: 0 | CP10: 4845117.7 | CQ10: 5346934 | CR10: 4892646 | CS10: -501816.33 | CT10: -47528.273 | CU10: 4055004.2 | CV10: 0.19484899 | CX10: 6537355.3 | DA10: 6381337.3 | DB10: 4860610.1 | DC10: 0.34496601 | DD10: -1 | DE10: -1
B11: vers On net | D11: 3334591.7 | E11: 3918900 | F11: -584308.32 | G11: 3717939 | H11: -0.10310747 | J11: 3196832.6 | K11: 4916120 | L11: -1719287.4 | M11: 3680759.6 | N11: -0.13147476 | P11: 4114723 | Q11: 4971276.5 | R11: -856553.48 | S11: 3643952 | T11: 0.12919244 | V11: 4190862.3 | W11: 4994706.8 | X11: 5194706.8 | Y11: -803844.56 | Z11: -1003844.6 | AA11: 3680391.5 | AB11: 0.13870013 | AD11: 4726636.9 | AE11: 4957695.1 | AF11: 5357695.1 | AG11: -231058.2 | AH11: -631058.2 | AI11: 3661989.5 | AJ11: 0.29072922 | AL11: 4759374.5 | AM11: 5252849 | AN11: 5392849 | AO11: -493474.47 | AP11: -633474.47 | AQ11: 3680299.5 | AT11: 4039169.4 | AU11: 5395491.4 | AV11: 5495491.4 | AW11: -1356322.1 | AX11: -1456322.1 | AY11: 3698701 | AZ11: 0.092050799 | BB11: 4874589.1 | BC11: 5406762.6 | BD11: 5706762.6 | BE11: -532173.43 | BF11: -832173.43 | BG11: 3706098.4 | BH11: 0.31528865 | BJ11: 4972080.9 | BK11: 5581150.7 | BL11: 5981150.7 | BM11: -609069.76 | BN11: -1009069.8 | BO11: 3706098.4 | BP11: 0.34159442 | BR11: 5172886.8 | BS11: 5680060.8 | BT11: 6080060.8 | BU11: -507173.98 | BV11: -907173.98 | BW11: 3720937.6 | BX11: 0.39021057 | CC11: 0 | CD11: 0 | CK11: 0 | CL11: 0 | CP11: 43381747 | CQ11: 51075013 | CR11: 44288921 | CS11: -7693265.7 | CT11: -907173.98 | CU11: 36897166 | CV11: 0.17574739 | CX11: 62772070 | DA11: 58971442 | DB11: 44270547 | DC11: 0.41791947 | DD11: -1 | DE11: -1
B12: vers Off net local | D12: 1951935 | E12: 2222500 | F12: -270565 | G12: 2288385 | H12: -0.14702509 | J12: 1871056 | K12: 2266925 | L12: -395869 | M12: 1933622 | N12: -0.032356893 | P12: 2431857 | Q12: 2334932.8 | R12: 96924.25 | S12: 1971004 | T12: 0.23381637 | V12: 2480478 | W12: 2354310 | X12: 2453743.7 | Y12: 126167.98 | Z12: 26734.287 | AA12: 2344265 | AB12: 0.058104779 | AD12: 2816556 | AE12: 2368917.8 | AF12: 2475827.4 | AG12: 447638.23 | AH12: 340728.59 | AI12: 2084885 | AJ12: 0.3509407 | AL12: 2832771 | AM12: 2376581.4 | AN12: 2498109.9 | AO12: 456189.59 | AP12: 334661.15 | AQ12: 1852526 | AR12: 0.52913967 | AT12: 2390175.2 | AU12: 2384104.8 | AV12: 2876007.9 | AW12: 6070.4416 | AX12: -485832.65 | AY12: 2076526 | AZ12: 0.15104517 | BB12: 2790175.2 | BC12: 2386837.9 | BD12: 2891823.6 | BE12: 403337.34 | BF12: -101648.43 | BG12: 1861364 | BH12: 0.49899494 | BJ12: 2320663 | BK12: 2390175.2 | BL12: 2815286.8 | BM12: -69512.217 | BN12: -494623.79 | BO12: 1861364 | BP12: 0.24675399 | BR12: 3101303 | BS12: 2418156.8 | BT12: 2840624.4 | BU12: 683146.22 | BV12: 260678.63 | BW12: 1792378 | BX12: 0.73027289 | CC12: 0 | CD12: 0 | CK12: 0 | CL12: 0 | CP12: 24986969 | CQ12: 23503442 | CR12: 24726291 | CS12: 1483527.8 | CT12: 260678.63 | CU12: 20066319 | CV12: 0.24521939 | CX12: 28410035 | DA12: 31454944 | DB12: 24006012 | DC12: 0.18345499 | DD12: -1 | DE12: -1 | DF12: 0.31029446
B13: vers International | D13: 91847 | E13: 155000 | F13: -63153 | G13: 114191 | H13: -0.19567216 | J13: 88293 | K13: 162750 | L13: -74457 | M13: 84986 | N13: 0.038912291 | P13: 90070 | Q13: 170887.5 | R13: -80817.5 | S13: 99589 | T13: -0.095582845 | V13: 88115 | W13: 176014.12 | X13: 97275.6 | Y13: -87899.125 | Z13: -9160.6 | AA13: 104631 | AB13: -0.15784997 | AD13: 80415 | AE13: 181294.55 | AF13: 105057.65 | AG13: -100879.55 | AH13: -24642.648 | AI13: 89608 | AJ13: -0.10259129 | AL13: 84265 | AM13: 184920.44 | AN13: 113462.26 | AO13: -100655.44 | AP13: -29197.26 | AQ13: 96636 | AR13: -0.12801647 | AT13: 85444.71 | AU13: 188618.85 | AV13: 93796.056 | AW13: -103174.14 | AX13: -8351.346 | AY13: 98682 | AZ13: -0.13414088 | BB13: 87153.604 | BC13: 192391.23 | BD13: 92280.287 | BE13: -105237.62 | BF13: -5126.6826 | BG13: 95118 | BH13: -0.083731742 | BJ13: 82471 | BK13: 196239.05 | BL13: 94125.893 | BM13: -113768.05 | BN13: -11654.893 | BO13: 95118 | BP13: -0.13296116 | BR13: 69176 | BS13: 198201.44 | BT13: 101655.96 | BU13: -129025.44 | BV13: -32479.964 | BW13: 86587.15 | BX13: -0.20108238 | CC13: 0 | CD13: 0 | CK13: 0 | CL13: 0 | CP13: 847250.31 | CQ13: 1806317.2 | CR13: 879730.28 | CS13: -959066.86 | CT13: -32479.964 | CU13: 965146.15 | CV13: -0.12215335 | CX13: 2208685.9 | DA13: 1119745.1 | DB13: 1160728.1 | DC13: 0.90284514 | DD13: -1 | DE13: -1 | DF13: -0.035308028
B14: vers Sonitel (fixe) | BO14: 0
B15: vers l'international | BO15: 0
B16: vers Moov | BO16: 0
B17: vers Airtel | F17: 0 | L17: 0 | R17: 0 | Y17: 0 | Z17: 0 | AG17: 0 | AH17: 0 | AO17: 0 | AP17: 0 | AW17: 0 | AX17: 0 | BE17: 0 | BF17: 0 | BM17: 0 | BN17: 0 | BO17: 0 | BU17: 0 | BV17: 0 | CC17: 0 | CD17: 0 | CK17: 0 | CL17: 0 | CP17: 0 | CQ17: 0 | CR17: 0 | CS17: 0 | CT17: 0 | CU17: 0 | DB17: 0 | DD17: #DIV/0! | DE17: #DIV/0! | DF17: #DIV/0!
B18: vers Orange | F18: 0 | L18: 0 | R18: 0 | Y18: 0 | Z18: 0 | AG18: 0 | AH18: 0 | AO18: 0 | AP18: 0 | AW18: 0 | AX18: 0 | BE18: 0 | BF18: 0 | BM18: 0 | BN18: 0 | BO18: 0 | BU18: 0 | BV18: 0 | CC18: 0 | CD18: 0 | CK18: 0 | CL18: 0 | CP18: 0 | CQ18: 0 | CR18: 0 | CS18: 0 | CT18: 0 | CU18: 0 | DB18: 0 | DD18: #DIV/0! | DE18: #DIV/0! | DF18: #DIV/0!
B19: vers Sahelcom | F19: 0 | L19: 0 | R19: 0 | Y19: 0 | Z19: 0 | AG19: 0 | AH19: 0 | AO19: 0 | AP19: 0 | AW19: 0 | AX19: 0 | BE19: 0 | BF19: 0 | BM19: 0 | BN19: 0 | BO19: 0 | BU19: 0 | BV19: 0 | CC19: 0 | CD19: 0 | CK19: 0 | CL19: 0 | CP19: 0 | CQ19: 0 | CR19: 0 | CS19: 0 | CT19: 0 | CU19: 0 | DB19: 0 | DD19: #DIV/0! | DE19: #DIV/0! | DF19: #DIV/0!
BO20: 0
